Compiled from "ExchangeCodec.java"
public class org.apache.dubbo.remoting.exchange.codec.ExchangeCodec extends org.apache.dubbo.remoting.telnet.codec.TelnetCodec {
  protected static final int HEADER_LENGTH;

  protected static final short MAGIC;

  protected static final byte MAGIC_HIGH;

  protected static final byte MAGIC_LOW;

  protected static final byte FLAG_REQUEST;

  protected static final byte FLAG_TWOWAY;

  protected static final byte FLAG_EVENT;

  protected static final int SERIALIZATION_MASK;

  private static final org.apache.dubbo.common.logger.ErrorTypeAwareLogger logger;

  public org.apache.dubbo.remoting.exchange.codec.ExchangeCodec();
    Code:
       0: aload_0
       1: invokespecial #2                  // Method org/apache/dubbo/remoting/telnet/codec/TelnetCodec."<init>":()V
       4: return

  public java.lang.Short getMagicCode();
    Code:
       0: sipush        -9541
       3: invokestatic  #4                  // Method java/lang/Short.valueOf:(S)Ljava/lang/Short;
       6: areturn

  public void encode(org.apache.dubbo.remoting.Channel, org.apache.dubbo.remoting.buffer.ChannelBuffer, java.lang.Object) throws java.io.IOException;
    Code:
       0: aload_3
       1: instanceof    #5                  // class org/apache/dubbo/remoting/exchange/Request
       4: ifeq          20
       7: aload_0
       8: aload_1
       9: aload_2
      10: aload_3
      11: checkcast     #5                  // class org/apache/dubbo/remoting/exchange/Request
      14: invokevirtual #6                  // Method encodeRequest:(Lorg/apache/dubbo/remoting/Channel;Lorg/apache/dubbo/remoting/buffer/ChannelBuffer;Lorg/apache/dubbo/remoting/exchange/Request;)V
      17: goto          47
      20: aload_3
      21: instanceof    #7                  // class org/apache/dubbo/remoting/exchange/Response
      24: ifeq          40
      27: aload_0
      28: aload_1
      29: aload_2
      30: aload_3
      31: checkcast     #7                  // class org/apache/dubbo/remoting/exchange/Response
      34: invokevirtual #8                  // Method encodeResponse:(Lorg/apache/dubbo/remoting/Channel;Lorg/apache/dubbo/remoting/buffer/ChannelBuffer;Lorg/apache/dubbo/remoting/exchange/Response;)V
      37: goto          47
      40: aload_0
      41: aload_1
      42: aload_2
      43: aload_3
      44: invokespecial #9                  // Method org/apache/dubbo/remoting/telnet/codec/TelnetCodec.encode:(Lorg/apache/dubbo/remoting/Channel;Lorg/apache/dubbo/remoting/buffer/ChannelBuffer;Ljava/lang/Object;)V
      47: return

  public java.lang.Object decode(org.apache.dubbo.remoting.Channel, org.apache.dubbo.remoting.buffer.ChannelBuffer) throws java.io.IOException;
    Code:
       0: aload_2
       1: invokeinterface #10,  1           // InterfaceMethod org/apache/dubbo/remoting/buffer/ChannelBuffer.readableBytes:()I
       6: istore_3
       7: iload_3
       8: bipush        16
      10: invokestatic  #11                 // Method java/lang/Math.min:(II)I
      13: newarray       byte
      15: astore        4
      17: aload_2
      18: aload         4
      20: invokeinterface #12,  2           // InterfaceMethod org/apache/dubbo/remoting/buffer/ChannelBuffer.readBytes:([B)V
      25: aload_0
      26: aload_1
      27: aload_2
      28: iload_3
      29: aload         4
      31: invokevirtual #13                 // Method decode:(Lorg/apache/dubbo/remoting/Channel;Lorg/apache/dubbo/remoting/buffer/ChannelBuffer;I[B)Ljava/lang/Object;
      34: areturn

  protected java.lang.Object decode(org.apache.dubbo.remoting.Channel, org.apache.dubbo.remoting.buffer.ChannelBuffer, int, byte[]) throws java.io.IOException;
    Code:
       0: iload_3
       1: ifle          14
       4: aload         4
       6: iconst_0
       7: baload
       8: getstatic     #14                 // Field MAGIC_HIGH:B
      11: if_icmpne     29
      14: iload_3
      15: iconst_1
      16: if_icmple     147
      19: aload         4
      21: iconst_1
      22: baload
      23: getstatic     #15                 // Field MAGIC_LOW:B
      26: if_icmpeq     147
      29: aload         4
      31: arraylength
      32: istore        5
      34: aload         4
      36: arraylength
      37: iload_3
      38: if_icmpge     63
      41: aload         4
      43: iload_3
      44: invokestatic  #16                 // Method org/apache/dubbo/common/io/Bytes.copyOf:([BI)[B
      47: astore        4
      49: aload_2
      50: aload         4
      52: iload         5
      54: iload_3
      55: iload         5
      57: isub
      58: invokeinterface #17,  4           // InterfaceMethod org/apache/dubbo/remoting/buffer/ChannelBuffer.readBytes:([BII)V
      63: iconst_1
      64: istore        6
      66: iload         6
      68: aload         4
      70: arraylength
      71: iconst_1
      72: isub
      73: if_icmpge     137
      76: aload         4
      78: iload         6
      80: baload
      81: getstatic     #14                 // Field MAGIC_HIGH:B
      84: if_icmpne     131
      87: aload         4
      89: iload         6
      91: iconst_1
      92: iadd
      93: baload
      94: getstatic     #15                 // Field MAGIC_LOW:B
      97: if_icmpne     131
     100: aload_2
     101: aload_2
     102: invokeinterface #18,  1           // InterfaceMethod org/apache/dubbo/remoting/buffer/ChannelBuffer.readerIndex:()I
     107: aload         4
     109: arraylength
     110: isub
     111: iload         6
     113: iadd
     114: invokeinterface #19,  2           // InterfaceMethod org/apache/dubbo/remoting/buffer/ChannelBuffer.readerIndex:(I)V
     119: aload         4
     121: iload         6
     123: invokestatic  #16                 // Method org/apache/dubbo/common/io/Bytes.copyOf:([BI)[B
     126: astore        4
     128: goto          137
     131: iinc          6, 1
     134: goto          66
     137: aload_0
     138: aload_1
     139: aload_2
     140: iload_3
     141: aload         4
     143: invokespecial #20                 // Method org/apache/dubbo/remoting/telnet/codec/TelnetCodec.decode:(Lorg/apache/dubbo/remoting/Channel;Lorg/apache/dubbo/remoting/buffer/ChannelBuffer;I[B)Ljava/lang/Object;
     146: areturn
     147: iload_3
     148: bipush        16
     150: if_icmpge     157
     153: getstatic     #21                 // Field org/apache/dubbo/remoting/Codec2$DecodeResult.NEED_MORE_INPUT:Lorg/apache/dubbo/remoting/Codec2$DecodeResult;
     156: areturn
     157: aload         4
     159: bipush        12
     161: invokestatic  #22                 // Method org/apache/dubbo/common/io/Bytes.bytes2int:([BI)I
     164: istore        5
     166: aload_0
     167: aload_1
     168: iload         5
     170: i2l
     171: aload         4
     173: invokespecial #23                 // Method finishRespWhenOverPayload:(Lorg/apache/dubbo/remoting/Channel;J[B)Ljava/lang/Object;
     176: astore        6
     178: aconst_null
     179: aload         6
     181: if_acmpeq     187
     184: aload         6
     186: areturn
     187: iload         5
     189: bipush        16
     191: iadd
     192: istore        7
     194: iload_3
     195: iload         7
     197: if_icmpge     204
     200: getstatic     #21                 // Field org/apache/dubbo/remoting/Codec2$DecodeResult.NEED_MORE_INPUT:Lorg/apache/dubbo/remoting/Codec2$DecodeResult;
     203: areturn
     204: new           #24                 // class org/apache/dubbo/remoting/buffer/ChannelBufferInputStream
     207: dup
     208: aload_2
     209: iload         5
     211: invokespecial #25                 // Method org/apache/dubbo/remoting/buffer/ChannelBufferInputStream."<init>":(Lorg/apache/dubbo/remoting/buffer/ChannelBuffer;I)V
     214: astore        8
     216: aload_0
     217: aload_1
     218: aload         8
     220: aload         4
     222: invokevirtual #26                 // Method decodeBody:(Lorg/apache/dubbo/remoting/Channel;Ljava/io/InputStream;[B)Ljava/lang/Object;
     225: astore        9
     227: aload         8
     229: invokevirtual #27                 // Method org/apache/dubbo/remoting/buffer/ChannelBufferInputStream.available:()I
     232: ifle          314
     235: getstatic     #28                 // Field logger:Lorg/apache/dubbo/common/logger/ErrorTypeAwareLogger;
     238: invokeinterface #29,  1           // InterfaceMethod org/apache/dubbo/common/logger/ErrorTypeAwareLogger.isWarnEnabled:()Z
     243: ifeq          283
     246: getstatic     #28                 // Field logger:Lorg/apache/dubbo/common/logger/ErrorTypeAwareLogger;
     249: ldc           #30                 // String 6-15
     251: ldc           #31                 // String
     253: ldc           #31                 // String
     255: new           #32                 // class java/lang/StringBuilder
     258: dup
     259: invokespecial #33                 // Method java/lang/StringBuilder."<init>":()V
     262: ldc           #34                 // String Skip input stream
     264: invokevirtual #35                 // Method java/lang/StringBuilder.append:(Ljava/lang/String;)Ljava/lang/StringBuilder;
     267: aload         8
     269: invokevirtual #27                 // Method org/apache/dubbo/remoting/buffer/ChannelBufferInputStream.available:()I
     272: invokevirtual #36                 // Method java/lang/StringBuilder.append:(I)Ljava/lang/StringBuilder;
     275: invokevirtual #37                 // Method java/lang/StringBuilder.toString:()Ljava/lang/String;
     278: invokeinterface #38,  5           // InterfaceMethod org/apache/dubbo/common/logger/ErrorTypeAwareLogger.warn:(Ljava/lang/String;Ljava/lang/String;Ljava/lang/String;Ljava/lang/String;)V
     283: aload         8
     285: invokestatic  #39                 // Method org/apache/dubbo/common/io/StreamUtils.skipUnusedStream:(Ljava/io/InputStream;)V
     288: goto          314
     291: astore        10
     293: getstatic     #28                 // Field logger:Lorg/apache/dubbo/common/logger/ErrorTypeAwareLogger;
     296: ldc           #30                 // String 6-15
     298: ldc           #31                 // String
     300: ldc           #31                 // String
     302: aload         10
     304: invokevirtual #41                 // Method java/io/IOException.getMessage:()Ljava/lang/String;
     307: aload         10
     309: invokeinterface #42,  6           // InterfaceMethod org/apache/dubbo/common/logger/ErrorTypeAwareLogger.warn:(Ljava/lang/String;Ljava/lang/String;Ljava/lang/String;Ljava/lang/String;Ljava/lang/Throwable;)V
     314: aload         9
     316: areturn
     317: astore        11
     319: aload         8
     321: invokevirtual #27                 // Method org/apache/dubbo/remoting/buffer/ChannelBufferInputStream.available:()I
     324: ifle          406
     327: getstatic     #28                 // Field logger:Lorg/apache/dubbo/common/logger/ErrorTypeAwareLogger;
     330: invokeinterface #29,  1           // InterfaceMethod org/apache/dubbo/common/logger/ErrorTypeAwareLogger.isWarnEnabled:()Z
     335: ifeq          375
     338: getstatic     #28                 // Field logger:Lorg/apache/dubbo/common/logger/ErrorTypeAwareLogger;
     341: ldc           #30                 // String 6-15
     343: ldc           #31                 // String
     345: ldc           #31                 // String
     347: new           #32                 // class java/lang/StringBuilder
     350: dup
     351: invokespecial #33                 // Method java/lang/StringBuilder."<init>":()V
     354: ldc           #34                 // String Skip input stream
     356: invokevirtual #35                 // Method java/lang/StringBuilder.append:(Ljava/lang/String;)Ljava/lang/StringBuilder;
     359: aload         8
     361: invokevirtual #27                 // Method org/apache/dubbo/remoting/buffer/ChannelBufferInputStream.available:()I
     364: invokevirtual #36                 // Method java/lang/StringBuilder.append:(I)Ljava/lang/StringBuilder;
     367: invokevirtual #37                 // Method java/lang/StringBuilder.toString:()Ljava/lang/String;
     370: invokeinterface #38,  5           // InterfaceMethod org/apache/dubbo/common/logger/ErrorTypeAwareLogger.warn:(Ljava/lang/String;Ljava/lang/String;Ljava/lang/String;Ljava/lang/String;)V
     375: aload         8
     377: invokestatic  #39                 // Method org/apache/dubbo/common/io/StreamUtils.skipUnusedStream:(Ljava/io/InputStream;)V
     380: goto          406
     383: astore        12
     385: getstatic     #28                 // Field logger:Lorg/apache/dubbo/common/logger/ErrorTypeAwareLogger;
     388: ldc           #30                 // String 6-15
     390: ldc           #31                 // String
     392: ldc           #31                 // String
     394: aload         12
     396: invokevirtual #41                 // Method java/io/IOException.getMessage:()Ljava/lang/String;
     399: aload         12
     401: invokeinterface #42,  6           // InterfaceMethod org/apache/dubbo/common/logger/ErrorTypeAwareLogger.warn:(Ljava/lang/String;Ljava/lang/String;Ljava/lang/String;Ljava/lang/String;Ljava/lang/Throwable;)V
     406: aload         11
     408: athrow
    Exception table:
       from    to  target type
         235   288   291   Class java/io/IOException
         216   227   317   any
         327   380   383   Class java/io/IOException
         317   319   317   any

  protected java.lang.Object decodeBody(org.apache.dubbo.remoting.Channel, java.io.InputStream, byte[]) throws java.io.IOException;
    Code:
       0: aload_3
       1: iconst_2
       2: baload
       3: istore        4
       5: iload         4
       7: bipush        31
       9: iand
      10: i2b
      11: istore        5
      13: aload_3
      14: iconst_4
      15: invokestatic  #43                 // Method org/apache/dubbo/common/io/Bytes.bytes2long:([BI)J
      18: lstore        6
      20: iload         4
      22: bipush        -128
      24: iand
      25: ifne          219
      28: new           #7                  // class org/apache/dubbo/remoting/exchange/Response
      31: dup
      32: lload         6
      34: invokespecial #44                 // Method org/apache/dubbo/remoting/exchange/Response."<init>":(J)V
      37: astore        8
      39: iload         4
      41: bipush        32
      43: iand
      44: ifeq          53
      47: aload         8
      49: iconst_1
      50: invokevirtual #45                 // Method org/apache/dubbo/remoting/exchange/Response.setEvent:(Z)V
      53: aload_3
      54: iconst_3
      55: baload
      56: istore        9
      58: aload         8
      60: iload         9
      62: invokevirtual #46                 // Method org/apache/dubbo/remoting/exchange/Response.setStatus:(B)V
      65: iload         9
      67: bipush        20
      69: if_icmpne     172
      72: aload         8
      74: invokevirtual #47                 // Method org/apache/dubbo/remoting/exchange/Response.isEvent:()Z
      77: ifeq          134
      80: aload_2
      81: invokestatic  #48                 // Method org/apache/dubbo/remoting/transport/CodecSupport.getPayload:(Ljava/io/InputStream;)[B
      84: astore        11
      86: aload         11
      88: iload         5
      90: invokestatic  #49                 // Method org/apache/dubbo/remoting/transport/CodecSupport.isHeartBeat:([BB)Z
      93: ifeq          102
      96: aconst_null
      97: astore        10
      99: goto          131
     102: aload_0
     103: aload_1
     104: aload_1
     105: invokeinterface #50,  1           // InterfaceMethod org/apache/dubbo/remoting/Channel.getUrl:()Lorg/apache/dubbo/common/URL;
     110: new           #51                 // class java/io/ByteArrayInputStream
     113: dup
     114: aload         11
     116: invokespecial #52                 // Method java/io/ByteArrayInputStream."<init>":([B)V
     119: iload         5
     121: invokestatic  #53                 // Method org/apache/dubbo/remoting/transport/CodecSupport.deserialize:(Lorg/apache/dubbo/common/URL;Ljava/io/InputStream;B)Lorg/apache/dubbo/common/serialize/ObjectInput;
     124: aload         11
     126: invokevirtual #54                 // Method decodeEventData:(Lorg/apache/dubbo/remoting/Channel;Lorg/apache/dubbo/common/serialize/ObjectInput;[B)Ljava/lang/Object;
     129: astore        10
     131: goto          162
     134: aload_0
     135: aload_1
     136: aload_1
     137: invokeinterface #50,  1           // InterfaceMethod org/apache/dubbo/remoting/Channel.getUrl:()Lorg/apache/dubbo/common/URL;
     142: aload_2
     143: iload         5
     145: invokestatic  #53                 // Method org/apache/dubbo/remoting/transport/CodecSupport.deserialize:(Lorg/apache/dubbo/common/URL;Ljava/io/InputStream;B)Lorg/apache/dubbo/common/serialize/ObjectInput;
     148: aload_0
     149: aload_1
     150: aload         8
     152: lload         6
     154: invokevirtual #55                 // Method getRequestData:(Lorg/apache/dubbo/remoting/Channel;Lorg/apache/dubbo/remoting/exchange/Response;J)Ljava/lang/Object;
     157: invokevirtual #56                 // Method decodeResponseData:(Lorg/apache/dubbo/remoting/Channel;Lorg/apache/dubbo/common/serialize/ObjectInput;Ljava/lang/Object;)Ljava/lang/Object;
     160: astore        10
     162: aload         8
     164: aload         10
     166: invokevirtual #57                 // Method org/apache/dubbo/remoting/exchange/Response.setResult:(Ljava/lang/Object;)V
     169: goto          194
     172: aload         8
     174: aload_1
     175: invokeinterface #50,  1           // InterfaceMethod org/apache/dubbo/remoting/Channel.getUrl:()Lorg/apache/dubbo/common/URL;
     180: aload_2
     181: iload         5
     183: invokestatic  #53                 // Method org/apache/dubbo/remoting/transport/CodecSupport.deserialize:(Lorg/apache/dubbo/common/URL;Ljava/io/InputStream;B)Lorg/apache/dubbo/common/serialize/ObjectInput;
     186: invokeinterface #58,  1           // InterfaceMethod org/apache/dubbo/common/serialize/ObjectInput.readUTF:()Ljava/lang/String;
     191: invokevirtual #59                 // Method org/apache/dubbo/remoting/exchange/Response.setErrorMessage:(Ljava/lang/String;)V
     194: goto          216
     197: astore        10
     199: aload         8
     201: bipush        90
     203: invokevirtual #46                 // Method org/apache/dubbo/remoting/exchange/Response.setStatus:(B)V
     206: aload         8
     208: aload         10
     210: invokestatic  #61                 // Method org/apache/dubbo/common/utils/StringUtils.toString:(Ljava/lang/Throwable;)Ljava/lang/String;
     213: invokevirtual #59                 // Method org/apache/dubbo/remoting/exchange/Response.setErrorMessage:(Ljava/lang/String;)V
     216: aload         8
     218: areturn
     219: iload         4
     221: bipush        32
     223: iand
     224: ifeq          319
     227: aload_2
     228: invokestatic  #48                 // Method org/apache/dubbo/remoting/transport/CodecSupport.getPayload:(Ljava/io/InputStream;)[B
     231: astore        10
     233: aload         10
     235: iload         5
     237: invokestatic  #49                 // Method org/apache/dubbo/remoting/transport/CodecSupport.isHeartBeat:([BB)Z
     240: ifeq          270
     243: new           #62                 // class org/apache/dubbo/remoting/exchange/HeartBeatRequest
     246: dup
     247: lload         6
     249: invokespecial #63                 // Method org/apache/dubbo/remoting/exchange/HeartBeatRequest."<init>":(J)V
     252: astore        8
     254: aload         8
     256: checkcast     #62                 // class org/apache/dubbo/remoting/exchange/HeartBeatRequest
     259: iload         5
     261: invokevirtual #64                 // Method org/apache/dubbo/remoting/exchange/HeartBeatRequest.setProto:(B)V
     264: aconst_null
     265: astore        9
     267: goto          310
     270: new           #5                  // class org/apache/dubbo/remoting/exchange/Request
     273: dup
     274: lload         6
     276: invokespecial #65                 // Method org/apache/dubbo/remoting/exchange/Request."<init>":(J)V
     279: astore        8
     281: aload_0
     282: aload_1
     283: aload_1
     284: invokeinterface #50,  1           // InterfaceMethod org/apache/dubbo/remoting/Channel.getUrl:()Lorg/apache/dubbo/common/URL;
     289: new           #51                 // class java/io/ByteArrayInputStream
     292: dup
     293: aload         10
     295: invokespecial #52                 // Method java/io/ByteArrayInputStream."<init>":([B)V
     298: iload         5
     300: invokestatic  #53                 // Method org/apache/dubbo/remoting/transport/CodecSupport.deserialize:(Lorg/apache/dubbo/common/URL;Ljava/io/InputStream;B)Lorg/apache/dubbo/common/serialize/ObjectInput;
     303: aload         10
     305: invokevirtual #54                 // Method decodeEventData:(Lorg/apache/dubbo/remoting/Channel;Lorg/apache/dubbo/common/serialize/ObjectInput;[B)Ljava/lang/Object;
     308: astore        9
     310: aload         8
     312: iconst_1
     313: invokevirtual #66                 // Method org/apache/dubbo/remoting/exchange/Request.setEvent:(Z)V
     316: goto          349
     319: new           #5                  // class org/apache/dubbo/remoting/exchange/Request
     322: dup
     323: lload         6
     325: invokespecial #65                 // Method org/apache/dubbo/remoting/exchange/Request."<init>":(J)V
     328: astore        8
     330: aload_0
     331: aload_1
     332: aload_1
     333: invokeinterface #50,  1           // InterfaceMethod org/apache/dubbo/remoting/Channel.getUrl:()Lorg/apache/dubbo/common/URL;
     338: aload_2
     339: iload         5
     341: invokestatic  #53                 // Method org/apache/dubbo/remoting/transport/CodecSupport.deserialize:(Lorg/apache/dubbo/common/URL;Ljava/io/InputStream;B)Lorg/apache/dubbo/common/serialize/ObjectInput;
     344: invokevirtual #67                 // Method decodeRequestData:(Lorg/apache/dubbo/remoting/Channel;Lorg/apache/dubbo/common/serialize/ObjectInput;)Ljava/lang/Object;
     347: astore        9
     349: aload         8
     351: aload         9
     353: invokevirtual #68                 // Method org/apache/dubbo/remoting/exchange/Request.setData:(Ljava/lang/Object;)V
     356: goto          385
     359: astore        9
     361: new           #5                  // class org/apache/dubbo/remoting/exchange/Request
     364: dup
     365: lload         6
     367: invokespecial #65                 // Method org/apache/dubbo/remoting/exchange/Request."<init>":(J)V
     370: astore        8
     372: aload         8
     374: iconst_1
     375: invokevirtual #69                 // Method org/apache/dubbo/remoting/exchange/Request.setBroken:(Z)V
     378: aload         8
     380: aload         9
     382: invokevirtual #68                 // Method org/apache/dubbo/remoting/exchange/Request.setData:(Ljava/lang/Object;)V
     385: aload         8
     387: invokestatic  #70                 // Method org/apache/dubbo/common/Version.getProtocolVersion:()Ljava/lang/String;
     390: invokevirtual #71                 // Method org/apache/dubbo/remoting/exchange/Request.setVersion:(Ljava/lang/String;)V
     393: aload         8
     395: iload         4
     397: bipush        64
     399: iand
     400: ifeq          407
     403: iconst_1
     404: goto          408
     407: iconst_0
     408: invokevirtual #72                 // Method org/apache/dubbo/remoting/exchange/Request.setTwoWay:(Z)V
     411: aload         8
     413: areturn
    Exception table:
       from    to  target type
          65   194   197   Class java/lang/Throwable
         219   356   359   Class java/lang/Throwable

  protected java.lang.Object getRequestData(org.apache.dubbo.remoting.Channel, org.apache.dubbo.remoting.exchange.Response, long);
    Code:
       0: lload_3
       1: invokestatic  #73                 // Method org/apache/dubbo/remoting/exchange/support/DefaultFuture.getFuture:(J)Lorg/apache/dubbo/remoting/exchange/support/DefaultFuture;
       4: astore        5
       6: aload         5
       8: ifnull        29
      11: aload         5
      13: invokevirtual #74                 // Method org/apache/dubbo/remoting/exchange/support/DefaultFuture.getRequest:()Lorg/apache/dubbo/remoting/exchange/Request;
      16: astore        6
      18: aload         6
      20: ifnull        29
      23: aload         6
      25: invokevirtual #75                 // Method org/apache/dubbo/remoting/exchange/Request.getData:()Ljava/lang/Object;
      28: areturn
      29: getstatic     #28                 // Field logger:Lorg/apache/dubbo/common/logger/ErrorTypeAwareLogger;
      32: ldc           #76                 // String 4-13
      34: ldc           #31                 // String
      36: ldc           #31                 // String
      38: new           #32                 // class java/lang/StringBuilder
      41: dup
      42: invokespecial #33                 // Method java/lang/StringBuilder."<init>":()V
      45: ldc           #77                 // String The timeout response finally returned at
      47: invokevirtual #35                 // Method java/lang/StringBuilder.append:(Ljava/lang/String;)Ljava/lang/StringBuilder;
      50: new           #78                 // class java/text/SimpleDateFormat
      53: dup
      54: ldc           #79                 // String yyyy-MM-dd HH:mm:ss.SSS
      56: invokespecial #80                 // Method java/text/SimpleDateFormat."<init>":(Ljava/lang/String;)V
      59: new           #81                 // class java/util/Date
      62: dup
      63: invokespecial #82                 // Method java/util/Date."<init>":()V
      66: invokevirtual #83                 // Method java/text/SimpleDateFormat.format:(Ljava/util/Date;)Ljava/lang/String;
      69: invokevirtual #35                 // Method java/lang/StringBuilder.append:(Ljava/lang/String;)Ljava/lang/StringBuilder;
      72: ldc           #84                 // String , response status is
      74: invokevirtual #35                 // Method java/lang/StringBuilder.append:(Ljava/lang/String;)Ljava/lang/StringBuilder;
      77: aload_2
      78: invokevirtual #85                 // Method org/apache/dubbo/remoting/exchange/Response.getStatus:()B
      81: invokevirtual #36                 // Method java/lang/StringBuilder.append:(I)Ljava/lang/StringBuilder;
      84: ldc           #86                 // String , response id is
      86: invokevirtual #35                 // Method java/lang/StringBuilder.append:(Ljava/lang/String;)Ljava/lang/StringBuilder;
      89: aload_2
      90: invokevirtual #87                 // Method org/apache/dubbo/remoting/exchange/Response.getId:()J
      93: invokevirtual #88                 // Method java/lang/StringBuilder.append:(J)Ljava/lang/StringBuilder;
      96: aload_1
      97: ifnonnull     105
     100: ldc           #31                 // String
     102: goto          143
     105: new           #32                 // class java/lang/StringBuilder
     108: dup
     109: invokespecial #33                 // Method java/lang/StringBuilder."<init>":()V
     112: ldc           #89                 // String , channel:
     114: invokevirtual #35                 // Method java/lang/StringBuilder.append:(Ljava/lang/String;)Ljava/lang/StringBuilder;
     117: aload_1
     118: invokeinterface #90,  1           // InterfaceMethod org/apache/dubbo/remoting/Channel.getLocalAddress:()Ljava/net/InetSocketAddress;
     123: invokevirtual #91                 // Method java/lang/StringBuilder.append:(Ljava/lang/Object;)Ljava/lang/StringBuilder;
     126: ldc           #92                 // String  ->
     128: invokevirtual #35                 // Method java/lang/StringBuilder.append:(Ljava/lang/String;)Ljava/lang/StringBuilder;
     131: aload_1
     132: invokeinterface #93,  1           // InterfaceMethod org/apache/dubbo/remoting/Channel.getRemoteAddress:()Ljava/net/InetSocketAddress;
     137: invokevirtual #91                 // Method java/lang/StringBuilder.append:(Ljava/lang/Object;)Ljava/lang/StringBuilder;
     140: invokevirtual #37                 // Method java/lang/StringBuilder.toString:()Ljava/lang/String;
     143: invokevirtual #35                 // Method java/lang/StringBuilder.append:(Ljava/lang/String;)Ljava/lang/StringBuilder;
     146: ldc           #94                 // String , please check provider side for detailed result.
     148: invokevirtual #35                 // Method java/lang/StringBuilder.append:(Ljava/lang/String;)Ljava/lang/StringBuilder;
     151: invokevirtual #37                 // Method java/lang/StringBuilder.toString:()Ljava/lang/String;
     154: invokeinterface #38,  5           // InterfaceMethod org/apache/dubbo/common/logger/ErrorTypeAwareLogger.warn:(Ljava/lang/String;Ljava/lang/String;Ljava/lang/String;Ljava/lang/String;)V
     159: new           #95                 // class java/lang/IllegalArgumentException
     162: dup
     163: new           #32                 // class java/lang/StringBuilder
     166: dup
     167: invokespecial #33                 // Method java/lang/StringBuilder."<init>":()V
     170: ldc           #96                 // String Failed to find any request match the response, response id:
     172: invokevirtual #35                 // Method java/lang/StringBuilder.append:(Ljava/lang/String;)Ljava/lang/StringBuilder;
     175: lload_3
     176: invokevirtual #88                 // Method java/lang/StringBuilder.append:(J)Ljava/lang/StringBuilder;
     179: invokevirtual #37                 // Method java/lang/StringBuilder.toString:()Ljava/lang/String;
     182: invokespecial #97                 // Method java/lang/IllegalArgumentException."<init>":(Ljava/lang/String;)V
     185: athrow

  protected void encodeRequest(org.apache.dubbo.remoting.Channel, org.apache.dubbo.remoting.buffer.ChannelBuffer, org.apache.dubbo.remoting.exchange.Request) throws java.io.IOException;
    Code:
       0: aload_0
       1: aload_1
       2: aload_3
       3: invokevirtual #98                 // Method getSerialization:(Lorg/apache/dubbo/remoting/Channel;Lorg/apache/dubbo/remoting/exchange/Request;)Lorg/apache/dubbo/common/serialize/Serialization;
       6: astore        4
       8: bipush        16
      10: newarray       byte
      12: astore        5
      14: sipush        -9541
      17: aload         5
      19: invokestatic  #99                 // Method org/apache/dubbo/common/io/Bytes.short2bytes:(S[B)V
      22: aload         5
      24: iconst_2
      25: bipush        -128
      27: aload         4
      29: invokeinterface #100,  1          // InterfaceMethod org/apache/dubbo/common/serialize/Serialization.getContentTypeId:()B
      34: ior
      35: i2b
      36: bastore
      37: aload_3
      38: invokevirtual #101                // Method org/apache/dubbo/remoting/exchange/Request.isTwoWay:()Z
      41: ifeq          54
      44: aload         5
      46: iconst_2
      47: dup2
      48: baload
      49: bipush        64
      51: ior
      52: i2b
      53: bastore
      54: aload_3
      55: invokevirtual #102                // Method org/apache/dubbo/remoting/exchange/Request.isEvent:()Z
      58: ifeq          71
      61: aload         5
      63: iconst_2
      64: dup2
      65: baload
      66: bipush        32
      68: ior
      69: i2b
      70: bastore
      71: aload_3
      72: invokevirtual #103                // Method org/apache/dubbo/remoting/exchange/Request.getId:()J
      75: aload         5
      77: iconst_4
      78: invokestatic  #104                // Method org/apache/dubbo/common/io/Bytes.long2bytes:(J[BI)V
      81: aload_2
      82: invokeinterface #105,  1          // InterfaceMethod org/apache/dubbo/remoting/buffer/ChannelBuffer.writerIndex:()I
      87: istore        6
      89: aload_2
      90: iload         6
      92: bipush        16
      94: iadd
      95: invokeinterface #106,  2          // InterfaceMethod org/apache/dubbo/remoting/buffer/ChannelBuffer.writerIndex:(I)V
     100: new           #107                // class org/apache/dubbo/remoting/buffer/ChannelBufferOutputStream
     103: dup
     104: aload_2
     105: invokespecial #108                // Method org/apache/dubbo/remoting/buffer/ChannelBufferOutputStream."<init>":(Lorg/apache/dubbo/remoting/buffer/ChannelBuffer;)V
     108: astore        7
     110: aload_3
     111: invokevirtual #109                // Method org/apache/dubbo/remoting/exchange/Request.isHeartbeat:()Z
     114: ifeq          130
     117: aload         7
     119: aload         4
     121: invokestatic  #110                // Method org/apache/dubbo/remoting/transport/CodecSupport.getNullBytesOf:(Lorg/apache/dubbo/common/serialize/Serialization;)[B
     124: invokevirtual #111                // Method org/apache/dubbo/remoting/buffer/ChannelBufferOutputStream.write:([B)V
     127: goto          208
     130: aload         4
     132: aload_1
     133: invokeinterface #50,  1           // InterfaceMethod org/apache/dubbo/remoting/Channel.getUrl:()Lorg/apache/dubbo/common/URL;
     138: aload         7
     140: invokeinterface #112,  3          // InterfaceMethod org/apache/dubbo/common/serialize/Serialization.serialize:(Lorg/apache/dubbo/common/URL;Ljava/io/OutputStream;)Lorg/apache/dubbo/common/serialize/ObjectOutput;
     145: astore        8
     147: aload_3
     148: invokevirtual #102                // Method org/apache/dubbo/remoting/exchange/Request.isEvent:()Z
     151: ifeq          168
     154: aload_0
     155: aload_1
     156: aload         8
     158: aload_3
     159: invokevirtual #75                 // Method org/apache/dubbo/remoting/exchange/Request.getData:()Ljava/lang/Object;
     162: invokespecial #113                // Method encodeEventData:(Lorg/apache/dubbo/remoting/Channel;Lorg/apache/dubbo/common/serialize/ObjectOutput;Ljava/lang/Object;)V
     165: goto          183
     168: aload_0
     169: aload_1
     170: aload         8
     172: aload_3
     173: invokevirtual #75                 // Method org/apache/dubbo/remoting/exchange/Request.getData:()Ljava/lang/Object;
     176: aload_3
     177: invokevirtual #114                // Method org/apache/dubbo/remoting/exchange/Request.getVersion:()Ljava/lang/String;
     180: invokevirtual #115                // Method encodeRequestData:(Lorg/apache/dubbo/remoting/Channel;Lorg/apache/dubbo/common/serialize/ObjectOutput;Ljava/lang/Object;Ljava/lang/String;)V
     183: aload         8
     185: invokeinterface #116,  1          // InterfaceMethod org/apache/dubbo/common/serialize/ObjectOutput.flushBuffer:()V
     190: aload         8
     192: instanceof    #117                // class org/apache/dubbo/common/serialize/Cleanable
     195: ifeq          208
     198: aload         8
     200: checkcast     #117                // class org/apache/dubbo/common/serialize/Cleanable
     203: invokeinterface #118,  1          // InterfaceMethod org/apache/dubbo/common/serialize/Cleanable.cleanup:()V
     208: aload         7
     210: invokevirtual #119                // Method org/apache/dubbo/remoting/buffer/ChannelBufferOutputStream.flush:()V
     213: aload         7
     215: invokevirtual #120                // Method org/apache/dubbo/remoting/buffer/ChannelBufferOutputStream.close:()V
     218: aload         7
     220: invokevirtual #121                // Method org/apache/dubbo/remoting/buffer/ChannelBufferOutputStream.writtenBytes:()I
     223: istore        8
     225: aload_1
     226: aload_3
     227: invokevirtual #122                // Method org/apache/dubbo/remoting/exchange/Request.getPayload:()I
     230: iload         8
     232: i2l
     233: invokestatic  #123                // Method checkPayload:(Lorg/apache/dubbo/remoting/Channel;IJ)V
     236: iload         8
     238: aload         5
     240: bipush        12
     242: invokestatic  #124                // Method org/apache/dubbo/common/io/Bytes.int2bytes:(I[BI)V
     245: aload_2
     246: iload         6
     248: invokeinterface #106,  2          // InterfaceMethod org/apache/dubbo/remoting/buffer/ChannelBuffer.writerIndex:(I)V
     253: aload_2
     254: aload         5
     256: invokeinterface #125,  2          // InterfaceMethod org/apache/dubbo/remoting/buffer/ChannelBuffer.writeBytes:([B)V
     261: aload_2
     262: iload         6
     264: bipush        16
     266: iadd
     267: iload         8
     269: iadd
     270: invokeinterface #106,  2          // InterfaceMethod org/apache/dubbo/remoting/buffer/ChannelBuffer.writerIndex:(I)V
     275: return

  protected void encodeResponse(org.apache.dubbo.remoting.Channel, org.apache.dubbo.remoting.buffer.ChannelBuffer, org.apache.dubbo.remoting.exchange.Response) throws java.io.IOException;
    Code:
       0: aload_2
       1: invokeinterface #105,  1          // InterfaceMethod org/apache/dubbo/remoting/buffer/ChannelBuffer.writerIndex:()I
       6: istore        4
       8: aload_0
       9: aload_1
      10: aload_3
      11: invokevirtual #126                // Method getSerialization:(Lorg/apache/dubbo/remoting/Channel;Lorg/apache/dubbo/remoting/exchange/Response;)Lorg/apache/dubbo/common/serialize/Serialization;
      14: astore        5
      16: bipush        16
      18: newarray       byte
      20: astore        6
      22: sipush        -9541
      25: aload         6
      27: invokestatic  #99                 // Method org/apache/dubbo/common/io/Bytes.short2bytes:(S[B)V
      30: aload         6
      32: iconst_2
      33: aload         5
      35: invokeinterface #100,  1          // InterfaceMethod org/apache/dubbo/common/serialize/Serialization.getContentTypeId:()B
      40: bastore
      41: aload_3
      42: invokevirtual #127                // Method org/apache/dubbo/remoting/exchange/Response.isHeartbeat:()Z
      45: ifeq          58
      48: aload         6
      50: iconst_2
      51: dup2
      52: baload
      53: bipush        32
      55: ior
      56: i2b
      57: bastore
      58: aload_3
      59: invokevirtual #85                 // Method org/apache/dubbo/remoting/exchange/Response.getStatus:()B
      62: istore        7
      64: aload         6
      66: iconst_3
      67: iload         7
      69: bastore
      70: aload_3
      71: invokevirtual #87                 // Method org/apache/dubbo/remoting/exchange/Response.getId:()J
      74: aload         6
      76: iconst_4
      77: invokestatic  #104                // Method org/apache/dubbo/common/io/Bytes.long2bytes:(J[BI)V
      80: aload_2
      81: iload         4
      83: bipush        16
      85: iadd
      86: invokeinterface #106,  2          // InterfaceMethod org/apache/dubbo/remoting/buffer/ChannelBuffer.writerIndex:(I)V
      91: new           #107                // class org/apache/dubbo/remoting/buffer/ChannelBufferOutputStream
      94: dup
      95: aload_2
      96: invokespecial #108                // Method org/apache/dubbo/remoting/buffer/ChannelBufferOutputStream."<init>":(Lorg/apache/dubbo/remoting/buffer/ChannelBuffer;)V
      99: astore        8
     101: iload         7
     103: bipush        20
     105: if_icmpne     209
     108: aload_3
     109: invokevirtual #127                // Method org/apache/dubbo/remoting/exchange/Response.isHeartbeat:()Z
     112: ifeq          128
     115: aload         8
     117: aload         5
     119: invokestatic  #110                // Method org/apache/dubbo/remoting/transport/CodecSupport.getNullBytesOf:(Lorg/apache/dubbo/common/serialize/Serialization;)[B
     122: invokevirtual #111                // Method org/apache/dubbo/remoting/buffer/ChannelBufferOutputStream.write:([B)V
     125: goto          262
     128: aload         5
     130: aload_1
     131: invokeinterface #50,  1           // InterfaceMethod org/apache/dubbo/remoting/Channel.getUrl:()Lorg/apache/dubbo/common/URL;
     136: aload         8
     138: invokeinterface #112,  3          // InterfaceMethod org/apache/dubbo/common/serialize/Serialization.serialize:(Lorg/apache/dubbo/common/URL;Ljava/io/OutputStream;)Lorg/apache/dubbo/common/serialize/ObjectOutput;
     143: astore        9
     145: aload_3
     146: invokevirtual #47                 // Method org/apache/dubbo/remoting/exchange/Response.isEvent:()Z
     149: ifeq          166
     152: aload_0
     153: aload_1
     154: aload         9
     156: aload_3
     157: invokevirtual #128                // Method org/apache/dubbo/remoting/exchange/Response.getResult:()Ljava/lang/Object;
     160: invokespecial #113                // Method encodeEventData:(Lorg/apache/dubbo/remoting/Channel;Lorg/apache/dubbo/common/serialize/ObjectOutput;Ljava/lang/Object;)V
     163: goto          181
     166: aload_0
     167: aload_1
     168: aload         9
     170: aload_3
     171: invokevirtual #128                // Method org/apache/dubbo/remoting/exchange/Response.getResult:()Ljava/lang/Object;
     174: aload_3
     175: invokevirtual #129                // Method org/apache/dubbo/remoting/exchange/Response.getVersion:()Ljava/lang/String;
     178: invokevirtual #130                // Method encodeResponseData:(Lorg/apache/dubbo/remoting/Channel;Lorg/apache/dubbo/common/serialize/ObjectOutput;Ljava/lang/Object;Ljava/lang/String;)V
     181: aload         9
     183: invokeinterface #116,  1          // InterfaceMethod org/apache/dubbo/common/serialize/ObjectOutput.flushBuffer:()V
     188: aload         9
     190: instanceof    #117                // class org/apache/dubbo/common/serialize/Cleanable
     193: ifeq          206
     196: aload         9
     198: checkcast     #117                // class org/apache/dubbo/common/serialize/Cleanable
     201: invokeinterface #118,  1          // InterfaceMethod org/apache/dubbo/common/serialize/Cleanable.cleanup:()V
     206: goto          262
     209: aload         5
     211: aload_1
     212: invokeinterface #50,  1           // InterfaceMethod org/apache/dubbo/remoting/Channel.getUrl:()Lorg/apache/dubbo/common/URL;
     217: aload         8
     219: invokeinterface #112,  3          // InterfaceMethod org/apache/dubbo/common/serialize/Serialization.serialize:(Lorg/apache/dubbo/common/URL;Ljava/io/OutputStream;)Lorg/apache/dubbo/common/serialize/ObjectOutput;
     224: astore        9
     226: aload         9
     228: aload_3
     229: invokevirtual #131                // Method org/apache/dubbo/remoting/exchange/Response.getErrorMessage:()Ljava/lang/String;
     232: invokeinterface #132,  2          // InterfaceMethod org/apache/dubbo/common/serialize/ObjectOutput.writeUTF:(Ljava/lang/String;)V
     237: aload         9
     239: invokeinterface #116,  1          // InterfaceMethod org/apache/dubbo/common/serialize/ObjectOutput.flushBuffer:()V
     244: aload         9
     246: instanceof    #117                // class org/apache/dubbo/common/serialize/Cleanable
     249: ifeq          262
     252: aload         9
     254: checkcast     #117                // class org/apache/dubbo/common/serialize/Cleanable
     257: invokeinterface #118,  1          // InterfaceMethod org/apache/dubbo/common/serialize/Cleanable.cleanup:()V
     262: aload         8
     264: invokevirtual #119                // Method org/apache/dubbo/remoting/buffer/ChannelBufferOutputStream.flush:()V
     267: aload         8
     269: invokevirtual #120                // Method org/apache/dubbo/remoting/buffer/ChannelBufferOutputStream.close:()V
     272: aload         8
     274: invokevirtual #121                // Method org/apache/dubbo/remoting/buffer/ChannelBufferOutputStream.writtenBytes:()I
     277: istore        9
     279: aload_1
     280: iload         9
     282: i2l
     283: invokestatic  #133                // Method checkPayload:(Lorg/apache/dubbo/remoting/Channel;J)V
     286: iload         9
     288: aload         6
     290: bipush        12
     292: invokestatic  #124                // Method org/apache/dubbo/common/io/Bytes.int2bytes:(I[BI)V
     295: aload_2
     296: iload         4
     298: invokeinterface #106,  2          // InterfaceMethod org/apache/dubbo/remoting/buffer/ChannelBuffer.writerIndex:(I)V
     303: aload_2
     304: aload         6
     306: invokeinterface #125,  2          // InterfaceMethod org/apache/dubbo/remoting/buffer/ChannelBuffer.writeBytes:([B)V
     311: aload_2
     312: iload         4
     314: bipush        16
     316: iadd
     317: iload         9
     319: iadd
     320: invokeinterface #106,  2          // InterfaceMethod org/apache/dubbo/remoting/buffer/ChannelBuffer.writerIndex:(I)V
     325: goto          684
     328: astore        5
     330: aload_2
     331: iload         4
     333: invokeinterface #106,  2          // InterfaceMethod org/apache/dubbo/remoting/buffer/ChannelBuffer.writerIndex:(I)V
     338: aload_3
     339: invokevirtual #47                 // Method org/apache/dubbo/remoting/exchange/Response.isEvent:()Z
     342: ifne          627
     345: aload_3
     346: invokevirtual #85                 // Method org/apache/dubbo/remoting/exchange/Response.getStatus:()B
     349: bipush        50
     351: if_icmpeq     627
     354: new           #7                  // class org/apache/dubbo/remoting/exchange/Response
     357: dup
     358: aload_3
     359: invokevirtual #87                 // Method org/apache/dubbo/remoting/exchange/Response.getId:()J
     362: aload_3
     363: invokevirtual #129                // Method org/apache/dubbo/remoting/exchange/Response.getVersion:()Ljava/lang/String;
     366: invokespecial #134                // Method org/apache/dubbo/remoting/exchange/Response."<init>":(JLjava/lang/String;)V
     369: astore        6
     371: aload         6
     373: bipush        50
     375: invokevirtual #46                 // Method org/apache/dubbo/remoting/exchange/Response.setStatus:(B)V
     378: aload         5
     380: instanceof    #135                // class org/apache/dubbo/remoting/transport/ExceedPayloadLimitException
     383: ifeq          483
     386: getstatic     #28                 // Field logger:Lorg/apache/dubbo/common/logger/ErrorTypeAwareLogger;
     389: ldc           #136                // String 6-10
     391: ldc           #31                 // String
     393: ldc           #31                 // String
     395: aload         5
     397: invokevirtual #137                // Method java/lang/Throwable.getMessage:()Ljava/lang/String;
     400: aload         5
     402: invokeinterface #42,  6           // InterfaceMethod org/apache/dubbo/common/logger/ErrorTypeAwareLogger.warn:(Ljava/lang/String;Ljava/lang/String;Ljava/lang/String;Ljava/lang/String;Ljava/lang/Throwable;)V
     407: aload         6
     409: aload         5
     411: invokevirtual #137                // Method java/lang/Throwable.getMessage:()Ljava/lang/String;
     414: invokevirtual #59                 // Method org/apache/dubbo/remoting/exchange/Response.setErrorMessage:(Ljava/lang/String;)V
     417: aload_1
     418: aload         6
     420: invokeinterface #138,  2          // InterfaceMethod org/apache/dubbo/remoting/Channel.send:(Ljava/lang/Object;)V
     425: return
     426: astore        7
     428: getstatic     #28                 // Field logger:Lorg/apache/dubbo/common/logger/ErrorTypeAwareLogger;
     431: ldc           #140                // String 6-14
     433: ldc           #31                 // String
     435: ldc           #31                 // String
     437: new           #32                 // class java/lang/StringBuilder
     440: dup
     441: invokespecial #33                 // Method java/lang/StringBuilder."<init>":()V
     444: ldc           #141                // String Failed to send bad_response info back:
     446: invokevirtual #35                 // Method java/lang/StringBuilder.append:(Ljava/lang/String;)Ljava/lang/StringBuilder;
     449: aload         5
     451: invokevirtual #137                // Method java/lang/Throwable.getMessage:()Ljava/lang/String;
     454: invokevirtual #35                 // Method java/lang/StringBuilder.append:(Ljava/lang/String;)Ljava/lang/StringBuilder;
     457: ldc           #142                // String , cause:
     459: invokevirtual #35                 // Method java/lang/StringBuilder.append:(Ljava/lang/String;)Ljava/lang/StringBuilder;
     462: aload         7
     464: invokevirtual #143                // Method org/apache/dubbo/remoting/RemotingException.getMessage:()Ljava/lang/String;
     467: invokevirtual #35                 // Method java/lang/StringBuilder.append:(Ljava/lang/String;)Ljava/lang/StringBuilder;
     470: invokevirtual #37                 // Method java/lang/StringBuilder.toString:()Ljava/lang/String;
     473: aload         7
     475: invokeinterface #42,  6           // InterfaceMethod org/apache/dubbo/common/logger/ErrorTypeAwareLogger.warn:(Ljava/lang/String;Ljava/lang/String;Ljava/lang/String;Ljava/lang/String;Ljava/lang/Throwable;)V
     480: goto          627
     483: getstatic     #28                 // Field logger:Lorg/apache/dubbo/common/logger/ErrorTypeAwareLogger;
     486: ldc           #140                // String 6-14
     488: ldc           #31                 // String
     490: ldc           #31                 // String
     492: new           #32                 // class java/lang/StringBuilder
     495: dup
     496: invokespecial #33                 // Method java/lang/StringBuilder."<init>":()V
     499: ldc           #144                // String Fail to encode response:
     501: invokevirtual #35                 // Method java/lang/StringBuilder.append:(Ljava/lang/String;)Ljava/lang/StringBuilder;
     504: aload_3
     505: invokevirtual #91                 // Method java/lang/StringBuilder.append:(Ljava/lang/Object;)Ljava/lang/StringBuilder;
     508: ldc           #145                // String , send bad_response info instead, cause:
     510: invokevirtual #35                 // Method java/lang/StringBuilder.append:(Ljava/lang/String;)Ljava/lang/StringBuilder;
     513: aload         5
     515: invokevirtual #137                // Method java/lang/Throwable.getMessage:()Ljava/lang/String;
     518: invokevirtual #35                 // Method java/lang/StringBuilder.append:(Ljava/lang/String;)Ljava/lang/StringBuilder;
     521: invokevirtual #37                 // Method java/lang/StringBuilder.toString:()Ljava/lang/String;
     524: aload         5
     526: invokeinterface #42,  6           // InterfaceMethod org/apache/dubbo/common/logger/ErrorTypeAwareLogger.warn:(Ljava/lang/String;Ljava/lang/String;Ljava/lang/String;Ljava/lang/String;Ljava/lang/Throwable;)V
     531: aload         6
     533: new           #32                 // class java/lang/StringBuilder
     536: dup
     537: invokespecial #33                 // Method java/lang/StringBuilder."<init>":()V
     540: ldc           #146                // String Failed to send response:
     542: invokevirtual #35                 // Method java/lang/StringBuilder.append:(Ljava/lang/String;)Ljava/lang/StringBuilder;
     545: aload_3
     546: invokevirtual #91                 // Method java/lang/StringBuilder.append:(Ljava/lang/Object;)Ljava/lang/StringBuilder;
     549: ldc           #142                // String , cause:
     551: invokevirtual #35                 // Method java/lang/StringBuilder.append:(Ljava/lang/String;)Ljava/lang/StringBuilder;
     554: aload         5
     556: invokestatic  #61                 // Method org/apache/dubbo/common/utils/StringUtils.toString:(Ljava/lang/Throwable;)Ljava/lang/String;
     559: invokevirtual #35                 // Method java/lang/StringBuilder.append:(Ljava/lang/String;)Ljava/lang/StringBuilder;
     562: invokevirtual #37                 // Method java/lang/StringBuilder.toString:()Ljava/lang/String;
     565: invokevirtual #59                 // Method org/apache/dubbo/remoting/exchange/Response.setErrorMessage:(Ljava/lang/String;)V
     568: aload_1
     569: aload         6
     571: invokeinterface #138,  2          // InterfaceMethod org/apache/dubbo/remoting/Channel.send:(Ljava/lang/Object;)V
     576: return
     577: astore        7
     579: getstatic     #28                 // Field logger:Lorg/apache/dubbo/common/logger/ErrorTypeAwareLogger;
     582: ldc           #140                // String 6-14
     584: ldc           #31                 // String
     586: ldc           #31                 // String
     588: new           #32                 // class java/lang/StringBuilder
     591: dup
     592: invokespecial #33                 // Method java/lang/StringBuilder."<init>":()V
     595: ldc           #141                // String Failed to send bad_response info back:
     597: invokevirtual #35                 // Method java/lang/StringBuilder.append:(Ljava/lang/String;)Ljava/lang/StringBuilder;
     600: aload_3
     601: invokevirtual #91                 // Method java/lang/StringBuilder.append:(Ljava/lang/Object;)Ljava/lang/StringBuilder;
     604: ldc           #142                // String , cause:
     606: invokevirtual #35                 // Method java/lang/StringBuilder.append:(Ljava/lang/String;)Ljava/lang/StringBuilder;
     609: aload         7
     611: invokevirtual #143                // Method org/apache/dubbo/remoting/RemotingException.getMessage:()Ljava/lang/String;
     614: invokevirtual #35                 // Method java/lang/StringBuilder.append:(Ljava/lang/String;)Ljava/lang/StringBuilder;
     617: invokevirtual #37                 // Method java/lang/StringBuilder.toString:()Ljava/lang/String;
     620: aload         7
     622: invokeinterface #42,  6           // InterfaceMethod org/apache/dubbo/common/logger/ErrorTypeAwareLogger.warn:(Ljava/lang/String;Ljava/lang/String;Ljava/lang/String;Ljava/lang/String;Ljava/lang/Throwable;)V
     627: aload         5
     629: instanceof    #40                 // class java/io/IOException
     632: ifeq          641
     635: aload         5
     637: checkcast     #40                 // class java/io/IOException
     640: athrow
     641: aload         5
     643: instanceof    #147                // class java/lang/RuntimeException
     646: ifeq          655
     649: aload         5
     651: checkcast     #147                // class java/lang/RuntimeException
     654: athrow
     655: aload         5
     657: instanceof    #148                // class java/lang/Error
     660: ifeq          669
     663: aload         5
     665: checkcast     #148                // class java/lang/Error
     668: athrow
     669: new           #147                // class java/lang/RuntimeException
     672: dup
     673: aload         5
     675: invokevirtual #137                // Method java/lang/Throwable.getMessage:()Ljava/lang/String;
     678: aload         5
     680: invokespecial #149                // Method java/lang/RuntimeException."<init>":(Ljava/lang/String;Ljava/lang/Throwable;)V
     683: athrow
     684: return
    Exception table:
       from    to  target type
           8   325   328   Class java/lang/Throwable
         407   425   426   Class org/apache/dubbo/remoting/RemotingException
         531   576   577   Class org/apache/dubbo/remoting/RemotingException

  protected java.lang.Object decodeData(org.apache.dubbo.common.serialize.ObjectInput) throws java.io.IOException;
    Code:
       0: aload_0
       1: aload_1
       2: invokevirtual #150                // Method decodeRequestData:(Lorg/apache/dubbo/common/serialize/ObjectInput;)Ljava/lang/Object;
       5: areturn

  protected java.lang.Object decodeRequestData(org.apache.dubbo.common.serialize.ObjectInput) throws java.io.IOException;
    Code:
       0: aload_1
       1: invokeinterface #151,  1          // InterfaceMethod org/apache/dubbo/common/serialize/ObjectInput.readObject:()Ljava/lang/Object;
       6: areturn
       7: astore_2
       8: new           #40                 // class java/io/IOException
      11: dup
      12: ldc           #153                // String Read object failed.
      14: aload_2
      15: invokestatic  #154                // Method org/apache/dubbo/common/utils/StringUtils.toString:(Ljava/lang/String;Ljava/lang/Throwable;)Ljava/lang/String;
      18: invokespecial #155                // Method java/io/IOException."<init>":(Ljava/lang/String;)V
      21: athrow
    Exception table:
       from    to  target type
           0     6     7   Class java/lang/ClassNotFoundException

  protected java.lang.Object decodeResponseData(org.apache.dubbo.common.serialize.ObjectInput) throws java.io.IOException;
    Code:
       0: aload_1
       1: invokeinterface #151,  1          // InterfaceMethod org/apache/dubbo/common/serialize/ObjectInput.readObject:()Ljava/lang/Object;
       6: areturn
       7: astore_2
       8: new           #40                 // class java/io/IOException
      11: dup
      12: ldc           #153                // String Read object failed.
      14: aload_2
      15: invokestatic  #154                // Method org/apache/dubbo/common/utils/StringUtils.toString:(Ljava/lang/String;Ljava/lang/Throwable;)Ljava/lang/String;
      18: invokespecial #155                // Method java/io/IOException."<init>":(Ljava/lang/String;)V
      21: athrow
    Exception table:
       from    to  target type
           0     6     7   Class java/lang/ClassNotFoundException

  protected void encodeData(org.apache.dubbo.common.serialize.ObjectOutput, java.lang.Object) throws java.io.IOException;
    Code:
       0: aload_0
       1: aload_1
       2: aload_2
       3: invokevirtual #156                // Method encodeRequestData:(Lorg/apache/dubbo/common/serialize/ObjectOutput;Ljava/lang/Object;)V
       6: return

  private void encodeEventData(org.apache.dubbo.common.serialize.ObjectOutput, java.lang.Object) throws java.io.IOException;
    Code:
       0: aload_1
       1: aload_2
       2: checkcast     #157                // class java/lang/String
       5: invokeinterface #158,  2          // InterfaceMethod org/apache/dubbo/common/serialize/ObjectOutput.writeEvent:(Ljava/lang/String;)V
      10: return

  protected void encodeHeartbeatData(org.apache.dubbo.common.serialize.ObjectOutput, java.lang.Object) throws java.io.IOException;
    Code:
       0: aload_0
       1: aload_1
       2: aload_2
       3: invokespecial #159                // Method encodeEventData:(Lorg/apache/dubbo/common/serialize/ObjectOutput;Ljava/lang/Object;)V
       6: return

  protected void encodeRequestData(org.apache.dubbo.common.serialize.ObjectOutput, java.lang.Object) throws java.io.IOException;
    Code:
       0: aload_1
       1: aload_2
       2: invokeinterface #160,  2          // InterfaceMethod org/apache/dubbo/common/serialize/ObjectOutput.writeObject:(Ljava/lang/Object;)V
       7: return

  protected void encodeResponseData(org.apache.dubbo.common.serialize.ObjectOutput, java.lang.Object) throws java.io.IOException;
    Code:
       0: aload_1
       1: aload_2
       2: invokeinterface #160,  2          // InterfaceMethod org/apache/dubbo/common/serialize/ObjectOutput.writeObject:(Ljava/lang/Object;)V
       7: return

  protected java.lang.Object decodeData(org.apache.dubbo.remoting.Channel, org.apache.dubbo.common.serialize.ObjectInput) throws java.io.IOException;
    Code:
       0: aload_0
       1: aload_1
       2: aload_2
       3: invokevirtual #67                 // Method decodeRequestData:(Lorg/apache/dubbo/remoting/Channel;Lorg/apache/dubbo/common/serialize/ObjectInput;)Ljava/lang/Object;
       6: areturn

  protected java.lang.Object decodeEventData(org.apache.dubbo.remoting.Channel, org.apache.dubbo.common.serialize.ObjectInput, byte[]) throws java.io.IOException;
    Code:
       0: aload_3
       1: ifnull        81
       4: aload_3
       5: arraylength
       6: istore        4
       8: aload_1
       9: invokeinterface #50,  1           // InterfaceMethod org/apache/dubbo/remoting/Channel.getUrl:()Lorg/apache/dubbo/common/URL;
      14: invokevirtual #161                // Method org/apache/dubbo/common/URL.getScopeModel:()Lorg/apache/dubbo/rpc/model/ScopeModel;
      17: invokestatic  #162                // Method org/apache/dubbo/common/config/ConfigurationUtils.getSystemConfiguration:(Lorg/apache/dubbo/rpc/model/ScopeModel;)Lorg/apache/dubbo/common/config/Configuration;
      20: ldc           #163                // String deserialization.event.size
      22: bipush        15
      24: invokeinterface #164,  3          // InterfaceMethod org/apache/dubbo/common/config/Configuration.getInt:(Ljava/lang/String;I)I
      29: istore        5
      31: iload         4
      33: iload         5
      35: if_icmple     81
      38: new           #95                 // class java/lang/IllegalArgumentException
      41: dup
      42: new           #32                 // class java/lang/StringBuilder
      45: dup
      46: invokespecial #33                 // Method java/lang/StringBuilder."<init>":()V
      49: ldc           #165                // String Event data too long, actual size
      51: invokevirtual #35                 // Method java/lang/StringBuilder.append:(Ljava/lang/String;)Ljava/lang/StringBuilder;
      54: iload         5
      56: invokevirtual #36                 // Method java/lang/StringBuilder.append:(I)Ljava/lang/StringBuilder;
      59: ldc           #166                // String , threshold
      61: invokevirtual #35                 // Method java/lang/StringBuilder.append:(Ljava/lang/String;)Ljava/lang/StringBuilder;
      64: iload         5
      66: invokevirtual #36                 // Method java/lang/StringBuilder.append:(I)Ljava/lang/StringBuilder;
      69: ldc           #167                // String  rejected for security consideration.
      71: invokevirtual #35                 // Method java/lang/StringBuilder.append:(Ljava/lang/String;)Ljava/lang/StringBuilder;
      74: invokevirtual #37                 // Method java/lang/StringBuilder.toString:()Ljava/lang/String;
      77: invokespecial #97                 // Method java/lang/IllegalArgumentException."<init>":(Ljava/lang/String;)V
      80: athrow
      81: aload_2
      82: invokeinterface #168,  1          // InterfaceMethod org/apache/dubbo/common/serialize/ObjectInput.readEvent:()Ljava/lang/String;
      87: areturn
      88: astore        4
      90: new           #40                 // class java/io/IOException
      93: dup
      94: ldc           #169                // String Decode dubbo protocol event failed.
      96: aload         4
      98: invokestatic  #154                // Method org/apache/dubbo/common/utils/StringUtils.toString:(Ljava/lang/String;Ljava/lang/Throwable;)Ljava/lang/String;
     101: invokespecial #155                // Method java/io/IOException."<init>":(Ljava/lang/String;)V
     104: athrow
    Exception table:
       from    to  target type
           0    87    88   Class java/io/IOException
           0    87    88   Class java/lang/ClassNotFoundException

  protected java.lang.Object decodeRequestData(org.apache.dubbo.remoting.Channel, org.apache.dubbo.common.serialize.ObjectInput) throws java.io.IOException;
    Code:
       0: aload_0
       1: aload_2
       2: invokevirtual #150                // Method decodeRequestData:(Lorg/apache/dubbo/common/serialize/ObjectInput;)Ljava/lang/Object;
       5: areturn

  protected java.lang.Object decodeResponseData(org.apache.dubbo.remoting.Channel, org.apache.dubbo.common.serialize.ObjectInput) throws java.io.IOException;
    Code:
       0: aload_0
       1: aload_2
       2: invokevirtual #170                // Method decodeResponseData:(Lorg/apache/dubbo/common/serialize/ObjectInput;)Ljava/lang/Object;
       5: areturn

  protected java.lang.Object decodeResponseData(org.apache.dubbo.remoting.Channel, org.apache.dubbo.common.serialize.ObjectInput, java.lang.Object) throws java.io.IOException;
    Code:
       0: aload_0
       1: aload_1
       2: aload_2
       3: invokevirtual #171                // Method decodeResponseData:(Lorg/apache/dubbo/remoting/Channel;Lorg/apache/dubbo/common/serialize/ObjectInput;)Ljava/lang/Object;
       6: areturn

  protected void encodeData(org.apache.dubbo.remoting.Channel, org.apache.dubbo.common.serialize.ObjectOutput, java.lang.Object) throws java.io.IOException;
    Code:
       0: aload_0
       1: aload_1
       2: aload_2
       3: aload_3
       4: invokevirtual #172                // Method encodeRequestData:(Lorg/apache/dubbo/remoting/Channel;Lorg/apache/dubbo/common/serialize/ObjectOutput;Ljava/lang/Object;)V
       7: return

  private void encodeEventData(org.apache.dubbo.remoting.Channel, org.apache.dubbo.common.serialize.ObjectOutput, java.lang.Object) throws java.io.IOException;
    Code:
       0: aload_0
       1: aload_2
       2: aload_3
       3: invokespecial #159                // Method encodeEventData:(Lorg/apache/dubbo/common/serialize/ObjectOutput;Ljava/lang/Object;)V
       6: return

  protected void encodeHeartbeatData(org.apache.dubbo.remoting.Channel, org.apache.dubbo.common.serialize.ObjectOutput, java.lang.Object) throws java.io.IOException;
    Code:
       0: aload_0
       1: aload_2
       2: aload_3
       3: invokevirtual #173                // Method encodeHeartbeatData:(Lorg/apache/dubbo/common/serialize/ObjectOutput;Ljava/lang/Object;)V
       6: return

  protected void encodeRequestData(org.apache.dubbo.remoting.Channel, org.apache.dubbo.common.serialize.ObjectOutput, java.lang.Object) throws java.io.IOException;
    Code:
       0: aload_0
       1: aload_2
       2: aload_3
       3: invokevirtual #156                // Method encodeRequestData:(Lorg/apache/dubbo/common/serialize/ObjectOutput;Ljava/lang/Object;)V
       6: return

  protected void encodeResponseData(org.apache.dubbo.remoting.Channel, org.apache.dubbo.common.serialize.ObjectOutput, java.lang.Object) throws java.io.IOException;
    Code:
       0: aload_0
       1: aload_2
       2: aload_3
       3: invokevirtual #174                // Method encodeResponseData:(Lorg/apache/dubbo/common/serialize/ObjectOutput;Ljava/lang/Object;)V
       6: return

  protected void encodeRequestData(org.apache.dubbo.remoting.Channel, org.apache.dubbo.common.serialize.ObjectOutput, java.lang.Object, java.lang.String) throws java.io.IOException;
    Code:
       0: aload_0
       1: aload_2
       2: aload_3
       3: invokevirtual #156                // Method encodeRequestData:(Lorg/apache/dubbo/common/serialize/ObjectOutput;Ljava/lang/Object;)V
       6: return

  protected void encodeResponseData(org.apache.dubbo.remoting.Channel, org.apache.dubbo.common.serialize.ObjectOutput, java.lang.Object, java.lang.String) throws java.io.IOException;
    Code:
       0: aload_0
       1: aload_2
       2: aload_3
       3: invokevirtual #174                // Method encodeResponseData:(Lorg/apache/dubbo/common/serialize/ObjectOutput;Ljava/lang/Object;)V
       6: return

  private java.lang.Object finishRespWhenOverPayload(org.apache.dubbo.remoting.Channel, long, byte[]);
    Code:
       0: aload         4
       2: iconst_2
       3: baload
       4: istore        5
       6: iload         5
       8: bipush        -128
      10: iand
      11: ifne          139
      14: aload_1
      15: invokestatic  #175                // Method getPayload:(Lorg/apache/dubbo/remoting/Channel;)I
      18: istore        6
      20: iload         6
      22: lload_2
      23: invokestatic  #176                // Method isOverPayload:(IJ)Z
      26: istore        7
      28: iload         7
      30: ifeq          139
      33: aload         4
      35: iconst_4
      36: invokestatic  #43                 // Method org/apache/dubbo/common/io/Bytes.bytes2long:([BI)J
      39: lstore        8
      41: new           #7                  // class org/apache/dubbo/remoting/exchange/Response
      44: dup
      45: lload         8
      47: invokespecial #44                 // Method org/apache/dubbo/remoting/exchange/Response."<init>":(J)V
      50: astore        10
      52: iload         5
      54: bipush        32
      56: iand
      57: ifeq          66
      60: aload         10
      62: iconst_1
      63: invokevirtual #45                 // Method org/apache/dubbo/remoting/exchange/Response.setEvent:(Z)V
      66: aload         10
      68: bipush        90
      70: invokevirtual #46                 // Method org/apache/dubbo/remoting/exchange/Response.setStatus:(B)V
      73: new           #32                 // class java/lang/StringBuilder
      76: dup
      77: invokespecial #33                 // Method java/lang/StringBuilder."<init>":()V
      80: ldc           #177                // String Data length too large:
      82: invokevirtual #35                 // Method java/lang/StringBuilder.append:(Ljava/lang/String;)Ljava/lang/StringBuilder;
      85: lload_2
      86: invokevirtual #88                 // Method java/lang/StringBuilder.append:(J)Ljava/lang/StringBuilder;
      89: ldc           #178                // String , max payload:
      91: invokevirtual #35                 // Method java/lang/StringBuilder.append:(Ljava/lang/String;)Ljava/lang/StringBuilder;
      94: iload         6
      96: invokevirtual #36                 // Method java/lang/StringBuilder.append:(I)Ljava/lang/StringBuilder;
      99: ldc           #89                 // String , channel:
     101: invokevirtual #35                 // Method java/lang/StringBuilder.append:(Ljava/lang/String;)Ljava/lang/StringBuilder;
     104: aload_1
     105: invokevirtual #91                 // Method java/lang/StringBuilder.append:(Ljava/lang/Object;)Ljava/lang/StringBuilder;
     108: invokevirtual #37                 // Method java/lang/StringBuilder.toString:()Ljava/lang/String;
     111: astore        11
     113: getstatic     #28                 // Field logger:Lorg/apache/dubbo/common/logger/ErrorTypeAwareLogger;
     116: ldc           #136                // String 6-10
     118: ldc           #31                 // String
     120: ldc           #31                 // String
     122: aload         11
     124: invokeinterface #179,  5          // InterfaceMethod org/apache/dubbo/common/logger/ErrorTypeAwareLogger.error:(Ljava/lang/String;Ljava/lang/String;Ljava/lang/String;Ljava/lang/String;)V
     129: aload         10
     131: aload         11
     133: invokevirtual #59                 // Method org/apache/dubbo/remoting/exchange/Response.setErrorMessage:(Ljava/lang/String;)V
     136: aload         10
     138: areturn
     139: aconst_null
     140: areturn

  static {};
    Code:
       0: sipush        -9541
       3: invokestatic  #180                // Method org/apache/dubbo/common/io/Bytes.short2bytes:(S)[B
       6: iconst_0
       7: baload
       8: putstatic     #14                 // Field MAGIC_HIGH:B
      11: sipush        -9541
      14: invokestatic  #180                // Method org/apache/dubbo/common/io/Bytes.short2bytes:(S)[B
      17: iconst_1
      18: baload
      19: putstatic     #15                 // Field MAGIC_LOW:B
      22: ldc           #3                  // class org/apache/dubbo/remoting/exchange/codec/ExchangeCodec
      24: invokestatic  #181                // Method org/apache/dubbo/common/logger/LoggerFactory.getErrorTypeAwareLogger:(Ljava/lang/Class;)Lorg/apache/dubbo/common/logger/ErrorTypeAwareLogger;
      27: putstatic     #28                 // Field logger:Lorg/apache/dubbo/common/logger/ErrorTypeAwareLogger;
      30: return
}
