Compiled from "Hessian2ScopeModelInitializer.java"
public class org.apache.dubbo.common.serialize.hessian2.Hessian2ScopeModelInitializer implements org.apache.dubbo.rpc.model.ScopeModelInitializer {
  public org.apache.dubbo.common.serialize.hessian2.Hessian2ScopeModelInitializer();
    Code:
       0: aload_0
       1: invokespecial #1                  // Method java/lang/Object."<init>":()V
       4: return

  public void initializeFrameworkModel(org.apache.dubbo.rpc.model.FrameworkModel);
    Code:
       0: aload_1
       1: invokevirtual #2                  // Method org/apache/dubbo/rpc/model/FrameworkModel.getBeanFactory:()Lorg/apache/dubbo/common/beans/factory/ScopeBeanFactory;
       4: astore_2
       5: aload_2
       6: ldc           #3                  // class org/apache/dubbo/common/serialize/hessian2/Hessian2FactoryManager
       8: invokevirtual #4                  // Method org/apache/dubbo/common/beans/factory/ScopeBeanFactory.registerBean:(Ljava/lang/Class;)Ljava/lang/Object;
      11: pop
      12: aload_1
      13: new           #5                  // class org/apache/dubbo/common/serialize/hessian2/Hessian2ClassLoaderListener
      16: dup
      17: invokespecial #6                  // Method org/apache/dubbo/common/serialize/hessian2/Hessian2ClassLoaderListener."<init>":()V
      20: invokevirtual #7                  // Method org/apache/dubbo/rpc/model/FrameworkModel.addClassLoaderListener:(Lorg/apache/dubbo/rpc/model/ScopeClassLoaderListener;)V
      23: return

  public void initializeApplicationModel(org.apache.dubbo.rpc.model.ApplicationModel);
    Code:
       0: return

  public void initializeModuleModel(org.apache.dubbo.rpc.model.ModuleModel);
    Code:
       0: return
}
