Compiled from "Hessian2SerializerFactory.java"
public class org.apache.dubbo.common.serialize.hessian2.Hessian2SerializerFactory extends com.alibaba.com.caucho.hessian.io.SerializerFactory {
  private final org.apache.dubbo.common.utils.DefaultSerializeClassChecker defaultSerializeClassChecker;

  public org.apache.dubbo.common.serialize.hessian2.Hessian2SerializerFactory(org.apache.dubbo.common.utils.DefaultSerializeClassChecker);
    Code:
       0: aload_0
       1: invokespecial #1                  // Method com/alibaba/com/caucho/hessian/io/SerializerFactory."<init>":()V
       4: aload_0
       5: aload_1
       6: putfield      #2                  // Field defaultSerializeClassChecker:Lorg/apache/dubbo/common/utils/DefaultSerializeClassChecker;
       9: return

  public java.lang.Class<?> loadSerializedClass(java.lang.String) throws java.lang.ClassNotFoundException;
    Code:
       0: aload_0
       1: getfield      #2                  // Field defaultSerializeClassChecker:Lorg/apache/dubbo/common/utils/DefaultSerializeClassChecker;
       4: aload_0
       5: invokevirtual #3                  // Method getClassLoader:()Ljava/lang/ClassLoader;
       8: aload_1
       9: invokevirtual #4                  // Method org/apache/dubbo/common/utils/DefaultSerializeClassChecker.loadClass:(Ljava/lang/ClassLoader;Ljava/lang/String;)Ljava/lang/Class;
      12: areturn

  protected com.alibaba.com.caucho.hessian.io.Serializer getDefaultSerializer(java.lang.Class);
    Code:
       0: aload_0
       1: getfield      #5                  // Field _defaultSerializer:Lcom/alibaba/com/caucho/hessian/io/Serializer;
       4: ifnull        12
       7: aload_0
       8: getfield      #5                  // Field _defaultSerializer:Lcom/alibaba/com/caucho/hessian/io/Serializer;
      11: areturn
      12: aload_0
      13: getfield      #2                  // Field defaultSerializeClassChecker:Lorg/apache/dubbo/common/utils/DefaultSerializeClassChecker;
      16: aload_0
      17: invokevirtual #3                  // Method getClassLoader:()Ljava/lang/ClassLoader;
      20: aload_1
      21: invokevirtual #6                  // Method java/lang/Class.getName:()Ljava/lang/String;
      24: invokevirtual #4                  // Method org/apache/dubbo/common/utils/DefaultSerializeClassChecker.loadClass:(Ljava/lang/ClassLoader;Ljava/lang/String;)Ljava/lang/Class;
      27: pop
      28: goto          32
      31: astore_2
      32: aload_0
      33: aload_1
      34: invokespecial #8                  // Method checkSerializable:(Ljava/lang/Class;)V
      37: new           #9                  // class com/alibaba/com/caucho/hessian/io/JavaSerializer
      40: dup
      41: aload_1
      42: aload_0
      43: invokevirtual #3                  // Method getClassLoader:()Ljava/lang/ClassLoader;
      46: invokespecial #10                 // Method com/alibaba/com/caucho/hessian/io/JavaSerializer."<init>":(Ljava/lang/Class;Ljava/lang/ClassLoader;)V
      49: areturn
    Exception table:
       from    to  target type
          12    28    31   Class java/lang/ClassNotFoundException

  protected com.alibaba.com.caucho.hessian.io.Deserializer getDefaultDeserializer(java.lang.Class);
    Code:
       0: aload_0
       1: getfield      #2                  // Field defaultSerializeClassChecker:Lorg/apache/dubbo/common/utils/DefaultSerializeClassChecker;
       4: aload_0
       5: invokevirtual #3                  // Method getClassLoader:()Ljava/lang/ClassLoader;
       8: aload_1
       9: invokevirtual #6                  // Method java/lang/Class.getName:()Ljava/lang/String;
      12: invokevirtual #4                  // Method org/apache/dubbo/common/utils/DefaultSerializeClassChecker.loadClass:(Ljava/lang/ClassLoader;Ljava/lang/String;)Ljava/lang/Class;
      15: pop
      16: goto          20
      19: astore_2
      20: aload_0
      21: aload_1
      22: invokespecial #8                  // Method checkSerializable:(Ljava/lang/Class;)V
      25: new           #11                 // class com/alibaba/com/caucho/hessian/io/JavaDeserializer
      28: dup
      29: aload_1
      30: invokespecial #12                 // Method com/alibaba/com/caucho/hessian/io/JavaDeserializer."<init>":(Ljava/lang/Class;)V
      33: areturn
    Exception table:
       from    to  target type
           0    16    19   Class java/lang/ClassNotFoundException

  private void checkSerializable(java.lang.Class<?>);
    Code:
       0: ldc           #13                 // class java/io/Serializable
       2: aload_1
       3: invokevirtual #14                 // Method java/lang/Class.isAssignableFrom:(Ljava/lang/Class;)Z
       6: ifne          61
       9: aload_0
      10: invokevirtual #15                 // Method isAllowNonSerializable:()Z
      13: ifeq          26
      16: aload_0
      17: getfield      #2                  // Field defaultSerializeClassChecker:Lorg/apache/dubbo/common/utils/DefaultSerializeClassChecker;
      20: invokevirtual #16                 // Method org/apache/dubbo/common/utils/DefaultSerializeClassChecker.isCheckSerializable:()Z
      23: ifeq          61
      26: new           #17                 // class java/lang/IllegalStateException
      29: dup
      30: new           #18                 // class java/lang/StringBuilder
      33: dup
      34: invokespecial #19                 // Method java/lang/StringBuilder."<init>":()V
      37: ldc           #20                 // String Serialized class
      39: invokevirtual #21                 // Method java/lang/StringBuilder.append:(Ljava/lang/String;)Ljava/lang/StringBuilder;
      42: aload_1
      43: invokevirtual #6                  // Method java/lang/Class.getName:()Ljava/lang/String;
      46: invokevirtual #21                 // Method java/lang/StringBuilder.append:(Ljava/lang/String;)Ljava/lang/StringBuilder;
      49: ldc           #22                 // String  must implement java.io.Serializable
      51: invokevirtual #21                 // Method java/lang/StringBuilder.append:(Ljava/lang/String;)Ljava/lang/StringBuilder;
      54: invokevirtual #23                 // Method java/lang/StringBuilder.toString:()Ljava/lang/String;
      57: invokespecial #24                 // Method java/lang/IllegalStateException."<init>":(Ljava/lang/String;)V
      60: athrow
      61: return
}
