Compiled from "Hessian2ObjectOutput.java"
public class org.apache.dubbo.common.serialize.hessian2.Hessian2ObjectOutput implements org.apache.dubbo.common.serialize.ObjectOutput,org.apache.dubbo.common.serialize.Cleanable {
  private final com.alibaba.com.caucho.hessian.io.Hessian2Output mH2o;

  public org.apache.dubbo.common.serialize.hessian2.Hessian2ObjectOutput(java.io.OutputStream);
    Code:
       0: aload_0
       1: invokespecial #1                  // Method java/lang/Object."<init>":()V
       4: aload_0
       5: new           #2                  // class com/alibaba/com/caucho/hessian/io/Hessian2Output
       8: dup
       9: aload_1
      10: invokespecial #3                  // Method com/alibaba/com/caucho/hessian/io/Hessian2Output."<init>":(Ljava/io/OutputStream;)V
      13: putfield      #4                  // Field mH2o:Lcom/alibaba/com/caucho/hessian/io/Hessian2Output;
      16: invokestatic  #5                  // Method org/apache/dubbo/rpc/model/FrameworkModel.defaultModel:()Lorg/apache/dubbo/rpc/model/FrameworkModel;
      19: invokevirtual #6                  // Method org/apache/dubbo/rpc/model/FrameworkModel.getBeanFactory:()Lorg/apache/dubbo/common/beans/factory/ScopeBeanFactory;
      22: ldc           #7                  // class org/apache/dubbo/common/serialize/hessian2/Hessian2FactoryManager
      24: invokevirtual #8                  // Method org/apache/dubbo/common/beans/factory/ScopeBeanFactory.getOrRegisterBean:(Ljava/lang/Class;)Ljava/lang/Object;
      27: checkcast     #7                  // class org/apache/dubbo/common/serialize/hessian2/Hessian2FactoryManager
      30: astore_2
      31: aload_0
      32: getfield      #4                  // Field mH2o:Lcom/alibaba/com/caucho/hessian/io/Hessian2Output;
      35: aload_2
      36: invokestatic  #9                  // Method java/lang/Thread.currentThread:()Ljava/lang/Thread;
      39: invokevirtual #10                 // Method java/lang/Thread.getContextClassLoader:()Ljava/lang/ClassLoader;
      42: invokevirtual #11                 // Method org/apache/dubbo/common/serialize/hessian2/Hessian2FactoryManager.getSerializerFactory:(Ljava/lang/ClassLoader;)Lcom/alibaba/com/caucho/hessian/io/SerializerFactory;
      45: invokevirtual #12                 // Method com/alibaba/com/caucho/hessian/io/Hessian2Output.setSerializerFactory:(Lcom/alibaba/com/caucho/hessian/io/SerializerFactory;)V
      48: return

  public org.apache.dubbo.common.serialize.hessian2.Hessian2ObjectOutput(java.io.OutputStream, org.apache.dubbo.common.serialize.hessian2.Hessian2FactoryManager);
    Code:
       0: aload_0
       1: invokespecial #1                  // Method java/lang/Object."<init>":()V
       4: aload_0
       5: new           #2                  // class com/alibaba/com/caucho/hessian/io/Hessian2Output
       8: dup
       9: aload_1
      10: invokespecial #3                  // Method com/alibaba/com/caucho/hessian/io/Hessian2Output."<init>":(Ljava/io/OutputStream;)V
      13: putfield      #4                  // Field mH2o:Lcom/alibaba/com/caucho/hessian/io/Hessian2Output;
      16: aload_0
      17: getfield      #4                  // Field mH2o:Lcom/alibaba/com/caucho/hessian/io/Hessian2Output;
      20: aload_2
      21: invokestatic  #9                  // Method java/lang/Thread.currentThread:()Ljava/lang/Thread;
      24: invokevirtual #10                 // Method java/lang/Thread.getContextClassLoader:()Ljava/lang/ClassLoader;
      27: invokevirtual #11                 // Method org/apache/dubbo/common/serialize/hessian2/Hessian2FactoryManager.getSerializerFactory:(Ljava/lang/ClassLoader;)Lcom/alibaba/com/caucho/hessian/io/SerializerFactory;
      30: invokevirtual #12                 // Method com/alibaba/com/caucho/hessian/io/Hessian2Output.setSerializerFactory:(Lcom/alibaba/com/caucho/hessian/io/SerializerFactory;)V
      33: return

  public void writeBool(boolean) throws java.io.IOException;
    Code:
       0: aload_0
       1: getfield      #4                  // Field mH2o:Lcom/alibaba/com/caucho/hessian/io/Hessian2Output;
       4: iload_1
       5: invokevirtual #13                 // Method com/alibaba/com/caucho/hessian/io/Hessian2Output.writeBoolean:(Z)V
       8: return

  public void writeByte(byte) throws java.io.IOException;
    Code:
       0: aload_0
       1: getfield      #4                  // Field mH2o:Lcom/alibaba/com/caucho/hessian/io/Hessian2Output;
       4: iload_1
       5: invokevirtual #14                 // Method com/alibaba/com/caucho/hessian/io/Hessian2Output.writeInt:(I)V
       8: return

  public void writeShort(short) throws java.io.IOException;
    Code:
       0: aload_0
       1: getfield      #4                  // Field mH2o:Lcom/alibaba/com/caucho/hessian/io/Hessian2Output;
       4: iload_1
       5: invokevirtual #14                 // Method com/alibaba/com/caucho/hessian/io/Hessian2Output.writeInt:(I)V
       8: return

  public void writeInt(int) throws java.io.IOException;
    Code:
       0: aload_0
       1: getfield      #4                  // Field mH2o:Lcom/alibaba/com/caucho/hessian/io/Hessian2Output;
       4: iload_1
       5: invokevirtual #14                 // Method com/alibaba/com/caucho/hessian/io/Hessian2Output.writeInt:(I)V
       8: return

  public void writeLong(long) throws java.io.IOException;
    Code:
       0: aload_0
       1: getfield      #4                  // Field mH2o:Lcom/alibaba/com/caucho/hessian/io/Hessian2Output;
       4: lload_1
       5: invokevirtual #15                 // Method com/alibaba/com/caucho/hessian/io/Hessian2Output.writeLong:(J)V
       8: return

  public void writeFloat(float) throws java.io.IOException;
    Code:
       0: aload_0
       1: getfield      #4                  // Field mH2o:Lcom/alibaba/com/caucho/hessian/io/Hessian2Output;
       4: fload_1
       5: f2d
       6: invokevirtual #16                 // Method com/alibaba/com/caucho/hessian/io/Hessian2Output.writeDouble:(D)V
       9: return

  public void writeDouble(double) throws java.io.IOException;
    Code:
       0: aload_0
       1: getfield      #4                  // Field mH2o:Lcom/alibaba/com/caucho/hessian/io/Hessian2Output;
       4: dload_1
       5: invokevirtual #16                 // Method com/alibaba/com/caucho/hessian/io/Hessian2Output.writeDouble:(D)V
       8: return

  public void writeBytes(byte[]) throws java.io.IOException;
    Code:
       0: aload_0
       1: getfield      #4                  // Field mH2o:Lcom/alibaba/com/caucho/hessian/io/Hessian2Output;
       4: aload_1
       5: invokevirtual #17                 // Method com/alibaba/com/caucho/hessian/io/Hessian2Output.writeBytes:([B)V
       8: return

  public void writeBytes(byte[], int, int) throws java.io.IOException;
    Code:
       0: aload_0
       1: getfield      #4                  // Field mH2o:Lcom/alibaba/com/caucho/hessian/io/Hessian2Output;
       4: aload_1
       5: iload_2
       6: iload_3
       7: invokevirtual #18                 // Method com/alibaba/com/caucho/hessian/io/Hessian2Output.writeBytes:([BII)V
      10: return

  public void writeUTF(java.lang.String) throws java.io.IOException;
    Code:
       0: aload_0
       1: getfield      #4                  // Field mH2o:Lcom/alibaba/com/caucho/hessian/io/Hessian2Output;
       4: aload_1
       5: invokevirtual #19                 // Method com/alibaba/com/caucho/hessian/io/Hessian2Output.writeString:(Ljava/lang/String;)V
       8: return

  public void writeObject(java.lang.Object) throws java.io.IOException;
    Code:
       0: aload_0
       1: getfield      #4                  // Field mH2o:Lcom/alibaba/com/caucho/hessian/io/Hessian2Output;
       4: aload_1
       5: invokevirtual #20                 // Method com/alibaba/com/caucho/hessian/io/Hessian2Output.writeObject:(Ljava/lang/Object;)V
       8: return

  public void flushBuffer() throws java.io.IOException;
    Code:
       0: aload_0
       1: getfield      #4                  // Field mH2o:Lcom/alibaba/com/caucho/hessian/io/Hessian2Output;
       4: invokevirtual #21                 // Method com/alibaba/com/caucho/hessian/io/Hessian2Output.flushBuffer:()V
       7: return

  public java.io.OutputStream getOutputStream() throws java.io.IOException;
    Code:
       0: aload_0
       1: getfield      #4                  // Field mH2o:Lcom/alibaba/com/caucho/hessian/io/Hessian2Output;
       4: invokevirtual #22                 // Method com/alibaba/com/caucho/hessian/io/Hessian2Output.getBytesOutputStream:()Ljava/io/OutputStream;
       7: areturn

  public void cleanup();
    Code:
       0: aload_0
       1: getfield      #4                  // Field mH2o:Lcom/alibaba/com/caucho/hessian/io/Hessian2Output;
       4: ifnull        14
       7: aload_0
       8: getfield      #4                  // Field mH2o:Lcom/alibaba/com/caucho/hessian/io/Hessian2Output;
      11: invokevirtual #23                 // Method com/alibaba/com/caucho/hessian/io/Hessian2Output.reset:()V
      14: return
}
