Compiled from "Hessian2FactoryManager.java"
public class org.apache.dubbo.common.serialize.hessian2.Hessian2FactoryManager {
  java.lang.String WHITELIST;

  java.lang.String ALLOW;

  java.lang.String DENY;

  private volatile com.alibaba.com.caucho.hessian.io.SerializerFactory SYSTEM_SERIALIZER_FACTORY;

  private final java.util.Map<java.lang.ClassLoader, com.alibaba.com.caucho.hessian.io.SerializerFactory> CL_2_SERIALIZER_FACTORY;

  private final org.apache.dubbo.common.utils.SerializeSecurityManager serializeSecurityManager;

  private final org.apache.dubbo.common.utils.DefaultSerializeClassChecker defaultSerializeClassChecker;

  public org.apache.dubbo.common.serialize.hessian2.Hessian2FactoryManager(org.apache.dubbo.rpc.model.FrameworkModel);
    Code:
       0: aload_0
       1: invokespecial #1                  // Method java/lang/Object."<init>":()V
       4: aload_0
       5: ldc           #2                  // String dubbo.application.hessian2.whitelist
       7: putfield      #3                  // Field WHITELIST:Ljava/lang/String;
      10: aload_0
      11: ldc           #4                  // String dubbo.application.hessian2.allow
      13: putfield      #5                  // Field ALLOW:Ljava/lang/String;
      16: aload_0
      17: ldc           #6                  // String dubbo.application.hessian2.deny
      19: putfield      #7                  // Field DENY:Ljava/lang/String;
      22: aload_0
      23: new           #8                  // class java/util/concurrent/ConcurrentHashMap
      26: dup
      27: invokespecial #9                  // Method java/util/concurrent/ConcurrentHashMap."<init>":()V
      30: putfield      #10                 // Field CL_2_SERIALIZER_FACTORY:Ljava/util/Map;
      33: aload_0
      34: aload_1
      35: invokevirtual #11                 // Method org/apache/dubbo/rpc/model/FrameworkModel.getBeanFactory:()Lorg/apache/dubbo/common/beans/factory/ScopeBeanFactory;
      38: ldc           #12                 // class org/apache/dubbo/common/utils/SerializeSecurityManager
      40: invokevirtual #13                 // Method org/apache/dubbo/common/beans/factory/ScopeBeanFactory.getOrRegisterBean:(Ljava/lang/Class;)Ljava/lang/Object;
      43: checkcast     #12                 // class org/apache/dubbo/common/utils/SerializeSecurityManager
      46: putfield      #14                 // Field serializeSecurityManager:Lorg/apache/dubbo/common/utils/SerializeSecurityManager;
      49: aload_0
      50: aload_1
      51: invokevirtual #11                 // Method org/apache/dubbo/rpc/model/FrameworkModel.getBeanFactory:()Lorg/apache/dubbo/common/beans/factory/ScopeBeanFactory;
      54: ldc           #15                 // class org/apache/dubbo/common/utils/DefaultSerializeClassChecker
      56: invokevirtual #13                 // Method org/apache/dubbo/common/beans/factory/ScopeBeanFactory.getOrRegisterBean:(Ljava/lang/Class;)Ljava/lang/Object;
      59: checkcast     #15                 // class org/apache/dubbo/common/utils/DefaultSerializeClassChecker
      62: putfield      #16                 // Field defaultSerializeClassChecker:Lorg/apache/dubbo/common/utils/DefaultSerializeClassChecker;
      65: return

  public com.alibaba.com.caucho.hessian.io.SerializerFactory getSerializerFactory(java.lang.ClassLoader);
    Code:
       0: aload_1
       1: ifnonnull     45
       4: aload_0
       5: getfield      #17                 // Field SYSTEM_SERIALIZER_FACTORY:Lcom/alibaba/com/caucho/hessian/io/SerializerFactory;
       8: ifnonnull     40
      11: aload_0
      12: dup
      13: astore_2
      14: monitorenter
      15: aload_0
      16: getfield      #17                 // Field SYSTEM_SERIALIZER_FACTORY:Lcom/alibaba/com/caucho/hessian/io/SerializerFactory;
      19: ifnonnull     30
      22: aload_0
      23: aload_0
      24: invokespecial #18                 // Method createSerializerFactory:()Lcom/alibaba/com/caucho/hessian/io/SerializerFactory;
      27: putfield      #17                 // Field SYSTEM_SERIALIZER_FACTORY:Lcom/alibaba/com/caucho/hessian/io/SerializerFactory;
      30: aload_2
      31: monitorexit
      32: goto          40
      35: astore_3
      36: aload_2
      37: monitorexit
      38: aload_3
      39: athrow
      40: aload_0
      41: getfield      #17                 // Field SYSTEM_SERIALIZER_FACTORY:Lcom/alibaba/com/caucho/hessian/io/SerializerFactory;
      44: areturn
      45: aload_0
      46: getfield      #10                 // Field CL_2_SERIALIZER_FACTORY:Ljava/util/Map;
      49: aload_1
      50: invokeinterface #19,  2           // InterfaceMethod java/util/Map.containsKey:(Ljava/lang/Object;)Z
      55: ifne          108
      58: aload_0
      59: dup
      60: astore_2
      61: monitorenter
      62: aload_0
      63: getfield      #10                 // Field CL_2_SERIALIZER_FACTORY:Ljava/util/Map;
      66: aload_1
      67: invokeinterface #19,  2           // InterfaceMethod java/util/Map.containsKey:(Ljava/lang/Object;)Z
      72: ifne          96
      75: aload_0
      76: invokespecial #18                 // Method createSerializerFactory:()Lcom/alibaba/com/caucho/hessian/io/SerializerFactory;
      79: astore_3
      80: aload_0
      81: getfield      #10                 // Field CL_2_SERIALIZER_FACTORY:Ljava/util/Map;
      84: aload_1
      85: aload_3
      86: invokeinterface #20,  3           // InterfaceMethod java/util/Map.put:(Ljava/lang/Object;Ljava/lang/Object;)Ljava/lang/Object;
      91: pop
      92: aload_3
      93: aload_2
      94: monitorexit
      95: areturn
      96: aload_2
      97: monitorexit
      98: goto          108
     101: astore        4
     103: aload_2
     104: monitorexit
     105: aload         4
     107: athrow
     108: aload_0
     109: getfield      #10                 // Field CL_2_SERIALIZER_FACTORY:Ljava/util/Map;
     112: aload_1
     113: invokeinterface #21,  2           // InterfaceMethod java/util/Map.get:(Ljava/lang/Object;)Ljava/lang/Object;
     118: checkcast     #22                 // class com/alibaba/com/caucho/hessian/io/SerializerFactory
     121: areturn
    Exception table:
       from    to  target type
          15    32    35   any
          35    38    35   any
          62    95   101   any
          96    98   101   any
         101   105   101   any

  private com.alibaba.com.caucho.hessian.io.SerializerFactory createSerializerFactory();
    Code:
       0: aload_0
       1: getfield      #3                  // Field WHITELIST:Ljava/lang/String;
       4: invokestatic  #23                 // Method java/lang/System.getProperty:(Ljava/lang/String;)Ljava/lang/String;
       7: astore_1
       8: aload_1
       9: invokestatic  #24                 // Method org/apache/dubbo/common/utils/StringUtils.isNotEmpty:(Ljava/lang/String;)Z
      12: ifeq          20
      15: aload_0
      16: invokevirtual #25                 // Method createWhiteListSerializerFactory:()Lcom/alibaba/com/caucho/hessian/io/SerializerFactory;
      19: areturn
      20: aload_0
      21: invokespecial #26                 // Method createDefaultSerializerFactory:()Lcom/alibaba/com/caucho/hessian/io/SerializerFactory;
      24: areturn

  private com.alibaba.com.caucho.hessian.io.SerializerFactory createDefaultSerializerFactory();
    Code:
       0: new           #27                 // class org/apache/dubbo/common/serialize/hessian2/Hessian2SerializerFactory
       3: dup
       4: aload_0
       5: getfield      #16                 // Field defaultSerializeClassChecker:Lorg/apache/dubbo/common/utils/DefaultSerializeClassChecker;
       8: invokespecial #28                 // Method org/apache/dubbo/common/serialize/hessian2/Hessian2SerializerFactory."<init>":(Lorg/apache/dubbo/common/utils/DefaultSerializeClassChecker;)V
      11: astore_1
      12: aload_1
      13: ldc           #29                 // String dubbo.hessian.allowNonSerializable
      15: ldc           #30                 // String false
      17: invokestatic  #31                 // Method java/lang/System.getProperty:(Ljava/lang/String;Ljava/lang/String;)Ljava/lang/String;
      20: invokestatic  #32                 // Method java/lang/Boolean.parseBoolean:(Ljava/lang/String;)Z
      23: invokevirtual #33                 // Method org/apache/dubbo/common/serialize/hessian2/Hessian2SerializerFactory.setAllowNonSerializable:(Z)V
      26: aload_1
      27: invokevirtual #34                 // Method org/apache/dubbo/common/serialize/hessian2/Hessian2SerializerFactory.getClassFactory:()Lcom/alibaba/com/caucho/hessian/io/ClassFactory;
      30: ldc           #35                 // String org.apache.dubbo.*
      32: invokevirtual #36                 // Method com/alibaba/com/caucho/hessian/io/ClassFactory.allow:(Ljava/lang/String;)V
      35: aload_1
      36: areturn

  public com.alibaba.com.caucho.hessian.io.SerializerFactory createWhiteListSerializerFactory();
    Code:
       0: new           #27                 // class org/apache/dubbo/common/serialize/hessian2/Hessian2SerializerFactory
       3: dup
       4: aload_0
       5: getfield      #16                 // Field defaultSerializeClassChecker:Lorg/apache/dubbo/common/utils/DefaultSerializeClassChecker;
       8: invokespecial #28                 // Method org/apache/dubbo/common/serialize/hessian2/Hessian2SerializerFactory."<init>":(Lorg/apache/dubbo/common/utils/DefaultSerializeClassChecker;)V
      11: astore_1
      12: aload_0
      13: getfield      #3                  // Field WHITELIST:Ljava/lang/String;
      16: invokestatic  #23                 // Method java/lang/System.getProperty:(Ljava/lang/String;)Ljava/lang/String;
      19: astore_2
      20: ldc           #37                 // String true
      22: aload_2
      23: invokevirtual #38                 // Method java/lang/String.equals:(Ljava/lang/Object;)Z
      26: ifeq          119
      29: aload_1
      30: invokevirtual #39                 // Method com/alibaba/com/caucho/hessian/io/SerializerFactory.getClassFactory:()Lcom/alibaba/com/caucho/hessian/io/ClassFactory;
      33: iconst_1
      34: invokevirtual #40                 // Method com/alibaba/com/caucho/hessian/io/ClassFactory.setWhitelist:(Z)V
      37: aload_0
      38: getfield      #5                  // Field ALLOW:Ljava/lang/String;
      41: invokestatic  #23                 // Method java/lang/System.getProperty:(Ljava/lang/String;)Ljava/lang/String;
      44: astore_3
      45: aload_3
      46: invokestatic  #24                 // Method org/apache/dubbo/common/utils/StringUtils.isNotEmpty:(Ljava/lang/String;)Z
      49: ifeq          106
      52: aload_3
      53: ldc           #41                 // String ;
      55: invokevirtual #42                 // Method java/lang/String.split:(Ljava/lang/String;)[Ljava/lang/String;
      58: astore        4
      60: aload         4
      62: arraylength
      63: istore        5
      65: iconst_0
      66: istore        6
      68: iload         6
      70: iload         5
      72: if_icmpge     106
      75: aload         4
      77: iload         6
      79: aaload
      80: astore        7
      82: aload_1
      83: invokevirtual #39                 // Method com/alibaba/com/caucho/hessian/io/SerializerFactory.getClassFactory:()Lcom/alibaba/com/caucho/hessian/io/ClassFactory;
      86: aload         7
      88: invokevirtual #36                 // Method com/alibaba/com/caucho/hessian/io/ClassFactory.allow:(Ljava/lang/String;)V
      91: aload_0
      92: getfield      #14                 // Field serializeSecurityManager:Lorg/apache/dubbo/common/utils/SerializeSecurityManager;
      95: aload         7
      97: invokevirtual #43                 // Method org/apache/dubbo/common/utils/SerializeSecurityManager.addToAlwaysAllowed:(Ljava/lang/String;)V
     100: iinc          6, 1
     103: goto          68
     106: aload_0
     107: getfield      #14                 // Field serializeSecurityManager:Lorg/apache/dubbo/common/utils/SerializeSecurityManager;
     110: getstatic     #44                 // Field org/apache/dubbo/common/utils/SerializeCheckStatus.STRICT:Lorg/apache/dubbo/common/utils/SerializeCheckStatus;
     113: invokevirtual #45                 // Method org/apache/dubbo/common/utils/SerializeSecurityManager.setCheckStatus:(Lorg/apache/dubbo/common/utils/SerializeCheckStatus;)V
     116: goto          196
     119: aload_1
     120: invokevirtual #39                 // Method com/alibaba/com/caucho/hessian/io/SerializerFactory.getClassFactory:()Lcom/alibaba/com/caucho/hessian/io/ClassFactory;
     123: iconst_0
     124: invokevirtual #40                 // Method com/alibaba/com/caucho/hessian/io/ClassFactory.setWhitelist:(Z)V
     127: aload_0
     128: getfield      #7                  // Field DENY:Ljava/lang/String;
     131: invokestatic  #23                 // Method java/lang/System.getProperty:(Ljava/lang/String;)Ljava/lang/String;
     134: astore_3
     135: aload_3
     136: invokestatic  #24                 // Method org/apache/dubbo/common/utils/StringUtils.isNotEmpty:(Ljava/lang/String;)Z
     139: ifeq          196
     142: aload_3
     143: ldc           #41                 // String ;
     145: invokevirtual #42                 // Method java/lang/String.split:(Ljava/lang/String;)[Ljava/lang/String;
     148: astore        4
     150: aload         4
     152: arraylength
     153: istore        5
     155: iconst_0
     156: istore        6
     158: iload         6
     160: iload         5
     162: if_icmpge     196
     165: aload         4
     167: iload         6
     169: aaload
     170: astore        7
     172: aload_1
     173: invokevirtual #39                 // Method com/alibaba/com/caucho/hessian/io/SerializerFactory.getClassFactory:()Lcom/alibaba/com/caucho/hessian/io/ClassFactory;
     176: aload         7
     178: invokevirtual #46                 // Method com/alibaba/com/caucho/hessian/io/ClassFactory.deny:(Ljava/lang/String;)V
     181: aload_0
     182: getfield      #14                 // Field serializeSecurityManager:Lorg/apache/dubbo/common/utils/SerializeSecurityManager;
     185: aload         7
     187: invokevirtual #47                 // Method org/apache/dubbo/common/utils/SerializeSecurityManager.addToDisAllowed:(Ljava/lang/String;)V
     190: iinc          6, 1
     193: goto          158
     196: aload_1
     197: ldc           #29                 // String dubbo.hessian.allowNonSerializable
     199: ldc           #30                 // String false
     201: invokestatic  #31                 // Method java/lang/System.getProperty:(Ljava/lang/String;Ljava/lang/String;)Ljava/lang/String;
     204: invokestatic  #32                 // Method java/lang/Boolean.parseBoolean:(Ljava/lang/String;)Z
     207: invokevirtual #48                 // Method com/alibaba/com/caucho/hessian/io/SerializerFactory.setAllowNonSerializable:(Z)V
     210: aload_1
     211: invokevirtual #39                 // Method com/alibaba/com/caucho/hessian/io/SerializerFactory.getClassFactory:()Lcom/alibaba/com/caucho/hessian/io/ClassFactory;
     214: ldc           #35                 // String org.apache.dubbo.*
     216: invokevirtual #36                 // Method com/alibaba/com/caucho/hessian/io/ClassFactory.allow:(Ljava/lang/String;)V
     219: aload_1
     220: areturn

  public void onRemoveClassLoader(java.lang.ClassLoader);
    Code:
       0: aload_0
       1: getfield      #10                 // Field CL_2_SERIALIZER_FACTORY:Ljava/util/Map;
       4: aload_1
       5: invokeinterface #49,  2           // InterfaceMethod java/util/Map.remove:(Ljava/lang/Object;)Ljava/lang/Object;
      10: pop
      11: return
}
