Compiled from "Hessian2ObjectInput.java"
public class org.apache.dubbo.common.serialize.hessian2.Hessian2ObjectInput implements org.apache.dubbo.common.serialize.ObjectInput,org.apache.dubbo.common.serialize.Cleanable {
  private final com.alibaba.com.caucho.hessian.io.Hessian2Input mH2i;

  private final org.apache.dubbo.common.serialize.hessian2.Hessian2FactoryManager hessian2FactoryManager;

  public org.apache.dubbo.common.serialize.hessian2.Hessian2ObjectInput(java.io.InputStream);
    Code:
       0: aload_0
       1: invokespecial #1                  // Method java/lang/Object."<init>":()V
       4: aload_0
       5: new           #2                  // class com/alibaba/com/caucho/hessian/io/Hessian2Input
       8: dup
       9: aload_1
      10: invokespecial #3                  // Method com/alibaba/com/caucho/hessian/io/Hessian2Input."<init>":(Ljava/io/InputStream;)V
      13: putfield      #4                  // Field mH2i:Lcom/alibaba/com/caucho/hessian/io/Hessian2Input;
      16: aload_0
      17: invokestatic  #5                  // Method org/apache/dubbo/rpc/model/FrameworkModel.defaultModel:()Lorg/apache/dubbo/rpc/model/FrameworkModel;
      20: invokevirtual #6                  // Method org/apache/dubbo/rpc/model/FrameworkModel.getBeanFactory:()Lorg/apache/dubbo/common/beans/factory/ScopeBeanFactory;
      23: ldc           #7                  // class org/apache/dubbo/common/serialize/hessian2/Hessian2FactoryManager
      25: invokevirtual #8                  // Method org/apache/dubbo/common/beans/factory/ScopeBeanFactory.getOrRegisterBean:(Ljava/lang/Class;)Ljava/lang/Object;
      28: checkcast     #7                  // class org/apache/dubbo/common/serialize/hessian2/Hessian2FactoryManager
      31: putfield      #9                  // Field hessian2FactoryManager:Lorg/apache/dubbo/common/serialize/hessian2/Hessian2FactoryManager;
      34: aload_0
      35: getfield      #4                  // Field mH2i:Lcom/alibaba/com/caucho/hessian/io/Hessian2Input;
      38: aload_0
      39: getfield      #9                  // Field hessian2FactoryManager:Lorg/apache/dubbo/common/serialize/hessian2/Hessian2FactoryManager;
      42: invokestatic  #10                 // Method java/lang/Thread.currentThread:()Ljava/lang/Thread;
      45: invokevirtual #11                 // Method java/lang/Thread.getContextClassLoader:()Ljava/lang/ClassLoader;
      48: invokevirtual #12                 // Method org/apache/dubbo/common/serialize/hessian2/Hessian2FactoryManager.getSerializerFactory:(Ljava/lang/ClassLoader;)Lcom/alibaba/com/caucho/hessian/io/SerializerFactory;
      51: invokevirtual #13                 // Method com/alibaba/com/caucho/hessian/io/Hessian2Input.setSerializerFactory:(Lcom/alibaba/com/caucho/hessian/io/SerializerFactory;)V
      54: return

  public org.apache.dubbo.common.serialize.hessian2.Hessian2ObjectInput(java.io.InputStream, org.apache.dubbo.common.serialize.hessian2.Hessian2FactoryManager);
    Code:
       0: aload_0
       1: invokespecial #1                  // Method java/lang/Object."<init>":()V
       4: aload_0
       5: new           #2                  // class com/alibaba/com/caucho/hessian/io/Hessian2Input
       8: dup
       9: aload_1
      10: invokespecial #3                  // Method com/alibaba/com/caucho/hessian/io/Hessian2Input."<init>":(Ljava/io/InputStream;)V
      13: putfield      #4                  // Field mH2i:Lcom/alibaba/com/caucho/hessian/io/Hessian2Input;
      16: aload_0
      17: aload_2
      18: putfield      #9                  // Field hessian2FactoryManager:Lorg/apache/dubbo/common/serialize/hessian2/Hessian2FactoryManager;
      21: aload_0
      22: getfield      #4                  // Field mH2i:Lcom/alibaba/com/caucho/hessian/io/Hessian2Input;
      25: aload_2
      26: invokestatic  #10                 // Method java/lang/Thread.currentThread:()Ljava/lang/Thread;
      29: invokevirtual #11                 // Method java/lang/Thread.getContextClassLoader:()Ljava/lang/ClassLoader;
      32: invokevirtual #12                 // Method org/apache/dubbo/common/serialize/hessian2/Hessian2FactoryManager.getSerializerFactory:(Ljava/lang/ClassLoader;)Lcom/alibaba/com/caucho/hessian/io/SerializerFactory;
      35: invokevirtual #13                 // Method com/alibaba/com/caucho/hessian/io/Hessian2Input.setSerializerFactory:(Lcom/alibaba/com/caucho/hessian/io/SerializerFactory;)V
      38: return

  public boolean readBool() throws java.io.IOException;
    Code:
       0: aload_0
       1: getfield      #4                  // Field mH2i:Lcom/alibaba/com/caucho/hessian/io/Hessian2Input;
       4: invokevirtual #14                 // Method com/alibaba/com/caucho/hessian/io/Hessian2Input.readBoolean:()Z
       7: ireturn

  public byte readByte() throws java.io.IOException;
    Code:
       0: aload_0
       1: getfield      #4                  // Field mH2i:Lcom/alibaba/com/caucho/hessian/io/Hessian2Input;
       4: invokevirtual #15                 // Method com/alibaba/com/caucho/hessian/io/Hessian2Input.readInt:()I
       7: i2b
       8: ireturn

  public short readShort() throws java.io.IOException;
    Code:
       0: aload_0
       1: getfield      #4                  // Field mH2i:Lcom/alibaba/com/caucho/hessian/io/Hessian2Input;
       4: invokevirtual #15                 // Method com/alibaba/com/caucho/hessian/io/Hessian2Input.readInt:()I
       7: i2s
       8: ireturn

  public int readInt() throws java.io.IOException;
    Code:
       0: aload_0
       1: getfield      #4                  // Field mH2i:Lcom/alibaba/com/caucho/hessian/io/Hessian2Input;
       4: invokevirtual #15                 // Method com/alibaba/com/caucho/hessian/io/Hessian2Input.readInt:()I
       7: ireturn

  public long readLong() throws java.io.IOException;
    Code:
       0: aload_0
       1: getfield      #4                  // Field mH2i:Lcom/alibaba/com/caucho/hessian/io/Hessian2Input;
       4: invokevirtual #16                 // Method com/alibaba/com/caucho/hessian/io/Hessian2Input.readLong:()J
       7: lreturn

  public float readFloat() throws java.io.IOException;
    Code:
       0: aload_0
       1: getfield      #4                  // Field mH2i:Lcom/alibaba/com/caucho/hessian/io/Hessian2Input;
       4: invokevirtual #17                 // Method com/alibaba/com/caucho/hessian/io/Hessian2Input.readDouble:()D
       7: d2f
       8: freturn

  public double readDouble() throws java.io.IOException;
    Code:
       0: aload_0
       1: getfield      #4                  // Field mH2i:Lcom/alibaba/com/caucho/hessian/io/Hessian2Input;
       4: invokevirtual #17                 // Method com/alibaba/com/caucho/hessian/io/Hessian2Input.readDouble:()D
       7: dreturn

  public byte[] readBytes() throws java.io.IOException;
    Code:
       0: aload_0
       1: getfield      #4                  // Field mH2i:Lcom/alibaba/com/caucho/hessian/io/Hessian2Input;
       4: invokevirtual #18                 // Method com/alibaba/com/caucho/hessian/io/Hessian2Input.readBytes:()[B
       7: areturn

  public java.lang.String readUTF() throws java.io.IOException;
    Code:
       0: aload_0
       1: getfield      #4                  // Field mH2i:Lcom/alibaba/com/caucho/hessian/io/Hessian2Input;
       4: invokevirtual #19                 // Method com/alibaba/com/caucho/hessian/io/Hessian2Input.readString:()Ljava/lang/String;
       7: areturn

  public java.lang.Object readObject() throws java.io.IOException;
    Code:
       0: aload_0
       1: getfield      #4                  // Field mH2i:Lcom/alibaba/com/caucho/hessian/io/Hessian2Input;
       4: invokevirtual #20                 // Method com/alibaba/com/caucho/hessian/io/Hessian2Input.getSerializerFactory:()Lcom/alibaba/com/caucho/hessian/io/SerializerFactory;
       7: invokevirtual #21                 // Method com/alibaba/com/caucho/hessian/io/SerializerFactory.getClassLoader:()Ljava/lang/ClassLoader;
      10: invokestatic  #10                 // Method java/lang/Thread.currentThread:()Ljava/lang/Thread;
      13: invokevirtual #11                 // Method java/lang/Thread.getContextClassLoader:()Ljava/lang/ClassLoader;
      16: invokevirtual #22                 // Method java/lang/Object.equals:(Ljava/lang/Object;)Z
      19: ifne          42
      22: aload_0
      23: getfield      #4                  // Field mH2i:Lcom/alibaba/com/caucho/hessian/io/Hessian2Input;
      26: aload_0
      27: getfield      #9                  // Field hessian2FactoryManager:Lorg/apache/dubbo/common/serialize/hessian2/Hessian2FactoryManager;
      30: invokestatic  #10                 // Method java/lang/Thread.currentThread:()Ljava/lang/Thread;
      33: invokevirtual #11                 // Method java/lang/Thread.getContextClassLoader:()Ljava/lang/ClassLoader;
      36: invokevirtual #12                 // Method org/apache/dubbo/common/serialize/hessian2/Hessian2FactoryManager.getSerializerFactory:(Ljava/lang/ClassLoader;)Lcom/alibaba/com/caucho/hessian/io/SerializerFactory;
      39: invokevirtual #13                 // Method com/alibaba/com/caucho/hessian/io/Hessian2Input.setSerializerFactory:(Lcom/alibaba/com/caucho/hessian/io/SerializerFactory;)V
      42: aload_0
      43: getfield      #4                  // Field mH2i:Lcom/alibaba/com/caucho/hessian/io/Hessian2Input;
      46: invokevirtual #23                 // Method com/alibaba/com/caucho/hessian/io/Hessian2Input.readObject:()Ljava/lang/Object;
      49: areturn

  public <T> T readObject(java.lang.Class<T>) throws java.io.IOException, java.lang.ClassNotFoundException;
    Code:
       0: aload_0
       1: getfield      #4                  // Field mH2i:Lcom/alibaba/com/caucho/hessian/io/Hessian2Input;
       4: invokevirtual #20                 // Method com/alibaba/com/caucho/hessian/io/Hessian2Input.getSerializerFactory:()Lcom/alibaba/com/caucho/hessian/io/SerializerFactory;
       7: invokevirtual #21                 // Method com/alibaba/com/caucho/hessian/io/SerializerFactory.getClassLoader:()Ljava/lang/ClassLoader;
      10: invokestatic  #10                 // Method java/lang/Thread.currentThread:()Ljava/lang/Thread;
      13: invokevirtual #11                 // Method java/lang/Thread.getContextClassLoader:()Ljava/lang/ClassLoader;
      16: invokevirtual #22                 // Method java/lang/Object.equals:(Ljava/lang/Object;)Z
      19: ifne          42
      22: aload_0
      23: getfield      #4                  // Field mH2i:Lcom/alibaba/com/caucho/hessian/io/Hessian2Input;
      26: aload_0
      27: getfield      #9                  // Field hessian2FactoryManager:Lorg/apache/dubbo/common/serialize/hessian2/Hessian2FactoryManager;
      30: invokestatic  #10                 // Method java/lang/Thread.currentThread:()Ljava/lang/Thread;
      33: invokevirtual #11                 // Method java/lang/Thread.getContextClassLoader:()Ljava/lang/ClassLoader;
      36: invokevirtual #12                 // Method org/apache/dubbo/common/serialize/hessian2/Hessian2FactoryManager.getSerializerFactory:(Ljava/lang/ClassLoader;)Lcom/alibaba/com/caucho/hessian/io/SerializerFactory;
      39: invokevirtual #13                 // Method com/alibaba/com/caucho/hessian/io/Hessian2Input.setSerializerFactory:(Lcom/alibaba/com/caucho/hessian/io/SerializerFactory;)V
      42: aload_0
      43: getfield      #4                  // Field mH2i:Lcom/alibaba/com/caucho/hessian/io/Hessian2Input;
      46: aload_1
      47: invokevirtual #24                 // Method com/alibaba/com/caucho/hessian/io/Hessian2Input.readObject:(Ljava/lang/Class;)Ljava/lang/Object;
      50: areturn

  public <T> T readObject(java.lang.Class<T>, java.lang.reflect.Type) throws java.io.IOException, java.lang.ClassNotFoundException;
    Code:
       0: aload_0
       1: getfield      #4                  // Field mH2i:Lcom/alibaba/com/caucho/hessian/io/Hessian2Input;
       4: invokevirtual #20                 // Method com/alibaba/com/caucho/hessian/io/Hessian2Input.getSerializerFactory:()Lcom/alibaba/com/caucho/hessian/io/SerializerFactory;
       7: invokevirtual #21                 // Method com/alibaba/com/caucho/hessian/io/SerializerFactory.getClassLoader:()Ljava/lang/ClassLoader;
      10: invokestatic  #10                 // Method java/lang/Thread.currentThread:()Ljava/lang/Thread;
      13: invokevirtual #11                 // Method java/lang/Thread.getContextClassLoader:()Ljava/lang/ClassLoader;
      16: invokevirtual #22                 // Method java/lang/Object.equals:(Ljava/lang/Object;)Z
      19: ifne          42
      22: aload_0
      23: getfield      #4                  // Field mH2i:Lcom/alibaba/com/caucho/hessian/io/Hessian2Input;
      26: aload_0
      27: getfield      #9                  // Field hessian2FactoryManager:Lorg/apache/dubbo/common/serialize/hessian2/Hessian2FactoryManager;
      30: invokestatic  #10                 // Method java/lang/Thread.currentThread:()Ljava/lang/Thread;
      33: invokevirtual #11                 // Method java/lang/Thread.getContextClassLoader:()Ljava/lang/ClassLoader;
      36: invokevirtual #12                 // Method org/apache/dubbo/common/serialize/hessian2/Hessian2FactoryManager.getSerializerFactory:(Ljava/lang/ClassLoader;)Lcom/alibaba/com/caucho/hessian/io/SerializerFactory;
      39: invokevirtual #13                 // Method com/alibaba/com/caucho/hessian/io/Hessian2Input.setSerializerFactory:(Lcom/alibaba/com/caucho/hessian/io/SerializerFactory;)V
      42: aload_0
      43: aload_1
      44: invokevirtual #25                 // Method readObject:(Ljava/lang/Class;)Ljava/lang/Object;
      47: areturn

  public java.io.InputStream readInputStream() throws java.io.IOException;
    Code:
       0: aload_0
       1: getfield      #4                  // Field mH2i:Lcom/alibaba/com/caucho/hessian/io/Hessian2Input;
       4: invokevirtual #26                 // Method com/alibaba/com/caucho/hessian/io/Hessian2Input.readInputStream:()Ljava/io/InputStream;
       7: areturn

  public void cleanup();
    Code:
       0: aload_0
       1: getfield      #4                  // Field mH2i:Lcom/alibaba/com/caucho/hessian/io/Hessian2Input;
       4: ifnull        14
       7: aload_0
       8: getfield      #4                  // Field mH2i:Lcom/alibaba/com/caucho/hessian/io/Hessian2Input;
      11: invokevirtual #27                 // Method com/alibaba/com/caucho/hessian/io/Hessian2Input.reset:()V
      14: return
}
