Compiled from "Hessian2ClassLoaderListener.java"
public class org.apache.dubbo.common.serialize.hessian2.Hessian2ClassLoaderListener implements org.apache.dubbo.rpc.model.ScopeClassLoaderListener<org.apache.dubbo.rpc.model.FrameworkModel> {
  public org.apache.dubbo.common.serialize.hessian2.Hessian2ClassLoaderListener();
    Code:
       0: aload_0
       1: invokespecial #1                  // Method java/lang/Object."<init>":()V
       4: return

  public void onAddClassLoader(org.apache.dubbo.rpc.model.FrameworkModel, java.lang.ClassLoader);
    Code:
       0: return

  public void onRemoveClassLoader(org.apache.dubbo.rpc.model.FrameworkModel, java.lang.ClassLoader);
    Code:
       0: aload_1
       1: invokevirtual #2                  // Method org/apache/dubbo/rpc/model/FrameworkModel.getBeanFactory:()Lorg/apache/dubbo/common/beans/factory/ScopeBeanFactory;
       4: ldc           #3                  // class org/apache/dubbo/common/serialize/hessian2/Hessian2FactoryManager
       6: invokevirtual #4                  // Method org/apache/dubbo/common/beans/factory/ScopeBeanFactory.getBean:(Ljava/lang/Class;)Ljava/lang/Object;
       9: checkcast     #3                  // class org/apache/dubbo/common/serialize/hessian2/Hessian2FactoryManager
      12: astore_3
      13: aload_3
      14: aload_2
      15: invokevirtual #5                  // Method org/apache/dubbo/common/serialize/hessian2/Hessian2FactoryManager.onRemoveClassLoader:(Ljava/lang/ClassLoader;)V
      18: return

  public void onRemoveClassLoader(org.apache.dubbo.rpc.model.ScopeModel, java.lang.ClassLoader);
    Code:
       0: aload_0
       1: aload_1
       2: checkcast     #6                  // class org/apache/dubbo/rpc/model/FrameworkModel
       5: aload_2
       6: invokevirtual #7                  // Method onRemoveClassLoader:(Lorg/apache/dubbo/rpc/model/FrameworkModel;Ljava/lang/ClassLoader;)V
       9: return

  public void onAddClassLoader(org.apache.dubbo.rpc.model.ScopeModel, java.lang.ClassLoader);
    Code:
       0: aload_0
       1: aload_1
       2: checkcast     #6                  // class org/apache/dubbo/rpc/model/FrameworkModel
       5: aload_2
       6: invokevirtual #8                  // Method onAddClassLoader:(Lorg/apache/dubbo/rpc/model/FrameworkModel;Ljava/lang/ClassLoader;)V
       9: return
}
