Compiled from "FullServiceDefinition.java"
public class org.apache.dubbo.metadata.definition.model.FullServiceDefinition extends org.apache.dubbo.metadata.definition.model.ServiceDefinition {
  private java.util.Map<java.lang.String, java.lang.String> parameters;

  public org.apache.dubbo.metadata.definition.model.FullServiceDefinition();
    Code:
       0: aload_0
       1: invokespecial #1                  // Method org/apache/dubbo/metadata/definition/model/ServiceDefinition."<init>":()V
       4: return

  public java.util.Map<java.lang.String, java.lang.String> getParameters();
    Code:
       0: aload_0
       1: getfield      #2                  // Field parameters:Ljava/util/Map;
       4: areturn

  public void setParameters(java.util.Map<java.lang.String, java.lang.String>);
    Code:
       0: aload_0
       1: aload_1
       2: putfield      #2                  // Field parameters:Ljava/util/Map;
       5: return

  public java.lang.String toString();
    Code:
       0: new           #3                  // class java/lang/StringBuilder
       3: dup
       4: invokespecial #4                  // Method java/lang/StringBuilder."<init>":()V
       7: ldc           #5                  // String FullServiceDefinition{parameters=
       9: invokevirtual #6                  // Method java/lang/StringBuilder.append:(Ljava/lang/String;)Ljava/lang/StringBuilder;
      12: aload_0
      13: getfield      #2                  // Field parameters:Ljava/util/Map;
      16: invokevirtual #7                  // Method java/lang/StringBuilder.append:(Ljava/lang/Object;)Ljava/lang/StringBuilder;
      19: ldc           #8                  // String }
      21: invokevirtual #6                  // Method java/lang/StringBuilder.append:(Ljava/lang/String;)Ljava/lang/StringBuilder;
      24: aload_0
      25: invokespecial #9                  // Method org/apache/dubbo/metadata/definition/model/ServiceDefinition.toString:()Ljava/lang/String;
      28: invokevirtual #6                  // Method java/lang/StringBuilder.append:(Ljava/lang/String;)Ljava/lang/StringBuilder;
      31: invokevirtual #10                 // Method java/lang/StringBuilder.toString:()Ljava/lang/String;
      34: areturn
}
