Compiled from "MethodDefinition.java"
public class org.apache.dubbo.metadata.definition.model.MethodDefinition implements java.io.Serializable {
  private java.lang.String name;

  private java.lang.String[] parameterTypes;

  private java.lang.String returnType;

  private java.util.List<org.apache.dubbo.metadata.definition.model.TypeDefinition> parameters;

  private java.util.List<java.lang.String> annotations;

  public org.apache.dubbo.metadata.definition.model.MethodDefinition();
    Code:
       0: aload_0
       1: invokespecial #1                  // Method java/lang/Object."<init>":()V
       4: return

  public java.lang.String getName();
    Code:
       0: aload_0
       1: getfield      #2                  // Field name:Ljava/lang/String;
       4: areturn

  public java.util.List<org.apache.dubbo.metadata.definition.model.TypeDefinition> getParameters();
    Code:
       0: aload_0
       1: getfield      #3                  // Field parameters:Ljava/util/List;
       4: ifnonnull     18
       7: aload_0
       8: new           #4                  // class java/util/ArrayList
      11: dup
      12: invokespecial #5                  // Method java/util/ArrayList."<init>":()V
      15: putfield      #3                  // Field parameters:Ljava/util/List;
      18: aload_0
      19: getfield      #3                  // Field parameters:Ljava/util/List;
      22: areturn

  public java.lang.String[] getParameterTypes();
    Code:
       0: aload_0
       1: getfield      #6                  // Field parameterTypes:[Ljava/lang/String;
       4: areturn

  public java.lang.String getReturnType();
    Code:
       0: aload_0
       1: getfield      #7                  // Field returnType:Ljava/lang/String;
       4: areturn

  public void setName(java.lang.String);
    Code:
       0: aload_0
       1: aload_1
       2: putfield      #2                  // Field name:Ljava/lang/String;
       5: return

  public void setParameters(java.util.List<org.apache.dubbo.metadata.definition.model.TypeDefinition>);
    Code:
       0: aload_0
       1: aload_1
       2: putfield      #3                  // Field parameters:Ljava/util/List;
       5: return

  public void setParameterTypes(java.lang.String[]);
    Code:
       0: aload_0
       1: aload_1
       2: invokestatic  #8                  // Method org/apache/dubbo/metadata/definition/model/TypeDefinition.formatTypes:([Ljava/lang/String;)[Ljava/lang/String;
       5: putfield      #6                  // Field parameterTypes:[Ljava/lang/String;
       8: return

  public void setReturnType(java.lang.String);
    Code:
       0: aload_0
       1: aload_1
       2: invokestatic  #9                  // Method org/apache/dubbo/metadata/definition/model/TypeDefinition.formatType:(Ljava/lang/String;)Ljava/lang/String;
       5: putfield      #7                  // Field returnType:Ljava/lang/String;
       8: return

  public java.util.List<java.lang.String> getAnnotations();
    Code:
       0: aload_0
       1: getfield      #10                 // Field annotations:Ljava/util/List;
       4: ifnonnull     14
       7: aload_0
       8: invokestatic  #11                 // Method java/util/Collections.emptyList:()Ljava/util/List;
      11: putfield      #10                 // Field annotations:Ljava/util/List;
      14: aload_0
      15: getfield      #10                 // Field annotations:Ljava/util/List;
      18: areturn

  public void setAnnotations(java.util.List<java.lang.String>);
    Code:
       0: aload_0
       1: aload_1
       2: putfield      #10                 // Field annotations:Ljava/util/List;
       5: return

  public java.lang.String toString();
    Code:
       0: new           #12                 // class java/lang/StringBuilder
       3: dup
       4: invokespecial #13                 // Method java/lang/StringBuilder."<init>":()V
       7: ldc           #14                 // String MethodDefinition [name=
       9: invokevirtual #15                 // Method java/lang/StringBuilder.append:(Ljava/lang/String;)Ljava/lang/StringBuilder;
      12: aload_0
      13: getfield      #2                  // Field name:Ljava/lang/String;
      16: invokevirtual #15                 // Method java/lang/StringBuilder.append:(Ljava/lang/String;)Ljava/lang/StringBuilder;
      19: ldc           #16                 // String , parameterTypes=
      21: invokevirtual #15                 // Method java/lang/StringBuilder.append:(Ljava/lang/String;)Ljava/lang/StringBuilder;
      24: aload_0
      25: getfield      #6                  // Field parameterTypes:[Ljava/lang/String;
      28: invokestatic  #17                 // Method java/util/Arrays.toString:([Ljava/lang/Object;)Ljava/lang/String;
      31: invokevirtual #15                 // Method java/lang/StringBuilder.append:(Ljava/lang/String;)Ljava/lang/StringBuilder;
      34: ldc           #18                 // String , returnType=
      36: invokevirtual #15                 // Method java/lang/StringBuilder.append:(Ljava/lang/String;)Ljava/lang/StringBuilder;
      39: aload_0
      40: getfield      #7                  // Field returnType:Ljava/lang/String;
      43: invokevirtual #15                 // Method java/lang/StringBuilder.append:(Ljava/lang/String;)Ljava/lang/StringBuilder;
      46: ldc           #19                 // String ]
      48: invokevirtual #15                 // Method java/lang/StringBuilder.append:(Ljava/lang/String;)Ljava/lang/StringBuilder;
      51: invokevirtual #20                 // Method java/lang/StringBuilder.toString:()Ljava/lang/String;
      54: areturn

  public boolean equals(java.lang.Object);
    Code:
       0: aload_0
       1: aload_1
       2: if_acmpne     7
       5: iconst_1
       6: ireturn
       7: aload_1
       8: instanceof    #21                 // class org/apache/dubbo/metadata/definition/model/MethodDefinition
      11: ifne          16
      14: iconst_0
      15: ireturn
      16: aload_1
      17: checkcast     #21                 // class org/apache/dubbo/metadata/definition/model/MethodDefinition
      20: astore_2
      21: aload_0
      22: invokevirtual #22                 // Method getName:()Ljava/lang/String;
      25: aload_2
      26: invokevirtual #22                 // Method getName:()Ljava/lang/String;
      29: invokestatic  #23                 // Method java/util/Objects.equals:(Ljava/lang/Object;Ljava/lang/Object;)Z
      32: ifeq          67
      35: aload_0
      36: invokevirtual #24                 // Method getParameterTypes:()[Ljava/lang/String;
      39: aload_2
      40: invokevirtual #24                 // Method getParameterTypes:()[Ljava/lang/String;
      43: invokestatic  #25                 // Method java/util/Arrays.equals:([Ljava/lang/Object;[Ljava/lang/Object;)Z
      46: ifeq          67
      49: aload_0
      50: invokevirtual #26                 // Method getReturnType:()Ljava/lang/String;
      53: aload_2
      54: invokevirtual #26                 // Method getReturnType:()Ljava/lang/String;
      57: invokestatic  #23                 // Method java/util/Objects.equals:(Ljava/lang/Object;Ljava/lang/Object;)Z
      60: ifeq          67
      63: iconst_1
      64: goto          68
      67: iconst_0
      68: ireturn

  public int hashCode();
    Code:
       0: iconst_3
       1: anewarray     #27                 // class java/lang/Object
       4: dup
       5: iconst_0
       6: aload_0
       7: invokevirtual #22                 // Method getName:()Ljava/lang/String;
      10: aastore
      11: dup
      12: iconst_1
      13: aload_0
      14: invokevirtual #26                 // Method getReturnType:()Ljava/lang/String;
      17: aastore
      18: dup
      19: iconst_2
      20: aload_0
      21: invokevirtual #24                 // Method getParameterTypes:()[Ljava/lang/String;
      24: invokestatic  #17                 // Method java/util/Arrays.toString:([Ljava/lang/Object;)Ljava/lang/String;
      27: aastore
      28: invokestatic  #28                 // Method java/util/Objects.hash:([Ljava/lang/Object;)I
      31: ireturn
}
