Compiled from "ServiceDefinition.java"
public class org.apache.dubbo.metadata.definition.model.ServiceDefinition implements java.io.Serializable {
  private java.lang.String canonicalName;

  private java.lang.String codeSource;

  private java.util.List<org.apache.dubbo.metadata.definition.model.MethodDefinition> methods;

  private java.util.List<org.apache.dubbo.metadata.definition.model.TypeDefinition> types;

  private java.util.List<java.lang.String> annotations;

  public org.apache.dubbo.metadata.definition.model.ServiceDefinition();
    Code:
       0: aload_0
       1: invokespecial #1                  // Method java/lang/Object."<init>":()V
       4: return

  public java.lang.String getCanonicalName();
    Code:
       0: aload_0
       1: getfield      #2                  // Field canonicalName:Ljava/lang/String;
       4: areturn

  public java.lang.String getCodeSource();
    Code:
       0: aload_0
       1: getfield      #3                  // Field codeSource:Ljava/lang/String;
       4: areturn

  public java.util.List<org.apache.dubbo.metadata.definition.model.MethodDefinition> getMethods();
    Code:
       0: aload_0
       1: getfield      #4                  // Field methods:Ljava/util/List;
       4: ifnonnull     18
       7: aload_0
       8: new           #5                  // class java/util/ArrayList
      11: dup
      12: invokespecial #6                  // Method java/util/ArrayList."<init>":()V
      15: putfield      #4                  // Field methods:Ljava/util/List;
      18: aload_0
      19: getfield      #4                  // Field methods:Ljava/util/List;
      22: areturn

  public java.util.List<org.apache.dubbo.metadata.definition.model.TypeDefinition> getTypes();
    Code:
       0: aload_0
       1: getfield      #7                  // Field types:Ljava/util/List;
       4: ifnonnull     18
       7: aload_0
       8: new           #5                  // class java/util/ArrayList
      11: dup
      12: invokespecial #6                  // Method java/util/ArrayList."<init>":()V
      15: putfield      #7                  // Field types:Ljava/util/List;
      18: aload_0
      19: getfield      #7                  // Field types:Ljava/util/List;
      22: areturn

  public java.lang.String getUniqueId();
    Code:
       0: new           #8                  // class java/lang/StringBuilder
       3: dup
       4: invokespecial #9                  // Method java/lang/StringBuilder."<init>":()V
       7: aload_0
       8: getfield      #2                  // Field canonicalName:Ljava/lang/String;
      11: invokevirtual #10                 // Method java/lang/StringBuilder.append:(Ljava/lang/String;)Ljava/lang/StringBuilder;
      14: ldc           #11                 // String @
      16: invokevirtual #10                 // Method java/lang/StringBuilder.append:(Ljava/lang/String;)Ljava/lang/StringBuilder;
      19: aload_0
      20: getfield      #3                  // Field codeSource:Ljava/lang/String;
      23: invokevirtual #10                 // Method java/lang/StringBuilder.append:(Ljava/lang/String;)Ljava/lang/StringBuilder;
      26: invokevirtual #12                 // Method java/lang/StringBuilder.toString:()Ljava/lang/String;
      29: areturn

  public void setCanonicalName(java.lang.String);
    Code:
       0: aload_0
       1: aload_1
       2: putfield      #2                  // Field canonicalName:Ljava/lang/String;
       5: return

  public void setCodeSource(java.lang.String);
    Code:
       0: aload_0
       1: aload_1
       2: putfield      #3                  // Field codeSource:Ljava/lang/String;
       5: return

  public void setMethods(java.util.List<org.apache.dubbo.metadata.definition.model.MethodDefinition>);
    Code:
       0: aload_0
       1: aload_1
       2: putfield      #4                  // Field methods:Ljava/util/List;
       5: return

  public void setTypes(java.util.List<org.apache.dubbo.metadata.definition.model.TypeDefinition>);
    Code:
       0: aload_0
       1: aload_1
       2: putfield      #7                  // Field types:Ljava/util/List;
       5: return

  public java.util.List<java.lang.String> getAnnotations();
    Code:
       0: aload_0
       1: getfield      #13                 // Field annotations:Ljava/util/List;
       4: ifnonnull     14
       7: aload_0
       8: invokestatic  #14                 // Method java/util/Collections.emptyList:()Ljava/util/List;
      11: putfield      #13                 // Field annotations:Ljava/util/List;
      14: aload_0
      15: getfield      #13                 // Field annotations:Ljava/util/List;
      18: areturn

  public void setAnnotations(java.util.List<java.lang.String>);
    Code:
       0: aload_0
       1: aload_1
       2: putfield      #13                 // Field annotations:Ljava/util/List;
       5: return

  public java.lang.String toString();
    Code:
       0: new           #8                  // class java/lang/StringBuilder
       3: dup
       4: invokespecial #9                  // Method java/lang/StringBuilder."<init>":()V
       7: ldc           #15                 // String ServiceDefinition [canonicalName=
       9: invokevirtual #10                 // Method java/lang/StringBuilder.append:(Ljava/lang/String;)Ljava/lang/StringBuilder;
      12: aload_0
      13: getfield      #2                  // Field canonicalName:Ljava/lang/String;
      16: invokevirtual #10                 // Method java/lang/StringBuilder.append:(Ljava/lang/String;)Ljava/lang/StringBuilder;
      19: ldc           #16                 // String , codeSource=
      21: invokevirtual #10                 // Method java/lang/StringBuilder.append:(Ljava/lang/String;)Ljava/lang/StringBuilder;
      24: aload_0
      25: getfield      #3                  // Field codeSource:Ljava/lang/String;
      28: invokevirtual #10                 // Method java/lang/StringBuilder.append:(Ljava/lang/String;)Ljava/lang/StringBuilder;
      31: ldc           #17                 // String , methods=
      33: invokevirtual #10                 // Method java/lang/StringBuilder.append:(Ljava/lang/String;)Ljava/lang/StringBuilder;
      36: aload_0
      37: getfield      #4                  // Field methods:Ljava/util/List;
      40: invokevirtual #18                 // Method java/lang/StringBuilder.append:(Ljava/lang/Object;)Ljava/lang/StringBuilder;
      43: ldc           #19                 // String ]
      45: invokevirtual #10                 // Method java/lang/StringBuilder.append:(Ljava/lang/String;)Ljava/lang/StringBuilder;
      48: invokevirtual #12                 // Method java/lang/StringBuilder.toString:()Ljava/lang/String;
      51: areturn

  public boolean equals(java.lang.Object);
    Code:
       0: aload_0
       1: aload_1
       2: if_acmpne     7
       5: iconst_1
       6: ireturn
       7: aload_1
       8: instanceof    #20                 // class org/apache/dubbo/metadata/definition/model/ServiceDefinition
      11: ifne          16
      14: iconst_0
      15: ireturn
      16: aload_1
      17: checkcast     #20                 // class org/apache/dubbo/metadata/definition/model/ServiceDefinition
      20: astore_2
      21: aload_0
      22: invokevirtual #21                 // Method getCanonicalName:()Ljava/lang/String;
      25: aload_2
      26: invokevirtual #21                 // Method getCanonicalName:()Ljava/lang/String;
      29: invokestatic  #22                 // Method java/util/Objects.equals:(Ljava/lang/Object;Ljava/lang/Object;)Z
      32: ifeq          81
      35: aload_0
      36: invokevirtual #23                 // Method getCodeSource:()Ljava/lang/String;
      39: aload_2
      40: invokevirtual #23                 // Method getCodeSource:()Ljava/lang/String;
      43: invokestatic  #22                 // Method java/util/Objects.equals:(Ljava/lang/Object;Ljava/lang/Object;)Z
      46: ifeq          81
      49: aload_0
      50: invokevirtual #24                 // Method getMethods:()Ljava/util/List;
      53: aload_2
      54: invokevirtual #24                 // Method getMethods:()Ljava/util/List;
      57: invokestatic  #22                 // Method java/util/Objects.equals:(Ljava/lang/Object;Ljava/lang/Object;)Z
      60: ifeq          81
      63: aload_0
      64: invokevirtual #25                 // Method getTypes:()Ljava/util/List;
      67: aload_2
      68: invokevirtual #25                 // Method getTypes:()Ljava/util/List;
      71: invokestatic  #22                 // Method java/util/Objects.equals:(Ljava/lang/Object;Ljava/lang/Object;)Z
      74: ifeq          81
      77: iconst_1
      78: goto          82
      81: iconst_0
      82: ireturn

  public int hashCode();
    Code:
       0: iconst_4
       1: anewarray     #26                 // class java/lang/Object
       4: dup
       5: iconst_0
       6: aload_0
       7: invokevirtual #21                 // Method getCanonicalName:()Ljava/lang/String;
      10: aastore
      11: dup
      12: iconst_1
      13: aload_0
      14: invokevirtual #23                 // Method getCodeSource:()Ljava/lang/String;
      17: aastore
      18: dup
      19: iconst_2
      20: aload_0
      21: invokevirtual #24                 // Method getMethods:()Ljava/util/List;
      24: aastore
      25: dup
      26: iconst_3
      27: aload_0
      28: invokevirtual #25                 // Method getTypes:()Ljava/util/List;
      31: aastore
      32: invokestatic  #27                 // Method java/util/Objects.hash:([Ljava/lang/Object;)I
      35: ireturn
}
