Compiled from "TypeDefinition.java"
public class org.apache.dubbo.metadata.definition.model.TypeDefinition implements java.io.Serializable {
  private java.lang.String type;

  private java.util.List<java.lang.String> items;

  private java.util.List<java.lang.String> enums;

  private java.util.Map<java.lang.String, java.lang.String> properties;

  public org.apache.dubbo.metadata.definition.model.TypeDefinition();
    Code:
       0: aload_0
       1: invokespecial #1                  // Method java/lang/Object."<init>":()V
       4: return

  public org.apache.dubbo.metadata.definition.model.TypeDefinition(java.lang.String);
    Code:
       0: aload_0
       1: invokespecial #1                  // Method java/lang/Object."<init>":()V
       4: aload_0
       5: aload_1
       6: invokevirtual #2                  // Method setType:(Ljava/lang/String;)V
       9: return

  public static java.lang.String[] formatTypes(java.lang.String[]);
    Code:
       0: aload_0
       1: arraylength
       2: anewarray     #3                  // class java/lang/String
       5: astore_1
       6: iconst_0
       7: istore_2
       8: iload_2
       9: aload_0
      10: arraylength
      11: if_icmpge     29
      14: aload_1
      15: iload_2
      16: aload_0
      17: iload_2
      18: aaload
      19: invokestatic  #4                  // Method formatType:(Ljava/lang/String;)Ljava/lang/String;
      22: aastore
      23: iinc          2, 1
      26: goto          8
      29: aload_1
      30: areturn

  public static java.lang.String formatType(java.lang.String);
    Code:
       0: aload_0
       1: invokestatic  #5                  // Method isGenericType:(Ljava/lang/String;)Z
       4: ifeq          12
       7: aload_0
       8: invokestatic  #6                  // Method formatGenericType:(Ljava/lang/String;)Ljava/lang/String;
      11: areturn
      12: aload_0
      13: areturn

  private static java.lang.String formatGenericType(java.lang.String);
    Code:
       0: aload_0
       1: ldc           #7                  // String ,
       3: ldc           #8                  // String ,
       5: invokestatic  #9                  // Method org/apache/dubbo/common/utils/StringUtils.replace:(Ljava/lang/String;Ljava/lang/String;Ljava/lang/String;)Ljava/lang/String;
       8: areturn

  private static boolean isGenericType(java.lang.String);
    Code:
       0: aload_0
       1: ldc           #10                 // String <
       3: invokevirtual #11                 // Method java/lang/String.contains:(Ljava/lang/CharSequence;)Z
       6: ifeq          22
       9: aload_0
      10: ldc           #12                 // String >
      12: invokevirtual #11                 // Method java/lang/String.contains:(Ljava/lang/CharSequence;)Z
      15: ifeq          22
      18: iconst_1
      19: goto          23
      22: iconst_0
      23: ireturn

  public java.util.List<java.lang.String> getEnums();
    Code:
       0: aload_0
       1: getfield      #13                 // Field enums:Ljava/util/List;
       4: ifnonnull     18
       7: aload_0
       8: new           #14                 // class java/util/ArrayList
      11: dup
      12: invokespecial #15                 // Method java/util/ArrayList."<init>":()V
      15: putfield      #13                 // Field enums:Ljava/util/List;
      18: aload_0
      19: getfield      #13                 // Field enums:Ljava/util/List;
      22: areturn

  public java.util.List<java.lang.String> getItems();
    Code:
       0: aload_0
       1: getfield      #16                 // Field items:Ljava/util/List;
       4: ifnonnull     18
       7: aload_0
       8: new           #14                 // class java/util/ArrayList
      11: dup
      12: invokespecial #15                 // Method java/util/ArrayList."<init>":()V
      15: putfield      #16                 // Field items:Ljava/util/List;
      18: aload_0
      19: getfield      #16                 // Field items:Ljava/util/List;
      22: areturn

  public java.util.Map<java.lang.String, java.lang.String> getProperties();
    Code:
       0: aload_0
       1: getfield      #17                 // Field properties:Ljava/util/Map;
       4: ifnonnull     18
       7: aload_0
       8: new           #18                 // class java/util/HashMap
      11: dup
      12: invokespecial #19                 // Method java/util/HashMap."<init>":()V
      15: putfield      #17                 // Field properties:Ljava/util/Map;
      18: aload_0
      19: getfield      #17                 // Field properties:Ljava/util/Map;
      22: areturn

  public java.lang.String getType();
    Code:
       0: aload_0
       1: getfield      #20                 // Field type:Ljava/lang/String;
       4: areturn

  public void setEnums(java.util.List<java.lang.String>);
    Code:
       0: aload_0
       1: aload_1
       2: putfield      #13                 // Field enums:Ljava/util/List;
       5: return

  public void setItems(java.util.List<java.lang.String>);
    Code:
       0: aload_0
       1: aload_1
       2: putfield      #16                 // Field items:Ljava/util/List;
       5: return

  public void setProperties(java.util.Map<java.lang.String, java.lang.String>);
    Code:
       0: aload_0
       1: aload_1
       2: putfield      #17                 // Field properties:Ljava/util/Map;
       5: return

  public void setType(java.lang.String);
    Code:
       0: aload_0
       1: aload_1
       2: invokestatic  #4                  // Method formatType:(Ljava/lang/String;)Ljava/lang/String;
       5: putfield      #20                 // Field type:Ljava/lang/String;
       8: return

  public java.lang.String toString();
    Code:
       0: new           #21                 // class java/lang/StringBuilder
       3: dup
       4: invokespecial #22                 // Method java/lang/StringBuilder."<init>":()V
       7: ldc           #23                 // String TypeDefinition [type=
       9: invokevirtual #24                 // Method java/lang/StringBuilder.append:(Ljava/lang/String;)Ljava/lang/StringBuilder;
      12: aload_0
      13: getfield      #20                 // Field type:Ljava/lang/String;
      16: invokevirtual #24                 // Method java/lang/StringBuilder.append:(Ljava/lang/String;)Ljava/lang/StringBuilder;
      19: ldc           #25                 // String , properties=
      21: invokevirtual #24                 // Method java/lang/StringBuilder.append:(Ljava/lang/String;)Ljava/lang/StringBuilder;
      24: aload_0
      25: getfield      #17                 // Field properties:Ljava/util/Map;
      28: invokevirtual #26                 // Method java/lang/StringBuilder.append:(Ljava/lang/Object;)Ljava/lang/StringBuilder;
      31: ldc           #27                 // String ]
      33: invokevirtual #24                 // Method java/lang/StringBuilder.append:(Ljava/lang/String;)Ljava/lang/StringBuilder;
      36: invokevirtual #28                 // Method java/lang/StringBuilder.toString:()Ljava/lang/String;
      39: areturn

  public boolean equals(java.lang.Object);
    Code:
       0: aload_0
       1: aload_1
       2: if_acmpne     7
       5: iconst_1
       6: ireturn
       7: aload_1
       8: instanceof    #29                 // class org/apache/dubbo/metadata/definition/model/TypeDefinition
      11: ifne          16
      14: iconst_0
      15: ireturn
      16: aload_1
      17: checkcast     #29                 // class org/apache/dubbo/metadata/definition/model/TypeDefinition
      20: astore_2
      21: aload_0
      22: invokevirtual #30                 // Method getType:()Ljava/lang/String;
      25: aload_2
      26: invokevirtual #30                 // Method getType:()Ljava/lang/String;
      29: invokestatic  #31                 // Method java/util/Objects.equals:(Ljava/lang/Object;Ljava/lang/Object;)Z
      32: ifeq          81
      35: aload_0
      36: invokevirtual #32                 // Method getItems:()Ljava/util/List;
      39: aload_2
      40: invokevirtual #32                 // Method getItems:()Ljava/util/List;
      43: invokestatic  #31                 // Method java/util/Objects.equals:(Ljava/lang/Object;Ljava/lang/Object;)Z
      46: ifeq          81
      49: aload_0
      50: invokevirtual #33                 // Method getEnums:()Ljava/util/List;
      53: aload_2
      54: invokevirtual #33                 // Method getEnums:()Ljava/util/List;
      57: invokestatic  #31                 // Method java/util/Objects.equals:(Ljava/lang/Object;Ljava/lang/Object;)Z
      60: ifeq          81
      63: aload_0
      64: invokevirtual #34                 // Method getProperties:()Ljava/util/Map;
      67: aload_2
      68: invokevirtual #34                 // Method getProperties:()Ljava/util/Map;
      71: invokestatic  #31                 // Method java/util/Objects.equals:(Ljava/lang/Object;Ljava/lang/Object;)Z
      74: ifeq          81
      77: iconst_1
      78: goto          82
      81: iconst_0
      82: ireturn

  public int hashCode();
    Code:
       0: iconst_4
       1: anewarray     #35                 // class java/lang/Object
       4: dup
       5: iconst_0
       6: aload_0
       7: invokevirtual #30                 // Method getType:()Ljava/lang/String;
      10: aastore
      11: dup
      12: iconst_1
      13: aload_0
      14: invokevirtual #32                 // Method getItems:()Ljava/util/List;
      17: aastore
      18: dup
      19: iconst_2
      20: aload_0
      21: invokevirtual #33                 // Method getEnums:()Ljava/util/List;
      24: aastore
      25: dup
      26: iconst_3
      27: aload_0
      28: invokevirtual #34                 // Method getProperties:()Ljava/util/Map;
      31: aastore
      32: invokestatic  #36                 // Method java/util/Objects.hash:([Ljava/lang/Object;)I
      35: ireturn
}
