Compiled from "AbstractServiceNameMapping.java"
class org.apache.dubbo.metadata.AbstractServiceNameMapping$AsyncMappingTask implements java.util.concurrent.Callable<java.util.Set<java.lang.String>> {
  private final org.apache.dubbo.metadata.MappingListener listener;

  private final org.apache.dubbo.common.URL subscribedURL;

  private final boolean notifyAtFirstTime;

  final org.apache.dubbo.metadata.AbstractServiceNameMapping this$0;

  public org.apache.dubbo.metadata.AbstractServiceNameMapping$AsyncMappingTask(org.apache.dubbo.metadata.AbstractServiceNameMapping, org.apache.dubbo.metadata.MappingListener, org.apache.dubbo.common.URL, boolean);
    Code:
       0: aload_0
       1: aload_1
       2: putfield      #2                  // Field this$0:Lorg/apache/dubbo/metadata/AbstractServiceNameMapping;
       5: aload_0
       6: invokespecial #3                  // Method java/lang/Object."<init>":()V
       9: aload_0
      10: aload_2
      11: putfield      #4                  // Field listener:Lorg/apache/dubbo/metadata/MappingListener;
      14: aload_0
      15: aload_3
      16: putfield      #5                  // Field subscribedURL:Lorg/apache/dubbo/common/URL;
      19: aload_0
      20: iload         4
      22: putfield      #6                  // Field notifyAtFirstTime:Z
      25: return

  public java.util.Set<java.lang.String> call() throws java.lang.Exception;
    Code:
       0: aload_0
       1: getfield      #2                  // Field this$0:Lorg/apache/dubbo/metadata/AbstractServiceNameMapping;
       4: invokestatic  #7                  // Method org/apache/dubbo/metadata/AbstractServiceNameMapping.access$000:(Lorg/apache/dubbo/metadata/AbstractServiceNameMapping;)Ljava/util/Map;
       7: dup
       8: astore_1
       9: monitorenter
      10: invokestatic  #8                  // Method java/util/Collections.emptySet:()Ljava/util/Set;
      13: astore_2
      14: aload_0
      15: getfield      #5                  // Field subscribedURL:Lorg/apache/dubbo/common/URL;
      18: invokestatic  #9                  // InterfaceMethod org/apache/dubbo/metadata/ServiceNameMapping.buildMappingKey:(Lorg/apache/dubbo/common/URL;)Ljava/lang/String;
      21: astore_3
      22: aload_0
      23: getfield      #4                  // Field listener:Lorg/apache/dubbo/metadata/MappingListener;
      26: ifnull        118
      29: aload_0
      30: getfield      #2                  // Field this$0:Lorg/apache/dubbo/metadata/AbstractServiceNameMapping;
      33: aload_0
      34: getfield      #5                  // Field subscribedURL:Lorg/apache/dubbo/common/URL;
      37: aload_0
      38: getfield      #4                  // Field listener:Lorg/apache/dubbo/metadata/MappingListener;
      41: invokevirtual #10                 // Method org/apache/dubbo/metadata/AbstractServiceNameMapping.getAndListen:(Lorg/apache/dubbo/common/URL;Lorg/apache/dubbo/metadata/MappingListener;)Ljava/util/Set;
      44: invokestatic  #11                 // Method org/apache/dubbo/common/utils/CollectionUtils.toTreeSet:(Ljava/util/Set;)Ljava/util/Set;
      47: astore_2
      48: aload_0
      49: getfield      #2                  // Field this$0:Lorg/apache/dubbo/metadata/AbstractServiceNameMapping;
      52: invokestatic  #7                  // Method org/apache/dubbo/metadata/AbstractServiceNameMapping.access$000:(Lorg/apache/dubbo/metadata/AbstractServiceNameMapping;)Ljava/util/Map;
      55: aload_3
      56: invokedynamic #12,  0             // InvokeDynamic #0:apply:()Ljava/util/function/Function;
      61: invokeinterface #13,  3           // InterfaceMethod java/util/Map.computeIfAbsent:(Ljava/lang/Object;Ljava/util/function/Function;)Ljava/lang/Object;
      66: checkcast     #14                 // class java/util/Set
      69: astore        4
      71: aload         4
      73: aload_0
      74: getfield      #4                  // Field listener:Lorg/apache/dubbo/metadata/MappingListener;
      77: invokeinterface #15,  2           // InterfaceMethod java/util/Set.add:(Ljava/lang/Object;)Z
      82: pop
      83: aload_2
      84: invokestatic  #16                 // Method org/apache/dubbo/common/utils/CollectionUtils.isNotEmpty:(Ljava/util/Collection;)Z
      87: ifeq          115
      90: aload_0
      91: getfield      #6                  // Field notifyAtFirstTime:Z
      94: ifeq          115
      97: aload_0
      98: getfield      #4                  // Field listener:Lorg/apache/dubbo/metadata/MappingListener;
     101: new           #17                 // class org/apache/dubbo/metadata/MappingChangedEvent
     104: dup
     105: aload_3
     106: aload_2
     107: invokespecial #18                 // Method org/apache/dubbo/metadata/MappingChangedEvent."<init>":(Ljava/lang/String;Ljava/util/Set;)V
     110: invokeinterface #19,  2           // InterfaceMethod org/apache/dubbo/metadata/MappingListener.onEvent:(Lorg/apache/dubbo/metadata/MappingChangedEvent;)V
     115: goto          146
     118: aload_0
     119: getfield      #2                  // Field this$0:Lorg/apache/dubbo/metadata/AbstractServiceNameMapping;
     122: aload_0
     123: getfield      #5                  // Field subscribedURL:Lorg/apache/dubbo/common/URL;
     126: invokevirtual #20                 // Method org/apache/dubbo/metadata/AbstractServiceNameMapping.get:(Lorg/apache/dubbo/common/URL;)Ljava/util/Set;
     129: astore_2
     130: aload_2
     131: invokestatic  #16                 // Method org/apache/dubbo/common/utils/CollectionUtils.isNotEmpty:(Ljava/util/Collection;)Z
     134: ifeq          146
     137: aload_0
     138: getfield      #2                  // Field this$0:Lorg/apache/dubbo/metadata/AbstractServiceNameMapping;
     141: aload_3
     142: aload_2
     143: invokevirtual #21                 // Method org/apache/dubbo/metadata/AbstractServiceNameMapping.putCachedMapping:(Ljava/lang/String;Ljava/util/Set;)V
     146: goto          171
     149: astore_3
     150: aload_0
     151: getfield      #2                  // Field this$0:Lorg/apache/dubbo/metadata/AbstractServiceNameMapping;
     154: getfield      #23                 // Field org/apache/dubbo/metadata/AbstractServiceNameMapping.logger:Lorg/apache/dubbo/common/logger/ErrorTypeAwareLogger;
     157: ldc           #24                 // String 0-25
     159: ldc           #25                 // String
     161: ldc           #25                 // String
     163: ldc           #26                 // String Failed getting mapping info from remote center.
     165: aload_3
     166: invokeinterface #27,  6           // InterfaceMethod org/apache/dubbo/common/logger/ErrorTypeAwareLogger.error:(Ljava/lang/String;Ljava/lang/String;Ljava/lang/String;Ljava/lang/String;Ljava/lang/Throwable;)V
     171: aload_2
     172: aload_1
     173: monitorexit
     174: areturn
     175: astore        5
     177: aload_1
     178: monitorexit
     179: aload         5
     181: athrow
    Exception table:
       from    to  target type
          14   146   149   Class java/lang/Exception
          10   174   175   any
         175   179   175   any

  public java.lang.Object call() throws java.lang.Exception;
    Code:
       0: aload_0
       1: invokevirtual #28                 // Method call:()Ljava/util/Set;
       4: areturn

  private static java.util.Set lambda$call$0(java.lang.String);
    Code:
       0: new           #29                 // class java/util/HashSet
       3: dup
       4: invokespecial #30                 // Method java/util/HashSet."<init>":()V
       7: areturn
}
