Compiled from "AbstractCacheManager.java"
public abstract class org.apache.dubbo.metadata.AbstractCacheManager<V> implements org.apache.dubbo.common.resource.Disposable {
  protected final org.apache.dubbo.common.logger.ErrorTypeAwareLogger logger;

  private java.util.concurrent.ScheduledExecutorService executorService;

  protected org.apache.dubbo.common.cache.FileCacheStore cacheStore;

  protected org.apache.dubbo.common.utils.LRUCache<java.lang.String, V> cache;

  public org.apache.dubbo.metadata.AbstractCacheManager();
    Code:
       0: aload_0
       1: invokespecial #2                  // Method java/lang/Object."<init>":()V
       4: aload_0
       5: aload_0
       6: invokevirtual #3                  // Method java/lang/Object.getClass:()Ljava/lang/Class;
       9: invokestatic  #4                  // Method org/apache/dubbo/common/logger/LoggerFactory.getErrorTypeAwareLogger:(Ljava/lang/Class;)Lorg/apache/dubbo/common/logger/ErrorTypeAwareLogger;
      12: putfield      #5                  // Field logger:Lorg/apache/dubbo/common/logger/ErrorTypeAwareLogger;
      15: return

  protected void init(boolean, java.lang.String, java.lang.String, int, long, int, java.util.concurrent.ScheduledExecutorService);
    Code:
       0: aload_0
       1: new           #6                  // class org/apache/dubbo/common/utils/LRUCache
       4: dup
       5: iload         4
       7: invokespecial #7                  // Method org/apache/dubbo/common/utils/LRUCache."<init>":(I)V
      10: putfield      #8                  // Field cache:Lorg/apache/dubbo/common/utils/LRUCache;
      13: aload_0
      14: aload_2
      15: aload_3
      16: iload_1
      17: invokestatic  #9                  // Method org/apache/dubbo/common/cache/FileCacheStoreFactory.getInstance:(Ljava/lang/String;Ljava/lang/String;Z)Lorg/apache/dubbo/common/cache/FileCacheStore;
      20: putfield      #10                 // Field cacheStore:Lorg/apache/dubbo/common/cache/FileCacheStore;
      23: aload_0
      24: getfield      #10                 // Field cacheStore:Lorg/apache/dubbo/common/cache/FileCacheStore;
      27: iload         4
      29: invokevirtual #11                 // Method org/apache/dubbo/common/cache/FileCacheStore.loadCache:(I)Ljava/util/Map;
      32: astore        9
      34: aload_0
      35: getfield      #5                  // Field logger:Lorg/apache/dubbo/common/logger/ErrorTypeAwareLogger;
      38: new           #12                 // class java/lang/StringBuilder
      41: dup
      42: invokespecial #13                 // Method java/lang/StringBuilder."<init>":()V
      45: ldc           #14                 // String Successfully loaded
      47: invokevirtual #15                 // Method java/lang/StringBuilder.append:(Ljava/lang/String;)Ljava/lang/StringBuilder;
      50: aload_0
      51: invokevirtual #16                 // Method getName:()Ljava/lang/String;
      54: invokevirtual #15                 // Method java/lang/StringBuilder.append:(Ljava/lang/String;)Ljava/lang/StringBuilder;
      57: ldc           #17                 // String  cache from file
      59: invokevirtual #15                 // Method java/lang/StringBuilder.append:(Ljava/lang/String;)Ljava/lang/StringBuilder;
      62: aload_3
      63: invokevirtual #15                 // Method java/lang/StringBuilder.append:(Ljava/lang/String;)Ljava/lang/StringBuilder;
      66: ldc           #18                 // String , entries
      68: invokevirtual #15                 // Method java/lang/StringBuilder.append:(Ljava/lang/String;)Ljava/lang/StringBuilder;
      71: aload         9
      73: invokeinterface #19,  1           // InterfaceMethod java/util/Map.size:()I
      78: invokevirtual #20                 // Method java/lang/StringBuilder.append:(I)Ljava/lang/StringBuilder;
      81: invokevirtual #21                 // Method java/lang/StringBuilder.toString:()Ljava/lang/String;
      84: invokeinterface #22,  2           // InterfaceMethod org/apache/dubbo/common/logger/ErrorTypeAwareLogger.info:(Ljava/lang/String;)V
      89: aload         9
      91: invokeinterface #23,  1           // InterfaceMethod java/util/Map.entrySet:()Ljava/util/Set;
      96: invokeinterface #24,  1           // InterfaceMethod java/util/Set.iterator:()Ljava/util/Iterator;
     101: astore        10
     103: aload         10
     105: invokeinterface #25,  1           // InterfaceMethod java/util/Iterator.hasNext:()Z
     110: ifeq          168
     113: aload         10
     115: invokeinterface #26,  1           // InterfaceMethod java/util/Iterator.next:()Ljava/lang/Object;
     120: checkcast     #27                 // class java/util/Map$Entry
     123: astore        11
     125: aload         11
     127: invokeinterface #28,  1           // InterfaceMethod java/util/Map$Entry.getKey:()Ljava/lang/Object;
     132: checkcast     #29                 // class java/lang/String
     135: astore        12
     137: aload         11
     139: invokeinterface #30,  1           // InterfaceMethod java/util/Map$Entry.getValue:()Ljava/lang/Object;
     144: checkcast     #29                 // class java/lang/String
     147: astore        13
     149: aload_0
     150: getfield      #8                  // Field cache:Lorg/apache/dubbo/common/utils/LRUCache;
     153: aload         12
     155: aload_0
     156: aload         13
     158: invokevirtual #31                 // Method toValueType:(Ljava/lang/String;)Ljava/lang/Object;
     161: invokevirtual #32                 // Method org/apache/dubbo/common/utils/LRUCache.put:(Ljava/lang/Object;Ljava/lang/Object;)Ljava/lang/Object;
     164: pop
     165: goto          103
     168: aload         8
     170: ifnonnull     193
     173: aload_0
     174: new           #33                 // class org/apache/dubbo/common/utils/NamedThreadFactory
     177: dup
     178: ldc           #34                 // String Dubbo-cache-refreshing-scheduler
     180: iconst_1
     181: invokespecial #35                 // Method org/apache/dubbo/common/utils/NamedThreadFactory."<init>":(Ljava/lang/String;Z)V
     184: invokestatic  #36                 // Method java/util/concurrent/Executors.newSingleThreadScheduledExecutor:(Ljava/util/concurrent/ThreadFactory;)Ljava/util/concurrent/ScheduledExecutorService;
     187: putfield      #37                 // Field executorService:Ljava/util/concurrent/ScheduledExecutorService;
     190: goto          199
     193: aload_0
     194: aload         8
     196: putfield      #37                 // Field executorService:Ljava/util/concurrent/ScheduledExecutorService;
     199: aload_0
     200: getfield      #37                 // Field executorService:Ljava/util/concurrent/ScheduledExecutorService;
     203: new           #38                 // class org/apache/dubbo/metadata/AbstractCacheManager$CacheRefreshTask
     206: dup
     207: aload_0
     208: getfield      #10                 // Field cacheStore:Lorg/apache/dubbo/common/cache/FileCacheStore;
     211: aload_0
     212: getfield      #8                  // Field cache:Lorg/apache/dubbo/common/utils/LRUCache;
     215: aload_0
     216: lload         5
     218: invokespecial #39                 // Method org/apache/dubbo/metadata/AbstractCacheManager$CacheRefreshTask."<init>":(Lorg/apache/dubbo/common/cache/FileCacheStore;Lorg/apache/dubbo/common/utils/LRUCache;Lorg/apache/dubbo/metadata/AbstractCacheManager;J)V
     221: ldc2_w        #40                 // long 10l
     224: iload         7
     226: i2l
     227: getstatic     #42                 // Field java/util/concurrent/TimeUnit.MINUTES:Ljava/util/concurrent/TimeUnit;
     230: invokeinterface #43,  7           // InterfaceMethod java/util/concurrent/ScheduledExecutorService.scheduleWithFixedDelay:(Ljava/lang/Runnable;JJLjava/util/concurrent/TimeUnit;)Ljava/util/concurrent/ScheduledFuture;
     235: pop
     236: goto          260
     239: astore        9
     241: aload_0
     242: getfield      #5                  // Field logger:Lorg/apache/dubbo/common/logger/ErrorTypeAwareLogger;
     245: ldc           #45                 // String 0-25
     247: ldc           #46                 // String
     249: ldc           #46                 // String
     251: ldc           #47                 // String Load mapping from local cache file error
     253: aload         9
     255: invokeinterface #48,  6           // InterfaceMethod org/apache/dubbo/common/logger/ErrorTypeAwareLogger.error:(Ljava/lang/String;Ljava/lang/String;Ljava/lang/String;Ljava/lang/String;Ljava/lang/Throwable;)V
     260: return
    Exception table:
       from    to  target type
          13   236   239   Class java/lang/Exception

  protected abstract V toValueType(java.lang.String);

  protected abstract java.lang.String getName();

  public V get(java.lang.String);
    Code:
       0: aload_0
       1: getfield      #8                  // Field cache:Lorg/apache/dubbo/common/utils/LRUCache;
       4: aload_1
       5: invokevirtual #49                 // Method org/apache/dubbo/common/utils/LRUCache.get:(Ljava/lang/Object;)Ljava/lang/Object;
       8: areturn

  public void put(java.lang.String, V);
    Code:
       0: aload_0
       1: getfield      #8                  // Field cache:Lorg/apache/dubbo/common/utils/LRUCache;
       4: aload_1
       5: aload_2
       6: invokevirtual #32                 // Method org/apache/dubbo/common/utils/LRUCache.put:(Ljava/lang/Object;Ljava/lang/Object;)Ljava/lang/Object;
       9: pop
      10: return

  public V remove(java.lang.String);
    Code:
       0: aload_0
       1: getfield      #8                  // Field cache:Lorg/apache/dubbo/common/utils/LRUCache;
       4: aload_1
       5: invokevirtual #50                 // Method org/apache/dubbo/common/utils/LRUCache.remove:(Ljava/lang/Object;)Ljava/lang/Object;
       8: areturn

  public java.util.Map<java.lang.String, V> getAll();
    Code:
       0: aload_0
       1: getfield      #8                  // Field cache:Lorg/apache/dubbo/common/utils/LRUCache;
       4: invokevirtual #51                 // Method org/apache/dubbo/common/utils/LRUCache.isEmpty:()Z
       7: ifeq          14
      10: invokestatic  #52                 // Method java/util/Collections.emptyMap:()Ljava/util/Map;
      13: areturn
      14: new           #53                 // class java/util/HashMap
      17: dup
      18: invokespecial #54                 // Method java/util/HashMap."<init>":()V
      21: astore_1
      22: aload_0
      23: getfield      #8                  // Field cache:Lorg/apache/dubbo/common/utils/LRUCache;
      26: invokevirtual #55                 // Method org/apache/dubbo/common/utils/LRUCache.lock:()V
      29: aload_0
      30: getfield      #8                  // Field cache:Lorg/apache/dubbo/common/utils/LRUCache;
      33: invokevirtual #56                 // Method org/apache/dubbo/common/utils/LRUCache.entrySet:()Ljava/util/Set;
      36: invokeinterface #24,  1           // InterfaceMethod java/util/Set.iterator:()Ljava/util/Iterator;
      41: astore_2
      42: aload_2
      43: invokeinterface #25,  1           // InterfaceMethod java/util/Iterator.hasNext:()Z
      48: ifeq          83
      51: aload_2
      52: invokeinterface #26,  1           // InterfaceMethod java/util/Iterator.next:()Ljava/lang/Object;
      57: checkcast     #27                 // class java/util/Map$Entry
      60: astore_3
      61: aload_1
      62: aload_3
      63: invokeinterface #28,  1           // InterfaceMethod java/util/Map$Entry.getKey:()Ljava/lang/Object;
      68: aload_3
      69: invokeinterface #30,  1           // InterfaceMethod java/util/Map$Entry.getValue:()Ljava/lang/Object;
      74: invokeinterface #57,  3           // InterfaceMethod java/util/Map.put:(Ljava/lang/Object;Ljava/lang/Object;)Ljava/lang/Object;
      79: pop
      80: goto          42
      83: aload_0
      84: getfield      #8                  // Field cache:Lorg/apache/dubbo/common/utils/LRUCache;
      87: invokevirtual #58                 // Method org/apache/dubbo/common/utils/LRUCache.releaseLock:()V
      90: goto          105
      93: astore        4
      95: aload_0
      96: getfield      #8                  // Field cache:Lorg/apache/dubbo/common/utils/LRUCache;
      99: invokevirtual #58                 // Method org/apache/dubbo/common/utils/LRUCache.releaseLock:()V
     102: aload         4
     104: athrow
     105: aload_1
     106: invokestatic  #59                 // Method java/util/Collections.unmodifiableMap:(Ljava/util/Map;)Ljava/util/Map;
     109: areturn
    Exception table:
       from    to  target type
          29    83    93   any
          93    95    93   any

  public void update(java.util.Map<java.lang.String, V>);
    Code:
       0: aload_1
       1: invokeinterface #23,  1           // InterfaceMethod java/util/Map.entrySet:()Ljava/util/Set;
       6: invokeinterface #24,  1           // InterfaceMethod java/util/Set.iterator:()Ljava/util/Iterator;
      11: astore_2
      12: aload_2
      13: invokeinterface #25,  1           // InterfaceMethod java/util/Iterator.hasNext:()Z
      18: ifeq          54
      21: aload_2
      22: invokeinterface #26,  1           // InterfaceMethod java/util/Iterator.next:()Ljava/lang/Object;
      27: checkcast     #27                 // class java/util/Map$Entry
      30: astore_3
      31: aload_0
      32: getfield      #8                  // Field cache:Lorg/apache/dubbo/common/utils/LRUCache;
      35: aload_3
      36: invokeinterface #28,  1           // InterfaceMethod java/util/Map$Entry.getKey:()Ljava/lang/Object;
      41: aload_3
      42: invokeinterface #30,  1           // InterfaceMethod java/util/Map$Entry.getValue:()Ljava/lang/Object;
      47: invokevirtual #32                 // Method org/apache/dubbo/common/utils/LRUCache.put:(Ljava/lang/Object;Ljava/lang/Object;)Ljava/lang/Object;
      50: pop
      51: goto          12
      54: return

  public void destroy();
    Code:
       0: aload_0
       1: getfield      #37                 // Field executorService:Ljava/util/concurrent/ScheduledExecutorService;
       4: ifnull        17
       7: aload_0
       8: getfield      #37                 // Field executorService:Ljava/util/concurrent/ScheduledExecutorService;
      11: invokeinterface #60,  1           // InterfaceMethod java/util/concurrent/ScheduledExecutorService.shutdownNow:()Ljava/util/List;
      16: pop
      17: aload_0
      18: getfield      #10                 // Field cacheStore:Lorg/apache/dubbo/common/cache/FileCacheStore;
      21: ifnull        31
      24: aload_0
      25: getfield      #10                 // Field cacheStore:Lorg/apache/dubbo/common/cache/FileCacheStore;
      28: invokevirtual #61                 // Method org/apache/dubbo/common/cache/FileCacheStore.destroy:()V
      31: aload_0
      32: getfield      #8                  // Field cache:Lorg/apache/dubbo/common/utils/LRUCache;
      35: ifnull        45
      38: aload_0
      39: getfield      #8                  // Field cache:Lorg/apache/dubbo/common/utils/LRUCache;
      42: invokevirtual #62                 // Method org/apache/dubbo/common/utils/LRUCache.clear:()V
      45: return

  public org.apache.dubbo.common.cache.FileCacheStore getCacheStore();
    Code:
       0: aload_0
       1: getfield      #10                 // Field cacheStore:Lorg/apache/dubbo/common/cache/FileCacheStore;
       4: areturn

  public org.apache.dubbo.common.utils.LRUCache<java.lang.String, V> getCache();
    Code:
       0: aload_0
       1: getfield      #8                  // Field cache:Lorg/apache/dubbo/common/utils/LRUCache;
       4: areturn
}
