Compiled from "MappingChangedEvent.java"
public class org.apache.dubbo.metadata.MappingChangedEvent {
  private final java.lang.String serviceKey;

  private final java.util.Set<java.lang.String> apps;

  public org.apache.dubbo.metadata.MappingChangedEvent(java.lang.String, java.util.Set<java.lang.String>);
    Code:
       0: aload_0
       1: invokespecial #1                  // Method java/lang/Object."<init>":()V
       4: aload_0
       5: aload_1
       6: putfield      #2                  // Field serviceKey:Ljava/lang/String;
       9: aload_0
      10: aload_2
      11: putfield      #3                  // Field apps:Ljava/util/Set;
      14: return

  public java.lang.String getServiceKey();
    Code:
       0: aload_0
       1: getfield      #2                  // Field serviceKey:Ljava/lang/String;
       4: areturn

  public java.util.Set<java.lang.String> getApps();
    Code:
       0: aload_0
       1: getfield      #3                  // Field apps:Ljava/util/Set;
       4: areturn

  public java.lang.String toString();
    Code:
       0: new           #4                  // class java/lang/StringBuilder
       3: dup
       4: invokespecial #5                  // Method java/lang/StringBuilder."<init>":()V
       7: ldc           #6                  // String {serviceKey:
       9: invokevirtual #7                  // Method java/lang/StringBuilder.append:(Ljava/lang/String;)Ljava/lang/StringBuilder;
      12: aload_0
      13: getfield      #2                  // Field serviceKey:Ljava/lang/String;
      16: invokevirtual #7                  // Method java/lang/StringBuilder.append:(Ljava/lang/String;)Ljava/lang/StringBuilder;
      19: ldc           #8                  // String , apps:
      21: invokevirtual #7                  // Method java/lang/StringBuilder.append:(Ljava/lang/String;)Ljava/lang/StringBuilder;
      24: aload_0
      25: getfield      #3                  // Field apps:Ljava/util/Set;
      28: invokevirtual #9                  // Method java/lang/Object.toString:()Ljava/lang/String;
      31: invokevirtual #7                  // Method java/lang/StringBuilder.append:(Ljava/lang/String;)Ljava/lang/StringBuilder;
      34: ldc           #10                 // String }
      36: invokevirtual #7                  // Method java/lang/StringBuilder.append:(Ljava/lang/String;)Ljava/lang/StringBuilder;
      39: invokevirtual #11                 // Method java/lang/StringBuilder.toString:()Ljava/lang/String;
      42: areturn
}
