Compiled from "MetadataService.java"
public interface org.apache.dubbo.metadata.MetadataService {
  public static final java.lang.String ALL_SERVICE_INTERFACES;

  public static final java.lang.String VERSION;

  public abstract java.lang.String serviceName();

  public default java.lang.String version();
    Code:
       0: ldc           #2                  // String 1.0.0
       2: areturn

  public abstract org.apache.dubbo.common.URL getMetadataURL();

  public default java.util.SortedSet<java.lang.String> getSubscribedURLs();
    Code:
       0: new           #3                  // class java/lang/UnsupportedOperationException
       3: dup
       4: ldc           #4                  // String This operation is not supported for consumer.
       6: invokespecial #5                  // Method java/lang/UnsupportedOperationException."<init>":(Ljava/lang/String;)V
       9: athrow

  public default java.util.SortedSet<java.lang.String> getExportedURLs();
    Code:
       0: aload_0
       1: ldc           #6                  // String *
       3: invokeinterface #7,  2            // InterfaceMethod getExportedURLs:(Ljava/lang/String;)Ljava/util/SortedSet;
       8: areturn

  public default java.util.SortedSet<java.lang.String> getExportedURLs(java.lang.String);
    Code:
       0: aload_0
       1: aload_1
       2: aconst_null
       3: invokeinterface #8,  3            // InterfaceMethod getExportedURLs:(Ljava/lang/String;Ljava/lang/String;)Ljava/util/SortedSet;
       8: areturn

  public default java.util.SortedSet<java.lang.String> getExportedURLs(java.lang.String, java.lang.String);
    Code:
       0: aload_0
       1: aload_1
       2: aload_2
       3: aconst_null
       4: invokeinterface #9,  4            // InterfaceMethod getExportedURLs:(Ljava/lang/String;Ljava/lang/String;Ljava/lang/String;)Ljava/util/SortedSet;
       9: areturn

  public default java.util.SortedSet<java.lang.String> getExportedURLs(java.lang.String, java.lang.String, java.lang.String);
    Code:
       0: aload_0
       1: aload_1
       2: aload_2
       3: aload_3
       4: aconst_null
       5: invokeinterface #10,  5           // InterfaceMethod getExportedURLs:(Ljava/lang/String;Ljava/lang/String;Ljava/lang/String;Ljava/lang/String;)Ljava/util/SortedSet;
      10: areturn

  public abstract java.util.SortedSet<java.lang.String> getExportedURLs(java.lang.String, java.lang.String, java.lang.String, java.lang.String);

  public default java.util.Set<org.apache.dubbo.common.URL> getExportedServiceURLs();
    Code:
       0: invokestatic  #11                 // Method java/util/Collections.emptySet:()Ljava/util/Set;
       3: areturn

  public default java.lang.String getServiceDefinition(java.lang.String, java.lang.String, java.lang.String);
    Code:
       0: aload_0
       1: aload_1
       2: aload_3
       3: aload_2
       4: invokestatic  #12                 // Method org/apache/dubbo/common/URL.buildKey:(Ljava/lang/String;Ljava/lang/String;Ljava/lang/String;)Ljava/lang/String;
       7: invokeinterface #13,  2           // InterfaceMethod getServiceDefinition:(Ljava/lang/String;)Ljava/lang/String;
      12: areturn

  public abstract java.lang.String getServiceDefinition(java.lang.String);

  public abstract org.apache.dubbo.metadata.MetadataInfo getMetadataInfo(java.lang.String);

  public abstract java.util.List<org.apache.dubbo.metadata.MetadataInfo> getMetadataInfos();

  public static java.util.SortedSet<java.lang.String> toSortedStrings(java.lang.Iterable<org.apache.dubbo.common.URL>);
    Code:
       0: aload_0
       1: invokeinterface #14,  1           // InterfaceMethod java/lang/Iterable.spliterator:()Ljava/util/Spliterator;
       6: iconst_0
       7: invokestatic  #15                 // Method java/util/stream/StreamSupport.stream:(Ljava/util/Spliterator;Z)Ljava/util/stream/Stream;
      10: invokestatic  #16                 // InterfaceMethod toSortedStrings:(Ljava/util/stream/Stream;)Ljava/util/SortedSet;
      13: areturn

  public static java.util.SortedSet<java.lang.String> toSortedStrings(java.util.stream.Stream<org.apache.dubbo.common.URL>);
    Code:
       0: aload_0
       1: invokedynamic #17,  0             // InvokeDynamic #0:apply:()Ljava/util/function/Function;
       6: invokeinterface #18,  2           // InterfaceMethod java/util/stream/Stream.map:(Ljava/util/function/Function;)Ljava/util/stream/Stream;
      11: invokedynamic #19,  0             // InvokeDynamic #1:get:()Ljava/util/function/Supplier;
      16: invokedynamic #20,  0             // InvokeDynamic #2:accept:()Ljava/util/function/BiConsumer;
      21: invokedynamic #21,  0             // InvokeDynamic #3:accept:()Ljava/util/function/BiConsumer;
      26: invokeinterface #22,  4           // InterfaceMethod java/util/stream/Stream.collect:(Ljava/util/function/Supplier;Ljava/util/function/BiConsumer;Ljava/util/function/BiConsumer;)Ljava/lang/Object;
      31: checkcast     #23                 // class java/util/SortedSet
      34: invokestatic  #24                 // Method java/util/Collections.unmodifiableSortedSet:(Ljava/util/SortedSet;)Ljava/util/SortedSet;
      37: areturn

  public static boolean isMetadataService(java.lang.String);
    Code:
       0: aload_0
       1: ifnull        20
       4: aload_0
       5: ldc           #1                  // class org/apache/dubbo/metadata/MetadataService
       7: invokevirtual #25                 // Method java/lang/Class.getName:()Ljava/lang/String;
      10: invokevirtual #26                 // Method java/lang/String.equals:(Ljava/lang/Object;)Z
      13: ifeq          20
      16: iconst_1
      17: goto          21
      20: iconst_0
      21: ireturn

  public abstract void exportInstanceMetadata(java.lang.String);

  public abstract java.util.Map<java.lang.String, org.apache.dubbo.metadata.InstanceMetadataChangedListener> getInstanceMetadataChangedListenerMap();

  public abstract java.lang.String getAndListenInstanceMetadata(java.lang.String, org.apache.dubbo.metadata.InstanceMetadataChangedListener);
}
