Compiled from "MetadataInfo.java"
public class org.apache.dubbo.metadata.MetadataInfo implements java.io.Serializable {
  public static final org.apache.dubbo.metadata.MetadataInfo EMPTY;

  private static final org.apache.dubbo.common.logger.Logger logger;

  private java.lang.String app;

  private volatile java.lang.String revision;

  private final java.util.Map<java.lang.String, org.apache.dubbo.metadata.MetadataInfo$ServiceInfo> services;

  private transient java.util.concurrent.atomic.AtomicBoolean initiated;

  private volatile transient java.lang.String rawMetadataInfo;

  private transient java.util.Map<java.lang.String, java.util.Set<org.apache.dubbo.metadata.MetadataInfo$ServiceInfo>> subscribedServices;

  private final transient java.util.Map<java.lang.String, java.lang.String> extendParams;

  private final transient java.util.Map<java.lang.String, java.lang.String> instanceParams;

  protected volatile transient boolean updated;

  private transient java.util.concurrent.ConcurrentNavigableMap<java.lang.String, java.util.SortedSet<org.apache.dubbo.common.URL>> subscribedServiceURLs;

  private transient java.util.concurrent.ConcurrentNavigableMap<java.lang.String, java.util.SortedSet<org.apache.dubbo.common.URL>> exportedServiceURLs;

  private transient org.apache.dubbo.common.extension.ExtensionLoader<org.apache.dubbo.metadata.MetadataParamsFilter> loader;

  public org.apache.dubbo.metadata.MetadataInfo();
    Code:
       0: aload_0
       1: aconst_null
       2: invokespecial #3                  // Method "<init>":(Ljava/lang/String;)V
       5: return

  public org.apache.dubbo.metadata.MetadataInfo(java.lang.String);
    Code:
       0: aload_0
       1: aload_1
       2: aconst_null
       3: aconst_null
       4: invokespecial #4                  // Method "<init>":(Ljava/lang/String;Ljava/lang/String;Ljava/util/Map;)V
       7: return

  public org.apache.dubbo.metadata.MetadataInfo(java.lang.String, java.lang.String, java.util.Map<java.lang.String, org.apache.dubbo.metadata.MetadataInfo$ServiceInfo>);
    Code:
       0: aload_0
       1: invokespecial #5                  // Method java/lang/Object."<init>":()V
       4: aload_0
       5: new           #6                  // class java/util/concurrent/atomic/AtomicBoolean
       8: dup
       9: iconst_0
      10: invokespecial #7                  // Method java/util/concurrent/atomic/AtomicBoolean."<init>":(Z)V
      13: putfield      #8                  // Field initiated:Ljava/util/concurrent/atomic/AtomicBoolean;
      16: aload_0
      17: iconst_0
      18: putfield      #9                  // Field updated:Z
      21: aload_0
      22: aload_1
      23: putfield      #10                 // Field app:Ljava/lang/String;
      26: aload_0
      27: aload_2
      28: putfield      #11                 // Field revision:Ljava/lang/String;
      31: aload_0
      32: aload_3
      33: ifnonnull     46
      36: new           #12                 // class java/util/concurrent/ConcurrentHashMap
      39: dup
      40: invokespecial #13                 // Method java/util/concurrent/ConcurrentHashMap."<init>":()V
      43: goto          47
      46: aload_3
      47: putfield      #14                 // Field services:Ljava/util/Map;
      50: aload_0
      51: new           #12                 // class java/util/concurrent/ConcurrentHashMap
      54: dup
      55: invokespecial #13                 // Method java/util/concurrent/ConcurrentHashMap."<init>":()V
      58: putfield      #15                 // Field extendParams:Ljava/util/Map;
      61: aload_0
      62: new           #12                 // class java/util/concurrent/ConcurrentHashMap
      65: dup
      66: invokespecial #13                 // Method java/util/concurrent/ConcurrentHashMap."<init>":()V
      69: putfield      #16                 // Field instanceParams:Ljava/util/Map;
      72: return

  private org.apache.dubbo.metadata.MetadataInfo(java.lang.String, java.lang.String, java.util.Map<java.lang.String, org.apache.dubbo.metadata.MetadataInfo$ServiceInfo>, java.util.concurrent.atomic.AtomicBoolean, java.util.Map<java.lang.String, java.lang.String>, java.util.Map<java.lang.String, java.lang.String>, boolean, java.util.concurrent.ConcurrentNavigableMap<java.lang.String, java.util.SortedSet<org.apache.dubbo.common.URL>>, java.util.concurrent.ConcurrentNavigableMap<java.lang.String, java.util.SortedSet<org.apache.dubbo.common.URL>>, org.apache.dubbo.common.extension.ExtensionLoader<org.apache.dubbo.metadata.MetadataParamsFilter>);
    Code:
       0: aload_0
       1: invokespecial #5                  // Method java/lang/Object."<init>":()V
       4: aload_0
       5: new           #6                  // class java/util/concurrent/atomic/AtomicBoolean
       8: dup
       9: iconst_0
      10: invokespecial #7                  // Method java/util/concurrent/atomic/AtomicBoolean."<init>":(Z)V
      13: putfield      #8                  // Field initiated:Ljava/util/concurrent/atomic/AtomicBoolean;
      16: aload_0
      17: iconst_0
      18: putfield      #9                  // Field updated:Z
      21: aload_0
      22: aload_1
      23: putfield      #10                 // Field app:Ljava/lang/String;
      26: aload_0
      27: aload_2
      28: putfield      #11                 // Field revision:Ljava/lang/String;
      31: aload_0
      32: new           #12                 // class java/util/concurrent/ConcurrentHashMap
      35: dup
      36: aload_3
      37: invokespecial #17                 // Method java/util/concurrent/ConcurrentHashMap."<init>":(Ljava/util/Map;)V
      40: putfield      #14                 // Field services:Ljava/util/Map;
      43: aload_0
      44: new           #6                  // class java/util/concurrent/atomic/AtomicBoolean
      47: dup
      48: aload         4
      50: invokevirtual #18                 // Method java/util/concurrent/atomic/AtomicBoolean.get:()Z
      53: invokespecial #7                  // Method java/util/concurrent/atomic/AtomicBoolean."<init>":(Z)V
      56: putfield      #8                  // Field initiated:Ljava/util/concurrent/atomic/AtomicBoolean;
      59: aload_0
      60: new           #12                 // class java/util/concurrent/ConcurrentHashMap
      63: dup
      64: aload         5
      66: invokespecial #17                 // Method java/util/concurrent/ConcurrentHashMap."<init>":(Ljava/util/Map;)V
      69: putfield      #15                 // Field extendParams:Ljava/util/Map;
      72: aload_0
      73: new           #12                 // class java/util/concurrent/ConcurrentHashMap
      76: dup
      77: aload         6
      79: invokespecial #17                 // Method java/util/concurrent/ConcurrentHashMap."<init>":(Ljava/util/Map;)V
      82: putfield      #16                 // Field instanceParams:Ljava/util/Map;
      85: aload_0
      86: iload         7
      88: putfield      #9                  // Field updated:Z
      91: aload_0
      92: aload         8
      94: ifnonnull     101
      97: aconst_null
      98: goto          110
     101: new           #19                 // class java/util/concurrent/ConcurrentSkipListMap
     104: dup
     105: aload         8
     107: invokespecial #20                 // Method java/util/concurrent/ConcurrentSkipListMap."<init>":(Ljava/util/SortedMap;)V
     110: putfield      #21                 // Field subscribedServiceURLs:Ljava/util/concurrent/ConcurrentNavigableMap;
     113: aload_0
     114: aload         9
     116: ifnonnull     123
     119: aconst_null
     120: goto          132
     123: new           #19                 // class java/util/concurrent/ConcurrentSkipListMap
     126: dup
     127: aload         9
     129: invokespecial #20                 // Method java/util/concurrent/ConcurrentSkipListMap."<init>":(Ljava/util/SortedMap;)V
     132: putfield      #22                 // Field exportedServiceURLs:Ljava/util/concurrent/ConcurrentNavigableMap;
     135: aload_0
     136: aload         10
     138: putfield      #23                 // Field loader:Lorg/apache/dubbo/common/extension/ExtensionLoader;
     141: return

  public void init();
    Code:
       0: aload_0
       1: getfield      #8                  // Field initiated:Ljava/util/concurrent/atomic/AtomicBoolean;
       4: iconst_0
       5: iconst_1
       6: invokevirtual #24                 // Method java/util/concurrent/atomic/AtomicBoolean.compareAndSet:(ZZ)Z
       9: ifne          13
      12: return
      13: aload_0
      14: getfield      #14                 // Field services:Ljava/util/Map;
      17: invokestatic  #25                 // Method org/apache/dubbo/common/utils/CollectionUtils.isNotEmptyMap:(Ljava/util/Map;)Z
      20: ifeq          38
      23: aload_0
      24: getfield      #14                 // Field services:Ljava/util/Map;
      27: aload_0
      28: invokedynamic #26,  0             // InvokeDynamic #0:accept:(Lorg/apache/dubbo/metadata/MetadataInfo;)Ljava/util/function/BiConsumer;
      33: invokeinterface #27,  2           // InterfaceMethod java/util/Map.forEach:(Ljava/util/function/BiConsumer;)V
      38: return

  public synchronized void addService(org.apache.dubbo.common.URL);
    Code:
       0: aload_0
       1: getfield      #23                 // Field loader:Lorg/apache/dubbo/common/extension/ExtensionLoader;
       4: ifnonnull     20
       7: aload_0
       8: aload_1
       9: invokevirtual #28                 // Method org/apache/dubbo/common/URL.getOrDefaultApplicationModel:()Lorg/apache/dubbo/rpc/model/ApplicationModel;
      12: ldc           #29                 // class org/apache/dubbo/metadata/MetadataParamsFilter
      14: invokevirtual #30                 // Method org/apache/dubbo/rpc/model/ApplicationModel.getExtensionLoader:(Ljava/lang/Class;)Lorg/apache/dubbo/common/extension/ExtensionLoader;
      17: putfield      #23                 // Field loader:Lorg/apache/dubbo/common/extension/ExtensionLoader;
      20: aload_0
      21: getfield      #23                 // Field loader:Lorg/apache/dubbo/common/extension/ExtensionLoader;
      24: aload_1
      25: ldc           #31                 // String params-filter
      27: invokevirtual #32                 // Method org/apache/dubbo/common/extension/ExtensionLoader.getActivateExtension:(Lorg/apache/dubbo/common/URL;Ljava/lang/String;)Ljava/util/List;
      30: astore_2
      31: new           #33                 // class org/apache/dubbo/metadata/MetadataInfo$ServiceInfo
      34: dup
      35: aload_1
      36: aload_2
      37: invokespecial #34                 // Method org/apache/dubbo/metadata/MetadataInfo$ServiceInfo."<init>":(Lorg/apache/dubbo/common/URL;Ljava/util/List;)V
      40: astore_3
      41: aload_0
      42: getfield      #14                 // Field services:Ljava/util/Map;
      45: aload_3
      46: invokevirtual #35                 // Method org/apache/dubbo/metadata/MetadataInfo$ServiceInfo.getMatchKey:()Ljava/lang/String;
      49: aload_3
      50: invokeinterface #36,  3           // InterfaceMethod java/util/Map.put:(Ljava/lang/Object;Ljava/lang/Object;)Ljava/lang/Object;
      55: pop
      56: aload_0
      57: aload_1
      58: aload_2
      59: invokespecial #37                 // Method extractInstanceParams:(Lorg/apache/dubbo/common/URL;Ljava/util/List;)V
      62: aload_0
      63: getfield      #22                 // Field exportedServiceURLs:Ljava/util/concurrent/ConcurrentNavigableMap;
      66: ifnonnull     80
      69: aload_0
      70: new           #19                 // class java/util/concurrent/ConcurrentSkipListMap
      73: dup
      74: invokespecial #38                 // Method java/util/concurrent/ConcurrentSkipListMap."<init>":()V
      77: putfield      #22                 // Field exportedServiceURLs:Ljava/util/concurrent/ConcurrentNavigableMap;
      80: aload_0
      81: aload_0
      82: getfield      #22                 // Field exportedServiceURLs:Ljava/util/concurrent/ConcurrentNavigableMap;
      85: aload_1
      86: invokespecial #39                 // Method addURL:(Ljava/util/Map;Lorg/apache/dubbo/common/URL;)Z
      89: pop
      90: aload_0
      91: iconst_1
      92: putfield      #9                  // Field updated:Z
      95: return

  public synchronized void removeService(org.apache.dubbo.common.URL);
    Code:
       0: aload_1
       1: ifnonnull     5
       4: return
       5: aload_0
       6: getfield      #14                 // Field services:Ljava/util/Map;
       9: aload_1
      10: invokevirtual #40                 // Method org/apache/dubbo/common/URL.getProtocolServiceKey:()Ljava/lang/String;
      13: invokeinterface #41,  2           // InterfaceMethod java/util/Map.remove:(Ljava/lang/Object;)Ljava/lang/Object;
      18: pop
      19: aload_0
      20: getfield      #22                 // Field exportedServiceURLs:Ljava/util/concurrent/ConcurrentNavigableMap;
      23: ifnull        36
      26: aload_0
      27: aload_0
      28: getfield      #22                 // Field exportedServiceURLs:Ljava/util/concurrent/ConcurrentNavigableMap;
      31: aload_1
      32: invokevirtual #42                 // Method removeURL:(Ljava/util/Map;Lorg/apache/dubbo/common/URL;)Z
      35: pop
      36: aload_0
      37: iconst_1
      38: putfield      #9                  // Field updated:Z
      41: return

  public java.lang.String getRevision();
    Code:
       0: aload_0
       1: getfield      #11                 // Field revision:Ljava/lang/String;
       4: areturn

  public synchronized java.lang.String calAndGetRevision();
    Code:
       0: aload_0
       1: getfield      #11                 // Field revision:Ljava/lang/String;
       4: ifnull        19
       7: aload_0
       8: getfield      #9                  // Field updated:Z
      11: ifne          19
      14: aload_0
      15: getfield      #11                 // Field revision:Ljava/lang/String;
      18: areturn
      19: aload_0
      20: iconst_0
      21: putfield      #9                  // Field updated:Z
      24: aload_0
      25: getfield      #14                 // Field services:Ljava/util/Map;
      28: invokestatic  #43                 // Method org/apache/dubbo/common/utils/CollectionUtils.isEmptyMap:(Ljava/util/Map;)Z
      31: ifeq          43
      34: aload_0
      35: ldc           #44                 // String 0
      37: putfield      #11                 // Field revision:Ljava/lang/String;
      40: goto          212
      43: new           #45                 // class java/lang/StringBuilder
      46: dup
      47: invokespecial #46                 // Method java/lang/StringBuilder."<init>":()V
      50: astore_1
      51: aload_1
      52: aload_0
      53: getfield      #10                 // Field app:Ljava/lang/String;
      56: invokevirtual #47                 // Method java/lang/StringBuilder.append:(Ljava/lang/String;)Ljava/lang/StringBuilder;
      59: pop
      60: new           #48                 // class java/util/TreeMap
      63: dup
      64: aload_0
      65: getfield      #14                 // Field services:Ljava/util/Map;
      68: invokespecial #49                 // Method java/util/TreeMap."<init>":(Ljava/util/Map;)V
      71: invokevirtual #50                 // Method java/util/TreeMap.entrySet:()Ljava/util/Set;
      74: invokeinterface #51,  1           // InterfaceMethod java/util/Set.iterator:()Ljava/util/Iterator;
      79: astore_2
      80: aload_2
      81: invokeinterface #52,  1           // InterfaceMethod java/util/Iterator.hasNext:()Z
      86: ifeq          119
      89: aload_2
      90: invokeinterface #53,  1           // InterfaceMethod java/util/Iterator.next:()Ljava/lang/Object;
      95: checkcast     #54                 // class java/util/Map$Entry
      98: astore_3
      99: aload_1
     100: aload_3
     101: invokeinterface #55,  1           // InterfaceMethod java/util/Map$Entry.getValue:()Ljava/lang/Object;
     106: checkcast     #33                 // class org/apache/dubbo/metadata/MetadataInfo$ServiceInfo
     109: invokevirtual #56                 // Method org/apache/dubbo/metadata/MetadataInfo$ServiceInfo.toDescString:()Ljava/lang/String;
     112: invokevirtual #47                 // Method java/lang/StringBuilder.append:(Ljava/lang/String;)Ljava/lang/StringBuilder;
     115: pop
     116: goto          80
     119: aload_1
     120: invokevirtual #57                 // Method java/lang/StringBuilder.toString:()Ljava/lang/String;
     123: invokestatic  #58                 // Method org/apache/dubbo/metadata/RevisionResolver.calRevision:(Ljava/lang/String;)Ljava/lang/String;
     126: astore_2
     127: aload_0
     128: getfield      #11                 // Field revision:Ljava/lang/String;
     131: aload_2
     132: invokestatic  #59                 // Method org/apache/dubbo/common/utils/StringUtils.isEquals:(Ljava/lang/String;Ljava/lang/String;)Z
     135: ifne          212
     138: getstatic     #60                 // Field logger:Lorg/apache/dubbo/common/logger/Logger;
     141: invokeinterface #61,  1           // InterfaceMethod org/apache/dubbo/common/logger/Logger.isInfoEnabled:()Z
     146: ifeq          199
     149: getstatic     #60                 // Field logger:Lorg/apache/dubbo/common/logger/Logger;
     152: ldc           #62                 // String metadata revision changed: %s -> %s, app: %s, services: %d
     154: iconst_4
     155: anewarray     #63                 // class java/lang/Object
     158: dup
     159: iconst_0
     160: aload_0
     161: getfield      #11                 // Field revision:Ljava/lang/String;
     164: aastore
     165: dup
     166: iconst_1
     167: aload_2
     168: aastore
     169: dup
     170: iconst_2
     171: aload_0
     172: getfield      #10                 // Field app:Ljava/lang/String;
     175: aastore
     176: dup
     177: iconst_3
     178: aload_0
     179: getfield      #14                 // Field services:Ljava/util/Map;
     182: invokeinterface #64,  1           // InterfaceMethod java/util/Map.size:()I
     187: invokestatic  #65                 // Method java/lang/Integer.valueOf:(I)Ljava/lang/Integer;
     190: aastore
     191: invokestatic  #66                 // Method java/lang/String.format:(Ljava/lang/String;[Ljava/lang/Object;)Ljava/lang/String;
     194: invokeinterface #67,  2           // InterfaceMethod org/apache/dubbo/common/logger/Logger.info:(Ljava/lang/String;)V
     199: aload_0
     200: aload_2
     201: putfield      #11                 // Field revision:Ljava/lang/String;
     204: aload_0
     205: aload_0
     206: invokestatic  #68                 // Method org/apache/dubbo/common/utils/JsonUtils.toJson:(Ljava/lang/Object;)Ljava/lang/String;
     209: putfield      #69                 // Field rawMetadataInfo:Ljava/lang/String;
     212: aload_0
     213: getfield      #11                 // Field revision:Ljava/lang/String;
     216: areturn

  public void setRevision(java.lang.String);
    Code:
       0: aload_0
       1: aload_1
       2: putfield      #11                 // Field revision:Ljava/lang/String;
       5: return

  public java.lang.String getContent();
    Code:
       0: aload_0
       1: getfield      #69                 // Field rawMetadataInfo:Ljava/lang/String;
       4: areturn

  public java.lang.String getApp();
    Code:
       0: aload_0
       1: getfield      #10                 // Field app:Ljava/lang/String;
       4: areturn

  public void setApp(java.lang.String);
    Code:
       0: aload_0
       1: aload_1
       2: putfield      #10                 // Field app:Ljava/lang/String;
       5: return

  public java.util.Map<java.lang.String, org.apache.dubbo.metadata.MetadataInfo$ServiceInfo> getServices();
    Code:
       0: aload_0
       1: getfield      #14                 // Field services:Ljava/util/Map;
       4: areturn

  public org.apache.dubbo.metadata.MetadataInfo$ServiceInfo getServiceInfo(java.lang.String);
    Code:
       0: aload_0
       1: getfield      #14                 // Field services:Ljava/util/Map;
       4: aload_1
       5: invokeinterface #70,  2           // InterfaceMethod java/util/Map.get:(Ljava/lang/Object;)Ljava/lang/Object;
      10: checkcast     #33                 // class org/apache/dubbo/metadata/MetadataInfo$ServiceInfo
      13: areturn

  public org.apache.dubbo.metadata.MetadataInfo$ServiceInfo getNoProtocolServiceInfo(java.lang.String);
    Code:
       0: aload_0
       1: getfield      #71                 // Field subscribedServices:Ljava/util/Map;
       4: invokestatic  #43                 // Method org/apache/dubbo/common/utils/CollectionUtils.isEmptyMap:(Ljava/util/Map;)Z
       7: ifeq          12
      10: aconst_null
      11: areturn
      12: aload_0
      13: getfield      #71                 // Field subscribedServices:Ljava/util/Map;
      16: aload_1
      17: invokeinterface #70,  2           // InterfaceMethod java/util/Map.get:(Ljava/lang/Object;)Ljava/lang/Object;
      22: checkcast     #72                 // class java/util/Set
      25: astore_2
      26: aload_2
      27: invokestatic  #73                 // Method org/apache/dubbo/common/utils/CollectionUtils.isNotEmpty:(Ljava/util/Collection;)Z
      30: ifeq          48
      33: aload_2
      34: invokeinterface #51,  1           // InterfaceMethod java/util/Set.iterator:()Ljava/util/Iterator;
      39: invokeinterface #53,  1           // InterfaceMethod java/util/Iterator.next:()Ljava/lang/Object;
      44: checkcast     #33                 // class org/apache/dubbo/metadata/MetadataInfo$ServiceInfo
      47: areturn
      48: aconst_null
      49: areturn

  public org.apache.dubbo.metadata.MetadataInfo$ServiceInfo getValidServiceInfo(java.lang.String);
    Code:
       0: aload_0
       1: aload_1
       2: invokevirtual #74                 // Method getServiceInfo:(Ljava/lang/String;)Lorg/apache/dubbo/metadata/MetadataInfo$ServiceInfo;
       5: astore_2
       6: aload_2
       7: ifnonnull     22
      10: aload_0
      11: aload_1
      12: invokevirtual #75                 // Method getNoProtocolServiceInfo:(Ljava/lang/String;)Lorg/apache/dubbo/metadata/MetadataInfo$ServiceInfo;
      15: astore_2
      16: aload_2
      17: ifnonnull     22
      20: aconst_null
      21: areturn
      22: aload_2
      23: areturn

  public java.util.List<org.apache.dubbo.metadata.MetadataInfo$ServiceInfo> getMatchedServiceInfos(org.apache.dubbo.common.ProtocolServiceKey);
    Code:
       0: aload_0
       1: invokevirtual #76                 // Method getServices:()Ljava/util/Map;
       4: invokeinterface #77,  1           // InterfaceMethod java/util/Map.values:()Ljava/util/Collection;
       9: invokeinterface #78,  1           // InterfaceMethod java/util/Collection.stream:()Ljava/util/stream/Stream;
      14: aload_1
      15: invokedynamic #79,  0             // InvokeDynamic #1:test:(Lorg/apache/dubbo/common/ProtocolServiceKey;)Ljava/util/function/Predicate;
      20: invokeinterface #80,  2           // InterfaceMethod java/util/stream/Stream.filter:(Ljava/util/function/Predicate;)Ljava/util/stream/Stream;
      25: invokestatic  #81                 // Method java/util/stream/Collectors.toList:()Ljava/util/stream/Collector;
      28: invokeinterface #82,  2           // InterfaceMethod java/util/stream/Stream.collect:(Ljava/util/stream/Collector;)Ljava/lang/Object;
      33: checkcast     #83                 // class java/util/List
      36: areturn

  public java.util.Map<java.lang.String, java.lang.String> getExtendParams();
    Code:
       0: aload_0
       1: getfield      #15                 // Field extendParams:Ljava/util/Map;
       4: areturn

  public java.util.Map<java.lang.String, java.lang.String> getInstanceParams();
    Code:
       0: aload_0
       1: getfield      #16                 // Field instanceParams:Ljava/util/Map;
       4: areturn

  public java.lang.String getParameter(java.lang.String, java.lang.String);
    Code:
       0: aload_0
       1: aload_2
       2: invokevirtual #84                 // Method getValidServiceInfo:(Ljava/lang/String;)Lorg/apache/dubbo/metadata/MetadataInfo$ServiceInfo;
       5: astore_3
       6: aload_3
       7: ifnonnull     12
      10: aconst_null
      11: areturn
      12: aload_3
      13: aload_1
      14: invokevirtual #85                 // Method org/apache/dubbo/metadata/MetadataInfo$ServiceInfo.getParameter:(Ljava/lang/String;)Ljava/lang/String;
      17: areturn

  public java.util.Map<java.lang.String, java.lang.String> getParameters(java.lang.String);
    Code:
       0: aload_0
       1: aload_1
       2: invokevirtual #84                 // Method getValidServiceInfo:(Ljava/lang/String;)Lorg/apache/dubbo/metadata/MetadataInfo$ServiceInfo;
       5: astore_2
       6: aload_2
       7: ifnonnull     14
      10: invokestatic  #86                 // Method java/util/Collections.emptyMap:()Ljava/util/Map;
      13: areturn
      14: aload_2
      15: invokevirtual #87                 // Method org/apache/dubbo/metadata/MetadataInfo$ServiceInfo.getAllParams:()Ljava/util/Map;
      18: areturn

  public java.lang.String getServiceString(java.lang.String);
    Code:
       0: aload_1
       1: ifnonnull     6
       4: aconst_null
       5: areturn
       6: aload_0
       7: aload_1
       8: invokevirtual #84                 // Method getValidServiceInfo:(Ljava/lang/String;)Lorg/apache/dubbo/metadata/MetadataInfo$ServiceInfo;
      11: astore_2
      12: aload_2
      13: ifnonnull     18
      16: aconst_null
      17: areturn
      18: aload_2
      19: invokevirtual #88                 // Method org/apache/dubbo/metadata/MetadataInfo$ServiceInfo.toFullString:()Ljava/lang/String;
      22: areturn

  public synchronized void addSubscribedURL(org.apache.dubbo.common.URL);
    Code:
       0: aload_0
       1: getfield      #21                 // Field subscribedServiceURLs:Ljava/util/concurrent/ConcurrentNavigableMap;
       4: ifnonnull     18
       7: aload_0
       8: new           #19                 // class java/util/concurrent/ConcurrentSkipListMap
      11: dup
      12: invokespecial #38                 // Method java/util/concurrent/ConcurrentSkipListMap."<init>":()V
      15: putfield      #21                 // Field subscribedServiceURLs:Ljava/util/concurrent/ConcurrentNavigableMap;
      18: aload_0
      19: aload_0
      20: getfield      #21                 // Field subscribedServiceURLs:Ljava/util/concurrent/ConcurrentNavigableMap;
      23: aload_1
      24: invokespecial #39                 // Method addURL:(Ljava/util/Map;Lorg/apache/dubbo/common/URL;)Z
      27: pop
      28: return

  public boolean removeSubscribedURL(org.apache.dubbo.common.URL);
    Code:
       0: aload_0
       1: getfield      #21                 // Field subscribedServiceURLs:Ljava/util/concurrent/ConcurrentNavigableMap;
       4: ifnonnull     9
       7: iconst_1
       8: ireturn
       9: aload_0
      10: aload_0
      11: getfield      #21                 // Field subscribedServiceURLs:Ljava/util/concurrent/ConcurrentNavigableMap;
      14: aload_1
      15: invokevirtual #42                 // Method removeURL:(Ljava/util/Map;Lorg/apache/dubbo/common/URL;)Z
      18: ireturn

  public java.util.concurrent.ConcurrentNavigableMap<java.lang.String, java.util.SortedSet<org.apache.dubbo.common.URL>> getSubscribedServiceURLs();
    Code:
       0: aload_0
       1: getfield      #21                 // Field subscribedServiceURLs:Ljava/util/concurrent/ConcurrentNavigableMap;
       4: areturn

  public java.util.concurrent.ConcurrentNavigableMap<java.lang.String, java.util.SortedSet<org.apache.dubbo.common.URL>> getExportedServiceURLs();
    Code:
       0: aload_0
       1: getfield      #22                 // Field exportedServiceURLs:Ljava/util/concurrent/ConcurrentNavigableMap;
       4: areturn

  public java.util.Set<org.apache.dubbo.common.URL> collectExportedURLSet();
    Code:
       0: aload_0
       1: getfield      #22                 // Field exportedServiceURLs:Ljava/util/concurrent/ConcurrentNavigableMap;
       4: ifnonnull     11
       7: invokestatic  #89                 // Method java/util/Collections.emptySet:()Ljava/util/Set;
      10: areturn
      11: aload_0
      12: getfield      #22                 // Field exportedServiceURLs:Ljava/util/concurrent/ConcurrentNavigableMap;
      15: invokeinterface #90,  1           // InterfaceMethod java/util/concurrent/ConcurrentNavigableMap.values:()Ljava/util/Collection;
      20: invokeinterface #78,  1           // InterfaceMethod java/util/Collection.stream:()Ljava/util/stream/Stream;
      25: invokedynamic #91,  0             // InvokeDynamic #2:test:()Ljava/util/function/Predicate;
      30: invokeinterface #80,  2           // InterfaceMethod java/util/stream/Stream.filter:(Ljava/util/function/Predicate;)Ljava/util/stream/Stream;
      35: invokedynamic #92,  0             // InvokeDynamic #3:apply:()Ljava/util/function/Function;
      40: invokeinterface #93,  2           // InterfaceMethod java/util/stream/Stream.flatMap:(Ljava/util/function/Function;)Ljava/util/stream/Stream;
      45: invokestatic  #94                 // Method java/util/stream/Collectors.toSet:()Ljava/util/stream/Collector;
      48: invokeinterface #82,  2           // InterfaceMethod java/util/stream/Stream.collect:(Ljava/util/stream/Collector;)Ljava/lang/Object;
      53: checkcast     #72                 // class java/util/Set
      56: areturn

  private boolean addURL(java.util.Map<java.lang.String, java.util.SortedSet<org.apache.dubbo.common.URL>>, org.apache.dubbo.common.URL);
    Code:
       0: aload_1
       1: aload_2
       2: invokevirtual #95                 // Method org/apache/dubbo/common/URL.getServiceKey:()Ljava/lang/String;
       5: aload_0
       6: invokedynamic #96,  0             // InvokeDynamic #4:apply:(Lorg/apache/dubbo/metadata/MetadataInfo;)Ljava/util/function/Function;
      11: invokeinterface #97,  3           // InterfaceMethod java/util/Map.computeIfAbsent:(Ljava/lang/Object;Ljava/util/function/Function;)Ljava/lang/Object;
      16: checkcast     #98                 // class java/util/SortedSet
      19: astore_3
      20: aload_3
      21: aload_2
      22: invokeinterface #99,  2           // InterfaceMethod java/util/SortedSet.add:(Ljava/lang/Object;)Z
      27: ireturn

  boolean removeURL(java.util.Map<java.lang.String, java.util.SortedSet<org.apache.dubbo.common.URL>>, org.apache.dubbo.common.URL);
    Code:
       0: aload_2
       1: invokevirtual #95                 // Method org/apache/dubbo/common/URL.getServiceKey:()Ljava/lang/String;
       4: astore_3
       5: aload_1
       6: aload_3
       7: aconst_null
       8: invokeinterface #100,  3          // InterfaceMethod java/util/Map.getOrDefault:(Ljava/lang/Object;Ljava/lang/Object;)Ljava/lang/Object;
      13: checkcast     #98                 // class java/util/SortedSet
      16: astore        4
      18: aload         4
      20: ifnonnull     25
      23: iconst_1
      24: ireturn
      25: aload         4
      27: aload_2
      28: invokeinterface #101,  2          // InterfaceMethod java/util/SortedSet.remove:(Ljava/lang/Object;)Z
      33: istore        5
      35: aload         4
      37: invokeinterface #102,  1          // InterfaceMethod java/util/SortedSet.isEmpty:()Z
      42: ifeq          53
      45: aload_1
      46: aload_3
      47: invokeinterface #41,  2           // InterfaceMethod java/util/Map.remove:(Ljava/lang/Object;)Ljava/lang/Object;
      52: pop
      53: iload         5
      55: ireturn

  private java.util.SortedSet<org.apache.dubbo.common.URL> newSortedURLs(java.lang.String);
    Code:
       0: new           #103                // class java/util/TreeSet
       3: dup
       4: getstatic     #104                // Field org/apache/dubbo/metadata/MetadataInfo$URLComparator.INSTANCE:Lorg/apache/dubbo/metadata/MetadataInfo$URLComparator;
       7: invokespecial #105                // Method java/util/TreeSet."<init>":(Ljava/util/Comparator;)V
      10: areturn

  public int hashCode();
    Code:
       0: iconst_2
       1: anewarray     #63                 // class java/lang/Object
       4: dup
       5: iconst_0
       6: aload_0
       7: getfield      #10                 // Field app:Ljava/lang/String;
      10: aastore
      11: dup
      12: iconst_1
      13: aload_0
      14: getfield      #14                 // Field services:Ljava/util/Map;
      17: aastore
      18: invokestatic  #106                // Method java/util/Objects.hash:([Ljava/lang/Object;)I
      21: ireturn

  public boolean equals(java.lang.Object);
    Code:
       0: aload_1
       1: aload_0
       2: if_acmpne     7
       5: iconst_1
       6: ireturn
       7: aload_1
       8: instanceof    #107                // class org/apache/dubbo/metadata/MetadataInfo
      11: ifne          16
      14: iconst_0
      15: ireturn
      16: aload_1
      17: checkcast     #107                // class org/apache/dubbo/metadata/MetadataInfo
      20: astore_2
      21: aload_0
      22: getfield      #10                 // Field app:Ljava/lang/String;
      25: aload_2
      26: invokevirtual #108                // Method getApp:()Ljava/lang/String;
      29: invokestatic  #109                // Method java/util/Objects.equals:(Ljava/lang/Object;Ljava/lang/Object;)Z
      32: ifeq          76
      35: aload_0
      36: getfield      #14                 // Field services:Ljava/util/Map;
      39: ifnonnull     49
      42: aload_2
      43: getfield      #14                 // Field services:Ljava/util/Map;
      46: ifnull        72
      49: aload_0
      50: getfield      #14                 // Field services:Ljava/util/Map;
      53: ifnull        76
      56: aload_0
      57: getfield      #14                 // Field services:Ljava/util/Map;
      60: aload_2
      61: getfield      #14                 // Field services:Ljava/util/Map;
      64: invokeinterface #110,  2          // InterfaceMethod java/util/Map.equals:(Ljava/lang/Object;)Z
      69: ifeq          76
      72: iconst_1
      73: goto          77
      76: iconst_0
      77: ireturn

  private void extractInstanceParams(org.apache.dubbo.common.URL, java.util.List<org.apache.dubbo.metadata.MetadataParamsFilter>);
    Code:
       0: aload_2
       1: invokestatic  #111                // Method org/apache/dubbo/common/utils/CollectionUtils.isEmpty:(Ljava/util/Collection;)Z
       4: ifeq          8
       7: return
       8: aload_2
       9: invokeinterface #112,  1          // InterfaceMethod java/util/List.size:()I
      14: iconst_1
      15: if_icmpne     50
      18: aload_2
      19: iconst_0
      20: invokeinterface #113,  2          // InterfaceMethod java/util/List.get:(I)Ljava/lang/Object;
      25: checkcast     #29                 // class org/apache/dubbo/metadata/MetadataParamsFilter
      28: astore        5
      30: aload         5
      32: invokeinterface #114,  1          // InterfaceMethod org/apache/dubbo/metadata/MetadataParamsFilter.instanceParamsIncluded:()[Ljava/lang/String;
      37: astore_3
      38: aload         5
      40: invokeinterface #115,  1          // InterfaceMethod org/apache/dubbo/metadata/MetadataParamsFilter.instanceParamsExcluded:()[Ljava/lang/String;
      45: astore        4
      47: goto          114
      50: new           #116                // class java/util/HashSet
      53: dup
      54: invokespecial #117                // Method java/util/HashSet."<init>":()V
      57: astore        5
      59: new           #116                // class java/util/HashSet
      62: dup
      63: invokespecial #117                // Method java/util/HashSet."<init>":()V
      66: astore        6
      68: aload_2
      69: aload         5
      71: aload         6
      73: invokedynamic #118,  0            // InvokeDynamic #5:accept:(Ljava/util/Set;Ljava/util/Set;)Ljava/util/function/Consumer;
      78: invokeinterface #119,  2          // InterfaceMethod java/util/List.forEach:(Ljava/util/function/Consumer;)V
      83: aload         5
      85: iconst_0
      86: anewarray     #120                // class java/lang/String
      89: invokeinterface #121,  2          // InterfaceMethod java/util/Set.toArray:([Ljava/lang/Object;)[Ljava/lang/Object;
      94: checkcast     #122                // class "[Ljava/lang/String;"
      97: astore_3
      98: aload         6
     100: iconst_0
     101: anewarray     #120                // class java/lang/String
     104: invokeinterface #121,  2          // InterfaceMethod java/util/Set.toArray:([Ljava/lang/Object;)[Ljava/lang/Object;
     109: checkcast     #122                // class "[Ljava/lang/String;"
     112: astore        4
     114: new           #123                // class java/util/HashMap
     117: dup
     118: invokespecial #124                // Method java/util/HashMap."<init>":()V
     121: astore        5
     123: aload_3
     124: invokestatic  #125                // Method org/apache/dubbo/common/utils/ArrayUtils.isNotEmpty:([Ljava/lang/Object;)Z
     127: ifeq          189
     130: aload_3
     131: astore        6
     133: aload         6
     135: arraylength
     136: istore        7
     138: iconst_0
     139: istore        8
     141: iload         8
     143: iload         7
     145: if_icmpge     186
     148: aload         6
     150: iload         8
     152: aaload
     153: astore        9
     155: aload_1
     156: aload         9
     158: invokevirtual #126                // Method org/apache/dubbo/common/URL.getParameter:(Ljava/lang/String;)Ljava/lang/String;
     161: astore        10
     163: aload         10
     165: ifnull        180
     168: aload         5
     170: aload         9
     172: aload         10
     174: invokeinterface #36,  3           // InterfaceMethod java/util/Map.put:(Ljava/lang/Object;Ljava/lang/Object;)Ljava/lang/Object;
     179: pop
     180: iinc          8, 1
     183: goto          141
     186: goto          250
     189: aload         4
     191: invokestatic  #125                // Method org/apache/dubbo/common/utils/ArrayUtils.isNotEmpty:([Ljava/lang/Object;)Z
     194: ifeq          250
     197: aload         5
     199: aload_1
     200: invokevirtual #127                // Method org/apache/dubbo/common/URL.getParameters:()Ljava/util/Map;
     203: invokeinterface #128,  2          // InterfaceMethod java/util/Map.putAll:(Ljava/util/Map;)V
     208: aload         4
     210: astore        6
     212: aload         6
     214: arraylength
     215: istore        7
     217: iconst_0
     218: istore        8
     220: iload         8
     222: iload         7
     224: if_icmpge     250
     227: aload         6
     229: iload         8
     231: aaload
     232: astore        9
     234: aload         5
     236: aload         9
     238: invokeinterface #41,  2           // InterfaceMethod java/util/Map.remove:(Ljava/lang/Object;)Ljava/lang/Object;
     243: pop
     244: iinc          8, 1
     247: goto          220
     250: aload         5
     252: aload_0
     253: invokedynamic #129,  0            // InvokeDynamic #6:accept:(Lorg/apache/dubbo/metadata/MetadataInfo;)Ljava/util/function/BiConsumer;
     258: invokeinterface #27,  2           // InterfaceMethod java/util/Map.forEach:(Ljava/util/function/BiConsumer;)V
     263: return

  public java.lang.String toString();
    Code:
       0: new           #45                 // class java/lang/StringBuilder
       3: dup
       4: invokespecial #46                 // Method java/lang/StringBuilder."<init>":()V
       7: ldc           #130                // String metadata{app=\'
       9: invokevirtual #47                 // Method java/lang/StringBuilder.append:(Ljava/lang/String;)Ljava/lang/StringBuilder;
      12: aload_0
      13: getfield      #10                 // Field app:Ljava/lang/String;
      16: invokevirtual #47                 // Method java/lang/StringBuilder.append:(Ljava/lang/String;)Ljava/lang/StringBuilder;
      19: ldc           #131                // String \',revision=\'
      21: invokevirtual #47                 // Method java/lang/StringBuilder.append:(Ljava/lang/String;)Ljava/lang/StringBuilder;
      24: aload_0
      25: getfield      #11                 // Field revision:Ljava/lang/String;
      28: invokevirtual #47                 // Method java/lang/StringBuilder.append:(Ljava/lang/String;)Ljava/lang/StringBuilder;
      31: ldc           #132                // String \',size=
      33: invokevirtual #47                 // Method java/lang/StringBuilder.append:(Ljava/lang/String;)Ljava/lang/StringBuilder;
      36: aload_0
      37: getfield      #14                 // Field services:Ljava/util/Map;
      40: ifnonnull     47
      43: iconst_0
      44: goto          56
      47: aload_0
      48: getfield      #14                 // Field services:Ljava/util/Map;
      51: invokeinterface #64,  1           // InterfaceMethod java/util/Map.size:()I
      56: invokevirtual #133                // Method java/lang/StringBuilder.append:(I)Ljava/lang/StringBuilder;
      59: ldc           #134                // String ,services=
      61: invokevirtual #47                 // Method java/lang/StringBuilder.append:(Ljava/lang/String;)Ljava/lang/StringBuilder;
      64: aload_0
      65: aload_0
      66: getfield      #14                 // Field services:Ljava/util/Map;
      69: invokespecial #135                // Method getSimplifiedServices:(Ljava/util/Map;)Ljava/lang/String;
      72: invokevirtual #47                 // Method java/lang/StringBuilder.append:(Ljava/lang/String;)Ljava/lang/StringBuilder;
      75: ldc           #136                // String }
      77: invokevirtual #47                 // Method java/lang/StringBuilder.append:(Ljava/lang/String;)Ljava/lang/StringBuilder;
      80: invokevirtual #57                 // Method java/lang/StringBuilder.toString:()Ljava/lang/String;
      83: areturn

  public java.lang.String toFullString();
    Code:
       0: new           #45                 // class java/lang/StringBuilder
       3: dup
       4: invokespecial #46                 // Method java/lang/StringBuilder."<init>":()V
       7: ldc           #130                // String metadata{app=\'
       9: invokevirtual #47                 // Method java/lang/StringBuilder.append:(Ljava/lang/String;)Ljava/lang/StringBuilder;
      12: aload_0
      13: getfield      #10                 // Field app:Ljava/lang/String;
      16: invokevirtual #47                 // Method java/lang/StringBuilder.append:(Ljava/lang/String;)Ljava/lang/StringBuilder;
      19: ldc           #131                // String \',revision=\'
      21: invokevirtual #47                 // Method java/lang/StringBuilder.append:(Ljava/lang/String;)Ljava/lang/StringBuilder;
      24: aload_0
      25: getfield      #11                 // Field revision:Ljava/lang/String;
      28: invokevirtual #47                 // Method java/lang/StringBuilder.append:(Ljava/lang/String;)Ljava/lang/StringBuilder;
      31: ldc           #137                // String \',services=
      33: invokevirtual #47                 // Method java/lang/StringBuilder.append:(Ljava/lang/String;)Ljava/lang/StringBuilder;
      36: aload_0
      37: getfield      #14                 // Field services:Ljava/util/Map;
      40: invokevirtual #138                // Method java/lang/StringBuilder.append:(Ljava/lang/Object;)Ljava/lang/StringBuilder;
      43: ldc           #136                // String }
      45: invokevirtual #47                 // Method java/lang/StringBuilder.append:(Ljava/lang/String;)Ljava/lang/StringBuilder;
      48: invokevirtual #57                 // Method java/lang/StringBuilder.toString:()Ljava/lang/String;
      51: areturn

  private java.lang.String getSimplifiedServices(java.util.Map<java.lang.String, org.apache.dubbo.metadata.MetadataInfo$ServiceInfo>);
    Code:
       0: aload_1
       1: ifnonnull     7
       4: ldc           #139                // String []
       6: areturn
       7: aload_1
       8: invokeinterface #140,  1          // InterfaceMethod java/util/Map.keySet:()Ljava/util/Set;
      13: invokevirtual #141                // Method java/lang/Object.toString:()Ljava/lang/String;
      16: areturn

  public synchronized org.apache.dubbo.metadata.MetadataInfo clone();
    Code:
       0: new           #107                // class org/apache/dubbo/metadata/MetadataInfo
       3: dup
       4: aload_0
       5: getfield      #10                 // Field app:Ljava/lang/String;
       8: aload_0
       9: getfield      #11                 // Field revision:Ljava/lang/String;
      12: aload_0
      13: getfield      #14                 // Field services:Ljava/util/Map;
      16: aload_0
      17: getfield      #8                  // Field initiated:Ljava/util/concurrent/atomic/AtomicBoolean;
      20: aload_0
      21: getfield      #15                 // Field extendParams:Ljava/util/Map;
      24: aload_0
      25: getfield      #16                 // Field instanceParams:Ljava/util/Map;
      28: aload_0
      29: getfield      #9                  // Field updated:Z
      32: aload_0
      33: getfield      #21                 // Field subscribedServiceURLs:Ljava/util/concurrent/ConcurrentNavigableMap;
      36: aload_0
      37: getfield      #22                 // Field exportedServiceURLs:Ljava/util/concurrent/ConcurrentNavigableMap;
      40: aload_0
      41: getfield      #23                 // Field loader:Lorg/apache/dubbo/common/extension/ExtensionLoader;
      44: invokespecial #142                // Method "<init>":(Ljava/lang/String;Ljava/lang/String;Ljava/util/Map;Ljava/util/concurrent/atomic/AtomicBoolean;Ljava/util/Map;Ljava/util/Map;ZLjava/util/concurrent/ConcurrentNavigableMap;Ljava/util/concurrent/ConcurrentNavigableMap;Lorg/apache/dubbo/common/extension/ExtensionLoader;)V
      47: areturn

  private java.lang.Object readResolve();
    Code:
       0: new           #107                // class org/apache/dubbo/metadata/MetadataInfo
       3: dup
       4: aload_0
       5: getfield      #10                 // Field app:Ljava/lang/String;
       8: aload_0
       9: getfield      #11                 // Field revision:Ljava/lang/String;
      12: aload_0
      13: getfield      #14                 // Field services:Ljava/util/Map;
      16: invokespecial #4                  // Method "<init>":(Ljava/lang/String;Ljava/lang/String;Ljava/util/Map;)V
      19: areturn

  public java.lang.Object clone() throws java.lang.CloneNotSupportedException;
    Code:
       0: aload_0
       1: invokevirtual #143                // Method clone:()Lorg/apache/dubbo/metadata/MetadataInfo;
       4: areturn

  private void lambda$extractInstanceParams$4(java.lang.String, java.lang.String);
    Code:
       0: aload_0
       1: getfield      #16                 // Field instanceParams:Ljava/util/Map;
       4: aload_1
       5: aload_2
       6: invokeinterface #36,  3           // InterfaceMethod java/util/Map.put:(Ljava/lang/Object;Ljava/lang/Object;)Ljava/lang/Object;
      11: checkcast     #120                // class java/lang/String
      14: astore_3
      15: ldc           #144                // String timestamp
      17: aload_1
      18: invokevirtual #145                // Method java/lang/String.equals:(Ljava/lang/Object;)Z
      21: ifne          61
      24: aload_3
      25: ifnull        61
      28: aload_3
      29: aload_2
      30: invokevirtual #145                // Method java/lang/String.equals:(Ljava/lang/Object;)Z
      33: ifne          61
      36: new           #146                // class java/lang/IllegalStateException
      39: dup
      40: ldc           #147                // String Inconsistent instance metadata found in different services: %s, %s
      42: iconst_2
      43: anewarray     #63                 // class java/lang/Object
      46: dup
      47: iconst_0
      48: aload_3
      49: aastore
      50: dup
      51: iconst_1
      52: aload_2
      53: aastore
      54: invokestatic  #66                 // Method java/lang/String.format:(Ljava/lang/String;[Ljava/lang/Object;)Ljava/lang/String;
      57: invokespecial #148                // Method java/lang/IllegalStateException."<init>":(Ljava/lang/String;)V
      60: athrow
      61: return

  private static void lambda$extractInstanceParams$3(java.util.Set, java.util.Set, org.apache.dubbo.metadata.MetadataParamsFilter);
    Code:
       0: aload_2
       1: invokeinterface #114,  1          // InterfaceMethod org/apache/dubbo/metadata/MetadataParamsFilter.instanceParamsIncluded:()[Ljava/lang/String;
       6: invokestatic  #125                // Method org/apache/dubbo/common/utils/ArrayUtils.isNotEmpty:([Ljava/lang/Object;)Z
       9: ifeq          28
      12: aload_0
      13: aload_2
      14: invokeinterface #114,  1          // InterfaceMethod org/apache/dubbo/metadata/MetadataParamsFilter.instanceParamsIncluded:()[Ljava/lang/String;
      19: invokestatic  #149                // Method java/util/Arrays.asList:([Ljava/lang/Object;)Ljava/util/List;
      22: invokeinterface #150,  2          // InterfaceMethod java/util/Set.addAll:(Ljava/util/Collection;)Z
      27: pop
      28: aload_2
      29: invokeinterface #115,  1          // InterfaceMethod org/apache/dubbo/metadata/MetadataParamsFilter.instanceParamsExcluded:()[Ljava/lang/String;
      34: invokestatic  #125                // Method org/apache/dubbo/common/utils/ArrayUtils.isNotEmpty:([Ljava/lang/Object;)Z
      37: ifeq          56
      40: aload_1
      41: aload_2
      42: invokeinterface #115,  1          // InterfaceMethod org/apache/dubbo/metadata/MetadataParamsFilter.instanceParamsExcluded:()[Ljava/lang/String;
      47: invokestatic  #149                // Method java/util/Arrays.asList:([Ljava/lang/Object;)Ljava/util/List;
      50: invokeinterface #150,  2          // InterfaceMethod java/util/Set.addAll:(Ljava/util/Collection;)Z
      55: pop
      56: return

  private static boolean lambda$getMatchedServiceInfos$2(org.apache.dubbo.common.ProtocolServiceKey, org.apache.dubbo.metadata.MetadataInfo$ServiceInfo);
    Code:
       0: aload_1
       1: aload_0
       2: invokevirtual #151                // Method org/apache/dubbo/metadata/MetadataInfo$ServiceInfo.matchProtocolServiceKey:(Lorg/apache/dubbo/common/ProtocolServiceKey;)Z
       5: ireturn

  private void lambda$init$1(java.lang.String, org.apache.dubbo.metadata.MetadataInfo$ServiceInfo);
    Code:
       0: aload_2
       1: invokevirtual #152                // Method org/apache/dubbo/metadata/MetadataInfo$ServiceInfo.init:()V
       4: aload_0
       5: getfield      #71                 // Field subscribedServices:Ljava/util/Map;
       8: ifnonnull     22
      11: aload_0
      12: new           #123                // class java/util/HashMap
      15: dup
      16: invokespecial #124                // Method java/util/HashMap."<init>":()V
      19: putfield      #71                 // Field subscribedServices:Ljava/util/Map;
      22: aload_0
      23: getfield      #71                 // Field subscribedServices:Ljava/util/Map;
      26: aload_2
      27: invokevirtual #153                // Method org/apache/dubbo/metadata/MetadataInfo$ServiceInfo.getServiceKey:()Ljava/lang/String;
      30: invokedynamic #154,  0            // InvokeDynamic #7:apply:()Ljava/util/function/Function;
      35: invokeinterface #97,  3           // InterfaceMethod java/util/Map.computeIfAbsent:(Ljava/lang/Object;Ljava/util/function/Function;)Ljava/lang/Object;
      40: checkcast     #72                 // class java/util/Set
      43: astore_3
      44: aload_3
      45: aload_2
      46: invokeinterface #155,  2          // InterfaceMethod java/util/Set.add:(Ljava/lang/Object;)Z
      51: pop
      52: return

  private static java.util.Set lambda$null$0(java.lang.String);
    Code:
       0: new           #116                // class java/util/HashSet
       3: dup
       4: invokespecial #117                // Method java/util/HashSet."<init>":()V
       7: areturn

  static {};
    Code:
       0: new           #107                // class org/apache/dubbo/metadata/MetadataInfo
       3: dup
       4: invokespecial #156                // Method "<init>":()V
       7: putstatic     #157                // Field EMPTY:Lorg/apache/dubbo/metadata/MetadataInfo;
      10: ldc           #107                // class org/apache/dubbo/metadata/MetadataInfo
      12: invokestatic  #158                // Method org/apache/dubbo/common/logger/LoggerFactory.getLogger:(Ljava/lang/Class;)Lorg/apache/dubbo/common/logger/Logger;
      15: putstatic     #60                 // Field logger:Lorg/apache/dubbo/common/logger/Logger;
      18: return
}
