Compiled from "MetadataInfo.java"
public class org.apache.dubbo.metadata.MetadataInfo$ServiceInfo implements java.io.Serializable {
  private java.lang.String name;

  private java.lang.String group;

  private java.lang.String version;

  private java.lang.String protocol;

  private int port;

  private java.lang.String path;

  private java.util.Map<java.lang.String, java.lang.String> params;

  private volatile transient java.util.Map<java.lang.String, java.lang.String> consumerParams;

  private volatile transient java.util.Map<java.lang.String, java.util.Map<java.lang.String, java.lang.String>> methodParams;

  private volatile transient java.util.Map<java.lang.String, java.util.Map<java.lang.String, java.lang.String>> consumerMethodParams;

  private volatile transient java.util.Map<java.lang.String, java.lang.Number> numbers;

  private volatile transient java.util.Map<java.lang.String, java.util.Map<java.lang.String, java.lang.Number>> methodNumbers;

  private volatile transient java.lang.String serviceKey;

  private volatile transient java.lang.String matchKey;

  private volatile transient org.apache.dubbo.common.ProtocolServiceKey protocolServiceKey;

  private transient org.apache.dubbo.common.URL url;

  public org.apache.dubbo.metadata.MetadataInfo$ServiceInfo();
    Code:
       0: aload_0
       1: invokespecial #2                  // Method java/lang/Object."<init>":()V
       4: aload_0
       5: iconst_m1
       6: putfield      #3                  // Field port:I
       9: return

  public org.apache.dubbo.metadata.MetadataInfo$ServiceInfo(org.apache.dubbo.common.URL, java.util.List<org.apache.dubbo.metadata.MetadataParamsFilter>);
    Code:
       0: aload_0
       1: aload_1
       2: invokevirtual #4                  // Method org/apache/dubbo/common/URL.getServiceInterface:()Ljava/lang/String;
       5: aload_1
       6: invokevirtual #5                  // Method org/apache/dubbo/common/URL.getGroup:()Ljava/lang/String;
       9: aload_1
      10: invokevirtual #6                  // Method org/apache/dubbo/common/URL.getVersion:()Ljava/lang/String;
      13: aload_1
      14: invokevirtual #7                  // Method org/apache/dubbo/common/URL.getProtocol:()Ljava/lang/String;
      17: aload_1
      18: invokevirtual #8                  // Method org/apache/dubbo/common/URL.getPort:()I
      21: aload_1
      22: invokevirtual #9                  // Method org/apache/dubbo/common/URL.getPath:()Ljava/lang/String;
      25: aconst_null
      26: invokespecial #10                 // Method "<init>":(Ljava/lang/String;Ljava/lang/String;Ljava/lang/String;Ljava/lang/String;ILjava/lang/String;Ljava/util/Map;)V
      29: aload_0
      30: aload_1
      31: putfield      #11                 // Field url:Lorg/apache/dubbo/common/URL;
      34: aload_0
      35: aload_1
      36: aload_2
      37: invokespecial #12                 // Method extractServiceParams:(Lorg/apache/dubbo/common/URL;Ljava/util/List;)Ljava/util/Map;
      40: astore_3
      41: aload_0
      42: aload_3
      43: invokestatic  #13                 // Method org/apache/dubbo/common/url/component/URLParam.initMethodParameters:(Ljava/util/Map;)Ljava/util/Map;
      46: putfield      #14                 // Field methodParams:Ljava/util/Map;
      49: aload_0
      50: aload_0
      51: getfield      #15                 // Field consumerParams:Ljava/util/Map;
      54: invokestatic  #13                 // Method org/apache/dubbo/common/url/component/URLParam.initMethodParameters:(Ljava/util/Map;)Ljava/util/Map;
      57: putfield      #16                 // Field consumerMethodParams:Ljava/util/Map;
      60: return

  public org.apache.dubbo.metadata.MetadataInfo$ServiceInfo(java.lang.String, java.lang.String, java.lang.String, java.lang.String, int, java.lang.String, java.util.Map<java.lang.String, java.lang.String>);
    Code:
       0: aload_0
       1: invokespecial #2                  // Method java/lang/Object."<init>":()V
       4: aload_0
       5: iconst_m1
       6: putfield      #3                  // Field port:I
       9: aload_0
      10: aload_1
      11: putfield      #17                 // Field name:Ljava/lang/String;
      14: aload_0
      15: aload_2
      16: putfield      #18                 // Field group:Ljava/lang/String;
      19: aload_0
      20: aload_3
      21: putfield      #19                 // Field version:Ljava/lang/String;
      24: aload_0
      25: aload         4
      27: putfield      #20                 // Field protocol:Ljava/lang/String;
      30: aload_0
      31: iload         5
      33: putfield      #3                  // Field port:I
      36: aload_0
      37: aload         6
      39: putfield      #21                 // Field path:Ljava/lang/String;
      42: aload_0
      43: aload         7
      45: ifnonnull     58
      48: new           #22                 // class java/util/concurrent/ConcurrentHashMap
      51: dup
      52: invokespecial #23                 // Method java/util/concurrent/ConcurrentHashMap."<init>":()V
      55: goto          60
      58: aload         7
      60: putfield      #24                 // Field params:Ljava/util/Map;
      63: aload_0
      64: aload_0
      65: aload_1
      66: aload_2
      67: aload_3
      68: invokespecial #25                 // Method buildServiceKey:(Ljava/lang/String;Ljava/lang/String;Ljava/lang/String;)Ljava/lang/String;
      71: putfield      #26                 // Field serviceKey:Ljava/lang/String;
      74: aload_0
      75: aload_0
      76: invokespecial #27                 // Method buildMatchKey:()Ljava/lang/String;
      79: putfield      #28                 // Field matchKey:Ljava/lang/String;
      82: return

  private java.util.Map<java.lang.String, java.lang.String> extractServiceParams(org.apache.dubbo.common.URL, java.util.List<org.apache.dubbo.metadata.MetadataParamsFilter>);
    Code:
       0: new           #29                 // class java/util/HashMap
       3: dup
       4: invokespecial #30                 // Method java/util/HashMap."<init>":()V
       7: astore_3
       8: aload_2
       9: invokestatic  #31                 // Method org/apache/dubbo/common/utils/CollectionUtils.isEmpty:(Ljava/util/Collection;)Z
      12: ifeq          32
      15: aload_3
      16: aload_1
      17: invokevirtual #32                 // Method org/apache/dubbo/common/URL.getParameters:()Ljava/util/Map;
      20: invokeinterface #33,  2           // InterfaceMethod java/util/Map.putAll:(Ljava/util/Map;)V
      25: aload_0
      26: aload_3
      27: putfield      #24                 // Field params:Ljava/util/Map;
      30: aload_3
      31: areturn
      32: aload_2
      33: invokeinterface #34,  1           // InterfaceMethod java/util/List.size:()I
      38: iconst_1
      39: if_icmpne     79
      42: aload_2
      43: iconst_0
      44: invokeinterface #35,  2           // InterfaceMethod java/util/List.get:(I)Ljava/lang/Object;
      49: checkcast     #36                 // class org/apache/dubbo/metadata/MetadataParamsFilter
      52: invokeinterface #37,  1           // InterfaceMethod org/apache/dubbo/metadata/MetadataParamsFilter.serviceParamsIncluded:()[Ljava/lang/String;
      57: astore        4
      59: aload_2
      60: iconst_0
      61: invokeinterface #35,  2           // InterfaceMethod java/util/List.get:(I)Ljava/lang/Object;
      66: checkcast     #36                 // class org/apache/dubbo/metadata/MetadataParamsFilter
      69: invokeinterface #38,  1           // InterfaceMethod org/apache/dubbo/metadata/MetadataParamsFilter.serviceParamsExcluded:()[Ljava/lang/String;
      74: astore        5
      76: goto          224
      79: new           #39                 // class java/util/HashSet
      82: dup
      83: invokespecial #40                 // Method java/util/HashSet."<init>":()V
      86: astore        6
      88: new           #39                 // class java/util/HashSet
      91: dup
      92: invokespecial #40                 // Method java/util/HashSet."<init>":()V
      95: astore        7
      97: aload_2
      98: invokeinterface #41,  1           // InterfaceMethod java/util/List.iterator:()Ljava/util/Iterator;
     103: astore        8
     105: aload         8
     107: invokeinterface #42,  1           // InterfaceMethod java/util/Iterator.hasNext:()Z
     112: ifeq          192
     115: aload         8
     117: invokeinterface #43,  1           // InterfaceMethod java/util/Iterator.next:()Ljava/lang/Object;
     122: checkcast     #36                 // class org/apache/dubbo/metadata/MetadataParamsFilter
     125: astore        9
     127: aload         9
     129: invokeinterface #37,  1           // InterfaceMethod org/apache/dubbo/metadata/MetadataParamsFilter.serviceParamsIncluded:()[Ljava/lang/String;
     134: invokestatic  #44                 // Method org/apache/dubbo/common/utils/ArrayUtils.isNotEmpty:([Ljava/lang/Object;)Z
     137: ifeq          158
     140: aload         6
     142: aload         9
     144: invokeinterface #37,  1           // InterfaceMethod org/apache/dubbo/metadata/MetadataParamsFilter.serviceParamsIncluded:()[Ljava/lang/String;
     149: invokestatic  #45                 // Method java/util/Arrays.asList:([Ljava/lang/Object;)Ljava/util/List;
     152: invokeinterface #46,  2           // InterfaceMethod java/util/Set.addAll:(Ljava/util/Collection;)Z
     157: pop
     158: aload         9
     160: invokeinterface #38,  1           // InterfaceMethod org/apache/dubbo/metadata/MetadataParamsFilter.serviceParamsExcluded:()[Ljava/lang/String;
     165: invokestatic  #44                 // Method org/apache/dubbo/common/utils/ArrayUtils.isNotEmpty:([Ljava/lang/Object;)Z
     168: ifeq          189
     171: aload         7
     173: aload         9
     175: invokeinterface #38,  1           // InterfaceMethod org/apache/dubbo/metadata/MetadataParamsFilter.serviceParamsExcluded:()[Ljava/lang/String;
     180: invokestatic  #45                 // Method java/util/Arrays.asList:([Ljava/lang/Object;)Ljava/util/List;
     183: invokeinterface #46,  2           // InterfaceMethod java/util/Set.addAll:(Ljava/util/Collection;)Z
     188: pop
     189: goto          105
     192: aload         6
     194: iconst_0
     195: anewarray     #47                 // class java/lang/String
     198: invokeinterface #48,  2           // InterfaceMethod java/util/Set.toArray:([Ljava/lang/Object;)[Ljava/lang/Object;
     203: checkcast     #49                 // class "[Ljava/lang/String;"
     206: astore        4
     208: aload         7
     210: iconst_0
     211: anewarray     #47                 // class java/lang/String
     214: invokeinterface #48,  2           // InterfaceMethod java/util/Set.toArray:([Ljava/lang/Object;)[Ljava/lang/Object;
     219: checkcast     #49                 // class "[Ljava/lang/String;"
     222: astore        5
     224: aload         4
     226: invokestatic  #44                 // Method org/apache/dubbo/common/utils/ArrayUtils.isNotEmpty:([Ljava/lang/Object;)Z
     229: ifeq          327
     232: aload_1
     233: ldc           #50                 // String methods
     235: aconst_null
     236: checkcast     #49                 // class "[Ljava/lang/String;"
     239: invokevirtual #51                 // Method org/apache/dubbo/common/URL.getParameter:(Ljava/lang/String;[Ljava/lang/String;)[Ljava/lang/String;
     242: astore        6
     244: aload         4
     246: astore        7
     248: aload         7
     250: arraylength
     251: istore        8
     253: iconst_0
     254: istore        9
     256: iload         9
     258: iload         8
     260: if_icmpge     324
     263: aload         7
     265: iload         9
     267: aaload
     268: astore        10
     270: aload_1
     271: aload         10
     273: invokevirtual #52                 // Method org/apache/dubbo/common/URL.getParameter:(Ljava/lang/String;)Ljava/lang/String;
     276: astore        11
     278: aload         11
     280: invokestatic  #53                 // Method org/apache/dubbo/common/utils/StringUtils.isNotEmpty:(Ljava/lang/String;)Z
     283: ifeq          308
     286: aload_3
     287: aload         10
     289: invokeinterface #54,  2           // InterfaceMethod java/util/Map.get:(Ljava/lang/Object;)Ljava/lang/Object;
     294: ifnonnull     308
     297: aload_3
     298: aload         10
     300: aload         11
     302: invokeinterface #55,  3           // InterfaceMethod java/util/Map.put:(Ljava/lang/Object;Ljava/lang/Object;)Ljava/lang/Object;
     307: pop
     308: aload_0
     309: aload_1
     310: aload_3
     311: aload         6
     313: aload         10
     315: invokespecial #56                 // Method appendMethodParams:(Lorg/apache/dubbo/common/URL;Ljava/util/Map;[Ljava/lang/String;Ljava/lang/String;)V
     318: iinc          9, 1
     321: goto          256
     324: goto          495
     327: aload         5
     329: invokestatic  #44                 // Method org/apache/dubbo/common/utils/ArrayUtils.isNotEmpty:([Ljava/lang/Object;)Z
     332: ifeq          495
     335: aload_1
     336: invokevirtual #32                 // Method org/apache/dubbo/common/URL.getParameters:()Ljava/util/Map;
     339: invokeinterface #57,  1           // InterfaceMethod java/util/Map.entrySet:()Ljava/util/Set;
     344: invokeinterface #58,  1           // InterfaceMethod java/util/Set.iterator:()Ljava/util/Iterator;
     349: astore        6
     351: aload         6
     353: invokeinterface #42,  1           // InterfaceMethod java/util/Iterator.hasNext:()Z
     358: ifeq          495
     361: aload         6
     363: invokeinterface #43,  1           // InterfaceMethod java/util/Iterator.next:()Ljava/lang/Object;
     368: checkcast     #59                 // class java/util/Map$Entry
     371: astore        7
     373: aload         7
     375: invokeinterface #60,  1           // InterfaceMethod java/util/Map$Entry.getKey:()Ljava/lang/Object;
     380: checkcast     #47                 // class java/lang/String
     383: astore        8
     385: aload         7
     387: invokeinterface #61,  1           // InterfaceMethod java/util/Map$Entry.getValue:()Ljava/lang/Object;
     392: checkcast     #47                 // class java/lang/String
     395: astore        9
     397: iconst_1
     398: istore        10
     400: aload         5
     402: astore        11
     404: aload         11
     406: arraylength
     407: istore        12
     409: iconst_0
     410: istore        13
     412: iload         13
     414: iload         12
     416: if_icmpge     476
     419: aload         11
     421: iload         13
     423: aaload
     424: astore        14
     426: aload         8
     428: aload         14
     430: invokevirtual #62                 // Method java/lang/String.equalsIgnoreCase:(Ljava/lang/String;)Z
     433: ifne          464
     436: aload         8
     438: new           #63                 // class java/lang/StringBuilder
     441: dup
     442: invokespecial #64                 // Method java/lang/StringBuilder."<init>":()V
     445: ldc           #65                 // String .
     447: invokevirtual #66                 // Method java/lang/StringBuilder.append:(Ljava/lang/String;)Ljava/lang/StringBuilder;
     450: aload         14
     452: invokevirtual #66                 // Method java/lang/StringBuilder.append:(Ljava/lang/String;)Ljava/lang/StringBuilder;
     455: invokevirtual #67                 // Method java/lang/StringBuilder.toString:()Ljava/lang/String;
     458: invokevirtual #68                 // Method java/lang/String.contains:(Ljava/lang/CharSequence;)Z
     461: ifeq          470
     464: iconst_0
     465: istore        10
     467: goto          476
     470: iinc          13, 1
     473: goto          412
     476: iload         10
     478: ifeq          492
     481: aload_3
     482: aload         8
     484: aload         9
     486: invokeinterface #55,  3           // InterfaceMethod java/util/Map.put:(Ljava/lang/Object;Ljava/lang/Object;)Ljava/lang/Object;
     491: pop
     492: goto          351
     495: aload_0
     496: aload_3
     497: putfield      #24                 // Field params:Ljava/util/Map;
     500: aload_3
     501: areturn

  private void appendMethodParams(org.apache.dubbo.common.URL, java.util.Map<java.lang.String, java.lang.String>, java.lang.String[], java.lang.String);
    Code:
       0: aload_3
       1: ifnull        87
       4: aload_3
       5: astore        5
       7: aload         5
       9: arraylength
      10: istore        6
      12: iconst_0
      13: istore        7
      15: iload         7
      17: iload         6
      19: if_icmpge     87
      22: aload         5
      24: iload         7
      26: aaload
      27: astore        8
      29: aload_1
      30: aload         8
      32: aload         4
      34: invokevirtual #69                 // Method org/apache/dubbo/common/URL.getMethodParameterStrict:(Ljava/lang/String;Ljava/lang/String;)Ljava/lang/String;
      37: astore        9
      39: aload         9
      41: invokestatic  #53                 // Method org/apache/dubbo/common/utils/StringUtils.isNotEmpty:(Ljava/lang/String;)Z
      44: ifeq          81
      47: aload_2
      48: new           #63                 // class java/lang/StringBuilder
      51: dup
      52: invokespecial #64                 // Method java/lang/StringBuilder."<init>":()V
      55: aload         8
      57: invokevirtual #66                 // Method java/lang/StringBuilder.append:(Ljava/lang/String;)Ljava/lang/StringBuilder;
      60: ldc           #65                 // String .
      62: invokevirtual #66                 // Method java/lang/StringBuilder.append:(Ljava/lang/String;)Ljava/lang/StringBuilder;
      65: aload         4
      67: invokevirtual #66                 // Method java/lang/StringBuilder.append:(Ljava/lang/String;)Ljava/lang/StringBuilder;
      70: invokevirtual #67                 // Method java/lang/StringBuilder.toString:()Ljava/lang/String;
      73: aload         9
      75: invokeinterface #55,  3           // InterfaceMethod java/util/Map.put:(Ljava/lang/Object;Ljava/lang/Object;)Ljava/lang/Object;
      80: pop
      81: iinc          7, 1
      84: goto          15
      87: return

  protected void init();
    Code:
       0: aload_0
       1: invokespecial #27                 // Method buildMatchKey:()Ljava/lang/String;
       4: pop
       5: aload_0
       6: aload_0
       7: getfield      #17                 // Field name:Ljava/lang/String;
      10: aload_0
      11: getfield      #18                 // Field group:Ljava/lang/String;
      14: aload_0
      15: getfield      #19                 // Field version:Ljava/lang/String;
      18: invokespecial #25                 // Method buildServiceKey:(Ljava/lang/String;Ljava/lang/String;Ljava/lang/String;)Ljava/lang/String;
      21: pop
      22: aload_0
      23: aload_0
      24: getfield      #24                 // Field params:Ljava/util/Map;
      27: invokestatic  #13                 // Method org/apache/dubbo/common/url/component/URLParam.initMethodParameters:(Ljava/util/Map;)Ljava/util/Map;
      30: putfield      #14                 // Field methodParams:Ljava/util/Map;
      33: return

  public java.lang.String getMatchKey();
    Code:
       0: aload_0
       1: getfield      #28                 // Field matchKey:Ljava/lang/String;
       4: ifnull        12
       7: aload_0
       8: getfield      #28                 // Field matchKey:Ljava/lang/String;
      11: areturn
      12: aload_0
      13: invokespecial #27                 // Method buildMatchKey:()Ljava/lang/String;
      16: pop
      17: aload_0
      18: getfield      #28                 // Field matchKey:Ljava/lang/String;
      21: areturn

  private java.lang.String buildMatchKey();
    Code:
       0: aload_0
       1: aload_0
       2: invokevirtual #70                 // Method getServiceKey:()Ljava/lang/String;
       5: putfield      #28                 // Field matchKey:Ljava/lang/String;
       8: aload_0
       9: getfield      #20                 // Field protocol:Ljava/lang/String;
      12: invokestatic  #53                 // Method org/apache/dubbo/common/utils/StringUtils.isNotEmpty:(Ljava/lang/String;)Z
      15: ifeq          51
      18: aload_0
      19: new           #63                 // class java/lang/StringBuilder
      22: dup
      23: invokespecial #64                 // Method java/lang/StringBuilder."<init>":()V
      26: aload_0
      27: invokevirtual #70                 // Method getServiceKey:()Ljava/lang/String;
      30: invokevirtual #66                 // Method java/lang/StringBuilder.append:(Ljava/lang/String;)Ljava/lang/StringBuilder;
      33: ldc           #71                 // String :
      35: invokevirtual #66                 // Method java/lang/StringBuilder.append:(Ljava/lang/String;)Ljava/lang/StringBuilder;
      38: aload_0
      39: getfield      #20                 // Field protocol:Ljava/lang/String;
      42: invokevirtual #66                 // Method java/lang/StringBuilder.append:(Ljava/lang/String;)Ljava/lang/StringBuilder;
      45: invokevirtual #67                 // Method java/lang/StringBuilder.toString:()Ljava/lang/String;
      48: putfield      #28                 // Field matchKey:Ljava/lang/String;
      51: aload_0
      52: getfield      #28                 // Field matchKey:Ljava/lang/String;
      55: areturn

  public boolean matchProtocolServiceKey(org.apache.dubbo.common.ProtocolServiceKey);
    Code:
       0: aload_1
       1: aload_0
       2: invokevirtual #72                 // Method getProtocolServiceKey:()Lorg/apache/dubbo/common/ProtocolServiceKey;
       5: invokestatic  #73                 // Method org/apache/dubbo/common/ProtocolServiceKey$Matcher.isMatch:(Lorg/apache/dubbo/common/ProtocolServiceKey;Lorg/apache/dubbo/common/ProtocolServiceKey;)Z
       8: ireturn

  public org.apache.dubbo.common.ProtocolServiceKey getProtocolServiceKey();
    Code:
       0: aload_0
       1: getfield      #74                 // Field protocolServiceKey:Lorg/apache/dubbo/common/ProtocolServiceKey;
       4: ifnull        12
       7: aload_0
       8: getfield      #74                 // Field protocolServiceKey:Lorg/apache/dubbo/common/ProtocolServiceKey;
      11: areturn
      12: aload_0
      13: new           #75                 // class org/apache/dubbo/common/ProtocolServiceKey
      16: dup
      17: aload_0
      18: getfield      #17                 // Field name:Ljava/lang/String;
      21: aload_0
      22: getfield      #19                 // Field version:Ljava/lang/String;
      25: aload_0
      26: getfield      #18                 // Field group:Ljava/lang/String;
      29: aload_0
      30: getfield      #20                 // Field protocol:Ljava/lang/String;
      33: invokespecial #76                 // Method org/apache/dubbo/common/ProtocolServiceKey."<init>":(Ljava/lang/String;Ljava/lang/String;Ljava/lang/String;Ljava/lang/String;)V
      36: putfield      #74                 // Field protocolServiceKey:Lorg/apache/dubbo/common/ProtocolServiceKey;
      39: aload_0
      40: getfield      #74                 // Field protocolServiceKey:Lorg/apache/dubbo/common/ProtocolServiceKey;
      43: areturn

  private java.lang.String buildServiceKey(java.lang.String, java.lang.String, java.lang.String);
    Code:
       0: aload_0
       1: aload_1
       2: aload_2
       3: aload_3
       4: invokestatic  #77                 // Method org/apache/dubbo/common/URL.buildKey:(Ljava/lang/String;Ljava/lang/String;Ljava/lang/String;)Ljava/lang/String;
       7: putfield      #26                 // Field serviceKey:Ljava/lang/String;
      10: aload_0
      11: getfield      #26                 // Field serviceKey:Ljava/lang/String;
      14: areturn

  public java.lang.String getServiceKey();
    Code:
       0: aload_0
       1: getfield      #26                 // Field serviceKey:Ljava/lang/String;
       4: ifnull        12
       7: aload_0
       8: getfield      #26                 // Field serviceKey:Ljava/lang/String;
      11: areturn
      12: aload_0
      13: aload_0
      14: getfield      #17                 // Field name:Ljava/lang/String;
      17: aload_0
      18: getfield      #18                 // Field group:Ljava/lang/String;
      21: aload_0
      22: getfield      #19                 // Field version:Ljava/lang/String;
      25: invokespecial #25                 // Method buildServiceKey:(Ljava/lang/String;Ljava/lang/String;Ljava/lang/String;)Ljava/lang/String;
      28: pop
      29: aload_0
      30: getfield      #26                 // Field serviceKey:Ljava/lang/String;
      33: areturn

  public java.lang.String getName();
    Code:
       0: aload_0
       1: getfield      #17                 // Field name:Ljava/lang/String;
       4: areturn

  public void setName(java.lang.String);
    Code:
       0: aload_0
       1: aload_1
       2: putfield      #17                 // Field name:Ljava/lang/String;
       5: return

  public java.lang.String getGroup();
    Code:
       0: aload_0
       1: getfield      #18                 // Field group:Ljava/lang/String;
       4: areturn

  public void setGroup(java.lang.String);
    Code:
       0: aload_0
       1: aload_1
       2: putfield      #18                 // Field group:Ljava/lang/String;
       5: return

  public java.lang.String getVersion();
    Code:
       0: aload_0
       1: getfield      #19                 // Field version:Ljava/lang/String;
       4: areturn

  public void setVersion(java.lang.String);
    Code:
       0: aload_0
       1: aload_1
       2: putfield      #19                 // Field version:Ljava/lang/String;
       5: return

  public java.lang.String getPath();
    Code:
       0: aload_0
       1: getfield      #21                 // Field path:Ljava/lang/String;
       4: areturn

  public void setPath(java.lang.String);
    Code:
       0: aload_0
       1: aload_1
       2: putfield      #21                 // Field path:Ljava/lang/String;
       5: return

  public java.lang.String getProtocol();
    Code:
       0: aload_0
       1: getfield      #20                 // Field protocol:Ljava/lang/String;
       4: areturn

  public void setProtocol(java.lang.String);
    Code:
       0: aload_0
       1: aload_1
       2: putfield      #20                 // Field protocol:Ljava/lang/String;
       5: return

  public int getPort();
    Code:
       0: aload_0
       1: getfield      #3                  // Field port:I
       4: ireturn

  public void setPort(int);
    Code:
       0: aload_0
       1: iload_1
       2: putfield      #3                  // Field port:I
       5: return

  public java.util.Map<java.lang.String, java.lang.String> getParams();
    Code:
       0: aload_0
       1: getfield      #24                 // Field params:Ljava/util/Map;
       4: ifnonnull     11
       7: invokestatic  #78                 // Method java/util/Collections.emptyMap:()Ljava/util/Map;
      10: areturn
      11: aload_0
      12: getfield      #24                 // Field params:Ljava/util/Map;
      15: areturn

  public void setParams(java.util.Map<java.lang.String, java.lang.String>);
    Code:
       0: aload_0
       1: aload_1
       2: putfield      #24                 // Field params:Ljava/util/Map;
       5: return

  public java.util.Map<java.lang.String, java.lang.String> getAllParams();
    Code:
       0: aload_0
       1: getfield      #15                 // Field consumerParams:Ljava/util/Map;
       4: ifnull        63
       7: new           #29                 // class java/util/HashMap
      10: dup
      11: aload_0
      12: getfield      #24                 // Field params:Ljava/util/Map;
      15: invokeinterface #79,  1           // InterfaceMethod java/util/Map.size:()I
      20: aload_0
      21: getfield      #15                 // Field consumerParams:Ljava/util/Map;
      24: invokeinterface #79,  1           // InterfaceMethod java/util/Map.size:()I
      29: iadd
      30: i2f
      31: ldc           #80                 // float 0.75f
      33: fdiv
      34: fconst_1
      35: fadd
      36: f2i
      37: invokespecial #81                 // Method java/util/HashMap."<init>":(I)V
      40: astore_1
      41: aload_1
      42: aload_0
      43: getfield      #24                 // Field params:Ljava/util/Map;
      46: invokeinterface #33,  2           // InterfaceMethod java/util/Map.putAll:(Ljava/util/Map;)V
      51: aload_1
      52: aload_0
      53: getfield      #15                 // Field consumerParams:Ljava/util/Map;
      56: invokeinterface #33,  2           // InterfaceMethod java/util/Map.putAll:(Ljava/util/Map;)V
      61: aload_1
      62: areturn
      63: aload_0
      64: getfield      #24                 // Field params:Ljava/util/Map;
      67: areturn

  public java.lang.String getParameter(java.lang.String);
    Code:
       0: aload_0
       1: getfield      #15                 // Field consumerParams:Ljava/util/Map;
       4: ifnull        27
       7: aload_0
       8: getfield      #15                 // Field consumerParams:Ljava/util/Map;
      11: aload_1
      12: invokeinterface #54,  2           // InterfaceMethod java/util/Map.get:(Ljava/lang/Object;)Ljava/lang/Object;
      17: checkcast     #47                 // class java/lang/String
      20: astore_2
      21: aload_2
      22: ifnull        27
      25: aload_2
      26: areturn
      27: aload_0
      28: getfield      #24                 // Field params:Ljava/util/Map;
      31: aload_1
      32: invokeinterface #54,  2           // InterfaceMethod java/util/Map.get:(Ljava/lang/Object;)Ljava/lang/Object;
      37: checkcast     #47                 // class java/lang/String
      40: areturn

  public java.lang.String getMethodParameter(java.lang.String, java.lang.String, java.lang.String);
    Code:
       0: aload_0
       1: aload_1
       2: aload_2
       3: aload_0
       4: getfield      #16                 // Field consumerMethodParams:Ljava/util/Map;
       7: invokespecial #82                 // Method getMethodParameter:(Ljava/lang/String;Ljava/lang/String;Ljava/util/Map;)Ljava/lang/String;
      10: astore        4
      12: aload         4
      14: ifnull        20
      17: aload         4
      19: areturn
      20: aload_0
      21: aload_1
      22: aload_2
      23: aload_0
      24: getfield      #14                 // Field methodParams:Ljava/util/Map;
      27: invokespecial #82                 // Method getMethodParameter:(Ljava/lang/String;Ljava/lang/String;Ljava/util/Map;)Ljava/lang/String;
      30: astore        4
      32: aload         4
      34: ifnonnull     41
      37: aload_3
      38: goto          43
      41: aload         4
      43: areturn

  private java.lang.String getMethodParameter(java.lang.String, java.lang.String, java.util.Map<java.lang.String, java.util.Map<java.lang.String, java.lang.String>>);
    Code:
       0: aconst_null
       1: astore        4
       3: aload_3
       4: ifnonnull     10
       7: aload         4
       9: areturn
      10: aload_3
      11: aload_1
      12: invokeinterface #54,  2           // InterfaceMethod java/util/Map.get:(Ljava/lang/Object;)Ljava/lang/Object;
      17: checkcast     #83                 // class java/util/Map
      20: astore        5
      22: aload         5
      24: ifnull        40
      27: aload         5
      29: aload_2
      30: invokeinterface #54,  2           // InterfaceMethod java/util/Map.get:(Ljava/lang/Object;)Ljava/lang/Object;
      35: checkcast     #47                 // class java/lang/String
      38: astore        4
      40: aload         4
      42: areturn

  public boolean hasMethodParameter(java.lang.String, java.lang.String);
    Code:
       0: aload_0
       1: aload_1
       2: aload_2
       3: aconst_null
       4: checkcast     #47                 // class java/lang/String
       7: invokevirtual #84                 // Method getMethodParameter:(Ljava/lang/String;Ljava/lang/String;Ljava/lang/String;)Ljava/lang/String;
      10: astore_3
      11: aload_3
      12: invokestatic  #53                 // Method org/apache/dubbo/common/utils/StringUtils.isNotEmpty:(Ljava/lang/String;)Z
      15: ireturn

  public boolean hasMethodParameter(java.lang.String);
    Code:
       0: aload_0
       1: getfield      #16                 // Field consumerMethodParams:Ljava/util/Map;
       4: ifnull        20
       7: aload_0
       8: getfield      #16                 // Field consumerMethodParams:Ljava/util/Map;
      11: aload_1
      12: invokeinterface #85,  2           // InterfaceMethod java/util/Map.containsKey:(Ljava/lang/Object;)Z
      17: ifne          40
      20: aload_0
      21: getfield      #14                 // Field methodParams:Ljava/util/Map;
      24: ifnull        44
      27: aload_0
      28: getfield      #14                 // Field methodParams:Ljava/util/Map;
      31: aload_1
      32: invokeinterface #85,  2           // InterfaceMethod java/util/Map.containsKey:(Ljava/lang/Object;)Z
      37: ifeq          44
      40: iconst_1
      41: goto          45
      44: iconst_0
      45: ireturn

  public java.lang.String toDescString();
    Code:
       0: new           #63                 // class java/lang/StringBuilder
       3: dup
       4: invokespecial #64                 // Method java/lang/StringBuilder."<init>":()V
       7: aload_0
       8: invokevirtual #86                 // Method getMatchKey:()Ljava/lang/String;
      11: invokevirtual #66                 // Method java/lang/StringBuilder.append:(Ljava/lang/String;)Ljava/lang/StringBuilder;
      14: aload_0
      15: getfield      #3                  // Field port:I
      18: invokevirtual #87                 // Method java/lang/StringBuilder.append:(I)Ljava/lang/StringBuilder;
      21: aload_0
      22: getfield      #21                 // Field path:Ljava/lang/String;
      25: invokevirtual #66                 // Method java/lang/StringBuilder.append:(Ljava/lang/String;)Ljava/lang/StringBuilder;
      28: new           #88                 // class java/util/TreeMap
      31: dup
      32: aload_0
      33: invokevirtual #89                 // Method getParams:()Ljava/util/Map;
      36: invokespecial #90                 // Method java/util/TreeMap."<init>":(Ljava/util/Map;)V
      39: invokevirtual #91                 // Method java/lang/StringBuilder.append:(Ljava/lang/Object;)Ljava/lang/StringBuilder;
      42: invokevirtual #67                 // Method java/lang/StringBuilder.toString:()Ljava/lang/String;
      45: areturn

  public void addParameter(java.lang.String, java.lang.String);
    Code:
       0: aload_0
       1: getfield      #15                 // Field consumerParams:Ljava/util/Map;
       4: ifnull        19
       7: aload_0
       8: getfield      #15                 // Field consumerParams:Ljava/util/Map;
      11: aload_1
      12: aload_2
      13: invokeinterface #55,  3           // InterfaceMethod java/util/Map.put:(Ljava/lang/Object;Ljava/lang/Object;)Ljava/lang/Object;
      18: pop
      19: aload_0
      20: aload_0
      21: getfield      #15                 // Field consumerParams:Ljava/util/Map;
      24: invokestatic  #13                 // Method org/apache/dubbo/common/url/component/URLParam.initMethodParameters:(Ljava/util/Map;)Ljava/util/Map;
      27: putfield      #16                 // Field consumerMethodParams:Ljava/util/Map;
      30: return

  public void addParameterIfAbsent(java.lang.String, java.lang.String);
    Code:
       0: aload_0
       1: getfield      #15                 // Field consumerParams:Ljava/util/Map;
       4: ifnull        19
       7: aload_0
       8: getfield      #15                 // Field consumerParams:Ljava/util/Map;
      11: aload_1
      12: aload_2
      13: invokeinterface #92,  3           // InterfaceMethod java/util/Map.putIfAbsent:(Ljava/lang/Object;Ljava/lang/Object;)Ljava/lang/Object;
      18: pop
      19: aload_0
      20: aload_0
      21: getfield      #15                 // Field consumerParams:Ljava/util/Map;
      24: invokestatic  #13                 // Method org/apache/dubbo/common/url/component/URLParam.initMethodParameters:(Ljava/util/Map;)Ljava/util/Map;
      27: putfield      #16                 // Field consumerMethodParams:Ljava/util/Map;
      30: return

  public void addConsumerParams(java.util.Map<java.lang.String, java.lang.String>);
    Code:
       0: aload_0
       1: getfield      #15                 // Field consumerParams:Ljava/util/Map;
       4: ifnonnull     30
       7: aload_0
       8: new           #22                 // class java/util/concurrent/ConcurrentHashMap
      11: dup
      12: aload_1
      13: invokespecial #93                 // Method java/util/concurrent/ConcurrentHashMap."<init>":(Ljava/util/Map;)V
      16: putfield      #15                 // Field consumerParams:Ljava/util/Map;
      19: aload_0
      20: aload_0
      21: getfield      #15                 // Field consumerParams:Ljava/util/Map;
      24: invokestatic  #13                 // Method org/apache/dubbo/common/url/component/URLParam.initMethodParameters:(Ljava/util/Map;)Ljava/util/Map;
      27: putfield      #16                 // Field consumerMethodParams:Ljava/util/Map;
      30: return

  public java.util.Map<java.lang.String, java.lang.Number> getNumbers();
    Code:
       0: aload_0
       1: getfield      #94                 // Field numbers:Ljava/util/Map;
       4: ifnonnull     18
       7: aload_0
       8: new           #22                 // class java/util/concurrent/ConcurrentHashMap
      11: dup
      12: invokespecial #23                 // Method java/util/concurrent/ConcurrentHashMap."<init>":()V
      15: putfield      #94                 // Field numbers:Ljava/util/Map;
      18: aload_0
      19: getfield      #94                 // Field numbers:Ljava/util/Map;
      22: areturn

  public java.util.Map<java.lang.String, java.util.Map<java.lang.String, java.lang.Number>> getMethodNumbers();
    Code:
       0: aload_0
       1: getfield      #95                 // Field methodNumbers:Ljava/util/Map;
       4: ifnonnull     18
       7: aload_0
       8: new           #22                 // class java/util/concurrent/ConcurrentHashMap
      11: dup
      12: invokespecial #23                 // Method java/util/concurrent/ConcurrentHashMap."<init>":()V
      15: putfield      #95                 // Field methodNumbers:Ljava/util/Map;
      18: aload_0
      19: getfield      #95                 // Field methodNumbers:Ljava/util/Map;
      22: areturn

  public org.apache.dubbo.common.URL getUrl();
    Code:
       0: aload_0
       1: getfield      #11                 // Field url:Lorg/apache/dubbo/common/URL;
       4: areturn

  public boolean equals(java.lang.Object);
    Code:
       0: aload_1
       1: ifnonnull     6
       4: iconst_0
       5: ireturn
       6: aload_1
       7: instanceof    #96                 // class org/apache/dubbo/metadata/MetadataInfo$ServiceInfo
      10: ifne          15
      13: iconst_0
      14: ireturn
      15: aload_1
      16: checkcast     #96                 // class org/apache/dubbo/metadata/MetadataInfo$ServiceInfo
      19: astore_2
      20: aload_0
      21: invokevirtual #97                 // Method getVersion:()Ljava/lang/String;
      24: aload_2
      25: invokevirtual #97                 // Method getVersion:()Ljava/lang/String;
      28: invokestatic  #98                 // Method java/util/Objects.equals:(Ljava/lang/Object;Ljava/lang/Object;)Z
      31: ifeq          116
      34: aload_0
      35: invokevirtual #99                 // Method getGroup:()Ljava/lang/String;
      38: aload_2
      39: invokevirtual #99                 // Method getGroup:()Ljava/lang/String;
      42: invokestatic  #98                 // Method java/util/Objects.equals:(Ljava/lang/Object;Ljava/lang/Object;)Z
      45: ifeq          116
      48: aload_0
      49: invokevirtual #100                // Method getName:()Ljava/lang/String;
      52: aload_2
      53: invokevirtual #100                // Method getName:()Ljava/lang/String;
      56: invokestatic  #98                 // Method java/util/Objects.equals:(Ljava/lang/Object;Ljava/lang/Object;)Z
      59: ifeq          116
      62: aload_0
      63: invokevirtual #101                // Method getProtocol:()Ljava/lang/String;
      66: aload_2
      67: invokevirtual #101                // Method getProtocol:()Ljava/lang/String;
      70: invokestatic  #98                 // Method java/util/Objects.equals:(Ljava/lang/Object;Ljava/lang/Object;)Z
      73: ifeq          116
      76: aload_0
      77: invokevirtual #102                // Method getPort:()I
      80: invokestatic  #103                // Method java/lang/Integer.valueOf:(I)Ljava/lang/Integer;
      83: aload_2
      84: invokevirtual #102                // Method getPort:()I
      87: invokestatic  #103                // Method java/lang/Integer.valueOf:(I)Ljava/lang/Integer;
      90: invokestatic  #98                 // Method java/util/Objects.equals:(Ljava/lang/Object;Ljava/lang/Object;)Z
      93: ifeq          116
      96: aload_0
      97: invokevirtual #89                 // Method getParams:()Ljava/util/Map;
     100: aload_2
     101: invokevirtual #89                 // Method getParams:()Ljava/util/Map;
     104: invokeinterface #104,  2          // InterfaceMethod java/util/Map.equals:(Ljava/lang/Object;)Z
     109: ifeq          116
     112: iconst_1
     113: goto          117
     116: iconst_0
     117: ireturn

  public int hashCode();
    Code:
       0: bipush        6
       2: anewarray     #105                // class java/lang/Object
       5: dup
       6: iconst_0
       7: aload_0
       8: invokevirtual #97                 // Method getVersion:()Ljava/lang/String;
      11: aastore
      12: dup
      13: iconst_1
      14: aload_0
      15: invokevirtual #99                 // Method getGroup:()Ljava/lang/String;
      18: aastore
      19: dup
      20: iconst_2
      21: aload_0
      22: invokevirtual #100                // Method getName:()Ljava/lang/String;
      25: aastore
      26: dup
      27: iconst_3
      28: aload_0
      29: invokevirtual #101                // Method getProtocol:()Ljava/lang/String;
      32: aastore
      33: dup
      34: iconst_4
      35: aload_0
      36: invokevirtual #102                // Method getPort:()I
      39: invokestatic  #103                // Method java/lang/Integer.valueOf:(I)Ljava/lang/Integer;
      42: aastore
      43: dup
      44: iconst_5
      45: aload_0
      46: invokevirtual #89                 // Method getParams:()Ljava/util/Map;
      49: aastore
      50: invokestatic  #106                // Method java/util/Objects.hash:([Ljava/lang/Object;)I
      53: ireturn

  public java.lang.String toString();
    Code:
       0: aload_0
       1: invokevirtual #86                 // Method getMatchKey:()Ljava/lang/String;
       4: areturn

  public java.lang.String toFullString();
    Code:
       0: new           #63                 // class java/lang/StringBuilder
       3: dup
       4: invokespecial #64                 // Method java/lang/StringBuilder."<init>":()V
       7: ldc           #107                // String service{name=\'
       9: invokevirtual #66                 // Method java/lang/StringBuilder.append:(Ljava/lang/String;)Ljava/lang/StringBuilder;
      12: aload_0
      13: getfield      #17                 // Field name:Ljava/lang/String;
      16: invokevirtual #66                 // Method java/lang/StringBuilder.append:(Ljava/lang/String;)Ljava/lang/StringBuilder;
      19: ldc           #108                // String \',group=\'
      21: invokevirtual #66                 // Method java/lang/StringBuilder.append:(Ljava/lang/String;)Ljava/lang/StringBuilder;
      24: aload_0
      25: getfield      #18                 // Field group:Ljava/lang/String;
      28: invokevirtual #66                 // Method java/lang/StringBuilder.append:(Ljava/lang/String;)Ljava/lang/StringBuilder;
      31: ldc           #109                // String \',version=\'
      33: invokevirtual #66                 // Method java/lang/StringBuilder.append:(Ljava/lang/String;)Ljava/lang/StringBuilder;
      36: aload_0
      37: getfield      #19                 // Field version:Ljava/lang/String;
      40: invokevirtual #66                 // Method java/lang/StringBuilder.append:(Ljava/lang/String;)Ljava/lang/StringBuilder;
      43: ldc           #110                // String \',protocol=\'
      45: invokevirtual #66                 // Method java/lang/StringBuilder.append:(Ljava/lang/String;)Ljava/lang/StringBuilder;
      48: aload_0
      49: getfield      #20                 // Field protocol:Ljava/lang/String;
      52: invokevirtual #66                 // Method java/lang/StringBuilder.append:(Ljava/lang/String;)Ljava/lang/StringBuilder;
      55: ldc           #111                // String \',port=\'
      57: invokevirtual #66                 // Method java/lang/StringBuilder.append:(Ljava/lang/String;)Ljava/lang/StringBuilder;
      60: aload_0
      61: getfield      #3                  // Field port:I
      64: invokevirtual #87                 // Method java/lang/StringBuilder.append:(I)Ljava/lang/StringBuilder;
      67: ldc           #112                // String \',params=
      69: invokevirtual #66                 // Method java/lang/StringBuilder.append:(Ljava/lang/String;)Ljava/lang/StringBuilder;
      72: aload_0
      73: getfield      #24                 // Field params:Ljava/util/Map;
      76: invokevirtual #91                 // Method java/lang/StringBuilder.append:(Ljava/lang/Object;)Ljava/lang/StringBuilder;
      79: ldc           #113                // String ,}
      81: invokevirtual #66                 // Method java/lang/StringBuilder.append:(Ljava/lang/String;)Ljava/lang/StringBuilder;
      84: invokevirtual #67                 // Method java/lang/StringBuilder.toString:()Ljava/lang/String;
      87: areturn
}
