Compiled from "ParameterTypesComparator.java"
public class org.apache.dubbo.metadata.ParameterTypesComparator {
  private java.lang.Class[] parameterTypes;

  public org.apache.dubbo.metadata.ParameterTypesComparator(java.lang.Class[]);
    Code:
       0: aload_0
       1: invokespecial #1                  // Method java/lang/Object."<init>":()V
       4: aload_0
       5: aload_1
       6: putfield      #2                  // Field parameterTypes:[Ljava/lang/Class;
       9: return

  public boolean equals(java.lang.Object);
    Code:
       0: aload_0
       1: aload_1
       2: if_acmpne     7
       5: iconst_1
       6: ireturn
       7: aload_1
       8: ifnull        22
      11: aload_0
      12: invokevirtual #3                  // Method java/lang/Object.getClass:()Ljava/lang/Class;
      15: aload_1
      16: invokevirtual #3                  // Method java/lang/Object.getClass:()Ljava/lang/Class;
      19: if_acmpeq     24
      22: iconst_0
      23: ireturn
      24: aload_1
      25: checkcast     #4                  // class org/apache/dubbo/metadata/ParameterTypesComparator
      28: astore_2
      29: aload_0
      30: getfield      #2                  // Field parameterTypes:[Ljava/lang/Class;
      33: aload_2
      34: getfield      #2                  // Field parameterTypes:[Ljava/lang/Class;
      37: invokestatic  #5                  // Method java/util/Arrays.equals:([Ljava/lang/Object;[Ljava/lang/Object;)Z
      40: ireturn

  public int hashCode();
    Code:
       0: aload_0
       1: getfield      #2                  // Field parameterTypes:[Ljava/lang/Class;
       4: invokestatic  #6                  // Method java/util/Arrays.hashCode:([Ljava/lang/Object;)I
       7: ireturn

  public static org.apache.dubbo.metadata.ParameterTypesComparator getInstance(java.lang.Class[]);
    Code:
       0: new           #4                  // class org/apache/dubbo/metadata/ParameterTypesComparator
       3: dup
       4: aload_0
       5: invokespecial #7                  // Method "<init>":([Ljava/lang/Class;)V
       8: areturn
}
