Compiled from "RevisionResolver.java"
public class org.apache.dubbo.metadata.RevisionResolver {
  public static final java.lang.String EMPTY_REVISION;

  private static org.apache.dubbo.common.utils.MD5Utils md5Utils;

  public org.apache.dubbo.metadata.RevisionResolver();
    Code:
       0: aload_0
       1: invokespecial #1                  // Method java/lang/Object."<init>":()V
       4: return

  public static java.lang.String calRevision(java.lang.String);
    Code:
       0: getstatic     #2                  // Field md5Utils:Lorg/apache/dubbo/common/utils/MD5Utils;
       3: aload_0
       4: invokevirtual #3                  // Method org/apache/dubbo/common/utils/MD5Utils.getMd5:(Ljava/lang/String;)Ljava/lang/String;
       7: areturn

  static {};
    Code:
       0: new           #4                  // class org/apache/dubbo/common/utils/MD5Utils
       3: dup
       4: invokespecial #5                  // Method org/apache/dubbo/common/utils/MD5Utils."<init>":()V
       7: putstatic     #2                  // Field md5Utils:Lorg/apache/dubbo/common/utils/MD5Utils;
      10: return
}
