Compiled from "ServiceNameMapping.java"
public interface org.apache.dubbo.metadata.ServiceNameMapping extends org.apache.dubbo.rpc.service.Destroyable {
  public static final java.lang.String DEFAULT_MAPPING_GROUP;

  public abstract boolean map(org.apache.dubbo.common.URL);

  public abstract boolean hasValidMetadataCenter();

  public static org.apache.dubbo.metadata.ServiceNameMapping getDefaultExtension(org.apache.dubbo.rpc.model.ScopeModel);
    Code:
       0: aload_0
       1: invokestatic  #2                  // Method org/apache/dubbo/rpc/model/ScopeModelUtil.getApplicationModel:(Lorg/apache/dubbo/rpc/model/ScopeModel;)Lorg/apache/dubbo/rpc/model/ApplicationModel;
       4: ldc           #3                  // class org/apache/dubbo/metadata/ServiceNameMapping
       6: invokevirtual #4                  // Method org/apache/dubbo/rpc/model/ApplicationModel.getDefaultExtension:(Ljava/lang/Class;)Ljava/lang/Object;
       9: checkcast     #3                  // class org/apache/dubbo/metadata/ServiceNameMapping
      12: areturn

  public static java.lang.String buildMappingKey(org.apache.dubbo.common.URL);
    Code:
       0: aload_0
       1: invokevirtual #5                  // Method org/apache/dubbo/common/URL.getServiceInterface:()Ljava/lang/String;
       4: invokestatic  #6                  // InterfaceMethod buildGroup:(Ljava/lang/String;)Ljava/lang/String;
       7: areturn

  public static java.lang.String buildGroup(java.lang.String);
    Code:
       0: aload_0
       1: areturn

  public static java.lang.String toStringKeys(java.util.Set<java.lang.String>);
    Code:
       0: aload_0
       1: invokestatic  #7                  // Method org/apache/dubbo/common/utils/CollectionUtils.isEmpty:(Ljava/util/Collection;)Z
       4: ifeq          10
       7: ldc           #8                  // String
       9: areturn
      10: new           #9                  // class java/lang/StringBuilder
      13: dup
      14: invokespecial #10                 // Method java/lang/StringBuilder."<init>":()V
      17: astore_1
      18: aload_0
      19: invokeinterface #11,  1           // InterfaceMethod java/util/Set.iterator:()Ljava/util/Iterator;
      24: astore_2
      25: aload_2
      26: invokeinterface #12,  1           // InterfaceMethod java/util/Iterator.hasNext:()Z
      31: ifeq          60
      34: aload_2
      35: invokeinterface #13,  1           // InterfaceMethod java/util/Iterator.next:()Ljava/lang/Object;
      40: checkcast     #14                 // class java/lang/String
      43: astore_3
      44: aload_1
      45: aload_3
      46: invokevirtual #15                 // Method java/lang/StringBuilder.append:(Ljava/lang/String;)Ljava/lang/StringBuilder;
      49: pop
      50: aload_1
      51: ldc           #16                 // String ,
      53: invokevirtual #15                 // Method java/lang/StringBuilder.append:(Ljava/lang/String;)Ljava/lang/StringBuilder;
      56: pop
      57: goto          25
      60: aload_1
      61: aload_1
      62: invokevirtual #17                 // Method java/lang/StringBuilder.length:()I
      65: iconst_1
      66: isub
      67: invokevirtual #18                 // Method java/lang/StringBuilder.deleteCharAt:(I)Ljava/lang/StringBuilder;
      70: pop
      71: aload_1
      72: invokevirtual #19                 // Method java/lang/StringBuilder.toString:()Ljava/lang/String;
      75: areturn

  public static java.util.Set<java.lang.String> getAppNames(java.lang.String);
    Code:
       0: aload_0
       1: invokestatic  #20                 // Method org/apache/dubbo/common/utils/StringUtils.isBlank:(Ljava/lang/CharSequence;)Z
       4: ifeq          11
       7: invokestatic  #21                 // Method java/util/Collections.emptySet:()Ljava/util/Set;
      10: areturn
      11: new           #22                 // class java/util/TreeSet
      14: dup
      15: aload_0
      16: ldc           #16                 // String ,
      18: invokevirtual #23                 // Method java/lang/String.split:(Ljava/lang/String;)[Ljava/lang/String;
      21: invokestatic  #24                 // Method java/util/Arrays.asList:([Ljava/lang/Object;)Ljava/util/List;
      24: invokespecial #25                 // Method java/util/TreeSet."<init>":(Ljava/util/Collection;)V
      27: areturn

  public static java.util.Set<java.lang.String> getMappingByUrl(org.apache.dubbo.common.URL);
    Code:
       0: aload_0
       1: ldc           #27                 // String provided-by
       3: invokevirtual #28                 // Method org/apache/dubbo/common/URL.getParameter:(Ljava/lang/String;)Ljava/lang/String;
       6: astore_1
       7: aload_1
       8: invokestatic  #20                 // Method org/apache/dubbo/common/utils/StringUtils.isBlank:(Ljava/lang/CharSequence;)Z
      11: ifeq          16
      14: aconst_null
      15: areturn
      16: aload_1
      17: invokestatic  #29                 // Method org/apache/dubbo/metadata/AbstractServiceNameMapping.parseServices:(Ljava/lang/String;)Ljava/util/Set;
      20: areturn

  public abstract java.util.Set<java.lang.String> getAndListen(org.apache.dubbo.common.URL, org.apache.dubbo.common.URL, org.apache.dubbo.metadata.MappingListener);

  public abstract org.apache.dubbo.metadata.MappingListener stopListen(org.apache.dubbo.common.URL, org.apache.dubbo.metadata.MappingListener);

  public abstract void putCachedMapping(java.lang.String, java.util.Set<java.lang.String>);

  public abstract java.util.Set<java.lang.String> getMapping(org.apache.dubbo.common.URL);

  public abstract java.util.Set<java.lang.String> getRemoteMapping(org.apache.dubbo.common.URL);

  public abstract java.util.Set<java.lang.String> removeCachedMapping(java.lang.String);
}
