Compiled from "GracefulShutdown.java"
final class org.springframework.boot.web.embedded.jetty.GracefulShutdown {
  private static final org.apache.commons.logging.Log logger;

  private final org.eclipse.jetty.server.Server server;

  private final java.util.function.Supplier<java.lang.Integer> activeRequests;

  private volatile boolean shuttingDown;

  org.springframework.boot.web.embedded.jetty.GracefulShutdown(org.eclipse.jetty.server.Server, java.util.function.Supplier<java.lang.Integer>);
    Code:
       0: aload_0
       1: invokespecial #1                  // Method java/lang/Object."<init>":()V
       4: aload_0
       5: iconst_0
       6: putfield      #7                  // Field shuttingDown:Z
       9: aload_0
      10: aload_1
      11: putfield      #13                 // Field server:Lorg/eclipse/jetty/server/Server;
      14: aload_0
      15: aload_2
      16: putfield      #17                 // Field activeRequests:Ljava/util/function/Supplier;
      19: return

  void shutDownGracefully(org.springframework.boot.web.server.GracefulShutdownCallback);
    Code:
       0: getstatic     #21                 // Field logger:Lorg/apache/commons/logging/Log;
       3: ldc           #25                 // String Commencing graceful shutdown. Waiting for active requests to complete
       5: invokeinterface #27,  2           // InterfaceMethod org/apache/commons/logging/Log.info:(Ljava/lang/Object;)V
      10: aload_0
      11: invokevirtual #33                 // Method isJetty10:()Z
      14: istore_2
      15: aload_0
      16: getfield      #13                 // Field server:Lorg/eclipse/jetty/server/Server;
      19: invokevirtual #37                 // Method org/eclipse/jetty/server/Server.getConnectors:()[Lorg/eclipse/jetty/server/Connector;
      22: astore_3
      23: aload_3
      24: arraylength
      25: istore        4
      27: iconst_0
      28: istore        5
      30: iload         5
      32: iload         4
      34: if_icmpge     64
      37: aload_3
      38: iload         5
      40: aaload
      41: astore        6
      43: aload_0
      44: aload         6
      46: iload_2
      47: ifne          54
      50: iconst_1
      51: goto          55
      54: iconst_0
      55: invokevirtual #43                 // Method shutdown:(Lorg/eclipse/jetty/server/Connector;Z)V
      58: iinc          5, 1
      61: goto          30
      64: aload_0
      65: iconst_1
      66: putfield      #7                  // Field shuttingDown:Z
      69: new           #47                 // class java/lang/Thread
      72: dup
      73: aload_0
      74: aload_1
      75: invokedynamic #49,  0             // InvokeDynamic #0:run:(Lorg/springframework/boot/web/embedded/jetty/GracefulShutdown;Lorg/springframework/boot/web/server/GracefulShutdownCallback;)Ljava/lang/Runnable;
      80: ldc           #53                 // String jetty-shutdown
      82: invokespecial #55                 // Method java/lang/Thread."<init>":(Ljava/lang/Runnable;Ljava/lang/String;)V
      85: invokevirtual #58                 // Method java/lang/Thread.start:()V
      88: return

  private void shutdown(org.eclipse.jetty.server.Connector, boolean);
    Code:
       0: aload_1
       1: invokeinterface #61,  1           // InterfaceMethod org/eclipse/jetty/server/Connector.shutdown:()Ljava/util/concurrent/CompletableFuture;
       6: astore_3
       7: goto          33
      10: astore        4
      12: aload_1
      13: invokevirtual #68                 // Method java/lang/Object.getClass:()Ljava/lang/Class;
      16: ldc           #72                 // String shutdown
      18: invokestatic  #73                 // Method org/springframework/util/ReflectionUtils.findMethod:(Ljava/lang/Class;Ljava/lang/String;)Ljava/lang/reflect/Method;
      21: astore        5
      23: aload         5
      25: aload_1
      26: invokestatic  #79                 // Method org/springframework/util/ReflectionUtils.invokeMethod:(Ljava/lang/reflect/Method;Ljava/lang/Object;)Ljava/lang/Object;
      29: checkcast     #83                 // class java/util/concurrent/Future
      32: astore_3
      33: iload_2
      34: ifeq          60
      37: aload_3
      38: invokeinterface #85,  1           // InterfaceMethod java/util/concurrent/Future.get:()Ljava/lang/Object;
      43: pop
      44: goto          60
      47: astore        4
      49: invokestatic  #91                 // Method java/lang/Thread.currentThread:()Ljava/lang/Thread;
      52: invokevirtual #95                 // Method java/lang/Thread.interrupt:()V
      55: goto          60
      58: astore        4
      60: return
    Exception table:
       from    to  target type
           0     7    10   Class java/lang/NoSuchMethodError
          37    44    47   Class java/lang/InterruptedException
          37    44    58   Class java/util/concurrent/ExecutionException

  private boolean isJetty10();
    Code:
       0: ldc           #100                // class java/util/concurrent/CompletableFuture
       2: ldc           #62                 // class org/eclipse/jetty/server/Connector
       4: ldc           #72                 // String shutdown
       6: iconst_0
       7: anewarray     #102                // class java/lang/Class
      10: invokevirtual #104                // Method java/lang/Class.getMethod:(Ljava/lang/String;[Ljava/lang/Class;)Ljava/lang/reflect/Method;
      13: invokevirtual #108                // Method java/lang/reflect/Method.getReturnType:()Ljava/lang/Class;
      16: invokevirtual #113                // Method java/lang/Object.equals:(Ljava/lang/Object;)Z
      19: ireturn
      20: astore_1
      21: iconst_0
      22: ireturn
    Exception table:
       from    to  target type
           0    19    20   Class java/lang/Exception

  private void awaitShutdown(org.springframework.boot.web.server.GracefulShutdownCallback);
    Code:
       0: aload_0
       1: getfield      #7                  // Field shuttingDown:Z
       4: ifeq          35
       7: aload_0
       8: getfield      #17                 // Field activeRequests:Ljava/util/function/Supplier;
      11: invokeinterface #119,  1          // InterfaceMethod java/util/function/Supplier.get:()Ljava/lang/Object;
      16: checkcast     #122                // class java/lang/Integer
      19: invokevirtual #124                // Method java/lang/Integer.intValue:()I
      22: ifle          35
      25: aload_0
      26: ldc2_w        #128                // long 100l
      29: invokevirtual #130                // Method sleep:(J)V
      32: goto          0
      35: aload_0
      36: iconst_0
      37: putfield      #7                  // Field shuttingDown:Z
      40: aload_0
      41: getfield      #17                 // Field activeRequests:Ljava/util/function/Supplier;
      44: invokeinterface #119,  1          // InterfaceMethod java/util/function/Supplier.get:()Ljava/lang/Object;
      49: checkcast     #122                // class java/lang/Integer
      52: invokevirtual #124                // Method java/lang/Integer.intValue:()I
      55: i2l
      56: lstore_2
      57: lload_2
      58: lconst_0
      59: lcmp
      60: ifne          85
      63: getstatic     #21                 // Field logger:Lorg/apache/commons/logging/Log;
      66: ldc           #134                // String Graceful shutdown complete
      68: invokeinterface #27,  2           // InterfaceMethod org/apache/commons/logging/Log.info:(Ljava/lang/Object;)V
      73: aload_1
      74: getstatic     #136                // Field org/springframework/boot/web/server/GracefulShutdownResult.IDLE:Lorg/springframework/boot/web/server/GracefulShutdownResult;
      77: invokeinterface #142,  2          // InterfaceMethod org/springframework/boot/web/server/GracefulShutdownCallback.shutdownComplete:(Lorg/springframework/boot/web/server/GracefulShutdownResult;)V
      82: goto          111
      85: getstatic     #21                 // Field logger:Lorg/apache/commons/logging/Log;
      88: ldc           #148                // String Graceful shutdown aborted with %d request(s) still active
      90: lload_2
      91: invokestatic  #150                // Method java/lang/Long.valueOf:(J)Ljava/lang/Long;
      94: invokestatic  #156                // Method org/springframework/core/log/LogMessage.format:(Ljava/lang/String;Ljava/lang/Object;)Lorg/springframework/core/log/LogMessage;
      97: invokeinterface #27,  2           // InterfaceMethod org/apache/commons/logging/Log.info:(Ljava/lang/Object;)V
     102: aload_1
     103: getstatic     #162                // Field org/springframework/boot/web/server/GracefulShutdownResult.REQUESTS_ACTIVE:Lorg/springframework/boot/web/server/GracefulShutdownResult;
     106: invokeinterface #142,  2          // InterfaceMethod org/springframework/boot/web/server/GracefulShutdownCallback.shutdownComplete:(Lorg/springframework/boot/web/server/GracefulShutdownResult;)V
     111: return

  private void sleep(long);
    Code:
       0: lload_1
       1: invokestatic  #165                // Method java/lang/Thread.sleep:(J)V
       4: goto          14
       7: astore_3
       8: invokestatic  #91                 // Method java/lang/Thread.currentThread:()Ljava/lang/Thread;
      11: invokevirtual #95                 // Method java/lang/Thread.interrupt:()V
      14: return
    Exception table:
       from    to  target type
           0     4     7   Class java/lang/InterruptedException

  void abort();
    Code:
       0: aload_0
       1: iconst_0
       2: putfield      #7                  // Field shuttingDown:Z
       5: return

  private void lambda$shutDownGracefully$0(org.springframework.boot.web.server.GracefulShutdownCallback);
    Code:
       0: aload_0
       1: aload_1
       2: invokevirtual #166                // Method awaitShutdown:(Lorg/springframework/boot/web/server/GracefulShutdownCallback;)V
       5: return

  static {};
    Code:
       0: ldc           #8                  // class org/springframework/boot/web/embedded/jetty/GracefulShutdown
       2: invokestatic  #170                // Method org/apache/commons/logging/LogFactory.getLog:(Ljava/lang/Class;)Lorg/apache/commons/logging/Log;
       5: putstatic     #21                 // Field logger:Lorg/apache/commons/logging/Log;
       8: return
}
