Compiled from "JasperInitializer.java"
class org.springframework.boot.web.embedded.jetty.JasperInitializer extends org.eclipse.jetty.util.component.AbstractLifeCycle {
  private static final java.lang.String[] INITIALIZER_CLASSES;

  private final org.eclipse.jetty.webapp.WebAppContext context;

  private final jakarta.servlet.ServletContainerInitializer initializer;

  org.springframework.boot.web.embedded.jetty.JasperInitializer(org.eclipse.jetty.webapp.WebAppContext);
    Code:
       0: aload_0
       1: invokespecial #1                  // Method org/eclipse/jetty/util/component/AbstractLifeCycle."<init>":()V
       4: aload_0
       5: aload_1
       6: putfield      #7                  // Field context:Lorg/eclipse/jetty/webapp/WebAppContext;
       9: aload_0
      10: aload_0
      11: invokevirtual #13                 // Method newInitializer:()Ljakarta/servlet/ServletContainerInitializer;
      14: putfield      #17                 // Field initializer:Ljakarta/servlet/ServletContainerInitializer;
      17: return

  private jakarta.servlet.ServletContainerInitializer newInitializer();
    Code:
       0: getstatic     #21                 // Field INITIALIZER_CLASSES:[Ljava/lang/String;
       3: astore_1
       4: aload_1
       5: arraylength
       6: istore_2
       7: iconst_0
       8: istore_3
       9: iload_3
      10: iload_2
      11: if_icmpge     55
      14: aload_1
      15: iload_3
      16: aaload
      17: astore        4
      19: aload         4
      21: aconst_null
      22: invokestatic  #25                 // Method org/springframework/util/ClassUtils.forName:(Ljava/lang/String;Ljava/lang/ClassLoader;)Ljava/lang/Class;
      25: astore        5
      27: aload         5
      29: iconst_0
      30: anewarray     #31                 // class java/lang/Class
      33: invokevirtual #33                 // Method java/lang/Class.getDeclaredConstructor:([Ljava/lang/Class;)Ljava/lang/reflect/Constructor;
      36: iconst_0
      37: anewarray     #37                 // class java/lang/Object
      40: invokevirtual #39                 // Method java/lang/reflect/Constructor.newInstance:([Ljava/lang/Object;)Ljava/lang/Object;
      43: checkcast     #45                 // class jakarta/servlet/ServletContainerInitializer
      46: areturn
      47: astore        5
      49: iinc          3, 1
      52: goto          9
      55: aconst_null
      56: areturn
    Exception table:
       from    to  target type
          19    46    47   Class java/lang/Exception

  protected void doStart() throws java.lang.Exception;
    Code:
       0: aload_0
       1: getfield      #17                 // Field initializer:Ljakarta/servlet/ServletContainerInitializer;
       4: ifnonnull     8
       7: return
       8: ldc           #49                 // String org.apache.catalina.webresources.TomcatURLStreamHandlerFactory
      10: aload_0
      11: invokevirtual #51                 // Method java/lang/Object.getClass:()Ljava/lang/Class;
      14: invokevirtual #55                 // Method java/lang/Class.getClassLoader:()Ljava/lang/ClassLoader;
      17: invokestatic  #59                 // Method org/springframework/util/ClassUtils.isPresent:(Ljava/lang/String;Ljava/lang/ClassLoader;)Z
      20: ifeq          30
      23: invokestatic  #63                 // Method org/apache/catalina/webresources/TomcatURLStreamHandlerFactory.register:()Z
      26: pop
      27: goto          44
      30: new           #69                 // class org/springframework/boot/web/embedded/jetty/JasperInitializer$WarUrlStreamHandlerFactory
      33: dup
      34: invokespecial #71                 // Method org/springframework/boot/web/embedded/jetty/JasperInitializer$WarUrlStreamHandlerFactory."<init>":()V
      37: invokestatic  #72                 // Method java/net/URL.setURLStreamHandlerFactory:(Ljava/net/URLStreamHandlerFactory;)V
      40: goto          44
      43: astore_1
      44: invokestatic  #80                 // Method java/lang/Thread.currentThread:()Ljava/lang/Thread;
      47: invokevirtual #86                 // Method java/lang/Thread.getContextClassLoader:()Ljava/lang/ClassLoader;
      50: astore_1
      51: invokestatic  #80                 // Method java/lang/Thread.currentThread:()Ljava/lang/Thread;
      54: aload_0
      55: getfield      #7                  // Field context:Lorg/eclipse/jetty/webapp/WebAppContext;
      58: invokevirtual #89                 // Method org/eclipse/jetty/webapp/WebAppContext.getClassLoader:()Ljava/lang/ClassLoader;
      61: invokevirtual #92                 // Method java/lang/Thread.setContextClassLoader:(Ljava/lang/ClassLoader;)V
      64: aload_0
      65: iconst_1
      66: invokevirtual #96                 // Method setExtendedListenerTypes:(Z)V
      69: aload_0
      70: getfield      #17                 // Field initializer:Ljakarta/servlet/ServletContainerInitializer;
      73: aconst_null
      74: aload_0
      75: getfield      #7                  // Field context:Lorg/eclipse/jetty/webapp/WebAppContext;
      78: invokevirtual #100                // Method org/eclipse/jetty/webapp/WebAppContext.getServletContext:()Lorg/eclipse/jetty/server/handler/ContextHandler$Context;
      81: invokeinterface #104,  3          // InterfaceMethod jakarta/servlet/ServletContainerInitializer.onStartup:(Ljava/util/Set;Ljakarta/servlet/ServletContext;)V
      86: aload_0
      87: iconst_0
      88: invokevirtual #96                 // Method setExtendedListenerTypes:(Z)V
      91: goto          102
      94: astore_2
      95: aload_0
      96: iconst_0
      97: invokevirtual #96                 // Method setExtendedListenerTypes:(Z)V
     100: aload_2
     101: athrow
     102: invokestatic  #80                 // Method java/lang/Thread.currentThread:()Ljava/lang/Thread;
     105: aload_1
     106: invokevirtual #92                 // Method java/lang/Thread.setContextClassLoader:(Ljava/lang/ClassLoader;)V
     109: goto          122
     112: astore_3
     113: invokestatic  #80                 // Method java/lang/Thread.currentThread:()Ljava/lang/Thread;
     116: aload_1
     117: invokevirtual #92                 // Method java/lang/Thread.setContextClassLoader:(Ljava/lang/ClassLoader;)V
     120: aload_3
     121: athrow
     122: return
    Exception table:
       from    to  target type
          30    40    43   Class java/lang/Error
          64    86    94   any
          51   102   112   any

  private void setExtendedListenerTypes(boolean);
    Code:
       0: aload_0
       1: getfield      #7                  // Field context:Lorg/eclipse/jetty/webapp/WebAppContext;
       4: invokevirtual #100                // Method org/eclipse/jetty/webapp/WebAppContext.getServletContext:()Lorg/eclipse/jetty/server/handler/ContextHandler$Context;
       7: iload_1
       8: invokevirtual #108                // Method org/eclipse/jetty/server/handler/ContextHandler$Context.setExtendedListenerTypes:(Z)V
      11: goto          15
      14: astore_2
      15: return
    Exception table:
       from    to  target type
           0    11    14   Class java/lang/NoSuchMethodError

  static {};
    Code:
       0: iconst_2
       1: anewarray     #113                // class java/lang/String
       4: dup
       5: iconst_0
       6: ldc           #115                // String org.eclipse.jetty.apache.jsp.JettyJasperInitializer
       8: aastore
       9: dup
      10: iconst_1
      11: ldc           #117                // String org.apache.jasper.servlet.JasperInitializer
      13: aastore
      14: putstatic     #21                 // Field INITIALIZER_CLASSES:[Ljava/lang/String;
      17: return
}
