Compiled from "JettyHandlerWrappers.java"
class org.springframework.boot.web.embedded.jetty.JettyHandlerWrappers$ServerHeaderHandler extends org.eclipse.jetty.server.handler.HandlerWrapper {
  private static final java.lang.String SERVER_HEADER;

  private final java.lang.String value;

  org.springframework.boot.web.embedded.jetty.JettyHandlerWrappers$ServerHeaderHandler(java.lang.String);
    Code:
       0: aload_0
       1: invokespecial #1                  // Method org/eclipse/jetty/server/handler/HandlerWrapper."<init>":()V
       4: aload_0
       5: aload_1
       6: putfield      #7                  // Field value:Ljava/lang/String;
       9: return

  public void handle(java.lang.String, org.eclipse.jetty.server.Request, jakarta.servlet.http.HttpServletRequest, jakarta.servlet.http.HttpServletResponse) throws java.io.IOException, jakarta.servlet.ServletException;
    Code:
       0: aload         4
       2: invokeinterface #13,  1           // InterfaceMethod jakarta/servlet/http/HttpServletResponse.getHeaderNames:()Ljava/util/Collection;
       7: ldc           #19                 // String server
       9: invokeinterface #21,  2           // InterfaceMethod java/util/Collection.contains:(Ljava/lang/Object;)Z
      14: ifne          30
      17: aload         4
      19: ldc           #19                 // String server
      21: aload_0
      22: getfield      #7                  // Field value:Ljava/lang/String;
      25: invokeinterface #27,  3           // InterfaceMethod jakarta/servlet/http/HttpServletResponse.setHeader:(Ljava/lang/String;Ljava/lang/String;)V
      30: aload_0
      31: aload_1
      32: aload_2
      33: aload_3
      34: aload         4
      36: invokespecial #31                 // Method org/eclipse/jetty/server/handler/HandlerWrapper.handle:(Ljava/lang/String;Lorg/eclipse/jetty/server/Request;Ljakarta/servlet/http/HttpServletRequest;Ljakarta/servlet/http/HttpServletResponse;)V
      39: return
}
