Compiled from "JettyServletWebServerFactory.java"
class org.springframework.boot.web.embedded.jetty.JettyServletWebServerFactory$SuppliedSameSiteCookieHandlerWrapper$ResponseWrapper extends jakarta.servlet.http.HttpServletResponseWrapper {
  final org.springframework.boot.web.embedded.jetty.JettyServletWebServerFactory$SuppliedSameSiteCookieHandlerWrapper this$0;

  org.springframework.boot.web.embedded.jetty.JettyServletWebServerFactory$SuppliedSameSiteCookieHandlerWrapper$ResponseWrapper(org.springframework.boot.web.embedded.jetty.JettyServletWebServerFactory$SuppliedSameSiteCookieHandlerWrapper, jakarta.servlet.http.HttpServletResponse);
    Code:
       0: aload_0
       1: aload_1
       2: putfield      #1                  // Field this$0:Lorg/springframework/boot/web/embedded/jetty/JettyServletWebServerFactory$SuppliedSameSiteCookieHandlerWrapper;
       5: aload_0
       6: aload_2
       7: invokespecial #7                  // Method jakarta/servlet/http/HttpServletResponseWrapper."<init>":(Ljakarta/servlet/http/HttpServletResponse;)V
      10: return

  public void addCookie(jakarta.servlet.http.Cookie);
    Code:
       0: aload_0
       1: aload_1
       2: invokevirtual #13                 // Method getSameSite:(Ljakarta/servlet/http/Cookie;)Lorg/springframework/boot/web/server/Cookie$SameSite;
       5: astore_2
       6: aload_2
       7: ifnull        46
      10: aload_1
      11: invokevirtual #17                 // Method jakarta/servlet/http/Cookie.getComment:()Ljava/lang/String;
      14: invokestatic  #23                 // Method org/eclipse/jetty/http/HttpCookie.getCommentWithoutAttributes:(Ljava/lang/String;)Ljava/lang/String;
      17: astore_3
      18: aload_0
      19: aload_2
      20: invokevirtual #29                 // Method getSameSiteComment:(Lorg/springframework/boot/web/server/Cookie$SameSite;)Ljava/lang/String;
      23: astore        4
      25: aload_1
      26: aload_3
      27: ifnull        41
      30: aload_3
      31: aload         4
      33: invokedynamic #33,  0             // InvokeDynamic #0:makeConcatWithConstants:(Ljava/lang/String;Ljava/lang/String;)Ljava/lang/String;
      38: goto          43
      41: aload         4
      43: invokevirtual #37                 // Method jakarta/servlet/http/Cookie.setComment:(Ljava/lang/String;)V
      46: aload_0
      47: aload_1
      48: invokespecial #41                 // Method jakarta/servlet/http/HttpServletResponseWrapper.addCookie:(Ljakarta/servlet/http/Cookie;)V
      51: return

  private java.lang.String getSameSiteComment(org.springframework.boot.web.server.Cookie$SameSite);
    Code:
       0: getstatic     #45                 // Field org/springframework/boot/web/embedded/jetty/JettyServletWebServerFactory$3.$SwitchMap$org$springframework$boot$web$server$Cookie$SameSite:[I
       3: aload_1
       4: invokevirtual #51                 // Method org/springframework/boot/web/server/Cookie$SameSite.ordinal:()I
       7: iaload
       8: tableswitch   { // 1 to 3
                     1: 44
                     2: 49
                     3: 54
               default: 36
          }
      36: new           #57                 // class java/lang/IncompatibleClassChangeError
      39: dup
      40: invokespecial #59                 // Method java/lang/IncompatibleClassChangeError."<init>":()V
      43: athrow
      44: ldc           #62                 // String __SAME_SITE_NONE__
      46: goto          56
      49: ldc           #64                 // String __SAME_SITE_LAX__
      51: goto          56
      54: ldc           #66                 // String __SAME_SITE_STRICT__
      56: areturn

  private org.springframework.boot.web.server.Cookie$SameSite getSameSite(jakarta.servlet.http.Cookie);
    Code:
       0: aload_0
       1: getfield      #1                  // Field this$0:Lorg/springframework/boot/web/embedded/jetty/JettyServletWebServerFactory$SuppliedSameSiteCookieHandlerWrapper;
       4: getfield      #68                 // Field org/springframework/boot/web/embedded/jetty/JettyServletWebServerFactory$SuppliedSameSiteCookieHandlerWrapper.suppliers:Ljava/util/List;
       7: invokeinterface #74,  1           // InterfaceMethod java/util/List.iterator:()Ljava/util/Iterator;
      12: astore_2
      13: aload_2
      14: invokeinterface #80,  1           // InterfaceMethod java/util/Iterator.hasNext:()Z
      19: ifeq          52
      22: aload_2
      23: invokeinterface #86,  1           // InterfaceMethod java/util/Iterator.next:()Ljava/lang/Object;
      28: checkcast     #90                 // class org/springframework/boot/web/servlet/server/CookieSameSiteSupplier
      31: astore_3
      32: aload_3
      33: aload_1
      34: invokeinterface #92,  2           // InterfaceMethod org/springframework/boot/web/servlet/server/CookieSameSiteSupplier.getSameSite:(Ljakarta/servlet/http/Cookie;)Lorg/springframework/boot/web/server/Cookie$SameSite;
      39: astore        4
      41: aload         4
      43: ifnull        49
      46: aload         4
      48: areturn
      49: goto          13
      52: aconst_null
      53: areturn
}
