Compiled from "JettyServletWebServerFactory.java"
class org.springframework.boot.web.embedded.jetty.JettyServletWebServerFactory$SuppliedSameSiteCookieHandlerWrapper extends org.eclipse.jetty.server.handler.HandlerWrapper {
  private final java.util.List<org.springframework.boot.web.servlet.server.CookieSameSiteSupplier> suppliers;

  org.springframework.boot.web.embedded.jetty.JettyServletWebServerFactory$SuppliedSameSiteCookieHandlerWrapper(java.util.List<org.springframework.boot.web.servlet.server.CookieSameSiteSupplier>);
    Code:
       0: aload_0
       1: invokespecial #1                  // Method org/eclipse/jetty/server/handler/HandlerWrapper."<init>":()V
       4: aload_0
       5: aload_1
       6: putfield      #7                  // Field suppliers:Ljava/util/List;
       9: return

  public void handle(java.lang.String, org.eclipse.jetty.server.Request, jakarta.servlet.http.HttpServletRequest, jakarta.servlet.http.HttpServletResponse) throws java.io.IOException, jakarta.servlet.ServletException;
    Code:
       0: new           #13                 // class org/springframework/boot/web/embedded/jetty/JettyServletWebServerFactory$SuppliedSameSiteCookieHandlerWrapper$ResponseWrapper
       3: dup
       4: aload_0
       5: aload         4
       7: invokespecial #15                 // Method org/springframework/boot/web/embedded/jetty/JettyServletWebServerFactory$SuppliedSameSiteCookieHandlerWrapper$ResponseWrapper."<init>":(Lorg/springframework/boot/web/embedded/jetty/JettyServletWebServerFactory$SuppliedSameSiteCookieHandlerWrapper;Ljakarta/servlet/http/HttpServletResponse;)V
      10: astore        5
      12: aload_0
      13: aload_1
      14: aload_2
      15: aload_3
      16: aload         5
      18: invokespecial #18                 // Method org/eclipse/jetty/server/handler/HandlerWrapper.handle:(Ljava/lang/String;Lorg/eclipse/jetty/server/Request;Ljakarta/servlet/http/HttpServletRequest;Ljakarta/servlet/http/HttpServletResponse;)V
      21: return
}
