Compiled from "JettyServletWebServerFactory.java"
class org.springframework.boot.web.embedded.jetty.JettyServletWebServerFactory$WebListenersConfiguration extends org.eclipse.jetty.webapp.AbstractConfiguration {
  private final java.util.Set<java.lang.String> classNames;

  org.springframework.boot.web.embedded.jetty.JettyServletWebServerFactory$WebListenersConfiguration(java.util.Set<java.lang.String>);
    Code:
       0: aload_0
       1: invokespecial #1                  // Method org/eclipse/jetty/webapp/AbstractConfiguration."<init>":()V
       4: aload_0
       5: aload_1
       6: putfield      #7                  // Field classNames:Ljava/util/Set;
       9: return

  public void configure(org.eclipse.jetty.webapp.WebAppContext) throws java.lang.Exception;
    Code:
       0: aload_1
       1: invokevirtual #13                 // Method org/eclipse/jetty/webapp/WebAppContext.getServletHandler:()Lorg/eclipse/jetty/servlet/ServletHandler;
       4: astore_2
       5: aload_0
       6: getfield      #7                  // Field classNames:Ljava/util/Set;
       9: invokeinterface #19,  1           // InterfaceMethod java/util/Set.iterator:()Ljava/util/Iterator;
      14: astore_3
      15: aload_3
      16: invokeinterface #25,  1           // InterfaceMethod java/util/Iterator.hasNext:()Z
      21: ifeq          46
      24: aload_3
      25: invokeinterface #31,  1           // InterfaceMethod java/util/Iterator.next:()Ljava/lang/Object;
      30: checkcast     #35                 // class java/lang/String
      33: astore        4
      35: aload_0
      36: aload_1
      37: aload_2
      38: aload         4
      40: invokevirtual #37                 // Method configure:(Lorg/eclipse/jetty/webapp/WebAppContext;Lorg/eclipse/jetty/servlet/ServletHandler;Ljava/lang/String;)V
      43: goto          15
      46: return

  private void configure(org.eclipse.jetty.webapp.WebAppContext, org.eclipse.jetty.servlet.ServletHandler, java.lang.String) throws java.lang.ClassNotFoundException;
    Code:
       0: aload_2
       1: new           #41                 // class org/eclipse/jetty/servlet/Source
       4: dup
       5: getstatic     #43                 // Field org/eclipse/jetty/servlet/Source$Origin.ANNOTATION:Lorg/eclipse/jetty/servlet/Source$Origin;
       8: aload_3
       9: invokespecial #49                 // Method org/eclipse/jetty/servlet/Source."<init>":(Lorg/eclipse/jetty/servlet/Source$Origin;Ljava/lang/String;)V
      12: invokevirtual #52                 // Method org/eclipse/jetty/servlet/ServletHandler.newListenerHolder:(Lorg/eclipse/jetty/servlet/Source;)Lorg/eclipse/jetty/servlet/ListenerHolder;
      15: astore        4
      17: aload         4
      19: aload_0
      20: aload_1
      21: aload_3
      22: invokevirtual #58                 // Method loadClass:(Lorg/eclipse/jetty/webapp/WebAppContext;Ljava/lang/String;)Ljava/lang/Class;
      25: invokevirtual #62                 // Method org/eclipse/jetty/servlet/ListenerHolder.setHeldClass:(Ljava/lang/Class;)V
      28: aload_2
      29: aload         4
      31: invokevirtual #68                 // Method org/eclipse/jetty/servlet/ServletHandler.addListener:(Lorg/eclipse/jetty/servlet/ListenerHolder;)V
      34: return

  private java.lang.Class<? extends java.util.EventListener> loadClass(org.eclipse.jetty.webapp.WebAppContext, java.lang.String) throws java.lang.ClassNotFoundException;
    Code:
       0: aload_1
       1: invokevirtual #72                 // Method org/eclipse/jetty/webapp/WebAppContext.getClassLoader:()Ljava/lang/ClassLoader;
       4: astore_3
       5: aload_3
       6: ifnull        13
       9: aload_3
      10: goto          20
      13: aload_0
      14: invokevirtual #76                 // Method java/lang/Object.getClass:()Ljava/lang/Class;
      17: invokevirtual #82                 // Method java/lang/Class.getClassLoader:()Ljava/lang/ClassLoader;
      20: astore_3
      21: aload_3
      22: aload_2
      23: invokevirtual #85                 // Method java/lang/ClassLoader.loadClass:(Ljava/lang/String;)Ljava/lang/Class;
      26: areturn
}
