Compiled from "JettyWebServer.java"
public class org.springframework.boot.web.embedded.jetty.JettyWebServer implements org.springframework.boot.web.server.WebServer {
  private static final org.apache.commons.logging.Log logger;

  private final java.lang.Object monitor;

  private final org.eclipse.jetty.server.Server server;

  private final boolean autoStart;

  private final org.springframework.boot.web.embedded.jetty.GracefulShutdown gracefulShutdown;

  private org.eclipse.jetty.server.Connector[] connectors;

  private volatile boolean started;

  public org.springframework.boot.web.embedded.jetty.JettyWebServer(org.eclipse.jetty.server.Server);
    Code:
       0: aload_0
       1: aload_1
       2: iconst_1
       3: invokespecial #1                  // Method "<init>":(Lorg/eclipse/jetty/server/Server;Z)V
       6: return

  public org.springframework.boot.web.embedded.jetty.JettyWebServer(org.eclipse.jetty.server.Server, boolean);
    Code:
       0: aload_0
       1: invokespecial #7                  // Method java/lang/Object."<init>":()V
       4: aload_0
       5: new           #8                  // class java/lang/Object
       8: dup
       9: invokespecial #7                  // Method java/lang/Object."<init>":()V
      12: putfield      #12                 // Field monitor:Ljava/lang/Object;
      15: aload_0
      16: iload_2
      17: putfield      #16                 // Field autoStart:Z
      20: aload_1
      21: ldc           #20                 // String Jetty Server must not be null
      23: invokestatic  #22                 // Method org/springframework/util/Assert.notNull:(Ljava/lang/Object;Ljava/lang/String;)V
      26: aload_0
      27: aload_1
      28: putfield      #28                 // Field server:Lorg/eclipse/jetty/server/Server;
      31: aload_0
      32: aload_0
      33: aload_1
      34: invokevirtual #32                 // Method createGracefulShutdown:(Lorg/eclipse/jetty/server/Server;)Lorg/springframework/boot/web/embedded/jetty/GracefulShutdown;
      37: putfield      #36                 // Field gracefulShutdown:Lorg/springframework/boot/web/embedded/jetty/GracefulShutdown;
      40: aload_0
      41: invokevirtual #40                 // Method initialize:()V
      44: return

  private org.springframework.boot.web.embedded.jetty.GracefulShutdown createGracefulShutdown(org.eclipse.jetty.server.Server);
    Code:
       0: aload_0
       1: aload_1
       2: invokevirtual #43                 // Method findStatisticsHandler:(Lorg/eclipse/jetty/server/Server;)Lorg/eclipse/jetty/server/handler/StatisticsHandler;
       5: astore_2
       6: aload_2
       7: ifnonnull     12
      10: aconst_null
      11: areturn
      12: new           #47                 // class org/springframework/boot/web/embedded/jetty/GracefulShutdown
      15: dup
      16: aload_1
      17: aload_2
      18: dup
      19: invokestatic  #49                 // Method java/util/Objects.requireNonNull:(Ljava/lang/Object;)Ljava/lang/Object;
      22: pop
      23: invokedynamic #55,  0             // InvokeDynamic #0:get:(Lorg/eclipse/jetty/server/handler/StatisticsHandler;)Ljava/util/function/Supplier;
      28: invokespecial #59                 // Method org/springframework/boot/web/embedded/jetty/GracefulShutdown."<init>":(Lorg/eclipse/jetty/server/Server;Ljava/util/function/Supplier;)V
      31: areturn

  private org.eclipse.jetty.server.handler.StatisticsHandler findStatisticsHandler(org.eclipse.jetty.server.Server);
    Code:
       0: aload_0
       1: aload_1
       2: invokevirtual #62                 // Method org/eclipse/jetty/server/Server.getHandler:()Lorg/eclipse/jetty/server/Handler;
       5: invokevirtual #68                 // Method findStatisticsHandler:(Lorg/eclipse/jetty/server/Handler;)Lorg/eclipse/jetty/server/handler/StatisticsHandler;
       8: areturn

  private org.eclipse.jetty.server.handler.StatisticsHandler findStatisticsHandler(org.eclipse.jetty.server.Handler);
    Code:
       0: aload_1
       1: instanceof    #71                 // class org/eclipse/jetty/server/handler/StatisticsHandler
       4: ifeq          14
       7: aload_1
       8: checkcast     #71                 // class org/eclipse/jetty/server/handler/StatisticsHandler
      11: astore_2
      12: aload_2
      13: areturn
      14: aload_1
      15: instanceof    #73                 // class org/eclipse/jetty/server/handler/HandlerWrapper
      18: ifeq          35
      21: aload_1
      22: checkcast     #73                 // class org/eclipse/jetty/server/handler/HandlerWrapper
      25: astore_2
      26: aload_0
      27: aload_2
      28: invokevirtual #75                 // Method org/eclipse/jetty/server/handler/HandlerWrapper.getHandler:()Lorg/eclipse/jetty/server/Handler;
      31: invokevirtual #68                 // Method findStatisticsHandler:(Lorg/eclipse/jetty/server/Handler;)Lorg/eclipse/jetty/server/handler/StatisticsHandler;
      34: areturn
      35: aconst_null
      36: areturn

  private void initialize();
    Code:
       0: aload_0
       1: getfield      #12                 // Field monitor:Ljava/lang/Object;
       4: dup
       5: astore_1
       6: monitorenter
       7: aload_0
       8: aload_0
       9: getfield      #28                 // Field server:Lorg/eclipse/jetty/server/Server;
      12: invokevirtual #76                 // Method org/eclipse/jetty/server/Server.getConnectors:()[Lorg/eclipse/jetty/server/Connector;
      15: putfield      #80                 // Field connectors:[Lorg/eclipse/jetty/server/Connector;
      18: aload_0
      19: getfield      #28                 // Field server:Lorg/eclipse/jetty/server/Server;
      22: aconst_null
      23: invokevirtual #84                 // Method org/eclipse/jetty/server/Server.setConnectors:([Lorg/eclipse/jetty/server/Connector;)V
      26: aload_0
      27: getfield      #28                 // Field server:Lorg/eclipse/jetty/server/Server;
      30: invokevirtual #88                 // Method org/eclipse/jetty/server/Server.start:()V
      33: aload_0
      34: getfield      #28                 // Field server:Lorg/eclipse/jetty/server/Server;
      37: iconst_0
      38: invokevirtual #91                 // Method org/eclipse/jetty/server/Server.setStopAtShutdown:(Z)V
      41: goto          60
      44: astore_2
      45: aload_0
      46: invokevirtual #97                 // Method stopSilently:()V
      49: new           #100                // class org/springframework/boot/web/server/WebServerException
      52: dup
      53: ldc           #102                // String Unable to start embedded Jetty web server
      55: aload_2
      56: invokespecial #104                // Method org/springframework/boot/web/server/WebServerException."<init>":(Ljava/lang/String;Ljava/lang/Throwable;)V
      59: athrow
      60: aload_1
      61: monitorexit
      62: goto          70
      65: astore_3
      66: aload_1
      67: monitorexit
      68: aload_3
      69: athrow
      70: return
    Exception table:
       from    to  target type
           7    41    44   Class java/lang/Throwable
           7    62    65   any
          65    68    65   any

  private void stopSilently();
    Code:
       0: aload_0
       1: getfield      #28                 // Field server:Lorg/eclipse/jetty/server/Server;
       4: invokevirtual #107                // Method org/eclipse/jetty/server/Server.stop:()V
       7: goto          11
      10: astore_1
      11: return
    Exception table:
       from    to  target type
           0     7    10   Class java/lang/Exception

  public void start() throws org.springframework.boot.web.server.WebServerException;
    Code:
       0: aload_0
       1: getfield      #12                 // Field monitor:Ljava/lang/Object;
       4: dup
       5: astore_1
       6: monitorenter
       7: aload_0
       8: getfield      #112                // Field started:Z
      11: ifeq          17
      14: aload_1
      15: monitorexit
      16: return
      17: aload_0
      18: getfield      #28                 // Field server:Lorg/eclipse/jetty/server/Server;
      21: aload_0
      22: getfield      #80                 // Field connectors:[Lorg/eclipse/jetty/server/Connector;
      25: invokevirtual #84                 // Method org/eclipse/jetty/server/Server.setConnectors:([Lorg/eclipse/jetty/server/Connector;)V
      28: aload_0
      29: getfield      #16                 // Field autoStart:Z
      32: ifne          38
      35: aload_1
      36: monitorexit
      37: return
      38: aload_0
      39: getfield      #28                 // Field server:Lorg/eclipse/jetty/server/Server;
      42: invokevirtual #88                 // Method org/eclipse/jetty/server/Server.start:()V
      45: aload_0
      46: getfield      #28                 // Field server:Lorg/eclipse/jetty/server/Server;
      49: invokevirtual #115                // Method org/eclipse/jetty/server/Server.getHandlers:()[Lorg/eclipse/jetty/server/Handler;
      52: astore_2
      53: aload_2
      54: arraylength
      55: istore_3
      56: iconst_0
      57: istore        4
      59: iload         4
      61: iload_3
      62: if_icmpge     90
      65: aload_2
      66: iload         4
      68: aaload
      69: astore        5
      71: aload_0
      72: iconst_1
      73: anewarray     #119                // class org/eclipse/jetty/server/Handler
      76: dup
      77: iconst_0
      78: aload         5
      80: aastore
      81: invokevirtual #121                // Method handleDeferredInitialize:([Lorg/eclipse/jetty/server/Handler;)V
      84: iinc          4, 1
      87: goto          59
      90: aload_0
      91: getfield      #28                 // Field server:Lorg/eclipse/jetty/server/Server;
      94: invokevirtual #76                 // Method org/eclipse/jetty/server/Server.getConnectors:()[Lorg/eclipse/jetty/server/Connector;
      97: astore_2
      98: aload_2
      99: astore_3
     100: aload_3
     101: arraylength
     102: istore        4
     104: iconst_0
     105: istore        5
     107: iload         5
     109: iload         4
     111: if_icmpge     173
     114: aload_3
     115: iload         5
     117: aaload
     118: astore        6
     120: aload         6
     122: invokeinterface #125,  1          // InterfaceMethod org/eclipse/jetty/server/Connector.start:()V
     127: goto          167
     130: astore        7
     132: aload         6
     134: instanceof    #130                // class org/eclipse/jetty/server/NetworkConnector
     137: ifeq          164
     140: aload         6
     142: checkcast     #130                // class org/eclipse/jetty/server/NetworkConnector
     145: astore        8
     147: aload         7
     149: aload         8
     151: dup
     152: invokestatic  #49                 // Method java/util/Objects.requireNonNull:(Ljava/lang/Object;)Ljava/lang/Object;
     155: pop
     156: invokedynamic #132,  0            // InvokeDynamic #1:getAsInt:(Lorg/eclipse/jetty/server/NetworkConnector;)Ljava/util/function/IntSupplier;
     161: invokestatic  #136                // Method org/springframework/boot/web/server/PortInUseException.throwIfPortBindingException:(Ljava/lang/Exception;Ljava/util/function/IntSupplier;)V
     164: aload         7
     166: athrow
     167: iinc          5, 1
     170: goto          107
     173: aload_0
     174: iconst_1
     175: putfield      #112                // Field started:Z
     178: getstatic     #142                // Field logger:Lorg/apache/commons/logging/Log;
     181: aload_0
     182: invokevirtual #146                // Method getActualPortsDescription:()Ljava/lang/String;
     185: aload_0
     186: invokevirtual #150                // Method getContextPath:()Ljava/lang/String;
     189: invokedynamic #153,  0            // InvokeDynamic #2:makeConcatWithConstants:(Ljava/lang/String;Ljava/lang/String;)Ljava/lang/String;
     194: invokeinterface #157,  2          // InterfaceMethod org/apache/commons/logging/Log.info:(Ljava/lang/Object;)V
     199: goto          225
     202: astore_2
     203: aload_0
     204: invokevirtual #97                 // Method stopSilently:()V
     207: aload_2
     208: athrow
     209: astore_2
     210: aload_0
     211: invokevirtual #97                 // Method stopSilently:()V
     214: new           #100                // class org/springframework/boot/web/server/WebServerException
     217: dup
     218: ldc           #163                // String Unable to start embedded Jetty server
     220: aload_2
     221: invokespecial #104                // Method org/springframework/boot/web/server/WebServerException."<init>":(Ljava/lang/String;Ljava/lang/Throwable;)V
     224: athrow
     225: aload_1
     226: monitorexit
     227: goto          237
     230: astore        9
     232: aload_1
     233: monitorexit
     234: aload         9
     236: athrow
     237: return
    Exception table:
       from    to  target type
         120   127   130   Class java/io/IOException
          38   199   202   Class org/springframework/boot/web/server/WebServerException
          38   199   209   Class java/lang/Exception
           7    16   230   any
          17    37   230   any
          38   227   230   any
         230   234   230   any

  private java.lang.String getActualPortsDescription();
    Code:
       0: new           #165                // class java/lang/StringBuilder
       3: dup
       4: invokespecial #167                // Method java/lang/StringBuilder."<init>":()V
       7: astore_1
       8: aload_0
       9: getfield      #28                 // Field server:Lorg/eclipse/jetty/server/Server;
      12: invokevirtual #76                 // Method org/eclipse/jetty/server/Server.getConnectors:()[Lorg/eclipse/jetty/server/Connector;
      15: astore_2
      16: aload_2
      17: arraylength
      18: istore_3
      19: iconst_0
      20: istore        4
      22: iload         4
      24: iload_3
      25: if_icmpge     74
      28: aload_2
      29: iload         4
      31: aaload
      32: astore        5
      34: aload_1
      35: invokevirtual #168                // Method java/lang/StringBuilder.length:()I
      38: ifeq          48
      41: aload_1
      42: ldc           #172                // String ,
      44: invokevirtual #174                // Method java/lang/StringBuilder.append:(Ljava/lang/String;)Ljava/lang/StringBuilder;
      47: pop
      48: aload_1
      49: aload_0
      50: aload         5
      52: invokevirtual #178                // Method getLocalPort:(Lorg/eclipse/jetty/server/Connector;)Ljava/lang/Integer;
      55: invokevirtual #182                // Method java/lang/StringBuilder.append:(Ljava/lang/Object;)Ljava/lang/StringBuilder;
      58: aload_0
      59: aload         5
      61: invokevirtual #185                // Method getProtocols:(Lorg/eclipse/jetty/server/Connector;)Ljava/lang/String;
      64: invokevirtual #174                // Method java/lang/StringBuilder.append:(Ljava/lang/String;)Ljava/lang/StringBuilder;
      67: pop
      68: iinc          4, 1
      71: goto          22
      74: aload_1
      75: invokevirtual #189                // Method java/lang/StringBuilder.toString:()Ljava/lang/String;
      78: areturn

  private java.lang.String getProtocols(org.eclipse.jetty.server.Connector);
    Code:
       0: aload_1
       1: invokeinterface #192,  1          // InterfaceMethod org/eclipse/jetty/server/Connector.getProtocols:()Ljava/util/List;
       6: astore_2
       7: aload_2
       8: ldc           #172                // String ,
      10: invokestatic  #195                // Method org/springframework/util/StringUtils.collectionToDelimitedString:(Ljava/util/Collection;Ljava/lang/String;)Ljava/lang/String;
      13: invokedynamic #201,  0            // InvokeDynamic #3:makeConcatWithConstants:(Ljava/lang/String;)Ljava/lang/String;
      18: areturn

  private java.lang.String getContextPath();
    Code:
       0: aload_0
       1: getfield      #28                 // Field server:Lorg/eclipse/jetty/server/Server;
       4: invokevirtual #115                // Method org/eclipse/jetty/server/Server.getHandlers:()[Lorg/eclipse/jetty/server/Handler;
       7: invokestatic  #204                // Method java/util/Arrays.stream:([Ljava/lang/Object;)Ljava/util/stream/Stream;
      10: aload_0
      11: invokedynamic #210,  0            // InvokeDynamic #4:apply:(Lorg/springframework/boot/web/embedded/jetty/JettyWebServer;)Ljava/util/function/Function;
      16: invokeinterface #214,  2          // InterfaceMethod java/util/stream/Stream.map:(Ljava/util/function/Function;)Ljava/util/stream/Stream;
      21: invokedynamic #220,  0            // InvokeDynamic #5:test:()Ljava/util/function/Predicate;
      26: invokeinterface #224,  2          // InterfaceMethod java/util/stream/Stream.filter:(Ljava/util/function/Predicate;)Ljava/util/stream/Stream;
      31: invokedynamic #228,  0            // InvokeDynamic #6:apply:()Ljava/util/function/Function;
      36: invokeinterface #214,  2          // InterfaceMethod java/util/stream/Stream.map:(Ljava/util/function/Function;)Ljava/util/stream/Stream;
      41: ldc           #231                // String
      43: invokestatic  #233                // Method java/util/stream/Collectors.joining:(Ljava/lang/CharSequence;)Ljava/util/stream/Collector;
      46: invokeinterface #239,  2          // InterfaceMethod java/util/stream/Stream.collect:(Ljava/util/stream/Collector;)Ljava/lang/Object;
      51: checkcast     #243                // class java/lang/String
      54: areturn

  private org.eclipse.jetty.server.handler.ContextHandler findContextHandler(org.eclipse.jetty.server.Handler);
    Code:
       0: aload_1
       1: instanceof    #73                 // class org/eclipse/jetty/server/handler/HandlerWrapper
       4: ifeq          34
       7: aload_1
       8: checkcast     #73                 // class org/eclipse/jetty/server/handler/HandlerWrapper
      11: astore_2
      12: aload_1
      13: instanceof    #245                // class org/eclipse/jetty/server/handler/ContextHandler
      16: ifeq          26
      19: aload_1
      20: checkcast     #245                // class org/eclipse/jetty/server/handler/ContextHandler
      23: astore_3
      24: aload_3
      25: areturn
      26: aload_2
      27: invokevirtual #75                 // Method org/eclipse/jetty/server/handler/HandlerWrapper.getHandler:()Lorg/eclipse/jetty/server/Handler;
      30: astore_1
      31: goto          0
      34: aconst_null
      35: areturn

  private void handleDeferredInitialize(org.eclipse.jetty.server.Handler...) throws java.lang.Exception;
    Code:
       0: aload_1
       1: astore_2
       2: aload_2
       3: arraylength
       4: istore_3
       5: iconst_0
       6: istore        4
       8: iload         4
      10: iload_3
      11: if_icmpge     107
      14: aload_2
      15: iload         4
      17: aaload
      18: astore        5
      20: aload         5
      22: instanceof    #247                // class org/springframework/boot/web/embedded/jetty/JettyEmbeddedWebAppContext
      25: ifeq          43
      28: aload         5
      30: checkcast     #247                // class org/springframework/boot/web/embedded/jetty/JettyEmbeddedWebAppContext
      33: astore        6
      35: aload         6
      37: invokevirtual #249                // Method org/springframework/boot/web/embedded/jetty/JettyEmbeddedWebAppContext.deferredInitialize:()V
      40: goto          101
      43: aload         5
      45: instanceof    #73                 // class org/eclipse/jetty/server/handler/HandlerWrapper
      48: ifeq          77
      51: aload         5
      53: checkcast     #73                 // class org/eclipse/jetty/server/handler/HandlerWrapper
      56: astore        7
      58: aload_0
      59: iconst_1
      60: anewarray     #119                // class org/eclipse/jetty/server/Handler
      63: dup
      64: iconst_0
      65: aload         7
      67: invokevirtual #75                 // Method org/eclipse/jetty/server/handler/HandlerWrapper.getHandler:()Lorg/eclipse/jetty/server/Handler;
      70: aastore
      71: invokevirtual #121                // Method handleDeferredInitialize:([Lorg/eclipse/jetty/server/Handler;)V
      74: goto          101
      77: aload         5
      79: instanceof    #252                // class org/eclipse/jetty/server/handler/HandlerCollection
      82: ifeq          101
      85: aload         5
      87: checkcast     #252                // class org/eclipse/jetty/server/handler/HandlerCollection
      90: astore        8
      92: aload_0
      93: aload         8
      95: invokevirtual #254                // Method org/eclipse/jetty/server/handler/HandlerCollection.getHandlers:()[Lorg/eclipse/jetty/server/Handler;
      98: invokevirtual #121                // Method handleDeferredInitialize:([Lorg/eclipse/jetty/server/Handler;)V
     101: iinc          4, 1
     104: goto          8
     107: return

  public void stop();
    Code:
       0: aload_0
       1: getfield      #12                 // Field monitor:Ljava/lang/Object;
       4: dup
       5: astore_1
       6: monitorenter
       7: aload_0
       8: iconst_0
       9: putfield      #112                // Field started:Z
      12: aload_0
      13: getfield      #36                 // Field gracefulShutdown:Lorg/springframework/boot/web/embedded/jetty/GracefulShutdown;
      16: ifnull        26
      19: aload_0
      20: getfield      #36                 // Field gracefulShutdown:Lorg/springframework/boot/web/embedded/jetty/GracefulShutdown;
      23: invokevirtual #255                // Method org/springframework/boot/web/embedded/jetty/GracefulShutdown.abort:()V
      26: aload_0
      27: getfield      #28                 // Field server:Lorg/eclipse/jetty/server/Server;
      30: invokevirtual #107                // Method org/eclipse/jetty/server/Server.stop:()V
      33: goto          59
      36: astore_2
      37: invokestatic  #260                // Method java/lang/Thread.currentThread:()Ljava/lang/Thread;
      40: invokevirtual #266                // Method java/lang/Thread.interrupt:()V
      43: goto          59
      46: astore_2
      47: new           #100                // class org/springframework/boot/web/server/WebServerException
      50: dup
      51: ldc_w         #269                // String Unable to stop embedded Jetty server
      54: aload_2
      55: invokespecial #104                // Method org/springframework/boot/web/server/WebServerException."<init>":(Ljava/lang/String;Ljava/lang/Throwable;)V
      58: athrow
      59: aload_1
      60: monitorexit
      61: goto          69
      64: astore_3
      65: aload_1
      66: monitorexit
      67: aload_3
      68: athrow
      69: return
    Exception table:
       from    to  target type
          26    33    36   Class java/lang/InterruptedException
          26    33    46   Class java/lang/Exception
           7    61    64   any
          64    67    64   any

  public int getPort();
    Code:
       0: aload_0
       1: getfield      #28                 // Field server:Lorg/eclipse/jetty/server/Server;
       4: invokevirtual #76                 // Method org/eclipse/jetty/server/Server.getConnectors:()[Lorg/eclipse/jetty/server/Connector;
       7: astore_1
       8: aload_1
       9: astore_2
      10: aload_2
      11: arraylength
      12: istore_3
      13: iconst_0
      14: istore        4
      16: iload         4
      18: iload_3
      19: if_icmpge     61
      22: aload_2
      23: iload         4
      25: aaload
      26: astore        5
      28: aload_0
      29: aload         5
      31: invokevirtual #178                // Method getLocalPort:(Lorg/eclipse/jetty/server/Connector;)Ljava/lang/Integer;
      34: astore        6
      36: aload         6
      38: ifnull        55
      41: aload         6
      43: invokevirtual #271                // Method java/lang/Integer.intValue:()I
      46: ifle          55
      49: aload         6
      51: invokevirtual #271                // Method java/lang/Integer.intValue:()I
      54: ireturn
      55: iinc          4, 1
      58: goto          16
      61: iconst_m1
      62: ireturn

  private java.lang.Integer getLocalPort(org.eclipse.jetty.server.Connector);
    Code:
       0: aload_1
       1: instanceof    #130                // class org/eclipse/jetty/server/NetworkConnector
       4: ifeq          22
       7: aload_1
       8: checkcast     #130                // class org/eclipse/jetty/server/NetworkConnector
      11: astore_2
      12: aload_2
      13: invokeinterface #276,  1          // InterfaceMethod org/eclipse/jetty/server/NetworkConnector.getLocalPort:()I
      18: invokestatic  #278                // Method java/lang/Integer.valueOf:(I)Ljava/lang/Integer;
      21: areturn
      22: iconst_0
      23: invokestatic  #278                // Method java/lang/Integer.valueOf:(I)Ljava/lang/Integer;
      26: areturn

  public void shutDownGracefully(org.springframework.boot.web.server.GracefulShutdownCallback);
    Code:
       0: aload_0
       1: getfield      #36                 // Field gracefulShutdown:Lorg/springframework/boot/web/embedded/jetty/GracefulShutdown;
       4: ifnonnull     17
       7: aload_1
       8: getstatic     #282                // Field org/springframework/boot/web/server/GracefulShutdownResult.IMMEDIATE:Lorg/springframework/boot/web/server/GracefulShutdownResult;
      11: invokeinterface #288,  2          // InterfaceMethod org/springframework/boot/web/server/GracefulShutdownCallback.shutdownComplete:(Lorg/springframework/boot/web/server/GracefulShutdownResult;)V
      16: return
      17: aload_0
      18: getfield      #36                 // Field gracefulShutdown:Lorg/springframework/boot/web/embedded/jetty/GracefulShutdown;
      21: aload_1
      22: invokevirtual #294                // Method org/springframework/boot/web/embedded/jetty/GracefulShutdown.shutDownGracefully:(Lorg/springframework/boot/web/server/GracefulShutdownCallback;)V
      25: return

  public org.eclipse.jetty.server.Server getServer();
    Code:
       0: aload_0
       1: getfield      #28                 // Field server:Lorg/eclipse/jetty/server/Server;
       4: areturn

  static {};
    Code:
       0: ldc           #2                  // class org/springframework/boot/web/embedded/jetty/JettyWebServer
       2: invokestatic  #298                // Method org/apache/commons/logging/LogFactory.getLog:(Ljava/lang/Class;)Lorg/apache/commons/logging/Log;
       5: putstatic     #142                // Field logger:Lorg/apache/commons/logging/Log;
       8: return
}
