Compiled from "JettyServletWebServerFactory.java"
public class org.springframework.boot.web.embedded.jetty.JettyServletWebServerFactory extends org.springframework.boot.web.servlet.server.AbstractServletWebServerFactory implements org.springframework.boot.web.embedded.jetty.ConfigurableJettyWebServerFactory,org.springframework.context.ResourceLoaderAware {
  private java.util.List<org.eclipse.jetty.webapp.Configuration> configurations;

  private boolean useForwardHeaders;

  private int acceptors;

  private int selectors;

  private java.util.Set<org.springframework.boot.web.embedded.jetty.JettyServerCustomizer> jettyServerCustomizers;

  private org.springframework.core.io.ResourceLoader resourceLoader;

  private org.eclipse.jetty.util.thread.ThreadPool threadPool;

  public org.springframework.boot.web.embedded.jetty.JettyServletWebServerFactory();
    Code:
       0: aload_0
       1: invokespecial #1                  // Method org/springframework/boot/web/servlet/server/AbstractServletWebServerFactory."<init>":()V
       4: aload_0
       5: new           #7                  // class java/util/ArrayList
       8: dup
       9: invokespecial #9                  // Method java/util/ArrayList."<init>":()V
      12: putfield      #10                 // Field configurations:Ljava/util/List;
      15: aload_0
      16: iconst_m1
      17: putfield      #16                 // Field acceptors:I
      20: aload_0
      21: iconst_m1
      22: putfield      #20                 // Field selectors:I
      25: aload_0
      26: new           #23                 // class java/util/LinkedHashSet
      29: dup
      30: invokespecial #25                 // Method java/util/LinkedHashSet."<init>":()V
      33: putfield      #26                 // Field jettyServerCustomizers:Ljava/util/Set;
      36: return

  public org.springframework.boot.web.embedded.jetty.JettyServletWebServerFactory(int);
    Code:
       0: aload_0
       1: iload_1
       2: invokespecial #30                 // Method org/springframework/boot/web/servlet/server/AbstractServletWebServerFactory."<init>":(I)V
       5: aload_0
       6: new           #7                  // class java/util/ArrayList
       9: dup
      10: invokespecial #9                  // Method java/util/ArrayList."<init>":()V
      13: putfield      #10                 // Field configurations:Ljava/util/List;
      16: aload_0
      17: iconst_m1
      18: putfield      #16                 // Field acceptors:I
      21: aload_0
      22: iconst_m1
      23: putfield      #20                 // Field selectors:I
      26: aload_0
      27: new           #23                 // class java/util/LinkedHashSet
      30: dup
      31: invokespecial #25                 // Method java/util/LinkedHashSet."<init>":()V
      34: putfield      #26                 // Field jettyServerCustomizers:Ljava/util/Set;
      37: return

  public org.springframework.boot.web.embedded.jetty.JettyServletWebServerFactory(java.lang.String, int);
    Code:
       0: aload_0
       1: aload_1
       2: iload_2
       3: invokespecial #33                 // Method org/springframework/boot/web/servlet/server/AbstractServletWebServerFactory."<init>":(Ljava/lang/String;I)V
       6: aload_0
       7: new           #7                  // class java/util/ArrayList
      10: dup
      11: invokespecial #9                  // Method java/util/ArrayList."<init>":()V
      14: putfield      #10                 // Field configurations:Ljava/util/List;
      17: aload_0
      18: iconst_m1
      19: putfield      #16                 // Field acceptors:I
      22: aload_0
      23: iconst_m1
      24: putfield      #20                 // Field selectors:I
      27: aload_0
      28: new           #23                 // class java/util/LinkedHashSet
      31: dup
      32: invokespecial #25                 // Method java/util/LinkedHashSet."<init>":()V
      35: putfield      #26                 // Field jettyServerCustomizers:Ljava/util/Set;
      38: return

  public org.springframework.boot.web.server.WebServer getWebServer(org.springframework.boot.web.servlet.ServletContextInitializer...);
    Code:
       0: new           #36                 // class org/springframework/boot/web/embedded/jetty/JettyEmbeddedWebAppContext
       3: dup
       4: invokespecial #38                 // Method org/springframework/boot/web/embedded/jetty/JettyEmbeddedWebAppContext."<init>":()V
       7: astore_2
       8: aload_0
       9: invokevirtual #39                 // Method getPort:()I
      12: iconst_0
      13: invokestatic  #43                 // Method java/lang/Math.max:(II)I
      16: istore_3
      17: new           #49                 // class java/net/InetSocketAddress
      20: dup
      21: aload_0
      22: invokevirtual #51                 // Method getAddress:()Ljava/net/InetAddress;
      25: iload_3
      26: invokespecial #55                 // Method java/net/InetSocketAddress."<init>":(Ljava/net/InetAddress;I)V
      29: astore        4
      31: aload_0
      32: aload         4
      34: invokevirtual #58                 // Method createServer:(Ljava/net/InetSocketAddress;)Lorg/eclipse/jetty/server/Server;
      37: astore        5
      39: aload_0
      40: aload_2
      41: aload_1
      42: invokevirtual #62                 // Method configureWebAppContext:(Lorg/eclipse/jetty/webapp/WebAppContext;[Lorg/springframework/boot/web/servlet/ServletContextInitializer;)V
      45: aload         5
      47: aload_0
      48: aload_2
      49: invokevirtual #66                 // Method addHandlerWrappers:(Lorg/eclipse/jetty/server/Handler;)Lorg/eclipse/jetty/server/Handler;
      52: invokevirtual #70                 // Method org/eclipse/jetty/server/Server.setHandler:(Lorg/eclipse/jetty/server/Handler;)V
      55: aload_0
      56: getfield      #76                 // Field logger:Lorg/apache/commons/logging/Log;
      59: iload_3
      60: invokedynamic #80,  0             // InvokeDynamic #0:makeConcatWithConstants:(I)Ljava/lang/String;
      65: invokeinterface #84,  2           // InterfaceMethod org/apache/commons/logging/Log.info:(Ljava/lang/Object;)V
      70: aload_0
      71: invokevirtual #90                 // Method getSsl:()Lorg/springframework/boot/web/server/Ssl;
      74: invokestatic  #94                 // Method org/springframework/boot/web/server/Ssl.isEnabled:(Lorg/springframework/boot/web/server/Ssl;)Z
      77: ifeq          88
      80: aload_0
      81: aload         5
      83: aload         4
      85: invokevirtual #100                // Method customizeSsl:(Lorg/eclipse/jetty/server/Server;Ljava/net/InetSocketAddress;)V
      88: aload_0
      89: invokevirtual #104                // Method getServerCustomizers:()Ljava/util/Collection;
      92: invokeinterface #108,  1          // InterfaceMethod java/util/Collection.iterator:()Ljava/util/Iterator;
      97: astore        6
      99: aload         6
     101: invokeinterface #114,  1          // InterfaceMethod java/util/Iterator.hasNext:()Z
     106: ifeq          133
     109: aload         6
     111: invokeinterface #120,  1          // InterfaceMethod java/util/Iterator.next:()Ljava/lang/Object;
     116: checkcast     #124                // class org/springframework/boot/web/embedded/jetty/JettyServerCustomizer
     119: astore        7
     121: aload         7
     123: aload         5
     125: invokeinterface #126,  2          // InterfaceMethod org/springframework/boot/web/embedded/jetty/JettyServerCustomizer.customize:(Lorg/eclipse/jetty/server/Server;)V
     130: goto          99
     133: aload_0
     134: getfield      #130                // Field useForwardHeaders:Z
     137: ifeq          152
     140: new           #134                // class org/springframework/boot/web/embedded/jetty/ForwardHeadersCustomizer
     143: dup
     144: invokespecial #136                // Method org/springframework/boot/web/embedded/jetty/ForwardHeadersCustomizer."<init>":()V
     147: aload         5
     149: invokevirtual #137                // Method org/springframework/boot/web/embedded/jetty/ForwardHeadersCustomizer.customize:(Lorg/eclipse/jetty/server/Server;)V
     152: aload_0
     153: invokevirtual #138                // Method getShutdown:()Lorg/springframework/boot/web/server/Shutdown;
     156: getstatic     #142                // Field org/springframework/boot/web/server/Shutdown.GRACEFUL:Lorg/springframework/boot/web/server/Shutdown;
     159: if_acmpne     188
     162: new           #148                // class org/eclipse/jetty/server/handler/StatisticsHandler
     165: dup
     166: invokespecial #150                // Method org/eclipse/jetty/server/handler/StatisticsHandler."<init>":()V
     169: astore        6
     171: aload         6
     173: aload         5
     175: invokevirtual #151                // Method org/eclipse/jetty/server/Server.getHandler:()Lorg/eclipse/jetty/server/Handler;
     178: invokevirtual #155                // Method org/eclipse/jetty/server/handler/StatisticsHandler.setHandler:(Lorg/eclipse/jetty/server/Handler;)V
     181: aload         5
     183: aload         6
     185: invokevirtual #70                 // Method org/eclipse/jetty/server/Server.setHandler:(Lorg/eclipse/jetty/server/Handler;)V
     188: aload_0
     189: aload         5
     191: invokevirtual #156                // Method getJettyWebServer:(Lorg/eclipse/jetty/server/Server;)Lorg/springframework/boot/web/embedded/jetty/JettyWebServer;
     194: areturn

  private org.eclipse.jetty.server.Server createServer(java.net.InetSocketAddress);
    Code:
       0: new           #71                 // class org/eclipse/jetty/server/Server
       3: dup
       4: aload_0
       5: invokevirtual #160                // Method getThreadPool:()Lorg/eclipse/jetty/util/thread/ThreadPool;
       8: invokespecial #164                // Method org/eclipse/jetty/server/Server."<init>":(Lorg/eclipse/jetty/util/thread/ThreadPool;)V
      11: astore_2
      12: aload_2
      13: iconst_1
      14: anewarray     #167                // class org/eclipse/jetty/server/Connector
      17: dup
      18: iconst_0
      19: aload_0
      20: aload_1
      21: aload_2
      22: invokevirtual #169                // Method createConnector:(Ljava/net/InetSocketAddress;Lorg/eclipse/jetty/server/Server;)Lorg/eclipse/jetty/server/AbstractConnector;
      25: aastore
      26: invokevirtual #173                // Method org/eclipse/jetty/server/Server.setConnectors:([Lorg/eclipse/jetty/server/Connector;)V
      29: aload_2
      30: lconst_0
      31: invokevirtual #177                // Method org/eclipse/jetty/server/Server.setStopTimeout:(J)V
      34: aload_2
      35: areturn

  private org.eclipse.jetty.server.AbstractConnector createConnector(java.net.InetSocketAddress, org.eclipse.jetty.server.Server);
    Code:
       0: new           #181                // class org/eclipse/jetty/server/HttpConfiguration
       3: dup
       4: invokespecial #183                // Method org/eclipse/jetty/server/HttpConfiguration."<init>":()V
       7: astore_3
       8: aload_3
       9: iconst_0
      10: invokevirtual #184                // Method org/eclipse/jetty/server/HttpConfiguration.setSendServerVersion:(Z)V
      13: new           #7                  // class java/util/ArrayList
      16: dup
      17: invokespecial #9                  // Method java/util/ArrayList."<init>":()V
      20: astore        4
      22: aload         4
      24: new           #188                // class org/eclipse/jetty/server/HttpConnectionFactory
      27: dup
      28: aload_3
      29: invokespecial #190                // Method org/eclipse/jetty/server/HttpConnectionFactory."<init>":(Lorg/eclipse/jetty/server/HttpConfiguration;)V
      32: invokeinterface #193,  2          // InterfaceMethod java/util/List.add:(Ljava/lang/Object;)Z
      37: pop
      38: aload_0
      39: invokevirtual #199                // Method getHttp2:()Lorg/springframework/boot/web/server/Http2;
      42: ifnull        71
      45: aload_0
      46: invokevirtual #199                // Method getHttp2:()Lorg/springframework/boot/web/server/Http2;
      49: invokevirtual #203                // Method org/springframework/boot/web/server/Http2.isEnabled:()Z
      52: ifeq          71
      55: aload         4
      57: new           #207                // class org/eclipse/jetty/http2/server/HTTP2CServerConnectionFactory
      60: dup
      61: aload_3
      62: invokespecial #209                // Method org/eclipse/jetty/http2/server/HTTP2CServerConnectionFactory."<init>":(Lorg/eclipse/jetty/server/HttpConfiguration;)V
      65: invokeinterface #193,  2          // InterfaceMethod java/util/List.add:(Ljava/lang/Object;)Z
      70: pop
      71: new           #210                // class org/eclipse/jetty/server/ServerConnector
      74: dup
      75: aload_2
      76: aload_0
      77: getfield      #16                 // Field acceptors:I
      80: aload_0
      81: getfield      #20                 // Field selectors:I
      84: aload         4
      86: iconst_0
      87: anewarray     #212                // class org/eclipse/jetty/server/ConnectionFactory
      90: invokeinterface #214,  2          // InterfaceMethod java/util/List.toArray:([Ljava/lang/Object;)[Ljava/lang/Object;
      95: checkcast     #218                // class "[Lorg/eclipse/jetty/server/ConnectionFactory;"
      98: invokespecial #220                // Method org/eclipse/jetty/server/ServerConnector."<init>":(Lorg/eclipse/jetty/server/Server;II[Lorg/eclipse/jetty/server/ConnectionFactory;)V
     101: astore        5
     103: aload         5
     105: aload_1
     106: invokevirtual #223                // Method java/net/InetSocketAddress.getHostString:()Ljava/lang/String;
     109: invokevirtual #227                // Method org/eclipse/jetty/server/ServerConnector.setHost:(Ljava/lang/String;)V
     112: aload         5
     114: aload_1
     115: invokevirtual #231                // Method java/net/InetSocketAddress.getPort:()I
     118: invokevirtual #232                // Method org/eclipse/jetty/server/ServerConnector.setPort:(I)V
     121: aload         5
     123: areturn

  private org.eclipse.jetty.server.Handler addHandlerWrappers(org.eclipse.jetty.server.Handler);
    Code:
       0: aload_0
       1: invokevirtual #235                // Method getCompression:()Lorg/springframework/boot/web/server/Compression;
       4: ifnull        30
       7: aload_0
       8: invokevirtual #235                // Method getCompression:()Lorg/springframework/boot/web/server/Compression;
      11: invokevirtual #239                // Method org/springframework/boot/web/server/Compression.getEnabled:()Z
      14: ifeq          30
      17: aload_0
      18: aload_1
      19: aload_0
      20: invokevirtual #235                // Method getCompression:()Lorg/springframework/boot/web/server/Compression;
      23: invokestatic  #244                // Method org/springframework/boot/web/embedded/jetty/JettyHandlerWrappers.createGzipHandlerWrapper:(Lorg/springframework/boot/web/server/Compression;)Lorg/eclipse/jetty/server/handler/HandlerWrapper;
      26: invokevirtual #250                // Method applyWrapper:(Lorg/eclipse/jetty/server/Handler;Lorg/eclipse/jetty/server/handler/HandlerWrapper;)Lorg/eclipse/jetty/server/Handler;
      29: astore_1
      30: aload_0
      31: invokevirtual #254                // Method getServerHeader:()Ljava/lang/String;
      34: invokestatic  #257                // Method org/springframework/util/StringUtils.hasText:(Ljava/lang/String;)Z
      37: ifeq          53
      40: aload_0
      41: aload_1
      42: aload_0
      43: invokevirtual #254                // Method getServerHeader:()Ljava/lang/String;
      46: invokestatic  #263                // Method org/springframework/boot/web/embedded/jetty/JettyHandlerWrappers.createServerHeaderHandlerWrapper:(Ljava/lang/String;)Lorg/eclipse/jetty/server/handler/HandlerWrapper;
      49: invokevirtual #250                // Method applyWrapper:(Lorg/eclipse/jetty/server/Handler;Lorg/eclipse/jetty/server/handler/HandlerWrapper;)Lorg/eclipse/jetty/server/Handler;
      52: astore_1
      53: aload_0
      54: invokevirtual #267                // Method getCookieSameSiteSuppliers:()Ljava/util/List;
      57: invokestatic  #271                // Method org/springframework/util/CollectionUtils.isEmpty:(Ljava/util/Collection;)Z
      60: ifne          80
      63: aload_0
      64: aload_1
      65: new           #277                // class org/springframework/boot/web/embedded/jetty/JettyServletWebServerFactory$SuppliedSameSiteCookieHandlerWrapper
      68: dup
      69: aload_0
      70: invokevirtual #267                // Method getCookieSameSiteSuppliers:()Ljava/util/List;
      73: invokespecial #279                // Method org/springframework/boot/web/embedded/jetty/JettyServletWebServerFactory$SuppliedSameSiteCookieHandlerWrapper."<init>":(Ljava/util/List;)V
      76: invokevirtual #250                // Method applyWrapper:(Lorg/eclipse/jetty/server/Handler;Lorg/eclipse/jetty/server/handler/HandlerWrapper;)Lorg/eclipse/jetty/server/Handler;
      79: astore_1
      80: aload_1
      81: areturn

  private org.eclipse.jetty.server.Handler applyWrapper(org.eclipse.jetty.server.Handler, org.eclipse.jetty.server.handler.HandlerWrapper);
    Code:
       0: aload_2
       1: aload_1
       2: invokevirtual #282                // Method org/eclipse/jetty/server/handler/HandlerWrapper.setHandler:(Lorg/eclipse/jetty/server/Handler;)V
       5: aload_2
       6: areturn

  private void customizeSsl(org.eclipse.jetty.server.Server, java.net.InetSocketAddress);
    Code:
       0: new           #285                // class org/springframework/boot/web/embedded/jetty/SslServerCustomizer
       3: dup
       4: aload_0
       5: invokevirtual #199                // Method getHttp2:()Lorg/springframework/boot/web/server/Http2;
       8: aload_2
       9: aload_0
      10: invokevirtual #90                 // Method getSsl:()Lorg/springframework/boot/web/server/Ssl;
      13: invokevirtual #287                // Method org/springframework/boot/web/server/Ssl.getClientAuth:()Lorg/springframework/boot/web/server/Ssl$ClientAuth;
      16: aload_0
      17: invokevirtual #291                // Method getSslBundle:()Lorg/springframework/boot/ssl/SslBundle;
      20: invokespecial #295                // Method org/springframework/boot/web/embedded/jetty/SslServerCustomizer."<init>":(Lorg/springframework/boot/web/server/Http2;Ljava/net/InetSocketAddress;Lorg/springframework/boot/web/server/Ssl$ClientAuth;Lorg/springframework/boot/ssl/SslBundle;)V
      23: aload_1
      24: invokevirtual #298                // Method org/springframework/boot/web/embedded/jetty/SslServerCustomizer.customize:(Lorg/eclipse/jetty/server/Server;)V
      27: return

  protected final void configureWebAppContext(org.eclipse.jetty.webapp.WebAppContext, org.springframework.boot.web.servlet.ServletContextInitializer...);
    Code:
       0: aload_1
       1: ldc_w         #299                // String Context must not be null
       4: invokestatic  #301                // Method org/springframework/util/Assert.notNull:(Ljava/lang/Object;Ljava/lang/String;)V
       7: aload_1
       8: invokevirtual #307                // Method org/eclipse/jetty/webapp/WebAppContext.clearAliasChecks:()V
      11: aload_1
      12: aload_0
      13: invokevirtual #312                // Method getTempDirectory:()Ljava/io/File;
      16: invokevirtual #316                // Method org/eclipse/jetty/webapp/WebAppContext.setTempDirectory:(Ljava/io/File;)V
      19: aload_0
      20: getfield      #320                // Field resourceLoader:Lorg/springframework/core/io/ResourceLoader;
      23: ifnull        39
      26: aload_1
      27: aload_0
      28: getfield      #320                // Field resourceLoader:Lorg/springframework/core/io/ResourceLoader;
      31: invokeinterface #324,  1          // InterfaceMethod org/springframework/core/io/ResourceLoader.getClassLoader:()Ljava/lang/ClassLoader;
      36: invokevirtual #330                // Method org/eclipse/jetty/webapp/WebAppContext.setClassLoader:(Ljava/lang/ClassLoader;)V
      39: aload_0
      40: invokevirtual #334                // Method getContextPath:()Ljava/lang/String;
      43: astore_3
      44: aload_1
      45: aload_3
      46: invokestatic  #337                // Method org/springframework/util/StringUtils.hasLength:(Ljava/lang/String;)Z
      49: ifeq          56
      52: aload_3
      53: goto          59
      56: ldc_w         #340                // String /
      59: invokevirtual #342                // Method org/eclipse/jetty/webapp/WebAppContext.setContextPath:(Ljava/lang/String;)V
      62: aload_1
      63: aload_0
      64: invokevirtual #345                // Method getDisplayName:()Ljava/lang/String;
      67: invokevirtual #348                // Method org/eclipse/jetty/webapp/WebAppContext.setDisplayName:(Ljava/lang/String;)V
      70: aload_0
      71: aload_1
      72: invokevirtual #351                // Method configureDocumentRoot:(Lorg/eclipse/jetty/webapp/WebAppContext;)V
      75: aload_0
      76: invokevirtual #355                // Method isRegisterDefaultServlet:()Z
      79: ifeq          87
      82: aload_0
      83: aload_1
      84: invokevirtual #358                // Method addDefaultServlet:(Lorg/eclipse/jetty/webapp/WebAppContext;)V
      87: aload_0
      88: invokevirtual #361                // Method shouldRegisterJspServlet:()Z
      91: ifeq          113
      94: aload_0
      95: aload_1
      96: invokevirtual #364                // Method addJspServlet:(Lorg/eclipse/jetty/webapp/WebAppContext;)V
      99: aload_1
     100: new           #367                // class org/springframework/boot/web/embedded/jetty/JasperInitializer
     103: dup
     104: aload_1
     105: invokespecial #369                // Method org/springframework/boot/web/embedded/jetty/JasperInitializer."<init>":(Lorg/eclipse/jetty/webapp/WebAppContext;)V
     108: iconst_1
     109: invokevirtual #371                // Method org/eclipse/jetty/webapp/WebAppContext.addBean:(Ljava/lang/Object;Z)Z
     112: pop
     113: aload_0
     114: aload_1
     115: invokevirtual #375                // Method addLocaleMappings:(Lorg/eclipse/jetty/webapp/WebAppContext;)V
     118: aload_0
     119: aload_2
     120: invokevirtual #378                // Method mergeInitializers:([Lorg/springframework/boot/web/servlet/ServletContextInitializer;)[Lorg/springframework/boot/web/servlet/ServletContextInitializer;
     123: astore        4
     125: aload_0
     126: aload_1
     127: aload         4
     129: invokevirtual #382                // Method getWebAppContextConfigurations:(Lorg/eclipse/jetty/webapp/WebAppContext;[Lorg/springframework/boot/web/servlet/ServletContextInitializer;)[Lorg/eclipse/jetty/webapp/Configuration;
     132: astore        5
     134: aload_1
     135: aload         5
     137: invokevirtual #386                // Method org/eclipse/jetty/webapp/WebAppContext.setConfigurations:([Lorg/eclipse/jetty/webapp/Configuration;)V
     140: aload_1
     141: iconst_1
     142: invokevirtual #390                // Method org/eclipse/jetty/webapp/WebAppContext.setThrowUnavailableOnStartupException:(Z)V
     145: aload_0
     146: aload_1
     147: invokevirtual #393                // Method configureSession:(Lorg/eclipse/jetty/webapp/WebAppContext;)V
     150: aload_0
     151: aload_1
     152: invokevirtual #396                // Method postProcessWebAppContext:(Lorg/eclipse/jetty/webapp/WebAppContext;)V
     155: return

  private void configureSession(org.eclipse.jetty.webapp.WebAppContext);
    Code:
       0: aload_1
       1: invokevirtual #399                // Method org/eclipse/jetty/webapp/WebAppContext.getSessionHandler:()Lorg/eclipse/jetty/server/session/SessionHandler;
       4: astore_2
       5: aload_0
       6: invokevirtual #403                // Method getSession:()Lorg/springframework/boot/web/servlet/server/Session;
       9: invokevirtual #407                // Method org/springframework/boot/web/servlet/server/Session.getCookie:()Lorg/springframework/boot/web/servlet/server/Session$Cookie;
      12: invokevirtual #413                // Method org/springframework/boot/web/servlet/server/Session$Cookie.getSameSite:()Lorg/springframework/boot/web/server/Cookie$SameSite;
      15: astore_3
      16: aload_3
      17: ifnull        31
      20: aload_2
      21: aload_3
      22: invokevirtual #419                // Method org/springframework/boot/web/server/Cookie$SameSite.name:()Ljava/lang/String;
      25: invokestatic  #424                // Method org/eclipse/jetty/http/HttpCookie$SameSite.valueOf:(Ljava/lang/String;)Lorg/eclipse/jetty/http/HttpCookie$SameSite;
      28: invokevirtual #430                // Method org/eclipse/jetty/server/session/SessionHandler.setSameSite:(Lorg/eclipse/jetty/http/HttpCookie$SameSite;)V
      31: aload_0
      32: invokevirtual #403                // Method getSession:()Lorg/springframework/boot/web/servlet/server/Session;
      35: invokevirtual #436                // Method org/springframework/boot/web/servlet/server/Session.getTimeout:()Ljava/time/Duration;
      38: astore        4
      40: aload_2
      41: aload_0
      42: aload         4
      44: invokevirtual #440                // Method isNegative:(Ljava/time/Duration;)Z
      47: ifeq          54
      50: iconst_m1
      51: goto          60
      54: aload         4
      56: invokevirtual #444                // Method java/time/Duration.getSeconds:()J
      59: l2i
      60: invokevirtual #450                // Method org/eclipse/jetty/server/session/SessionHandler.setMaxInactiveInterval:(I)V
      63: aload_0
      64: invokevirtual #403                // Method getSession:()Lorg/springframework/boot/web/servlet/server/Session;
      67: invokevirtual #453                // Method org/springframework/boot/web/servlet/server/Session.isPersistent:()Z
      70: ifeq          114
      73: new           #456                // class org/eclipse/jetty/server/session/DefaultSessionCache
      76: dup
      77: aload_2
      78: invokespecial #458                // Method org/eclipse/jetty/server/session/DefaultSessionCache."<init>":(Lorg/eclipse/jetty/server/session/SessionHandler;)V
      81: astore        5
      83: new           #461                // class org/eclipse/jetty/server/session/FileSessionDataStore
      86: dup
      87: invokespecial #463                // Method org/eclipse/jetty/server/session/FileSessionDataStore."<init>":()V
      90: astore        6
      92: aload         6
      94: aload_0
      95: invokevirtual #464                // Method getValidSessionStoreDir:()Ljava/io/File;
      98: invokevirtual #467                // Method org/eclipse/jetty/server/session/FileSessionDataStore.setStoreDir:(Ljava/io/File;)V
     101: aload         5
     103: aload         6
     105: invokevirtual #470                // Method org/eclipse/jetty/server/session/DefaultSessionCache.setSessionDataStore:(Lorg/eclipse/jetty/server/session/SessionDataStore;)V
     108: aload_2
     109: aload         5
     111: invokevirtual #474                // Method org/eclipse/jetty/server/session/SessionHandler.setSessionCache:(Lorg/eclipse/jetty/server/session/SessionCache;)V
     114: return

  private boolean isNegative(java.time.Duration);
    Code:
       0: aload_1
       1: ifnull        11
       4: aload_1
       5: invokevirtual #478                // Method java/time/Duration.isNegative:()Z
       8: ifeq          15
      11: iconst_1
      12: goto          16
      15: iconst_0
      16: ireturn

  private void addLocaleMappings(org.eclipse.jetty.webapp.WebAppContext);
    Code:
       0: aload_0
       1: invokevirtual #480                // Method getLocaleCharsetMappings:()Ljava/util/Map;
       4: aload_1
       5: invokedynamic #484,  0            // InvokeDynamic #1:accept:(Lorg/eclipse/jetty/webapp/WebAppContext;)Ljava/util/function/BiConsumer;
      10: invokeinterface #488,  2          // InterfaceMethod java/util/Map.forEach:(Ljava/util/function/BiConsumer;)V
      15: return

  private java.io.File getTempDirectory();
    Code:
       0: ldc_w         #494                // String java.io.tmpdir
       3: invokestatic  #496                // Method java/lang/System.getProperty:(Ljava/lang/String;)Ljava/lang/String;
       6: astore_1
       7: aload_1
       8: ifnull        22
      11: new           #502                // class java/io/File
      14: dup
      15: aload_1
      16: invokespecial #504                // Method java/io/File."<init>":(Ljava/lang/String;)V
      19: goto          23
      22: aconst_null
      23: areturn

  private void configureDocumentRoot(org.eclipse.jetty.webapp.WebAppContext);
    Code:
       0: aload_0
       1: invokevirtual #506                // Method getValidDocumentRoot:()Ljava/io/File;
       4: astore_2
       5: aload_2
       6: ifnull        13
       9: aload_2
      10: goto          20
      13: aload_0
      14: ldc_w         #509                // String jetty-docbase
      17: invokevirtual #511                // Method createTempDir:(Ljava/lang/String;)Ljava/io/File;
      20: astore_3
      21: new           #7                  // class java/util/ArrayList
      24: dup
      25: invokespecial #9                  // Method java/util/ArrayList."<init>":()V
      28: astore        4
      30: aload_3
      31: invokevirtual #515                // Method java/io/File.isDirectory:()Z
      34: ifeq          47
      37: aload_3
      38: invokevirtual #518                // Method java/io/File.getCanonicalFile:()Ljava/io/File;
      41: invokestatic  #521                // Method org/eclipse/jetty/util/resource/Resource.newResource:(Ljava/io/File;)Lorg/eclipse/jetty/util/resource/Resource;
      44: goto          54
      47: aload_3
      48: invokestatic  #521                // Method org/eclipse/jetty/util/resource/Resource.newResource:(Ljava/io/File;)Lorg/eclipse/jetty/util/resource/Resource;
      51: invokestatic  #527                // Method org/eclipse/jetty/util/resource/JarResource.newJarResource:(Lorg/eclipse/jetty/util/resource/Resource;)Lorg/eclipse/jetty/util/resource/Resource;
      54: astore        5
      56: aload         4
      58: aload_2
      59: ifnull        74
      62: new           #533                // class org/springframework/boot/web/embedded/jetty/JettyServletWebServerFactory$LoaderHidingResource
      65: dup
      66: aload         5
      68: invokespecial #535                // Method org/springframework/boot/web/embedded/jetty/JettyServletWebServerFactory$LoaderHidingResource."<init>":(Lorg/eclipse/jetty/util/resource/Resource;)V
      71: goto          76
      74: aload         5
      76: invokeinterface #193,  2          // InterfaceMethod java/util/List.add:(Ljava/lang/Object;)Z
      81: pop
      82: aload_0
      83: invokevirtual #538                // Method getUrlsOfJarsWithMetaInfResources:()Ljava/util/List;
      86: invokeinterface #541,  1          // InterfaceMethod java/util/List.iterator:()Ljava/util/Iterator;
      91: astore        6
      93: aload         6
      95: invokeinterface #114,  1          // InterfaceMethod java/util/Iterator.hasNext:()Z
     100: ifeq          152
     103: aload         6
     105: invokeinterface #120,  1          // InterfaceMethod java/util/Iterator.next:()Ljava/lang/Object;
     110: checkcast     #542                // class java/net/URL
     113: astore        7
     115: aload_0
     116: aload         7
     118: invokevirtual #544                // Method createResource:(Ljava/net/URL;)Lorg/eclipse/jetty/util/resource/Resource;
     121: astore        8
     123: aload         8
     125: invokevirtual #548                // Method org/eclipse/jetty/util/resource/Resource.exists:()Z
     128: ifeq          149
     131: aload         8
     133: invokevirtual #551                // Method org/eclipse/jetty/util/resource/Resource.isDirectory:()Z
     136: ifeq          149
     139: aload         4
     141: aload         8
     143: invokeinterface #193,  2          // InterfaceMethod java/util/List.add:(Ljava/lang/Object;)Z
     148: pop
     149: goto          93
     152: aload_1
     153: new           #552                // class org/eclipse/jetty/util/resource/ResourceCollection
     156: dup
     157: aload         4
     159: iconst_0
     160: anewarray     #522                // class org/eclipse/jetty/util/resource/Resource
     163: invokeinterface #214,  2          // InterfaceMethod java/util/List.toArray:([Ljava/lang/Object;)[Ljava/lang/Object;
     168: checkcast     #554                // class "[Lorg/eclipse/jetty/util/resource/Resource;"
     171: invokespecial #556                // Method org/eclipse/jetty/util/resource/ResourceCollection."<init>":([Lorg/eclipse/jetty/util/resource/Resource;)V
     174: invokevirtual #559                // Method org/eclipse/jetty/webapp/WebAppContext.setBaseResource:(Lorg/eclipse/jetty/util/resource/Resource;)V
     177: goto          192
     180: astore        4
     182: new           #564                // class java/lang/IllegalStateException
     185: dup
     186: aload         4
     188: invokespecial #566                // Method java/lang/IllegalStateException."<init>":(Ljava/lang/Throwable;)V
     191: athrow
     192: return
    Exception table:
       from    to  target type
          21   177   180   Class java/lang/Exception

  private org.eclipse.jetty.util.resource.Resource createResource(java.net.URL) throws java.lang.Exception;
    Code:
       0: ldc_w         #569                // String file
       3: aload_1
       4: invokevirtual #571                // Method java/net/URL.getProtocol:()Ljava/lang/String;
       7: invokevirtual #574                // Method java/lang/String.equals:(Ljava/lang/Object;)Z
      10: ifeq          42
      13: new           #502                // class java/io/File
      16: dup
      17: aload_1
      18: invokevirtual #579                // Method java/net/URL.toURI:()Ljava/net/URI;
      21: invokespecial #583                // Method java/io/File."<init>":(Ljava/net/URI;)V
      24: astore_2
      25: aload_2
      26: invokevirtual #586                // Method java/io/File.isFile:()Z
      29: ifeq          42
      32: aload_1
      33: invokedynamic #589,  0            // InvokeDynamic #2:makeConcatWithConstants:(Ljava/net/URL;)Ljava/lang/String;
      38: invokestatic  #592                // Method org/eclipse/jetty/util/resource/Resource.newResource:(Ljava/lang/String;)Lorg/eclipse/jetty/util/resource/Resource;
      41: areturn
      42: aload_1
      43: invokedynamic #595,  0            // InvokeDynamic #3:makeConcatWithConstants:(Ljava/net/URL;)Ljava/lang/String;
      48: invokestatic  #592                // Method org/eclipse/jetty/util/resource/Resource.newResource:(Ljava/lang/String;)Lorg/eclipse/jetty/util/resource/Resource;
      51: areturn

  protected final void addDefaultServlet(org.eclipse.jetty.webapp.WebAppContext);
    Code:
       0: aload_1
       1: ldc_w         #299                // String Context must not be null
       4: invokestatic  #301                // Method org/springframework/util/Assert.notNull:(Ljava/lang/Object;Ljava/lang/String;)V
       7: new           #596                // class org/eclipse/jetty/servlet/ServletHolder
      10: dup
      11: invokespecial #598                // Method org/eclipse/jetty/servlet/ServletHolder."<init>":()V
      14: astore_2
      15: aload_2
      16: ldc_w         #599                // String default
      19: invokevirtual #601                // Method org/eclipse/jetty/servlet/ServletHolder.setName:(Ljava/lang/String;)V
      22: aload_2
      23: ldc_w         #604                // String org.eclipse.jetty.servlet.DefaultServlet
      26: invokevirtual #606                // Method org/eclipse/jetty/servlet/ServletHolder.setClassName:(Ljava/lang/String;)V
      29: aload_2
      30: ldc_w         #609                // String dirAllowed
      33: ldc_w         #611                // String false
      36: invokevirtual #613                // Method org/eclipse/jetty/servlet/ServletHolder.setInitParameter:(Ljava/lang/String;Ljava/lang/String;)V
      39: aload_2
      40: iconst_1
      41: invokevirtual #617                // Method org/eclipse/jetty/servlet/ServletHolder.setInitOrder:(I)V
      44: aload_1
      45: invokevirtual #620                // Method org/eclipse/jetty/webapp/WebAppContext.getServletHandler:()Lorg/eclipse/jetty/servlet/ServletHandler;
      48: aload_2
      49: ldc_w         #340                // String /
      52: invokevirtual #624                // Method org/eclipse/jetty/servlet/ServletHandler.addServletWithMapping:(Lorg/eclipse/jetty/servlet/ServletHolder;Ljava/lang/String;)V
      55: aload_1
      56: invokevirtual #620                // Method org/eclipse/jetty/webapp/WebAppContext.getServletHandler:()Lorg/eclipse/jetty/servlet/ServletHandler;
      59: ldc_w         #340                // String /
      62: invokevirtual #630                // Method org/eclipse/jetty/servlet/ServletHandler.getServletMapping:(Ljava/lang/String;)Lorg/eclipse/jetty/servlet/ServletMapping;
      65: astore_3
      66: aload_3
      67: iconst_1
      68: invokevirtual #634                // Method org/eclipse/jetty/servlet/ServletMapping.setFromDefaultDescriptor:(Z)V
      71: return

  protected final void addJspServlet(org.eclipse.jetty.webapp.WebAppContext);
    Code:
       0: aload_1
       1: ldc_w         #299                // String Context must not be null
       4: invokestatic  #301                // Method org/springframework/util/Assert.notNull:(Ljava/lang/Object;Ljava/lang/String;)V
       7: new           #596                // class org/eclipse/jetty/servlet/ServletHolder
      10: dup
      11: invokespecial #598                // Method org/eclipse/jetty/servlet/ServletHolder."<init>":()V
      14: astore_2
      15: aload_2
      16: ldc_w         #639                // String jsp
      19: invokevirtual #601                // Method org/eclipse/jetty/servlet/ServletHolder.setName:(Ljava/lang/String;)V
      22: aload_2
      23: aload_0
      24: invokevirtual #641                // Method getJsp:()Lorg/springframework/boot/web/servlet/server/Jsp;
      27: invokevirtual #645                // Method org/springframework/boot/web/servlet/server/Jsp.getClassName:()Ljava/lang/String;
      30: invokevirtual #606                // Method org/eclipse/jetty/servlet/ServletHolder.setClassName:(Ljava/lang/String;)V
      33: aload_2
      34: ldc_w         #650                // String fork
      37: ldc_w         #611                // String false
      40: invokevirtual #613                // Method org/eclipse/jetty/servlet/ServletHolder.setInitParameter:(Ljava/lang/String;Ljava/lang/String;)V
      43: aload_2
      44: aload_0
      45: invokevirtual #641                // Method getJsp:()Lorg/springframework/boot/web/servlet/server/Jsp;
      48: invokevirtual #652                // Method org/springframework/boot/web/servlet/server/Jsp.getInitParameters:()Ljava/util/Map;
      51: invokevirtual #655                // Method org/eclipse/jetty/servlet/ServletHolder.setInitParameters:(Ljava/util/Map;)V
      54: aload_2
      55: iconst_3
      56: invokevirtual #617                // Method org/eclipse/jetty/servlet/ServletHolder.setInitOrder:(I)V
      59: aload_1
      60: invokevirtual #620                // Method org/eclipse/jetty/webapp/WebAppContext.getServletHandler:()Lorg/eclipse/jetty/servlet/ServletHandler;
      63: aload_2
      64: invokevirtual #659                // Method org/eclipse/jetty/servlet/ServletHandler.addServlet:(Lorg/eclipse/jetty/servlet/ServletHolder;)V
      67: new           #635                // class org/eclipse/jetty/servlet/ServletMapping
      70: dup
      71: invokespecial #663                // Method org/eclipse/jetty/servlet/ServletMapping."<init>":()V
      74: astore_3
      75: aload_3
      76: ldc_w         #639                // String jsp
      79: invokevirtual #664                // Method org/eclipse/jetty/servlet/ServletMapping.setServletName:(Ljava/lang/String;)V
      82: aload_3
      83: iconst_2
      84: anewarray     #575                // class java/lang/String
      87: dup
      88: iconst_0
      89: ldc_w         #667                // String *.jsp
      92: aastore
      93: dup
      94: iconst_1
      95: ldc_w         #669                // String *.jspx
      98: aastore
      99: invokevirtual #671                // Method org/eclipse/jetty/servlet/ServletMapping.setPathSpecs:([Ljava/lang/String;)V
     102: aload_1
     103: invokevirtual #620                // Method org/eclipse/jetty/webapp/WebAppContext.getServletHandler:()Lorg/eclipse/jetty/servlet/ServletHandler;
     106: aload_3
     107: invokevirtual #675                // Method org/eclipse/jetty/servlet/ServletHandler.addServletMapping:(Lorg/eclipse/jetty/servlet/ServletMapping;)V
     110: return

  protected org.eclipse.jetty.webapp.Configuration[] getWebAppContextConfigurations(org.eclipse.jetty.webapp.WebAppContext, org.springframework.boot.web.servlet.ServletContextInitializer...);
    Code:
       0: new           #7                  // class java/util/ArrayList
       3: dup
       4: invokespecial #9                  // Method java/util/ArrayList."<init>":()V
       7: astore_3
       8: aload_3
       9: aload_0
      10: aload_1
      11: aload_2
      12: invokevirtual #679                // Method getServletContextInitializerConfiguration:(Lorg/eclipse/jetty/webapp/WebAppContext;[Lorg/springframework/boot/web/servlet/ServletContextInitializer;)Lorg/eclipse/jetty/webapp/Configuration;
      15: invokeinterface #193,  2          // InterfaceMethod java/util/List.add:(Ljava/lang/Object;)Z
      20: pop
      21: aload_3
      22: aload_0
      23: invokevirtual #683                // Method getErrorPageConfiguration:()Lorg/eclipse/jetty/webapp/Configuration;
      26: invokeinterface #193,  2          // InterfaceMethod java/util/List.add:(Ljava/lang/Object;)Z
      31: pop
      32: aload_3
      33: aload_0
      34: invokevirtual #687                // Method getMimeTypeConfiguration:()Lorg/eclipse/jetty/webapp/Configuration;
      37: invokeinterface #193,  2          // InterfaceMethod java/util/List.add:(Ljava/lang/Object;)Z
      42: pop
      43: aload_3
      44: new           #690                // class org/springframework/boot/web/embedded/jetty/JettyServletWebServerFactory$WebListenersConfiguration
      47: dup
      48: aload_0
      49: invokevirtual #692                // Method getWebListenerClassNames:()Ljava/util/Set;
      52: invokespecial #696                // Method org/springframework/boot/web/embedded/jetty/JettyServletWebServerFactory$WebListenersConfiguration."<init>":(Ljava/util/Set;)V
      55: invokeinterface #193,  2          // InterfaceMethod java/util/List.add:(Ljava/lang/Object;)Z
      60: pop
      61: aload_3
      62: aload_0
      63: invokevirtual #699                // Method getConfigurations:()Ljava/util/Collection;
      66: invokeinterface #702,  2          // InterfaceMethod java/util/List.addAll:(Ljava/util/Collection;)Z
      71: pop
      72: aload_3
      73: iconst_0
      74: anewarray     #705                // class org/eclipse/jetty/webapp/Configuration
      77: invokeinterface #214,  2          // InterfaceMethod java/util/List.toArray:([Ljava/lang/Object;)[Ljava/lang/Object;
      82: checkcast     #707                // class "[Lorg/eclipse/jetty/webapp/Configuration;"
      85: areturn

  private org.eclipse.jetty.webapp.Configuration getErrorPageConfiguration();
    Code:
       0: new           #709                // class org/springframework/boot/web/embedded/jetty/JettyServletWebServerFactory$1
       3: dup
       4: aload_0
       5: invokespecial #711                // Method org/springframework/boot/web/embedded/jetty/JettyServletWebServerFactory$1."<init>":(Lorg/springframework/boot/web/embedded/jetty/JettyServletWebServerFactory;)V
       8: areturn

  private org.eclipse.jetty.webapp.Configuration getMimeTypeConfiguration();
    Code:
       0: new           #714                // class org/springframework/boot/web/embedded/jetty/JettyServletWebServerFactory$2
       3: dup
       4: aload_0
       5: invokespecial #716                // Method org/springframework/boot/web/embedded/jetty/JettyServletWebServerFactory$2."<init>":(Lorg/springframework/boot/web/embedded/jetty/JettyServletWebServerFactory;)V
       8: areturn

  protected org.eclipse.jetty.webapp.Configuration getServletContextInitializerConfiguration(org.eclipse.jetty.webapp.WebAppContext, org.springframework.boot.web.servlet.ServletContextInitializer...);
    Code:
       0: new           #717                // class org/springframework/boot/web/embedded/jetty/ServletContextInitializerConfiguration
       3: dup
       4: aload_2
       5: invokespecial #719                // Method org/springframework/boot/web/embedded/jetty/ServletContextInitializerConfiguration."<init>":([Lorg/springframework/boot/web/servlet/ServletContextInitializer;)V
       8: areturn

  protected void postProcessWebAppContext(org.eclipse.jetty.webapp.WebAppContext);
    Code:
       0: return

  protected org.springframework.boot.web.embedded.jetty.JettyWebServer getJettyWebServer(org.eclipse.jetty.server.Server);
    Code:
       0: new           #722                // class org/springframework/boot/web/embedded/jetty/JettyWebServer
       3: dup
       4: aload_1
       5: aload_0
       6: invokevirtual #39                 // Method getPort:()I
       9: iflt          16
      12: iconst_1
      13: goto          17
      16: iconst_0
      17: invokespecial #724                // Method org/springframework/boot/web/embedded/jetty/JettyWebServer."<init>":(Lorg/eclipse/jetty/server/Server;Z)V
      20: areturn

  public void setResourceLoader(org.springframework.core.io.ResourceLoader);
    Code:
       0: aload_0
       1: aload_1
       2: putfield      #320                // Field resourceLoader:Lorg/springframework/core/io/ResourceLoader;
       5: return

  public void setUseForwardHeaders(boolean);
    Code:
       0: aload_0
       1: iload_1
       2: putfield      #130                // Field useForwardHeaders:Z
       5: return

  public void setAcceptors(int);
    Code:
       0: aload_0
       1: iload_1
       2: putfield      #16                 // Field acceptors:I
       5: return

  public void setSelectors(int);
    Code:
       0: aload_0
       1: iload_1
       2: putfield      #20                 // Field selectors:I
       5: return

  public void setServerCustomizers(java.util.Collection<? extends org.springframework.boot.web.embedded.jetty.JettyServerCustomizer>);
    Code:
       0: aload_1
       1: ldc_w         #727                // String Customizers must not be null
       4: invokestatic  #301                // Method org/springframework/util/Assert.notNull:(Ljava/lang/Object;Ljava/lang/String;)V
       7: aload_0
       8: new           #23                 // class java/util/LinkedHashSet
      11: dup
      12: aload_1
      13: invokespecial #729                // Method java/util/LinkedHashSet."<init>":(Ljava/util/Collection;)V
      16: putfield      #26                 // Field jettyServerCustomizers:Ljava/util/Set;
      19: return

  public java.util.Collection<org.springframework.boot.web.embedded.jetty.JettyServerCustomizer> getServerCustomizers();
    Code:
       0: aload_0
       1: getfield      #26                 // Field jettyServerCustomizers:Ljava/util/Set;
       4: areturn

  public void addServerCustomizers(org.springframework.boot.web.embedded.jetty.JettyServerCustomizer...);
    Code:
       0: aload_1
       1: ldc_w         #727                // String Customizers must not be null
       4: invokestatic  #301                // Method org/springframework/util/Assert.notNull:(Ljava/lang/Object;Ljava/lang/String;)V
       7: aload_0
       8: getfield      #26                 // Field jettyServerCustomizers:Ljava/util/Set;
      11: aload_1
      12: invokestatic  #732                // Method java/util/Arrays.asList:([Ljava/lang/Object;)Ljava/util/List;
      15: invokeinterface #738,  2          // InterfaceMethod java/util/Set.addAll:(Ljava/util/Collection;)Z
      20: pop
      21: return

  public void setConfigurations(java.util.Collection<? extends org.eclipse.jetty.webapp.Configuration>);
    Code:
       0: aload_1
       1: ldc_w         #741                // String Configurations must not be null
       4: invokestatic  #301                // Method org/springframework/util/Assert.notNull:(Ljava/lang/Object;Ljava/lang/String;)V
       7: aload_0
       8: new           #7                  // class java/util/ArrayList
      11: dup
      12: aload_1
      13: invokespecial #743                // Method java/util/ArrayList."<init>":(Ljava/util/Collection;)V
      16: putfield      #10                 // Field configurations:Ljava/util/List;
      19: return

  public java.util.Collection<org.eclipse.jetty.webapp.Configuration> getConfigurations();
    Code:
       0: aload_0
       1: getfield      #10                 // Field configurations:Ljava/util/List;
       4: areturn

  public void addConfigurations(org.eclipse.jetty.webapp.Configuration...);
    Code:
       0: aload_1
       1: ldc_w         #741                // String Configurations must not be null
       4: invokestatic  #301                // Method org/springframework/util/Assert.notNull:(Ljava/lang/Object;Ljava/lang/String;)V
       7: aload_0
       8: getfield      #10                 // Field configurations:Ljava/util/List;
      11: aload_1
      12: invokestatic  #732                // Method java/util/Arrays.asList:([Ljava/lang/Object;)Ljava/util/List;
      15: invokeinterface #702,  2          // InterfaceMethod java/util/List.addAll:(Ljava/util/Collection;)Z
      20: pop
      21: return

  public org.eclipse.jetty.util.thread.ThreadPool getThreadPool();
    Code:
       0: aload_0
       1: getfield      #744                // Field threadPool:Lorg/eclipse/jetty/util/thread/ThreadPool;
       4: areturn

  public void setThreadPool(org.eclipse.jetty.util.thread.ThreadPool);
    Code:
       0: aload_0
       1: aload_1
       2: putfield      #744                // Field threadPool:Lorg/eclipse/jetty/util/thread/ThreadPool;
       5: return

  private void addJettyErrorPages(org.eclipse.jetty.server.handler.ErrorHandler, java.util.Collection<org.springframework.boot.web.server.ErrorPage>);
    Code:
       0: aload_1
       1: instanceof    #748                // class org/eclipse/jetty/servlet/ErrorPageErrorHandler
       4: ifeq          107
       7: aload_1
       8: checkcast     #748                // class org/eclipse/jetty/servlet/ErrorPageErrorHandler
      11: astore_3
      12: aload_2
      13: invokeinterface #108,  1          // InterfaceMethod java/util/Collection.iterator:()Ljava/util/Iterator;
      18: astore        4
      20: aload         4
      22: invokeinterface #114,  1          // InterfaceMethod java/util/Iterator.hasNext:()Z
      27: ifeq          107
      30: aload         4
      32: invokeinterface #120,  1          // InterfaceMethod java/util/Iterator.next:()Ljava/lang/Object;
      37: checkcast     #750                // class org/springframework/boot/web/server/ErrorPage
      40: astore        5
      42: aload         5
      44: invokevirtual #752                // Method org/springframework/boot/web/server/ErrorPage.isGlobal:()Z
      47: ifeq          65
      50: aload_3
      51: ldc_w         #755                // String org.eclipse.jetty.server.error_page.global
      54: aload         5
      56: invokevirtual #757                // Method org/springframework/boot/web/server/ErrorPage.getPath:()Ljava/lang/String;
      59: invokevirtual #760                // Method org/eclipse/jetty/servlet/ErrorPageErrorHandler.addErrorPage:(Ljava/lang/String;Ljava/lang/String;)V
      62: goto          104
      65: aload         5
      67: invokevirtual #763                // Method org/springframework/boot/web/server/ErrorPage.getExceptionName:()Ljava/lang/String;
      70: ifnull        90
      73: aload_3
      74: aload         5
      76: invokevirtual #763                // Method org/springframework/boot/web/server/ErrorPage.getExceptionName:()Ljava/lang/String;
      79: aload         5
      81: invokevirtual #757                // Method org/springframework/boot/web/server/ErrorPage.getPath:()Ljava/lang/String;
      84: invokevirtual #760                // Method org/eclipse/jetty/servlet/ErrorPageErrorHandler.addErrorPage:(Ljava/lang/String;Ljava/lang/String;)V
      87: goto          104
      90: aload_3
      91: aload         5
      93: invokevirtual #766                // Method org/springframework/boot/web/server/ErrorPage.getStatusCode:()I
      96: aload         5
      98: invokevirtual #757                // Method org/springframework/boot/web/server/ErrorPage.getPath:()Ljava/lang/String;
     101: invokevirtual #769                // Method org/eclipse/jetty/servlet/ErrorPageErrorHandler.addErrorPage:(ILjava/lang/String;)V
     104: goto          20
     107: return

  private static void lambda$addLocaleMappings$0(org.eclipse.jetty.webapp.WebAppContext, java.util.Locale, java.nio.charset.Charset);
    Code:
       0: aload_0
       1: aload_1
       2: invokevirtual #772                // Method java/util/Locale.toString:()Ljava/lang/String;
       5: aload_2
       6: invokevirtual #777                // Method java/nio/charset/Charset.toString:()Ljava/lang/String;
       9: invokevirtual #780                // Method org/eclipse/jetty/webapp/WebAppContext.addLocaleEncoding:(Ljava/lang/String;Ljava/lang/String;)V
      12: return
}
