Compiled from "JettyEmbeddedWebAppContext.java"
class org.springframework.boot.web.embedded.jetty.JettyEmbeddedWebAppContext extends org.eclipse.jetty.webapp.WebAppContext {
  org.springframework.boot.web.embedded.jetty.JettyEmbeddedWebAppContext();
    Code:
       0: aload_0
       1: invokespecial #1                  // Method org/eclipse/jetty/webapp/WebAppContext."<init>":()V
       4: return

  protected org.eclipse.jetty.servlet.ServletHandler newServletHandler();
    Code:
       0: new           #7                  // class org/springframework/boot/web/embedded/jetty/JettyEmbeddedWebAppContext$JettyEmbeddedServletHandler
       3: dup
       4: invokespecial #9                  // Method org/springframework/boot/web/embedded/jetty/JettyEmbeddedWebAppContext$JettyEmbeddedServletHandler."<init>":()V
       7: areturn

  void deferredInitialize() throws java.lang.Exception;
    Code:
       0: aload_0
       1: invokevirtual #10                 // Method getServletHandler:()Lorg/eclipse/jetty/servlet/ServletHandler;
       4: checkcast     #7                  // class org/springframework/boot/web/embedded/jetty/JettyEmbeddedWebAppContext$JettyEmbeddedServletHandler
       7: invokevirtual #16                 // Method org/springframework/boot/web/embedded/jetty/JettyEmbeddedWebAppContext$JettyEmbeddedServletHandler.deferredInitialize:()V
      10: return
}
