Compiled from "JettyReactiveWebServerFactory.java"
public class org.springframework.boot.web.embedded.jetty.JettyReactiveWebServerFactory extends org.springframework.boot.web.reactive.server.AbstractReactiveWebServerFactory implements org.springframework.boot.web.embedded.jetty.ConfigurableJettyWebServerFactory {
  private static final org.apache.commons.logging.Log logger;

  private int acceptors;

  private int selectors;

  private boolean useForwardHeaders;

  private java.util.Set<org.springframework.boot.web.embedded.jetty.JettyServerCustomizer> jettyServerCustomizers;

  private org.springframework.http.client.reactive.JettyResourceFactory resourceFactory;

  private org.eclipse.jetty.util.thread.ThreadPool threadPool;

  public org.springframework.boot.web.embedded.jetty.JettyReactiveWebServerFactory();
    Code:
       0: aload_0
       1: invokespecial #1                  // Method org/springframework/boot/web/reactive/server/AbstractReactiveWebServerFactory."<init>":()V
       4: aload_0
       5: iconst_m1
       6: putfield      #7                  // Field acceptors:I
       9: aload_0
      10: iconst_m1
      11: putfield      #13                 // Field selectors:I
      14: aload_0
      15: new           #16                 // class java/util/LinkedHashSet
      18: dup
      19: invokespecial #18                 // Method java/util/LinkedHashSet."<init>":()V
      22: putfield      #19                 // Field jettyServerCustomizers:Ljava/util/Set;
      25: return

  public org.springframework.boot.web.embedded.jetty.JettyReactiveWebServerFactory(int);
    Code:
       0: aload_0
       1: iload_1
       2: invokespecial #23                 // Method org/springframework/boot/web/reactive/server/AbstractReactiveWebServerFactory."<init>":(I)V
       5: aload_0
       6: iconst_m1
       7: putfield      #7                  // Field acceptors:I
      10: aload_0
      11: iconst_m1
      12: putfield      #13                 // Field selectors:I
      15: aload_0
      16: new           #16                 // class java/util/LinkedHashSet
      19: dup
      20: invokespecial #18                 // Method java/util/LinkedHashSet."<init>":()V
      23: putfield      #19                 // Field jettyServerCustomizers:Ljava/util/Set;
      26: return

  public void setUseForwardHeaders(boolean);
    Code:
       0: aload_0
       1: iload_1
       2: putfield      #26                 // Field useForwardHeaders:Z
       5: return

  public void setAcceptors(int);
    Code:
       0: aload_0
       1: iload_1
       2: putfield      #7                  // Field acceptors:I
       5: return

  public org.springframework.boot.web.server.WebServer getWebServer(org.springframework.http.server.reactive.HttpHandler);
    Code:
       0: new           #30                 // class org/springframework/http/server/reactive/JettyHttpHandlerAdapter
       3: dup
       4: aload_1
       5: invokespecial #32                 // Method org/springframework/http/server/reactive/JettyHttpHandlerAdapter."<init>":(Lorg/springframework/http/server/reactive/HttpHandler;)V
       8: astore_2
       9: aload_0
      10: aload_2
      11: invokevirtual #35                 // Method createJettyServer:(Lorg/springframework/http/server/reactive/JettyHttpHandlerAdapter;)Lorg/eclipse/jetty/server/Server;
      14: astore_3
      15: new           #39                 // class org/springframework/boot/web/embedded/jetty/JettyWebServer
      18: dup
      19: aload_3
      20: aload_0
      21: invokevirtual #41                 // Method getPort:()I
      24: iflt          31
      27: iconst_1
      28: goto          32
      31: iconst_0
      32: invokespecial #45                 // Method org/springframework/boot/web/embedded/jetty/JettyWebServer."<init>":(Lorg/eclipse/jetty/server/Server;Z)V
      35: areturn

  public void addServerCustomizers(org.springframework.boot.web.embedded.jetty.JettyServerCustomizer...);
    Code:
       0: aload_1
       1: ldc           #48                 // String Customizers must not be null
       3: invokestatic  #50                 // Method org/springframework/util/Assert.notNull:(Ljava/lang/Object;Ljava/lang/String;)V
       6: aload_0
       7: getfield      #19                 // Field jettyServerCustomizers:Ljava/util/Set;
      10: aload_1
      11: invokestatic  #56                 // Method java/util/Arrays.asList:([Ljava/lang/Object;)Ljava/util/List;
      14: invokeinterface #62,  2           // InterfaceMethod java/util/Set.addAll:(Ljava/util/Collection;)Z
      19: pop
      20: return

  public void setServerCustomizers(java.util.Collection<? extends org.springframework.boot.web.embedded.jetty.JettyServerCustomizer>);
    Code:
       0: aload_1
       1: ldc           #48                 // String Customizers must not be null
       3: invokestatic  #50                 // Method org/springframework/util/Assert.notNull:(Ljava/lang/Object;Ljava/lang/String;)V
       6: aload_0
       7: new           #16                 // class java/util/LinkedHashSet
      10: dup
      11: aload_1
      12: invokespecial #68                 // Method java/util/LinkedHashSet."<init>":(Ljava/util/Collection;)V
      15: putfield      #19                 // Field jettyServerCustomizers:Ljava/util/Set;
      18: return

  public java.util.Collection<org.springframework.boot.web.embedded.jetty.JettyServerCustomizer> getServerCustomizers();
    Code:
       0: aload_0
       1: getfield      #19                 // Field jettyServerCustomizers:Ljava/util/Set;
       4: areturn

  public org.eclipse.jetty.util.thread.ThreadPool getThreadPool();
    Code:
       0: aload_0
       1: getfield      #71                 // Field threadPool:Lorg/eclipse/jetty/util/thread/ThreadPool;
       4: areturn

  public void setThreadPool(org.eclipse.jetty.util.thread.ThreadPool);
    Code:
       0: aload_0
       1: aload_1
       2: putfield      #71                 // Field threadPool:Lorg/eclipse/jetty/util/thread/ThreadPool;
       5: return

  public void setSelectors(int);
    Code:
       0: aload_0
       1: iload_1
       2: putfield      #13                 // Field selectors:I
       5: return

  public void setResourceFactory(org.springframework.http.client.reactive.JettyResourceFactory);
    Code:
       0: aload_0
       1: aload_1
       2: putfield      #75                 // Field resourceFactory:Lorg/springframework/http/client/reactive/JettyResourceFactory;
       5: return

  protected org.springframework.http.client.reactive.JettyResourceFactory getResourceFactory();
    Code:
       0: aload_0
       1: getfield      #75                 // Field resourceFactory:Lorg/springframework/http/client/reactive/JettyResourceFactory;
       4: areturn

  protected org.eclipse.jetty.server.Server createJettyServer(org.springframework.http.server.reactive.JettyHttpHandlerAdapter);
    Code:
       0: aload_0
       1: invokevirtual #41                 // Method getPort:()I
       4: iconst_0
       5: invokestatic  #79                 // Method java/lang/Math.max:(II)I
       8: istore_2
       9: new           #85                 // class java/net/InetSocketAddress
      12: dup
      13: aload_0
      14: invokevirtual #87                 // Method getAddress:()Ljava/net/InetAddress;
      17: iload_2
      18: invokespecial #91                 // Method java/net/InetSocketAddress."<init>":(Ljava/net/InetAddress;I)V
      21: astore_3
      22: new           #94                 // class org/eclipse/jetty/server/Server
      25: dup
      26: aload_0
      27: invokevirtual #96                 // Method getThreadPool:()Lorg/eclipse/jetty/util/thread/ThreadPool;
      30: invokespecial #100                // Method org/eclipse/jetty/server/Server."<init>":(Lorg/eclipse/jetty/util/thread/ThreadPool;)V
      33: astore        4
      35: aload         4
      37: aload_0
      38: aload_3
      39: aload         4
      41: invokevirtual #103                // Method createConnector:(Ljava/net/InetSocketAddress;Lorg/eclipse/jetty/server/Server;)Lorg/eclipse/jetty/server/AbstractConnector;
      44: invokevirtual #107                // Method org/eclipse/jetty/server/Server.addConnector:(Lorg/eclipse/jetty/server/Connector;)V
      47: aload         4
      49: lconst_0
      50: invokevirtual #111                // Method org/eclipse/jetty/server/Server.setStopTimeout:(J)V
      53: new           #115                // class org/eclipse/jetty/servlet/ServletHolder
      56: dup
      57: aload_1
      58: invokespecial #117                // Method org/eclipse/jetty/servlet/ServletHolder."<init>":(Ljakarta/servlet/Servlet;)V
      61: astore        5
      63: aload         5
      65: iconst_1
      66: invokevirtual #120                // Method org/eclipse/jetty/servlet/ServletHolder.setAsyncSupported:(Z)V
      69: new           #124                // class org/eclipse/jetty/servlet/ServletContextHandler
      72: dup
      73: aload         4
      75: ldc           #126                // String /
      77: iconst_0
      78: iconst_0
      79: invokespecial #128                // Method org/eclipse/jetty/servlet/ServletContextHandler."<init>":(Lorg/eclipse/jetty/server/HandlerContainer;Ljava/lang/String;ZZ)V
      82: astore        6
      84: aload         6
      86: aload         5
      88: ldc           #126                // String /
      90: invokevirtual #131                // Method org/eclipse/jetty/servlet/ServletContextHandler.addServlet:(Lorg/eclipse/jetty/servlet/ServletHolder;Ljava/lang/String;)V
      93: aload         4
      95: aload_0
      96: aload         6
      98: invokevirtual #135                // Method addHandlerWrappers:(Lorg/eclipse/jetty/server/Handler;)Lorg/eclipse/jetty/server/Handler;
     101: invokevirtual #139                // Method org/eclipse/jetty/server/Server.setHandler:(Lorg/eclipse/jetty/server/Handler;)V
     104: getstatic     #143                // Field logger:Lorg/apache/commons/logging/Log;
     107: iload_2
     108: invokedynamic #147,  0            // InvokeDynamic #0:makeConcatWithConstants:(I)Ljava/lang/String;
     113: invokeinterface #151,  2          // InterfaceMethod org/apache/commons/logging/Log.info:(Ljava/lang/Object;)V
     118: aload_0
     119: invokevirtual #157                // Method getSsl:()Lorg/springframework/boot/web/server/Ssl;
     122: invokestatic  #161                // Method org/springframework/boot/web/server/Ssl.isEnabled:(Lorg/springframework/boot/web/server/Ssl;)Z
     125: ifeq          135
     128: aload_0
     129: aload         4
     131: aload_3
     132: invokevirtual #167                // Method customizeSsl:(Lorg/eclipse/jetty/server/Server;Ljava/net/InetSocketAddress;)V
     135: aload_0
     136: invokevirtual #171                // Method getServerCustomizers:()Ljava/util/Collection;
     139: invokeinterface #175,  1          // InterfaceMethod java/util/Collection.iterator:()Ljava/util/Iterator;
     144: astore        7
     146: aload         7
     148: invokeinterface #181,  1          // InterfaceMethod java/util/Iterator.hasNext:()Z
     153: ifeq          180
     156: aload         7
     158: invokeinterface #187,  1          // InterfaceMethod java/util/Iterator.next:()Ljava/lang/Object;
     163: checkcast     #191                // class org/springframework/boot/web/embedded/jetty/JettyServerCustomizer
     166: astore        8
     168: aload         8
     170: aload         4
     172: invokeinterface #193,  2          // InterfaceMethod org/springframework/boot/web/embedded/jetty/JettyServerCustomizer.customize:(Lorg/eclipse/jetty/server/Server;)V
     177: goto          146
     180: aload_0
     181: getfield      #26                 // Field useForwardHeaders:Z
     184: ifeq          199
     187: new           #197                // class org/springframework/boot/web/embedded/jetty/ForwardHeadersCustomizer
     190: dup
     191: invokespecial #199                // Method org/springframework/boot/web/embedded/jetty/ForwardHeadersCustomizer."<init>":()V
     194: aload         4
     196: invokevirtual #200                // Method org/springframework/boot/web/embedded/jetty/ForwardHeadersCustomizer.customize:(Lorg/eclipse/jetty/server/Server;)V
     199: aload_0
     200: invokevirtual #201                // Method getShutdown:()Lorg/springframework/boot/web/server/Shutdown;
     203: getstatic     #205                // Field org/springframework/boot/web/server/Shutdown.GRACEFUL:Lorg/springframework/boot/web/server/Shutdown;
     206: if_acmpne     235
     209: new           #211                // class org/eclipse/jetty/server/handler/StatisticsHandler
     212: dup
     213: invokespecial #213                // Method org/eclipse/jetty/server/handler/StatisticsHandler."<init>":()V
     216: astore        7
     218: aload         7
     220: aload         4
     222: invokevirtual #214                // Method org/eclipse/jetty/server/Server.getHandler:()Lorg/eclipse/jetty/server/Handler;
     225: invokevirtual #218                // Method org/eclipse/jetty/server/handler/StatisticsHandler.setHandler:(Lorg/eclipse/jetty/server/Handler;)V
     228: aload         4
     230: aload         7
     232: invokevirtual #139                // Method org/eclipse/jetty/server/Server.setHandler:(Lorg/eclipse/jetty/server/Handler;)V
     235: aload         4
     237: areturn

  private org.eclipse.jetty.server.AbstractConnector createConnector(java.net.InetSocketAddress, org.eclipse.jetty.server.Server);
    Code:
       0: new           #219                // class org/eclipse/jetty/server/HttpConfiguration
       3: dup
       4: invokespecial #221                // Method org/eclipse/jetty/server/HttpConfiguration."<init>":()V
       7: astore_3
       8: aload_3
       9: iconst_0
      10: invokevirtual #222                // Method org/eclipse/jetty/server/HttpConfiguration.setSendServerVersion:(Z)V
      13: new           #225                // class java/util/ArrayList
      16: dup
      17: invokespecial #227                // Method java/util/ArrayList."<init>":()V
      20: astore        4
      22: aload         4
      24: new           #228                // class org/eclipse/jetty/server/HttpConnectionFactory
      27: dup
      28: aload_3
      29: invokespecial #230                // Method org/eclipse/jetty/server/HttpConnectionFactory."<init>":(Lorg/eclipse/jetty/server/HttpConfiguration;)V
      32: invokeinterface #233,  2          // InterfaceMethod java/util/List.add:(Ljava/lang/Object;)Z
      37: pop
      38: aload_0
      39: invokevirtual #239                // Method getHttp2:()Lorg/springframework/boot/web/server/Http2;
      42: ifnull        71
      45: aload_0
      46: invokevirtual #239                // Method getHttp2:()Lorg/springframework/boot/web/server/Http2;
      49: invokevirtual #243                // Method org/springframework/boot/web/server/Http2.isEnabled:()Z
      52: ifeq          71
      55: aload         4
      57: new           #247                // class org/eclipse/jetty/http2/server/HTTP2CServerConnectionFactory
      60: dup
      61: aload_3
      62: invokespecial #249                // Method org/eclipse/jetty/http2/server/HTTP2CServerConnectionFactory."<init>":(Lorg/eclipse/jetty/server/HttpConfiguration;)V
      65: invokeinterface #233,  2          // InterfaceMethod java/util/List.add:(Ljava/lang/Object;)Z
      70: pop
      71: aload_0
      72: invokevirtual #250                // Method getResourceFactory:()Lorg/springframework/http/client/reactive/JettyResourceFactory;
      75: astore        5
      77: aload         5
      79: ifnull        132
      82: new           #254                // class org/eclipse/jetty/server/ServerConnector
      85: dup
      86: aload_2
      87: aload         5
      89: invokevirtual #256                // Method org/springframework/http/client/reactive/JettyResourceFactory.getExecutor:()Ljava/util/concurrent/Executor;
      92: aload         5
      94: invokevirtual #262                // Method org/springframework/http/client/reactive/JettyResourceFactory.getScheduler:()Lorg/eclipse/jetty/util/thread/Scheduler;
      97: aload         5
      99: invokevirtual #266                // Method org/springframework/http/client/reactive/JettyResourceFactory.getByteBufferPool:()Lorg/eclipse/jetty/io/ByteBufferPool;
     102: aload_0
     103: getfield      #7                  // Field acceptors:I
     106: aload_0
     107: getfield      #13                 // Field selectors:I
     110: aload         4
     112: iconst_0
     113: anewarray     #270                // class org/eclipse/jetty/server/ConnectionFactory
     116: invokeinterface #272,  2          // InterfaceMethod java/util/List.toArray:([Ljava/lang/Object;)[Ljava/lang/Object;
     121: checkcast     #276                // class "[Lorg/eclipse/jetty/server/ConnectionFactory;"
     124: invokespecial #278                // Method org/eclipse/jetty/server/ServerConnector."<init>":(Lorg/eclipse/jetty/server/Server;Ljava/util/concurrent/Executor;Lorg/eclipse/jetty/util/thread/Scheduler;Lorg/eclipse/jetty/io/ByteBufferPool;II[Lorg/eclipse/jetty/server/ConnectionFactory;)V
     127: astore        6
     129: goto          164
     132: new           #254                // class org/eclipse/jetty/server/ServerConnector
     135: dup
     136: aload_2
     137: aload_0
     138: getfield      #7                  // Field acceptors:I
     141: aload_0
     142: getfield      #13                 // Field selectors:I
     145: aload         4
     147: iconst_0
     148: anewarray     #270                // class org/eclipse/jetty/server/ConnectionFactory
     151: invokeinterface #272,  2          // InterfaceMethod java/util/List.toArray:([Ljava/lang/Object;)[Ljava/lang/Object;
     156: checkcast     #276                // class "[Lorg/eclipse/jetty/server/ConnectionFactory;"
     159: invokespecial #281                // Method org/eclipse/jetty/server/ServerConnector."<init>":(Lorg/eclipse/jetty/server/Server;II[Lorg/eclipse/jetty/server/ConnectionFactory;)V
     162: astore        6
     164: aload         6
     166: aload_1
     167: invokevirtual #284                // Method java/net/InetSocketAddress.getHostString:()Ljava/lang/String;
     170: invokevirtual #288                // Method org/eclipse/jetty/server/ServerConnector.setHost:(Ljava/lang/String;)V
     173: aload         6
     175: aload_1
     176: invokevirtual #292                // Method java/net/InetSocketAddress.getPort:()I
     179: invokevirtual #293                // Method org/eclipse/jetty/server/ServerConnector.setPort:(I)V
     182: aload         6
     184: areturn

  private org.eclipse.jetty.server.Handler addHandlerWrappers(org.eclipse.jetty.server.Handler);
    Code:
       0: aload_0
       1: invokevirtual #296                // Method getCompression:()Lorg/springframework/boot/web/server/Compression;
       4: ifnull        30
       7: aload_0
       8: invokevirtual #296                // Method getCompression:()Lorg/springframework/boot/web/server/Compression;
      11: invokevirtual #300                // Method org/springframework/boot/web/server/Compression.getEnabled:()Z
      14: ifeq          30
      17: aload_0
      18: aload_1
      19: aload_0
      20: invokevirtual #296                // Method getCompression:()Lorg/springframework/boot/web/server/Compression;
      23: invokestatic  #305                // Method org/springframework/boot/web/embedded/jetty/JettyHandlerWrappers.createGzipHandlerWrapper:(Lorg/springframework/boot/web/server/Compression;)Lorg/eclipse/jetty/server/handler/HandlerWrapper;
      26: invokevirtual #311                // Method applyWrapper:(Lorg/eclipse/jetty/server/Handler;Lorg/eclipse/jetty/server/handler/HandlerWrapper;)Lorg/eclipse/jetty/server/Handler;
      29: astore_1
      30: aload_0
      31: invokevirtual #315                // Method getServerHeader:()Ljava/lang/String;
      34: invokestatic  #318                // Method org/springframework/util/StringUtils.hasText:(Ljava/lang/String;)Z
      37: ifeq          53
      40: aload_0
      41: aload_1
      42: aload_0
      43: invokevirtual #315                // Method getServerHeader:()Ljava/lang/String;
      46: invokestatic  #324                // Method org/springframework/boot/web/embedded/jetty/JettyHandlerWrappers.createServerHeaderHandlerWrapper:(Ljava/lang/String;)Lorg/eclipse/jetty/server/handler/HandlerWrapper;
      49: invokevirtual #311                // Method applyWrapper:(Lorg/eclipse/jetty/server/Handler;Lorg/eclipse/jetty/server/handler/HandlerWrapper;)Lorg/eclipse/jetty/server/Handler;
      52: astore_1
      53: aload_1
      54: areturn

  private org.eclipse.jetty.server.Handler applyWrapper(org.eclipse.jetty.server.Handler, org.eclipse.jetty.server.handler.HandlerWrapper);
    Code:
       0: aload_2
       1: aload_1
       2: invokevirtual #328                // Method org/eclipse/jetty/server/handler/HandlerWrapper.setHandler:(Lorg/eclipse/jetty/server/Handler;)V
       5: aload_2
       6: areturn

  private void customizeSsl(org.eclipse.jetty.server.Server, java.net.InetSocketAddress);
    Code:
       0: new           #331                // class org/springframework/boot/web/embedded/jetty/SslServerCustomizer
       3: dup
       4: aload_0
       5: invokevirtual #239                // Method getHttp2:()Lorg/springframework/boot/web/server/Http2;
       8: aload_2
       9: aload_0
      10: invokevirtual #157                // Method getSsl:()Lorg/springframework/boot/web/server/Ssl;
      13: invokevirtual #333                // Method org/springframework/boot/web/server/Ssl.getClientAuth:()Lorg/springframework/boot/web/server/Ssl$ClientAuth;
      16: aload_0
      17: invokevirtual #337                // Method getSslBundle:()Lorg/springframework/boot/ssl/SslBundle;
      20: invokespecial #341                // Method org/springframework/boot/web/embedded/jetty/SslServerCustomizer."<init>":(Lorg/springframework/boot/web/server/Http2;Ljava/net/InetSocketAddress;Lorg/springframework/boot/web/server/Ssl$ClientAuth;Lorg/springframework/boot/ssl/SslBundle;)V
      23: aload_1
      24: invokevirtual #344                // Method org/springframework/boot/web/embedded/jetty/SslServerCustomizer.customize:(Lorg/eclipse/jetty/server/Server;)V
      27: return

  static {};
    Code:
       0: ldc           #8                  // class org/springframework/boot/web/embedded/jetty/JettyReactiveWebServerFactory
       2: invokestatic  #345                // Method org/apache/commons/logging/LogFactory.getLog:(Ljava/lang/Class;)Lorg/apache/commons/logging/Log;
       5: putstatic     #143                // Field logger:Lorg/apache/commons/logging/Log;
       8: return
}
