Compiled from "ServletContextInitializerConfiguration.java"
public class org.springframework.boot.web.embedded.jetty.ServletContextInitializerConfiguration extends org.eclipse.jetty.webapp.AbstractConfiguration {
  private final org.springframework.boot.web.servlet.ServletContextInitializer[] initializers;

  public org.springframework.boot.web.embedded.jetty.ServletContextInitializerConfiguration(org.springframework.boot.web.servlet.ServletContextInitializer...);
    Code:
       0: aload_0
       1: invokespecial #1                  // Method org/eclipse/jetty/webapp/AbstractConfiguration."<init>":()V
       4: aload_1
       5: ldc           #7                  // String Initializers must not be null
       7: invokestatic  #9                  // Method org/springframework/util/Assert.notNull:(Ljava/lang/Object;Ljava/lang/String;)V
      10: aload_0
      11: aload_1
      12: putfield      #15                 // Field initializers:[Lorg/springframework/boot/web/servlet/ServletContextInitializer;
      15: return

  public void configure(org.eclipse.jetty.webapp.WebAppContext) throws java.lang.Exception;
    Code:
       0: invokestatic  #21                 // Method java/lang/Thread.currentThread:()Ljava/lang/Thread;
       3: invokevirtual #27                 // Method java/lang/Thread.getContextClassLoader:()Ljava/lang/ClassLoader;
       6: astore_2
       7: invokestatic  #21                 // Method java/lang/Thread.currentThread:()Ljava/lang/Thread;
      10: aload_1
      11: invokevirtual #31                 // Method org/eclipse/jetty/webapp/WebAppContext.getClassLoader:()Ljava/lang/ClassLoader;
      14: invokevirtual #36                 // Method java/lang/Thread.setContextClassLoader:(Ljava/lang/ClassLoader;)V
      17: aload_0
      18: aload_1
      19: invokevirtual #40                 // Method callInitializers:(Lorg/eclipse/jetty/webapp/WebAppContext;)V
      22: invokestatic  #21                 // Method java/lang/Thread.currentThread:()Ljava/lang/Thread;
      25: aload_2
      26: invokevirtual #36                 // Method java/lang/Thread.setContextClassLoader:(Ljava/lang/ClassLoader;)V
      29: goto          42
      32: astore_3
      33: invokestatic  #21                 // Method java/lang/Thread.currentThread:()Ljava/lang/Thread;
      36: aload_2
      37: invokevirtual #36                 // Method java/lang/Thread.setContextClassLoader:(Ljava/lang/ClassLoader;)V
      40: aload_3
      41: athrow
      42: return
    Exception table:
       from    to  target type
          17    22    32   any

  private void callInitializers(org.eclipse.jetty.webapp.WebAppContext) throws jakarta.servlet.ServletException;
    Code:
       0: aload_0
       1: aload_1
       2: iconst_1
       3: invokevirtual #44                 // Method setExtendedListenerTypes:(Lorg/eclipse/jetty/webapp/WebAppContext;Z)V
       6: aload_0
       7: getfield      #15                 // Field initializers:[Lorg/springframework/boot/web/servlet/ServletContextInitializer;
      10: astore_2
      11: aload_2
      12: arraylength
      13: istore_3
      14: iconst_0
      15: istore        4
      17: iload         4
      19: iload_3
      20: if_icmpge     46
      23: aload_2
      24: iload         4
      26: aaload
      27: astore        5
      29: aload         5
      31: aload_1
      32: invokevirtual #48                 // Method org/eclipse/jetty/webapp/WebAppContext.getServletContext:()Lorg/eclipse/jetty/server/handler/ContextHandler$Context;
      35: invokeinterface #52,  2           // InterfaceMethod org/springframework/boot/web/servlet/ServletContextInitializer.onStartup:(Ljakarta/servlet/ServletContext;)V
      40: iinc          4, 1
      43: goto          17
      46: aload_0
      47: aload_1
      48: iconst_0
      49: invokevirtual #44                 // Method setExtendedListenerTypes:(Lorg/eclipse/jetty/webapp/WebAppContext;Z)V
      52: goto          66
      55: astore        6
      57: aload_0
      58: aload_1
      59: iconst_0
      60: invokevirtual #44                 // Method setExtendedListenerTypes:(Lorg/eclipse/jetty/webapp/WebAppContext;Z)V
      63: aload         6
      65: athrow
      66: return
    Exception table:
       from    to  target type
           0    46    55   any
          55    57    55   any

  private void setExtendedListenerTypes(org.eclipse.jetty.webapp.WebAppContext, boolean);
    Code:
       0: aload_1
       1: invokevirtual #48                 // Method org/eclipse/jetty/webapp/WebAppContext.getServletContext:()Lorg/eclipse/jetty/server/handler/ContextHandler$Context;
       4: iload_2
       5: invokevirtual #58                 // Method org/eclipse/jetty/server/handler/ContextHandler$Context.setExtendedListenerTypes:(Z)V
       8: goto          12
      11: astore_3
      12: return
    Exception table:
       from    to  target type
           0     8    11   Class java/lang/NoSuchMethodError
}
