Compiled from "SslServerCustomizer.java"
class org.springframework.boot.web.embedded.jetty.SslServerCustomizer$SslValidatingServerConnector extends org.eclipse.jetty.server.ServerConnector {
  private final org.springframework.boot.ssl.SslBundleKey key;

  private final org.eclipse.jetty.util.ssl.SslContextFactory sslContextFactory;

  org.springframework.boot.web.embedded.jetty.SslServerCustomizer$SslValidatingServerConnector(org.springframework.boot.ssl.SslBundleKey, org.eclipse.jetty.util.ssl.SslContextFactory, org.eclipse.jetty.server.Server, org.eclipse.jetty.server.SslConnectionFactory, org.eclipse.jetty.server.HttpConnectionFactory);
    Code:
       0: aload_0
       1: aload_3
       2: iconst_2
       3: anewarray     #1                  // class org/eclipse/jetty/server/ConnectionFactory
       6: dup
       7: iconst_0
       8: aload         4
      10: aastore
      11: dup
      12: iconst_1
      13: aload         5
      15: aastore
      16: invokespecial #3                  // Method org/eclipse/jetty/server/ServerConnector."<init>":(Lorg/eclipse/jetty/server/Server;[Lorg/eclipse/jetty/server/ConnectionFactory;)V
      19: aload_0
      20: aload_1
      21: putfield      #9                  // Field key:Lorg/springframework/boot/ssl/SslBundleKey;
      24: aload_0
      25: aload_2
      26: putfield      #15                 // Field sslContextFactory:Lorg/eclipse/jetty/util/ssl/SslContextFactory;
      29: return

  org.springframework.boot.web.embedded.jetty.SslServerCustomizer$SslValidatingServerConnector(org.springframework.boot.ssl.SslBundleKey, org.eclipse.jetty.util.ssl.SslContextFactory, org.eclipse.jetty.server.Server, org.eclipse.jetty.server.ConnectionFactory...);
    Code:
       0: aload_0
       1: aload_3
       2: aload         4
       4: invokespecial #3                  // Method org/eclipse/jetty/server/ServerConnector."<init>":(Lorg/eclipse/jetty/server/Server;[Lorg/eclipse/jetty/server/ConnectionFactory;)V
       7: aload_0
       8: aload_1
       9: putfield      #9                  // Field key:Lorg/springframework/boot/ssl/SslBundleKey;
      12: aload_0
      13: aload_2
      14: putfield      #15                 // Field sslContextFactory:Lorg/eclipse/jetty/util/ssl/SslContextFactory;
      17: return

  protected void doStart() throws java.lang.Exception;
    Code:
       0: aload_0
       1: invokespecial #19                 // Method org/eclipse/jetty/server/ServerConnector.doStart:()V
       4: aload_0
       5: getfield      #9                  // Field key:Lorg/springframework/boot/ssl/SslBundleKey;
       8: aload_0
       9: getfield      #15                 // Field sslContextFactory:Lorg/eclipse/jetty/util/ssl/SslContextFactory;
      12: invokevirtual #23                 // Method org/eclipse/jetty/util/ssl/SslContextFactory.getKeyStore:()Ljava/security/KeyStore;
      15: invokeinterface #29,  2           // InterfaceMethod org/springframework/boot/ssl/SslBundleKey.assertContainsAlias:(Ljava/security/KeyStore;)V
      20: return
}
