Compiled from "AbstractConnectionClient.java"
public abstract class org.apache.dubbo.remoting.api.connection.AbstractConnectionClient extends org.apache.dubbo.remoting.transport.AbstractClient {
  private static final org.apache.dubbo.common.logger.ErrorTypeAwareLogger logger;

  protected org.apache.dubbo.remoting.api.WireProtocol protocol;

  protected java.net.InetSocketAddress remote;

  protected java.util.concurrent.atomic.AtomicBoolean init;

  protected static final java.lang.Object CONNECTED_OBJECT;

  private volatile long counter;

  private static final java.util.concurrent.atomic.AtomicLongFieldUpdater<org.apache.dubbo.remoting.api.connection.AbstractConnectionClient> COUNTER_UPDATER;

  protected org.apache.dubbo.remoting.api.connection.AbstractConnectionClient(org.apache.dubbo.common.URL, org.apache.dubbo.remoting.ChannelHandler) throws org.apache.dubbo.remoting.RemotingException;
    Code:
       0: aload_0
       1: aload_1
       2: aload_2
       3: invokespecial #2                  // Method org/apache/dubbo/remoting/transport/AbstractClient."<init>":(Lorg/apache/dubbo/common/URL;Lorg/apache/dubbo/remoting/ChannelHandler;)V
       6: getstatic     #3                  // Field COUNTER_UPDATER:Ljava/util/concurrent/atomic/AtomicLongFieldUpdater;
       9: aload_0
      10: lconst_1
      11: invokevirtual #4                  // Method java/util/concurrent/atomic/AtomicLongFieldUpdater.set:(Ljava/lang/Object;J)V
      14: return

  public final org.apache.dubbo.remoting.api.connection.AbstractConnectionClient retain();
    Code:
       0: getstatic     #3                  // Field COUNTER_UPDATER:Ljava/util/concurrent/atomic/AtomicLongFieldUpdater;
       3: aload_0
       4: invokevirtual #5                  // Method java/util/concurrent/atomic/AtomicLongFieldUpdater.getAndIncrement:(Ljava/lang/Object;)J
       7: lstore_1
       8: lload_1
       9: lconst_0
      10: lcmp
      11: ifgt          32
      14: getstatic     #3                  // Field COUNTER_UPDATER:Ljava/util/concurrent/atomic/AtomicLongFieldUpdater;
      17: aload_0
      18: invokevirtual #6                  // Method java/util/concurrent/atomic/AtomicLongFieldUpdater.getAndDecrement:(Ljava/lang/Object;)J
      21: pop2
      22: new           #7                  // class java/lang/AssertionError
      25: dup
      26: ldc           #8                  // String This instance has been destroyed
      28: invokespecial #9                  // Method java/lang/AssertionError."<init>":(Ljava/lang/Object;)V
      31: athrow
      32: aload_0
      33: areturn

  public final boolean release();
    Code:
       0: getstatic     #3                  // Field COUNTER_UPDATER:Ljava/util/concurrent/atomic/AtomicLongFieldUpdater;
       3: aload_0
       4: invokevirtual #10                 // Method java/util/concurrent/atomic/AtomicLongFieldUpdater.decrementAndGet:(Ljava/lang/Object;)J
       7: lstore_1
       8: lload_1
       9: lconst_0
      10: lcmp
      11: ifne          20
      14: aload_0
      15: invokevirtual #11                 // Method destroy:()V
      18: iconst_1
      19: ireturn
      20: lload_1
      21: ldc2_w        #12                 // long -1l
      24: lcmp
      25: ifgt          46
      28: getstatic     #14                 // Field logger:Lorg/apache/dubbo/common/logger/ErrorTypeAwareLogger;
      31: ldc           #15                 // String 4-7
      33: ldc           #16                 // String
      35: ldc           #16                 // String
      37: ldc           #8                  // String This instance has been destroyed
      39: invokeinterface #17,  5           // InterfaceMethod org/apache/dubbo/common/logger/ErrorTypeAwareLogger.warn:(Ljava/lang/String;Ljava/lang/String;Ljava/lang/String;Ljava/lang/String;)V
      44: iconst_0
      45: ireturn
      46: iconst_0
      47: ireturn

  protected abstract void initConnectionClient();

  public abstract boolean isAvailable();

  public abstract void createConnectingPromise();

  public abstract void addCloseListener(java.lang.Runnable);

  public abstract void onConnected(java.lang.Object);

  public abstract void onGoaway(java.lang.Object);

  public abstract void destroy();

  public abstract java.lang.Object getChannel(java.lang.Boolean);

  public long getCounter();
    Code:
       0: getstatic     #3                  // Field COUNTER_UPDATER:Ljava/util/concurrent/atomic/AtomicLongFieldUpdater;
       3: aload_0
       4: invokevirtual #18                 // Method java/util/concurrent/atomic/AtomicLongFieldUpdater.get:(Ljava/lang/Object;)J
       7: lreturn

  static {};
    Code:
       0: ldc           #19                 // class org/apache/dubbo/remoting/api/connection/AbstractConnectionClient
       2: invokestatic  #20                 // Method org/apache/dubbo/common/logger/LoggerFactory.getErrorTypeAwareLogger:(Ljava/lang/Class;)Lorg/apache/dubbo/common/logger/ErrorTypeAwareLogger;
       5: putstatic     #14                 // Field logger:Lorg/apache/dubbo/common/logger/ErrorTypeAwareLogger;
       8: new           #21                 // class java/lang/Object
      11: dup
      12: invokespecial #22                 // Method java/lang/Object."<init>":()V
      15: putstatic     #23                 // Field CONNECTED_OBJECT:Ljava/lang/Object;
      18: ldc           #19                 // class org/apache/dubbo/remoting/api/connection/AbstractConnectionClient
      20: ldc           #24                 // String counter
      22: invokestatic  #25                 // Method java/util/concurrent/atomic/AtomicLongFieldUpdater.newUpdater:(Ljava/lang/Class;Ljava/lang/String;)Ljava/util/concurrent/atomic/AtomicLongFieldUpdater;
      25: putstatic     #3                  // Field COUNTER_UPDATER:Ljava/util/concurrent/atomic/AtomicLongFieldUpdater;
      28: return
}
