Compiled from "SingleProtocolConnectionManager.java"
public class org.apache.dubbo.remoting.api.connection.SingleProtocolConnectionManager implements org.apache.dubbo.remoting.api.connection.ConnectionManager {
  public static final java.lang.String NAME;

  private final java.util.concurrent.ConcurrentMap<java.lang.String, org.apache.dubbo.remoting.api.connection.AbstractConnectionClient> connections;

  private org.apache.dubbo.rpc.model.FrameworkModel frameworkModel;

  public org.apache.dubbo.remoting.api.connection.SingleProtocolConnectionManager(org.apache.dubbo.rpc.model.FrameworkModel);
    Code:
       0: aload_0
       1: invokespecial #1                  // Method java/lang/Object."<init>":()V
       4: aload_0
       5: new           #2                  // class java/util/concurrent/ConcurrentHashMap
       8: dup
       9: bipush        16
      11: invokespecial #3                  // Method java/util/concurrent/ConcurrentHashMap."<init>":(I)V
      14: putfield      #4                  // Field connections:Ljava/util/concurrent/ConcurrentMap;
      17: aload_0
      18: aload_1
      19: putfield      #5                  // Field frameworkModel:Lorg/apache/dubbo/rpc/model/FrameworkModel;
      22: return

  public org.apache.dubbo.remoting.api.connection.AbstractConnectionClient connect(org.apache.dubbo.common.URL, org.apache.dubbo.remoting.ChannelHandler);
    Code:
       0: aload_1
       1: ifnonnull     14
       4: new           #6                  // class java/lang/IllegalArgumentException
       7: dup
       8: ldc           #7                  // String url == null
      10: invokespecial #8                  // Method java/lang/IllegalArgumentException."<init>":(Ljava/lang/String;)V
      13: athrow
      14: aload_0
      15: getfield      #4                  // Field connections:Ljava/util/concurrent/ConcurrentMap;
      18: aload_1
      19: invokevirtual #9                  // Method org/apache/dubbo/common/URL.getAddress:()Ljava/lang/String;
      22: aload_0
      23: aload_1
      24: aload_2
      25: invokedynamic #10,  0             // InvokeDynamic #0:apply:(Lorg/apache/dubbo/remoting/api/connection/SingleProtocolConnectionManager;Lorg/apache/dubbo/common/URL;Lorg/apache/dubbo/remoting/ChannelHandler;)Ljava/util/function/BiFunction;
      30: invokeinterface #11,  3           // InterfaceMethod java/util/concurrent/ConcurrentMap.compute:(Ljava/lang/Object;Ljava/util/function/BiFunction;)Ljava/lang/Object;
      35: checkcast     #12                 // class org/apache/dubbo/remoting/api/connection/AbstractConnectionClient
      38: areturn

  public void forEachConnection(java.util.function.Consumer<org.apache.dubbo.remoting.api.connection.AbstractConnectionClient>);
    Code:
       0: aload_0
       1: getfield      #4                  // Field connections:Ljava/util/concurrent/ConcurrentMap;
       4: invokeinterface #13,  1           // InterfaceMethod java/util/concurrent/ConcurrentMap.values:()Ljava/util/Collection;
       9: aload_1
      10: invokeinterface #14,  2           // InterfaceMethod java/util/Collection.forEach:(Ljava/util/function/Consumer;)V
      15: return

  private org.apache.dubbo.remoting.api.connection.AbstractConnectionClient lambda$connect$1(org.apache.dubbo.common.URL, org.apache.dubbo.remoting.ChannelHandler, java.lang.String, org.apache.dubbo.remoting.api.connection.AbstractConnectionClient);
    Code:
       0: aload         4
       2: ifnonnull     62
       5: aload_1
       6: ldc           #16                 // String transporter
       8: ldc           #17                 // String netty4
      10: invokevirtual #18                 // Method org/apache/dubbo/common/URL.getParameter:(Ljava/lang/String;Ljava/lang/String;)Ljava/lang/String;
      13: astore        5
      15: aload_0
      16: getfield      #5                  // Field frameworkModel:Lorg/apache/dubbo/rpc/model/FrameworkModel;
      19: ldc           #19                 // class org/apache/dubbo/remoting/api/connection/ConnectionManager
      21: invokevirtual #20                 // Method org/apache/dubbo/rpc/model/FrameworkModel.getExtensionLoader:(Ljava/lang/Class;)Lorg/apache/dubbo/common/extension/ExtensionLoader;
      24: aload         5
      26: invokevirtual #21                 // Method org/apache/dubbo/common/extension/ExtensionLoader.getExtension:(Ljava/lang/String;)Ljava/lang/Object;
      29: checkcast     #19                 // class org/apache/dubbo/remoting/api/connection/ConnectionManager
      32: astore        6
      34: aload         6
      36: aload_1
      37: aload_2
      38: invokeinterface #22,  3           // InterfaceMethod org/apache/dubbo/remoting/api/connection/ConnectionManager.connect:(Lorg/apache/dubbo/common/URL;Lorg/apache/dubbo/remoting/ChannelHandler;)Lorg/apache/dubbo/remoting/api/connection/AbstractConnectionClient;
      43: astore        7
      45: aload         7
      47: aload_0
      48: aload_3
      49: aload         7
      51: invokedynamic #23,  0             // InvokeDynamic #1:run:(Lorg/apache/dubbo/remoting/api/connection/SingleProtocolConnectionManager;Ljava/lang/String;Lorg/apache/dubbo/remoting/api/connection/AbstractConnectionClient;)Ljava/lang/Runnable;
      56: invokevirtual #24                 // Method org/apache/dubbo/remoting/api/connection/AbstractConnectionClient.addCloseListener:(Ljava/lang/Runnable;)V
      59: aload         7
      61: areturn
      62: aload         4
      64: invokevirtual #25                 // Method org/apache/dubbo/remoting/api/connection/AbstractConnectionClient.retain:()Lorg/apache/dubbo/remoting/api/connection/AbstractConnectionClient;
      67: pop
      68: aload         4
      70: areturn

  private void lambda$null$0(java.lang.String, org.apache.dubbo.remoting.api.connection.AbstractConnectionClient);
    Code:
       0: aload_0
       1: getfield      #4                  // Field connections:Ljava/util/concurrent/ConcurrentMap;
       4: aload_1
       5: aload_2
       6: invokeinterface #26,  3           // InterfaceMethod java/util/concurrent/ConcurrentMap.remove:(Ljava/lang/Object;Ljava/lang/Object;)Z
      11: pop
      12: return
}
