Compiled from "QRCodeReader.java"
public class com.google.zxing.qrcode.QRCodeReader implements com.google.zxing.Reader {
  private static final com.google.zxing.ResultPoint[] NO_POINTS;

  private final com.google.zxing.qrcode.decoder.Decoder decoder;

  public com.google.zxing.qrcode.QRCodeReader();
    Code:
       0: aload_0
       1: invokespecial #1                  // Method java/lang/Object."<init>":()V
       4: aload_0
       5: new           #2                  // class com/google/zxing/qrcode/decoder/Decoder
       8: dup
       9: invokespecial #3                  // Method com/google/zxing/qrcode/decoder/Decoder."<init>":()V
      12: putfield      #4                  // Field decoder:Lcom/google/zxing/qrcode/decoder/Decoder;
      15: return

  protected final com.google.zxing.qrcode.decoder.Decoder getDecoder();
    Code:
       0: aload_0
       1: getfield      #4                  // Field decoder:Lcom/google/zxing/qrcode/decoder/Decoder;
       4: areturn

  public com.google.zxing.Result decode(com.google.zxing.BinaryBitmap) throws com.google.zxing.NotFoundException, com.google.zxing.ChecksumException, com.google.zxing.FormatException;
    Code:
       0: aload_0
       1: aload_1
       2: aconst_null
       3: invokevirtual #5                  // Method decode:(Lcom/google/zxing/BinaryBitmap;Ljava/util/Map;)Lcom/google/zxing/Result;
       6: areturn

  public final com.google.zxing.Result decode(com.google.zxing.BinaryBitmap, java.util.Map<com.google.zxing.DecodeHintType, ?>) throws com.google.zxing.NotFoundException, com.google.zxing.ChecksumException, com.google.zxing.FormatException;
    Code:
       0: aload_2
       1: ifnull        44
       4: aload_2
       5: getstatic     #6                  // Field com/google/zxing/DecodeHintType.PURE_BARCODE:Lcom/google/zxing/DecodeHintType;
       8: invokeinterface #7,  2            // InterfaceMethod java/util/Map.containsKey:(Ljava/lang/Object;)Z
      13: ifeq          44
      16: aload_1
      17: invokevirtual #8                  // Method com/google/zxing/BinaryBitmap.getBlackMatrix:()Lcom/google/zxing/common/BitMatrix;
      20: invokestatic  #9                  // Method extractPureBits:(Lcom/google/zxing/common/BitMatrix;)Lcom/google/zxing/common/BitMatrix;
      23: astore        5
      25: aload_0
      26: getfield      #4                  // Field decoder:Lcom/google/zxing/qrcode/decoder/Decoder;
      29: aload         5
      31: aload_2
      32: invokevirtual #10                 // Method com/google/zxing/qrcode/decoder/Decoder.decode:(Lcom/google/zxing/common/BitMatrix;Ljava/util/Map;)Lcom/google/zxing/common/DecoderResult;
      35: astore_3
      36: getstatic     #11                 // Field NO_POINTS:[Lcom/google/zxing/ResultPoint;
      39: astore        4
      41: goto          82
      44: new           #12                 // class com/google/zxing/qrcode/detector/Detector
      47: dup
      48: aload_1
      49: invokevirtual #8                  // Method com/google/zxing/BinaryBitmap.getBlackMatrix:()Lcom/google/zxing/common/BitMatrix;
      52: invokespecial #13                 // Method com/google/zxing/qrcode/detector/Detector."<init>":(Lcom/google/zxing/common/BitMatrix;)V
      55: aload_2
      56: invokevirtual #14                 // Method com/google/zxing/qrcode/detector/Detector.detect:(Ljava/util/Map;)Lcom/google/zxing/common/DetectorResult;
      59: astore        5
      61: aload_0
      62: getfield      #4                  // Field decoder:Lcom/google/zxing/qrcode/decoder/Decoder;
      65: aload         5
      67: invokevirtual #15                 // Method com/google/zxing/common/DetectorResult.getBits:()Lcom/google/zxing/common/BitMatrix;
      70: aload_2
      71: invokevirtual #10                 // Method com/google/zxing/qrcode/decoder/Decoder.decode:(Lcom/google/zxing/common/BitMatrix;Ljava/util/Map;)Lcom/google/zxing/common/DecoderResult;
      74: astore_3
      75: aload         5
      77: invokevirtual #16                 // Method com/google/zxing/common/DetectorResult.getPoints:()[Lcom/google/zxing/ResultPoint;
      80: astore        4
      82: aload_3
      83: invokevirtual #17                 // Method com/google/zxing/common/DecoderResult.getOther:()Ljava/lang/Object;
      86: instanceof    #18                 // class com/google/zxing/qrcode/decoder/QRCodeDecoderMetaData
      89: ifeq          104
      92: aload_3
      93: invokevirtual #17                 // Method com/google/zxing/common/DecoderResult.getOther:()Ljava/lang/Object;
      96: checkcast     #18                 // class com/google/zxing/qrcode/decoder/QRCodeDecoderMetaData
      99: aload         4
     101: invokevirtual #19                 // Method com/google/zxing/qrcode/decoder/QRCodeDecoderMetaData.applyMirroredCorrection:([Lcom/google/zxing/ResultPoint;)V
     104: new           #20                 // class com/google/zxing/Result
     107: dup
     108: aload_3
     109: invokevirtual #21                 // Method com/google/zxing/common/DecoderResult.getText:()Ljava/lang/String;
     112: aload_3
     113: invokevirtual #22                 // Method com/google/zxing/common/DecoderResult.getRawBytes:()[B
     116: aload         4
     118: getstatic     #23                 // Field com/google/zxing/BarcodeFormat.QR_CODE:Lcom/google/zxing/BarcodeFormat;
     121: invokespecial #24                 // Method com/google/zxing/Result."<init>":(Ljava/lang/String;[B[Lcom/google/zxing/ResultPoint;Lcom/google/zxing/BarcodeFormat;)V
     124: astore        5
     126: aload_3
     127: invokevirtual #25                 // Method com/google/zxing/common/DecoderResult.getByteSegments:()Ljava/util/List;
     130: astore        6
     132: aload         6
     134: ifnull        147
     137: aload         5
     139: getstatic     #26                 // Field com/google/zxing/ResultMetadataType.BYTE_SEGMENTS:Lcom/google/zxing/ResultMetadataType;
     142: aload         6
     144: invokevirtual #27                 // Method com/google/zxing/Result.putMetadata:(Lcom/google/zxing/ResultMetadataType;Ljava/lang/Object;)V
     147: aload_3
     148: invokevirtual #28                 // Method com/google/zxing/common/DecoderResult.getECLevel:()Ljava/lang/String;
     151: astore        7
     153: aload         7
     155: ifnull        168
     158: aload         5
     160: getstatic     #29                 // Field com/google/zxing/ResultMetadataType.ERROR_CORRECTION_LEVEL:Lcom/google/zxing/ResultMetadataType;
     163: aload         7
     165: invokevirtual #27                 // Method com/google/zxing/Result.putMetadata:(Lcom/google/zxing/ResultMetadataType;Ljava/lang/Object;)V
     168: aload_3
     169: invokevirtual #30                 // Method com/google/zxing/common/DecoderResult.hasStructuredAppend:()Z
     172: ifeq          205
     175: aload         5
     177: getstatic     #31                 // Field com/google/zxing/ResultMetadataType.STRUCTURED_APPEND_SEQUENCE:Lcom/google/zxing/ResultMetadataType;
     180: aload_3
     181: invokevirtual #32                 // Method com/google/zxing/common/DecoderResult.getStructuredAppendSequenceNumber:()I
     184: invokestatic  #33                 // Method java/lang/Integer.valueOf:(I)Ljava/lang/Integer;
     187: invokevirtual #27                 // Method com/google/zxing/Result.putMetadata:(Lcom/google/zxing/ResultMetadataType;Ljava/lang/Object;)V
     190: aload         5
     192: getstatic     #34                 // Field com/google/zxing/ResultMetadataType.STRUCTURED_APPEND_PARITY:Lcom/google/zxing/ResultMetadataType;
     195: aload_3
     196: invokevirtual #35                 // Method com/google/zxing/common/DecoderResult.getStructuredAppendParity:()I
     199: invokestatic  #33                 // Method java/lang/Integer.valueOf:(I)Ljava/lang/Integer;
     202: invokevirtual #27                 // Method com/google/zxing/Result.putMetadata:(Lcom/google/zxing/ResultMetadataType;Ljava/lang/Object;)V
     205: aload         5
     207: getstatic     #36                 // Field com/google/zxing/ResultMetadataType.SYMBOLOGY_IDENTIFIER:Lcom/google/zxing/ResultMetadataType;
     210: new           #37                 // class java/lang/StringBuilder
     213: dup
     214: invokespecial #38                 // Method java/lang/StringBuilder."<init>":()V
     217: ldc           #39                 // String ]Q
     219: invokevirtual #40                 // Method java/lang/StringBuilder.append:(Ljava/lang/String;)Ljava/lang/StringBuilder;
     222: aload_3
     223: invokevirtual #41                 // Method com/google/zxing/common/DecoderResult.getSymbologyModifier:()I
     226: invokevirtual #42                 // Method java/lang/StringBuilder.append:(I)Ljava/lang/StringBuilder;
     229: invokevirtual #43                 // Method java/lang/StringBuilder.toString:()Ljava/lang/String;
     232: invokevirtual #27                 // Method com/google/zxing/Result.putMetadata:(Lcom/google/zxing/ResultMetadataType;Ljava/lang/Object;)V
     235: aload         5
     237: areturn

  public void reset();
    Code:
       0: return

  private static com.google.zxing.common.BitMatrix extractPureBits(com.google.zxing.common.BitMatrix) throws com.google.zxing.NotFoundException;
    Code:
       0: aload_0
       1: invokevirtual #44                 // Method com/google/zxing/common/BitMatrix.getTopLeftOnBit:()[I
       4: astore_1
       5: aload_0
       6: invokevirtual #45                 // Method com/google/zxing/common/BitMatrix.getBottomRightOnBit:()[I
       9: astore_2
      10: aload_1
      11: ifnull        18
      14: aload_2
      15: ifnonnull     22
      18: invokestatic  #46                 // Method com/google/zxing/NotFoundException.getNotFoundInstance:()Lcom/google/zxing/NotFoundException;
      21: athrow
      22: aload_1
      23: aload_0
      24: invokestatic  #47                 // Method moduleSize:([ILcom/google/zxing/common/BitMatrix;)F
      27: fstore_3
      28: aload_1
      29: iconst_1
      30: iaload
      31: istore        4
      33: aload_2
      34: iconst_1
      35: iaload
      36: istore        5
      38: aload_1
      39: iconst_0
      40: iaload
      41: istore        6
      43: aload_2
      44: iconst_0
      45: iaload
      46: istore        7
      48: iload         6
      50: iload         7
      52: if_icmpge     62
      55: iload         4
      57: iload         5
      59: if_icmplt     66
      62: invokestatic  #46                 // Method com/google/zxing/NotFoundException.getNotFoundInstance:()Lcom/google/zxing/NotFoundException;
      65: athrow
      66: iload         5
      68: iload         4
      70: isub
      71: iload         7
      73: iload         6
      75: isub
      76: if_icmpeq     102
      79: iload         6
      81: iload         5
      83: iload         4
      85: isub
      86: iadd
      87: istore        7
      89: iload         7
      91: aload_0
      92: invokevirtual #48                 // Method com/google/zxing/common/BitMatrix.getWidth:()I
      95: if_icmplt     102
      98: invokestatic  #46                 // Method com/google/zxing/NotFoundException.getNotFoundInstance:()Lcom/google/zxing/NotFoundException;
     101: athrow
     102: iload         7
     104: iload         6
     106: isub
     107: iconst_1
     108: iadd
     109: i2f
     110: fload_3
     111: fdiv
     112: invokestatic  #49                 // Method java/lang/Math.round:(F)I
     115: istore        8
     117: iload         5
     119: iload         4
     121: isub
     122: iconst_1
     123: iadd
     124: i2f
     125: fload_3
     126: fdiv
     127: invokestatic  #49                 // Method java/lang/Math.round:(F)I
     130: istore        9
     132: iload         8
     134: ifle          142
     137: iload         9
     139: ifgt          146
     142: invokestatic  #46                 // Method com/google/zxing/NotFoundException.getNotFoundInstance:()Lcom/google/zxing/NotFoundException;
     145: athrow
     146: iload         9
     148: iload         8
     150: if_icmpeq     157
     153: invokestatic  #46                 // Method com/google/zxing/NotFoundException.getNotFoundInstance:()Lcom/google/zxing/NotFoundException;
     156: athrow
     157: fload_3
     158: fconst_2
     159: fdiv
     160: f2i
     161: istore        10
     163: iload         4
     165: iload         10
     167: iadd
     168: istore        4
     170: iload         6
     172: iload         10
     174: iadd
     175: istore        6
     177: iload         6
     179: iload         8
     181: iconst_1
     182: isub
     183: i2f
     184: fload_3
     185: fmul
     186: f2i
     187: iadd
     188: iload         7
     190: isub
     191: istore        11
     193: iload         11
     195: ifle          216
     198: iload         11
     200: iload         10
     202: if_icmple     209
     205: invokestatic  #46                 // Method com/google/zxing/NotFoundException.getNotFoundInstance:()Lcom/google/zxing/NotFoundException;
     208: athrow
     209: iload         6
     211: iload         11
     213: isub
     214: istore        6
     216: iload         4
     218: iload         9
     220: iconst_1
     221: isub
     222: i2f
     223: fload_3
     224: fmul
     225: f2i
     226: iadd
     227: iload         5
     229: isub
     230: istore        12
     232: iload         12
     234: ifle          255
     237: iload         12
     239: iload         10
     241: if_icmple     248
     244: invokestatic  #46                 // Method com/google/zxing/NotFoundException.getNotFoundInstance:()Lcom/google/zxing/NotFoundException;
     247: athrow
     248: iload         4
     250: iload         12
     252: isub
     253: istore        4
     255: new           #50                 // class com/google/zxing/common/BitMatrix
     258: dup
     259: iload         8
     261: iload         9
     263: invokespecial #51                 // Method com/google/zxing/common/BitMatrix."<init>":(II)V
     266: astore        13
     268: iconst_0
     269: istore        14
     271: iload         14
     273: iload         9
     275: if_icmpge     338
     278: iload         4
     280: iload         14
     282: i2f
     283: fload_3
     284: fmul
     285: f2i
     286: iadd
     287: istore        15
     289: iconst_0
     290: istore        16
     292: iload         16
     294: iload         8
     296: if_icmpge     332
     299: aload_0
     300: iload         6
     302: iload         16
     304: i2f
     305: fload_3
     306: fmul
     307: f2i
     308: iadd
     309: iload         15
     311: invokevirtual #52                 // Method com/google/zxing/common/BitMatrix.get:(II)Z
     314: ifeq          326
     317: aload         13
     319: iload         16
     321: iload         14
     323: invokevirtual #53                 // Method com/google/zxing/common/BitMatrix.set:(II)V
     326: iinc          16, 1
     329: goto          292
     332: iinc          14, 1
     335: goto          271
     338: aload         13
     340: areturn

  private static float moduleSize(int[], com.google.zxing.common.BitMatrix) throws com.google.zxing.NotFoundException;
    Code:
       0: aload_1
       1: invokevirtual #54                 // Method com/google/zxing/common/BitMatrix.getHeight:()I
       4: istore_2
       5: aload_1
       6: invokevirtual #48                 // Method com/google/zxing/common/BitMatrix.getWidth:()I
       9: istore_3
      10: aload_0
      11: iconst_0
      12: iaload
      13: istore        4
      15: aload_0
      16: iconst_1
      17: iaload
      18: istore        5
      20: iconst_1
      21: istore        6
      23: iconst_0
      24: istore        7
      26: iload         4
      28: iload_3
      29: if_icmpge     84
      32: iload         5
      34: iload_2
      35: if_icmpge     84
      38: iload         6
      40: aload_1
      41: iload         4
      43: iload         5
      45: invokevirtual #52                 // Method com/google/zxing/common/BitMatrix.get:(II)Z
      48: if_icmpeq     75
      51: iinc          7, 1
      54: iload         7
      56: iconst_5
      57: if_icmpne     63
      60: goto          84
      63: iload         6
      65: ifne          72
      68: iconst_1
      69: goto          73
      72: iconst_0
      73: istore        6
      75: iinc          4, 1
      78: iinc          5, 1
      81: goto          26
      84: iload         4
      86: iload_3
      87: if_icmpeq     96
      90: iload         5
      92: iload_2
      93: if_icmpne     100
      96: invokestatic  #46                 // Method com/google/zxing/NotFoundException.getNotFoundInstance:()Lcom/google/zxing/NotFoundException;
      99: athrow
     100: iload         4
     102: aload_0
     103: iconst_0
     104: iaload
     105: isub
     106: i2f
     107: ldc           #55                 // float 7.0f
     109: fdiv
     110: freturn

  static {};
    Code:
       0: iconst_0
       1: anewarray     #56                 // class com/google/zxing/ResultPoint
       4: putstatic     #11                 // Field NO_POINTS:[Lcom/google/zxing/ResultPoint;
       7: return
}
