Compiled from "QRCodeWriter.java"
public final class com.google.zxing.qrcode.QRCodeWriter implements com.google.zxing.Writer {
  private static final int QUIET_ZONE_SIZE;

  public com.google.zxing.qrcode.QRCodeWriter();
    Code:
       0: aload_0
       1: invokespecial #1                  // Method java/lang/Object."<init>":()V
       4: return

  public com.google.zxing.common.BitMatrix encode(java.lang.String, com.google.zxing.BarcodeFormat, int, int) throws com.google.zxing.WriterException;
    Code:
       0: aload_0
       1: aload_1
       2: aload_2
       3: iload_3
       4: iload         4
       6: aconst_null
       7: invokevirtual #2                  // Method encode:(Ljava/lang/String;Lcom/google/zxing/BarcodeFormat;IILjava/util/Map;)Lcom/google/zxing/common/BitMatrix;
      10: areturn

  public com.google.zxing.common.BitMatrix encode(java.lang.String, com.google.zxing.BarcodeFormat, int, int, java.util.Map<com.google.zxing.EncodeHintType, ?>) throws com.google.zxing.WriterException;
    Code:
       0: aload_1
       1: invokevirtual #3                  // Method java/lang/String.isEmpty:()Z
       4: ifeq          17
       7: new           #4                  // class java/lang/IllegalArgumentException
      10: dup
      11: ldc           #5                  // String Found empty contents
      13: invokespecial #6                  // Method java/lang/IllegalArgumentException."<init>":(Ljava/lang/String;)V
      16: athrow
      17: aload_2
      18: getstatic     #7                  // Field com/google/zxing/BarcodeFormat.QR_CODE:Lcom/google/zxing/BarcodeFormat;
      21: if_acmpeq     51
      24: new           #4                  // class java/lang/IllegalArgumentException
      27: dup
      28: new           #8                  // class java/lang/StringBuilder
      31: dup
      32: invokespecial #9                  // Method java/lang/StringBuilder."<init>":()V
      35: ldc           #10                 // String Can only encode QR_CODE, but got
      37: invokevirtual #11                 // Method java/lang/StringBuilder.append:(Ljava/lang/String;)Ljava/lang/StringBuilder;
      40: aload_2
      41: invokevirtual #12                 // Method java/lang/StringBuilder.append:(Ljava/lang/Object;)Ljava/lang/StringBuilder;
      44: invokevirtual #13                 // Method java/lang/StringBuilder.toString:()Ljava/lang/String;
      47: invokespecial #6                  // Method java/lang/IllegalArgumentException."<init>":(Ljava/lang/String;)V
      50: athrow
      51: iload_3
      52: iflt          60
      55: iload         4
      57: ifge          97
      60: new           #4                  // class java/lang/IllegalArgumentException
      63: dup
      64: new           #8                  // class java/lang/StringBuilder
      67: dup
      68: invokespecial #9                  // Method java/lang/StringBuilder."<init>":()V
      71: ldc           #14                 // String Requested dimensions are too small:
      73: invokevirtual #11                 // Method java/lang/StringBuilder.append:(Ljava/lang/String;)Ljava/lang/StringBuilder;
      76: iload_3
      77: invokevirtual #15                 // Method java/lang/StringBuilder.append:(I)Ljava/lang/StringBuilder;
      80: bipush        120
      82: invokevirtual #16                 // Method java/lang/StringBuilder.append:(C)Ljava/lang/StringBuilder;
      85: iload         4
      87: invokevirtual #15                 // Method java/lang/StringBuilder.append:(I)Ljava/lang/StringBuilder;
      90: invokevirtual #13                 // Method java/lang/StringBuilder.toString:()Ljava/lang/String;
      93: invokespecial #6                  // Method java/lang/IllegalArgumentException."<init>":(Ljava/lang/String;)V
      96: athrow
      97: getstatic     #17                 // Field com/google/zxing/qrcode/decoder/ErrorCorrectionLevel.L:Lcom/google/zxing/qrcode/decoder/ErrorCorrectionLevel;
     100: astore        6
     102: iconst_4
     103: istore        7
     105: aload         5
     107: ifnull        172
     110: aload         5
     112: getstatic     #19                 // Field com/google/zxing/EncodeHintType.ERROR_CORRECTION:Lcom/google/zxing/EncodeHintType;
     115: invokeinterface #20,  2           // InterfaceMethod java/util/Map.containsKey:(Ljava/lang/Object;)Z
     120: ifeq          141
     123: aload         5
     125: getstatic     #19                 // Field com/google/zxing/EncodeHintType.ERROR_CORRECTION:Lcom/google/zxing/EncodeHintType;
     128: invokeinterface #21,  2           // InterfaceMethod java/util/Map.get:(Ljava/lang/Object;)Ljava/lang/Object;
     133: invokevirtual #22                 // Method java/lang/Object.toString:()Ljava/lang/String;
     136: invokestatic  #23                 // Method com/google/zxing/qrcode/decoder/ErrorCorrectionLevel.valueOf:(Ljava/lang/String;)Lcom/google/zxing/qrcode/decoder/ErrorCorrectionLevel;
     139: astore        6
     141: aload         5
     143: getstatic     #24                 // Field com/google/zxing/EncodeHintType.MARGIN:Lcom/google/zxing/EncodeHintType;
     146: invokeinterface #20,  2           // InterfaceMethod java/util/Map.containsKey:(Ljava/lang/Object;)Z
     151: ifeq          172
     154: aload         5
     156: getstatic     #24                 // Field com/google/zxing/EncodeHintType.MARGIN:Lcom/google/zxing/EncodeHintType;
     159: invokeinterface #21,  2           // InterfaceMethod java/util/Map.get:(Ljava/lang/Object;)Ljava/lang/Object;
     164: invokevirtual #22                 // Method java/lang/Object.toString:()Ljava/lang/String;
     167: invokestatic  #25                 // Method java/lang/Integer.parseInt:(Ljava/lang/String;)I
     170: istore        7
     172: aload_1
     173: aload         6
     175: aload         5
     177: invokestatic  #26                 // Method com/google/zxing/qrcode/encoder/Encoder.encode:(Ljava/lang/String;Lcom/google/zxing/qrcode/decoder/ErrorCorrectionLevel;Ljava/util/Map;)Lcom/google/zxing/qrcode/encoder/QRCode;
     180: astore        8
     182: aload         8
     184: iload_3
     185: iload         4
     187: iload         7
     189: invokestatic  #27                 // Method renderResult:(Lcom/google/zxing/qrcode/encoder/QRCode;III)Lcom/google/zxing/common/BitMatrix;
     192: areturn

  private static com.google.zxing.common.BitMatrix renderResult(com.google.zxing.qrcode.encoder.QRCode, int, int, int);
    Code:
       0: aload_0
       1: invokevirtual #28                 // Method com/google/zxing/qrcode/encoder/QRCode.getMatrix:()Lcom/google/zxing/qrcode/encoder/ByteMatrix;
       4: astore        4
       6: aload         4
       8: ifnonnull     19
      11: new           #29                 // class java/lang/IllegalStateException
      14: dup
      15: invokespecial #30                 // Method java/lang/IllegalStateException."<init>":()V
      18: athrow
      19: aload         4
      21: invokevirtual #31                 // Method com/google/zxing/qrcode/encoder/ByteMatrix.getWidth:()I
      24: istore        5
      26: aload         4
      28: invokevirtual #32                 // Method com/google/zxing/qrcode/encoder/ByteMatrix.getHeight:()I
      31: istore        6
      33: iload         5
      35: iload_3
      36: iconst_2
      37: imul
      38: iadd
      39: istore        7
      41: iload         6
      43: iload_3
      44: iconst_2
      45: imul
      46: iadd
      47: istore        8
      49: iload_1
      50: iload         7
      52: invokestatic  #33                 // Method java/lang/Math.max:(II)I
      55: istore        9
      57: iload_2
      58: iload         8
      60: invokestatic  #33                 // Method java/lang/Math.max:(II)I
      63: istore        10
      65: iload         9
      67: iload         7
      69: idiv
      70: iload         10
      72: iload         8
      74: idiv
      75: invokestatic  #34                 // Method java/lang/Math.min:(II)I
      78: istore        11
      80: iload         9
      82: iload         5
      84: iload         11
      86: imul
      87: isub
      88: iconst_2
      89: idiv
      90: istore        12
      92: iload         10
      94: iload         6
      96: iload         11
      98: imul
      99: isub
     100: iconst_2
     101: idiv
     102: istore        13
     104: new           #35                 // class com/google/zxing/common/BitMatrix
     107: dup
     108: iload         9
     110: iload         10
     112: invokespecial #36                 // Method com/google/zxing/common/BitMatrix."<init>":(II)V
     115: astore        14
     117: iconst_0
     118: istore        15
     120: iload         13
     122: istore        16
     124: iload         15
     126: iload         6
     128: if_icmpge     197
     131: iconst_0
     132: istore        17
     134: iload         12
     136: istore        18
     138: iload         17
     140: iload         5
     142: if_icmpge     184
     145: aload         4
     147: iload         17
     149: iload         15
     151: invokevirtual #37                 // Method com/google/zxing/qrcode/encoder/ByteMatrix.get:(II)B
     154: iconst_1
     155: if_icmpne     171
     158: aload         14
     160: iload         18
     162: iload         16
     164: iload         11
     166: iload         11
     168: invokevirtual #38                 // Method com/google/zxing/common/BitMatrix.setRegion:(IIII)V
     171: iinc          17, 1
     174: iload         18
     176: iload         11
     178: iadd
     179: istore        18
     181: goto          138
     184: iinc          15, 1
     187: iload         16
     189: iload         11
     191: iadd
     192: istore        16
     194: goto          124
     197: aload         14
     199: areturn
}
