Compiled from "PayloadDropper.java"
public class org.apache.dubbo.remoting.utils.PayloadDropper {
  private static org.apache.dubbo.common.logger.Logger logger;

  public org.apache.dubbo.remoting.utils.PayloadDropper();
    Code:
       0: aload_0
       1: invokespecial #1                  // Method java/lang/Object."<init>":()V
       4: return

  public static java.lang.Object getRequestWithoutData(java.lang.Object);
    Code:
       0: getstatic     #2                  // Field logger:Lorg/apache/dubbo/common/logger/Logger;
       3: invokeinterface #3,  1            // InterfaceMethod org/apache/dubbo/common/logger/Logger.isDebugEnabled:()Z
       8: ifeq          13
      11: aload_0
      12: areturn
      13: aload_0
      14: instanceof    #4                  // class org/apache/dubbo/remoting/exchange/Request
      17: ifeq          32
      20: aload_0
      21: checkcast     #4                  // class org/apache/dubbo/remoting/exchange/Request
      24: astore_1
      25: aload_1
      26: aconst_null
      27: invokevirtual #5                  // Method org/apache/dubbo/remoting/exchange/Request.setData:(Ljava/lang/Object;)V
      30: aload_1
      31: areturn
      32: aload_0
      33: instanceof    #6                  // class org/apache/dubbo/remoting/exchange/Response
      36: ifeq          51
      39: aload_0
      40: checkcast     #6                  // class org/apache/dubbo/remoting/exchange/Response
      43: astore_1
      44: aload_1
      45: aconst_null
      46: invokevirtual #7                  // Method org/apache/dubbo/remoting/exchange/Response.setResult:(Ljava/lang/Object;)V
      49: aload_1
      50: areturn
      51: aload_0
      52: areturn

  static {};
    Code:
       0: ldc           #8                  // class org/apache/dubbo/remoting/utils/PayloadDropper
       2: invokestatic  #9                  // Method org/apache/dubbo/common/logger/LoggerFactory.getLogger:(Ljava/lang/Class;)Lorg/apache/dubbo/common/logger/Logger;
       5: putstatic     #2                  // Field logger:Lorg/apache/dubbo/common/logger/Logger;
       8: return
}
