Compiled from "UrlUtils.java"
public class org.apache.dubbo.remoting.utils.UrlUtils {
  private static final java.lang.String ALLOWED_SERIALIZATION_KEY;

  public org.apache.dubbo.remoting.utils.UrlUtils();
    Code:
       0: aload_0
       1: invokespecial #2                  // Method java/lang/Object."<init>":()V
       4: return

  public static int getIdleTimeout(org.apache.dubbo.common.URL);
    Code:
       0: aload_0
       1: invokestatic  #3                  // Method getHeartbeat:(Lorg/apache/dubbo/common/URL;)I
       4: istore_1
       5: aload_0
       6: ldc           #4                  // String heartbeat.timeout
       8: iload_1
       9: iconst_3
      10: imul
      11: invokevirtual #5                  // Method org/apache/dubbo/common/URL.getParameter:(Ljava/lang/String;I)I
      14: istore_2
      15: iload_2
      16: iload_1
      17: iconst_2
      18: imul
      19: if_icmpge     32
      22: new           #6                  // class java/lang/IllegalStateException
      25: dup
      26: ldc           #7                  // String idleTimeout < heartbeatInterval * 2
      28: invokespecial #8                  // Method java/lang/IllegalStateException."<init>":(Ljava/lang/String;)V
      31: athrow
      32: iload_2
      33: ireturn

  public static int getHeartbeat(org.apache.dubbo.common.URL);
    Code:
       0: ldc           #9                  // String dubbo.protocol.default-heartbeat
       2: invokestatic  #10                 // Method java/lang/System.getProperty:(Ljava/lang/String;)Ljava/lang/String;
       5: astore_1
       6: ldc           #11                 // int 60000
       8: istore_2
       9: aload_1
      10: invokestatic  #12                 // Method org/apache/dubbo/common/utils/StringUtils.isNotEmpty:(Ljava/lang/String;)Z
      13: ifeq          25
      16: aload_1
      17: invokestatic  #13                 // Method java/lang/Integer.parseInt:(Ljava/lang/String;)I
      20: istore_2
      21: goto          25
      24: astore_3
      25: aload_0
      26: ldc           #15                 // String heartbeat
      28: iload_2
      29: invokevirtual #5                  // Method org/apache/dubbo/common/URL.getParameter:(Ljava/lang/String;I)I
      32: ireturn
    Exception table:
       from    to  target type
          16    21    24   Class java/lang/NumberFormatException

  public static java.lang.Byte serializationId(org.apache.dubbo.common.URL);
    Code:
       0: aload_0
       1: invokestatic  #16                 // Method preferSerialization:(Lorg/apache/dubbo/common/URL;)Ljava/util/List;
       4: astore_2
       5: aload_2
       6: invokeinterface #17,  1           // InterfaceMethod java/util/List.iterator:()Ljava/util/Iterator;
      11: astore_3
      12: aload_3
      13: invokeinterface #18,  1           // InterfaceMethod java/util/Iterator.hasNext:()Z
      18: ifeq          47
      21: aload_3
      22: invokeinterface #19,  1           // InterfaceMethod java/util/Iterator.next:()Ljava/lang/Object;
      27: checkcast     #20                 // class java/lang/String
      30: astore        4
      32: aload         4
      34: invokestatic  #21                 // Method org/apache/dubbo/remoting/transport/CodecSupport.getIDByName:(Ljava/lang/String;)Ljava/lang/Byte;
      37: dup
      38: astore_1
      39: ifnull        44
      42: aload_1
      43: areturn
      44: goto          12
      47: aload_0
      48: ldc           #22                 // String serialization
      50: invokevirtual #23                 // Method org/apache/dubbo/common/URL.getParameter:(Ljava/lang/String;)Ljava/lang/String;
      53: invokestatic  #21                 // Method org/apache/dubbo/remoting/transport/CodecSupport.getIDByName:(Ljava/lang/String;)Ljava/lang/Byte;
      56: dup
      57: astore_1
      58: ifnull        63
      61: aload_1
      62: areturn
      63: invokestatic  #24                 // Method org/apache/dubbo/common/serialize/support/DefaultSerializationSelector.getDefaultRemotingSerialization:()Ljava/lang/String;
      66: invokestatic  #21                 // Method org/apache/dubbo/remoting/transport/CodecSupport.getIDByName:(Ljava/lang/String;)Ljava/lang/Byte;
      69: areturn

  public static java.lang.String serializationOrDefault(org.apache.dubbo.common.URL);
    Code:
       0: aload_0
       1: invokestatic  #25                 // Method allSerializations:(Lorg/apache/dubbo/common/URL;)Ljava/util/Collection;
       4: invokeinterface #26,  1           // InterfaceMethod java/util/Collection.stream:()Ljava/util/stream/Stream;
       9: invokeinterface #27,  1           // InterfaceMethod java/util/stream/Stream.findFirst:()Ljava/util/Optional;
      14: astore_1
      15: aload_1
      16: invokedynamic #28,  0             // InvokeDynamic #0:get:()Ljava/util/function/Supplier;
      21: invokevirtual #29                 // Method java/util/Optional.orElseGet:(Ljava/util/function/Supplier;)Ljava/lang/Object;
      24: checkcast     #20                 // class java/lang/String
      27: areturn

  public static java.util.Collection<java.lang.String> allSerializations(org.apache.dubbo.common.URL);
    Code:
       0: new           #30                 // class java/util/LinkedHashSet
       3: dup
       4: aload_0
       5: invokestatic  #16                 // Method preferSerialization:(Lorg/apache/dubbo/common/URL;)Ljava/util/List;
       8: invokespecial #31                 // Method java/util/LinkedHashSet."<init>":(Ljava/util/Collection;)V
      11: astore_1
      12: aload_0
      13: ldc           #22                 // String serialization
      15: invokevirtual #23                 // Method org/apache/dubbo/common/URL.getParameter:(Ljava/lang/String;)Ljava/lang/String;
      18: invokestatic  #32                 // Method java/util/Optional.ofNullable:(Ljava/lang/Object;)Ljava/util/Optional;
      21: invokedynamic #33,  0             // InvokeDynamic #1:test:()Ljava/util/function/Predicate;
      26: invokevirtual #34                 // Method java/util/Optional.filter:(Ljava/util/function/Predicate;)Ljava/util/Optional;
      29: aload_1
      30: dup
      31: invokevirtual #35                 // Method java/lang/Object.getClass:()Ljava/lang/Class;
      34: pop
      35: invokedynamic #36,  0             // InvokeDynamic #2:accept:(Ljava/util/Set;)Ljava/util/function/Consumer;
      40: invokevirtual #37                 // Method java/util/Optional.ifPresent:(Ljava/util/function/Consumer;)V
      43: aload_1
      44: invokestatic  #24                 // Method org/apache/dubbo/common/serialize/support/DefaultSerializationSelector.getDefaultRemotingSerialization:()Ljava/lang/String;
      47: invokeinterface #38,  2           // InterfaceMethod java/util/Set.add:(Ljava/lang/Object;)Z
      52: pop
      53: aload_1
      54: invokestatic  #39                 // Method java/util/Collections.unmodifiableSet:(Ljava/util/Set;)Ljava/util/Set;
      57: areturn

  public static java.util.List<java.lang.String> preferSerialization(org.apache.dubbo.common.URL);
    Code:
       0: aload_0
       1: ldc           #40                 // String prefer.serialization
       3: invokevirtual #23                 // Method org/apache/dubbo/common/URL.getParameter:(Ljava/lang/String;)Ljava/lang/String;
       6: astore_1
       7: aload_1
       8: invokestatic  #41                 // Method org/apache/dubbo/common/utils/StringUtils.isNotBlank:(Ljava/lang/CharSequence;)Z
      11: ifeq          24
      14: aload_1
      15: bipush        44
      17: invokestatic  #42                 // Method org/apache/dubbo/common/utils/StringUtils.splitToList:(Ljava/lang/String;C)Ljava/util/List;
      20: invokestatic  #43                 // Method java/util/Collections.unmodifiableList:(Ljava/util/List;)Ljava/util/List;
      23: areturn
      24: invokestatic  #44                 // Method java/util/Collections.emptyList:()Ljava/util/List;
      27: areturn
}
