Compiled from "Bzip2.java"
public class org.apache.dubbo.rpc.protocol.tri.compressor.Bzip2 implements org.apache.dubbo.rpc.protocol.tri.compressor.Compressor,org.apache.dubbo.rpc.protocol.tri.compressor.DeCompressor {
  public static final java.lang.String BZIP2;

  public org.apache.dubbo.rpc.protocol.tri.compressor.Bzip2();
    Code:
       0: aload_0
       1: invokespecial #1                  // Method java/lang/Object."<init>":()V
       4: return

  public java.lang.String getMessageEncoding();
    Code:
       0: ldc           #3                  // String bzip2
       2: areturn

  public byte[] compress(byte[]) throws org.apache.dubbo.rpc.RpcException;
    Code:
       0: aconst_null
       1: aload_1
       2: if_acmpeq     11
       5: iconst_0
       6: aload_1
       7: arraylength
       8: if_icmpne     15
      11: iconst_0
      12: newarray       byte
      14: areturn
      15: new           #4                  // class org/apache/commons/io/output/ByteArrayOutputStream
      18: dup
      19: invokespecial #5                  // Method org/apache/commons/io/output/ByteArrayOutputStream."<init>":()V
      22: astore_2
      23: new           #6                  // class org/apache/commons/compress/compressors/bzip2/BZip2CompressorOutputStream
      26: dup
      27: aload_2
      28: invokespecial #7                  // Method org/apache/commons/compress/compressors/bzip2/BZip2CompressorOutputStream."<init>":(Ljava/io/OutputStream;)V
      31: astore_3
      32: aload_3
      33: aload_1
      34: invokevirtual #8                  // Method org/apache/commons/compress/compressors/bzip2/BZip2CompressorOutputStream.write:([B)V
      37: aload_3
      38: invokevirtual #9                  // Method org/apache/commons/compress/compressors/bzip2/BZip2CompressorOutputStream.close:()V
      41: goto          56
      44: astore        4
      46: new           #11                 // class java/lang/IllegalStateException
      49: dup
      50: aload         4
      52: invokespecial #12                 // Method java/lang/IllegalStateException."<init>":(Ljava/lang/Throwable;)V
      55: athrow
      56: aload_2
      57: invokevirtual #13                 // Method org/apache/commons/io/output/ByteArrayOutputStream.toByteArray:()[B
      60: areturn
    Exception table:
       from    to  target type
          23    41    44   Class java/lang/Exception

  public byte[] decompress(byte[]);
    Code:
       0: aconst_null
       1: aload_1
       2: if_acmpeq     11
       5: iconst_0
       6: aload_1
       7: arraylength
       8: if_icmpne     15
      11: iconst_0
      12: newarray       byte
      14: areturn
      15: new           #4                  // class org/apache/commons/io/output/ByteArrayOutputStream
      18: dup
      19: invokespecial #5                  // Method org/apache/commons/io/output/ByteArrayOutputStream."<init>":()V
      22: astore_2
      23: new           #14                 // class java/io/ByteArrayInputStream
      26: dup
      27: aload_1
      28: invokespecial #15                 // Method java/io/ByteArrayInputStream."<init>":([B)V
      31: astore_3
      32: new           #16                 // class org/apache/commons/compress/compressors/bzip2/BZip2CompressorInputStream
      35: dup
      36: aload_3
      37: invokespecial #17                 // Method org/apache/commons/compress/compressors/bzip2/BZip2CompressorInputStream."<init>":(Ljava/io/InputStream;)V
      40: astore        4
      42: sipush        2048
      45: newarray       byte
      47: astore        5
      49: aload         4
      51: aload         5
      53: invokevirtual #18                 // Method org/apache/commons/compress/compressors/bzip2/BZip2CompressorInputStream.read:([B)I
      56: dup
      57: istore        6
      59: iflt          74
      62: aload_2
      63: aload         5
      65: iconst_0
      66: iload         6
      68: invokevirtual #19                 // Method org/apache/commons/io/output/ByteArrayOutputStream.write:([BII)V
      71: goto          49
      74: goto          89
      77: astore        4
      79: new           #11                 // class java/lang/IllegalStateException
      82: dup
      83: aload         4
      85: invokespecial #12                 // Method java/lang/IllegalStateException."<init>":(Ljava/lang/Throwable;)V
      88: athrow
      89: aload_2
      90: invokevirtual #13                 // Method org/apache/commons/io/output/ByteArrayOutputStream.toByteArray:()[B
      93: areturn
    Exception table:
       from    to  target type
          32    74    77   Class java/lang/Exception
}
