Compiled from "Compressor.java"
public interface org.apache.dubbo.rpc.protocol.tri.compressor.Compressor extends org.apache.dubbo.rpc.protocol.tri.compressor.MessageEncoding {
  public static final org.apache.dubbo.rpc.protocol.tri.compressor.Compressor NONE;

  public static org.apache.dubbo.rpc.protocol.tri.compressor.Compressor getCompressor(org.apache.dubbo.rpc.model.FrameworkModel, java.lang.String);
    Code:
       0: aconst_null
       1: aload_1
       2: if_acmpne     7
       5: aconst_null
       6: areturn
       7: aload_1
       8: ldc           #2                  // String identity
      10: invokevirtual #3                  // Method java/lang/String.equals:(Ljava/lang/Object;)Z
      13: ifeq          20
      16: getstatic     #4                  // Field NONE:Lorg/apache/dubbo/rpc/protocol/tri/compressor/Compressor;
      19: areturn
      20: aload_0
      21: ldc           #5                  // class org/apache/dubbo/rpc/protocol/tri/compressor/Compressor
      23: invokevirtual #6                  // Method org/apache/dubbo/rpc/model/FrameworkModel.getExtensionLoader:(Ljava/lang/Class;)Lorg/apache/dubbo/common/extension/ExtensionLoader;
      26: aload_1
      27: invokevirtual #7                  // Method org/apache/dubbo/common/extension/ExtensionLoader.getExtension:(Ljava/lang/String;)Ljava/lang/Object;
      30: checkcast     #5                  // class org/apache/dubbo/rpc/protocol/tri/compressor/Compressor
      33: areturn

  public abstract byte[] compress(byte[]);

  static {};
    Code:
       0: getstatic     #8                  // Field org/apache/dubbo/rpc/protocol/tri/compressor/Identity.IDENTITY:Lorg/apache/dubbo/rpc/protocol/tri/compressor/Identity;
       3: putstatic     #4                  // Field NONE:Lorg/apache/dubbo/rpc/protocol/tri/compressor/Compressor;
       6: return
}
