Compiled from "Identity.java"
public class org.apache.dubbo.rpc.protocol.tri.compressor.Identity implements org.apache.dubbo.rpc.protocol.tri.compressor.Compressor,org.apache.dubbo.rpc.protocol.tri.compressor.DeCompressor {
  public static final java.lang.String MESSAGE_ENCODING;

  public static final org.apache.dubbo.rpc.protocol.tri.compressor.Identity IDENTITY;

  public org.apache.dubbo.rpc.protocol.tri.compressor.Identity();
    Code:
       0: aload_0
       1: invokespecial #1                  // Method java/lang/Object."<init>":()V
       4: return

  public java.lang.String getMessageEncoding();
    Code:
       0: ldc           #3                  // String identity
       2: areturn

  public byte[] compress(byte[]);
    Code:
       0: aload_1
       1: areturn

  public byte[] decompress(byte[]);
    Code:
       0: aload_1
       1: areturn

  static {};
    Code:
       0: new           #2                  // class org/apache/dubbo/rpc/protocol/tri/compressor/Identity
       3: dup
       4: invokespecial #4                  // Method "<init>":()V
       7: putstatic     #5                  // Field IDENTITY:Lorg/apache/dubbo/rpc/protocol/tri/compressor/Identity;
      10: return
}
