Compiled from "Snappy.java"
public class org.apache.dubbo.rpc.protocol.tri.compressor.Snappy implements org.apache.dubbo.rpc.protocol.tri.compressor.Compressor,org.apache.dubbo.rpc.protocol.tri.compressor.DeCompressor {
  public static final java.lang.String SNAPPY;

  public org.apache.dubbo.rpc.protocol.tri.compressor.Snappy();
    Code:
       0: aload_0
       1: invokespecial #1                  // Method java/lang/Object."<init>":()V
       4: return

  public java.lang.String getMessageEncoding();
    Code:
       0: ldc           #3                  // String snappy
       2: areturn

  public byte[] compress(byte[]) throws org.apache.dubbo.rpc.RpcException;
    Code:
       0: aconst_null
       1: aload_1
       2: if_acmpeq     11
       5: iconst_0
       6: aload_1
       7: arraylength
       8: if_icmpne     15
      11: iconst_0
      12: newarray       byte
      14: areturn
      15: aload_1
      16: invokestatic  #4                  // Method org/xerial/snappy/Snappy.compress:([B)[B
      19: areturn
      20: astore_2
      21: new           #6                  // class java/lang/IllegalStateException
      24: dup
      25: aload_2
      26: invokespecial #7                  // Method java/lang/IllegalStateException."<init>":(Ljava/lang/Throwable;)V
      29: athrow
    Exception table:
       from    to  target type
          15    19    20   Class java/io/IOException

  public byte[] decompress(byte[]);
    Code:
       0: aconst_null
       1: aload_1
       2: if_acmpeq     11
       5: iconst_0
       6: aload_1
       7: arraylength
       8: if_icmpne     15
      11: iconst_0
      12: newarray       byte
      14: areturn
      15: aload_1
      16: invokestatic  #8                  // Method org/xerial/snappy/Snappy.uncompress:([B)[B
      19: areturn
      20: astore_2
      21: new           #6                  // class java/lang/IllegalStateException
      24: dup
      25: aload_2
      26: invokespecial #7                  // Method java/lang/IllegalStateException."<init>":(Ljava/lang/Throwable;)V
      29: athrow
    Exception table:
       from    to  target type
          15    19    20   Class java/io/IOException
}
