Compiled from "ApplicationContextHeaderFilter.java"
public class org.springframework.boot.web.servlet.filter.ApplicationContextHeaderFilter extends org.springframework.web.filter.OncePerRequestFilter {
  public static final java.lang.String HEADER_NAME;

  private final org.springframework.context.ApplicationContext applicationContext;

  public org.springframework.boot.web.servlet.filter.ApplicationContextHeaderFilter(org.springframework.context.ApplicationContext);
    Code:
       0: aload_0
       1: invokespecial #1                  // Method org/springframework/web/filter/OncePerRequestFilter."<init>":()V
       4: aload_0
       5: aload_1
       6: putfield      #7                  // Field applicationContext:Lorg/springframework/context/ApplicationContext;
       9: return

  protected void doFilterInternal(jakarta.servlet.http.HttpServletRequest, jakarta.servlet.http.HttpServletResponse, jakarta.servlet.FilterChain) throws jakarta.servlet.ServletException, java.io.IOException;
    Code:
       0: aload_2
       1: ldc           #13                 // String X-Application-Context
       3: aload_0
       4: getfield      #7                  // Field applicationContext:Lorg/springframework/context/ApplicationContext;
       7: invokeinterface #15,  1           // InterfaceMethod org/springframework/context/ApplicationContext.getId:()Ljava/lang/String;
      12: invokeinterface #21,  3           // InterfaceMethod jakarta/servlet/http/HttpServletResponse.addHeader:(Ljava/lang/String;Ljava/lang/String;)V
      17: aload_3
      18: aload_1
      19: aload_2
      20: invokeinterface #27,  3           // InterfaceMethod jakarta/servlet/FilterChain.doFilter:(Ljakarta/servlet/ServletRequest;Ljakarta/servlet/ServletResponse;)V
      25: return
}
