Compiled from "GracefulShutdown.java"
final class org.springframework.boot.web.embedded.netty.GracefulShutdown {
  private static final org.apache.commons.logging.Log logger;

  private final java.util.function.Supplier<reactor.netty.DisposableServer> disposableServer;

  private volatile java.lang.Thread shutdownThread;

  private volatile boolean shuttingDown;

  org.springframework.boot.web.embedded.netty.GracefulShutdown(java.util.function.Supplier<reactor.netty.DisposableServer>);
    Code:
       0: aload_0
       1: invokespecial #1                  // Method java/lang/Object."<init>":()V
       4: aload_0
       5: aload_1
       6: putfield      #7                  // Field disposableServer:Ljava/util/function/Supplier;
       9: return

  void shutDownGracefully(org.springframework.boot.web.server.GracefulShutdownCallback);
    Code:
       0: aload_0
       1: getfield      #7                  // Field disposableServer:Ljava/util/function/Supplier;
       4: invokeinterface #13,  1           // InterfaceMethod java/util/function/Supplier.get:()Ljava/lang/Object;
       9: checkcast     #19                 // class reactor/netty/DisposableServer
      12: astore_2
      13: aload_2
      14: ifnonnull     18
      17: return
      18: getstatic     #21                 // Field logger:Lorg/apache/commons/logging/Log;
      21: ldc           #25                 // String Commencing graceful shutdown. Waiting for active requests to complete
      23: invokeinterface #27,  2           // InterfaceMethod org/apache/commons/logging/Log.info:(Ljava/lang/Object;)V
      28: aload_0
      29: new           #33                 // class java/lang/Thread
      32: dup
      33: aload_0
      34: aload_1
      35: aload_2
      36: invokedynamic #35,  0             // InvokeDynamic #0:run:(Lorg/springframework/boot/web/embedded/netty/GracefulShutdown;Lorg/springframework/boot/web/server/GracefulShutdownCallback;Lreactor/netty/DisposableServer;)Ljava/lang/Runnable;
      41: ldc           #39                 // String netty-shutdown
      43: invokespecial #41                 // Method java/lang/Thread."<init>":(Ljava/lang/Runnable;Ljava/lang/String;)V
      46: putfield      #44                 // Field shutdownThread:Ljava/lang/Thread;
      49: aload_0
      50: getfield      #44                 // Field shutdownThread:Ljava/lang/Thread;
      53: invokevirtual #48                 // Method java/lang/Thread.start:()V
      56: return

  private void doShutdown(org.springframework.boot.web.server.GracefulShutdownCallback, reactor.netty.DisposableServer);
    Code:
       0: aload_0
       1: iconst_1
       2: putfield      #51                 // Field shuttingDown:Z
       5: aload_2
       6: ldc2_w        #57                 // long 9223372036854775807l
       9: invokestatic  #59                 // Method java/time/Duration.ofNanos:(J)Ljava/time/Duration;
      12: invokeinterface #65,  2           // InterfaceMethod reactor/netty/DisposableServer.disposeNow:(Ljava/time/Duration;)V
      17: getstatic     #21                 // Field logger:Lorg/apache/commons/logging/Log;
      20: ldc           #69                 // String Graceful shutdown complete
      22: invokeinterface #27,  2           // InterfaceMethod org/apache/commons/logging/Log.info:(Ljava/lang/Object;)V
      27: aload_1
      28: getstatic     #71                 // Field org/springframework/boot/web/server/GracefulShutdownResult.IDLE:Lorg/springframework/boot/web/server/GracefulShutdownResult;
      31: invokeinterface #77,  2           // InterfaceMethod org/springframework/boot/web/server/GracefulShutdownCallback.shutdownComplete:(Lorg/springframework/boot/web/server/GracefulShutdownResult;)V
      36: aload_0
      37: aconst_null
      38: putfield      #44                 // Field shutdownThread:Ljava/lang/Thread;
      41: aload_0
      42: iconst_0
      43: putfield      #51                 // Field shuttingDown:Z
      46: goto          97
      49: astore_3
      50: getstatic     #21                 // Field logger:Lorg/apache/commons/logging/Log;
      53: ldc           #85                 // String Graceful shutdown aborted with one or more requests still active
      55: invokeinterface #27,  2           // InterfaceMethod org/apache/commons/logging/Log.info:(Ljava/lang/Object;)V
      60: aload_1
      61: getstatic     #87                 // Field org/springframework/boot/web/server/GracefulShutdownResult.REQUESTS_ACTIVE:Lorg/springframework/boot/web/server/GracefulShutdownResult;
      64: invokeinterface #77,  2           // InterfaceMethod org/springframework/boot/web/server/GracefulShutdownCallback.shutdownComplete:(Lorg/springframework/boot/web/server/GracefulShutdownResult;)V
      69: aload_0
      70: aconst_null
      71: putfield      #44                 // Field shutdownThread:Ljava/lang/Thread;
      74: aload_0
      75: iconst_0
      76: putfield      #51                 // Field shuttingDown:Z
      79: goto          97
      82: astore        4
      84: aload_0
      85: aconst_null
      86: putfield      #44                 // Field shutdownThread:Ljava/lang/Thread;
      89: aload_0
      90: iconst_0
      91: putfield      #51                 // Field shuttingDown:Z
      94: aload         4
      96: athrow
      97: return
    Exception table:
       from    to  target type
           5    36    49   Class java/lang/Exception
           5    36    82   any
          49    69    82   any
          82    84    82   any

  void abort();
    Code:
       0: aload_0
       1: getfield      #44                 // Field shutdownThread:Ljava/lang/Thread;
       4: astore_1
       5: aload_1
       6: ifnull        30
       9: aload_0
      10: getfield      #51                 // Field shuttingDown:Z
      13: ifne          26
      16: aload_0
      17: ldc2_w        #90                 // long 50l
      20: invokevirtual #92                 // Method sleep:(J)V
      23: goto          9
      26: aload_1
      27: invokevirtual #96                 // Method java/lang/Thread.interrupt:()V
      30: return

  private void sleep(long);
    Code:
       0: lload_1
       1: invokestatic  #99                 // Method java/lang/Thread.sleep:(J)V
       4: goto          14
       7: astore_3
       8: invokestatic  #102                // Method java/lang/Thread.currentThread:()Ljava/lang/Thread;
      11: invokevirtual #96                 // Method java/lang/Thread.interrupt:()V
      14: return
    Exception table:
       from    to  target type
           0     4     7   Class java/lang/InterruptedException

  private void lambda$shutDownGracefully$0(org.springframework.boot.web.server.GracefulShutdownCallback, reactor.netty.DisposableServer);
    Code:
       0: aload_0
       1: aload_1
       2: aload_2
       3: invokevirtual #106                // Method doShutdown:(Lorg/springframework/boot/web/server/GracefulShutdownCallback;Lreactor/netty/DisposableServer;)V
       6: return

  static {};
    Code:
       0: ldc           #8                  // class org/springframework/boot/web/embedded/netty/GracefulShutdown
       2: invokestatic  #110                // Method org/apache/commons/logging/LogFactory.getLog:(Ljava/lang/Class;)Lorg/apache/commons/logging/Log;
       5: putstatic     #21                 // Field logger:Lorg/apache/commons/logging/Log;
       8: return
}
