Compiled from "NettyReactiveWebServerFactory.java"
public class org.springframework.boot.web.embedded.netty.NettyReactiveWebServerFactory extends org.springframework.boot.web.reactive.server.AbstractReactiveWebServerFactory {
  private java.util.Set<org.springframework.boot.web.embedded.netty.NettyServerCustomizer> serverCustomizers;

  private final java.util.List<org.springframework.boot.web.embedded.netty.NettyRouteProvider> routeProviders;

  private java.time.Duration lifecycleTimeout;

  private boolean useForwardHeaders;

  private org.springframework.http.client.reactive.ReactorResourceFactory resourceFactory;

  private org.springframework.boot.web.server.Shutdown shutdown;

  public org.springframework.boot.web.embedded.netty.NettyReactiveWebServerFactory();
    Code:
       0: aload_0
       1: invokespecial #1                  // Method org/springframework/boot/web/reactive/server/AbstractReactiveWebServerFactory."<init>":()V
       4: aload_0
       5: new           #7                  // class java/util/LinkedHashSet
       8: dup
       9: invokespecial #9                  // Method java/util/LinkedHashSet."<init>":()V
      12: putfield      #10                 // Field serverCustomizers:Ljava/util/Set;
      15: aload_0
      16: new           #16                 // class java/util/ArrayList
      19: dup
      20: invokespecial #18                 // Method java/util/ArrayList."<init>":()V
      23: putfield      #19                 // Field routeProviders:Ljava/util/List;
      26: return

  public org.springframework.boot.web.embedded.netty.NettyReactiveWebServerFactory(int);
    Code:
       0: aload_0
       1: iload_1
       2: invokespecial #23                 // Method org/springframework/boot/web/reactive/server/AbstractReactiveWebServerFactory."<init>":(I)V
       5: aload_0
       6: new           #7                  // class java/util/LinkedHashSet
       9: dup
      10: invokespecial #9                  // Method java/util/LinkedHashSet."<init>":()V
      13: putfield      #10                 // Field serverCustomizers:Ljava/util/Set;
      16: aload_0
      17: new           #16                 // class java/util/ArrayList
      20: dup
      21: invokespecial #18                 // Method java/util/ArrayList."<init>":()V
      24: putfield      #19                 // Field routeProviders:Ljava/util/List;
      27: return

  public org.springframework.boot.web.server.WebServer getWebServer(org.springframework.http.server.reactive.HttpHandler);
    Code:
       0: aload_0
       1: invokevirtual #26                 // Method createHttpServer:()Lreactor/netty/http/server/HttpServer;
       4: astore_2
       5: new           #30                 // class org/springframework/http/server/reactive/ReactorHttpHandlerAdapter
       8: dup
       9: aload_1
      10: invokespecial #32                 // Method org/springframework/http/server/reactive/ReactorHttpHandlerAdapter."<init>":(Lorg/springframework/http/server/reactive/HttpHandler;)V
      13: astore_3
      14: aload_0
      15: aload_2
      16: aload_3
      17: aload_0
      18: getfield      #35                 // Field lifecycleTimeout:Ljava/time/Duration;
      21: aload_0
      22: invokevirtual #39                 // Method getShutdown:()Lorg/springframework/boot/web/server/Shutdown;
      25: invokevirtual #43                 // Method createNettyWebServer:(Lreactor/netty/http/server/HttpServer;Lorg/springframework/http/server/reactive/ReactorHttpHandlerAdapter;Ljava/time/Duration;Lorg/springframework/boot/web/server/Shutdown;)Lorg/springframework/boot/web/embedded/netty/NettyWebServer;
      28: astore        4
      30: aload         4
      32: aload_0
      33: getfield      #19                 // Field routeProviders:Ljava/util/List;
      36: invokevirtual #47                 // Method org/springframework/boot/web/embedded/netty/NettyWebServer.setRouteProviders:(Ljava/util/List;)V
      39: aload         4
      41: areturn

  org.springframework.boot.web.embedded.netty.NettyWebServer createNettyWebServer(reactor.netty.http.server.HttpServer, org.springframework.http.server.reactive.ReactorHttpHandlerAdapter, java.time.Duration, org.springframework.boot.web.server.Shutdown);
    Code:
       0: new           #48                 // class org/springframework/boot/web/embedded/netty/NettyWebServer
       3: dup
       4: aload_1
       5: aload_2
       6: aload_3
       7: aload         4
       9: invokespecial #53                 // Method org/springframework/boot/web/embedded/netty/NettyWebServer."<init>":(Lreactor/netty/http/server/HttpServer;Lorg/springframework/http/server/reactive/ReactorHttpHandlerAdapter;Ljava/time/Duration;Lorg/springframework/boot/web/server/Shutdown;)V
      12: areturn

  public java.util.Collection<org.springframework.boot.web.embedded.netty.NettyServerCustomizer> getServerCustomizers();
    Code:
       0: aload_0
       1: getfield      #10                 // Field serverCustomizers:Ljava/util/Set;
       4: areturn

  public void setServerCustomizers(java.util.Collection<? extends org.springframework.boot.web.embedded.netty.NettyServerCustomizer>);
    Code:
       0: aload_1
       1: ldc           #56                 // String ServerCustomizers must not be null
       3: invokestatic  #58                 // Method org/springframework/util/Assert.notNull:(Ljava/lang/Object;Ljava/lang/String;)V
       6: aload_0
       7: new           #7                  // class java/util/LinkedHashSet
      10: dup
      11: aload_1
      12: invokespecial #64                 // Method java/util/LinkedHashSet."<init>":(Ljava/util/Collection;)V
      15: putfield      #10                 // Field serverCustomizers:Ljava/util/Set;
      18: return

  public void addServerCustomizers(org.springframework.boot.web.embedded.netty.NettyServerCustomizer...);
    Code:
       0: aload_1
       1: ldc           #67                 // String ServerCustomizer must not be null
       3: invokestatic  #58                 // Method org/springframework/util/Assert.notNull:(Ljava/lang/Object;Ljava/lang/String;)V
       6: aload_0
       7: getfield      #10                 // Field serverCustomizers:Ljava/util/Set;
      10: aload_1
      11: invokestatic  #69                 // Method java/util/Arrays.asList:([Ljava/lang/Object;)Ljava/util/List;
      14: invokeinterface #75,  2           // InterfaceMethod java/util/Set.addAll:(Ljava/util/Collection;)Z
      19: pop
      20: return

  public void addRouteProviders(org.springframework.boot.web.embedded.netty.NettyRouteProvider...);
    Code:
       0: aload_1
       1: ldc           #81                 // String NettyRouteProvider must not be null
       3: invokestatic  #58                 // Method org/springframework/util/Assert.notNull:(Ljava/lang/Object;Ljava/lang/String;)V
       6: aload_0
       7: getfield      #19                 // Field routeProviders:Ljava/util/List;
      10: aload_1
      11: invokestatic  #69                 // Method java/util/Arrays.asList:([Ljava/lang/Object;)Ljava/util/List;
      14: invokeinterface #83,  2           // InterfaceMethod java/util/List.addAll:(Ljava/util/Collection;)Z
      19: pop
      20: return

  public void setLifecycleTimeout(java.time.Duration);
    Code:
       0: aload_0
       1: aload_1
       2: putfield      #35                 // Field lifecycleTimeout:Ljava/time/Duration;
       5: return

  public void setUseForwardHeaders(boolean);
    Code:
       0: aload_0
       1: iload_1
       2: putfield      #86                 // Field useForwardHeaders:Z
       5: return

  public void setResourceFactory(org.springframework.http.client.reactive.ReactorResourceFactory);
    Code:
       0: aload_0
       1: aload_1
       2: putfield      #90                 // Field resourceFactory:Lorg/springframework/http/client/reactive/ReactorResourceFactory;
       5: return

  public void setShutdown(org.springframework.boot.web.server.Shutdown);
    Code:
       0: aload_0
       1: aload_1
       2: putfield      #94                 // Field shutdown:Lorg/springframework/boot/web/server/Shutdown;
       5: return

  public org.springframework.boot.web.server.Shutdown getShutdown();
    Code:
       0: aload_0
       1: getfield      #94                 // Field shutdown:Lorg/springframework/boot/web/server/Shutdown;
       4: areturn

  private reactor.netty.http.server.HttpServer createHttpServer();
    Code:
       0: invokestatic  #98                 // Method reactor/netty/http/server/HttpServer.create:()Lreactor/netty/http/server/HttpServer;
       3: astore_1
       4: aload_0
       5: getfield      #90                 // Field resourceFactory:Lorg/springframework/http/client/reactive/ReactorResourceFactory;
       8: ifnull        46
      11: aload_0
      12: getfield      #90                 // Field resourceFactory:Lorg/springframework/http/client/reactive/ReactorResourceFactory;
      15: invokevirtual #103                // Method org/springframework/http/client/reactive/ReactorResourceFactory.getLoopResources:()Lreactor/netty/resources/LoopResources;
      18: astore_2
      19: aload_2
      20: ldc           #109                // String No LoopResources: is ReactorResourceFactory not initialized yet?
      22: invokestatic  #58                 // Method org/springframework/util/Assert.notNull:(Ljava/lang/Object;Ljava/lang/String;)V
      25: aload_1
      26: aload_2
      27: invokevirtual #111                // Method reactor/netty/http/server/HttpServer.runOn:(Lreactor/netty/resources/LoopResources;)Lreactor/netty/transport/Transport;
      30: checkcast     #99                 // class reactor/netty/http/server/HttpServer
      33: aload_0
      34: invokedynamic #115,  0            // InvokeDynamic #0:get:(Lorg/springframework/boot/web/embedded/netty/NettyReactiveWebServerFactory;)Ljava/util/function/Supplier;
      39: invokevirtual #119                // Method reactor/netty/http/server/HttpServer.bindAddress:(Ljava/util/function/Supplier;)Lreactor/netty/http/server/HttpServer;
      42: astore_1
      43: goto          57
      46: aload_1
      47: aload_0
      48: invokedynamic #115,  0            // InvokeDynamic #0:get:(Lorg/springframework/boot/web/embedded/netty/NettyReactiveWebServerFactory;)Ljava/util/function/Supplier;
      53: invokevirtual #119                // Method reactor/netty/http/server/HttpServer.bindAddress:(Ljava/util/function/Supplier;)Lreactor/netty/http/server/HttpServer;
      56: astore_1
      57: aload_0
      58: invokevirtual #123                // Method getSsl:()Lorg/springframework/boot/web/server/Ssl;
      61: invokestatic  #127                // Method org/springframework/boot/web/server/Ssl.isEnabled:(Lorg/springframework/boot/web/server/Ssl;)Z
      64: ifeq          73
      67: aload_0
      68: aload_1
      69: invokevirtual #133                // Method customizeSslConfiguration:(Lreactor/netty/http/server/HttpServer;)Lreactor/netty/http/server/HttpServer;
      72: astore_1
      73: aload_0
      74: invokevirtual #137                // Method getCompression:()Lorg/springframework/boot/web/server/Compression;
      77: ifnull        108
      80: aload_0
      81: invokevirtual #137                // Method getCompression:()Lorg/springframework/boot/web/server/Compression;
      84: invokevirtual #141                // Method org/springframework/boot/web/server/Compression.getEnabled:()Z
      87: ifeq          108
      90: new           #147                // class org/springframework/boot/web/embedded/netty/CompressionCustomizer
      93: dup
      94: aload_0
      95: invokevirtual #137                // Method getCompression:()Lorg/springframework/boot/web/server/Compression;
      98: invokespecial #149                // Method org/springframework/boot/web/embedded/netty/CompressionCustomizer."<init>":(Lorg/springframework/boot/web/server/Compression;)V
     101: astore_2
     102: aload_2
     103: aload_1
     104: invokevirtual #152                // Method org/springframework/boot/web/embedded/netty/CompressionCustomizer.apply:(Lreactor/netty/http/server/HttpServer;)Lreactor/netty/http/server/HttpServer;
     107: astore_1
     108: aload_1
     109: aload_0
     110: invokevirtual #155                // Method listProtocols:()[Lreactor/netty/http/HttpProtocol;
     113: invokevirtual #159                // Method reactor/netty/http/server/HttpServer.protocol:([Lreactor/netty/http/HttpProtocol;)Lreactor/netty/http/server/HttpServer;
     116: aload_0
     117: getfield      #86                 // Field useForwardHeaders:Z
     120: invokevirtual #163                // Method reactor/netty/http/server/HttpServer.forwarded:(Z)Lreactor/netty/http/server/HttpServer;
     123: astore_1
     124: aload_0
     125: aload_1
     126: invokevirtual #167                // Method applyCustomizers:(Lreactor/netty/http/server/HttpServer;)Lreactor/netty/http/server/HttpServer;
     129: areturn

  private reactor.netty.http.server.HttpServer customizeSslConfiguration(reactor.netty.http.server.HttpServer);
    Code:
       0: new           #170                // class org/springframework/boot/web/embedded/netty/SslServerCustomizer
       3: dup
       4: aload_0
       5: invokevirtual #172                // Method getHttp2:()Lorg/springframework/boot/web/server/Http2;
       8: aload_0
       9: invokevirtual #123                // Method getSsl:()Lorg/springframework/boot/web/server/Ssl;
      12: invokevirtual #176                // Method org/springframework/boot/web/server/Ssl.getClientAuth:()Lorg/springframework/boot/web/server/Ssl$ClientAuth;
      15: aload_0
      16: invokevirtual #180                // Method getSslBundle:()Lorg/springframework/boot/ssl/SslBundle;
      19: invokespecial #184                // Method org/springframework/boot/web/embedded/netty/SslServerCustomizer."<init>":(Lorg/springframework/boot/web/server/Http2;Lorg/springframework/boot/web/server/Ssl$ClientAuth;Lorg/springframework/boot/ssl/SslBundle;)V
      22: aload_1
      23: invokevirtual #187                // Method org/springframework/boot/web/embedded/netty/SslServerCustomizer.apply:(Lreactor/netty/http/server/HttpServer;)Lreactor/netty/http/server/HttpServer;
      26: areturn

  private reactor.netty.http.HttpProtocol[] listProtocols();
    Code:
       0: new           #16                 // class java/util/ArrayList
       3: dup
       4: invokespecial #18                 // Method java/util/ArrayList."<init>":()V
       7: astore_1
       8: aload_1
       9: getstatic     #188                // Field reactor/netty/http/HttpProtocol.HTTP11:Lreactor/netty/http/HttpProtocol;
      12: invokeinterface #194,  2          // InterfaceMethod java/util/List.add:(Ljava/lang/Object;)Z
      17: pop
      18: aload_0
      19: invokevirtual #172                // Method getHttp2:()Lorg/springframework/boot/web/server/Http2;
      22: ifnull        75
      25: aload_0
      26: invokevirtual #172                // Method getHttp2:()Lorg/springframework/boot/web/server/Http2;
      29: invokevirtual #198                // Method org/springframework/boot/web/server/Http2.isEnabled:()Z
      32: ifeq          75
      35: aload_0
      36: invokevirtual #123                // Method getSsl:()Lorg/springframework/boot/web/server/Ssl;
      39: ifnull        65
      42: aload_0
      43: invokevirtual #123                // Method getSsl:()Lorg/springframework/boot/web/server/Ssl;
      46: invokevirtual #202                // Method org/springframework/boot/web/server/Ssl.isEnabled:()Z
      49: ifeq          65
      52: aload_1
      53: getstatic     #203                // Field reactor/netty/http/HttpProtocol.H2:Lreactor/netty/http/HttpProtocol;
      56: invokeinterface #194,  2          // InterfaceMethod java/util/List.add:(Ljava/lang/Object;)Z
      61: pop
      62: goto          75
      65: aload_1
      66: getstatic     #206                // Field reactor/netty/http/HttpProtocol.H2C:Lreactor/netty/http/HttpProtocol;
      69: invokeinterface #194,  2          // InterfaceMethod java/util/List.add:(Ljava/lang/Object;)Z
      74: pop
      75: aload_1
      76: iconst_0
      77: anewarray     #189                // class reactor/netty/http/HttpProtocol
      80: invokeinterface #209,  2          // InterfaceMethod java/util/List.toArray:([Ljava/lang/Object;)[Ljava/lang/Object;
      85: checkcast     #213                // class "[Lreactor/netty/http/HttpProtocol;"
      88: areturn

  private java.net.InetSocketAddress getListenAddress();
    Code:
       0: aload_0
       1: invokevirtual #215                // Method getAddress:()Ljava/net/InetAddress;
       4: ifnull        26
       7: new           #219                // class java/net/InetSocketAddress
      10: dup
      11: aload_0
      12: invokevirtual #215                // Method getAddress:()Ljava/net/InetAddress;
      15: invokevirtual #221                // Method java/net/InetAddress.getHostAddress:()Ljava/lang/String;
      18: aload_0
      19: invokevirtual #227                // Method getPort:()I
      22: invokespecial #231                // Method java/net/InetSocketAddress."<init>":(Ljava/lang/String;I)V
      25: areturn
      26: new           #219                // class java/net/InetSocketAddress
      29: dup
      30: aload_0
      31: invokevirtual #227                // Method getPort:()I
      34: invokespecial #234                // Method java/net/InetSocketAddress."<init>":(I)V
      37: areturn

  private reactor.netty.http.server.HttpServer applyCustomizers(reactor.netty.http.server.HttpServer);
    Code:
       0: aload_0
       1: getfield      #10                 // Field serverCustomizers:Ljava/util/Set;
       4: invokeinterface #235,  1          // InterfaceMethod java/util/Set.iterator:()Ljava/util/Iterator;
       9: astore_2
      10: aload_2
      11: invokeinterface #239,  1          // InterfaceMethod java/util/Iterator.hasNext:()Z
      16: ifeq          43
      19: aload_2
      20: invokeinterface #244,  1          // InterfaceMethod java/util/Iterator.next:()Ljava/lang/Object;
      25: checkcast     #248                // class org/springframework/boot/web/embedded/netty/NettyServerCustomizer
      28: astore_3
      29: aload_3
      30: aload_1
      31: invokeinterface #250,  2          // InterfaceMethod org/springframework/boot/web/embedded/netty/NettyServerCustomizer.apply:(Ljava/lang/Object;)Ljava/lang/Object;
      36: checkcast     #99                 // class reactor/netty/http/server/HttpServer
      39: astore_1
      40: goto          10
      43: aload_1
      44: areturn
}
