Compiled from "ApplicationServletEnvironment.java"
class org.springframework.boot.web.servlet.context.ApplicationServletEnvironment extends org.springframework.web.context.support.StandardServletEnvironment {
  org.springframework.boot.web.servlet.context.ApplicationServletEnvironment();
    Code:
       0: aload_0
       1: invokespecial #1                  // Method org/springframework/web/context/support/StandardServletEnvironment."<init>":()V
       4: return

  protected java.lang.String doGetActiveProfilesProperty();
    Code:
       0: aconst_null
       1: areturn

  protected java.lang.String doGetDefaultProfilesProperty();
    Code:
       0: aconst_null
       1: areturn

  protected org.springframework.core.env.ConfigurablePropertyResolver createPropertyResolver(org.springframework.core.env.MutablePropertySources);
    Code:
       0: aload_1
       1: invokestatic  #7                  // Method org/springframework/boot/context/properties/source/ConfigurationPropertySources.createPropertyResolver:(Lorg/springframework/core/env/MutablePropertySources;)Lorg/springframework/core/env/ConfigurablePropertyResolver;
       4: areturn
}
