Compiled from "WebApplicationContextServletContextAwareProcessor.java"
public class org.springframework.boot.web.servlet.context.WebApplicationContextServletContextAwareProcessor extends org.springframework.web.context.support.ServletContextAwareProcessor {
  private final org.springframework.web.context.ConfigurableWebApplicationContext webApplicationContext;

  public org.springframework.boot.web.servlet.context.WebApplicationContextServletContextAwareProcessor(org.springframework.web.context.ConfigurableWebApplicationContext);
    Code:
       0: aload_0
       1: invokespecial #1                  // Method org/springframework/web/context/support/ServletContextAwareProcessor."<init>":()V
       4: aload_1
       5: ldc           #7                  // String WebApplicationContext must not be null
       7: invokestatic  #9                  // Method org/springframework/util/Assert.notNull:(Ljava/lang/Object;Ljava/lang/String;)V
      10: aload_0
      11: aload_1
      12: putfield      #15                 // Field webApplicationContext:Lorg/springframework/web/context/ConfigurableWebApplicationContext;
      15: return

  protected jakarta.servlet.ServletContext getServletContext();
    Code:
       0: aload_0
       1: getfield      #15                 // Field webApplicationContext:Lorg/springframework/web/context/ConfigurableWebApplicationContext;
       4: invokeinterface #21,  1           // InterfaceMethod org/springframework/web/context/ConfigurableWebApplicationContext.getServletContext:()Ljakarta/servlet/ServletContext;
       9: astore_1
      10: aload_1
      11: ifnull        18
      14: aload_1
      15: goto          22
      18: aload_0
      19: invokespecial #27                 // Method org/springframework/web/context/support/ServletContextAwareProcessor.getServletContext:()Ljakarta/servlet/ServletContext;
      22: areturn

  protected jakarta.servlet.ServletConfig getServletConfig();
    Code:
       0: aload_0
       1: getfield      #15                 // Field webApplicationContext:Lorg/springframework/web/context/ConfigurableWebApplicationContext;
       4: invokeinterface #28,  1           // InterfaceMethod org/springframework/web/context/ConfigurableWebApplicationContext.getServletConfig:()Ljakarta/servlet/ServletConfig;
       9: astore_1
      10: aload_1
      11: ifnull        18
      14: aload_1
      15: goto          22
      18: aload_0
      19: invokespecial #32                 // Method org/springframework/web/context/support/ServletContextAwareProcessor.getServletConfig:()Ljakarta/servlet/ServletConfig;
      22: areturn
}
