Compiled from "WebServerStartStopLifecycle.java"
class org.springframework.boot.web.servlet.context.WebServerStartStopLifecycle implements org.springframework.context.SmartLifecycle {
  private final org.springframework.boot.web.servlet.context.ServletWebServerApplicationContext applicationContext;

  private final org.springframework.boot.web.server.WebServer webServer;

  private volatile boolean running;

  org.springframework.boot.web.servlet.context.WebServerStartStopLifecycle(org.springframework.boot.web.servlet.context.ServletWebServerApplicationContext, org.springframework.boot.web.server.WebServer);
    Code:
       0: aload_0
       1: invokespecial #1                  // Method java/lang/Object."<init>":()V
       4: aload_0
       5: aload_1
       6: putfield      #7                  // Field applicationContext:Lorg/springframework/boot/web/servlet/context/ServletWebServerApplicationContext;
       9: aload_0
      10: aload_2
      11: putfield      #13                 // Field webServer:Lorg/springframework/boot/web/server/WebServer;
      14: return

  public void start();
    Code:
       0: aload_0
       1: getfield      #13                 // Field webServer:Lorg/springframework/boot/web/server/WebServer;
       4: invokeinterface #17,  1           // InterfaceMethod org/springframework/boot/web/server/WebServer.start:()V
       9: aload_0
      10: iconst_1
      11: putfield      #22                 // Field running:Z
      14: aload_0
      15: getfield      #7                  // Field applicationContext:Lorg/springframework/boot/web/servlet/context/ServletWebServerApplicationContext;
      18: new           #26                 // class org/springframework/boot/web/servlet/context/ServletWebServerInitializedEvent
      21: dup
      22: aload_0
      23: getfield      #13                 // Field webServer:Lorg/springframework/boot/web/server/WebServer;
      26: aload_0
      27: getfield      #7                  // Field applicationContext:Lorg/springframework/boot/web/servlet/context/ServletWebServerApplicationContext;
      30: invokespecial #28                 // Method org/springframework/boot/web/servlet/context/ServletWebServerInitializedEvent."<init>":(Lorg/springframework/boot/web/server/WebServer;Lorg/springframework/boot/web/servlet/context/ServletWebServerApplicationContext;)V
      33: invokevirtual #31                 // Method org/springframework/boot/web/servlet/context/ServletWebServerApplicationContext.publishEvent:(Lorg/springframework/context/ApplicationEvent;)V
      36: return

  public void stop();
    Code:
       0: aload_0
       1: iconst_0
       2: putfield      #22                 // Field running:Z
       5: aload_0
       6: getfield      #13                 // Field webServer:Lorg/springframework/boot/web/server/WebServer;
       9: invokeinterface #37,  1           // InterfaceMethod org/springframework/boot/web/server/WebServer.stop:()V
      14: return

  public boolean isRunning();
    Code:
       0: aload_0
       1: getfield      #22                 // Field running:Z
       4: ireturn

  public int getPhase();
    Code:
       0: ldc           #42                 // int 2147481599
       2: ireturn
}
