Compiled from "DataParseUtils.java"
public class org.apache.dubbo.rpc.protocol.rest.util.DataParseUtils {
  public org.apache.dubbo.rpc.protocol.rest.util.DataParseUtils();
    Code:
       0: aload_0
       1: invokespecial #1                  // Method java/lang/Object."<init>":()V
       4: return

  public static java.lang.Object stringTypeConvert(java.lang.Class<?>, java.lang.String);
    Code:
       0: aload_1
       1: invokestatic  #2                  // Method org/apache/dubbo/common/utils/StringUtils.isEmpty:(Ljava/lang/String;)Z
       4: ifeq          9
       7: aconst_null
       8: areturn
       9: aload_0
      10: ldc           #3                  // class java/lang/Boolean
      12: if_acmpeq     22
      15: aload_0
      16: getstatic     #4                  // Field java/lang/Boolean.TYPE:Ljava/lang/Class;
      19: if_acmpne     27
      22: aload_1
      23: invokestatic  #5                  // Method java/lang/Boolean.valueOf:(Ljava/lang/String;)Ljava/lang/Boolean;
      26: areturn
      27: aload_0
      28: ldc           #6                  // class java/lang/String
      30: if_acmpne     35
      33: aload_1
      34: areturn
      35: ldc           #7                  // class java/lang/Number
      37: aload_0
      38: invokevirtual #8                  // Method java/lang/Class.isAssignableFrom:(Ljava/lang/Class;)Z
      41: ifeq          50
      44: aload_1
      45: aload_0
      46: invokestatic  #9                  // Method org/apache/dubbo/rpc/protocol/rest/util/NumberUtils.parseNumber:(Ljava/lang/String;Ljava/lang/Class;)Ljava/lang/Object;
      49: areturn
      50: aload_0
      51: ifnull        67
      54: aload_0
      55: invokevirtual #10                 // Method java/lang/Class.isPrimitive:()Z
      58: ifeq          67
      61: aload_1
      62: aload_0
      63: invokestatic  #9                  // Method org/apache/dubbo/rpc/protocol/rest/util/NumberUtils.parseNumber:(Ljava/lang/String;Ljava/lang/Class;)Ljava/lang/Object;
      66: areturn
      67: aload_1
      68: areturn

  public static boolean isTextType(java.lang.Class);
    Code:
       0: aload_0
       1: ifnonnull     6
       4: iconst_0
       5: ireturn
       6: aload_0
       7: ldc           #3                  // class java/lang/Boolean
       9: if_acmpeq     41
      12: aload_0
      13: getstatic     #4                  // Field java/lang/Boolean.TYPE:Ljava/lang/Class;
      16: if_acmpeq     41
      19: aload_0
      20: ldc           #6                  // class java/lang/String
      22: if_acmpeq     41
      25: ldc           #7                  // class java/lang/Number
      27: aload_0
      28: invokevirtual #8                  // Method java/lang/Class.isAssignableFrom:(Ljava/lang/Class;)Z
      31: ifne          41
      34: aload_0
      35: invokevirtual #10                 // Method java/lang/Class.isPrimitive:()Z
      38: ifeq          45
      41: iconst_1
      42: goto          46
      45: iconst_0
      46: ireturn

  public static void writeTextContent(java.lang.Object, java.io.OutputStream) throws java.io.IOException;
    Code:
       0: aload_1
       1: aload_0
       2: invokestatic  #11                 // Method objectTextConvertToByteArray:(Ljava/lang/Object;)[B
       5: invokevirtual #12                 // Method java/io/OutputStream.write:([B)V
       8: return

  public static void writeJsonContent(java.lang.Object, java.io.OutputStream) throws java.lang.Exception;
    Code:
       0: aload_1
       1: aload_0
       2: invokestatic  #13                 // Method org/apache/dubbo/common/utils/JsonUtils.toJson:(Ljava/lang/Object;)Ljava/lang/String;
       5: getstatic     #14                 // Field java/nio/charset/StandardCharsets.UTF_8:Ljava/nio/charset/Charset;
       8: invokevirtual #15                 // Method java/lang/String.getBytes:(Ljava/nio/charset/Charset;)[B
      11: invokevirtual #12                 // Method java/io/OutputStream.write:([B)V
      14: return

  public static void writeFormContent(java.util.Map, java.io.OutputStream) throws java.lang.Exception;
    Code:
       0: aload_1
       1: aload_0
       2: invokestatic  #16                 // Method java/nio/charset/Charset.defaultCharset:()Ljava/nio/charset/Charset;
       5: invokestatic  #17                 // Method serializeForm:(Ljava/util/Map;Ljava/nio/charset/Charset;)Ljava/lang/String;
       8: invokevirtual #18                 // Method java/lang/String.getBytes:()[B
      11: invokevirtual #12                 // Method java/io/OutputStream.write:([B)V
      14: return

  public static java.lang.String serializeForm(java.util.Map, java.nio.charset.Charset);
    Code:
       0: new           #19                 // class java/lang/StringBuilder
       3: dup
       4: invokespecial #20                 // Method java/lang/StringBuilder."<init>":()V
       7: astore_2
       8: aload_0
       9: aload_2
      10: aload_1
      11: invokedynamic #21,  0             // InvokeDynamic #0:accept:(Ljava/lang/StringBuilder;Ljava/nio/charset/Charset;)Ljava/util/function/BiConsumer;
      16: invokeinterface #22,  2           // InterfaceMethod java/util/Map.forEach:(Ljava/util/function/BiConsumer;)V
      21: aload_2
      22: invokevirtual #23                 // Method java/lang/StringBuilder.toString:()Ljava/lang/String;
      25: areturn

  public static byte[] objectTextConvertToByteArray(java.lang.Object);
    Code:
       0: aload_0
       1: invokevirtual #24                 // Method java/lang/Object.getClass:()Ljava/lang/Class;
       4: astore_1
       5: aload_1
       6: ldc           #3                  // class java/lang/Boolean
       8: if_acmpeq     18
      11: aload_1
      12: getstatic     #4                  // Field java/lang/Boolean.TYPE:Ljava/lang/Class;
      15: if_acmpne     26
      18: aload_0
      19: invokevirtual #25                 // Method java/lang/Object.toString:()Ljava/lang/String;
      22: invokevirtual #18                 // Method java/lang/String.getBytes:()[B
      25: areturn
      26: aload_1
      27: ldc           #6                  // class java/lang/String
      29: if_acmpne     40
      32: aload_0
      33: checkcast     #6                  // class java/lang/String
      36: invokevirtual #18                 // Method java/lang/String.getBytes:()[B
      39: areturn
      40: aload_1
      41: ldc           #7                  // class java/lang/Number
      43: invokevirtual #8                  // Method java/lang/Class.isAssignableFrom:(Ljava/lang/Class;)Z
      46: ifne          56
      49: aload_1
      50: invokevirtual #10                 // Method java/lang/Class.isPrimitive:()Z
      53: ifeq          70
      56: aload_0
      57: checkcast     #7                  // class java/lang/Number
      60: invokestatic  #26                 // Method org/apache/dubbo/rpc/protocol/rest/util/NumberUtils.numberToBytes:(Ljava/lang/Number;)Ljava/lang/Object;
      63: checkcast     #27                 // class "[B"
      66: checkcast     #27                 // class "[B"
      69: areturn
      70: aload_0
      71: invokevirtual #25                 // Method java/lang/Object.toString:()Ljava/lang/String;
      74: invokevirtual #18                 // Method java/lang/String.getBytes:()[B
      77: areturn

  public static java.lang.Object jsonConvert(java.lang.Class, byte[]) throws java.lang.Exception;
    Code:
       0: new           #6                  // class java/lang/String
       3: dup
       4: aload_1
       5: getstatic     #14                 // Field java/nio/charset/StandardCharsets.UTF_8:Ljava/nio/charset/Charset;
       8: invokespecial #28                 // Method java/lang/String."<init>":([BLjava/nio/charset/Charset;)V
      11: aload_0
      12: invokestatic  #29                 // Method org/apache/dubbo/common/utils/JsonUtils.toJavaObject:(Ljava/lang/String;Ljava/lang/reflect/Type;)Ljava/lang/Object;
      15: areturn

  public static java.lang.Object multipartFormConvert(byte[], java.nio.charset.Charset, java.lang.Class<?>) throws java.lang.Exception;
    Code:
       0: new           #6                  // class java/lang/String
       3: dup
       4: aload_0
       5: getstatic     #14                 // Field java/nio/charset/StandardCharsets.UTF_8:Ljava/nio/charset/Charset;
       8: invokespecial #28                 // Method java/lang/String."<init>":([BLjava/nio/charset/Charset;)V
      11: ldc           #30                 // String &
      13: invokestatic  #31                 // Method tokenizeToStringArray:(Ljava/lang/String;Ljava/lang/String;)[Ljava/lang/String;
      16: astore_3
      17: aload_2
      18: invokestatic  #32                 // Method org/apache/dubbo/rpc/protocol/rest/util/MultiValueCreator.providerCreateMultiValueMap:(Ljava/lang/Class;)Ljava/lang/Object;
      21: astore        4
      23: aload_3
      24: astore        5
      26: aload         5
      28: arraylength
      29: istore        6
      31: iconst_0
      32: istore        7
      34: iload         7
      36: iload         6
      38: if_icmpge     131
      41: aload         5
      43: iload         7
      45: aaload
      46: astore        8
      48: aload         8
      50: bipush        61
      52: invokevirtual #33                 // Method java/lang/String.indexOf:(I)I
      55: istore        9
      57: iload         9
      59: iconst_m1
      60: if_icmpne     81
      63: aload         4
      65: aload         8
      67: aload_1
      68: invokevirtual #34                 // Method java/nio/charset/Charset.name:()Ljava/lang/String;
      71: invokestatic  #35                 // Method java/net/URLDecoder.decode:(Ljava/lang/String;Ljava/lang/String;)Ljava/lang/String;
      74: aconst_null
      75: invokestatic  #36                 // Method org/apache/dubbo/rpc/protocol/rest/util/MultiValueCreator.add:(Ljava/lang/Object;Ljava/lang/String;Ljava/lang/Object;)V
      78: goto          125
      81: aload         8
      83: iconst_0
      84: iload         9
      86: invokevirtual #37                 // Method java/lang/String.substring:(II)Ljava/lang/String;
      89: aload_1
      90: invokevirtual #34                 // Method java/nio/charset/Charset.name:()Ljava/lang/String;
      93: invokestatic  #35                 // Method java/net/URLDecoder.decode:(Ljava/lang/String;Ljava/lang/String;)Ljava/lang/String;
      96: astore        10
      98: aload         8
     100: iload         9
     102: iconst_1
     103: iadd
     104: invokevirtual #38                 // Method java/lang/String.substring:(I)Ljava/lang/String;
     107: aload_1
     108: invokevirtual #34                 // Method java/nio/charset/Charset.name:()Ljava/lang/String;
     111: invokestatic  #35                 // Method java/net/URLDecoder.decode:(Ljava/lang/String;Ljava/lang/String;)Ljava/lang/String;
     114: astore        11
     116: aload         4
     118: aload         10
     120: aload         11
     122: invokestatic  #36                 // Method org/apache/dubbo/rpc/protocol/rest/util/MultiValueCreator.add:(Ljava/lang/Object;Ljava/lang/String;Ljava/lang/Object;)V
     125: iinc          7, 1
     128: goto          34
     131: aload         4
     133: areturn

  public static java.lang.Object multipartFormConvert(byte[], java.lang.Class<?>) throws java.lang.Exception;
    Code:
       0: aload_0
       1: invokestatic  #16                 // Method java/nio/charset/Charset.defaultCharset:()Ljava/nio/charset/Charset;
       4: aload_1
       5: invokestatic  #39                 // Method multipartFormConvert:([BLjava/nio/charset/Charset;Ljava/lang/Class;)Ljava/lang/Object;
       8: areturn

  public static java.lang.String[] tokenizeToStringArray(java.lang.String, java.lang.String);
    Code:
       0: aload_0
       1: aload_1
       2: iconst_1
       3: iconst_1
       4: invokestatic  #40                 // Method tokenizeToStringArray:(Ljava/lang/String;Ljava/lang/String;ZZ)[Ljava/lang/String;
       7: areturn

  public static java.lang.String[] tokenizeToStringArray(java.lang.String, java.lang.String, boolean, boolean);
    Code:
       0: aload_0
       1: ifnonnull     6
       4: aconst_null
       5: areturn
       6: new           #41                 // class java/util/StringTokenizer
       9: dup
      10: aload_0
      11: aload_1
      12: invokespecial #42                 // Method java/util/StringTokenizer."<init>":(Ljava/lang/String;Ljava/lang/String;)V
      15: astore        4
      17: new           #43                 // class java/util/ArrayList
      20: dup
      21: invokespecial #44                 // Method java/util/ArrayList."<init>":()V
      24: astore        5
      26: aload         4
      28: invokevirtual #45                 // Method java/util/StringTokenizer.hasMoreTokens:()Z
      31: ifne          40
      34: aload         5
      36: invokestatic  #46                 // Method toStringArray:(Ljava/util/Collection;)[Ljava/lang/String;
      39: areturn
      40: aload         4
      42: invokevirtual #47                 // Method java/util/StringTokenizer.nextToken:()Ljava/lang/String;
      45: astore        6
      47: iload_2
      48: ifeq          58
      51: aload         6
      53: invokevirtual #48                 // Method java/lang/String.trim:()Ljava/lang/String;
      56: astore        6
      58: iload_3
      59: ifeq          70
      62: aload         6
      64: invokevirtual #49                 // Method java/lang/String.length:()I
      67: ifle          26
      70: aload         5
      72: aload         6
      74: invokevirtual #50                 // Method java/util/ArrayList.add:(Ljava/lang/Object;)Z
      77: pop
      78: goto          26

  public static java.lang.String[] toStringArray(java.util.Collection<java.lang.String>);
    Code:
       0: aload_0
       1: ifnonnull     8
       4: aconst_null
       5: goto          26
       8: aload_0
       9: aload_0
      10: invokeinterface #51,  1           // InterfaceMethod java/util/Collection.size:()I
      15: anewarray     #6                  // class java/lang/String
      18: invokeinterface #52,  2           // InterfaceMethod java/util/Collection.toArray:([Ljava/lang/Object;)[Ljava/lang/Object;
      23: checkcast     #53                 // class "[Ljava/lang/String;"
      26: areturn

  private static void lambda$serializeForm$1(java.lang.StringBuilder, java.nio.charset.Charset, java.lang.Object, java.lang.Object);
    Code:
       0: aload_2
       1: ifnonnull     5
       4: return
       5: aload_3
       6: checkcast     #54                 // class java/util/List
       9: aload_0
      10: aload_2
      11: aload_1
      12: invokedynamic #55,  0             // InvokeDynamic #1:accept:(Ljava/lang/StringBuilder;Ljava/lang/Object;Ljava/nio/charset/Charset;)Ljava/util/function/Consumer;
      17: invokeinterface #56,  2           // InterfaceMethod java/util/List.forEach:(Ljava/util/function/Consumer;)V
      22: return

  private static void lambda$null$0(java.lang.StringBuilder, java.lang.Object, java.nio.charset.Charset, java.lang.Object);
    Code:
       0: aload_0
       1: invokevirtual #57                 // Method java/lang/StringBuilder.length:()I
       4: ifeq          14
       7: aload_0
       8: bipush        38
      10: invokevirtual #58                 // Method java/lang/StringBuilder.append:(C)Ljava/lang/StringBuilder;
      13: pop
      14: aload_0
      15: aload_1
      16: checkcast     #6                  // class java/lang/String
      19: aload_2
      20: invokevirtual #34                 // Method java/nio/charset/Charset.name:()Ljava/lang/String;
      23: invokestatic  #59                 // Method java/net/URLEncoder.encode:(Ljava/lang/String;Ljava/lang/String;)Ljava/lang/String;
      26: invokevirtual #60                 // Method java/lang/StringBuilder.append:(Ljava/lang/String;)Ljava/lang/StringBuilder;
      29: pop
      30: aload_3
      31: ifnull        57
      34: aload_0
      35: bipush        61
      37: invokevirtual #58                 // Method java/lang/StringBuilder.append:(C)Ljava/lang/StringBuilder;
      40: pop
      41: aload_0
      42: aload_3
      43: invokestatic  #61                 // Method java/lang/String.valueOf:(Ljava/lang/Object;)Ljava/lang/String;
      46: aload_2
      47: invokevirtual #34                 // Method java/nio/charset/Charset.name:()Ljava/lang/String;
      50: invokestatic  #59                 // Method java/net/URLEncoder.encode:(Ljava/lang/String;Ljava/lang/String;)Ljava/lang/String;
      53: invokevirtual #60                 // Method java/lang/StringBuilder.append:(Ljava/lang/String;)Ljava/lang/StringBuilder;
      56: pop
      57: goto          72
      60: astore        4
      62: new           #63                 // class java/lang/IllegalStateException
      65: dup
      66: aload         4
      68: invokespecial #64                 // Method java/lang/IllegalStateException."<init>":(Ljava/lang/Throwable;)V
      71: athrow
      72: return
    Exception table:
       from    to  target type
           0    57    60   Class java/io/UnsupportedEncodingException
}
