Compiled from "HttpHeaderUtil.java"
public class org.apache.dubbo.rpc.protocol.rest.util.HttpHeaderUtil {
  public org.apache.dubbo.rpc.protocol.rest.util.HttpHeaderUtil();
    Code:
       0: aload_0
       1: invokespecial #1                  // Method java/lang/Object."<init>":()V
       4: return

  public static java.util.Map<java.lang.String, java.util.List<java.lang.String>> createAttachments(java.util.Map<java.lang.String, java.lang.Object>);
    Code:
       0: new           #2                  // class java/util/HashMap
       3: dup
       4: invokespecial #3                  // Method java/util/HashMap."<init>":()V
       7: astore_1
       8: iconst_0
       9: istore_2
      10: aload_0
      11: invokeinterface #4,  1            // InterfaceMethod java/util/Map.entrySet:()Ljava/util/Set;
      16: invokeinterface #5,  1            // InterfaceMethod java/util/Set.iterator:()Ljava/util/Iterator;
      21: astore_3
      22: aload_3
      23: invokeinterface #6,  1            // InterfaceMethod java/util/Iterator.hasNext:()Z
      28: ifeq          134
      31: aload_3
      32: invokeinterface #7,  1            // InterfaceMethod java/util/Iterator.next:()Ljava/lang/Object;
      37: checkcast     #8                  // class java/util/Map$Entry
      40: astore        4
      42: aload         4
      44: invokeinterface #9,  1            // InterfaceMethod java/util/Map$Entry.getKey:()Ljava/lang/Object;
      49: checkcast     #10                 // class java/lang/String
      52: astore        5
      54: aload         4
      56: invokeinterface #11,  1           // InterfaceMethod java/util/Map$Entry.getValue:()Ljava/lang/Object;
      61: invokestatic  #12                 // Method java/lang/String.valueOf:(Ljava/lang/Object;)Ljava/lang/String;
      64: astore        6
      66: aload         6
      68: ifnull        83
      71: iload_2
      72: aload         6
      74: getstatic     #13                 // Field java/nio/charset/StandardCharsets.UTF_8:Ljava/nio/charset/Charset;
      77: invokevirtual #14                 // Method java/lang/String.getBytes:(Ljava/nio/charset/Charset;)[B
      80: arraylength
      81: iadd
      82: istore_2
      83: aload_1
      84: aload         5
      86: invokeinterface #15,  2           // InterfaceMethod java/util/Map.get:(Ljava/lang/Object;)Ljava/lang/Object;
      91: checkcast     #16                 // class java/util/List
      94: astore        7
      96: aload         7
      98: ifnonnull     121
     101: new           #17                 // class java/util/ArrayList
     104: dup
     105: invokespecial #18                 // Method java/util/ArrayList."<init>":()V
     108: astore        7
     110: aload_1
     111: aload         5
     113: aload         7
     115: invokeinterface #19,  3           // InterfaceMethod java/util/Map.put:(Ljava/lang/Object;Ljava/lang/Object;)Ljava/lang/Object;
     120: pop
     121: aload         7
     123: aload         6
     125: invokeinterface #20,  2           // InterfaceMethod java/util/List.add:(Ljava/lang/Object;)Z
     130: pop
     131: goto          22
     134: aload_1
     135: areturn

  public static void addRequestAttachments(org.apache.dubbo.remoting.http.RequestTemplate, java.util.Map<java.lang.String, java.lang.Object>);
    Code:
       0: aload_1
       1: invokestatic  #21                 // Method createAttachments:(Ljava/util/Map;)Ljava/util/Map;
       4: astore_2
       5: aload_2
       6: invokeinterface #4,  1            // InterfaceMethod java/util/Map.entrySet:()Ljava/util/Set;
      11: aload_0
      12: invokedynamic #22,  0             // InvokeDynamic #0:accept:(Lorg/apache/dubbo/remoting/http/RequestTemplate;)Ljava/util/function/Consumer;
      17: invokeinterface #23,  2           // InterfaceMethod java/util/Set.forEach:(Ljava/util/function/Consumer;)V
      22: return

  public static void addResponseAttachments(org.apache.dubbo.rpc.protocol.rest.netty.NettyHttpResponse);
    Code:
       0: invokestatic  #24                 // Method org/apache/dubbo/rpc/RpcContext.getServerContext:()Lorg/apache/dubbo/rpc/RpcContextAttachment;
       3: invokevirtual #25                 // Method org/apache/dubbo/rpc/RpcContextAttachment.getObjectAttachments:()Ljava/util/Map;
       6: invokestatic  #21                 // Method createAttachments:(Ljava/util/Map;)Ljava/util/Map;
       9: astore_1
      10: aload_1
      11: invokeinterface #4,  1            // InterfaceMethod java/util/Map.entrySet:()Ljava/util/Set;
      16: invokeinterface #26,  1           // InterfaceMethod java/util/Set.stream:()Ljava/util/stream/Stream;
      21: aload_0
      22: invokedynamic #27,  0             // InvokeDynamic #1:accept:(Lorg/apache/dubbo/rpc/protocol/rest/netty/NettyHttpResponse;)Ljava/util/function/Consumer;
      27: invokeinterface #28,  2           // InterfaceMethod java/util/stream/Stream.forEach:(Ljava/util/function/Consumer;)V
      32: return

  public static void parseRequestHeader(org.apache.dubbo.rpc.RpcInvocation, org.apache.dubbo.rpc.protocol.rest.request.RequestFacade);
    Code:
       0: aload_1
       1: invokevirtual #29                 // Method org/apache/dubbo/rpc/protocol/rest/request/RequestFacade.getHeaderNames:()Ljava/util/Enumeration;
       4: astore_2
       5: aload_2
       6: invokeinterface #30,  1           // InterfaceMethod java/util/Enumeration.hasMoreElements:()Z
      11: ifeq          64
      14: aload_2
      15: invokeinterface #31,  1           // InterfaceMethod java/util/Enumeration.nextElement:()Ljava/lang/Object;
      20: checkcast     #10                 // class java/lang/String
      23: astore_3
      24: aload_3
      25: invokestatic  #32                 // Method isRestAttachHeader:(Ljava/lang/String;)Z
      28: ifne          45
      31: aload_0
      32: aload_3
      33: aload_1
      34: aload_3
      35: invokevirtual #33                 // Method org/apache/dubbo/rpc/protocol/rest/request/RequestFacade.getHeader:(Ljava/lang/String;)Ljava/lang/String;
      38: invokevirtual #34                 // Method org/apache/dubbo/rpc/RpcInvocation.put:(Ljava/lang/Object;Ljava/lang/Object;)Ljava/lang/Object;
      41: pop
      42: goto          5
      45: aload_0
      46: aload_3
      47: invokevirtual #35                 // Method java/lang/String.trim:()Ljava/lang/String;
      50: invokestatic  #36                 // Method subRestAttachRealHeaderPrefix:(Ljava/lang/String;)Ljava/lang/String;
      53: aload_1
      54: aload_3
      55: invokevirtual #33                 // Method org/apache/dubbo/rpc/protocol/rest/request/RequestFacade.getHeader:(Ljava/lang/String;)Ljava/lang/String;
      58: invokevirtual #37                 // Method org/apache/dubbo/rpc/RpcInvocation.setAttachment:(Ljava/lang/String;Ljava/lang/String;)V
      61: goto          5
      64: return

  public static boolean isRestAttachHeader(java.lang.String);
    Code:
       0: aload_0
       1: invokestatic  #38                 // Method org/apache/dubbo/common/utils/StringUtils.isEmpty:(Ljava/lang/String;)Z
       4: ifne          20
       7: aload_0
       8: getstatic     #39                 // Field org/apache/dubbo/rpc/protocol/rest/RestHeaderEnum.REST_HEADER_PREFIX:Lorg/apache/dubbo/rpc/protocol/rest/RestHeaderEnum;
      11: invokevirtual #40                 // Method org/apache/dubbo/rpc/protocol/rest/RestHeaderEnum.getHeader:()Ljava/lang/String;
      14: invokevirtual #41                 // Method java/lang/String.startsWith:(Ljava/lang/String;)Z
      17: ifne          22
      20: iconst_0
      21: ireturn
      22: iconst_1
      23: ireturn

  public static java.lang.String subRestAttachRealHeaderPrefix(java.lang.String);
    Code:
       0: aload_0
       1: getstatic     #39                 // Field org/apache/dubbo/rpc/protocol/rest/RestHeaderEnum.REST_HEADER_PREFIX:Lorg/apache/dubbo/rpc/protocol/rest/RestHeaderEnum;
       4: invokevirtual #40                 // Method org/apache/dubbo/rpc/protocol/rest/RestHeaderEnum.getHeader:()Ljava/lang/String;
       7: invokevirtual #42                 // Method java/lang/String.length:()I
      10: invokevirtual #43                 // Method java/lang/String.substring:(I)Ljava/lang/String;
      13: areturn

  public static java.lang.String appendPrefixToAttachRealHeader(java.lang.String);
    Code:
       0: new           #44                 // class java/lang/StringBuilder
       3: dup
       4: invokespecial #45                 // Method java/lang/StringBuilder."<init>":()V
       7: getstatic     #39                 // Field org/apache/dubbo/rpc/protocol/rest/RestHeaderEnum.REST_HEADER_PREFIX:Lorg/apache/dubbo/rpc/protocol/rest/RestHeaderEnum;
      10: invokevirtual #40                 // Method org/apache/dubbo/rpc/protocol/rest/RestHeaderEnum.getHeader:()Ljava/lang/String;
      13: invokevirtual #46                 // Method java/lang/StringBuilder.append:(Ljava/lang/String;)Ljava/lang/StringBuilder;
      16: aload_0
      17: invokevirtual #46                 // Method java/lang/StringBuilder.append:(Ljava/lang/String;)Ljava/lang/StringBuilder;
      20: invokevirtual #47                 // Method java/lang/StringBuilder.toString:()Ljava/lang/String;
      23: areturn

  public static void parseRequestAttribute(org.apache.dubbo.rpc.RpcInvocation, org.apache.dubbo.rpc.protocol.rest.request.RequestFacade);
    Code:
       0: aload_1
       1: invokevirtual #48                 // Method org/apache/dubbo/rpc/protocol/rest/request/RequestFacade.getLocalPort:()I
       4: istore_2
       5: aload_1
       6: invokevirtual #49                 // Method org/apache/dubbo/rpc/protocol/rest/request/RequestFacade.getLocalAddr:()Ljava/lang/String;
       9: astore_3
      10: aload_1
      11: invokevirtual #50                 // Method org/apache/dubbo/rpc/protocol/rest/request/RequestFacade.getRemotePort:()I
      14: istore        4
      16: aload_1
      17: invokevirtual #51                 // Method org/apache/dubbo/rpc/protocol/rest/request/RequestFacade.getRemoteAddr:()Ljava/lang/String;
      20: astore        5
      22: aload_0
      23: ldc           #53                 // String REMOTE_ADDR
      25: aload         5
      27: invokevirtual #34                 // Method org/apache/dubbo/rpc/RpcInvocation.put:(Ljava/lang/Object;Ljava/lang/Object;)Ljava/lang/Object;
      30: pop
      31: aload_0
      32: ldc           #54                 // String LOCAL_ADDR
      34: aload_3
      35: invokevirtual #34                 // Method org/apache/dubbo/rpc/RpcInvocation.put:(Ljava/lang/Object;Ljava/lang/Object;)Ljava/lang/Object;
      38: pop
      39: aload_0
      40: ldc           #55                 // String REMOTE_PORT
      42: iload         4
      44: invokestatic  #56                 // Method java/lang/Integer.valueOf:(I)Ljava/lang/Integer;
      47: invokevirtual #34                 // Method org/apache/dubbo/rpc/RpcInvocation.put:(Ljava/lang/Object;Ljava/lang/Object;)Ljava/lang/Object;
      50: pop
      51: aload_0
      52: ldc           #57                 // String LOCAL_PORT
      54: iload_2
      55: invokestatic  #56                 // Method java/lang/Integer.valueOf:(I)Ljava/lang/Integer;
      58: invokevirtual #34                 // Method org/apache/dubbo/rpc/RpcInvocation.put:(Ljava/lang/Object;Ljava/lang/Object;)Ljava/lang/Object;
      61: pop
      62: return

  public static void parseRequest(org.apache.dubbo.rpc.RpcInvocation, org.apache.dubbo.rpc.protocol.rest.request.RequestFacade);
    Code:
       0: aload_0
       1: aload_1
       2: invokestatic  #58                 // Method parseRequestHeader:(Lorg/apache/dubbo/rpc/RpcInvocation;Lorg/apache/dubbo/rpc/protocol/rest/request/RequestFacade;)V
       5: aload_0
       6: aload_1
       7: invokestatic  #59                 // Method parseRequestAttribute:(Lorg/apache/dubbo/rpc/RpcInvocation;Lorg/apache/dubbo/rpc/protocol/rest/request/RequestFacade;)V
      10: return

  public static void parseResponseHeader(org.apache.dubbo.rpc.AppResponse, org.apache.dubbo.remoting.http.RestResult);
    Code:
       0: aload_1
       1: invokeinterface #60,  1           // InterfaceMethod org/apache/dubbo/remoting/http/RestResult.headers:()Ljava/util/Map;
       6: astore_2
       7: aload_2
       8: ifnull        20
      11: aload_2
      12: invokeinterface #61,  1           // InterfaceMethod java/util/Map.isEmpty:()Z
      17: ifeq          21
      20: return
      21: aload_2
      22: invokeinterface #4,  1            // InterfaceMethod java/util/Map.entrySet:()Ljava/util/Set;
      27: invokeinterface #26,  1           // InterfaceMethod java/util/Set.stream:()Ljava/util/stream/Stream;
      32: aload_0
      33: invokedynamic #62,  0             // InvokeDynamic #2:accept:(Lorg/apache/dubbo/rpc/AppResponse;)Ljava/util/function/Consumer;
      38: invokeinterface #28,  2           // InterfaceMethod java/util/stream/Stream.forEach:(Ljava/util/function/Consumer;)V
      43: return

  private static void lambda$parseResponseHeader$2(org.apache.dubbo.rpc.AppResponse, java.util.Map$Entry);
    Code:
       0: aload_1
       1: invokeinterface #9,  1            // InterfaceMethod java/util/Map$Entry.getKey:()Ljava/lang/Object;
       6: checkcast     #10                 // class java/lang/String
       9: astore_2
      10: aload_2
      11: invokestatic  #32                 // Method isRestAttachHeader:(Ljava/lang/String;)Z
      14: ifeq          34
      17: aload_0
      18: aload_2
      19: invokestatic  #36                 // Method subRestAttachRealHeaderPrefix:(Ljava/lang/String;)Ljava/lang/String;
      22: aload_1
      23: invokeinterface #11,  1           // InterfaceMethod java/util/Map$Entry.getValue:()Ljava/lang/Object;
      28: invokevirtual #63                 // Method org/apache/dubbo/rpc/AppResponse.setAttachment:(Ljava/lang/String;Ljava/lang/Object;)V
      31: goto          45
      34: aload_0
      35: aload_2
      36: aload_1
      37: invokeinterface #11,  1           // InterfaceMethod java/util/Map$Entry.getValue:()Ljava/lang/Object;
      42: invokevirtual #64                 // Method org/apache/dubbo/rpc/AppResponse.setAttribute:(Ljava/lang/String;Ljava/lang/Object;)V
      45: return

  private static void lambda$addResponseAttachments$1(org.apache.dubbo.rpc.protocol.rest.netty.NettyHttpResponse, java.util.Map$Entry);
    Code:
       0: aload_0
       1: invokevirtual #65                 // Method org/apache/dubbo/rpc/protocol/rest/netty/NettyHttpResponse.getOutputHeaders:()Ljava/util/Map;
       4: aload_1
       5: invokeinterface #9,  1            // InterfaceMethod java/util/Map$Entry.getKey:()Ljava/lang/Object;
      10: checkcast     #10                 // class java/lang/String
      13: invokestatic  #66                 // Method appendPrefixToAttachRealHeader:(Ljava/lang/String;)Ljava/lang/String;
      16: aload_1
      17: invokeinterface #11,  1           // InterfaceMethod java/util/Map$Entry.getValue:()Ljava/lang/Object;
      22: invokeinterface #19,  3           // InterfaceMethod java/util/Map.put:(Ljava/lang/Object;Ljava/lang/Object;)Ljava/lang/Object;
      27: pop
      28: return

  private static void lambda$addRequestAttachments$0(org.apache.dubbo.remoting.http.RequestTemplate, java.util.Map$Entry);
    Code:
       0: aload_0
       1: aload_1
       2: invokeinterface #9,  1            // InterfaceMethod java/util/Map$Entry.getKey:()Ljava/lang/Object;
       7: checkcast     #10                 // class java/lang/String
      10: invokestatic  #66                 // Method appendPrefixToAttachRealHeader:(Ljava/lang/String;)Ljava/lang/String;
      13: aload_1
      14: invokeinterface #11,  1           // InterfaceMethod java/util/Map$Entry.getValue:()Ljava/lang/Object;
      19: checkcast     #67                 // class java/util/Collection
      22: invokevirtual #68                 // Method org/apache/dubbo/remoting/http/RequestTemplate.addHeaders:(Ljava/lang/String;Ljava/util/Collection;)V
      25: return
}
