Compiled from "MediaTypeUtil.java"
public class org.apache.dubbo.rpc.protocol.rest.util.MediaTypeUtil {
  private static final java.util.List<org.apache.dubbo.metadata.rest.media.MediaType> mediaTypes;

  public org.apache.dubbo.rpc.protocol.rest.util.MediaTypeUtil();
    Code:
       0: aload_0
       1: invokespecial #1                  // Method java/lang/Object."<init>":()V
       4: return

  public static org.apache.dubbo.metadata.rest.media.MediaType convertMediaType(java.lang.Class<?>, java.lang.String...);
    Code:
       0: aload_1
       1: ifnull        9
       4: aload_1
       5: arraylength
       6: ifne          14
       9: aload_0
      10: invokestatic  #2                  // Method org/apache/dubbo/rpc/protocol/rest/message/HttpMessageCodecManager.typeSupport:(Ljava/lang/Class;)Lorg/apache/dubbo/metadata/rest/media/MediaType;
      13: areturn
      14: aload_1
      15: astore_2
      16: aload_2
      17: arraylength
      18: istore_3
      19: iconst_0
      20: istore        4
      22: iload         4
      24: iload_3
      25: if_icmpge     120
      28: aload_2
      29: iload         4
      31: aaload
      32: astore        5
      34: getstatic     #3                  // Field mediaTypes:Ljava/util/List;
      37: invokeinterface #4,  1            // InterfaceMethod java/util/List.iterator:()Ljava/util/Iterator;
      42: astore        6
      44: aload         6
      46: invokeinterface #5,  1            // InterfaceMethod java/util/Iterator.hasNext:()Z
      51: ifeq          90
      54: aload         6
      56: invokeinterface #6,  1            // InterfaceMethod java/util/Iterator.next:()Ljava/lang/Object;
      61: checkcast     #7                  // class org/apache/dubbo/metadata/rest/media/MediaType
      64: astore        7
      66: aload         5
      68: ifnull        87
      71: aload         5
      73: aload         7
      75: getfield      #8                  // Field org/apache/dubbo/metadata/rest/media/MediaType.value:Ljava/lang/String;
      78: invokevirtual #9                  // Method java/lang/String.contains:(Ljava/lang/CharSequence;)Z
      81: ifeq          87
      84: aload         7
      86: areturn
      87: goto          44
      90: aload         5
      92: ifnull        114
      95: aload         5
      97: getstatic     #10                 // Field org/apache/dubbo/metadata/rest/media/MediaType.ALL_VALUE:Lorg/apache/dubbo/metadata/rest/media/MediaType;
     100: getfield      #8                  // Field org/apache/dubbo/metadata/rest/media/MediaType.value:Ljava/lang/String;
     103: invokevirtual #9                  // Method java/lang/String.contains:(Ljava/lang/CharSequence;)Z
     106: ifeq          114
     109: aload_0
     110: invokestatic  #2                  // Method org/apache/dubbo/rpc/protocol/rest/message/HttpMessageCodecManager.typeSupport:(Ljava/lang/Class;)Lorg/apache/dubbo/metadata/rest/media/MediaType;
     113: areturn
     114: iinc          4, 1
     117: goto          22
     120: new           #11                 // class org/apache/dubbo/rpc/protocol/rest/exception/UnSupportContentTypeException
     123: dup
     124: aload_1
     125: invokestatic  #12                 // Method java/util/Arrays.toString:([Ljava/lang/Object;)Ljava/lang/String;
     128: invokespecial #13                 // Method org/apache/dubbo/rpc/protocol/rest/exception/UnSupportContentTypeException."<init>":(Ljava/lang/String;)V
     131: athrow

  static {};
    Code:
       0: invokestatic  #14                 // Method org/apache/dubbo/metadata/rest/media/MediaType.getSupportMediaTypes:()Ljava/util/List;
       3: putstatic     #3                  // Field mediaTypes:Ljava/util/List;
       6: return
}
