Compiled from "MultiValueCreator.java"
public class org.apache.dubbo.rpc.protocol.rest.util.MultiValueCreator {
  private static final org.apache.dubbo.common.logger.ErrorTypeAwareLogger logger;

  private static final java.lang.String SPRING_MultiValueMapImpl;

  private static final java.lang.String SPRING_MultiValueMap;

  private static final java.lang.String JAVAX_MultiValueMapImpl;

  private static final java.lang.String JAVAX_MultiValueMap;

  private static java.lang.Class springMultiValueMapImplClass;

  private static java.lang.Class springMultiValueMapClass;

  private static java.lang.reflect.Method springMultiValueMapAdd;

  private static java.lang.Class jaxrsMultiValueMapImplClass;

  private static java.lang.Class jaxrsMultiValueMapClass;

  private static java.lang.reflect.Method jaxrsMultiValueMapAdd;

  public org.apache.dubbo.rpc.protocol.rest.util.MultiValueCreator();
    Code:
       0: aload_0
       1: invokespecial #1                  // Method java/lang/Object."<init>":()V
       4: return

  public static java.lang.Object providerCreateMultiValueMap(java.lang.Class<?>);
    Code:
       0: getstatic     #2                  // Field springMultiValueMapClass:Ljava/lang/Class;
       3: aload_0
       4: invokestatic  #3                  // Method typeJudge:(Ljava/lang/Class;Ljava/lang/Class;)Z
       7: ifeq          28
      10: getstatic     #4                  // Field springMultiValueMapImplClass:Ljava/lang/Class;
      13: iconst_0
      14: anewarray     #5                  // class java/lang/Class
      17: invokevirtual #6                  // Method java/lang/Class.getDeclaredConstructor:([Ljava/lang/Class;)Ljava/lang/reflect/Constructor;
      20: iconst_0
      21: anewarray     #7                  // class java/lang/Object
      24: invokevirtual #8                  // Method java/lang/reflect/Constructor.newInstance:([Ljava/lang/Object;)Ljava/lang/Object;
      27: areturn
      28: getstatic     #9                  // Field jaxrsMultiValueMapClass:Ljava/lang/Class;
      31: aload_0
      32: invokestatic  #3                  // Method typeJudge:(Ljava/lang/Class;Ljava/lang/Class;)Z
      35: ifeq          56
      38: getstatic     #10                 // Field jaxrsMultiValueMapImplClass:Ljava/lang/Class;
      41: iconst_0
      42: anewarray     #5                  // class java/lang/Class
      45: invokevirtual #6                  // Method java/lang/Class.getDeclaredConstructor:([Ljava/lang/Class;)Ljava/lang/reflect/Constructor;
      48: iconst_0
      49: anewarray     #7                  // class java/lang/Object
      52: invokevirtual #8                  // Method java/lang/reflect/Constructor.newInstance:([Ljava/lang/Object;)Ljava/lang/Object;
      55: areturn
      56: goto          118
      59: astore_1
      60: getstatic     #12                 // Field logger:Lorg/apache/dubbo/common/logger/ErrorTypeAwareLogger;
      63: ldc           #13                 // String
      65: aload_1
      66: invokevirtual #14                 // Method java/lang/Exception.getMessage:()Ljava/lang/String;
      69: new           #15                 // class java/lang/StringBuilder
      72: dup
      73: invokespecial #16                 // Method java/lang/StringBuilder."<init>":()V
      76: ldc           #17                 // String current param type is:
      78: invokevirtual #18                 // Method java/lang/StringBuilder.append:(Ljava/lang/String;)Ljava/lang/StringBuilder;
      81: aload_0
      82: invokevirtual #19                 // Method java/lang/StringBuilder.append:(Ljava/lang/Object;)Ljava/lang/StringBuilder;
      85: ldc           #20                 // String and support type is :
      87: invokevirtual #18                 // Method java/lang/StringBuilder.append:(Ljava/lang/String;)Ljava/lang/StringBuilder;
      90: getstatic     #2                  // Field springMultiValueMapClass:Ljava/lang/Class;
      93: invokevirtual #19                 // Method java/lang/StringBuilder.append:(Ljava/lang/Object;)Ljava/lang/StringBuilder;
      96: ldc           #21                 // String or
      98: invokevirtual #18                 // Method java/lang/StringBuilder.append:(Ljava/lang/String;)Ljava/lang/StringBuilder;
     101: getstatic     #9                  // Field jaxrsMultiValueMapClass:Ljava/lang/Class;
     104: invokevirtual #19                 // Method java/lang/StringBuilder.append:(Ljava/lang/Object;)Ljava/lang/StringBuilder;
     107: invokevirtual #22                 // Method java/lang/StringBuilder.toString:()Ljava/lang/String;
     110: ldc           #23                 // String dubbo rest form content-type param construct error,un support  param type:
     112: aload_1
     113: invokeinterface #24,  6           // InterfaceMethod org/apache/dubbo/common/logger/ErrorTypeAwareLogger.error:(Ljava/lang/String;Ljava/lang/String;Ljava/lang/String;Ljava/lang/String;Ljava/lang/Throwable;)V
     118: aconst_null
     119: areturn
    Exception table:
       from    to  target type
           0    27    59   Class java/lang/Exception
          28    55    59   Class java/lang/Exception

  private static boolean typeJudge(java.lang.Class<?>, java.lang.Class<?>);
    Code:
       0: aload_0
       1: ifnonnull     6
       4: iconst_0
       5: ireturn
       6: ldc           #25                 // class java/util/Map
       8: aload_1
       9: invokevirtual #26                 // Method java/lang/Class.isAssignableFrom:(Ljava/lang/Class;)Z
      12: ifne          17
      15: iconst_1
      16: ireturn
      17: aload_0
      18: aload_1
      19: invokevirtual #26                 // Method java/lang/Class.isAssignableFrom:(Ljava/lang/Class;)Z
      22: ifne          33
      25: aload_0
      26: aload_1
      27: invokevirtual #27                 // Method java/lang/Object.equals:(Ljava/lang/Object;)Z
      30: ifeq          37
      33: iconst_1
      34: goto          38
      37: iconst_0
      38: ireturn

  public static void add(java.lang.Object, java.lang.String, java.lang.Object);
    Code:
       0: aload_0
       1: ifnonnull     5
       4: return
       5: aconst_null
       6: astore_3
       7: getstatic     #4                  // Field springMultiValueMapImplClass:Ljava/lang/Class;
      10: aload_0
      11: invokevirtual #28                 // Method java/lang/Object.getClass:()Ljava/lang/Class;
      14: invokevirtual #27                 // Method java/lang/Object.equals:(Ljava/lang/Object;)Z
      17: ifeq          27
      20: getstatic     #29                 // Field springMultiValueMapAdd:Ljava/lang/reflect/Method;
      23: astore_3
      24: goto          44
      27: getstatic     #10                 // Field jaxrsMultiValueMapImplClass:Ljava/lang/Class;
      30: aload_0
      31: invokevirtual #28                 // Method java/lang/Object.getClass:()Ljava/lang/Class;
      34: invokevirtual #27                 // Method java/lang/Object.equals:(Ljava/lang/Object;)Z
      37: ifeq          44
      40: getstatic     #30                 // Field jaxrsMultiValueMapAdd:Ljava/lang/reflect/Method;
      43: astore_3
      44: aload_0
      45: aload_3
      46: iconst_2
      47: anewarray     #7                  // class java/lang/Object
      50: dup
      51: iconst_0
      52: aload_1
      53: aastore
      54: dup
      55: iconst_1
      56: aload_2
      57: aastore
      58: invokestatic  #31                 // Method org/apache/dubbo/rpc/protocol/rest/util/ReflectUtils.invokeAndTryCatch:(Ljava/lang/Object;Ljava/lang/reflect/Method;[Ljava/lang/Object;)Ljava/lang/Object;
      61: pop
      62: goto          85
      65: astore_3
      66: getstatic     #12                 // Field logger:Lorg/apache/dubbo/common/logger/ErrorTypeAwareLogger;
      69: ldc           #13                 // String
      71: aload_3
      72: invokevirtual #14                 // Method java/lang/Exception.getMessage:()Ljava/lang/String;
      75: ldc           #13                 // String
      77: ldc           #32                 // String dubbo rest form content-type param add data  error:
      79: aload_3
      80: invokeinterface #24,  6           // InterfaceMethod org/apache/dubbo/common/logger/ErrorTypeAwareLogger.error:(Ljava/lang/String;Ljava/lang/String;Ljava/lang/String;Ljava/lang/String;Ljava/lang/Throwable;)V
      85: return
    Exception table:
       from    to  target type
           0     4    65   Class java/lang/Exception
           5    62    65   Class java/lang/Exception

  static {};
    Code:
       0: ldc           #33                 // class org/apache/dubbo/rpc/protocol/rest/util/MultiValueCreator
       2: invokestatic  #34                 // Method org/apache/dubbo/common/logger/LoggerFactory.getErrorTypeAwareLogger:(Ljava/lang/Class;)Lorg/apache/dubbo/common/logger/ErrorTypeAwareLogger;
       5: putstatic     #12                 // Field logger:Lorg/apache/dubbo/common/logger/ErrorTypeAwareLogger;
       8: aconst_null
       9: putstatic     #4                  // Field springMultiValueMapImplClass:Ljava/lang/Class;
      12: aconst_null
      13: putstatic     #2                  // Field springMultiValueMapClass:Ljava/lang/Class;
      16: aconst_null
      17: putstatic     #29                 // Field springMultiValueMapAdd:Ljava/lang/reflect/Method;
      20: aconst_null
      21: putstatic     #10                 // Field jaxrsMultiValueMapImplClass:Ljava/lang/Class;
      24: aconst_null
      25: putstatic     #9                  // Field jaxrsMultiValueMapClass:Ljava/lang/Class;
      28: aconst_null
      29: putstatic     #30                 // Field jaxrsMultiValueMapAdd:Ljava/lang/reflect/Method;
      32: iconst_1
      33: anewarray     #35                 // class java/lang/String
      36: dup
      37: iconst_0
      38: ldc           #36                 // String org.springframework.util.MultiValueMap
      40: aastore
      41: invokestatic  #37                 // Method org/apache/dubbo/rpc/protocol/rest/util/ReflectUtils.findClassTryException:([Ljava/lang/String;)Ljava/lang/Class;
      44: putstatic     #2                  // Field springMultiValueMapClass:Ljava/lang/Class;
      47: iconst_1
      48: anewarray     #35                 // class java/lang/String
      51: dup
      52: iconst_0
      53: ldc           #38                 // String org.springframework.util.LinkedMultiValueMap
      55: aastore
      56: invokestatic  #37                 // Method org/apache/dubbo/rpc/protocol/rest/util/ReflectUtils.findClassTryException:([Ljava/lang/String;)Ljava/lang/Class;
      59: putstatic     #4                  // Field springMultiValueMapImplClass:Ljava/lang/Class;
      62: getstatic     #4                  // Field springMultiValueMapImplClass:Ljava/lang/Class;
      65: ldc           #39                 // String add
      67: invokestatic  #40                 // Method org/apache/dubbo/rpc/protocol/rest/util/ReflectUtils.getMethodByName:(Ljava/lang/Class;Ljava/lang/String;)Ljava/lang/reflect/Method;
      70: putstatic     #29                 // Field springMultiValueMapAdd:Ljava/lang/reflect/Method;
      73: iconst_1
      74: anewarray     #35                 // class java/lang/String
      77: dup
      78: iconst_0
      79: ldc           #41                 // String javax.ws.rs.core.MultivaluedMap
      81: aastore
      82: invokestatic  #37                 // Method org/apache/dubbo/rpc/protocol/rest/util/ReflectUtils.findClassTryException:([Ljava/lang/String;)Ljava/lang/Class;
      85: putstatic     #9                  // Field jaxrsMultiValueMapClass:Ljava/lang/Class;
      88: iconst_1
      89: anewarray     #35                 // class java/lang/String
      92: dup
      93: iconst_0
      94: ldc           #42                 // String org.jboss.resteasy.specimpl.MultivaluedMapImpl
      96: aastore
      97: invokestatic  #37                 // Method org/apache/dubbo/rpc/protocol/rest/util/ReflectUtils.findClassTryException:([Ljava/lang/String;)Ljava/lang/Class;
     100: putstatic     #10                 // Field jaxrsMultiValueMapImplClass:Ljava/lang/Class;
     103: getstatic     #10                 // Field jaxrsMultiValueMapImplClass:Ljava/lang/Class;
     106: ldc           #39                 // String add
     108: invokestatic  #40                 // Method org/apache/dubbo/rpc/protocol/rest/util/ReflectUtils.getMethodByName:(Ljava/lang/Class;Ljava/lang/String;)Ljava/lang/reflect/Method;
     111: putstatic     #30                 // Field jaxrsMultiValueMapAdd:Ljava/lang/reflect/Method;
     114: return
}
