Compiled from "ReflectUtils.java"
public class org.apache.dubbo.rpc.protocol.rest.util.ReflectUtils {
  public org.apache.dubbo.rpc.protocol.rest.util.ReflectUtils();
    Code:
       0: aload_0
       1: invokespecial #1                  // Method java/lang/Object."<init>":()V
       4: return

  public static java.lang.Class findClass(java.lang.String, java.lang.ClassLoader) throws java.lang.ClassNotFoundException;
    Code:
       0: aload_1
       1: aload_0
       2: invokevirtual #2                  // Method java/lang/ClassLoader.loadClass:(Ljava/lang/String;)Ljava/lang/Class;
       5: areturn

  public static java.lang.Class findClass(java.lang.String) throws java.lang.ClassNotFoundException;
    Code:
       0: invokestatic  #3                  // Method java/lang/Thread.currentThread:()Ljava/lang/Thread;
       3: invokevirtual #4                  // Method java/lang/Thread.getContextClassLoader:()Ljava/lang/ClassLoader;
       6: iconst_1
       7: anewarray     #5                  // class java/lang/String
      10: dup
      11: iconst_0
      12: aload_0
      13: aastore
      14: invokestatic  #6                  // Method findClass:(Ljava/lang/ClassLoader;[Ljava/lang/String;)Ljava/lang/Class;
      17: areturn

  public static java.lang.Class findClassAndTryCatch(java.lang.String, java.lang.ClassLoader);
    Code:
       0: aload_0
       1: aload_1
       2: invokestatic  #7                  // Method findClass:(Ljava/lang/String;Ljava/lang/ClassLoader;)Ljava/lang/Class;
       5: areturn
       6: astore_2
       7: aconst_null
       8: areturn
    Exception table:
       from    to  target type
           0     5     6   Class java/lang/Throwable

  public static java.lang.Class findClass(java.lang.ClassLoader, java.lang.String...) throws java.lang.ClassNotFoundException;
    Code:
       0: aload_1
       1: astore_2
       2: aload_2
       3: astore        4
       5: aload         4
       7: arraylength
       8: istore        5
      10: iconst_0
      11: istore        6
      13: iload         6
      15: iload         5
      17: if_icmpge     49
      20: aload         4
      22: iload         6
      24: aaload
      25: astore        7
      27: aload         7
      29: aload_0
      30: invokestatic  #9                  // Method findClassAndTryCatch:(Ljava/lang/String;Ljava/lang/ClassLoader;)Ljava/lang/Class;
      33: astore_3
      34: aload_3
      35: ifnonnull     41
      38: goto          43
      41: aload_3
      42: areturn
      43: iinc          6, 1
      46: goto          13
      49: new           #10                 // class java/lang/ClassNotFoundException
      52: dup
      53: invokespecial #11                 // Method java/lang/ClassNotFoundException."<init>":()V
      56: athrow

  public static java.lang.Class findClassTryException(java.lang.ClassLoader, java.lang.String...);
    Code:
       0: aload_0
       1: aload_1
       2: invokestatic  #6                  // Method findClass:(Ljava/lang/ClassLoader;[Ljava/lang/String;)Ljava/lang/Class;
       5: areturn
       6: astore_2
       7: aconst_null
       8: areturn
    Exception table:
       from    to  target type
           0     5     6   Class java/lang/Exception

  public static java.util.List<java.lang.reflect.Method> getMethodByNameList(java.lang.Class, java.lang.String);
    Code:
       0: new           #13                 // class java/util/HashSet
       3: dup
       4: invokespecial #14                 // Method java/util/HashSet."<init>":()V
       7: astore_2
       8: aload_1
       9: aload_2
      10: aload_0
      11: invokevirtual #15                 // Method java/lang/Class.getDeclaredMethods:()[Ljava/lang/reflect/Method;
      14: invokestatic  #16                 // Method filterMethod:(Ljava/lang/String;Ljava/util/Set;[Ljava/lang/reflect/Method;)V
      17: goto          21
      20: astore_3
      21: aload_1
      22: aload_2
      23: aload_0
      24: invokevirtual #17                 // Method java/lang/Class.getMethods:()[Ljava/lang/reflect/Method;
      27: invokestatic  #16                 // Method filterMethod:(Ljava/lang/String;Ljava/util/Set;[Ljava/lang/reflect/Method;)V
      30: goto          34
      33: astore_3
      34: new           #18                 // class java/util/ArrayList
      37: dup
      38: aload_2
      39: invokespecial #19                 // Method java/util/ArrayList."<init>":(Ljava/util/Collection;)V
      42: areturn
    Exception table:
       from    to  target type
           8    17    20   Class java/lang/Exception
          21    30    33   Class java/lang/Exception

  public static java.util.List<java.lang.reflect.Constructor<?>> getConstructList(java.lang.Class);
    Code:
       0: new           #13                 // class java/util/HashSet
       3: dup
       4: invokespecial #14                 // Method java/util/HashSet."<init>":()V
       7: astore_1
       8: aload_1
       9: aload_0
      10: invokevirtual #20                 // Method java/lang/Class.getDeclaredConstructors:()[Ljava/lang/reflect/Constructor;
      13: invokestatic  #21                 // Method filterConstructMethod:(Ljava/util/Set;[Ljava/lang/reflect/Constructor;)V
      16: goto          20
      19: astore_2
      20: aload_1
      21: aload_0
      22: invokevirtual #22                 // Method java/lang/Class.getConstructors:()[Ljava/lang/reflect/Constructor;
      25: invokestatic  #21                 // Method filterConstructMethod:(Ljava/util/Set;[Ljava/lang/reflect/Constructor;)V
      28: goto          32
      31: astore_2
      32: new           #18                 // class java/util/ArrayList
      35: dup
      36: aload_1
      37: invokespecial #19                 // Method java/util/ArrayList."<init>":(Ljava/util/Collection;)V
      40: areturn
    Exception table:
       from    to  target type
           8    16    19   Class java/lang/Exception
          20    28    31   Class java/lang/Exception

  private static void filterConstructMethod(java.util.Set<java.lang.reflect.Constructor<?>>, java.lang.reflect.Constructor<?>[]);
    Code:
       0: aload_1
       1: astore_2
       2: aload_2
       3: arraylength
       4: istore_3
       5: iconst_0
       6: istore        4
       8: iload         4
      10: iload_3
      11: if_icmpge     35
      14: aload_2
      15: iload         4
      17: aaload
      18: astore        5
      20: aload_0
      21: aload         5
      23: invokeinterface #23,  2           // InterfaceMethod java/util/Set.add:(Ljava/lang/Object;)Z
      28: pop
      29: iinc          4, 1
      32: goto          8
      35: return

  private static void filterMethod(java.lang.String, java.util.Set<java.lang.reflect.Method>, java.lang.reflect.Method[]);
    Code:
       0: aload_2
       1: astore_3
       2: aload_3
       3: arraylength
       4: istore        4
       6: iconst_0
       7: istore        5
       9: iload         5
      11: iload         4
      13: if_icmpge     58
      16: aload_3
      17: iload         5
      19: aaload
      20: astore        6
      22: aload_0
      23: aload         6
      25: invokevirtual #24                 // Method java/lang/reflect/Method.getName:()Ljava/lang/String;
      28: invokevirtual #25                 // Method java/lang/String.equals:(Ljava/lang/Object;)Z
      31: ifne          37
      34: goto          52
      37: aload         6
      39: iconst_1
      40: invokevirtual #26                 // Method java/lang/reflect/Method.setAccessible:(Z)V
      43: aload_1
      44: aload         6
      46: invokeinterface #23,  2           // InterfaceMethod java/util/Set.add:(Ljava/lang/Object;)Z
      51: pop
      52: iinc          5, 1
      55: goto          9
      58: return

  public static java.lang.reflect.Method getMethodByName(java.lang.Class, java.lang.String);
    Code:
       0: aload_0
       1: aload_1
       2: invokestatic  #27                 // Method getMethodByNameList:(Ljava/lang/Class;Ljava/lang/String;)Ljava/util/List;
       5: astore_2
       6: aload_2
       7: invokeinterface #28,  1           // InterfaceMethod java/util/List.isEmpty:()Z
      12: ifeq          17
      15: aconst_null
      16: areturn
      17: aload_2
      18: iconst_0
      19: invokeinterface #29,  2           // InterfaceMethod java/util/List.get:(I)Ljava/lang/Object;
      24: checkcast     #30                 // class java/lang/reflect/Method
      27: areturn

  public static java.lang.Class findClassTryException(java.lang.String...);
    Code:
       0: invokestatic  #3                  // Method java/lang/Thread.currentThread:()Ljava/lang/Thread;
       3: invokevirtual #4                  // Method java/lang/Thread.getContextClassLoader:()Ljava/lang/ClassLoader;
       6: aload_0
       7: invokestatic  #31                 // Method findClassTryException:(Ljava/lang/ClassLoader;[Ljava/lang/String;)Ljava/lang/Class;
      10: areturn

  public static java.lang.Object invoke(java.lang.Object, java.lang.reflect.Method, java.lang.Object[]) throws java.lang.reflect.InvocationTargetException, java.lang.IllegalAccessException;
    Code:
       0: aload_1
       1: aload_0
       2: aload_2
       3: invokevirtual #32                 // Method java/lang/reflect/Method.invoke:(Ljava/lang/Object;[Ljava/lang/Object;)Ljava/lang/Object;
       6: areturn

  public static java.lang.Object invokeAndTryCatch(java.lang.Object, java.lang.reflect.Method, java.lang.Object[]);
    Code:
       0: aload_0
       1: aload_1
       2: aload_2
       3: invokestatic  #33                 // Method invoke:(Ljava/lang/Object;Ljava/lang/reflect/Method;[Ljava/lang/Object;)Ljava/lang/Object;
       6: areturn
       7: astore_3
       8: aconst_null
       9: areturn
    Exception table:
       from    to  target type
           0     6     7   Class java/lang/Exception
}
