Compiled from "CallbackServiceCodec.java"
public class org.apache.dubbo.rpc.protocol.dubbo.CallbackServiceCodec {
  private static final org.apache.dubbo.common.logger.ErrorTypeAwareLogger logger;

  private static final byte CALLBACK_NONE;

  private static final byte CALLBACK_CREATE;

  private static final byte CALLBACK_DESTROY;

  private static final java.lang.String INV_ATT_CALLBACK_KEY;

  private final org.apache.dubbo.rpc.ProxyFactory proxyFactory;

  private final org.apache.dubbo.rpc.Protocol protocolSPI;

  private final org.apache.dubbo.rpc.model.FrameworkModel frameworkModel;

  private final org.apache.dubbo.rpc.protocol.dubbo.DubboProtocol dubboProtocol;

  public org.apache.dubbo.rpc.protocol.dubbo.CallbackServiceCodec(org.apache.dubbo.rpc.model.FrameworkModel);
    Code:
       0: aload_0
       1: invokespecial #5                  // Method java/lang/Object."<init>":()V
       4: aload_0
       5: aload_1
       6: putfield      #6                  // Field frameworkModel:Lorg/apache/dubbo/rpc/model/FrameworkModel;
       9: aload_0
      10: aload_1
      11: ldc           #7                  // class org/apache/dubbo/rpc/ProxyFactory
      13: invokevirtual #8                  // Method org/apache/dubbo/rpc/model/FrameworkModel.getExtensionLoader:(Ljava/lang/Class;)Lorg/apache/dubbo/common/extension/ExtensionLoader;
      16: invokevirtual #9                  // Method org/apache/dubbo/common/extension/ExtensionLoader.getAdaptiveExtension:()Ljava/lang/Object;
      19: checkcast     #7                  // class org/apache/dubbo/rpc/ProxyFactory
      22: putfield      #10                 // Field proxyFactory:Lorg/apache/dubbo/rpc/ProxyFactory;
      25: aload_0
      26: aload_1
      27: ldc           #11                 // class org/apache/dubbo/rpc/Protocol
      29: invokevirtual #8                  // Method org/apache/dubbo/rpc/model/FrameworkModel.getExtensionLoader:(Ljava/lang/Class;)Lorg/apache/dubbo/common/extension/ExtensionLoader;
      32: ldc           #12                 // String dubbo
      34: invokevirtual #13                 // Method org/apache/dubbo/common/extension/ExtensionLoader.getExtension:(Ljava/lang/String;)Ljava/lang/Object;
      37: checkcast     #11                 // class org/apache/dubbo/rpc/Protocol
      40: putfield      #14                 // Field protocolSPI:Lorg/apache/dubbo/rpc/Protocol;
      43: aload_0
      44: aload_1
      45: ldc           #11                 // class org/apache/dubbo/rpc/Protocol
      47: invokevirtual #8                  // Method org/apache/dubbo/rpc/model/FrameworkModel.getExtensionLoader:(Ljava/lang/Class;)Lorg/apache/dubbo/common/extension/ExtensionLoader;
      50: ldc           #12                 // String dubbo
      52: iconst_0
      53: invokevirtual #16                 // Method org/apache/dubbo/common/extension/ExtensionLoader.getExtension:(Ljava/lang/String;Z)Ljava/lang/Object;
      56: checkcast     #15                 // class org/apache/dubbo/rpc/protocol/dubbo/DubboProtocol
      59: putfield      #17                 // Field dubboProtocol:Lorg/apache/dubbo/rpc/protocol/dubbo/DubboProtocol;
      62: return

  private static byte isCallBack(org.apache.dubbo.common.URL, java.lang.String, java.lang.String, int);
    Code:
       0: iconst_0
       1: istore        4
       3: aload_0
       4: ifnull        85
       7: aload_0
       8: aload_1
       9: aload_2
      10: invokevirtual #19                 // Method org/apache/dubbo/common/URL.hasServiceMethodParameter:(Ljava/lang/String;Ljava/lang/String;)Z
      13: ifeq          85
      16: aload_0
      17: aload_1
      18: new           #20                 // class java/lang/StringBuilder
      21: dup
      22: invokespecial #21                 // Method java/lang/StringBuilder."<init>":()V
      25: aload_2
      26: invokevirtual #22                 // Method java/lang/StringBuilder.append:(Ljava/lang/String;)Ljava/lang/StringBuilder;
      29: ldc           #23                 // String .
      31: invokevirtual #22                 // Method java/lang/StringBuilder.append:(Ljava/lang/String;)Ljava/lang/StringBuilder;
      34: iload_3
      35: invokevirtual #24                 // Method java/lang/StringBuilder.append:(I)Ljava/lang/StringBuilder;
      38: ldc           #25                 // String .callback
      40: invokevirtual #22                 // Method java/lang/StringBuilder.append:(Ljava/lang/String;)Ljava/lang/StringBuilder;
      43: invokevirtual #26                 // Method java/lang/StringBuilder.toString:()Ljava/lang/String;
      46: invokevirtual #27                 // Method org/apache/dubbo/common/URL.getServiceParameter:(Ljava/lang/String;Ljava/lang/String;)Ljava/lang/String;
      49: astore        5
      51: aload         5
      53: ifnull        85
      56: ldc           #28                 // String true
      58: aload         5
      60: invokevirtual #29                 // Method java/lang/String.equalsIgnoreCase:(Ljava/lang/String;)Z
      63: ifeq          72
      66: iconst_1
      67: istore        4
      69: goto          85
      72: ldc           #30                 // String false
      74: aload         5
      76: invokevirtual #29                 // Method java/lang/String.equalsIgnoreCase:(Ljava/lang/String;)Z
      79: ifeq          85
      82: iconst_2
      83: istore        4
      85: iload         4
      87: ireturn

  private java.lang.String exportOrUnexportCallbackService(org.apache.dubbo.remoting.Channel, org.apache.dubbo.rpc.RpcInvocation, org.apache.dubbo.common.URL, java.lang.Class, java.lang.Object, java.lang.Boolean) throws java.io.IOException;
    Code:
       0: aload         5
       2: invokestatic  #31                 // Method java/lang/System.identityHashCode:(Ljava/lang/Object;)I
       5: istore        7
       7: new           #32                 // class java/util/HashMap
      10: dup
      11: iconst_3
      12: invokespecial #33                 // Method java/util/HashMap."<init>":(I)V
      15: astore        8
      17: aload         8
      19: ldc           #34                 // String isserver
      21: getstatic     #35                 // Field java/lang/Boolean.FALSE:Ljava/lang/Boolean;
      24: invokevirtual #36                 // Method java/lang/Boolean.toString:()Ljava/lang/String;
      27: invokeinterface #37,  3           // InterfaceMethod java/util/Map.put:(Ljava/lang/Object;Ljava/lang/Object;)Ljava/lang/Object;
      32: pop
      33: aload         8
      35: ldc           #38                 // String is_callback_service
      37: getstatic     #39                 // Field java/lang/Boolean.TRUE:Ljava/lang/Boolean;
      40: invokevirtual #36                 // Method java/lang/Boolean.toString:()Ljava/lang/String;
      43: invokeinterface #37,  3           // InterfaceMethod java/util/Map.put:(Ljava/lang/Object;Ljava/lang/Object;)Ljava/lang/Object;
      48: pop
      49: aload_2
      50: ifnonnull     57
      53: aconst_null
      54: goto          66
      57: aload_2
      58: ldc           #40                 // String group
      60: invokevirtual #41                 // Method org/apache/dubbo/rpc/RpcInvocation.getObjectAttachmentWithoutConvert:(Ljava/lang/String;)Ljava/lang/Object;
      63: checkcast     #42                 // class java/lang/String
      66: astore        9
      68: aload         9
      70: ifnull        93
      73: aload         9
      75: invokevirtual #43                 // Method java/lang/String.length:()I
      78: ifle          93
      81: aload         8
      83: ldc           #40                 // String group
      85: aload         9
      87: invokeinterface #37,  3           // InterfaceMethod java/util/Map.put:(Ljava/lang/Object;Ljava/lang/Object;)Ljava/lang/Object;
      92: pop
      93: aload         8
      95: ldc           #44                 // String methods
      97: aload         4
      99: invokestatic  #45                 // Method org/apache/dubbo/common/utils/ClassUtils.getDeclaredMethodNames:(Ljava/lang/Class;)[Ljava/lang/String;
     102: ldc           #46                 // String ,
     104: invokestatic  #47                 // Method org/apache/dubbo/common/utils/StringUtils.join:([Ljava/lang/String;Ljava/lang/String;)Ljava/lang/String;
     107: invokeinterface #37,  3           // InterfaceMethod java/util/Map.put:(Ljava/lang/Object;Ljava/lang/Object;)Ljava/lang/Object;
     112: pop
     113: new           #32                 // class java/util/HashMap
     116: dup
     117: invokespecial #48                 // Method java/util/HashMap."<init>":()V
     120: astore        10
     122: aload_3
     123: ifnull        156
     126: aload_3
     127: invokevirtual #49                 // Method org/apache/dubbo/common/URL.getParameters:()Ljava/util/Map;
     130: astore        11
     132: aload         11
     134: ifnull        156
     137: aload         11
     139: invokeinterface #50,  1           // InterfaceMethod java/util/Map.isEmpty:()Z
     144: ifne          156
     147: aload         10
     149: aload         11
     151: invokeinterface #51,  2           // InterfaceMethod java/util/Map.putAll:(Ljava/util/Map;)V
     156: aload         10
     158: aload         8
     160: invokeinterface #51,  2           // InterfaceMethod java/util/Map.putAll:(Ljava/util/Map;)V
     165: aload         10
     167: ldc           #52                 // String version
     169: invokeinterface #53,  2           // InterfaceMethod java/util/Map.remove:(Ljava/lang/Object;)Ljava/lang/Object;
     174: pop
     175: aload         10
     177: ldc           #55                 // String bind.port
     179: invokeinterface #53,  2           // InterfaceMethod java/util/Map.remove:(Ljava/lang/Object;)Ljava/lang/Object;
     184: pop
     185: aload         10
     187: ldc           #56                 // String interface
     189: aload         4
     191: invokevirtual #57                 // Method java/lang/Class.getName:()Ljava/lang/String;
     194: invokeinterface #37,  3           // InterfaceMethod java/util/Map.put:(Ljava/lang/Object;Ljava/lang/Object;)Ljava/lang/Object;
     199: pop
     200: new           #58                 // class org/apache/dubbo/common/url/component/ServiceConfigURL
     203: dup
     204: ldc           #12                 // String dubbo
     206: aload_1
     207: invokeinterface #59,  1           // InterfaceMethod org/apache/dubbo/remoting/Channel.getLocalAddress:()Ljava/net/InetSocketAddress;
     212: invokevirtual #60                 // Method java/net/InetSocketAddress.getAddress:()Ljava/net/InetAddress;
     215: invokevirtual #61                 // Method java/net/InetAddress.getHostAddress:()Ljava/lang/String;
     218: aload_1
     219: invokeinterface #59,  1           // InterfaceMethod org/apache/dubbo/remoting/Channel.getLocalAddress:()Ljava/net/InetSocketAddress;
     224: invokevirtual #62                 // Method java/net/InetSocketAddress.getPort:()I
     227: new           #20                 // class java/lang/StringBuilder
     230: dup
     231: invokespecial #21                 // Method java/lang/StringBuilder."<init>":()V
     234: aload         4
     236: invokevirtual #57                 // Method java/lang/Class.getName:()Ljava/lang/String;
     239: invokevirtual #22                 // Method java/lang/StringBuilder.append:(Ljava/lang/String;)Ljava/lang/StringBuilder;
     242: ldc           #23                 // String .
     244: invokevirtual #22                 // Method java/lang/StringBuilder.append:(Ljava/lang/String;)Ljava/lang/StringBuilder;
     247: iload         7
     249: invokevirtual #24                 // Method java/lang/StringBuilder.append:(I)Ljava/lang/StringBuilder;
     252: invokevirtual #26                 // Method java/lang/StringBuilder.toString:()Ljava/lang/String;
     255: aload         10
     257: invokespecial #63                 // Method org/apache/dubbo/common/url/component/ServiceConfigURL."<init>":(Ljava/lang/String;Ljava/lang/String;ILjava/lang/String;Ljava/util/Map;)V
     260: astore        11
     262: iload         7
     264: invokestatic  #64                 // Method getClientSideCallbackServiceCacheKey:(I)Ljava/lang/String;
     267: astore        12
     269: aload         4
     271: invokevirtual #57                 // Method java/lang/Class.getName:()Ljava/lang/String;
     274: invokestatic  #65                 // Method getClientSideCountKey:(Ljava/lang/String;)Ljava/lang/String;
     277: astore        13
     279: aload         6
     281: invokevirtual #66                 // Method java/lang/Boolean.booleanValue:()Z
     284: ifeq          599
     287: aload_1
     288: aload         12
     290: invokeinterface #67,  2           // InterfaceMethod org/apache/dubbo/remoting/Channel.hasAttribute:(Ljava/lang/String;)Z
     295: ifne          644
     298: aload_1
     299: aload_3
     300: aload         4
     302: invokevirtual #57                 // Method java/lang/Class.getName:()Ljava/lang/String;
     305: iload         7
     307: iconst_0
     308: invokestatic  #68                 // Method isInstancesOverLimit:(Lorg/apache/dubbo/remoting/Channel;Lorg/apache/dubbo/common/URL;Ljava/lang/String;IZ)Z
     311: ifne          644
     314: aload_2
     315: invokevirtual #69                 // Method org/apache/dubbo/rpc/RpcInvocation.getServiceModel:()Lorg/apache/dubbo/rpc/model/ServiceModel;
     318: ifnonnull     365
     321: invokestatic  #70                 // Method org/apache/dubbo/rpc/model/ApplicationModel.defaultModel:()Lorg/apache/dubbo/rpc/model/ApplicationModel;
     324: invokevirtual #71                 // Method org/apache/dubbo/rpc/model/ApplicationModel.getDefaultModule:()Lorg/apache/dubbo/rpc/model/ModuleModel;
     327: astore        14
     329: getstatic     #72                 // Field logger:Lorg/apache/dubbo/common/logger/ErrorTypeAwareLogger;
     332: ldc           #73                 // String 4-18
     334: ldc           #74                 // String
     336: ldc           #74                 // String
     338: new           #20                 // class java/lang/StringBuilder
     341: dup
     342: invokespecial #21                 // Method java/lang/StringBuilder."<init>":()V
     345: ldc           #75                 // String Unable to get Service Model from Invocation. Please check if your invocation failed! This error only happen in UT cases! Invocation:
     347: invokevirtual #22                 // Method java/lang/StringBuilder.append:(Ljava/lang/String;)Ljava/lang/StringBuilder;
     350: aload_2
     351: invokevirtual #76                 // Method java/lang/StringBuilder.append:(Ljava/lang/Object;)Ljava/lang/StringBuilder;
     354: invokevirtual #26                 // Method java/lang/StringBuilder.toString:()Ljava/lang/String;
     357: invokeinterface #77,  5           // InterfaceMethod org/apache/dubbo/common/logger/ErrorTypeAwareLogger.error:(Ljava/lang/String;Ljava/lang/String;Ljava/lang/String;Ljava/lang/String;)V
     362: goto          374
     365: aload_2
     366: invokevirtual #69                 // Method org/apache/dubbo/rpc/RpcInvocation.getServiceModel:()Lorg/apache/dubbo/rpc/model/ServiceModel;
     369: invokevirtual #78                 // Method org/apache/dubbo/rpc/model/ServiceModel.getModuleModel:()Lorg/apache/dubbo/rpc/model/ModuleModel;
     372: astore        14
     374: aload         14
     376: invokevirtual #79                 // Method org/apache/dubbo/rpc/model/ModuleModel.getServiceRepository:()Lorg/apache/dubbo/rpc/model/ModuleServiceRepository;
     379: aload         4
     381: invokevirtual #80                 // Method org/apache/dubbo/rpc/model/ModuleServiceRepository.registerService:(Ljava/lang/Class;)Lorg/apache/dubbo/rpc/model/ServiceDescriptor;
     384: astore        15
     386: new           #81                 // class org/apache/dubbo/rpc/model/ServiceMetadata
     389: dup
     390: new           #20                 // class java/lang/StringBuilder
     393: dup
     394: invokespecial #21                 // Method java/lang/StringBuilder."<init>":()V
     397: aload         4
     399: invokevirtual #57                 // Method java/lang/Class.getName:()Ljava/lang/String;
     402: invokevirtual #22                 // Method java/lang/StringBuilder.append:(Ljava/lang/String;)Ljava/lang/StringBuilder;
     405: ldc           #23                 // String .
     407: invokevirtual #22                 // Method java/lang/StringBuilder.append:(Ljava/lang/String;)Ljava/lang/StringBuilder;
     410: iload         7
     412: invokevirtual #24                 // Method java/lang/StringBuilder.append:(I)Ljava/lang/StringBuilder;
     415: invokevirtual #26                 // Method java/lang/StringBuilder.toString:()Ljava/lang/String;
     418: aload         11
     420: invokevirtual #82                 // Method org/apache/dubbo/common/URL.getGroup:()Ljava/lang/String;
     423: aload         11
     425: invokevirtual #83                 // Method org/apache/dubbo/common/URL.getVersion:()Ljava/lang/String;
     428: aload         4
     430: invokespecial #84                 // Method org/apache/dubbo/rpc/model/ServiceMetadata."<init>":(Ljava/lang/String;Ljava/lang/String;Ljava/lang/String;Ljava/lang/Class;)V
     433: astore        16
     435: aload         11
     437: invokevirtual #85                 // Method org/apache/dubbo/common/URL.getPath:()Ljava/lang/String;
     440: aload         9
     442: aload         11
     444: invokevirtual #83                 // Method org/apache/dubbo/common/URL.getVersion:()Ljava/lang/String;
     447: invokestatic  #86                 // Method org/apache/dubbo/common/BaseServiceMetadata.buildServiceKey:(Ljava/lang/String;Ljava/lang/String;Ljava/lang/String;)Ljava/lang/String;
     450: astore        17
     452: new           #87                 // class org/apache/dubbo/rpc/model/ProviderModel
     455: dup
     456: aload         17
     458: aload         5
     460: aload         15
     462: aload         14
     464: aload         16
     466: aload         4
     468: invokestatic  #88                 // Method org/apache/dubbo/common/utils/ClassUtils.getClassLoader:(Ljava/lang/Class;)Ljava/lang/ClassLoader;
     471: invokespecial #89                 // Method org/apache/dubbo/rpc/model/ProviderModel."<init>":(Ljava/lang/String;Ljava/lang/Object;Lorg/apache/dubbo/rpc/model/ServiceDescriptor;Lorg/apache/dubbo/rpc/model/ModuleModel;Lorg/apache/dubbo/rpc/model/ServiceMetadata;Ljava/lang/ClassLoader;)V
     474: astore        18
     476: aload         14
     478: invokevirtual #79                 // Method org/apache/dubbo/rpc/model/ModuleModel.getServiceRepository:()Lorg/apache/dubbo/rpc/model/ModuleServiceRepository;
     481: aload         18
     483: invokevirtual #90                 // Method org/apache/dubbo/rpc/model/ModuleServiceRepository.registerProvider:(Lorg/apache/dubbo/rpc/model/ProviderModel;)V
     486: aload         11
     488: aload         14
     490: invokevirtual #91                 // Method org/apache/dubbo/common/URL.setScopeModel:(Lorg/apache/dubbo/rpc/model/ScopeModel;)Lorg/apache/dubbo/common/URL;
     493: astore        11
     495: aload         11
     497: aload         18
     499: invokevirtual #92                 // Method org/apache/dubbo/common/URL.setServiceModel:(Lorg/apache/dubbo/rpc/model/ServiceModel;)Lorg/apache/dubbo/common/URL;
     502: astore        11
     504: aload_0
     505: getfield      #10                 // Field proxyFactory:Lorg/apache/dubbo/rpc/ProxyFactory;
     508: aload         5
     510: aload         4
     512: aload         11
     514: invokeinterface #93,  4           // InterfaceMethod org/apache/dubbo/rpc/ProxyFactory.getInvoker:(Ljava/lang/Object;Ljava/lang/Class;Lorg/apache/dubbo/common/URL;)Lorg/apache/dubbo/rpc/Invoker;
     519: astore        19
     521: aload_0
     522: getfield      #14                 // Field protocolSPI:Lorg/apache/dubbo/rpc/Protocol;
     525: aload         19
     527: invokeinterface #94,  2           // InterfaceMethod org/apache/dubbo/rpc/Protocol.export:(Lorg/apache/dubbo/rpc/Invoker;)Lorg/apache/dubbo/rpc/Exporter;
     532: astore        20
     534: aload_1
     535: aload         12
     537: aload         20
     539: invokeinterface #95,  3           // InterfaceMethod org/apache/dubbo/remoting/Channel.setAttribute:(Ljava/lang/String;Ljava/lang/Object;)V
     544: getstatic     #72                 // Field logger:Lorg/apache/dubbo/common/logger/ErrorTypeAwareLogger;
     547: new           #20                 // class java/lang/StringBuilder
     550: dup
     551: invokespecial #21                 // Method java/lang/StringBuilder."<init>":()V
     554: ldc           #96                 // String Export a callback service :
     556: invokevirtual #22                 // Method java/lang/StringBuilder.append:(Ljava/lang/String;)Ljava/lang/StringBuilder;
     559: aload         11
     561: invokevirtual #76                 // Method java/lang/StringBuilder.append:(Ljava/lang/Object;)Ljava/lang/StringBuilder;
     564: ldc           #97                 // String , on
     566: invokevirtual #22                 // Method java/lang/StringBuilder.append:(Ljava/lang/String;)Ljava/lang/StringBuilder;
     569: aload_1
     570: invokevirtual #76                 // Method java/lang/StringBuilder.append:(Ljava/lang/Object;)Ljava/lang/StringBuilder;
     573: ldc           #98                 // String , url is:
     575: invokevirtual #22                 // Method java/lang/StringBuilder.append:(Ljava/lang/String;)Ljava/lang/StringBuilder;
     578: aload_3
     579: invokevirtual #76                 // Method java/lang/StringBuilder.append:(Ljava/lang/Object;)Ljava/lang/StringBuilder;
     582: invokevirtual #26                 // Method java/lang/StringBuilder.toString:()Ljava/lang/String;
     585: invokeinterface #99,  2           // InterfaceMethod org/apache/dubbo/common/logger/ErrorTypeAwareLogger.info:(Ljava/lang/String;)V
     590: aload_1
     591: aload         13
     593: invokestatic  #100                // Method increaseInstanceCount:(Lorg/apache/dubbo/remoting/Channel;Ljava/lang/String;)V
     596: goto          644
     599: aload_1
     600: aload         12
     602: invokeinterface #67,  2           // InterfaceMethod org/apache/dubbo/remoting/Channel.hasAttribute:(Ljava/lang/String;)Z
     607: ifeq          644
     610: aload_1
     611: aload         12
     613: invokeinterface #101,  2          // InterfaceMethod org/apache/dubbo/remoting/Channel.getAttribute:(Ljava/lang/String;)Ljava/lang/Object;
     618: checkcast     #102                // class org/apache/dubbo/rpc/Exporter
     621: astore        14
     623: aload         14
     625: invokeinterface #103,  1          // InterfaceMethod org/apache/dubbo/rpc/Exporter.unexport:()V
     630: aload_1
     631: aload         12
     633: invokeinterface #104,  2          // InterfaceMethod org/apache/dubbo/remoting/Channel.removeAttribute:(Ljava/lang/String;)V
     638: aload_1
     639: aload         13
     641: invokestatic  #105                // Method decreaseInstanceCount:(Lorg/apache/dubbo/remoting/Channel;Ljava/lang/String;)V
     644: iload         7
     646: invokestatic  #106                // Method java/lang/String.valueOf:(I)Ljava/lang/String;
     649: areturn

  private java.lang.Object referOrDestroyCallbackService(org.apache.dubbo.remoting.Channel, org.apache.dubbo.common.URL, java.lang.Class<?>, org.apache.dubbo.rpc.Invocation, int, boolean);
    Code:
       0: aload_1
       1: aload_3
       2: invokevirtual #57                 // Method java/lang/Class.getName:()Ljava/lang/String;
       5: iload         5
       7: invokestatic  #107                // Method getServerSideCallbackInvokerCacheKey:(Lorg/apache/dubbo/remoting/Channel;Ljava/lang/String;I)Ljava/lang/String;
      10: astore        8
      12: aload_1
      13: aload_3
      14: invokevirtual #57                 // Method java/lang/Class.getName:()Ljava/lang/String;
      17: iload         5
      19: invokestatic  #108                // Method getServerSideCallbackServiceCacheKey:(Lorg/apache/dubbo/remoting/Channel;Ljava/lang/String;I)Ljava/lang/String;
      22: astore        9
      24: aload_1
      25: aload         9
      27: invokeinterface #101,  2          // InterfaceMethod org/apache/dubbo/remoting/Channel.getAttribute:(Ljava/lang/String;)Ljava/lang/Object;
      32: astore        7
      34: aload_1
      35: aload_3
      36: invokevirtual #57                 // Method java/lang/Class.getName:()Ljava/lang/String;
      39: invokestatic  #109                // Method getServerSideCountKey:(Lorg/apache/dubbo/remoting/Channel;Ljava/lang/String;)Ljava/lang/String;
      42: astore        10
      44: iload         6
      46: ifeq          333
      49: aload         7
      51: ifnonnull     434
      54: new           #20                 // class java/lang/StringBuilder
      57: dup
      58: invokespecial #21                 // Method java/lang/StringBuilder."<init>":()V
      61: ldc           #110                // String callback://
      63: invokevirtual #22                 // Method java/lang/StringBuilder.append:(Ljava/lang/String;)Ljava/lang/StringBuilder;
      66: aload_2
      67: invokevirtual #111                // Method org/apache/dubbo/common/URL.getAddress:()Ljava/lang/String;
      70: invokevirtual #22                 // Method java/lang/StringBuilder.append:(Ljava/lang/String;)Ljava/lang/StringBuilder;
      73: ldc           #112                // String /
      75: invokevirtual #22                 // Method java/lang/StringBuilder.append:(Ljava/lang/String;)Ljava/lang/StringBuilder;
      78: aload_3
      79: invokevirtual #57                 // Method java/lang/Class.getName:()Ljava/lang/String;
      82: invokevirtual #22                 // Method java/lang/StringBuilder.append:(Ljava/lang/String;)Ljava/lang/StringBuilder;
      85: ldc           #113                // String ?
      87: invokevirtual #22                 // Method java/lang/StringBuilder.append:(Ljava/lang/String;)Ljava/lang/StringBuilder;
      90: ldc           #56                 // String interface
      92: invokevirtual #22                 // Method java/lang/StringBuilder.append:(Ljava/lang/String;)Ljava/lang/StringBuilder;
      95: ldc           #114                // String =
      97: invokevirtual #22                 // Method java/lang/StringBuilder.append:(Ljava/lang/String;)Ljava/lang/StringBuilder;
     100: aload_3
     101: invokevirtual #57                 // Method java/lang/Class.getName:()Ljava/lang/String;
     104: invokevirtual #22                 // Method java/lang/StringBuilder.append:(Ljava/lang/String;)Ljava/lang/StringBuilder;
     107: invokevirtual #26                 // Method java/lang/StringBuilder.toString:()Ljava/lang/String;
     110: invokestatic  #115                // Method org/apache/dubbo/common/URL.valueOf:(Ljava/lang/String;)Lorg/apache/dubbo/common/URL;
     113: astore        11
     115: aload         11
     117: aload_2
     118: invokevirtual #49                 // Method org/apache/dubbo/common/URL.getParameters:()Ljava/util/Map;
     121: invokevirtual #116                // Method org/apache/dubbo/common/URL.addParametersIfAbsent:(Ljava/util/Map;)Lorg/apache/dubbo/common/URL;
     124: ldc           #44                 // String methods
     126: invokevirtual #117                // Method org/apache/dubbo/common/URL.removeParameter:(Ljava/lang/String;)Lorg/apache/dubbo/common/URL;
     129: astore        11
     131: aload_1
     132: aload         11
     134: aload_3
     135: invokevirtual #57                 // Method java/lang/Class.getName:()Ljava/lang/String;
     138: iload         5
     140: iconst_1
     141: invokestatic  #68                 // Method isInstancesOverLimit:(Lorg/apache/dubbo/remoting/Channel;Lorg/apache/dubbo/common/URL;Ljava/lang/String;IZ)Z
     144: ifne          330
     147: aload_2
     148: invokevirtual #118                // Method org/apache/dubbo/common/URL.getOrDefaultApplicationModel:()Lorg/apache/dubbo/rpc/model/ApplicationModel;
     151: invokevirtual #71                 // Method org/apache/dubbo/rpc/model/ApplicationModel.getDefaultModule:()Lorg/apache/dubbo/rpc/model/ModuleModel;
     154: invokevirtual #79                 // Method org/apache/dubbo/rpc/model/ModuleModel.getServiceRepository:()Lorg/apache/dubbo/rpc/model/ModuleServiceRepository;
     157: aload_3
     158: invokevirtual #80                 // Method org/apache/dubbo/rpc/model/ModuleServiceRepository.registerService:(Ljava/lang/Class;)Lorg/apache/dubbo/rpc/model/ServiceDescriptor;
     161: pop
     162: new           #119                // class org/apache/dubbo/rpc/protocol/dubbo/ChannelWrappedInvoker
     165: dup
     166: aload_3
     167: aload_1
     168: aload         11
     170: iload         5
     172: invokestatic  #106                // Method java/lang/String.valueOf:(I)Ljava/lang/String;
     175: invokespecial #120                // Method org/apache/dubbo/rpc/protocol/dubbo/ChannelWrappedInvoker."<init>":(Ljava/lang/Class;Lorg/apache/dubbo/remoting/Channel;Lorg/apache/dubbo/common/URL;Ljava/lang/String;)V
     178: astore        12
     180: aload_0
     181: getfield      #10                 // Field proxyFactory:Lorg/apache/dubbo/rpc/ProxyFactory;
     184: aload         12
     186: invokeinterface #121,  2          // InterfaceMethod org/apache/dubbo/rpc/ProxyFactory.getProxy:(Lorg/apache/dubbo/rpc/Invoker;)Ljava/lang/Object;
     191: astore        7
     193: aload_1
     194: aload         9
     196: aload         7
     198: invokeinterface #95,  3           // InterfaceMethod org/apache/dubbo/remoting/Channel.setAttribute:(Ljava/lang/String;Ljava/lang/Object;)V
     203: aload_1
     204: aload         8
     206: aload         12
     208: invokeinterface #95,  3           // InterfaceMethod org/apache/dubbo/remoting/Channel.setAttribute:(Ljava/lang/String;Ljava/lang/Object;)V
     213: aload_1
     214: aload         10
     216: invokestatic  #100                // Method increaseInstanceCount:(Lorg/apache/dubbo/remoting/Channel;Ljava/lang/String;)V
     219: aload_1
     220: ldc           #122                // String channel.callback.invokers.key
     222: invokeinterface #101,  2          // InterfaceMethod org/apache/dubbo/remoting/Channel.getAttribute:(Ljava/lang/String;)Ljava/lang/Object;
     227: checkcast     #123                // class java/util/Set
     230: astore        13
     232: aload         13
     234: ifnonnull     257
     237: new           #124                // class org/apache/dubbo/common/utils/ConcurrentHashSet
     240: dup
     241: iconst_1
     242: invokespecial #125                // Method org/apache/dubbo/common/utils/ConcurrentHashSet."<init>":(I)V
     245: astore        13
     247: aload_1
     248: ldc           #122                // String channel.callback.invokers.key
     250: aload         13
     252: invokeinterface #95,  3           // InterfaceMethod org/apache/dubbo/remoting/Channel.setAttribute:(Ljava/lang/String;Ljava/lang/Object;)V
     257: aload         13
     259: aload         12
     261: invokeinterface #126,  2          // InterfaceMethod java/util/Set.add:(Ljava/lang/Object;)Z
     266: pop
     267: getstatic     #72                 // Field logger:Lorg/apache/dubbo/common/logger/ErrorTypeAwareLogger;
     270: new           #20                 // class java/lang/StringBuilder
     273: dup
     274: invokespecial #21                 // Method java/lang/StringBuilder."<init>":()V
     277: ldc           #127                // String method
     279: invokevirtual #22                 // Method java/lang/StringBuilder.append:(Ljava/lang/String;)Ljava/lang/StringBuilder;
     282: aload         4
     284: invokeinterface #128,  1          // InterfaceMethod org/apache/dubbo/rpc/Invocation.getMethodName:()Ljava/lang/String;
     289: invokevirtual #22                 // Method java/lang/StringBuilder.append:(Ljava/lang/String;)Ljava/lang/StringBuilder;
     292: ldc           #129                // String  include a callback service :
     294: invokevirtual #22                 // Method java/lang/StringBuilder.append:(Ljava/lang/String;)Ljava/lang/StringBuilder;
     297: aload         12
     299: invokeinterface #130,  1          // InterfaceMethod org/apache/dubbo/rpc/Invoker.getUrl:()Lorg/apache/dubbo/common/URL;
     304: invokevirtual #76                 // Method java/lang/StringBuilder.append:(Ljava/lang/Object;)Ljava/lang/StringBuilder;
     307: ldc           #131                // String , a proxy :
     309: invokevirtual #22                 // Method java/lang/StringBuilder.append:(Ljava/lang/String;)Ljava/lang/StringBuilder;
     312: aload         12
     314: invokevirtual #76                 // Method java/lang/StringBuilder.append:(Ljava/lang/Object;)Ljava/lang/StringBuilder;
     317: ldc           #132                // String  has been created.
     319: invokevirtual #22                 // Method java/lang/StringBuilder.append:(Ljava/lang/String;)Ljava/lang/StringBuilder;
     322: invokevirtual #26                 // Method java/lang/StringBuilder.toString:()Ljava/lang/String;
     325: invokeinterface #99,  2           // InterfaceMethod org/apache/dubbo/common/logger/ErrorTypeAwareLogger.info:(Ljava/lang/String;)V
     330: goto          434
     333: aload         7
     335: ifnull        434
     338: aload_1
     339: aload         8
     341: invokeinterface #101,  2          // InterfaceMethod org/apache/dubbo/remoting/Channel.getAttribute:(Ljava/lang/String;)Ljava/lang/Object;
     346: checkcast     #133                // class org/apache/dubbo/rpc/Invoker
     349: astore        11
     351: aload_1
     352: ldc           #122                // String channel.callback.invokers.key
     354: invokeinterface #101,  2          // InterfaceMethod org/apache/dubbo/remoting/Channel.getAttribute:(Ljava/lang/String;)Ljava/lang/Object;
     359: checkcast     #123                // class java/util/Set
     362: astore        12
     364: aload         12
     366: ifnull        379
     369: aload         12
     371: aload         11
     373: invokeinterface #134,  2          // InterfaceMethod java/util/Set.remove:(Ljava/lang/Object;)Z
     378: pop
     379: aload         11
     381: invokeinterface #135,  1          // InterfaceMethod org/apache/dubbo/rpc/Invoker.destroy:()V
     386: goto          412
     389: astore        12
     391: getstatic     #72                 // Field logger:Lorg/apache/dubbo/common/logger/ErrorTypeAwareLogger;
     394: ldc           #137                // String 4-17
     396: ldc           #74                 // String
     398: ldc           #74                 // String
     400: aload         12
     402: invokevirtual #138                // Method java/lang/Exception.getMessage:()Ljava/lang/String;
     405: aload         12
     407: invokeinterface #139,  6          // InterfaceMethod org/apache/dubbo/common/logger/ErrorTypeAwareLogger.error:(Ljava/lang/String;Ljava/lang/String;Ljava/lang/String;Ljava/lang/String;Ljava/lang/Throwable;)V
     412: aload_1
     413: aload         9
     415: invokeinterface #104,  2          // InterfaceMethod org/apache/dubbo/remoting/Channel.removeAttribute:(Ljava/lang/String;)V
     420: aload_1
     421: aload         8
     423: invokeinterface #104,  2          // InterfaceMethod org/apache/dubbo/remoting/Channel.removeAttribute:(Ljava/lang/String;)V
     428: aload_1
     429: aload         10
     431: invokestatic  #105                // Method decreaseInstanceCount:(Lorg/apache/dubbo/remoting/Channel;Ljava/lang/String;)V
     434: aload         7
     436: areturn
    Exception table:
       from    to  target type
         351   386   389   Class java/lang/Exception

  private static java.lang.String getClientSideCallbackServiceCacheKey(int);
    Code:
       0: new           #20                 // class java/lang/StringBuilder
       3: dup
       4: invokespecial #21                 // Method java/lang/StringBuilder."<init>":()V
       7: ldc           #140                // String callback.service.instid.
       9: invokevirtual #22                 // Method java/lang/StringBuilder.append:(Ljava/lang/String;)Ljava/lang/StringBuilder;
      12: iload_0
      13: invokevirtual #24                 // Method java/lang/StringBuilder.append:(I)Ljava/lang/StringBuilder;
      16: invokevirtual #26                 // Method java/lang/StringBuilder.toString:()Ljava/lang/String;
      19: areturn

  private static java.lang.String getServerSideCallbackServiceCacheKey(org.apache.dubbo.remoting.Channel, java.lang.String, int);
    Code:
       0: new           #20                 // class java/lang/StringBuilder
       3: dup
       4: invokespecial #21                 // Method java/lang/StringBuilder."<init>":()V
       7: ldc           #141                // String callback.service.proxy.
       9: invokevirtual #22                 // Method java/lang/StringBuilder.append:(Ljava/lang/String;)Ljava/lang/StringBuilder;
      12: aload_0
      13: invokestatic  #31                 // Method java/lang/System.identityHashCode:(Ljava/lang/Object;)I
      16: invokevirtual #24                 // Method java/lang/StringBuilder.append:(I)Ljava/lang/StringBuilder;
      19: ldc           #23                 // String .
      21: invokevirtual #22                 // Method java/lang/StringBuilder.append:(Ljava/lang/String;)Ljava/lang/StringBuilder;
      24: aload_1
      25: invokevirtual #22                 // Method java/lang/StringBuilder.append:(Ljava/lang/String;)Ljava/lang/StringBuilder;
      28: ldc           #23                 // String .
      30: invokevirtual #22                 // Method java/lang/StringBuilder.append:(Ljava/lang/String;)Ljava/lang/StringBuilder;
      33: iload_2
      34: invokevirtual #24                 // Method java/lang/StringBuilder.append:(I)Ljava/lang/StringBuilder;
      37: invokevirtual #26                 // Method java/lang/StringBuilder.toString:()Ljava/lang/String;
      40: areturn

  private static java.lang.String getServerSideCallbackInvokerCacheKey(org.apache.dubbo.remoting.Channel, java.lang.String, int);
    Code:
       0: new           #20                 // class java/lang/StringBuilder
       3: dup
       4: invokespecial #21                 // Method java/lang/StringBuilder."<init>":()V
       7: aload_0
       8: aload_1
       9: iload_2
      10: invokestatic  #108                // Method getServerSideCallbackServiceCacheKey:(Lorg/apache/dubbo/remoting/Channel;Ljava/lang/String;I)Ljava/lang/String;
      13: invokevirtual #22                 // Method java/lang/StringBuilder.append:(Ljava/lang/String;)Ljava/lang/StringBuilder;
      16: ldc           #142                // String .invoker
      18: invokevirtual #22                 // Method java/lang/StringBuilder.append:(Ljava/lang/String;)Ljava/lang/StringBuilder;
      21: invokevirtual #26                 // Method java/lang/StringBuilder.toString:()Ljava/lang/String;
      24: areturn

  private static java.lang.String getClientSideCountKey(java.lang.String);
    Code:
       0: new           #20                 // class java/lang/StringBuilder
       3: dup
       4: invokespecial #21                 // Method java/lang/StringBuilder."<init>":()V
       7: ldc           #140                // String callback.service.instid.
       9: invokevirtual #22                 // Method java/lang/StringBuilder.append:(Ljava/lang/String;)Ljava/lang/StringBuilder;
      12: aload_0
      13: invokevirtual #22                 // Method java/lang/StringBuilder.append:(Ljava/lang/String;)Ljava/lang/StringBuilder;
      16: ldc           #143                // String .COUNT
      18: invokevirtual #22                 // Method java/lang/StringBuilder.append:(Ljava/lang/String;)Ljava/lang/StringBuilder;
      21: invokevirtual #26                 // Method java/lang/StringBuilder.toString:()Ljava/lang/String;
      24: areturn

  private static java.lang.String getServerSideCountKey(org.apache.dubbo.remoting.Channel, java.lang.String);
    Code:
       0: new           #20                 // class java/lang/StringBuilder
       3: dup
       4: invokespecial #21                 // Method java/lang/StringBuilder."<init>":()V
       7: ldc           #141                // String callback.service.proxy.
       9: invokevirtual #22                 // Method java/lang/StringBuilder.append:(Ljava/lang/String;)Ljava/lang/StringBuilder;
      12: aload_0
      13: invokestatic  #31                 // Method java/lang/System.identityHashCode:(Ljava/lang/Object;)I
      16: invokevirtual #24                 // Method java/lang/StringBuilder.append:(I)Ljava/lang/StringBuilder;
      19: ldc           #23                 // String .
      21: invokevirtual #22                 // Method java/lang/StringBuilder.append:(Ljava/lang/String;)Ljava/lang/StringBuilder;
      24: aload_1
      25: invokevirtual #22                 // Method java/lang/StringBuilder.append:(Ljava/lang/String;)Ljava/lang/StringBuilder;
      28: ldc           #143                // String .COUNT
      30: invokevirtual #22                 // Method java/lang/StringBuilder.append:(Ljava/lang/String;)Ljava/lang/StringBuilder;
      33: invokevirtual #26                 // Method java/lang/StringBuilder.toString:()Ljava/lang/String;
      36: areturn

  private static boolean isInstancesOverLimit(org.apache.dubbo.remoting.Channel, org.apache.dubbo.common.URL, java.lang.String, int, boolean);
    Code:
       0: aload_0
       1: iload         4
       3: ifeq          14
       6: aload_0
       7: aload_2
       8: invokestatic  #109                // Method getServerSideCountKey:(Lorg/apache/dubbo/remoting/Channel;Ljava/lang/String;)Ljava/lang/String;
      11: goto          18
      14: aload_2
      15: invokestatic  #65                 // Method getClientSideCountKey:(Ljava/lang/String;)Ljava/lang/String;
      18: invokeinterface #101,  2          // InterfaceMethod org/apache/dubbo/remoting/Channel.getAttribute:(Ljava/lang/String;)Ljava/lang/Object;
      23: checkcast     #144                // class java/lang/Integer
      26: astore        5
      28: aload_1
      29: ldc           #145                // String callbacks
      31: iconst_1
      32: invokevirtual #146                // Method org/apache/dubbo/common/URL.getParameter:(Ljava/lang/String;I)I
      35: istore        6
      37: aload         5
      39: ifnull        113
      42: aload         5
      44: invokevirtual #147                // Method java/lang/Integer.intValue:()I
      47: iload         6
      49: if_icmplt     113
      52: new           #148                // class java/lang/IllegalStateException
      55: dup
      56: new           #20                 // class java/lang/StringBuilder
      59: dup
      60: invokespecial #21                 // Method java/lang/StringBuilder."<init>":()V
      63: ldc           #149                // String interface
      65: invokevirtual #22                 // Method java/lang/StringBuilder.append:(Ljava/lang/String;)Ljava/lang/StringBuilder;
      68: aload_2
      69: invokevirtual #22                 // Method java/lang/StringBuilder.append:(Ljava/lang/String;)Ljava/lang/StringBuilder;
      72: ldc           #150                // String  `s callback instances num exceed providers limit :
      74: invokevirtual #22                 // Method java/lang/StringBuilder.append:(Ljava/lang/String;)Ljava/lang/StringBuilder;
      77: iload         6
      79: invokevirtual #24                 // Method java/lang/StringBuilder.append:(I)Ljava/lang/StringBuilder;
      82: ldc           #151                // String  ,current num:
      84: invokevirtual #22                 // Method java/lang/StringBuilder.append:(Ljava/lang/String;)Ljava/lang/StringBuilder;
      87: aload         5
      89: invokevirtual #147                // Method java/lang/Integer.intValue:()I
      92: iconst_1
      93: iadd
      94: invokevirtual #24                 // Method java/lang/StringBuilder.append:(I)Ljava/lang/StringBuilder;
      97: ldc           #152                // String . The new callback service will not work !!! you can cancle the callback service which exported before. channel :
      99: invokevirtual #22                 // Method java/lang/StringBuilder.append:(Ljava/lang/String;)Ljava/lang/StringBuilder;
     102: aload_0
     103: invokevirtual #76                 // Method java/lang/StringBuilder.append:(Ljava/lang/Object;)Ljava/lang/StringBuilder;
     106: invokevirtual #26                 // Method java/lang/StringBuilder.toString:()Ljava/lang/String;
     109: invokespecial #153                // Method java/lang/IllegalStateException."<init>":(Ljava/lang/String;)V
     112: athrow
     113: iconst_0
     114: ireturn

  private static void increaseInstanceCount(org.apache.dubbo.remoting.Channel, java.lang.String);
    Code:
       0: aload_0
       1: aload_1
       2: invokeinterface #101,  2          // InterfaceMethod org/apache/dubbo/remoting/Channel.getAttribute:(Ljava/lang/String;)Ljava/lang/Object;
       7: checkcast     #144                // class java/lang/Integer
      10: astore_2
      11: aload_2
      12: ifnonnull     23
      15: iconst_1
      16: invokestatic  #154                // Method java/lang/Integer.valueOf:(I)Ljava/lang/Integer;
      19: astore_2
      20: goto          40
      23: aload_2
      24: astore_3
      25: aload_2
      26: invokevirtual #147                // Method java/lang/Integer.intValue:()I
      29: iconst_1
      30: iadd
      31: invokestatic  #154                // Method java/lang/Integer.valueOf:(I)Ljava/lang/Integer;
      34: dup
      35: astore_2
      36: astore        4
      38: aload_3
      39: pop
      40: aload_0
      41: aload_1
      42: aload_2
      43: invokeinterface #95,  3           // InterfaceMethod org/apache/dubbo/remoting/Channel.setAttribute:(Ljava/lang/String;Ljava/lang/Object;)V
      48: goto          71
      51: astore_2
      52: getstatic     #72                 // Field logger:Lorg/apache/dubbo/common/logger/ErrorTypeAwareLogger;
      55: ldc           #155                // String 0-2
      57: ldc           #74                 // String
      59: ldc           #74                 // String
      61: aload_2
      62: invokevirtual #138                // Method java/lang/Exception.getMessage:()Ljava/lang/String;
      65: aload_2
      66: invokeinterface #139,  6          // InterfaceMethod org/apache/dubbo/common/logger/ErrorTypeAwareLogger.error:(Ljava/lang/String;Ljava/lang/String;Ljava/lang/String;Ljava/lang/String;Ljava/lang/Throwable;)V
      71: return
    Exception table:
       from    to  target type
           0    48    51   Class java/lang/Exception

  private static void decreaseInstanceCount(org.apache.dubbo.remoting.Channel, java.lang.String);
    Code:
       0: aload_0
       1: aload_1
       2: invokeinterface #101,  2          // InterfaceMethod org/apache/dubbo/remoting/Channel.getAttribute:(Ljava/lang/String;)Ljava/lang/Object;
       7: checkcast     #144                // class java/lang/Integer
      10: astore_2
      11: aload_2
      12: ifnull        22
      15: aload_2
      16: invokevirtual #147                // Method java/lang/Integer.intValue:()I
      19: ifgt          23
      22: return
      23: aload_2
      24: astore_3
      25: aload_2
      26: invokevirtual #147                // Method java/lang/Integer.intValue:()I
      29: iconst_1
      30: isub
      31: invokestatic  #154                // Method java/lang/Integer.valueOf:(I)Ljava/lang/Integer;
      34: dup
      35: astore_2
      36: astore        4
      38: aload_3
      39: pop
      40: aload_0
      41: aload_1
      42: aload_2
      43: invokeinterface #95,  3           // InterfaceMethod org/apache/dubbo/remoting/Channel.setAttribute:(Ljava/lang/String;Ljava/lang/Object;)V
      48: goto          71
      51: astore_2
      52: getstatic     #72                 // Field logger:Lorg/apache/dubbo/common/logger/ErrorTypeAwareLogger;
      55: ldc           #155                // String 0-2
      57: ldc           #74                 // String
      59: ldc           #74                 // String
      61: aload_2
      62: invokevirtual #138                // Method java/lang/Exception.getMessage:()Ljava/lang/String;
      65: aload_2
      66: invokeinterface #139,  6          // InterfaceMethod org/apache/dubbo/common/logger/ErrorTypeAwareLogger.error:(Ljava/lang/String;Ljava/lang/String;Ljava/lang/String;Ljava/lang/String;Ljava/lang/Throwable;)V
      71: return
    Exception table:
       from    to  target type
           0    22    51   Class java/lang/Exception
          23    48    51   Class java/lang/Exception

  public java.lang.Object encodeInvocationArgument(org.apache.dubbo.remoting.Channel, org.apache.dubbo.rpc.RpcInvocation, int) throws java.io.IOException;
    Code:
       0: aload_2
       1: invokevirtual #156                // Method org/apache/dubbo/rpc/RpcInvocation.getInvoker:()Lorg/apache/dubbo/rpc/Invoker;
       4: ifnonnull     11
       7: aconst_null
       8: goto          20
      11: aload_2
      12: invokevirtual #156                // Method org/apache/dubbo/rpc/RpcInvocation.getInvoker:()Lorg/apache/dubbo/rpc/Invoker;
      15: invokeinterface #130,  1          // InterfaceMethod org/apache/dubbo/rpc/Invoker.getUrl:()Lorg/apache/dubbo/common/URL;
      20: astore        4
      22: aload         4
      24: aload_2
      25: invokevirtual #157                // Method org/apache/dubbo/rpc/RpcInvocation.getProtocolServiceKey:()Ljava/lang/String;
      28: aload_2
      29: invokevirtual #158                // Method org/apache/dubbo/rpc/RpcInvocation.getMethodName:()Ljava/lang/String;
      32: iload_3
      33: invokestatic  #159                // Method isCallBack:(Lorg/apache/dubbo/common/URL;Ljava/lang/String;Ljava/lang/String;I)B
      36: istore        5
      38: aload_2
      39: invokevirtual #160                // Method org/apache/dubbo/rpc/RpcInvocation.getArguments:()[Ljava/lang/Object;
      42: astore        6
      44: aload_2
      45: invokevirtual #161                // Method org/apache/dubbo/rpc/RpcInvocation.getParameterTypes:()[Ljava/lang/Class;
      48: astore        7
      50: iload         5
      52: lookupswitch  { // 2
                     1: 80
                     2: 125
               default: 170
          }
      80: aload_2
      81: new           #20                 // class java/lang/StringBuilder
      84: dup
      85: invokespecial #21                 // Method java/lang/StringBuilder."<init>":()V
      88: ldc           #162                // String sys_callback_arg-
      90: invokevirtual #22                 // Method java/lang/StringBuilder.append:(Ljava/lang/String;)Ljava/lang/StringBuilder;
      93: iload_3
      94: invokevirtual #24                 // Method java/lang/StringBuilder.append:(I)Ljava/lang/StringBuilder;
      97: invokevirtual #26                 // Method java/lang/StringBuilder.toString:()Ljava/lang/String;
     100: aload_0
     101: aload_1
     102: aload_2
     103: aload         4
     105: aload         7
     107: iload_3
     108: aaload
     109: aload         6
     111: iload_3
     112: aaload
     113: iconst_1
     114: invokestatic  #163                // Method java/lang/Boolean.valueOf:(Z)Ljava/lang/Boolean;
     117: invokespecial #164                // Method exportOrUnexportCallbackService:(Lorg/apache/dubbo/remoting/Channel;Lorg/apache/dubbo/rpc/RpcInvocation;Lorg/apache/dubbo/common/URL;Ljava/lang/Class;Ljava/lang/Object;Ljava/lang/Boolean;)Ljava/lang/String;
     120: invokevirtual #165                // Method org/apache/dubbo/rpc/RpcInvocation.setAttachment:(Ljava/lang/String;Ljava/lang/String;)V
     123: aconst_null
     124: areturn
     125: aload_2
     126: new           #20                 // class java/lang/StringBuilder
     129: dup
     130: invokespecial #21                 // Method java/lang/StringBuilder."<init>":()V
     133: ldc           #162                // String sys_callback_arg-
     135: invokevirtual #22                 // Method java/lang/StringBuilder.append:(Ljava/lang/String;)Ljava/lang/StringBuilder;
     138: iload_3
     139: invokevirtual #24                 // Method java/lang/StringBuilder.append:(I)Ljava/lang/StringBuilder;
     142: invokevirtual #26                 // Method java/lang/StringBuilder.toString:()Ljava/lang/String;
     145: aload_0
     146: aload_1
     147: aload_2
     148: aload         4
     150: aload         7
     152: iload_3
     153: aaload
     154: aload         6
     156: iload_3
     157: aaload
     158: iconst_0
     159: invokestatic  #163                // Method java/lang/Boolean.valueOf:(Z)Ljava/lang/Boolean;
     162: invokespecial #164                // Method exportOrUnexportCallbackService:(Lorg/apache/dubbo/remoting/Channel;Lorg/apache/dubbo/rpc/RpcInvocation;Lorg/apache/dubbo/common/URL;Ljava/lang/Class;Ljava/lang/Object;Ljava/lang/Boolean;)Ljava/lang/String;
     165: invokevirtual #165                // Method org/apache/dubbo/rpc/RpcInvocation.setAttachment:(Ljava/lang/String;Ljava/lang/String;)V
     168: aconst_null
     169: areturn
     170: aload         6
     172: iload_3
     173: aaload
     174: areturn

  public java.lang.Object decodeInvocationArgument(org.apache.dubbo.remoting.Channel, org.apache.dubbo.rpc.RpcInvocation, java.lang.Class<?>[], int, java.lang.Object) throws java.io.IOException;
    Code:
       0: aconst_null
       1: astore        6
       3: aload_0
       4: getfield      #17                 // Field dubboProtocol:Lorg/apache/dubbo/rpc/protocol/dubbo/DubboProtocol;
       7: aload_1
       8: aload_2
       9: invokevirtual #166                // Method org/apache/dubbo/rpc/protocol/dubbo/DubboProtocol.getInvoker:(Lorg/apache/dubbo/remoting/Channel;Lorg/apache/dubbo/rpc/Invocation;)Lorg/apache/dubbo/rpc/Invoker;
      12: invokeinterface #130,  1          // InterfaceMethod org/apache/dubbo/rpc/Invoker.getUrl:()Lorg/apache/dubbo/common/URL;
      17: astore        6
      19: goto          53
      22: astore        7
      24: getstatic     #72                 // Field logger:Lorg/apache/dubbo/common/logger/ErrorTypeAwareLogger;
      27: invokeinterface #168,  1          // InterfaceMethod org/apache/dubbo/common/logger/ErrorTypeAwareLogger.isInfoEnabled:()Z
      32: ifeq          50
      35: getstatic     #72                 // Field logger:Lorg/apache/dubbo/common/logger/ErrorTypeAwareLogger;
      38: aload         7
      40: invokevirtual #169                // Method org/apache/dubbo/remoting/RemotingException.getMessage:()Ljava/lang/String;
      43: aload         7
      45: invokeinterface #170,  3          // InterfaceMethod org/apache/dubbo/common/logger/ErrorTypeAwareLogger.info:(Ljava/lang/String;Ljava/lang/Throwable;)V
      50: aload         5
      52: areturn
      53: aload         6
      55: aload_2
      56: invokevirtual #157                // Method org/apache/dubbo/rpc/RpcInvocation.getProtocolServiceKey:()Ljava/lang/String;
      59: aload_2
      60: invokevirtual #158                // Method org/apache/dubbo/rpc/RpcInvocation.getMethodName:()Ljava/lang/String;
      63: iload         4
      65: invokestatic  #159                // Method isCallBack:(Lorg/apache/dubbo/common/URL;Ljava/lang/String;Ljava/lang/String;I)B
      68: istore        7
      70: iload         7
      72: lookupswitch  { // 2
                     1: 100
                     2: 177
               default: 233
          }
     100: aload_0
     101: aload_1
     102: aload         6
     104: aload_3
     105: iload         4
     107: aaload
     108: aload_2
     109: aload_2
     110: new           #20                 // class java/lang/StringBuilder
     113: dup
     114: invokespecial #21                 // Method java/lang/StringBuilder."<init>":()V
     117: ldc           #162                // String sys_callback_arg-
     119: invokevirtual #22                 // Method java/lang/StringBuilder.append:(Ljava/lang/String;)Ljava/lang/StringBuilder;
     122: iload         4
     124: invokevirtual #24                 // Method java/lang/StringBuilder.append:(I)Ljava/lang/StringBuilder;
     127: invokevirtual #26                 // Method java/lang/StringBuilder.toString:()Ljava/lang/String;
     130: invokevirtual #171                // Method org/apache/dubbo/rpc/RpcInvocation.getAttachment:(Ljava/lang/String;)Ljava/lang/String;
     133: invokestatic  #172                // Method java/lang/Integer.parseInt:(Ljava/lang/String;)I
     136: iconst_1
     137: invokespecial #173                // Method referOrDestroyCallbackService:(Lorg/apache/dubbo/remoting/Channel;Lorg/apache/dubbo/common/URL;Ljava/lang/Class;Lorg/apache/dubbo/rpc/Invocation;IZ)Ljava/lang/Object;
     140: areturn
     141: astore        8
     143: getstatic     #72                 // Field logger:Lorg/apache/dubbo/common/logger/ErrorTypeAwareLogger;
     146: ldc           #137                // String 4-17
     148: ldc           #74                 // String
     150: ldc           #74                 // String
     152: aload         8
     154: invokevirtual #138                // Method java/lang/Exception.getMessage:()Ljava/lang/String;
     157: aload         8
     159: invokeinterface #139,  6          // InterfaceMethod org/apache/dubbo/common/logger/ErrorTypeAwareLogger.error:(Ljava/lang/String;Ljava/lang/String;Ljava/lang/String;Ljava/lang/String;Ljava/lang/Throwable;)V
     164: new           #174                // class java/io/IOException
     167: dup
     168: aload         8
     170: invokestatic  #175                // Method org/apache/dubbo/common/utils/StringUtils.toString:(Ljava/lang/Throwable;)Ljava/lang/String;
     173: invokespecial #176                // Method java/io/IOException."<init>":(Ljava/lang/String;)V
     176: athrow
     177: aload_0
     178: aload_1
     179: aload         6
     181: aload_3
     182: iload         4
     184: aaload
     185: aload_2
     186: aload_2
     187: new           #20                 // class java/lang/StringBuilder
     190: dup
     191: invokespecial #21                 // Method java/lang/StringBuilder."<init>":()V
     194: ldc           #162                // String sys_callback_arg-
     196: invokevirtual #22                 // Method java/lang/StringBuilder.append:(Ljava/lang/String;)Ljava/lang/StringBuilder;
     199: iload         4
     201: invokevirtual #24                 // Method java/lang/StringBuilder.append:(I)Ljava/lang/StringBuilder;
     204: invokevirtual #26                 // Method java/lang/StringBuilder.toString:()Ljava/lang/String;
     207: invokevirtual #171                // Method org/apache/dubbo/rpc/RpcInvocation.getAttachment:(Ljava/lang/String;)Ljava/lang/String;
     210: invokestatic  #172                // Method java/lang/Integer.parseInt:(Ljava/lang/String;)I
     213: iconst_0
     214: invokespecial #173                // Method referOrDestroyCallbackService:(Lorg/apache/dubbo/remoting/Channel;Lorg/apache/dubbo/common/URL;Ljava/lang/Class;Lorg/apache/dubbo/rpc/Invocation;IZ)Ljava/lang/Object;
     217: areturn
     218: astore        8
     220: new           #174                // class java/io/IOException
     223: dup
     224: aload         8
     226: invokestatic  #175                // Method org/apache/dubbo/common/utils/StringUtils.toString:(Ljava/lang/Throwable;)Ljava/lang/String;
     229: invokespecial #176                // Method java/io/IOException."<init>":(Ljava/lang/String;)V
     232: athrow
     233: aload         5
     235: areturn
    Exception table:
       from    to  target type
           3    19    22   Class org/apache/dubbo/remoting/RemotingException
         100   140   141   Class java/lang/Exception
         177   217   218   Class java/lang/Exception

  static {};
    Code:
       0: ldc           #18                 // class org/apache/dubbo/rpc/protocol/dubbo/CallbackServiceCodec
       2: invokestatic  #177                // Method org/apache/dubbo/common/logger/LoggerFactory.getErrorTypeAwareLogger:(Ljava/lang/Class;)Lorg/apache/dubbo/common/logger/ErrorTypeAwareLogger;
       5: putstatic     #72                 // Field logger:Lorg/apache/dubbo/common/logger/ErrorTypeAwareLogger;
       8: return
}
