Compiled from "ChannelWrappedInvoker.java"
class org.apache.dubbo.rpc.protocol.dubbo.ChannelWrappedInvoker<T> extends org.apache.dubbo.rpc.protocol.AbstractInvoker<T> {
  private final org.apache.dubbo.remoting.Channel channel;

  private final java.lang.String serviceKey;

  private final org.apache.dubbo.remoting.exchange.ExchangeClient currentClient;

  org.apache.dubbo.rpc.protocol.dubbo.ChannelWrappedInvoker(java.lang.Class<T>, org.apache.dubbo.remoting.Channel, org.apache.dubbo.common.URL, java.lang.String);
    Code:
       0: aload_0
       1: aload_1
       2: aload_3
       3: iconst_2
       4: anewarray     #5                  // class java/lang/String
       7: dup
       8: iconst_0
       9: ldc           #6                  // String group
      11: aastore
      12: dup
      13: iconst_1
      14: ldc           #7                  // String token
      16: aastore
      17: invokespecial #8                  // Method org/apache/dubbo/rpc/protocol/AbstractInvoker."<init>":(Ljava/lang/Class;Lorg/apache/dubbo/common/URL;[Ljava/lang/String;)V
      20: aload_0
      21: aload_2
      22: putfield      #9                  // Field channel:Lorg/apache/dubbo/remoting/Channel;
      25: aload_0
      26: aload         4
      28: putfield      #10                 // Field serviceKey:Ljava/lang/String;
      31: aload_0
      32: new           #11                 // class org/apache/dubbo/remoting/exchange/support/header/HeaderExchangeClient
      35: dup
      36: new           #12                 // class org/apache/dubbo/rpc/protocol/dubbo/ChannelWrappedInvoker$ChannelWrapper
      39: dup
      40: aload_0
      41: getfield      #9                  // Field channel:Lorg/apache/dubbo/remoting/Channel;
      44: invokespecial #13                 // Method org/apache/dubbo/rpc/protocol/dubbo/ChannelWrappedInvoker$ChannelWrapper."<init>":(Lorg/apache/dubbo/remoting/Channel;)V
      47: iconst_0
      48: invokespecial #14                 // Method org/apache/dubbo/remoting/exchange/support/header/HeaderExchangeClient."<init>":(Lorg/apache/dubbo/remoting/Client;Z)V
      51: putfield      #15                 // Field currentClient:Lorg/apache/dubbo/remoting/exchange/ExchangeClient;
      54: return

  protected org.apache.dubbo.rpc.Result doInvoke(org.apache.dubbo.rpc.Invocation) throws java.lang.Throwable;
    Code:
       0: aload_1
       1: checkcast     #16                 // class org/apache/dubbo/rpc/RpcInvocation
       4: astore_2
       5: aload_2
       6: ldc           #17                 // String path
       8: aload_0
       9: invokevirtual #18                 // Method getInterface:()Ljava/lang/Class;
      12: invokevirtual #19                 // Method java/lang/Class.getName:()Ljava/lang/String;
      15: invokevirtual #20                 // Method org/apache/dubbo/rpc/RpcInvocation.setAttachment:(Ljava/lang/String;Ljava/lang/String;)V
      18: aload_2
      19: ldc           #21                 // String callback.service.instid
      21: aload_0
      22: getfield      #10                 // Field serviceKey:Ljava/lang/String;
      25: invokevirtual #20                 // Method org/apache/dubbo/rpc/RpcInvocation.setAttachment:(Ljava/lang/String;Ljava/lang/String;)V
      28: aload_0
      29: invokevirtual #22                 // Method getUrl:()Lorg/apache/dubbo/common/URL;
      32: ldc           #23                 // String payload
      34: ldc           #24                 // class java/lang/Integer
      36: invokevirtual #25                 // Method org/apache/dubbo/common/URL.getParameter:(Ljava/lang/String;Ljava/lang/Class;)Ljava/lang/Object;
      39: checkcast     #24                 // class java/lang/Integer
      42: astore_3
      43: new           #26                 // class org/apache/dubbo/remoting/exchange/Request
      46: dup
      47: invokespecial #27                 // Method org/apache/dubbo/remoting/exchange/Request."<init>":()V
      50: astore        4
      52: aload_3
      53: ifnull        65
      56: aload         4
      58: aload_3
      59: invokevirtual #28                 // Method java/lang/Integer.intValue:()I
      62: invokevirtual #29                 // Method org/apache/dubbo/remoting/exchange/Request.setPayload:(I)V
      65: aload         4
      67: aload_2
      68: invokevirtual #30                 // Method org/apache/dubbo/remoting/exchange/Request.setData:(Ljava/lang/Object;)V
      71: aload         4
      73: invokestatic  #31                 // Method org/apache/dubbo/common/Version.getProtocolVersion:()Ljava/lang/String;
      76: invokevirtual #32                 // Method org/apache/dubbo/remoting/exchange/Request.setVersion:(Ljava/lang/String;)V
      79: aload_0
      80: invokevirtual #22                 // Method getUrl:()Lorg/apache/dubbo/common/URL;
      83: aload_2
      84: invokestatic  #33                 // Method org/apache/dubbo/rpc/support/RpcUtils.isOneway:(Lorg/apache/dubbo/common/URL;Lorg/apache/dubbo/rpc/Invocation;)Z
      87: ifeq          122
      90: aload_0
      91: getfield      #15                 // Field currentClient:Lorg/apache/dubbo/remoting/exchange/ExchangeClient;
      94: aload         4
      96: aload_0
      97: invokevirtual #22                 // Method getUrl:()Lorg/apache/dubbo/common/URL;
     100: aload_1
     101: invokeinterface #34,  1           // InterfaceMethod org/apache/dubbo/rpc/Invocation.getMethodName:()Ljava/lang/String;
     106: ldc           #35                 // String sent
     108: iconst_0
     109: invokevirtual #36                 // Method org/apache/dubbo/common/URL.getMethodParameter:(Ljava/lang/String;Ljava/lang/String;Z)Z
     112: invokeinterface #37,  3           // InterfaceMethod org/apache/dubbo/remoting/exchange/ExchangeClient.send:(Ljava/lang/Object;Z)V
     117: aload_1
     118: invokestatic  #38                 // Method org/apache/dubbo/rpc/AsyncRpcResult.newDefaultAsyncResult:(Lorg/apache/dubbo/rpc/Invocation;)Lorg/apache/dubbo/rpc/AsyncRpcResult;
     121: areturn
     122: aload_0
     123: getfield      #15                 // Field currentClient:Lorg/apache/dubbo/remoting/exchange/ExchangeClient;
     126: aload         4
     128: invokeinterface #39,  2           // InterfaceMethod org/apache/dubbo/remoting/exchange/ExchangeClient.request:(Ljava/lang/Object;)Ljava/util/concurrent/CompletableFuture;
     133: ldc           #40                 // class org/apache/dubbo/rpc/AppResponse
     135: dup
     136: invokevirtual #41                 // Method java/lang/Object.getClass:()Ljava/lang/Class;
     139: pop
     140: invokedynamic #42,  0             // InvokeDynamic #0:apply:(Ljava/lang/Class;)Ljava/util/function/Function;
     145: invokevirtual #43                 // Method java/util/concurrent/CompletableFuture.thenApply:(Ljava/util/function/Function;)Ljava/util/concurrent/CompletableFuture;
     148: astore        5
     150: new           #44                 // class org/apache/dubbo/rpc/AsyncRpcResult
     153: dup
     154: aload         5
     156: aload_2
     157: invokespecial #45                 // Method org/apache/dubbo/rpc/AsyncRpcResult."<init>":(Ljava/util/concurrent/CompletableFuture;Lorg/apache/dubbo/rpc/Invocation;)V
     160: areturn
     161: astore        5
     163: aload         5
     165: athrow
     166: astore        5
     168: new           #46                 // class org/apache/dubbo/rpc/RpcException
     171: dup
     172: iconst_2
     173: aload         5
     175: invokevirtual #48                 // Method org/apache/dubbo/remoting/TimeoutException.getMessage:()Ljava/lang/String;
     178: aload         5
     180: invokespecial #49                 // Method org/apache/dubbo/rpc/RpcException."<init>":(ILjava/lang/String;Ljava/lang/Throwable;)V
     183: athrow
     184: astore        5
     186: new           #46                 // class org/apache/dubbo/rpc/RpcException
     189: dup
     190: iconst_1
     191: aload         5
     193: invokevirtual #51                 // Method org/apache/dubbo/remoting/RemotingException.getMessage:()Ljava/lang/String;
     196: aload         5
     198: invokespecial #49                 // Method org/apache/dubbo/rpc/RpcException."<init>":(ILjava/lang/String;Ljava/lang/Throwable;)V
     201: athrow
     202: astore        5
     204: new           #46                 // class org/apache/dubbo/rpc/RpcException
     207: dup
     208: aload         5
     210: invokevirtual #53                 // Method java/lang/Throwable.getMessage:()Ljava/lang/String;
     213: aload         5
     215: invokespecial #54                 // Method org/apache/dubbo/rpc/RpcException."<init>":(Ljava/lang/String;Ljava/lang/Throwable;)V
     218: athrow
    Exception table:
       from    to  target type
          79   121   161   Class org/apache/dubbo/rpc/RpcException
         122   160   161   Class org/apache/dubbo/rpc/RpcException
          79   121   166   Class org/apache/dubbo/remoting/TimeoutException
         122   160   166   Class org/apache/dubbo/remoting/TimeoutException
          79   121   184   Class org/apache/dubbo/remoting/RemotingException
         122   160   184   Class org/apache/dubbo/remoting/RemotingException
          79   121   202   Class java/lang/Throwable
         122   160   202   Class java/lang/Throwable

  public void destroy();
    Code:
       0: return
}
