Compiled from "ChannelWrappedInvoker.java"
public class org.apache.dubbo.rpc.protocol.dubbo.ChannelWrappedInvoker$ChannelWrapper extends org.apache.dubbo.remoting.transport.ClientDelegate {
  private final org.apache.dubbo.remoting.Channel channel;

  private final org.apache.dubbo.common.URL url;

  org.apache.dubbo.rpc.protocol.dubbo.ChannelWrappedInvoker$ChannelWrapper(org.apache.dubbo.remoting.Channel);
    Code:
       0: aload_0
       1: invokespecial #1                  // Method org/apache/dubbo/remoting/transport/ClientDelegate."<init>":()V
       4: aload_0
       5: aload_1
       6: putfield      #2                  // Field channel:Lorg/apache/dubbo/remoting/Channel;
       9: aload_0
      10: aload_1
      11: invokeinterface #3,  1            // InterfaceMethod org/apache/dubbo/remoting/Channel.getUrl:()Lorg/apache/dubbo/common/URL;
      16: ldc           #4                  // String codec
      18: ldc           #6                  // String dubbo
      20: invokevirtual #7                  // Method org/apache/dubbo/common/URL.addParameter:(Ljava/lang/String;Ljava/lang/String;)Lorg/apache/dubbo/common/URL;
      23: putfield      #8                  // Field url:Lorg/apache/dubbo/common/URL;
      26: return

  public org.apache.dubbo.common.URL getUrl();
    Code:
       0: aload_0
       1: getfield      #8                  // Field url:Lorg/apache/dubbo/common/URL;
       4: areturn

  public org.apache.dubbo.remoting.ChannelHandler getChannelHandler();
    Code:
       0: aload_0
       1: getfield      #2                  // Field channel:Lorg/apache/dubbo/remoting/Channel;
       4: invokeinterface #9,  1            // InterfaceMethod org/apache/dubbo/remoting/Channel.getChannelHandler:()Lorg/apache/dubbo/remoting/ChannelHandler;
       9: areturn

  public java.net.InetSocketAddress getLocalAddress();
    Code:
       0: aload_0
       1: getfield      #2                  // Field channel:Lorg/apache/dubbo/remoting/Channel;
       4: invokeinterface #10,  1           // InterfaceMethod org/apache/dubbo/remoting/Channel.getLocalAddress:()Ljava/net/InetSocketAddress;
       9: areturn

  public void close();
    Code:
       0: aload_0
       1: getfield      #2                  // Field channel:Lorg/apache/dubbo/remoting/Channel;
       4: invokeinterface #11,  1           // InterfaceMethod org/apache/dubbo/remoting/Channel.close:()V
       9: return

  public boolean isClosed();
    Code:
       0: aload_0
       1: getfield      #2                  // Field channel:Lorg/apache/dubbo/remoting/Channel;
       4: ifnull        19
       7: aload_0
       8: getfield      #2                  // Field channel:Lorg/apache/dubbo/remoting/Channel;
      11: invokeinterface #12,  1           // InterfaceMethod org/apache/dubbo/remoting/Channel.isClosed:()Z
      16: ifeq          23
      19: iconst_1
      20: goto          24
      23: iconst_0
      24: ireturn

  public void reset(org.apache.dubbo.common.URL);
    Code:
       0: new           #13                 // class org/apache/dubbo/rpc/RpcException
       3: dup
       4: ldc           #14                 // String ChannelInvoker can not reset.
       6: invokespecial #15                 // Method org/apache/dubbo/rpc/RpcException."<init>":(Ljava/lang/String;)V
       9: athrow

  public java.net.InetSocketAddress getRemoteAddress();
    Code:
       0: aload_0
       1: getfield      #2                  // Field channel:Lorg/apache/dubbo/remoting/Channel;
       4: invokeinterface #16,  1           // InterfaceMethod org/apache/dubbo/remoting/Channel.getRemoteAddress:()Ljava/net/InetSocketAddress;
       9: areturn

  public boolean isConnected();
    Code:
       0: aload_0
       1: getfield      #2                  // Field channel:Lorg/apache/dubbo/remoting/Channel;
       4: ifnull        23
       7: aload_0
       8: getfield      #2                  // Field channel:Lorg/apache/dubbo/remoting/Channel;
      11: invokeinterface #17,  1           // InterfaceMethod org/apache/dubbo/remoting/Channel.isConnected:()Z
      16: ifeq          23
      19: iconst_1
      20: goto          24
      23: iconst_0
      24: ireturn

  public boolean hasAttribute(java.lang.String);
    Code:
       0: aload_0
       1: getfield      #2                  // Field channel:Lorg/apache/dubbo/remoting/Channel;
       4: aload_1
       5: invokeinterface #18,  2           // InterfaceMethod org/apache/dubbo/remoting/Channel.hasAttribute:(Ljava/lang/String;)Z
      10: ireturn

  public java.lang.Object getAttribute(java.lang.String);
    Code:
       0: aload_0
       1: getfield      #2                  // Field channel:Lorg/apache/dubbo/remoting/Channel;
       4: aload_1
       5: invokeinterface #19,  2           // InterfaceMethod org/apache/dubbo/remoting/Channel.getAttribute:(Ljava/lang/String;)Ljava/lang/Object;
      10: areturn

  public void setAttribute(java.lang.String, java.lang.Object);
    Code:
       0: aload_0
       1: getfield      #2                  // Field channel:Lorg/apache/dubbo/remoting/Channel;
       4: aload_1
       5: aload_2
       6: invokeinterface #20,  3           // InterfaceMethod org/apache/dubbo/remoting/Channel.setAttribute:(Ljava/lang/String;Ljava/lang/Object;)V
      11: return

  public void removeAttribute(java.lang.String);
    Code:
       0: aload_0
       1: getfield      #2                  // Field channel:Lorg/apache/dubbo/remoting/Channel;
       4: aload_1
       5: invokeinterface #21,  2           // InterfaceMethod org/apache/dubbo/remoting/Channel.removeAttribute:(Ljava/lang/String;)V
      10: return

  public void reconnect() throws org.apache.dubbo.remoting.RemotingException;
    Code:
       0: return

  public void send(java.lang.Object) throws org.apache.dubbo.remoting.RemotingException;
    Code:
       0: aload_0
       1: getfield      #2                  // Field channel:Lorg/apache/dubbo/remoting/Channel;
       4: aload_1
       5: invokeinterface #22,  2           // InterfaceMethod org/apache/dubbo/remoting/Channel.send:(Ljava/lang/Object;)V
      10: return

  public void send(java.lang.Object, boolean) throws org.apache.dubbo.remoting.RemotingException;
    Code:
       0: aload_0
       1: getfield      #2                  // Field channel:Lorg/apache/dubbo/remoting/Channel;
       4: aload_1
       5: iload_2
       6: invokeinterface #23,  3           // InterfaceMethod org/apache/dubbo/remoting/Channel.send:(Ljava/lang/Object;Z)V
      11: return
}
