Compiled from "DecodeableRpcResult.java"
public class org.apache.dubbo.rpc.protocol.dubbo.DecodeableRpcResult extends org.apache.dubbo.rpc.AppResponse implements org.apache.dubbo.remoting.Codec,org.apache.dubbo.remoting.Decodeable {
  private static final org.apache.dubbo.common.logger.ErrorTypeAwareLogger log;

  private final org.apache.dubbo.remoting.Channel channel;

  private final byte serializationType;

  private final java.io.InputStream inputStream;

  private final org.apache.dubbo.remoting.exchange.Response response;

  private final org.apache.dubbo.rpc.Invocation invocation;

  private volatile boolean hasDecoded;

  public org.apache.dubbo.rpc.protocol.dubbo.DecodeableRpcResult(org.apache.dubbo.remoting.Channel, org.apache.dubbo.remoting.exchange.Response, java.io.InputStream, org.apache.dubbo.rpc.Invocation, byte);
    Code:
       0: aload_0
       1: invokespecial #3                  // Method org/apache/dubbo/rpc/AppResponse."<init>":()V
       4: aload_1
       5: ldc           #4                  // String channel == null
       7: invokestatic  #5                  // Method org/apache/dubbo/common/utils/Assert.notNull:(Ljava/lang/Object;Ljava/lang/String;)V
      10: aload_2
      11: ldc           #6                  // String response == null
      13: invokestatic  #5                  // Method org/apache/dubbo/common/utils/Assert.notNull:(Ljava/lang/Object;Ljava/lang/String;)V
      16: aload_3
      17: ldc           #7                  // String inputStream == null
      19: invokestatic  #5                  // Method org/apache/dubbo/common/utils/Assert.notNull:(Ljava/lang/Object;Ljava/lang/String;)V
      22: aload_0
      23: aload_1
      24: putfield      #8                  // Field channel:Lorg/apache/dubbo/remoting/Channel;
      27: aload_0
      28: aload_2
      29: putfield      #9                  // Field response:Lorg/apache/dubbo/remoting/exchange/Response;
      32: aload_0
      33: aload_3
      34: putfield      #10                 // Field inputStream:Ljava/io/InputStream;
      37: aload_0
      38: aload         4
      40: putfield      #11                 // Field invocation:Lorg/apache/dubbo/rpc/Invocation;
      43: aload_0
      44: iload         5
      46: putfield      #12                 // Field serializationType:B
      49: return

  public void encode(org.apache.dubbo.remoting.Channel, java.io.OutputStream, java.lang.Object) throws java.io.IOException;
    Code:
       0: new           #13                 // class java/lang/UnsupportedOperationException
       3: dup
       4: invokespecial #14                 // Method java/lang/UnsupportedOperationException."<init>":()V
       7: athrow

  public java.lang.Object decode(org.apache.dubbo.remoting.Channel, java.io.InputStream) throws java.io.IOException;
    Code:
       0: getstatic     #15                 // Field log:Lorg/apache/dubbo/common/logger/ErrorTypeAwareLogger;
       3: invokeinterface #16,  1           // InterfaceMethod org/apache/dubbo/common/logger/ErrorTypeAwareLogger.isDebugEnabled:()Z
       8: ifeq          62
      11: invokestatic  #17                 // Method java/lang/Thread.currentThread:()Ljava/lang/Thread;
      14: astore_3
      15: getstatic     #15                 // Field log:Lorg/apache/dubbo/common/logger/ErrorTypeAwareLogger;
      18: new           #18                 // class java/lang/StringBuilder
      21: dup
      22: invokespecial #19                 // Method java/lang/StringBuilder."<init>":()V
      25: ldc           #20                 // String Decoding in thread -- [
      27: invokevirtual #21                 // Method java/lang/StringBuilder.append:(Ljava/lang/String;)Ljava/lang/StringBuilder;
      30: aload_3
      31: invokevirtual #22                 // Method java/lang/Thread.getName:()Ljava/lang/String;
      34: invokevirtual #21                 // Method java/lang/StringBuilder.append:(Ljava/lang/String;)Ljava/lang/StringBuilder;
      37: ldc           #23                 // String #
      39: invokevirtual #21                 // Method java/lang/StringBuilder.append:(Ljava/lang/String;)Ljava/lang/StringBuilder;
      42: aload_3
      43: invokevirtual #24                 // Method java/lang/Thread.getId:()J
      46: invokevirtual #25                 // Method java/lang/StringBuilder.append:(J)Ljava/lang/StringBuilder;
      49: ldc           #26                 // String ]
      51: invokevirtual #21                 // Method java/lang/StringBuilder.append:(Ljava/lang/String;)Ljava/lang/StringBuilder;
      54: invokevirtual #27                 // Method java/lang/StringBuilder.toString:()Ljava/lang/String;
      57: invokeinterface #28,  2           // InterfaceMethod org/apache/dubbo/common/logger/ErrorTypeAwareLogger.debug:(Ljava/lang/String;)V
      62: aload_0
      63: getfield      #11                 // Field invocation:Lorg/apache/dubbo/rpc/Invocation;
      66: ifnull        99
      69: aload_0
      70: getfield      #11                 // Field invocation:Lorg/apache/dubbo/rpc/Invocation;
      73: invokeinterface #29,  1           // InterfaceMethod org/apache/dubbo/rpc/Invocation.getServiceModel:()Lorg/apache/dubbo/rpc/model/ServiceModel;
      78: ifnull        99
      81: invokestatic  #17                 // Method java/lang/Thread.currentThread:()Ljava/lang/Thread;
      84: aload_0
      85: getfield      #11                 // Field invocation:Lorg/apache/dubbo/rpc/Invocation;
      88: invokeinterface #29,  1           // InterfaceMethod org/apache/dubbo/rpc/Invocation.getServiceModel:()Lorg/apache/dubbo/rpc/model/ServiceModel;
      93: invokevirtual #30                 // Method org/apache/dubbo/rpc/model/ServiceModel.getClassLoader:()Ljava/lang/ClassLoader;
      96: invokevirtual #31                 // Method java/lang/Thread.setContextClassLoader:(Ljava/lang/ClassLoader;)V
      99: aload_0
     100: getfield      #12                 // Field serializationType:B
     103: invokestatic  #32                 // Method java/lang/Byte.valueOf:(B)Ljava/lang/Byte;
     106: invokestatic  #33                 // Method org/apache/dubbo/remoting/transport/CodecSupport.getSerialization:(Ljava/lang/Byte;)Lorg/apache/dubbo/common/serialize/Serialization;
     109: aload_1
     110: invokeinterface #34,  1           // InterfaceMethod org/apache/dubbo/remoting/Channel.getUrl:()Lorg/apache/dubbo/common/URL;
     115: aload_2
     116: invokeinterface #35,  3           // InterfaceMethod org/apache/dubbo/common/serialize/Serialization.deserialize:(Lorg/apache/dubbo/common/URL;Ljava/io/InputStream;)Lorg/apache/dubbo/common/serialize/ObjectInput;
     121: astore_3
     122: aload_3
     123: invokeinterface #36,  1           // InterfaceMethod org/apache/dubbo/common/serialize/ObjectInput.readByte:()B
     128: istore        4
     130: iload         4
     132: tableswitch   { // 0 to 5
                     0: 183
                     1: 175
                     2: 172
                     3: 212
                     4: 199
                     5: 191
               default: 225
          }
     172: goto          253
     175: aload_0
     176: aload_3
     177: invokespecial #37                 // Method handleValue:(Lorg/apache/dubbo/common/serialize/ObjectInput;)V
     180: goto          253
     183: aload_0
     184: aload_3
     185: invokespecial #38                 // Method handleException:(Lorg/apache/dubbo/common/serialize/ObjectInput;)V
     188: goto          253
     191: aload_0
     192: aload_3
     193: invokespecial #39                 // Method handleAttachment:(Lorg/apache/dubbo/common/serialize/ObjectInput;)V
     196: goto          253
     199: aload_0
     200: aload_3
     201: invokespecial #37                 // Method handleValue:(Lorg/apache/dubbo/common/serialize/ObjectInput;)V
     204: aload_0
     205: aload_3
     206: invokespecial #39                 // Method handleAttachment:(Lorg/apache/dubbo/common/serialize/ObjectInput;)V
     209: goto          253
     212: aload_0
     213: aload_3
     214: invokespecial #38                 // Method handleException:(Lorg/apache/dubbo/common/serialize/ObjectInput;)V
     217: aload_0
     218: aload_3
     219: invokespecial #39                 // Method handleAttachment:(Lorg/apache/dubbo/common/serialize/ObjectInput;)V
     222: goto          253
     225: new           #40                 // class java/io/IOException
     228: dup
     229: new           #18                 // class java/lang/StringBuilder
     232: dup
     233: invokespecial #19                 // Method java/lang/StringBuilder."<init>":()V
     236: ldc           #41                 // String Unknown result flag, expect \'0\' \'1\' \'2\' \'3\' \'4\' \'5\', but received:
     238: invokevirtual #21                 // Method java/lang/StringBuilder.append:(Ljava/lang/String;)Ljava/lang/StringBuilder;
     241: iload         4
     243: invokevirtual #42                 // Method java/lang/StringBuilder.append:(I)Ljava/lang/StringBuilder;
     246: invokevirtual #27                 // Method java/lang/StringBuilder.toString:()Ljava/lang/String;
     249: invokespecial #43                 // Method java/io/IOException."<init>":(Ljava/lang/String;)V
     252: athrow
     253: aload_3
     254: instanceof    #44                 // class org/apache/dubbo/common/serialize/Cleanable
     257: ifeq          269
     260: aload_3
     261: checkcast     #44                 // class org/apache/dubbo/common/serialize/Cleanable
     264: invokeinterface #45,  1           // InterfaceMethod org/apache/dubbo/common/serialize/Cleanable.cleanup:()V
     269: aload_0
     270: areturn

  public void decode() throws java.lang.Exception;
    Code:
       0: aload_0
       1: getfield      #46                 // Field hasDecoded:Z
       4: ifne          237
       7: aload_0
       8: getfield      #8                  // Field channel:Lorg/apache/dubbo/remoting/Channel;
      11: ifnull        237
      14: aload_0
      15: getfield      #10                 // Field inputStream:Ljava/io/InputStream;
      18: ifnull        237
      21: aload_0
      22: getfield      #11                 // Field invocation:Lorg/apache/dubbo/rpc/Invocation;
      25: ifnull        131
      28: aconst_null
      29: astore_1
      30: aload_0
      31: getfield      #8                  // Field channel:Lorg/apache/dubbo/remoting/Channel;
      34: invokeinterface #34,  1           // InterfaceMethod org/apache/dubbo/remoting/Channel.getUrl:()Lorg/apache/dubbo/common/URL;
      39: invokevirtual #47                 // Method org/apache/dubbo/common/URL.getScopeModel:()Lorg/apache/dubbo/rpc/model/ScopeModel;
      42: invokestatic  #48                 // Method org/apache/dubbo/common/config/ConfigurationUtils.getSystemConfiguration:(Lorg/apache/dubbo/rpc/model/ScopeModel;)Lorg/apache/dubbo/common/config/Configuration;
      45: astore_1
      46: goto          50
      49: astore_2
      50: aload_1
      51: ifnull        66
      54: aload_1
      55: ldc           #50                 // String serialization.security.check
      57: iconst_1
      58: invokeinterface #51,  3           // InterfaceMethod org/apache/dubbo/common/config/Configuration.getBoolean:(Ljava/lang/String;Z)Z
      63: ifeq          131
      66: aload_0
      67: getfield      #11                 // Field invocation:Lorg/apache/dubbo/rpc/Invocation;
      70: ldc           #52                 // String serialization_id
      72: invokeinterface #53,  2           // InterfaceMethod org/apache/dubbo/rpc/Invocation.get:(Ljava/lang/Object;)Ljava/lang/Object;
      77: astore_2
      78: aload_2
      79: ifnull        131
      82: aload_2
      83: checkcast     #54                 // class java/lang/Byte
      86: invokevirtual #55                 // Method java/lang/Byte.byteValue:()B
      89: aload_0
      90: getfield      #12                 // Field serializationType:B
      93: if_icmpeq     131
      96: new           #40                 // class java/io/IOException
      99: dup
     100: new           #18                 // class java/lang/StringBuilder
     103: dup
     104: invokespecial #19                 // Method java/lang/StringBuilder."<init>":()V
     107: ldc           #56                 // String Unexpected serialization id:
     109: invokevirtual #21                 // Method java/lang/StringBuilder.append:(Ljava/lang/String;)Ljava/lang/StringBuilder;
     112: aload_0
     113: getfield      #12                 // Field serializationType:B
     116: invokevirtual #42                 // Method java/lang/StringBuilder.append:(I)Ljava/lang/StringBuilder;
     119: ldc           #57                 // String  received from network, please check if the peer send the right id.
     121: invokevirtual #21                 // Method java/lang/StringBuilder.append:(Ljava/lang/String;)Ljava/lang/StringBuilder;
     124: invokevirtual #27                 // Method java/lang/StringBuilder.toString:()Ljava/lang/String;
     127: invokespecial #43                 // Method java/io/IOException."<init>":(Ljava/lang/String;)V
     130: athrow
     131: aload_0
     132: aload_0
     133: getfield      #8                  // Field channel:Lorg/apache/dubbo/remoting/Channel;
     136: aload_0
     137: getfield      #10                 // Field inputStream:Ljava/io/InputStream;
     140: invokevirtual #58                 // Method decode:(Lorg/apache/dubbo/remoting/Channel;Ljava/io/InputStream;)Ljava/lang/Object;
     143: pop
     144: aload_0
     145: iconst_1
     146: putfield      #46                 // Field hasDecoded:Z
     149: goto          237
     152: astore_1
     153: getstatic     #15                 // Field log:Lorg/apache/dubbo/common/logger/ErrorTypeAwareLogger;
     156: invokeinterface #60,  1           // InterfaceMethod org/apache/dubbo/common/logger/ErrorTypeAwareLogger.isWarnEnabled:()Z
     161: ifeq          201
     164: getstatic     #15                 // Field log:Lorg/apache/dubbo/common/logger/ErrorTypeAwareLogger;
     167: ldc           #61                 // String 4-20
     169: ldc           #62                 // String
     171: ldc           #62                 // String
     173: new           #18                 // class java/lang/StringBuilder
     176: dup
     177: invokespecial #19                 // Method java/lang/StringBuilder."<init>":()V
     180: ldc           #63                 // String Decode rpc result failed:
     182: invokevirtual #21                 // Method java/lang/StringBuilder.append:(Ljava/lang/String;)Ljava/lang/StringBuilder;
     185: aload_1
     186: invokevirtual #64                 // Method java/lang/Throwable.getMessage:()Ljava/lang/String;
     189: invokevirtual #21                 // Method java/lang/StringBuilder.append:(Ljava/lang/String;)Ljava/lang/StringBuilder;
     192: invokevirtual #27                 // Method java/lang/StringBuilder.toString:()Ljava/lang/String;
     195: aload_1
     196: invokeinterface #65,  6           // InterfaceMethod org/apache/dubbo/common/logger/ErrorTypeAwareLogger.warn:(Ljava/lang/String;Ljava/lang/String;Ljava/lang/String;Ljava/lang/String;Ljava/lang/Throwable;)V
     201: aload_0
     202: getfield      #9                  // Field response:Lorg/apache/dubbo/remoting/exchange/Response;
     205: bipush        90
     207: invokevirtual #67                 // Method org/apache/dubbo/remoting/exchange/Response.setStatus:(B)V
     210: aload_0
     211: getfield      #9                  // Field response:Lorg/apache/dubbo/remoting/exchange/Response;
     214: aload_1
     215: invokestatic  #68                 // Method org/apache/dubbo/common/utils/StringUtils.toString:(Ljava/lang/Throwable;)Ljava/lang/String;
     218: invokevirtual #69                 // Method org/apache/dubbo/remoting/exchange/Response.setErrorMessage:(Ljava/lang/String;)V
     221: aload_0
     222: iconst_1
     223: putfield      #46                 // Field hasDecoded:Z
     226: goto          237
     229: astore_3
     230: aload_0
     231: iconst_1
     232: putfield      #46                 // Field hasDecoded:Z
     235: aload_3
     236: athrow
     237: return
    Exception table:
       from    to  target type
          30    46    49   Class java/lang/Exception
          21   144   152   Class java/lang/Throwable
          21   144   229   any
         152   221   229   any

  private void handleValue(org.apache.dubbo.common.serialize.ObjectInput) throws java.io.IOException;
    Code:
       0: aload_0
       1: getfield      #11                 // Field invocation:Lorg/apache/dubbo/rpc/Invocation;
       4: invokestatic  #70                 // Method org/apache/dubbo/rpc/support/RpcUtils.getReturnTypes:(Lorg/apache/dubbo/rpc/Invocation;)[Ljava/lang/reflect/Type;
       7: astore_2
       8: aload_2
       9: invokestatic  #71                 // Method org/apache/dubbo/common/utils/ArrayUtils.isEmpty:([Ljava/lang/Object;)Z
      12: ifeq          25
      15: aload_1
      16: invokeinterface #72,  1           // InterfaceMethod org/apache/dubbo/common/serialize/ObjectInput.readObject:()Ljava/lang/Object;
      21: astore_3
      22: goto          63
      25: aload_2
      26: arraylength
      27: iconst_1
      28: if_icmpne     47
      31: aload_1
      32: aload_2
      33: iconst_0
      34: aaload
      35: checkcast     #73                 // class java/lang/Class
      38: invokeinterface #74,  2           // InterfaceMethod org/apache/dubbo/common/serialize/ObjectInput.readObject:(Ljava/lang/Class;)Ljava/lang/Object;
      43: astore_3
      44: goto          63
      47: aload_1
      48: aload_2
      49: iconst_0
      50: aaload
      51: checkcast     #73                 // class java/lang/Class
      54: aload_2
      55: iconst_1
      56: aaload
      57: invokeinterface #75,  3           // InterfaceMethod org/apache/dubbo/common/serialize/ObjectInput.readObject:(Ljava/lang/Class;Ljava/lang/reflect/Type;)Ljava/lang/Object;
      62: astore_3
      63: aload_0
      64: aload_3
      65: invokevirtual #76                 // Method setValue:(Ljava/lang/Object;)V
      68: goto          77
      71: astore_2
      72: aload_0
      73: aload_2
      74: invokespecial #78                 // Method rethrow:(Ljava/lang/Exception;)V
      77: return
    Exception table:
       from    to  target type
           0    68    71   Class java/lang/ClassNotFoundException

  private void handleException(org.apache.dubbo.common.serialize.ObjectInput) throws java.io.IOException;
    Code:
       0: aload_0
       1: aload_1
       2: invokeinterface #79,  1           // InterfaceMethod org/apache/dubbo/common/serialize/ObjectInput.readThrowable:()Ljava/lang/Throwable;
       7: invokevirtual #80                 // Method setException:(Ljava/lang/Throwable;)V
      10: goto          19
      13: astore_2
      14: aload_0
      15: aload_2
      16: invokespecial #78                 // Method rethrow:(Ljava/lang/Exception;)V
      19: return
    Exception table:
       from    to  target type
           0    10    13   Class java/lang/ClassNotFoundException

  private void handleAttachment(org.apache.dubbo.common.serialize.ObjectInput) throws java.io.IOException;
    Code:
       0: aload_0
       1: aload_1
       2: invokeinterface #81,  1           // InterfaceMethod org/apache/dubbo/common/serialize/ObjectInput.readAttachments:()Ljava/util/Map;
       7: invokevirtual #82                 // Method addObjectAttachments:(Ljava/util/Map;)V
      10: goto          19
      13: astore_2
      14: aload_0
      15: aload_2
      16: invokespecial #78                 // Method rethrow:(Ljava/lang/Exception;)V
      19: return
    Exception table:
       from    to  target type
           0    10    13   Class java/lang/ClassNotFoundException

  private void rethrow(java.lang.Exception) throws java.io.IOException;
    Code:
       0: new           #40                 // class java/io/IOException
       3: dup
       4: ldc           #83                 // String Read response data failed.
       6: aload_1
       7: invokestatic  #84                 // Method org/apache/dubbo/common/utils/StringUtils.toString:(Ljava/lang/String;Ljava/lang/Throwable;)Ljava/lang/String;
      10: invokespecial #43                 // Method java/io/IOException."<init>":(Ljava/lang/String;)V
      13: athrow

  static {};
    Code:
       0: ldc           #85                 // class org/apache/dubbo/rpc/protocol/dubbo/DecodeableRpcResult
       2: invokestatic  #86                 // Method org/apache/dubbo/common/logger/LoggerFactory.getErrorTypeAwareLogger:(Ljava/lang/Class;)Lorg/apache/dubbo/common/logger/ErrorTypeAwareLogger;
       5: putstatic     #15                 // Field log:Lorg/apache/dubbo/common/logger/ErrorTypeAwareLogger;
       8: return
}
