Compiled from "DecodeableRpcInvocation.java"
public class org.apache.dubbo.rpc.protocol.dubbo.DecodeableRpcInvocation extends org.apache.dubbo.rpc.RpcInvocation implements org.apache.dubbo.remoting.Codec,org.apache.dubbo.remoting.Decodeable {
  protected static final org.apache.dubbo.common.logger.ErrorTypeAwareLogger log;

  protected final transient org.apache.dubbo.remoting.Channel channel;

  protected final byte serializationType;

  protected final transient java.io.InputStream inputStream;

  protected final transient org.apache.dubbo.remoting.exchange.Request request;

  protected volatile boolean hasDecoded;

  protected final org.apache.dubbo.rpc.model.FrameworkModel frameworkModel;

  protected final transient java.util.function.Supplier<org.apache.dubbo.rpc.protocol.dubbo.CallbackServiceCodec> callbackServiceCodecFactory;

  private static final boolean CHECK_SERIALIZATION;

  public org.apache.dubbo.rpc.protocol.dubbo.DecodeableRpcInvocation(org.apache.dubbo.rpc.model.FrameworkModel, org.apache.dubbo.remoting.Channel, org.apache.dubbo.remoting.exchange.Request, java.io.InputStream, byte);
    Code:
       0: aload_0
       1: invokespecial #4                  // Method org/apache/dubbo/rpc/RpcInvocation."<init>":()V
       4: aload_0
       5: aload_1
       6: putfield      #5                  // Field frameworkModel:Lorg/apache/dubbo/rpc/model/FrameworkModel;
       9: aload_2
      10: ldc           #6                  // String channel == null
      12: invokestatic  #7                  // Method org/apache/dubbo/common/utils/Assert.notNull:(Ljava/lang/Object;Ljava/lang/String;)V
      15: aload_3
      16: ldc           #8                  // String request == null
      18: invokestatic  #7                  // Method org/apache/dubbo/common/utils/Assert.notNull:(Ljava/lang/Object;Ljava/lang/String;)V
      21: aload         4
      23: ldc           #9                  // String inputStream == null
      25: invokestatic  #7                  // Method org/apache/dubbo/common/utils/Assert.notNull:(Ljava/lang/Object;Ljava/lang/String;)V
      28: aload_0
      29: aload_2
      30: putfield      #10                 // Field channel:Lorg/apache/dubbo/remoting/Channel;
      33: aload_0
      34: aload_3
      35: putfield      #11                 // Field request:Lorg/apache/dubbo/remoting/exchange/Request;
      38: aload_0
      39: aload         4
      41: putfield      #12                 // Field inputStream:Ljava/io/InputStream;
      44: aload_0
      45: iload         5
      47: putfield      #13                 // Field serializationType:B
      50: aload_0
      51: aload_1
      52: invokedynamic #14,  0             // InvokeDynamic #0:get:(Lorg/apache/dubbo/rpc/model/FrameworkModel;)Ljava/util/function/Supplier;
      57: invokestatic  #15                 // Method org/apache/dubbo/common/utils/CacheableSupplier.newSupplier:(Ljava/util/function/Supplier;)Lorg/apache/dubbo/common/utils/CacheableSupplier;
      60: putfield      #16                 // Field callbackServiceCodecFactory:Ljava/util/function/Supplier;
      63: return

  public void decode() throws java.lang.Exception;
    Code:
       0: aload_0
       1: getfield      #17                 // Field hasDecoded:Z
       4: ifne          123
       7: aload_0
       8: getfield      #10                 // Field channel:Lorg/apache/dubbo/remoting/Channel;
      11: ifnull        123
      14: aload_0
      15: getfield      #12                 // Field inputStream:Ljava/io/InputStream;
      18: ifnull        123
      21: aload_0
      22: aload_0
      23: getfield      #10                 // Field channel:Lorg/apache/dubbo/remoting/Channel;
      26: aload_0
      27: getfield      #12                 // Field inputStream:Ljava/io/InputStream;
      30: invokevirtual #18                 // Method decode:(Lorg/apache/dubbo/remoting/Channel;Ljava/io/InputStream;)Ljava/lang/Object;
      33: pop
      34: aload_0
      35: iconst_1
      36: putfield      #17                 // Field hasDecoded:Z
      39: goto          123
      42: astore_1
      43: getstatic     #20                 // Field log:Lorg/apache/dubbo/common/logger/ErrorTypeAwareLogger;
      46: invokeinterface #21,  1           // InterfaceMethod org/apache/dubbo/common/logger/ErrorTypeAwareLogger.isWarnEnabled:()Z
      51: ifeq          91
      54: getstatic     #20                 // Field log:Lorg/apache/dubbo/common/logger/ErrorTypeAwareLogger;
      57: ldc           #22                 // String 4-20
      59: ldc           #23                 // String
      61: ldc           #23                 // String
      63: new           #24                 // class java/lang/StringBuilder
      66: dup
      67: invokespecial #25                 // Method java/lang/StringBuilder."<init>":()V
      70: ldc           #26                 // String Decode rpc invocation failed:
      72: invokevirtual #27                 // Method java/lang/StringBuilder.append:(Ljava/lang/String;)Ljava/lang/StringBuilder;
      75: aload_1
      76: invokevirtual #28                 // Method java/lang/Throwable.getMessage:()Ljava/lang/String;
      79: invokevirtual #27                 // Method java/lang/StringBuilder.append:(Ljava/lang/String;)Ljava/lang/StringBuilder;
      82: invokevirtual #29                 // Method java/lang/StringBuilder.toString:()Ljava/lang/String;
      85: aload_1
      86: invokeinterface #30,  6           // InterfaceMethod org/apache/dubbo/common/logger/ErrorTypeAwareLogger.warn:(Ljava/lang/String;Ljava/lang/String;Ljava/lang/String;Ljava/lang/String;Ljava/lang/Throwable;)V
      91: aload_0
      92: getfield      #11                 // Field request:Lorg/apache/dubbo/remoting/exchange/Request;
      95: iconst_1
      96: invokevirtual #31                 // Method org/apache/dubbo/remoting/exchange/Request.setBroken:(Z)V
      99: aload_0
     100: getfield      #11                 // Field request:Lorg/apache/dubbo/remoting/exchange/Request;
     103: aload_1
     104: invokevirtual #32                 // Method org/apache/dubbo/remoting/exchange/Request.setData:(Ljava/lang/Object;)V
     107: aload_0
     108: iconst_1
     109: putfield      #17                 // Field hasDecoded:Z
     112: goto          123
     115: astore_2
     116: aload_0
     117: iconst_1
     118: putfield      #17                 // Field hasDecoded:Z
     121: aload_2
     122: athrow
     123: return
    Exception table:
       from    to  target type
          21    34    42   Class java/lang/Throwable
          21    34   115   any
          42   107   115   any

  public void encode(org.apache.dubbo.remoting.Channel, java.io.OutputStream, java.lang.Object) throws java.io.IOException;
    Code:
       0: new           #33                 // class java/lang/UnsupportedOperationException
       3: dup
       4: invokespecial #34                 // Method java/lang/UnsupportedOperationException."<init>":()V
       7: athrow

  public java.lang.Object decode(org.apache.dubbo.remoting.Channel, java.io.InputStream) throws java.io.IOException;
    Code:
       0: aload_0
       1: getfield      #13                 // Field serializationType:B
       4: invokestatic  #35                 // Method java/lang/Byte.valueOf:(B)Ljava/lang/Byte;
       7: invokestatic  #36                 // Method org/apache/dubbo/remoting/transport/CodecSupport.getSerialization:(Ljava/lang/Byte;)Lorg/apache/dubbo/common/serialize/Serialization;
      10: aload_1
      11: invokeinterface #37,  1           // InterfaceMethod org/apache/dubbo/remoting/Channel.getUrl:()Lorg/apache/dubbo/common/URL;
      16: aload_2
      17: invokeinterface #38,  3           // InterfaceMethod org/apache/dubbo/common/serialize/Serialization.deserialize:(Lorg/apache/dubbo/common/URL;Ljava/io/InputStream;)Lorg/apache/dubbo/common/serialize/ObjectInput;
      22: astore_3
      23: aload_0
      24: ldc           #39                 // String serialization_id
      26: aload_0
      27: getfield      #13                 // Field serializationType:B
      30: invokestatic  #35                 // Method java/lang/Byte.valueOf:(B)Ljava/lang/Byte;
      33: invokevirtual #40                 // Method put:(Ljava/lang/Object;Ljava/lang/Object;)Ljava/lang/Object;
      36: pop
      37: aload_3
      38: invokeinterface #41,  1           // InterfaceMethod org/apache/dubbo/common/serialize/ObjectInput.readUTF:()Ljava/lang/String;
      43: astore        4
      45: aload_0
      46: getfield      #11                 // Field request:Lorg/apache/dubbo/remoting/exchange/Request;
      49: aload         4
      51: invokevirtual #42                 // Method org/apache/dubbo/remoting/exchange/Request.setVersion:(Ljava/lang/String;)V
      54: aload_0
      55: ldc           #43                 // String dubbo
      57: aload         4
      59: invokevirtual #44                 // Method setAttachment:(Ljava/lang/String;Ljava/lang/String;)V
      62: aload_3
      63: invokeinterface #41,  1           // InterfaceMethod org/apache/dubbo/common/serialize/ObjectInput.readUTF:()Ljava/lang/String;
      68: astore        5
      70: aload_0
      71: ldc           #45                 // String path
      73: aload         5
      75: invokevirtual #44                 // Method setAttachment:(Ljava/lang/String;Ljava/lang/String;)V
      78: aload_3
      79: invokeinterface #41,  1           // InterfaceMethod org/apache/dubbo/common/serialize/ObjectInput.readUTF:()Ljava/lang/String;
      84: astore        6
      86: aload_0
      87: ldc           #46                 // String version
      89: aload         6
      91: invokevirtual #44                 // Method setAttachment:(Ljava/lang/String;Ljava/lang/String;)V
      94: aload         5
      96: aload         6
      98: invokestatic  #47                 // Method org/apache/dubbo/common/BaseServiceMetadata.keyWithoutGroup:(Ljava/lang/String;Ljava/lang/String;)Ljava/lang/String;
     101: astore        7
     103: aload_0
     104: aload         7
     106: invokespecial #48                 // Method checkPayload:(Ljava/lang/String;)V
     109: aload_0
     110: aload_3
     111: invokeinterface #41,  1           // InterfaceMethod org/apache/dubbo/common/serialize/ObjectInput.readUTF:()Ljava/lang/String;
     116: invokevirtual #49                 // Method setMethodName:(Ljava/lang/String;)V
     119: aload_3
     120: invokeinterface #41,  1           // InterfaceMethod org/apache/dubbo/common/serialize/ObjectInput.readUTF:()Ljava/lang/String;
     125: astore        8
     127: aload_0
     128: aload         8
     130: invokevirtual #50                 // Method setParameterTypesDesc:(Ljava/lang/String;)V
     133: invokestatic  #51                 // Method java/lang/Thread.currentThread:()Ljava/lang/Thread;
     136: invokevirtual #52                 // Method java/lang/Thread.getContextClassLoader:()Ljava/lang/ClassLoader;
     139: astore        9
     141: getstatic     #53                 // Field CHECK_SERIALIZATION:Z
     144: ifeq          216
     147: aload_0
     148: getfield      #5                  // Field frameworkModel:Lorg/apache/dubbo/rpc/model/FrameworkModel;
     151: invokevirtual #54                 // Method org/apache/dubbo/rpc/model/FrameworkModel.getBeanFactory:()Lorg/apache/dubbo/common/beans/factory/ScopeBeanFactory;
     154: ldc           #55                 // class org/apache/dubbo/rpc/protocol/PermittedSerializationKeeper
     156: invokevirtual #56                 // Method org/apache/dubbo/common/beans/factory/ScopeBeanFactory.getBean:(Ljava/lang/Class;)Ljava/lang/Object;
     159: checkcast     #55                 // class org/apache/dubbo/rpc/protocol/PermittedSerializationKeeper
     162: astore        10
     164: aload         10
     166: aload         7
     168: aload_0
     169: getfield      #13                 // Field serializationType:B
     172: invokestatic  #35                 // Method java/lang/Byte.valueOf:(B)Ljava/lang/Byte;
     175: invokevirtual #57                 // Method org/apache/dubbo/rpc/protocol/PermittedSerializationKeeper.checkSerializationPermitted:(Ljava/lang/String;Ljava/lang/Byte;)Z
     178: ifne          216
     181: new           #58                 // class java/io/IOException
     184: dup
     185: new           #24                 // class java/lang/StringBuilder
     188: dup
     189: invokespecial #25                 // Method java/lang/StringBuilder."<init>":()V
     192: ldc           #59                 // String Unexpected serialization id:
     194: invokevirtual #27                 // Method java/lang/StringBuilder.append:(Ljava/lang/String;)Ljava/lang/StringBuilder;
     197: aload_0
     198: getfield      #13                 // Field serializationType:B
     201: invokevirtual #60                 // Method java/lang/StringBuilder.append:(I)Ljava/lang/StringBuilder;
     204: ldc           #61                 // String  received from network, please check if the peer send the right id.
     206: invokevirtual #27                 // Method java/lang/StringBuilder.append:(Ljava/lang/String;)Ljava/lang/StringBuilder;
     209: invokevirtual #29                 // Method java/lang/StringBuilder.toString:()Ljava/lang/String;
     212: invokespecial #62                 // Method java/io/IOException."<init>":(Ljava/lang/String;)V
     215: athrow
     216: getstatic     #63                 // Field org/apache/dubbo/rpc/protocol/dubbo/DubboCodec.EMPTY_OBJECT_ARRAY:[Ljava/lang/Object;
     219: astore        10
     221: getstatic     #64                 // Field org/apache/dubbo/rpc/protocol/dubbo/DubboCodec.EMPTY_CLASS_ARRAY:[Ljava/lang/Class;
     224: astore        11
     226: aload         8
     228: invokevirtual #65                 // Method java/lang/String.length:()I
     231: ifle          336
     234: aload_0
     235: aload         5
     237: aload         6
     239: aload         8
     241: aload         11
     243: invokevirtual #66                 // Method drawPts:(Ljava/lang/String;Ljava/lang/String;Ljava/lang/String;[Ljava/lang/Class;)[Ljava/lang/Class;
     246: astore        11
     248: aload         11
     250: getstatic     #64                 // Field org/apache/dubbo/rpc/protocol/dubbo/DubboCodec.EMPTY_CLASS_ARRAY:[Ljava/lang/Class;
     253: if_acmpne     327
     256: aload         8
     258: aload_0
     259: invokevirtual #67                 // Method getMethodName:()Ljava/lang/String;
     262: invokestatic  #68                 // Method org/apache/dubbo/rpc/support/RpcUtils.isGenericCall:(Ljava/lang/String;Ljava/lang/String;)Z
     265: ifne          320
     268: aload         8
     270: aload_0
     271: invokevirtual #67                 // Method getMethodName:()Ljava/lang/String;
     274: invokestatic  #69                 // Method org/apache/dubbo/rpc/support/RpcUtils.isEcho:(Ljava/lang/String;Ljava/lang/String;)Z
     277: ifne          320
     280: new           #70                 // class java/lang/IllegalArgumentException
     283: dup
     284: new           #24                 // class java/lang/StringBuilder
     287: dup
     288: invokespecial #25                 // Method java/lang/StringBuilder."<init>":()V
     291: ldc           #71                 // String Service not found:
     293: invokevirtual #27                 // Method java/lang/StringBuilder.append:(Ljava/lang/String;)Ljava/lang/StringBuilder;
     296: aload         5
     298: invokevirtual #27                 // Method java/lang/StringBuilder.append:(Ljava/lang/String;)Ljava/lang/StringBuilder;
     301: ldc           #72                 // String ,
     303: invokevirtual #27                 // Method java/lang/StringBuilder.append:(Ljava/lang/String;)Ljava/lang/StringBuilder;
     306: aload_0
     307: invokevirtual #67                 // Method getMethodName:()Ljava/lang/String;
     310: invokevirtual #27                 // Method java/lang/StringBuilder.append:(Ljava/lang/String;)Ljava/lang/StringBuilder;
     313: invokevirtual #29                 // Method java/lang/StringBuilder.toString:()Ljava/lang/String;
     316: invokespecial #73                 // Method java/lang/IllegalArgumentException."<init>":(Ljava/lang/String;)V
     319: athrow
     320: aload         8
     322: invokestatic  #74                 // Method org/apache/dubbo/common/utils/ReflectUtils.desc2classArray:(Ljava/lang/String;)[Ljava/lang/Class;
     325: astore        11
     327: aload_0
     328: aload_3
     329: aload         11
     331: invokevirtual #75                 // Method drawArgs:(Lorg/apache/dubbo/common/serialize/ObjectInput;[Ljava/lang/Class;)[Ljava/lang/Object;
     334: astore        10
     336: aload_0
     337: aload         11
     339: invokevirtual #76                 // Method setParameterTypes:([Ljava/lang/Class;)V
     342: aload_3
     343: invokeinterface #77,  1           // InterfaceMethod org/apache/dubbo/common/serialize/ObjectInput.readAttachments:()Ljava/util/Map;
     348: astore        12
     350: aload         12
     352: invokestatic  #78                 // Method org/apache/dubbo/common/utils/CollectionUtils.isNotEmptyMap:(Ljava/util/Map;)Z
     355: ifeq          364
     358: aload_0
     359: aload         12
     361: invokevirtual #79                 // Method addObjectAttachments:(Ljava/util/Map;)V
     364: aload_0
     365: aload_1
     366: aload         11
     368: aload         10
     370: invokevirtual #80                 // Method decodeArgument:(Lorg/apache/dubbo/remoting/Channel;[Ljava/lang/Class;[Ljava/lang/Object;)V
     373: invokestatic  #51                 // Method java/lang/Thread.currentThread:()Ljava/lang/Thread;
     376: aload         9
     378: invokevirtual #81                 // Method java/lang/Thread.setContextClassLoader:(Ljava/lang/ClassLoader;)V
     381: aload_3
     382: instanceof    #82                 // class org/apache/dubbo/common/serialize/Cleanable
     385: ifeq          446
     388: aload_3
     389: checkcast     #82                 // class org/apache/dubbo/common/serialize/Cleanable
     392: invokeinterface #83,  1           // InterfaceMethod org/apache/dubbo/common/serialize/Cleanable.cleanup:()V
     397: goto          446
     400: astore        10
     402: new           #58                 // class java/io/IOException
     405: dup
     406: ldc           #85                 // String Read invocation data failed.
     408: aload         10
     410: invokestatic  #86                 // Method org/apache/dubbo/common/utils/StringUtils.toString:(Ljava/lang/String;Ljava/lang/Throwable;)Ljava/lang/String;
     413: invokespecial #62                 // Method java/io/IOException."<init>":(Ljava/lang/String;)V
     416: athrow
     417: astore        13
     419: invokestatic  #51                 // Method java/lang/Thread.currentThread:()Ljava/lang/Thread;
     422: aload         9
     424: invokevirtual #81                 // Method java/lang/Thread.setContextClassLoader:(Ljava/lang/ClassLoader;)V
     427: aload_3
     428: instanceof    #82                 // class org/apache/dubbo/common/serialize/Cleanable
     431: ifeq          443
     434: aload_3
     435: checkcast     #82                 // class org/apache/dubbo/common/serialize/Cleanable
     438: invokeinterface #83,  1           // InterfaceMethod org/apache/dubbo/common/serialize/Cleanable.cleanup:()V
     443: aload         13
     445: athrow
     446: aload_0
     447: areturn
    Exception table:
       from    to  target type
         141   373   400   Class java/lang/ClassNotFoundException
         141   373   417   any
         400   419   417   any

  protected void decodeArgument(org.apache.dubbo.remoting.Channel, java.lang.Class<?>[], java.lang.Object[]) throws java.io.IOException;
    Code:
       0: aload_0
       1: getfield      #16                 // Field callbackServiceCodecFactory:Ljava/util/function/Supplier;
       4: invokeinterface #87,  1           // InterfaceMethod java/util/function/Supplier.get:()Ljava/lang/Object;
       9: checkcast     #88                 // class org/apache/dubbo/rpc/protocol/dubbo/CallbackServiceCodec
      12: astore        4
      14: iconst_0
      15: istore        5
      17: iload         5
      19: aload_3
      20: arraylength
      21: if_icmpge     48
      24: aload_3
      25: iload         5
      27: aload         4
      29: aload_1
      30: aload_0
      31: aload_2
      32: iload         5
      34: aload_3
      35: iload         5
      37: aaload
      38: invokevirtual #89                 // Method org/apache/dubbo/rpc/protocol/dubbo/CallbackServiceCodec.decodeInvocationArgument:(Lorg/apache/dubbo/remoting/Channel;Lorg/apache/dubbo/rpc/RpcInvocation;[Ljava/lang/Class;ILjava/lang/Object;)Ljava/lang/Object;
      41: aastore
      42: iinc          5, 1
      45: goto          17
      48: aload_0
      49: aload_3
      50: invokevirtual #90                 // Method setArguments:([Ljava/lang/Object;)V
      53: aload_0
      54: ldc           #45                 // String path
      56: invokevirtual #91                 // Method getAttachment:(Ljava/lang/String;)Ljava/lang/String;
      59: aload_0
      60: ldc           #92                 // String group
      62: invokevirtual #91                 // Method getAttachment:(Ljava/lang/String;)Ljava/lang/String;
      65: aload_0
      66: ldc           #46                 // String version
      68: invokevirtual #91                 // Method getAttachment:(Ljava/lang/String;)Ljava/lang/String;
      71: invokestatic  #93                 // Method org/apache/dubbo/common/URL.buildKey:(Ljava/lang/String;Ljava/lang/String;Ljava/lang/String;)Ljava/lang/String;
      74: astore        5
      76: aload_0
      77: aload         5
      79: invokevirtual #94                 // Method setTargetServiceUniqueName:(Ljava/lang/String;)V
      82: return

  protected java.lang.Class<?>[] drawPts(java.lang.String, java.lang.String, java.lang.String, java.lang.Class<?>[]);
    Code:
       0: aload_0
       1: getfield      #5                  // Field frameworkModel:Lorg/apache/dubbo/rpc/model/FrameworkModel;
       4: invokevirtual #95                 // Method org/apache/dubbo/rpc/model/FrameworkModel.getServiceRepository:()Lorg/apache/dubbo/rpc/model/FrameworkServiceRepository;
       7: astore        5
       9: aload         5
      11: aload_1
      12: aload_2
      13: invokestatic  #47                 // Method org/apache/dubbo/common/BaseServiceMetadata.keyWithoutGroup:(Ljava/lang/String;Ljava/lang/String;)Ljava/lang/String;
      16: invokevirtual #96                 // Method org/apache/dubbo/rpc/model/FrameworkServiceRepository.lookupExportedServicesWithoutGroup:(Ljava/lang/String;)Ljava/util/List;
      19: astore        6
      21: aconst_null
      22: astore        7
      24: aload         6
      26: invokestatic  #97                 // Method org/apache/dubbo/common/utils/CollectionUtils.isNotEmpty:(Ljava/util/Collection;)Z
      29: ifeq          81
      32: aload         6
      34: invokeinterface #98,  1           // InterfaceMethod java/util/List.iterator:()Ljava/util/Iterator;
      39: astore        8
      41: aload         8
      43: invokeinterface #99,  1           // InterfaceMethod java/util/Iterator.hasNext:()Z
      48: ifeq          81
      51: aload         8
      53: invokeinterface #100,  1          // InterfaceMethod java/util/Iterator.next:()Ljava/lang/Object;
      58: checkcast     #101                // class org/apache/dubbo/rpc/model/ProviderModel
      61: astore        9
      63: aload         9
      65: invokevirtual #102                // Method org/apache/dubbo/rpc/model/ProviderModel.getServiceModel:()Lorg/apache/dubbo/rpc/model/ServiceDescriptor;
      68: astore        7
      70: aload         7
      72: ifnull        78
      75: goto          81
      78: goto          41
      81: aload         7
      83: ifnonnull     181
      86: aload_0
      87: getfield      #5                  // Field frameworkModel:Lorg/apache/dubbo/rpc/model/FrameworkModel;
      90: invokevirtual #103                // Method org/apache/dubbo/rpc/model/FrameworkModel.getApplicationModels:()Ljava/util/List;
      93: invokeinterface #98,  1           // InterfaceMethod java/util/List.iterator:()Ljava/util/Iterator;
      98: astore        8
     100: aload         8
     102: invokeinterface #99,  1           // InterfaceMethod java/util/Iterator.hasNext:()Z
     107: ifeq          181
     110: aload         8
     112: invokeinterface #100,  1          // InterfaceMethod java/util/Iterator.next:()Ljava/lang/Object;
     117: checkcast     #104                // class org/apache/dubbo/rpc/model/ApplicationModel
     120: astore        9
     122: aload         9
     124: invokevirtual #105                // Method org/apache/dubbo/rpc/model/ApplicationModel.getModuleModels:()Ljava/util/List;
     127: invokeinterface #98,  1           // InterfaceMethod java/util/List.iterator:()Ljava/util/Iterator;
     132: astore        10
     134: aload         10
     136: invokeinterface #99,  1           // InterfaceMethod java/util/Iterator.hasNext:()Z
     141: ifeq          178
     144: aload         10
     146: invokeinterface #100,  1          // InterfaceMethod java/util/Iterator.next:()Ljava/lang/Object;
     151: checkcast     #106                // class org/apache/dubbo/rpc/model/ModuleModel
     154: astore        11
     156: aload         11
     158: invokevirtual #107                // Method org/apache/dubbo/rpc/model/ModuleModel.getServiceRepository:()Lorg/apache/dubbo/rpc/model/ModuleServiceRepository;
     161: aload_1
     162: invokevirtual #108                // Method org/apache/dubbo/rpc/model/ModuleServiceRepository.lookupService:(Ljava/lang/String;)Lorg/apache/dubbo/rpc/model/ServiceDescriptor;
     165: astore        7
     167: aload         7
     169: ifnull        175
     172: goto          178
     175: goto          134
     178: goto          100
     181: aload         7
     183: ifnull        388
     186: aload         7
     188: aload_0
     189: invokevirtual #67                 // Method getMethodName:()Ljava/lang/String;
     192: aload_3
     193: invokeinterface #109,  3          // InterfaceMethod org/apache/dubbo/rpc/model/ServiceDescriptor.getMethod:(Ljava/lang/String;Ljava/lang/String;)Lorg/apache/dubbo/rpc/model/MethodDescriptor;
     198: astore        8
     200: aload         8
     202: ifnull        388
     205: aload         8
     207: invokeinterface #110,  1          // InterfaceMethod org/apache/dubbo/rpc/model/MethodDescriptor.getParameterClasses:()[Ljava/lang/Class;
     212: astore        4
     214: aload_0
     215: aload         8
     217: invokeinterface #111,  1          // InterfaceMethod org/apache/dubbo/rpc/model/MethodDescriptor.getReturnTypes:()[Ljava/lang/reflect/Type;
     222: invokevirtual #112                // Method setReturnTypes:([Ljava/lang/reflect/Type;)V
     225: aload         6
     227: invokestatic  #97                 // Method org/apache/dubbo/common/utils/CollectionUtils.isNotEmpty:(Ljava/util/Collection;)Z
     230: ifeq          388
     233: aload         6
     235: invokeinterface #113,  1          // InterfaceMethod java/util/List.size:()I
     240: iconst_1
     241: if_icmpne     267
     244: invokestatic  #51                 // Method java/lang/Thread.currentThread:()Ljava/lang/Thread;
     247: aload         6
     249: iconst_0
     250: invokeinterface #114,  2          // InterfaceMethod java/util/List.get:(I)Ljava/lang/Object;
     255: checkcast     #101                // class org/apache/dubbo/rpc/model/ProviderModel
     258: invokevirtual #115                // Method org/apache/dubbo/rpc/model/ProviderModel.getClassLoader:()Ljava/lang/ClassLoader;
     261: invokevirtual #81                 // Method java/lang/Thread.setContextClassLoader:(Ljava/lang/ClassLoader;)V
     264: goto          388
     267: aload         6
     269: invokeinterface #98,  1           // InterfaceMethod java/util/List.iterator:()Ljava/util/Iterator;
     274: astore        9
     276: aload         9
     278: invokeinterface #99,  1           // InterfaceMethod java/util/Iterator.hasNext:()Z
     283: ifeq          388
     286: aload         9
     288: invokeinterface #100,  1          // InterfaceMethod java/util/Iterator.next:()Ljava/lang/Object;
     293: checkcast     #101                // class org/apache/dubbo/rpc/model/ProviderModel
     296: astore        10
     298: aload         10
     300: invokevirtual #115                // Method org/apache/dubbo/rpc/model/ProviderModel.getClassLoader:()Ljava/lang/ClassLoader;
     303: astore        11
     305: iconst_1
     306: istore        12
     308: aload         4
     310: astore        13
     312: aload         13
     314: arraylength
     315: istore        14
     317: iconst_0
     318: istore        15
     320: iload         15
     322: iload         14
     324: if_icmpge     369
     327: aload         13
     329: iload         15
     331: aaload
     332: astore        16
     334: aload         16
     336: aload         11
     338: aload         16
     340: invokevirtual #116                // Method java/lang/Class.getName:()Ljava/lang/String;
     343: invokevirtual #117                // Method java/lang/ClassLoader.loadClass:(Ljava/lang/String;)Ljava/lang/Class;
     346: invokevirtual #118                // Method java/lang/Object.equals:(Ljava/lang/Object;)Z
     349: ifne          355
     352: iconst_0
     353: istore        12
     355: goto          363
     358: astore        17
     360: iconst_0
     361: istore        12
     363: iinc          15, 1
     366: goto          320
     369: iload         12
     371: ifeq          385
     374: invokestatic  #51                 // Method java/lang/Thread.currentThread:()Ljava/lang/Thread;
     377: aload         11
     379: invokevirtual #81                 // Method java/lang/Thread.setContextClassLoader:(Ljava/lang/ClassLoader;)V
     382: goto          388
     385: goto          276
     388: aload         4
     390: areturn
    Exception table:
       from    to  target type
         334   355   358   Class java/lang/ClassNotFoundException

  protected java.lang.Object[] drawArgs(org.apache.dubbo.common.serialize.ObjectInput, java.lang.Class<?>[]) throws java.io.IOException, java.lang.ClassNotFoundException;
    Code:
       0: aload_2
       1: arraylength
       2: anewarray     #119                // class java/lang/Object
       5: astore_3
       6: iconst_0
       7: istore        4
       9: iload         4
      11: aload_3
      12: arraylength
      13: if_icmpge     36
      16: aload_3
      17: iload         4
      19: aload_1
      20: aload_2
      21: iload         4
      23: aaload
      24: invokeinterface #120,  2          // InterfaceMethod org/apache/dubbo/common/serialize/ObjectInput.readObject:(Ljava/lang/Class;)Ljava/lang/Object;
      29: aastore
      30: iinc          4, 1
      33: goto          9
      36: aload_3
      37: areturn

  private void checkPayload(java.lang.String) throws java.io.IOException;
    Code:
       0: aload_0
       1: getfield      #5                  // Field frameworkModel:Lorg/apache/dubbo/rpc/model/FrameworkModel;
       4: invokevirtual #95                 // Method org/apache/dubbo/rpc/model/FrameworkModel.getServiceRepository:()Lorg/apache/dubbo/rpc/model/FrameworkServiceRepository;
       7: aload_1
       8: invokevirtual #121                // Method org/apache/dubbo/rpc/model/FrameworkServiceRepository.lookupExportedServiceWithoutGroup:(Ljava/lang/String;)Lorg/apache/dubbo/rpc/model/ProviderModel;
      11: astore_2
      12: aload_2
      13: ifnull        142
      16: aload_2
      17: invokevirtual #122                // Method org/apache/dubbo/rpc/model/ProviderModel.getServiceMetadata:()Lorg/apache/dubbo/rpc/model/ServiceMetadata;
      20: invokevirtual #123                // Method org/apache/dubbo/rpc/model/ServiceMetadata.getAttachments:()Ljava/util/Map;
      23: ldc           #124                // String payload
      25: invokeinterface #125,  2          // InterfaceMethod java/util/Map.get:(Ljava/lang/Object;)Ljava/lang/Object;
      30: checkcast     #126                // class java/lang/String
      33: astore_3
      34: aload_3
      35: ifnull        142
      38: aload_3
      39: invokestatic  #127                // Method java/lang/Integer.parseInt:(Ljava/lang/String;)I
      42: istore        4
      44: iload         4
      46: ifgt          50
      49: return
      50: aload_0
      51: getfield      #11                 // Field request:Lorg/apache/dubbo/remoting/exchange/Request;
      54: invokevirtual #128                // Method org/apache/dubbo/remoting/exchange/Request.getPayload:()I
      57: iload         4
      59: if_icmple     142
      62: new           #129                // class org/apache/dubbo/remoting/transport/ExceedPayloadLimitException
      65: dup
      66: new           #24                 // class java/lang/StringBuilder
      69: dup
      70: invokespecial #25                 // Method java/lang/StringBuilder."<init>":()V
      73: ldc           #130                // String Data length too large:
      75: invokevirtual #27                 // Method java/lang/StringBuilder.append:(Ljava/lang/String;)Ljava/lang/StringBuilder;
      78: aload_0
      79: getfield      #11                 // Field request:Lorg/apache/dubbo/remoting/exchange/Request;
      82: invokevirtual #128                // Method org/apache/dubbo/remoting/exchange/Request.getPayload:()I
      85: invokevirtual #60                 // Method java/lang/StringBuilder.append:(I)Ljava/lang/StringBuilder;
      88: ldc           #131                // String , max payload:
      90: invokevirtual #27                 // Method java/lang/StringBuilder.append:(Ljava/lang/String;)Ljava/lang/StringBuilder;
      93: iload         4
      95: invokevirtual #60                 // Method java/lang/StringBuilder.append:(I)Ljava/lang/StringBuilder;
      98: ldc           #132                // String , channel:
     100: invokevirtual #27                 // Method java/lang/StringBuilder.append:(Ljava/lang/String;)Ljava/lang/StringBuilder;
     103: aload_0
     104: getfield      #10                 // Field channel:Lorg/apache/dubbo/remoting/Channel;
     107: invokevirtual #133                // Method java/lang/StringBuilder.append:(Ljava/lang/Object;)Ljava/lang/StringBuilder;
     110: invokevirtual #29                 // Method java/lang/StringBuilder.toString:()Ljava/lang/String;
     113: invokespecial #134                // Method org/apache/dubbo/remoting/transport/ExceedPayloadLimitException."<init>":(Ljava/lang/String;)V
     116: astore        5
     118: getstatic     #20                 // Field log:Lorg/apache/dubbo/common/logger/ErrorTypeAwareLogger;
     121: ldc           #135                // String 6-10
     123: ldc           #23                 // String
     125: ldc           #23                 // String
     127: aload         5
     129: invokevirtual #136                // Method org/apache/dubbo/remoting/transport/ExceedPayloadLimitException.getMessage:()Ljava/lang/String;
     132: aload         5
     134: invokeinterface #137,  6          // InterfaceMethod org/apache/dubbo/common/logger/ErrorTypeAwareLogger.error:(Ljava/lang/String;Ljava/lang/String;Ljava/lang/String;Ljava/lang/String;Ljava/lang/Throwable;)V
     139: aload         5
     141: athrow
     142: return

  protected void fillInvoker(org.apache.dubbo.rpc.protocol.dubbo.DubboProtocol) throws org.apache.dubbo.remoting.RemotingException;
    Code:
       0: aload_0
       1: aload_1
       2: aload_0
       3: getfield      #10                 // Field channel:Lorg/apache/dubbo/remoting/Channel;
       6: aload_0
       7: invokevirtual #138                // Method org/apache/dubbo/rpc/protocol/dubbo/DubboProtocol.getInvoker:(Lorg/apache/dubbo/remoting/Channel;Lorg/apache/dubbo/rpc/Invocation;)Lorg/apache/dubbo/rpc/Invoker;
      10: invokevirtual #139                // Method setInvoker:(Lorg/apache/dubbo/rpc/Invoker;)V
      13: return

  private static org.apache.dubbo.rpc.protocol.dubbo.CallbackServiceCodec lambda$new$0(org.apache.dubbo.rpc.model.FrameworkModel);
    Code:
       0: new           #88                 // class org/apache/dubbo/rpc/protocol/dubbo/CallbackServiceCodec
       3: dup
       4: aload_0
       5: invokespecial #140                // Method org/apache/dubbo/rpc/protocol/dubbo/CallbackServiceCodec."<init>":(Lorg/apache/dubbo/rpc/model/FrameworkModel;)V
       8: areturn

  static {};
    Code:
       0: ldc           #141                // class org/apache/dubbo/rpc/protocol/dubbo/DecodeableRpcInvocation
       2: invokestatic  #142                // Method org/apache/dubbo/common/logger/LoggerFactory.getErrorTypeAwareLogger:(Ljava/lang/Class;)Lorg/apache/dubbo/common/logger/ErrorTypeAwareLogger;
       5: putstatic     #20                 // Field log:Lorg/apache/dubbo/common/logger/ErrorTypeAwareLogger;
       8: ldc           #143                // String serialization.security.check
      10: ldc           #144                // String true
      12: invokestatic  #145                // Method java/lang/System.getProperty:(Ljava/lang/String;Ljava/lang/String;)Ljava/lang/String;
      15: invokestatic  #146                // Method java/lang/Boolean.parseBoolean:(Ljava/lang/String;)Z
      18: putstatic     #53                 // Field CHECK_SERIALIZATION:Z
      21: return
}
