Compiled from "DubboIsolationExecutorSupportFactory.java"
public class org.apache.dubbo.rpc.protocol.dubbo.DubboIsolationExecutorSupportFactory implements org.apache.dubbo.rpc.executor.IsolationExecutorSupportFactory {
  public org.apache.dubbo.rpc.protocol.dubbo.DubboIsolationExecutorSupportFactory();
    Code:
       0: aload_0
       1: invokespecial #1                  // Method java/lang/Object."<init>":()V
       4: return

  public org.apache.dubbo.rpc.executor.ExecutorSupport createIsolationExecutorSupport(org.apache.dubbo.common.URL);
    Code:
       0: new           #2                  // class org/apache/dubbo/rpc/protocol/dubbo/DubboIsolationExecutorSupport
       3: dup
       4: aload_1
       5: invokespecial #3                  // Method org/apache/dubbo/rpc/protocol/dubbo/DubboIsolationExecutorSupport."<init>":(Lorg/apache/dubbo/common/URL;)V
       8: areturn
}
