Compiled from "DubboCountCodec.java"
public final class org.apache.dubbo.rpc.protocol.dubbo.DubboCountCodec implements org.apache.dubbo.remoting.Codec2 {
  private final org.apache.dubbo.rpc.protocol.dubbo.DubboCodec codec;

  public org.apache.dubbo.rpc.protocol.dubbo.DubboCountCodec(org.apache.dubbo.rpc.model.FrameworkModel);
    Code:
       0: aload_0
       1: invokespecial #2                  // Method java/lang/Object."<init>":()V
       4: aload_0
       5: new           #3                  // class org/apache/dubbo/rpc/protocol/dubbo/DubboCodec
       8: dup
       9: aload_1
      10: invokespecial #4                  // Method org/apache/dubbo/rpc/protocol/dubbo/DubboCodec."<init>":(Lorg/apache/dubbo/rpc/model/FrameworkModel;)V
      13: putfield      #5                  // Field codec:Lorg/apache/dubbo/rpc/protocol/dubbo/DubboCodec;
      16: return

  public void encode(org.apache.dubbo.remoting.Channel, org.apache.dubbo.remoting.buffer.ChannelBuffer, java.lang.Object) throws java.io.IOException;
    Code:
       0: aload_3
       1: instanceof    #6                  // class org/apache/dubbo/remoting/exchange/support/MultiMessage
       4: ifeq          56
       7: aload_3
       8: checkcast     #6                  // class org/apache/dubbo/remoting/exchange/support/MultiMessage
      11: astore        4
      13: aload         4
      15: invokevirtual #7                  // Method org/apache/dubbo/remoting/exchange/support/MultiMessage.iterator:()Ljava/util/Iterator;
      18: astore        5
      20: aload         5
      22: invokeinterface #8,  1            // InterfaceMethod java/util/Iterator.hasNext:()Z
      27: ifeq          53
      30: aload         5
      32: invokeinterface #9,  1            // InterfaceMethod java/util/Iterator.next:()Ljava/lang/Object;
      37: astore        6
      39: aload_0
      40: getfield      #5                  // Field codec:Lorg/apache/dubbo/rpc/protocol/dubbo/DubboCodec;
      43: aload_1
      44: aload_2
      45: aload         6
      47: invokevirtual #10                 // Method org/apache/dubbo/rpc/protocol/dubbo/DubboCodec.encode:(Lorg/apache/dubbo/remoting/Channel;Lorg/apache/dubbo/remoting/buffer/ChannelBuffer;Ljava/lang/Object;)V
      50: goto          20
      53: goto          66
      56: aload_0
      57: getfield      #5                  // Field codec:Lorg/apache/dubbo/rpc/protocol/dubbo/DubboCodec;
      60: aload_1
      61: aload_2
      62: aload_3
      63: invokevirtual #10                 // Method org/apache/dubbo/rpc/protocol/dubbo/DubboCodec.encode:(Lorg/apache/dubbo/remoting/Channel;Lorg/apache/dubbo/remoting/buffer/ChannelBuffer;Ljava/lang/Object;)V
      66: return

  public java.lang.Object decode(org.apache.dubbo.remoting.Channel, org.apache.dubbo.remoting.buffer.ChannelBuffer) throws java.io.IOException;
    Code:
       0: aload_2
       1: invokeinterface #11,  1           // InterfaceMethod org/apache/dubbo/remoting/buffer/ChannelBuffer.readerIndex:()I
       6: istore_3
       7: invokestatic  #12                 // Method org/apache/dubbo/remoting/exchange/support/MultiMessage.create:()Lorg/apache/dubbo/remoting/exchange/support/MultiMessage;
      10: astore        4
      12: aload_0
      13: getfield      #5                  // Field codec:Lorg/apache/dubbo/rpc/protocol/dubbo/DubboCodec;
      16: aload_1
      17: aload_2
      18: invokevirtual #13                 // Method org/apache/dubbo/rpc/protocol/dubbo/DubboCodec.decode:(Lorg/apache/dubbo/remoting/Channel;Lorg/apache/dubbo/remoting/buffer/ChannelBuffer;)Ljava/lang/Object;
      21: astore        5
      23: getstatic     #14                 // Field org/apache/dubbo/remoting/Codec2$DecodeResult.NEED_MORE_INPUT:Lorg/apache/dubbo/remoting/Codec2$DecodeResult;
      26: aload         5
      28: if_acmpne     41
      31: aload_2
      32: iload_3
      33: invokeinterface #15,  2           // InterfaceMethod org/apache/dubbo/remoting/buffer/ChannelBuffer.readerIndex:(I)V
      38: goto          72
      41: aload         4
      43: aload         5
      45: invokevirtual #16                 // Method org/apache/dubbo/remoting/exchange/support/MultiMessage.addMessage:(Ljava/lang/Object;)V
      48: aload_0
      49: aload         5
      51: aload_2
      52: invokeinterface #11,  1           // InterfaceMethod org/apache/dubbo/remoting/buffer/ChannelBuffer.readerIndex:()I
      57: iload_3
      58: isub
      59: invokespecial #17                 // Method logMessageLength:(Ljava/lang/Object;I)V
      62: aload_2
      63: invokeinterface #11,  1           // InterfaceMethod org/apache/dubbo/remoting/buffer/ChannelBuffer.readerIndex:()I
      68: istore_3
      69: goto          12
      72: aload         4
      74: invokevirtual #18                 // Method org/apache/dubbo/remoting/exchange/support/MultiMessage.isEmpty:()Z
      77: ifeq          84
      80: getstatic     #14                 // Field org/apache/dubbo/remoting/Codec2$DecodeResult.NEED_MORE_INPUT:Lorg/apache/dubbo/remoting/Codec2$DecodeResult;
      83: areturn
      84: aload         4
      86: invokevirtual #19                 // Method org/apache/dubbo/remoting/exchange/support/MultiMessage.size:()I
      89: iconst_1
      90: if_icmpne     100
      93: aload         4
      95: iconst_0
      96: invokevirtual #20                 // Method org/apache/dubbo/remoting/exchange/support/MultiMessage.get:(I)Ljava/lang/Object;
      99: areturn
     100: aload         4
     102: areturn

  private void logMessageLength(java.lang.Object, int);
    Code:
       0: iload_2
       1: ifgt          5
       4: return
       5: aload_1
       6: instanceof    #21                 // class org/apache/dubbo/remoting/exchange/Request
       9: ifeq          38
      12: aload_1
      13: checkcast     #21                 // class org/apache/dubbo/remoting/exchange/Request
      16: invokevirtual #22                 // Method org/apache/dubbo/remoting/exchange/Request.getData:()Ljava/lang/Object;
      19: checkcast     #23                 // class org/apache/dubbo/rpc/RpcInvocation
      22: ldc           #24                 // String input
      24: iload_2
      25: invokestatic  #25                 // Method java/lang/String.valueOf:(I)Ljava/lang/String;
      28: invokevirtual #26                 // Method org/apache/dubbo/rpc/RpcInvocation.setAttachment:(Ljava/lang/String;Ljava/lang/String;)V
      31: goto          68
      34: astore_3
      35: goto          68
      38: aload_1
      39: instanceof    #28                 // class org/apache/dubbo/remoting/exchange/Response
      42: ifeq          68
      45: aload_1
      46: checkcast     #28                 // class org/apache/dubbo/remoting/exchange/Response
      49: invokevirtual #29                 // Method org/apache/dubbo/remoting/exchange/Response.getResult:()Ljava/lang/Object;
      52: checkcast     #30                 // class org/apache/dubbo/rpc/AppResponse
      55: ldc           #31                 // String output
      57: iload_2
      58: invokestatic  #25                 // Method java/lang/String.valueOf:(I)Ljava/lang/String;
      61: invokevirtual #32                 // Method org/apache/dubbo/rpc/AppResponse.setAttachment:(Ljava/lang/String;Ljava/lang/String;)V
      64: goto          68
      67: astore_3
      68: return
    Exception table:
       from    to  target type
          12    31    34   Class java/lang/Throwable
          45    64    67   Class java/lang/Throwable
}
