Compiled from "DubboExporter.java"
public class org.apache.dubbo.rpc.protocol.dubbo.DubboExporter<T> extends org.apache.dubbo.rpc.protocol.AbstractExporter<T> {
  private final java.lang.String key;

  private final java.util.Map<java.lang.String, org.apache.dubbo.rpc.Exporter<?>> exporterMap;

  public org.apache.dubbo.rpc.protocol.dubbo.DubboExporter(org.apache.dubbo.rpc.Invoker<T>, java.lang.String, java.util.Map<java.lang.String, org.apache.dubbo.rpc.Exporter<?>>);
    Code:
       0: aload_0
       1: aload_1
       2: invokespecial #1                  // Method org/apache/dubbo/rpc/protocol/AbstractExporter."<init>":(Lorg/apache/dubbo/rpc/Invoker;)V
       5: aload_0
       6: aload_2
       7: putfield      #2                  // Field key:Ljava/lang/String;
      10: aload_0
      11: aload_3
      12: putfield      #3                  // Field exporterMap:Ljava/util/Map;
      15: aload_3
      16: aload_2
      17: aload_0
      18: invokeinterface #4,  3            // InterfaceMethod java/util/Map.put:(Ljava/lang/Object;Ljava/lang/Object;)Ljava/lang/Object;
      23: pop
      24: return

  public void afterUnExport();
    Code:
       0: aload_0
       1: getfield      #3                  // Field exporterMap:Ljava/util/Map;
       4: aload_0
       5: getfield      #2                  // Field key:Ljava/lang/String;
       8: aload_0
       9: invokeinterface #5,  3            // InterfaceMethod java/util/Map.remove:(Ljava/lang/Object;Ljava/lang/Object;)Z
      14: pop
      15: return
}
