Compiled from "DubboCodec.java"
public class org.apache.dubbo.rpc.protocol.dubbo.DubboCodec extends org.apache.dubbo.remoting.exchange.codec.ExchangeCodec {
  public static final java.lang.String NAME;

  public static final java.lang.String DUBBO_VERSION;

  public static final byte RESPONSE_WITH_EXCEPTION;

  public static final byte RESPONSE_VALUE;

  public static final byte RESPONSE_NULL_VALUE;

  public static final byte RESPONSE_WITH_EXCEPTION_WITH_ATTACHMENTS;

  public static final byte RESPONSE_VALUE_WITH_ATTACHMENTS;

  public static final byte RESPONSE_NULL_VALUE_WITH_ATTACHMENTS;

  public static final java.lang.Object[] EMPTY_OBJECT_ARRAY;

  public static final java.lang.Class<?>[] EMPTY_CLASS_ARRAY;

  private static final org.apache.dubbo.common.logger.ErrorTypeAwareLogger log;

  private static final java.util.concurrent.atomic.AtomicBoolean decodeInUserThreadLogged;

  private final org.apache.dubbo.rpc.protocol.dubbo.CallbackServiceCodec callbackServiceCodec;

  private final org.apache.dubbo.rpc.model.FrameworkModel frameworkModel;

  private final org.apache.dubbo.rpc.protocol.dubbo.ByteAccessor customByteAccessor;

  private static final java.lang.String DECODE_IN_IO_THREAD_KEY;

  public org.apache.dubbo.rpc.protocol.dubbo.DubboCodec(org.apache.dubbo.rpc.model.FrameworkModel);
    Code:
       0: aload_0
       1: invokespecial #4                  // Method org/apache/dubbo/remoting/exchange/codec/ExchangeCodec."<init>":()V
       4: aload_0
       5: aload_1
       6: putfield      #5                  // Field frameworkModel:Lorg/apache/dubbo/rpc/model/FrameworkModel;
       9: aload_0
      10: new           #6                  // class org/apache/dubbo/rpc/protocol/dubbo/CallbackServiceCodec
      13: dup
      14: aload_1
      15: invokespecial #7                  // Method org/apache/dubbo/rpc/protocol/dubbo/CallbackServiceCodec."<init>":(Lorg/apache/dubbo/rpc/model/FrameworkModel;)V
      18: putfield      #8                  // Field callbackServiceCodec:Lorg/apache/dubbo/rpc/protocol/dubbo/CallbackServiceCodec;
      21: aload_0
      22: ldc           #9                  // String byte.accessor
      24: invokestatic  #10                 // Method java/lang/System.getProperty:(Ljava/lang/String;)Ljava/lang/String;
      27: invokestatic  #11                 // Method java/util/Optional.ofNullable:(Ljava/lang/Object;)Ljava/util/Optional;
      30: invokedynamic #12,  0             // InvokeDynamic #0:test:()Ljava/util/function/Predicate;
      35: invokevirtual #13                 // Method java/util/Optional.filter:(Ljava/util/function/Predicate;)Ljava/util/Optional;
      38: aload_1
      39: invokedynamic #14,  0             // InvokeDynamic #1:apply:(Lorg/apache/dubbo/rpc/model/FrameworkModel;)Ljava/util/function/Function;
      44: invokevirtual #15                 // Method java/util/Optional.map:(Ljava/util/function/Function;)Ljava/util/Optional;
      47: aconst_null
      48: invokevirtual #16                 // Method java/util/Optional.orElse:(Ljava/lang/Object;)Ljava/lang/Object;
      51: checkcast     #17                 // class org/apache/dubbo/rpc/protocol/dubbo/ByteAccessor
      54: putfield      #18                 // Field customByteAccessor:Lorg/apache/dubbo/rpc/protocol/dubbo/ByteAccessor;
      57: return

  protected java.lang.Object decodeBody(org.apache.dubbo.remoting.Channel, java.io.InputStream, byte[]) throws java.io.IOException;
    Code:
       0: aload_3
       1: iconst_2
       2: baload
       3: istore        4
       5: iload         4
       7: bipush        31
       9: iand
      10: i2b
      11: istore        5
      13: aload_3
      14: iconst_4
      15: invokestatic  #20                 // Method org/apache/dubbo/common/io/Bytes.bytes2long:([BI)J
      18: lstore        6
      20: iload         4
      22: bipush        -128
      24: iand
      25: ifne          341
      28: new           #21                 // class org/apache/dubbo/remoting/exchange/Response
      31: dup
      32: lload         6
      34: invokespecial #22                 // Method org/apache/dubbo/remoting/exchange/Response."<init>":(J)V
      37: astore        8
      39: iload         4
      41: bipush        32
      43: iand
      44: ifeq          53
      47: aload         8
      49: iconst_1
      50: invokevirtual #23                 // Method org/apache/dubbo/remoting/exchange/Response.setEvent:(Z)V
      53: aload_3
      54: iconst_3
      55: baload
      56: istore        9
      58: aload         8
      60: iload         9
      62: invokevirtual #24                 // Method org/apache/dubbo/remoting/exchange/Response.setStatus:(B)V
      65: iload         9
      67: bipush        20
      69: if_icmpne     240
      72: aload         8
      74: invokevirtual #25                 // Method org/apache/dubbo/remoting/exchange/Response.isEvent:()Z
      77: ifeq          138
      80: aload_2
      81: invokestatic  #26                 // Method org/apache/dubbo/remoting/transport/CodecSupport.getPayload:(Ljava/io/InputStream;)[B
      84: astore        11
      86: aload         11
      88: iload         5
      90: invokestatic  #27                 // Method org/apache/dubbo/remoting/transport/CodecSupport.isHeartBeat:([BB)Z
      93: ifeq          102
      96: aconst_null
      97: astore        10
      99: goto          135
     102: aload_1
     103: invokeinterface #28,  1           // InterfaceMethod org/apache/dubbo/remoting/Channel.getUrl:()Lorg/apache/dubbo/common/URL;
     108: new           #29                 // class java/io/ByteArrayInputStream
     111: dup
     112: aload         11
     114: invokespecial #30                 // Method java/io/ByteArrayInputStream."<init>":([B)V
     117: iload         5
     119: invokestatic  #31                 // Method org/apache/dubbo/remoting/transport/CodecSupport.deserialize:(Lorg/apache/dubbo/common/URL;Ljava/io/InputStream;B)Lorg/apache/dubbo/common/serialize/ObjectInput;
     122: astore        12
     124: aload_0
     125: aload_1
     126: aload         12
     128: aload         11
     130: invokevirtual #32                 // Method decodeEventData:(Lorg/apache/dubbo/remoting/Channel;Lorg/apache/dubbo/common/serialize/ObjectInput;[B)Ljava/lang/Object;
     133: astore        10
     135: goto          230
     138: aload_1
     139: invokeinterface #28,  1           // InterfaceMethod org/apache/dubbo/remoting/Channel.getUrl:()Lorg/apache/dubbo/common/URL;
     144: ldc           #34                 // String decode.in.io.thread
     146: iconst_0
     147: invokevirtual #35                 // Method org/apache/dubbo/common/URL.getParameter:(Ljava/lang/String;Z)Z
     150: ifeq          188
     153: new           #36                 // class org/apache/dubbo/rpc/protocol/dubbo/DecodeableRpcResult
     156: dup
     157: aload_1
     158: aload         8
     160: aload_2
     161: aload_0
     162: aload_1
     163: aload         8
     165: lload         6
     167: invokevirtual #37                 // Method getRequestData:(Lorg/apache/dubbo/remoting/Channel;Lorg/apache/dubbo/remoting/exchange/Response;J)Ljava/lang/Object;
     170: checkcast     #38                 // class org/apache/dubbo/rpc/Invocation
     173: iload         5
     175: invokespecial #39                 // Method org/apache/dubbo/rpc/protocol/dubbo/DecodeableRpcResult."<init>":(Lorg/apache/dubbo/remoting/Channel;Lorg/apache/dubbo/remoting/exchange/Response;Ljava/io/InputStream;Lorg/apache/dubbo/rpc/Invocation;B)V
     178: astore        11
     180: aload         11
     182: invokevirtual #40                 // Method org/apache/dubbo/rpc/protocol/dubbo/DecodeableRpcResult.decode:()V
     185: goto          226
     188: new           #36                 // class org/apache/dubbo/rpc/protocol/dubbo/DecodeableRpcResult
     191: dup
     192: aload_1
     193: aload         8
     195: new           #41                 // class org/apache/dubbo/common/io/UnsafeByteArrayInputStream
     198: dup
     199: aload_0
     200: aload_2
     201: invokespecial #42                 // Method readMessageData:(Ljava/io/InputStream;)[B
     204: invokespecial #43                 // Method org/apache/dubbo/common/io/UnsafeByteArrayInputStream."<init>":([B)V
     207: aload_0
     208: aload_1
     209: aload         8
     211: lload         6
     213: invokevirtual #37                 // Method getRequestData:(Lorg/apache/dubbo/remoting/Channel;Lorg/apache/dubbo/remoting/exchange/Response;J)Ljava/lang/Object;
     216: checkcast     #38                 // class org/apache/dubbo/rpc/Invocation
     219: iload         5
     221: invokespecial #39                 // Method org/apache/dubbo/rpc/protocol/dubbo/DecodeableRpcResult."<init>":(Lorg/apache/dubbo/remoting/Channel;Lorg/apache/dubbo/remoting/exchange/Response;Ljava/io/InputStream;Lorg/apache/dubbo/rpc/Invocation;B)V
     224: astore        11
     226: aload         11
     228: astore        10
     230: aload         8
     232: aload         10
     234: invokevirtual #44                 // Method org/apache/dubbo/remoting/exchange/Response.setResult:(Ljava/lang/Object;)V
     237: goto          266
     240: aload_1
     241: invokeinterface #28,  1           // InterfaceMethod org/apache/dubbo/remoting/Channel.getUrl:()Lorg/apache/dubbo/common/URL;
     246: aload_2
     247: iload         5
     249: invokestatic  #31                 // Method org/apache/dubbo/remoting/transport/CodecSupport.deserialize:(Lorg/apache/dubbo/common/URL;Ljava/io/InputStream;B)Lorg/apache/dubbo/common/serialize/ObjectInput;
     252: astore        10
     254: aload         8
     256: aload         10
     258: invokeinterface #45,  1           // InterfaceMethod org/apache/dubbo/common/serialize/ObjectInput.readUTF:()Ljava/lang/String;
     263: invokevirtual #46                 // Method org/apache/dubbo/remoting/exchange/Response.setErrorMessage:(Ljava/lang/String;)V
     266: goto          338
     269: astore        10
     271: getstatic     #48                 // Field log:Lorg/apache/dubbo/common/logger/ErrorTypeAwareLogger;
     274: invokeinterface #49,  1           // InterfaceMethod org/apache/dubbo/common/logger/ErrorTypeAwareLogger.isWarnEnabled:()Z
     279: ifeq          321
     282: getstatic     #48                 // Field log:Lorg/apache/dubbo/common/logger/ErrorTypeAwareLogger;
     285: ldc           #50                 // String 4-20
     287: ldc           #51                 // String
     289: ldc           #51                 // String
     291: new           #52                 // class java/lang/StringBuilder
     294: dup
     295: invokespecial #53                 // Method java/lang/StringBuilder."<init>":()V
     298: ldc           #54                 // String Decode response failed:
     300: invokevirtual #55                 // Method java/lang/StringBuilder.append:(Ljava/lang/String;)Ljava/lang/StringBuilder;
     303: aload         10
     305: invokevirtual #56                 // Method java/lang/Throwable.getMessage:()Ljava/lang/String;
     308: invokevirtual #55                 // Method java/lang/StringBuilder.append:(Ljava/lang/String;)Ljava/lang/StringBuilder;
     311: invokevirtual #57                 // Method java/lang/StringBuilder.toString:()Ljava/lang/String;
     314: aload         10
     316: invokeinterface #58,  6           // InterfaceMethod org/apache/dubbo/common/logger/ErrorTypeAwareLogger.warn:(Ljava/lang/String;Ljava/lang/String;Ljava/lang/String;Ljava/lang/String;Ljava/lang/Throwable;)V
     321: aload         8
     323: bipush        90
     325: invokevirtual #24                 // Method org/apache/dubbo/remoting/exchange/Response.setStatus:(B)V
     328: aload         8
     330: aload         10
     332: invokestatic  #59                 // Method org/apache/dubbo/common/utils/StringUtils.toString:(Ljava/lang/Throwable;)Ljava/lang/String;
     335: invokevirtual #46                 // Method org/apache/dubbo/remoting/exchange/Response.setErrorMessage:(Ljava/lang/String;)V
     338: aload         8
     340: areturn
     341: iload         4
     343: bipush        32
     345: iand
     346: ifeq          497
     349: aload_2
     350: invokestatic  #26                 // Method org/apache/dubbo/remoting/transport/CodecSupport.getPayload:(Ljava/io/InputStream;)[B
     353: astore        10
     355: aload         10
     357: iload         5
     359: invokestatic  #27                 // Method org/apache/dubbo/remoting/transport/CodecSupport.isHeartBeat:([BB)Z
     362: ifeq          418
     365: new           #60                 // class org/apache/dubbo/remoting/exchange/HeartBeatRequest
     368: dup
     369: lload         6
     371: invokespecial #61                 // Method org/apache/dubbo/remoting/exchange/HeartBeatRequest."<init>":(J)V
     374: astore        8
     376: aload         8
     378: invokestatic  #62                 // Method org/apache/dubbo/common/Version.getProtocolVersion:()Ljava/lang/String;
     381: invokevirtual #63                 // Method org/apache/dubbo/remoting/exchange/Request.setVersion:(Ljava/lang/String;)V
     384: aload         8
     386: iload         4
     388: bipush        64
     390: iand
     391: ifeq          398
     394: iconst_1
     395: goto          399
     398: iconst_0
     399: invokevirtual #64                 // Method org/apache/dubbo/remoting/exchange/Request.setTwoWay:(Z)V
     402: aload         8
     404: checkcast     #60                 // class org/apache/dubbo/remoting/exchange/HeartBeatRequest
     407: iload         5
     409: invokevirtual #65                 // Method org/apache/dubbo/remoting/exchange/HeartBeatRequest.setProto:(B)V
     412: aconst_null
     413: astore        9
     415: goto          488
     418: new           #66                 // class org/apache/dubbo/remoting/exchange/Request
     421: dup
     422: lload         6
     424: invokespecial #67                 // Method org/apache/dubbo/remoting/exchange/Request."<init>":(J)V
     427: astore        8
     429: aload         8
     431: invokestatic  #62                 // Method org/apache/dubbo/common/Version.getProtocolVersion:()Ljava/lang/String;
     434: invokevirtual #63                 // Method org/apache/dubbo/remoting/exchange/Request.setVersion:(Ljava/lang/String;)V
     437: aload         8
     439: iload         4
     441: bipush        64
     443: iand
     444: ifeq          451
     447: iconst_1
     448: goto          452
     451: iconst_0
     452: invokevirtual #64                 // Method org/apache/dubbo/remoting/exchange/Request.setTwoWay:(Z)V
     455: aload_1
     456: invokeinterface #28,  1           // InterfaceMethod org/apache/dubbo/remoting/Channel.getUrl:()Lorg/apache/dubbo/common/URL;
     461: new           #29                 // class java/io/ByteArrayInputStream
     464: dup
     465: aload         10
     467: invokespecial #30                 // Method java/io/ByteArrayInputStream."<init>":([B)V
     470: iload         5
     472: invokestatic  #31                 // Method org/apache/dubbo/remoting/transport/CodecSupport.deserialize:(Lorg/apache/dubbo/common/URL;Ljava/io/InputStream;B)Lorg/apache/dubbo/common/serialize/ObjectInput;
     475: astore        11
     477: aload_0
     478: aload_1
     479: aload         11
     481: aload         10
     483: invokevirtual #32                 // Method decodeEventData:(Lorg/apache/dubbo/remoting/Channel;Lorg/apache/dubbo/common/serialize/ObjectInput;[B)Ljava/lang/Object;
     486: astore        9
     488: aload         8
     490: iconst_1
     491: invokevirtual #68                 // Method org/apache/dubbo/remoting/exchange/Request.setEvent:(Z)V
     494: goto          705
     497: new           #66                 // class org/apache/dubbo/remoting/exchange/Request
     500: dup
     501: lload         6
     503: invokespecial #67                 // Method org/apache/dubbo/remoting/exchange/Request."<init>":(J)V
     506: astore        8
     508: aload         8
     510: invokestatic  #62                 // Method org/apache/dubbo/common/Version.getProtocolVersion:()Ljava/lang/String;
     513: invokevirtual #63                 // Method org/apache/dubbo/remoting/exchange/Request.setVersion:(Ljava/lang/String;)V
     516: aload         8
     518: iload         4
     520: bipush        64
     522: iand
     523: ifeq          530
     526: iconst_1
     527: goto          531
     530: iconst_0
     531: invokevirtual #64                 // Method org/apache/dubbo/remoting/exchange/Request.setTwoWay:(Z)V
     534: aload_3
     535: bipush        12
     537: invokestatic  #69                 // Method org/apache/dubbo/common/io/Bytes.bytes2int:([BI)I
     540: istore        10
     542: aload         8
     544: iload         10
     546: invokevirtual #70                 // Method org/apache/dubbo/remoting/exchange/Request.setPayload:(I)V
     549: aload_0
     550: aload_1
     551: invokespecial #71                 // Method isDecodeDataInIoThread:(Lorg/apache/dubbo/remoting/Channel;)Z
     554: ifeq          633
     557: aload_0
     558: getfield      #18                 // Field customByteAccessor:Lorg/apache/dubbo/rpc/protocol/dubbo/ByteAccessor;
     561: ifnull        595
     564: aload_0
     565: getfield      #18                 // Field customByteAccessor:Lorg/apache/dubbo/rpc/protocol/dubbo/ByteAccessor;
     568: aload_1
     569: aload         8
     571: new           #41                 // class org/apache/dubbo/common/io/UnsafeByteArrayInputStream
     574: dup
     575: aload_0
     576: aload_2
     577: invokespecial #42                 // Method readMessageData:(Ljava/io/InputStream;)[B
     580: invokespecial #43                 // Method org/apache/dubbo/common/io/UnsafeByteArrayInputStream."<init>":([B)V
     583: iload         5
     585: invokeinterface #72,  5           // InterfaceMethod org/apache/dubbo/rpc/protocol/dubbo/ByteAccessor.getRpcInvocation:(Lorg/apache/dubbo/remoting/Channel;Lorg/apache/dubbo/remoting/exchange/Request;Ljava/io/InputStream;B)Lorg/apache/dubbo/rpc/protocol/dubbo/DecodeableRpcInvocation;
     590: astore        11
     592: goto          625
     595: new           #73                 // class org/apache/dubbo/rpc/protocol/dubbo/DecodeableRpcInvocation
     598: dup
     599: aload_0
     600: getfield      #5                  // Field frameworkModel:Lorg/apache/dubbo/rpc/model/FrameworkModel;
     603: aload_1
     604: aload         8
     606: new           #41                 // class org/apache/dubbo/common/io/UnsafeByteArrayInputStream
     609: dup
     610: aload_0
     611: aload_2
     612: invokespecial #42                 // Method readMessageData:(Ljava/io/InputStream;)[B
     615: invokespecial #43                 // Method org/apache/dubbo/common/io/UnsafeByteArrayInputStream."<init>":([B)V
     618: iload         5
     620: invokespecial #74                 // Method org/apache/dubbo/rpc/protocol/dubbo/DecodeableRpcInvocation."<init>":(Lorg/apache/dubbo/rpc/model/FrameworkModel;Lorg/apache/dubbo/remoting/Channel;Lorg/apache/dubbo/remoting/exchange/Request;Ljava/io/InputStream;B)V
     623: astore        11
     625: aload         11
     627: invokevirtual #75                 // Method org/apache/dubbo/rpc/protocol/dubbo/DecodeableRpcInvocation.decode:()V
     630: goto          701
     633: aload_0
     634: getfield      #18                 // Field customByteAccessor:Lorg/apache/dubbo/rpc/protocol/dubbo/ByteAccessor;
     637: ifnull        671
     640: aload_0
     641: getfield      #18                 // Field customByteAccessor:Lorg/apache/dubbo/rpc/protocol/dubbo/ByteAccessor;
     644: aload_1
     645: aload         8
     647: new           #41                 // class org/apache/dubbo/common/io/UnsafeByteArrayInputStream
     650: dup
     651: aload_0
     652: aload_2
     653: invokespecial #42                 // Method readMessageData:(Ljava/io/InputStream;)[B
     656: invokespecial #43                 // Method org/apache/dubbo/common/io/UnsafeByteArrayInputStream."<init>":([B)V
     659: iload         5
     661: invokeinterface #72,  5           // InterfaceMethod org/apache/dubbo/rpc/protocol/dubbo/ByteAccessor.getRpcInvocation:(Lorg/apache/dubbo/remoting/Channel;Lorg/apache/dubbo/remoting/exchange/Request;Ljava/io/InputStream;B)Lorg/apache/dubbo/rpc/protocol/dubbo/DecodeableRpcInvocation;
     666: astore        11
     668: goto          701
     671: new           #73                 // class org/apache/dubbo/rpc/protocol/dubbo/DecodeableRpcInvocation
     674: dup
     675: aload_0
     676: getfield      #5                  // Field frameworkModel:Lorg/apache/dubbo/rpc/model/FrameworkModel;
     679: aload_1
     680: aload         8
     682: new           #41                 // class org/apache/dubbo/common/io/UnsafeByteArrayInputStream
     685: dup
     686: aload_0
     687: aload_2
     688: invokespecial #42                 // Method readMessageData:(Ljava/io/InputStream;)[B
     691: invokespecial #43                 // Method org/apache/dubbo/common/io/UnsafeByteArrayInputStream."<init>":([B)V
     694: iload         5
     696: invokespecial #74                 // Method org/apache/dubbo/rpc/protocol/dubbo/DecodeableRpcInvocation."<init>":(Lorg/apache/dubbo/rpc/model/FrameworkModel;Lorg/apache/dubbo/remoting/Channel;Lorg/apache/dubbo/remoting/exchange/Request;Ljava/io/InputStream;B)V
     699: astore        11
     701: aload         11
     703: astore        9
     705: aload         8
     707: aload         9
     709: invokevirtual #76                 // Method org/apache/dubbo/remoting/exchange/Request.setData:(Ljava/lang/Object;)V
     712: goto          791
     715: astore        9
     717: getstatic     #48                 // Field log:Lorg/apache/dubbo/common/logger/ErrorTypeAwareLogger;
     720: invokeinterface #49,  1           // InterfaceMethod org/apache/dubbo/common/logger/ErrorTypeAwareLogger.isWarnEnabled:()Z
     725: ifeq          767
     728: getstatic     #48                 // Field log:Lorg/apache/dubbo/common/logger/ErrorTypeAwareLogger;
     731: ldc           #50                 // String 4-20
     733: ldc           #51                 // String
     735: ldc           #51                 // String
     737: new           #52                 // class java/lang/StringBuilder
     740: dup
     741: invokespecial #53                 // Method java/lang/StringBuilder."<init>":()V
     744: ldc           #77                 // String Decode request failed:
     746: invokevirtual #55                 // Method java/lang/StringBuilder.append:(Ljava/lang/String;)Ljava/lang/StringBuilder;
     749: aload         9
     751: invokevirtual #56                 // Method java/lang/Throwable.getMessage:()Ljava/lang/String;
     754: invokevirtual #55                 // Method java/lang/StringBuilder.append:(Ljava/lang/String;)Ljava/lang/StringBuilder;
     757: invokevirtual #57                 // Method java/lang/StringBuilder.toString:()Ljava/lang/String;
     760: aload         9
     762: invokeinterface #58,  6           // InterfaceMethod org/apache/dubbo/common/logger/ErrorTypeAwareLogger.warn:(Ljava/lang/String;Ljava/lang/String;Ljava/lang/String;Ljava/lang/String;Ljava/lang/Throwable;)V
     767: new           #60                 // class org/apache/dubbo/remoting/exchange/HeartBeatRequest
     770: dup
     771: lload         6
     773: invokespecial #61                 // Method org/apache/dubbo/remoting/exchange/HeartBeatRequest."<init>":(J)V
     776: astore        8
     778: aload         8
     780: iconst_1
     781: invokevirtual #78                 // Method org/apache/dubbo/remoting/exchange/Request.setBroken:(Z)V
     784: aload         8
     786: aload         9
     788: invokevirtual #76                 // Method org/apache/dubbo/remoting/exchange/Request.setData:(Ljava/lang/Object;)V
     791: aload         8
     793: areturn
    Exception table:
       from    to  target type
          65   266   269   Class java/lang/Throwable
         341   712   715   Class java/lang/Throwable

  private boolean isDecodeDataInIoThread(org.apache.dubbo.remoting.Channel);
    Code:
       0: aload_1
       1: ldc           #34                 // String decode.in.io.thread
       3: invokeinterface #79,  2           // InterfaceMethod org/apache/dubbo/remoting/Channel.getAttribute:(Ljava/lang/String;)Ljava/lang/Object;
       8: astore_2
       9: aload_2
      10: instanceof    #80                 // class java/lang/Boolean
      13: ifeq          24
      16: aload_2
      17: checkcast     #80                 // class java/lang/Boolean
      20: invokevirtual #81                 // Method java/lang/Boolean.booleanValue:()Z
      23: ireturn
      24: aload_1
      25: invokeinterface #28,  1           // InterfaceMethod org/apache/dubbo/remoting/Channel.getUrl:()Lorg/apache/dubbo/common/URL;
      30: invokevirtual #82                 // Method org/apache/dubbo/common/URL.getOrDefaultApplicationModel:()Lorg/apache/dubbo/rpc/model/ApplicationModel;
      33: invokestatic  #83                 // InterfaceMethod org/apache/dubbo/common/threadpool/manager/ExecutorRepository.getMode:(Lorg/apache/dubbo/rpc/model/ApplicationModel;)Ljava/lang/String;
      36: astore_3
      37: ldc           #84                 // String isolation
      39: aload_3
      40: invokevirtual #85                 // Method java/lang/String.equals:(Ljava/lang/Object;)Z
      43: istore        4
      45: iload         4
      47: ifeq          75
      50: getstatic     #86                 // Field decodeInUserThreadLogged:Ljava/util/concurrent/atomic/AtomicBoolean;
      53: iconst_0
      54: iconst_1
      55: invokevirtual #87                 // Method java/util/concurrent/atomic/AtomicBoolean.compareAndSet:(ZZ)Z
      58: ifne          75
      61: aload_1
      62: ldc           #34                 // String decode.in.io.thread
      64: iconst_1
      65: invokestatic  #88                 // Method java/lang/Boolean.valueOf:(Z)Ljava/lang/Boolean;
      68: invokeinterface #89,  3           // InterfaceMethod org/apache/dubbo/remoting/Channel.setAttribute:(Ljava/lang/String;Ljava/lang/Object;)V
      73: iconst_1
      74: ireturn
      75: aload_1
      76: invokeinterface #28,  1           // InterfaceMethod org/apache/dubbo/remoting/Channel.getUrl:()Lorg/apache/dubbo/common/URL;
      81: ldc           #34                 // String decode.in.io.thread
      83: iconst_0
      84: invokevirtual #35                 // Method org/apache/dubbo/common/URL.getParameter:(Ljava/lang/String;Z)Z
      87: istore        5
      89: iload         4
      91: ifeq          123
      94: iload         5
      96: ifne          123
      99: getstatic     #48                 // Field log:Lorg/apache/dubbo/common/logger/ErrorTypeAwareLogger;
     102: ldc           #90                 // String Because thread pool isolation is enabled on the dubbo protocol, the body can only be decoded on the io thread, and the parameter[decode.in.io.thread] will be ignored
     104: invokeinterface #91,  2           // InterfaceMethod org/apache/dubbo/common/logger/ErrorTypeAwareLogger.info:(Ljava/lang/String;)V
     109: aload_1
     110: ldc           #34                 // String decode.in.io.thread
     112: iconst_1
     113: invokestatic  #88                 // Method java/lang/Boolean.valueOf:(Z)Ljava/lang/Boolean;
     116: invokeinterface #89,  3           // InterfaceMethod org/apache/dubbo/remoting/Channel.setAttribute:(Ljava/lang/String;Ljava/lang/Object;)V
     121: iconst_1
     122: ireturn
     123: aload_1
     124: ldc           #34                 // String decode.in.io.thread
     126: iload         5
     128: invokestatic  #88                 // Method java/lang/Boolean.valueOf:(Z)Ljava/lang/Boolean;
     131: invokeinterface #89,  3           // InterfaceMethod org/apache/dubbo/remoting/Channel.setAttribute:(Ljava/lang/String;Ljava/lang/Object;)V
     136: iload         5
     138: ireturn

  private byte[] readMessageData(java.io.InputStream) throws java.io.IOException;
    Code:
       0: aload_1
       1: invokevirtual #92                 // Method java/io/InputStream.available:()I
       4: ifle          22
       7: aload_1
       8: invokevirtual #92                 // Method java/io/InputStream.available:()I
      11: newarray       byte
      13: astore_2
      14: aload_1
      15: aload_2
      16: invokevirtual #93                 // Method java/io/InputStream.read:([B)I
      19: pop
      20: aload_2
      21: areturn
      22: iconst_0
      23: newarray       byte
      25: areturn

  protected void encodeRequestData(org.apache.dubbo.remoting.Channel, org.apache.dubbo.common.serialize.ObjectOutput, java.lang.Object) throws java.io.IOException;
    Code:
       0: aload_0
       1: aload_1
       2: aload_2
       3: aload_3
       4: getstatic     #94                 // Field DUBBO_VERSION:Ljava/lang/String;
       7: invokevirtual #95                 // Method encodeRequestData:(Lorg/apache/dubbo/remoting/Channel;Lorg/apache/dubbo/common/serialize/ObjectOutput;Ljava/lang/Object;Ljava/lang/String;)V
      10: return

  protected void encodeResponseData(org.apache.dubbo.remoting.Channel, org.apache.dubbo.common.serialize.ObjectOutput, java.lang.Object) throws java.io.IOException;
    Code:
       0: aload_0
       1: aload_1
       2: aload_2
       3: aload_3
       4: getstatic     #94                 // Field DUBBO_VERSION:Ljava/lang/String;
       7: invokevirtual #96                 // Method encodeResponseData:(Lorg/apache/dubbo/remoting/Channel;Lorg/apache/dubbo/common/serialize/ObjectOutput;Ljava/lang/Object;Ljava/lang/String;)V
      10: return

  protected void encodeRequestData(org.apache.dubbo.remoting.Channel, org.apache.dubbo.common.serialize.ObjectOutput, java.lang.Object, java.lang.String) throws java.io.IOException;
    Code:
       0: aload_3
       1: checkcast     #97                 // class org/apache/dubbo/rpc/RpcInvocation
       4: astore        5
       6: aload_2
       7: aload         4
       9: invokeinterface #98,  2           // InterfaceMethod org/apache/dubbo/common/serialize/ObjectOutput.writeUTF:(Ljava/lang/String;)V
      14: aload         5
      16: ldc           #99                 // String interface
      18: invokevirtual #100                // Method org/apache/dubbo/rpc/RpcInvocation.getAttachment:(Ljava/lang/String;)Ljava/lang/String;
      21: astore        6
      23: aload         6
      25: ifnonnull     37
      28: aload         5
      30: ldc           #101                // String path
      32: invokevirtual #100                // Method org/apache/dubbo/rpc/RpcInvocation.getAttachment:(Ljava/lang/String;)Ljava/lang/String;
      35: astore        6
      37: aload_2
      38: aload         6
      40: invokeinterface #98,  2           // InterfaceMethod org/apache/dubbo/common/serialize/ObjectOutput.writeUTF:(Ljava/lang/String;)V
      45: aload_2
      46: aload         5
      48: ldc           #102                // String version
      50: invokevirtual #100                // Method org/apache/dubbo/rpc/RpcInvocation.getAttachment:(Ljava/lang/String;)Ljava/lang/String;
      53: invokeinterface #98,  2           // InterfaceMethod org/apache/dubbo/common/serialize/ObjectOutput.writeUTF:(Ljava/lang/String;)V
      58: aload_2
      59: aload         5
      61: invokevirtual #103                // Method org/apache/dubbo/rpc/RpcInvocation.getMethodName:()Ljava/lang/String;
      64: invokeinterface #98,  2           // InterfaceMethod org/apache/dubbo/common/serialize/ObjectOutput.writeUTF:(Ljava/lang/String;)V
      69: aload_2
      70: aload         5
      72: invokevirtual #104                // Method org/apache/dubbo/rpc/RpcInvocation.getParameterTypesDesc:()Ljava/lang/String;
      75: invokeinterface #98,  2           // InterfaceMethod org/apache/dubbo/common/serialize/ObjectOutput.writeUTF:(Ljava/lang/String;)V
      80: aload         5
      82: invokevirtual #105                // Method org/apache/dubbo/rpc/RpcInvocation.getArguments:()[Ljava/lang/Object;
      85: astore        7
      87: aload         7
      89: ifnull        127
      92: iconst_0
      93: istore        8
      95: iload         8
      97: aload         7
      99: arraylength
     100: if_icmpge     127
     103: aload_2
     104: aload_0
     105: getfield      #8                  // Field callbackServiceCodec:Lorg/apache/dubbo/rpc/protocol/dubbo/CallbackServiceCodec;
     108: aload_1
     109: aload         5
     111: iload         8
     113: invokevirtual #106                // Method org/apache/dubbo/rpc/protocol/dubbo/CallbackServiceCodec.encodeInvocationArgument:(Lorg/apache/dubbo/remoting/Channel;Lorg/apache/dubbo/rpc/RpcInvocation;I)Ljava/lang/Object;
     116: invokeinterface #107,  2          // InterfaceMethod org/apache/dubbo/common/serialize/ObjectOutput.writeObject:(Ljava/lang/Object;)V
     121: iinc          8, 1
     124: goto          95
     127: aload_2
     128: aload         5
     130: invokevirtual #108                // Method org/apache/dubbo/rpc/RpcInvocation.getObjectAttachments:()Ljava/util/Map;
     133: invokeinterface #109,  2          // InterfaceMethod org/apache/dubbo/common/serialize/ObjectOutput.writeAttachments:(Ljava/util/Map;)V
     138: return

  protected void encodeResponseData(org.apache.dubbo.remoting.Channel, org.apache.dubbo.common.serialize.ObjectOutput, java.lang.Object, java.lang.String) throws java.io.IOException;
    Code:
       0: aload_3
       1: checkcast     #110                // class org/apache/dubbo/rpc/Result
       4: astore        5
       6: aload         4
       8: invokestatic  #111                // Method org/apache/dubbo/common/Version.isSupportResponseAttachment:(Ljava/lang/String;)Z
      11: istore        6
      13: aload         5
      15: invokeinterface #112,  1          // InterfaceMethod org/apache/dubbo/rpc/Result.getException:()Ljava/lang/Throwable;
      20: astore        7
      22: aload         7
      24: ifnonnull     87
      27: aload         5
      29: invokeinterface #113,  1          // InterfaceMethod org/apache/dubbo/rpc/Result.getValue:()Ljava/lang/Object;
      34: astore        8
      36: aload         8
      38: ifnonnull     60
      41: aload_2
      42: iload         6
      44: ifeq          51
      47: iconst_5
      48: goto          52
      51: iconst_2
      52: invokeinterface #114,  2          // InterfaceMethod org/apache/dubbo/common/serialize/ObjectOutput.writeByte:(B)V
      57: goto          84
      60: aload_2
      61: iload         6
      63: ifeq          70
      66: iconst_4
      67: goto          71
      70: iconst_1
      71: invokeinterface #114,  2          // InterfaceMethod org/apache/dubbo/common/serialize/ObjectOutput.writeByte:(B)V
      76: aload_2
      77: aload         8
      79: invokeinterface #107,  2          // InterfaceMethod org/apache/dubbo/common/serialize/ObjectOutput.writeObject:(Ljava/lang/Object;)V
      84: goto          111
      87: aload_2
      88: iload         6
      90: ifeq          97
      93: iconst_3
      94: goto          98
      97: iconst_0
      98: invokeinterface #114,  2          // InterfaceMethod org/apache/dubbo/common/serialize/ObjectOutput.writeByte:(B)V
     103: aload_2
     104: aload         7
     106: invokeinterface #115,  2          // InterfaceMethod org/apache/dubbo/common/serialize/ObjectOutput.writeThrowable:(Ljava/lang/Throwable;)V
     111: iload         6
     113: ifeq          147
     116: aload         5
     118: invokeinterface #116,  1          // InterfaceMethod org/apache/dubbo/rpc/Result.getObjectAttachments:()Ljava/util/Map;
     123: ldc           #117                // String dubbo
     125: invokestatic  #62                 // Method org/apache/dubbo/common/Version.getProtocolVersion:()Ljava/lang/String;
     128: invokeinterface #118,  3          // InterfaceMethod java/util/Map.put:(Ljava/lang/Object;Ljava/lang/Object;)Ljava/lang/Object;
     133: pop
     134: aload_2
     135: aload         5
     137: invokeinterface #116,  1          // InterfaceMethod org/apache/dubbo/rpc/Result.getObjectAttachments:()Ljava/util/Map;
     142: invokeinterface #109,  2          // InterfaceMethod org/apache/dubbo/common/serialize/ObjectOutput.writeAttachments:(Ljava/util/Map;)V
     147: return

  protected org.apache.dubbo.common.serialize.Serialization getSerialization(org.apache.dubbo.remoting.Channel, org.apache.dubbo.remoting.exchange.Request);
    Code:
       0: aload_2
       1: invokevirtual #119                // Method org/apache/dubbo/remoting/exchange/Request.getData:()Ljava/lang/Object;
       4: instanceof    #38                 // class org/apache/dubbo/rpc/Invocation
       7: ifne          17
      10: aload_0
      11: aload_1
      12: aload_2
      13: invokespecial #120                // Method org/apache/dubbo/remoting/exchange/codec/ExchangeCodec.getSerialization:(Lorg/apache/dubbo/remoting/Channel;Lorg/apache/dubbo/remoting/exchange/Request;)Lorg/apache/dubbo/common/serialize/Serialization;
      16: areturn
      17: aload_1
      18: invokeinterface #28,  1           // InterfaceMethod org/apache/dubbo/remoting/Channel.getUrl:()Lorg/apache/dubbo/common/URL;
      23: aload_2
      24: invokevirtual #119                // Method org/apache/dubbo/remoting/exchange/Request.getData:()Ljava/lang/Object;
      27: checkcast     #38                 // class org/apache/dubbo/rpc/Invocation
      30: invokestatic  #121                // Method org/apache/dubbo/rpc/protocol/dubbo/DubboCodecSupport.getRequestSerialization:(Lorg/apache/dubbo/common/URL;Lorg/apache/dubbo/rpc/Invocation;)Lorg/apache/dubbo/common/serialize/Serialization;
      33: areturn

  protected org.apache.dubbo.common.serialize.Serialization getSerialization(org.apache.dubbo.remoting.Channel, org.apache.dubbo.remoting.exchange.Response);
    Code:
       0: aload_2
       1: instanceof    #122                // class org/apache/dubbo/remoting/exchange/HeartBeatResponse
       4: ifeq          21
       7: aload_2
       8: checkcast     #122                // class org/apache/dubbo/remoting/exchange/HeartBeatResponse
      11: invokevirtual #123                // Method org/apache/dubbo/remoting/exchange/HeartBeatResponse.getProto:()B
      14: invokestatic  #124                // Method java/lang/Byte.valueOf:(B)Ljava/lang/Byte;
      17: invokestatic  #125                // Method org/apache/dubbo/remoting/transport/CodecSupport.getSerializationById:(Ljava/lang/Byte;)Lorg/apache/dubbo/common/serialize/Serialization;
      20: areturn
      21: aload_2
      22: invokevirtual #126                // Method org/apache/dubbo/remoting/exchange/Response.getResult:()Ljava/lang/Object;
      25: instanceof    #127                // class org/apache/dubbo/rpc/AppResponse
      28: ifne          38
      31: aload_0
      32: aload_1
      33: aload_2
      34: invokespecial #128                // Method org/apache/dubbo/remoting/exchange/codec/ExchangeCodec.getSerialization:(Lorg/apache/dubbo/remoting/Channel;Lorg/apache/dubbo/remoting/exchange/Response;)Lorg/apache/dubbo/common/serialize/Serialization;
      37: areturn
      38: aload_1
      39: invokeinterface #28,  1           // InterfaceMethod org/apache/dubbo/remoting/Channel.getUrl:()Lorg/apache/dubbo/common/URL;
      44: aload_2
      45: invokevirtual #126                // Method org/apache/dubbo/remoting/exchange/Response.getResult:()Ljava/lang/Object;
      48: checkcast     #127                // class org/apache/dubbo/rpc/AppResponse
      51: invokestatic  #129                // Method org/apache/dubbo/rpc/protocol/dubbo/DubboCodecSupport.getResponseSerialization:(Lorg/apache/dubbo/common/URL;Lorg/apache/dubbo/rpc/AppResponse;)Lorg/apache/dubbo/common/serialize/Serialization;
      54: areturn

  private static org.apache.dubbo.rpc.protocol.dubbo.ByteAccessor lambda$new$0(org.apache.dubbo.rpc.model.FrameworkModel, java.lang.String);
    Code:
       0: aload_0
       1: ldc           #17                 // class org/apache/dubbo/rpc/protocol/dubbo/ByteAccessor
       3: invokevirtual #130                // Method org/apache/dubbo/rpc/model/FrameworkModel.getExtensionLoader:(Ljava/lang/Class;)Lorg/apache/dubbo/common/extension/ExtensionLoader;
       6: aload_1
       7: invokevirtual #131                // Method org/apache/dubbo/common/extension/ExtensionLoader.getExtension:(Ljava/lang/String;)Ljava/lang/Object;
      10: checkcast     #17                 // class org/apache/dubbo/rpc/protocol/dubbo/ByteAccessor
      13: areturn

  static {};
    Code:
       0: invokestatic  #62                 // Method org/apache/dubbo/common/Version.getProtocolVersion:()Ljava/lang/String;
       3: putstatic     #94                 // Field DUBBO_VERSION:Ljava/lang/String;
       6: iconst_0
       7: anewarray     #132                // class java/lang/Object
      10: putstatic     #133                // Field EMPTY_OBJECT_ARRAY:[Ljava/lang/Object;
      13: iconst_0
      14: anewarray     #134                // class java/lang/Class
      17: putstatic     #135                // Field EMPTY_CLASS_ARRAY:[Ljava/lang/Class;
      20: ldc           #33                 // class org/apache/dubbo/rpc/protocol/dubbo/DubboCodec
      22: invokestatic  #136                // Method org/apache/dubbo/common/logger/LoggerFactory.getErrorTypeAwareLogger:(Ljava/lang/Class;)Lorg/apache/dubbo/common/logger/ErrorTypeAwareLogger;
      25: putstatic     #48                 // Field log:Lorg/apache/dubbo/common/logger/ErrorTypeAwareLogger;
      28: new           #137                // class java/util/concurrent/atomic/AtomicBoolean
      31: dup
      32: iconst_0
      33: invokespecial #138                // Method java/util/concurrent/atomic/AtomicBoolean."<init>":(Z)V
      36: putstatic     #86                 // Field decodeInUserThreadLogged:Ljava/util/concurrent/atomic/AtomicBoolean;
      39: return
}
