Compiled from "DubboProtocol.java"
class org.apache.dubbo.rpc.protocol.dubbo.DubboProtocol$1 extends org.apache.dubbo.remoting.exchange.support.ExchangeHandlerAdapter {
  final org.apache.dubbo.rpc.protocol.dubbo.DubboProtocol this$0;

  org.apache.dubbo.rpc.protocol.dubbo.DubboProtocol$1(org.apache.dubbo.rpc.protocol.dubbo.DubboProtocol, org.apache.dubbo.rpc.model.FrameworkModel);
    Code:
       0: aload_0
       1: aload_1
       2: putfield      #5                  // Field this$0:Lorg/apache/dubbo/rpc/protocol/dubbo/DubboProtocol;
       5: aload_0
       6: aload_2
       7: invokespecial #6                  // Method org/apache/dubbo/remoting/exchange/support/ExchangeHandlerAdapter."<init>":(Lorg/apache/dubbo/rpc/model/FrameworkModel;)V
      10: return

  public java.util.concurrent.CompletableFuture<java.lang.Object> reply(org.apache.dubbo.remoting.exchange.ExchangeChannel, java.lang.Object) throws org.apache.dubbo.remoting.RemotingException;
    Code:
       0: aload_2
       1: instanceof    #7                  // class org/apache/dubbo/rpc/Invocation
       4: ifne          99
       7: new           #8                  // class org/apache/dubbo/remoting/RemotingException
      10: dup
      11: aload_1
      12: new           #9                  // class java/lang/StringBuilder
      15: dup
      16: invokespecial #10                 // Method java/lang/StringBuilder."<init>":()V
      19: ldc           #11                 // String Unsupported request:
      21: invokevirtual #12                 // Method java/lang/StringBuilder.append:(Ljava/lang/String;)Ljava/lang/StringBuilder;
      24: aload_2
      25: ifnonnull     32
      28: aconst_null
      29: goto          61
      32: new           #9                  // class java/lang/StringBuilder
      35: dup
      36: invokespecial #10                 // Method java/lang/StringBuilder."<init>":()V
      39: aload_2
      40: invokevirtual #13                 // Method java/lang/Object.getClass:()Ljava/lang/Class;
      43: invokevirtual #14                 // Method java/lang/Class.getName:()Ljava/lang/String;
      46: invokevirtual #12                 // Method java/lang/StringBuilder.append:(Ljava/lang/String;)Ljava/lang/StringBuilder;
      49: ldc           #15                 // String :
      51: invokevirtual #12                 // Method java/lang/StringBuilder.append:(Ljava/lang/String;)Ljava/lang/StringBuilder;
      54: aload_2
      55: invokevirtual #16                 // Method java/lang/StringBuilder.append:(Ljava/lang/Object;)Ljava/lang/StringBuilder;
      58: invokevirtual #17                 // Method java/lang/StringBuilder.toString:()Ljava/lang/String;
      61: invokevirtual #12                 // Method java/lang/StringBuilder.append:(Ljava/lang/String;)Ljava/lang/StringBuilder;
      64: ldc           #18                 // String , channel: consumer:
      66: invokevirtual #12                 // Method java/lang/StringBuilder.append:(Ljava/lang/String;)Ljava/lang/StringBuilder;
      69: aload_1
      70: invokeinterface #19,  1           // InterfaceMethod org/apache/dubbo/remoting/exchange/ExchangeChannel.getRemoteAddress:()Ljava/net/InetSocketAddress;
      75: invokevirtual #16                 // Method java/lang/StringBuilder.append:(Ljava/lang/Object;)Ljava/lang/StringBuilder;
      78: ldc           #20                 // String  --> provider:
      80: invokevirtual #12                 // Method java/lang/StringBuilder.append:(Ljava/lang/String;)Ljava/lang/StringBuilder;
      83: aload_1
      84: invokeinterface #21,  1           // InterfaceMethod org/apache/dubbo/remoting/exchange/ExchangeChannel.getLocalAddress:()Ljava/net/InetSocketAddress;
      89: invokevirtual #16                 // Method java/lang/StringBuilder.append:(Ljava/lang/Object;)Ljava/lang/StringBuilder;
      92: invokevirtual #17                 // Method java/lang/StringBuilder.toString:()Ljava/lang/String;
      95: invokespecial #22                 // Method org/apache/dubbo/remoting/RemotingException."<init>":(Lorg/apache/dubbo/remoting/Channel;Ljava/lang/String;)V
      98: athrow
      99: aload_2
     100: checkcast     #7                  // class org/apache/dubbo/rpc/Invocation
     103: astore_3
     104: aload_3
     105: invokeinterface #23,  1           // InterfaceMethod org/apache/dubbo/rpc/Invocation.getInvoker:()Lorg/apache/dubbo/rpc/Invoker;
     110: ifnonnull     125
     113: aload_0
     114: getfield      #5                  // Field this$0:Lorg/apache/dubbo/rpc/protocol/dubbo/DubboProtocol;
     117: aload_1
     118: aload_3
     119: invokevirtual #24                 // Method org/apache/dubbo/rpc/protocol/dubbo/DubboProtocol.getInvoker:(Lorg/apache/dubbo/remoting/Channel;Lorg/apache/dubbo/rpc/Invocation;)Lorg/apache/dubbo/rpc/Invoker;
     122: goto          131
     125: aload_3
     126: invokeinterface #23,  1           // InterfaceMethod org/apache/dubbo/rpc/Invocation.getInvoker:()Lorg/apache/dubbo/rpc/Invoker;
     131: astore        4
     133: aload         4
     135: invokeinterface #25,  1           // InterfaceMethod org/apache/dubbo/rpc/Invoker.getUrl:()Lorg/apache/dubbo/common/URL;
     140: invokevirtual #26                 // Method org/apache/dubbo/common/URL.getServiceModel:()Lorg/apache/dubbo/rpc/model/ServiceModel;
     143: ifnull        165
     146: invokestatic  #27                 // Method java/lang/Thread.currentThread:()Ljava/lang/Thread;
     149: aload         4
     151: invokeinterface #25,  1           // InterfaceMethod org/apache/dubbo/rpc/Invoker.getUrl:()Lorg/apache/dubbo/common/URL;
     156: invokevirtual #26                 // Method org/apache/dubbo/common/URL.getServiceModel:()Lorg/apache/dubbo/rpc/model/ServiceModel;
     159: invokevirtual #28                 // Method org/apache/dubbo/rpc/model/ServiceModel.getClassLoader:()Ljava/lang/ClassLoader;
     162: invokevirtual #29                 // Method java/lang/Thread.setContextClassLoader:(Ljava/lang/ClassLoader;)V
     165: getstatic     #30                 // Field java/lang/Boolean.TRUE:Ljava/lang/Boolean;
     168: invokevirtual #31                 // Method java/lang/Boolean.toString:()Ljava/lang/String;
     171: aload_3
     172: ldc           #32                 // String _isCallBackServiceInvoke
     174: invokeinterface #33,  2           // InterfaceMethod org/apache/dubbo/rpc/Invocation.getObjectAttachmentWithoutConvert:(Ljava/lang/String;)Ljava/lang/Object;
     179: invokevirtual #34                 // Method java/lang/String.equals:(Ljava/lang/Object;)Z
     182: ifeq          395
     185: aload         4
     187: invokeinterface #25,  1           // InterfaceMethod org/apache/dubbo/rpc/Invoker.getUrl:()Lorg/apache/dubbo/common/URL;
     192: invokevirtual #35                 // Method org/apache/dubbo/common/URL.getParameters:()Ljava/util/Map;
     195: ldc           #36                 // String methods
     197: invokeinterface #37,  2           // InterfaceMethod java/util/Map.get:(Ljava/lang/Object;)Ljava/lang/Object;
     202: checkcast     #38                 // class java/lang/String
     205: astore        5
     207: iconst_0
     208: istore        6
     210: aload         5
     212: ifnull        225
     215: aload         5
     217: ldc           #39                 // String ,
     219: invokevirtual #40                 // Method java/lang/String.contains:(Ljava/lang/CharSequence;)Z
     222: ifne          241
     225: aload_3
     226: invokeinterface #41,  1           // InterfaceMethod org/apache/dubbo/rpc/Invocation.getMethodName:()Ljava/lang/String;
     231: aload         5
     233: invokevirtual #34                 // Method java/lang/String.equals:(Ljava/lang/Object;)Z
     236: istore        6
     238: goto          302
     241: aload         5
     243: ldc           #39                 // String ,
     245: invokevirtual #42                 // Method java/lang/String.split:(Ljava/lang/String;)[Ljava/lang/String;
     248: astore        7
     250: aload         7
     252: astore        8
     254: aload         8
     256: arraylength
     257: istore        9
     259: iconst_0
     260: istore        10
     262: iload         10
     264: iload         9
     266: if_icmpge     302
     269: aload         8
     271: iload         10
     273: aaload
     274: astore        11
     276: aload_3
     277: invokeinterface #41,  1           // InterfaceMethod org/apache/dubbo/rpc/Invocation.getMethodName:()Ljava/lang/String;
     282: aload         11
     284: invokevirtual #34                 // Method java/lang/String.equals:(Ljava/lang/Object;)Z
     287: ifeq          296
     290: iconst_1
     291: istore        6
     293: goto          302
     296: iinc          10, 1
     299: goto          262
     302: iload         6
     304: ifne          395
     307: aload_0
     308: getfield      #5                  // Field this$0:Lorg/apache/dubbo/rpc/protocol/dubbo/DubboProtocol;
     311: invokestatic  #43                 // Method org/apache/dubbo/rpc/protocol/dubbo/DubboProtocol.access$000:(Lorg/apache/dubbo/rpc/protocol/dubbo/DubboProtocol;)Lorg/apache/dubbo/common/logger/ErrorTypeAwareLogger;
     314: ldc           #44                 // String 4-3
     316: ldc           #45                 // String
     318: ldc           #45                 // String
     320: new           #9                  // class java/lang/StringBuilder
     323: dup
     324: invokespecial #10                 // Method java/lang/StringBuilder."<init>":()V
     327: new           #46                 // class java/lang/IllegalStateException
     330: dup
     331: new           #9                  // class java/lang/StringBuilder
     334: dup
     335: invokespecial #10                 // Method java/lang/StringBuilder."<init>":()V
     338: ldc           #47                 // String The methodName
     340: invokevirtual #12                 // Method java/lang/StringBuilder.append:(Ljava/lang/String;)Ljava/lang/StringBuilder;
     343: aload_3
     344: invokeinterface #41,  1           // InterfaceMethod org/apache/dubbo/rpc/Invocation.getMethodName:()Ljava/lang/String;
     349: invokevirtual #12                 // Method java/lang/StringBuilder.append:(Ljava/lang/String;)Ljava/lang/StringBuilder;
     352: ldc           #48                 // String  not found in callback service interface ,invoke will be ignored. please update the api interface. url is:
     354: invokevirtual #12                 // Method java/lang/StringBuilder.append:(Ljava/lang/String;)Ljava/lang/StringBuilder;
     357: aload         4
     359: invokeinterface #25,  1           // InterfaceMethod org/apache/dubbo/rpc/Invoker.getUrl:()Lorg/apache/dubbo/common/URL;
     364: invokevirtual #16                 // Method java/lang/StringBuilder.append:(Ljava/lang/Object;)Ljava/lang/StringBuilder;
     367: invokevirtual #17                 // Method java/lang/StringBuilder.toString:()Ljava/lang/String;
     370: invokespecial #49                 // Method java/lang/IllegalStateException."<init>":(Ljava/lang/String;)V
     373: invokevirtual #16                 // Method java/lang/StringBuilder.append:(Ljava/lang/Object;)Ljava/lang/StringBuilder;
     376: ldc           #50                 // String  ,invocation is :
     378: invokevirtual #12                 // Method java/lang/StringBuilder.append:(Ljava/lang/String;)Ljava/lang/StringBuilder;
     381: aload_3
     382: invokevirtual #16                 // Method java/lang/StringBuilder.append:(Ljava/lang/Object;)Ljava/lang/StringBuilder;
     385: invokevirtual #17                 // Method java/lang/StringBuilder.toString:()Ljava/lang/String;
     388: invokeinterface #51,  5           // InterfaceMethod org/apache/dubbo/common/logger/ErrorTypeAwareLogger.warn:(Ljava/lang/String;Ljava/lang/String;Ljava/lang/String;Ljava/lang/String;)V
     393: aconst_null
     394: areturn
     395: invokestatic  #52                 // Method org/apache/dubbo/rpc/RpcContext.getServiceContext:()Lorg/apache/dubbo/rpc/RpcServiceContext;
     398: aload_1
     399: invokeinterface #19,  1           // InterfaceMethod org/apache/dubbo/remoting/exchange/ExchangeChannel.getRemoteAddress:()Ljava/net/InetSocketAddress;
     404: invokevirtual #53                 // Method org/apache/dubbo/rpc/RpcServiceContext.setRemoteAddress:(Ljava/net/InetSocketAddress;)Lorg/apache/dubbo/rpc/RpcServiceContext;
     407: pop
     408: aload         4
     410: aload_3
     411: invokeinterface #54,  2           // InterfaceMethod org/apache/dubbo/rpc/Invoker.invoke:(Lorg/apache/dubbo/rpc/Invocation;)Lorg/apache/dubbo/rpc/Result;
     416: astore        5
     418: aload         5
     420: invokestatic  #55                 // InterfaceMethod java/util/function/Function.identity:()Ljava/util/function/Function;
     423: invokeinterface #56,  2           // InterfaceMethod org/apache/dubbo/rpc/Result.thenApply:(Ljava/util/function/Function;)Ljava/util/concurrent/CompletableFuture;
     428: areturn

  public void received(org.apache.dubbo.remoting.Channel, java.lang.Object) throws org.apache.dubbo.remoting.RemotingException;
    Code:
       0: aload_2
       1: instanceof    #7                  // class org/apache/dubbo/rpc/Invocation
       4: ifeq          20
       7: aload_0
       8: aload_1
       9: checkcast     #57                 // class org/apache/dubbo/remoting/exchange/ExchangeChannel
      12: aload_2
      13: invokevirtual #58                 // Method reply:(Lorg/apache/dubbo/remoting/exchange/ExchangeChannel;Ljava/lang/Object;)Ljava/util/concurrent/CompletableFuture;
      16: pop
      17: goto          26
      20: aload_0
      21: aload_1
      22: aload_2
      23: invokespecial #59                 // Method org/apache/dubbo/remoting/exchange/support/ExchangeHandlerAdapter.received:(Lorg/apache/dubbo/remoting/Channel;Ljava/lang/Object;)V
      26: return

  public void connected(org.apache.dubbo.remoting.Channel) throws org.apache.dubbo.remoting.RemotingException;
    Code:
       0: aload_0
       1: aload_1
       2: ldc           #60                 // String onconnect
       4: invokespecial #61                 // Method invoke:(Lorg/apache/dubbo/remoting/Channel;Ljava/lang/String;)V
       7: return

  public void disconnected(org.apache.dubbo.remoting.Channel) throws org.apache.dubbo.remoting.RemotingException;
    Code:
       0: aload_0
       1: getfield      #5                  // Field this$0:Lorg/apache/dubbo/rpc/protocol/dubbo/DubboProtocol;
       4: invokestatic  #62                 // Method org/apache/dubbo/rpc/protocol/dubbo/DubboProtocol.access$100:(Lorg/apache/dubbo/rpc/protocol/dubbo/DubboProtocol;)Lorg/apache/dubbo/common/logger/ErrorTypeAwareLogger;
       7: invokeinterface #63,  1           // InterfaceMethod org/apache/dubbo/common/logger/ErrorTypeAwareLogger.isDebugEnabled:()Z
      12: ifeq          65
      15: aload_0
      16: getfield      #5                  // Field this$0:Lorg/apache/dubbo/rpc/protocol/dubbo/DubboProtocol;
      19: invokestatic  #64                 // Method org/apache/dubbo/rpc/protocol/dubbo/DubboProtocol.access$200:(Lorg/apache/dubbo/rpc/protocol/dubbo/DubboProtocol;)Lorg/apache/dubbo/common/logger/ErrorTypeAwareLogger;
      22: new           #9                  // class java/lang/StringBuilder
      25: dup
      26: invokespecial #10                 // Method java/lang/StringBuilder."<init>":()V
      29: ldc           #65                 // String disconnected from
      31: invokevirtual #12                 // Method java/lang/StringBuilder.append:(Ljava/lang/String;)Ljava/lang/StringBuilder;
      34: aload_1
      35: invokeinterface #66,  1           // InterfaceMethod org/apache/dubbo/remoting/Channel.getRemoteAddress:()Ljava/net/InetSocketAddress;
      40: invokevirtual #16                 // Method java/lang/StringBuilder.append:(Ljava/lang/Object;)Ljava/lang/StringBuilder;
      43: ldc           #67                 // String ,url:
      45: invokevirtual #12                 // Method java/lang/StringBuilder.append:(Ljava/lang/String;)Ljava/lang/StringBuilder;
      48: aload_1
      49: invokeinterface #68,  1           // InterfaceMethod org/apache/dubbo/remoting/Channel.getUrl:()Lorg/apache/dubbo/common/URL;
      54: invokevirtual #16                 // Method java/lang/StringBuilder.append:(Ljava/lang/Object;)Ljava/lang/StringBuilder;
      57: invokevirtual #17                 // Method java/lang/StringBuilder.toString:()Ljava/lang/String;
      60: invokeinterface #69,  2           // InterfaceMethod org/apache/dubbo/common/logger/ErrorTypeAwareLogger.debug:(Ljava/lang/String;)V
      65: aload_0
      66: aload_1
      67: ldc           #70                 // String ondisconnect
      69: invokespecial #61                 // Method invoke:(Lorg/apache/dubbo/remoting/Channel;Ljava/lang/String;)V
      72: return

  private void invoke(org.apache.dubbo.remoting.Channel, java.lang.String);
    Code:
       0: aload_0
       1: aload_1
       2: aload_1
       3: invokeinterface #68,  1           // InterfaceMethod org/apache/dubbo/remoting/Channel.getUrl:()Lorg/apache/dubbo/common/URL;
       8: aload_2
       9: invokespecial #71                 // Method createInvocation:(Lorg/apache/dubbo/remoting/Channel;Lorg/apache/dubbo/common/URL;Ljava/lang/String;)Lorg/apache/dubbo/rpc/Invocation;
      12: astore_3
      13: aload_3
      14: ifnull        111
      17: getstatic     #30                 // Field java/lang/Boolean.TRUE:Ljava/lang/Boolean;
      20: invokevirtual #31                 // Method java/lang/Boolean.toString:()Ljava/lang/String;
      23: aload_3
      24: ldc           #72                 // String dubbo.stub.event
      26: invokeinterface #73,  2           // InterfaceMethod org/apache/dubbo/rpc/Invocation.getAttachment:(Ljava/lang/String;)Ljava/lang/String;
      31: invokevirtual #34                 // Method java/lang/String.equals:(Ljava/lang/Object;)Z
      34: ifeq          43
      37: aload_0
      38: aload_1
      39: aload_3
      40: invokespecial #74                 // Method tryToGetStubService:(Lorg/apache/dubbo/remoting/Channel;Lorg/apache/dubbo/rpc/Invocation;)V
      43: aload_0
      44: aload_1
      45: aload_3
      46: invokevirtual #75                 // Method received:(Lorg/apache/dubbo/remoting/Channel;Ljava/lang/Object;)V
      49: goto          111
      52: astore        4
      54: aload_0
      55: getfield      #5                  // Field this$0:Lorg/apache/dubbo/rpc/protocol/dubbo/DubboProtocol;
      58: invokestatic  #77                 // Method org/apache/dubbo/rpc/protocol/dubbo/DubboProtocol.access$300:(Lorg/apache/dubbo/rpc/protocol/dubbo/DubboProtocol;)Lorg/apache/dubbo/common/logger/ErrorTypeAwareLogger;
      61: ldc           #44                 // String 4-3
      63: ldc           #45                 // String
      65: ldc           #45                 // String
      67: new           #9                  // class java/lang/StringBuilder
      70: dup
      71: invokespecial #10                 // Method java/lang/StringBuilder."<init>":()V
      74: ldc           #78                 // String Failed to invoke event method
      76: invokevirtual #12                 // Method java/lang/StringBuilder.append:(Ljava/lang/String;)Ljava/lang/StringBuilder;
      79: aload_3
      80: invokeinterface #41,  1           // InterfaceMethod org/apache/dubbo/rpc/Invocation.getMethodName:()Ljava/lang/String;
      85: invokevirtual #12                 // Method java/lang/StringBuilder.append:(Ljava/lang/String;)Ljava/lang/StringBuilder;
      88: ldc           #79                 // String (), cause:
      90: invokevirtual #12                 // Method java/lang/StringBuilder.append:(Ljava/lang/String;)Ljava/lang/StringBuilder;
      93: aload         4
      95: invokevirtual #80                 // Method java/lang/Throwable.getMessage:()Ljava/lang/String;
      98: invokevirtual #12                 // Method java/lang/StringBuilder.append:(Ljava/lang/String;)Ljava/lang/StringBuilder;
     101: invokevirtual #17                 // Method java/lang/StringBuilder.toString:()Ljava/lang/String;
     104: aload         4
     106: invokeinterface #81,  6           // InterfaceMethod org/apache/dubbo/common/logger/ErrorTypeAwareLogger.warn:(Ljava/lang/String;Ljava/lang/String;Ljava/lang/String;Ljava/lang/String;Ljava/lang/Throwable;)V
     111: return
    Exception table:
       from    to  target type
          17    49    52   Class java/lang/Throwable

  private void tryToGetStubService(org.apache.dubbo.remoting.Channel, org.apache.dubbo.rpc.Invocation) throws org.apache.dubbo.remoting.RemotingException;
    Code:
       0: aload_0
       1: getfield      #5                  // Field this$0:Lorg/apache/dubbo/rpc/protocol/dubbo/DubboProtocol;
       4: aload_1
       5: aload_2
       6: invokevirtual #24                 // Method org/apache/dubbo/rpc/protocol/dubbo/DubboProtocol.getInvoker:(Lorg/apache/dubbo/remoting/Channel;Lorg/apache/dubbo/rpc/Invocation;)Lorg/apache/dubbo/rpc/Invoker;
       9: astore_3
      10: goto          87
      13: astore_3
      14: iconst_0
      15: aload_2
      16: ldc           #82                 // String path
      18: invokeinterface #33,  2           // InterfaceMethod org/apache/dubbo/rpc/Invocation.getObjectAttachmentWithoutConvert:(Ljava/lang/String;)Ljava/lang/Object;
      23: checkcast     #38                 // class java/lang/String
      26: aload_2
      27: ldc           #83                 // String version
      29: invokeinterface #33,  2           // InterfaceMethod org/apache/dubbo/rpc/Invocation.getObjectAttachmentWithoutConvert:(Ljava/lang/String;)Ljava/lang/Object;
      34: checkcast     #38                 // class java/lang/String
      37: aload_2
      38: ldc           #84                 // String group
      40: invokeinterface #33,  2           // InterfaceMethod org/apache/dubbo/rpc/Invocation.getObjectAttachmentWithoutConvert:(Ljava/lang/String;)Ljava/lang/Object;
      45: checkcast     #38                 // class java/lang/String
      48: invokestatic  #85                 // Method org/apache/dubbo/rpc/protocol/dubbo/DubboProtocol.access$400:(ILjava/lang/String;Ljava/lang/String;Ljava/lang/String;)Ljava/lang/String;
      51: astore        4
      53: new           #8                  // class org/apache/dubbo/remoting/RemotingException
      56: dup
      57: aload_1
      58: new           #9                  // class java/lang/StringBuilder
      61: dup
      62: invokespecial #10                 // Method java/lang/StringBuilder."<init>":()V
      65: ldc           #86                 // String The stub service[
      67: invokevirtual #12                 // Method java/lang/StringBuilder.append:(Ljava/lang/String;)Ljava/lang/StringBuilder;
      70: aload         4
      72: invokevirtual #12                 // Method java/lang/StringBuilder.append:(Ljava/lang/String;)Ljava/lang/StringBuilder;
      75: ldc           #87                 // String ] is not found, it may not be exported yet
      77: invokevirtual #12                 // Method java/lang/StringBuilder.append:(Ljava/lang/String;)Ljava/lang/StringBuilder;
      80: invokevirtual #17                 // Method java/lang/StringBuilder.toString:()Ljava/lang/String;
      83: invokespecial #22                 // Method org/apache/dubbo/remoting/RemotingException."<init>":(Lorg/apache/dubbo/remoting/Channel;Ljava/lang/String;)V
      86: athrow
      87: return
    Exception table:
       from    to  target type
           0    10    13   Class org/apache/dubbo/remoting/RemotingException

  private org.apache.dubbo.rpc.Invocation createInvocation(org.apache.dubbo.remoting.Channel, org.apache.dubbo.common.URL, java.lang.String);
    Code:
       0: aload_2
       1: aload_3
       2: invokevirtual #88                 // Method org/apache/dubbo/common/URL.getParameter:(Ljava/lang/String;)Ljava/lang/String;
       5: astore        4
       7: aload         4
       9: ifnull        20
      12: aload         4
      14: invokevirtual #89                 // Method java/lang/String.length:()I
      17: ifne          22
      20: aconst_null
      21: areturn
      22: new           #90                 // class org/apache/dubbo/rpc/RpcInvocation
      25: dup
      26: aload_2
      27: invokevirtual #26                 // Method org/apache/dubbo/common/URL.getServiceModel:()Lorg/apache/dubbo/rpc/model/ServiceModel;
      30: aload         4
      32: aload_2
      33: ldc           #91                 // String interface
      35: invokevirtual #88                 // Method org/apache/dubbo/common/URL.getParameter:(Ljava/lang/String;)Ljava/lang/String;
      38: ldc           #45                 // String
      40: iconst_0
      41: anewarray     #92                 // class java/lang/Class
      44: iconst_0
      45: anewarray     #93                 // class java/lang/Object
      48: invokespecial #94                 // Method org/apache/dubbo/rpc/RpcInvocation."<init>":(Lorg/apache/dubbo/rpc/model/ServiceModel;Ljava/lang/String;Ljava/lang/String;Ljava/lang/String;[Ljava/lang/Class;[Ljava/lang/Object;)V
      51: astore        5
      53: aload         5
      55: ldc           #82                 // String path
      57: aload_2
      58: invokevirtual #95                 // Method org/apache/dubbo/common/URL.getPath:()Ljava/lang/String;
      61: invokevirtual #96                 // Method org/apache/dubbo/rpc/RpcInvocation.setAttachment:(Ljava/lang/String;Ljava/lang/String;)V
      64: aload         5
      66: ldc           #84                 // String group
      68: aload_2
      69: invokevirtual #97                 // Method org/apache/dubbo/common/URL.getGroup:()Ljava/lang/String;
      72: invokevirtual #96                 // Method org/apache/dubbo/rpc/RpcInvocation.setAttachment:(Ljava/lang/String;Ljava/lang/String;)V
      75: aload         5
      77: ldc           #91                 // String interface
      79: aload_2
      80: ldc           #91                 // String interface
      82: invokevirtual #88                 // Method org/apache/dubbo/common/URL.getParameter:(Ljava/lang/String;)Ljava/lang/String;
      85: invokevirtual #96                 // Method org/apache/dubbo/rpc/RpcInvocation.setAttachment:(Ljava/lang/String;Ljava/lang/String;)V
      88: aload         5
      90: ldc           #83                 // String version
      92: aload_2
      93: invokevirtual #98                 // Method org/apache/dubbo/common/URL.getVersion:()Ljava/lang/String;
      96: invokevirtual #96                 // Method org/apache/dubbo/rpc/RpcInvocation.setAttachment:(Ljava/lang/String;Ljava/lang/String;)V
      99: aload_2
     100: ldc           #72                 // String dubbo.stub.event
     102: iconst_0
     103: invokevirtual #99                 // Method org/apache/dubbo/common/URL.getParameter:(Ljava/lang/String;Z)Z
     106: ifeq          122
     109: aload         5
     111: ldc           #72                 // String dubbo.stub.event
     113: getstatic     #30                 // Field java/lang/Boolean.TRUE:Ljava/lang/Boolean;
     116: invokevirtual #31                 // Method java/lang/Boolean.toString:()Ljava/lang/String;
     119: invokevirtual #96                 // Method org/apache/dubbo/rpc/RpcInvocation.setAttachment:(Ljava/lang/String;Ljava/lang/String;)V
     122: aload         5
     124: areturn
}
