Compiled from "DubboCodecSupport.java"
public class org.apache.dubbo.rpc.protocol.dubbo.DubboCodecSupport {
  public org.apache.dubbo.rpc.protocol.dubbo.DubboCodecSupport();
    Code:
       0: aload_0
       1: invokespecial #2                  // Method java/lang/Object."<init>":()V
       4: return

  public static org.apache.dubbo.common.serialize.Serialization getRequestSerialization(org.apache.dubbo.common.URL, org.apache.dubbo.rpc.Invocation);
    Code:
       0: aload_1
       1: ldc           #3                  // String serialization_id
       3: invokeinterface #4,  2            // InterfaceMethod org/apache/dubbo/rpc/Invocation.get:(Ljava/lang/Object;)Ljava/lang/Object;
       8: astore_2
       9: aload_2
      10: ifnull        27
      13: aload_2
      14: checkcast     #5                  // class java/lang/Byte
      17: invokevirtual #6                  // Method java/lang/Byte.byteValue:()B
      20: invokestatic  #7                  // Method java/lang/Byte.valueOf:(B)Ljava/lang/Byte;
      23: invokestatic  #8                  // Method org/apache/dubbo/remoting/transport/CodecSupport.getSerializationById:(Ljava/lang/Byte;)Lorg/apache/dubbo/common/serialize/Serialization;
      26: areturn
      27: aload_0
      28: invokevirtual #9                  // Method org/apache/dubbo/common/URL.getOrDefaultFrameworkModel:()Lorg/apache/dubbo/rpc/model/FrameworkModel;
      31: ldc           #10                 // class org/apache/dubbo/common/serialize/Serialization
      33: invokevirtual #11                 // Method org/apache/dubbo/rpc/model/FrameworkModel.getExtensionLoader:(Ljava/lang/Class;)Lorg/apache/dubbo/common/extension/ExtensionLoader;
      36: aload_0
      37: invokestatic  #12                 // Method org/apache/dubbo/remoting/utils/UrlUtils.serializationOrDefault:(Lorg/apache/dubbo/common/URL;)Ljava/lang/String;
      40: invokevirtual #13                 // Method org/apache/dubbo/common/extension/ExtensionLoader.getExtension:(Ljava/lang/String;)Ljava/lang/Object;
      43: checkcast     #10                 // class org/apache/dubbo/common/serialize/Serialization
      46: areturn

  public static org.apache.dubbo.common.serialize.Serialization getResponseSerialization(org.apache.dubbo.common.URL, org.apache.dubbo.rpc.AppResponse);
    Code:
       0: aload_1
       1: ldc           #14                 // String invocation
       3: invokevirtual #15                 // Method org/apache/dubbo/rpc/AppResponse.getAttribute:(Ljava/lang/String;)Ljava/lang/Object;
       6: astore_2
       7: aload_2
       8: ifnull        46
      11: aload_2
      12: checkcast     #16                 // class org/apache/dubbo/rpc/Invocation
      15: astore_3
      16: aload_3
      17: ldc           #3                  // String serialization_id
      19: invokeinterface #4,  2            // InterfaceMethod org/apache/dubbo/rpc/Invocation.get:(Ljava/lang/Object;)Ljava/lang/Object;
      24: astore        4
      26: aload         4
      28: ifnull        46
      31: aload         4
      33: checkcast     #5                  // class java/lang/Byte
      36: invokevirtual #6                  // Method java/lang/Byte.byteValue:()B
      39: invokestatic  #7                  // Method java/lang/Byte.valueOf:(B)Ljava/lang/Byte;
      42: invokestatic  #8                  // Method org/apache/dubbo/remoting/transport/CodecSupport.getSerializationById:(Ljava/lang/Byte;)Lorg/apache/dubbo/common/serialize/Serialization;
      45: areturn
      46: aload_0
      47: invokevirtual #9                  // Method org/apache/dubbo/common/URL.getOrDefaultFrameworkModel:()Lorg/apache/dubbo/rpc/model/FrameworkModel;
      50: ldc           #10                 // class org/apache/dubbo/common/serialize/Serialization
      52: invokevirtual #11                 // Method org/apache/dubbo/rpc/model/FrameworkModel.getExtensionLoader:(Ljava/lang/Class;)Lorg/apache/dubbo/common/extension/ExtensionLoader;
      55: aload_0
      56: invokestatic  #12                 // Method org/apache/dubbo/remoting/utils/UrlUtils.serializationOrDefault:(Lorg/apache/dubbo/common/URL;)Ljava/lang/String;
      59: invokevirtual #13                 // Method org/apache/dubbo/common/extension/ExtensionLoader.getExtension:(Ljava/lang/String;)Ljava/lang/Object;
      62: checkcast     #10                 // class org/apache/dubbo/common/serialize/Serialization
      65: areturn
}
