Compiled from "DubboProtocolServer.java"
public class org.apache.dubbo.rpc.protocol.dubbo.DubboProtocolServer implements org.apache.dubbo.rpc.ProtocolServer {
  private final org.apache.dubbo.remoting.RemotingServer server;

  private java.lang.String address;

  private final java.util.Map<java.lang.String, java.lang.Object> attributes;

  public org.apache.dubbo.rpc.protocol.dubbo.DubboProtocolServer(org.apache.dubbo.remoting.RemotingServer);
    Code:
       0: aload_0
       1: invokespecial #1                  // Method java/lang/Object."<init>":()V
       4: aload_0
       5: new           #2                  // class java/util/concurrent/ConcurrentHashMap
       8: dup
       9: invokespecial #3                  // Method java/util/concurrent/ConcurrentHashMap."<init>":()V
      12: putfield      #4                  // Field attributes:Ljava/util/Map;
      15: aload_0
      16: aload_1
      17: putfield      #5                  // Field server:Lorg/apache/dubbo/remoting/RemotingServer;
      20: return

  public org.apache.dubbo.remoting.RemotingServer getRemotingServer();
    Code:
       0: aload_0
       1: getfield      #5                  // Field server:Lorg/apache/dubbo/remoting/RemotingServer;
       4: areturn

  public java.lang.String getAddress();
    Code:
       0: aload_0
       1: getfield      #6                  // Field address:Ljava/lang/String;
       4: invokestatic  #7                  // Method org/apache/dubbo/common/utils/StringUtils.isNotEmpty:(Ljava/lang/String;)Z
       7: ifeq          17
      10: aload_0
      11: getfield      #6                  // Field address:Ljava/lang/String;
      14: goto          29
      17: aload_0
      18: getfield      #5                  // Field server:Lorg/apache/dubbo/remoting/RemotingServer;
      21: invokeinterface #8,  1            // InterfaceMethod org/apache/dubbo/remoting/RemotingServer.getUrl:()Lorg/apache/dubbo/common/URL;
      26: invokevirtual #9                  // Method org/apache/dubbo/common/URL.getAddress:()Ljava/lang/String;
      29: areturn

  public void setAddress(java.lang.String);
    Code:
       0: aload_0
       1: aload_1
       2: putfield      #6                  // Field address:Ljava/lang/String;
       5: return

  public org.apache.dubbo.common.URL getUrl();
    Code:
       0: aload_0
       1: getfield      #5                  // Field server:Lorg/apache/dubbo/remoting/RemotingServer;
       4: invokeinterface #8,  1            // InterfaceMethod org/apache/dubbo/remoting/RemotingServer.getUrl:()Lorg/apache/dubbo/common/URL;
       9: areturn

  public void reset(org.apache.dubbo.common.URL);
    Code:
       0: aload_0
       1: getfield      #5                  // Field server:Lorg/apache/dubbo/remoting/RemotingServer;
       4: aload_1
       5: invokeinterface #10,  2           // InterfaceMethod org/apache/dubbo/remoting/RemotingServer.reset:(Lorg/apache/dubbo/common/URL;)V
      10: return

  public void close();
    Code:
       0: aload_0
       1: getfield      #5                  // Field server:Lorg/apache/dubbo/remoting/RemotingServer;
       4: invokeinterface #11,  1           // InterfaceMethod org/apache/dubbo/remoting/RemotingServer.close:()V
       9: return

  public java.util.Map<java.lang.String, java.lang.Object> getAttributes();
    Code:
       0: aload_0
       1: getfield      #4                  // Field attributes:Ljava/util/Map;
       4: areturn
}
