Compiled from "DubboProtocol.java"
public class org.apache.dubbo.rpc.protocol.dubbo.DubboProtocol extends org.apache.dubbo.rpc.protocol.AbstractProtocol {
  public static final java.lang.String NAME;

  public static final int DEFAULT_PORT;

  private static final java.lang.String IS_CALLBACK_SERVICE_INVOKE;

  private final java.util.Map<java.lang.String, org.apache.dubbo.rpc.protocol.dubbo.SharedClientsProvider> referenceClientMap;

  private final java.util.concurrent.atomic.AtomicBoolean destroyed;

  private final org.apache.dubbo.remoting.exchange.ExchangeHandler requestHandler;

  public org.apache.dubbo.rpc.protocol.dubbo.DubboProtocol(org.apache.dubbo.rpc.model.FrameworkModel);
    Code:
       0: aload_0
       1: invokespecial #8                  // Method org/apache/dubbo/rpc/protocol/AbstractProtocol."<init>":()V
       4: aload_0
       5: new           #9                  // class java/util/concurrent/ConcurrentHashMap
       8: dup
       9: invokespecial #10                 // Method java/util/concurrent/ConcurrentHashMap."<init>":()V
      12: putfield      #11                 // Field referenceClientMap:Ljava/util/Map;
      15: aload_0
      16: new           #12                 // class java/util/concurrent/atomic/AtomicBoolean
      19: dup
      20: invokespecial #13                 // Method java/util/concurrent/atomic/AtomicBoolean."<init>":()V
      23: putfield      #14                 // Field destroyed:Ljava/util/concurrent/atomic/AtomicBoolean;
      26: aload_0
      27: new           #15                 // class org/apache/dubbo/rpc/protocol/dubbo/DubboProtocol$1
      30: dup
      31: aload_0
      32: aload_1
      33: invokespecial #16                 // Method org/apache/dubbo/rpc/protocol/dubbo/DubboProtocol$1."<init>":(Lorg/apache/dubbo/rpc/protocol/dubbo/DubboProtocol;Lorg/apache/dubbo/rpc/model/FrameworkModel;)V
      36: putfield      #17                 // Field requestHandler:Lorg/apache/dubbo/remoting/exchange/ExchangeHandler;
      39: aload_0
      40: aload_1
      41: putfield      #18                 // Field frameworkModel:Lorg/apache/dubbo/rpc/model/FrameworkModel;
      44: aload_0
      45: getfield      #18                 // Field frameworkModel:Lorg/apache/dubbo/rpc/model/FrameworkModel;
      48: invokevirtual #19                 // Method org/apache/dubbo/rpc/model/FrameworkModel.getBeanFactory:()Lorg/apache/dubbo/common/beans/factory/ScopeBeanFactory;
      51: new           #20                 // class org/apache/dubbo/rpc/protocol/dubbo/DubboGracefulShutdown
      54: dup
      55: aload_0
      56: invokespecial #21                 // Method org/apache/dubbo/rpc/protocol/dubbo/DubboGracefulShutdown."<init>":(Lorg/apache/dubbo/rpc/protocol/dubbo/DubboProtocol;)V
      59: invokevirtual #22                 // Method org/apache/dubbo/common/beans/factory/ScopeBeanFactory.registerBean:(Ljava/lang/Object;)V
      62: return

  public static org.apache.dubbo.rpc.protocol.dubbo.DubboProtocol getDubboProtocol();
    Code:
       0: invokestatic  #23                 // Method org/apache/dubbo/rpc/model/FrameworkModel.defaultModel:()Lorg/apache/dubbo/rpc/model/FrameworkModel;
       3: ldc           #24                 // class org/apache/dubbo/rpc/Protocol
       5: invokevirtual #25                 // Method org/apache/dubbo/rpc/model/FrameworkModel.getExtensionLoader:(Ljava/lang/Class;)Lorg/apache/dubbo/common/extension/ExtensionLoader;
       8: ldc           #27                 // String dubbo
      10: iconst_0
      11: invokevirtual #28                 // Method org/apache/dubbo/common/extension/ExtensionLoader.getExtension:(Ljava/lang/String;Z)Ljava/lang/Object;
      14: checkcast     #26                 // class org/apache/dubbo/rpc/protocol/dubbo/DubboProtocol
      17: areturn

  public static org.apache.dubbo.rpc.protocol.dubbo.DubboProtocol getDubboProtocol(org.apache.dubbo.rpc.model.ScopeModel);
    Code:
       0: aload_0
       1: ldc           #24                 // class org/apache/dubbo/rpc/Protocol
       3: invokevirtual #29                 // Method org/apache/dubbo/rpc/model/ScopeModel.getExtensionLoader:(Ljava/lang/Class;)Lorg/apache/dubbo/common/extension/ExtensionLoader;
       6: ldc           #27                 // String dubbo
       8: iconst_0
       9: invokevirtual #28                 // Method org/apache/dubbo/common/extension/ExtensionLoader.getExtension:(Ljava/lang/String;Z)Ljava/lang/Object;
      12: checkcast     #26                 // class org/apache/dubbo/rpc/protocol/dubbo/DubboProtocol
      15: areturn

  private boolean isClientSide(org.apache.dubbo.remoting.Channel);
    Code:
       0: aload_1
       1: invokeinterface #30,  1           // InterfaceMethod org/apache/dubbo/remoting/Channel.getRemoteAddress:()Ljava/net/InetSocketAddress;
       6: astore_2
       7: aload_1
       8: invokeinterface #31,  1           // InterfaceMethod org/apache/dubbo/remoting/Channel.getUrl:()Lorg/apache/dubbo/common/URL;
      13: astore_3
      14: aload_3
      15: invokevirtual #32                 // Method org/apache/dubbo/common/URL.getPort:()I
      18: aload_2
      19: invokevirtual #33                 // Method java/net/InetSocketAddress.getPort:()I
      22: if_icmpne     57
      25: aload_1
      26: invokeinterface #31,  1           // InterfaceMethod org/apache/dubbo/remoting/Channel.getUrl:()Lorg/apache/dubbo/common/URL;
      31: invokevirtual #34                 // Method org/apache/dubbo/common/URL.getIp:()Ljava/lang/String;
      34: invokestatic  #35                 // Method org/apache/dubbo/common/utils/NetUtils.filterLocalHost:(Ljava/lang/String;)Ljava/lang/String;
      37: aload_2
      38: invokevirtual #36                 // Method java/net/InetSocketAddress.getAddress:()Ljava/net/InetAddress;
      41: invokevirtual #37                 // Method java/net/InetAddress.getHostAddress:()Ljava/lang/String;
      44: invokestatic  #35                 // Method org/apache/dubbo/common/utils/NetUtils.filterLocalHost:(Ljava/lang/String;)Ljava/lang/String;
      47: invokevirtual #38                 // Method java/lang/String.equals:(Ljava/lang/Object;)Z
      50: ifeq          57
      53: iconst_1
      54: goto          58
      57: iconst_0
      58: ireturn

  org.apache.dubbo.rpc.Invoker<?> getInvoker(org.apache.dubbo.remoting.Channel, org.apache.dubbo.rpc.Invocation) throws org.apache.dubbo.remoting.RemotingException;
    Code:
       0: aload_1
       1: invokeinterface #39,  1           // InterfaceMethod org/apache/dubbo/remoting/Channel.getLocalAddress:()Ljava/net/InetSocketAddress;
       6: invokevirtual #33                 // Method java/net/InetSocketAddress.getPort:()I
       9: istore        5
      11: aload_2
      12: ldc           #40                 // String path
      14: invokeinterface #41,  2           // InterfaceMethod org/apache/dubbo/rpc/Invocation.getObjectAttachmentWithoutConvert:(Ljava/lang/String;)Ljava/lang/Object;
      19: checkcast     #42                 // class java/lang/String
      22: astore        6
      24: getstatic     #43                 // Field java/lang/Boolean.TRUE:Ljava/lang/Boolean;
      27: invokevirtual #44                 // Method java/lang/Boolean.toString:()Ljava/lang/String;
      30: aload_2
      31: ldc           #45                 // String dubbo.stub.event
      33: invokeinterface #41,  2           // InterfaceMethod org/apache/dubbo/rpc/Invocation.getObjectAttachmentWithoutConvert:(Ljava/lang/String;)Ljava/lang/Object;
      38: invokevirtual #38                 // Method java/lang/String.equals:(Ljava/lang/Object;)Z
      41: istore        4
      43: iload         4
      45: ifeq          51
      48: iconst_0
      49: istore        5
      51: aload_0
      52: aload_1
      53: invokespecial #46                 // Method isClientSide:(Lorg/apache/dubbo/remoting/Channel;)Z
      56: ifeq          68
      59: iload         4
      61: ifne          68
      64: iconst_1
      65: goto          69
      68: iconst_0
      69: istore_3
      70: iload_3
      71: ifeq          121
      74: new           #47                 // class java/lang/StringBuilder
      77: dup
      78: invokespecial #48                 // Method java/lang/StringBuilder."<init>":()V
      81: aload         6
      83: invokevirtual #49                 // Method java/lang/StringBuilder.append:(Ljava/lang/String;)Ljava/lang/StringBuilder;
      86: ldc           #50                 // String .
      88: invokevirtual #49                 // Method java/lang/StringBuilder.append:(Ljava/lang/String;)Ljava/lang/StringBuilder;
      91: aload_2
      92: ldc           #51                 // String callback.service.instid
      94: invokeinterface #41,  2           // InterfaceMethod org/apache/dubbo/rpc/Invocation.getObjectAttachmentWithoutConvert:(Ljava/lang/String;)Ljava/lang/Object;
      99: invokevirtual #52                 // Method java/lang/StringBuilder.append:(Ljava/lang/Object;)Ljava/lang/StringBuilder;
     102: invokevirtual #53                 // Method java/lang/StringBuilder.toString:()Ljava/lang/String;
     105: astore        6
     107: aload_2
     108: ldc           #54                 // String _isCallBackServiceInvoke
     110: getstatic     #43                 // Field java/lang/Boolean.TRUE:Ljava/lang/Boolean;
     113: invokevirtual #44                 // Method java/lang/Boolean.toString:()Ljava/lang/String;
     116: invokeinterface #55,  3           // InterfaceMethod org/apache/dubbo/rpc/Invocation.setObjectAttachment:(Ljava/lang/String;Ljava/lang/Object;)V
     121: iload         5
     123: aload         6
     125: aload_2
     126: ldc           #56                 // String version
     128: invokeinterface #41,  2           // InterfaceMethod org/apache/dubbo/rpc/Invocation.getObjectAttachmentWithoutConvert:(Ljava/lang/String;)Ljava/lang/Object;
     133: checkcast     #42                 // class java/lang/String
     136: aload_2
     137: ldc           #57                 // String group
     139: invokeinterface #41,  2           // InterfaceMethod org/apache/dubbo/rpc/Invocation.getObjectAttachmentWithoutConvert:(Ljava/lang/String;)Ljava/lang/Object;
     144: checkcast     #42                 // class java/lang/String
     147: invokestatic  #6                  // Method serviceKey:(ILjava/lang/String;Ljava/lang/String;Ljava/lang/String;)Ljava/lang/String;
     150: astore        7
     152: aload_0
     153: getfield      #58                 // Field exporterMap:Ljava/util/Map;
     156: aload         7
     158: invokeinterface #59,  2           // InterfaceMethod java/util/Map.get:(Ljava/lang/Object;)Ljava/lang/Object;
     163: checkcast     #60                 // class org/apache/dubbo/rpc/protocol/dubbo/DubboExporter
     166: astore        8
     168: aload         8
     170: ifnonnull     260
     173: new           #61                 // class org/apache/dubbo/remoting/RemotingException
     176: dup
     177: aload_1
     178: new           #47                 // class java/lang/StringBuilder
     181: dup
     182: invokespecial #48                 // Method java/lang/StringBuilder."<init>":()V
     185: ldc           #62                 // String Not found exported service:
     187: invokevirtual #49                 // Method java/lang/StringBuilder.append:(Ljava/lang/String;)Ljava/lang/StringBuilder;
     190: aload         7
     192: invokevirtual #49                 // Method java/lang/StringBuilder.append:(Ljava/lang/String;)Ljava/lang/StringBuilder;
     195: ldc           #63                 // String  in
     197: invokevirtual #49                 // Method java/lang/StringBuilder.append:(Ljava/lang/String;)Ljava/lang/StringBuilder;
     200: aload_0
     201: getfield      #58                 // Field exporterMap:Ljava/util/Map;
     204: invokeinterface #64,  1           // InterfaceMethod java/util/Map.keySet:()Ljava/util/Set;
     209: invokevirtual #52                 // Method java/lang/StringBuilder.append:(Ljava/lang/Object;)Ljava/lang/StringBuilder;
     212: ldc           #65                 // String , may be version or group mismatch , channel: consumer:
     214: invokevirtual #49                 // Method java/lang/StringBuilder.append:(Ljava/lang/String;)Ljava/lang/StringBuilder;
     217: aload_1
     218: invokeinterface #30,  1           // InterfaceMethod org/apache/dubbo/remoting/Channel.getRemoteAddress:()Ljava/net/InetSocketAddress;
     223: invokevirtual #52                 // Method java/lang/StringBuilder.append:(Ljava/lang/Object;)Ljava/lang/StringBuilder;
     226: ldc           #66                 // String  --> provider:
     228: invokevirtual #49                 // Method java/lang/StringBuilder.append:(Ljava/lang/String;)Ljava/lang/StringBuilder;
     231: aload_1
     232: invokeinterface #39,  1           // InterfaceMethod org/apache/dubbo/remoting/Channel.getLocalAddress:()Ljava/net/InetSocketAddress;
     237: invokevirtual #52                 // Method java/lang/StringBuilder.append:(Ljava/lang/Object;)Ljava/lang/StringBuilder;
     240: ldc           #67                 // String , message:
     242: invokevirtual #49                 // Method java/lang/StringBuilder.append:(Ljava/lang/String;)Ljava/lang/StringBuilder;
     245: aload_0
     246: aload_2
     247: invokespecial #68                 // Method getInvocationWithoutData:(Lorg/apache/dubbo/rpc/Invocation;)Lorg/apache/dubbo/rpc/Invocation;
     250: invokevirtual #52                 // Method java/lang/StringBuilder.append:(Ljava/lang/Object;)Ljava/lang/StringBuilder;
     253: invokevirtual #53                 // Method java/lang/StringBuilder.toString:()Ljava/lang/String;
     256: invokespecial #69                 // Method org/apache/dubbo/remoting/RemotingException."<init>":(Lorg/apache/dubbo/remoting/Channel;Ljava/lang/String;)V
     259: athrow
     260: aload         8
     262: invokevirtual #70                 // Method org/apache/dubbo/rpc/protocol/dubbo/DubboExporter.getInvoker:()Lorg/apache/dubbo/rpc/Invoker;
     265: astore        9
     267: aload_2
     268: aload         9
     270: invokeinterface #71,  1           // InterfaceMethod org/apache/dubbo/rpc/Invoker.getUrl:()Lorg/apache/dubbo/common/URL;
     275: invokevirtual #72                 // Method org/apache/dubbo/common/URL.getServiceModel:()Lorg/apache/dubbo/rpc/model/ServiceModel;
     278: invokeinterface #73,  2           // InterfaceMethod org/apache/dubbo/rpc/Invocation.setServiceModel:(Lorg/apache/dubbo/rpc/model/ServiceModel;)V
     283: aload         9
     285: areturn

  public java.util.Collection<org.apache.dubbo.rpc.Invoker<?>> getInvokers();
    Code:
       0: aload_0
       1: getfield      #74                 // Field invokers:Ljava/util/Set;
       4: invokestatic  #75                 // Method java/util/Collections.unmodifiableCollection:(Ljava/util/Collection;)Ljava/util/Collection;
       7: areturn

  public int getDefaultPort();
    Code:
       0: sipush        20880
       3: ireturn

  public <T> org.apache.dubbo.rpc.Exporter<T> export(org.apache.dubbo.rpc.Invoker<T>) throws org.apache.dubbo.rpc.RpcException;
    Code:
       0: aload_0
       1: invokespecial #76                 // Method checkDestroyed:()V
       4: aload_1
       5: invokeinterface #71,  1           // InterfaceMethod org/apache/dubbo/rpc/Invoker.getUrl:()Lorg/apache/dubbo/common/URL;
      10: astore_2
      11: aload_2
      12: invokestatic  #77                 // Method serviceKey:(Lorg/apache/dubbo/common/URL;)Ljava/lang/String;
      15: astore_3
      16: new           #60                 // class org/apache/dubbo/rpc/protocol/dubbo/DubboExporter
      19: dup
      20: aload_1
      21: aload_3
      22: aload_0
      23: getfield      #58                 // Field exporterMap:Ljava/util/Map;
      26: invokespecial #78                 // Method org/apache/dubbo/rpc/protocol/dubbo/DubboExporter."<init>":(Lorg/apache/dubbo/rpc/Invoker;Ljava/lang/String;Ljava/util/Map;)V
      29: astore        4
      31: aload_2
      32: ldc           #45                 // String dubbo.stub.event
      34: iconst_0
      35: invokevirtual #79                 // Method org/apache/dubbo/common/URL.getParameter:(Ljava/lang/String;Z)Z
      38: istore        5
      40: aload_2
      41: ldc           #80                 // String is_callback_service
      43: iconst_0
      44: invokevirtual #79                 // Method org/apache/dubbo/common/URL.getParameter:(Ljava/lang/String;Z)Z
      47: istore        6
      49: iload         5
      51: ifeq          136
      54: iload         6
      56: ifne          136
      59: aload_2
      60: ldc           #81                 // String dubbo.stub.event.methods
      62: invokevirtual #82                 // Method org/apache/dubbo/common/URL.getParameter:(Ljava/lang/String;)Ljava/lang/String;
      65: astore        7
      67: aload         7
      69: ifnull        80
      72: aload         7
      74: invokevirtual #83                 // Method java/lang/String.length:()I
      77: ifne          136
      80: aload_0
      81: getfield      #7                  // Field logger:Lorg/apache/dubbo/common/logger/ErrorTypeAwareLogger;
      84: invokeinterface #84,  1           // InterfaceMethod org/apache/dubbo/common/logger/ErrorTypeAwareLogger.isWarnEnabled:()Z
      89: ifeq          136
      92: aload_0
      93: getfield      #7                  // Field logger:Lorg/apache/dubbo/common/logger/ErrorTypeAwareLogger;
      96: ldc           #85                 // String 4-1
      98: ldc           #86                 // String
     100: ldc           #86                 // String
     102: new           #47                 // class java/lang/StringBuilder
     105: dup
     106: invokespecial #48                 // Method java/lang/StringBuilder."<init>":()V
     109: ldc           #87                 // String consumer [
     111: invokevirtual #49                 // Method java/lang/StringBuilder.append:(Ljava/lang/String;)Ljava/lang/StringBuilder;
     114: aload_2
     115: ldc           #88                 // String interface
     117: invokevirtual #82                 // Method org/apache/dubbo/common/URL.getParameter:(Ljava/lang/String;)Ljava/lang/String;
     120: invokevirtual #49                 // Method java/lang/StringBuilder.append:(Ljava/lang/String;)Ljava/lang/StringBuilder;
     123: ldc           #89                 // String ], has set stub proxy support event ,but no stub methods founded.
     125: invokevirtual #49                 // Method java/lang/StringBuilder.append:(Ljava/lang/String;)Ljava/lang/StringBuilder;
     128: invokevirtual #53                 // Method java/lang/StringBuilder.toString:()Ljava/lang/String;
     131: invokeinterface #90,  5           // InterfaceMethod org/apache/dubbo/common/logger/ErrorTypeAwareLogger.warn:(Ljava/lang/String;Ljava/lang/String;Ljava/lang/String;Ljava/lang/String;)V
     136: aload_0
     137: aload_2
     138: invokespecial #91                 // Method openServer:(Lorg/apache/dubbo/common/URL;)V
     141: aload_0
     142: aload_2
     143: invokevirtual #92                 // Method optimizeSerialization:(Lorg/apache/dubbo/common/URL;)V
     146: aload         4
     148: areturn

  private void openServer(org.apache.dubbo.common.URL);
    Code:
       0: aload_0
       1: invokespecial #76                 // Method checkDestroyed:()V
       4: aload_1
       5: invokevirtual #93                 // Method org/apache/dubbo/common/URL.getAddress:()Ljava/lang/String;
       8: astore_2
       9: aload_1
      10: ldc           #94                 // String isserver
      12: iconst_1
      13: invokevirtual #79                 // Method org/apache/dubbo/common/URL.getParameter:(Ljava/lang/String;Z)Z
      16: istore_3
      17: iload_3
      18: ifeq          108
      21: aload_0
      22: getfield      #95                 // Field serverMap:Ljava/util/concurrent/ConcurrentMap;
      25: aload_2
      26: invokeinterface #96,  2           // InterfaceMethod java/util/concurrent/ConcurrentMap.get:(Ljava/lang/Object;)Ljava/lang/Object;
      31: checkcast     #97                 // class org/apache/dubbo/rpc/ProtocolServer
      34: astore        4
      36: aload         4
      38: ifnonnull     100
      41: aload_0
      42: dup
      43: astore        5
      45: monitorenter
      46: aload_0
      47: getfield      #95                 // Field serverMap:Ljava/util/concurrent/ConcurrentMap;
      50: aload_2
      51: invokeinterface #96,  2           // InterfaceMethod java/util/concurrent/ConcurrentMap.get:(Ljava/lang/Object;)Ljava/lang/Object;
      56: checkcast     #97                 // class org/apache/dubbo/rpc/ProtocolServer
      59: astore        4
      61: aload         4
      63: ifnonnull     86
      66: aload_0
      67: getfield      #95                 // Field serverMap:Ljava/util/concurrent/ConcurrentMap;
      70: aload_2
      71: aload_0
      72: aload_1
      73: invokespecial #98                 // Method createServer:(Lorg/apache/dubbo/common/URL;)Lorg/apache/dubbo/rpc/ProtocolServer;
      76: invokeinterface #99,  3           // InterfaceMethod java/util/concurrent/ConcurrentMap.put:(Ljava/lang/Object;Ljava/lang/Object;)Ljava/lang/Object;
      81: pop
      82: aload         5
      84: monitorexit
      85: return
      86: aload         5
      88: monitorexit
      89: goto          100
      92: astore        6
      94: aload         5
      96: monitorexit
      97: aload         6
      99: athrow
     100: aload         4
     102: aload_1
     103: invokeinterface #100,  2          // InterfaceMethod org/apache/dubbo/rpc/ProtocolServer.reset:(Lorg/apache/dubbo/common/URL;)V
     108: return
    Exception table:
       from    to  target type
          46    85    92   any
          86    89    92   any
          92    97    92   any

  private void checkDestroyed();
    Code:
       0: aload_0
       1: getfield      #14                 // Field destroyed:Ljava/util/concurrent/atomic/AtomicBoolean;
       4: invokevirtual #101                // Method java/util/concurrent/atomic/AtomicBoolean.get:()Z
       7: ifeq          43
      10: new           #102                // class java/lang/IllegalStateException
      13: dup
      14: new           #47                 // class java/lang/StringBuilder
      17: dup
      18: invokespecial #48                 // Method java/lang/StringBuilder."<init>":()V
      21: aload_0
      22: invokevirtual #103                // Method java/lang/Object.getClass:()Ljava/lang/Class;
      25: invokevirtual #104                // Method java/lang/Class.getSimpleName:()Ljava/lang/String;
      28: invokevirtual #49                 // Method java/lang/StringBuilder.append:(Ljava/lang/String;)Ljava/lang/StringBuilder;
      31: ldc           #105                // String  is destroyed
      33: invokevirtual #49                 // Method java/lang/StringBuilder.append:(Ljava/lang/String;)Ljava/lang/StringBuilder;
      36: invokevirtual #53                 // Method java/lang/StringBuilder.toString:()Ljava/lang/String;
      39: invokespecial #106                // Method java/lang/IllegalStateException."<init>":(Ljava/lang/String;)V
      42: athrow
      43: return

  private org.apache.dubbo.rpc.ProtocolServer createServer(org.apache.dubbo.common.URL);
    Code:
       0: aload_1
       1: invokestatic  #107                // Method org/apache/dubbo/common/URLBuilder.from:(Lorg/apache/dubbo/common/URL;)Lorg/apache/dubbo/common/URLBuilder;
       4: ldc           #108                // String channel.readonly.sent
       6: getstatic     #43                 // Field java/lang/Boolean.TRUE:Ljava/lang/Boolean;
       9: invokevirtual #44                 // Method java/lang/Boolean.toString:()Ljava/lang/String;
      12: invokevirtual #109                // Method org/apache/dubbo/common/URLBuilder.addParameterIfAbsent:(Ljava/lang/String;Ljava/lang/String;)Lorg/apache/dubbo/common/URLBuilder;
      15: ldc           #110                // String heartbeat
      17: ldc           #111                // int 60000
      19: invokestatic  #112                // Method java/lang/String.valueOf:(I)Ljava/lang/String;
      22: invokevirtual #109                // Method org/apache/dubbo/common/URLBuilder.addParameterIfAbsent:(Ljava/lang/String;Ljava/lang/String;)Lorg/apache/dubbo/common/URLBuilder;
      25: ldc           #113                // String codec
      27: ldc           #27                 // String dubbo
      29: invokevirtual #115                // Method org/apache/dubbo/common/URLBuilder.addParameter:(Ljava/lang/String;Ljava/lang/String;)Lorg/apache/dubbo/common/URLBuilder;
      32: invokevirtual #116                // Method org/apache/dubbo/common/URLBuilder.build:()Lorg/apache/dubbo/common/url/component/ServiceConfigURL;
      35: astore_1
      36: aload_1
      37: ldc           #117                // String server
      39: ldc           #118                // String netty
      41: invokevirtual #119                // Method org/apache/dubbo/common/URL.getParameter:(Ljava/lang/String;Ljava/lang/String;)Ljava/lang/String;
      44: astore_2
      45: aload_2
      46: invokestatic  #120                // Method org/apache/dubbo/common/utils/StringUtils.isNotEmpty:(Ljava/lang/String;)Z
      49: ifeq          104
      52: aload_1
      53: invokevirtual #121                // Method org/apache/dubbo/common/URL.getOrDefaultFrameworkModel:()Lorg/apache/dubbo/rpc/model/FrameworkModel;
      56: ldc           #122                // class org/apache/dubbo/remoting/Transporter
      58: invokevirtual #25                 // Method org/apache/dubbo/rpc/model/FrameworkModel.getExtensionLoader:(Ljava/lang/Class;)Lorg/apache/dubbo/common/extension/ExtensionLoader;
      61: aload_2
      62: invokevirtual #123                // Method org/apache/dubbo/common/extension/ExtensionLoader.hasExtension:(Ljava/lang/String;)Z
      65: ifne          104
      68: new           #124                // class org/apache/dubbo/rpc/RpcException
      71: dup
      72: new           #47                 // class java/lang/StringBuilder
      75: dup
      76: invokespecial #48                 // Method java/lang/StringBuilder."<init>":()V
      79: ldc           #125                // String Unsupported server type:
      81: invokevirtual #49                 // Method java/lang/StringBuilder.append:(Ljava/lang/String;)Ljava/lang/StringBuilder;
      84: aload_2
      85: invokevirtual #49                 // Method java/lang/StringBuilder.append:(Ljava/lang/String;)Ljava/lang/StringBuilder;
      88: ldc           #126                // String , url:
      90: invokevirtual #49                 // Method java/lang/StringBuilder.append:(Ljava/lang/String;)Ljava/lang/StringBuilder;
      93: aload_1
      94: invokevirtual #52                 // Method java/lang/StringBuilder.append:(Ljava/lang/Object;)Ljava/lang/StringBuilder;
      97: invokevirtual #53                 // Method java/lang/StringBuilder.toString:()Ljava/lang/String;
     100: invokespecial #127                // Method org/apache/dubbo/rpc/RpcException."<init>":(Ljava/lang/String;)V
     103: athrow
     104: aload_1
     105: aload_0
     106: getfield      #17                 // Field requestHandler:Lorg/apache/dubbo/remoting/exchange/ExchangeHandler;
     109: invokestatic  #128                // Method org/apache/dubbo/remoting/exchange/Exchangers.bind:(Lorg/apache/dubbo/common/URL;Lorg/apache/dubbo/remoting/exchange/ExchangeHandler;)Lorg/apache/dubbo/remoting/exchange/ExchangeServer;
     112: astore_3
     113: goto          160
     116: astore        4
     118: new           #124                // class org/apache/dubbo/rpc/RpcException
     121: dup
     122: new           #47                 // class java/lang/StringBuilder
     125: dup
     126: invokespecial #48                 // Method java/lang/StringBuilder."<init>":()V
     129: ldc           #129                // String Fail to start server(url:
     131: invokevirtual #49                 // Method java/lang/StringBuilder.append:(Ljava/lang/String;)Ljava/lang/StringBuilder;
     134: aload_1
     135: invokevirtual #52                 // Method java/lang/StringBuilder.append:(Ljava/lang/Object;)Ljava/lang/StringBuilder;
     138: ldc           #130                // String )
     140: invokevirtual #49                 // Method java/lang/StringBuilder.append:(Ljava/lang/String;)Ljava/lang/StringBuilder;
     143: aload         4
     145: invokevirtual #131                // Method org/apache/dubbo/remoting/RemotingException.getMessage:()Ljava/lang/String;
     148: invokevirtual #49                 // Method java/lang/StringBuilder.append:(Ljava/lang/String;)Ljava/lang/StringBuilder;
     151: invokevirtual #53                 // Method java/lang/StringBuilder.toString:()Ljava/lang/String;
     154: aload         4
     156: invokespecial #132                // Method org/apache/dubbo/rpc/RpcException."<init>":(Ljava/lang/String;Ljava/lang/Throwable;)V
     159: athrow
     160: aload_1
     161: ldc           #133                // String client
     163: invokevirtual #82                 // Method org/apache/dubbo/common/URL.getParameter:(Ljava/lang/String;)Ljava/lang/String;
     166: astore_2
     167: aload_2
     168: invokestatic  #120                // Method org/apache/dubbo/common/utils/StringUtils.isNotEmpty:(Ljava/lang/String;)Z
     171: ifeq          217
     174: aload_1
     175: invokevirtual #121                // Method org/apache/dubbo/common/URL.getOrDefaultFrameworkModel:()Lorg/apache/dubbo/rpc/model/FrameworkModel;
     178: ldc           #122                // class org/apache/dubbo/remoting/Transporter
     180: invokevirtual #25                 // Method org/apache/dubbo/rpc/model/FrameworkModel.getExtensionLoader:(Ljava/lang/Class;)Lorg/apache/dubbo/common/extension/ExtensionLoader;
     183: aload_2
     184: invokevirtual #123                // Method org/apache/dubbo/common/extension/ExtensionLoader.hasExtension:(Ljava/lang/String;)Z
     187: ifne          217
     190: new           #124                // class org/apache/dubbo/rpc/RpcException
     193: dup
     194: new           #47                 // class java/lang/StringBuilder
     197: dup
     198: invokespecial #48                 // Method java/lang/StringBuilder."<init>":()V
     201: ldc           #134                // String Unsupported client type:
     203: invokevirtual #49                 // Method java/lang/StringBuilder.append:(Ljava/lang/String;)Ljava/lang/StringBuilder;
     206: aload_2
     207: invokevirtual #49                 // Method java/lang/StringBuilder.append:(Ljava/lang/String;)Ljava/lang/StringBuilder;
     210: invokevirtual #53                 // Method java/lang/StringBuilder.toString:()Ljava/lang/String;
     213: invokespecial #127                // Method org/apache/dubbo/rpc/RpcException."<init>":(Ljava/lang/String;)V
     216: athrow
     217: new           #135                // class org/apache/dubbo/rpc/protocol/dubbo/DubboProtocolServer
     220: dup
     221: aload_3
     222: invokespecial #136                // Method org/apache/dubbo/rpc/protocol/dubbo/DubboProtocolServer."<init>":(Lorg/apache/dubbo/remoting/RemotingServer;)V
     225: astore        4
     227: aload_0
     228: aload         4
     230: invokevirtual #137                // Method loadServerProperties:(Lorg/apache/dubbo/rpc/ProtocolServer;)V
     233: aload         4
     235: areturn
    Exception table:
       from    to  target type
         104   113   116   Class org/apache/dubbo/remoting/RemotingException

  public <T> org.apache.dubbo.rpc.Invoker<T> refer(java.lang.Class<T>, org.apache.dubbo.common.URL) throws org.apache.dubbo.rpc.RpcException;
    Code:
       0: aload_0
       1: invokespecial #76                 // Method checkDestroyed:()V
       4: aload_0
       5: aload_1
       6: aload_2
       7: invokevirtual #138                // Method protocolBindingRefer:(Ljava/lang/Class;Lorg/apache/dubbo/common/URL;)Lorg/apache/dubbo/rpc/Invoker;
      10: areturn

  public <T> org.apache.dubbo.rpc.Invoker<T> protocolBindingRefer(java.lang.Class<T>, org.apache.dubbo.common.URL) throws org.apache.dubbo.rpc.RpcException;
    Code:
       0: aload_0
       1: invokespecial #76                 // Method checkDestroyed:()V
       4: aload_0
       5: aload_2
       6: invokevirtual #92                 // Method optimizeSerialization:(Lorg/apache/dubbo/common/URL;)V
       9: new           #139                // class org/apache/dubbo/rpc/protocol/dubbo/DubboInvoker
      12: dup
      13: aload_1
      14: aload_2
      15: aload_0
      16: aload_2
      17: invokespecial #140                // Method getClients:(Lorg/apache/dubbo/common/URL;)Lorg/apache/dubbo/rpc/protocol/dubbo/ClientsProvider;
      20: aload_0
      21: getfield      #74                 // Field invokers:Ljava/util/Set;
      24: invokespecial #141                // Method org/apache/dubbo/rpc/protocol/dubbo/DubboInvoker."<init>":(Ljava/lang/Class;Lorg/apache/dubbo/common/URL;Lorg/apache/dubbo/rpc/protocol/dubbo/ClientsProvider;Ljava/util/Set;)V
      27: astore_3
      28: aload_0
      29: getfield      #74                 // Field invokers:Ljava/util/Set;
      32: aload_3
      33: invokeinterface #142,  2          // InterfaceMethod java/util/Set.add:(Ljava/lang/Object;)Z
      38: pop
      39: aload_3
      40: areturn

  private org.apache.dubbo.rpc.protocol.dubbo.ClientsProvider getClients(org.apache.dubbo.common.URL);
    Code:
       0: aload_1
       1: ldc           #143                // String connections
       3: iconst_0
       4: invokevirtual #144                // Method org/apache/dubbo/common/URL.getParameter:(Ljava/lang/String;I)I
       7: istore_2
       8: iload_2
       9: ifne          65
      12: aload_1
      13: ldc           #145                // String shareconnections
      15: aconst_null
      16: checkcast     #42                 // class java/lang/String
      19: invokevirtual #119                // Method org/apache/dubbo/common/URL.getParameter:(Ljava/lang/String;Ljava/lang/String;)Ljava/lang/String;
      22: invokestatic  #146                // Method org/apache/dubbo/common/utils/StringUtils.isBlank:(Ljava/lang/CharSequence;)Z
      25: ifeq          42
      28: aload_1
      29: invokevirtual #147                // Method org/apache/dubbo/common/URL.getOrDefaultApplicationModel:()Lorg/apache/dubbo/rpc/model/ApplicationModel;
      32: ldc           #145                // String shareconnections
      34: ldc           #148                // String 1
      36: invokestatic  #149                // Method org/apache/dubbo/common/config/ConfigurationUtils.getProperty:(Lorg/apache/dubbo/rpc/model/ScopeModel;Ljava/lang/String;Ljava/lang/String;)Ljava/lang/String;
      39: goto          52
      42: aload_1
      43: ldc           #145                // String shareconnections
      45: aconst_null
      46: checkcast     #42                 // class java/lang/String
      49: invokevirtual #119                // Method org/apache/dubbo/common/URL.getParameter:(Ljava/lang/String;Ljava/lang/String;)Ljava/lang/String;
      52: astore_3
      53: aload_3
      54: invokestatic  #150                // Method java/lang/Integer.parseInt:(Ljava/lang/String;)I
      57: istore_2
      58: aload_0
      59: aload_1
      60: iload_2
      61: invokespecial #151                // Method getSharedClient:(Lorg/apache/dubbo/common/URL;I)Lorg/apache/dubbo/rpc/protocol/dubbo/SharedClientsProvider;
      64: areturn
      65: iconst_0
      66: iload_2
      67: invokestatic  #152                // InterfaceMethod java/util/stream/IntStream.range:(II)Ljava/util/stream/IntStream;
      70: aload_0
      71: aload_1
      72: invokedynamic #153,  0            // InvokeDynamic #0:apply:(Lorg/apache/dubbo/rpc/protocol/dubbo/DubboProtocol;Lorg/apache/dubbo/common/URL;)Ljava/util/function/IntFunction;
      77: invokeinterface #154,  2          // InterfaceMethod java/util/stream/IntStream.mapToObj:(Ljava/util/function/IntFunction;)Ljava/util/stream/Stream;
      82: invokestatic  #155                // Method java/util/stream/Collectors.toList:()Ljava/util/stream/Collector;
      85: invokeinterface #156,  2          // InterfaceMethod java/util/stream/Stream.collect:(Ljava/util/stream/Collector;)Ljava/lang/Object;
      90: checkcast     #157                // class java/util/List
      93: astore_3
      94: new           #158                // class org/apache/dubbo/rpc/protocol/dubbo/ExclusiveClientsProvider
      97: dup
      98: aload_3
      99: invokespecial #159                // Method org/apache/dubbo/rpc/protocol/dubbo/ExclusiveClientsProvider."<init>":(Ljava/util/List;)V
     102: areturn

  private org.apache.dubbo.rpc.protocol.dubbo.SharedClientsProvider getSharedClient(org.apache.dubbo.common.URL, int);
    Code:
       0: aload_1
       1: invokevirtual #93                 // Method org/apache/dubbo/common/URL.getAddress:()Ljava/lang/String;
       4: astore_3
       5: iload_2
       6: iconst_1
       7: invokestatic  #160                // Method java/lang/Math.max:(II)I
      10: istore        4
      12: aload_0
      13: getfield      #11                 // Field referenceClientMap:Ljava/util/Map;
      16: aload_3
      17: aload_0
      18: aload_1
      19: iload         4
      21: invokedynamic #161,  0            // InvokeDynamic #1:apply:(Lorg/apache/dubbo/rpc/protocol/dubbo/DubboProtocol;Lorg/apache/dubbo/common/URL;I)Ljava/util/function/BiFunction;
      26: invokeinterface #162,  3          // InterfaceMethod java/util/Map.compute:(Ljava/lang/Object;Ljava/util/function/BiFunction;)Ljava/lang/Object;
      31: checkcast     #163                // class org/apache/dubbo/rpc/protocol/dubbo/SharedClientsProvider
      34: areturn

  protected void scheduleRemoveSharedClient(java.lang.String, org.apache.dubbo.rpc.protocol.dubbo.SharedClientsProvider);
    Code:
       0: aload_0
       1: getfield      #18                 // Field frameworkModel:Lorg/apache/dubbo/rpc/model/FrameworkModel;
       4: invokevirtual #19                 // Method org/apache/dubbo/rpc/model/FrameworkModel.getBeanFactory:()Lorg/apache/dubbo/common/beans/factory/ScopeBeanFactory;
       7: ldc           #164                // class org/apache/dubbo/common/threadpool/manager/FrameworkExecutorRepository
       9: invokevirtual #165                // Method org/apache/dubbo/common/beans/factory/ScopeBeanFactory.getBean:(Ljava/lang/Class;)Ljava/lang/Object;
      12: checkcast     #164                // class org/apache/dubbo/common/threadpool/manager/FrameworkExecutorRepository
      15: invokevirtual #166                // Method org/apache/dubbo/common/threadpool/manager/FrameworkExecutorRepository.getSharedExecutor:()Ljava/util/concurrent/ExecutorService;
      18: aload_0
      19: aload_1
      20: aload_2
      21: invokedynamic #167,  0            // InvokeDynamic #2:call:(Lorg/apache/dubbo/rpc/protocol/dubbo/DubboProtocol;Ljava/lang/String;Lorg/apache/dubbo/rpc/protocol/dubbo/SharedClientsProvider;)Ljava/util/concurrent/Callable;
      26: invokeinterface #168,  2          // InterfaceMethod java/util/concurrent/ExecutorService.submit:(Ljava/util/concurrent/Callable;)Ljava/util/concurrent/Future;
      31: pop
      32: return

  private java.util.List<org.apache.dubbo.rpc.protocol.dubbo.ReferenceCountExchangeClient> buildReferenceCountExchangeClientList(org.apache.dubbo.common.URL, int);
    Code:
       0: new           #169                // class java/util/ArrayList
       3: dup
       4: invokespecial #170                // Method java/util/ArrayList."<init>":()V
       7: astore_3
       8: iconst_0
       9: istore        4
      11: iload         4
      13: iload_2
      14: if_icmpge     35
      17: aload_3
      18: aload_0
      19: aload_1
      20: invokespecial #171                // Method buildReferenceCountExchangeClient:(Lorg/apache/dubbo/common/URL;)Lorg/apache/dubbo/rpc/protocol/dubbo/ReferenceCountExchangeClient;
      23: invokeinterface #172,  2          // InterfaceMethod java/util/List.add:(Ljava/lang/Object;)Z
      28: pop
      29: iinc          4, 1
      32: goto          11
      35: aload_3
      36: areturn

  private org.apache.dubbo.rpc.protocol.dubbo.ReferenceCountExchangeClient buildReferenceCountExchangeClient(org.apache.dubbo.common.URL);
    Code:
       0: aload_0
       1: aload_1
       2: invokespecial #173                // Method initClient:(Lorg/apache/dubbo/common/URL;)Lorg/apache/dubbo/remoting/exchange/ExchangeClient;
       5: astore_2
       6: new           #174                // class org/apache/dubbo/rpc/protocol/dubbo/ReferenceCountExchangeClient
       9: dup
      10: aload_2
      11: ldc           #27                 // String dubbo
      13: invokespecial #175                // Method org/apache/dubbo/rpc/protocol/dubbo/ReferenceCountExchangeClient."<init>":(Lorg/apache/dubbo/remoting/exchange/ExchangeClient;Ljava/lang/String;)V
      16: astore_3
      17: aload_1
      18: invokevirtual #176                // Method org/apache/dubbo/common/URL.getScopeModel:()Lorg/apache/dubbo/rpc/model/ScopeModel;
      21: invokestatic  #177                // Method org/apache/dubbo/common/config/ConfigurationUtils.getServerShutdownTimeout:(Lorg/apache/dubbo/rpc/model/ScopeModel;)I
      24: istore        4
      26: aload_3
      27: iload         4
      29: invokevirtual #178                // Method org/apache/dubbo/rpc/protocol/dubbo/ReferenceCountExchangeClient.setShutdownWaitTime:(I)V
      32: aload_3
      33: areturn

  private org.apache.dubbo.remoting.exchange.ExchangeClient initClient(org.apache.dubbo.common.URL);
    Code:
       0: aload_1
       1: ldc           #133                // String client
       3: aload_1
       4: ldc           #117                // String server
       6: ldc           #118                // String netty
       8: invokevirtual #119                // Method org/apache/dubbo/common/URL.getParameter:(Ljava/lang/String;Ljava/lang/String;)Ljava/lang/String;
      11: invokevirtual #119                // Method org/apache/dubbo/common/URL.getParameter:(Ljava/lang/String;Ljava/lang/String;)Ljava/lang/String;
      14: astore_2
      15: aload_2
      16: invokestatic  #120                // Method org/apache/dubbo/common/utils/StringUtils.isNotEmpty:(Ljava/lang/String;)Z
      19: ifeq          90
      22: aload_1
      23: invokevirtual #121                // Method org/apache/dubbo/common/URL.getOrDefaultFrameworkModel:()Lorg/apache/dubbo/rpc/model/FrameworkModel;
      26: ldc           #122                // class org/apache/dubbo/remoting/Transporter
      28: invokevirtual #25                 // Method org/apache/dubbo/rpc/model/FrameworkModel.getExtensionLoader:(Ljava/lang/Class;)Lorg/apache/dubbo/common/extension/ExtensionLoader;
      31: aload_2
      32: invokevirtual #123                // Method org/apache/dubbo/common/extension/ExtensionLoader.hasExtension:(Ljava/lang/String;)Z
      35: ifne          90
      38: new           #124                // class org/apache/dubbo/rpc/RpcException
      41: dup
      42: new           #47                 // class java/lang/StringBuilder
      45: dup
      46: invokespecial #48                 // Method java/lang/StringBuilder."<init>":()V
      49: ldc           #134                // String Unsupported client type:
      51: invokevirtual #49                 // Method java/lang/StringBuilder.append:(Ljava/lang/String;)Ljava/lang/StringBuilder;
      54: aload_2
      55: invokevirtual #49                 // Method java/lang/StringBuilder.append:(Ljava/lang/String;)Ljava/lang/StringBuilder;
      58: ldc           #179                // String , supported client type is
      60: invokevirtual #49                 // Method java/lang/StringBuilder.append:(Ljava/lang/String;)Ljava/lang/StringBuilder;
      63: aload_1
      64: invokevirtual #121                // Method org/apache/dubbo/common/URL.getOrDefaultFrameworkModel:()Lorg/apache/dubbo/rpc/model/FrameworkModel;
      67: ldc           #122                // class org/apache/dubbo/remoting/Transporter
      69: invokevirtual #25                 // Method org/apache/dubbo/rpc/model/FrameworkModel.getExtensionLoader:(Ljava/lang/Class;)Lorg/apache/dubbo/common/extension/ExtensionLoader;
      72: invokevirtual #180                // Method org/apache/dubbo/common/extension/ExtensionLoader.getSupportedExtensions:()Ljava/util/Set;
      75: ldc           #181                // String
      77: invokestatic  #182                // Method org/apache/dubbo/common/utils/StringUtils.join:(Ljava/util/Collection;Ljava/lang/String;)Ljava/lang/String;
      80: invokevirtual #49                 // Method java/lang/StringBuilder.append:(Ljava/lang/String;)Ljava/lang/StringBuilder;
      83: invokevirtual #53                 // Method java/lang/StringBuilder.toString:()Ljava/lang/String;
      86: invokespecial #127                // Method org/apache/dubbo/rpc/RpcException."<init>":(Ljava/lang/String;)V
      89: athrow
      90: new           #183                // class org/apache/dubbo/common/url/component/ServiceConfigURL
      93: dup
      94: ldc           #27                 // String dubbo
      96: aload_1
      97: invokevirtual #184                // Method org/apache/dubbo/common/URL.getUsername:()Ljava/lang/String;
     100: aload_1
     101: invokevirtual #185                // Method org/apache/dubbo/common/URL.getPassword:()Ljava/lang/String;
     104: aload_1
     105: invokevirtual #186                // Method org/apache/dubbo/common/URL.getHost:()Ljava/lang/String;
     108: aload_1
     109: invokevirtual #32                 // Method org/apache/dubbo/common/URL.getPort:()I
     112: aload_1
     113: invokevirtual #187                // Method org/apache/dubbo/common/URL.getPath:()Ljava/lang/String;
     116: aload_1
     117: invokevirtual #188                // Method org/apache/dubbo/common/URL.getAllParameters:()Ljava/util/Map;
     120: invokespecial #189                // Method org/apache/dubbo/common/url/component/ServiceConfigURL."<init>":(Ljava/lang/String;Ljava/lang/String;Ljava/lang/String;Ljava/lang/String;ILjava/lang/String;Ljava/util/Map;)V
     123: astore_1
     124: aload_1
     125: ldc           #113                // String codec
     127: ldc           #27                 // String dubbo
     129: invokevirtual #190                // Method org/apache/dubbo/common/URL.addParameter:(Ljava/lang/String;Ljava/lang/String;)Lorg/apache/dubbo/common/URL;
     132: astore_1
     133: aload_1
     134: ldc           #110                // String heartbeat
     136: ldc           #111                // int 60000
     138: invokestatic  #112                // Method java/lang/String.valueOf:(I)Ljava/lang/String;
     141: invokevirtual #191                // Method org/apache/dubbo/common/URL.addParameterIfAbsent:(Ljava/lang/String;Ljava/lang/String;)Lorg/apache/dubbo/common/URL;
     144: astore_1
     145: aload_1
     146: ldc           #192                // String lazy
     148: iconst_0
     149: invokevirtual #79                 // Method org/apache/dubbo/common/URL.getParameter:(Ljava/lang/String;Z)Z
     152: ifeq          170
     155: new           #193                // class org/apache/dubbo/rpc/protocol/dubbo/LazyConnectExchangeClient
     158: dup
     159: aload_1
     160: aload_0
     161: getfield      #17                 // Field requestHandler:Lorg/apache/dubbo/remoting/exchange/ExchangeHandler;
     164: invokespecial #194                // Method org/apache/dubbo/rpc/protocol/dubbo/LazyConnectExchangeClient."<init>":(Lorg/apache/dubbo/common/URL;Lorg/apache/dubbo/remoting/exchange/ExchangeHandler;)V
     167: goto          178
     170: aload_1
     171: aload_0
     172: getfield      #17                 // Field requestHandler:Lorg/apache/dubbo/remoting/exchange/ExchangeHandler;
     175: invokestatic  #195                // Method org/apache/dubbo/remoting/exchange/Exchangers.connect:(Lorg/apache/dubbo/common/URL;Lorg/apache/dubbo/remoting/exchange/ExchangeHandler;)Lorg/apache/dubbo/remoting/exchange/ExchangeClient;
     178: areturn
     179: astore_3
     180: new           #124                // class org/apache/dubbo/rpc/RpcException
     183: dup
     184: new           #47                 // class java/lang/StringBuilder
     187: dup
     188: invokespecial #48                 // Method java/lang/StringBuilder."<init>":()V
     191: ldc           #196                // String Fail to create remoting client for service(
     193: invokevirtual #49                 // Method java/lang/StringBuilder.append:(Ljava/lang/String;)Ljava/lang/StringBuilder;
     196: aload_1
     197: invokevirtual #52                 // Method java/lang/StringBuilder.append:(Ljava/lang/Object;)Ljava/lang/StringBuilder;
     200: ldc           #197                // String ):
     202: invokevirtual #49                 // Method java/lang/StringBuilder.append:(Ljava/lang/String;)Ljava/lang/StringBuilder;
     205: aload_3
     206: invokevirtual #131                // Method org/apache/dubbo/remoting/RemotingException.getMessage:()Ljava/lang/String;
     209: invokevirtual #49                 // Method java/lang/StringBuilder.append:(Ljava/lang/String;)Ljava/lang/StringBuilder;
     212: invokevirtual #53                 // Method java/lang/StringBuilder.toString:()Ljava/lang/String;
     215: aload_3
     216: invokespecial #132                // Method org/apache/dubbo/rpc/RpcException."<init>":(Ljava/lang/String;Ljava/lang/Throwable;)V
     219: athrow
    Exception table:
       from    to  target type
          90   178   179   Class org/apache/dubbo/remoting/RemotingException

  public void destroy();
    Code:
       0: aload_0
       1: getfield      #14                 // Field destroyed:Ljava/util/concurrent/atomic/AtomicBoolean;
       4: iconst_0
       5: iconst_1
       6: invokevirtual #198                // Method java/util/concurrent/atomic/AtomicBoolean.compareAndSet:(ZZ)Z
       9: ifne          13
      12: return
      13: aload_0
      14: getfield      #7                  // Field logger:Lorg/apache/dubbo/common/logger/ErrorTypeAwareLogger;
      17: invokeinterface #199,  1          // InterfaceMethod org/apache/dubbo/common/logger/ErrorTypeAwareLogger.isInfoEnabled:()Z
      22: ifeq          64
      25: aload_0
      26: getfield      #7                  // Field logger:Lorg/apache/dubbo/common/logger/ErrorTypeAwareLogger;
      29: new           #47                 // class java/lang/StringBuilder
      32: dup
      33: invokespecial #48                 // Method java/lang/StringBuilder."<init>":()V
      36: ldc           #200                // String Destroying protocol [
      38: invokevirtual #49                 // Method java/lang/StringBuilder.append:(Ljava/lang/String;)Ljava/lang/StringBuilder;
      41: aload_0
      42: invokevirtual #103                // Method java/lang/Object.getClass:()Ljava/lang/Class;
      45: invokevirtual #104                // Method java/lang/Class.getSimpleName:()Ljava/lang/String;
      48: invokevirtual #49                 // Method java/lang/StringBuilder.append:(Ljava/lang/String;)Ljava/lang/StringBuilder;
      51: ldc           #201                // String ] ...
      53: invokevirtual #49                 // Method java/lang/StringBuilder.append:(Ljava/lang/String;)Ljava/lang/StringBuilder;
      56: invokevirtual #53                 // Method java/lang/StringBuilder.toString:()Ljava/lang/String;
      59: invokeinterface #202,  2          // InterfaceMethod org/apache/dubbo/common/logger/ErrorTypeAwareLogger.info:(Ljava/lang/String;)V
      64: new           #169                // class java/util/ArrayList
      67: dup
      68: aload_0
      69: getfield      #95                 // Field serverMap:Ljava/util/concurrent/ConcurrentMap;
      72: invokeinterface #203,  1          // InterfaceMethod java/util/concurrent/ConcurrentMap.keySet:()Ljava/util/Set;
      77: invokespecial #204                // Method java/util/ArrayList."<init>":(Ljava/util/Collection;)V
      80: invokevirtual #205                // Method java/util/ArrayList.iterator:()Ljava/util/Iterator;
      83: astore_1
      84: aload_1
      85: invokeinterface #206,  1          // InterfaceMethod java/util/Iterator.hasNext:()Z
      90: ifeq          253
      93: aload_1
      94: invokeinterface #207,  1          // InterfaceMethod java/util/Iterator.next:()Ljava/lang/Object;
      99: checkcast     #42                 // class java/lang/String
     102: astore_2
     103: aload_0
     104: getfield      #95                 // Field serverMap:Ljava/util/concurrent/ConcurrentMap;
     107: aload_2
     108: invokeinterface #208,  2          // InterfaceMethod java/util/concurrent/ConcurrentMap.remove:(Ljava/lang/Object;)Ljava/lang/Object;
     113: checkcast     #97                 // class org/apache/dubbo/rpc/ProtocolServer
     116: astore_3
     117: aload_3
     118: ifnonnull     124
     121: goto          84
     124: aload_3
     125: invokeinterface #209,  1          // InterfaceMethod org/apache/dubbo/rpc/ProtocolServer.getRemotingServer:()Lorg/apache/dubbo/remoting/RemotingServer;
     130: astore        4
     132: aload_0
     133: getfield      #7                  // Field logger:Lorg/apache/dubbo/common/logger/ErrorTypeAwareLogger;
     136: invokeinterface #199,  1          // InterfaceMethod org/apache/dubbo/common/logger/ErrorTypeAwareLogger.isInfoEnabled:()Z
     141: ifeq          178
     144: aload_0
     145: getfield      #7                  // Field logger:Lorg/apache/dubbo/common/logger/ErrorTypeAwareLogger;
     148: new           #47                 // class java/lang/StringBuilder
     151: dup
     152: invokespecial #48                 // Method java/lang/StringBuilder."<init>":()V
     155: ldc           #210                // String Closing dubbo server:
     157: invokevirtual #49                 // Method java/lang/StringBuilder.append:(Ljava/lang/String;)Ljava/lang/StringBuilder;
     160: aload         4
     162: invokeinterface #211,  1          // InterfaceMethod org/apache/dubbo/remoting/RemotingServer.getLocalAddress:()Ljava/net/InetSocketAddress;
     167: invokevirtual #52                 // Method java/lang/StringBuilder.append:(Ljava/lang/Object;)Ljava/lang/StringBuilder;
     170: invokevirtual #53                 // Method java/lang/StringBuilder.toString:()Ljava/lang/String;
     173: invokeinterface #202,  2          // InterfaceMethod org/apache/dubbo/common/logger/ErrorTypeAwareLogger.info:(Ljava/lang/String;)V
     178: aload         4
     180: aload_0
     181: aload_3
     182: invokevirtual #212                // Method getServerShutdownTimeout:(Lorg/apache/dubbo/rpc/ProtocolServer;)I
     185: invokeinterface #213,  2          // InterfaceMethod org/apache/dubbo/remoting/RemotingServer.close:(I)V
     190: goto          250
     193: astore        5
     195: aload_0
     196: getfield      #7                  // Field logger:Lorg/apache/dubbo/common/logger/ErrorTypeAwareLogger;
     199: ldc           #215                // String 4-8
     201: ldc           #86                 // String
     203: ldc           #86                 // String
     205: new           #47                 // class java/lang/StringBuilder
     208: dup
     209: invokespecial #48                 // Method java/lang/StringBuilder."<init>":()V
     212: ldc           #216                // String Close dubbo server [
     214: invokevirtual #49                 // Method java/lang/StringBuilder.append:(Ljava/lang/String;)Ljava/lang/StringBuilder;
     217: aload         4
     219: invokeinterface #211,  1          // InterfaceMethod org/apache/dubbo/remoting/RemotingServer.getLocalAddress:()Ljava/net/InetSocketAddress;
     224: invokevirtual #52                 // Method java/lang/StringBuilder.append:(Ljava/lang/Object;)Ljava/lang/StringBuilder;
     227: ldc           #217                // String ] failed:
     229: invokevirtual #49                 // Method java/lang/StringBuilder.append:(Ljava/lang/String;)Ljava/lang/StringBuilder;
     232: aload         5
     234: invokevirtual #218                // Method java/lang/Throwable.getMessage:()Ljava/lang/String;
     237: invokevirtual #49                 // Method java/lang/StringBuilder.append:(Ljava/lang/String;)Ljava/lang/StringBuilder;
     240: invokevirtual #53                 // Method java/lang/StringBuilder.toString:()Ljava/lang/String;
     243: aload         5
     245: invokeinterface #219,  6          // InterfaceMethod org/apache/dubbo/common/logger/ErrorTypeAwareLogger.warn:(Ljava/lang/String;Ljava/lang/String;Ljava/lang/String;Ljava/lang/String;Ljava/lang/Throwable;)V
     250: goto          84
     253: aload_0
     254: getfield      #95                 // Field serverMap:Ljava/util/concurrent/ConcurrentMap;
     257: invokeinterface #220,  1          // InterfaceMethod java/util/concurrent/ConcurrentMap.clear:()V
     262: new           #169                // class java/util/ArrayList
     265: dup
     266: aload_0
     267: getfield      #11                 // Field referenceClientMap:Ljava/util/Map;
     270: invokeinterface #64,  1           // InterfaceMethod java/util/Map.keySet:()Ljava/util/Set;
     275: invokespecial #204                // Method java/util/ArrayList."<init>":(Ljava/util/Collection;)V
     278: invokevirtual #205                // Method java/util/ArrayList.iterator:()Ljava/util/Iterator;
     281: astore_1
     282: aload_1
     283: invokeinterface #206,  1          // InterfaceMethod java/util/Iterator.hasNext:()Z
     288: ifeq          322
     291: aload_1
     292: invokeinterface #207,  1          // InterfaceMethod java/util/Iterator.next:()Ljava/lang/Object;
     297: checkcast     #42                 // class java/lang/String
     300: astore_2
     301: aload_0
     302: getfield      #11                 // Field referenceClientMap:Ljava/util/Map;
     305: aload_2
     306: invokeinterface #221,  2          // InterfaceMethod java/util/Map.remove:(Ljava/lang/Object;)Ljava/lang/Object;
     311: checkcast     #163                // class org/apache/dubbo/rpc/protocol/dubbo/SharedClientsProvider
     314: astore_3
     315: aload_3
     316: invokevirtual #222                // Method org/apache/dubbo/rpc/protocol/dubbo/SharedClientsProvider.forceClose:()V
     319: goto          282
     322: invokestatic  #223                // Method org/apache/dubbo/remoting/exchange/PortUnificationExchanger.close:()V
     325: aload_0
     326: getfield      #11                 // Field referenceClientMap:Ljava/util/Map;
     329: invokeinterface #224,  1          // InterfaceMethod java/util/Map.clear:()V
     334: aload_0
     335: invokespecial #225                // Method org/apache/dubbo/rpc/protocol/AbstractProtocol.destroy:()V
     338: return
    Exception table:
       from    to  target type
         132   190   193   Class java/lang/Throwable

  private org.apache.dubbo.rpc.Invocation getInvocationWithoutData(org.apache.dubbo.rpc.Invocation);
    Code:
       0: aload_0
       1: getfield      #7                  // Field logger:Lorg/apache/dubbo/common/logger/ErrorTypeAwareLogger;
       4: invokeinterface #226,  1          // InterfaceMethod org/apache/dubbo/common/logger/ErrorTypeAwareLogger.isDebugEnabled:()Z
       9: ifeq          14
      12: aload_1
      13: areturn
      14: aload_1
      15: instanceof    #227                // class org/apache/dubbo/rpc/RpcInvocation
      18: ifeq          33
      21: aload_1
      22: checkcast     #227                // class org/apache/dubbo/rpc/RpcInvocation
      25: astore_2
      26: aload_2
      27: aconst_null
      28: invokevirtual #228                // Method org/apache/dubbo/rpc/RpcInvocation.setArguments:([Ljava/lang/Object;)V
      31: aload_2
      32: areturn
      33: aload_1
      34: areturn

  private java.lang.Boolean lambda$scheduleRemoveSharedClient$2(java.lang.String, org.apache.dubbo.rpc.protocol.dubbo.SharedClientsProvider) throws java.lang.Exception;
    Code:
       0: aload_0
       1: getfield      #11                 // Field referenceClientMap:Ljava/util/Map;
       4: aload_1
       5: aload_2
       6: invokeinterface #229,  3          // InterfaceMethod java/util/Map.remove:(Ljava/lang/Object;Ljava/lang/Object;)Z
      11: invokestatic  #230                // Method java/lang/Boolean.valueOf:(Z)Ljava/lang/Boolean;
      14: areturn

  private org.apache.dubbo.rpc.protocol.dubbo.SharedClientsProvider lambda$getSharedClient$1(org.apache.dubbo.common.URL, int, java.lang.String, org.apache.dubbo.rpc.protocol.dubbo.SharedClientsProvider);
    Code:
       0: aload         4
       2: ifnull        16
       5: aload         4
       7: invokevirtual #231                // Method org/apache/dubbo/rpc/protocol/dubbo/SharedClientsProvider.increaseCount:()Z
      10: ifeq          16
      13: aload         4
      15: areturn
      16: new           #163                // class org/apache/dubbo/rpc/protocol/dubbo/SharedClientsProvider
      19: dup
      20: aload_0
      21: aload_3
      22: aload_0
      23: aload_1
      24: iload_2
      25: invokespecial #232                // Method buildReferenceCountExchangeClientList:(Lorg/apache/dubbo/common/URL;I)Ljava/util/List;
      28: invokespecial #233                // Method org/apache/dubbo/rpc/protocol/dubbo/SharedClientsProvider."<init>":(Lorg/apache/dubbo/rpc/protocol/dubbo/DubboProtocol;Ljava/lang/String;Ljava/util/List;)V
      31: areturn

  private org.apache.dubbo.remoting.exchange.ExchangeClient lambda$getClients$0(org.apache.dubbo.common.URL, int);
    Code:
       0: aload_0
       1: aload_1
       2: invokespecial #173                // Method initClient:(Lorg/apache/dubbo/common/URL;)Lorg/apache/dubbo/remoting/exchange/ExchangeClient;
       5: areturn

  static org.apache.dubbo.common.logger.ErrorTypeAwareLogger access$000(org.apache.dubbo.rpc.protocol.dubbo.DubboProtocol);
    Code:
       0: aload_0
       1: getfield      #7                  // Field logger:Lorg/apache/dubbo/common/logger/ErrorTypeAwareLogger;
       4: areturn

  static org.apache.dubbo.common.logger.ErrorTypeAwareLogger access$100(org.apache.dubbo.rpc.protocol.dubbo.DubboProtocol);
    Code:
       0: aload_0
       1: getfield      #7                  // Field logger:Lorg/apache/dubbo/common/logger/ErrorTypeAwareLogger;
       4: areturn

  static org.apache.dubbo.common.logger.ErrorTypeAwareLogger access$200(org.apache.dubbo.rpc.protocol.dubbo.DubboProtocol);
    Code:
       0: aload_0
       1: getfield      #7                  // Field logger:Lorg/apache/dubbo/common/logger/ErrorTypeAwareLogger;
       4: areturn

  static org.apache.dubbo.common.logger.ErrorTypeAwareLogger access$300(org.apache.dubbo.rpc.protocol.dubbo.DubboProtocol);
    Code:
       0: aload_0
       1: getfield      #7                  // Field logger:Lorg/apache/dubbo/common/logger/ErrorTypeAwareLogger;
       4: areturn

  static java.lang.String access$400(int, java.lang.String, java.lang.String, java.lang.String);
    Code:
       0: iload_0
       1: aload_1
       2: aload_2
       3: aload_3
       4: invokestatic  #6                  // Method serviceKey:(ILjava/lang/String;Ljava/lang/String;Ljava/lang/String;)Ljava/lang/String;
       7: areturn
}
