Compiled from "DubboIsolationExecutorSupport.java"
public class org.apache.dubbo.rpc.protocol.dubbo.DubboIsolationExecutorSupport extends org.apache.dubbo.rpc.executor.AbstractIsolationExecutorSupport {
  private static final org.apache.dubbo.common.logger.ErrorTypeAwareLogger logger;

  private final org.apache.dubbo.rpc.model.FrameworkServiceRepository frameworkServiceRepository;

  private final org.apache.dubbo.rpc.protocol.dubbo.DubboProtocol dubboProtocol;

  public org.apache.dubbo.rpc.protocol.dubbo.DubboIsolationExecutorSupport(org.apache.dubbo.common.URL);
    Code:
       0: aload_0
       1: aload_1
       2: invokespecial #1                  // Method org/apache/dubbo/rpc/executor/AbstractIsolationExecutorSupport."<init>":(Lorg/apache/dubbo/common/URL;)V
       5: aload_0
       6: aload_1
       7: invokevirtual #2                  // Method org/apache/dubbo/common/URL.getOrDefaultFrameworkModel:()Lorg/apache/dubbo/rpc/model/FrameworkModel;
      10: invokevirtual #3                  // Method org/apache/dubbo/rpc/model/FrameworkModel.getServiceRepository:()Lorg/apache/dubbo/rpc/model/FrameworkServiceRepository;
      13: putfield      #4                  // Field frameworkServiceRepository:Lorg/apache/dubbo/rpc/model/FrameworkServiceRepository;
      16: aload_0
      17: aload_1
      18: invokevirtual #2                  // Method org/apache/dubbo/common/URL.getOrDefaultFrameworkModel:()Lorg/apache/dubbo/rpc/model/FrameworkModel;
      21: invokestatic  #5                  // Method org/apache/dubbo/rpc/protocol/dubbo/DubboProtocol.getDubboProtocol:(Lorg/apache/dubbo/rpc/model/ScopeModel;)Lorg/apache/dubbo/rpc/protocol/dubbo/DubboProtocol;
      24: putfield      #6                  // Field dubboProtocol:Lorg/apache/dubbo/rpc/protocol/dubbo/DubboProtocol;
      27: return

  protected org.apache.dubbo.rpc.model.ProviderModel getProviderModel(java.lang.Object);
    Code:
       0: aload_1
       1: instanceof    #7                  // class org/apache/dubbo/remoting/exchange/Request
       4: ifne          9
       7: aconst_null
       8: areturn
       9: aload_1
      10: checkcast     #7                  // class org/apache/dubbo/remoting/exchange/Request
      13: astore_2
      14: aload_2
      15: invokevirtual #8                  // Method org/apache/dubbo/remoting/exchange/Request.getData:()Ljava/lang/Object;
      18: instanceof    #9                  // class org/apache/dubbo/rpc/protocol/dubbo/DecodeableRpcInvocation
      21: ifne          26
      24: aconst_null
      25: areturn
      26: aload_2
      27: invokevirtual #8                  // Method org/apache/dubbo/remoting/exchange/Request.getData:()Ljava/lang/Object;
      30: checkcast     #9                  // class org/apache/dubbo/rpc/protocol/dubbo/DecodeableRpcInvocation
      33: aload_0
      34: getfield      #6                  // Field dubboProtocol:Lorg/apache/dubbo/rpc/protocol/dubbo/DubboProtocol;
      37: invokevirtual #10                 // Method org/apache/dubbo/rpc/protocol/dubbo/DecodeableRpcInvocation.fillInvoker:(Lorg/apache/dubbo/rpc/protocol/dubbo/DubboProtocol;)V
      40: goto          44
      43: astore_3
      44: aload_2
      45: invokevirtual #8                  // Method org/apache/dubbo/remoting/exchange/Request.getData:()Ljava/lang/Object;
      48: checkcast     #12                 // class org/apache/dubbo/rpc/Invocation
      51: invokeinterface #13,  1           // InterfaceMethod org/apache/dubbo/rpc/Invocation.getServiceModel:()Lorg/apache/dubbo/rpc/model/ServiceModel;
      56: astore_3
      57: aload_3
      58: instanceof    #14                 // class org/apache/dubbo/rpc/model/ProviderModel
      61: ifeq          69
      64: aload_3
      65: checkcast     #14                 // class org/apache/dubbo/rpc/model/ProviderModel
      68: areturn
      69: aload_2
      70: invokevirtual #8                  // Method org/apache/dubbo/remoting/exchange/Request.getData:()Ljava/lang/Object;
      73: checkcast     #12                 // class org/apache/dubbo/rpc/Invocation
      76: invokeinterface #15,  1           // InterfaceMethod org/apache/dubbo/rpc/Invocation.getTargetServiceUniqueName:()Ljava/lang/String;
      81: astore        4
      83: aload         4
      85: invokestatic  #16                 // Method org/apache/dubbo/common/utils/StringUtils.isNotEmpty:(Ljava/lang/String;)Z
      88: ifeq          101
      91: aload_0
      92: getfield      #4                  // Field frameworkServiceRepository:Lorg/apache/dubbo/rpc/model/FrameworkServiceRepository;
      95: aload         4
      97: invokevirtual #17                 // Method org/apache/dubbo/rpc/model/FrameworkServiceRepository.lookupExportedService:(Ljava/lang/String;)Lorg/apache/dubbo/rpc/model/ProviderModel;
     100: areturn
     101: aconst_null
     102: areturn
    Exception table:
       from    to  target type
          26    40    43   Class org/apache/dubbo/remoting/RemotingException

  static {};
    Code:
       0: ldc           #18                 // class org/apache/dubbo/rpc/protocol/dubbo/DubboIsolationExecutorSupport
       2: invokestatic  #19                 // Method org/apache/dubbo/common/logger/LoggerFactory.getErrorTypeAwareLogger:(Ljava/lang/Class;)Lorg/apache/dubbo/common/logger/ErrorTypeAwareLogger;
       5: putstatic     #20                 // Field logger:Lorg/apache/dubbo/common/logger/ErrorTypeAwareLogger;
       8: return
}
