Compiled from "ExclusiveClientsProvider.java"
public class org.apache.dubbo.rpc.protocol.dubbo.ExclusiveClientsProvider implements org.apache.dubbo.rpc.protocol.dubbo.ClientsProvider {
  private static final org.apache.dubbo.common.logger.ErrorTypeAwareLogger logger;

  private final java.util.List<org.apache.dubbo.remoting.exchange.ExchangeClient> clients;

  public org.apache.dubbo.rpc.protocol.dubbo.ExclusiveClientsProvider(java.util.List<org.apache.dubbo.remoting.exchange.ExchangeClient>);
    Code:
       0: aload_0
       1: invokespecial #2                  // Method java/lang/Object."<init>":()V
       4: aload_0
       5: aload_1
       6: putfield      #3                  // Field clients:Ljava/util/List;
       9: return

  public java.util.List<org.apache.dubbo.remoting.exchange.ExchangeClient> getClients();
    Code:
       0: aload_0
       1: getfield      #3                  // Field clients:Ljava/util/List;
       4: areturn

  public void close(int);
    Code:
       0: aload_0
       1: getfield      #3                  // Field clients:Ljava/util/List;
       4: invokeinterface #4,  1            // InterfaceMethod java/util/List.iterator:()Ljava/util/Iterator;
       9: astore_2
      10: aload_2
      11: invokeinterface #5,  1            // InterfaceMethod java/util/Iterator.hasNext:()Z
      16: ifeq          65
      19: aload_2
      20: invokeinterface #6,  1            // InterfaceMethod java/util/Iterator.next:()Ljava/lang/Object;
      25: checkcast     #7                  // class org/apache/dubbo/remoting/exchange/ExchangeClient
      28: astore_3
      29: aload_3
      30: iload_1
      31: invokeinterface #8,  2            // InterfaceMethod org/apache/dubbo/remoting/exchange/ExchangeClient.close:(I)V
      36: goto          62
      39: astore        4
      41: getstatic     #10                 // Field logger:Lorg/apache/dubbo/common/logger/ErrorTypeAwareLogger;
      44: ldc           #11                 // String 4-7
      46: ldc           #12                 // String
      48: ldc           #12                 // String
      50: aload         4
      52: invokevirtual #13                 // Method java/lang/Throwable.getMessage:()Ljava/lang/String;
      55: aload         4
      57: invokeinterface #14,  6           // InterfaceMethod org/apache/dubbo/common/logger/ErrorTypeAwareLogger.warn:(Ljava/lang/String;Ljava/lang/String;Ljava/lang/String;Ljava/lang/String;Ljava/lang/Throwable;)V
      62: goto          10
      65: return
    Exception table:
       from    to  target type
          29    36    39   Class java/lang/Throwable

  static {};
    Code:
       0: ldc           #15                 // class org/apache/dubbo/rpc/protocol/dubbo/ExclusiveClientsProvider
       2: invokestatic  #16                 // Method org/apache/dubbo/common/logger/LoggerFactory.getErrorTypeAwareLogger:(Ljava/lang/Class;)Lorg/apache/dubbo/common/logger/ErrorTypeAwareLogger;
       5: putstatic     #10                 // Field logger:Lorg/apache/dubbo/common/logger/ErrorTypeAwareLogger;
       8: return
}
