Compiled from "FutureAdapter.java"
public class org.apache.dubbo.rpc.protocol.dubbo.FutureAdapter<V> extends java.util.concurrent.CompletableFuture<V> {
  private final java.util.concurrent.CompletableFuture<org.apache.dubbo.rpc.AppResponse> appResponseFuture;

  public org.apache.dubbo.rpc.protocol.dubbo.FutureAdapter(java.util.concurrent.CompletableFuture<org.apache.dubbo.rpc.AppResponse>);
    Code:
       0: aload_0
       1: invokespecial #1                  // Method java/util/concurrent/CompletableFuture."<init>":()V
       4: aload_0
       5: aload_1
       6: putfield      #2                  // Field appResponseFuture:Ljava/util/concurrent/CompletableFuture;
       9: aload_1
      10: aload_0
      11: invokedynamic #3,  0              // InvokeDynamic #0:accept:(Lorg/apache/dubbo/rpc/protocol/dubbo/FutureAdapter;)Ljava/util/function/BiConsumer;
      16: invokevirtual #4                  // Method java/util/concurrent/CompletableFuture.whenComplete:(Ljava/util/function/BiConsumer;)Ljava/util/concurrent/CompletableFuture;
      19: pop
      20: return

  public boolean cancel(boolean);
    Code:
       0: aload_0
       1: getfield      #2                  // Field appResponseFuture:Ljava/util/concurrent/CompletableFuture;
       4: iload_1
       5: invokevirtual #5                  // Method java/util/concurrent/CompletableFuture.cancel:(Z)Z
       8: ireturn

  public boolean isCancelled();
    Code:
       0: aload_0
       1: getfield      #2                  // Field appResponseFuture:Ljava/util/concurrent/CompletableFuture;
       4: invokevirtual #6                  // Method java/util/concurrent/CompletableFuture.isCancelled:()Z
       7: ireturn

  public boolean isDone();
    Code:
       0: aload_0
       1: invokespecial #7                  // Method java/util/concurrent/CompletableFuture.isDone:()Z
       4: ireturn

  public V get() throws java.lang.InterruptedException, java.util.concurrent.ExecutionException;
    Code:
       0: aload_0
       1: invokespecial #8                  // Method java/util/concurrent/CompletableFuture.get:()Ljava/lang/Object;
       4: areturn
       5: astore_1
       6: aload_1
       7: athrow
       8: astore_1
       9: new           #12                 // class org/apache/dubbo/rpc/RpcException
      12: dup
      13: aload_1
      14: invokespecial #13                 // Method org/apache/dubbo/rpc/RpcException."<init>":(Ljava/lang/Throwable;)V
      17: athrow
    Exception table:
       from    to  target type
           0     4     5   Class java/util/concurrent/ExecutionException
           0     4     5   Class java/lang/InterruptedException
           0     4     8   Class java/lang/Throwable

  public V get(long, java.util.concurrent.TimeUnit) throws java.lang.InterruptedException, java.util.concurrent.ExecutionException, java.util.concurrent.TimeoutException;
    Code:
       0: aload_0
       1: lload_1
       2: aload_3
       3: invokespecial #14                 // Method java/util/concurrent/CompletableFuture.get:(JLjava/util/concurrent/TimeUnit;)Ljava/lang/Object;
       6: areturn
       7: astore        4
       9: aload         4
      11: athrow
      12: astore        4
      14: new           #12                 // class org/apache/dubbo/rpc/RpcException
      17: dup
      18: aload         4
      20: invokespecial #13                 // Method org/apache/dubbo/rpc/RpcException."<init>":(Ljava/lang/Throwable;)V
      23: athrow
    Exception table:
       from    to  target type
           0     6     7   Class java/util/concurrent/TimeoutException
           0     6     7   Class java/util/concurrent/ExecutionException
           0     6     7   Class java/lang/InterruptedException
           0     6    12   Class java/lang/Throwable

  private void lambda$new$0(org.apache.dubbo.rpc.AppResponse, java.lang.Throwable);
    Code:
       0: aload_2
       1: ifnull        25
       4: aload_2
       5: instanceof    #16                 // class java/util/concurrent/CompletionException
       8: ifeq          16
      11: aload_2
      12: invokevirtual #17                 // Method java/lang/Throwable.getCause:()Ljava/lang/Throwable;
      15: astore_2
      16: aload_0
      17: aload_2
      18: invokevirtual #18                 // Method completeExceptionally:(Ljava/lang/Throwable;)Z
      21: pop
      22: goto          53
      25: aload_1
      26: invokevirtual #19                 // Method org/apache/dubbo/rpc/AppResponse.hasException:()Z
      29: ifeq          44
      32: aload_0
      33: aload_1
      34: invokevirtual #20                 // Method org/apache/dubbo/rpc/AppResponse.getException:()Ljava/lang/Throwable;
      37: invokevirtual #18                 // Method completeExceptionally:(Ljava/lang/Throwable;)Z
      40: pop
      41: goto          53
      44: aload_0
      45: aload_1
      46: invokevirtual #21                 // Method org/apache/dubbo/rpc/AppResponse.getValue:()Ljava/lang/Object;
      49: invokevirtual #22                 // Method complete:(Ljava/lang/Object;)Z
      52: pop
      53: return
}
