Compiled from "ReferenceCountExchangeClient.java"
final class org.apache.dubbo.rpc.protocol.dubbo.ReferenceCountExchangeClient implements org.apache.dubbo.remoting.exchange.ExchangeClient {
  private static final org.apache.dubbo.common.logger.ErrorTypeAwareLogger logger;

  private final org.apache.dubbo.common.URL url;

  private final java.util.concurrent.atomic.AtomicInteger referenceCount;

  private final java.util.concurrent.atomic.AtomicInteger disconnectCount;

  private static final java.lang.Integer warningPeriod;

  private org.apache.dubbo.remoting.exchange.ExchangeClient client;

  private int shutdownWaitTime;

  public org.apache.dubbo.rpc.protocol.dubbo.ReferenceCountExchangeClient(org.apache.dubbo.remoting.exchange.ExchangeClient, java.lang.String);
    Code:
       0: aload_0
       1: invokespecial #3                  // Method java/lang/Object."<init>":()V
       4: aload_0
       5: new           #4                  // class java/util/concurrent/atomic/AtomicInteger
       8: dup
       9: iconst_0
      10: invokespecial #5                  // Method java/util/concurrent/atomic/AtomicInteger."<init>":(I)V
      13: putfield      #6                  // Field referenceCount:Ljava/util/concurrent/atomic/AtomicInteger;
      16: aload_0
      17: new           #4                  // class java/util/concurrent/atomic/AtomicInteger
      20: dup
      21: iconst_0
      22: invokespecial #5                  // Method java/util/concurrent/atomic/AtomicInteger."<init>":(I)V
      25: putfield      #7                  // Field disconnectCount:Ljava/util/concurrent/atomic/AtomicInteger;
      28: aload_0
      29: sipush        10000
      32: putfield      #8                  // Field shutdownWaitTime:I
      35: aload_0
      36: aload_1
      37: putfield      #9                  // Field client:Lorg/apache/dubbo/remoting/exchange/ExchangeClient;
      40: aload_0
      41: getfield      #6                  // Field referenceCount:Ljava/util/concurrent/atomic/AtomicInteger;
      44: invokevirtual #10                 // Method java/util/concurrent/atomic/AtomicInteger.incrementAndGet:()I
      47: pop
      48: aload_0
      49: aload_1
      50: invokeinterface #11,  1           // InterfaceMethod org/apache/dubbo/remoting/exchange/ExchangeClient.getUrl:()Lorg/apache/dubbo/common/URL;
      55: putfield      #12                 // Field url:Lorg/apache/dubbo/common/URL;
      58: return

  public void reset(org.apache.dubbo.common.URL);
    Code:
       0: aload_0
       1: getfield      #9                  // Field client:Lorg/apache/dubbo/remoting/exchange/ExchangeClient;
       4: aload_1
       5: invokeinterface #13,  2           // InterfaceMethod org/apache/dubbo/remoting/exchange/ExchangeClient.reset:(Lorg/apache/dubbo/common/URL;)V
      10: return

  public java.util.concurrent.CompletableFuture<java.lang.Object> request(java.lang.Object) throws org.apache.dubbo.remoting.RemotingException;
    Code:
       0: aload_0
       1: getfield      #9                  // Field client:Lorg/apache/dubbo/remoting/exchange/ExchangeClient;
       4: aload_1
       5: invokeinterface #14,  2           // InterfaceMethod org/apache/dubbo/remoting/exchange/ExchangeClient.request:(Ljava/lang/Object;)Ljava/util/concurrent/CompletableFuture;
      10: areturn

  public org.apache.dubbo.common.URL getUrl();
    Code:
       0: aload_0
       1: getfield      #9                  // Field client:Lorg/apache/dubbo/remoting/exchange/ExchangeClient;
       4: invokeinterface #11,  1           // InterfaceMethod org/apache/dubbo/remoting/exchange/ExchangeClient.getUrl:()Lorg/apache/dubbo/common/URL;
       9: areturn

  public java.net.InetSocketAddress getRemoteAddress();
    Code:
       0: aload_0
       1: getfield      #9                  // Field client:Lorg/apache/dubbo/remoting/exchange/ExchangeClient;
       4: invokeinterface #15,  1           // InterfaceMethod org/apache/dubbo/remoting/exchange/ExchangeClient.getRemoteAddress:()Ljava/net/InetSocketAddress;
       9: areturn

  public org.apache.dubbo.remoting.ChannelHandler getChannelHandler();
    Code:
       0: aload_0
       1: getfield      #9                  // Field client:Lorg/apache/dubbo/remoting/exchange/ExchangeClient;
       4: invokeinterface #16,  1           // InterfaceMethod org/apache/dubbo/remoting/exchange/ExchangeClient.getChannelHandler:()Lorg/apache/dubbo/remoting/ChannelHandler;
       9: areturn

  public java.util.concurrent.CompletableFuture<java.lang.Object> request(java.lang.Object, int) throws org.apache.dubbo.remoting.RemotingException;
    Code:
       0: aload_0
       1: getfield      #9                  // Field client:Lorg/apache/dubbo/remoting/exchange/ExchangeClient;
       4: aload_1
       5: iload_2
       6: invokeinterface #17,  3           // InterfaceMethod org/apache/dubbo/remoting/exchange/ExchangeClient.request:(Ljava/lang/Object;I)Ljava/util/concurrent/CompletableFuture;
      11: areturn

  public java.util.concurrent.CompletableFuture<java.lang.Object> request(java.lang.Object, java.util.concurrent.ExecutorService) throws org.apache.dubbo.remoting.RemotingException;
    Code:
       0: aload_0
       1: getfield      #9                  // Field client:Lorg/apache/dubbo/remoting/exchange/ExchangeClient;
       4: aload_1
       5: aload_2
       6: invokeinterface #18,  3           // InterfaceMethod org/apache/dubbo/remoting/exchange/ExchangeClient.request:(Ljava/lang/Object;Ljava/util/concurrent/ExecutorService;)Ljava/util/concurrent/CompletableFuture;
      11: areturn

  public java.util.concurrent.CompletableFuture<java.lang.Object> request(java.lang.Object, int, java.util.concurrent.ExecutorService) throws org.apache.dubbo.remoting.RemotingException;
    Code:
       0: aload_0
       1: getfield      #9                  // Field client:Lorg/apache/dubbo/remoting/exchange/ExchangeClient;
       4: aload_1
       5: iload_2
       6: aload_3
       7: invokeinterface #19,  4           // InterfaceMethod org/apache/dubbo/remoting/exchange/ExchangeClient.request:(Ljava/lang/Object;ILjava/util/concurrent/ExecutorService;)Ljava/util/concurrent/CompletableFuture;
      12: areturn

  public boolean isConnected();
    Code:
       0: aload_0
       1: getfield      #9                  // Field client:Lorg/apache/dubbo/remoting/exchange/ExchangeClient;
       4: invokeinterface #20,  1           // InterfaceMethod org/apache/dubbo/remoting/exchange/ExchangeClient.isConnected:()Z
       9: ireturn

  public void reconnect() throws org.apache.dubbo.remoting.RemotingException;
    Code:
       0: aload_0
       1: getfield      #9                  // Field client:Lorg/apache/dubbo/remoting/exchange/ExchangeClient;
       4: invokeinterface #21,  1           // InterfaceMethod org/apache/dubbo/remoting/exchange/ExchangeClient.reconnect:()V
       9: return

  public java.net.InetSocketAddress getLocalAddress();
    Code:
       0: aload_0
       1: getfield      #9                  // Field client:Lorg/apache/dubbo/remoting/exchange/ExchangeClient;
       4: invokeinterface #22,  1           // InterfaceMethod org/apache/dubbo/remoting/exchange/ExchangeClient.getLocalAddress:()Ljava/net/InetSocketAddress;
       9: areturn

  public boolean hasAttribute(java.lang.String);
    Code:
       0: aload_0
       1: getfield      #9                  // Field client:Lorg/apache/dubbo/remoting/exchange/ExchangeClient;
       4: aload_1
       5: invokeinterface #23,  2           // InterfaceMethod org/apache/dubbo/remoting/exchange/ExchangeClient.hasAttribute:(Ljava/lang/String;)Z
      10: ireturn

  public void reset(org.apache.dubbo.common.Parameters);
    Code:
       0: aload_0
       1: getfield      #9                  // Field client:Lorg/apache/dubbo/remoting/exchange/ExchangeClient;
       4: aload_1
       5: invokeinterface #24,  2           // InterfaceMethod org/apache/dubbo/remoting/exchange/ExchangeClient.reset:(Lorg/apache/dubbo/common/Parameters;)V
      10: return

  public void send(java.lang.Object) throws org.apache.dubbo.remoting.RemotingException;
    Code:
       0: aload_0
       1: getfield      #9                  // Field client:Lorg/apache/dubbo/remoting/exchange/ExchangeClient;
       4: aload_1
       5: invokeinterface #25,  2           // InterfaceMethod org/apache/dubbo/remoting/exchange/ExchangeClient.send:(Ljava/lang/Object;)V
      10: return

  public org.apache.dubbo.remoting.exchange.ExchangeHandler getExchangeHandler();
    Code:
       0: aload_0
       1: getfield      #9                  // Field client:Lorg/apache/dubbo/remoting/exchange/ExchangeClient;
       4: invokeinterface #26,  1           // InterfaceMethod org/apache/dubbo/remoting/exchange/ExchangeClient.getExchangeHandler:()Lorg/apache/dubbo/remoting/exchange/ExchangeHandler;
       9: areturn

  public java.lang.Object getAttribute(java.lang.String);
    Code:
       0: aload_0
       1: getfield      #9                  // Field client:Lorg/apache/dubbo/remoting/exchange/ExchangeClient;
       4: aload_1
       5: invokeinterface #27,  2           // InterfaceMethod org/apache/dubbo/remoting/exchange/ExchangeClient.getAttribute:(Ljava/lang/String;)Ljava/lang/Object;
      10: areturn

  public void send(java.lang.Object, boolean) throws org.apache.dubbo.remoting.RemotingException;
    Code:
       0: aload_0
       1: getfield      #9                  // Field client:Lorg/apache/dubbo/remoting/exchange/ExchangeClient;
       4: aload_1
       5: iload_2
       6: invokeinterface #28,  3           // InterfaceMethod org/apache/dubbo/remoting/exchange/ExchangeClient.send:(Ljava/lang/Object;Z)V
      11: return

  public void setAttribute(java.lang.String, java.lang.Object);
    Code:
       0: aload_0
       1: getfield      #9                  // Field client:Lorg/apache/dubbo/remoting/exchange/ExchangeClient;
       4: aload_1
       5: aload_2
       6: invokeinterface #29,  3           // InterfaceMethod org/apache/dubbo/remoting/exchange/ExchangeClient.setAttribute:(Ljava/lang/String;Ljava/lang/Object;)V
      11: return

  public void removeAttribute(java.lang.String);
    Code:
       0: aload_0
       1: getfield      #9                  // Field client:Lorg/apache/dubbo/remoting/exchange/ExchangeClient;
       4: aload_1
       5: invokeinterface #30,  2           // InterfaceMethod org/apache/dubbo/remoting/exchange/ExchangeClient.removeAttribute:(Ljava/lang/String;)V
      10: return

  public void close();
    Code:
       0: aload_0
       1: iconst_0
       2: invokevirtual #31                 // Method close:(I)V
       5: return

  public void close(int);
    Code:
       0: aload_0
       1: getfield      #6                  // Field referenceCount:Ljava/util/concurrent/atomic/AtomicInteger;
       4: invokevirtual #32                 // Method java/util/concurrent/atomic/AtomicInteger.decrementAndGet:()I
       7: ifgt          40
      10: iload_1
      11: ifne          26
      14: aload_0
      15: getfield      #9                  // Field client:Lorg/apache/dubbo/remoting/exchange/ExchangeClient;
      18: invokeinterface #33,  1           // InterfaceMethod org/apache/dubbo/remoting/exchange/ExchangeClient.close:()V
      23: goto          36
      26: aload_0
      27: getfield      #9                  // Field client:Lorg/apache/dubbo/remoting/exchange/ExchangeClient;
      30: iload_1
      31: invokeinterface #34,  2           // InterfaceMethod org/apache/dubbo/remoting/exchange/ExchangeClient.close:(I)V
      36: aload_0
      37: invokespecial #35                 // Method replaceWithLazyClient:()V
      40: return

  public void startClose();
    Code:
       0: aload_0
       1: getfield      #9                  // Field client:Lorg/apache/dubbo/remoting/exchange/ExchangeClient;
       4: invokeinterface #36,  1           // InterfaceMethod org/apache/dubbo/remoting/exchange/ExchangeClient.startClose:()V
       9: return

  private void replaceWithLazyClient();
    Code:
       0: aload_0
       1: getfield      #7                  // Field disconnectCount:Ljava/util/concurrent/atomic/AtomicInteger;
       4: invokevirtual #37                 // Method java/util/concurrent/atomic/AtomicInteger.getAndIncrement:()I
       7: getstatic     #38                 // Field warningPeriod:Ljava/lang/Integer;
      10: invokevirtual #39                 // Method java/lang/Integer.intValue:()I
      13: irem
      14: iconst_1
      15: if_icmpne     72
      18: getstatic     #40                 // Field logger:Lorg/apache/dubbo/common/logger/ErrorTypeAwareLogger;
      21: ldc           #41                 // String 4-11
      23: ldc           #42                 // String
      25: ldc           #42                 // String
      27: new           #43                 // class java/lang/StringBuilder
      30: dup
      31: invokespecial #44                 // Method java/lang/StringBuilder."<init>":()V
      34: aload_0
      35: getfield      #12                 // Field url:Lorg/apache/dubbo/common/URL;
      38: invokevirtual #45                 // Method org/apache/dubbo/common/URL.getAddress:()Ljava/lang/String;
      41: invokevirtual #46                 // Method java/lang/StringBuilder.append:(Ljava/lang/String;)Ljava/lang/StringBuilder;
      44: ldc           #47                 // String
      46: invokevirtual #46                 // Method java/lang/StringBuilder.append:(Ljava/lang/String;)Ljava/lang/StringBuilder;
      49: aload_0
      50: getfield      #12                 // Field url:Lorg/apache/dubbo/common/URL;
      53: invokevirtual #48                 // Method org/apache/dubbo/common/URL.getServiceKey:()Ljava/lang/String;
      56: invokevirtual #46                 // Method java/lang/StringBuilder.append:(Ljava/lang/String;)Ljava/lang/StringBuilder;
      59: ldc           #49                 // String  safe guard client , should not be called ,must have a bug.
      61: invokevirtual #46                 // Method java/lang/StringBuilder.append:(Ljava/lang/String;)Ljava/lang/StringBuilder;
      64: invokevirtual #50                 // Method java/lang/StringBuilder.toString:()Ljava/lang/String;
      67: invokeinterface #51,  5           // InterfaceMethod org/apache/dubbo/common/logger/ErrorTypeAwareLogger.warn:(Ljava/lang/String;Ljava/lang/String;Ljava/lang/String;Ljava/lang/String;)V
      72: aload_0
      73: getfield      #9                  // Field client:Lorg/apache/dubbo/remoting/exchange/ExchangeClient;
      76: instanceof    #52                 // class org/apache/dubbo/rpc/protocol/dubbo/LazyConnectExchangeClient
      79: ifne          106
      82: aload_0
      83: new           #52                 // class org/apache/dubbo/rpc/protocol/dubbo/LazyConnectExchangeClient
      86: dup
      87: aload_0
      88: getfield      #12                 // Field url:Lorg/apache/dubbo/common/URL;
      91: aload_0
      92: getfield      #9                  // Field client:Lorg/apache/dubbo/remoting/exchange/ExchangeClient;
      95: invokeinterface #26,  1           // InterfaceMethod org/apache/dubbo/remoting/exchange/ExchangeClient.getExchangeHandler:()Lorg/apache/dubbo/remoting/exchange/ExchangeHandler;
     100: invokespecial #53                 // Method org/apache/dubbo/rpc/protocol/dubbo/LazyConnectExchangeClient."<init>":(Lorg/apache/dubbo/common/URL;Lorg/apache/dubbo/remoting/exchange/ExchangeHandler;)V
     103: putfield      #9                  // Field client:Lorg/apache/dubbo/remoting/exchange/ExchangeClient;
     106: return

  public boolean isClosed();
    Code:
       0: aload_0
       1: getfield      #9                  // Field client:Lorg/apache/dubbo/remoting/exchange/ExchangeClient;
       4: invokeinterface #54,  1           // InterfaceMethod org/apache/dubbo/remoting/exchange/ExchangeClient.isClosed:()Z
       9: ireturn

  public void incrementAndGetCount();
    Code:
       0: aload_0
       1: getfield      #6                  // Field referenceCount:Ljava/util/concurrent/atomic/AtomicInteger;
       4: invokevirtual #10                 // Method java/util/concurrent/atomic/AtomicInteger.incrementAndGet:()I
       7: pop
       8: return

  public int getCount();
    Code:
       0: aload_0
       1: getfield      #6                  // Field referenceCount:Ljava/util/concurrent/atomic/AtomicInteger;
       4: invokevirtual #55                 // Method java/util/concurrent/atomic/AtomicInteger.get:()I
       7: ireturn

  public int getShutdownWaitTime();
    Code:
       0: aload_0
       1: getfield      #8                  // Field shutdownWaitTime:I
       4: ireturn

  public void setShutdownWaitTime(int);
    Code:
       0: aload_0
       1: iload_1
       2: putfield      #8                  // Field shutdownWaitTime:I
       5: return

  static {};
    Code:
       0: ldc           #56                 // class org/apache/dubbo/rpc/protocol/dubbo/ReferenceCountExchangeClient
       2: invokestatic  #57                 // Method org/apache/dubbo/common/logger/LoggerFactory.getErrorTypeAwareLogger:(Ljava/lang/Class;)Lorg/apache/dubbo/common/logger/ErrorTypeAwareLogger;
       5: putstatic     #40                 // Field logger:Lorg/apache/dubbo/common/logger/ErrorTypeAwareLogger;
       8: bipush        50
      10: invokestatic  #58                 // Method java/lang/Integer.valueOf:(I)Ljava/lang/Integer;
      13: putstatic     #38                 // Field warningPeriod:Ljava/lang/Integer;
      16: return
}
