Compiled from "ConfigValidationUtils.java"
public class org.apache.dubbo.config.utils.ConfigValidationUtils {
  private static org.apache.dubbo.common.logger.ErrorTypeAwareLogger logger;

  private static final int MAX_LENGTH;

  private static final int MAX_PATH_LENGTH;

  private static final java.util.regex.Pattern PATTERN_NAME;

  private static final java.util.regex.Pattern PATTERN_MULTI_NAME;

  private static final java.util.regex.Pattern PATTERN_METHOD_NAME;

  private static final java.util.regex.Pattern PATTERN_PATH;

  private static final java.util.regex.Pattern PATTERN_NAME_HAS_SYMBOL;

  private static final java.util.regex.Pattern PATTERN_KEY;

  public static final java.lang.String IPV6_START_MARK;

  public static final java.lang.String IPV6_END_MARK;

  public org.apache.dubbo.config.utils.ConfigValidationUtils();
    Code:
       0: aload_0
       1: invokespecial #11                 // Method java/lang/Object."<init>":()V
       4: return

  public static java.util.List<org.apache.dubbo.common.URL> loadRegistries(org.apache.dubbo.config.AbstractInterfaceConfig, boolean);
    Code:
       0: new           #12                 // class java/util/ArrayList
       3: dup
       4: invokespecial #13                 // Method java/util/ArrayList."<init>":()V
       7: astore_2
       8: aload_0
       9: invokevirtual #14                 // Method org/apache/dubbo/config/AbstractInterfaceConfig.getApplication:()Lorg/apache/dubbo/config/ApplicationConfig;
      12: astore_3
      13: aload_0
      14: invokevirtual #15                 // Method org/apache/dubbo/config/AbstractInterfaceConfig.getRegistries:()Ljava/util/List;
      17: astore        4
      19: aload         4
      21: invokestatic  #16                 // Method org/apache/dubbo/common/utils/CollectionUtils.isNotEmpty:(Ljava/util/Collection;)Z
      24: ifeq          271
      27: aload         4
      29: invokeinterface #17,  1           // InterfaceMethod java/util/List.iterator:()Ljava/util/Iterator;
      34: astore        5
      36: aload         5
      38: invokeinterface #18,  1           // InterfaceMethod java/util/Iterator.hasNext:()Z
      43: ifeq          271
      46: aload         5
      48: invokeinterface #19,  1           // InterfaceMethod java/util/Iterator.next:()Ljava/lang/Object;
      53: checkcast     #20                 // class org/apache/dubbo/config/RegistryConfig
      56: astore        6
      58: aload         6
      60: invokevirtual #21                 // Method org/apache/dubbo/config/RegistryConfig.isRefreshed:()Z
      63: ifne          71
      66: aload         6
      68: invokevirtual #22                 // Method org/apache/dubbo/config/RegistryConfig.refresh:()V
      71: aload         6
      73: invokevirtual #23                 // Method org/apache/dubbo/config/RegistryConfig.getAddress:()Ljava/lang/String;
      76: astore        7
      78: aload         7
      80: invokestatic  #24                 // Method org/apache/dubbo/common/utils/StringUtils.isEmpty:(Ljava/lang/String;)Z
      83: ifeq          90
      86: ldc           #25                 // String 0.0.0.0
      88: astore        7
      90: ldc           #26                 // String N/A
      92: aload         7
      94: invokevirtual #27                 // Method java/lang/String.equalsIgnoreCase:(Ljava/lang/String;)Z
      97: ifne          268
     100: new           #28                 // class java/util/HashMap
     103: dup
     104: invokespecial #29                 // Method java/util/HashMap."<init>":()V
     107: astore        8
     109: aload         8
     111: aload_3
     112: invokestatic  #30                 // Method org/apache/dubbo/config/AbstractConfig.appendParameters:(Ljava/util/Map;Ljava/lang/Object;)V
     115: aload         8
     117: aload         6
     119: invokestatic  #30                 // Method org/apache/dubbo/config/AbstractConfig.appendParameters:(Ljava/util/Map;Ljava/lang/Object;)V
     122: aload         8
     124: ldc           #31                 // String path
     126: ldc           #32                 // class org/apache/dubbo/registry/RegistryService
     128: invokevirtual #33                 // Method java/lang/Class.getName:()Ljava/lang/String;
     131: invokeinterface #34,  3           // InterfaceMethod java/util/Map.put:(Ljava/lang/Object;Ljava/lang/Object;)Ljava/lang/Object;
     136: pop
     137: aload         8
     139: invokestatic  #35                 // Method org/apache/dubbo/config/AbstractInterfaceConfig.appendRuntimeParameters:(Ljava/util/Map;)V
     142: aload         8
     144: ldc           #36                 // String protocol
     146: invokeinterface #37,  2           // InterfaceMethod java/util/Map.containsKey:(Ljava/lang/Object;)Z
     151: ifne          166
     154: aload         8
     156: ldc           #36                 // String protocol
     158: ldc           #38                 // String dubbo
     160: invokeinterface #34,  3           // InterfaceMethod java/util/Map.put:(Ljava/lang/Object;Ljava/lang/Object;)Ljava/lang/Object;
     165: pop
     166: aload         7
     168: aload         8
     170: invokestatic  #39                 // Method org/apache/dubbo/common/utils/UrlUtils.parseURLs:(Ljava/lang/String;Ljava/util/Map;)Ljava/util/List;
     173: astore        9
     175: aload         9
     177: invokeinterface #17,  1           // InterfaceMethod java/util/List.iterator:()Ljava/util/Iterator;
     182: astore        10
     184: aload         10
     186: invokeinterface #18,  1           // InterfaceMethod java/util/Iterator.hasNext:()Z
     191: ifeq          268
     194: aload         10
     196: invokeinterface #19,  1           // InterfaceMethod java/util/Iterator.next:()Ljava/lang/Object;
     201: checkcast     #40                 // class org/apache/dubbo/common/URL
     204: astore        11
     206: aload         11
     208: invokestatic  #41                 // Method org/apache/dubbo/common/URLBuilder.from:(Lorg/apache/dubbo/common/URL;)Lorg/apache/dubbo/common/URLBuilder;
     211: ldc           #42                 // String registry
     213: aload         11
     215: invokevirtual #43                 // Method org/apache/dubbo/common/URL.getProtocol:()Ljava/lang/String;
     218: invokevirtual #44                 // Method org/apache/dubbo/common/URLBuilder.addParameter:(Ljava/lang/String;Ljava/lang/String;)Lorg/apache/dubbo/common/URLBuilder;
     221: aload         11
     223: invokestatic  #45                 // Method extractRegistryType:(Lorg/apache/dubbo/common/URL;)Ljava/lang/String;
     226: invokevirtual #46                 // Method org/apache/dubbo/common/URLBuilder.setProtocol:(Ljava/lang/String;)Lorg/apache/dubbo/common/URLBuilder;
     229: aload_0
     230: invokevirtual #47                 // Method org/apache/dubbo/config/AbstractInterfaceConfig.getScopeModel:()Lorg/apache/dubbo/rpc/model/ModuleModel;
     233: invokevirtual #48                 // Method org/apache/dubbo/common/URLBuilder.setScopeModel:(Lorg/apache/dubbo/rpc/model/ScopeModel;)Lorg/apache/dubbo/common/URLBuilder;
     236: invokevirtual #49                 // Method org/apache/dubbo/common/URLBuilder.build:()Lorg/apache/dubbo/common/url/component/ServiceConfigURL;
     239: astore        11
     241: iload_1
     242: ifne          256
     245: aload         11
     247: ldc           #50                 // String subscribe
     249: iconst_1
     250: invokevirtual #51                 // Method org/apache/dubbo/common/URL.getParameter:(Ljava/lang/String;Z)Z
     253: ifeq          265
     256: aload_2
     257: aload         11
     259: invokeinterface #52,  2           // InterfaceMethod java/util/List.add:(Ljava/lang/Object;)Z
     264: pop
     265: goto          184
     268: goto          36
     271: aload_0
     272: invokevirtual #47                 // Method org/apache/dubbo/config/AbstractInterfaceConfig.getScopeModel:()Lorg/apache/dubbo/rpc/model/ModuleModel;
     275: aload_2
     276: iload_1
     277: invokestatic  #53                 // Method genCompatibleRegistries:(Lorg/apache/dubbo/rpc/model/ScopeModel;Ljava/util/List;Z)Ljava/util/List;
     280: areturn

  private static java.util.List<org.apache.dubbo.common.URL> genCompatibleRegistries(org.apache.dubbo.rpc.model.ScopeModel, java.util.List<org.apache.dubbo.common.URL>, boolean);
    Code:
       0: new           #12                 // class java/util/ArrayList
       3: dup
       4: aload_1
       5: invokeinterface #54,  1           // InterfaceMethod java/util/List.size:()I
      10: invokespecial #55                 // Method java/util/ArrayList."<init>":(I)V
      13: astore_3
      14: aload_1
      15: iload_2
      16: aload_0
      17: aload_3
      18: aload_1
      19: invokedynamic #56,  0             // InvokeDynamic #0:accept:(ZLorg/apache/dubbo/rpc/model/ScopeModel;Ljava/util/List;Ljava/util/List;)Ljava/util/function/Consumer;
      24: invokeinterface #57,  2           // InterfaceMethod java/util/List.forEach:(Ljava/util/function/Consumer;)V
      29: aload_3
      30: areturn

  private static boolean isValidRegisterMode(java.lang.String);
    Code:
       0: aload_0
       1: invokestatic  #58                 // Method org/apache/dubbo/common/utils/StringUtils.isNotEmpty:(Ljava/lang/String;)Z
       4: ifeq          38
       7: ldc           #59                 // String interface
       9: aload_0
      10: invokevirtual #27                 // Method java/lang/String.equalsIgnoreCase:(Ljava/lang/String;)Z
      13: ifne          34
      16: ldc           #60                 // String instance
      18: aload_0
      19: invokevirtual #27                 // Method java/lang/String.equalsIgnoreCase:(Ljava/lang/String;)Z
      22: ifne          34
      25: ldc           #61                 // String all
      27: aload_0
      28: invokevirtual #27                 // Method java/lang/String.equalsIgnoreCase:(Ljava/lang/String;)Z
      31: ifeq          38
      34: iconst_1
      35: goto          39
      38: iconst_0
      39: ireturn

  private static boolean registryNotExists(org.apache.dubbo.common.URL, java.util.List<org.apache.dubbo.common.URL>, java.lang.String);
    Code:
       0: aload_1
       1: invokeinterface #62,  1           // InterfaceMethod java/util/List.stream:()Ljava/util/stream/Stream;
       6: aload_2
       7: aload_0
       8: invokedynamic #63,  0             // InvokeDynamic #1:test:(Ljava/lang/String;Lorg/apache/dubbo/common/URL;)Ljava/util/function/Predicate;
      13: invokeinterface #64,  2           // InterfaceMethod java/util/stream/Stream.noneMatch:(Ljava/util/function/Predicate;)Z
      18: ireturn

  public static org.apache.dubbo.common.URL loadMonitor(org.apache.dubbo.config.AbstractInterfaceConfig, org.apache.dubbo.common.URL);
    Code:
       0: new           #28                 // class java/util/HashMap
       3: dup
       4: invokespecial #29                 // Method java/util/HashMap."<init>":()V
       7: astore_2
       8: aload_2
       9: ldc           #59                 // String interface
      11: ldc           #65                 // class org/apache/dubbo/monitor/MonitorService
      13: invokevirtual #33                 // Method java/lang/Class.getName:()Ljava/lang/String;
      16: invokeinterface #34,  3           // InterfaceMethod java/util/Map.put:(Ljava/lang/Object;Ljava/lang/Object;)Ljava/lang/Object;
      21: pop
      22: aload_2
      23: invokestatic  #35                 // Method org/apache/dubbo/config/AbstractInterfaceConfig.appendRuntimeParameters:(Ljava/util/Map;)V
      26: ldc           #66                 // String DUBBO_IP_TO_REGISTRY
      28: invokestatic  #67                 // Method org/apache/dubbo/common/utils/ConfigUtils.getSystemProperty:(Ljava/lang/String;)Ljava/lang/String;
      31: astore_3
      32: aload_3
      33: invokestatic  #24                 // Method org/apache/dubbo/common/utils/StringUtils.isEmpty:(Ljava/lang/String;)Z
      36: ifeq          46
      39: invokestatic  #68                 // Method org/apache/dubbo/common/utils/NetUtils.getLocalHost:()Ljava/lang/String;
      42: astore_3
      43: goto          80
      46: aload_3
      47: invokestatic  #69                 // Method org/apache/dubbo/common/utils/NetUtils.isInvalidLocalHost:(Ljava/lang/String;)Z
      50: ifeq          80
      53: new           #70                 // class java/lang/IllegalArgumentException
      56: dup
      57: new           #71                 // class java/lang/StringBuilder
      60: dup
      61: invokespecial #72                 // Method java/lang/StringBuilder."<init>":()V
      64: ldc           #73                 // String Specified invalid registry ip from property:DUBBO_IP_TO_REGISTRY, value:
      66: invokevirtual #74                 // Method java/lang/StringBuilder.append:(Ljava/lang/String;)Ljava/lang/StringBuilder;
      69: aload_3
      70: invokevirtual #74                 // Method java/lang/StringBuilder.append:(Ljava/lang/String;)Ljava/lang/StringBuilder;
      73: invokevirtual #75                 // Method java/lang/StringBuilder.toString:()Ljava/lang/String;
      76: invokespecial #76                 // Method java/lang/IllegalArgumentException."<init>":(Ljava/lang/String;)V
      79: athrow
      80: aload_2
      81: ldc           #77                 // String register.ip
      83: aload_3
      84: invokeinterface #34,  3           // InterfaceMethod java/util/Map.put:(Ljava/lang/Object;Ljava/lang/Object;)Ljava/lang/Object;
      89: pop
      90: aload_0
      91: invokevirtual #78                 // Method org/apache/dubbo/config/AbstractInterfaceConfig.getMonitor:()Lorg/apache/dubbo/config/MonitorConfig;
      94: astore        4
      96: aload_0
      97: invokevirtual #14                 // Method org/apache/dubbo/config/AbstractInterfaceConfig.getApplication:()Lorg/apache/dubbo/config/ApplicationConfig;
     100: astore        5
     102: aload_2
     103: aload         4
     105: invokestatic  #30                 // Method org/apache/dubbo/config/AbstractConfig.appendParameters:(Ljava/util/Map;Ljava/lang/Object;)V
     108: aload_2
     109: aload         5
     111: invokestatic  #30                 // Method org/apache/dubbo/config/AbstractConfig.appendParameters:(Ljava/util/Map;Ljava/lang/Object;)V
     114: aconst_null
     115: astore        6
     117: ldc           #79                 // String dubbo.monitor.address
     119: invokestatic  #80                 // Method java/lang/System.getProperty:(Ljava/lang/String;)Ljava/lang/String;
     122: astore        7
     124: aload         7
     126: ifnull        144
     129: aload         7
     131: invokevirtual #81                 // Method java/lang/String.length:()I
     134: ifle          144
     137: aload         7
     139: astore        6
     141: goto          156
     144: aload         4
     146: ifnull        156
     149: aload         4
     151: invokevirtual #82                 // Method org/apache/dubbo/config/MonitorConfig.getAddress:()Ljava/lang/String;
     154: astore        6
     156: aload         4
     158: ifnonnull     165
     161: aconst_null
     162: goto          170
     165: aload         4
     167: invokevirtual #83                 // Method org/apache/dubbo/config/MonitorConfig.getProtocol:()Ljava/lang/String;
     170: astore        8
     172: aload         4
     174: ifnull        227
     177: ldc           #42                 // String registry
     179: aload         8
     181: invokevirtual #84                 // Method java/lang/String.equals:(Ljava/lang/Object;)Z
     184: ifne          197
     187: ldc           #85                 // String service-discovery-registry
     189: aload         8
     191: invokevirtual #84                 // Method java/lang/String.equals:(Ljava/lang/Object;)Z
     194: ifeq          227
     197: aload_1
     198: ifnull        227
     201: aload_1
     202: invokestatic  #41                 // Method org/apache/dubbo/common/URLBuilder.from:(Lorg/apache/dubbo/common/URL;)Lorg/apache/dubbo/common/URLBuilder;
     205: ldc           #38                 // String dubbo
     207: invokevirtual #46                 // Method org/apache/dubbo/common/URLBuilder.setProtocol:(Ljava/lang/String;)Lorg/apache/dubbo/common/URLBuilder;
     210: ldc           #36                 // String protocol
     212: aload         8
     214: invokevirtual #44                 // Method org/apache/dubbo/common/URLBuilder.addParameter:(Ljava/lang/String;Ljava/lang/String;)Lorg/apache/dubbo/common/URLBuilder;
     217: ldc           #86                 // String refer
     219: aload_2
     220: invokevirtual #87                 // Method org/apache/dubbo/common/URLBuilder.putAttribute:(Ljava/lang/String;Ljava/lang/Object;)Lorg/apache/dubbo/common/URLBuilder;
     223: invokevirtual #49                 // Method org/apache/dubbo/common/URLBuilder.build:()Lorg/apache/dubbo/common/url/component/ServiceConfigURL;
     226: areturn
     227: aload         6
     229: invokestatic  #88                 // Method org/apache/dubbo/common/utils/ConfigUtils.isNotEmpty:(Ljava/lang/String;)Z
     232: ifne          243
     235: aload         8
     237: invokestatic  #88                 // Method org/apache/dubbo/common/utils/ConfigUtils.isNotEmpty:(Ljava/lang/String;)Z
     240: ifeq          337
     243: aload_2
     244: ldc           #36                 // String protocol
     246: invokeinterface #37,  2           // InterfaceMethod java/util/Map.containsKey:(Ljava/lang/Object;)Z
     251: ifne          318
     254: aload_0
     255: invokevirtual #47                 // Method org/apache/dubbo/config/AbstractInterfaceConfig.getScopeModel:()Lorg/apache/dubbo/rpc/model/ModuleModel;
     258: ldc           #89                 // class org/apache/dubbo/monitor/MonitorFactory
     260: invokevirtual #90                 // Method org/apache/dubbo/rpc/model/ModuleModel.getExtensionLoader:(Ljava/lang/Class;)Lorg/apache/dubbo/common/extension/ExtensionLoader;
     263: ldc           #91                 // String logstat
     265: invokevirtual #92                 // Method org/apache/dubbo/common/extension/ExtensionLoader.hasExtension:(Ljava/lang/String;)Z
     268: ifeq          285
     271: aload_2
     272: ldc           #36                 // String protocol
     274: ldc           #91                 // String logstat
     276: invokeinterface #34,  3           // InterfaceMethod java/util/Map.put:(Ljava/lang/Object;Ljava/lang/Object;)Ljava/lang/Object;
     281: pop
     282: goto          318
     285: aload         8
     287: invokestatic  #88                 // Method org/apache/dubbo/common/utils/ConfigUtils.isNotEmpty:(Ljava/lang/String;)Z
     290: ifeq          307
     293: aload_2
     294: ldc           #36                 // String protocol
     296: aload         8
     298: invokeinterface #34,  3           // InterfaceMethod java/util/Map.put:(Ljava/lang/Object;Ljava/lang/Object;)Ljava/lang/Object;
     303: pop
     304: goto          318
     307: aload_2
     308: ldc           #36                 // String protocol
     310: ldc           #38                 // String dubbo
     312: invokeinterface #34,  3           // InterfaceMethod java/util/Map.put:(Ljava/lang/Object;Ljava/lang/Object;)Ljava/lang/Object;
     317: pop
     318: aload         6
     320: invokestatic  #93                 // Method org/apache/dubbo/common/utils/ConfigUtils.isEmpty:(Ljava/lang/String;)Z
     323: ifeq          330
     326: ldc           #94                 // String 127.0.0.1
     328: astore        6
     330: aload         6
     332: aload_2
     333: invokestatic  #95                 // Method org/apache/dubbo/common/utils/UrlUtils.parseURL:(Ljava/lang/String;Ljava/util/Map;)Lorg/apache/dubbo/common/URL;
     336: areturn
     337: aconst_null
     338: areturn

  public static void checkMock(java.lang.Class<?>, org.apache.dubbo.config.AbstractInterfaceConfig);
    Code:
       0: aload_1
       1: invokevirtual #96                 // Method org/apache/dubbo/config/AbstractInterfaceConfig.getMock:()Ljava/lang/String;
       4: astore_2
       5: aload_2
       6: invokestatic  #93                 // Method org/apache/dubbo/common/utils/ConfigUtils.isEmpty:(Ljava/lang/String;)Z
       9: ifeq          13
      12: return
      13: aload_2
      14: invokestatic  #97                 // Method org/apache/dubbo/rpc/support/MockInvoker.normalizeMock:(Ljava/lang/String;)Ljava/lang/String;
      17: astore_3
      18: aload_3
      19: ldc           #98                 // String return
      21: invokevirtual #99                 // Method java/lang/String.startsWith:(Ljava/lang/String;)Z
      24: ifeq          82
      27: aload_3
      28: ldc           #98                 // String return
      30: invokevirtual #81                 // Method java/lang/String.length:()I
      33: invokevirtual #100                // Method java/lang/String.substring:(I)Ljava/lang/String;
      36: invokevirtual #101                // Method java/lang/String.trim:()Ljava/lang/String;
      39: astore_3
      40: aload_3
      41: invokestatic  #102                // Method org/apache/dubbo/rpc/support/MockInvoker.parseMockValue:(Ljava/lang/String;)Ljava/lang/Object;
      44: pop
      45: goto          166
      48: astore        4
      50: new           #104                // class java/lang/IllegalStateException
      53: dup
      54: new           #71                 // class java/lang/StringBuilder
      57: dup
      58: invokespecial #72                 // Method java/lang/StringBuilder."<init>":()V
      61: ldc           #105                // String Illegal mock return in <dubbo:service/reference ... mock=\"
      63: invokevirtual #74                 // Method java/lang/StringBuilder.append:(Ljava/lang/String;)Ljava/lang/StringBuilder;
      66: aload_2
      67: invokevirtual #74                 // Method java/lang/StringBuilder.append:(Ljava/lang/String;)Ljava/lang/StringBuilder;
      70: ldc           #106                // String \" />
      72: invokevirtual #74                 // Method java/lang/StringBuilder.append:(Ljava/lang/String;)Ljava/lang/StringBuilder;
      75: invokevirtual #75                 // Method java/lang/StringBuilder.toString:()Ljava/lang/String;
      78: invokespecial #107                // Method java/lang/IllegalStateException."<init>":(Ljava/lang/String;)V
      81: athrow
      82: aload_3
      83: ldc           #108                // String throw
      85: invokevirtual #99                 // Method java/lang/String.startsWith:(Ljava/lang/String;)Z
      88: ifeq          153
      91: aload_3
      92: ldc           #108                // String throw
      94: invokevirtual #81                 // Method java/lang/String.length:()I
      97: invokevirtual #100                // Method java/lang/String.substring:(I)Ljava/lang/String;
     100: invokevirtual #101                // Method java/lang/String.trim:()Ljava/lang/String;
     103: astore_3
     104: aload_3
     105: invokestatic  #88                 // Method org/apache/dubbo/common/utils/ConfigUtils.isNotEmpty:(Ljava/lang/String;)Z
     108: ifeq          166
     111: aload_3
     112: invokestatic  #109                // Method org/apache/dubbo/rpc/support/MockInvoker.getThrowable:(Ljava/lang/String;)Ljava/lang/Throwable;
     115: pop
     116: goto          166
     119: astore        4
     121: new           #104                // class java/lang/IllegalStateException
     124: dup
     125: new           #71                 // class java/lang/StringBuilder
     128: dup
     129: invokespecial #72                 // Method java/lang/StringBuilder."<init>":()V
     132: ldc           #110                // String Illegal mock throw in <dubbo:service/reference ... mock=\"
     134: invokevirtual #74                 // Method java/lang/StringBuilder.append:(Ljava/lang/String;)Ljava/lang/StringBuilder;
     137: aload_2
     138: invokevirtual #74                 // Method java/lang/StringBuilder.append:(Ljava/lang/String;)Ljava/lang/StringBuilder;
     141: ldc           #106                // String \" />
     143: invokevirtual #74                 // Method java/lang/StringBuilder.append:(Ljava/lang/String;)Ljava/lang/StringBuilder;
     146: invokevirtual #75                 // Method java/lang/StringBuilder.toString:()Ljava/lang/String;
     149: invokespecial #107                // Method java/lang/IllegalStateException."<init>":(Ljava/lang/String;)V
     152: athrow
     153: aload_1
     154: invokevirtual #47                 // Method org/apache/dubbo/config/AbstractInterfaceConfig.getScopeModel:()Lorg/apache/dubbo/rpc/model/ModuleModel;
     157: invokevirtual #111                // Method org/apache/dubbo/rpc/model/ModuleModel.getExtensionDirector:()Lorg/apache/dubbo/common/extension/ExtensionDirector;
     160: aload_3
     161: aload_0
     162: invokestatic  #112                // Method org/apache/dubbo/rpc/support/MockInvoker.getMockObject:(Lorg/apache/dubbo/common/extension/ExtensionDirector;Ljava/lang/String;Ljava/lang/Class;)Ljava/lang/Object;
     165: pop
     166: return
    Exception table:
       from    to  target type
          40    45    48   Class java/lang/Exception
         111   116   119   Class java/lang/Exception

  public static void validateAbstractInterfaceConfig(org.apache.dubbo.config.AbstractInterfaceConfig);
    Code:
       0: ldc           #113                // String local
       2: aload_0
       3: invokevirtual #114                // Method org/apache/dubbo/config/AbstractInterfaceConfig.getLocal:()Ljava/lang/String;
       6: invokestatic  #115                // Method checkName:(Ljava/lang/String;Ljava/lang/String;)V
       9: ldc           #116                // String stub
      11: aload_0
      12: invokevirtual #117                // Method org/apache/dubbo/config/AbstractInterfaceConfig.getStub:()Ljava/lang/String;
      15: invokestatic  #115                // Method checkName:(Ljava/lang/String;Ljava/lang/String;)V
      18: ldc           #118                // String owner
      20: aload_0
      21: invokevirtual #119                // Method org/apache/dubbo/config/AbstractInterfaceConfig.getOwner:()Ljava/lang/String;
      24: invokestatic  #120                // Method checkMultiName:(Ljava/lang/String;Ljava/lang/String;)V
      27: aload_0
      28: invokevirtual #47                 // Method org/apache/dubbo/config/AbstractInterfaceConfig.getScopeModel:()Lorg/apache/dubbo/rpc/model/ModuleModel;
      31: ldc           #121                // class org/apache/dubbo/rpc/ProxyFactory
      33: ldc           #122                // String proxy
      35: aload_0
      36: invokevirtual #123                // Method org/apache/dubbo/config/AbstractInterfaceConfig.getProxy:()Ljava/lang/String;
      39: invokestatic  #124                // Method checkExtension:(Lorg/apache/dubbo/rpc/model/ScopeModel;Ljava/lang/Class;Ljava/lang/String;Ljava/lang/String;)V
      42: aload_0
      43: invokevirtual #47                 // Method org/apache/dubbo/config/AbstractInterfaceConfig.getScopeModel:()Lorg/apache/dubbo/rpc/model/ModuleModel;
      46: ldc           #125                // class org/apache/dubbo/rpc/cluster/Cluster
      48: ldc           #126                // String cluster
      50: aload_0
      51: invokevirtual #127                // Method org/apache/dubbo/config/AbstractInterfaceConfig.getCluster:()Ljava/lang/String;
      54: invokestatic  #124                // Method checkExtension:(Lorg/apache/dubbo/rpc/model/ScopeModel;Ljava/lang/Class;Ljava/lang/String;Ljava/lang/String;)V
      57: aload_0
      58: invokevirtual #47                 // Method org/apache/dubbo/config/AbstractInterfaceConfig.getScopeModel:()Lorg/apache/dubbo/rpc/model/ModuleModel;
      61: iconst_2
      62: anewarray     #128                // class java/lang/Class
      65: dup
      66: iconst_0
      67: ldc           #129                // class org/apache/dubbo/rpc/Filter
      69: aastore
      70: dup
      71: iconst_1
      72: ldc           #130                // class org/apache/dubbo/rpc/cluster/filter/ClusterFilter
      74: aastore
      75: invokestatic  #131                // Method java/util/Arrays.asList:([Ljava/lang/Object;)Ljava/util/List;
      78: ldc           #132                // String filter
      80: aload_0
      81: invokevirtual #133                // Method org/apache/dubbo/config/AbstractInterfaceConfig.getFilter:()Ljava/lang/String;
      84: invokestatic  #134                // Method checkMultiExtension:(Lorg/apache/dubbo/rpc/model/ScopeModel;Ljava/util/List;Ljava/lang/String;Ljava/lang/String;)V
      87: ldc           #135                // String layer
      89: aload_0
      90: invokevirtual #136                // Method org/apache/dubbo/config/AbstractInterfaceConfig.getLayer:()Ljava/lang/String;
      93: invokestatic  #137                // Method checkNameHasSymbol:(Ljava/lang/String;Ljava/lang/String;)V
      96: aload_0
      97: invokevirtual #138                // Method org/apache/dubbo/config/AbstractInterfaceConfig.getMethods:()Ljava/util/List;
     100: astore_1
     101: aload_1
     102: invokestatic  #16                 // Method org/apache/dubbo/common/utils/CollectionUtils.isNotEmpty:(Ljava/util/Collection;)Z
     105: ifeq          119
     108: aload_1
     109: invokedynamic #139,  0            // InvokeDynamic #2:accept:()Ljava/util/function/Consumer;
     114: invokeinterface #57,  2           // InterfaceMethod java/util/List.forEach:(Ljava/util/function/Consumer;)V
     119: return

  public static void validateServiceConfig(org.apache.dubbo.config.ServiceConfig);
    Code:
       0: ldc           #140                // String version
       2: aload_0
       3: invokevirtual #141                // Method org/apache/dubbo/config/ServiceConfig.getVersion:()Ljava/lang/String;
       6: invokestatic  #142                // Method checkKey:(Ljava/lang/String;Ljava/lang/String;)V
       9: ldc           #143                // String group
      11: aload_0
      12: invokevirtual #144                // Method org/apache/dubbo/config/ServiceConfig.getGroup:()Ljava/lang/String;
      15: invokestatic  #142                // Method checkKey:(Ljava/lang/String;Ljava/lang/String;)V
      18: ldc           #145                // String token
      20: aload_0
      21: invokevirtual #146                // Method org/apache/dubbo/config/ServiceConfig.getToken:()Ljava/lang/String;
      24: invokestatic  #115                // Method checkName:(Ljava/lang/String;Ljava/lang/String;)V
      27: ldc           #31                 // String path
      29: aload_0
      30: invokevirtual #147                // Method org/apache/dubbo/config/ServiceConfig.getPath:()Ljava/lang/String;
      33: invokestatic  #148                // Method checkPathName:(Ljava/lang/String;Ljava/lang/String;)V
      36: aload_0
      37: invokevirtual #149                // Method org/apache/dubbo/config/ServiceConfig.getScopeModel:()Lorg/apache/dubbo/rpc/model/ModuleModel;
      40: ldc           #150                // class org/apache/dubbo/rpc/ExporterListener
      42: ldc           #151                // String listener
      44: aload_0
      45: invokevirtual #152                // Method org/apache/dubbo/config/ServiceConfig.getListener:()Ljava/lang/String;
      48: invokestatic  #153                // Method checkMultiExtension:(Lorg/apache/dubbo/rpc/model/ScopeModel;Ljava/lang/Class;Ljava/lang/String;Ljava/lang/String;)V
      51: aload_0
      52: invokestatic  #154                // Method validateAbstractInterfaceConfig:(Lorg/apache/dubbo/config/AbstractInterfaceConfig;)V
      55: aload_0
      56: invokevirtual #155                // Method org/apache/dubbo/config/ServiceConfig.getRegistries:()Ljava/util/List;
      59: astore_1
      60: aload_1
      61: ifnull        97
      64: aload_1
      65: invokeinterface #17,  1           // InterfaceMethod java/util/List.iterator:()Ljava/util/Iterator;
      70: astore_2
      71: aload_2
      72: invokeinterface #18,  1           // InterfaceMethod java/util/Iterator.hasNext:()Z
      77: ifeq          97
      80: aload_2
      81: invokeinterface #19,  1           // InterfaceMethod java/util/Iterator.next:()Ljava/lang/Object;
      86: checkcast     #20                 // class org/apache/dubbo/config/RegistryConfig
      89: astore_3
      90: aload_3
      91: invokestatic  #156                // Method validateRegistryConfig:(Lorg/apache/dubbo/config/RegistryConfig;)V
      94: goto          71
      97: aload_0
      98: invokevirtual #157                // Method org/apache/dubbo/config/ServiceConfig.getProtocols:()Ljava/util/List;
     101: astore_2
     102: aload_2
     103: ifnull        141
     106: aload_2
     107: invokeinterface #17,  1           // InterfaceMethod java/util/List.iterator:()Ljava/util/Iterator;
     112: astore_3
     113: aload_3
     114: invokeinterface #18,  1           // InterfaceMethod java/util/Iterator.hasNext:()Z
     119: ifeq          141
     122: aload_3
     123: invokeinterface #19,  1           // InterfaceMethod java/util/Iterator.next:()Ljava/lang/Object;
     128: checkcast     #158                // class org/apache/dubbo/config/ProtocolConfig
     131: astore        4
     133: aload         4
     135: invokestatic  #159                // Method validateProtocolConfig:(Lorg/apache/dubbo/config/ProtocolConfig;)V
     138: goto          113
     141: aload_0
     142: invokevirtual #160                // Method org/apache/dubbo/config/ServiceConfig.getProvider:()Lorg/apache/dubbo/config/ProviderConfig;
     145: astore_3
     146: aload_3
     147: ifnull        154
     150: aload_3
     151: invokestatic  #161                // Method validateProviderConfig:(Lorg/apache/dubbo/config/ProviderConfig;)V
     154: return

  public static void validateReferenceConfig(org.apache.dubbo.config.ReferenceConfig);
    Code:
       0: aload_0
       1: invokevirtual #162                // Method org/apache/dubbo/config/ReferenceConfig.getScopeModel:()Lorg/apache/dubbo/rpc/model/ModuleModel;
       4: ldc           #163                // class org/apache/dubbo/rpc/InvokerListener
       6: ldc           #151                // String listener
       8: aload_0
       9: invokevirtual #164                // Method org/apache/dubbo/config/ReferenceConfig.getListener:()Ljava/lang/String;
      12: invokestatic  #153                // Method checkMultiExtension:(Lorg/apache/dubbo/rpc/model/ScopeModel;Ljava/lang/Class;Ljava/lang/String;Ljava/lang/String;)V
      15: ldc           #140                // String version
      17: aload_0
      18: invokevirtual #165                // Method org/apache/dubbo/config/ReferenceConfig.getVersion:()Ljava/lang/String;
      21: invokestatic  #142                // Method checkKey:(Ljava/lang/String;Ljava/lang/String;)V
      24: ldc           #143                // String group
      26: aload_0
      27: invokevirtual #166                // Method org/apache/dubbo/config/ReferenceConfig.getGroup:()Ljava/lang/String;
      30: invokestatic  #142                // Method checkKey:(Ljava/lang/String;Ljava/lang/String;)V
      33: ldc           #167                // String client
      35: aload_0
      36: invokevirtual #168                // Method org/apache/dubbo/config/ReferenceConfig.getClient:()Ljava/lang/String;
      39: invokestatic  #115                // Method checkName:(Ljava/lang/String;Ljava/lang/String;)V
      42: aload_0
      43: invokestatic  #154                // Method validateAbstractInterfaceConfig:(Lorg/apache/dubbo/config/AbstractInterfaceConfig;)V
      46: aload_0
      47: invokevirtual #169                // Method org/apache/dubbo/config/ReferenceConfig.getRegistries:()Ljava/util/List;
      50: astore_1
      51: aload_1
      52: ifnull        88
      55: aload_1
      56: invokeinterface #17,  1           // InterfaceMethod java/util/List.iterator:()Ljava/util/Iterator;
      61: astore_2
      62: aload_2
      63: invokeinterface #18,  1           // InterfaceMethod java/util/Iterator.hasNext:()Z
      68: ifeq          88
      71: aload_2
      72: invokeinterface #19,  1           // InterfaceMethod java/util/Iterator.next:()Ljava/lang/Object;
      77: checkcast     #20                 // class org/apache/dubbo/config/RegistryConfig
      80: astore_3
      81: aload_3
      82: invokestatic  #156                // Method validateRegistryConfig:(Lorg/apache/dubbo/config/RegistryConfig;)V
      85: goto          62
      88: aload_0
      89: invokevirtual #170                // Method org/apache/dubbo/config/ReferenceConfig.getConsumer:()Lorg/apache/dubbo/config/ConsumerConfig;
      92: astore_2
      93: aload_2
      94: ifnull        101
      97: aload_2
      98: invokestatic  #171                // Method validateConsumerConfig:(Lorg/apache/dubbo/config/ConsumerConfig;)V
     101: return

  public static void validateConfigCenterConfig(org.apache.dubbo.config.ConfigCenterConfig);
    Code:
       0: aload_0
       1: ifnull        11
       4: aload_0
       5: invokevirtual #172                // Method org/apache/dubbo/config/ConfigCenterConfig.getParameters:()Ljava/util/Map;
       8: invokestatic  #173                // Method checkParameterName:(Ljava/util/Map;)V
      11: return

  public static void validateApplicationConfig(org.apache.dubbo.config.ApplicationConfig);
    Code:
       0: aload_0
       1: ifnonnull     5
       4: return
       5: aload_0
       6: invokevirtual #174                // Method org/apache/dubbo/config/ApplicationConfig.isValid:()Z
       9: ifne          22
      12: new           #104                // class java/lang/IllegalStateException
      15: dup
      16: ldc           #175                // String No application config found or it\'s not a valid config! Please add <dubbo:application name=\"...\" /> to your spring config.
      18: invokespecial #107                // Method java/lang/IllegalStateException."<init>":(Ljava/lang/String;)V
      21: athrow
      22: aload_0
      23: invokevirtual #176                // Method org/apache/dubbo/config/ApplicationConfig.getScopeModel:()Lorg/apache/dubbo/rpc/model/ScopeModel;
      26: invokestatic  #177                // Method org/apache/dubbo/rpc/model/ScopeModelUtil.getOrDefaultApplicationModel:(Lorg/apache/dubbo/rpc/model/ScopeModel;)Lorg/apache/dubbo/rpc/model/ApplicationModel;
      29: astore_1
      30: aload_1
      31: invokevirtual #178                // Method org/apache/dubbo/rpc/model/ScopeModel.getModelEnvironment:()Lorg/apache/dubbo/common/config/Environment;
      34: invokevirtual #179                // Method org/apache/dubbo/common/config/Environment.getPropertiesConfiguration:()Lorg/apache/dubbo/common/config/PropertiesConfiguration;
      37: astore_2
      38: aload_2
      39: ldc           #180                // String dubbo.service.shutdown.wait
      41: invokevirtual #181                // Method org/apache/dubbo/common/config/PropertiesConfiguration.getProperty:(Ljava/lang/String;)Ljava/lang/String;
      44: astore_3
      45: aload_3
      46: ifnull        72
      49: aload_3
      50: invokevirtual #101                // Method java/lang/String.trim:()Ljava/lang/String;
      53: invokevirtual #81                 // Method java/lang/String.length:()I
      56: ifle          72
      59: ldc           #180                // String dubbo.service.shutdown.wait
      61: aload_3
      62: invokevirtual #101                // Method java/lang/String.trim:()Ljava/lang/String;
      65: invokestatic  #182                // Method java/lang/System.setProperty:(Ljava/lang/String;Ljava/lang/String;)Ljava/lang/String;
      68: pop
      69: goto          103
      72: aload_2
      73: ldc           #183                // String dubbo.service.shutdown.wait.seconds
      75: invokevirtual #181                // Method org/apache/dubbo/common/config/PropertiesConfiguration.getProperty:(Ljava/lang/String;)Ljava/lang/String;
      78: astore_3
      79: aload_3
      80: ifnull        103
      83: aload_3
      84: invokevirtual #101                // Method java/lang/String.trim:()Ljava/lang/String;
      87: invokevirtual #81                 // Method java/lang/String.length:()I
      90: ifle          103
      93: ldc           #183                // String dubbo.service.shutdown.wait.seconds
      95: aload_3
      96: invokevirtual #101                // Method java/lang/String.trim:()Ljava/lang/String;
      99: invokestatic  #182                // Method java/lang/System.setProperty:(Ljava/lang/String;Ljava/lang/String;)Ljava/lang/String;
     102: pop
     103: ldc           #184                // String name
     105: aload_0
     106: invokevirtual #185                // Method org/apache/dubbo/config/ApplicationConfig.getName:()Ljava/lang/String;
     109: invokestatic  #115                // Method checkName:(Ljava/lang/String;Ljava/lang/String;)V
     112: ldc           #118                // String owner
     114: aload_0
     115: invokevirtual #186                // Method org/apache/dubbo/config/ApplicationConfig.getOwner:()Ljava/lang/String;
     118: invokestatic  #120                // Method checkMultiName:(Ljava/lang/String;Ljava/lang/String;)V
     121: ldc           #187                // String organization
     123: aload_0
     124: invokevirtual #188                // Method org/apache/dubbo/config/ApplicationConfig.getOrganization:()Ljava/lang/String;
     127: invokestatic  #115                // Method checkName:(Ljava/lang/String;Ljava/lang/String;)V
     130: ldc           #189                // String architecture
     132: aload_0
     133: invokevirtual #190                // Method org/apache/dubbo/config/ApplicationConfig.getArchitecture:()Ljava/lang/String;
     136: invokestatic  #115                // Method checkName:(Ljava/lang/String;Ljava/lang/String;)V
     139: ldc           #191                // String environment
     141: aload_0
     142: invokevirtual #192                // Method org/apache/dubbo/config/ApplicationConfig.getEnvironment:()Ljava/lang/String;
     145: invokestatic  #115                // Method checkName:(Ljava/lang/String;Ljava/lang/String;)V
     148: aload_0
     149: invokevirtual #193                // Method org/apache/dubbo/config/ApplicationConfig.getParameters:()Ljava/util/Map;
     152: invokestatic  #173                // Method checkParameterName:(Ljava/util/Map;)V
     155: aload_0
     156: invokestatic  #194                // Method checkQosDependency:(Lorg/apache/dubbo/config/ApplicationConfig;)V
     159: return

  private static void checkQosDependency(org.apache.dubbo.config.ApplicationConfig);
    Code:
       0: getstatic     #195                // Field java/lang/Boolean.FALSE:Ljava/lang/Boolean;
       3: aload_0
       4: invokevirtual #196                // Method org/apache/dubbo/config/ApplicationConfig.getQosEnable:()Ljava/lang/Boolean;
       7: invokevirtual #197                // Method java/lang/Boolean.equals:(Ljava/lang/Object;)Z
      10: ifne          40
      13: ldc           #198                // String org.apache.dubbo.qos.protocol.QosProtocolWrapper
      15: invokestatic  #199                // Method org/apache/dubbo/common/utils/ClassUtils.forName:(Ljava/lang/String;)Ljava/lang/Class;
      18: pop
      19: goto          40
      22: astore_1
      23: getstatic     #201                // Field logger:Lorg/apache/dubbo/common/logger/ErrorTypeAwareLogger;
      26: ldc           #202                // String 0-7
      28: ldc           #203                // String
      30: ldc           #203                // String
      32: ldc           #204                // String No QosProtocolWrapper class was found. Please check the dependency of dubbo-qos whether was imported correctly.
      34: aload_1
      35: invokeinterface #205,  6          // InterfaceMethod org/apache/dubbo/common/logger/ErrorTypeAwareLogger.warn:(Ljava/lang/String;Ljava/lang/String;Ljava/lang/String;Ljava/lang/String;Ljava/lang/Throwable;)V
      40: return
    Exception table:
       from    to  target type
          13    19    22   Class java/lang/ClassNotFoundException

  public static void validateModuleConfig(org.apache.dubbo.config.ModuleConfig);
    Code:
       0: aload_0
       1: ifnull        31
       4: ldc           #184                // String name
       6: aload_0
       7: invokevirtual #206                // Method org/apache/dubbo/config/ModuleConfig.getName:()Ljava/lang/String;
      10: invokestatic  #115                // Method checkName:(Ljava/lang/String;Ljava/lang/String;)V
      13: ldc           #118                // String owner
      15: aload_0
      16: invokevirtual #207                // Method org/apache/dubbo/config/ModuleConfig.getOwner:()Ljava/lang/String;
      19: invokestatic  #115                // Method checkName:(Ljava/lang/String;Ljava/lang/String;)V
      22: ldc           #187                // String organization
      24: aload_0
      25: invokevirtual #208                // Method org/apache/dubbo/config/ModuleConfig.getOrganization:()Ljava/lang/String;
      28: invokestatic  #115                // Method checkName:(Ljava/lang/String;Ljava/lang/String;)V
      31: return

  public static boolean isValidMetadataConfig(org.apache.dubbo.config.MetadataReportConfig);
    Code:
       0: aload_0
       1: ifnonnull     6
       4: iconst_0
       5: ireturn
       6: getstatic     #195                // Field java/lang/Boolean.FALSE:Ljava/lang/Boolean;
       9: aload_0
      10: invokevirtual #209                // Method org/apache/dubbo/config/MetadataReportConfig.getReportMetadata:()Ljava/lang/Boolean;
      13: invokevirtual #197                // Method java/lang/Boolean.equals:(Ljava/lang/Object;)Z
      16: ifeq          34
      19: getstatic     #195                // Field java/lang/Boolean.FALSE:Ljava/lang/Boolean;
      22: aload_0
      23: invokevirtual #210                // Method org/apache/dubbo/config/MetadataReportConfig.getReportDefinition:()Ljava/lang/Boolean;
      26: invokevirtual #197                // Method java/lang/Boolean.equals:(Ljava/lang/Object;)Z
      29: ifeq          34
      32: iconst_0
      33: ireturn
      34: aload_0
      35: invokevirtual #211                // Method org/apache/dubbo/config/MetadataReportConfig.getAddress:()Ljava/lang/String;
      38: invokestatic  #24                 // Method org/apache/dubbo/common/utils/StringUtils.isEmpty:(Ljava/lang/String;)Z
      41: ifne          48
      44: iconst_1
      45: goto          49
      48: iconst_0
      49: ireturn

  public static void validateMetadataConfig(org.apache.dubbo.config.MetadataReportConfig);
    Code:
       0: aload_0
       1: invokestatic  #212                // Method isValidMetadataConfig:(Lorg/apache/dubbo/config/MetadataReportConfig;)Z
       4: ifne          8
       7: return
       8: aload_0
       9: invokevirtual #211                // Method org/apache/dubbo/config/MetadataReportConfig.getAddress:()Ljava/lang/String;
      12: astore_1
      13: aload_0
      14: invokevirtual #213                // Method org/apache/dubbo/config/MetadataReportConfig.getProtocol:()Ljava/lang/String;
      17: astore_2
      18: aload_1
      19: invokestatic  #24                 // Method org/apache/dubbo/common/utils/StringUtils.isEmpty:(Ljava/lang/String;)Z
      22: ifne          34
      25: aload_1
      26: ldc           #214                // String ://
      28: invokevirtual #215                // Method java/lang/String.contains:(Ljava/lang/CharSequence;)Z
      31: ifne          68
      34: aload_2
      35: invokestatic  #24                 // Method org/apache/dubbo/common/utils/StringUtils.isEmpty:(Ljava/lang/String;)Z
      38: ifeq          68
      41: new           #70                 // class java/lang/IllegalArgumentException
      44: dup
      45: new           #71                 // class java/lang/StringBuilder
      48: dup
      49: invokespecial #72                 // Method java/lang/StringBuilder."<init>":()V
      52: ldc           #216                // String Please specify valid protocol or address for metadata report
      54: invokevirtual #74                 // Method java/lang/StringBuilder.append:(Ljava/lang/String;)Ljava/lang/StringBuilder;
      57: aload_1
      58: invokevirtual #74                 // Method java/lang/StringBuilder.append:(Ljava/lang/String;)Ljava/lang/StringBuilder;
      61: invokevirtual #75                 // Method java/lang/StringBuilder.toString:()Ljava/lang/String;
      64: invokespecial #76                 // Method java/lang/IllegalArgumentException."<init>":(Ljava/lang/String;)V
      67: athrow
      68: return

  public static void validateMetricsConfig(org.apache.dubbo.config.MetricsConfig);
    Code:
       0: aload_0
       1: ifnonnull     5
       4: return
       5: return

  public static void validateTracingConfig(org.apache.dubbo.config.TracingConfig);
    Code:
       0: aload_0
       1: ifnonnull     5
       4: return
       5: return

  public static void validateSslConfig(org.apache.dubbo.config.SslConfig);
    Code:
       0: aload_0
       1: ifnonnull     5
       4: return
       5: return

  public static void validateMonitorConfig(org.apache.dubbo.config.MonitorConfig);
    Code:
       0: aload_0
       1: ifnull        28
       4: aload_0
       5: invokevirtual #217                // Method org/apache/dubbo/config/MonitorConfig.isValid:()Z
       8: ifne          21
      11: getstatic     #201                // Field logger:Lorg/apache/dubbo/common/logger/ErrorTypeAwareLogger;
      14: ldc           #218                // String There\'s no valid monitor config found, if you want to open monitor statistics for Dubbo, please make sure your monitor is configured properly.
      16: invokeinterface #219,  2          // InterfaceMethod org/apache/dubbo/common/logger/ErrorTypeAwareLogger.info:(Ljava/lang/String;)V
      21: aload_0
      22: invokevirtual #220                // Method org/apache/dubbo/config/MonitorConfig.getParameters:()Ljava/util/Map;
      25: invokestatic  #173                // Method checkParameterName:(Ljava/util/Map;)V
      28: return

  public static void validateProtocolConfig(org.apache.dubbo.config.ProtocolConfig);
    Code:
       0: aload_0
       1: ifnull        207
       4: aload_0
       5: invokevirtual #221                // Method org/apache/dubbo/config/ProtocolConfig.getName:()Ljava/lang/String;
       8: astore_1
       9: ldc           #184                // String name
      11: aload_1
      12: invokestatic  #115                // Method checkName:(Ljava/lang/String;Ljava/lang/String;)V
      15: ldc           #222                // String host
      17: aload_0
      18: invokevirtual #223                // Method org/apache/dubbo/config/ProtocolConfig.getHost:()Ljava/lang/String;
      21: invokestatic  #224                // Method checkHost:(Ljava/lang/String;Ljava/lang/String;)V
      24: ldc           #225                // String contextpath
      26: aload_0
      27: invokevirtual #226                // Method org/apache/dubbo/config/ProtocolConfig.getContextpath:()Ljava/lang/String;
      30: invokestatic  #148                // Method checkPathName:(Ljava/lang/String;Ljava/lang/String;)V
      33: ldc           #38                 // String dubbo
      35: aload_1
      36: invokevirtual #84                 // Method java/lang/String.equals:(Ljava/lang/Object;)Z
      39: ifeq          102
      42: aload_0
      43: invokevirtual #227                // Method org/apache/dubbo/config/ProtocolConfig.getScopeModel:()Lorg/apache/dubbo/rpc/model/ScopeModel;
      46: ldc           #228                // class org/apache/dubbo/remoting/Codec2
      48: ldc           #229                // String codec
      50: aload_0
      51: invokevirtual #230                // Method org/apache/dubbo/config/ProtocolConfig.getCodec:()Ljava/lang/String;
      54: invokestatic  #153                // Method checkMultiExtension:(Lorg/apache/dubbo/rpc/model/ScopeModel;Ljava/lang/Class;Ljava/lang/String;Ljava/lang/String;)V
      57: aload_0
      58: invokevirtual #227                // Method org/apache/dubbo/config/ProtocolConfig.getScopeModel:()Lorg/apache/dubbo/rpc/model/ScopeModel;
      61: ldc           #231                // class org/apache/dubbo/common/serialize/Serialization
      63: ldc           #232                // String serialization
      65: aload_0
      66: invokevirtual #233                // Method org/apache/dubbo/config/ProtocolConfig.getSerialization:()Ljava/lang/String;
      69: invokestatic  #153                // Method checkMultiExtension:(Lorg/apache/dubbo/rpc/model/ScopeModel;Ljava/lang/Class;Ljava/lang/String;Ljava/lang/String;)V
      72: aload_0
      73: invokevirtual #227                // Method org/apache/dubbo/config/ProtocolConfig.getScopeModel:()Lorg/apache/dubbo/rpc/model/ScopeModel;
      76: ldc           #234                // class org/apache/dubbo/remoting/Transporter
      78: ldc           #235                // String server
      80: aload_0
      81: invokevirtual #236                // Method org/apache/dubbo/config/ProtocolConfig.getServer:()Ljava/lang/String;
      84: invokestatic  #153                // Method checkMultiExtension:(Lorg/apache/dubbo/rpc/model/ScopeModel;Ljava/lang/Class;Ljava/lang/String;Ljava/lang/String;)V
      87: aload_0
      88: invokevirtual #227                // Method org/apache/dubbo/config/ProtocolConfig.getScopeModel:()Lorg/apache/dubbo/rpc/model/ScopeModel;
      91: ldc           #234                // class org/apache/dubbo/remoting/Transporter
      93: ldc           #167                // String client
      95: aload_0
      96: invokevirtual #237                // Method org/apache/dubbo/config/ProtocolConfig.getClient:()Ljava/lang/String;
      99: invokestatic  #153                // Method checkMultiExtension:(Lorg/apache/dubbo/rpc/model/ScopeModel;Ljava/lang/Class;Ljava/lang/String;Ljava/lang/String;)V
     102: aload_0
     103: invokevirtual #227                // Method org/apache/dubbo/config/ProtocolConfig.getScopeModel:()Lorg/apache/dubbo/rpc/model/ScopeModel;
     106: ldc           #238                // class org/apache/dubbo/remoting/telnet/TelnetHandler
     108: ldc           #239                // String telnet
     110: aload_0
     111: invokevirtual #240                // Method org/apache/dubbo/config/ProtocolConfig.getTelnet:()Ljava/lang/String;
     114: invokestatic  #153                // Method checkMultiExtension:(Lorg/apache/dubbo/rpc/model/ScopeModel;Ljava/lang/Class;Ljava/lang/String;Ljava/lang/String;)V
     117: aload_0
     118: invokevirtual #227                // Method org/apache/dubbo/config/ProtocolConfig.getScopeModel:()Lorg/apache/dubbo/rpc/model/ScopeModel;
     121: ldc           #241                // class org/apache/dubbo/common/status/StatusChecker
     123: ldc           #242                // String status
     125: aload_0
     126: invokevirtual #243                // Method org/apache/dubbo/config/ProtocolConfig.getStatus:()Ljava/lang/String;
     129: invokestatic  #153                // Method checkMultiExtension:(Lorg/apache/dubbo/rpc/model/ScopeModel;Ljava/lang/Class;Ljava/lang/String;Ljava/lang/String;)V
     132: aload_0
     133: invokevirtual #227                // Method org/apache/dubbo/config/ProtocolConfig.getScopeModel:()Lorg/apache/dubbo/rpc/model/ScopeModel;
     136: ldc           #234                // class org/apache/dubbo/remoting/Transporter
     138: ldc           #244                // String transporter
     140: aload_0
     141: invokevirtual #245                // Method org/apache/dubbo/config/ProtocolConfig.getTransporter:()Ljava/lang/String;
     144: invokestatic  #124                // Method checkExtension:(Lorg/apache/dubbo/rpc/model/ScopeModel;Ljava/lang/Class;Ljava/lang/String;Ljava/lang/String;)V
     147: aload_0
     148: invokevirtual #227                // Method org/apache/dubbo/config/ProtocolConfig.getScopeModel:()Lorg/apache/dubbo/rpc/model/ScopeModel;
     151: ldc           #246                // class org/apache/dubbo/remoting/exchange/Exchanger
     153: ldc           #247                // String exchanger
     155: aload_0
     156: invokevirtual #248                // Method org/apache/dubbo/config/ProtocolConfig.getExchanger:()Ljava/lang/String;
     159: invokestatic  #124                // Method checkExtension:(Lorg/apache/dubbo/rpc/model/ScopeModel;Ljava/lang/Class;Ljava/lang/String;Ljava/lang/String;)V
     162: aload_0
     163: invokevirtual #227                // Method org/apache/dubbo/config/ProtocolConfig.getScopeModel:()Lorg/apache/dubbo/rpc/model/ScopeModel;
     166: ldc           #249                // class org/apache/dubbo/remoting/Dispatcher
     168: ldc           #250                // String dispatcher
     170: aload_0
     171: invokevirtual #251                // Method org/apache/dubbo/config/ProtocolConfig.getDispatcher:()Ljava/lang/String;
     174: invokestatic  #124                // Method checkExtension:(Lorg/apache/dubbo/rpc/model/ScopeModel;Ljava/lang/Class;Ljava/lang/String;Ljava/lang/String;)V
     177: aload_0
     178: invokevirtual #227                // Method org/apache/dubbo/config/ProtocolConfig.getScopeModel:()Lorg/apache/dubbo/rpc/model/ScopeModel;
     181: ldc           #249                // class org/apache/dubbo/remoting/Dispatcher
     183: ldc           #252                // String dispather
     185: aload_0
     186: invokevirtual #253                // Method org/apache/dubbo/config/ProtocolConfig.getDispather:()Ljava/lang/String;
     189: invokestatic  #124                // Method checkExtension:(Lorg/apache/dubbo/rpc/model/ScopeModel;Ljava/lang/Class;Ljava/lang/String;Ljava/lang/String;)V
     192: aload_0
     193: invokevirtual #227                // Method org/apache/dubbo/config/ProtocolConfig.getScopeModel:()Lorg/apache/dubbo/rpc/model/ScopeModel;
     196: ldc           #254                // class org/apache/dubbo/common/threadpool/ThreadPool
     198: ldc           #255                // String threadpool
     200: aload_0
     201: invokevirtual #256                // Method org/apache/dubbo/config/ProtocolConfig.getThreadpool:()Ljava/lang/String;
     204: invokestatic  #124                // Method checkExtension:(Lorg/apache/dubbo/rpc/model/ScopeModel;Ljava/lang/Class;Ljava/lang/String;Ljava/lang/String;)V
     207: return

  public static void validateProviderConfig(org.apache.dubbo.config.ProviderConfig);
    Code:
       0: ldc           #225                // String contextpath
       2: aload_0
       3: invokevirtual #257                // Method org/apache/dubbo/config/ProviderConfig.getContextpath:()Ljava/lang/String;
       6: invokestatic  #148                // Method checkPathName:(Ljava/lang/String;Ljava/lang/String;)V
       9: aload_0
      10: invokevirtual #258                // Method org/apache/dubbo/config/ProviderConfig.getScopeModel:()Lorg/apache/dubbo/rpc/model/ModuleModel;
      13: ldc           #254                // class org/apache/dubbo/common/threadpool/ThreadPool
      15: ldc           #255                // String threadpool
      17: aload_0
      18: invokevirtual #259                // Method org/apache/dubbo/config/ProviderConfig.getThreadpool:()Ljava/lang/String;
      21: invokestatic  #124                // Method checkExtension:(Lorg/apache/dubbo/rpc/model/ScopeModel;Ljava/lang/Class;Ljava/lang/String;Ljava/lang/String;)V
      24: aload_0
      25: invokevirtual #258                // Method org/apache/dubbo/config/ProviderConfig.getScopeModel:()Lorg/apache/dubbo/rpc/model/ModuleModel;
      28: ldc           #238                // class org/apache/dubbo/remoting/telnet/TelnetHandler
      30: ldc           #239                // String telnet
      32: aload_0
      33: invokevirtual #260                // Method org/apache/dubbo/config/ProviderConfig.getTelnet:()Ljava/lang/String;
      36: invokestatic  #153                // Method checkMultiExtension:(Lorg/apache/dubbo/rpc/model/ScopeModel;Ljava/lang/Class;Ljava/lang/String;Ljava/lang/String;)V
      39: aload_0
      40: invokevirtual #258                // Method org/apache/dubbo/config/ProviderConfig.getScopeModel:()Lorg/apache/dubbo/rpc/model/ModuleModel;
      43: ldc           #241                // class org/apache/dubbo/common/status/StatusChecker
      45: ldc           #242                // String status
      47: aload_0
      48: invokevirtual #261                // Method org/apache/dubbo/config/ProviderConfig.getStatus:()Ljava/lang/String;
      51: invokestatic  #153                // Method checkMultiExtension:(Lorg/apache/dubbo/rpc/model/ScopeModel;Ljava/lang/Class;Ljava/lang/String;Ljava/lang/String;)V
      54: aload_0
      55: invokevirtual #258                // Method org/apache/dubbo/config/ProviderConfig.getScopeModel:()Lorg/apache/dubbo/rpc/model/ModuleModel;
      58: ldc           #234                // class org/apache/dubbo/remoting/Transporter
      60: ldc           #244                // String transporter
      62: aload_0
      63: invokevirtual #262                // Method org/apache/dubbo/config/ProviderConfig.getTransporter:()Ljava/lang/String;
      66: invokestatic  #124                // Method checkExtension:(Lorg/apache/dubbo/rpc/model/ScopeModel;Ljava/lang/Class;Ljava/lang/String;Ljava/lang/String;)V
      69: aload_0
      70: invokevirtual #258                // Method org/apache/dubbo/config/ProviderConfig.getScopeModel:()Lorg/apache/dubbo/rpc/model/ModuleModel;
      73: ldc           #246                // class org/apache/dubbo/remoting/exchange/Exchanger
      75: ldc           #247                // String exchanger
      77: aload_0
      78: invokevirtual #263                // Method org/apache/dubbo/config/ProviderConfig.getExchanger:()Ljava/lang/String;
      81: invokestatic  #124                // Method checkExtension:(Lorg/apache/dubbo/rpc/model/ScopeModel;Ljava/lang/Class;Ljava/lang/String;Ljava/lang/String;)V
      84: return

  public static void validateConsumerConfig(org.apache.dubbo.config.ConsumerConfig);
    Code:
       0: aload_0
       1: ifnonnull     5
       4: return
       5: return

  public static void validateRegistryConfig(org.apache.dubbo.config.RegistryConfig);
    Code:
       0: ldc           #36                 // String protocol
       2: aload_0
       3: invokevirtual #264                // Method org/apache/dubbo/config/RegistryConfig.getProtocol:()Ljava/lang/String;
       6: invokestatic  #115                // Method checkName:(Ljava/lang/String;Ljava/lang/String;)V
       9: ldc_w         #265                // String username
      12: aload_0
      13: invokevirtual #266                // Method org/apache/dubbo/config/RegistryConfig.getUsername:()Ljava/lang/String;
      16: invokestatic  #115                // Method checkName:(Ljava/lang/String;Ljava/lang/String;)V
      19: ldc_w         #267                // String password
      22: aload_0
      23: invokevirtual #268                // Method org/apache/dubbo/config/RegistryConfig.getPassword:()Ljava/lang/String;
      26: invokestatic  #269                // Method checkLength:(Ljava/lang/String;Ljava/lang/String;)V
      29: ldc_w         #270                // String file
      32: aload_0
      33: invokevirtual #271                // Method org/apache/dubbo/config/RegistryConfig.getFile:()Ljava/lang/String;
      36: invokestatic  #272                // Method checkPathLength:(Ljava/lang/String;Ljava/lang/String;)V
      39: ldc           #244                // String transporter
      41: aload_0
      42: invokevirtual #273                // Method org/apache/dubbo/config/RegistryConfig.getTransporter:()Ljava/lang/String;
      45: invokestatic  #115                // Method checkName:(Ljava/lang/String;Ljava/lang/String;)V
      48: ldc           #235                // String server
      50: aload_0
      51: invokevirtual #274                // Method org/apache/dubbo/config/RegistryConfig.getServer:()Ljava/lang/String;
      54: invokestatic  #115                // Method checkName:(Ljava/lang/String;Ljava/lang/String;)V
      57: ldc           #167                // String client
      59: aload_0
      60: invokevirtual #275                // Method org/apache/dubbo/config/RegistryConfig.getClient:()Ljava/lang/String;
      63: invokestatic  #115                // Method checkName:(Ljava/lang/String;Ljava/lang/String;)V
      66: aload_0
      67: invokevirtual #276                // Method org/apache/dubbo/config/RegistryConfig.getParameters:()Ljava/util/Map;
      70: invokestatic  #173                // Method checkParameterName:(Ljava/util/Map;)V
      73: return

  public static void validateMethodConfig(org.apache.dubbo.config.MethodConfig);
    Code:
       0: aload_0
       1: invokevirtual #277                // Method org/apache/dubbo/config/MethodConfig.getScopeModel:()Lorg/apache/dubbo/rpc/model/ModuleModel;
       4: ldc_w         #278                // class org/apache/dubbo/rpc/cluster/LoadBalance
       7: ldc_w         #279                // String loadbalance
      10: aload_0
      11: invokevirtual #280                // Method org/apache/dubbo/config/MethodConfig.getLoadbalance:()Ljava/lang/String;
      14: invokestatic  #124                // Method checkExtension:(Lorg/apache/dubbo/rpc/model/ScopeModel;Ljava/lang/Class;Ljava/lang/String;Ljava/lang/String;)V
      17: aload_0
      18: invokevirtual #281                // Method org/apache/dubbo/config/MethodConfig.getParameters:()Ljava/util/Map;
      21: invokestatic  #173                // Method checkParameterName:(Ljava/util/Map;)V
      24: ldc           #184                // String name
      26: aload_0
      27: invokevirtual #282                // Method org/apache/dubbo/config/MethodConfig.getName:()Ljava/lang/String;
      30: invokestatic  #283                // Method checkMethodName:(Ljava/lang/String;Ljava/lang/String;)V
      33: aload_0
      34: invokevirtual #284                // Method org/apache/dubbo/config/MethodConfig.getMock:()Ljava/lang/String;
      37: astore_1
      38: aload_1
      39: invokestatic  #58                 // Method org/apache/dubbo/common/utils/StringUtils.isNotEmpty:(Ljava/lang/String;)Z
      42: ifeq          111
      45: aload_1
      46: ldc           #98                 // String return
      48: invokevirtual #99                 // Method java/lang/String.startsWith:(Ljava/lang/String;)Z
      51: ifne          64
      54: aload_1
      55: ldc_w         #285                // String throw
      58: invokevirtual #99                 // Method java/lang/String.startsWith:(Ljava/lang/String;)Z
      61: ifeq          74
      64: ldc_w         #286                // String mock
      67: aload_1
      68: invokestatic  #269                // Method checkLength:(Ljava/lang/String;Ljava/lang/String;)V
      71: goto          111
      74: aload_1
      75: ldc_w         #287                // String fail:
      78: invokevirtual #99                 // Method java/lang/String.startsWith:(Ljava/lang/String;)Z
      81: ifne          94
      84: aload_1
      85: ldc_w         #288                // String force:
      88: invokevirtual #99                 // Method java/lang/String.startsWith:(Ljava/lang/String;)Z
      91: ifeq          104
      94: ldc_w         #286                // String mock
      97: aload_1
      98: invokestatic  #137                // Method checkNameHasSymbol:(Ljava/lang/String;Ljava/lang/String;)V
     101: goto          111
     104: ldc_w         #286                // String mock
     107: aload_1
     108: invokestatic  #115                // Method checkName:(Ljava/lang/String;Ljava/lang/String;)V
     111: return

  private static java.lang.String extractRegistryType(org.apache.dubbo.common.URL);
    Code:
       0: aload_0
       1: invokestatic  #289                // Method org/apache/dubbo/common/utils/UrlUtils.hasServiceDiscoveryRegistryTypeKey:(Lorg/apache/dubbo/common/URL;)Z
       4: ifeq          12
       7: ldc           #85                 // String service-discovery-registry
       9: goto          16
      12: aload_0
      13: invokestatic  #290                // Method getRegistryProtocolType:(Lorg/apache/dubbo/common/URL;)Ljava/lang/String;
      16: areturn

  private static java.lang.String getRegistryProtocolType(org.apache.dubbo.common.URL);
    Code:
       0: aload_0
       1: ldc_w         #291                // String registry-protocol-type
       4: invokevirtual #292                // Method org/apache/dubbo/common/URL.getParameter:(Ljava/lang/String;)Ljava/lang/String;
       7: astore_1
       8: aload_1
       9: invokestatic  #58                 // Method org/apache/dubbo/common/utils/StringUtils.isNotEmpty:(Ljava/lang/String;)Z
      12: ifeq          19
      15: aload_1
      16: goto          21
      19: ldc           #42                 // String registry
      21: areturn

  public static void checkExtension(org.apache.dubbo.rpc.model.ScopeModel, java.lang.Class<?>, java.lang.String, java.lang.String);
    Code:
       0: aload_2
       1: aload_3
       2: invokestatic  #115                // Method checkName:(Ljava/lang/String;Ljava/lang/String;)V
       5: aload_3
       6: invokestatic  #58                 // Method org/apache/dubbo/common/utils/StringUtils.isNotEmpty:(Ljava/lang/String;)Z
       9: ifeq          75
      12: aload_0
      13: aload_1
      14: invokevirtual #293                // Method org/apache/dubbo/rpc/model/ScopeModel.getExtensionLoader:(Ljava/lang/Class;)Lorg/apache/dubbo/common/extension/ExtensionLoader;
      17: aload_3
      18: invokevirtual #92                 // Method org/apache/dubbo/common/extension/ExtensionLoader.hasExtension:(Ljava/lang/String;)Z
      21: ifne          75
      24: new           #104                // class java/lang/IllegalStateException
      27: dup
      28: new           #71                 // class java/lang/StringBuilder
      31: dup
      32: invokespecial #72                 // Method java/lang/StringBuilder."<init>":()V
      35: ldc_w         #294                // String No such extension
      38: invokevirtual #74                 // Method java/lang/StringBuilder.append:(Ljava/lang/String;)Ljava/lang/StringBuilder;
      41: aload_3
      42: invokevirtual #74                 // Method java/lang/StringBuilder.append:(Ljava/lang/String;)Ljava/lang/StringBuilder;
      45: ldc_w         #295                // String  for
      48: invokevirtual #74                 // Method java/lang/StringBuilder.append:(Ljava/lang/String;)Ljava/lang/StringBuilder;
      51: aload_2
      52: invokevirtual #74                 // Method java/lang/StringBuilder.append:(Ljava/lang/String;)Ljava/lang/StringBuilder;
      55: ldc_w         #296                // String /
      58: invokevirtual #74                 // Method java/lang/StringBuilder.append:(Ljava/lang/String;)Ljava/lang/StringBuilder;
      61: aload_1
      62: invokevirtual #33                 // Method java/lang/Class.getName:()Ljava/lang/String;
      65: invokevirtual #74                 // Method java/lang/StringBuilder.append:(Ljava/lang/String;)Ljava/lang/StringBuilder;
      68: invokevirtual #75                 // Method java/lang/StringBuilder.toString:()Ljava/lang/String;
      71: invokespecial #107                // Method java/lang/IllegalStateException."<init>":(Ljava/lang/String;)V
      74: athrow
      75: return

  public static void checkMultiExtension(org.apache.dubbo.rpc.model.ScopeModel, java.lang.Class<?>, java.lang.String, java.lang.String);
    Code:
       0: aload_0
       1: aload_1
       2: invokestatic  #297                // Method java/util/Collections.singletonList:(Ljava/lang/Object;)Ljava/util/List;
       5: aload_2
       6: aload_3
       7: invokestatic  #134                // Method checkMultiExtension:(Lorg/apache/dubbo/rpc/model/ScopeModel;Ljava/util/List;Ljava/lang/String;Ljava/lang/String;)V
      10: return

  public static void checkMultiExtension(org.apache.dubbo.rpc.model.ScopeModel, java.util.List<java.lang.Class<?>>, java.lang.String, java.lang.String);
    Code:
       0: aload_2
       1: aload_3
       2: invokestatic  #120                // Method checkMultiName:(Ljava/lang/String;Ljava/lang/String;)V
       5: aload_3
       6: invokestatic  #58                 // Method org/apache/dubbo/common/utils/StringUtils.isNotEmpty:(Ljava/lang/String;)Z
       9: ifeq          222
      12: aload_3
      13: ldc_w         #298                // String \\s*[,]+\\s*
      16: invokevirtual #299                // Method java/lang/String.split:(Ljava/lang/String;)[Ljava/lang/String;
      19: astore        4
      21: aload         4
      23: astore        5
      25: aload         5
      27: arraylength
      28: istore        6
      30: iconst_0
      31: istore        7
      33: iload         7
      35: iload         6
      37: if_icmpge     222
      40: aload         5
      42: iload         7
      44: aaload
      45: astore        8
      47: aload         8
      49: ldc_w         #300                // String -
      52: invokevirtual #99                 // Method java/lang/String.startsWith:(Ljava/lang/String;)Z
      55: ifeq          66
      58: aload         8
      60: iconst_1
      61: invokevirtual #100                // Method java/lang/String.substring:(I)Ljava/lang/String;
      64: astore        8
      66: ldc_w         #301                // String default
      69: aload         8
      71: invokevirtual #84                 // Method java/lang/String.equals:(Ljava/lang/Object;)Z
      74: ifeq          80
      77: goto          216
      80: iconst_0
      81: istore        9
      83: aload_1
      84: invokeinterface #17,  1           // InterfaceMethod java/util/List.iterator:()Ljava/util/Iterator;
      89: astore        10
      91: aload         10
      93: invokeinterface #18,  1           // InterfaceMethod java/util/Iterator.hasNext:()Z
      98: ifeq          133
     101: aload         10
     103: invokeinterface #19,  1           // InterfaceMethod java/util/Iterator.next:()Ljava/lang/Object;
     108: checkcast     #128                // class java/lang/Class
     111: astore        11
     113: aload_0
     114: aload         11
     116: invokevirtual #293                // Method org/apache/dubbo/rpc/model/ScopeModel.getExtensionLoader:(Ljava/lang/Class;)Lorg/apache/dubbo/common/extension/ExtensionLoader;
     119: aload         8
     121: invokevirtual #92                 // Method org/apache/dubbo/common/extension/ExtensionLoader.hasExtension:(Ljava/lang/String;)Z
     124: ifeq          130
     127: iconst_1
     128: istore        9
     130: goto          91
     133: iload         9
     135: ifne          216
     138: new           #104                // class java/lang/IllegalStateException
     141: dup
     142: new           #71                 // class java/lang/StringBuilder
     145: dup
     146: invokespecial #72                 // Method java/lang/StringBuilder."<init>":()V
     149: ldc_w         #294                // String No such extension
     152: invokevirtual #74                 // Method java/lang/StringBuilder.append:(Ljava/lang/String;)Ljava/lang/StringBuilder;
     155: aload         8
     157: invokevirtual #74                 // Method java/lang/StringBuilder.append:(Ljava/lang/String;)Ljava/lang/StringBuilder;
     160: ldc_w         #295                // String  for
     163: invokevirtual #74                 // Method java/lang/StringBuilder.append:(Ljava/lang/String;)Ljava/lang/StringBuilder;
     166: aload_2
     167: invokevirtual #74                 // Method java/lang/StringBuilder.append:(Ljava/lang/String;)Ljava/lang/StringBuilder;
     170: ldc_w         #296                // String /
     173: invokevirtual #74                 // Method java/lang/StringBuilder.append:(Ljava/lang/String;)Ljava/lang/StringBuilder;
     176: aload_1
     177: invokeinterface #62,  1           // InterfaceMethod java/util/List.stream:()Ljava/util/stream/Stream;
     182: invokedynamic #302,  0            // InvokeDynamic #3:apply:()Ljava/util/function/Function;
     187: invokeinterface #303,  2          // InterfaceMethod java/util/stream/Stream.map:(Ljava/util/function/Function;)Ljava/util/stream/Stream;
     192: ldc_w         #304                // String ,
     195: invokestatic  #305                // Method java/util/stream/Collectors.joining:(Ljava/lang/CharSequence;)Ljava/util/stream/Collector;
     198: invokeinterface #306,  2          // InterfaceMethod java/util/stream/Stream.collect:(Ljava/util/stream/Collector;)Ljava/lang/Object;
     203: checkcast     #307                // class java/lang/String
     206: invokevirtual #74                 // Method java/lang/StringBuilder.append:(Ljava/lang/String;)Ljava/lang/StringBuilder;
     209: invokevirtual #75                 // Method java/lang/StringBuilder.toString:()Ljava/lang/String;
     212: invokespecial #107                // Method java/lang/IllegalStateException."<init>":(Ljava/lang/String;)V
     215: athrow
     216: iinc          7, 1
     219: goto          33
     222: return

  public static void checkLength(java.lang.String, java.lang.String);
    Code:
       0: aload_0
       1: aload_1
       2: sipush        200
       5: aconst_null
       6: invokestatic  #309                // Method checkProperty:(Ljava/lang/String;Ljava/lang/String;ILjava/util/regex/Pattern;)V
       9: return

  public static void checkPathLength(java.lang.String, java.lang.String);
    Code:
       0: aload_0
       1: aload_1
       2: sipush        200
       5: aconst_null
       6: invokestatic  #309                // Method checkProperty:(Ljava/lang/String;Ljava/lang/String;ILjava/util/regex/Pattern;)V
       9: return

  public static void checkName(java.lang.String, java.lang.String);
    Code:
       0: aload_0
       1: aload_1
       2: sipush        200
       5: getstatic     #310                // Field PATTERN_NAME:Ljava/util/regex/Pattern;
       8: invokestatic  #309                // Method checkProperty:(Ljava/lang/String;Ljava/lang/String;ILjava/util/regex/Pattern;)V
      11: return

  public static void checkHost(java.lang.String, java.lang.String);
    Code:
       0: aload_1
       1: invokestatic  #24                 // Method org/apache/dubbo/common/utils/StringUtils.isEmpty:(Ljava/lang/String;)Z
       4: ifeq          8
       7: return
       8: aload_1
       9: ldc_w         #311                // String [
      12: invokevirtual #99                 // Method java/lang/String.startsWith:(Ljava/lang/String;)Z
      15: ifeq          35
      18: aload_1
      19: ldc_w         #312                // String ]
      22: invokevirtual #313                // Method java/lang/String.endsWith:(Ljava/lang/String;)Z
      25: ifeq          35
      28: aload_1
      29: invokestatic  #314                // Method java/net/InetAddress.getByName:(Ljava/lang/String;)Ljava/net/InetAddress;
      32: pop
      33: return
      34: astore_2
      35: aload_0
      36: aload_1
      37: invokestatic  #115                // Method checkName:(Ljava/lang/String;Ljava/lang/String;)V
      40: return
    Exception table:
       from    to  target type
          28    33    34   Class java/net/UnknownHostException

  public static void checkNameHasSymbol(java.lang.String, java.lang.String);
    Code:
       0: aload_0
       1: aload_1
       2: sipush        200
       5: getstatic     #316                // Field PATTERN_NAME_HAS_SYMBOL:Ljava/util/regex/Pattern;
       8: invokestatic  #309                // Method checkProperty:(Ljava/lang/String;Ljava/lang/String;ILjava/util/regex/Pattern;)V
      11: return

  public static void checkKey(java.lang.String, java.lang.String);
    Code:
       0: aload_0
       1: aload_1
       2: sipush        200
       5: getstatic     #317                // Field PATTERN_KEY:Ljava/util/regex/Pattern;
       8: invokestatic  #309                // Method checkProperty:(Ljava/lang/String;Ljava/lang/String;ILjava/util/regex/Pattern;)V
      11: return

  public static void checkMultiName(java.lang.String, java.lang.String);
    Code:
       0: aload_0
       1: aload_1
       2: sipush        200
       5: getstatic     #318                // Field PATTERN_MULTI_NAME:Ljava/util/regex/Pattern;
       8: invokestatic  #309                // Method checkProperty:(Ljava/lang/String;Ljava/lang/String;ILjava/util/regex/Pattern;)V
      11: return

  public static void checkPathName(java.lang.String, java.lang.String);
    Code:
       0: aload_0
       1: aload_1
       2: sipush        200
       5: getstatic     #319                // Field PATTERN_PATH:Ljava/util/regex/Pattern;
       8: invokestatic  #309                // Method checkProperty:(Ljava/lang/String;Ljava/lang/String;ILjava/util/regex/Pattern;)V
      11: return

  public static void checkMethodName(java.lang.String, java.lang.String);
    Code:
       0: aload_0
       1: aload_1
       2: sipush        200
       5: getstatic     #320                // Field PATTERN_METHOD_NAME:Ljava/util/regex/Pattern;
       8: invokestatic  #309                // Method checkProperty:(Ljava/lang/String;Ljava/lang/String;ILjava/util/regex/Pattern;)V
      11: return

  public static void checkParameterName(java.util.Map<java.lang.String, java.lang.String>);
    Code:
       0: aload_0
       1: invokestatic  #321                // Method org/apache/dubbo/common/utils/CollectionUtils.isEmptyMap:(Ljava/util/Map;)Z
       4: ifeq          8
       7: return
       8: new           #12                 // class java/util/ArrayList
      11: dup
      12: invokespecial #13                 // Method java/util/ArrayList."<init>":()V
      15: astore_1
      16: aload_1
      17: ldc_w         #322                // String backup
      20: invokeinterface #52,  2           // InterfaceMethod java/util/List.add:(Ljava/lang/Object;)Z
      25: pop
      26: aload_0
      27: ldc_w         #323                // String ignoreCheckKeys
      30: invokeinterface #324,  2          // InterfaceMethod java/util/Map.get:(Ljava/lang/Object;)Ljava/lang/Object;
      35: checkcast     #307                // class java/lang/String
      38: astore_2
      39: aload_2
      40: invokestatic  #325                // Method org/apache/dubbo/common/utils/StringUtils.isBlank:(Ljava/lang/CharSequence;)Z
      43: ifne          63
      46: aload_1
      47: aload_2
      48: ldc_w         #304                // String ,
      51: invokevirtual #299                // Method java/lang/String.split:(Ljava/lang/String;)[Ljava/lang/String;
      54: invokestatic  #131                // Method java/util/Arrays.asList:([Ljava/lang/Object;)Ljava/util/List;
      57: invokeinterface #326,  2          // InterfaceMethod java/util/List.addAll:(Ljava/util/Collection;)Z
      62: pop
      63: aload_0
      64: invokeinterface #327,  1          // InterfaceMethod java/util/Map.entrySet:()Ljava/util/Set;
      69: invokeinterface #328,  1          // InterfaceMethod java/util/Set.iterator:()Ljava/util/Iterator;
      74: astore_3
      75: aload_3
      76: invokeinterface #18,  1           // InterfaceMethod java/util/Iterator.hasNext:()Z
      81: ifeq          137
      84: aload_3
      85: invokeinterface #19,  1           // InterfaceMethod java/util/Iterator.next:()Ljava/lang/Object;
      90: checkcast     #329                // class java/util/Map$Entry
      93: astore        4
      95: aload_1
      96: aload         4
      98: invokeinterface #330,  1          // InterfaceMethod java/util/Map$Entry.getKey:()Ljava/lang/Object;
     103: invokeinterface #331,  2          // InterfaceMethod java/util/List.contains:(Ljava/lang/Object;)Z
     108: ifne          134
     111: aload         4
     113: invokeinterface #330,  1          // InterfaceMethod java/util/Map$Entry.getKey:()Ljava/lang/Object;
     118: checkcast     #307                // class java/lang/String
     121: aload         4
     123: invokeinterface #332,  1          // InterfaceMethod java/util/Map$Entry.getValue:()Ljava/lang/Object;
     128: checkcast     #307                // class java/lang/String
     131: invokestatic  #137                // Method checkNameHasSymbol:(Ljava/lang/String;Ljava/lang/String;)V
     134: goto          75
     137: return

  public static void checkProperty(java.lang.String, java.lang.String, int, java.util.regex.Pattern);
    Code:
       0: aload_1
       1: invokestatic  #24                 // Method org/apache/dubbo/common/utils/StringUtils.isEmpty:(Ljava/lang/String;)Z
       4: ifeq          8
       7: return
       8: aload_1
       9: invokevirtual #81                 // Method java/lang/String.length:()I
      12: iload_2
      13: if_icmple     72
      16: getstatic     #201                // Field logger:Lorg/apache/dubbo/common/logger/ErrorTypeAwareLogger;
      19: ldc_w         #333                // String 5-17
      22: ldc_w         #334                // String the value content is too long
      25: ldc           #203                // String
      27: new           #71                 // class java/lang/StringBuilder
      30: dup
      31: invokespecial #72                 // Method java/lang/StringBuilder."<init>":()V
      34: ldc_w         #335                // String Parameter value format error. Invalid
      37: invokevirtual #74                 // Method java/lang/StringBuilder.append:(Ljava/lang/String;)Ljava/lang/StringBuilder;
      40: aload_0
      41: invokevirtual #74                 // Method java/lang/StringBuilder.append:(Ljava/lang/String;)Ljava/lang/StringBuilder;
      44: ldc_w         #336                // String =\"
      47: invokevirtual #74                 // Method java/lang/StringBuilder.append:(Ljava/lang/String;)Ljava/lang/StringBuilder;
      50: aload_1
      51: invokevirtual #74                 // Method java/lang/StringBuilder.append:(Ljava/lang/String;)Ljava/lang/StringBuilder;
      54: ldc_w         #337                // String \" is longer than
      57: invokevirtual #74                 // Method java/lang/StringBuilder.append:(Ljava/lang/String;)Ljava/lang/StringBuilder;
      60: iload_2
      61: invokevirtual #338                // Method java/lang/StringBuilder.append:(I)Ljava/lang/StringBuilder;
      64: invokevirtual #75                 // Method java/lang/StringBuilder.toString:()Ljava/lang/String;
      67: invokeinterface #339,  5          // InterfaceMethod org/apache/dubbo/common/logger/ErrorTypeAwareLogger.error:(Ljava/lang/String;Ljava/lang/String;Ljava/lang/String;Ljava/lang/String;)V
      72: aload_3
      73: ifnull        143
      76: aload_3
      77: aload_1
      78: invokevirtual #340                // Method java/util/regex/Pattern.matcher:(Ljava/lang/CharSequence;)Ljava/util/regex/Matcher;
      81: astore        4
      83: aload         4
      85: invokevirtual #341                // Method java/util/regex/Matcher.matches:()Z
      88: ifne          143
      91: getstatic     #201                // Field logger:Lorg/apache/dubbo/common/logger/ErrorTypeAwareLogger;
      94: ldc_w         #333                // String 5-17
      97: ldc_w         #342                // String the value content is illegal character
     100: ldc           #203                // String
     102: new           #71                 // class java/lang/StringBuilder
     105: dup
     106: invokespecial #72                 // Method java/lang/StringBuilder."<init>":()V
     109: ldc_w         #335                // String Parameter value format error. Invalid
     112: invokevirtual #74                 // Method java/lang/StringBuilder.append:(Ljava/lang/String;)Ljava/lang/StringBuilder;
     115: aload_0
     116: invokevirtual #74                 // Method java/lang/StringBuilder.append:(Ljava/lang/String;)Ljava/lang/StringBuilder;
     119: ldc_w         #336                // String =\"
     122: invokevirtual #74                 // Method java/lang/StringBuilder.append:(Ljava/lang/String;)Ljava/lang/StringBuilder;
     125: aload_1
     126: invokevirtual #74                 // Method java/lang/StringBuilder.append:(Ljava/lang/String;)Ljava/lang/StringBuilder;
     129: ldc_w         #343                // String \" contains illegal character, only digit, letter, \'-\', \'_\' or \'.\' is legal.
     132: invokevirtual #74                 // Method java/lang/StringBuilder.append:(Ljava/lang/String;)Ljava/lang/StringBuilder;
     135: invokevirtual #75                 // Method java/lang/StringBuilder.toString:()Ljava/lang/String;
     138: invokeinterface #339,  5          // InterfaceMethod org/apache/dubbo/common/logger/ErrorTypeAwareLogger.error:(Ljava/lang/String;Ljava/lang/String;Ljava/lang/String;Ljava/lang/String;)V
     143: return

  private static boolean lambda$registryNotExists$1(java.lang.String, org.apache.dubbo.common.URL, org.apache.dubbo.common.URL);
    Code:
       0: aload_0
       1: aload_2
       2: invokevirtual #43                 // Method org/apache/dubbo/common/URL.getProtocol:()Ljava/lang/String;
       5: invokevirtual #84                 // Method java/lang/String.equals:(Ljava/lang/Object;)Z
       8: ifeq          29
      11: aload_1
      12: invokevirtual #344                // Method org/apache/dubbo/common/URL.getBackupAddress:()Ljava/lang/String;
      15: aload_2
      16: invokevirtual #344                // Method org/apache/dubbo/common/URL.getBackupAddress:()Ljava/lang/String;
      19: invokevirtual #84                 // Method java/lang/String.equals:(Ljava/lang/Object;)Z
      22: ifeq          29
      25: iconst_1
      26: goto          30
      29: iconst_0
      30: ireturn

  private static void lambda$genCompatibleRegistries$0(boolean, org.apache.dubbo.rpc.model.ScopeModel, java.util.List, java.util.List, org.apache.dubbo.common.URL);
    Code:
       0: iload_0
       1: ifeq          265
       4: ldc           #85                 // String service-discovery-registry
       6: aload         4
       8: invokevirtual #43                 // Method org/apache/dubbo/common/URL.getProtocol:()Ljava/lang/String;
      11: invokevirtual #84                 // Method java/lang/String.equals:(Ljava/lang/Object;)Z
      14: ifeq          111
      17: aload         4
      19: ldc_w         #345                // String register-mode
      22: aload_1
      23: ldc_w         #346                // String dubbo.application.register-mode
      26: ldc           #60                 // String instance
      28: invokestatic  #347                // Method org/apache/dubbo/common/config/ConfigurationUtils.getCachedDynamicProperty:(Lorg/apache/dubbo/rpc/model/ScopeModel;Ljava/lang/String;Ljava/lang/String;)Ljava/lang/String;
      31: invokevirtual #348                // Method org/apache/dubbo/common/URL.getParameter:(Ljava/lang/String;Ljava/lang/String;)Ljava/lang/String;
      34: astore        5
      36: aload         5
      38: invokestatic  #349                // Method isValidRegisterMode:(Ljava/lang/String;)Z
      41: ifne          48
      44: ldc           #60                 // String instance
      46: astore        5
      48: aload_2
      49: aload         4
      51: invokeinterface #52,  2           // InterfaceMethod java/util/List.add:(Ljava/lang/Object;)Z
      56: pop
      57: ldc           #61                 // String all
      59: aload         5
      61: invokevirtual #27                 // Method java/lang/String.equalsIgnoreCase:(Ljava/lang/String;)Z
      64: ifeq          232
      67: aload         4
      69: aload_3
      70: ldc           #42                 // String registry
      72: invokestatic  #350                // Method registryNotExists:(Lorg/apache/dubbo/common/URL;Ljava/util/List;Ljava/lang/String;)Z
      75: ifeq          232
      78: aload         4
      80: invokestatic  #41                 // Method org/apache/dubbo/common/URLBuilder.from:(Lorg/apache/dubbo/common/URL;)Lorg/apache/dubbo/common/URLBuilder;
      83: ldc           #42                 // String registry
      85: invokevirtual #46                 // Method org/apache/dubbo/common/URLBuilder.setProtocol:(Ljava/lang/String;)Lorg/apache/dubbo/common/URLBuilder;
      88: ldc_w         #351                // String registry-type
      91: invokevirtual #352                // Method org/apache/dubbo/common/URLBuilder.removeParameter:(Ljava/lang/String;)Lorg/apache/dubbo/common/URLBuilder;
      94: invokevirtual #49                 // Method org/apache/dubbo/common/URLBuilder.build:()Lorg/apache/dubbo/common/url/component/ServiceConfigURL;
      97: astore        6
      99: aload_2
     100: aload         6
     102: invokeinterface #52,  2           // InterfaceMethod java/util/List.add:(Ljava/lang/Object;)Z
     107: pop
     108: goto          232
     111: aload         4
     113: ldc_w         #345                // String register-mode
     116: aload_1
     117: ldc_w         #346                // String dubbo.application.register-mode
     120: ldc           #61                 // String all
     122: invokestatic  #347                // Method org/apache/dubbo/common/config/ConfigurationUtils.getCachedDynamicProperty:(Lorg/apache/dubbo/rpc/model/ScopeModel;Ljava/lang/String;Ljava/lang/String;)Ljava/lang/String;
     125: invokevirtual #348                // Method org/apache/dubbo/common/URL.getParameter:(Ljava/lang/String;Ljava/lang/String;)Ljava/lang/String;
     128: astore        5
     130: aload         5
     132: invokestatic  #349                // Method isValidRegisterMode:(Ljava/lang/String;)Z
     135: ifne          142
     138: ldc           #59                 // String interface
     140: astore        5
     142: ldc           #60                 // String instance
     144: aload         5
     146: invokevirtual #27                 // Method java/lang/String.equalsIgnoreCase:(Ljava/lang/String;)Z
     149: ifne          162
     152: ldc           #61                 // String all
     154: aload         5
     156: invokevirtual #27                 // Method java/lang/String.equalsIgnoreCase:(Ljava/lang/String;)Z
     159: ifeq          203
     162: aload         4
     164: aload_3
     165: ldc           #85                 // String service-discovery-registry
     167: invokestatic  #350                // Method registryNotExists:(Lorg/apache/dubbo/common/URL;Ljava/util/List;Ljava/lang/String;)Z
     170: ifeq          203
     173: aload         4
     175: invokestatic  #41                 // Method org/apache/dubbo/common/URLBuilder.from:(Lorg/apache/dubbo/common/URL;)Lorg/apache/dubbo/common/URLBuilder;
     178: ldc           #85                 // String service-discovery-registry
     180: invokevirtual #46                 // Method org/apache/dubbo/common/URLBuilder.setProtocol:(Ljava/lang/String;)Lorg/apache/dubbo/common/URLBuilder;
     183: ldc_w         #351                // String registry-type
     186: invokevirtual #352                // Method org/apache/dubbo/common/URLBuilder.removeParameter:(Ljava/lang/String;)Lorg/apache/dubbo/common/URLBuilder;
     189: invokevirtual #49                 // Method org/apache/dubbo/common/URLBuilder.build:()Lorg/apache/dubbo/common/url/component/ServiceConfigURL;
     192: astore        6
     194: aload_2
     195: aload         6
     197: invokeinterface #52,  2           // InterfaceMethod java/util/List.add:(Ljava/lang/Object;)Z
     202: pop
     203: ldc           #59                 // String interface
     205: aload         5
     207: invokevirtual #27                 // Method java/lang/String.equalsIgnoreCase:(Ljava/lang/String;)Z
     210: ifne          223
     213: ldc           #61                 // String all
     215: aload         5
     217: invokevirtual #27                 // Method java/lang/String.equalsIgnoreCase:(Ljava/lang/String;)Z
     220: ifeq          232
     223: aload_2
     224: aload         4
     226: invokeinterface #52,  2           // InterfaceMethod java/util/List.add:(Ljava/lang/Object;)Z
     231: pop
     232: aload_1
     233: invokestatic  #353                // Method org/apache/dubbo/rpc/model/ScopeModelUtil.getApplicationModel:(Lorg/apache/dubbo/rpc/model/ScopeModel;)Lorg/apache/dubbo/rpc/model/ApplicationModel;
     236: invokevirtual #354                // Method org/apache/dubbo/rpc/model/ApplicationModel.getBeanFactory:()Lorg/apache/dubbo/common/beans/factory/ScopeBeanFactory;
     239: ldc_w         #355                // class org/apache/dubbo/common/status/reporter/FrameworkStatusReportService
     242: invokevirtual #356                // Method org/apache/dubbo/common/beans/factory/ScopeBeanFactory.getBean:(Ljava/lang/Class;)Ljava/lang/Object;
     245: checkcast     #355                // class org/apache/dubbo/common/status/reporter/FrameworkStatusReportService
     248: astore        6
     250: aload         6
     252: aload         6
     254: aload         5
     256: invokevirtual #357                // Method org/apache/dubbo/common/status/reporter/FrameworkStatusReportService.createRegistrationReport:(Ljava/lang/String;)Ljava/lang/String;
     259: invokevirtual #358                // Method org/apache/dubbo/common/status/reporter/FrameworkStatusReportService.reportRegistrationStatus:(Ljava/lang/Object;)V
     262: goto          274
     265: aload_2
     266: aload         4
     268: invokeinterface #52,  2           // InterfaceMethod java/util/List.add:(Ljava/lang/Object;)Z
     273: pop
     274: return

  static {};
    Code:
       0: ldc_w         #308                // class org/apache/dubbo/config/utils/ConfigValidationUtils
       3: invokestatic  #359                // Method org/apache/dubbo/common/logger/LoggerFactory.getErrorTypeAwareLogger:(Ljava/lang/Class;)Lorg/apache/dubbo/common/logger/ErrorTypeAwareLogger;
       6: putstatic     #201                // Field logger:Lorg/apache/dubbo/common/logger/ErrorTypeAwareLogger;
       9: ldc_w         #360                // String [\\-._0-9a-zA-Z]+
      12: invokestatic  #361                // Method java/util/regex/Pattern.compile:(Ljava/lang/String;)Ljava/util/regex/Pattern;
      15: putstatic     #310                // Field PATTERN_NAME:Ljava/util/regex/Pattern;
      18: ldc_w         #362                // String [,\\-._0-9a-zA-Z]+
      21: invokestatic  #361                // Method java/util/regex/Pattern.compile:(Ljava/lang/String;)Ljava/util/regex/Pattern;
      24: putstatic     #318                // Field PATTERN_MULTI_NAME:Ljava/util/regex/Pattern;
      27: ldc_w         #363                // String [a-zA-Z][0-9a-zA-Z]*
      30: invokestatic  #361                // Method java/util/regex/Pattern.compile:(Ljava/lang/String;)Ljava/util/regex/Pattern;
      33: putstatic     #320                // Field PATTERN_METHOD_NAME:Ljava/util/regex/Pattern;
      36: ldc_w         #364                // String [/\\-$._0-9a-zA-Z]+
      39: invokestatic  #361                // Method java/util/regex/Pattern.compile:(Ljava/lang/String;)Ljava/util/regex/Pattern;
      42: putstatic     #319                // Field PATTERN_PATH:Ljava/util/regex/Pattern;
      45: ldc_w         #365                // String [:*,\\s/\\-._0-9a-zA-Z]+
      48: invokestatic  #361                // Method java/util/regex/Pattern.compile:(Ljava/lang/String;)Ljava/util/regex/Pattern;
      51: putstatic     #316                // Field PATTERN_NAME_HAS_SYMBOL:Ljava/util/regex/Pattern;
      54: ldc_w         #366                // String [*,\\-._0-9a-zA-Z]+
      57: invokestatic  #361                // Method java/util/regex/Pattern.compile:(Ljava/lang/String;)Ljava/util/regex/Pattern;
      60: putstatic     #317                // Field PATTERN_KEY:Ljava/util/regex/Pattern;
      63: return
}
