Compiled from "DefaultConfigValidator.java"
public class org.apache.dubbo.config.utils.DefaultConfigValidator implements org.apache.dubbo.config.context.ConfigValidator {
  public org.apache.dubbo.config.utils.DefaultConfigValidator();
    Code:
       0: aload_0
       1: invokespecial #1                  // Method java/lang/Object."<init>":()V
       4: return

  public void validate(org.apache.dubbo.config.AbstractConfig);
    Code:
       0: aload_1
       1: instanceof    #2                  // class org/apache/dubbo/config/ProtocolConfig
       4: ifeq          17
       7: aload_1
       8: checkcast     #2                  // class org/apache/dubbo/config/ProtocolConfig
      11: invokestatic  #3                  // Method org/apache/dubbo/config/utils/ConfigValidationUtils.validateProtocolConfig:(Lorg/apache/dubbo/config/ProtocolConfig;)V
      14: goto          184
      17: aload_1
      18: instanceof    #4                  // class org/apache/dubbo/config/RegistryConfig
      21: ifeq          34
      24: aload_1
      25: checkcast     #4                  // class org/apache/dubbo/config/RegistryConfig
      28: invokestatic  #5                  // Method org/apache/dubbo/config/utils/ConfigValidationUtils.validateRegistryConfig:(Lorg/apache/dubbo/config/RegistryConfig;)V
      31: goto          184
      34: aload_1
      35: instanceof    #6                  // class org/apache/dubbo/config/MetadataReportConfig
      38: ifeq          51
      41: aload_1
      42: checkcast     #6                  // class org/apache/dubbo/config/MetadataReportConfig
      45: invokestatic  #7                  // Method org/apache/dubbo/config/utils/ConfigValidationUtils.validateMetadataConfig:(Lorg/apache/dubbo/config/MetadataReportConfig;)V
      48: goto          184
      51: aload_1
      52: instanceof    #8                  // class org/apache/dubbo/config/ProviderConfig
      55: ifeq          68
      58: aload_1
      59: checkcast     #8                  // class org/apache/dubbo/config/ProviderConfig
      62: invokestatic  #9                  // Method org/apache/dubbo/config/utils/ConfigValidationUtils.validateProviderConfig:(Lorg/apache/dubbo/config/ProviderConfig;)V
      65: goto          184
      68: aload_1
      69: instanceof    #10                 // class org/apache/dubbo/config/ConsumerConfig
      72: ifeq          85
      75: aload_1
      76: checkcast     #10                 // class org/apache/dubbo/config/ConsumerConfig
      79: invokestatic  #11                 // Method org/apache/dubbo/config/utils/ConfigValidationUtils.validateConsumerConfig:(Lorg/apache/dubbo/config/ConsumerConfig;)V
      82: goto          184
      85: aload_1
      86: instanceof    #12                 // class org/apache/dubbo/config/ApplicationConfig
      89: ifeq          102
      92: aload_1
      93: checkcast     #12                 // class org/apache/dubbo/config/ApplicationConfig
      96: invokestatic  #13                 // Method org/apache/dubbo/config/utils/ConfigValidationUtils.validateApplicationConfig:(Lorg/apache/dubbo/config/ApplicationConfig;)V
      99: goto          184
     102: aload_1
     103: instanceof    #14                 // class org/apache/dubbo/config/MonitorConfig
     106: ifeq          119
     109: aload_1
     110: checkcast     #14                 // class org/apache/dubbo/config/MonitorConfig
     113: invokestatic  #15                 // Method org/apache/dubbo/config/utils/ConfigValidationUtils.validateMonitorConfig:(Lorg/apache/dubbo/config/MonitorConfig;)V
     116: goto          184
     119: aload_1
     120: instanceof    #16                 // class org/apache/dubbo/config/ModuleConfig
     123: ifeq          136
     126: aload_1
     127: checkcast     #16                 // class org/apache/dubbo/config/ModuleConfig
     130: invokestatic  #17                 // Method org/apache/dubbo/config/utils/ConfigValidationUtils.validateModuleConfig:(Lorg/apache/dubbo/config/ModuleConfig;)V
     133: goto          184
     136: aload_1
     137: instanceof    #18                 // class org/apache/dubbo/config/MetricsConfig
     140: ifeq          153
     143: aload_1
     144: checkcast     #18                 // class org/apache/dubbo/config/MetricsConfig
     147: invokestatic  #19                 // Method org/apache/dubbo/config/utils/ConfigValidationUtils.validateMetricsConfig:(Lorg/apache/dubbo/config/MetricsConfig;)V
     150: goto          184
     153: aload_1
     154: instanceof    #20                 // class org/apache/dubbo/config/TracingConfig
     157: ifeq          170
     160: aload_1
     161: checkcast     #20                 // class org/apache/dubbo/config/TracingConfig
     164: invokestatic  #21                 // Method org/apache/dubbo/config/utils/ConfigValidationUtils.validateTracingConfig:(Lorg/apache/dubbo/config/TracingConfig;)V
     167: goto          184
     170: aload_1
     171: instanceof    #22                 // class org/apache/dubbo/config/SslConfig
     174: ifeq          184
     177: aload_1
     178: checkcast     #22                 // class org/apache/dubbo/config/SslConfig
     181: invokestatic  #23                 // Method org/apache/dubbo/config/utils/ConfigValidationUtils.validateSslConfig:(Lorg/apache/dubbo/config/SslConfig;)V
     184: return
}
