Compiled from "SpringExtensionInjector.java"
public class org.apache.dubbo.config.spring.extension.SpringExtensionInjector implements org.apache.dubbo.common.extension.ExtensionInjector {
  private org.springframework.context.ApplicationContext context;

  public org.apache.dubbo.config.spring.extension.SpringExtensionInjector();
    Code:
       0: aload_0
       1: invokespecial #1                  // Method java/lang/Object."<init>":()V
       4: return

  public static void addApplicationContext(org.springframework.context.ApplicationContext);
    Code:
       0: return

  public static org.apache.dubbo.config.spring.extension.SpringExtensionInjector get(org.apache.dubbo.common.extension.ExtensionAccessor);
    Code:
       0: aload_0
       1: ldc           #2                  // class org/apache/dubbo/common/extension/ExtensionInjector
       3: ldc           #3                  // String spring
       5: invokeinterface #4,  3            // InterfaceMethod org/apache/dubbo/common/extension/ExtensionAccessor.getExtension:(Ljava/lang/Class;Ljava/lang/String;)Ljava/lang/Object;
      10: checkcast     #5                  // class org/apache/dubbo/config/spring/extension/SpringExtensionInjector
      13: areturn

  public org.springframework.context.ApplicationContext getContext();
    Code:
       0: aload_0
       1: getfield      #6                  // Field context:Lorg/springframework/context/ApplicationContext;
       4: areturn

  public void init(org.springframework.context.ApplicationContext);
    Code:
       0: aload_0
       1: aload_1
       2: putfield      #6                  // Field context:Lorg/springframework/context/ApplicationContext;
       5: return

  public <T> T getInstance(java.lang.Class<T>, java.lang.String);
    Code:
       0: aload_0
       1: getfield      #6                  // Field context:Lorg/springframework/context/ApplicationContext;
       4: ifnonnull     9
       7: aconst_null
       8: areturn
       9: aload_1
      10: invokevirtual #7                  // Method java/lang/Class.isInterface:()Z
      13: ifeq          27
      16: aload_1
      17: ldc           #8                  // class org/apache/dubbo/common/extension/SPI
      19: invokevirtual #9                  // Method java/lang/Class.isAnnotationPresent:(Ljava/lang/Class;)Z
      22: ifeq          27
      25: aconst_null
      26: areturn
      27: aload_0
      28: aload_0
      29: getfield      #6                  // Field context:Lorg/springframework/context/ApplicationContext;
      32: aload_2
      33: aload_1
      34: invokespecial #10                 // Method getOptionalBean:(Lorg/springframework/beans/factory/ListableBeanFactory;Ljava/lang/String;Ljava/lang/Class;)Ljava/lang/Object;
      37: astore_3
      38: aload_3
      39: ifnull        44
      42: aload_3
      43: areturn
      44: aconst_null
      45: areturn

  private <T> T getOptionalBean(org.springframework.beans.factory.ListableBeanFactory, java.lang.String, java.lang.Class<T>);
    Code:
       0: aload_2
       1: invokestatic  #11                 // Method org/apache/dubbo/common/utils/StringUtils.isEmpty:(Ljava/lang/String;)Z
       4: ifeq          14
       7: aload_0
       8: aload_1
       9: aload_3
      10: invokespecial #12                 // Method getOptionalBeanByType:(Lorg/springframework/beans/factory/ListableBeanFactory;Ljava/lang/Class;)Ljava/lang/Object;
      13: areturn
      14: aload_1
      15: aload_2
      16: invokeinterface #13,  2           // InterfaceMethod org/springframework/beans/factory/ListableBeanFactory.containsBean:(Ljava/lang/String;)Z
      21: ifeq          33
      24: aload_1
      25: aload_2
      26: aload_3
      27: invokeinterface #14,  3           // InterfaceMethod org/springframework/beans/factory/ListableBeanFactory.getBean:(Ljava/lang/String;Ljava/lang/Class;)Ljava/lang/Object;
      32: areturn
      33: aconst_null
      34: areturn

  private <T> T getOptionalBeanByType(org.springframework.beans.factory.ListableBeanFactory, java.lang.Class<T>);
    Code:
       0: aload_1
       1: aload_2
       2: iconst_1
       3: iconst_0
       4: invokeinterface #15,  4           // InterfaceMethod org/springframework/beans/factory/ListableBeanFactory.getBeanNamesForType:(Ljava/lang/Class;ZZ)[Ljava/lang/String;
       9: astore_3
      10: aload_3
      11: ifnonnull     16
      14: aconst_null
      15: areturn
      16: aload_3
      17: arraylength
      18: iconst_1
      19: if_icmple     62
      22: new           #16                 // class java/lang/IllegalStateException
      25: dup
      26: new           #17                 // class java/lang/StringBuilder
      29: dup
      30: invokespecial #18                 // Method java/lang/StringBuilder."<init>":()V
      33: ldc           #19                 // String Expect single but found
      35: invokevirtual #20                 // Method java/lang/StringBuilder.append:(Ljava/lang/String;)Ljava/lang/StringBuilder;
      38: aload_3
      39: arraylength
      40: invokevirtual #21                 // Method java/lang/StringBuilder.append:(I)Ljava/lang/StringBuilder;
      43: ldc           #22                 // String  beans in spring context:
      45: invokevirtual #20                 // Method java/lang/StringBuilder.append:(Ljava/lang/String;)Ljava/lang/StringBuilder;
      48: aload_3
      49: invokestatic  #23                 // Method java/util/Arrays.toString:([Ljava/lang/Object;)Ljava/lang/String;
      52: invokevirtual #20                 // Method java/lang/StringBuilder.append:(Ljava/lang/String;)Ljava/lang/StringBuilder;
      55: invokevirtual #24                 // Method java/lang/StringBuilder.toString:()Ljava/lang/String;
      58: invokespecial #25                 // Method java/lang/IllegalStateException."<init>":(Ljava/lang/String;)V
      61: athrow
      62: aload_1
      63: aload_3
      64: iconst_0
      65: aaload
      66: aload_2
      67: invokeinterface #14,  3           // InterfaceMethod org/springframework/beans/factory/ListableBeanFactory.getBean:(Ljava/lang/String;Ljava/lang/Class;)Ljava/lang/Object;
      72: areturn
}
