Compiled from "AbstractIdleService.java"
final class com.google.common.util.concurrent.AbstractIdleService$DelegateService extends com.google.common.util.concurrent.AbstractService {
  final com.google.common.util.concurrent.AbstractIdleService this$0;

  private com.google.common.util.concurrent.AbstractIdleService$DelegateService(com.google.common.util.concurrent.AbstractIdleService);
    Code:
       0: aload_0
       1: aload_1
       2: putfield      #2                  // Field this$0:Lcom/google/common/util/concurrent/AbstractIdleService;
       5: aload_0
       6: invokespecial #3                  // Method com/google/common/util/concurrent/AbstractService."<init>":()V
       9: return

  protected final void doStart();
    Code:
       0: aload_0
       1: getfield      #2                  // Field this$0:Lcom/google/common/util/concurrent/AbstractIdleService;
       4: invokevirtual #4                  // Method com/google/common/util/concurrent/AbstractIdleService.executor:()Ljava/util/concurrent/Executor;
       7: aload_0
       8: getfield      #2                  // Field this$0:Lcom/google/common/util/concurrent/AbstractIdleService;
      11: invokestatic  #5                  // Method com/google/common/util/concurrent/AbstractIdleService.access$200:(Lcom/google/common/util/concurrent/AbstractIdleService;)Lcom/google/common/base/Supplier;
      14: invokestatic  #6                  // Method com/google/common/util/concurrent/MoreExecutors.renamingDecorator:(Ljava/util/concurrent/Executor;Lcom/google/common/base/Supplier;)Ljava/util/concurrent/Executor;
      17: aload_0
      18: invokedynamic #7,  0              // InvokeDynamic #0:run:(Lcom/google/common/util/concurrent/AbstractIdleService$DelegateService;)Ljava/lang/Runnable;
      23: invokeinterface #8,  2            // InterfaceMethod java/util/concurrent/Executor.execute:(Ljava/lang/Runnable;)V
      28: return

  protected final void doStop();
    Code:
       0: aload_0
       1: getfield      #2                  // Field this$0:Lcom/google/common/util/concurrent/AbstractIdleService;
       4: invokevirtual #4                  // Method com/google/common/util/concurrent/AbstractIdleService.executor:()Ljava/util/concurrent/Executor;
       7: aload_0
       8: getfield      #2                  // Field this$0:Lcom/google/common/util/concurrent/AbstractIdleService;
      11: invokestatic  #5                  // Method com/google/common/util/concurrent/AbstractIdleService.access$200:(Lcom/google/common/util/concurrent/AbstractIdleService;)Lcom/google/common/base/Supplier;
      14: invokestatic  #6                  // Method com/google/common/util/concurrent/MoreExecutors.renamingDecorator:(Ljava/util/concurrent/Executor;Lcom/google/common/base/Supplier;)Ljava/util/concurrent/Executor;
      17: aload_0
      18: invokedynamic #9,  0              // InvokeDynamic #1:run:(Lcom/google/common/util/concurrent/AbstractIdleService$DelegateService;)Ljava/lang/Runnable;
      23: invokeinterface #8,  2            // InterfaceMethod java/util/concurrent/Executor.execute:(Ljava/lang/Runnable;)V
      28: return

  public java.lang.String toString();
    Code:
       0: aload_0
       1: getfield      #2                  // Field this$0:Lcom/google/common/util/concurrent/AbstractIdleService;
       4: invokevirtual #10                 // Method com/google/common/util/concurrent/AbstractIdleService.toString:()Ljava/lang/String;
       7: areturn

  private void lambda$doStop$1();
    Code:
       0: aload_0
       1: getfield      #2                  // Field this$0:Lcom/google/common/util/concurrent/AbstractIdleService;
       4: invokevirtual #11                 // Method com/google/common/util/concurrent/AbstractIdleService.shutDown:()V
       7: aload_0
       8: invokevirtual #12                 // Method notifyStopped:()V
      11: goto          24
      14: astore_1
      15: aload_1
      16: invokestatic  #14                 // Method com/google/common/util/concurrent/Platform.restoreInterruptIfIsInterruptedException:(Ljava/lang/Throwable;)V
      19: aload_0
      20: aload_1
      21: invokevirtual #15                 // Method notifyFailed:(Ljava/lang/Throwable;)V
      24: return
    Exception table:
       from    to  target type
           0    11    14   Class java/lang/Throwable

  private void lambda$doStart$0();
    Code:
       0: aload_0
       1: getfield      #2                  // Field this$0:Lcom/google/common/util/concurrent/AbstractIdleService;
       4: invokevirtual #16                 // Method com/google/common/util/concurrent/AbstractIdleService.startUp:()V
       7: aload_0
       8: invokevirtual #17                 // Method notifyStarted:()V
      11: goto          24
      14: astore_1
      15: aload_1
      16: invokestatic  #14                 // Method com/google/common/util/concurrent/Platform.restoreInterruptIfIsInterruptedException:(Ljava/lang/Throwable;)V
      19: aload_0
      20: aload_1
      21: invokevirtual #15                 // Method notifyFailed:(Ljava/lang/Throwable;)V
      24: return
    Exception table:
       from    to  target type
           0    11    14   Class java/lang/Throwable

  com.google.common.util.concurrent.AbstractIdleService$DelegateService(com.google.common.util.concurrent.AbstractIdleService, com.google.common.util.concurrent.AbstractIdleService$1);
    Code:
       0: aload_0
       1: aload_1
       2: invokespecial #1                  // Method "<init>":(Lcom/google/common/util/concurrent/AbstractIdleService;)V
       5: return
}
