Compiled from "AbstractExecutionThreadService.java"
class com.google.common.util.concurrent.AbstractExecutionThreadService$1 extends com.google.common.util.concurrent.AbstractService {
  final com.google.common.util.concurrent.AbstractExecutionThreadService this$0;

  com.google.common.util.concurrent.AbstractExecutionThreadService$1(com.google.common.util.concurrent.AbstractExecutionThreadService);
    Code:
       0: aload_0
       1: aload_1
       2: putfield      #1                  // Field this$0:Lcom/google/common/util/concurrent/AbstractExecutionThreadService;
       5: aload_0
       6: invokespecial #2                  // Method com/google/common/util/concurrent/AbstractService."<init>":()V
       9: return

  protected final void doStart();
    Code:
       0: aload_0
       1: getfield      #1                  // Field this$0:Lcom/google/common/util/concurrent/AbstractExecutionThreadService;
       4: invokevirtual #3                  // Method com/google/common/util/concurrent/AbstractExecutionThreadService.executor:()Ljava/util/concurrent/Executor;
       7: aload_0
       8: invokedynamic #4,  0              // InvokeDynamic #0:get:(Lcom/google/common/util/concurrent/AbstractExecutionThreadService$1;)Lcom/google/common/base/Supplier;
      13: invokestatic  #5                  // Method com/google/common/util/concurrent/MoreExecutors.renamingDecorator:(Ljava/util/concurrent/Executor;Lcom/google/common/base/Supplier;)Ljava/util/concurrent/Executor;
      16: astore_1
      17: aload_1
      18: aload_0
      19: invokedynamic #6,  0              // InvokeDynamic #1:run:(Lcom/google/common/util/concurrent/AbstractExecutionThreadService$1;)Ljava/lang/Runnable;
      24: invokeinterface #7,  2            // InterfaceMethod java/util/concurrent/Executor.execute:(Ljava/lang/Runnable;)V
      29: return

  protected void doStop();
    Code:
       0: aload_0
       1: getfield      #1                  // Field this$0:Lcom/google/common/util/concurrent/AbstractExecutionThreadService;
       4: invokevirtual #8                  // Method com/google/common/util/concurrent/AbstractExecutionThreadService.triggerShutdown:()V
       7: return

  public java.lang.String toString();
    Code:
       0: aload_0
       1: getfield      #1                  // Field this$0:Lcom/google/common/util/concurrent/AbstractExecutionThreadService;
       4: invokevirtual #9                  // Method com/google/common/util/concurrent/AbstractExecutionThreadService.toString:()Ljava/lang/String;
       7: areturn

  private void lambda$doStart$1();
    Code:
       0: aload_0
       1: getfield      #1                  // Field this$0:Lcom/google/common/util/concurrent/AbstractExecutionThreadService;
       4: invokevirtual #10                 // Method com/google/common/util/concurrent/AbstractExecutionThreadService.startUp:()V
       7: aload_0
       8: invokevirtual #11                 // Method notifyStarted:()V
      11: aload_0
      12: invokevirtual #12                 // Method isRunning:()Z
      15: ifeq          66
      18: aload_0
      19: getfield      #1                  // Field this$0:Lcom/google/common/util/concurrent/AbstractExecutionThreadService;
      22: invokevirtual #13                 // Method com/google/common/util/concurrent/AbstractExecutionThreadService.run:()V
      25: goto          66
      28: astore_1
      29: aload_1
      30: invokestatic  #15                 // Method com/google/common/util/concurrent/Platform.restoreInterruptIfIsInterruptedException:(Ljava/lang/Throwable;)V
      33: aload_0
      34: getfield      #1                  // Field this$0:Lcom/google/common/util/concurrent/AbstractExecutionThreadService;
      37: invokevirtual #16                 // Method com/google/common/util/concurrent/AbstractExecutionThreadService.shutDown:()V
      40: goto          60
      43: astore_2
      44: aload_2
      45: invokestatic  #15                 // Method com/google/common/util/concurrent/Platform.restoreInterruptIfIsInterruptedException:(Ljava/lang/Throwable;)V
      48: invokestatic  #18                 // Method com/google/common/util/concurrent/AbstractExecutionThreadService.access$000:()Ljava/util/logging/Logger;
      51: getstatic     #19                 // Field java/util/logging/Level.WARNING:Ljava/util/logging/Level;
      54: ldc           #20                 // String Error while attempting to shut down the service after failure.
      56: aload_2
      57: invokevirtual #21                 // Method java/util/logging/Logger.log:(Ljava/util/logging/Level;Ljava/lang/String;Ljava/lang/Throwable;)V
      60: aload_0
      61: aload_1
      62: invokevirtual #22                 // Method notifyFailed:(Ljava/lang/Throwable;)V
      65: return
      66: aload_0
      67: getfield      #1                  // Field this$0:Lcom/google/common/util/concurrent/AbstractExecutionThreadService;
      70: invokevirtual #16                 // Method com/google/common/util/concurrent/AbstractExecutionThreadService.shutDown:()V
      73: aload_0
      74: invokevirtual #23                 // Method notifyStopped:()V
      77: goto          90
      80: astore_1
      81: aload_1
      82: invokestatic  #15                 // Method com/google/common/util/concurrent/Platform.restoreInterruptIfIsInterruptedException:(Ljava/lang/Throwable;)V
      85: aload_0
      86: aload_1
      87: invokevirtual #22                 // Method notifyFailed:(Ljava/lang/Throwable;)V
      90: return
    Exception table:
       from    to  target type
          18    25    28   Class java/lang/Throwable
          33    40    43   Class java/lang/Exception
           0    65    80   Class java/lang/Throwable
          66    77    80   Class java/lang/Throwable

  private java.lang.String lambda$doStart$0();
    Code:
       0: aload_0
       1: getfield      #1                  // Field this$0:Lcom/google/common/util/concurrent/AbstractExecutionThreadService;
       4: invokevirtual #24                 // Method com/google/common/util/concurrent/AbstractExecutionThreadService.serviceName:()Ljava/lang/String;
       7: areturn
}
