Compiled from "AbstractScheduledService.java"
class com.google.common.util.concurrent.AbstractScheduledService$ServiceDelegate$Task implements java.lang.Runnable {
  final com.google.common.util.concurrent.AbstractScheduledService$ServiceDelegate this$1;

  com.google.common.util.concurrent.AbstractScheduledService$ServiceDelegate$Task(com.google.common.util.concurrent.AbstractScheduledService$ServiceDelegate);
    Code:
       0: aload_0
       1: aload_1
       2: putfield      #1                  // Field this$1:Lcom/google/common/util/concurrent/AbstractScheduledService$ServiceDelegate;
       5: aload_0
       6: invokespecial #2                  // Method java/lang/Object."<init>":()V
       9: return

  public void run();
    Code:
       0: aload_0
       1: getfield      #1                  // Field this$1:Lcom/google/common/util/concurrent/AbstractScheduledService$ServiceDelegate;
       4: invokestatic  #3                  // Method com/google/common/util/concurrent/AbstractScheduledService$ServiceDelegate.access$200:(Lcom/google/common/util/concurrent/AbstractScheduledService$ServiceDelegate;)Ljava/util/concurrent/locks/ReentrantLock;
       7: invokevirtual #4                  // Method java/util/concurrent/locks/ReentrantLock.lock:()V
      10: aload_0
      11: getfield      #1                  // Field this$1:Lcom/google/common/util/concurrent/AbstractScheduledService$ServiceDelegate;
      14: invokestatic  #5                  // Method com/google/common/util/concurrent/AbstractScheduledService$ServiceDelegate.access$300:(Lcom/google/common/util/concurrent/AbstractScheduledService$ServiceDelegate;)Lcom/google/common/util/concurrent/AbstractScheduledService$Cancellable;
      17: invokestatic  #6                  // Method java/util/Objects.requireNonNull:(Ljava/lang/Object;)Ljava/lang/Object;
      20: checkcast     #7                  // class com/google/common/util/concurrent/AbstractScheduledService$Cancellable
      23: invokeinterface #8,  1            // InterfaceMethod com/google/common/util/concurrent/AbstractScheduledService$Cancellable.isCancelled:()Z
      28: ifeq          42
      31: aload_0
      32: getfield      #1                  // Field this$1:Lcom/google/common/util/concurrent/AbstractScheduledService$ServiceDelegate;
      35: invokestatic  #3                  // Method com/google/common/util/concurrent/AbstractScheduledService$ServiceDelegate.access$200:(Lcom/google/common/util/concurrent/AbstractScheduledService$ServiceDelegate;)Ljava/util/concurrent/locks/ReentrantLock;
      38: invokevirtual #9                  // Method java/util/concurrent/locks/ReentrantLock.unlock:()V
      41: return
      42: aload_0
      43: getfield      #1                  // Field this$1:Lcom/google/common/util/concurrent/AbstractScheduledService$ServiceDelegate;
      46: getfield      #10                 // Field com/google/common/util/concurrent/AbstractScheduledService$ServiceDelegate.this$0:Lcom/google/common/util/concurrent/AbstractScheduledService;
      49: invokevirtual #11                 // Method com/google/common/util/concurrent/AbstractScheduledService.runOneIteration:()V
      52: aload_0
      53: getfield      #1                  // Field this$1:Lcom/google/common/util/concurrent/AbstractScheduledService$ServiceDelegate;
      56: invokestatic  #3                  // Method com/google/common/util/concurrent/AbstractScheduledService$ServiceDelegate.access$200:(Lcom/google/common/util/concurrent/AbstractScheduledService$ServiceDelegate;)Ljava/util/concurrent/locks/ReentrantLock;
      59: invokevirtual #9                  // Method java/util/concurrent/locks/ReentrantLock.unlock:()V
      62: goto          153
      65: astore_1
      66: aload_1
      67: invokestatic  #13                 // Method com/google/common/util/concurrent/Platform.restoreInterruptIfIsInterruptedException:(Ljava/lang/Throwable;)V
      70: aload_0
      71: getfield      #1                  // Field this$1:Lcom/google/common/util/concurrent/AbstractScheduledService$ServiceDelegate;
      74: getfield      #10                 // Field com/google/common/util/concurrent/AbstractScheduledService$ServiceDelegate.this$0:Lcom/google/common/util/concurrent/AbstractScheduledService;
      77: invokevirtual #14                 // Method com/google/common/util/concurrent/AbstractScheduledService.shutDown:()V
      80: goto          100
      83: astore_2
      84: aload_2
      85: invokestatic  #13                 // Method com/google/common/util/concurrent/Platform.restoreInterruptIfIsInterruptedException:(Ljava/lang/Throwable;)V
      88: invokestatic  #16                 // Method com/google/common/util/concurrent/AbstractScheduledService.access$400:()Ljava/util/logging/Logger;
      91: getstatic     #17                 // Field java/util/logging/Level.WARNING:Ljava/util/logging/Level;
      94: ldc           #18                 // String Error while attempting to shut down the service after failure.
      96: aload_2
      97: invokevirtual #19                 // Method java/util/logging/Logger.log:(Ljava/util/logging/Level;Ljava/lang/String;Ljava/lang/Throwable;)V
     100: aload_0
     101: getfield      #1                  // Field this$1:Lcom/google/common/util/concurrent/AbstractScheduledService$ServiceDelegate;
     104: aload_1
     105: invokevirtual #20                 // Method com/google/common/util/concurrent/AbstractScheduledService$ServiceDelegate.notifyFailed:(Ljava/lang/Throwable;)V
     108: aload_0
     109: getfield      #1                  // Field this$1:Lcom/google/common/util/concurrent/AbstractScheduledService$ServiceDelegate;
     112: invokestatic  #5                  // Method com/google/common/util/concurrent/AbstractScheduledService$ServiceDelegate.access$300:(Lcom/google/common/util/concurrent/AbstractScheduledService$ServiceDelegate;)Lcom/google/common/util/concurrent/AbstractScheduledService$Cancellable;
     115: invokestatic  #6                  // Method java/util/Objects.requireNonNull:(Ljava/lang/Object;)Ljava/lang/Object;
     118: checkcast     #7                  // class com/google/common/util/concurrent/AbstractScheduledService$Cancellable
     121: iconst_0
     122: invokeinterface #21,  2           // InterfaceMethod com/google/common/util/concurrent/AbstractScheduledService$Cancellable.cancel:(Z)V
     127: aload_0
     128: getfield      #1                  // Field this$1:Lcom/google/common/util/concurrent/AbstractScheduledService$ServiceDelegate;
     131: invokestatic  #3                  // Method com/google/common/util/concurrent/AbstractScheduledService$ServiceDelegate.access$200:(Lcom/google/common/util/concurrent/AbstractScheduledService$ServiceDelegate;)Ljava/util/concurrent/locks/ReentrantLock;
     134: invokevirtual #9                  // Method java/util/concurrent/locks/ReentrantLock.unlock:()V
     137: goto          153
     140: astore_3
     141: aload_0
     142: getfield      #1                  // Field this$1:Lcom/google/common/util/concurrent/AbstractScheduledService$ServiceDelegate;
     145: invokestatic  #3                  // Method com/google/common/util/concurrent/AbstractScheduledService$ServiceDelegate.access$200:(Lcom/google/common/util/concurrent/AbstractScheduledService$ServiceDelegate;)Ljava/util/concurrent/locks/ReentrantLock;
     148: invokevirtual #9                  // Method java/util/concurrent/locks/ReentrantLock.unlock:()V
     151: aload_3
     152: athrow
     153: return
    Exception table:
       from    to  target type
          10    31    65   Class java/lang/Throwable
          42    52    65   Class java/lang/Throwable
          70    80    83   Class java/lang/Exception
          10    31   140   any
          42    52   140   any
          65   127   140   any
}
