Compiled from "AbstractCatchingFuture.java"
abstract class com.google.common.util.concurrent.AbstractCatchingFuture<V, X extends java.lang.Throwable, F, T> extends com.google.common.util.concurrent.FluentFuture$TrustedFuture<V> implements java.lang.Runnable {
  com.google.common.util.concurrent.ListenableFuture<? extends V> inputFuture;

  java.lang.Class<X> exceptionType;

  F fallback;

  static <V, X extends java.lang.Throwable> com.google.common.util.concurrent.ListenableFuture<V> create(com.google.common.util.concurrent.ListenableFuture<? extends V>, java.lang.Class<X>, com.google.common.base.Function<? super X, ? extends V>, java.util.concurrent.Executor);
    Code:
       0: new           #1                  // class com/google/common/util/concurrent/AbstractCatchingFuture$CatchingFuture
       3: dup
       4: aload_0
       5: aload_1
       6: aload_2
       7: invokespecial #2                  // Method com/google/common/util/concurrent/AbstractCatchingFuture$CatchingFuture."<init>":(Lcom/google/common/util/concurrent/ListenableFuture;Ljava/lang/Class;Lcom/google/common/base/Function;)V
      10: astore        4
      12: aload_0
      13: aload         4
      15: aload_3
      16: aload         4
      18: invokestatic  #3                  // Method com/google/common/util/concurrent/MoreExecutors.rejectionPropagatingExecutor:(Ljava/util/concurrent/Executor;Lcom/google/common/util/concurrent/AbstractFuture;)Ljava/util/concurrent/Executor;
      21: invokeinterface #4,  3            // InterfaceMethod com/google/common/util/concurrent/ListenableFuture.addListener:(Ljava/lang/Runnable;Ljava/util/concurrent/Executor;)V
      26: aload         4
      28: areturn

  static <X extends java.lang.Throwable, V> com.google.common.util.concurrent.ListenableFuture<V> create(com.google.common.util.concurrent.ListenableFuture<? extends V>, java.lang.Class<X>, com.google.common.util.concurrent.AsyncFunction<? super X, ? extends V>, java.util.concurrent.Executor);
    Code:
       0: new           #5                  // class com/google/common/util/concurrent/AbstractCatchingFuture$AsyncCatchingFuture
       3: dup
       4: aload_0
       5: aload_1
       6: aload_2
       7: invokespecial #6                  // Method com/google/common/util/concurrent/AbstractCatchingFuture$AsyncCatchingFuture."<init>":(Lcom/google/common/util/concurrent/ListenableFuture;Ljava/lang/Class;Lcom/google/common/util/concurrent/AsyncFunction;)V
      10: astore        4
      12: aload_0
      13: aload         4
      15: aload_3
      16: aload         4
      18: invokestatic  #3                  // Method com/google/common/util/concurrent/MoreExecutors.rejectionPropagatingExecutor:(Ljava/util/concurrent/Executor;Lcom/google/common/util/concurrent/AbstractFuture;)Ljava/util/concurrent/Executor;
      21: invokeinterface #4,  3            // InterfaceMethod com/google/common/util/concurrent/ListenableFuture.addListener:(Ljava/lang/Runnable;Ljava/util/concurrent/Executor;)V
      26: aload         4
      28: areturn

  com.google.common.util.concurrent.AbstractCatchingFuture(com.google.common.util.concurrent.ListenableFuture<? extends V>, java.lang.Class<X>, F);
    Code:
       0: aload_0
       1: invokespecial #7                  // Method com/google/common/util/concurrent/FluentFuture$TrustedFuture."<init>":()V
       4: aload_0
       5: aload_1
       6: invokestatic  #8                  // Method com/google/common/base/Preconditions.checkNotNull:(Ljava/lang/Object;)Ljava/lang/Object;
       9: checkcast     #9                  // class com/google/common/util/concurrent/ListenableFuture
      12: putfield      #10                 // Field inputFuture:Lcom/google/common/util/concurrent/ListenableFuture;
      15: aload_0
      16: aload_2
      17: invokestatic  #8                  // Method com/google/common/base/Preconditions.checkNotNull:(Ljava/lang/Object;)Ljava/lang/Object;
      20: checkcast     #11                 // class java/lang/Class
      23: putfield      #12                 // Field exceptionType:Ljava/lang/Class;
      26: aload_0
      27: aload_3
      28: invokestatic  #8                  // Method com/google/common/base/Preconditions.checkNotNull:(Ljava/lang/Object;)Ljava/lang/Object;
      31: putfield      #13                 // Field fallback:Ljava/lang/Object;
      34: return

  public final void run();
    Code:
       0: aload_0
       1: getfield      #10                 // Field inputFuture:Lcom/google/common/util/concurrent/ListenableFuture;
       4: astore_1
       5: aload_0
       6: getfield      #12                 // Field exceptionType:Ljava/lang/Class;
       9: astore_2
      10: aload_0
      11: getfield      #13                 // Field fallback:Ljava/lang/Object;
      14: astore_3
      15: aload_1
      16: ifnonnull     23
      19: iconst_1
      20: goto          24
      23: iconst_0
      24: aload_2
      25: ifnonnull     32
      28: iconst_1
      29: goto          33
      32: iconst_0
      33: ior
      34: aload_3
      35: ifnonnull     42
      38: iconst_1
      39: goto          43
      42: iconst_0
      43: ior
      44: ifne          54
      47: aload_0
      48: invokevirtual #14                 // Method isCancelled:()Z
      51: ifeq          55
      54: return
      55: aload_0
      56: aconst_null
      57: putfield      #10                 // Field inputFuture:Lcom/google/common/util/concurrent/ListenableFuture;
      60: aconst_null
      61: astore        4
      63: aconst_null
      64: astore        5
      66: aload_1
      67: instanceof    #15                 // class com/google/common/util/concurrent/internal/InternalFutureFailureAccess
      70: ifeq          82
      73: aload_1
      74: checkcast     #15                 // class com/google/common/util/concurrent/internal/InternalFutureFailureAccess
      77: invokestatic  #16                 // Method com/google/common/util/concurrent/internal/InternalFutures.tryInternalFastPathGetFailure:(Lcom/google/common/util/concurrent/internal/InternalFutureFailureAccess;)Ljava/lang/Throwable;
      80: astore        5
      82: aload         5
      84: ifnonnull     93
      87: aload_1
      88: invokestatic  #17                 // Method com/google/common/util/concurrent/Futures.getDone:(Ljava/util/concurrent/Future;)Ljava/lang/Object;
      91: astore        4
      93: goto          168
      96: astore        6
      98: aload         6
     100: invokevirtual #19                 // Method java/util/concurrent/ExecutionException.getCause:()Ljava/lang/Throwable;
     103: astore        5
     105: aload         5
     107: ifnonnull     159
     110: new           #20                 // class java/lang/NullPointerException
     113: dup
     114: new           #21                 // class java/lang/StringBuilder
     117: dup
     118: invokespecial #22                 // Method java/lang/StringBuilder."<init>":()V
     121: ldc           #23                 // String Future type
     123: invokevirtual #24                 // Method java/lang/StringBuilder.append:(Ljava/lang/String;)Ljava/lang/StringBuilder;
     126: aload_1
     127: invokevirtual #25                 // Method java/lang/Object.getClass:()Ljava/lang/Class;
     130: invokevirtual #26                 // Method java/lang/StringBuilder.append:(Ljava/lang/Object;)Ljava/lang/StringBuilder;
     133: ldc           #27                 // String  threw
     135: invokevirtual #24                 // Method java/lang/StringBuilder.append:(Ljava/lang/String;)Ljava/lang/StringBuilder;
     138: aload         6
     140: invokevirtual #25                 // Method java/lang/Object.getClass:()Ljava/lang/Class;
     143: invokevirtual #26                 // Method java/lang/StringBuilder.append:(Ljava/lang/Object;)Ljava/lang/StringBuilder;
     146: ldc           #28                 // String  without a cause
     148: invokevirtual #24                 // Method java/lang/StringBuilder.append:(Ljava/lang/String;)Ljava/lang/StringBuilder;
     151: invokevirtual #29                 // Method java/lang/StringBuilder.toString:()Ljava/lang/String;
     154: invokespecial #30                 // Method java/lang/NullPointerException."<init>":(Ljava/lang/String;)V
     157: astore        5
     159: goto          168
     162: astore        6
     164: aload         6
     166: astore        5
     168: aload         5
     170: ifnonnull     184
     173: aload_0
     174: aload         4
     176: invokestatic  #33                 // Method com/google/common/util/concurrent/NullnessCasts.uncheckedCastNullableTToT:(Ljava/lang/Object;)Ljava/lang/Object;
     179: invokevirtual #34                 // Method set:(Ljava/lang/Object;)Z
     182: pop
     183: return
     184: aload         5
     186: aload_2
     187: invokestatic  #35                 // Method com/google/common/util/concurrent/Platform.isInstanceOfThrowableClass:(Ljava/lang/Throwable;Ljava/lang/Class;)Z
     190: ifne          200
     193: aload_0
     194: aload_1
     195: invokevirtual #36                 // Method setFuture:(Lcom/google/common/util/concurrent/ListenableFuture;)Z
     198: pop
     199: return
     200: aload         5
     202: astore        6
     204: aload_0
     205: aload_3
     206: aload         6
     208: invokevirtual #37                 // Method doFallback:(Ljava/lang/Object;Ljava/lang/Throwable;)Ljava/lang/Object;
     211: astore        7
     213: aload_0
     214: aconst_null
     215: putfield      #12                 // Field exceptionType:Ljava/lang/Class;
     218: aload_0
     219: aconst_null
     220: putfield      #13                 // Field fallback:Ljava/lang/Object;
     223: goto          266
     226: astore        8
     228: aload         8
     230: invokestatic  #39                 // Method com/google/common/util/concurrent/Platform.restoreInterruptIfIsInterruptedException:(Ljava/lang/Throwable;)V
     233: aload_0
     234: aload         8
     236: invokevirtual #40                 // Method setException:(Ljava/lang/Throwable;)Z
     239: pop
     240: aload_0
     241: aconst_null
     242: putfield      #12                 // Field exceptionType:Ljava/lang/Class;
     245: aload_0
     246: aconst_null
     247: putfield      #13                 // Field fallback:Ljava/lang/Object;
     250: return
     251: astore        9
     253: aload_0
     254: aconst_null
     255: putfield      #12                 // Field exceptionType:Ljava/lang/Class;
     258: aload_0
     259: aconst_null
     260: putfield      #13                 // Field fallback:Ljava/lang/Object;
     263: aload         9
     265: athrow
     266: aload_0
     267: aload         7
     269: invokevirtual #41                 // Method setResult:(Ljava/lang/Object;)V
     272: return
    Exception table:
       from    to  target type
          66    93    96   Class java/util/concurrent/ExecutionException
          66    93   162   Class java/lang/RuntimeException
          66    93   162   Class java/lang/Error
         204   213   226   Class java/lang/Throwable
         204   213   251   any
         226   240   251   any
         251   253   251   any

  protected java.lang.String pendingToString();
    Code:
       0: aload_0
       1: getfield      #10                 // Field inputFuture:Lcom/google/common/util/concurrent/ListenableFuture;
       4: astore_1
       5: aload_0
       6: getfield      #12                 // Field exceptionType:Ljava/lang/Class;
       9: astore_2
      10: aload_0
      11: getfield      #13                 // Field fallback:Ljava/lang/Object;
      14: astore_3
      15: aload_0
      16: invokespecial #42                 // Method com/google/common/util/concurrent/FluentFuture$TrustedFuture.pendingToString:()Ljava/lang/String;
      19: astore        4
      21: ldc           #43                 // String
      23: astore        5
      25: aload_1
      26: ifnull        55
      29: new           #21                 // class java/lang/StringBuilder
      32: dup
      33: invokespecial #22                 // Method java/lang/StringBuilder."<init>":()V
      36: ldc           #44                 // String inputFuture=[
      38: invokevirtual #24                 // Method java/lang/StringBuilder.append:(Ljava/lang/String;)Ljava/lang/StringBuilder;
      41: aload_1
      42: invokevirtual #26                 // Method java/lang/StringBuilder.append:(Ljava/lang/Object;)Ljava/lang/StringBuilder;
      45: ldc           #45                 // String ],
      47: invokevirtual #24                 // Method java/lang/StringBuilder.append:(Ljava/lang/String;)Ljava/lang/StringBuilder;
      50: invokevirtual #29                 // Method java/lang/StringBuilder.toString:()Ljava/lang/String;
      53: astore        5
      55: aload_2
      56: ifnull        102
      59: aload_3
      60: ifnull        102
      63: new           #21                 // class java/lang/StringBuilder
      66: dup
      67: invokespecial #22                 // Method java/lang/StringBuilder."<init>":()V
      70: aload         5
      72: invokevirtual #24                 // Method java/lang/StringBuilder.append:(Ljava/lang/String;)Ljava/lang/StringBuilder;
      75: ldc           #46                 // String exceptionType=[
      77: invokevirtual #24                 // Method java/lang/StringBuilder.append:(Ljava/lang/String;)Ljava/lang/StringBuilder;
      80: aload_2
      81: invokevirtual #26                 // Method java/lang/StringBuilder.append:(Ljava/lang/Object;)Ljava/lang/StringBuilder;
      84: ldc           #47                 // String ], fallback=[
      86: invokevirtual #24                 // Method java/lang/StringBuilder.append:(Ljava/lang/String;)Ljava/lang/StringBuilder;
      89: aload_3
      90: invokevirtual #26                 // Method java/lang/StringBuilder.append:(Ljava/lang/Object;)Ljava/lang/StringBuilder;
      93: ldc           #48                 // String ]
      95: invokevirtual #24                 // Method java/lang/StringBuilder.append:(Ljava/lang/String;)Ljava/lang/StringBuilder;
      98: invokevirtual #29                 // Method java/lang/StringBuilder.toString:()Ljava/lang/String;
     101: areturn
     102: aload         4
     104: ifnull        128
     107: new           #21                 // class java/lang/StringBuilder
     110: dup
     111: invokespecial #22                 // Method java/lang/StringBuilder."<init>":()V
     114: aload         5
     116: invokevirtual #24                 // Method java/lang/StringBuilder.append:(Ljava/lang/String;)Ljava/lang/StringBuilder;
     119: aload         4
     121: invokevirtual #24                 // Method java/lang/StringBuilder.append:(Ljava/lang/String;)Ljava/lang/StringBuilder;
     124: invokevirtual #29                 // Method java/lang/StringBuilder.toString:()Ljava/lang/String;
     127: areturn
     128: aconst_null
     129: areturn

  abstract T doFallback(F, X) throws java.lang.Exception;

  abstract void setResult(T);

  protected final void afterDone();
    Code:
       0: aload_0
       1: aload_0
       2: getfield      #10                 // Field inputFuture:Lcom/google/common/util/concurrent/ListenableFuture;
       5: invokevirtual #49                 // Method maybePropagateCancellationTo:(Ljava/util/concurrent/Future;)V
       8: aload_0
       9: aconst_null
      10: putfield      #10                 // Field inputFuture:Lcom/google/common/util/concurrent/ListenableFuture;
      13: aload_0
      14: aconst_null
      15: putfield      #12                 // Field exceptionType:Ljava/lang/Class;
      18: aload_0
      19: aconst_null
      20: putfield      #13                 // Field fallback:Ljava/lang/Object;
      23: return
}
