Compiled from "AbstractIdleService.java"
public abstract class com.google.common.util.concurrent.AbstractIdleService implements com.google.common.util.concurrent.Service {
  private final com.google.common.base.Supplier<java.lang.String> threadNameSupplier;

  private final com.google.common.util.concurrent.Service delegate;

  protected com.google.common.util.concurrent.AbstractIdleService();
    Code:
       0: aload_0
       1: invokespecial #2                  // Method java/lang/Object."<init>":()V
       4: aload_0
       5: new           #3                  // class com/google/common/util/concurrent/AbstractIdleService$ThreadNameSupplier
       8: dup
       9: aload_0
      10: aconst_null
      11: invokespecial #4                  // Method com/google/common/util/concurrent/AbstractIdleService$ThreadNameSupplier."<init>":(Lcom/google/common/util/concurrent/AbstractIdleService;Lcom/google/common/util/concurrent/AbstractIdleService$1;)V
      14: putfield      #1                  // Field threadNameSupplier:Lcom/google/common/base/Supplier;
      17: aload_0
      18: new           #5                  // class com/google/common/util/concurrent/AbstractIdleService$DelegateService
      21: dup
      22: aload_0
      23: aconst_null
      24: invokespecial #6                  // Method com/google/common/util/concurrent/AbstractIdleService$DelegateService."<init>":(Lcom/google/common/util/concurrent/AbstractIdleService;Lcom/google/common/util/concurrent/AbstractIdleService$1;)V
      27: putfield      #7                  // Field delegate:Lcom/google/common/util/concurrent/Service;
      30: return

  protected abstract void startUp() throws java.lang.Exception;

  protected abstract void shutDown() throws java.lang.Exception;

  protected java.util.concurrent.Executor executor();
    Code:
       0: aload_0
       1: invokedynamic #8,  0              // InvokeDynamic #0:execute:(Lcom/google/common/util/concurrent/AbstractIdleService;)Ljava/util/concurrent/Executor;
       6: areturn

  public java.lang.String toString();
    Code:
       0: new           #9                  // class java/lang/StringBuilder
       3: dup
       4: invokespecial #10                 // Method java/lang/StringBuilder."<init>":()V
       7: aload_0
       8: invokevirtual #11                 // Method serviceName:()Ljava/lang/String;
      11: invokevirtual #12                 // Method java/lang/StringBuilder.append:(Ljava/lang/String;)Ljava/lang/StringBuilder;
      14: ldc           #13                 // String  [
      16: invokevirtual #12                 // Method java/lang/StringBuilder.append:(Ljava/lang/String;)Ljava/lang/StringBuilder;
      19: aload_0
      20: invokevirtual #14                 // Method state:()Lcom/google/common/util/concurrent/Service$State;
      23: invokevirtual #15                 // Method java/lang/StringBuilder.append:(Ljava/lang/Object;)Ljava/lang/StringBuilder;
      26: ldc           #16                 // String ]
      28: invokevirtual #12                 // Method java/lang/StringBuilder.append:(Ljava/lang/String;)Ljava/lang/StringBuilder;
      31: invokevirtual #17                 // Method java/lang/StringBuilder.toString:()Ljava/lang/String;
      34: areturn

  public final boolean isRunning();
    Code:
       0: aload_0
       1: getfield      #7                  // Field delegate:Lcom/google/common/util/concurrent/Service;
       4: invokeinterface #18,  1           // InterfaceMethod com/google/common/util/concurrent/Service.isRunning:()Z
       9: ireturn

  public final com.google.common.util.concurrent.Service$State state();
    Code:
       0: aload_0
       1: getfield      #7                  // Field delegate:Lcom/google/common/util/concurrent/Service;
       4: invokeinterface #19,  1           // InterfaceMethod com/google/common/util/concurrent/Service.state:()Lcom/google/common/util/concurrent/Service$State;
       9: areturn

  public final void addListener(com.google.common.util.concurrent.Service$Listener, java.util.concurrent.Executor);
    Code:
       0: aload_0
       1: getfield      #7                  // Field delegate:Lcom/google/common/util/concurrent/Service;
       4: aload_1
       5: aload_2
       6: invokeinterface #20,  3           // InterfaceMethod com/google/common/util/concurrent/Service.addListener:(Lcom/google/common/util/concurrent/Service$Listener;Ljava/util/concurrent/Executor;)V
      11: return

  public final java.lang.Throwable failureCause();
    Code:
       0: aload_0
       1: getfield      #7                  // Field delegate:Lcom/google/common/util/concurrent/Service;
       4: invokeinterface #21,  1           // InterfaceMethod com/google/common/util/concurrent/Service.failureCause:()Ljava/lang/Throwable;
       9: areturn

  public final com.google.common.util.concurrent.Service startAsync();
    Code:
       0: aload_0
       1: getfield      #7                  // Field delegate:Lcom/google/common/util/concurrent/Service;
       4: invokeinterface #22,  1           // InterfaceMethod com/google/common/util/concurrent/Service.startAsync:()Lcom/google/common/util/concurrent/Service;
       9: pop
      10: aload_0
      11: areturn

  public final com.google.common.util.concurrent.Service stopAsync();
    Code:
       0: aload_0
       1: getfield      #7                  // Field delegate:Lcom/google/common/util/concurrent/Service;
       4: invokeinterface #23,  1           // InterfaceMethod com/google/common/util/concurrent/Service.stopAsync:()Lcom/google/common/util/concurrent/Service;
       9: pop
      10: aload_0
      11: areturn

  public final void awaitRunning();
    Code:
       0: aload_0
       1: getfield      #7                  // Field delegate:Lcom/google/common/util/concurrent/Service;
       4: invokeinterface #24,  1           // InterfaceMethod com/google/common/util/concurrent/Service.awaitRunning:()V
       9: return

  public final void awaitRunning(java.time.Duration) throws java.util.concurrent.TimeoutException;
    Code:
       0: aload_0
       1: aload_1
       2: invokespecial #25                 // InterfaceMethod com/google/common/util/concurrent/Service.awaitRunning:(Ljava/time/Duration;)V
       5: return

  public final void awaitRunning(long, java.util.concurrent.TimeUnit) throws java.util.concurrent.TimeoutException;
    Code:
       0: aload_0
       1: getfield      #7                  // Field delegate:Lcom/google/common/util/concurrent/Service;
       4: lload_1
       5: aload_3
       6: invokeinterface #26,  4           // InterfaceMethod com/google/common/util/concurrent/Service.awaitRunning:(JLjava/util/concurrent/TimeUnit;)V
      11: return

  public final void awaitTerminated();
    Code:
       0: aload_0
       1: getfield      #7                  // Field delegate:Lcom/google/common/util/concurrent/Service;
       4: invokeinterface #27,  1           // InterfaceMethod com/google/common/util/concurrent/Service.awaitTerminated:()V
       9: return

  public final void awaitTerminated(java.time.Duration) throws java.util.concurrent.TimeoutException;
    Code:
       0: aload_0
       1: aload_1
       2: invokespecial #28                 // InterfaceMethod com/google/common/util/concurrent/Service.awaitTerminated:(Ljava/time/Duration;)V
       5: return

  public final void awaitTerminated(long, java.util.concurrent.TimeUnit) throws java.util.concurrent.TimeoutException;
    Code:
       0: aload_0
       1: getfield      #7                  // Field delegate:Lcom/google/common/util/concurrent/Service;
       4: lload_1
       5: aload_3
       6: invokeinterface #29,  4           // InterfaceMethod com/google/common/util/concurrent/Service.awaitTerminated:(JLjava/util/concurrent/TimeUnit;)V
      11: return

  protected java.lang.String serviceName();
    Code:
       0: aload_0
       1: invokevirtual #30                 // Method java/lang/Object.getClass:()Ljava/lang/Class;
       4: invokevirtual #31                 // Method java/lang/Class.getSimpleName:()Ljava/lang/String;
       7: areturn

  private void lambda$executor$0(java.lang.Runnable);
    Code:
       0: aload_0
       1: getfield      #1                  // Field threadNameSupplier:Lcom/google/common/base/Supplier;
       4: invokeinterface #32,  1           // InterfaceMethod com/google/common/base/Supplier.get:()Ljava/lang/Object;
       9: checkcast     #33                 // class java/lang/String
      12: aload_1
      13: invokestatic  #34                 // Method com/google/common/util/concurrent/MoreExecutors.newThread:(Ljava/lang/String;Ljava/lang/Runnable;)Ljava/lang/Thread;
      16: invokevirtual #35                 // Method java/lang/Thread.start:()V
      19: return

  static com.google.common.base.Supplier access$200(com.google.common.util.concurrent.AbstractIdleService);
    Code:
       0: aload_0
       1: getfield      #1                  // Field threadNameSupplier:Lcom/google/common/base/Supplier;
       4: areturn
}
