Compiled from "AbstractScheduledService.java"
final class com.google.common.util.concurrent.AbstractScheduledService$ServiceDelegate extends com.google.common.util.concurrent.AbstractService {
  private volatile com.google.common.util.concurrent.AbstractScheduledService$Cancellable runningTask;

  private volatile java.util.concurrent.ScheduledExecutorService executorService;

  private final java.util.concurrent.locks.ReentrantLock lock;

  private final java.lang.Runnable task;

  final com.google.common.util.concurrent.AbstractScheduledService this$0;

  private com.google.common.util.concurrent.AbstractScheduledService$ServiceDelegate(com.google.common.util.concurrent.AbstractScheduledService);
    Code:
       0: aload_0
       1: aload_1
       2: putfield      #4                  // Field this$0:Lcom/google/common/util/concurrent/AbstractScheduledService;
       5: aload_0
       6: invokespecial #5                  // Method com/google/common/util/concurrent/AbstractService."<init>":()V
       9: aload_0
      10: new           #6                  // class java/util/concurrent/locks/ReentrantLock
      13: dup
      14: invokespecial #7                  // Method java/util/concurrent/locks/ReentrantLock."<init>":()V
      17: putfield      #2                  // Field lock:Ljava/util/concurrent/locks/ReentrantLock;
      20: aload_0
      21: new           #8                  // class com/google/common/util/concurrent/AbstractScheduledService$ServiceDelegate$Task
      24: dup
      25: aload_0
      26: invokespecial #9                  // Method com/google/common/util/concurrent/AbstractScheduledService$ServiceDelegate$Task."<init>":(Lcom/google/common/util/concurrent/AbstractScheduledService$ServiceDelegate;)V
      29: putfield      #10                 // Field task:Ljava/lang/Runnable;
      32: return

  protected final void doStart();
    Code:
       0: aload_0
       1: aload_0
       2: getfield      #4                  // Field this$0:Lcom/google/common/util/concurrent/AbstractScheduledService;
       5: invokevirtual #11                 // Method com/google/common/util/concurrent/AbstractScheduledService.executor:()Ljava/util/concurrent/ScheduledExecutorService;
       8: aload_0
       9: invokedynamic #12,  0             // InvokeDynamic #0:get:(Lcom/google/common/util/concurrent/AbstractScheduledService$ServiceDelegate;)Lcom/google/common/base/Supplier;
      14: invokestatic  #13                 // Method com/google/common/util/concurrent/MoreExecutors.renamingDecorator:(Ljava/util/concurrent/ScheduledExecutorService;Lcom/google/common/base/Supplier;)Ljava/util/concurrent/ScheduledExecutorService;
      17: putfield      #14                 // Field executorService:Ljava/util/concurrent/ScheduledExecutorService;
      20: aload_0
      21: getfield      #14                 // Field executorService:Ljava/util/concurrent/ScheduledExecutorService;
      24: aload_0
      25: invokedynamic #15,  0             // InvokeDynamic #1:run:(Lcom/google/common/util/concurrent/AbstractScheduledService$ServiceDelegate;)Ljava/lang/Runnable;
      30: invokeinterface #16,  2           // InterfaceMethod java/util/concurrent/ScheduledExecutorService.execute:(Ljava/lang/Runnable;)V
      35: return

  protected final void doStop();
    Code:
       0: aload_0
       1: getfield      #1                  // Field runningTask:Lcom/google/common/util/concurrent/AbstractScheduledService$Cancellable;
       4: invokestatic  #17                 // Method java/util/Objects.requireNonNull:(Ljava/lang/Object;)Ljava/lang/Object;
       7: pop
       8: aload_0
       9: getfield      #14                 // Field executorService:Ljava/util/concurrent/ScheduledExecutorService;
      12: invokestatic  #17                 // Method java/util/Objects.requireNonNull:(Ljava/lang/Object;)Ljava/lang/Object;
      15: pop
      16: aload_0
      17: getfield      #1                  // Field runningTask:Lcom/google/common/util/concurrent/AbstractScheduledService$Cancellable;
      20: iconst_0
      21: invokeinterface #18,  2           // InterfaceMethod com/google/common/util/concurrent/AbstractScheduledService$Cancellable.cancel:(Z)V
      26: aload_0
      27: getfield      #14                 // Field executorService:Ljava/util/concurrent/ScheduledExecutorService;
      30: aload_0
      31: invokedynamic #19,  0             // InvokeDynamic #2:run:(Lcom/google/common/util/concurrent/AbstractScheduledService$ServiceDelegate;)Ljava/lang/Runnable;
      36: invokeinterface #16,  2           // InterfaceMethod java/util/concurrent/ScheduledExecutorService.execute:(Ljava/lang/Runnable;)V
      41: return

  public java.lang.String toString();
    Code:
       0: aload_0
       1: getfield      #4                  // Field this$0:Lcom/google/common/util/concurrent/AbstractScheduledService;
       4: invokevirtual #20                 // Method com/google/common/util/concurrent/AbstractScheduledService.toString:()Ljava/lang/String;
       7: areturn

  private void lambda$doStop$2();
    Code:
       0: aload_0
       1: getfield      #2                  // Field lock:Ljava/util/concurrent/locks/ReentrantLock;
       4: invokevirtual #21                 // Method java/util/concurrent/locks/ReentrantLock.lock:()V
       7: aload_0
       8: invokevirtual #22                 // Method state:()Lcom/google/common/util/concurrent/Service$State;
      11: getstatic     #23                 // Field com/google/common/util/concurrent/Service$State.STOPPING:Lcom/google/common/util/concurrent/Service$State;
      14: if_acmpeq     25
      17: aload_0
      18: getfield      #2                  // Field lock:Ljava/util/concurrent/locks/ReentrantLock;
      21: invokevirtual #24                 // Method java/util/concurrent/locks/ReentrantLock.unlock:()V
      24: return
      25: aload_0
      26: getfield      #4                  // Field this$0:Lcom/google/common/util/concurrent/AbstractScheduledService;
      29: invokevirtual #25                 // Method com/google/common/util/concurrent/AbstractScheduledService.shutDown:()V
      32: aload_0
      33: getfield      #2                  // Field lock:Ljava/util/concurrent/locks/ReentrantLock;
      36: invokevirtual #24                 // Method java/util/concurrent/locks/ReentrantLock.unlock:()V
      39: goto          52
      42: astore_1
      43: aload_0
      44: getfield      #2                  // Field lock:Ljava/util/concurrent/locks/ReentrantLock;
      47: invokevirtual #24                 // Method java/util/concurrent/locks/ReentrantLock.unlock:()V
      50: aload_1
      51: athrow
      52: aload_0
      53: invokevirtual #26                 // Method notifyStopped:()V
      56: goto          69
      59: astore_1
      60: aload_1
      61: invokestatic  #28                 // Method com/google/common/util/concurrent/Platform.restoreInterruptIfIsInterruptedException:(Ljava/lang/Throwable;)V
      64: aload_0
      65: aload_1
      66: invokevirtual #29                 // Method notifyFailed:(Ljava/lang/Throwable;)V
      69: return
    Exception table:
       from    to  target type
           7    17    42   any
          25    32    42   any
           0    24    59   Class java/lang/Throwable
          25    56    59   Class java/lang/Throwable

  private void lambda$doStart$1();
    Code:
       0: aload_0
       1: getfield      #2                  // Field lock:Ljava/util/concurrent/locks/ReentrantLock;
       4: invokevirtual #21                 // Method java/util/concurrent/locks/ReentrantLock.lock:()V
       7: aload_0
       8: getfield      #4                  // Field this$0:Lcom/google/common/util/concurrent/AbstractScheduledService;
      11: invokevirtual #30                 // Method com/google/common/util/concurrent/AbstractScheduledService.startUp:()V
      14: aload_0
      15: getfield      #14                 // Field executorService:Ljava/util/concurrent/ScheduledExecutorService;
      18: invokestatic  #17                 // Method java/util/Objects.requireNonNull:(Ljava/lang/Object;)Ljava/lang/Object;
      21: pop
      22: aload_0
      23: aload_0
      24: getfield      #4                  // Field this$0:Lcom/google/common/util/concurrent/AbstractScheduledService;
      27: invokevirtual #31                 // Method com/google/common/util/concurrent/AbstractScheduledService.scheduler:()Lcom/google/common/util/concurrent/AbstractScheduledService$Scheduler;
      30: aload_0
      31: getfield      #4                  // Field this$0:Lcom/google/common/util/concurrent/AbstractScheduledService;
      34: invokestatic  #32                 // Method com/google/common/util/concurrent/AbstractScheduledService.access$500:(Lcom/google/common/util/concurrent/AbstractScheduledService;)Lcom/google/common/util/concurrent/AbstractService;
      37: aload_0
      38: getfield      #14                 // Field executorService:Ljava/util/concurrent/ScheduledExecutorService;
      41: aload_0
      42: getfield      #10                 // Field task:Ljava/lang/Runnable;
      45: invokevirtual #33                 // Method com/google/common/util/concurrent/AbstractScheduledService$Scheduler.schedule:(Lcom/google/common/util/concurrent/AbstractService;Ljava/util/concurrent/ScheduledExecutorService;Ljava/lang/Runnable;)Lcom/google/common/util/concurrent/AbstractScheduledService$Cancellable;
      48: putfield      #1                  // Field runningTask:Lcom/google/common/util/concurrent/AbstractScheduledService$Cancellable;
      51: aload_0
      52: invokevirtual #34                 // Method notifyStarted:()V
      55: aload_0
      56: getfield      #2                  // Field lock:Ljava/util/concurrent/locks/ReentrantLock;
      59: invokevirtual #24                 // Method java/util/concurrent/locks/ReentrantLock.unlock:()V
      62: goto          112
      65: astore_1
      66: aload_1
      67: invokestatic  #28                 // Method com/google/common/util/concurrent/Platform.restoreInterruptIfIsInterruptedException:(Ljava/lang/Throwable;)V
      70: aload_0
      71: aload_1
      72: invokevirtual #29                 // Method notifyFailed:(Ljava/lang/Throwable;)V
      75: aload_0
      76: getfield      #1                  // Field runningTask:Lcom/google/common/util/concurrent/AbstractScheduledService$Cancellable;
      79: ifnull        92
      82: aload_0
      83: getfield      #1                  // Field runningTask:Lcom/google/common/util/concurrent/AbstractScheduledService$Cancellable;
      86: iconst_0
      87: invokeinterface #18,  2           // InterfaceMethod com/google/common/util/concurrent/AbstractScheduledService$Cancellable.cancel:(Z)V
      92: aload_0
      93: getfield      #2                  // Field lock:Ljava/util/concurrent/locks/ReentrantLock;
      96: invokevirtual #24                 // Method java/util/concurrent/locks/ReentrantLock.unlock:()V
      99: goto          112
     102: astore_2
     103: aload_0
     104: getfield      #2                  // Field lock:Ljava/util/concurrent/locks/ReentrantLock;
     107: invokevirtual #24                 // Method java/util/concurrent/locks/ReentrantLock.unlock:()V
     110: aload_2
     111: athrow
     112: return
    Exception table:
       from    to  target type
           7    55    65   Class java/lang/Throwable
           7    55   102   any
          65    92   102   any

  private java.lang.String lambda$doStart$0();
    Code:
       0: new           #35                 // class java/lang/StringBuilder
       3: dup
       4: invokespecial #36                 // Method java/lang/StringBuilder."<init>":()V
       7: aload_0
       8: getfield      #4                  // Field this$0:Lcom/google/common/util/concurrent/AbstractScheduledService;
      11: invokevirtual #37                 // Method com/google/common/util/concurrent/AbstractScheduledService.serviceName:()Ljava/lang/String;
      14: invokevirtual #38                 // Method java/lang/StringBuilder.append:(Ljava/lang/String;)Ljava/lang/StringBuilder;
      17: ldc           #39                 // String
      19: invokevirtual #38                 // Method java/lang/StringBuilder.append:(Ljava/lang/String;)Ljava/lang/StringBuilder;
      22: aload_0
      23: invokevirtual #22                 // Method state:()Lcom/google/common/util/concurrent/Service$State;
      26: invokevirtual #40                 // Method java/lang/StringBuilder.append:(Ljava/lang/Object;)Ljava/lang/StringBuilder;
      29: invokevirtual #41                 // Method java/lang/StringBuilder.toString:()Ljava/lang/String;
      32: areturn

  com.google.common.util.concurrent.AbstractScheduledService$ServiceDelegate(com.google.common.util.concurrent.AbstractScheduledService, com.google.common.util.concurrent.AbstractScheduledService$1);
    Code:
       0: aload_0
       1: aload_1
       2: invokespecial #3                  // Method "<init>":(Lcom/google/common/util/concurrent/AbstractScheduledService;)V
       5: return

  static java.util.concurrent.locks.ReentrantLock access$200(com.google.common.util.concurrent.AbstractScheduledService$ServiceDelegate);
    Code:
       0: aload_0
       1: getfield      #2                  // Field lock:Ljava/util/concurrent/locks/ReentrantLock;
       4: areturn

  static com.google.common.util.concurrent.AbstractScheduledService$Cancellable access$300(com.google.common.util.concurrent.AbstractScheduledService$ServiceDelegate);
    Code:
       0: aload_0
       1: getfield      #1                  // Field runningTask:Lcom/google/common/util/concurrent/AbstractScheduledService$Cancellable;
       4: areturn
}
