Compiled from "FuturesGetChecked.java"
class com.google.common.util.concurrent.FuturesGetChecked$GetCheckedTypeValidatorHolder {
  static final java.lang.String CLASS_VALUE_VALIDATOR_NAME;

  static final com.google.common.util.concurrent.FuturesGetChecked$GetCheckedTypeValidator BEST_VALIDATOR;

  com.google.common.util.concurrent.FuturesGetChecked$GetCheckedTypeValidatorHolder();
    Code:
       0: aload_0
       1: invokespecial #1                  // Method java/lang/Object."<init>":()V
       4: return

  static com.google.common.util.concurrent.FuturesGetChecked$GetCheckedTypeValidator getBestValidator();
    Code:
       0: getstatic     #2                  // Field CLASS_VALUE_VALIDATOR_NAME:Ljava/lang/String;
       3: invokestatic  #3                  // Method java/lang/Class.forName:(Ljava/lang/String;)Ljava/lang/Class;
       6: ldc           #4                  // class java/lang/Enum
       8: invokevirtual #5                  // Method java/lang/Class.asSubclass:(Ljava/lang/Class;)Ljava/lang/Class;
      11: astore_0
      12: aload_0
      13: invokevirtual #6                  // Method java/lang/Class.getEnumConstants:()[Ljava/lang/Object;
      16: checkcast     #7                  // class "[Ljava/lang/Enum;"
      19: iconst_0
      20: aaload
      21: checkcast     #8                  // class com/google/common/util/concurrent/FuturesGetChecked$GetCheckedTypeValidator
      24: areturn
      25: astore_0
      26: invokestatic  #12                 // Method com/google/common/util/concurrent/FuturesGetChecked.weakSetValidator:()Lcom/google/common/util/concurrent/FuturesGetChecked$GetCheckedTypeValidator;
      29: areturn
    Exception table:
       from    to  target type
           0    24    25   Class java/lang/ClassNotFoundException
           0    24    25   Class java/lang/RuntimeException
           0    24    25   Class java/lang/Error

  static {};
    Code:
       0: new           #13                 // class java/lang/StringBuilder
       3: dup
       4: invokespecial #14                 // Method java/lang/StringBuilder."<init>":()V
       7: ldc           #15                 // class com/google/common/util/concurrent/FuturesGetChecked$GetCheckedTypeValidatorHolder
       9: invokevirtual #16                 // Method java/lang/Class.getName:()Ljava/lang/String;
      12: invokevirtual #17                 // Method java/lang/StringBuilder.append:(Ljava/lang/String;)Ljava/lang/StringBuilder;
      15: ldc           #18                 // String $ClassValueValidator
      17: invokevirtual #17                 // Method java/lang/StringBuilder.append:(Ljava/lang/String;)Ljava/lang/StringBuilder;
      20: invokevirtual #19                 // Method java/lang/StringBuilder.toString:()Ljava/lang/String;
      23: putstatic     #2                  // Field CLASS_VALUE_VALIDATOR_NAME:Ljava/lang/String;
      26: invokestatic  #20                 // Method getBestValidator:()Lcom/google/common/util/concurrent/FuturesGetChecked$GetCheckedTypeValidator;
      29: putstatic     #21                 // Field BEST_VALIDATOR:Lcom/google/common/util/concurrent/FuturesGetChecked$GetCheckedTypeValidator;
      32: return
}
