Compiled from "MoreExecutors.java"
final class com.google.common.util.concurrent.MoreExecutors$ScheduledListeningDecorator$NeverSuccessfulListenableFutureTask extends com.google.common.util.concurrent.AbstractFuture$TrustedFuture<java.lang.Void> implements java.lang.Runnable {
  private final java.lang.Runnable delegate;

  public com.google.common.util.concurrent.MoreExecutors$ScheduledListeningDecorator$NeverSuccessfulListenableFutureTask(java.lang.Runnable);
    Code:
       0: aload_0
       1: invokespecial #1                  // Method com/google/common/util/concurrent/AbstractFuture$TrustedFuture."<init>":()V
       4: aload_0
       5: aload_1
       6: invokestatic  #2                  // Method com/google/common/base/Preconditions.checkNotNull:(Ljava/lang/Object;)Ljava/lang/Object;
       9: checkcast     #3                  // class java/lang/Runnable
      12: putfield      #4                  // Field delegate:Ljava/lang/Runnable;
      15: return

  public void run();
    Code:
       0: aload_0
       1: getfield      #4                  // Field delegate:Ljava/lang/Runnable;
       4: invokeinterface #5,  1            // InterfaceMethod java/lang/Runnable.run:()V
       9: goto          21
      12: astore_1
      13: aload_0
      14: aload_1
      15: invokevirtual #8                  // Method setException:(Ljava/lang/Throwable;)Z
      18: pop
      19: aload_1
      20: athrow
      21: return
    Exception table:
       from    to  target type
           0     9    12   Class java/lang/RuntimeException
           0     9    12   Class java/lang/Error

  protected java.lang.String pendingToString();
    Code:
       0: new           #9                  // class java/lang/StringBuilder
       3: dup
       4: invokespecial #10                 // Method java/lang/StringBuilder."<init>":()V
       7: ldc           #11                 // String task=[
       9: invokevirtual #12                 // Method java/lang/StringBuilder.append:(Ljava/lang/String;)Ljava/lang/StringBuilder;
      12: aload_0
      13: getfield      #4                  // Field delegate:Ljava/lang/Runnable;
      16: invokevirtual #13                 // Method java/lang/StringBuilder.append:(Ljava/lang/Object;)Ljava/lang/StringBuilder;
      19: ldc           #14                 // String ]
      21: invokevirtual #12                 // Method java/lang/StringBuilder.append:(Ljava/lang/String;)Ljava/lang/StringBuilder;
      24: invokevirtual #15                 // Method java/lang/StringBuilder.toString:()Ljava/lang/String;
      27: areturn
}
