Compiled from "Platform.java"
final class com.google.common.util.concurrent.Platform {
  static boolean isInstanceOfThrowableClass(java.lang.Throwable, java.lang.Class<? extends java.lang.Throwable>);
    Code:
       0: aload_1
       1: aload_0
       2: invokevirtual #1                  // Method java/lang/Class.isInstance:(Ljava/lang/Object;)Z
       5: ireturn

  static void restoreInterruptIfIsInterruptedException(java.lang.Throwable);
    Code:
       0: aload_0
       1: invokestatic  #2                  // Method com/google/common/base/Preconditions.checkNotNull:(Ljava/lang/Object;)Ljava/lang/Object;
       4: pop
       5: aload_0
       6: instanceof    #3                  // class java/lang/InterruptedException
       9: ifeq          18
      12: invokestatic  #4                  // Method java/lang/Thread.currentThread:()Ljava/lang/Thread;
      15: invokevirtual #5                  // Method java/lang/Thread.interrupt:()V
      18: return

  private com.google.common.util.concurrent.Platform();
    Code:
       0: aload_0
       1: invokespecial #6                  // Method java/lang/Object."<init>":()V
       4: return
}
