Compiled from "TimeoutFuture.java"
final class com.google.common.util.concurrent.TimeoutFuture$Fire<V> implements java.lang.Runnable {
  com.google.common.util.concurrent.TimeoutFuture<V> timeoutFutureRef;

  com.google.common.util.concurrent.TimeoutFuture$Fire(com.google.common.util.concurrent.TimeoutFuture<V>);
    Code:
       0: aload_0
       1: invokespecial #1                  // Method java/lang/Object."<init>":()V
       4: aload_0
       5: aload_1
       6: putfield      #2                  // Field timeoutFutureRef:Lcom/google/common/util/concurrent/TimeoutFuture;
       9: return

  public void run();
    Code:
       0: aload_0
       1: getfield      #2                  // Field timeoutFutureRef:Lcom/google/common/util/concurrent/TimeoutFuture;
       4: astore_1
       5: aload_1
       6: ifnonnull     10
       9: return
      10: aload_1
      11: invokestatic  #3                  // Method com/google/common/util/concurrent/TimeoutFuture.access$000:(Lcom/google/common/util/concurrent/TimeoutFuture;)Lcom/google/common/util/concurrent/ListenableFuture;
      14: astore_2
      15: aload_2
      16: ifnonnull     20
      19: return
      20: aload_0
      21: aconst_null
      22: putfield      #2                  // Field timeoutFutureRef:Lcom/google/common/util/concurrent/TimeoutFuture;
      25: aload_2
      26: invokeinterface #4,  1            // InterfaceMethod com/google/common/util/concurrent/ListenableFuture.isDone:()Z
      31: ifeq          43
      34: aload_1
      35: aload_2
      36: invokevirtual #5                  // Method com/google/common/util/concurrent/TimeoutFuture.setFuture:(Lcom/google/common/util/concurrent/ListenableFuture;)Z
      39: pop
      40: goto          205
      43: aload_1
      44: invokestatic  #6                  // Method com/google/common/util/concurrent/TimeoutFuture.access$100:(Lcom/google/common/util/concurrent/TimeoutFuture;)Ljava/util/concurrent/ScheduledFuture;
      47: astore_3
      48: aload_1
      49: aconst_null
      50: invokestatic  #7                  // Method com/google/common/util/concurrent/TimeoutFuture.access$102:(Lcom/google/common/util/concurrent/TimeoutFuture;Ljava/util/concurrent/ScheduledFuture;)Ljava/util/concurrent/ScheduledFuture;
      53: pop
      54: ldc           #8                  // String Timed out
      56: astore        4
      58: aload_3
      59: ifnull        117
      62: aload_3
      63: getstatic     #9                  // Field java/util/concurrent/TimeUnit.MILLISECONDS:Ljava/util/concurrent/TimeUnit;
      66: invokeinterface #10,  2           // InterfaceMethod java/util/concurrent/ScheduledFuture.getDelay:(Ljava/util/concurrent/TimeUnit;)J
      71: invokestatic  #11                 // Method java/lang/Math.abs:(J)J
      74: lstore        5
      76: lload         5
      78: ldc2_w        #12                 // long 10l
      81: lcmp
      82: ifle          117
      85: new           #14                 // class java/lang/StringBuilder
      88: dup
      89: invokespecial #15                 // Method java/lang/StringBuilder."<init>":()V
      92: aload         4
      94: invokevirtual #16                 // Method java/lang/StringBuilder.append:(Ljava/lang/String;)Ljava/lang/StringBuilder;
      97: ldc           #17                 // String  (timeout delayed by
      99: invokevirtual #16                 // Method java/lang/StringBuilder.append:(Ljava/lang/String;)Ljava/lang/StringBuilder;
     102: lload         5
     104: invokevirtual #18                 // Method java/lang/StringBuilder.append:(J)Ljava/lang/StringBuilder;
     107: ldc           #19                 // String  ms after scheduled time)
     109: invokevirtual #16                 // Method java/lang/StringBuilder.append:(Ljava/lang/String;)Ljava/lang/StringBuilder;
     112: invokevirtual #20                 // Method java/lang/StringBuilder.toString:()Ljava/lang/String;
     115: astore        4
     117: new           #14                 // class java/lang/StringBuilder
     120: dup
     121: invokespecial #15                 // Method java/lang/StringBuilder."<init>":()V
     124: aload         4
     126: invokevirtual #16                 // Method java/lang/StringBuilder.append:(Ljava/lang/String;)Ljava/lang/StringBuilder;
     129: ldc           #21                 // String :
     131: invokevirtual #16                 // Method java/lang/StringBuilder.append:(Ljava/lang/String;)Ljava/lang/StringBuilder;
     134: aload_2
     135: invokevirtual #22                 // Method java/lang/StringBuilder.append:(Ljava/lang/Object;)Ljava/lang/StringBuilder;
     138: invokevirtual #20                 // Method java/lang/StringBuilder.toString:()Ljava/lang/String;
     141: astore        4
     143: aload_1
     144: new           #23                 // class com/google/common/util/concurrent/TimeoutFuture$TimeoutFutureException
     147: dup
     148: aload         4
     150: aconst_null
     151: invokespecial #24                 // Method com/google/common/util/concurrent/TimeoutFuture$TimeoutFutureException."<init>":(Ljava/lang/String;Lcom/google/common/util/concurrent/TimeoutFuture$1;)V
     154: invokevirtual #25                 // Method com/google/common/util/concurrent/TimeoutFuture.setException:(Ljava/lang/Throwable;)Z
     157: pop
     158: goto          181
     161: astore        7
     163: aload_1
     164: new           #23                 // class com/google/common/util/concurrent/TimeoutFuture$TimeoutFutureException
     167: dup
     168: aload         4
     170: aconst_null
     171: invokespecial #24                 // Method com/google/common/util/concurrent/TimeoutFuture$TimeoutFutureException."<init>":(Ljava/lang/String;Lcom/google/common/util/concurrent/TimeoutFuture$1;)V
     174: invokevirtual #25                 // Method com/google/common/util/concurrent/TimeoutFuture.setException:(Ljava/lang/Throwable;)Z
     177: pop
     178: aload         7
     180: athrow
     181: aload_2
     182: iconst_1
     183: invokeinterface #26,  2           // InterfaceMethod com/google/common/util/concurrent/ListenableFuture.cancel:(Z)Z
     188: pop
     189: goto          205
     192: astore        8
     194: aload_2
     195: iconst_1
     196: invokeinterface #26,  2           // InterfaceMethod com/google/common/util/concurrent/ListenableFuture.cancel:(Z)Z
     201: pop
     202: aload         8
     204: athrow
     205: return
    Exception table:
       from    to  target type
          58   143   161   any
         161   163   161   any
          43   181   192   any
         192   194   192   any
}
