Compiled from "AbstractBuilder.java"
public abstract class org.apache.dubbo.config.bootstrap.builders.AbstractBuilder<C extends org.apache.dubbo.config.AbstractConfig, B extends org.apache.dubbo.config.bootstrap.builders.AbstractBuilder> {
  protected java.lang.String id;

  public org.apache.dubbo.config.bootstrap.builders.AbstractBuilder();
    Code:
       0: aload_0
       1: invokespecial #1                  // Method java/lang/Object."<init>":()V
       4: return

  public B id(java.lang.String);
    Code:
       0: aload_0
       1: aload_1
       2: putfield      #2                  // Field id:Ljava/lang/String;
       5: aload_0
       6: invokevirtual #3                  // Method getThis:()Lorg/apache/dubbo/config/bootstrap/builders/AbstractBuilder;
       9: areturn

  protected abstract B getThis();

  protected static java.util.Map<java.lang.String, java.lang.String> appendParameter(java.util.Map<java.lang.String, java.lang.String>, java.lang.String, java.lang.String);
    Code:
       0: aload_0
       1: ifnonnull     12
       4: new           #4                  // class java/util/HashMap
       7: dup
       8: invokespecial #5                  // Method java/util/HashMap."<init>":()V
      11: astore_0
      12: aload_0
      13: aload_1
      14: aload_2
      15: invokeinterface #6,  3            // InterfaceMethod java/util/Map.put:(Ljava/lang/Object;Ljava/lang/Object;)Ljava/lang/Object;
      20: pop
      21: aload_0
      22: areturn

  protected static java.util.Map<java.lang.String, java.lang.String> appendParameters(java.util.Map<java.lang.String, java.lang.String>, java.util.Map<java.lang.String, java.lang.String>);
    Code:
       0: aload_0
       1: ifnonnull     12
       4: new           #4                  // class java/util/HashMap
       7: dup
       8: invokespecial #5                  // Method java/util/HashMap."<init>":()V
      11: astore_0
      12: aload_0
      13: aload_1
      14: invokeinterface #7,  2            // InterfaceMethod java/util/Map.putAll:(Ljava/util/Map;)V
      19: aload_0
      20: areturn

  protected void build(C);
    Code:
       0: aload_0
       1: getfield      #2                  // Field id:Ljava/lang/String;
       4: invokestatic  #8                  // Method org/apache/dubbo/common/utils/StringUtils.isEmpty:(Ljava/lang/String;)Z
       7: ifne          18
      10: aload_1
      11: aload_0
      12: getfield      #2                  // Field id:Ljava/lang/String;
      15: invokevirtual #9                  // Method org/apache/dubbo/config/AbstractConfig.setId:(Ljava/lang/String;)V
      18: return

  public abstract C build();
}
