Compiled from "AbstractReferenceBuilder.java"
public abstract class org.apache.dubbo.config.bootstrap.builders.AbstractReferenceBuilder<T extends org.apache.dubbo.config.AbstractReferenceConfig, B extends org.apache.dubbo.config.bootstrap.builders.AbstractReferenceBuilder<T, B>> extends org.apache.dubbo.config.bootstrap.builders.AbstractInterfaceBuilder<T, B> {
  protected java.lang.Boolean check;

  protected java.lang.Boolean init;

  protected java.lang.String generic;

  protected java.lang.Boolean injvm;

  protected java.lang.Boolean lazy;

  protected java.lang.String reconnect;

  protected java.lang.Boolean sticky;

  protected java.lang.String version;

  protected java.lang.String group;

  public org.apache.dubbo.config.bootstrap.builders.AbstractReferenceBuilder();
    Code:
       0: aload_0
       1: invokespecial #1                  // Method org/apache/dubbo/config/bootstrap/builders/AbstractInterfaceBuilder."<init>":()V
       4: return

  public B check(java.lang.Boolean);
    Code:
       0: aload_0
       1: aload_1
       2: putfield      #2                  // Field check:Ljava/lang/Boolean;
       5: aload_0
       6: invokevirtual #3                  // Method getThis:()Lorg/apache/dubbo/config/bootstrap/builders/AbstractBuilder;
       9: checkcast     #4                  // class org/apache/dubbo/config/bootstrap/builders/AbstractReferenceBuilder
      12: areturn

  public B init(java.lang.Boolean);
    Code:
       0: aload_0
       1: aload_1
       2: putfield      #5                  // Field init:Ljava/lang/Boolean;
       5: aload_0
       6: invokevirtual #3                  // Method getThis:()Lorg/apache/dubbo/config/bootstrap/builders/AbstractBuilder;
       9: checkcast     #4                  // class org/apache/dubbo/config/bootstrap/builders/AbstractReferenceBuilder
      12: areturn

  public B generic(java.lang.String);
    Code:
       0: aload_0
       1: aload_1
       2: putfield      #6                  // Field generic:Ljava/lang/String;
       5: aload_0
       6: invokevirtual #3                  // Method getThis:()Lorg/apache/dubbo/config/bootstrap/builders/AbstractBuilder;
       9: checkcast     #4                  // class org/apache/dubbo/config/bootstrap/builders/AbstractReferenceBuilder
      12: areturn

  public B generic(java.lang.Boolean);
    Code:
       0: aload_1
       1: ifnull        15
       4: aload_0
       5: aload_1
       6: invokevirtual #7                  // Method java/lang/Boolean.toString:()Ljava/lang/String;
       9: putfield      #6                  // Field generic:Ljava/lang/String;
      12: goto          20
      15: aload_0
      16: aconst_null
      17: putfield      #6                  // Field generic:Ljava/lang/String;
      20: aload_0
      21: invokevirtual #3                  // Method getThis:()Lorg/apache/dubbo/config/bootstrap/builders/AbstractBuilder;
      24: checkcast     #4                  // class org/apache/dubbo/config/bootstrap/builders/AbstractReferenceBuilder
      27: areturn

  public B injvm(java.lang.Boolean);
    Code:
       0: aload_0
       1: aload_1
       2: putfield      #8                  // Field injvm:Ljava/lang/Boolean;
       5: aload_0
       6: invokevirtual #3                  // Method getThis:()Lorg/apache/dubbo/config/bootstrap/builders/AbstractBuilder;
       9: checkcast     #4                  // class org/apache/dubbo/config/bootstrap/builders/AbstractReferenceBuilder
      12: areturn

  public B lazy(java.lang.Boolean);
    Code:
       0: aload_0
       1: aload_1
       2: putfield      #9                  // Field lazy:Ljava/lang/Boolean;
       5: aload_0
       6: invokevirtual #3                  // Method getThis:()Lorg/apache/dubbo/config/bootstrap/builders/AbstractBuilder;
       9: checkcast     #4                  // class org/apache/dubbo/config/bootstrap/builders/AbstractReferenceBuilder
      12: areturn

  public B reconnect(java.lang.String);
    Code:
       0: aload_0
       1: aload_1
       2: putfield      #10                 // Field reconnect:Ljava/lang/String;
       5: aload_0
       6: invokevirtual #3                  // Method getThis:()Lorg/apache/dubbo/config/bootstrap/builders/AbstractBuilder;
       9: checkcast     #4                  // class org/apache/dubbo/config/bootstrap/builders/AbstractReferenceBuilder
      12: areturn

  public B sticky(java.lang.Boolean);
    Code:
       0: aload_0
       1: aload_1
       2: putfield      #11                 // Field sticky:Ljava/lang/Boolean;
       5: aload_0
       6: invokevirtual #3                  // Method getThis:()Lorg/apache/dubbo/config/bootstrap/builders/AbstractBuilder;
       9: checkcast     #4                  // class org/apache/dubbo/config/bootstrap/builders/AbstractReferenceBuilder
      12: areturn

  public B version(java.lang.String);
    Code:
       0: aload_0
       1: aload_1
       2: putfield      #12                 // Field version:Ljava/lang/String;
       5: aload_0
       6: invokevirtual #3                  // Method getThis:()Lorg/apache/dubbo/config/bootstrap/builders/AbstractBuilder;
       9: checkcast     #4                  // class org/apache/dubbo/config/bootstrap/builders/AbstractReferenceBuilder
      12: areturn

  public B group(java.lang.String);
    Code:
       0: aload_0
       1: aload_1
       2: putfield      #13                 // Field group:Ljava/lang/String;
       5: aload_0
       6: invokevirtual #3                  // Method getThis:()Lorg/apache/dubbo/config/bootstrap/builders/AbstractBuilder;
       9: checkcast     #4                  // class org/apache/dubbo/config/bootstrap/builders/AbstractReferenceBuilder
      12: areturn

  public void build(T);
    Code:
       0: aload_0
       1: aload_1
       2: invokespecial #14                 // Method org/apache/dubbo/config/bootstrap/builders/AbstractInterfaceBuilder.build:(Lorg/apache/dubbo/config/AbstractInterfaceConfig;)V
       5: aload_0
       6: getfield      #2                  // Field check:Ljava/lang/Boolean;
       9: ifnull        20
      12: aload_1
      13: aload_0
      14: getfield      #2                  // Field check:Ljava/lang/Boolean;
      17: invokevirtual #15                 // Method org/apache/dubbo/config/AbstractReferenceConfig.setCheck:(Ljava/lang/Boolean;)V
      20: aload_0
      21: getfield      #5                  // Field init:Ljava/lang/Boolean;
      24: ifnull        35
      27: aload_1
      28: aload_0
      29: getfield      #5                  // Field init:Ljava/lang/Boolean;
      32: invokevirtual #16                 // Method org/apache/dubbo/config/AbstractReferenceConfig.setInit:(Ljava/lang/Boolean;)V
      35: aload_0
      36: getfield      #6                  // Field generic:Ljava/lang/String;
      39: invokestatic  #17                 // Method org/apache/dubbo/common/utils/StringUtils.isEmpty:(Ljava/lang/String;)Z
      42: ifne          53
      45: aload_1
      46: aload_0
      47: getfield      #6                  // Field generic:Ljava/lang/String;
      50: invokevirtual #18                 // Method org/apache/dubbo/config/AbstractReferenceConfig.setGeneric:(Ljava/lang/String;)V
      53: aload_0
      54: getfield      #8                  // Field injvm:Ljava/lang/Boolean;
      57: ifnull        68
      60: aload_1
      61: aload_0
      62: getfield      #8                  // Field injvm:Ljava/lang/Boolean;
      65: invokevirtual #19                 // Method org/apache/dubbo/config/AbstractReferenceConfig.setInjvm:(Ljava/lang/Boolean;)V
      68: aload_0
      69: getfield      #9                  // Field lazy:Ljava/lang/Boolean;
      72: ifnull        83
      75: aload_1
      76: aload_0
      77: getfield      #9                  // Field lazy:Ljava/lang/Boolean;
      80: invokevirtual #20                 // Method org/apache/dubbo/config/AbstractReferenceConfig.setLazy:(Ljava/lang/Boolean;)V
      83: aload_0
      84: getfield      #10                 // Field reconnect:Ljava/lang/String;
      87: invokestatic  #17                 // Method org/apache/dubbo/common/utils/StringUtils.isEmpty:(Ljava/lang/String;)Z
      90: ifne          101
      93: aload_1
      94: aload_0
      95: getfield      #10                 // Field reconnect:Ljava/lang/String;
      98: invokevirtual #21                 // Method org/apache/dubbo/config/AbstractReferenceConfig.setReconnect:(Ljava/lang/String;)V
     101: aload_0
     102: getfield      #11                 // Field sticky:Ljava/lang/Boolean;
     105: ifnull        116
     108: aload_1
     109: aload_0
     110: getfield      #11                 // Field sticky:Ljava/lang/Boolean;
     113: invokevirtual #22                 // Method org/apache/dubbo/config/AbstractReferenceConfig.setSticky:(Ljava/lang/Boolean;)V
     116: aload_0
     117: getfield      #12                 // Field version:Ljava/lang/String;
     120: invokestatic  #17                 // Method org/apache/dubbo/common/utils/StringUtils.isEmpty:(Ljava/lang/String;)Z
     123: ifne          134
     126: aload_1
     127: aload_0
     128: getfield      #12                 // Field version:Ljava/lang/String;
     131: invokevirtual #23                 // Method org/apache/dubbo/config/AbstractReferenceConfig.setVersion:(Ljava/lang/String;)V
     134: aload_0
     135: getfield      #13                 // Field group:Ljava/lang/String;
     138: invokestatic  #17                 // Method org/apache/dubbo/common/utils/StringUtils.isEmpty:(Ljava/lang/String;)Z
     141: ifne          152
     144: aload_1
     145: aload_0
     146: getfield      #13                 // Field group:Ljava/lang/String;
     149: invokevirtual #24                 // Method org/apache/dubbo/config/AbstractReferenceConfig.setGroup:(Ljava/lang/String;)V
     152: return

  public void build(org.apache.dubbo.config.AbstractInterfaceConfig);
    Code:
       0: aload_0
       1: aload_1
       2: checkcast     #25                 // class org/apache/dubbo/config/AbstractReferenceConfig
       5: invokevirtual #26                 // Method build:(Lorg/apache/dubbo/config/AbstractReferenceConfig;)V
       8: return

  public void build(org.apache.dubbo.config.AbstractMethodConfig);
    Code:
       0: aload_0
       1: aload_1
       2: checkcast     #25                 // class org/apache/dubbo/config/AbstractReferenceConfig
       5: invokevirtual #26                 // Method build:(Lorg/apache/dubbo/config/AbstractReferenceConfig;)V
       8: return

  public void build(org.apache.dubbo.config.AbstractConfig);
    Code:
       0: aload_0
       1: aload_1
       2: checkcast     #25                 // class org/apache/dubbo/config/AbstractReferenceConfig
       5: invokevirtual #26                 // Method build:(Lorg/apache/dubbo/config/AbstractReferenceConfig;)V
       8: return
}
