Compiled from "AbstractServiceBuilder.java"
public abstract class org.apache.dubbo.config.bootstrap.builders.AbstractServiceBuilder<T extends org.apache.dubbo.config.AbstractServiceConfig, B extends org.apache.dubbo.config.bootstrap.builders.AbstractServiceBuilder<T, B>> extends org.apache.dubbo.config.bootstrap.builders.AbstractInterfaceBuilder<T, B> {
  protected java.lang.String version;

  protected java.lang.String group;

  protected java.lang.Boolean deprecated;

  protected java.lang.Integer delay;

  protected java.lang.Boolean export;

  protected java.lang.Integer weight;

  protected java.lang.String document;

  protected java.lang.Boolean dynamic;

  protected java.lang.String token;

  protected java.lang.String accesslog;

  protected java.util.List<org.apache.dubbo.config.ProtocolConfig> protocols;

  protected java.lang.String protocolIds;

  private java.lang.Integer executes;

  private java.lang.Boolean register;

  private java.lang.Integer warmup;

  private java.lang.String serialization;

  private java.util.concurrent.Executor executor;

  private java.lang.String preferSerialization;

  public org.apache.dubbo.config.bootstrap.builders.AbstractServiceBuilder();
    Code:
       0: aload_0
       1: invokespecial #1                  // Method org/apache/dubbo/config/bootstrap/builders/AbstractInterfaceBuilder."<init>":()V
       4: return

  public B version(java.lang.String);
    Code:
       0: aload_0
       1: aload_1
       2: putfield      #2                  // Field version:Ljava/lang/String;
       5: aload_0
       6: invokevirtual #3                  // Method getThis:()Lorg/apache/dubbo/config/bootstrap/builders/AbstractBuilder;
       9: checkcast     #4                  // class org/apache/dubbo/config/bootstrap/builders/AbstractServiceBuilder
      12: areturn

  public B group(java.lang.String);
    Code:
       0: aload_0
       1: aload_1
       2: putfield      #5                  // Field group:Ljava/lang/String;
       5: aload_0
       6: invokevirtual #3                  // Method getThis:()Lorg/apache/dubbo/config/bootstrap/builders/AbstractBuilder;
       9: checkcast     #4                  // class org/apache/dubbo/config/bootstrap/builders/AbstractServiceBuilder
      12: areturn

  public B deprecated(java.lang.Boolean);
    Code:
       0: aload_0
       1: aload_1
       2: putfield      #6                  // Field deprecated:Ljava/lang/Boolean;
       5: aload_0
       6: invokevirtual #3                  // Method getThis:()Lorg/apache/dubbo/config/bootstrap/builders/AbstractBuilder;
       9: checkcast     #4                  // class org/apache/dubbo/config/bootstrap/builders/AbstractServiceBuilder
      12: areturn

  public B delay(java.lang.Integer);
    Code:
       0: aload_0
       1: aload_1
       2: putfield      #7                  // Field delay:Ljava/lang/Integer;
       5: aload_0
       6: invokevirtual #3                  // Method getThis:()Lorg/apache/dubbo/config/bootstrap/builders/AbstractBuilder;
       9: checkcast     #4                  // class org/apache/dubbo/config/bootstrap/builders/AbstractServiceBuilder
      12: areturn

  public B export(java.lang.Boolean);
    Code:
       0: aload_0
       1: aload_1
       2: putfield      #8                  // Field export:Ljava/lang/Boolean;
       5: aload_0
       6: invokevirtual #3                  // Method getThis:()Lorg/apache/dubbo/config/bootstrap/builders/AbstractBuilder;
       9: checkcast     #4                  // class org/apache/dubbo/config/bootstrap/builders/AbstractServiceBuilder
      12: areturn

  public B weight(java.lang.Integer);
    Code:
       0: aload_0
       1: aload_1
       2: putfield      #9                  // Field weight:Ljava/lang/Integer;
       5: aload_0
       6: invokevirtual #3                  // Method getThis:()Lorg/apache/dubbo/config/bootstrap/builders/AbstractBuilder;
       9: checkcast     #4                  // class org/apache/dubbo/config/bootstrap/builders/AbstractServiceBuilder
      12: areturn

  public B document(java.lang.String);
    Code:
       0: aload_0
       1: aload_1
       2: putfield      #10                 // Field document:Ljava/lang/String;
       5: aload_0
       6: invokevirtual #3                  // Method getThis:()Lorg/apache/dubbo/config/bootstrap/builders/AbstractBuilder;
       9: checkcast     #4                  // class org/apache/dubbo/config/bootstrap/builders/AbstractServiceBuilder
      12: areturn

  public B dynamic(java.lang.Boolean);
    Code:
       0: aload_0
       1: aload_1
       2: putfield      #11                 // Field dynamic:Ljava/lang/Boolean;
       5: aload_0
       6: invokevirtual #3                  // Method getThis:()Lorg/apache/dubbo/config/bootstrap/builders/AbstractBuilder;
       9: checkcast     #4                  // class org/apache/dubbo/config/bootstrap/builders/AbstractServiceBuilder
      12: areturn

  public B token(java.lang.String);
    Code:
       0: aload_0
       1: aload_1
       2: putfield      #12                 // Field token:Ljava/lang/String;
       5: aload_0
       6: invokevirtual #3                  // Method getThis:()Lorg/apache/dubbo/config/bootstrap/builders/AbstractBuilder;
       9: checkcast     #4                  // class org/apache/dubbo/config/bootstrap/builders/AbstractServiceBuilder
      12: areturn

  public B token(java.lang.Boolean);
    Code:
       0: aload_1
       1: ifnull        15
       4: aload_0
       5: aload_1
       6: invokevirtual #13                 // Method java/lang/Boolean.toString:()Ljava/lang/String;
       9: putfield      #12                 // Field token:Ljava/lang/String;
      12: goto          20
      15: aload_0
      16: aconst_null
      17: putfield      #12                 // Field token:Ljava/lang/String;
      20: aload_0
      21: invokevirtual #3                  // Method getThis:()Lorg/apache/dubbo/config/bootstrap/builders/AbstractBuilder;
      24: checkcast     #4                  // class org/apache/dubbo/config/bootstrap/builders/AbstractServiceBuilder
      27: areturn

  public B accesslog(java.lang.String);
    Code:
       0: aload_0
       1: aload_1
       2: putfield      #14                 // Field accesslog:Ljava/lang/String;
       5: aload_0
       6: invokevirtual #3                  // Method getThis:()Lorg/apache/dubbo/config/bootstrap/builders/AbstractBuilder;
       9: checkcast     #4                  // class org/apache/dubbo/config/bootstrap/builders/AbstractServiceBuilder
      12: areturn

  public B accesslog(java.lang.Boolean);
    Code:
       0: aload_1
       1: ifnull        15
       4: aload_0
       5: aload_1
       6: invokevirtual #13                 // Method java/lang/Boolean.toString:()Ljava/lang/String;
       9: putfield      #14                 // Field accesslog:Ljava/lang/String;
      12: goto          20
      15: aload_0
      16: aconst_null
      17: putfield      #14                 // Field accesslog:Ljava/lang/String;
      20: aload_0
      21: invokevirtual #3                  // Method getThis:()Lorg/apache/dubbo/config/bootstrap/builders/AbstractBuilder;
      24: checkcast     #4                  // class org/apache/dubbo/config/bootstrap/builders/AbstractServiceBuilder
      27: areturn

  public B addProtocols(java.util.List<org.apache.dubbo.config.ProtocolConfig>);
    Code:
       0: aload_0
       1: getfield      #15                 // Field protocols:Ljava/util/List;
       4: ifnonnull     18
       7: aload_0
       8: new           #16                 // class java/util/ArrayList
      11: dup
      12: invokespecial #17                 // Method java/util/ArrayList."<init>":()V
      15: putfield      #15                 // Field protocols:Ljava/util/List;
      18: aload_0
      19: getfield      #15                 // Field protocols:Ljava/util/List;
      22: aload_1
      23: invokeinterface #18,  2           // InterfaceMethod java/util/List.addAll:(Ljava/util/Collection;)Z
      28: pop
      29: aload_0
      30: invokevirtual #3                  // Method getThis:()Lorg/apache/dubbo/config/bootstrap/builders/AbstractBuilder;
      33: checkcast     #4                  // class org/apache/dubbo/config/bootstrap/builders/AbstractServiceBuilder
      36: areturn

  public B addProtocol(org.apache.dubbo.config.ProtocolConfig);
    Code:
       0: aload_0
       1: getfield      #15                 // Field protocols:Ljava/util/List;
       4: ifnonnull     18
       7: aload_0
       8: new           #16                 // class java/util/ArrayList
      11: dup
      12: invokespecial #17                 // Method java/util/ArrayList."<init>":()V
      15: putfield      #15                 // Field protocols:Ljava/util/List;
      18: aload_0
      19: getfield      #15                 // Field protocols:Ljava/util/List;
      22: aload_1
      23: invokeinterface #19,  2           // InterfaceMethod java/util/List.add:(Ljava/lang/Object;)Z
      28: pop
      29: aload_0
      30: invokevirtual #3                  // Method getThis:()Lorg/apache/dubbo/config/bootstrap/builders/AbstractBuilder;
      33: checkcast     #4                  // class org/apache/dubbo/config/bootstrap/builders/AbstractServiceBuilder
      36: areturn

  public B protocolIds(java.lang.String);
    Code:
       0: aload_0
       1: aload_1
       2: putfield      #20                 // Field protocolIds:Ljava/lang/String;
       5: aload_0
       6: invokevirtual #3                  // Method getThis:()Lorg/apache/dubbo/config/bootstrap/builders/AbstractBuilder;
       9: checkcast     #4                  // class org/apache/dubbo/config/bootstrap/builders/AbstractServiceBuilder
      12: areturn

  public B executes(java.lang.Integer);
    Code:
       0: aload_0
       1: aload_1
       2: putfield      #21                 // Field executes:Ljava/lang/Integer;
       5: aload_0
       6: invokevirtual #3                  // Method getThis:()Lorg/apache/dubbo/config/bootstrap/builders/AbstractBuilder;
       9: checkcast     #4                  // class org/apache/dubbo/config/bootstrap/builders/AbstractServiceBuilder
      12: areturn

  public B register(java.lang.Boolean);
    Code:
       0: aload_0
       1: aload_1
       2: putfield      #22                 // Field register:Ljava/lang/Boolean;
       5: aload_0
       6: invokevirtual #3                  // Method getThis:()Lorg/apache/dubbo/config/bootstrap/builders/AbstractBuilder;
       9: checkcast     #4                  // class org/apache/dubbo/config/bootstrap/builders/AbstractServiceBuilder
      12: areturn

  public B warmup(java.lang.Integer);
    Code:
       0: aload_0
       1: aload_1
       2: putfield      #23                 // Field warmup:Ljava/lang/Integer;
       5: aload_0
       6: invokevirtual #3                  // Method getThis:()Lorg/apache/dubbo/config/bootstrap/builders/AbstractBuilder;
       9: checkcast     #4                  // class org/apache/dubbo/config/bootstrap/builders/AbstractServiceBuilder
      12: areturn

  public B serialization(java.lang.String);
    Code:
       0: aload_0
       1: aload_1
       2: putfield      #24                 // Field serialization:Ljava/lang/String;
       5: aload_0
       6: invokevirtual #3                  // Method getThis:()Lorg/apache/dubbo/config/bootstrap/builders/AbstractBuilder;
       9: checkcast     #4                  // class org/apache/dubbo/config/bootstrap/builders/AbstractServiceBuilder
      12: areturn

  public B executor(java.util.concurrent.Executor);
    Code:
       0: aload_0
       1: aload_1
       2: putfield      #25                 // Field executor:Ljava/util/concurrent/Executor;
       5: aload_0
       6: invokevirtual #3                  // Method getThis:()Lorg/apache/dubbo/config/bootstrap/builders/AbstractBuilder;
       9: checkcast     #4                  // class org/apache/dubbo/config/bootstrap/builders/AbstractServiceBuilder
      12: areturn

  public B preferSerialization(java.lang.String);
    Code:
       0: aload_0
       1: aload_1
       2: putfield      #26                 // Field preferSerialization:Ljava/lang/String;
       5: aload_0
       6: invokevirtual #3                  // Method getThis:()Lorg/apache/dubbo/config/bootstrap/builders/AbstractBuilder;
       9: checkcast     #4                  // class org/apache/dubbo/config/bootstrap/builders/AbstractServiceBuilder
      12: areturn

  public void build(T);
    Code:
       0: aload_0
       1: aload_1
       2: invokespecial #27                 // Method org/apache/dubbo/config/bootstrap/builders/AbstractInterfaceBuilder.build:(Lorg/apache/dubbo/config/AbstractInterfaceConfig;)V
       5: aload_0
       6: getfield      #2                  // Field version:Ljava/lang/String;
       9: invokestatic  #28                 // Method org/apache/dubbo/common/utils/StringUtils.isEmpty:(Ljava/lang/String;)Z
      12: ifne          23
      15: aload_1
      16: aload_0
      17: getfield      #2                  // Field version:Ljava/lang/String;
      20: invokevirtual #29                 // Method org/apache/dubbo/config/AbstractServiceConfig.setVersion:(Ljava/lang/String;)V
      23: aload_0
      24: getfield      #5                  // Field group:Ljava/lang/String;
      27: invokestatic  #28                 // Method org/apache/dubbo/common/utils/StringUtils.isEmpty:(Ljava/lang/String;)Z
      30: ifne          41
      33: aload_1
      34: aload_0
      35: getfield      #5                  // Field group:Ljava/lang/String;
      38: invokevirtual #30                 // Method org/apache/dubbo/config/AbstractServiceConfig.setGroup:(Ljava/lang/String;)V
      41: aload_0
      42: getfield      #6                  // Field deprecated:Ljava/lang/Boolean;
      45: ifnull        56
      48: aload_1
      49: aload_0
      50: getfield      #6                  // Field deprecated:Ljava/lang/Boolean;
      53: invokevirtual #31                 // Method org/apache/dubbo/config/AbstractServiceConfig.setDeprecated:(Ljava/lang/Boolean;)V
      56: aload_0
      57: getfield      #7                  // Field delay:Ljava/lang/Integer;
      60: ifnull        71
      63: aload_1
      64: aload_0
      65: getfield      #7                  // Field delay:Ljava/lang/Integer;
      68: invokevirtual #32                 // Method org/apache/dubbo/config/AbstractServiceConfig.setDelay:(Ljava/lang/Integer;)V
      71: aload_0
      72: getfield      #8                  // Field export:Ljava/lang/Boolean;
      75: ifnull        86
      78: aload_1
      79: aload_0
      80: getfield      #8                  // Field export:Ljava/lang/Boolean;
      83: invokevirtual #33                 // Method org/apache/dubbo/config/AbstractServiceConfig.setExport:(Ljava/lang/Boolean;)V
      86: aload_0
      87: getfield      #9                  // Field weight:Ljava/lang/Integer;
      90: ifnull        101
      93: aload_1
      94: aload_0
      95: getfield      #9                  // Field weight:Ljava/lang/Integer;
      98: invokevirtual #34                 // Method org/apache/dubbo/config/AbstractServiceConfig.setWeight:(Ljava/lang/Integer;)V
     101: aload_0
     102: getfield      #10                 // Field document:Ljava/lang/String;
     105: invokestatic  #28                 // Method org/apache/dubbo/common/utils/StringUtils.isEmpty:(Ljava/lang/String;)Z
     108: ifne          119
     111: aload_1
     112: aload_0
     113: getfield      #10                 // Field document:Ljava/lang/String;
     116: invokevirtual #35                 // Method org/apache/dubbo/config/AbstractServiceConfig.setDocument:(Ljava/lang/String;)V
     119: aload_0
     120: getfield      #11                 // Field dynamic:Ljava/lang/Boolean;
     123: ifnull        134
     126: aload_1
     127: aload_0
     128: getfield      #11                 // Field dynamic:Ljava/lang/Boolean;
     131: invokevirtual #36                 // Method org/apache/dubbo/config/AbstractServiceConfig.setDynamic:(Ljava/lang/Boolean;)V
     134: aload_0
     135: getfield      #12                 // Field token:Ljava/lang/String;
     138: invokestatic  #28                 // Method org/apache/dubbo/common/utils/StringUtils.isEmpty:(Ljava/lang/String;)Z
     141: ifne          152
     144: aload_1
     145: aload_0
     146: getfield      #12                 // Field token:Ljava/lang/String;
     149: invokevirtual #37                 // Method org/apache/dubbo/config/AbstractServiceConfig.setToken:(Ljava/lang/String;)V
     152: aload_0
     153: getfield      #14                 // Field accesslog:Ljava/lang/String;
     156: invokestatic  #28                 // Method org/apache/dubbo/common/utils/StringUtils.isEmpty:(Ljava/lang/String;)Z
     159: ifne          170
     162: aload_1
     163: aload_0
     164: getfield      #14                 // Field accesslog:Ljava/lang/String;
     167: invokevirtual #38                 // Method org/apache/dubbo/config/AbstractServiceConfig.setAccesslog:(Ljava/lang/String;)V
     170: aload_0
     171: getfield      #15                 // Field protocols:Ljava/util/List;
     174: ifnull        185
     177: aload_1
     178: aload_0
     179: getfield      #15                 // Field protocols:Ljava/util/List;
     182: invokevirtual #39                 // Method org/apache/dubbo/config/AbstractServiceConfig.setProtocols:(Ljava/util/List;)V
     185: aload_0
     186: getfield      #20                 // Field protocolIds:Ljava/lang/String;
     189: invokestatic  #28                 // Method org/apache/dubbo/common/utils/StringUtils.isEmpty:(Ljava/lang/String;)Z
     192: ifne          203
     195: aload_1
     196: aload_0
     197: getfield      #20                 // Field protocolIds:Ljava/lang/String;
     200: invokevirtual #40                 // Method org/apache/dubbo/config/AbstractServiceConfig.setProtocolIds:(Ljava/lang/String;)V
     203: aload_0
     204: getfield      #21                 // Field executes:Ljava/lang/Integer;
     207: ifnull        218
     210: aload_1
     211: aload_0
     212: getfield      #21                 // Field executes:Ljava/lang/Integer;
     215: invokevirtual #41                 // Method org/apache/dubbo/config/AbstractServiceConfig.setExecutes:(Ljava/lang/Integer;)V
     218: aload_0
     219: getfield      #22                 // Field register:Ljava/lang/Boolean;
     222: ifnull        233
     225: aload_1
     226: aload_0
     227: getfield      #22                 // Field register:Ljava/lang/Boolean;
     230: invokevirtual #42                 // Method org/apache/dubbo/config/AbstractServiceConfig.setRegister:(Ljava/lang/Boolean;)V
     233: aload_0
     234: getfield      #23                 // Field warmup:Ljava/lang/Integer;
     237: ifnull        248
     240: aload_1
     241: aload_0
     242: getfield      #23                 // Field warmup:Ljava/lang/Integer;
     245: invokevirtual #43                 // Method org/apache/dubbo/config/AbstractServiceConfig.setWarmup:(Ljava/lang/Integer;)V
     248: aload_0
     249: getfield      #24                 // Field serialization:Ljava/lang/String;
     252: invokestatic  #28                 // Method org/apache/dubbo/common/utils/StringUtils.isEmpty:(Ljava/lang/String;)Z
     255: ifne          266
     258: aload_1
     259: aload_0
     260: getfield      #24                 // Field serialization:Ljava/lang/String;
     263: invokevirtual #44                 // Method org/apache/dubbo/config/AbstractServiceConfig.setSerialization:(Ljava/lang/String;)V
     266: aload_0
     267: getfield      #25                 // Field executor:Ljava/util/concurrent/Executor;
     270: ifnull        281
     273: aload_1
     274: aload_0
     275: getfield      #25                 // Field executor:Ljava/util/concurrent/Executor;
     278: invokevirtual #45                 // Method org/apache/dubbo/config/AbstractServiceConfig.setExecutor:(Ljava/util/concurrent/Executor;)V
     281: aload_0
     282: getfield      #26                 // Field preferSerialization:Ljava/lang/String;
     285: invokestatic  #46                 // Method org/apache/dubbo/common/utils/StringUtils.isNotBlank:(Ljava/lang/CharSequence;)Z
     288: ifeq          299
     291: aload_1
     292: aload_0
     293: getfield      #26                 // Field preferSerialization:Ljava/lang/String;
     296: invokevirtual #47                 // Method org/apache/dubbo/config/AbstractServiceConfig.setPreferSerialization:(Ljava/lang/String;)V
     299: return

  public void build(org.apache.dubbo.config.AbstractInterfaceConfig);
    Code:
       0: aload_0
       1: aload_1
       2: checkcast     #48                 // class org/apache/dubbo/config/AbstractServiceConfig
       5: invokevirtual #49                 // Method build:(Lorg/apache/dubbo/config/AbstractServiceConfig;)V
       8: return

  public void build(org.apache.dubbo.config.AbstractMethodConfig);
    Code:
       0: aload_0
       1: aload_1
       2: checkcast     #48                 // class org/apache/dubbo/config/AbstractServiceConfig
       5: invokevirtual #49                 // Method build:(Lorg/apache/dubbo/config/AbstractServiceConfig;)V
       8: return

  public void build(org.apache.dubbo.config.AbstractConfig);
    Code:
       0: aload_0
       1: aload_1
       2: checkcast     #48                 // class org/apache/dubbo/config/AbstractServiceConfig
       5: invokevirtual #49                 // Method build:(Lorg/apache/dubbo/config/AbstractServiceConfig;)V
       8: return
}
