Compiled from "AbstractInterfaceBuilder.java"
public abstract class org.apache.dubbo.config.bootstrap.builders.AbstractInterfaceBuilder<T extends org.apache.dubbo.config.AbstractInterfaceConfig, B extends org.apache.dubbo.config.bootstrap.builders.AbstractInterfaceBuilder<T, B>> extends org.apache.dubbo.config.bootstrap.builders.AbstractMethodBuilder<T, B> {
  protected java.lang.String local;

  protected java.lang.String stub;

  protected org.apache.dubbo.config.MonitorConfig monitor;

  protected java.lang.String proxy;

  protected java.lang.String cluster;

  protected java.lang.String filter;

  protected java.lang.String listener;

  protected java.lang.String owner;

  protected java.lang.Integer connections;

  protected java.lang.String layer;

  protected org.apache.dubbo.config.ApplicationConfig application;

  protected org.apache.dubbo.config.ModuleConfig module;

  protected java.util.List<org.apache.dubbo.config.RegistryConfig> registries;

  protected java.lang.String registryIds;

  protected java.lang.String onconnect;

  protected java.lang.String ondisconnect;

  protected org.apache.dubbo.config.MetadataReportConfig metadataReportConfig;

  protected org.apache.dubbo.config.ConfigCenterConfig configCenter;

  private java.lang.Integer callbacks;

  private java.lang.String scope;

  private java.lang.String tag;

  public org.apache.dubbo.config.bootstrap.builders.AbstractInterfaceBuilder();
    Code:
       0: aload_0
       1: invokespecial #1                  // Method org/apache/dubbo/config/bootstrap/builders/AbstractMethodBuilder."<init>":()V
       4: return

  public B local(java.lang.String);
    Code:
       0: aload_0
       1: aload_1
       2: putfield      #2                  // Field local:Ljava/lang/String;
       5: aload_0
       6: invokevirtual #3                  // Method getThis:()Lorg/apache/dubbo/config/bootstrap/builders/AbstractBuilder;
       9: checkcast     #4                  // class org/apache/dubbo/config/bootstrap/builders/AbstractInterfaceBuilder
      12: areturn

  public B local(java.lang.Boolean);
    Code:
       0: aload_1
       1: ifnull        15
       4: aload_0
       5: aload_1
       6: invokevirtual #5                  // Method java/lang/Boolean.toString:()Ljava/lang/String;
       9: putfield      #2                  // Field local:Ljava/lang/String;
      12: goto          20
      15: aload_0
      16: aconst_null
      17: putfield      #2                  // Field local:Ljava/lang/String;
      20: aload_0
      21: invokevirtual #3                  // Method getThis:()Lorg/apache/dubbo/config/bootstrap/builders/AbstractBuilder;
      24: checkcast     #4                  // class org/apache/dubbo/config/bootstrap/builders/AbstractInterfaceBuilder
      27: areturn

  public B stub(java.lang.String);
    Code:
       0: aload_0
       1: aload_1
       2: putfield      #6                  // Field stub:Ljava/lang/String;
       5: aload_0
       6: invokevirtual #3                  // Method getThis:()Lorg/apache/dubbo/config/bootstrap/builders/AbstractBuilder;
       9: checkcast     #4                  // class org/apache/dubbo/config/bootstrap/builders/AbstractInterfaceBuilder
      12: areturn

  public B stub(java.lang.Boolean);
    Code:
       0: aload_1
       1: ifnull        15
       4: aload_0
       5: aload_1
       6: invokevirtual #5                  // Method java/lang/Boolean.toString:()Ljava/lang/String;
       9: putfield      #6                  // Field stub:Ljava/lang/String;
      12: goto          20
      15: aload_0
      16: aconst_null
      17: putfield      #6                  // Field stub:Ljava/lang/String;
      20: aload_0
      21: invokevirtual #3                  // Method getThis:()Lorg/apache/dubbo/config/bootstrap/builders/AbstractBuilder;
      24: checkcast     #4                  // class org/apache/dubbo/config/bootstrap/builders/AbstractInterfaceBuilder
      27: areturn

  public B monitor(org.apache.dubbo.config.MonitorConfig);
    Code:
       0: aload_0
       1: aload_1
       2: putfield      #7                  // Field monitor:Lorg/apache/dubbo/config/MonitorConfig;
       5: aload_0
       6: invokevirtual #3                  // Method getThis:()Lorg/apache/dubbo/config/bootstrap/builders/AbstractBuilder;
       9: checkcast     #4                  // class org/apache/dubbo/config/bootstrap/builders/AbstractInterfaceBuilder
      12: areturn

  public B monitor(java.lang.String);
    Code:
       0: aload_0
       1: new           #8                  // class org/apache/dubbo/config/MonitorConfig
       4: dup
       5: aload_1
       6: invokespecial #9                  // Method org/apache/dubbo/config/MonitorConfig."<init>":(Ljava/lang/String;)V
       9: putfield      #7                  // Field monitor:Lorg/apache/dubbo/config/MonitorConfig;
      12: aload_0
      13: invokevirtual #3                  // Method getThis:()Lorg/apache/dubbo/config/bootstrap/builders/AbstractBuilder;
      16: checkcast     #4                  // class org/apache/dubbo/config/bootstrap/builders/AbstractInterfaceBuilder
      19: areturn

  public B proxy(java.lang.String);
    Code:
       0: aload_0
       1: aload_1
       2: putfield      #10                 // Field proxy:Ljava/lang/String;
       5: aload_0
       6: invokevirtual #3                  // Method getThis:()Lorg/apache/dubbo/config/bootstrap/builders/AbstractBuilder;
       9: checkcast     #4                  // class org/apache/dubbo/config/bootstrap/builders/AbstractInterfaceBuilder
      12: areturn

  public B cluster(java.lang.String);
    Code:
       0: aload_0
       1: aload_1
       2: putfield      #11                 // Field cluster:Ljava/lang/String;
       5: aload_0
       6: invokevirtual #3                  // Method getThis:()Lorg/apache/dubbo/config/bootstrap/builders/AbstractBuilder;
       9: checkcast     #4                  // class org/apache/dubbo/config/bootstrap/builders/AbstractInterfaceBuilder
      12: areturn

  public B filter(java.lang.String);
    Code:
       0: aload_0
       1: aload_1
       2: putfield      #12                 // Field filter:Ljava/lang/String;
       5: aload_0
       6: invokevirtual #3                  // Method getThis:()Lorg/apache/dubbo/config/bootstrap/builders/AbstractBuilder;
       9: checkcast     #4                  // class org/apache/dubbo/config/bootstrap/builders/AbstractInterfaceBuilder
      12: areturn

  public B listener(java.lang.String);
    Code:
       0: aload_0
       1: aload_1
       2: putfield      #13                 // Field listener:Ljava/lang/String;
       5: aload_0
       6: invokevirtual #3                  // Method getThis:()Lorg/apache/dubbo/config/bootstrap/builders/AbstractBuilder;
       9: checkcast     #4                  // class org/apache/dubbo/config/bootstrap/builders/AbstractInterfaceBuilder
      12: areturn

  public B owner(java.lang.String);
    Code:
       0: aload_0
       1: aload_1
       2: putfield      #14                 // Field owner:Ljava/lang/String;
       5: aload_0
       6: invokevirtual #3                  // Method getThis:()Lorg/apache/dubbo/config/bootstrap/builders/AbstractBuilder;
       9: checkcast     #4                  // class org/apache/dubbo/config/bootstrap/builders/AbstractInterfaceBuilder
      12: areturn

  public B connections(java.lang.Integer);
    Code:
       0: aload_0
       1: aload_1
       2: putfield      #15                 // Field connections:Ljava/lang/Integer;
       5: aload_0
       6: invokevirtual #3                  // Method getThis:()Lorg/apache/dubbo/config/bootstrap/builders/AbstractBuilder;
       9: checkcast     #4                  // class org/apache/dubbo/config/bootstrap/builders/AbstractInterfaceBuilder
      12: areturn

  public B layer(java.lang.String);
    Code:
       0: aload_0
       1: aload_1
       2: putfield      #16                 // Field layer:Ljava/lang/String;
       5: aload_0
       6: invokevirtual #3                  // Method getThis:()Lorg/apache/dubbo/config/bootstrap/builders/AbstractBuilder;
       9: checkcast     #4                  // class org/apache/dubbo/config/bootstrap/builders/AbstractInterfaceBuilder
      12: areturn

  public B application(org.apache.dubbo.config.ApplicationConfig);
    Code:
       0: aload_0
       1: aload_1
       2: putfield      #17                 // Field application:Lorg/apache/dubbo/config/ApplicationConfig;
       5: aload_0
       6: invokevirtual #3                  // Method getThis:()Lorg/apache/dubbo/config/bootstrap/builders/AbstractBuilder;
       9: checkcast     #4                  // class org/apache/dubbo/config/bootstrap/builders/AbstractInterfaceBuilder
      12: areturn

  public B module(org.apache.dubbo.config.ModuleConfig);
    Code:
       0: aload_0
       1: aload_1
       2: putfield      #18                 // Field module:Lorg/apache/dubbo/config/ModuleConfig;
       5: aload_0
       6: invokevirtual #3                  // Method getThis:()Lorg/apache/dubbo/config/bootstrap/builders/AbstractBuilder;
       9: checkcast     #4                  // class org/apache/dubbo/config/bootstrap/builders/AbstractInterfaceBuilder
      12: areturn

  public B addRegistries(java.util.List<org.apache.dubbo.config.RegistryConfig>);
    Code:
       0: aload_0
       1: getfield      #19                 // Field registries:Ljava/util/List;
       4: ifnonnull     18
       7: aload_0
       8: new           #20                 // class java/util/ArrayList
      11: dup
      12: invokespecial #21                 // Method java/util/ArrayList."<init>":()V
      15: putfield      #19                 // Field registries:Ljava/util/List;
      18: aload_0
      19: getfield      #19                 // Field registries:Ljava/util/List;
      22: aload_1
      23: invokeinterface #22,  2           // InterfaceMethod java/util/List.addAll:(Ljava/util/Collection;)Z
      28: pop
      29: aload_0
      30: invokevirtual #3                  // Method getThis:()Lorg/apache/dubbo/config/bootstrap/builders/AbstractBuilder;
      33: checkcast     #4                  // class org/apache/dubbo/config/bootstrap/builders/AbstractInterfaceBuilder
      36: areturn

  public B addRegistry(org.apache.dubbo.config.RegistryConfig);
    Code:
       0: aload_0
       1: getfield      #19                 // Field registries:Ljava/util/List;
       4: ifnonnull     18
       7: aload_0
       8: new           #20                 // class java/util/ArrayList
      11: dup
      12: invokespecial #21                 // Method java/util/ArrayList."<init>":()V
      15: putfield      #19                 // Field registries:Ljava/util/List;
      18: aload_0
      19: getfield      #19                 // Field registries:Ljava/util/List;
      22: aload_1
      23: invokeinterface #23,  2           // InterfaceMethod java/util/List.add:(Ljava/lang/Object;)Z
      28: pop
      29: aload_0
      30: invokevirtual #3                  // Method getThis:()Lorg/apache/dubbo/config/bootstrap/builders/AbstractBuilder;
      33: checkcast     #4                  // class org/apache/dubbo/config/bootstrap/builders/AbstractInterfaceBuilder
      36: areturn

  public B registryIds(java.lang.String);
    Code:
       0: aload_0
       1: aload_1
       2: putfield      #24                 // Field registryIds:Ljava/lang/String;
       5: aload_0
       6: invokevirtual #3                  // Method getThis:()Lorg/apache/dubbo/config/bootstrap/builders/AbstractBuilder;
       9: checkcast     #4                  // class org/apache/dubbo/config/bootstrap/builders/AbstractInterfaceBuilder
      12: areturn

  public B onconnect(java.lang.String);
    Code:
       0: aload_0
       1: aload_1
       2: putfield      #25                 // Field onconnect:Ljava/lang/String;
       5: aload_0
       6: invokevirtual #3                  // Method getThis:()Lorg/apache/dubbo/config/bootstrap/builders/AbstractBuilder;
       9: checkcast     #4                  // class org/apache/dubbo/config/bootstrap/builders/AbstractInterfaceBuilder
      12: areturn

  public B ondisconnect(java.lang.String);
    Code:
       0: aload_0
       1: aload_1
       2: putfield      #26                 // Field ondisconnect:Ljava/lang/String;
       5: aload_0
       6: invokevirtual #3                  // Method getThis:()Lorg/apache/dubbo/config/bootstrap/builders/AbstractBuilder;
       9: checkcast     #4                  // class org/apache/dubbo/config/bootstrap/builders/AbstractInterfaceBuilder
      12: areturn

  public B metadataReportConfig(org.apache.dubbo.config.MetadataReportConfig);
    Code:
       0: aload_0
       1: aload_1
       2: putfield      #27                 // Field metadataReportConfig:Lorg/apache/dubbo/config/MetadataReportConfig;
       5: aload_0
       6: invokevirtual #3                  // Method getThis:()Lorg/apache/dubbo/config/bootstrap/builders/AbstractBuilder;
       9: checkcast     #4                  // class org/apache/dubbo/config/bootstrap/builders/AbstractInterfaceBuilder
      12: areturn

  public B configCenter(org.apache.dubbo.config.ConfigCenterConfig);
    Code:
       0: aload_0
       1: aload_1
       2: putfield      #28                 // Field configCenter:Lorg/apache/dubbo/config/ConfigCenterConfig;
       5: aload_0
       6: invokevirtual #3                  // Method getThis:()Lorg/apache/dubbo/config/bootstrap/builders/AbstractBuilder;
       9: checkcast     #4                  // class org/apache/dubbo/config/bootstrap/builders/AbstractInterfaceBuilder
      12: areturn

  public B callbacks(java.lang.Integer);
    Code:
       0: aload_0
       1: aload_1
       2: putfield      #29                 // Field callbacks:Ljava/lang/Integer;
       5: aload_0
       6: invokevirtual #3                  // Method getThis:()Lorg/apache/dubbo/config/bootstrap/builders/AbstractBuilder;
       9: checkcast     #4                  // class org/apache/dubbo/config/bootstrap/builders/AbstractInterfaceBuilder
      12: areturn

  public B scope(java.lang.String);
    Code:
       0: aload_0
       1: aload_1
       2: putfield      #30                 // Field scope:Ljava/lang/String;
       5: aload_0
       6: invokevirtual #3                  // Method getThis:()Lorg/apache/dubbo/config/bootstrap/builders/AbstractBuilder;
       9: checkcast     #4                  // class org/apache/dubbo/config/bootstrap/builders/AbstractInterfaceBuilder
      12: areturn

  public B tag(java.lang.String);
    Code:
       0: aload_0
       1: aload_1
       2: putfield      #31                 // Field tag:Ljava/lang/String;
       5: aload_0
       6: invokevirtual #3                  // Method getThis:()Lorg/apache/dubbo/config/bootstrap/builders/AbstractBuilder;
       9: checkcast     #4                  // class org/apache/dubbo/config/bootstrap/builders/AbstractInterfaceBuilder
      12: areturn

  public void build(T);
    Code:
       0: aload_0
       1: aload_1
       2: invokespecial #32                 // Method org/apache/dubbo/config/bootstrap/builders/AbstractMethodBuilder.build:(Lorg/apache/dubbo/config/AbstractMethodConfig;)V
       5: aload_0
       6: getfield      #2                  // Field local:Ljava/lang/String;
       9: invokestatic  #33                 // Method org/apache/dubbo/common/utils/StringUtils.isEmpty:(Ljava/lang/String;)Z
      12: ifne          23
      15: aload_1
      16: aload_0
      17: getfield      #2                  // Field local:Ljava/lang/String;
      20: invokevirtual #34                 // Method org/apache/dubbo/config/AbstractInterfaceConfig.setLocal:(Ljava/lang/String;)V
      23: aload_0
      24: getfield      #6                  // Field stub:Ljava/lang/String;
      27: invokestatic  #33                 // Method org/apache/dubbo/common/utils/StringUtils.isEmpty:(Ljava/lang/String;)Z
      30: ifne          41
      33: aload_1
      34: aload_0
      35: getfield      #6                  // Field stub:Ljava/lang/String;
      38: invokevirtual #35                 // Method org/apache/dubbo/config/AbstractInterfaceConfig.setStub:(Ljava/lang/String;)V
      41: aload_0
      42: getfield      #7                  // Field monitor:Lorg/apache/dubbo/config/MonitorConfig;
      45: ifnull        56
      48: aload_1
      49: aload_0
      50: getfield      #7                  // Field monitor:Lorg/apache/dubbo/config/MonitorConfig;
      53: invokevirtual #36                 // Method org/apache/dubbo/config/AbstractInterfaceConfig.setMonitor:(Lorg/apache/dubbo/config/MonitorConfig;)V
      56: aload_0
      57: getfield      #10                 // Field proxy:Ljava/lang/String;
      60: invokestatic  #33                 // Method org/apache/dubbo/common/utils/StringUtils.isEmpty:(Ljava/lang/String;)Z
      63: ifne          74
      66: aload_1
      67: aload_0
      68: getfield      #10                 // Field proxy:Ljava/lang/String;
      71: invokevirtual #37                 // Method org/apache/dubbo/config/AbstractInterfaceConfig.setProxy:(Ljava/lang/String;)V
      74: aload_0
      75: getfield      #11                 // Field cluster:Ljava/lang/String;
      78: invokestatic  #33                 // Method org/apache/dubbo/common/utils/StringUtils.isEmpty:(Ljava/lang/String;)Z
      81: ifne          92
      84: aload_1
      85: aload_0
      86: getfield      #11                 // Field cluster:Ljava/lang/String;
      89: invokevirtual #38                 // Method org/apache/dubbo/config/AbstractInterfaceConfig.setCluster:(Ljava/lang/String;)V
      92: aload_0
      93: getfield      #12                 // Field filter:Ljava/lang/String;
      96: invokestatic  #33                 // Method org/apache/dubbo/common/utils/StringUtils.isEmpty:(Ljava/lang/String;)Z
      99: ifne          110
     102: aload_1
     103: aload_0
     104: getfield      #12                 // Field filter:Ljava/lang/String;
     107: invokevirtual #39                 // Method org/apache/dubbo/config/AbstractInterfaceConfig.setFilter:(Ljava/lang/String;)V
     110: aload_0
     111: getfield      #13                 // Field listener:Ljava/lang/String;
     114: invokestatic  #33                 // Method org/apache/dubbo/common/utils/StringUtils.isEmpty:(Ljava/lang/String;)Z
     117: ifne          128
     120: aload_1
     121: aload_0
     122: getfield      #13                 // Field listener:Ljava/lang/String;
     125: invokevirtual #40                 // Method org/apache/dubbo/config/AbstractInterfaceConfig.setListener:(Ljava/lang/String;)V
     128: aload_0
     129: getfield      #14                 // Field owner:Ljava/lang/String;
     132: invokestatic  #33                 // Method org/apache/dubbo/common/utils/StringUtils.isEmpty:(Ljava/lang/String;)Z
     135: ifne          146
     138: aload_1
     139: aload_0
     140: getfield      #14                 // Field owner:Ljava/lang/String;
     143: invokevirtual #41                 // Method org/apache/dubbo/config/AbstractInterfaceConfig.setOwner:(Ljava/lang/String;)V
     146: aload_0
     147: getfield      #15                 // Field connections:Ljava/lang/Integer;
     150: ifnull        161
     153: aload_1
     154: aload_0
     155: getfield      #15                 // Field connections:Ljava/lang/Integer;
     158: invokevirtual #42                 // Method org/apache/dubbo/config/AbstractInterfaceConfig.setConnections:(Ljava/lang/Integer;)V
     161: aload_0
     162: getfield      #16                 // Field layer:Ljava/lang/String;
     165: invokestatic  #33                 // Method org/apache/dubbo/common/utils/StringUtils.isEmpty:(Ljava/lang/String;)Z
     168: ifne          179
     171: aload_1
     172: aload_0
     173: getfield      #16                 // Field layer:Ljava/lang/String;
     176: invokevirtual #43                 // Method org/apache/dubbo/config/AbstractInterfaceConfig.setLayer:(Ljava/lang/String;)V
     179: aload_0
     180: getfield      #17                 // Field application:Lorg/apache/dubbo/config/ApplicationConfig;
     183: ifnull        194
     186: aload_1
     187: aload_0
     188: getfield      #17                 // Field application:Lorg/apache/dubbo/config/ApplicationConfig;
     191: invokevirtual #44                 // Method org/apache/dubbo/config/AbstractInterfaceConfig.setApplication:(Lorg/apache/dubbo/config/ApplicationConfig;)V
     194: aload_0
     195: getfield      #18                 // Field module:Lorg/apache/dubbo/config/ModuleConfig;
     198: ifnull        209
     201: aload_1
     202: aload_0
     203: getfield      #18                 // Field module:Lorg/apache/dubbo/config/ModuleConfig;
     206: invokevirtual #45                 // Method org/apache/dubbo/config/AbstractInterfaceConfig.setModule:(Lorg/apache/dubbo/config/ModuleConfig;)V
     209: aload_0
     210: getfield      #19                 // Field registries:Ljava/util/List;
     213: ifnull        224
     216: aload_1
     217: aload_0
     218: getfield      #19                 // Field registries:Ljava/util/List;
     221: invokevirtual #46                 // Method org/apache/dubbo/config/AbstractInterfaceConfig.setRegistries:(Ljava/util/List;)V
     224: aload_0
     225: getfield      #24                 // Field registryIds:Ljava/lang/String;
     228: invokestatic  #33                 // Method org/apache/dubbo/common/utils/StringUtils.isEmpty:(Ljava/lang/String;)Z
     231: ifne          242
     234: aload_1
     235: aload_0
     236: getfield      #24                 // Field registryIds:Ljava/lang/String;
     239: invokevirtual #47                 // Method org/apache/dubbo/config/AbstractInterfaceConfig.setRegistryIds:(Ljava/lang/String;)V
     242: aload_0
     243: getfield      #25                 // Field onconnect:Ljava/lang/String;
     246: invokestatic  #33                 // Method org/apache/dubbo/common/utils/StringUtils.isEmpty:(Ljava/lang/String;)Z
     249: ifne          260
     252: aload_1
     253: aload_0
     254: getfield      #25                 // Field onconnect:Ljava/lang/String;
     257: invokevirtual #48                 // Method org/apache/dubbo/config/AbstractInterfaceConfig.setOnconnect:(Ljava/lang/String;)V
     260: aload_0
     261: getfield      #26                 // Field ondisconnect:Ljava/lang/String;
     264: invokestatic  #33                 // Method org/apache/dubbo/common/utils/StringUtils.isEmpty:(Ljava/lang/String;)Z
     267: ifne          278
     270: aload_1
     271: aload_0
     272: getfield      #26                 // Field ondisconnect:Ljava/lang/String;
     275: invokevirtual #49                 // Method org/apache/dubbo/config/AbstractInterfaceConfig.setOndisconnect:(Ljava/lang/String;)V
     278: aload_0
     279: getfield      #27                 // Field metadataReportConfig:Lorg/apache/dubbo/config/MetadataReportConfig;
     282: ifnull        293
     285: aload_1
     286: aload_0
     287: getfield      #27                 // Field metadataReportConfig:Lorg/apache/dubbo/config/MetadataReportConfig;
     290: invokevirtual #50                 // Method org/apache/dubbo/config/AbstractInterfaceConfig.setMetadataReportConfig:(Lorg/apache/dubbo/config/MetadataReportConfig;)V
     293: aload_0
     294: getfield      #28                 // Field configCenter:Lorg/apache/dubbo/config/ConfigCenterConfig;
     297: ifnull        308
     300: aload_1
     301: aload_0
     302: getfield      #28                 // Field configCenter:Lorg/apache/dubbo/config/ConfigCenterConfig;
     305: invokevirtual #51                 // Method org/apache/dubbo/config/AbstractInterfaceConfig.setConfigCenter:(Lorg/apache/dubbo/config/ConfigCenterConfig;)V
     308: aload_0
     309: getfield      #29                 // Field callbacks:Ljava/lang/Integer;
     312: ifnull        323
     315: aload_1
     316: aload_0
     317: getfield      #29                 // Field callbacks:Ljava/lang/Integer;
     320: invokevirtual #52                 // Method org/apache/dubbo/config/AbstractInterfaceConfig.setCallbacks:(Ljava/lang/Integer;)V
     323: aload_0
     324: getfield      #30                 // Field scope:Ljava/lang/String;
     327: invokestatic  #33                 // Method org/apache/dubbo/common/utils/StringUtils.isEmpty:(Ljava/lang/String;)Z
     330: ifne          341
     333: aload_1
     334: aload_0
     335: getfield      #30                 // Field scope:Ljava/lang/String;
     338: invokevirtual #53                 // Method org/apache/dubbo/config/AbstractInterfaceConfig.setScope:(Ljava/lang/String;)V
     341: aload_0
     342: getfield      #31                 // Field tag:Ljava/lang/String;
     345: invokestatic  #54                 // Method org/apache/dubbo/common/utils/StringUtils.isNotEmpty:(Ljava/lang/String;)Z
     348: ifeq          359
     351: aload_1
     352: aload_0
     353: getfield      #31                 // Field tag:Ljava/lang/String;
     356: invokevirtual #55                 // Method org/apache/dubbo/config/AbstractInterfaceConfig.setTag:(Ljava/lang/String;)V
     359: return

  public void build(org.apache.dubbo.config.AbstractMethodConfig);
    Code:
       0: aload_0
       1: aload_1
       2: checkcast     #56                 // class org/apache/dubbo/config/AbstractInterfaceConfig
       5: invokevirtual #57                 // Method build:(Lorg/apache/dubbo/config/AbstractInterfaceConfig;)V
       8: return

  public void build(org.apache.dubbo.config.AbstractConfig);
    Code:
       0: aload_0
       1: aload_1
       2: checkcast     #56                 // class org/apache/dubbo/config/AbstractInterfaceConfig
       5: invokevirtual #57                 // Method build:(Lorg/apache/dubbo/config/AbstractInterfaceConfig;)V
       8: return
}
