Compiled from "AbstractMethodBuilder.java"
public abstract class org.apache.dubbo.config.bootstrap.builders.AbstractMethodBuilder<T extends org.apache.dubbo.config.AbstractMethodConfig, B extends org.apache.dubbo.config.bootstrap.builders.AbstractMethodBuilder<T, B>> extends org.apache.dubbo.config.bootstrap.builders.AbstractBuilder<T, B> {
  protected java.lang.Integer timeout;

  protected java.lang.Integer retries;

  protected java.lang.Integer actives;

  protected java.lang.String loadbalance;

  protected java.lang.Boolean async;

  protected java.lang.Boolean sent;

  protected java.lang.String mock;

  protected java.lang.String merger;

  protected java.lang.String cache;

  protected java.lang.String validation;

  protected java.util.Map<java.lang.String, java.lang.String> parameters;

  protected java.lang.Integer forks;

  public org.apache.dubbo.config.bootstrap.builders.AbstractMethodBuilder();
    Code:
       0: aload_0
       1: invokespecial #1                  // Method org/apache/dubbo/config/bootstrap/builders/AbstractBuilder."<init>":()V
       4: return

  public B timeout(java.lang.Integer);
    Code:
       0: aload_0
       1: aload_1
       2: putfield      #2                  // Field timeout:Ljava/lang/Integer;
       5: aload_0
       6: invokevirtual #3                  // Method getThis:()Lorg/apache/dubbo/config/bootstrap/builders/AbstractBuilder;
       9: checkcast     #4                  // class org/apache/dubbo/config/bootstrap/builders/AbstractMethodBuilder
      12: areturn

  public B retries(java.lang.Integer);
    Code:
       0: aload_0
       1: aload_1
       2: putfield      #5                  // Field retries:Ljava/lang/Integer;
       5: aload_0
       6: invokevirtual #3                  // Method getThis:()Lorg/apache/dubbo/config/bootstrap/builders/AbstractBuilder;
       9: checkcast     #4                  // class org/apache/dubbo/config/bootstrap/builders/AbstractMethodBuilder
      12: areturn

  public B actives(java.lang.Integer);
    Code:
       0: aload_0
       1: aload_1
       2: putfield      #6                  // Field actives:Ljava/lang/Integer;
       5: aload_0
       6: invokevirtual #3                  // Method getThis:()Lorg/apache/dubbo/config/bootstrap/builders/AbstractBuilder;
       9: checkcast     #4                  // class org/apache/dubbo/config/bootstrap/builders/AbstractMethodBuilder
      12: areturn

  public B loadbalance(java.lang.String);
    Code:
       0: aload_0
       1: aload_1
       2: putfield      #7                  // Field loadbalance:Ljava/lang/String;
       5: aload_0
       6: invokevirtual #3                  // Method getThis:()Lorg/apache/dubbo/config/bootstrap/builders/AbstractBuilder;
       9: checkcast     #4                  // class org/apache/dubbo/config/bootstrap/builders/AbstractMethodBuilder
      12: areturn

  public B async(java.lang.Boolean);
    Code:
       0: aload_0
       1: aload_1
       2: putfield      #8                  // Field async:Ljava/lang/Boolean;
       5: aload_0
       6: invokevirtual #3                  // Method getThis:()Lorg/apache/dubbo/config/bootstrap/builders/AbstractBuilder;
       9: checkcast     #4                  // class org/apache/dubbo/config/bootstrap/builders/AbstractMethodBuilder
      12: areturn

  public B sent(java.lang.Boolean);
    Code:
       0: aload_0
       1: aload_1
       2: putfield      #9                  // Field sent:Ljava/lang/Boolean;
       5: aload_0
       6: invokevirtual #3                  // Method getThis:()Lorg/apache/dubbo/config/bootstrap/builders/AbstractBuilder;
       9: checkcast     #4                  // class org/apache/dubbo/config/bootstrap/builders/AbstractMethodBuilder
      12: areturn

  public B mock(java.lang.String);
    Code:
       0: aload_0
       1: aload_1
       2: putfield      #10                 // Field mock:Ljava/lang/String;
       5: aload_0
       6: invokevirtual #3                  // Method getThis:()Lorg/apache/dubbo/config/bootstrap/builders/AbstractBuilder;
       9: checkcast     #4                  // class org/apache/dubbo/config/bootstrap/builders/AbstractMethodBuilder
      12: areturn

  public B mock(java.lang.Boolean);
    Code:
       0: aload_1
       1: ifnull        15
       4: aload_0
       5: aload_1
       6: invokevirtual #11                 // Method java/lang/Boolean.toString:()Ljava/lang/String;
       9: putfield      #10                 // Field mock:Ljava/lang/String;
      12: goto          20
      15: aload_0
      16: aconst_null
      17: putfield      #10                 // Field mock:Ljava/lang/String;
      20: aload_0
      21: invokevirtual #3                  // Method getThis:()Lorg/apache/dubbo/config/bootstrap/builders/AbstractBuilder;
      24: checkcast     #4                  // class org/apache/dubbo/config/bootstrap/builders/AbstractMethodBuilder
      27: areturn

  public B merger(java.lang.String);
    Code:
       0: aload_0
       1: aload_1
       2: putfield      #12                 // Field merger:Ljava/lang/String;
       5: aload_0
       6: invokevirtual #3                  // Method getThis:()Lorg/apache/dubbo/config/bootstrap/builders/AbstractBuilder;
       9: checkcast     #4                  // class org/apache/dubbo/config/bootstrap/builders/AbstractMethodBuilder
      12: areturn

  public B cache(java.lang.String);
    Code:
       0: aload_0
       1: aload_1
       2: putfield      #13                 // Field cache:Ljava/lang/String;
       5: aload_0
       6: invokevirtual #3                  // Method getThis:()Lorg/apache/dubbo/config/bootstrap/builders/AbstractBuilder;
       9: checkcast     #4                  // class org/apache/dubbo/config/bootstrap/builders/AbstractMethodBuilder
      12: areturn

  public B validation(java.lang.String);
    Code:
       0: aload_0
       1: aload_1
       2: putfield      #14                 // Field validation:Ljava/lang/String;
       5: aload_0
       6: invokevirtual #3                  // Method getThis:()Lorg/apache/dubbo/config/bootstrap/builders/AbstractBuilder;
       9: checkcast     #4                  // class org/apache/dubbo/config/bootstrap/builders/AbstractMethodBuilder
      12: areturn

  public B appendParameters(java.util.Map<java.lang.String, java.lang.String>);
    Code:
       0: aload_0
       1: aload_0
       2: getfield      #15                 // Field parameters:Ljava/util/Map;
       5: aload_1
       6: invokestatic  #16                 // Method appendParameters:(Ljava/util/Map;Ljava/util/Map;)Ljava/util/Map;
       9: putfield      #15                 // Field parameters:Ljava/util/Map;
      12: aload_0
      13: invokevirtual #3                  // Method getThis:()Lorg/apache/dubbo/config/bootstrap/builders/AbstractBuilder;
      16: checkcast     #4                  // class org/apache/dubbo/config/bootstrap/builders/AbstractMethodBuilder
      19: areturn

  public B appendParameter(java.lang.String, java.lang.String);
    Code:
       0: aload_0
       1: aload_0
       2: getfield      #15                 // Field parameters:Ljava/util/Map;
       5: aload_1
       6: aload_2
       7: invokestatic  #17                 // Method appendParameter:(Ljava/util/Map;Ljava/lang/String;Ljava/lang/String;)Ljava/util/Map;
      10: putfield      #15                 // Field parameters:Ljava/util/Map;
      13: aload_0
      14: invokevirtual #3                  // Method getThis:()Lorg/apache/dubbo/config/bootstrap/builders/AbstractBuilder;
      17: checkcast     #4                  // class org/apache/dubbo/config/bootstrap/builders/AbstractMethodBuilder
      20: areturn

  public B forks(java.lang.Integer);
    Code:
       0: aload_0
       1: aload_1
       2: putfield      #18                 // Field forks:Ljava/lang/Integer;
       5: aload_0
       6: invokevirtual #3                  // Method getThis:()Lorg/apache/dubbo/config/bootstrap/builders/AbstractBuilder;
       9: checkcast     #4                  // class org/apache/dubbo/config/bootstrap/builders/AbstractMethodBuilder
      12: areturn

  public void build(T);
    Code:
       0: aload_0
       1: aload_1
       2: invokespecial #19                 // Method org/apache/dubbo/config/bootstrap/builders/AbstractBuilder.build:(Lorg/apache/dubbo/config/AbstractConfig;)V
       5: aload_0
       6: getfield      #6                  // Field actives:Ljava/lang/Integer;
       9: ifnull        20
      12: aload_1
      13: aload_0
      14: getfield      #6                  // Field actives:Ljava/lang/Integer;
      17: invokevirtual #20                 // Method org/apache/dubbo/config/AbstractMethodConfig.setActives:(Ljava/lang/Integer;)V
      20: aload_0
      21: getfield      #8                  // Field async:Ljava/lang/Boolean;
      24: ifnull        35
      27: aload_1
      28: aload_0
      29: getfield      #8                  // Field async:Ljava/lang/Boolean;
      32: invokevirtual #21                 // Method org/apache/dubbo/config/AbstractMethodConfig.setAsync:(Ljava/lang/Boolean;)V
      35: aload_0
      36: getfield      #13                 // Field cache:Ljava/lang/String;
      39: invokestatic  #22                 // Method org/apache/dubbo/common/utils/StringUtils.isEmpty:(Ljava/lang/String;)Z
      42: ifne          53
      45: aload_1
      46: aload_0
      47: getfield      #13                 // Field cache:Ljava/lang/String;
      50: invokevirtual #23                 // Method org/apache/dubbo/config/AbstractMethodConfig.setCache:(Ljava/lang/String;)V
      53: aload_0
      54: getfield      #18                 // Field forks:Ljava/lang/Integer;
      57: ifnull        68
      60: aload_1
      61: aload_0
      62: getfield      #18                 // Field forks:Ljava/lang/Integer;
      65: invokevirtual #24                 // Method org/apache/dubbo/config/AbstractMethodConfig.setForks:(Ljava/lang/Integer;)V
      68: aload_0
      69: getfield      #7                  // Field loadbalance:Ljava/lang/String;
      72: invokestatic  #22                 // Method org/apache/dubbo/common/utils/StringUtils.isEmpty:(Ljava/lang/String;)Z
      75: ifne          86
      78: aload_1
      79: aload_0
      80: getfield      #7                  // Field loadbalance:Ljava/lang/String;
      83: invokevirtual #25                 // Method org/apache/dubbo/config/AbstractMethodConfig.setLoadbalance:(Ljava/lang/String;)V
      86: aload_0
      87: getfield      #12                 // Field merger:Ljava/lang/String;
      90: invokestatic  #22                 // Method org/apache/dubbo/common/utils/StringUtils.isEmpty:(Ljava/lang/String;)Z
      93: ifne          104
      96: aload_1
      97: aload_0
      98: getfield      #12                 // Field merger:Ljava/lang/String;
     101: invokevirtual #26                 // Method org/apache/dubbo/config/AbstractMethodConfig.setMerger:(Ljava/lang/String;)V
     104: aload_0
     105: getfield      #10                 // Field mock:Ljava/lang/String;
     108: invokestatic  #22                 // Method org/apache/dubbo/common/utils/StringUtils.isEmpty:(Ljava/lang/String;)Z
     111: ifne          122
     114: aload_1
     115: aload_0
     116: getfield      #10                 // Field mock:Ljava/lang/String;
     119: invokevirtual #27                 // Method org/apache/dubbo/config/AbstractMethodConfig.setMock:(Ljava/lang/String;)V
     122: aload_0
     123: getfield      #5                  // Field retries:Ljava/lang/Integer;
     126: ifnull        137
     129: aload_1
     130: aload_0
     131: getfield      #5                  // Field retries:Ljava/lang/Integer;
     134: invokevirtual #28                 // Method org/apache/dubbo/config/AbstractMethodConfig.setRetries:(Ljava/lang/Integer;)V
     137: aload_0
     138: getfield      #9                  // Field sent:Ljava/lang/Boolean;
     141: ifnull        152
     144: aload_1
     145: aload_0
     146: getfield      #9                  // Field sent:Ljava/lang/Boolean;
     149: invokevirtual #29                 // Method org/apache/dubbo/config/AbstractMethodConfig.setSent:(Ljava/lang/Boolean;)V
     152: aload_0
     153: getfield      #2                  // Field timeout:Ljava/lang/Integer;
     156: ifnull        167
     159: aload_1
     160: aload_0
     161: getfield      #2                  // Field timeout:Ljava/lang/Integer;
     164: invokevirtual #30                 // Method org/apache/dubbo/config/AbstractMethodConfig.setTimeout:(Ljava/lang/Integer;)V
     167: aload_0
     168: getfield      #14                 // Field validation:Ljava/lang/String;
     171: invokestatic  #22                 // Method org/apache/dubbo/common/utils/StringUtils.isEmpty:(Ljava/lang/String;)Z
     174: ifne          185
     177: aload_1
     178: aload_0
     179: getfield      #14                 // Field validation:Ljava/lang/String;
     182: invokevirtual #31                 // Method org/apache/dubbo/config/AbstractMethodConfig.setValidation:(Ljava/lang/String;)V
     185: aload_0
     186: getfield      #15                 // Field parameters:Ljava/util/Map;
     189: ifnull        200
     192: aload_1
     193: aload_0
     194: getfield      #15                 // Field parameters:Ljava/util/Map;
     197: invokevirtual #32                 // Method org/apache/dubbo/config/AbstractMethodConfig.setParameters:(Ljava/util/Map;)V
     200: return

  public void build(org.apache.dubbo.config.AbstractConfig);
    Code:
       0: aload_0
       1: aload_1
       2: checkcast     #33                 // class org/apache/dubbo/config/AbstractMethodConfig
       5: invokevirtual #34                 // Method build:(Lorg/apache/dubbo/config/AbstractMethodConfig;)V
       8: return
}
