Compiled from "ApplicationBuilder.java"
public class org.apache.dubbo.config.bootstrap.builders.ApplicationBuilder extends org.apache.dubbo.config.bootstrap.builders.AbstractBuilder<org.apache.dubbo.config.ApplicationConfig, org.apache.dubbo.config.bootstrap.builders.ApplicationBuilder> {
  private java.lang.String name;

  private java.lang.String metadata;

  private java.lang.String version;

  private java.lang.String owner;

  private java.lang.String organization;

  private java.lang.String architecture;

  private java.lang.String environment;

  private java.lang.String compiler;

  private java.lang.String logger;

  private java.util.List<org.apache.dubbo.config.RegistryConfig> registries;

  private java.lang.String registryIds;

  private org.apache.dubbo.config.MonitorConfig monitor;

  private java.lang.Boolean isDefault;

  private java.lang.String dumpDirectory;

  private java.lang.Boolean qosEnable;

  private java.lang.Integer qosPort;

  private java.lang.Boolean qosAcceptForeignIp;

  private java.util.Map<java.lang.String, java.lang.String> parameters;

  private java.lang.String shutwait;

  private java.lang.Integer metadataServicePort;

  private java.lang.String livenessProbe;

  private java.lang.String readinessProbe;

  private java.lang.String startupProbe;

  public org.apache.dubbo.config.bootstrap.builders.ApplicationBuilder();
    Code:
       0: aload_0
       1: invokespecial #2                  // Method org/apache/dubbo/config/bootstrap/builders/AbstractBuilder."<init>":()V
       4: aload_0
       5: ldc           #3                  // String product
       7: putfield      #4                  // Field environment:Ljava/lang/String;
      10: return

  public static org.apache.dubbo.config.bootstrap.builders.ApplicationBuilder newBuilder();
    Code:
       0: new           #5                  // class org/apache/dubbo/config/bootstrap/builders/ApplicationBuilder
       3: dup
       4: invokespecial #6                  // Method "<init>":()V
       7: areturn

  public org.apache.dubbo.config.bootstrap.builders.ApplicationBuilder name(java.lang.String);
    Code:
       0: aload_0
       1: aload_1
       2: putfield      #7                  // Field name:Ljava/lang/String;
       5: aload_0
       6: invokevirtual #8                  // Method getThis:()Lorg/apache/dubbo/config/bootstrap/builders/ApplicationBuilder;
       9: areturn

  public org.apache.dubbo.config.bootstrap.builders.ApplicationBuilder metadata(java.lang.String);
    Code:
       0: aload_0
       1: aload_1
       2: putfield      #9                  // Field metadata:Ljava/lang/String;
       5: aload_0
       6: invokevirtual #8                  // Method getThis:()Lorg/apache/dubbo/config/bootstrap/builders/ApplicationBuilder;
       9: areturn

  public org.apache.dubbo.config.bootstrap.builders.ApplicationBuilder version(java.lang.String);
    Code:
       0: aload_0
       1: aload_1
       2: putfield      #10                 // Field version:Ljava/lang/String;
       5: aload_0
       6: invokevirtual #8                  // Method getThis:()Lorg/apache/dubbo/config/bootstrap/builders/ApplicationBuilder;
       9: areturn

  public org.apache.dubbo.config.bootstrap.builders.ApplicationBuilder owner(java.lang.String);
    Code:
       0: aload_0
       1: aload_1
       2: putfield      #11                 // Field owner:Ljava/lang/String;
       5: aload_0
       6: invokevirtual #8                  // Method getThis:()Lorg/apache/dubbo/config/bootstrap/builders/ApplicationBuilder;
       9: areturn

  public org.apache.dubbo.config.bootstrap.builders.ApplicationBuilder organization(java.lang.String);
    Code:
       0: aload_0
       1: aload_1
       2: putfield      #12                 // Field organization:Ljava/lang/String;
       5: aload_0
       6: invokevirtual #8                  // Method getThis:()Lorg/apache/dubbo/config/bootstrap/builders/ApplicationBuilder;
       9: areturn

  public org.apache.dubbo.config.bootstrap.builders.ApplicationBuilder architecture(java.lang.String);
    Code:
       0: aload_0
       1: aload_1
       2: putfield      #13                 // Field architecture:Ljava/lang/String;
       5: aload_0
       6: invokevirtual #8                  // Method getThis:()Lorg/apache/dubbo/config/bootstrap/builders/ApplicationBuilder;
       9: areturn

  public org.apache.dubbo.config.bootstrap.builders.ApplicationBuilder environment(java.lang.String);
    Code:
       0: aload_0
       1: aload_1
       2: putfield      #4                  // Field environment:Ljava/lang/String;
       5: aload_0
       6: invokevirtual #8                  // Method getThis:()Lorg/apache/dubbo/config/bootstrap/builders/ApplicationBuilder;
       9: areturn

  public org.apache.dubbo.config.bootstrap.builders.ApplicationBuilder compiler(java.lang.String);
    Code:
       0: aload_0
       1: aload_1
       2: putfield      #14                 // Field compiler:Ljava/lang/String;
       5: aload_0
       6: invokevirtual #8                  // Method getThis:()Lorg/apache/dubbo/config/bootstrap/builders/ApplicationBuilder;
       9: areturn

  public org.apache.dubbo.config.bootstrap.builders.ApplicationBuilder logger(java.lang.String);
    Code:
       0: aload_0
       1: aload_1
       2: putfield      #15                 // Field logger:Ljava/lang/String;
       5: aload_0
       6: invokevirtual #8                  // Method getThis:()Lorg/apache/dubbo/config/bootstrap/builders/ApplicationBuilder;
       9: areturn

  public org.apache.dubbo.config.bootstrap.builders.ApplicationBuilder addRegistry(org.apache.dubbo.config.RegistryConfig);
    Code:
       0: aload_0
       1: getfield      #16                 // Field registries:Ljava/util/List;
       4: ifnonnull     18
       7: aload_0
       8: new           #17                 // class java/util/ArrayList
      11: dup
      12: invokespecial #18                 // Method java/util/ArrayList."<init>":()V
      15: putfield      #16                 // Field registries:Ljava/util/List;
      18: aload_0
      19: getfield      #16                 // Field registries:Ljava/util/List;
      22: aload_1
      23: invokeinterface #19,  2           // InterfaceMethod java/util/List.add:(Ljava/lang/Object;)Z
      28: pop
      29: aload_0
      30: invokevirtual #8                  // Method getThis:()Lorg/apache/dubbo/config/bootstrap/builders/ApplicationBuilder;
      33: areturn

  public org.apache.dubbo.config.bootstrap.builders.ApplicationBuilder addRegistries(java.util.List<? extends org.apache.dubbo.config.RegistryConfig>);
    Code:
       0: aload_0
       1: getfield      #16                 // Field registries:Ljava/util/List;
       4: ifnonnull     18
       7: aload_0
       8: new           #17                 // class java/util/ArrayList
      11: dup
      12: invokespecial #18                 // Method java/util/ArrayList."<init>":()V
      15: putfield      #16                 // Field registries:Ljava/util/List;
      18: aload_0
      19: getfield      #16                 // Field registries:Ljava/util/List;
      22: aload_1
      23: invokeinterface #20,  2           // InterfaceMethod java/util/List.addAll:(Ljava/util/Collection;)Z
      28: pop
      29: aload_0
      30: invokevirtual #8                  // Method getThis:()Lorg/apache/dubbo/config/bootstrap/builders/ApplicationBuilder;
      33: areturn

  public org.apache.dubbo.config.bootstrap.builders.ApplicationBuilder registryIds(java.lang.String);
    Code:
       0: aload_0
       1: aload_1
       2: putfield      #21                 // Field registryIds:Ljava/lang/String;
       5: aload_0
       6: invokevirtual #8                  // Method getThis:()Lorg/apache/dubbo/config/bootstrap/builders/ApplicationBuilder;
       9: areturn

  public org.apache.dubbo.config.bootstrap.builders.ApplicationBuilder monitor(org.apache.dubbo.config.MonitorConfig);
    Code:
       0: aload_0
       1: aload_1
       2: putfield      #22                 // Field monitor:Lorg/apache/dubbo/config/MonitorConfig;
       5: aload_0
       6: invokevirtual #8                  // Method getThis:()Lorg/apache/dubbo/config/bootstrap/builders/ApplicationBuilder;
       9: areturn

  public org.apache.dubbo.config.bootstrap.builders.ApplicationBuilder monitor(java.lang.String);
    Code:
       0: aload_0
       1: new           #23                 // class org/apache/dubbo/config/MonitorConfig
       4: dup
       5: aload_1
       6: invokespecial #24                 // Method org/apache/dubbo/config/MonitorConfig."<init>":(Ljava/lang/String;)V
       9: putfield      #22                 // Field monitor:Lorg/apache/dubbo/config/MonitorConfig;
      12: aload_0
      13: invokevirtual #8                  // Method getThis:()Lorg/apache/dubbo/config/bootstrap/builders/ApplicationBuilder;
      16: areturn

  public org.apache.dubbo.config.bootstrap.builders.ApplicationBuilder isDefault(java.lang.Boolean);
    Code:
       0: aload_0
       1: aload_1
       2: putfield      #25                 // Field isDefault:Ljava/lang/Boolean;
       5: aload_0
       6: invokevirtual #8                  // Method getThis:()Lorg/apache/dubbo/config/bootstrap/builders/ApplicationBuilder;
       9: areturn

  public org.apache.dubbo.config.bootstrap.builders.ApplicationBuilder dumpDirectory(java.lang.String);
    Code:
       0: aload_0
       1: aload_1
       2: putfield      #26                 // Field dumpDirectory:Ljava/lang/String;
       5: aload_0
       6: invokevirtual #8                  // Method getThis:()Lorg/apache/dubbo/config/bootstrap/builders/ApplicationBuilder;
       9: areturn

  public org.apache.dubbo.config.bootstrap.builders.ApplicationBuilder qosEnable(java.lang.Boolean);
    Code:
       0: aload_0
       1: aload_1
       2: putfield      #27                 // Field qosEnable:Ljava/lang/Boolean;
       5: aload_0
       6: invokevirtual #8                  // Method getThis:()Lorg/apache/dubbo/config/bootstrap/builders/ApplicationBuilder;
       9: areturn

  public org.apache.dubbo.config.bootstrap.builders.ApplicationBuilder qosPort(java.lang.Integer);
    Code:
       0: aload_0
       1: aload_1
       2: putfield      #28                 // Field qosPort:Ljava/lang/Integer;
       5: aload_0
       6: invokevirtual #8                  // Method getThis:()Lorg/apache/dubbo/config/bootstrap/builders/ApplicationBuilder;
       9: areturn

  public org.apache.dubbo.config.bootstrap.builders.ApplicationBuilder qosAcceptForeignIp(java.lang.Boolean);
    Code:
       0: aload_0
       1: aload_1
       2: putfield      #29                 // Field qosAcceptForeignIp:Ljava/lang/Boolean;
       5: aload_0
       6: invokevirtual #8                  // Method getThis:()Lorg/apache/dubbo/config/bootstrap/builders/ApplicationBuilder;
       9: areturn

  public org.apache.dubbo.config.bootstrap.builders.ApplicationBuilder shutwait(java.lang.String);
    Code:
       0: aload_0
       1: aload_1
       2: putfield      #30                 // Field shutwait:Ljava/lang/String;
       5: aload_0
       6: invokevirtual #8                  // Method getThis:()Lorg/apache/dubbo/config/bootstrap/builders/ApplicationBuilder;
       9: areturn

  public org.apache.dubbo.config.bootstrap.builders.ApplicationBuilder appendParameter(java.lang.String, java.lang.String);
    Code:
       0: aload_0
       1: aload_0
       2: getfield      #31                 // Field parameters:Ljava/util/Map;
       5: aload_1
       6: aload_2
       7: invokestatic  #32                 // Method appendParameter:(Ljava/util/Map;Ljava/lang/String;Ljava/lang/String;)Ljava/util/Map;
      10: putfield      #31                 // Field parameters:Ljava/util/Map;
      13: aload_0
      14: invokevirtual #8                  // Method getThis:()Lorg/apache/dubbo/config/bootstrap/builders/ApplicationBuilder;
      17: areturn

  public org.apache.dubbo.config.bootstrap.builders.ApplicationBuilder appendParameters(java.util.Map<java.lang.String, java.lang.String>);
    Code:
       0: aload_0
       1: aload_0
       2: getfield      #31                 // Field parameters:Ljava/util/Map;
       5: aload_1
       6: invokestatic  #33                 // Method appendParameters:(Ljava/util/Map;Ljava/util/Map;)Ljava/util/Map;
       9: putfield      #31                 // Field parameters:Ljava/util/Map;
      12: aload_0
      13: invokevirtual #8                  // Method getThis:()Lorg/apache/dubbo/config/bootstrap/builders/ApplicationBuilder;
      16: areturn

  public org.apache.dubbo.config.bootstrap.builders.ApplicationBuilder metadataServicePort(java.lang.Integer);
    Code:
       0: aload_0
       1: aload_1
       2: putfield      #34                 // Field metadataServicePort:Ljava/lang/Integer;
       5: aload_0
       6: invokevirtual #8                  // Method getThis:()Lorg/apache/dubbo/config/bootstrap/builders/ApplicationBuilder;
       9: areturn

  public org.apache.dubbo.config.bootstrap.builders.ApplicationBuilder livenessProbe(java.lang.String);
    Code:
       0: aload_0
       1: aload_1
       2: putfield      #35                 // Field livenessProbe:Ljava/lang/String;
       5: aload_0
       6: invokevirtual #8                  // Method getThis:()Lorg/apache/dubbo/config/bootstrap/builders/ApplicationBuilder;
       9: areturn

  public org.apache.dubbo.config.bootstrap.builders.ApplicationBuilder readinessProbe(java.lang.String);
    Code:
       0: aload_0
       1: aload_1
       2: putfield      #36                 // Field readinessProbe:Ljava/lang/String;
       5: aload_0
       6: invokevirtual #8                  // Method getThis:()Lorg/apache/dubbo/config/bootstrap/builders/ApplicationBuilder;
       9: areturn

  public org.apache.dubbo.config.bootstrap.builders.ApplicationBuilder startupProbe(java.lang.String);
    Code:
       0: aload_0
       1: aload_1
       2: putfield      #37                 // Field startupProbe:Ljava/lang/String;
       5: aload_0
       6: invokevirtual #8                  // Method getThis:()Lorg/apache/dubbo/config/bootstrap/builders/ApplicationBuilder;
       9: areturn

  public org.apache.dubbo.config.ApplicationConfig build();
    Code:
       0: new           #38                 // class org/apache/dubbo/config/ApplicationConfig
       3: dup
       4: invokespecial #39                 // Method org/apache/dubbo/config/ApplicationConfig."<init>":()V
       7: astore_1
       8: aload_0
       9: aload_1
      10: invokespecial #40                 // Method org/apache/dubbo/config/bootstrap/builders/AbstractBuilder.build:(Lorg/apache/dubbo/config/AbstractConfig;)V
      13: aload_1
      14: aload_0
      15: getfield      #7                  // Field name:Ljava/lang/String;
      18: invokevirtual #41                 // Method org/apache/dubbo/config/ApplicationConfig.setName:(Ljava/lang/String;)V
      21: aload_1
      22: aload_0
      23: getfield      #9                  // Field metadata:Ljava/lang/String;
      26: invokevirtual #42                 // Method org/apache/dubbo/config/ApplicationConfig.setMetadataType:(Ljava/lang/String;)V
      29: aload_1
      30: aload_0
      31: getfield      #10                 // Field version:Ljava/lang/String;
      34: invokevirtual #43                 // Method org/apache/dubbo/config/ApplicationConfig.setVersion:(Ljava/lang/String;)V
      37: aload_1
      38: aload_0
      39: getfield      #11                 // Field owner:Ljava/lang/String;
      42: invokevirtual #44                 // Method org/apache/dubbo/config/ApplicationConfig.setOwner:(Ljava/lang/String;)V
      45: aload_1
      46: aload_0
      47: getfield      #12                 // Field organization:Ljava/lang/String;
      50: invokevirtual #45                 // Method org/apache/dubbo/config/ApplicationConfig.setOrganization:(Ljava/lang/String;)V
      53: aload_1
      54: aload_0
      55: getfield      #13                 // Field architecture:Ljava/lang/String;
      58: invokevirtual #46                 // Method org/apache/dubbo/config/ApplicationConfig.setArchitecture:(Ljava/lang/String;)V
      61: aload_1
      62: aload_0
      63: getfield      #4                  // Field environment:Ljava/lang/String;
      66: invokevirtual #47                 // Method org/apache/dubbo/config/ApplicationConfig.setEnvironment:(Ljava/lang/String;)V
      69: aload_1
      70: aload_0
      71: getfield      #14                 // Field compiler:Ljava/lang/String;
      74: invokevirtual #48                 // Method org/apache/dubbo/config/ApplicationConfig.setCompiler:(Ljava/lang/String;)V
      77: aload_1
      78: aload_0
      79: getfield      #15                 // Field logger:Ljava/lang/String;
      82: invokevirtual #49                 // Method org/apache/dubbo/config/ApplicationConfig.setLogger:(Ljava/lang/String;)V
      85: aload_1
      86: aload_0
      87: getfield      #16                 // Field registries:Ljava/util/List;
      90: invokevirtual #50                 // Method org/apache/dubbo/config/ApplicationConfig.setRegistries:(Ljava/util/List;)V
      93: aload_1
      94: aload_0
      95: getfield      #21                 // Field registryIds:Ljava/lang/String;
      98: invokevirtual #51                 // Method org/apache/dubbo/config/ApplicationConfig.setRegistryIds:(Ljava/lang/String;)V
     101: aload_1
     102: aload_0
     103: getfield      #22                 // Field monitor:Lorg/apache/dubbo/config/MonitorConfig;
     106: invokevirtual #52                 // Method org/apache/dubbo/config/ApplicationConfig.setMonitor:(Lorg/apache/dubbo/config/MonitorConfig;)V
     109: aload_1
     110: aload_0
     111: getfield      #25                 // Field isDefault:Ljava/lang/Boolean;
     114: invokevirtual #53                 // Method org/apache/dubbo/config/ApplicationConfig.setDefault:(Ljava/lang/Boolean;)V
     117: aload_1
     118: aload_0
     119: getfield      #26                 // Field dumpDirectory:Ljava/lang/String;
     122: invokevirtual #54                 // Method org/apache/dubbo/config/ApplicationConfig.setDumpDirectory:(Ljava/lang/String;)V
     125: aload_1
     126: aload_0
     127: getfield      #27                 // Field qosEnable:Ljava/lang/Boolean;
     130: invokevirtual #55                 // Method org/apache/dubbo/config/ApplicationConfig.setQosEnable:(Ljava/lang/Boolean;)V
     133: aload_1
     134: aload_0
     135: getfield      #28                 // Field qosPort:Ljava/lang/Integer;
     138: invokevirtual #56                 // Method org/apache/dubbo/config/ApplicationConfig.setQosPort:(Ljava/lang/Integer;)V
     141: aload_1
     142: aload_0
     143: getfield      #29                 // Field qosAcceptForeignIp:Ljava/lang/Boolean;
     146: invokevirtual #57                 // Method org/apache/dubbo/config/ApplicationConfig.setQosAcceptForeignIp:(Ljava/lang/Boolean;)V
     149: aload_1
     150: aload_0
     151: getfield      #34                 // Field metadataServicePort:Ljava/lang/Integer;
     154: invokevirtual #58                 // Method org/apache/dubbo/config/ApplicationConfig.setMetadataServicePort:(Ljava/lang/Integer;)V
     157: aload_1
     158: aload_0
     159: getfield      #35                 // Field livenessProbe:Ljava/lang/String;
     162: invokevirtual #59                 // Method org/apache/dubbo/config/ApplicationConfig.setLivenessProbe:(Ljava/lang/String;)V
     165: aload_1
     166: aload_0
     167: getfield      #36                 // Field readinessProbe:Ljava/lang/String;
     170: invokevirtual #60                 // Method org/apache/dubbo/config/ApplicationConfig.setReadinessProbe:(Ljava/lang/String;)V
     173: aload_1
     174: aload_0
     175: getfield      #37                 // Field startupProbe:Ljava/lang/String;
     178: invokevirtual #61                 // Method org/apache/dubbo/config/ApplicationConfig.setStartupProbe:(Ljava/lang/String;)V
     181: aload_1
     182: aload_0
     183: getfield      #31                 // Field parameters:Ljava/util/Map;
     186: invokevirtual #62                 // Method org/apache/dubbo/config/ApplicationConfig.setParameters:(Ljava/util/Map;)V
     189: aload_0
     190: getfield      #30                 // Field shutwait:Ljava/lang/String;
     193: invokestatic  #63                 // Method org/apache/dubbo/common/utils/StringUtils.isEmpty:(Ljava/lang/String;)Z
     196: ifne          207
     199: aload_1
     200: aload_0
     201: getfield      #30                 // Field shutwait:Ljava/lang/String;
     204: invokevirtual #64                 // Method org/apache/dubbo/config/ApplicationConfig.setShutwait:(Ljava/lang/String;)V
     207: aload_1
     208: areturn

  protected org.apache.dubbo.config.bootstrap.builders.ApplicationBuilder getThis();
    Code:
       0: aload_0
       1: areturn

  public org.apache.dubbo.config.AbstractConfig build();
    Code:
       0: aload_0
       1: invokevirtual #65                 // Method build:()Lorg/apache/dubbo/config/ApplicationConfig;
       4: areturn

  protected org.apache.dubbo.config.bootstrap.builders.AbstractBuilder getThis();
    Code:
       0: aload_0
       1: invokevirtual #8                  // Method getThis:()Lorg/apache/dubbo/config/bootstrap/builders/ApplicationBuilder;
       4: areturn
}
