Compiled from "ArgumentBuilder.java"
public class org.apache.dubbo.config.bootstrap.builders.ArgumentBuilder {
  private java.lang.Integer index;

  private java.lang.String type;

  private java.lang.Boolean callback;

  public org.apache.dubbo.config.bootstrap.builders.ArgumentBuilder();
    Code:
       0: aload_0
       1: invokespecial #1                  // Method java/lang/Object."<init>":()V
       4: aload_0
       5: iconst_m1
       6: invokestatic  #2                  // Method java/lang/Integer.valueOf:(I)Ljava/lang/Integer;
       9: putfield      #3                  // Field index:Ljava/lang/Integer;
      12: return

  public org.apache.dubbo.config.bootstrap.builders.ArgumentBuilder index(java.lang.Integer);
    Code:
       0: aload_0
       1: aload_1
       2: putfield      #3                  // Field index:Ljava/lang/Integer;
       5: aload_0
       6: areturn

  public org.apache.dubbo.config.bootstrap.builders.ArgumentBuilder type(java.lang.String);
    Code:
       0: aload_0
       1: aload_1
       2: putfield      #4                  // Field type:Ljava/lang/String;
       5: aload_0
       6: areturn

  public org.apache.dubbo.config.bootstrap.builders.ArgumentBuilder callback(java.lang.Boolean);
    Code:
       0: aload_0
       1: aload_1
       2: putfield      #5                  // Field callback:Ljava/lang/Boolean;
       5: aload_0
       6: areturn

  public org.apache.dubbo.config.ArgumentConfig build();
    Code:
       0: new           #6                  // class org/apache/dubbo/config/ArgumentConfig
       3: dup
       4: invokespecial #7                  // Method org/apache/dubbo/config/ArgumentConfig."<init>":()V
       7: astore_1
       8: aload_1
       9: aload_0
      10: getfield      #3                  // Field index:Ljava/lang/Integer;
      13: invokevirtual #8                  // Method org/apache/dubbo/config/ArgumentConfig.setIndex:(Ljava/lang/Integer;)V
      16: aload_1
      17: aload_0
      18: getfield      #4                  // Field type:Ljava/lang/String;
      21: invokevirtual #9                  // Method org/apache/dubbo/config/ArgumentConfig.setType:(Ljava/lang/String;)V
      24: aload_1
      25: aload_0
      26: getfield      #5                  // Field callback:Ljava/lang/Boolean;
      29: invokevirtual #10                 // Method org/apache/dubbo/config/ArgumentConfig.setCallback:(Ljava/lang/Boolean;)V
      32: aload_1
      33: areturn
}
