Compiled from "ConfigCenterBuilder.java"
public class org.apache.dubbo.config.bootstrap.builders.ConfigCenterBuilder extends org.apache.dubbo.config.bootstrap.builders.AbstractBuilder<org.apache.dubbo.config.ConfigCenterConfig, org.apache.dubbo.config.bootstrap.builders.ConfigCenterBuilder> {
  private java.lang.String protocol;

  private java.lang.String address;

  private java.lang.String cluster;

  private java.lang.String namespace;

  private java.lang.String group;

  private java.lang.String username;

  private java.lang.String password;

  private java.lang.Long timeout;

  private java.lang.Boolean highestPriority;

  private java.lang.Boolean check;

  private java.lang.String configFile;

  private java.lang.String appConfigFile;

  private java.util.Map<java.lang.String, java.lang.String> parameters;

  public org.apache.dubbo.config.bootstrap.builders.ConfigCenterBuilder();
    Code:
       0: aload_0
       1: invokespecial #1                  // Method org/apache/dubbo/config/bootstrap/builders/AbstractBuilder."<init>":()V
       4: aload_0
       5: ldc           #2                  // String dubbo
       7: putfield      #3                  // Field namespace:Ljava/lang/String;
      10: aload_0
      11: ldc           #2                  // String dubbo
      13: putfield      #4                  // Field group:Ljava/lang/String;
      16: aload_0
      17: ldc2_w        #5                  // long 3000l
      20: invokestatic  #7                  // Method java/lang/Long.valueOf:(J)Ljava/lang/Long;
      23: putfield      #8                  // Field timeout:Ljava/lang/Long;
      26: aload_0
      27: iconst_1
      28: invokestatic  #9                  // Method java/lang/Boolean.valueOf:(Z)Ljava/lang/Boolean;
      31: putfield      #10                 // Field highestPriority:Ljava/lang/Boolean;
      34: aload_0
      35: iconst_1
      36: invokestatic  #9                  // Method java/lang/Boolean.valueOf:(Z)Ljava/lang/Boolean;
      39: putfield      #11                 // Field check:Ljava/lang/Boolean;
      42: aload_0
      43: ldc           #12                 // String dubbo.properties
      45: putfield      #13                 // Field configFile:Ljava/lang/String;
      48: return

  public org.apache.dubbo.config.bootstrap.builders.ConfigCenterBuilder protocol(java.lang.String);
    Code:
       0: aload_0
       1: aload_1
       2: putfield      #14                 // Field protocol:Ljava/lang/String;
       5: aload_0
       6: invokevirtual #15                 // Method getThis:()Lorg/apache/dubbo/config/bootstrap/builders/ConfigCenterBuilder;
       9: areturn

  public org.apache.dubbo.config.bootstrap.builders.ConfigCenterBuilder address(java.lang.String);
    Code:
       0: aload_0
       1: aload_1
       2: putfield      #16                 // Field address:Ljava/lang/String;
       5: aload_0
       6: invokevirtual #15                 // Method getThis:()Lorg/apache/dubbo/config/bootstrap/builders/ConfigCenterBuilder;
       9: areturn

  public org.apache.dubbo.config.bootstrap.builders.ConfigCenterBuilder cluster(java.lang.String);
    Code:
       0: aload_0
       1: aload_1
       2: putfield      #17                 // Field cluster:Ljava/lang/String;
       5: aload_0
       6: invokevirtual #15                 // Method getThis:()Lorg/apache/dubbo/config/bootstrap/builders/ConfigCenterBuilder;
       9: areturn

  public org.apache.dubbo.config.bootstrap.builders.ConfigCenterBuilder namespace(java.lang.String);
    Code:
       0: aload_0
       1: aload_1
       2: putfield      #3                  // Field namespace:Ljava/lang/String;
       5: aload_0
       6: invokevirtual #15                 // Method getThis:()Lorg/apache/dubbo/config/bootstrap/builders/ConfigCenterBuilder;
       9: areturn

  public org.apache.dubbo.config.bootstrap.builders.ConfigCenterBuilder group(java.lang.String);
    Code:
       0: aload_0
       1: aload_1
       2: putfield      #4                  // Field group:Ljava/lang/String;
       5: aload_0
       6: invokevirtual #15                 // Method getThis:()Lorg/apache/dubbo/config/bootstrap/builders/ConfigCenterBuilder;
       9: areturn

  public org.apache.dubbo.config.bootstrap.builders.ConfigCenterBuilder username(java.lang.String);
    Code:
       0: aload_0
       1: aload_1
       2: putfield      #18                 // Field username:Ljava/lang/String;
       5: aload_0
       6: invokevirtual #15                 // Method getThis:()Lorg/apache/dubbo/config/bootstrap/builders/ConfigCenterBuilder;
       9: areturn

  public org.apache.dubbo.config.bootstrap.builders.ConfigCenterBuilder password(java.lang.String);
    Code:
       0: aload_0
       1: aload_1
       2: putfield      #19                 // Field password:Ljava/lang/String;
       5: aload_0
       6: invokevirtual #15                 // Method getThis:()Lorg/apache/dubbo/config/bootstrap/builders/ConfigCenterBuilder;
       9: areturn

  public org.apache.dubbo.config.bootstrap.builders.ConfigCenterBuilder timeout(java.lang.Long);
    Code:
       0: aload_0
       1: aload_1
       2: putfield      #8                  // Field timeout:Ljava/lang/Long;
       5: aload_0
       6: invokevirtual #15                 // Method getThis:()Lorg/apache/dubbo/config/bootstrap/builders/ConfigCenterBuilder;
       9: areturn

  public org.apache.dubbo.config.bootstrap.builders.ConfigCenterBuilder highestPriority(java.lang.Boolean);
    Code:
       0: aload_0
       1: aload_1
       2: putfield      #10                 // Field highestPriority:Ljava/lang/Boolean;
       5: aload_0
       6: invokevirtual #15                 // Method getThis:()Lorg/apache/dubbo/config/bootstrap/builders/ConfigCenterBuilder;
       9: areturn

  public org.apache.dubbo.config.bootstrap.builders.ConfigCenterBuilder check(java.lang.Boolean);
    Code:
       0: aload_0
       1: aload_1
       2: putfield      #11                 // Field check:Ljava/lang/Boolean;
       5: aload_0
       6: invokevirtual #15                 // Method getThis:()Lorg/apache/dubbo/config/bootstrap/builders/ConfigCenterBuilder;
       9: areturn

  public org.apache.dubbo.config.bootstrap.builders.ConfigCenterBuilder configFile(java.lang.String);
    Code:
       0: aload_0
       1: aload_1
       2: putfield      #13                 // Field configFile:Ljava/lang/String;
       5: aload_0
       6: invokevirtual #15                 // Method getThis:()Lorg/apache/dubbo/config/bootstrap/builders/ConfigCenterBuilder;
       9: areturn

  public org.apache.dubbo.config.bootstrap.builders.ConfigCenterBuilder appConfigFile(java.lang.String);
    Code:
       0: aload_0
       1: aload_1
       2: putfield      #20                 // Field appConfigFile:Ljava/lang/String;
       5: aload_0
       6: invokevirtual #15                 // Method getThis:()Lorg/apache/dubbo/config/bootstrap/builders/ConfigCenterBuilder;
       9: areturn

  public org.apache.dubbo.config.bootstrap.builders.ConfigCenterBuilder appendParameters(java.util.Map<java.lang.String, java.lang.String>);
    Code:
       0: aload_0
       1: aload_0
       2: getfield      #21                 // Field parameters:Ljava/util/Map;
       5: aload_1
       6: invokestatic  #22                 // Method appendParameters:(Ljava/util/Map;Ljava/util/Map;)Ljava/util/Map;
       9: putfield      #21                 // Field parameters:Ljava/util/Map;
      12: aload_0
      13: invokevirtual #15                 // Method getThis:()Lorg/apache/dubbo/config/bootstrap/builders/ConfigCenterBuilder;
      16: areturn

  public org.apache.dubbo.config.bootstrap.builders.ConfigCenterBuilder appendParameter(java.lang.String, java.lang.String);
    Code:
       0: aload_0
       1: aload_0
       2: getfield      #21                 // Field parameters:Ljava/util/Map;
       5: aload_1
       6: aload_2
       7: invokestatic  #23                 // Method appendParameter:(Ljava/util/Map;Ljava/lang/String;Ljava/lang/String;)Ljava/util/Map;
      10: putfield      #21                 // Field parameters:Ljava/util/Map;
      13: aload_0
      14: invokevirtual #15                 // Method getThis:()Lorg/apache/dubbo/config/bootstrap/builders/ConfigCenterBuilder;
      17: areturn

  public org.apache.dubbo.config.ConfigCenterConfig build();
    Code:
       0: new           #24                 // class org/apache/dubbo/config/ConfigCenterConfig
       3: dup
       4: invokespecial #25                 // Method org/apache/dubbo/config/ConfigCenterConfig."<init>":()V
       7: astore_1
       8: aload_0
       9: aload_1
      10: invokespecial #26                 // Method org/apache/dubbo/config/bootstrap/builders/AbstractBuilder.build:(Lorg/apache/dubbo/config/AbstractConfig;)V
      13: aload_1
      14: aload_0
      15: getfield      #14                 // Field protocol:Ljava/lang/String;
      18: invokevirtual #27                 // Method org/apache/dubbo/config/ConfigCenterConfig.setProtocol:(Ljava/lang/String;)V
      21: aload_1
      22: aload_0
      23: getfield      #16                 // Field address:Ljava/lang/String;
      26: invokevirtual #28                 // Method org/apache/dubbo/config/ConfigCenterConfig.setAddress:(Ljava/lang/String;)V
      29: aload_1
      30: aload_0
      31: getfield      #17                 // Field cluster:Ljava/lang/String;
      34: invokevirtual #29                 // Method org/apache/dubbo/config/ConfigCenterConfig.setCluster:(Ljava/lang/String;)V
      37: aload_1
      38: aload_0
      39: getfield      #3                  // Field namespace:Ljava/lang/String;
      42: invokevirtual #30                 // Method org/apache/dubbo/config/ConfigCenterConfig.setNamespace:(Ljava/lang/String;)V
      45: aload_1
      46: aload_0
      47: getfield      #4                  // Field group:Ljava/lang/String;
      50: invokevirtual #31                 // Method org/apache/dubbo/config/ConfigCenterConfig.setGroup:(Ljava/lang/String;)V
      53: aload_1
      54: aload_0
      55: getfield      #18                 // Field username:Ljava/lang/String;
      58: invokevirtual #32                 // Method org/apache/dubbo/config/ConfigCenterConfig.setUsername:(Ljava/lang/String;)V
      61: aload_1
      62: aload_0
      63: getfield      #19                 // Field password:Ljava/lang/String;
      66: invokevirtual #33                 // Method org/apache/dubbo/config/ConfigCenterConfig.setPassword:(Ljava/lang/String;)V
      69: aload_1
      70: aload_0
      71: getfield      #8                  // Field timeout:Ljava/lang/Long;
      74: invokevirtual #34                 // Method org/apache/dubbo/config/ConfigCenterConfig.setTimeout:(Ljava/lang/Long;)V
      77: aload_1
      78: aload_0
      79: getfield      #10                 // Field highestPriority:Ljava/lang/Boolean;
      82: invokevirtual #35                 // Method org/apache/dubbo/config/ConfigCenterConfig.setHighestPriority:(Ljava/lang/Boolean;)V
      85: aload_1
      86: aload_0
      87: getfield      #11                 // Field check:Ljava/lang/Boolean;
      90: invokevirtual #36                 // Method org/apache/dubbo/config/ConfigCenterConfig.setCheck:(Ljava/lang/Boolean;)V
      93: aload_1
      94: aload_0
      95: getfield      #13                 // Field configFile:Ljava/lang/String;
      98: invokevirtual #37                 // Method org/apache/dubbo/config/ConfigCenterConfig.setConfigFile:(Ljava/lang/String;)V
     101: aload_1
     102: aload_0
     103: getfield      #20                 // Field appConfigFile:Ljava/lang/String;
     106: invokevirtual #38                 // Method org/apache/dubbo/config/ConfigCenterConfig.setAppConfigFile:(Ljava/lang/String;)V
     109: aload_1
     110: aload_0
     111: getfield      #21                 // Field parameters:Ljava/util/Map;
     114: invokevirtual #39                 // Method org/apache/dubbo/config/ConfigCenterConfig.setParameters:(Ljava/util/Map;)V
     117: aload_1
     118: areturn

  protected org.apache.dubbo.config.bootstrap.builders.ConfigCenterBuilder getThis();
    Code:
       0: aload_0
       1: areturn

  public org.apache.dubbo.config.AbstractConfig build();
    Code:
       0: aload_0
       1: invokevirtual #40                 // Method build:()Lorg/apache/dubbo/config/ConfigCenterConfig;
       4: areturn

  protected org.apache.dubbo.config.bootstrap.builders.AbstractBuilder getThis();
    Code:
       0: aload_0
       1: invokevirtual #15                 // Method getThis:()Lorg/apache/dubbo/config/bootstrap/builders/ConfigCenterBuilder;
       4: areturn
}
