Compiled from "ConsumerBuilder.java"
public class org.apache.dubbo.config.bootstrap.builders.ConsumerBuilder extends org.apache.dubbo.config.bootstrap.builders.AbstractReferenceBuilder<org.apache.dubbo.config.ConsumerConfig, org.apache.dubbo.config.bootstrap.builders.ConsumerBuilder> {
  private java.lang.Boolean isDefault;

  private java.lang.String client;

  private java.lang.String threadpool;

  private java.lang.Integer corethreads;

  private java.lang.Integer threads;

  private java.lang.Integer queues;

  private java.lang.Integer shareconnections;

  private java.lang.String urlMergeProcessor;

  public org.apache.dubbo.config.bootstrap.builders.ConsumerBuilder();
    Code:
       0: aload_0
       1: invokespecial #1                  // Method org/apache/dubbo/config/bootstrap/builders/AbstractReferenceBuilder."<init>":()V
       4: return

  public org.apache.dubbo.config.bootstrap.builders.ConsumerBuilder isDefault(java.lang.Boolean);
    Code:
       0: aload_0
       1: aload_1
       2: putfield      #2                  // Field isDefault:Ljava/lang/Boolean;
       5: aload_0
       6: invokevirtual #3                  // Method getThis:()Lorg/apache/dubbo/config/bootstrap/builders/ConsumerBuilder;
       9: areturn

  public org.apache.dubbo.config.bootstrap.builders.ConsumerBuilder client(java.lang.String);
    Code:
       0: aload_0
       1: aload_1
       2: putfield      #4                  // Field client:Ljava/lang/String;
       5: aload_0
       6: invokevirtual #3                  // Method getThis:()Lorg/apache/dubbo/config/bootstrap/builders/ConsumerBuilder;
       9: areturn

  public org.apache.dubbo.config.bootstrap.builders.ConsumerBuilder threadPool(java.lang.String);
    Code:
       0: aload_0
       1: aload_1
       2: putfield      #5                  // Field threadpool:Ljava/lang/String;
       5: aload_0
       6: invokevirtual #3                  // Method getThis:()Lorg/apache/dubbo/config/bootstrap/builders/ConsumerBuilder;
       9: areturn

  public org.apache.dubbo.config.bootstrap.builders.ConsumerBuilder coreThreads(java.lang.Integer);
    Code:
       0: aload_0
       1: aload_1
       2: putfield      #6                  // Field corethreads:Ljava/lang/Integer;
       5: aload_0
       6: invokevirtual #3                  // Method getThis:()Lorg/apache/dubbo/config/bootstrap/builders/ConsumerBuilder;
       9: areturn

  public org.apache.dubbo.config.bootstrap.builders.ConsumerBuilder threads(java.lang.Integer);
    Code:
       0: aload_0
       1: aload_1
       2: putfield      #7                  // Field threads:Ljava/lang/Integer;
       5: aload_0
       6: invokevirtual #3                  // Method getThis:()Lorg/apache/dubbo/config/bootstrap/builders/ConsumerBuilder;
       9: areturn

  public org.apache.dubbo.config.bootstrap.builders.ConsumerBuilder queues(java.lang.Integer);
    Code:
       0: aload_0
       1: aload_1
       2: putfield      #8                  // Field queues:Ljava/lang/Integer;
       5: aload_0
       6: invokevirtual #3                  // Method getThis:()Lorg/apache/dubbo/config/bootstrap/builders/ConsumerBuilder;
       9: areturn

  public org.apache.dubbo.config.bootstrap.builders.ConsumerBuilder shareConnections(java.lang.Integer);
    Code:
       0: aload_0
       1: aload_1
       2: putfield      #9                  // Field shareconnections:Ljava/lang/Integer;
       5: aload_0
       6: invokevirtual #3                  // Method getThis:()Lorg/apache/dubbo/config/bootstrap/builders/ConsumerBuilder;
       9: areturn

  public org.apache.dubbo.config.bootstrap.builders.ConsumerBuilder urlMergeProcessor(java.lang.String);
    Code:
       0: aload_0
       1: aload_1
       2: putfield      #10                 // Field urlMergeProcessor:Ljava/lang/String;
       5: aload_0
       6: invokevirtual #3                  // Method getThis:()Lorg/apache/dubbo/config/bootstrap/builders/ConsumerBuilder;
       9: areturn

  public org.apache.dubbo.config.ConsumerConfig build();
    Code:
       0: new           #11                 // class org/apache/dubbo/config/ConsumerConfig
       3: dup
       4: invokespecial #12                 // Method org/apache/dubbo/config/ConsumerConfig."<init>":()V
       7: astore_1
       8: aload_0
       9: aload_1
      10: invokespecial #13                 // Method org/apache/dubbo/config/bootstrap/builders/AbstractReferenceBuilder.build:(Lorg/apache/dubbo/config/AbstractReferenceConfig;)V
      13: aload_1
      14: aload_0
      15: getfield      #2                  // Field isDefault:Ljava/lang/Boolean;
      18: invokevirtual #14                 // Method org/apache/dubbo/config/ConsumerConfig.setDefault:(Ljava/lang/Boolean;)V
      21: aload_1
      22: aload_0
      23: getfield      #4                  // Field client:Ljava/lang/String;
      26: invokevirtual #15                 // Method org/apache/dubbo/config/ConsumerConfig.setClient:(Ljava/lang/String;)V
      29: aload_1
      30: aload_0
      31: getfield      #5                  // Field threadpool:Ljava/lang/String;
      34: invokevirtual #16                 // Method org/apache/dubbo/config/ConsumerConfig.setThreadpool:(Ljava/lang/String;)V
      37: aload_1
      38: aload_0
      39: getfield      #6                  // Field corethreads:Ljava/lang/Integer;
      42: invokevirtual #17                 // Method org/apache/dubbo/config/ConsumerConfig.setCorethreads:(Ljava/lang/Integer;)V
      45: aload_1
      46: aload_0
      47: getfield      #7                  // Field threads:Ljava/lang/Integer;
      50: invokevirtual #18                 // Method org/apache/dubbo/config/ConsumerConfig.setThreads:(Ljava/lang/Integer;)V
      53: aload_1
      54: aload_0
      55: getfield      #8                  // Field queues:Ljava/lang/Integer;
      58: invokevirtual #19                 // Method org/apache/dubbo/config/ConsumerConfig.setQueues:(Ljava/lang/Integer;)V
      61: aload_1
      62: aload_0
      63: getfield      #9                  // Field shareconnections:Ljava/lang/Integer;
      66: invokevirtual #20                 // Method org/apache/dubbo/config/ConsumerConfig.setShareconnections:(Ljava/lang/Integer;)V
      69: aload_1
      70: aload_0
      71: getfield      #10                 // Field urlMergeProcessor:Ljava/lang/String;
      74: invokevirtual #21                 // Method org/apache/dubbo/config/ConsumerConfig.setUrlMergeProcessor:(Ljava/lang/String;)V
      77: aload_1
      78: areturn

  protected org.apache.dubbo.config.bootstrap.builders.ConsumerBuilder getThis();
    Code:
       0: aload_0
       1: areturn

  public org.apache.dubbo.config.AbstractConfig build();
    Code:
       0: aload_0
       1: invokevirtual #22                 // Method build:()Lorg/apache/dubbo/config/ConsumerConfig;
       4: areturn

  protected org.apache.dubbo.config.bootstrap.builders.AbstractBuilder getThis();
    Code:
       0: aload_0
       1: invokevirtual #3                  // Method getThis:()Lorg/apache/dubbo/config/bootstrap/builders/ConsumerBuilder;
       4: areturn
}
