Compiled from "InternalServiceConfigBuilder.java"
public class org.apache.dubbo.config.bootstrap.builders.InternalServiceConfigBuilder<T> {
  private final org.apache.dubbo.common.logger.ErrorTypeAwareLogger logger;

  private static final java.util.Set<java.lang.String> UNACCEPTABLE_PROTOCOL;

  private final org.apache.dubbo.rpc.model.ApplicationModel applicationModel;

  private java.lang.String protocol;

  private java.lang.Integer port;

  private java.lang.String registryId;

  private java.lang.Class<T> interfaceClass;

  private java.util.concurrent.Executor executor;

  private T ref;

  private org.apache.dubbo.config.bootstrap.builders.InternalServiceConfigBuilder(org.apache.dubbo.rpc.model.ApplicationModel);
    Code:
       0: aload_0
       1: invokespecial #4                  // Method java/lang/Object."<init>":()V
       4: aload_0
       5: aload_0
       6: invokevirtual #5                  // Method java/lang/Object.getClass:()Ljava/lang/Class;
       9: invokestatic  #6                  // Method org/apache/dubbo/common/logger/LoggerFactory.getErrorTypeAwareLogger:(Ljava/lang/Class;)Lorg/apache/dubbo/common/logger/ErrorTypeAwareLogger;
      12: putfield      #7                  // Field logger:Lorg/apache/dubbo/common/logger/ErrorTypeAwareLogger;
      15: aload_0
      16: aload_1
      17: putfield      #8                  // Field applicationModel:Lorg/apache/dubbo/rpc/model/ApplicationModel;
      20: return

  public static <T> org.apache.dubbo.config.bootstrap.builders.InternalServiceConfigBuilder<T> newBuilder(org.apache.dubbo.rpc.model.ApplicationModel);
    Code:
       0: new           #9                  // class org/apache/dubbo/config/bootstrap/builders/InternalServiceConfigBuilder
       3: dup
       4: aload_0
       5: invokespecial #10                 // Method "<init>":(Lorg/apache/dubbo/rpc/model/ApplicationModel;)V
       8: areturn

  public org.apache.dubbo.config.bootstrap.builders.InternalServiceConfigBuilder<T> interfaceClass(java.lang.Class<T>);
    Code:
       0: aload_0
       1: aload_1
       2: putfield      #11                 // Field interfaceClass:Ljava/lang/Class;
       5: aload_0
       6: invokevirtual #12                 // Method getThis:()Lorg/apache/dubbo/config/bootstrap/builders/InternalServiceConfigBuilder;
       9: areturn

  public org.apache.dubbo.config.bootstrap.builders.InternalServiceConfigBuilder<T> executor(java.util.concurrent.Executor);
    Code:
       0: aload_0
       1: aload_1
       2: putfield      #13                 // Field executor:Ljava/util/concurrent/Executor;
       5: aload_0
       6: invokevirtual #12                 // Method getThis:()Lorg/apache/dubbo/config/bootstrap/builders/InternalServiceConfigBuilder;
       9: areturn

  public org.apache.dubbo.config.bootstrap.builders.InternalServiceConfigBuilder<T> ref(T);
    Code:
       0: aload_0
       1: aload_1
       2: putfield      #14                 // Field ref:Ljava/lang/Object;
       5: aload_0
       6: invokevirtual #12                 // Method getThis:()Lorg/apache/dubbo/config/bootstrap/builders/InternalServiceConfigBuilder;
       9: areturn

  public org.apache.dubbo.config.bootstrap.builders.InternalServiceConfigBuilder<T> registryId(java.lang.String);
    Code:
       0: aload_0
       1: aload_1
       2: putfield      #15                 // Field registryId:Ljava/lang/String;
       5: aload_0
       6: invokevirtual #12                 // Method getThis:()Lorg/apache/dubbo/config/bootstrap/builders/InternalServiceConfigBuilder;
       9: areturn

  public org.apache.dubbo.config.bootstrap.builders.InternalServiceConfigBuilder<T> protocol(java.lang.String, java.lang.String);
    Code:
       0: aload_1
       1: invokestatic  #16                 // Method org/apache/dubbo/common/utils/StringUtils.isEmpty:(Ljava/lang/String;)Z
       4: ifeq          40
       7: aload_2
       8: invokestatic  #17                 // Method org/apache/dubbo/common/utils/StringUtils.isNotBlank:(Ljava/lang/CharSequence;)Z
      11: ifeq          40
      14: aload_0
      15: invokespecial #18                 // Method getApplicationConfig:()Lorg/apache/dubbo/config/ApplicationConfig;
      18: invokevirtual #19                 // Method org/apache/dubbo/config/ApplicationConfig.getParameters:()Ljava/util/Map;
      21: astore_3
      22: aload_3
      23: invokestatic  #20                 // Method org/apache/dubbo/common/utils/CollectionUtils.isNotEmptyMap:(Ljava/util/Map;)Z
      26: ifeq          40
      29: aload_3
      30: aload_2
      31: invokeinterface #21,  2           // InterfaceMethod java/util/Map.get:(Ljava/lang/Object;)Ljava/lang/Object;
      36: checkcast     #22                 // class java/lang/String
      39: astore_1
      40: aload_0
      41: aload_1
      42: invokestatic  #23                 // Method org/apache/dubbo/common/utils/StringUtils.isNotEmpty:(Ljava/lang/String;)Z
      45: ifeq          52
      48: aload_1
      49: goto          56
      52: aload_0
      53: invokespecial #24                 // Method getRelatedOrDefaultProtocol:()Ljava/lang/String;
      56: putfield      #25                 // Field protocol:Ljava/lang/String;
      59: aload_0
      60: invokevirtual #12                 // Method getThis:()Lorg/apache/dubbo/config/bootstrap/builders/InternalServiceConfigBuilder;
      63: areturn

  private java.lang.String getRelatedOrDefaultProtocol();
    Code:
       0: ldc           #26                 // String
       2: astore_1
       3: aload_0
       4: getfield      #8                  // Field applicationModel:Lorg/apache/dubbo/rpc/model/ApplicationModel;
       7: invokevirtual #27                 // Method org/apache/dubbo/rpc/model/ApplicationModel.getPubModuleModels:()Ljava/util/List;
      10: astore_2
      11: aload_2
      12: invokeinterface #28,  1           // InterfaceMethod java/util/List.stream:()Ljava/util/stream/Stream;
      17: invokedynamic #29,  0             // InvokeDynamic #0:apply:()Ljava/util/function/Function;
      22: invokeinterface #30,  2           // InterfaceMethod java/util/stream/Stream.map:(Ljava/util/function/Function;)Ljava/util/stream/Stream;
      27: invokedynamic #31,  0             // InvokeDynamic #1:apply:()Ljava/util/function/Function;
      32: invokeinterface #30,  2           // InterfaceMethod java/util/stream/Stream.map:(Ljava/util/function/Function;)Ljava/util/stream/Stream;
      37: invokedynamic #32,  0             // InvokeDynamic #2:test:()Ljava/util/function/Predicate;
      42: invokeinterface #33,  2           // InterfaceMethod java/util/stream/Stream.filter:(Ljava/util/function/Predicate;)Ljava/util/stream/Stream;
      47: invokedynamic #34,  0             // InvokeDynamic #3:apply:()Ljava/util/function/Function;
      52: invokeinterface #35,  2           // InterfaceMethod java/util/stream/Stream.flatMap:(Ljava/util/function/Function;)Ljava/util/stream/Stream;
      57: invokedynamic #36,  0             // InvokeDynamic #4:apply:()Ljava/util/function/Function;
      62: invokeinterface #30,  2           // InterfaceMethod java/util/stream/Stream.map:(Ljava/util/function/Function;)Ljava/util/stream/Stream;
      67: invokedynamic #37,  0             // InvokeDynamic #5:test:()Ljava/util/function/Predicate;
      72: invokeinterface #33,  2           // InterfaceMethod java/util/stream/Stream.filter:(Ljava/util/function/Predicate;)Ljava/util/stream/Stream;
      77: invokedynamic #38,  0             // InvokeDynamic #6:test:()Ljava/util/function/Predicate;
      82: invokeinterface #33,  2           // InterfaceMethod java/util/stream/Stream.filter:(Ljava/util/function/Predicate;)Ljava/util/stream/Stream;
      87: invokeinterface #39,  1           // InterfaceMethod java/util/stream/Stream.findFirst:()Ljava/util/Optional;
      92: ldc           #26                 // String
      94: invokevirtual #40                 // Method java/util/Optional.orElse:(Ljava/lang/Object;)Ljava/lang/Object;
      97: checkcast     #22                 // class java/lang/String
     100: astore_1
     101: aload_1
     102: invokestatic  #16                 // Method org/apache/dubbo/common/utils/StringUtils.isEmpty:(Ljava/lang/String;)Z
     105: ifeq          210
     108: aload_2
     109: invokeinterface #28,  1           // InterfaceMethod java/util/List.stream:()Ljava/util/stream/Stream;
     114: invokedynamic #29,  0             // InvokeDynamic #0:apply:()Ljava/util/function/Function;
     119: invokeinterface #30,  2           // InterfaceMethod java/util/stream/Stream.map:(Ljava/util/function/Function;)Ljava/util/stream/Stream;
     124: invokedynamic #41,  0             // InvokeDynamic #7:apply:()Ljava/util/function/Function;
     129: invokeinterface #30,  2           // InterfaceMethod java/util/stream/Stream.map:(Ljava/util/function/Function;)Ljava/util/stream/Stream;
     134: invokedynamic #32,  0             // InvokeDynamic #2:test:()Ljava/util/function/Predicate;
     139: invokeinterface #33,  2           // InterfaceMethod java/util/stream/Stream.filter:(Ljava/util/function/Predicate;)Ljava/util/stream/Stream;
     144: invokedynamic #34,  0             // InvokeDynamic #3:apply:()Ljava/util/function/Function;
     149: invokeinterface #35,  2           // InterfaceMethod java/util/stream/Stream.flatMap:(Ljava/util/function/Function;)Ljava/util/stream/Stream;
     154: astore_3
     155: aload_3
     156: invokedynamic #42,  0             // InvokeDynamic #8:test:()Ljava/util/function/Predicate;
     161: invokeinterface #33,  2           // InterfaceMethod java/util/stream/Stream.filter:(Ljava/util/function/Predicate;)Ljava/util/stream/Stream;
     166: invokedynamic #43,  0             // InvokeDynamic #9:apply:()Ljava/util/function/Function;
     171: invokeinterface #30,  2           // InterfaceMethod java/util/stream/Stream.map:(Ljava/util/function/Function;)Ljava/util/stream/Stream;
     176: invokedynamic #37,  0             // InvokeDynamic #5:test:()Ljava/util/function/Predicate;
     181: invokeinterface #33,  2           // InterfaceMethod java/util/stream/Stream.filter:(Ljava/util/function/Predicate;)Ljava/util/stream/Stream;
     186: invokedynamic #44,  0             // InvokeDynamic #10:test:()Ljava/util/function/Predicate;
     191: invokeinterface #33,  2           // InterfaceMethod java/util/stream/Stream.filter:(Ljava/util/function/Predicate;)Ljava/util/stream/Stream;
     196: invokeinterface #39,  1           // InterfaceMethod java/util/stream/Stream.findFirst:()Ljava/util/Optional;
     201: ldc           #26                 // String
     203: invokevirtual #40                 // Method java/util/Optional.orElse:(Ljava/lang/Object;)Ljava/lang/Object;
     206: checkcast     #22                 // class java/lang/String
     209: astore_1
     210: aload_1
     211: invokestatic  #16                 // Method org/apache/dubbo/common/utils/StringUtils.isEmpty:(Ljava/lang/String;)Z
     214: ifeq          285
     217: aload_0
     218: getfield      #8                  // Field applicationModel:Lorg/apache/dubbo/rpc/model/ApplicationModel;
     221: invokevirtual #45                 // Method org/apache/dubbo/rpc/model/ApplicationModel.getApplicationConfigManager:()Lorg/apache/dubbo/config/context/ConfigManager;
     224: invokevirtual #46                 // Method org/apache/dubbo/config/context/ConfigManager.getProtocols:()Ljava/util/Collection;
     227: astore_3
     228: aload_3
     229: invokestatic  #47                 // Method org/apache/dubbo/common/utils/CollectionUtils.isNotEmpty:(Ljava/util/Collection;)Z
     232: ifeq          285
     235: aload_3
     236: invokeinterface #48,  1           // InterfaceMethod java/util/Collection.stream:()Ljava/util/stream/Stream;
     241: invokedynamic #49,  0             // InvokeDynamic #11:apply:()Ljava/util/function/Function;
     246: invokeinterface #30,  2           // InterfaceMethod java/util/stream/Stream.map:(Ljava/util/function/Function;)Ljava/util/stream/Stream;
     251: invokedynamic #37,  0             // InvokeDynamic #5:test:()Ljava/util/function/Predicate;
     256: invokeinterface #33,  2           // InterfaceMethod java/util/stream/Stream.filter:(Ljava/util/function/Predicate;)Ljava/util/stream/Stream;
     261: invokedynamic #50,  0             // InvokeDynamic #12:test:()Ljava/util/function/Predicate;
     266: invokeinterface #33,  2           // InterfaceMethod java/util/stream/Stream.filter:(Ljava/util/function/Predicate;)Ljava/util/stream/Stream;
     271: invokeinterface #39,  1           // InterfaceMethod java/util/stream/Stream.findFirst:()Ljava/util/Optional;
     276: ldc           #26                 // String
     278: invokevirtual #40                 // Method java/util/Optional.orElse:(Ljava/lang/Object;)Ljava/lang/Object;
     281: checkcast     #22                 // class java/lang/String
     284: astore_1
     285: aload_1
     286: invokestatic  #16                 // Method org/apache/dubbo/common/utils/StringUtils.isEmpty:(Ljava/lang/String;)Z
     289: ifeq          334
     292: aload_0
     293: invokespecial #18                 // Method getApplicationConfig:()Lorg/apache/dubbo/config/ApplicationConfig;
     296: invokevirtual #51                 // Method org/apache/dubbo/config/ApplicationConfig.getProtocol:()Ljava/lang/String;
     299: astore_1
     300: aload_1
     301: invokestatic  #16                 // Method org/apache/dubbo/common/utils/StringUtils.isEmpty:(Ljava/lang/String;)Z
     304: ifeq          334
     307: aload_0
     308: invokespecial #18                 // Method getApplicationConfig:()Lorg/apache/dubbo/config/ApplicationConfig;
     311: invokevirtual #19                 // Method org/apache/dubbo/config/ApplicationConfig.getParameters:()Ljava/util/Map;
     314: astore_3
     315: aload_3
     316: invokestatic  #20                 // Method org/apache/dubbo/common/utils/CollectionUtils.isNotEmptyMap:(Ljava/util/Map;)Z
     319: ifeq          334
     322: aload_3
     323: ldc           #52                 // String application-protocol
     325: invokeinterface #21,  2           // InterfaceMethod java/util/Map.get:(Ljava/lang/Object;)Ljava/lang/Object;
     330: checkcast     #22                 // class java/lang/String
     333: astore_1
     334: aload_1
     335: invokestatic  #23                 // Method org/apache/dubbo/common/utils/StringUtils.isNotEmpty:(Ljava/lang/String;)Z
     338: ifeq          357
     341: getstatic     #53                 // Field UNACCEPTABLE_PROTOCOL:Ljava/util/Set;
     344: aload_1
     345: invokeinterface #54,  2           // InterfaceMethod java/util/Set.contains:(Ljava/lang/Object;)Z
     350: ifne          357
     353: aload_1
     354: goto          359
     357: ldc           #55                 // String dubbo
     359: areturn

  public org.apache.dubbo.config.bootstrap.builders.InternalServiceConfigBuilder<T> protocol(java.lang.String);
    Code:
       0: aload_0
       1: aload_1
       2: aconst_null
       3: invokevirtual #56                 // Method protocol:(Ljava/lang/String;Ljava/lang/String;)Lorg/apache/dubbo/config/bootstrap/builders/InternalServiceConfigBuilder;
       6: pop
       7: aload_0
       8: invokevirtual #12                 // Method getThis:()Lorg/apache/dubbo/config/bootstrap/builders/InternalServiceConfigBuilder;
      11: areturn

  public org.apache.dubbo.config.bootstrap.builders.InternalServiceConfigBuilder<T> port(java.lang.Integer);
    Code:
       0: aload_0
       1: aload_1
       2: aconst_null
       3: invokevirtual #57                 // Method port:(Ljava/lang/Integer;Ljava/lang/String;)Lorg/apache/dubbo/config/bootstrap/builders/InternalServiceConfigBuilder;
       6: areturn

  public org.apache.dubbo.config.bootstrap.builders.InternalServiceConfigBuilder<T> port(java.lang.Integer, java.lang.String);
    Code:
       0: aload_0
       1: getfield      #25                 // Field protocol:Ljava/lang/String;
       4: ldc           #58                 // String export protocol is null
       6: invokestatic  #59                 // Method org/apache/dubbo/common/utils/Assert.notEmptyString:(Ljava/lang/String;Ljava/lang/String;)V
       9: aload_0
      10: getfield      #11                 // Field interfaceClass:Ljava/lang/Class;
      13: ldc           #60                 // String export interfaceClass is null
      15: invokestatic  #61                 // Method org/apache/dubbo/common/utils/Assert.notNull:(Ljava/lang/Object;Ljava/lang/String;)V
      18: aload_1
      19: ifnull        32
      22: aload_0
      23: aload_1
      24: putfield      #62                 // Field port:Ljava/lang/Integer;
      27: aload_0
      28: invokevirtual #12                 // Method getThis:()Lorg/apache/dubbo/config/bootstrap/builders/InternalServiceConfigBuilder;
      31: areturn
      32: aload_0
      33: invokespecial #18                 // Method getApplicationConfig:()Lorg/apache/dubbo/config/ApplicationConfig;
      36: invokevirtual #19                 // Method org/apache/dubbo/config/ApplicationConfig.getParameters:()Ljava/util/Map;
      39: astore_3
      40: aload_3
      41: invokestatic  #20                 // Method org/apache/dubbo/common/utils/CollectionUtils.isNotEmptyMap:(Ljava/util/Map;)Z
      44: ifeq          89
      47: aload_2
      48: invokestatic  #17                 // Method org/apache/dubbo/common/utils/StringUtils.isNotBlank:(Ljava/lang/CharSequence;)Z
      51: ifeq          89
      54: aload_0
      55: invokespecial #18                 // Method getApplicationConfig:()Lorg/apache/dubbo/config/ApplicationConfig;
      58: invokevirtual #19                 // Method org/apache/dubbo/config/ApplicationConfig.getParameters:()Ljava/util/Map;
      61: aload_2
      62: invokeinterface #21,  2           // InterfaceMethod java/util/Map.get:(Ljava/lang/Object;)Ljava/lang/Object;
      67: checkcast     #22                 // class java/lang/String
      70: astore        4
      72: aload         4
      74: invokestatic  #23                 // Method org/apache/dubbo/common/utils/StringUtils.isNotEmpty:(Ljava/lang/String;)Z
      77: ifeq          89
      80: aload         4
      82: invokestatic  #63                 // Method java/lang/Integer.parseInt:(Ljava/lang/String;)I
      85: invokestatic  #64                 // Method java/lang/Integer.valueOf:(I)Ljava/lang/Integer;
      88: astore_1
      89: aload_1
      90: ifnull        101
      93: aload_1
      94: invokevirtual #65                 // Method java/lang/Integer.intValue:()I
      97: iconst_m1
      98: if_icmpge     374
     101: aload_0
     102: getfield      #7                  // Field logger:Lorg/apache/dubbo/common/logger/ErrorTypeAwareLogger;
     105: invokeinterface #66,  1           // InterfaceMethod org/apache/dubbo/common/logger/ErrorTypeAwareLogger.isInfoEnabled:()Z
     110: ifeq          147
     113: aload_0
     114: getfield      #7                  // Field logger:Lorg/apache/dubbo/common/logger/ErrorTypeAwareLogger;
     117: new           #67                 // class java/lang/StringBuilder
     120: dup
     121: invokespecial #68                 // Method java/lang/StringBuilder."<init>":()V
     124: aload_0
     125: getfield      #11                 // Field interfaceClass:Ljava/lang/Class;
     128: invokevirtual #69                 // Method java/lang/Class.getName:()Ljava/lang/String;
     131: invokevirtual #70                 // Method java/lang/StringBuilder.append:(Ljava/lang/String;)Ljava/lang/StringBuilder;
     134: ldc           #71                 // String Service Port hasn\'t been set will use default protocol defined in protocols.
     136: invokevirtual #70                 // Method java/lang/StringBuilder.append:(Ljava/lang/String;)Ljava/lang/StringBuilder;
     139: invokevirtual #72                 // Method java/lang/StringBuilder.toString:()Ljava/lang/String;
     142: invokeinterface #73,  2           // InterfaceMethod org/apache/dubbo/common/logger/ErrorTypeAwareLogger.info:(Ljava/lang/String;)V
     147: aload_0
     148: getfield      #8                  // Field applicationModel:Lorg/apache/dubbo/rpc/model/ApplicationModel;
     151: ldc           #74                 // class org/apache/dubbo/rpc/Protocol
     153: invokevirtual #75                 // Method org/apache/dubbo/rpc/model/ApplicationModel.getExtensionLoader:(Ljava/lang/Class;)Lorg/apache/dubbo/common/extension/ExtensionLoader;
     156: aload_0
     157: getfield      #25                 // Field protocol:Ljava/lang/String;
     160: invokevirtual #76                 // Method org/apache/dubbo/common/extension/ExtensionLoader.getExtension:(Ljava/lang/String;)Ljava/lang/Object;
     163: checkcast     #74                 // class org/apache/dubbo/rpc/Protocol
     166: astore        4
     168: aload         4
     170: ifnull        317
     173: aload         4
     175: invokeinterface #77,  1           // InterfaceMethod org/apache/dubbo/rpc/Protocol.getServers:()Ljava/util/List;
     180: ifnull        317
     183: aload         4
     185: invokeinterface #77,  1           // InterfaceMethod org/apache/dubbo/rpc/Protocol.getServers:()Ljava/util/List;
     190: invokeinterface #78,  1           // InterfaceMethod java/util/List.iterator:()Ljava/util/Iterator;
     195: astore        5
     197: aload         5
     199: invokeinterface #79,  1           // InterfaceMethod java/util/Iterator.hasNext:()Z
     204: ifeq          278
     207: aload         5
     209: invokeinterface #80,  1           // InterfaceMethod java/util/Iterator.next:()Ljava/lang/Object;
     214: checkcast     #81                 // class org/apache/dubbo/rpc/ProtocolServer
     217: astore        6
     219: aload         6
     221: invokeinterface #82,  1           // InterfaceMethod org/apache/dubbo/rpc/ProtocolServer.getUrl:()Lorg/apache/dubbo/common/URL;
     226: ldc           #83                 // String bind.port
     228: invokevirtual #84                 // Method org/apache/dubbo/common/URL.getParameter:(Ljava/lang/String;)Ljava/lang/String;
     231: astore        7
     233: aload         7
     235: ifnonnull     263
     238: aload         6
     240: invokeinterface #85,  1           // InterfaceMethod org/apache/dubbo/rpc/ProtocolServer.getAddress:()Ljava/lang/String;
     245: astore        8
     247: aload         8
     249: aload         8
     251: ldc           #86                 // String :
     253: invokevirtual #87                 // Method java/lang/String.indexOf:(Ljava/lang/String;)I
     256: iconst_1
     257: iadd
     258: invokevirtual #88                 // Method java/lang/String.substring:(I)Ljava/lang/String;
     261: astore        7
     263: aload_0
     264: aload         7
     266: invokestatic  #63                 // Method java/lang/Integer.parseInt:(Ljava/lang/String;)I
     269: invokestatic  #64                 // Method java/lang/Integer.valueOf:(I)Ljava/lang/Integer;
     272: putfield      #62                 // Field port:Ljava/lang/Integer;
     275: goto          317
     278: aload_0
     279: invokespecial #89                 // Method getProtocolConfig:()Lorg/apache/dubbo/config/ProtocolConfig;
     282: astore        6
     284: aload         6
     286: ifnull        317
     289: aload         6
     291: invokevirtual #90                 // Method org/apache/dubbo/config/ProtocolConfig.getPort:()Ljava/lang/Integer;
     294: astore        7
     296: aconst_null
     297: aload         7
     299: if_acmpeq     317
     302: aload         7
     304: invokevirtual #65                 // Method java/lang/Integer.intValue:()I
     307: iconst_m1
     308: if_icmpeq     317
     311: aload_0
     312: aload         7
     314: putfield      #62                 // Field port:Ljava/lang/Integer;
     317: goto          374
     320: astore        4
     322: aload_0
     323: getfield      #7                  // Field logger:Lorg/apache/dubbo/common/logger/ErrorTypeAwareLogger;
     326: ldc           #92                 // String 99-0
     328: new           #67                 // class java/lang/StringBuilder
     331: dup
     332: invokespecial #68                 // Method java/lang/StringBuilder."<init>":()V
     335: ldc           #93                 // String invalid specified
     337: invokevirtual #70                 // Method java/lang/StringBuilder.append:(Ljava/lang/String;)Ljava/lang/StringBuilder;
     340: aload_0
     341: getfield      #62                 // Field port:Ljava/lang/Integer;
     344: invokevirtual #94                 // Method java/lang/StringBuilder.append:(Ljava/lang/Object;)Ljava/lang/StringBuilder;
     347: ldc           #95                 // String   port, error
     349: invokevirtual #70                 // Method java/lang/StringBuilder.append:(Ljava/lang/String;)Ljava/lang/StringBuilder;
     352: aload         4
     354: invokevirtual #96                 // Method java/lang/Exception.getMessage:()Ljava/lang/String;
     357: invokevirtual #70                 // Method java/lang/StringBuilder.append:(Ljava/lang/String;)Ljava/lang/StringBuilder;
     360: invokevirtual #72                 // Method java/lang/StringBuilder.toString:()Ljava/lang/String;
     363: ldc           #26                 // String
     365: ldc           #97                 // String Failed to find any valid protocol, will use random port to export  service.
     367: aload         4
     369: invokeinterface #98,  6           // InterfaceMethod org/apache/dubbo/common/logger/ErrorTypeAwareLogger.error:(Ljava/lang/String;Ljava/lang/String;Ljava/lang/String;Ljava/lang/String;Ljava/lang/Throwable;)V
     374: aload_0
     375: getfield      #62                 // Field port:Ljava/lang/Integer;
     378: ifnonnull     389
     381: aload_0
     382: iconst_m1
     383: invokestatic  #64                 // Method java/lang/Integer.valueOf:(I)Ljava/lang/Integer;
     386: putfield      #62                 // Field port:Ljava/lang/Integer;
     389: aload_0
     390: invokevirtual #12                 // Method getThis:()Lorg/apache/dubbo/config/bootstrap/builders/InternalServiceConfigBuilder;
     393: areturn
    Exception table:
       from    to  target type
         101   317   320   Class java/lang/Exception

  private org.apache.dubbo.config.ProtocolConfig getProtocolConfig();
    Code:
       0: aload_0
       1: getfield      #8                  // Field applicationModel:Lorg/apache/dubbo/rpc/model/ApplicationModel;
       4: invokevirtual #45                 // Method org/apache/dubbo/rpc/model/ApplicationModel.getApplicationConfigManager:()Lorg/apache/dubbo/config/context/ConfigManager;
       7: aload_0
       8: getfield      #25                 // Field protocol:Ljava/lang/String;
      11: invokevirtual #99                 // Method org/apache/dubbo/config/context/ConfigManager.getProtocol:(Ljava/lang/String;)Ljava/util/Optional;
      14: aconst_null
      15: invokevirtual #40                 // Method java/util/Optional.orElse:(Ljava/lang/Object;)Ljava/lang/Object;
      18: checkcast     #100                // class org/apache/dubbo/config/ProtocolConfig
      21: areturn

  public org.apache.dubbo.config.ServiceConfig<T> build(java.util.function.Consumer<org.apache.dubbo.config.ServiceConfig<T>>);
    Code:
       0: new           #100                // class org/apache/dubbo/config/ProtocolConfig
       3: dup
       4: invokespecial #101                // Method org/apache/dubbo/config/ProtocolConfig."<init>":()V
       7: astore_2
       8: aload_2
       9: aload_0
      10: getfield      #25                 // Field protocol:Ljava/lang/String;
      13: invokevirtual #102                // Method org/apache/dubbo/config/ProtocolConfig.setName:(Ljava/lang/String;)V
      16: aload_2
      17: aload_0
      18: getfield      #62                 // Field port:Ljava/lang/Integer;
      21: invokevirtual #103                // Method org/apache/dubbo/config/ProtocolConfig.setPort:(Ljava/lang/Integer;)V
      24: aload_0
      25: invokespecial #104                // Method nullAssert:()V
      28: aload_0
      29: getfield      #7                  // Field logger:Lorg/apache/dubbo/common/logger/ErrorTypeAwareLogger;
      32: new           #67                 // class java/lang/StringBuilder
      35: dup
      36: invokespecial #68                 // Method java/lang/StringBuilder."<init>":()V
      39: ldc           #105                // String Using
      41: invokevirtual #70                 // Method java/lang/StringBuilder.append:(Ljava/lang/String;)Ljava/lang/StringBuilder;
      44: aload_0
      45: getfield      #25                 // Field protocol:Ljava/lang/String;
      48: invokevirtual #70                 // Method java/lang/StringBuilder.append:(Ljava/lang/String;)Ljava/lang/StringBuilder;
      51: ldc           #106                // String  protocol to export
      53: invokevirtual #70                 // Method java/lang/StringBuilder.append:(Ljava/lang/String;)Ljava/lang/StringBuilder;
      56: aload_0
      57: getfield      #11                 // Field interfaceClass:Ljava/lang/Class;
      60: invokevirtual #69                 // Method java/lang/Class.getName:()Ljava/lang/String;
      63: invokevirtual #70                 // Method java/lang/StringBuilder.append:(Ljava/lang/String;)Ljava/lang/StringBuilder;
      66: ldc           #107                // String  service on port
      68: invokevirtual #70                 // Method java/lang/StringBuilder.append:(Ljava/lang/String;)Ljava/lang/StringBuilder;
      71: aload_2
      72: invokevirtual #90                 // Method org/apache/dubbo/config/ProtocolConfig.getPort:()Ljava/lang/Integer;
      75: invokevirtual #94                 // Method java/lang/StringBuilder.append:(Ljava/lang/Object;)Ljava/lang/StringBuilder;
      78: invokevirtual #72                 // Method java/lang/StringBuilder.toString:()Ljava/lang/String;
      81: invokeinterface #73,  2           // InterfaceMethod org/apache/dubbo/common/logger/ErrorTypeAwareLogger.info:(Ljava/lang/String;)V
      86: aload_0
      87: getfield      #8                  // Field applicationModel:Lorg/apache/dubbo/rpc/model/ApplicationModel;
      90: invokevirtual #45                 // Method org/apache/dubbo/rpc/model/ApplicationModel.getApplicationConfigManager:()Lorg/apache/dubbo/config/context/ConfigManager;
      93: aload_0
      94: getfield      #25                 // Field protocol:Ljava/lang/String;
      97: invokevirtual #99                 // Method org/apache/dubbo/config/context/ConfigManager.getProtocol:(Ljava/lang/String;)Ljava/util/Optional;
     100: aload_2
     101: dup
     102: invokevirtual #5                  // Method java/lang/Object.getClass:()Ljava/lang/Class;
     105: pop
     106: invokedynamic #108,  0            // InvokeDynamic #13:accept:(Lorg/apache/dubbo/config/ProtocolConfig;)Ljava/util/function/Consumer;
     111: invokevirtual #109                // Method java/util/Optional.ifPresent:(Ljava/util/function/Consumer;)V
     114: aload_0
     115: invokespecial #18                 // Method getApplicationConfig:()Lorg/apache/dubbo/config/ApplicationConfig;
     118: astore_3
     119: new           #110                // class org/apache/dubbo/config/ServiceConfig
     122: dup
     123: invokespecial #111                // Method org/apache/dubbo/config/ServiceConfig."<init>":()V
     126: astore        4
     128: aload         4
     130: aload_0
     131: getfield      #8                  // Field applicationModel:Lorg/apache/dubbo/rpc/model/ApplicationModel;
     134: invokevirtual #112                // Method org/apache/dubbo/rpc/model/ApplicationModel.getInternalModule:()Lorg/apache/dubbo/rpc/model/ModuleModel;
     137: invokevirtual #113                // Method org/apache/dubbo/config/ServiceConfig.setScopeModel:(Lorg/apache/dubbo/rpc/model/ScopeModel;)V
     140: aload         4
     142: aload_3
     143: invokevirtual #114                // Method org/apache/dubbo/config/ServiceConfig.setApplication:(Lorg/apache/dubbo/config/ApplicationConfig;)V
     146: new           #115                // class org/apache/dubbo/config/RegistryConfig
     149: dup
     150: ldc           #116                // String N/A
     152: invokespecial #117                // Method org/apache/dubbo/config/RegistryConfig."<init>":(Ljava/lang/String;)V
     155: astore        5
     157: aload         5
     159: aload_0
     160: getfield      #15                 // Field registryId:Ljava/lang/String;
     163: invokevirtual #118                // Method org/apache/dubbo/config/RegistryConfig.setId:(Ljava/lang/String;)V
     166: aload         5
     168: aload_0
     169: getfield      #8                  // Field applicationModel:Lorg/apache/dubbo/rpc/model/ApplicationModel;
     172: invokevirtual #119                // Method org/apache/dubbo/config/RegistryConfig.setScopeModel:(Lorg/apache/dubbo/rpc/model/ScopeModel;)V
     175: aload         4
     177: aload         5
     179: invokevirtual #120                // Method org/apache/dubbo/config/ServiceConfig.setRegistry:(Lorg/apache/dubbo/config/RegistryConfig;)V
     182: aload         4
     184: iconst_0
     185: invokestatic  #121                // Method java/lang/Boolean.valueOf:(Z)Ljava/lang/Boolean;
     188: invokevirtual #122                // Method org/apache/dubbo/config/ServiceConfig.setRegister:(Ljava/lang/Boolean;)V
     191: aload         4
     193: aload_2
     194: invokevirtual #123                // Method org/apache/dubbo/config/ServiceConfig.setProtocol:(Lorg/apache/dubbo/config/ProtocolConfig;)V
     197: aload         4
     199: iconst_0
     200: invokestatic  #64                 // Method java/lang/Integer.valueOf:(I)Ljava/lang/Integer;
     203: invokevirtual #124                // Method org/apache/dubbo/config/ServiceConfig.setDelay:(Ljava/lang/Integer;)V
     206: aload         4
     208: aload_0
     209: getfield      #11                 // Field interfaceClass:Ljava/lang/Class;
     212: invokevirtual #125                // Method org/apache/dubbo/config/ServiceConfig.setInterface:(Ljava/lang/Class;)V
     215: aload         4
     217: aload_0
     218: getfield      #14                 // Field ref:Ljava/lang/Object;
     221: invokevirtual #126                // Method org/apache/dubbo/config/ServiceConfig.setRef:(Ljava/lang/Object;)V
     224: aload         4
     226: aload_3
     227: invokevirtual #127                // Method org/apache/dubbo/config/ApplicationConfig.getName:()Ljava/lang/String;
     230: invokevirtual #128                // Method org/apache/dubbo/config/ServiceConfig.setGroup:(Ljava/lang/String;)V
     233: aload         4
     235: ldc           #129                // String 1.0.0
     237: invokevirtual #130                // Method org/apache/dubbo/config/ServiceConfig.setVersion:(Ljava/lang/String;)V
     240: aload         4
     242: aload_0
     243: getfield      #13                 // Field executor:Ljava/util/concurrent/Executor;
     246: invokevirtual #131                // Method org/apache/dubbo/config/ServiceConfig.setExecutor:(Ljava/util/concurrent/Executor;)V
     249: aconst_null
     250: aload_1
     251: if_acmpeq     262
     254: aload_1
     255: aload         4
     257: invokeinterface #132,  2          // InterfaceMethod java/util/function/Consumer.accept:(Ljava/lang/Object;)V
     262: aload         4
     264: areturn

  public org.apache.dubbo.config.ServiceConfig<T> build();
    Code:
       0: aload_0
       1: aconst_null
       2: invokevirtual #133                // Method build:(Ljava/util/function/Consumer;)Lorg/apache/dubbo/config/ServiceConfig;
       5: areturn

  private void nullAssert();
    Code:
       0: aload_0
       1: getfield      #62                 // Field port:Ljava/lang/Integer;
       4: ldc           #134                // String export service port is null
       6: invokestatic  #61                 // Method org/apache/dubbo/common/utils/Assert.notNull:(Ljava/lang/Object;Ljava/lang/String;)V
       9: aload_0
      10: getfield      #25                 // Field protocol:Ljava/lang/String;
      13: ldc           #135                // String export service protocol is null
      15: invokestatic  #61                 // Method org/apache/dubbo/common/utils/Assert.notNull:(Ljava/lang/Object;Ljava/lang/String;)V
      18: aload_0
      19: getfield      #11                 // Field interfaceClass:Ljava/lang/Class;
      22: ldc           #136                // String export service interfaceClass is null
      24: invokestatic  #61                 // Method org/apache/dubbo/common/utils/Assert.notNull:(Ljava/lang/Object;Ljava/lang/String;)V
      27: aload_0
      28: getfield      #14                 // Field ref:Ljava/lang/Object;
      31: ldc           #137                // String export service ref is null
      33: invokestatic  #61                 // Method org/apache/dubbo/common/utils/Assert.notNull:(Ljava/lang/Object;Ljava/lang/String;)V
      36: aload_0
      37: getfield      #15                 // Field registryId:Ljava/lang/String;
      40: ldc           #138                // String export service registryId is null
      42: invokestatic  #61                 // Method org/apache/dubbo/common/utils/Assert.notNull:(Ljava/lang/Object;Ljava/lang/String;)V
      45: return

  protected org.apache.dubbo.config.bootstrap.builders.InternalServiceConfigBuilder<T> getThis();
    Code:
       0: aload_0
       1: areturn

  private org.apache.dubbo.config.ApplicationConfig getApplicationConfig();
    Code:
       0: aload_0
       1: getfield      #8                  // Field applicationModel:Lorg/apache/dubbo/rpc/model/ApplicationModel;
       4: invokevirtual #45                 // Method org/apache/dubbo/rpc/model/ApplicationModel.getApplicationConfigManager:()Lorg/apache/dubbo/config/context/ConfigManager;
       7: invokevirtual #139                // Method org/apache/dubbo/config/context/ConfigManager.getApplicationOrElseThrow:()Lorg/apache/dubbo/config/ApplicationConfig;
      10: areturn

  private static boolean lambda$getRelatedOrDefaultProtocol$4(java.lang.String);
    Code:
       0: getstatic     #53                 // Field UNACCEPTABLE_PROTOCOL:Ljava/util/Set;
       3: aload_0
       4: invokeinterface #54,  2           // InterfaceMethod java/util/Set.contains:(Ljava/lang/Object;)Z
       9: ifne          16
      12: iconst_1
      13: goto          17
      16: iconst_0
      17: ireturn

  private static boolean lambda$getRelatedOrDefaultProtocol$3(java.lang.String);
    Code:
       0: getstatic     #53                 // Field UNACCEPTABLE_PROTOCOL:Ljava/util/Set;
       3: aload_0
       4: invokeinterface #54,  2           // InterfaceMethod java/util/Set.contains:(Ljava/lang/Object;)Z
       9: ifne          16
      12: iconst_1
      13: goto          17
      16: iconst_0
      17: ireturn

  private static java.lang.String lambda$getRelatedOrDefaultProtocol$2(org.apache.dubbo.config.ProviderConfig);
    Code:
       0: aload_0
       1: invokevirtual #140                // Method org/apache/dubbo/config/ProviderConfig.getProtocol:()Lorg/apache/dubbo/config/ProtocolConfig;
       4: ifnull        28
       7: aload_0
       8: invokevirtual #140                // Method org/apache/dubbo/config/ProviderConfig.getProtocol:()Lorg/apache/dubbo/config/ProtocolConfig;
      11: invokevirtual #141                // Method org/apache/dubbo/config/ProtocolConfig.getName:()Ljava/lang/String;
      14: invokestatic  #23                 // Method org/apache/dubbo/common/utils/StringUtils.isNotEmpty:(Ljava/lang/String;)Z
      17: ifeq          28
      20: aload_0
      21: invokevirtual #140                // Method org/apache/dubbo/config/ProviderConfig.getProtocol:()Lorg/apache/dubbo/config/ProtocolConfig;
      24: invokevirtual #141                // Method org/apache/dubbo/config/ProtocolConfig.getName:()Ljava/lang/String;
      27: areturn
      28: aload_0
      29: invokevirtual #142                // Method org/apache/dubbo/config/ProviderConfig.getProtocols:()Ljava/util/List;
      32: invokeinterface #28,  1           // InterfaceMethod java/util/List.stream:()Ljava/util/stream/Stream;
      37: invokedynamic #49,  0             // InvokeDynamic #11:apply:()Ljava/util/function/Function;
      42: invokeinterface #30,  2           // InterfaceMethod java/util/stream/Stream.map:(Ljava/util/function/Function;)Ljava/util/stream/Stream;
      47: invokedynamic #37,  0             // InvokeDynamic #5:test:()Ljava/util/function/Predicate;
      52: invokeinterface #33,  2           // InterfaceMethod java/util/stream/Stream.filter:(Ljava/util/function/Predicate;)Ljava/util/stream/Stream;
      57: invokeinterface #39,  1           // InterfaceMethod java/util/stream/Stream.findFirst:()Ljava/util/Optional;
      62: ldc           #26                 // String
      64: invokevirtual #40                 // Method java/util/Optional.orElse:(Ljava/lang/Object;)Ljava/lang/Object;
      67: checkcast     #22                 // class java/lang/String
      70: areturn

  private static boolean lambda$getRelatedOrDefaultProtocol$1(org.apache.dubbo.config.ProviderConfig);
    Code:
       0: aload_0
       1: invokevirtual #140                // Method org/apache/dubbo/config/ProviderConfig.getProtocol:()Lorg/apache/dubbo/config/ProtocolConfig;
       4: ifnonnull     17
       7: aload_0
       8: invokevirtual #142                // Method org/apache/dubbo/config/ProviderConfig.getProtocols:()Ljava/util/List;
      11: invokestatic  #47                 // Method org/apache/dubbo/common/utils/CollectionUtils.isNotEmpty:(Ljava/util/Collection;)Z
      14: ifeq          21
      17: iconst_1
      18: goto          22
      21: iconst_0
      22: ireturn

  private static boolean lambda$getRelatedOrDefaultProtocol$0(java.lang.String);
    Code:
       0: getstatic     #53                 // Field UNACCEPTABLE_PROTOCOL:Ljava/util/Set;
       3: aload_0
       4: invokeinterface #54,  2           // InterfaceMethod java/util/Set.contains:(Ljava/lang/Object;)Z
       9: ifne          16
      12: iconst_1
      13: goto          17
      16: iconst_0
      17: ireturn

  static {};
    Code:
       0: iconst_2
       1: anewarray     #22                 // class java/lang/String
       4: dup
       5: iconst_0
       6: ldc           #143                // String rest
       8: aastore
       9: dup
      10: iconst_1
      11: ldc           #144                // String grpc
      13: aastore
      14: invokestatic  #145                // InterfaceMethod java/util/stream/Stream.of:([Ljava/lang/Object;)Ljava/util/stream/Stream;
      17: invokestatic  #146                // Method java/util/stream/Collectors.toSet:()Ljava/util/stream/Collector;
      20: invokeinterface #147,  2          // InterfaceMethod java/util/stream/Stream.collect:(Ljava/util/stream/Collector;)Ljava/lang/Object;
      25: checkcast     #148                // class java/util/Set
      28: putstatic     #53                 // Field UNACCEPTABLE_PROTOCOL:Ljava/util/Set;
      31: return
}
