Compiled from "MetadataReportBuilder.java"
public class org.apache.dubbo.config.bootstrap.builders.MetadataReportBuilder extends org.apache.dubbo.config.bootstrap.builders.AbstractBuilder<org.apache.dubbo.config.MetadataReportConfig, org.apache.dubbo.config.bootstrap.builders.MetadataReportBuilder> {
  private java.lang.String address;

  private java.lang.String username;

  private java.lang.String password;

  private java.lang.Integer timeout;

  private java.lang.String group;

  private java.util.Map<java.lang.String, java.lang.String> parameters;

  private java.lang.Integer retryTimes;

  private java.lang.Integer retryPeriod;

  private java.lang.Boolean cycleReport;

  private java.lang.Boolean syncReport;

  private java.lang.Boolean check;

  public org.apache.dubbo.config.bootstrap.builders.MetadataReportBuilder();
    Code:
       0: aload_0
       1: invokespecial #1                  // Method org/apache/dubbo/config/bootstrap/builders/AbstractBuilder."<init>":()V
       4: return

  public static org.apache.dubbo.config.bootstrap.builders.MetadataReportBuilder newBuilder();
    Code:
       0: new           #2                  // class org/apache/dubbo/config/bootstrap/builders/MetadataReportBuilder
       3: dup
       4: invokespecial #3                  // Method "<init>":()V
       7: areturn

  public org.apache.dubbo.config.bootstrap.builders.MetadataReportBuilder address(java.lang.String);
    Code:
       0: aload_0
       1: aload_1
       2: putfield      #4                  // Field address:Ljava/lang/String;
       5: aload_0
       6: invokevirtual #5                  // Method getThis:()Lorg/apache/dubbo/config/bootstrap/builders/MetadataReportBuilder;
       9: areturn

  public org.apache.dubbo.config.bootstrap.builders.MetadataReportBuilder username(java.lang.String);
    Code:
       0: aload_0
       1: aload_1
       2: putfield      #6                  // Field username:Ljava/lang/String;
       5: aload_0
       6: invokevirtual #5                  // Method getThis:()Lorg/apache/dubbo/config/bootstrap/builders/MetadataReportBuilder;
       9: areturn

  public org.apache.dubbo.config.bootstrap.builders.MetadataReportBuilder password(java.lang.String);
    Code:
       0: aload_0
       1: aload_1
       2: putfield      #7                  // Field password:Ljava/lang/String;
       5: aload_0
       6: invokevirtual #5                  // Method getThis:()Lorg/apache/dubbo/config/bootstrap/builders/MetadataReportBuilder;
       9: areturn

  public org.apache.dubbo.config.bootstrap.builders.MetadataReportBuilder timeout(java.lang.Integer);
    Code:
       0: aload_0
       1: aload_1
       2: putfield      #8                  // Field timeout:Ljava/lang/Integer;
       5: aload_0
       6: invokevirtual #5                  // Method getThis:()Lorg/apache/dubbo/config/bootstrap/builders/MetadataReportBuilder;
       9: areturn

  public org.apache.dubbo.config.bootstrap.builders.MetadataReportBuilder group(java.lang.String);
    Code:
       0: aload_0
       1: aload_1
       2: putfield      #9                  // Field group:Ljava/lang/String;
       5: aload_0
       6: invokevirtual #5                  // Method getThis:()Lorg/apache/dubbo/config/bootstrap/builders/MetadataReportBuilder;
       9: areturn

  public org.apache.dubbo.config.bootstrap.builders.MetadataReportBuilder appendParameters(java.util.Map<java.lang.String, java.lang.String>);
    Code:
       0: aload_0
       1: aload_0
       2: getfield      #10                 // Field parameters:Ljava/util/Map;
       5: aload_1
       6: invokestatic  #11                 // Method appendParameters:(Ljava/util/Map;Ljava/util/Map;)Ljava/util/Map;
       9: putfield      #10                 // Field parameters:Ljava/util/Map;
      12: aload_0
      13: invokevirtual #5                  // Method getThis:()Lorg/apache/dubbo/config/bootstrap/builders/MetadataReportBuilder;
      16: areturn

  public org.apache.dubbo.config.bootstrap.builders.MetadataReportBuilder appendParameter(java.lang.String, java.lang.String);
    Code:
       0: aload_0
       1: aload_0
       2: getfield      #10                 // Field parameters:Ljava/util/Map;
       5: aload_1
       6: aload_2
       7: invokestatic  #12                 // Method appendParameter:(Ljava/util/Map;Ljava/lang/String;Ljava/lang/String;)Ljava/util/Map;
      10: putfield      #10                 // Field parameters:Ljava/util/Map;
      13: aload_0
      14: invokevirtual #5                  // Method getThis:()Lorg/apache/dubbo/config/bootstrap/builders/MetadataReportBuilder;
      17: areturn

  public org.apache.dubbo.config.bootstrap.builders.MetadataReportBuilder retryTimes(java.lang.Integer);
    Code:
       0: aload_0
       1: aload_1
       2: putfield      #13                 // Field retryTimes:Ljava/lang/Integer;
       5: aload_0
       6: invokevirtual #5                  // Method getThis:()Lorg/apache/dubbo/config/bootstrap/builders/MetadataReportBuilder;
       9: areturn

  public org.apache.dubbo.config.bootstrap.builders.MetadataReportBuilder retryPeriod(java.lang.Integer);
    Code:
       0: aload_0
       1: aload_1
       2: putfield      #14                 // Field retryPeriod:Ljava/lang/Integer;
       5: aload_0
       6: invokevirtual #5                  // Method getThis:()Lorg/apache/dubbo/config/bootstrap/builders/MetadataReportBuilder;
       9: areturn

  public org.apache.dubbo.config.bootstrap.builders.MetadataReportBuilder cycleReport(java.lang.Boolean);
    Code:
       0: aload_0
       1: aload_1
       2: putfield      #15                 // Field cycleReport:Ljava/lang/Boolean;
       5: aload_0
       6: invokevirtual #5                  // Method getThis:()Lorg/apache/dubbo/config/bootstrap/builders/MetadataReportBuilder;
       9: areturn

  public org.apache.dubbo.config.bootstrap.builders.MetadataReportBuilder syncReport(java.lang.Boolean);
    Code:
       0: aload_0
       1: aload_1
       2: putfield      #16                 // Field syncReport:Ljava/lang/Boolean;
       5: aload_0
       6: invokevirtual #5                  // Method getThis:()Lorg/apache/dubbo/config/bootstrap/builders/MetadataReportBuilder;
       9: areturn

  public org.apache.dubbo.config.bootstrap.builders.MetadataReportBuilder check(java.lang.Boolean);
    Code:
       0: aload_0
       1: aload_1
       2: putfield      #17                 // Field check:Ljava/lang/Boolean;
       5: aload_0
       6: invokevirtual #5                  // Method getThis:()Lorg/apache/dubbo/config/bootstrap/builders/MetadataReportBuilder;
       9: areturn

  public org.apache.dubbo.config.MetadataReportConfig build();
    Code:
       0: new           #18                 // class org/apache/dubbo/config/MetadataReportConfig
       3: dup
       4: invokespecial #19                 // Method org/apache/dubbo/config/MetadataReportConfig."<init>":()V
       7: astore_1
       8: aload_0
       9: aload_1
      10: invokespecial #20                 // Method org/apache/dubbo/config/bootstrap/builders/AbstractBuilder.build:(Lorg/apache/dubbo/config/AbstractConfig;)V
      13: aload_1
      14: aload_0
      15: getfield      #4                  // Field address:Ljava/lang/String;
      18: invokevirtual #21                 // Method org/apache/dubbo/config/MetadataReportConfig.setAddress:(Ljava/lang/String;)V
      21: aload_1
      22: aload_0
      23: getfield      #6                  // Field username:Ljava/lang/String;
      26: invokevirtual #22                 // Method org/apache/dubbo/config/MetadataReportConfig.setUsername:(Ljava/lang/String;)V
      29: aload_1
      30: aload_0
      31: getfield      #7                  // Field password:Ljava/lang/String;
      34: invokevirtual #23                 // Method org/apache/dubbo/config/MetadataReportConfig.setPassword:(Ljava/lang/String;)V
      37: aload_1
      38: aload_0
      39: getfield      #8                  // Field timeout:Ljava/lang/Integer;
      42: invokevirtual #24                 // Method org/apache/dubbo/config/MetadataReportConfig.setTimeout:(Ljava/lang/Integer;)V
      45: aload_1
      46: aload_0
      47: getfield      #9                  // Field group:Ljava/lang/String;
      50: invokevirtual #25                 // Method org/apache/dubbo/config/MetadataReportConfig.setGroup:(Ljava/lang/String;)V
      53: aload_1
      54: aload_0
      55: getfield      #10                 // Field parameters:Ljava/util/Map;
      58: invokevirtual #26                 // Method org/apache/dubbo/config/MetadataReportConfig.setParameters:(Ljava/util/Map;)V
      61: aload_1
      62: aload_0
      63: getfield      #13                 // Field retryTimes:Ljava/lang/Integer;
      66: invokevirtual #27                 // Method org/apache/dubbo/config/MetadataReportConfig.setRetryTimes:(Ljava/lang/Integer;)V
      69: aload_1
      70: aload_0
      71: getfield      #14                 // Field retryPeriod:Ljava/lang/Integer;
      74: invokevirtual #28                 // Method org/apache/dubbo/config/MetadataReportConfig.setRetryPeriod:(Ljava/lang/Integer;)V
      77: aload_1
      78: aload_0
      79: getfield      #15                 // Field cycleReport:Ljava/lang/Boolean;
      82: invokevirtual #29                 // Method org/apache/dubbo/config/MetadataReportConfig.setCycleReport:(Ljava/lang/Boolean;)V
      85: aload_1
      86: aload_0
      87: getfield      #16                 // Field syncReport:Ljava/lang/Boolean;
      90: invokevirtual #30                 // Method org/apache/dubbo/config/MetadataReportConfig.setSyncReport:(Ljava/lang/Boolean;)V
      93: aload_1
      94: aload_0
      95: getfield      #17                 // Field check:Ljava/lang/Boolean;
      98: invokevirtual #31                 // Method org/apache/dubbo/config/MetadataReportConfig.setCheck:(Ljava/lang/Boolean;)V
     101: aload_1
     102: areturn

  protected org.apache.dubbo.config.bootstrap.builders.MetadataReportBuilder getThis();
    Code:
       0: aload_0
       1: areturn

  public org.apache.dubbo.config.AbstractConfig build();
    Code:
       0: aload_0
       1: invokevirtual #32                 // Method build:()Lorg/apache/dubbo/config/MetadataReportConfig;
       4: areturn

  protected org.apache.dubbo.config.bootstrap.builders.AbstractBuilder getThis();
    Code:
       0: aload_0
       1: invokevirtual #5                  // Method getThis:()Lorg/apache/dubbo/config/bootstrap/builders/MetadataReportBuilder;
       4: areturn
}
