Compiled from "MethodBuilder.java"
public class org.apache.dubbo.config.bootstrap.builders.MethodBuilder extends org.apache.dubbo.config.bootstrap.builders.AbstractMethodBuilder<org.apache.dubbo.config.MethodConfig, org.apache.dubbo.config.bootstrap.builders.MethodBuilder> {
  private java.lang.String name;

  private java.lang.Integer stat;

  private java.lang.Boolean retry;

  private java.lang.Boolean reliable;

  private java.lang.Integer executes;

  private java.lang.Boolean deprecated;

  private java.lang.Boolean sticky;

  private java.lang.Boolean isReturn;

  private java.lang.Object oninvoke;

  private java.lang.String oninvokeMethod;

  private java.lang.Object onreturn;

  private java.lang.String onreturnMethod;

  private java.lang.Object onthrow;

  private java.lang.String onthrowMethod;

  private java.util.List<org.apache.dubbo.config.ArgumentConfig> arguments;

  private java.lang.String service;

  private java.lang.String serviceId;

  public org.apache.dubbo.config.bootstrap.builders.MethodBuilder();
    Code:
       0: aload_0
       1: invokespecial #1                  // Method org/apache/dubbo/config/bootstrap/builders/AbstractMethodBuilder."<init>":()V
       4: return

  public org.apache.dubbo.config.bootstrap.builders.MethodBuilder name(java.lang.String);
    Code:
       0: aload_0
       1: aload_1
       2: putfield      #2                  // Field name:Ljava/lang/String;
       5: aload_0
       6: invokevirtual #3                  // Method getThis:()Lorg/apache/dubbo/config/bootstrap/builders/MethodBuilder;
       9: areturn

  public org.apache.dubbo.config.bootstrap.builders.MethodBuilder stat(java.lang.Integer);
    Code:
       0: aload_0
       1: aload_1
       2: putfield      #4                  // Field stat:Ljava/lang/Integer;
       5: aload_0
       6: invokevirtual #3                  // Method getThis:()Lorg/apache/dubbo/config/bootstrap/builders/MethodBuilder;
       9: areturn

  public org.apache.dubbo.config.bootstrap.builders.MethodBuilder retry(java.lang.Boolean);
    Code:
       0: aload_0
       1: aload_1
       2: putfield      #5                  // Field retry:Ljava/lang/Boolean;
       5: aload_0
       6: invokevirtual #3                  // Method getThis:()Lorg/apache/dubbo/config/bootstrap/builders/MethodBuilder;
       9: areturn

  public org.apache.dubbo.config.bootstrap.builders.MethodBuilder reliable(java.lang.Boolean);
    Code:
       0: aload_0
       1: aload_1
       2: putfield      #6                  // Field reliable:Ljava/lang/Boolean;
       5: aload_0
       6: invokevirtual #3                  // Method getThis:()Lorg/apache/dubbo/config/bootstrap/builders/MethodBuilder;
       9: areturn

  public org.apache.dubbo.config.bootstrap.builders.MethodBuilder executes(java.lang.Integer);
    Code:
       0: aload_0
       1: aload_1
       2: putfield      #7                  // Field executes:Ljava/lang/Integer;
       5: aload_0
       6: invokevirtual #3                  // Method getThis:()Lorg/apache/dubbo/config/bootstrap/builders/MethodBuilder;
       9: areturn

  public org.apache.dubbo.config.bootstrap.builders.MethodBuilder deprecated(java.lang.Boolean);
    Code:
       0: aload_0
       1: aload_1
       2: putfield      #8                  // Field deprecated:Ljava/lang/Boolean;
       5: aload_0
       6: invokevirtual #3                  // Method getThis:()Lorg/apache/dubbo/config/bootstrap/builders/MethodBuilder;
       9: areturn

  public org.apache.dubbo.config.bootstrap.builders.MethodBuilder sticky(java.lang.Boolean);
    Code:
       0: aload_0
       1: aload_1
       2: putfield      #9                  // Field sticky:Ljava/lang/Boolean;
       5: aload_0
       6: invokevirtual #3                  // Method getThis:()Lorg/apache/dubbo/config/bootstrap/builders/MethodBuilder;
       9: areturn

  public org.apache.dubbo.config.bootstrap.builders.MethodBuilder isReturn(java.lang.Boolean);
    Code:
       0: aload_0
       1: aload_1
       2: putfield      #10                 // Field isReturn:Ljava/lang/Boolean;
       5: aload_0
       6: invokevirtual #3                  // Method getThis:()Lorg/apache/dubbo/config/bootstrap/builders/MethodBuilder;
       9: areturn

  public org.apache.dubbo.config.bootstrap.builders.MethodBuilder oninvoke(java.lang.Object);
    Code:
       0: aload_0
       1: aload_1
       2: putfield      #11                 // Field oninvoke:Ljava/lang/Object;
       5: aload_0
       6: invokevirtual #3                  // Method getThis:()Lorg/apache/dubbo/config/bootstrap/builders/MethodBuilder;
       9: areturn

  public org.apache.dubbo.config.bootstrap.builders.MethodBuilder oninvokeMethod(java.lang.String);
    Code:
       0: aload_0
       1: aload_1
       2: putfield      #12                 // Field oninvokeMethod:Ljava/lang/String;
       5: aload_0
       6: invokevirtual #3                  // Method getThis:()Lorg/apache/dubbo/config/bootstrap/builders/MethodBuilder;
       9: areturn

  public org.apache.dubbo.config.bootstrap.builders.MethodBuilder onreturn(java.lang.Object);
    Code:
       0: aload_0
       1: aload_1
       2: putfield      #13                 // Field onreturn:Ljava/lang/Object;
       5: aload_0
       6: invokevirtual #3                  // Method getThis:()Lorg/apache/dubbo/config/bootstrap/builders/MethodBuilder;
       9: areturn

  public org.apache.dubbo.config.bootstrap.builders.MethodBuilder onreturnMethod(java.lang.String);
    Code:
       0: aload_0
       1: aload_1
       2: putfield      #14                 // Field onreturnMethod:Ljava/lang/String;
       5: aload_0
       6: invokevirtual #3                  // Method getThis:()Lorg/apache/dubbo/config/bootstrap/builders/MethodBuilder;
       9: areturn

  public org.apache.dubbo.config.bootstrap.builders.MethodBuilder onthrow(java.lang.Object);
    Code:
       0: aload_0
       1: aload_1
       2: putfield      #15                 // Field onthrow:Ljava/lang/Object;
       5: aload_0
       6: invokevirtual #3                  // Method getThis:()Lorg/apache/dubbo/config/bootstrap/builders/MethodBuilder;
       9: areturn

  public org.apache.dubbo.config.bootstrap.builders.MethodBuilder onthrowMethod(java.lang.String);
    Code:
       0: aload_0
       1: aload_1
       2: putfield      #16                 // Field onthrowMethod:Ljava/lang/String;
       5: aload_0
       6: invokevirtual #3                  // Method getThis:()Lorg/apache/dubbo/config/bootstrap/builders/MethodBuilder;
       9: areturn

  public org.apache.dubbo.config.bootstrap.builders.MethodBuilder addArguments(java.util.List<? extends org.apache.dubbo.config.ArgumentConfig>);
    Code:
       0: aload_0
       1: getfield      #17                 // Field arguments:Ljava/util/List;
       4: ifnonnull     18
       7: aload_0
       8: new           #18                 // class java/util/ArrayList
      11: dup
      12: invokespecial #19                 // Method java/util/ArrayList."<init>":()V
      15: putfield      #17                 // Field arguments:Ljava/util/List;
      18: aload_0
      19: getfield      #17                 // Field arguments:Ljava/util/List;
      22: aload_1
      23: invokeinterface #20,  2           // InterfaceMethod java/util/List.addAll:(Ljava/util/Collection;)Z
      28: pop
      29: aload_0
      30: invokevirtual #3                  // Method getThis:()Lorg/apache/dubbo/config/bootstrap/builders/MethodBuilder;
      33: areturn

  public org.apache.dubbo.config.bootstrap.builders.MethodBuilder addArgument(org.apache.dubbo.config.ArgumentConfig);
    Code:
       0: aload_0
       1: getfield      #17                 // Field arguments:Ljava/util/List;
       4: ifnonnull     18
       7: aload_0
       8: new           #18                 // class java/util/ArrayList
      11: dup
      12: invokespecial #19                 // Method java/util/ArrayList."<init>":()V
      15: putfield      #17                 // Field arguments:Ljava/util/List;
      18: aload_0
      19: getfield      #17                 // Field arguments:Ljava/util/List;
      22: aload_1
      23: invokeinterface #21,  2           // InterfaceMethod java/util/List.add:(Ljava/lang/Object;)Z
      28: pop
      29: aload_0
      30: invokevirtual #3                  // Method getThis:()Lorg/apache/dubbo/config/bootstrap/builders/MethodBuilder;
      33: areturn

  public org.apache.dubbo.config.bootstrap.builders.MethodBuilder service(java.lang.String);
    Code:
       0: aload_0
       1: aload_1
       2: putfield      #22                 // Field service:Ljava/lang/String;
       5: aload_0
       6: invokevirtual #3                  // Method getThis:()Lorg/apache/dubbo/config/bootstrap/builders/MethodBuilder;
       9: areturn

  public org.apache.dubbo.config.bootstrap.builders.MethodBuilder serviceId(java.lang.String);
    Code:
       0: aload_0
       1: aload_1
       2: putfield      #23                 // Field serviceId:Ljava/lang/String;
       5: aload_0
       6: invokevirtual #3                  // Method getThis:()Lorg/apache/dubbo/config/bootstrap/builders/MethodBuilder;
       9: areturn

  public org.apache.dubbo.config.MethodConfig build();
    Code:
       0: new           #24                 // class org/apache/dubbo/config/MethodConfig
       3: dup
       4: invokespecial #25                 // Method org/apache/dubbo/config/MethodConfig."<init>":()V
       7: astore_1
       8: aload_0
       9: aload_1
      10: invokespecial #26                 // Method org/apache/dubbo/config/bootstrap/builders/AbstractMethodBuilder.build:(Lorg/apache/dubbo/config/AbstractMethodConfig;)V
      13: aload_1
      14: aload_0
      15: getfield      #17                 // Field arguments:Ljava/util/List;
      18: invokevirtual #27                 // Method org/apache/dubbo/config/MethodConfig.setArguments:(Ljava/util/List;)V
      21: aload_1
      22: aload_0
      23: getfield      #8                  // Field deprecated:Ljava/lang/Boolean;
      26: invokevirtual #28                 // Method org/apache/dubbo/config/MethodConfig.setDeprecated:(Ljava/lang/Boolean;)V
      29: aload_1
      30: aload_0
      31: getfield      #7                  // Field executes:Ljava/lang/Integer;
      34: invokevirtual #29                 // Method org/apache/dubbo/config/MethodConfig.setExecutes:(Ljava/lang/Integer;)V
      37: aload_1
      38: aload_0
      39: getfield      #2                  // Field name:Ljava/lang/String;
      42: invokevirtual #30                 // Method org/apache/dubbo/config/MethodConfig.setName:(Ljava/lang/String;)V
      45: aload_1
      46: aload_0
      47: getfield      #11                 // Field oninvoke:Ljava/lang/Object;
      50: invokevirtual #31                 // Method org/apache/dubbo/config/MethodConfig.setOninvoke:(Ljava/lang/Object;)V
      53: aload_1
      54: aload_0
      55: getfield      #12                 // Field oninvokeMethod:Ljava/lang/String;
      58: invokevirtual #32                 // Method org/apache/dubbo/config/MethodConfig.setOninvokeMethod:(Ljava/lang/String;)V
      61: aload_1
      62: aload_0
      63: getfield      #13                 // Field onreturn:Ljava/lang/Object;
      66: invokevirtual #33                 // Method org/apache/dubbo/config/MethodConfig.setOnreturn:(Ljava/lang/Object;)V
      69: aload_1
      70: aload_0
      71: getfield      #14                 // Field onreturnMethod:Ljava/lang/String;
      74: invokevirtual #34                 // Method org/apache/dubbo/config/MethodConfig.setOnreturnMethod:(Ljava/lang/String;)V
      77: aload_1
      78: aload_0
      79: getfield      #15                 // Field onthrow:Ljava/lang/Object;
      82: invokevirtual #35                 // Method org/apache/dubbo/config/MethodConfig.setOnthrow:(Ljava/lang/Object;)V
      85: aload_1
      86: aload_0
      87: getfield      #16                 // Field onthrowMethod:Ljava/lang/String;
      90: invokevirtual #36                 // Method org/apache/dubbo/config/MethodConfig.setOnthrowMethod:(Ljava/lang/String;)V
      93: aload_1
      94: aload_0
      95: getfield      #10                 // Field isReturn:Ljava/lang/Boolean;
      98: invokevirtual #37                 // Method org/apache/dubbo/config/MethodConfig.setReturn:(Ljava/lang/Boolean;)V
     101: aload_1
     102: aload_0
     103: getfield      #22                 // Field service:Ljava/lang/String;
     106: invokevirtual #38                 // Method org/apache/dubbo/config/MethodConfig.setService:(Ljava/lang/String;)V
     109: aload_1
     110: aload_0
     111: getfield      #23                 // Field serviceId:Ljava/lang/String;
     114: invokevirtual #39                 // Method org/apache/dubbo/config/MethodConfig.setServiceId:(Ljava/lang/String;)V
     117: aload_1
     118: aload_0
     119: getfield      #9                  // Field sticky:Ljava/lang/Boolean;
     122: invokevirtual #40                 // Method org/apache/dubbo/config/MethodConfig.setSticky:(Ljava/lang/Boolean;)V
     125: aload_1
     126: aload_0
     127: getfield      #6                  // Field reliable:Ljava/lang/Boolean;
     130: invokevirtual #41                 // Method org/apache/dubbo/config/MethodConfig.setReliable:(Ljava/lang/Boolean;)V
     133: aload_1
     134: aload_0
     135: getfield      #4                  // Field stat:Ljava/lang/Integer;
     138: invokevirtual #42                 // Method org/apache/dubbo/config/MethodConfig.setStat:(Ljava/lang/Integer;)V
     141: aload_1
     142: aload_0
     143: getfield      #5                  // Field retry:Ljava/lang/Boolean;
     146: invokevirtual #43                 // Method org/apache/dubbo/config/MethodConfig.setRetry:(Ljava/lang/Boolean;)V
     149: aload_1
     150: areturn

  protected org.apache.dubbo.config.bootstrap.builders.MethodBuilder getThis();
    Code:
       0: aload_0
       1: areturn

  public org.apache.dubbo.config.AbstractConfig build();
    Code:
       0: aload_0
       1: invokevirtual #44                 // Method build:()Lorg/apache/dubbo/config/MethodConfig;
       4: areturn

  protected org.apache.dubbo.config.bootstrap.builders.AbstractBuilder getThis();
    Code:
       0: aload_0
       1: invokevirtual #3                  // Method getThis:()Lorg/apache/dubbo/config/bootstrap/builders/MethodBuilder;
       4: areturn
}
