Compiled from "ModuleBuilder.java"
public class org.apache.dubbo.config.bootstrap.builders.ModuleBuilder extends org.apache.dubbo.config.bootstrap.builders.AbstractBuilder<org.apache.dubbo.config.ModuleConfig, org.apache.dubbo.config.bootstrap.builders.ModuleBuilder> {
  private java.lang.String name;

  private java.lang.String version;

  private java.lang.String owner;

  private java.lang.String organization;

  private java.util.List<org.apache.dubbo.config.RegistryConfig> registries;

  private org.apache.dubbo.config.MonitorConfig monitor;

  private java.lang.Boolean isDefault;

  public org.apache.dubbo.config.bootstrap.builders.ModuleBuilder();
    Code:
       0: aload_0
       1: invokespecial #1                  // Method org/apache/dubbo/config/bootstrap/builders/AbstractBuilder."<init>":()V
       4: return

  public org.apache.dubbo.config.bootstrap.builders.ModuleBuilder name(java.lang.String);
    Code:
       0: aload_0
       1: aload_1
       2: putfield      #2                  // Field name:Ljava/lang/String;
       5: aload_0
       6: invokevirtual #3                  // Method getThis:()Lorg/apache/dubbo/config/bootstrap/builders/ModuleBuilder;
       9: areturn

  public org.apache.dubbo.config.bootstrap.builders.ModuleBuilder version(java.lang.String);
    Code:
       0: aload_0
       1: aload_1
       2: putfield      #4                  // Field version:Ljava/lang/String;
       5: aload_0
       6: invokevirtual #3                  // Method getThis:()Lorg/apache/dubbo/config/bootstrap/builders/ModuleBuilder;
       9: areturn

  public org.apache.dubbo.config.bootstrap.builders.ModuleBuilder owner(java.lang.String);
    Code:
       0: aload_0
       1: aload_1
       2: putfield      #5                  // Field owner:Ljava/lang/String;
       5: aload_0
       6: invokevirtual #3                  // Method getThis:()Lorg/apache/dubbo/config/bootstrap/builders/ModuleBuilder;
       9: areturn

  public org.apache.dubbo.config.bootstrap.builders.ModuleBuilder organization(java.lang.String);
    Code:
       0: aload_0
       1: aload_1
       2: putfield      #6                  // Field organization:Ljava/lang/String;
       5: aload_0
       6: invokevirtual #3                  // Method getThis:()Lorg/apache/dubbo/config/bootstrap/builders/ModuleBuilder;
       9: areturn

  public org.apache.dubbo.config.bootstrap.builders.ModuleBuilder addRegistries(java.util.List<? extends org.apache.dubbo.config.RegistryConfig>);
    Code:
       0: aload_0
       1: getfield      #7                  // Field registries:Ljava/util/List;
       4: ifnonnull     18
       7: aload_0
       8: new           #8                  // class java/util/ArrayList
      11: dup
      12: invokespecial #9                  // Method java/util/ArrayList."<init>":()V
      15: putfield      #7                  // Field registries:Ljava/util/List;
      18: aload_0
      19: getfield      #7                  // Field registries:Ljava/util/List;
      22: aload_1
      23: invokeinterface #10,  2           // InterfaceMethod java/util/List.addAll:(Ljava/util/Collection;)Z
      28: pop
      29: aload_0
      30: invokevirtual #3                  // Method getThis:()Lorg/apache/dubbo/config/bootstrap/builders/ModuleBuilder;
      33: areturn

  public org.apache.dubbo.config.bootstrap.builders.ModuleBuilder addRegistry(org.apache.dubbo.config.RegistryConfig);
    Code:
       0: aload_0
       1: getfield      #7                  // Field registries:Ljava/util/List;
       4: ifnonnull     18
       7: aload_0
       8: new           #8                  // class java/util/ArrayList
      11: dup
      12: invokespecial #9                  // Method java/util/ArrayList."<init>":()V
      15: putfield      #7                  // Field registries:Ljava/util/List;
      18: aload_0
      19: getfield      #7                  // Field registries:Ljava/util/List;
      22: aload_1
      23: invokeinterface #11,  2           // InterfaceMethod java/util/List.add:(Ljava/lang/Object;)Z
      28: pop
      29: aload_0
      30: invokevirtual #3                  // Method getThis:()Lorg/apache/dubbo/config/bootstrap/builders/ModuleBuilder;
      33: areturn

  public org.apache.dubbo.config.bootstrap.builders.ModuleBuilder monitor(org.apache.dubbo.config.MonitorConfig);
    Code:
       0: aload_0
       1: aload_1
       2: putfield      #12                 // Field monitor:Lorg/apache/dubbo/config/MonitorConfig;
       5: aload_0
       6: invokevirtual #3                  // Method getThis:()Lorg/apache/dubbo/config/bootstrap/builders/ModuleBuilder;
       9: areturn

  public org.apache.dubbo.config.bootstrap.builders.ModuleBuilder isDefault(java.lang.Boolean);
    Code:
       0: aload_0
       1: aload_1
       2: putfield      #13                 // Field isDefault:Ljava/lang/Boolean;
       5: aload_0
       6: invokevirtual #3                  // Method getThis:()Lorg/apache/dubbo/config/bootstrap/builders/ModuleBuilder;
       9: areturn

  public org.apache.dubbo.config.ModuleConfig build();
    Code:
       0: new           #14                 // class org/apache/dubbo/config/ModuleConfig
       3: dup
       4: invokespecial #15                 // Method org/apache/dubbo/config/ModuleConfig."<init>":()V
       7: astore_1
       8: aload_0
       9: aload_1
      10: invokespecial #16                 // Method org/apache/dubbo/config/bootstrap/builders/AbstractBuilder.build:(Lorg/apache/dubbo/config/AbstractConfig;)V
      13: aload_1
      14: aload_0
      15: getfield      #13                 // Field isDefault:Ljava/lang/Boolean;
      18: invokevirtual #17                 // Method org/apache/dubbo/config/ModuleConfig.setDefault:(Ljava/lang/Boolean;)V
      21: aload_1
      22: aload_0
      23: getfield      #12                 // Field monitor:Lorg/apache/dubbo/config/MonitorConfig;
      26: invokevirtual #18                 // Method org/apache/dubbo/config/ModuleConfig.setMonitor:(Lorg/apache/dubbo/config/MonitorConfig;)V
      29: aload_1
      30: aload_0
      31: getfield      #2                  // Field name:Ljava/lang/String;
      34: invokevirtual #19                 // Method org/apache/dubbo/config/ModuleConfig.setName:(Ljava/lang/String;)V
      37: aload_1
      38: aload_0
      39: getfield      #6                  // Field organization:Ljava/lang/String;
      42: invokevirtual #20                 // Method org/apache/dubbo/config/ModuleConfig.setOrganization:(Ljava/lang/String;)V
      45: aload_1
      46: aload_0
      47: getfield      #5                  // Field owner:Ljava/lang/String;
      50: invokevirtual #21                 // Method org/apache/dubbo/config/ModuleConfig.setOwner:(Ljava/lang/String;)V
      53: aload_1
      54: aload_0
      55: getfield      #7                  // Field registries:Ljava/util/List;
      58: invokevirtual #22                 // Method org/apache/dubbo/config/ModuleConfig.setRegistries:(Ljava/util/List;)V
      61: aload_1
      62: aload_0
      63: getfield      #4                  // Field version:Ljava/lang/String;
      66: invokevirtual #23                 // Method org/apache/dubbo/config/ModuleConfig.setVersion:(Ljava/lang/String;)V
      69: aload_1
      70: areturn

  protected org.apache.dubbo.config.bootstrap.builders.ModuleBuilder getThis();
    Code:
       0: aload_0
       1: areturn

  public org.apache.dubbo.config.AbstractConfig build();
    Code:
       0: aload_0
       1: invokevirtual #24                 // Method build:()Lorg/apache/dubbo/config/ModuleConfig;
       4: areturn

  protected org.apache.dubbo.config.bootstrap.builders.AbstractBuilder getThis();
    Code:
       0: aload_0
       1: invokevirtual #3                  // Method getThis:()Lorg/apache/dubbo/config/bootstrap/builders/ModuleBuilder;
       4: areturn
}
