Compiled from "MonitorBuilder.java"
public class org.apache.dubbo.config.bootstrap.builders.MonitorBuilder extends org.apache.dubbo.config.bootstrap.builders.AbstractBuilder<org.apache.dubbo.config.MonitorConfig, org.apache.dubbo.config.bootstrap.builders.MonitorBuilder> {
  private java.lang.String protocol;

  private java.lang.String address;

  private java.lang.String username;

  private java.lang.String password;

  private java.lang.String group;

  private java.lang.String version;

  private java.lang.String interval;

  private java.util.Map<java.lang.String, java.lang.String> parameters;

  private java.lang.Boolean isDefault;

  public org.apache.dubbo.config.bootstrap.builders.MonitorBuilder();
    Code:
       0: aload_0
       1: invokespecial #1                  // Method org/apache/dubbo/config/bootstrap/builders/AbstractBuilder."<init>":()V
       4: return

  public org.apache.dubbo.config.bootstrap.builders.MonitorBuilder protocol(java.lang.String);
    Code:
       0: aload_0
       1: aload_1
       2: putfield      #2                  // Field protocol:Ljava/lang/String;
       5: aload_0
       6: invokevirtual #3                  // Method getThis:()Lorg/apache/dubbo/config/bootstrap/builders/MonitorBuilder;
       9: areturn

  public org.apache.dubbo.config.bootstrap.builders.MonitorBuilder address(java.lang.String);
    Code:
       0: aload_0
       1: aload_1
       2: putfield      #4                  // Field address:Ljava/lang/String;
       5: aload_0
       6: invokevirtual #3                  // Method getThis:()Lorg/apache/dubbo/config/bootstrap/builders/MonitorBuilder;
       9: areturn

  public org.apache.dubbo.config.bootstrap.builders.MonitorBuilder username(java.lang.String);
    Code:
       0: aload_0
       1: aload_1
       2: putfield      #5                  // Field username:Ljava/lang/String;
       5: aload_0
       6: invokevirtual #3                  // Method getThis:()Lorg/apache/dubbo/config/bootstrap/builders/MonitorBuilder;
       9: areturn

  public org.apache.dubbo.config.bootstrap.builders.MonitorBuilder password(java.lang.String);
    Code:
       0: aload_0
       1: aload_1
       2: putfield      #6                  // Field password:Ljava/lang/String;
       5: aload_0
       6: invokevirtual #3                  // Method getThis:()Lorg/apache/dubbo/config/bootstrap/builders/MonitorBuilder;
       9: areturn

  public org.apache.dubbo.config.bootstrap.builders.MonitorBuilder group(java.lang.String);
    Code:
       0: aload_0
       1: aload_1
       2: putfield      #7                  // Field group:Ljava/lang/String;
       5: aload_0
       6: invokevirtual #3                  // Method getThis:()Lorg/apache/dubbo/config/bootstrap/builders/MonitorBuilder;
       9: areturn

  public org.apache.dubbo.config.bootstrap.builders.MonitorBuilder version(java.lang.String);
    Code:
       0: aload_0
       1: aload_1
       2: putfield      #8                  // Field version:Ljava/lang/String;
       5: aload_0
       6: invokevirtual #3                  // Method getThis:()Lorg/apache/dubbo/config/bootstrap/builders/MonitorBuilder;
       9: areturn

  public org.apache.dubbo.config.bootstrap.builders.MonitorBuilder interval(java.lang.String);
    Code:
       0: aload_0
       1: aload_1
       2: putfield      #9                  // Field interval:Ljava/lang/String;
       5: aload_0
       6: invokevirtual #3                  // Method getThis:()Lorg/apache/dubbo/config/bootstrap/builders/MonitorBuilder;
       9: areturn

  public org.apache.dubbo.config.bootstrap.builders.MonitorBuilder isDefault(java.lang.Boolean);
    Code:
       0: aload_0
       1: aload_1
       2: putfield      #10                 // Field isDefault:Ljava/lang/Boolean;
       5: aload_0
       6: invokevirtual #3                  // Method getThis:()Lorg/apache/dubbo/config/bootstrap/builders/MonitorBuilder;
       9: areturn

  public org.apache.dubbo.config.bootstrap.builders.MonitorBuilder appendParameter(java.lang.String, java.lang.String);
    Code:
       0: aload_0
       1: aload_0
       2: getfield      #11                 // Field parameters:Ljava/util/Map;
       5: aload_1
       6: aload_2
       7: invokestatic  #12                 // Method appendParameter:(Ljava/util/Map;Ljava/lang/String;Ljava/lang/String;)Ljava/util/Map;
      10: putfield      #11                 // Field parameters:Ljava/util/Map;
      13: aload_0
      14: invokevirtual #3                  // Method getThis:()Lorg/apache/dubbo/config/bootstrap/builders/MonitorBuilder;
      17: areturn

  public org.apache.dubbo.config.bootstrap.builders.MonitorBuilder appendParameters(java.util.Map<java.lang.String, java.lang.String>);
    Code:
       0: aload_0
       1: aload_0
       2: getfield      #11                 // Field parameters:Ljava/util/Map;
       5: aload_1
       6: invokestatic  #13                 // Method appendParameters:(Ljava/util/Map;Ljava/util/Map;)Ljava/util/Map;
       9: putfield      #11                 // Field parameters:Ljava/util/Map;
      12: aload_0
      13: invokevirtual #3                  // Method getThis:()Lorg/apache/dubbo/config/bootstrap/builders/MonitorBuilder;
      16: areturn

  public org.apache.dubbo.config.MonitorConfig build();
    Code:
       0: new           #14                 // class org/apache/dubbo/config/MonitorConfig
       3: dup
       4: invokespecial #15                 // Method org/apache/dubbo/config/MonitorConfig."<init>":()V
       7: astore_1
       8: aload_0
       9: aload_1
      10: invokespecial #16                 // Method org/apache/dubbo/config/bootstrap/builders/AbstractBuilder.build:(Lorg/apache/dubbo/config/AbstractConfig;)V
      13: aload_1
      14: aload_0
      15: getfield      #2                  // Field protocol:Ljava/lang/String;
      18: invokevirtual #17                 // Method org/apache/dubbo/config/MonitorConfig.setProtocol:(Ljava/lang/String;)V
      21: aload_1
      22: aload_0
      23: getfield      #4                  // Field address:Ljava/lang/String;
      26: invokevirtual #18                 // Method org/apache/dubbo/config/MonitorConfig.setAddress:(Ljava/lang/String;)V
      29: aload_1
      30: aload_0
      31: getfield      #5                  // Field username:Ljava/lang/String;
      34: invokevirtual #19                 // Method org/apache/dubbo/config/MonitorConfig.setUsername:(Ljava/lang/String;)V
      37: aload_1
      38: aload_0
      39: getfield      #6                  // Field password:Ljava/lang/String;
      42: invokevirtual #20                 // Method org/apache/dubbo/config/MonitorConfig.setPassword:(Ljava/lang/String;)V
      45: aload_1
      46: aload_0
      47: getfield      #7                  // Field group:Ljava/lang/String;
      50: invokevirtual #21                 // Method org/apache/dubbo/config/MonitorConfig.setGroup:(Ljava/lang/String;)V
      53: aload_1
      54: aload_0
      55: getfield      #8                  // Field version:Ljava/lang/String;
      58: invokevirtual #22                 // Method org/apache/dubbo/config/MonitorConfig.setVersion:(Ljava/lang/String;)V
      61: aload_1
      62: aload_0
      63: getfield      #9                  // Field interval:Ljava/lang/String;
      66: invokevirtual #23                 // Method org/apache/dubbo/config/MonitorConfig.setInterval:(Ljava/lang/String;)V
      69: aload_1
      70: aload_0
      71: getfield      #11                 // Field parameters:Ljava/util/Map;
      74: invokevirtual #24                 // Method org/apache/dubbo/config/MonitorConfig.setParameters:(Ljava/util/Map;)V
      77: aload_1
      78: aload_0
      79: getfield      #10                 // Field isDefault:Ljava/lang/Boolean;
      82: invokevirtual #25                 // Method org/apache/dubbo/config/MonitorConfig.setDefault:(Ljava/lang/Boolean;)V
      85: aload_1
      86: areturn

  protected org.apache.dubbo.config.bootstrap.builders.MonitorBuilder getThis();
    Code:
       0: aload_0
       1: areturn

  public org.apache.dubbo.config.AbstractConfig build();
    Code:
       0: aload_0
       1: invokevirtual #26                 // Method build:()Lorg/apache/dubbo/config/MonitorConfig;
       4: areturn

  protected org.apache.dubbo.config.bootstrap.builders.AbstractBuilder getThis();
    Code:
       0: aload_0
       1: invokevirtual #3                  // Method getThis:()Lorg/apache/dubbo/config/bootstrap/builders/MonitorBuilder;
       4: areturn
}
