Compiled from "ProtocolBuilder.java"
public class org.apache.dubbo.config.bootstrap.builders.ProtocolBuilder extends org.apache.dubbo.config.bootstrap.builders.AbstractBuilder<org.apache.dubbo.config.ProtocolConfig, org.apache.dubbo.config.bootstrap.builders.ProtocolBuilder> {
  private java.lang.String name;

  private java.lang.String host;

  private java.lang.Integer port;

  private java.lang.String contextpath;

  private java.lang.String threadpool;

  private java.lang.Integer corethreads;

  private java.lang.Integer threads;

  private java.lang.Integer iothreads;

  private java.lang.Integer queues;

  private java.lang.Integer accepts;

  private java.lang.String codec;

  private java.lang.String serialization;

  private java.lang.String charset;

  private java.lang.Integer payload;

  private java.lang.Integer buffer;

  private java.lang.Integer heartbeat;

  private java.lang.String accesslog;

  private java.lang.String transporter;

  private java.lang.String exchanger;

  private java.lang.String dispatcher;

  private java.lang.String networker;

  private java.lang.String server;

  private java.lang.String client;

  private java.lang.String telnet;

  private java.lang.String prompt;

  private java.lang.String status;

  private java.lang.Boolean register;

  private java.lang.Boolean keepAlive;

  private java.lang.String optimizer;

  private java.lang.String extension;

  private java.util.Map<java.lang.String, java.lang.String> parameters;

  private java.lang.Boolean isDefault;

  public org.apache.dubbo.config.bootstrap.builders.ProtocolBuilder();
    Code:
       0: aload_0
       1: invokespecial #1                  // Method org/apache/dubbo/config/bootstrap/builders/AbstractBuilder."<init>":()V
       4: return

  public static org.apache.dubbo.config.bootstrap.builders.ProtocolBuilder newBuilder();
    Code:
       0: new           #2                  // class org/apache/dubbo/config/bootstrap/builders/ProtocolBuilder
       3: dup
       4: invokespecial #3                  // Method "<init>":()V
       7: areturn

  public org.apache.dubbo.config.bootstrap.builders.ProtocolBuilder id(java.lang.String);
    Code:
       0: aload_0
       1: aload_1
       2: invokespecial #4                  // Method org/apache/dubbo/config/bootstrap/builders/AbstractBuilder.id:(Ljava/lang/String;)Lorg/apache/dubbo/config/bootstrap/builders/AbstractBuilder;
       5: checkcast     #2                  // class org/apache/dubbo/config/bootstrap/builders/ProtocolBuilder
       8: areturn

  public org.apache.dubbo.config.bootstrap.builders.ProtocolBuilder name(java.lang.String);
    Code:
       0: aload_0
       1: aload_1
       2: putfield      #5                  // Field name:Ljava/lang/String;
       5: aload_0
       6: invokevirtual #6                  // Method getThis:()Lorg/apache/dubbo/config/bootstrap/builders/ProtocolBuilder;
       9: areturn

  public org.apache.dubbo.config.bootstrap.builders.ProtocolBuilder host(java.lang.String);
    Code:
       0: aload_0
       1: aload_1
       2: putfield      #7                  // Field host:Ljava/lang/String;
       5: aload_0
       6: invokevirtual #6                  // Method getThis:()Lorg/apache/dubbo/config/bootstrap/builders/ProtocolBuilder;
       9: areturn

  public org.apache.dubbo.config.bootstrap.builders.ProtocolBuilder port(java.lang.Integer);
    Code:
       0: aload_0
       1: aload_1
       2: putfield      #8                  // Field port:Ljava/lang/Integer;
       5: aload_0
       6: invokevirtual #6                  // Method getThis:()Lorg/apache/dubbo/config/bootstrap/builders/ProtocolBuilder;
       9: areturn

  public org.apache.dubbo.config.bootstrap.builders.ProtocolBuilder contextpath(java.lang.String);
    Code:
       0: aload_0
       1: aload_1
       2: putfield      #9                  // Field contextpath:Ljava/lang/String;
       5: aload_0
       6: invokevirtual #6                  // Method getThis:()Lorg/apache/dubbo/config/bootstrap/builders/ProtocolBuilder;
       9: areturn

  public org.apache.dubbo.config.bootstrap.builders.ProtocolBuilder path(java.lang.String);
    Code:
       0: aload_0
       1: aload_1
       2: putfield      #9                  // Field contextpath:Ljava/lang/String;
       5: aload_0
       6: invokevirtual #6                  // Method getThis:()Lorg/apache/dubbo/config/bootstrap/builders/ProtocolBuilder;
       9: areturn

  public org.apache.dubbo.config.bootstrap.builders.ProtocolBuilder threadpool(java.lang.String);
    Code:
       0: aload_0
       1: aload_1
       2: putfield      #10                 // Field threadpool:Ljava/lang/String;
       5: aload_0
       6: invokevirtual #6                  // Method getThis:()Lorg/apache/dubbo/config/bootstrap/builders/ProtocolBuilder;
       9: areturn

  public org.apache.dubbo.config.bootstrap.builders.ProtocolBuilder corethreads(java.lang.Integer);
    Code:
       0: aload_0
       1: aload_1
       2: putfield      #11                 // Field corethreads:Ljava/lang/Integer;
       5: aload_0
       6: invokevirtual #6                  // Method getThis:()Lorg/apache/dubbo/config/bootstrap/builders/ProtocolBuilder;
       9: areturn

  public org.apache.dubbo.config.bootstrap.builders.ProtocolBuilder threads(java.lang.Integer);
    Code:
       0: aload_0
       1: aload_1
       2: putfield      #12                 // Field threads:Ljava/lang/Integer;
       5: aload_0
       6: invokevirtual #6                  // Method getThis:()Lorg/apache/dubbo/config/bootstrap/builders/ProtocolBuilder;
       9: areturn

  public org.apache.dubbo.config.bootstrap.builders.ProtocolBuilder iothreads(java.lang.Integer);
    Code:
       0: aload_0
       1: aload_1
       2: putfield      #13                 // Field iothreads:Ljava/lang/Integer;
       5: aload_0
       6: invokevirtual #6                  // Method getThis:()Lorg/apache/dubbo/config/bootstrap/builders/ProtocolBuilder;
       9: areturn

  public org.apache.dubbo.config.bootstrap.builders.ProtocolBuilder queues(java.lang.Integer);
    Code:
       0: aload_0
       1: aload_1
       2: putfield      #14                 // Field queues:Ljava/lang/Integer;
       5: aload_0
       6: invokevirtual #6                  // Method getThis:()Lorg/apache/dubbo/config/bootstrap/builders/ProtocolBuilder;
       9: areturn

  public org.apache.dubbo.config.bootstrap.builders.ProtocolBuilder accepts(java.lang.Integer);
    Code:
       0: aload_0
       1: aload_1
       2: putfield      #15                 // Field accepts:Ljava/lang/Integer;
       5: aload_0
       6: invokevirtual #6                  // Method getThis:()Lorg/apache/dubbo/config/bootstrap/builders/ProtocolBuilder;
       9: areturn

  public org.apache.dubbo.config.bootstrap.builders.ProtocolBuilder codec(java.lang.String);
    Code:
       0: aload_0
       1: aload_1
       2: putfield      #16                 // Field codec:Ljava/lang/String;
       5: aload_0
       6: invokevirtual #6                  // Method getThis:()Lorg/apache/dubbo/config/bootstrap/builders/ProtocolBuilder;
       9: areturn

  public org.apache.dubbo.config.bootstrap.builders.ProtocolBuilder serialization(java.lang.String);
    Code:
       0: aload_0
       1: aload_1
       2: putfield      #17                 // Field serialization:Ljava/lang/String;
       5: aload_0
       6: invokevirtual #6                  // Method getThis:()Lorg/apache/dubbo/config/bootstrap/builders/ProtocolBuilder;
       9: areturn

  public org.apache.dubbo.config.bootstrap.builders.ProtocolBuilder charset(java.lang.String);
    Code:
       0: aload_0
       1: aload_1
       2: putfield      #18                 // Field charset:Ljava/lang/String;
       5: aload_0
       6: invokevirtual #6                  // Method getThis:()Lorg/apache/dubbo/config/bootstrap/builders/ProtocolBuilder;
       9: areturn

  public org.apache.dubbo.config.bootstrap.builders.ProtocolBuilder payload(java.lang.Integer);
    Code:
       0: aload_0
       1: aload_1
       2: putfield      #19                 // Field payload:Ljava/lang/Integer;
       5: aload_0
       6: invokevirtual #6                  // Method getThis:()Lorg/apache/dubbo/config/bootstrap/builders/ProtocolBuilder;
       9: areturn

  public org.apache.dubbo.config.bootstrap.builders.ProtocolBuilder buffer(java.lang.Integer);
    Code:
       0: aload_0
       1: aload_1
       2: putfield      #20                 // Field buffer:Ljava/lang/Integer;
       5: aload_0
       6: invokevirtual #6                  // Method getThis:()Lorg/apache/dubbo/config/bootstrap/builders/ProtocolBuilder;
       9: areturn

  public org.apache.dubbo.config.bootstrap.builders.ProtocolBuilder heartbeat(java.lang.Integer);
    Code:
       0: aload_0
       1: aload_1
       2: putfield      #21                 // Field heartbeat:Ljava/lang/Integer;
       5: aload_0
       6: invokevirtual #6                  // Method getThis:()Lorg/apache/dubbo/config/bootstrap/builders/ProtocolBuilder;
       9: areturn

  public org.apache.dubbo.config.bootstrap.builders.ProtocolBuilder accesslog(java.lang.String);
    Code:
       0: aload_0
       1: aload_1
       2: putfield      #22                 // Field accesslog:Ljava/lang/String;
       5: aload_0
       6: invokevirtual #6                  // Method getThis:()Lorg/apache/dubbo/config/bootstrap/builders/ProtocolBuilder;
       9: areturn

  public org.apache.dubbo.config.bootstrap.builders.ProtocolBuilder transporter(java.lang.String);
    Code:
       0: aload_0
       1: aload_1
       2: putfield      #23                 // Field transporter:Ljava/lang/String;
       5: aload_0
       6: invokevirtual #6                  // Method getThis:()Lorg/apache/dubbo/config/bootstrap/builders/ProtocolBuilder;
       9: areturn

  public org.apache.dubbo.config.bootstrap.builders.ProtocolBuilder exchanger(java.lang.String);
    Code:
       0: aload_0
       1: aload_1
       2: putfield      #24                 // Field exchanger:Ljava/lang/String;
       5: aload_0
       6: invokevirtual #6                  // Method getThis:()Lorg/apache/dubbo/config/bootstrap/builders/ProtocolBuilder;
       9: areturn

  public org.apache.dubbo.config.bootstrap.builders.ProtocolBuilder dispatcher(java.lang.String);
    Code:
       0: aload_0
       1: aload_1
       2: putfield      #25                 // Field dispatcher:Ljava/lang/String;
       5: aload_0
       6: invokevirtual #6                  // Method getThis:()Lorg/apache/dubbo/config/bootstrap/builders/ProtocolBuilder;
       9: areturn

  public org.apache.dubbo.config.bootstrap.builders.ProtocolBuilder dispather(java.lang.String);
    Code:
       0: aload_0
       1: aload_1
       2: putfield      #25                 // Field dispatcher:Ljava/lang/String;
       5: aload_0
       6: invokevirtual #6                  // Method getThis:()Lorg/apache/dubbo/config/bootstrap/builders/ProtocolBuilder;
       9: areturn

  public org.apache.dubbo.config.bootstrap.builders.ProtocolBuilder networker(java.lang.String);
    Code:
       0: aload_0
       1: aload_1
       2: putfield      #26                 // Field networker:Ljava/lang/String;
       5: aload_0
       6: invokevirtual #6                  // Method getThis:()Lorg/apache/dubbo/config/bootstrap/builders/ProtocolBuilder;
       9: areturn

  public org.apache.dubbo.config.bootstrap.builders.ProtocolBuilder server(java.lang.String);
    Code:
       0: aload_0
       1: aload_1
       2: putfield      #27                 // Field server:Ljava/lang/String;
       5: aload_0
       6: invokevirtual #6                  // Method getThis:()Lorg/apache/dubbo/config/bootstrap/builders/ProtocolBuilder;
       9: areturn

  public org.apache.dubbo.config.bootstrap.builders.ProtocolBuilder client(java.lang.String);
    Code:
       0: aload_0
       1: aload_1
       2: putfield      #28                 // Field client:Ljava/lang/String;
       5: aload_0
       6: invokevirtual #6                  // Method getThis:()Lorg/apache/dubbo/config/bootstrap/builders/ProtocolBuilder;
       9: areturn

  public org.apache.dubbo.config.bootstrap.builders.ProtocolBuilder telnet(java.lang.String);
    Code:
       0: aload_0
       1: aload_1
       2: putfield      #29                 // Field telnet:Ljava/lang/String;
       5: aload_0
       6: invokevirtual #6                  // Method getThis:()Lorg/apache/dubbo/config/bootstrap/builders/ProtocolBuilder;
       9: areturn

  public org.apache.dubbo.config.bootstrap.builders.ProtocolBuilder prompt(java.lang.String);
    Code:
       0: aload_0
       1: aload_1
       2: putfield      #30                 // Field prompt:Ljava/lang/String;
       5: aload_0
       6: invokevirtual #6                  // Method getThis:()Lorg/apache/dubbo/config/bootstrap/builders/ProtocolBuilder;
       9: areturn

  public org.apache.dubbo.config.bootstrap.builders.ProtocolBuilder status(java.lang.String);
    Code:
       0: aload_0
       1: aload_1
       2: putfield      #31                 // Field status:Ljava/lang/String;
       5: aload_0
       6: invokevirtual #6                  // Method getThis:()Lorg/apache/dubbo/config/bootstrap/builders/ProtocolBuilder;
       9: areturn

  public org.apache.dubbo.config.bootstrap.builders.ProtocolBuilder register(java.lang.Boolean);
    Code:
       0: aload_0
       1: aload_1
       2: putfield      #32                 // Field register:Ljava/lang/Boolean;
       5: aload_0
       6: invokevirtual #6                  // Method getThis:()Lorg/apache/dubbo/config/bootstrap/builders/ProtocolBuilder;
       9: areturn

  public org.apache.dubbo.config.bootstrap.builders.ProtocolBuilder keepAlive(java.lang.Boolean);
    Code:
       0: aload_0
       1: aload_1
       2: putfield      #33                 // Field keepAlive:Ljava/lang/Boolean;
       5: aload_0
       6: invokevirtual #6                  // Method getThis:()Lorg/apache/dubbo/config/bootstrap/builders/ProtocolBuilder;
       9: areturn

  public org.apache.dubbo.config.bootstrap.builders.ProtocolBuilder optimizer(java.lang.String);
    Code:
       0: aload_0
       1: aload_1
       2: putfield      #34                 // Field optimizer:Ljava/lang/String;
       5: aload_0
       6: invokevirtual #6                  // Method getThis:()Lorg/apache/dubbo/config/bootstrap/builders/ProtocolBuilder;
       9: areturn

  public org.apache.dubbo.config.bootstrap.builders.ProtocolBuilder extension(java.lang.String);
    Code:
       0: aload_0
       1: aload_1
       2: putfield      #35                 // Field extension:Ljava/lang/String;
       5: aload_0
       6: invokevirtual #6                  // Method getThis:()Lorg/apache/dubbo/config/bootstrap/builders/ProtocolBuilder;
       9: areturn

  public org.apache.dubbo.config.bootstrap.builders.ProtocolBuilder appendParameter(java.lang.String, java.lang.String);
    Code:
       0: aload_0
       1: aload_0
       2: getfield      #36                 // Field parameters:Ljava/util/Map;
       5: aload_1
       6: aload_2
       7: invokestatic  #37                 // Method appendParameter:(Ljava/util/Map;Ljava/lang/String;Ljava/lang/String;)Ljava/util/Map;
      10: putfield      #36                 // Field parameters:Ljava/util/Map;
      13: aload_0
      14: invokevirtual #6                  // Method getThis:()Lorg/apache/dubbo/config/bootstrap/builders/ProtocolBuilder;
      17: areturn

  public org.apache.dubbo.config.bootstrap.builders.ProtocolBuilder appendParameters(java.util.Map<java.lang.String, java.lang.String>);
    Code:
       0: aload_0
       1: aload_0
       2: getfield      #36                 // Field parameters:Ljava/util/Map;
       5: aload_1
       6: invokestatic  #38                 // Method appendParameters:(Ljava/util/Map;Ljava/util/Map;)Ljava/util/Map;
       9: putfield      #36                 // Field parameters:Ljava/util/Map;
      12: aload_0
      13: invokevirtual #6                  // Method getThis:()Lorg/apache/dubbo/config/bootstrap/builders/ProtocolBuilder;
      16: areturn

  public org.apache.dubbo.config.bootstrap.builders.ProtocolBuilder isDefault(java.lang.Boolean);
    Code:
       0: aload_0
       1: aload_1
       2: putfield      #39                 // Field isDefault:Ljava/lang/Boolean;
       5: aload_0
       6: invokevirtual #6                  // Method getThis:()Lorg/apache/dubbo/config/bootstrap/builders/ProtocolBuilder;
       9: areturn

  public org.apache.dubbo.config.ProtocolConfig build();
    Code:
       0: new           #40                 // class org/apache/dubbo/config/ProtocolConfig
       3: dup
       4: invokespecial #41                 // Method org/apache/dubbo/config/ProtocolConfig."<init>":()V
       7: astore_1
       8: aload_0
       9: aload_1
      10: invokespecial #42                 // Method org/apache/dubbo/config/bootstrap/builders/AbstractBuilder.build:(Lorg/apache/dubbo/config/AbstractConfig;)V
      13: aload_1
      14: aload_0
      15: getfield      #15                 // Field accepts:Ljava/lang/Integer;
      18: invokevirtual #43                 // Method org/apache/dubbo/config/ProtocolConfig.setAccepts:(Ljava/lang/Integer;)V
      21: aload_1
      22: aload_0
      23: getfield      #22                 // Field accesslog:Ljava/lang/String;
      26: invokevirtual #44                 // Method org/apache/dubbo/config/ProtocolConfig.setAccesslog:(Ljava/lang/String;)V
      29: aload_1
      30: aload_0
      31: getfield      #20                 // Field buffer:Ljava/lang/Integer;
      34: invokevirtual #45                 // Method org/apache/dubbo/config/ProtocolConfig.setBuffer:(Ljava/lang/Integer;)V
      37: aload_1
      38: aload_0
      39: getfield      #18                 // Field charset:Ljava/lang/String;
      42: invokevirtual #46                 // Method org/apache/dubbo/config/ProtocolConfig.setCharset:(Ljava/lang/String;)V
      45: aload_1
      46: aload_0
      47: getfield      #28                 // Field client:Ljava/lang/String;
      50: invokevirtual #47                 // Method org/apache/dubbo/config/ProtocolConfig.setClient:(Ljava/lang/String;)V
      53: aload_1
      54: aload_0
      55: getfield      #16                 // Field codec:Ljava/lang/String;
      58: invokevirtual #48                 // Method org/apache/dubbo/config/ProtocolConfig.setCodec:(Ljava/lang/String;)V
      61: aload_1
      62: aload_0
      63: getfield      #9                  // Field contextpath:Ljava/lang/String;
      66: invokevirtual #49                 // Method org/apache/dubbo/config/ProtocolConfig.setContextpath:(Ljava/lang/String;)V
      69: aload_1
      70: aload_0
      71: getfield      #11                 // Field corethreads:Ljava/lang/Integer;
      74: invokevirtual #50                 // Method org/apache/dubbo/config/ProtocolConfig.setCorethreads:(Ljava/lang/Integer;)V
      77: aload_1
      78: aload_0
      79: getfield      #39                 // Field isDefault:Ljava/lang/Boolean;
      82: invokevirtual #51                 // Method org/apache/dubbo/config/ProtocolConfig.setDefault:(Ljava/lang/Boolean;)V
      85: aload_1
      86: aload_0
      87: getfield      #25                 // Field dispatcher:Ljava/lang/String;
      90: invokevirtual #52                 // Method org/apache/dubbo/config/ProtocolConfig.setDispatcher:(Ljava/lang/String;)V
      93: aload_1
      94: aload_0
      95: getfield      #24                 // Field exchanger:Ljava/lang/String;
      98: invokevirtual #53                 // Method org/apache/dubbo/config/ProtocolConfig.setExchanger:(Ljava/lang/String;)V
     101: aload_1
     102: aload_0
     103: getfield      #35                 // Field extension:Ljava/lang/String;
     106: invokevirtual #54                 // Method org/apache/dubbo/config/ProtocolConfig.setExtension:(Ljava/lang/String;)V
     109: aload_1
     110: aload_0
     111: getfield      #21                 // Field heartbeat:Ljava/lang/Integer;
     114: invokevirtual #55                 // Method org/apache/dubbo/config/ProtocolConfig.setHeartbeat:(Ljava/lang/Integer;)V
     117: aload_1
     118: aload_0
     119: getfield      #7                  // Field host:Ljava/lang/String;
     122: invokevirtual #56                 // Method org/apache/dubbo/config/ProtocolConfig.setHost:(Ljava/lang/String;)V
     125: aload_1
     126: aload_0
     127: getfield      #13                 // Field iothreads:Ljava/lang/Integer;
     130: invokevirtual #57                 // Method org/apache/dubbo/config/ProtocolConfig.setIothreads:(Ljava/lang/Integer;)V
     133: aload_1
     134: aload_0
     135: getfield      #33                 // Field keepAlive:Ljava/lang/Boolean;
     138: invokevirtual #58                 // Method org/apache/dubbo/config/ProtocolConfig.setKeepAlive:(Ljava/lang/Boolean;)V
     141: aload_1
     142: aload_0
     143: getfield      #5                  // Field name:Ljava/lang/String;
     146: invokevirtual #59                 // Method org/apache/dubbo/config/ProtocolConfig.setName:(Ljava/lang/String;)V
     149: aload_1
     150: aload_0
     151: getfield      #26                 // Field networker:Ljava/lang/String;
     154: invokevirtual #60                 // Method org/apache/dubbo/config/ProtocolConfig.setNetworker:(Ljava/lang/String;)V
     157: aload_1
     158: aload_0
     159: getfield      #34                 // Field optimizer:Ljava/lang/String;
     162: invokevirtual #61                 // Method org/apache/dubbo/config/ProtocolConfig.setOptimizer:(Ljava/lang/String;)V
     165: aload_1
     166: aload_0
     167: getfield      #36                 // Field parameters:Ljava/util/Map;
     170: invokevirtual #62                 // Method org/apache/dubbo/config/ProtocolConfig.setParameters:(Ljava/util/Map;)V
     173: aload_1
     174: aload_0
     175: getfield      #19                 // Field payload:Ljava/lang/Integer;
     178: invokevirtual #63                 // Method org/apache/dubbo/config/ProtocolConfig.setPayload:(Ljava/lang/Integer;)V
     181: aload_1
     182: aload_0
     183: getfield      #8                  // Field port:Ljava/lang/Integer;
     186: invokevirtual #64                 // Method org/apache/dubbo/config/ProtocolConfig.setPort:(Ljava/lang/Integer;)V
     189: aload_1
     190: aload_0
     191: getfield      #30                 // Field prompt:Ljava/lang/String;
     194: invokevirtual #65                 // Method org/apache/dubbo/config/ProtocolConfig.setPrompt:(Ljava/lang/String;)V
     197: aload_1
     198: aload_0
     199: getfield      #14                 // Field queues:Ljava/lang/Integer;
     202: invokevirtual #66                 // Method org/apache/dubbo/config/ProtocolConfig.setQueues:(Ljava/lang/Integer;)V
     205: aload_1
     206: aload_0
     207: getfield      #32                 // Field register:Ljava/lang/Boolean;
     210: invokevirtual #67                 // Method org/apache/dubbo/config/ProtocolConfig.setRegister:(Ljava/lang/Boolean;)V
     213: aload_1
     214: aload_0
     215: getfield      #17                 // Field serialization:Ljava/lang/String;
     218: invokevirtual #68                 // Method org/apache/dubbo/config/ProtocolConfig.setSerialization:(Ljava/lang/String;)V
     221: aload_1
     222: aload_0
     223: getfield      #27                 // Field server:Ljava/lang/String;
     226: invokevirtual #69                 // Method org/apache/dubbo/config/ProtocolConfig.setServer:(Ljava/lang/String;)V
     229: aload_1
     230: aload_0
     231: getfield      #31                 // Field status:Ljava/lang/String;
     234: invokevirtual #70                 // Method org/apache/dubbo/config/ProtocolConfig.setStatus:(Ljava/lang/String;)V
     237: aload_1
     238: aload_0
     239: getfield      #29                 // Field telnet:Ljava/lang/String;
     242: invokevirtual #71                 // Method org/apache/dubbo/config/ProtocolConfig.setTelnet:(Ljava/lang/String;)V
     245: aload_1
     246: aload_0
     247: getfield      #10                 // Field threadpool:Ljava/lang/String;
     250: invokevirtual #72                 // Method org/apache/dubbo/config/ProtocolConfig.setThreadpool:(Ljava/lang/String;)V
     253: aload_1
     254: aload_0
     255: getfield      #12                 // Field threads:Ljava/lang/Integer;
     258: invokevirtual #73                 // Method org/apache/dubbo/config/ProtocolConfig.setThreads:(Ljava/lang/Integer;)V
     261: aload_1
     262: aload_0
     263: getfield      #23                 // Field transporter:Ljava/lang/String;
     266: invokevirtual #74                 // Method org/apache/dubbo/config/ProtocolConfig.setTransporter:(Ljava/lang/String;)V
     269: aload_1
     270: areturn

  protected org.apache.dubbo.config.bootstrap.builders.ProtocolBuilder getThis();
    Code:
       0: aload_0
       1: areturn

  public org.apache.dubbo.config.AbstractConfig build();
    Code:
       0: aload_0
       1: invokevirtual #75                 // Method build:()Lorg/apache/dubbo/config/ProtocolConfig;
       4: areturn

  protected org.apache.dubbo.config.bootstrap.builders.AbstractBuilder getThis();
    Code:
       0: aload_0
       1: invokevirtual #6                  // Method getThis:()Lorg/apache/dubbo/config/bootstrap/builders/ProtocolBuilder;
       4: areturn

  public org.apache.dubbo.config.bootstrap.builders.AbstractBuilder id(java.lang.String);
    Code:
       0: aload_0
       1: aload_1
       2: invokevirtual #76                 // Method id:(Ljava/lang/String;)Lorg/apache/dubbo/config/bootstrap/builders/ProtocolBuilder;
       5: areturn
}
