Compiled from "ProviderBuilder.java"
public class org.apache.dubbo.config.bootstrap.builders.ProviderBuilder extends org.apache.dubbo.config.bootstrap.builders.AbstractServiceBuilder<org.apache.dubbo.config.ProviderConfig, org.apache.dubbo.config.bootstrap.builders.ProviderBuilder> {
  private java.lang.String host;

  private java.lang.Integer port;

  private java.lang.String contextpath;

  private java.lang.String threadpool;

  private java.lang.Integer threads;

  private java.lang.Integer iothreads;

  private java.lang.Integer queues;

  private java.lang.Integer accepts;

  private java.lang.String codec;

  private java.lang.String charset;

  private java.lang.Integer payload;

  private java.lang.Integer buffer;

  private java.lang.String transporter;

  private java.lang.String exchanger;

  private java.lang.String dispatcher;

  private java.lang.String networker;

  private java.lang.String server;

  private java.lang.String client;

  private java.lang.String telnet;

  private java.lang.String prompt;

  private java.lang.String status;

  private java.lang.Integer wait;

  private java.lang.Boolean isDefault;

  public org.apache.dubbo.config.bootstrap.builders.ProviderBuilder();
    Code:
       0: aload_0
       1: invokespecial #1                  // Method org/apache/dubbo/config/bootstrap/builders/AbstractServiceBuilder."<init>":()V
       4: return

  public org.apache.dubbo.config.bootstrap.builders.ProviderBuilder host(java.lang.String);
    Code:
       0: aload_0
       1: aload_1
       2: putfield      #2                  // Field host:Ljava/lang/String;
       5: aload_0
       6: invokevirtual #3                  // Method getThis:()Lorg/apache/dubbo/config/bootstrap/builders/ProviderBuilder;
       9: areturn

  public org.apache.dubbo.config.bootstrap.builders.ProviderBuilder port(java.lang.Integer);
    Code:
       0: aload_0
       1: aload_1
       2: putfield      #4                  // Field port:Ljava/lang/Integer;
       5: aload_0
       6: invokevirtual #3                  // Method getThis:()Lorg/apache/dubbo/config/bootstrap/builders/ProviderBuilder;
       9: areturn

  public org.apache.dubbo.config.bootstrap.builders.ProviderBuilder contextPath(java.lang.String);
    Code:
       0: aload_0
       1: aload_1
       2: putfield      #5                  // Field contextpath:Ljava/lang/String;
       5: aload_0
       6: invokevirtual #3                  // Method getThis:()Lorg/apache/dubbo/config/bootstrap/builders/ProviderBuilder;
       9: areturn

  public org.apache.dubbo.config.bootstrap.builders.ProviderBuilder threadPool(java.lang.String);
    Code:
       0: aload_0
       1: aload_1
       2: putfield      #6                  // Field threadpool:Ljava/lang/String;
       5: aload_0
       6: invokevirtual #3                  // Method getThis:()Lorg/apache/dubbo/config/bootstrap/builders/ProviderBuilder;
       9: areturn

  public org.apache.dubbo.config.bootstrap.builders.ProviderBuilder threads(java.lang.Integer);
    Code:
       0: aload_0
       1: aload_1
       2: putfield      #7                  // Field threads:Ljava/lang/Integer;
       5: aload_0
       6: invokevirtual #3                  // Method getThis:()Lorg/apache/dubbo/config/bootstrap/builders/ProviderBuilder;
       9: areturn

  public org.apache.dubbo.config.bootstrap.builders.ProviderBuilder ioThreads(java.lang.Integer);
    Code:
       0: aload_0
       1: aload_1
       2: putfield      #8                  // Field iothreads:Ljava/lang/Integer;
       5: aload_0
       6: invokevirtual #3                  // Method getThis:()Lorg/apache/dubbo/config/bootstrap/builders/ProviderBuilder;
       9: areturn

  public org.apache.dubbo.config.bootstrap.builders.ProviderBuilder queues(java.lang.Integer);
    Code:
       0: aload_0
       1: aload_1
       2: putfield      #9                  // Field queues:Ljava/lang/Integer;
       5: aload_0
       6: invokevirtual #3                  // Method getThis:()Lorg/apache/dubbo/config/bootstrap/builders/ProviderBuilder;
       9: areturn

  public org.apache.dubbo.config.bootstrap.builders.ProviderBuilder accepts(java.lang.Integer);
    Code:
       0: aload_0
       1: aload_1
       2: putfield      #10                 // Field accepts:Ljava/lang/Integer;
       5: aload_0
       6: invokevirtual #3                  // Method getThis:()Lorg/apache/dubbo/config/bootstrap/builders/ProviderBuilder;
       9: areturn

  public org.apache.dubbo.config.bootstrap.builders.ProviderBuilder codec(java.lang.String);
    Code:
       0: aload_0
       1: aload_1
       2: putfield      #11                 // Field codec:Ljava/lang/String;
       5: aload_0
       6: invokevirtual #3                  // Method getThis:()Lorg/apache/dubbo/config/bootstrap/builders/ProviderBuilder;
       9: areturn

  public org.apache.dubbo.config.bootstrap.builders.ProviderBuilder charset(java.lang.String);
    Code:
       0: aload_0
       1: aload_1
       2: putfield      #12                 // Field charset:Ljava/lang/String;
       5: aload_0
       6: invokevirtual #3                  // Method getThis:()Lorg/apache/dubbo/config/bootstrap/builders/ProviderBuilder;
       9: areturn

  public org.apache.dubbo.config.bootstrap.builders.ProviderBuilder payload(java.lang.Integer);
    Code:
       0: aload_0
       1: aload_1
       2: putfield      #13                 // Field payload:Ljava/lang/Integer;
       5: aload_0
       6: invokevirtual #3                  // Method getThis:()Lorg/apache/dubbo/config/bootstrap/builders/ProviderBuilder;
       9: areturn

  public org.apache.dubbo.config.bootstrap.builders.ProviderBuilder buffer(java.lang.Integer);
    Code:
       0: aload_0
       1: aload_1
       2: putfield      #14                 // Field buffer:Ljava/lang/Integer;
       5: aload_0
       6: invokevirtual #3                  // Method getThis:()Lorg/apache/dubbo/config/bootstrap/builders/ProviderBuilder;
       9: areturn

  public org.apache.dubbo.config.bootstrap.builders.ProviderBuilder transporter(java.lang.String);
    Code:
       0: aload_0
       1: aload_1
       2: putfield      #15                 // Field transporter:Ljava/lang/String;
       5: aload_0
       6: invokevirtual #3                  // Method getThis:()Lorg/apache/dubbo/config/bootstrap/builders/ProviderBuilder;
       9: areturn

  public org.apache.dubbo.config.bootstrap.builders.ProviderBuilder exchanger(java.lang.String);
    Code:
       0: aload_0
       1: aload_1
       2: putfield      #16                 // Field exchanger:Ljava/lang/String;
       5: aload_0
       6: invokevirtual #3                  // Method getThis:()Lorg/apache/dubbo/config/bootstrap/builders/ProviderBuilder;
       9: areturn

  public org.apache.dubbo.config.bootstrap.builders.ProviderBuilder dispatcher(java.lang.String);
    Code:
       0: aload_0
       1: aload_1
       2: putfield      #17                 // Field dispatcher:Ljava/lang/String;
       5: aload_0
       6: invokevirtual #3                  // Method getThis:()Lorg/apache/dubbo/config/bootstrap/builders/ProviderBuilder;
       9: areturn

  public org.apache.dubbo.config.bootstrap.builders.ProviderBuilder networker(java.lang.String);
    Code:
       0: aload_0
       1: aload_1
       2: putfield      #18                 // Field networker:Ljava/lang/String;
       5: aload_0
       6: invokevirtual #3                  // Method getThis:()Lorg/apache/dubbo/config/bootstrap/builders/ProviderBuilder;
       9: areturn

  public org.apache.dubbo.config.bootstrap.builders.ProviderBuilder server(java.lang.String);
    Code:
       0: aload_0
       1: aload_1
       2: putfield      #19                 // Field server:Ljava/lang/String;
       5: aload_0
       6: invokevirtual #3                  // Method getThis:()Lorg/apache/dubbo/config/bootstrap/builders/ProviderBuilder;
       9: areturn

  public org.apache.dubbo.config.bootstrap.builders.ProviderBuilder client(java.lang.String);
    Code:
       0: aload_0
       1: aload_1
       2: putfield      #20                 // Field client:Ljava/lang/String;
       5: aload_0
       6: invokevirtual #3                  // Method getThis:()Lorg/apache/dubbo/config/bootstrap/builders/ProviderBuilder;
       9: areturn

  public org.apache.dubbo.config.bootstrap.builders.ProviderBuilder telnet(java.lang.String);
    Code:
       0: aload_0
       1: aload_1
       2: putfield      #21                 // Field telnet:Ljava/lang/String;
       5: aload_0
       6: invokevirtual #3                  // Method getThis:()Lorg/apache/dubbo/config/bootstrap/builders/ProviderBuilder;
       9: areturn

  public org.apache.dubbo.config.bootstrap.builders.ProviderBuilder prompt(java.lang.String);
    Code:
       0: aload_0
       1: aload_1
       2: putfield      #22                 // Field prompt:Ljava/lang/String;
       5: aload_0
       6: invokevirtual #3                  // Method getThis:()Lorg/apache/dubbo/config/bootstrap/builders/ProviderBuilder;
       9: areturn

  public org.apache.dubbo.config.bootstrap.builders.ProviderBuilder status(java.lang.String);
    Code:
       0: aload_0
       1: aload_1
       2: putfield      #23                 // Field status:Ljava/lang/String;
       5: aload_0
       6: invokevirtual #3                  // Method getThis:()Lorg/apache/dubbo/config/bootstrap/builders/ProviderBuilder;
       9: areturn

  public org.apache.dubbo.config.bootstrap.builders.ProviderBuilder wait(java.lang.Integer);
    Code:
       0: aload_0
       1: aload_1
       2: putfield      #24                 // Field wait:Ljava/lang/Integer;
       5: aload_0
       6: invokevirtual #3                  // Method getThis:()Lorg/apache/dubbo/config/bootstrap/builders/ProviderBuilder;
       9: areturn

  public org.apache.dubbo.config.bootstrap.builders.ProviderBuilder isDefault(java.lang.Boolean);
    Code:
       0: aload_0
       1: aload_1
       2: putfield      #25                 // Field isDefault:Ljava/lang/Boolean;
       5: aload_0
       6: invokevirtual #3                  // Method getThis:()Lorg/apache/dubbo/config/bootstrap/builders/ProviderBuilder;
       9: areturn

  public org.apache.dubbo.config.ProviderConfig build();
    Code:
       0: new           #26                 // class org/apache/dubbo/config/ProviderConfig
       3: dup
       4: invokespecial #27                 // Method org/apache/dubbo/config/ProviderConfig."<init>":()V
       7: astore_1
       8: aload_0
       9: aload_1
      10: invokespecial #28                 // Method org/apache/dubbo/config/bootstrap/builders/AbstractServiceBuilder.build:(Lorg/apache/dubbo/config/AbstractServiceConfig;)V
      13: aload_1
      14: aload_0
      15: getfield      #2                  // Field host:Ljava/lang/String;
      18: invokevirtual #29                 // Method org/apache/dubbo/config/ProviderConfig.setHost:(Ljava/lang/String;)V
      21: aload_1
      22: aload_0
      23: getfield      #4                  // Field port:Ljava/lang/Integer;
      26: invokevirtual #30                 // Method org/apache/dubbo/config/ProviderConfig.setPort:(Ljava/lang/Integer;)V
      29: aload_1
      30: aload_0
      31: getfield      #5                  // Field contextpath:Ljava/lang/String;
      34: invokevirtual #31                 // Method org/apache/dubbo/config/ProviderConfig.setContextpath:(Ljava/lang/String;)V
      37: aload_1
      38: aload_0
      39: getfield      #6                  // Field threadpool:Ljava/lang/String;
      42: invokevirtual #32                 // Method org/apache/dubbo/config/ProviderConfig.setThreadpool:(Ljava/lang/String;)V
      45: aload_1
      46: aload_0
      47: getfield      #7                  // Field threads:Ljava/lang/Integer;
      50: invokevirtual #33                 // Method org/apache/dubbo/config/ProviderConfig.setThreads:(Ljava/lang/Integer;)V
      53: aload_1
      54: aload_0
      55: getfield      #8                  // Field iothreads:Ljava/lang/Integer;
      58: invokevirtual #34                 // Method org/apache/dubbo/config/ProviderConfig.setIothreads:(Ljava/lang/Integer;)V
      61: aload_1
      62: aload_0
      63: getfield      #9                  // Field queues:Ljava/lang/Integer;
      66: invokevirtual #35                 // Method org/apache/dubbo/config/ProviderConfig.setQueues:(Ljava/lang/Integer;)V
      69: aload_1
      70: aload_0
      71: getfield      #10                 // Field accepts:Ljava/lang/Integer;
      74: invokevirtual #36                 // Method org/apache/dubbo/config/ProviderConfig.setAccepts:(Ljava/lang/Integer;)V
      77: aload_1
      78: aload_0
      79: getfield      #11                 // Field codec:Ljava/lang/String;
      82: invokevirtual #37                 // Method org/apache/dubbo/config/ProviderConfig.setCodec:(Ljava/lang/String;)V
      85: aload_1
      86: aload_0
      87: getfield      #13                 // Field payload:Ljava/lang/Integer;
      90: invokevirtual #38                 // Method org/apache/dubbo/config/ProviderConfig.setPayload:(Ljava/lang/Integer;)V
      93: aload_1
      94: aload_0
      95: getfield      #12                 // Field charset:Ljava/lang/String;
      98: invokevirtual #39                 // Method org/apache/dubbo/config/ProviderConfig.setCharset:(Ljava/lang/String;)V
     101: aload_1
     102: aload_0
     103: getfield      #14                 // Field buffer:Ljava/lang/Integer;
     106: invokevirtual #40                 // Method org/apache/dubbo/config/ProviderConfig.setBuffer:(Ljava/lang/Integer;)V
     109: aload_1
     110: aload_0
     111: getfield      #15                 // Field transporter:Ljava/lang/String;
     114: invokevirtual #41                 // Method org/apache/dubbo/config/ProviderConfig.setTransporter:(Ljava/lang/String;)V
     117: aload_1
     118: aload_0
     119: getfield      #16                 // Field exchanger:Ljava/lang/String;
     122: invokevirtual #42                 // Method org/apache/dubbo/config/ProviderConfig.setExchanger:(Ljava/lang/String;)V
     125: aload_1
     126: aload_0
     127: getfield      #17                 // Field dispatcher:Ljava/lang/String;
     130: invokevirtual #43                 // Method org/apache/dubbo/config/ProviderConfig.setDispatcher:(Ljava/lang/String;)V
     133: aload_1
     134: aload_0
     135: getfield      #18                 // Field networker:Ljava/lang/String;
     138: invokevirtual #44                 // Method org/apache/dubbo/config/ProviderConfig.setNetworker:(Ljava/lang/String;)V
     141: aload_1
     142: aload_0
     143: getfield      #19                 // Field server:Ljava/lang/String;
     146: invokevirtual #45                 // Method org/apache/dubbo/config/ProviderConfig.setServer:(Ljava/lang/String;)V
     149: aload_1
     150: aload_0
     151: getfield      #20                 // Field client:Ljava/lang/String;
     154: invokevirtual #46                 // Method org/apache/dubbo/config/ProviderConfig.setClient:(Ljava/lang/String;)V
     157: aload_1
     158: aload_0
     159: getfield      #21                 // Field telnet:Ljava/lang/String;
     162: invokevirtual #47                 // Method org/apache/dubbo/config/ProviderConfig.setTelnet:(Ljava/lang/String;)V
     165: aload_1
     166: aload_0
     167: getfield      #22                 // Field prompt:Ljava/lang/String;
     170: invokevirtual #48                 // Method org/apache/dubbo/config/ProviderConfig.setPrompt:(Ljava/lang/String;)V
     173: aload_1
     174: aload_0
     175: getfield      #23                 // Field status:Ljava/lang/String;
     178: invokevirtual #49                 // Method org/apache/dubbo/config/ProviderConfig.setStatus:(Ljava/lang/String;)V
     181: aload_1
     182: aload_0
     183: getfield      #24                 // Field wait:Ljava/lang/Integer;
     186: invokevirtual #50                 // Method org/apache/dubbo/config/ProviderConfig.setWait:(Ljava/lang/Integer;)V
     189: aload_1
     190: aload_0
     191: getfield      #25                 // Field isDefault:Ljava/lang/Boolean;
     194: invokevirtual #51                 // Method org/apache/dubbo/config/ProviderConfig.setDefault:(Ljava/lang/Boolean;)V
     197: aload_1
     198: areturn

  protected org.apache.dubbo.config.bootstrap.builders.ProviderBuilder getThis();
    Code:
       0: aload_0
       1: areturn

  public org.apache.dubbo.config.AbstractConfig build();
    Code:
       0: aload_0
       1: invokevirtual #52                 // Method build:()Lorg/apache/dubbo/config/ProviderConfig;
       4: areturn

  protected org.apache.dubbo.config.bootstrap.builders.AbstractBuilder getThis();
    Code:
       0: aload_0
       1: invokevirtual #3                  // Method getThis:()Lorg/apache/dubbo/config/bootstrap/builders/ProviderBuilder;
       4: areturn
}
