Compiled from "ReferenceBuilder.java"
public class org.apache.dubbo.config.bootstrap.builders.ReferenceBuilder<T> extends org.apache.dubbo.config.bootstrap.builders.AbstractReferenceBuilder<org.apache.dubbo.config.ReferenceConfig<T>, org.apache.dubbo.config.bootstrap.builders.ReferenceBuilder<T>> {
  private java.lang.String interfaceName;

  private java.lang.Class<?> interfaceClass;

  private java.lang.String client;

  private java.lang.String url;

  private java.util.List<org.apache.dubbo.config.MethodConfig> methods;

  private org.apache.dubbo.config.ConsumerConfig consumer;

  private java.lang.String protocol;

  private java.lang.String services;

  public org.apache.dubbo.config.bootstrap.builders.ReferenceBuilder();
    Code:
       0: aload_0
       1: invokespecial #1                  // Method org/apache/dubbo/config/bootstrap/builders/AbstractReferenceBuilder."<init>":()V
       4: return

  public static <T> org.apache.dubbo.config.bootstrap.builders.ReferenceBuilder<T> newBuilder();
    Code:
       0: new           #2                  // class org/apache/dubbo/config/bootstrap/builders/ReferenceBuilder
       3: dup
       4: invokespecial #3                  // Method "<init>":()V
       7: areturn

  public org.apache.dubbo.config.bootstrap.builders.ReferenceBuilder<T> id(java.lang.String);
    Code:
       0: aload_0
       1: aload_1
       2: invokespecial #4                  // Method org/apache/dubbo/config/bootstrap/builders/AbstractReferenceBuilder.id:(Ljava/lang/String;)Lorg/apache/dubbo/config/bootstrap/builders/AbstractBuilder;
       5: checkcast     #2                  // class org/apache/dubbo/config/bootstrap/builders/ReferenceBuilder
       8: areturn

  public org.apache.dubbo.config.bootstrap.builders.ReferenceBuilder<T> interfaceName(java.lang.String);
    Code:
       0: aload_0
       1: aload_1
       2: putfield      #5                  // Field interfaceName:Ljava/lang/String;
       5: aload_0
       6: invokevirtual #6                  // Method getThis:()Lorg/apache/dubbo/config/bootstrap/builders/ReferenceBuilder;
       9: areturn

  public org.apache.dubbo.config.bootstrap.builders.ReferenceBuilder<T> interfaceClass(java.lang.Class<?>);
    Code:
       0: aload_0
       1: aload_1
       2: putfield      #7                  // Field interfaceClass:Ljava/lang/Class;
       5: aload_0
       6: invokevirtual #6                  // Method getThis:()Lorg/apache/dubbo/config/bootstrap/builders/ReferenceBuilder;
       9: areturn

  public org.apache.dubbo.config.bootstrap.builders.ReferenceBuilder<T> client(java.lang.String);
    Code:
       0: aload_0
       1: aload_1
       2: putfield      #8                  // Field client:Ljava/lang/String;
       5: aload_0
       6: invokevirtual #6                  // Method getThis:()Lorg/apache/dubbo/config/bootstrap/builders/ReferenceBuilder;
       9: areturn

  public org.apache.dubbo.config.bootstrap.builders.ReferenceBuilder<T> url(java.lang.String);
    Code:
       0: aload_0
       1: aload_1
       2: putfield      #9                  // Field url:Ljava/lang/String;
       5: aload_0
       6: invokevirtual #6                  // Method getThis:()Lorg/apache/dubbo/config/bootstrap/builders/ReferenceBuilder;
       9: areturn

  public org.apache.dubbo.config.bootstrap.builders.ReferenceBuilder<T> addMethods(java.util.List<org.apache.dubbo.config.MethodConfig>);
    Code:
       0: aload_0
       1: getfield      #10                 // Field methods:Ljava/util/List;
       4: ifnonnull     18
       7: aload_0
       8: new           #11                 // class java/util/ArrayList
      11: dup
      12: invokespecial #12                 // Method java/util/ArrayList."<init>":()V
      15: putfield      #10                 // Field methods:Ljava/util/List;
      18: aload_0
      19: getfield      #10                 // Field methods:Ljava/util/List;
      22: aload_1
      23: invokeinterface #13,  2           // InterfaceMethod java/util/List.addAll:(Ljava/util/Collection;)Z
      28: pop
      29: aload_0
      30: invokevirtual #6                  // Method getThis:()Lorg/apache/dubbo/config/bootstrap/builders/ReferenceBuilder;
      33: areturn

  public org.apache.dubbo.config.bootstrap.builders.ReferenceBuilder<T> addMethod(org.apache.dubbo.config.MethodConfig);
    Code:
       0: aload_0
       1: getfield      #10                 // Field methods:Ljava/util/List;
       4: ifnonnull     18
       7: aload_0
       8: new           #11                 // class java/util/ArrayList
      11: dup
      12: invokespecial #12                 // Method java/util/ArrayList."<init>":()V
      15: putfield      #10                 // Field methods:Ljava/util/List;
      18: aload_0
      19: getfield      #10                 // Field methods:Ljava/util/List;
      22: aload_1
      23: invokeinterface #14,  2           // InterfaceMethod java/util/List.add:(Ljava/lang/Object;)Z
      28: pop
      29: aload_0
      30: invokevirtual #6                  // Method getThis:()Lorg/apache/dubbo/config/bootstrap/builders/ReferenceBuilder;
      33: areturn

  public org.apache.dubbo.config.bootstrap.builders.ReferenceBuilder<T> consumer(org.apache.dubbo.config.ConsumerConfig);
    Code:
       0: aload_0
       1: aload_1
       2: putfield      #15                 // Field consumer:Lorg/apache/dubbo/config/ConsumerConfig;
       5: aload_0
       6: invokevirtual #6                  // Method getThis:()Lorg/apache/dubbo/config/bootstrap/builders/ReferenceBuilder;
       9: areturn

  public org.apache.dubbo.config.bootstrap.builders.ReferenceBuilder<T> protocol(java.lang.String);
    Code:
       0: aload_0
       1: aload_1
       2: putfield      #16                 // Field protocol:Ljava/lang/String;
       5: aload_0
       6: invokevirtual #6                  // Method getThis:()Lorg/apache/dubbo/config/bootstrap/builders/ReferenceBuilder;
       9: areturn

  public org.apache.dubbo.config.bootstrap.builders.ReferenceBuilder<T> services(java.lang.String, java.lang.String...);
    Code:
       0: aload_0
       1: aload_1
       2: aload_2
       3: invokestatic  #17                 // Method org/apache/dubbo/common/utils/StringUtils.toCommaDelimitedString:(Ljava/lang/String;[Ljava/lang/String;)Ljava/lang/String;
       6: putfield      #18                 // Field services:Ljava/lang/String;
       9: aload_0
      10: invokevirtual #6                  // Method getThis:()Lorg/apache/dubbo/config/bootstrap/builders/ReferenceBuilder;
      13: areturn

  public org.apache.dubbo.config.ReferenceConfig<T> build();
    Code:
       0: new           #19                 // class org/apache/dubbo/config/ReferenceConfig
       3: dup
       4: invokespecial #20                 // Method org/apache/dubbo/config/ReferenceConfig."<init>":()V
       7: astore_1
       8: aload_0
       9: aload_1
      10: invokespecial #21                 // Method org/apache/dubbo/config/bootstrap/builders/AbstractReferenceBuilder.build:(Lorg/apache/dubbo/config/AbstractReferenceConfig;)V
      13: aload_1
      14: aload_0
      15: getfield      #5                  // Field interfaceName:Ljava/lang/String;
      18: invokevirtual #22                 // Method org/apache/dubbo/config/ReferenceConfig.setInterface:(Ljava/lang/String;)V
      21: aload_0
      22: getfield      #7                  // Field interfaceClass:Ljava/lang/Class;
      25: ifnull        36
      28: aload_1
      29: aload_0
      30: getfield      #7                  // Field interfaceClass:Ljava/lang/Class;
      33: invokevirtual #23                 // Method org/apache/dubbo/config/ReferenceConfig.setInterface:(Ljava/lang/Class;)V
      36: aload_1
      37: aload_0
      38: getfield      #8                  // Field client:Ljava/lang/String;
      41: invokevirtual #24                 // Method org/apache/dubbo/config/ReferenceConfig.setClient:(Ljava/lang/String;)V
      44: aload_1
      45: aload_0
      46: getfield      #9                  // Field url:Ljava/lang/String;
      49: invokevirtual #25                 // Method org/apache/dubbo/config/ReferenceConfig.setUrl:(Ljava/lang/String;)V
      52: aload_1
      53: aload_0
      54: getfield      #10                 // Field methods:Ljava/util/List;
      57: invokevirtual #26                 // Method org/apache/dubbo/config/ReferenceConfig.setMethods:(Ljava/util/List;)V
      60: aload_1
      61: aload_0
      62: getfield      #15                 // Field consumer:Lorg/apache/dubbo/config/ConsumerConfig;
      65: invokevirtual #27                 // Method org/apache/dubbo/config/ReferenceConfig.setConsumer:(Lorg/apache/dubbo/config/ConsumerConfig;)V
      68: aload_1
      69: aload_0
      70: getfield      #16                 // Field protocol:Ljava/lang/String;
      73: invokevirtual #28                 // Method org/apache/dubbo/config/ReferenceConfig.setProtocol:(Ljava/lang/String;)V
      76: aload_1
      77: aload_0
      78: getfield      #18                 // Field services:Ljava/lang/String;
      81: invokevirtual #29                 // Method org/apache/dubbo/config/ReferenceConfig.setServices:(Ljava/lang/String;)V
      84: aload_1
      85: areturn

  protected org.apache.dubbo.config.bootstrap.builders.ReferenceBuilder<T> getThis();
    Code:
       0: aload_0
       1: areturn

  public org.apache.dubbo.config.AbstractConfig build();
    Code:
       0: aload_0
       1: invokevirtual #30                 // Method build:()Lorg/apache/dubbo/config/ReferenceConfig;
       4: areturn

  protected org.apache.dubbo.config.bootstrap.builders.AbstractBuilder getThis();
    Code:
       0: aload_0
       1: invokevirtual #6                  // Method getThis:()Lorg/apache/dubbo/config/bootstrap/builders/ReferenceBuilder;
       4: areturn

  public org.apache.dubbo.config.bootstrap.builders.AbstractBuilder id(java.lang.String);
    Code:
       0: aload_0
       1: aload_1
       2: invokevirtual #31                 // Method id:(Ljava/lang/String;)Lorg/apache/dubbo/config/bootstrap/builders/ReferenceBuilder;
       5: areturn
}
