Compiled from "RegistryBuilder.java"
public class org.apache.dubbo.config.bootstrap.builders.RegistryBuilder extends org.apache.dubbo.config.bootstrap.builders.AbstractBuilder<org.apache.dubbo.config.RegistryConfig, org.apache.dubbo.config.bootstrap.builders.RegistryBuilder> {
  private java.lang.String address;

  private java.lang.String username;

  private java.lang.String password;

  private java.lang.Integer port;

  private java.lang.String protocol;

  private java.lang.String transporter;

  private java.lang.String server;

  private java.lang.String client;

  private java.lang.String cluster;

  private java.lang.String group;

  private java.lang.String version;

  private java.lang.Integer timeout;

  private java.lang.Integer session;

  private java.lang.String file;

  private java.lang.Integer wait;

  private java.lang.Boolean check;

  private java.lang.Boolean dynamic;

  private java.lang.Boolean register;

  private java.lang.Boolean subscribe;

  private java.util.Map<java.lang.String, java.lang.String> parameters;

  private java.lang.Boolean isDefault;

  private java.lang.Boolean simplified;

  private java.lang.String extraKeys;

  private java.lang.Boolean useAsConfigCenter;

  private java.lang.Boolean useAsMetadataCenter;

  private java.lang.String accepts;

  private java.lang.Boolean preferred;

  private java.lang.Integer weight;

  public org.apache.dubbo.config.bootstrap.builders.RegistryBuilder();
    Code:
       0: aload_0
       1: invokespecial #1                  // Method org/apache/dubbo/config/bootstrap/builders/AbstractBuilder."<init>":()V
       4: return

  public static org.apache.dubbo.config.bootstrap.builders.RegistryBuilder newBuilder();
    Code:
       0: new           #2                  // class org/apache/dubbo/config/bootstrap/builders/RegistryBuilder
       3: dup
       4: invokespecial #3                  // Method "<init>":()V
       7: areturn

  public org.apache.dubbo.config.bootstrap.builders.RegistryBuilder id(java.lang.String);
    Code:
       0: aload_0
       1: aload_1
       2: invokespecial #4                  // Method org/apache/dubbo/config/bootstrap/builders/AbstractBuilder.id:(Ljava/lang/String;)Lorg/apache/dubbo/config/bootstrap/builders/AbstractBuilder;
       5: checkcast     #2                  // class org/apache/dubbo/config/bootstrap/builders/RegistryBuilder
       8: areturn

  public org.apache.dubbo.config.bootstrap.builders.RegistryBuilder address(java.lang.String);
    Code:
       0: aload_0
       1: aload_1
       2: putfield      #5                  // Field address:Ljava/lang/String;
       5: aload_0
       6: invokevirtual #6                  // Method getThis:()Lorg/apache/dubbo/config/bootstrap/builders/RegistryBuilder;
       9: areturn

  public org.apache.dubbo.config.bootstrap.builders.RegistryBuilder username(java.lang.String);
    Code:
       0: aload_0
       1: aload_1
       2: putfield      #7                  // Field username:Ljava/lang/String;
       5: aload_0
       6: invokevirtual #6                  // Method getThis:()Lorg/apache/dubbo/config/bootstrap/builders/RegistryBuilder;
       9: areturn

  public org.apache.dubbo.config.bootstrap.builders.RegistryBuilder password(java.lang.String);
    Code:
       0: aload_0
       1: aload_1
       2: putfield      #8                  // Field password:Ljava/lang/String;
       5: aload_0
       6: invokevirtual #6                  // Method getThis:()Lorg/apache/dubbo/config/bootstrap/builders/RegistryBuilder;
       9: areturn

  public org.apache.dubbo.config.bootstrap.builders.RegistryBuilder port(java.lang.Integer);
    Code:
       0: aload_0
       1: aload_1
       2: putfield      #9                  // Field port:Ljava/lang/Integer;
       5: aload_0
       6: invokevirtual #6                  // Method getThis:()Lorg/apache/dubbo/config/bootstrap/builders/RegistryBuilder;
       9: areturn

  public org.apache.dubbo.config.bootstrap.builders.RegistryBuilder protocol(java.lang.String);
    Code:
       0: aload_0
       1: aload_1
       2: putfield      #10                 // Field protocol:Ljava/lang/String;
       5: aload_0
       6: invokevirtual #6                  // Method getThis:()Lorg/apache/dubbo/config/bootstrap/builders/RegistryBuilder;
       9: areturn

  public org.apache.dubbo.config.bootstrap.builders.RegistryBuilder transporter(java.lang.String);
    Code:
       0: aload_0
       1: aload_1
       2: putfield      #11                 // Field transporter:Ljava/lang/String;
       5: aload_0
       6: invokevirtual #6                  // Method getThis:()Lorg/apache/dubbo/config/bootstrap/builders/RegistryBuilder;
       9: areturn

  public org.apache.dubbo.config.bootstrap.builders.RegistryBuilder transport(java.lang.String);
    Code:
       0: aload_0
       1: aload_1
       2: putfield      #11                 // Field transporter:Ljava/lang/String;
       5: aload_0
       6: invokevirtual #6                  // Method getThis:()Lorg/apache/dubbo/config/bootstrap/builders/RegistryBuilder;
       9: areturn

  public org.apache.dubbo.config.bootstrap.builders.RegistryBuilder server(java.lang.String);
    Code:
       0: aload_0
       1: aload_1
       2: putfield      #12                 // Field server:Ljava/lang/String;
       5: aload_0
       6: invokevirtual #6                  // Method getThis:()Lorg/apache/dubbo/config/bootstrap/builders/RegistryBuilder;
       9: areturn

  public org.apache.dubbo.config.bootstrap.builders.RegistryBuilder client(java.lang.String);
    Code:
       0: aload_0
       1: aload_1
       2: putfield      #13                 // Field client:Ljava/lang/String;
       5: aload_0
       6: invokevirtual #6                  // Method getThis:()Lorg/apache/dubbo/config/bootstrap/builders/RegistryBuilder;
       9: areturn

  public org.apache.dubbo.config.bootstrap.builders.RegistryBuilder cluster(java.lang.String);
    Code:
       0: aload_0
       1: aload_1
       2: putfield      #14                 // Field cluster:Ljava/lang/String;
       5: aload_0
       6: invokevirtual #6                  // Method getThis:()Lorg/apache/dubbo/config/bootstrap/builders/RegistryBuilder;
       9: areturn

  public org.apache.dubbo.config.bootstrap.builders.RegistryBuilder group(java.lang.String);
    Code:
       0: aload_0
       1: aload_1
       2: putfield      #15                 // Field group:Ljava/lang/String;
       5: aload_0
       6: invokevirtual #6                  // Method getThis:()Lorg/apache/dubbo/config/bootstrap/builders/RegistryBuilder;
       9: areturn

  public org.apache.dubbo.config.bootstrap.builders.RegistryBuilder version(java.lang.String);
    Code:
       0: aload_0
       1: aload_1
       2: putfield      #16                 // Field version:Ljava/lang/String;
       5: aload_0
       6: invokevirtual #6                  // Method getThis:()Lorg/apache/dubbo/config/bootstrap/builders/RegistryBuilder;
       9: areturn

  public org.apache.dubbo.config.bootstrap.builders.RegistryBuilder timeout(java.lang.Integer);
    Code:
       0: aload_0
       1: aload_1
       2: putfield      #17                 // Field timeout:Ljava/lang/Integer;
       5: aload_0
       6: invokevirtual #6                  // Method getThis:()Lorg/apache/dubbo/config/bootstrap/builders/RegistryBuilder;
       9: areturn

  public org.apache.dubbo.config.bootstrap.builders.RegistryBuilder session(java.lang.Integer);
    Code:
       0: aload_0
       1: aload_1
       2: putfield      #18                 // Field session:Ljava/lang/Integer;
       5: aload_0
       6: invokevirtual #6                  // Method getThis:()Lorg/apache/dubbo/config/bootstrap/builders/RegistryBuilder;
       9: areturn

  public org.apache.dubbo.config.bootstrap.builders.RegistryBuilder file(java.lang.String);
    Code:
       0: aload_0
       1: aload_1
       2: putfield      #19                 // Field file:Ljava/lang/String;
       5: aload_0
       6: invokevirtual #6                  // Method getThis:()Lorg/apache/dubbo/config/bootstrap/builders/RegistryBuilder;
       9: areturn

  public org.apache.dubbo.config.bootstrap.builders.RegistryBuilder wait(java.lang.Integer);
    Code:
       0: aload_0
       1: aload_1
       2: putfield      #20                 // Field wait:Ljava/lang/Integer;
       5: aload_0
       6: invokevirtual #6                  // Method getThis:()Lorg/apache/dubbo/config/bootstrap/builders/RegistryBuilder;
       9: areturn

  public org.apache.dubbo.config.bootstrap.builders.RegistryBuilder isCheck(java.lang.Boolean);
    Code:
       0: aload_0
       1: aload_1
       2: putfield      #21                 // Field check:Ljava/lang/Boolean;
       5: aload_0
       6: invokevirtual #6                  // Method getThis:()Lorg/apache/dubbo/config/bootstrap/builders/RegistryBuilder;
       9: areturn

  public org.apache.dubbo.config.bootstrap.builders.RegistryBuilder isDynamic(java.lang.Boolean);
    Code:
       0: aload_0
       1: aload_1
       2: putfield      #22                 // Field dynamic:Ljava/lang/Boolean;
       5: aload_0
       6: invokevirtual #6                  // Method getThis:()Lorg/apache/dubbo/config/bootstrap/builders/RegistryBuilder;
       9: areturn

  public org.apache.dubbo.config.bootstrap.builders.RegistryBuilder register(java.lang.Boolean);
    Code:
       0: aload_0
       1: aload_1
       2: putfield      #23                 // Field register:Ljava/lang/Boolean;
       5: aload_0
       6: invokevirtual #6                  // Method getThis:()Lorg/apache/dubbo/config/bootstrap/builders/RegistryBuilder;
       9: areturn

  public org.apache.dubbo.config.bootstrap.builders.RegistryBuilder subscribe(java.lang.Boolean);
    Code:
       0: aload_0
       1: aload_1
       2: putfield      #24                 // Field subscribe:Ljava/lang/Boolean;
       5: aload_0
       6: invokevirtual #6                  // Method getThis:()Lorg/apache/dubbo/config/bootstrap/builders/RegistryBuilder;
       9: areturn

  public org.apache.dubbo.config.bootstrap.builders.RegistryBuilder appendParameter(java.lang.String, java.lang.String);
    Code:
       0: aload_0
       1: aload_0
       2: getfield      #25                 // Field parameters:Ljava/util/Map;
       5: aload_1
       6: aload_2
       7: invokestatic  #26                 // Method appendParameter:(Ljava/util/Map;Ljava/lang/String;Ljava/lang/String;)Ljava/util/Map;
      10: putfield      #25                 // Field parameters:Ljava/util/Map;
      13: aload_0
      14: invokevirtual #6                  // Method getThis:()Lorg/apache/dubbo/config/bootstrap/builders/RegistryBuilder;
      17: areturn

  public org.apache.dubbo.config.bootstrap.builders.RegistryBuilder parameter(java.lang.String, java.lang.String);
    Code:
       0: aload_0
       1: aload_1
       2: aload_2
       3: invokevirtual #27                 // Method appendParameter:(Ljava/lang/String;Ljava/lang/String;)Lorg/apache/dubbo/config/bootstrap/builders/RegistryBuilder;
       6: areturn

  public org.apache.dubbo.config.bootstrap.builders.RegistryBuilder appendParameters(java.util.Map<java.lang.String, java.lang.String>);
    Code:
       0: aload_0
       1: aload_0
       2: getfield      #25                 // Field parameters:Ljava/util/Map;
       5: aload_1
       6: invokestatic  #28                 // Method appendParameters:(Ljava/util/Map;Ljava/util/Map;)Ljava/util/Map;
       9: putfield      #25                 // Field parameters:Ljava/util/Map;
      12: aload_0
      13: invokevirtual #6                  // Method getThis:()Lorg/apache/dubbo/config/bootstrap/builders/RegistryBuilder;
      16: areturn

  public org.apache.dubbo.config.bootstrap.builders.RegistryBuilder isDefault(java.lang.Boolean);
    Code:
       0: aload_0
       1: aload_1
       2: putfield      #29                 // Field isDefault:Ljava/lang/Boolean;
       5: aload_0
       6: invokevirtual #6                  // Method getThis:()Lorg/apache/dubbo/config/bootstrap/builders/RegistryBuilder;
       9: areturn

  public org.apache.dubbo.config.bootstrap.builders.RegistryBuilder simplified(java.lang.Boolean);
    Code:
       0: aload_0
       1: aload_1
       2: putfield      #30                 // Field simplified:Ljava/lang/Boolean;
       5: aload_0
       6: invokevirtual #6                  // Method getThis:()Lorg/apache/dubbo/config/bootstrap/builders/RegistryBuilder;
       9: areturn

  public org.apache.dubbo.config.bootstrap.builders.RegistryBuilder extraKeys(java.lang.String);
    Code:
       0: aload_0
       1: aload_1
       2: putfield      #31                 // Field extraKeys:Ljava/lang/String;
       5: aload_0
       6: invokevirtual #6                  // Method getThis:()Lorg/apache/dubbo/config/bootstrap/builders/RegistryBuilder;
       9: areturn

  public org.apache.dubbo.config.bootstrap.builders.RegistryBuilder useAsConfigCenter(java.lang.Boolean);
    Code:
       0: aload_0
       1: aload_1
       2: putfield      #32                 // Field useAsConfigCenter:Ljava/lang/Boolean;
       5: aload_0
       6: invokevirtual #6                  // Method getThis:()Lorg/apache/dubbo/config/bootstrap/builders/RegistryBuilder;
       9: areturn

  public org.apache.dubbo.config.bootstrap.builders.RegistryBuilder useAsMetadataCenter(java.lang.Boolean);
    Code:
       0: aload_0
       1: aload_1
       2: putfield      #33                 // Field useAsMetadataCenter:Ljava/lang/Boolean;
       5: aload_0
       6: invokevirtual #6                  // Method getThis:()Lorg/apache/dubbo/config/bootstrap/builders/RegistryBuilder;
       9: areturn

  public org.apache.dubbo.config.bootstrap.builders.RegistryBuilder preferred(java.lang.Boolean);
    Code:
       0: aload_0
       1: aload_1
       2: putfield      #34                 // Field preferred:Ljava/lang/Boolean;
       5: aload_0
       6: invokevirtual #6                  // Method getThis:()Lorg/apache/dubbo/config/bootstrap/builders/RegistryBuilder;
       9: areturn

  public org.apache.dubbo.config.bootstrap.builders.RegistryBuilder accepts(java.lang.String);
    Code:
       0: aload_0
       1: aload_1
       2: putfield      #35                 // Field accepts:Ljava/lang/String;
       5: aload_0
       6: invokevirtual #6                  // Method getThis:()Lorg/apache/dubbo/config/bootstrap/builders/RegistryBuilder;
       9: areturn

  public org.apache.dubbo.config.bootstrap.builders.RegistryBuilder weight(java.lang.Integer);
    Code:
       0: aload_0
       1: aload_1
       2: putfield      #36                 // Field weight:Ljava/lang/Integer;
       5: aload_0
       6: invokevirtual #6                  // Method getThis:()Lorg/apache/dubbo/config/bootstrap/builders/RegistryBuilder;
       9: areturn

  public org.apache.dubbo.config.RegistryConfig build();
    Code:
       0: new           #37                 // class org/apache/dubbo/config/RegistryConfig
       3: dup
       4: invokespecial #38                 // Method org/apache/dubbo/config/RegistryConfig."<init>":()V
       7: astore_1
       8: aload_0
       9: aload_1
      10: invokespecial #39                 // Method org/apache/dubbo/config/bootstrap/builders/AbstractBuilder.build:(Lorg/apache/dubbo/config/AbstractConfig;)V
      13: aload_1
      14: aload_0
      15: getfield      #21                 // Field check:Ljava/lang/Boolean;
      18: invokevirtual #40                 // Method org/apache/dubbo/config/RegistryConfig.setCheck:(Ljava/lang/Boolean;)V
      21: aload_1
      22: aload_0
      23: getfield      #13                 // Field client:Ljava/lang/String;
      26: invokevirtual #41                 // Method org/apache/dubbo/config/RegistryConfig.setClient:(Ljava/lang/String;)V
      29: aload_1
      30: aload_0
      31: getfield      #14                 // Field cluster:Ljava/lang/String;
      34: invokevirtual #42                 // Method org/apache/dubbo/config/RegistryConfig.setCluster:(Ljava/lang/String;)V
      37: aload_1
      38: aload_0
      39: getfield      #29                 // Field isDefault:Ljava/lang/Boolean;
      42: invokevirtual #43                 // Method org/apache/dubbo/config/RegistryConfig.setDefault:(Ljava/lang/Boolean;)V
      45: aload_1
      46: aload_0
      47: getfield      #22                 // Field dynamic:Ljava/lang/Boolean;
      50: invokevirtual #44                 // Method org/apache/dubbo/config/RegistryConfig.setDynamic:(Ljava/lang/Boolean;)V
      53: aload_1
      54: aload_0
      55: getfield      #31                 // Field extraKeys:Ljava/lang/String;
      58: invokevirtual #45                 // Method org/apache/dubbo/config/RegistryConfig.setExtraKeys:(Ljava/lang/String;)V
      61: aload_1
      62: aload_0
      63: getfield      #19                 // Field file:Ljava/lang/String;
      66: invokevirtual #46                 // Method org/apache/dubbo/config/RegistryConfig.setFile:(Ljava/lang/String;)V
      69: aload_1
      70: aload_0
      71: getfield      #15                 // Field group:Ljava/lang/String;
      74: invokevirtual #47                 // Method org/apache/dubbo/config/RegistryConfig.setGroup:(Ljava/lang/String;)V
      77: aload_1
      78: aload_0
      79: getfield      #25                 // Field parameters:Ljava/util/Map;
      82: invokevirtual #48                 // Method org/apache/dubbo/config/RegistryConfig.setParameters:(Ljava/util/Map;)V
      85: aload_1
      86: aload_0
      87: getfield      #8                  // Field password:Ljava/lang/String;
      90: invokevirtual #49                 // Method org/apache/dubbo/config/RegistryConfig.setPassword:(Ljava/lang/String;)V
      93: aload_1
      94: aload_0
      95: getfield      #9                  // Field port:Ljava/lang/Integer;
      98: invokevirtual #50                 // Method org/apache/dubbo/config/RegistryConfig.setPort:(Ljava/lang/Integer;)V
     101: aload_1
     102: aload_0
     103: getfield      #10                 // Field protocol:Ljava/lang/String;
     106: invokevirtual #51                 // Method org/apache/dubbo/config/RegistryConfig.setProtocol:(Ljava/lang/String;)V
     109: aload_1
     110: aload_0
     111: getfield      #23                 // Field register:Ljava/lang/Boolean;
     114: invokevirtual #52                 // Method org/apache/dubbo/config/RegistryConfig.setRegister:(Ljava/lang/Boolean;)V
     117: aload_1
     118: aload_0
     119: getfield      #12                 // Field server:Ljava/lang/String;
     122: invokevirtual #53                 // Method org/apache/dubbo/config/RegistryConfig.setServer:(Ljava/lang/String;)V
     125: aload_1
     126: aload_0
     127: getfield      #18                 // Field session:Ljava/lang/Integer;
     130: invokevirtual #54                 // Method org/apache/dubbo/config/RegistryConfig.setSession:(Ljava/lang/Integer;)V
     133: aload_1
     134: aload_0
     135: getfield      #30                 // Field simplified:Ljava/lang/Boolean;
     138: invokevirtual #55                 // Method org/apache/dubbo/config/RegistryConfig.setSimplified:(Ljava/lang/Boolean;)V
     141: aload_1
     142: aload_0
     143: getfield      #24                 // Field subscribe:Ljava/lang/Boolean;
     146: invokevirtual #56                 // Method org/apache/dubbo/config/RegistryConfig.setSubscribe:(Ljava/lang/Boolean;)V
     149: aload_1
     150: aload_0
     151: getfield      #17                 // Field timeout:Ljava/lang/Integer;
     154: invokevirtual #57                 // Method org/apache/dubbo/config/RegistryConfig.setTimeout:(Ljava/lang/Integer;)V
     157: aload_1
     158: aload_0
     159: getfield      #11                 // Field transporter:Ljava/lang/String;
     162: invokevirtual #58                 // Method org/apache/dubbo/config/RegistryConfig.setTransporter:(Ljava/lang/String;)V
     165: aload_1
     166: aload_0
     167: getfield      #7                  // Field username:Ljava/lang/String;
     170: invokevirtual #59                 // Method org/apache/dubbo/config/RegistryConfig.setUsername:(Ljava/lang/String;)V
     173: aload_1
     174: aload_0
     175: getfield      #16                 // Field version:Ljava/lang/String;
     178: invokevirtual #60                 // Method org/apache/dubbo/config/RegistryConfig.setVersion:(Ljava/lang/String;)V
     181: aload_1
     182: aload_0
     183: getfield      #20                 // Field wait:Ljava/lang/Integer;
     186: invokevirtual #61                 // Method org/apache/dubbo/config/RegistryConfig.setWait:(Ljava/lang/Integer;)V
     189: aload_1
     190: aload_0
     191: getfield      #32                 // Field useAsConfigCenter:Ljava/lang/Boolean;
     194: invokevirtual #62                 // Method org/apache/dubbo/config/RegistryConfig.setUseAsConfigCenter:(Ljava/lang/Boolean;)V
     197: aload_1
     198: aload_0
     199: getfield      #33                 // Field useAsMetadataCenter:Ljava/lang/Boolean;
     202: invokevirtual #63                 // Method org/apache/dubbo/config/RegistryConfig.setUseAsMetadataCenter:(Ljava/lang/Boolean;)V
     205: aload_1
     206: aload_0
     207: getfield      #35                 // Field accepts:Ljava/lang/String;
     210: invokevirtual #64                 // Method org/apache/dubbo/config/RegistryConfig.setAccepts:(Ljava/lang/String;)V
     213: aload_1
     214: aload_0
     215: getfield      #34                 // Field preferred:Ljava/lang/Boolean;
     218: invokevirtual #65                 // Method org/apache/dubbo/config/RegistryConfig.setPreferred:(Ljava/lang/Boolean;)V
     221: aload_1
     222: aload_0
     223: getfield      #36                 // Field weight:Ljava/lang/Integer;
     226: invokevirtual #66                 // Method org/apache/dubbo/config/RegistryConfig.setWeight:(Ljava/lang/Integer;)V
     229: aload_1
     230: aload_0
     231: getfield      #5                  // Field address:Ljava/lang/String;
     234: invokevirtual #67                 // Method org/apache/dubbo/config/RegistryConfig.setAddress:(Ljava/lang/String;)V
     237: aload_1
     238: areturn

  protected org.apache.dubbo.config.bootstrap.builders.RegistryBuilder getThis();
    Code:
       0: aload_0
       1: areturn

  public org.apache.dubbo.config.AbstractConfig build();
    Code:
       0: aload_0
       1: invokevirtual #68                 // Method build:()Lorg/apache/dubbo/config/RegistryConfig;
       4: areturn

  protected org.apache.dubbo.config.bootstrap.builders.AbstractBuilder getThis();
    Code:
       0: aload_0
       1: invokevirtual #6                  // Method getThis:()Lorg/apache/dubbo/config/bootstrap/builders/RegistryBuilder;
       4: areturn

  public org.apache.dubbo.config.bootstrap.builders.AbstractBuilder id(java.lang.String);
    Code:
       0: aload_0
       1: aload_1
       2: invokevirtual #69                 // Method id:(Ljava/lang/String;)Lorg/apache/dubbo/config/bootstrap/builders/RegistryBuilder;
       5: areturn
}
