Compiled from "ServiceBuilder.java"
public class org.apache.dubbo.config.bootstrap.builders.ServiceBuilder<U> extends org.apache.dubbo.config.bootstrap.builders.AbstractServiceBuilder<org.apache.dubbo.config.ServiceConfig<U>, org.apache.dubbo.config.bootstrap.builders.ServiceBuilder<U>> {
  private java.lang.String interfaceName;

  private java.lang.Class<?> interfaceClass;

  private U ref;

  private java.lang.String path;

  private java.util.List<org.apache.dubbo.config.MethodConfig> methods;

  private org.apache.dubbo.config.ProviderConfig provider;

  private java.lang.String providerIds;

  private java.lang.String generic;

  public org.apache.dubbo.config.bootstrap.builders.ServiceBuilder();
    Code:
       0: aload_0
       1: invokespecial #1                  // Method org/apache/dubbo/config/bootstrap/builders/AbstractServiceBuilder."<init>":()V
       4: return

  public static <T> org.apache.dubbo.config.bootstrap.builders.ServiceBuilder<T> newBuilder();
    Code:
       0: new           #2                  // class org/apache/dubbo/config/bootstrap/builders/ServiceBuilder
       3: dup
       4: invokespecial #3                  // Method "<init>":()V
       7: areturn

  public org.apache.dubbo.config.bootstrap.builders.ServiceBuilder<U> id(java.lang.String);
    Code:
       0: aload_0
       1: aload_1
       2: invokespecial #4                  // Method org/apache/dubbo/config/bootstrap/builders/AbstractServiceBuilder.id:(Ljava/lang/String;)Lorg/apache/dubbo/config/bootstrap/builders/AbstractBuilder;
       5: checkcast     #2                  // class org/apache/dubbo/config/bootstrap/builders/ServiceBuilder
       8: areturn

  public org.apache.dubbo.config.bootstrap.builders.ServiceBuilder<U> interfaceName(java.lang.String);
    Code:
       0: aload_0
       1: aload_1
       2: putfield      #5                  // Field interfaceName:Ljava/lang/String;
       5: aload_0
       6: invokevirtual #6                  // Method getThis:()Lorg/apache/dubbo/config/bootstrap/builders/ServiceBuilder;
       9: areturn

  public org.apache.dubbo.config.bootstrap.builders.ServiceBuilder<U> interfaceClass(java.lang.Class<?>);
    Code:
       0: aload_0
       1: aload_1
       2: putfield      #7                  // Field interfaceClass:Ljava/lang/Class;
       5: aload_0
       6: invokevirtual #6                  // Method getThis:()Lorg/apache/dubbo/config/bootstrap/builders/ServiceBuilder;
       9: areturn

  public org.apache.dubbo.config.bootstrap.builders.ServiceBuilder<U> ref(U);
    Code:
       0: aload_0
       1: aload_1
       2: putfield      #8                  // Field ref:Ljava/lang/Object;
       5: aload_0
       6: invokevirtual #6                  // Method getThis:()Lorg/apache/dubbo/config/bootstrap/builders/ServiceBuilder;
       9: areturn

  public org.apache.dubbo.config.bootstrap.builders.ServiceBuilder<U> path(java.lang.String);
    Code:
       0: aload_0
       1: aload_1
       2: putfield      #9                  // Field path:Ljava/lang/String;
       5: aload_0
       6: invokevirtual #6                  // Method getThis:()Lorg/apache/dubbo/config/bootstrap/builders/ServiceBuilder;
       9: areturn

  public org.apache.dubbo.config.bootstrap.builders.ServiceBuilder<U> addMethod(org.apache.dubbo.config.MethodConfig);
    Code:
       0: aload_0
       1: getfield      #10                 // Field methods:Ljava/util/List;
       4: ifnonnull     18
       7: aload_0
       8: new           #11                 // class java/util/ArrayList
      11: dup
      12: invokespecial #12                 // Method java/util/ArrayList."<init>":()V
      15: putfield      #10                 // Field methods:Ljava/util/List;
      18: aload_0
      19: getfield      #10                 // Field methods:Ljava/util/List;
      22: aload_1
      23: invokeinterface #13,  2           // InterfaceMethod java/util/List.add:(Ljava/lang/Object;)Z
      28: pop
      29: aload_0
      30: invokevirtual #6                  // Method getThis:()Lorg/apache/dubbo/config/bootstrap/builders/ServiceBuilder;
      33: areturn

  public org.apache.dubbo.config.bootstrap.builders.ServiceBuilder<U> addMethods(java.util.List<? extends org.apache.dubbo.config.MethodConfig>);
    Code:
       0: aload_0
       1: getfield      #10                 // Field methods:Ljava/util/List;
       4: ifnonnull     18
       7: aload_0
       8: new           #11                 // class java/util/ArrayList
      11: dup
      12: invokespecial #12                 // Method java/util/ArrayList."<init>":()V
      15: putfield      #10                 // Field methods:Ljava/util/List;
      18: aload_0
      19: getfield      #10                 // Field methods:Ljava/util/List;
      22: aload_1
      23: invokeinterface #14,  2           // InterfaceMethod java/util/List.addAll:(Ljava/util/Collection;)Z
      28: pop
      29: aload_0
      30: invokevirtual #6                  // Method getThis:()Lorg/apache/dubbo/config/bootstrap/builders/ServiceBuilder;
      33: areturn

  public org.apache.dubbo.config.bootstrap.builders.ServiceBuilder<U> provider(org.apache.dubbo.config.ProviderConfig);
    Code:
       0: aload_0
       1: aload_1
       2: putfield      #15                 // Field provider:Lorg/apache/dubbo/config/ProviderConfig;
       5: aload_0
       6: invokevirtual #6                  // Method getThis:()Lorg/apache/dubbo/config/bootstrap/builders/ServiceBuilder;
       9: areturn

  public org.apache.dubbo.config.bootstrap.builders.ServiceBuilder<U> providerIds(java.lang.String);
    Code:
       0: aload_0
       1: aload_1
       2: putfield      #16                 // Field providerIds:Ljava/lang/String;
       5: aload_0
       6: invokevirtual #6                  // Method getThis:()Lorg/apache/dubbo/config/bootstrap/builders/ServiceBuilder;
       9: areturn

  public org.apache.dubbo.config.bootstrap.builders.ServiceBuilder<U> generic(java.lang.String);
    Code:
       0: aload_0
       1: aload_1
       2: putfield      #17                 // Field generic:Ljava/lang/String;
       5: aload_0
       6: invokevirtual #6                  // Method getThis:()Lorg/apache/dubbo/config/bootstrap/builders/ServiceBuilder;
       9: areturn

  public org.apache.dubbo.config.ServiceConfig<U> build();
    Code:
       0: new           #18                 // class org/apache/dubbo/config/ServiceConfig
       3: dup
       4: invokespecial #19                 // Method org/apache/dubbo/config/ServiceConfig."<init>":()V
       7: astore_1
       8: aload_0
       9: aload_1
      10: invokespecial #20                 // Method org/apache/dubbo/config/bootstrap/builders/AbstractServiceBuilder.build:(Lorg/apache/dubbo/config/AbstractServiceConfig;)V
      13: aload_1
      14: aload_0
      15: getfield      #5                  // Field interfaceName:Ljava/lang/String;
      18: invokevirtual #21                 // Method org/apache/dubbo/config/ServiceConfig.setInterface:(Ljava/lang/String;)V
      21: aload_1
      22: aload_0
      23: getfield      #7                  // Field interfaceClass:Ljava/lang/Class;
      26: invokevirtual #22                 // Method org/apache/dubbo/config/ServiceConfig.setInterface:(Ljava/lang/Class;)V
      29: aload_1
      30: aload_0
      31: getfield      #8                  // Field ref:Ljava/lang/Object;
      34: invokevirtual #23                 // Method org/apache/dubbo/config/ServiceConfig.setRef:(Ljava/lang/Object;)V
      37: aload_1
      38: aload_0
      39: getfield      #9                  // Field path:Ljava/lang/String;
      42: invokevirtual #24                 // Method org/apache/dubbo/config/ServiceConfig.setPath:(Ljava/lang/String;)V
      45: aload_1
      46: aload_0
      47: getfield      #10                 // Field methods:Ljava/util/List;
      50: invokevirtual #25                 // Method org/apache/dubbo/config/ServiceConfig.setMethods:(Ljava/util/List;)V
      53: aload_1
      54: aload_0
      55: getfield      #15                 // Field provider:Lorg/apache/dubbo/config/ProviderConfig;
      58: invokevirtual #26                 // Method org/apache/dubbo/config/ServiceConfig.setProvider:(Lorg/apache/dubbo/config/ProviderConfig;)V
      61: aload_1
      62: aload_0
      63: getfield      #16                 // Field providerIds:Ljava/lang/String;
      66: invokevirtual #27                 // Method org/apache/dubbo/config/ServiceConfig.setProviderIds:(Ljava/lang/String;)V
      69: aload_1
      70: aload_0
      71: getfield      #17                 // Field generic:Ljava/lang/String;
      74: invokevirtual #28                 // Method org/apache/dubbo/config/ServiceConfig.setGeneric:(Ljava/lang/String;)V
      77: aload_1
      78: areturn

  protected org.apache.dubbo.config.bootstrap.builders.ServiceBuilder<U> getThis();
    Code:
       0: aload_0
       1: areturn

  public org.apache.dubbo.config.AbstractConfig build();
    Code:
       0: aload_0
       1: invokevirtual #29                 // Method build:()Lorg/apache/dubbo/config/ServiceConfig;
       4: areturn

  protected org.apache.dubbo.config.bootstrap.builders.AbstractBuilder getThis();
    Code:
       0: aload_0
       1: invokevirtual #6                  // Method getThis:()Lorg/apache/dubbo/config/bootstrap/builders/ServiceBuilder;
       4: areturn

  public org.apache.dubbo.config.bootstrap.builders.AbstractBuilder id(java.lang.String);
    Code:
       0: aload_0
       1: aload_1
       2: invokevirtual #30                 // Method id:(Ljava/lang/String;)Lorg/apache/dubbo/config/bootstrap/builders/ServiceBuilder;
       5: areturn
}
