Compiled from "Codec2.java"
public final class org.apache.dubbo.remoting.Codec2$DecodeResult extends java.lang.Enum<org.apache.dubbo.remoting.Codec2$DecodeResult> {
  public static final org.apache.dubbo.remoting.Codec2$DecodeResult NEED_MORE_INPUT;

  public static final org.apache.dubbo.remoting.Codec2$DecodeResult SKIP_SOME_INPUT;

  private static final org.apache.dubbo.remoting.Codec2$DecodeResult[] $VALUES;

  public static org.apache.dubbo.remoting.Codec2$DecodeResult[] values();
    Code:
       0: getstatic     #1                  // Field $VALUES:[Lorg/apache/dubbo/remoting/Codec2$DecodeResult;
       3: invokevirtual #2                  // Method "[Lorg/apache/dubbo/remoting/Codec2$DecodeResult;".clone:()Ljava/lang/Object;
       6: checkcast     #3                  // class "[Lorg/apache/dubbo/remoting/Codec2$DecodeResult;"
       9: areturn

  public static org.apache.dubbo.remoting.Codec2$DecodeResult valueOf(java.lang.String);
    Code:
       0: ldc           #4                  // class org/apache/dubbo/remoting/Codec2$DecodeResult
       2: aload_0
       3: invokestatic  #5                  // Method java/lang/Enum.valueOf:(Ljava/lang/Class;Ljava/lang/String;)Ljava/lang/Enum;
       6: checkcast     #4                  // class org/apache/dubbo/remoting/Codec2$DecodeResult
       9: areturn

  private org.apache.dubbo.remoting.Codec2$DecodeResult();
    Code:
       0: aload_0
       1: aload_1
       2: iload_2
       3: invokespecial #6                  // Method java/lang/Enum."<init>":(Ljava/lang/String;I)V
       6: return

  static {};
    Code:
       0: new           #4                  // class org/apache/dubbo/remoting/Codec2$DecodeResult
       3: dup
       4: ldc           #7                  // String NEED_MORE_INPUT
       6: iconst_0
       7: invokespecial #8                  // Method "<init>":(Ljava/lang/String;I)V
      10: putstatic     #9                  // Field NEED_MORE_INPUT:Lorg/apache/dubbo/remoting/Codec2$DecodeResult;
      13: new           #4                  // class org/apache/dubbo/remoting/Codec2$DecodeResult
      16: dup
      17: ldc           #10                 // String SKIP_SOME_INPUT
      19: iconst_1
      20: invokespecial #8                  // Method "<init>":(Ljava/lang/String;I)V
      23: putstatic     #11                 // Field SKIP_SOME_INPUT:Lorg/apache/dubbo/remoting/Codec2$DecodeResult;
      26: iconst_2
      27: anewarray     #4                  // class org/apache/dubbo/remoting/Codec2$DecodeResult
      30: dup
      31: iconst_0
      32: getstatic     #9                  // Field NEED_MORE_INPUT:Lorg/apache/dubbo/remoting/Codec2$DecodeResult;
      35: aastore
      36: dup
      37: iconst_1
      38: getstatic     #11                 // Field SKIP_SOME_INPUT:Lorg/apache/dubbo/remoting/Codec2$DecodeResult;
      41: aastore
      42: putstatic     #1                  // Field $VALUES:[Lorg/apache/dubbo/remoting/Codec2$DecodeResult;
      45: return
}
