Compiled from "Constants.java"
public interface org.apache.dubbo.remoting.Constants {
  public static final java.lang.String BUFFER_KEY;

  public static final int DEFAULT_BUFFER_SIZE;

  public static final int MAX_BUFFER_SIZE;

  public static final int MIN_BUFFER_SIZE;

  public static final java.lang.String IDLE_TIMEOUT_KEY;

  public static final int DEFAULT_IDLE_TIMEOUT;

  public static final java.lang.String ACCEPTS_KEY;

  public static final int DEFAULT_ACCEPTS;

  public static final java.lang.String CONNECT_QUEUE_CAPACITY;

  public static final java.lang.String CONNECT_QUEUE_WARNING_SIZE;

  public static final int DEFAULT_CONNECT_QUEUE_WARNING_SIZE;

  public static final java.lang.String CHARSET_KEY;

  public static final java.lang.String DEFAULT_CHARSET;

  public static final int HEARTBEAT_CHECK_TICK;

  public static final long LEAST_HEARTBEAT_DURATION;

  public static final int TICKS_PER_WHEEL;

  public static final java.lang.String PAYLOAD_KEY;

  public static final int DEFAULT_PAYLOAD;

  public static final java.lang.String CONNECT_TIMEOUT_KEY;

  public static final int DEFAULT_CONNECT_TIMEOUT;

  public static final java.lang.String SERIALIZATION_KEY;

  public static final java.lang.String PREFER_SERIALIZATION_KEY;

  public static final java.lang.String DEFAULT_REMOTING_SERIALIZATION_PROPERTY_KEY;

  public static final java.lang.String CODEC_KEY;

  public static final java.lang.String CODEC_VERSION_KEY;

  public static final java.lang.String SERVER_KEY;

  public static final java.lang.String IS_PU_SERVER_KEY;

  public static final java.lang.String CLIENT_KEY;

  public static final java.lang.String DEFAULT_REMOTING_CLIENT;

  public static final java.lang.String TRANSPORTER_KEY;

  public static final java.lang.String DEFAULT_TRANSPORTER;

  public static final java.lang.String EXCHANGER_KEY;

  public static final java.lang.String DEFAULT_EXCHANGER;

  public static final java.lang.String DISPACTHER_KEY;

  public static final int DEFAULT_IO_THREADS;

  public static final java.lang.String EVENT_LOOP_BOSS_POOL_NAME;

  public static final java.lang.String EVENT_LOOP_WORKER_POOL_NAME;

  public static final java.lang.String NETTY_EPOLL_ENABLE_KEY;

  public static final java.lang.String BIND_IP_KEY;

  public static final java.lang.String BIND_PORT_KEY;

  public static final java.lang.String SENT_KEY;

  public static final java.lang.String DISPATCHER_KEY;

  public static final java.lang.String CHANNEL_ATTRIBUTE_READONLY_KEY;

  public static final java.lang.String CHANNEL_READONLYEVENT_SENT_KEY;

  public static final java.lang.String CHANNEL_SEND_READONLYEVENT_KEY;

  public static final java.lang.String RECONNECT_KEY;

  public static final int DEFAULT_RECONNECT_PERIOD;

  public static final java.lang.String SEND_RECONNECT_KEY;

  public static final java.lang.String CHECK_KEY;

  public static final java.lang.String PROMPT_KEY;

  public static final java.lang.String DEFAULT_PROMPT;

  public static final java.lang.String TELNET_KEY;

  public static final java.lang.String HEARTBEAT_KEY;

  public static final java.lang.String HEARTBEAT_CONFIG_KEY;

  public static final int DEFAULT_HEARTBEAT;

  public static final java.lang.String HEARTBEAT_TIMEOUT_KEY;

  public static final java.lang.String CONNECTIONS_KEY;

  public static final int DEFAULT_BACKLOG;

  public static final java.lang.String CONNECTION;

  public static final java.lang.String KEEP_ALIVE;

  public static final java.lang.String KEEP_ALIVE_HEADER;

  public static final java.lang.String OK_HTTP;

  public static final java.lang.String URL_CONNECTION;

  public static final java.lang.String APACHE_HTTP_CLIENT;

  static {};
    Code:
       0: invokestatic  #1                  // Method java/lang/Runtime.getRuntime:()Ljava/lang/Runtime;
       3: invokevirtual #2                  // Method java/lang/Runtime.availableProcessors:()I
       6: iconst_1
       7: iadd
       8: bipush        32
      10: invokestatic  #3                  // Method java/lang/Math.min:(II)I
      13: putstatic     #4                  // Field DEFAULT_IO_THREADS:I
      16: return
}
