Compiled from "ExecutionException.java"
public class org.apache.dubbo.remoting.ExecutionException extends org.apache.dubbo.remoting.RemotingException {
  private static final long serialVersionUID;

  private final java.lang.Object request;

  public org.apache.dubbo.remoting.ExecutionException(java.lang.Object, org.apache.dubbo.remoting.Channel, java.lang.String, java.lang.Throwable);
    Code:
       0: aload_0
       1: aload_2
       2: aload_3
       3: aload         4
       5: invokespecial #1                  // Method org/apache/dubbo/remoting/RemotingException."<init>":(Lorg/apache/dubbo/remoting/Channel;Ljava/lang/String;Ljava/lang/Throwable;)V
       8: aload_0
       9: aload_1
      10: putfield      #2                  // Field request:Ljava/lang/Object;
      13: return

  public org.apache.dubbo.remoting.ExecutionException(java.lang.Object, org.apache.dubbo.remoting.Channel, java.lang.String);
    Code:
       0: aload_0
       1: aload_2
       2: aload_3
       3: invokespecial #3                  // Method org/apache/dubbo/remoting/RemotingException."<init>":(Lorg/apache/dubbo/remoting/Channel;Ljava/lang/String;)V
       6: aload_0
       7: aload_1
       8: putfield      #2                  // Field request:Ljava/lang/Object;
      11: return

  public org.apache.dubbo.remoting.ExecutionException(java.lang.Object, org.apache.dubbo.remoting.Channel, java.lang.Throwable);
    Code:
       0: aload_0
       1: aload_2
       2: aload_3
       3: invokespecial #4                  // Method org/apache/dubbo/remoting/RemotingException."<init>":(Lorg/apache/dubbo/remoting/Channel;Ljava/lang/Throwable;)V
       6: aload_0
       7: aload_1
       8: putfield      #2                  // Field request:Ljava/lang/Object;
      11: return

  public org.apache.dubbo.remoting.ExecutionException(java.lang.Object, java.net.InetSocketAddress, java.net.InetSocketAddress, java.lang.String, java.lang.Throwable);
    Code:
       0: aload_0
       1: aload_2
       2: aload_3
       3: aload         4
       5: aload         5
       7: invokespecial #5                  // Method org/apache/dubbo/remoting/RemotingException."<init>":(Ljava/net/InetSocketAddress;Ljava/net/InetSocketAddress;Ljava/lang/String;Ljava/lang/Throwable;)V
      10: aload_0
      11: aload_1
      12: putfield      #2                  // Field request:Ljava/lang/Object;
      15: return

  public org.apache.dubbo.remoting.ExecutionException(java.lang.Object, java.net.InetSocketAddress, java.net.InetSocketAddress, java.lang.String);
    Code:
       0: aload_0
       1: aload_2
       2: aload_3
       3: aload         4
       5: invokespecial #6                  // Method org/apache/dubbo/remoting/RemotingException."<init>":(Ljava/net/InetSocketAddress;Ljava/net/InetSocketAddress;Ljava/lang/String;)V
       8: aload_0
       9: aload_1
      10: putfield      #2                  // Field request:Ljava/lang/Object;
      13: return

  public org.apache.dubbo.remoting.ExecutionException(java.lang.Object, java.net.InetSocketAddress, java.net.InetSocketAddress, java.lang.Throwable);
    Code:
       0: aload_0
       1: aload_2
       2: aload_3
       3: aload         4
       5: invokespecial #7                  // Method org/apache/dubbo/remoting/RemotingException."<init>":(Ljava/net/InetSocketAddress;Ljava/net/InetSocketAddress;Ljava/lang/Throwable;)V
       8: aload_0
       9: aload_1
      10: putfield      #2                  // Field request:Ljava/lang/Object;
      13: return

  public java.lang.Object getRequest();
    Code:
       0: aload_0
       1: getfield      #2                  // Field request:Ljava/lang/Object;
       4: areturn
}
