Compiled from "RemotingScopeModelInitializer.java"
public class org.apache.dubbo.remoting.RemotingScopeModelInitializer implements org.apache.dubbo.rpc.model.ScopeModelInitializer {
  private static final org.apache.dubbo.common.logger.ErrorTypeAwareLogger logger;

  public org.apache.dubbo.remoting.RemotingScopeModelInitializer();
    Code:
       0: aload_0
       1: invokespecial #2                  // Method java/lang/Object."<init>":()V
       4: return

  public void initializeFrameworkModel(org.apache.dubbo.rpc.model.FrameworkModel);
    Code:
       0: return

  public void initializeApplicationModel(org.apache.dubbo.rpc.model.ApplicationModel);
    Code:
       0: aload_1
       1: aload_1
       2: invokedynamic #3,  0              // InvokeDynamic #0:onDestroy:(Lorg/apache/dubbo/rpc/model/ApplicationModel;)Lorg/apache/dubbo/rpc/model/ScopeModelDestroyListener;
       7: invokevirtual #4                  // Method org/apache/dubbo/rpc/model/ApplicationModel.addDestroyListener:(Lorg/apache/dubbo/rpc/model/ScopeModelDestroyListener;)V
      10: return

  public void initializeModuleModel(org.apache.dubbo.rpc.model.ModuleModel);
    Code:
       0: return

  private static void lambda$initializeApplicationModel$0(org.apache.dubbo.rpc.model.ApplicationModel, org.apache.dubbo.rpc.model.ScopeModel);
    Code:
       0: aload_0
       1: ldc           #5                  // class org/apache/dubbo/remoting/zookeeper/ZookeeperTransporter
       3: invokevirtual #6                  // Method org/apache/dubbo/rpc/model/ApplicationModel.getExtensionLoader:(Ljava/lang/Class;)Lorg/apache/dubbo/common/extension/ExtensionLoader;
       6: invokevirtual #7                  // Method org/apache/dubbo/common/extension/ExtensionLoader.getLoadedExtensionInstances:()Ljava/util/List;
       9: astore_2
      10: aload_2
      11: invokeinterface #8,  1            // InterfaceMethod java/util/List.iterator:()Ljava/util/Iterator;
      16: astore_3
      17: aload_3
      18: invokeinterface #9,  1            // InterfaceMethod java/util/Iterator.hasNext:()Z
      23: ifeq          47
      26: aload_3
      27: invokeinterface #10,  1           // InterfaceMethod java/util/Iterator.next:()Ljava/lang/Object;
      32: checkcast     #5                  // class org/apache/dubbo/remoting/zookeeper/ZookeeperTransporter
      35: astore        4
      37: aload         4
      39: invokeinterface #11,  1           // InterfaceMethod org/apache/dubbo/remoting/zookeeper/ZookeeperTransporter.destroy:()V
      44: goto          17
      47: goto          88
      50: astore_2
      51: getstatic     #13                 // Field logger:Lorg/apache/dubbo/common/logger/ErrorTypeAwareLogger;
      54: ldc           #14                 // String 6-12
      56: ldc           #15                 // String
      58: ldc           #15                 // String
      60: new           #16                 // class java/lang/StringBuilder
      63: dup
      64: invokespecial #17                 // Method java/lang/StringBuilder."<init>":()V
      67: ldc           #18                 // String Error encountered while destroying ZookeeperTransporter:
      69: invokevirtual #19                 // Method java/lang/StringBuilder.append:(Ljava/lang/String;)Ljava/lang/StringBuilder;
      72: aload_2
      73: invokevirtual #20                 // Method java/lang/Exception.getMessage:()Ljava/lang/String;
      76: invokevirtual #19                 // Method java/lang/StringBuilder.append:(Ljava/lang/String;)Ljava/lang/StringBuilder;
      79: invokevirtual #21                 // Method java/lang/StringBuilder.toString:()Ljava/lang/String;
      82: aload_2
      83: invokeinterface #22,  6           // InterfaceMethod org/apache/dubbo/common/logger/ErrorTypeAwareLogger.error:(Ljava/lang/String;Ljava/lang/String;Ljava/lang/String;Ljava/lang/String;Ljava/lang/Throwable;)V
      88: return
    Exception table:
       from    to  target type
           0    47    50   Class java/lang/Exception

  static {};
    Code:
       0: ldc           #23                 // class org/apache/dubbo/remoting/RemotingScopeModelInitializer
       2: invokestatic  #24                 // Method org/apache/dubbo/common/logger/LoggerFactory.getErrorTypeAwareLogger:(Ljava/lang/Class;)Lorg/apache/dubbo/common/logger/ErrorTypeAwareLogger;
       5: putstatic     #13                 // Field logger:Lorg/apache/dubbo/common/logger/ErrorTypeAwareLogger;
       8: return
}
