Compiled from "RemotingException.java"
public class org.apache.dubbo.remoting.RemotingException extends java.lang.Exception {
  private static final long serialVersionUID;

  private java.net.InetSocketAddress localAddress;

  private java.net.InetSocketAddress remoteAddress;

  public org.apache.dubbo.remoting.RemotingException(org.apache.dubbo.remoting.Channel, java.lang.String);
    Code:
       0: aload_0
       1: aload_1
       2: ifnonnull     9
       5: aconst_null
       6: goto          15
       9: aload_1
      10: invokeinterface #1,  1            // InterfaceMethod org/apache/dubbo/remoting/Channel.getLocalAddress:()Ljava/net/InetSocketAddress;
      15: aload_1
      16: ifnonnull     23
      19: aconst_null
      20: goto          29
      23: aload_1
      24: invokeinterface #2,  1            // InterfaceMethod org/apache/dubbo/remoting/Channel.getRemoteAddress:()Ljava/net/InetSocketAddress;
      29: aload_2
      30: invokespecial #3                  // Method "<init>":(Ljava/net/InetSocketAddress;Ljava/net/InetSocketAddress;Ljava/lang/String;)V
      33: return

  public org.apache.dubbo.remoting.RemotingException(java.net.InetSocketAddress, java.net.InetSocketAddress, java.lang.String);
    Code:
       0: aload_0
       1: aload_3
       2: invokespecial #4                  // Method java/lang/Exception."<init>":(Ljava/lang/String;)V
       5: aload_0
       6: aload_1
       7: putfield      #5                  // Field localAddress:Ljava/net/InetSocketAddress;
      10: aload_0
      11: aload_2
      12: putfield      #6                  // Field remoteAddress:Ljava/net/InetSocketAddress;
      15: return

  public org.apache.dubbo.remoting.RemotingException(org.apache.dubbo.remoting.Channel, java.lang.Throwable);
    Code:
       0: aload_0
       1: aload_1
       2: ifnonnull     9
       5: aconst_null
       6: goto          15
       9: aload_1
      10: invokeinterface #1,  1            // InterfaceMethod org/apache/dubbo/remoting/Channel.getLocalAddress:()Ljava/net/InetSocketAddress;
      15: aload_1
      16: ifnonnull     23
      19: aconst_null
      20: goto          29
      23: aload_1
      24: invokeinterface #2,  1            // InterfaceMethod org/apache/dubbo/remoting/Channel.getRemoteAddress:()Ljava/net/InetSocketAddress;
      29: aload_2
      30: invokespecial #7                  // Method "<init>":(Ljava/net/InetSocketAddress;Ljava/net/InetSocketAddress;Ljava/lang/Throwable;)V
      33: return

  public org.apache.dubbo.remoting.RemotingException(java.net.InetSocketAddress, java.net.InetSocketAddress, java.lang.Throwable);
    Code:
       0: aload_0
       1: aload_3
       2: invokespecial #8                  // Method java/lang/Exception."<init>":(Ljava/lang/Throwable;)V
       5: aload_0
       6: aload_1
       7: putfield      #5                  // Field localAddress:Ljava/net/InetSocketAddress;
      10: aload_0
      11: aload_2
      12: putfield      #6                  // Field remoteAddress:Ljava/net/InetSocketAddress;
      15: return

  public org.apache.dubbo.remoting.RemotingException(org.apache.dubbo.remoting.Channel, java.lang.String, java.lang.Throwable);
    Code:
       0: aload_0
       1: aload_1
       2: ifnonnull     9
       5: aconst_null
       6: goto          15
       9: aload_1
      10: invokeinterface #1,  1            // InterfaceMethod org/apache/dubbo/remoting/Channel.getLocalAddress:()Ljava/net/InetSocketAddress;
      15: aload_1
      16: ifnonnull     23
      19: aconst_null
      20: goto          29
      23: aload_1
      24: invokeinterface #2,  1            // InterfaceMethod org/apache/dubbo/remoting/Channel.getRemoteAddress:()Ljava/net/InetSocketAddress;
      29: aload_2
      30: aload_3
      31: invokespecial #9                  // Method "<init>":(Ljava/net/InetSocketAddress;Ljava/net/InetSocketAddress;Ljava/lang/String;Ljava/lang/Throwable;)V
      34: return

  public org.apache.dubbo.remoting.RemotingException(java.net.InetSocketAddress, java.net.InetSocketAddress, java.lang.String, java.lang.Throwable);
    Code:
       0: aload_0
       1: aload_3
       2: aload         4
       4: invokespecial #10                 // Method java/lang/Exception."<init>":(Ljava/lang/String;Ljava/lang/Throwable;)V
       7: aload_0
       8: aload_1
       9: putfield      #5                  // Field localAddress:Ljava/net/InetSocketAddress;
      12: aload_0
      13: aload_2
      14: putfield      #6                  // Field remoteAddress:Ljava/net/InetSocketAddress;
      17: return

  public java.net.InetSocketAddress getLocalAddress();
    Code:
       0: aload_0
       1: getfield      #5                  // Field localAddress:Ljava/net/InetSocketAddress;
       4: areturn

  public java.net.InetSocketAddress getRemoteAddress();
    Code:
       0: aload_0
       1: getfield      #6                  // Field remoteAddress:Ljava/net/InetSocketAddress;
       4: areturn
}
