Compiled from "TimeoutException.java"
public class org.apache.dubbo.remoting.TimeoutException extends org.apache.dubbo.remoting.RemotingException {
  public static final int CLIENT_SIDE;

  public static final int SERVER_SIDE;

  private static final long serialVersionUID;

  private final int phase;

  public org.apache.dubbo.remoting.TimeoutException(boolean, org.apache.dubbo.remoting.Channel, java.lang.String);
    Code:
       0: aload_0
       1: aload_2
       2: aload_3
       3: invokespecial #1                  // Method org/apache/dubbo/remoting/RemotingException."<init>":(Lorg/apache/dubbo/remoting/Channel;Ljava/lang/String;)V
       6: aload_0
       7: iload_1
       8: ifeq          15
      11: iconst_1
      12: goto          16
      15: iconst_0
      16: putfield      #3                  // Field phase:I
      19: return

  public org.apache.dubbo.remoting.TimeoutException(boolean, java.net.InetSocketAddress, java.net.InetSocketAddress, java.lang.String);
    Code:
       0: aload_0
       1: aload_2
       2: aload_3
       3: aload         4
       5: invokespecial #4                  // Method org/apache/dubbo/remoting/RemotingException."<init>":(Ljava/net/InetSocketAddress;Ljava/net/InetSocketAddress;Ljava/lang/String;)V
       8: aload_0
       9: iload_1
      10: ifeq          17
      13: iconst_1
      14: goto          18
      17: iconst_0
      18: putfield      #3                  // Field phase:I
      21: return

  public int getPhase();
    Code:
       0: aload_0
       1: getfield      #3                  // Field phase:I
       4: ireturn

  public boolean isServerSide();
    Code:
       0: aload_0
       1: getfield      #3                  // Field phase:I
       4: iconst_1
       5: if_icmpne     12
       8: iconst_1
       9: goto          13
      12: iconst_0
      13: ireturn

  public boolean isClientSide();
    Code:
       0: aload_0
       1: getfield      #3                  // Field phase:I
       4: ifne          11
       7: iconst_1
       8: goto          12
      11: iconst_0
      12: ireturn
}
