Compiled from "Transporters.java"
public class org.apache.dubbo.remoting.Transporters {
  private org.apache.dubbo.remoting.Transporters();
    Code:
       0: aload_0
       1: invokespecial #1                  // Method java/lang/Object."<init>":()V
       4: return

  public static org.apache.dubbo.remoting.RemotingServer bind(java.lang.String, org.apache.dubbo.remoting.ChannelHandler...) throws org.apache.dubbo.remoting.RemotingException;
    Code:
       0: aload_0
       1: invokestatic  #2                  // Method org/apache/dubbo/common/URL.valueOf:(Ljava/lang/String;)Lorg/apache/dubbo/common/URL;
       4: aload_1
       5: invokestatic  #3                  // Method bind:(Lorg/apache/dubbo/common/URL;[Lorg/apache/dubbo/remoting/ChannelHandler;)Lorg/apache/dubbo/remoting/RemotingServer;
       8: areturn

  public static org.apache.dubbo.remoting.RemotingServer bind(org.apache.dubbo.common.URL, org.apache.dubbo.remoting.ChannelHandler...) throws org.apache.dubbo.remoting.RemotingException;
    Code:
       0: aload_0
       1: ifnonnull     14
       4: new           #4                  // class java/lang/IllegalArgumentException
       7: dup
       8: ldc           #5                  // String url == null
      10: invokespecial #6                  // Method java/lang/IllegalArgumentException."<init>":(Ljava/lang/String;)V
      13: athrow
      14: aload_1
      15: ifnull        23
      18: aload_1
      19: arraylength
      20: ifne          33
      23: new           #4                  // class java/lang/IllegalArgumentException
      26: dup
      27: ldc           #7                  // String handlers == null
      29: invokespecial #6                  // Method java/lang/IllegalArgumentException."<init>":(Ljava/lang/String;)V
      32: athrow
      33: aload_1
      34: arraylength
      35: iconst_1
      36: if_icmpne     46
      39: aload_1
      40: iconst_0
      41: aaload
      42: astore_2
      43: goto          55
      46: new           #8                  // class org/apache/dubbo/remoting/transport/ChannelHandlerDispatcher
      49: dup
      50: aload_1
      51: invokespecial #9                  // Method org/apache/dubbo/remoting/transport/ChannelHandlerDispatcher."<init>":([Lorg/apache/dubbo/remoting/ChannelHandler;)V
      54: astore_2
      55: aload_0
      56: invokestatic  #10                 // Method getTransporter:(Lorg/apache/dubbo/common/URL;)Lorg/apache/dubbo/remoting/Transporter;
      59: aload_0
      60: aload_2
      61: invokeinterface #11,  3           // InterfaceMethod org/apache/dubbo/remoting/Transporter.bind:(Lorg/apache/dubbo/common/URL;Lorg/apache/dubbo/remoting/ChannelHandler;)Lorg/apache/dubbo/remoting/RemotingServer;
      66: areturn

  public static org.apache.dubbo.remoting.Client connect(java.lang.String, org.apache.dubbo.remoting.ChannelHandler...) throws org.apache.dubbo.remoting.RemotingException;
    Code:
       0: aload_0
       1: invokestatic  #2                  // Method org/apache/dubbo/common/URL.valueOf:(Ljava/lang/String;)Lorg/apache/dubbo/common/URL;
       4: aload_1
       5: invokestatic  #12                 // Method connect:(Lorg/apache/dubbo/common/URL;[Lorg/apache/dubbo/remoting/ChannelHandler;)Lorg/apache/dubbo/remoting/Client;
       8: areturn

  public static org.apache.dubbo.remoting.Client connect(org.apache.dubbo.common.URL, org.apache.dubbo.remoting.ChannelHandler...) throws org.apache.dubbo.remoting.RemotingException;
    Code:
       0: aload_0
       1: ifnonnull     14
       4: new           #4                  // class java/lang/IllegalArgumentException
       7: dup
       8: ldc           #5                  // String url == null
      10: invokespecial #6                  // Method java/lang/IllegalArgumentException."<init>":(Ljava/lang/String;)V
      13: athrow
      14: aload_1
      15: ifnull        23
      18: aload_1
      19: arraylength
      20: ifne          34
      23: new           #13                 // class org/apache/dubbo/remoting/transport/ChannelHandlerAdapter
      26: dup
      27: invokespecial #14                 // Method org/apache/dubbo/remoting/transport/ChannelHandlerAdapter."<init>":()V
      30: astore_2
      31: goto          56
      34: aload_1
      35: arraylength
      36: iconst_1
      37: if_icmpne     47
      40: aload_1
      41: iconst_0
      42: aaload
      43: astore_2
      44: goto          56
      47: new           #8                  // class org/apache/dubbo/remoting/transport/ChannelHandlerDispatcher
      50: dup
      51: aload_1
      52: invokespecial #9                  // Method org/apache/dubbo/remoting/transport/ChannelHandlerDispatcher."<init>":([Lorg/apache/dubbo/remoting/ChannelHandler;)V
      55: astore_2
      56: aload_0
      57: invokestatic  #10                 // Method getTransporter:(Lorg/apache/dubbo/common/URL;)Lorg/apache/dubbo/remoting/Transporter;
      60: aload_0
      61: aload_2
      62: invokeinterface #15,  3           // InterfaceMethod org/apache/dubbo/remoting/Transporter.connect:(Lorg/apache/dubbo/common/URL;Lorg/apache/dubbo/remoting/ChannelHandler;)Lorg/apache/dubbo/remoting/Client;
      67: areturn

  public static org.apache.dubbo.remoting.Transporter getTransporter(org.apache.dubbo.common.URL);
    Code:
       0: aload_0
       1: invokevirtual #16                 // Method org/apache/dubbo/common/URL.getOrDefaultFrameworkModel:()Lorg/apache/dubbo/rpc/model/FrameworkModel;
       4: ldc           #17                 // class org/apache/dubbo/remoting/Transporter
       6: invokevirtual #18                 // Method org/apache/dubbo/rpc/model/FrameworkModel.getExtensionLoader:(Ljava/lang/Class;)Lorg/apache/dubbo/common/extension/ExtensionLoader;
       9: invokevirtual #19                 // Method org/apache/dubbo/common/extension/ExtensionLoader.getAdaptiveExtension:()Ljava/lang/Object;
      12: checkcast     #17                 // class org/apache/dubbo/remoting/Transporter
      15: areturn
}
