Compiled from "Main.java"
public class org.apache.dubbo.container.Main {
  public static final java.lang.String CONTAINER_KEY;

  public static final java.lang.String SHUTDOWN_HOOK_KEY;

  private static final org.apache.dubbo.common.logger.ErrorTypeAwareLogger logger;

  private static final org.apache.dubbo.common.extension.ExtensionLoader<org.apache.dubbo.container.Container> LOADER;

  private static final java.util.concurrent.locks.ReentrantLock LOCK;

  private static final java.util.concurrent.locks.Condition STOP;

  public org.apache.dubbo.container.Main();
    Code:
       0: aload_0
       1: invokespecial #5                  // Method java/lang/Object."<init>":()V
       4: return

  public static void main(java.lang.String[]);
    Code:
       0: aload_0
       1: invokestatic  #6                  // Method org/apache/dubbo/common/utils/ArrayUtils.isEmpty:([Ljava/lang/Object;)Z
       4: ifeq          27
       7: ldc           #8                  // String dubbo.container
       9: getstatic     #9                  // Field LOADER:Lorg/apache/dubbo/common/extension/ExtensionLoader;
      12: invokevirtual #10                 // Method org/apache/dubbo/common/extension/ExtensionLoader.getDefaultExtensionName:()Ljava/lang/String;
      15: invokestatic  #11                 // Method java/lang/System.getProperty:(Ljava/lang/String;Ljava/lang/String;)Ljava/lang/String;
      18: astore_1
      19: getstatic     #12                 // Field org/apache/dubbo/common/constants/CommonConstants.COMMA_SPLIT_PATTERN:Ljava/util/regex/Pattern;
      22: aload_1
      23: invokevirtual #13                 // Method java/util/regex/Pattern.split:(Ljava/lang/CharSequence;)[Ljava/lang/String;
      26: astore_0
      27: new           #14                 // class java/util/ArrayList
      30: dup
      31: invokespecial #15                 // Method java/util/ArrayList."<init>":()V
      34: astore_1
      35: iconst_0
      36: istore_2
      37: iload_2
      38: aload_0
      39: arraylength
      40: if_icmpge     65
      43: aload_1
      44: getstatic     #9                  // Field LOADER:Lorg/apache/dubbo/common/extension/ExtensionLoader;
      47: aload_0
      48: iload_2
      49: aaload
      50: invokevirtual #16                 // Method org/apache/dubbo/common/extension/ExtensionLoader.getExtension:(Ljava/lang/String;)Ljava/lang/Object;
      53: invokeinterface #17,  2           // InterfaceMethod java/util/List.add:(Ljava/lang/Object;)Z
      58: pop
      59: iinc          2, 1
      62: goto          37
      65: getstatic     #4                  // Field logger:Lorg/apache/dubbo/common/logger/ErrorTypeAwareLogger;
      68: new           #18                 // class java/lang/StringBuilder
      71: dup
      72: invokespecial #19                 // Method java/lang/StringBuilder."<init>":()V
      75: ldc           #20                 // String Use container type(
      77: invokevirtual #21                 // Method java/lang/StringBuilder.append:(Ljava/lang/String;)Ljava/lang/StringBuilder;
      80: aload_0
      81: invokestatic  #22                 // Method java/util/Arrays.toString:([Ljava/lang/Object;)Ljava/lang/String;
      84: invokevirtual #21                 // Method java/lang/StringBuilder.append:(Ljava/lang/String;)Ljava/lang/StringBuilder;
      87: ldc           #23                 // String ) to run dubbo serivce.
      89: invokevirtual #21                 // Method java/lang/StringBuilder.append:(Ljava/lang/String;)Ljava/lang/StringBuilder;
      92: invokevirtual #24                 // Method java/lang/StringBuilder.toString:()Ljava/lang/String;
      95: invokeinterface #25,  2           // InterfaceMethod org/apache/dubbo/common/logger/ErrorTypeAwareLogger.info:(Ljava/lang/String;)V
     100: ldc           #26                 // String true
     102: ldc           #27                 // String dubbo.shutdown.hook
     104: invokestatic  #28                 // Method java/lang/System.getProperty:(Ljava/lang/String;)Ljava/lang/String;
     107: invokevirtual #29                 // Method java/lang/String.equals:(Ljava/lang/Object;)Z
     110: ifeq          129
     113: invokestatic  #30                 // Method java/lang/Runtime.getRuntime:()Ljava/lang/Runtime;
     116: new           #31                 // class org/apache/dubbo/container/Main$1
     119: dup
     120: ldc           #32                 // String dubbo-container-shutdown-hook
     122: aload_1
     123: invokespecial #33                 // Method org/apache/dubbo/container/Main$1."<init>":(Ljava/lang/String;Ljava/util/List;)V
     126: invokevirtual #34                 // Method java/lang/Runtime.addShutdownHook:(Ljava/lang/Thread;)V
     129: aload_1
     130: invokeinterface #35,  1           // InterfaceMethod java/util/List.iterator:()Ljava/util/Iterator;
     135: astore_2
     136: aload_2
     137: invokeinterface #36,  1           // InterfaceMethod java/util/Iterator.hasNext:()Z
     142: ifeq          202
     145: aload_2
     146: invokeinterface #37,  1           // InterfaceMethod java/util/Iterator.next:()Ljava/lang/Object;
     151: checkcast     #38                 // class org/apache/dubbo/container/Container
     154: astore_3
     155: aload_3
     156: invokeinterface #39,  1           // InterfaceMethod org/apache/dubbo/container/Container.start:()V
     161: getstatic     #4                  // Field logger:Lorg/apache/dubbo/common/logger/ErrorTypeAwareLogger;
     164: new           #18                 // class java/lang/StringBuilder
     167: dup
     168: invokespecial #19                 // Method java/lang/StringBuilder."<init>":()V
     171: ldc           #40                 // String Dubbo
     173: invokevirtual #21                 // Method java/lang/StringBuilder.append:(Ljava/lang/String;)Ljava/lang/StringBuilder;
     176: aload_3
     177: invokevirtual #41                 // Method java/lang/Object.getClass:()Ljava/lang/Class;
     180: invokevirtual #42                 // Method java/lang/Class.getSimpleName:()Ljava/lang/String;
     183: invokevirtual #21                 // Method java/lang/StringBuilder.append:(Ljava/lang/String;)Ljava/lang/StringBuilder;
     186: ldc           #43                 // String  started!
     188: invokevirtual #21                 // Method java/lang/StringBuilder.append:(Ljava/lang/String;)Ljava/lang/StringBuilder;
     191: invokevirtual #24                 // Method java/lang/StringBuilder.toString:()Ljava/lang/String;
     194: invokeinterface #25,  2           // InterfaceMethod org/apache/dubbo/common/logger/ErrorTypeAwareLogger.info:(Ljava/lang/String;)V
     199: goto          136
     202: getstatic     #44                 // Field java/lang/System.out:Ljava/io/PrintStream;
     205: new           #18                 // class java/lang/StringBuilder
     208: dup
     209: invokespecial #19                 // Method java/lang/StringBuilder."<init>":()V
     212: new           #45                 // class java/text/SimpleDateFormat
     215: dup
     216: ldc           #46                 // String [yyyy-MM-dd HH:mm:ss]
     218: invokespecial #47                 // Method java/text/SimpleDateFormat."<init>":(Ljava/lang/String;)V
     221: new           #48                 // class java/util/Date
     224: dup
     225: invokespecial #49                 // Method java/util/Date."<init>":()V
     228: invokevirtual #50                 // Method java/text/SimpleDateFormat.format:(Ljava/util/Date;)Ljava/lang/String;
     231: invokevirtual #21                 // Method java/lang/StringBuilder.append:(Ljava/lang/String;)Ljava/lang/StringBuilder;
     234: ldc           #51                 // String  Dubbo service server started!
     236: invokevirtual #21                 // Method java/lang/StringBuilder.append:(Ljava/lang/String;)Ljava/lang/StringBuilder;
     239: invokevirtual #24                 // Method java/lang/StringBuilder.toString:()Ljava/lang/String;
     242: invokevirtual #52                 // Method java/io/PrintStream.println:(Ljava/lang/String;)V
     245: goto          272
     248: astore_1
     249: getstatic     #4                  // Field logger:Lorg/apache/dubbo/common/logger/ErrorTypeAwareLogger;
     252: ldc           #54                 // String 5-35
     254: ldc           #55                 // String
     256: ldc           #55                 // String
     258: aload_1
     259: invokevirtual #56                 // Method java/lang/RuntimeException.getMessage:()Ljava/lang/String;
     262: aload_1
     263: invokeinterface #57,  6           // InterfaceMethod org/apache/dubbo/common/logger/ErrorTypeAwareLogger.error:(Ljava/lang/String;Ljava/lang/String;Ljava/lang/String;Ljava/lang/String;Ljava/lang/Throwable;)V
     268: iconst_1
     269: invokestatic  #58                 // Method java/lang/System.exit:(I)V
     272: getstatic     #3                  // Field LOCK:Ljava/util/concurrent/locks/ReentrantLock;
     275: invokevirtual #59                 // Method java/util/concurrent/locks/ReentrantLock.lock:()V
     278: getstatic     #2                  // Field STOP:Ljava/util/concurrent/locks/Condition;
     281: invokeinterface #60,  1           // InterfaceMethod java/util/concurrent/locks/Condition.await:()V
     286: getstatic     #3                  // Field LOCK:Ljava/util/concurrent/locks/ReentrantLock;
     289: invokevirtual #61                 // Method java/util/concurrent/locks/ReentrantLock.unlock:()V
     292: goto          333
     295: astore_1
     296: getstatic     #4                  // Field logger:Lorg/apache/dubbo/common/logger/ErrorTypeAwareLogger;
     299: ldc           #63                 // String 0-6
     301: ldc           #55                 // String
     303: ldc           #55                 // String
     305: ldc           #64                 // String Dubbo service server stopped, interrupted by other thread!
     307: aload_1
     308: invokeinterface #65,  6           // InterfaceMethod org/apache/dubbo/common/logger/ErrorTypeAwareLogger.warn:(Ljava/lang/String;Ljava/lang/String;Ljava/lang/String;Ljava/lang/String;Ljava/lang/Throwable;)V
     313: getstatic     #3                  // Field LOCK:Ljava/util/concurrent/locks/ReentrantLock;
     316: invokevirtual #61                 // Method java/util/concurrent/locks/ReentrantLock.unlock:()V
     319: goto          333
     322: astore        4
     324: getstatic     #3                  // Field LOCK:Ljava/util/concurrent/locks/ReentrantLock;
     327: invokevirtual #61                 // Method java/util/concurrent/locks/ReentrantLock.unlock:()V
     330: aload         4
     332: athrow
     333: return
    Exception table:
       from    to  target type
           0   245   248   Class java/lang/RuntimeException
         272   286   295   Class java/lang/InterruptedException
         272   286   322   any
         295   313   322   any
         322   324   322   any

  static org.apache.dubbo.common.logger.ErrorTypeAwareLogger access$000();
    Code:
       0: getstatic     #4                  // Field logger:Lorg/apache/dubbo/common/logger/ErrorTypeAwareLogger;
       3: areturn

  static java.util.concurrent.locks.ReentrantLock access$100();
    Code:
       0: getstatic     #3                  // Field LOCK:Ljava/util/concurrent/locks/ReentrantLock;
       3: areturn

  static java.util.concurrent.locks.Condition access$200();
    Code:
       0: getstatic     #2                  // Field STOP:Ljava/util/concurrent/locks/Condition;
       3: areturn

  static {};
    Code:
       0: ldc           #7                  // class org/apache/dubbo/container/Main
       2: invokestatic  #66                 // Method org/apache/dubbo/common/logger/LoggerFactory.getErrorTypeAwareLogger:(Ljava/lang/Class;)Lorg/apache/dubbo/common/logger/ErrorTypeAwareLogger;
       5: putstatic     #4                  // Field logger:Lorg/apache/dubbo/common/logger/ErrorTypeAwareLogger;
       8: ldc           #38                 // class org/apache/dubbo/container/Container
      10: invokestatic  #67                 // Method org/apache/dubbo/common/extension/ExtensionLoader.getExtensionLoader:(Ljava/lang/Class;)Lorg/apache/dubbo/common/extension/ExtensionLoader;
      13: putstatic     #9                  // Field LOADER:Lorg/apache/dubbo/common/extension/ExtensionLoader;
      16: new           #68                 // class java/util/concurrent/locks/ReentrantLock
      19: dup
      20: invokespecial #69                 // Method java/util/concurrent/locks/ReentrantLock."<init>":()V
      23: putstatic     #3                  // Field LOCK:Ljava/util/concurrent/locks/ReentrantLock;
      26: getstatic     #3                  // Field LOCK:Ljava/util/concurrent/locks/ReentrantLock;
      29: invokevirtual #70                 // Method java/util/concurrent/locks/ReentrantLock.newCondition:()Ljava/util/concurrent/locks/Condition;
      32: putstatic     #2                  // Field STOP:Ljava/util/concurrent/locks/Condition;
      35: return
}
