Compiled from "Main.java"
final class org.apache.dubbo.container.Main$1 extends java.lang.Thread {
  final java.util.List val$containers;

  org.apache.dubbo.container.Main$1(java.lang.String, java.util.List);
    Code:
       0: aload_0
       1: aload_2
       2: putfield      #2                  // Field val$containers:Ljava/util/List;
       5: aload_0
       6: aload_1
       7: invokespecial #3                  // Method java/lang/Thread."<init>":(Ljava/lang/String;)V
      10: return

  public void run();
    Code:
       0: aload_0
       1: getfield      #2                  // Field val$containers:Ljava/util/List;
       4: invokeinterface #4,  1            // InterfaceMethod java/util/List.iterator:()Ljava/util/Iterator;
       9: astore_1
      10: aload_1
      11: invokeinterface #5,  1            // InterfaceMethod java/util/Iterator.hasNext:()Z
      16: ifeq          133
      19: aload_1
      20: invokeinterface #6,  1            // InterfaceMethod java/util/Iterator.next:()Ljava/lang/Object;
      25: checkcast     #7                  // class org/apache/dubbo/container/Container
      28: astore_2
      29: aload_2
      30: invokeinterface #8,  1            // InterfaceMethod org/apache/dubbo/container/Container.stop:()V
      35: invokestatic  #9                  // Method org/apache/dubbo/container/Main.access$000:()Lorg/apache/dubbo/common/logger/ErrorTypeAwareLogger;
      38: new           #10                 // class java/lang/StringBuilder
      41: dup
      42: invokespecial #11                 // Method java/lang/StringBuilder."<init>":()V
      45: ldc           #12                 // String Dubbo
      47: invokevirtual #13                 // Method java/lang/StringBuilder.append:(Ljava/lang/String;)Ljava/lang/StringBuilder;
      50: aload_2
      51: invokevirtual #14                 // Method java/lang/Object.getClass:()Ljava/lang/Class;
      54: invokevirtual #15                 // Method java/lang/Class.getSimpleName:()Ljava/lang/String;
      57: invokevirtual #13                 // Method java/lang/StringBuilder.append:(Ljava/lang/String;)Ljava/lang/StringBuilder;
      60: ldc           #16                 // String  stopped!
      62: invokevirtual #13                 // Method java/lang/StringBuilder.append:(Ljava/lang/String;)Ljava/lang/StringBuilder;
      65: invokevirtual #17                 // Method java/lang/StringBuilder.toString:()Ljava/lang/String;
      68: invokeinterface #18,  2           // InterfaceMethod org/apache/dubbo/common/logger/ErrorTypeAwareLogger.info:(Ljava/lang/String;)V
      73: goto          96
      76: astore_3
      77: invokestatic  #9                  // Method org/apache/dubbo/container/Main.access$000:()Lorg/apache/dubbo/common/logger/ErrorTypeAwareLogger;
      80: ldc           #20                 // String 5-20
      82: ldc           #21                 // String
      84: ldc           #21                 // String
      86: aload_3
      87: invokevirtual #22                 // Method java/lang/Throwable.getMessage:()Ljava/lang/String;
      90: aload_3
      91: invokeinterface #23,  6           // InterfaceMethod org/apache/dubbo/common/logger/ErrorTypeAwareLogger.error:(Ljava/lang/String;Ljava/lang/String;Ljava/lang/String;Ljava/lang/String;Ljava/lang/Throwable;)V
      96: invokestatic  #24                 // Method org/apache/dubbo/container/Main.access$100:()Ljava/util/concurrent/locks/ReentrantLock;
      99: invokevirtual #25                 // Method java/util/concurrent/locks/ReentrantLock.lock:()V
     102: invokestatic  #26                 // Method org/apache/dubbo/container/Main.access$200:()Ljava/util/concurrent/locks/Condition;
     105: invokeinterface #27,  1           // InterfaceMethod java/util/concurrent/locks/Condition.signal:()V
     110: invokestatic  #24                 // Method org/apache/dubbo/container/Main.access$100:()Ljava/util/concurrent/locks/ReentrantLock;
     113: invokevirtual #28                 // Method java/util/concurrent/locks/ReentrantLock.unlock:()V
     116: goto          130
     119: astore        4
     121: invokestatic  #24                 // Method org/apache/dubbo/container/Main.access$100:()Ljava/util/concurrent/locks/ReentrantLock;
     124: invokevirtual #28                 // Method java/util/concurrent/locks/ReentrantLock.unlock:()V
     127: aload         4
     129: athrow
     130: goto          10
     133: return
    Exception table:
       from    to  target type
          29    73    76   Class java/lang/Throwable
          96   110   119   any
         119   121   119   any
}
