Compiled from "FailedSubscribedTask.java"
public final class org.apache.dubbo.registry.retry.FailedSubscribedTask extends org.apache.dubbo.registry.retry.AbstractRetryTask {
  private static final java.lang.String NAME;

  private final org.apache.dubbo.registry.NotifyListener listener;

  public org.apache.dubbo.registry.retry.FailedSubscribedTask(org.apache.dubbo.common.URL, org.apache.dubbo.registry.support.FailbackRegistry, org.apache.dubbo.registry.NotifyListener);
    Code:
       0: aload_0
       1: aload_1
       2: aload_2
       3: ldc           #2                  // String retry subscribe
       5: invokespecial #3                  // Method org/apache/dubbo/registry/retry/AbstractRetryTask."<init>":(Lorg/apache/dubbo/common/URL;Lorg/apache/dubbo/registry/support/FailbackRegistry;Ljava/lang/String;)V
       8: aload_3
       9: ifnonnull     20
      12: new           #4                  // class java/lang/IllegalArgumentException
      15: dup
      16: invokespecial #5                  // Method java/lang/IllegalArgumentException."<init>":()V
      19: athrow
      20: aload_0
      21: aload_3
      22: putfield      #6                  // Field listener:Lorg/apache/dubbo/registry/NotifyListener;
      25: return

  protected void doRetry(org.apache.dubbo.common.URL, org.apache.dubbo.registry.support.FailbackRegistry, org.apache.dubbo.common.timer.Timeout);
    Code:
       0: aload_2
       1: aload_1
       2: aload_0
       3: getfield      #6                  // Field listener:Lorg/apache/dubbo/registry/NotifyListener;
       6: invokevirtual #7                  // Method org/apache/dubbo/registry/support/FailbackRegistry.doSubscribe:(Lorg/apache/dubbo/common/URL;Lorg/apache/dubbo/registry/NotifyListener;)V
       9: aload_2
      10: aload_1
      11: aload_0
      12: getfield      #6                  // Field listener:Lorg/apache/dubbo/registry/NotifyListener;
      15: invokevirtual #8                  // Method org/apache/dubbo/registry/support/FailbackRegistry.removeFailedSubscribedTask:(Lorg/apache/dubbo/common/URL;Lorg/apache/dubbo/registry/NotifyListener;)V
      18: return
}
