Compiled from "FailedRegisteredTask.java"
public final class org.apache.dubbo.registry.retry.FailedRegisteredTask extends org.apache.dubbo.registry.retry.AbstractRetryTask {
  private static final java.lang.String NAME;

  public org.apache.dubbo.registry.retry.FailedRegisteredTask(org.apache.dubbo.common.URL, org.apache.dubbo.registry.support.FailbackRegistry);
    Code:
       0: aload_0
       1: aload_1
       2: aload_2
       3: ldc           #2                  // String retry register
       5: invokespecial #3                  // Method org/apache/dubbo/registry/retry/AbstractRetryTask."<init>":(Lorg/apache/dubbo/common/URL;Lorg/apache/dubbo/registry/support/FailbackRegistry;Ljava/lang/String;)V
       8: return

  protected void doRetry(org.apache.dubbo.common.URL, org.apache.dubbo.registry.support.FailbackRegistry, org.apache.dubbo.common.timer.Timeout);
    Code:
       0: aload_2
       1: aload_1
       2: invokevirtual #4                  // Method org/apache/dubbo/registry/support/FailbackRegistry.doRegister:(Lorg/apache/dubbo/common/URL;)V
       5: aload_2
       6: aload_1
       7: invokevirtual #5                  // Method org/apache/dubbo/registry/support/FailbackRegistry.removeFailedRegisteredTask:(Lorg/apache/dubbo/common/URL;)V
      10: return
}
