Compiled from "ReExportTask.java"
public class org.apache.dubbo.registry.retry.ReExportTask extends org.apache.dubbo.registry.retry.AbstractRetryTask {
  private static final java.lang.String NAME;

  private java.lang.Runnable runnable;

  public org.apache.dubbo.registry.retry.ReExportTask(java.lang.Runnable, org.apache.dubbo.common.URL, org.apache.dubbo.registry.support.FailbackRegistry);
    Code:
       0: aload_0
       1: aload_2
       2: aload_3
       3: ldc           #2                  // String retry re-export
       5: invokespecial #3                  // Method org/apache/dubbo/registry/retry/AbstractRetryTask."<init>":(Lorg/apache/dubbo/common/URL;Lorg/apache/dubbo/registry/support/FailbackRegistry;Ljava/lang/String;)V
       8: aload_0
       9: aload_1
      10: putfield      #4                  // Field runnable:Ljava/lang/Runnable;
      13: return

  protected void doRetry(org.apache.dubbo.common.URL, org.apache.dubbo.registry.support.FailbackRegistry, org.apache.dubbo.common.timer.Timeout);
    Code:
       0: aload_0
       1: getfield      #4                  // Field runnable:Ljava/lang/Runnable;
       4: invokeinterface #5,  1            // InterfaceMethod java/lang/Runnable.run:()V
       9: return
}
