Compiled from "ASCIIEncoder.java"
final class com.google.zxing.datamatrix.encoder.ASCIIEncoder implements com.google.zxing.datamatrix.encoder.Encoder {
  com.google.zxing.datamatrix.encoder.ASCIIEncoder();
    Code:
       0: aload_0
       1: invokespecial #1                  // Method java/lang/Object."<init>":()V
       4: return

  public int getEncodingMode();
    Code:
       0: iconst_0
       1: ireturn

  public void encode(com.google.zxing.datamatrix.encoder.EncoderContext);
    Code:
       0: aload_1
       1: invokevirtual #3                  // Method com/google/zxing/datamatrix/encoder/EncoderContext.getMessage:()Ljava/lang/String;
       4: aload_1
       5: getfield      #4                  // Field com/google/zxing/datamatrix/encoder/EncoderContext.pos:I
       8: invokestatic  #5                  // Method com/google/zxing/datamatrix/encoder/HighLevelEncoder.determineConsecutiveDigitCount:(Ljava/lang/CharSequence;I)I
      11: istore_2
      12: iload_2
      13: iconst_2
      14: if_icmplt     61
      17: aload_1
      18: aload_1
      19: invokevirtual #3                  // Method com/google/zxing/datamatrix/encoder/EncoderContext.getMessage:()Ljava/lang/String;
      22: aload_1
      23: getfield      #4                  // Field com/google/zxing/datamatrix/encoder/EncoderContext.pos:I
      26: invokevirtual #6                  // Method java/lang/String.charAt:(I)C
      29: aload_1
      30: invokevirtual #3                  // Method com/google/zxing/datamatrix/encoder/EncoderContext.getMessage:()Ljava/lang/String;
      33: aload_1
      34: getfield      #4                  // Field com/google/zxing/datamatrix/encoder/EncoderContext.pos:I
      37: iconst_1
      38: iadd
      39: invokevirtual #6                  // Method java/lang/String.charAt:(I)C
      42: invokestatic  #7                  // Method encodeASCIIDigits:(CC)C
      45: invokevirtual #8                  // Method com/google/zxing/datamatrix/encoder/EncoderContext.writeCodeword:(C)V
      48: aload_1
      49: dup
      50: getfield      #4                  // Field com/google/zxing/datamatrix/encoder/EncoderContext.pos:I
      53: iconst_2
      54: iadd
      55: putfield      #4                  // Field com/google/zxing/datamatrix/encoder/EncoderContext.pos:I
      58: goto          284
      61: aload_1
      62: invokevirtual #9                  // Method com/google/zxing/datamatrix/encoder/EncoderContext.getCurrentChar:()C
      65: istore_3
      66: aload_1
      67: invokevirtual #3                  // Method com/google/zxing/datamatrix/encoder/EncoderContext.getMessage:()Ljava/lang/String;
      70: aload_1
      71: getfield      #4                  // Field com/google/zxing/datamatrix/encoder/EncoderContext.pos:I
      74: aload_0
      75: invokevirtual #10                 // Method getEncodingMode:()I
      78: invokestatic  #11                 // Method com/google/zxing/datamatrix/encoder/HighLevelEncoder.lookAheadTest:(Ljava/lang/CharSequence;II)I
      81: istore        4
      83: iload         4
      85: aload_0
      86: invokevirtual #10                 // Method getEncodingMode:()I
      89: if_icmpeq     227
      92: iload         4
      94: tableswitch   { // 1 to 5
                     1: 141
                     2: 169
                     3: 154
                     4: 184
                     5: 128
               default: 199
          }
     128: aload_1
     129: sipush        231
     132: invokevirtual #8                  // Method com/google/zxing/datamatrix/encoder/EncoderContext.writeCodeword:(C)V
     135: aload_1
     136: iconst_5
     137: invokevirtual #12                 // Method com/google/zxing/datamatrix/encoder/EncoderContext.signalEncoderChange:(I)V
     140: return
     141: aload_1
     142: sipush        230
     145: invokevirtual #8                  // Method com/google/zxing/datamatrix/encoder/EncoderContext.writeCodeword:(C)V
     148: aload_1
     149: iconst_1
     150: invokevirtual #12                 // Method com/google/zxing/datamatrix/encoder/EncoderContext.signalEncoderChange:(I)V
     153: return
     154: aload_1
     155: sipush        238
     158: invokevirtual #8                  // Method com/google/zxing/datamatrix/encoder/EncoderContext.writeCodeword:(C)V
     161: aload_1
     162: iconst_3
     163: invokevirtual #12                 // Method com/google/zxing/datamatrix/encoder/EncoderContext.signalEncoderChange:(I)V
     166: goto          284
     169: aload_1
     170: sipush        239
     173: invokevirtual #8                  // Method com/google/zxing/datamatrix/encoder/EncoderContext.writeCodeword:(C)V
     176: aload_1
     177: iconst_2
     178: invokevirtual #12                 // Method com/google/zxing/datamatrix/encoder/EncoderContext.signalEncoderChange:(I)V
     181: goto          284
     184: aload_1
     185: sipush        240
     188: invokevirtual #8                  // Method com/google/zxing/datamatrix/encoder/EncoderContext.writeCodeword:(C)V
     191: aload_1
     192: iconst_4
     193: invokevirtual #12                 // Method com/google/zxing/datamatrix/encoder/EncoderContext.signalEncoderChange:(I)V
     196: goto          284
     199: new           #13                 // class java/lang/IllegalStateException
     202: dup
     203: new           #14                 // class java/lang/StringBuilder
     206: dup
     207: invokespecial #15                 // Method java/lang/StringBuilder."<init>":()V
     210: ldc           #16                 // String Illegal mode:
     212: invokevirtual #17                 // Method java/lang/StringBuilder.append:(Ljava/lang/String;)Ljava/lang/StringBuilder;
     215: iload         4
     217: invokevirtual #18                 // Method java/lang/StringBuilder.append:(I)Ljava/lang/StringBuilder;
     220: invokevirtual #19                 // Method java/lang/StringBuilder.toString:()Ljava/lang/String;
     223: invokespecial #20                 // Method java/lang/IllegalStateException."<init>":(Ljava/lang/String;)V
     226: athrow
     227: iload_3
     228: invokestatic  #21                 // Method com/google/zxing/datamatrix/encoder/HighLevelEncoder.isExtendedASCII:(C)Z
     231: ifeq          266
     234: aload_1
     235: sipush        235
     238: invokevirtual #8                  // Method com/google/zxing/datamatrix/encoder/EncoderContext.writeCodeword:(C)V
     241: aload_1
     242: iload_3
     243: sipush        128
     246: isub
     247: iconst_1
     248: iadd
     249: i2c
     250: invokevirtual #8                  // Method com/google/zxing/datamatrix/encoder/EncoderContext.writeCodeword:(C)V
     253: aload_1
     254: dup
     255: getfield      #4                  // Field com/google/zxing/datamatrix/encoder/EncoderContext.pos:I
     258: iconst_1
     259: iadd
     260: putfield      #4                  // Field com/google/zxing/datamatrix/encoder/EncoderContext.pos:I
     263: goto          284
     266: aload_1
     267: iload_3
     268: iconst_1
     269: iadd
     270: i2c
     271: invokevirtual #8                  // Method com/google/zxing/datamatrix/encoder/EncoderContext.writeCodeword:(C)V
     274: aload_1
     275: dup
     276: getfield      #4                  // Field com/google/zxing/datamatrix/encoder/EncoderContext.pos:I
     279: iconst_1
     280: iadd
     281: putfield      #4                  // Field com/google/zxing/datamatrix/encoder/EncoderContext.pos:I
     284: return

  private static char encodeASCIIDigits(char, char);
    Code:
       0: iload_0
       1: invokestatic  #22                 // Method com/google/zxing/datamatrix/encoder/HighLevelEncoder.isDigit:(C)Z
       4: ifeq          34
       7: iload_1
       8: invokestatic  #22                 // Method com/google/zxing/datamatrix/encoder/HighLevelEncoder.isDigit:(C)Z
      11: ifeq          34
      14: iload_0
      15: bipush        48
      17: isub
      18: bipush        10
      20: imul
      21: iload_1
      22: bipush        48
      24: isub
      25: iadd
      26: istore_2
      27: iload_2
      28: sipush        130
      31: iadd
      32: i2c
      33: ireturn
      34: new           #23                 // class java/lang/IllegalArgumentException
      37: dup
      38: new           #14                 // class java/lang/StringBuilder
      41: dup
      42: invokespecial #15                 // Method java/lang/StringBuilder."<init>":()V
      45: ldc           #24                 // String not digits:
      47: invokevirtual #17                 // Method java/lang/StringBuilder.append:(Ljava/lang/String;)Ljava/lang/StringBuilder;
      50: iload_0
      51: invokevirtual #25                 // Method java/lang/StringBuilder.append:(C)Ljava/lang/StringBuilder;
      54: iload_1
      55: invokevirtual #25                 // Method java/lang/StringBuilder.append:(C)Ljava/lang/StringBuilder;
      58: invokevirtual #19                 // Method java/lang/StringBuilder.toString:()Ljava/lang/String;
      61: invokespecial #26                 // Method java/lang/IllegalArgumentException."<init>":(Ljava/lang/String;)V
      64: athrow
}
