Compiled from "DataMatrixSymbolInfo144.java"
final class com.google.zxing.datamatrix.encoder.DataMatrixSymbolInfo144 extends com.google.zxing.datamatrix.encoder.SymbolInfo {
  com.google.zxing.datamatrix.encoder.DataMatrixSymbolInfo144();
    Code:
       0: aload_0
       1: iconst_0
       2: sipush        1558
       5: sipush        620
       8: bipush        22
      10: bipush        22
      12: bipush        36
      14: iconst_m1
      15: bipush        62
      17: invokespecial #1                  // Method com/google/zxing/datamatrix/encoder/SymbolInfo."<init>":(ZIIIIIII)V
      20: return

  public int getInterleavedBlockCount();
    Code:
       0: bipush        10
       2: ireturn

  public int getDataLengthForInterleavedBlock(int);
    Code:
       0: iload_1
       1: bipush        8
       3: if_icmpgt     12
       6: sipush        156
       9: goto          15
      12: sipush        155
      15: ireturn
}
