Compiled from "EncoderContext.java"
final class com.google.zxing.datamatrix.encoder.EncoderContext {
  private final java.lang.String msg;

  private com.google.zxing.datamatrix.encoder.SymbolShapeHint shape;

  private com.google.zxing.Dimension minSize;

  private com.google.zxing.Dimension maxSize;

  private final java.lang.StringBuilder codewords;

  int pos;

  private int newEncoding;

  private com.google.zxing.datamatrix.encoder.SymbolInfo symbolInfo;

  private int skipAtEnd;

  com.google.zxing.datamatrix.encoder.EncoderContext(java.lang.String);
    Code:
       0: aload_0
       1: invokespecial #1                  // Method java/lang/Object."<init>":()V
       4: aload_1
       5: getstatic     #2                  // Field java/nio/charset/StandardCharsets.ISO_8859_1:Ljava/nio/charset/Charset;
       8: invokevirtual #3                  // Method java/lang/String.getBytes:(Ljava/nio/charset/Charset;)[B
      11: astore_2
      12: new           #4                  // class java/lang/StringBuilder
      15: dup
      16: aload_2
      17: arraylength
      18: invokespecial #5                  // Method java/lang/StringBuilder."<init>":(I)V
      21: astore_3
      22: iconst_0
      23: istore        4
      25: aload_2
      26: arraylength
      27: istore        5
      29: iload         4
      31: iload         5
      33: if_icmpge     88
      36: aload_2
      37: iload         4
      39: baload
      40: sipush        255
      43: iand
      44: i2c
      45: istore        6
      47: iload         6
      49: bipush        63
      51: if_icmpne     75
      54: aload_1
      55: iload         4
      57: invokevirtual #6                  // Method java/lang/String.charAt:(I)C
      60: bipush        63
      62: if_icmpeq     75
      65: new           #7                  // class java/lang/IllegalArgumentException
      68: dup
      69: ldc           #8                  // String Message contains characters outside ISO-8859-1 encoding.
      71: invokespecial #9                  // Method java/lang/IllegalArgumentException."<init>":(Ljava/lang/String;)V
      74: athrow
      75: aload_3
      76: iload         6
      78: invokevirtual #10                 // Method java/lang/StringBuilder.append:(C)Ljava/lang/StringBuilder;
      81: pop
      82: iinc          4, 1
      85: goto          29
      88: aload_0
      89: aload_3
      90: invokevirtual #11                 // Method java/lang/StringBuilder.toString:()Ljava/lang/String;
      93: putfield      #12                 // Field msg:Ljava/lang/String;
      96: aload_0
      97: getstatic     #13                 // Field com/google/zxing/datamatrix/encoder/SymbolShapeHint.FORCE_NONE:Lcom/google/zxing/datamatrix/encoder/SymbolShapeHint;
     100: putfield      #14                 // Field shape:Lcom/google/zxing/datamatrix/encoder/SymbolShapeHint;
     103: aload_0
     104: new           #4                  // class java/lang/StringBuilder
     107: dup
     108: aload_1
     109: invokevirtual #15                 // Method java/lang/String.length:()I
     112: invokespecial #5                  // Method java/lang/StringBuilder."<init>":(I)V
     115: putfield      #16                 // Field codewords:Ljava/lang/StringBuilder;
     118: aload_0
     119: iconst_m1
     120: putfield      #17                 // Field newEncoding:I
     123: return

  public void setSymbolShape(com.google.zxing.datamatrix.encoder.SymbolShapeHint);
    Code:
       0: aload_0
       1: aload_1
       2: putfield      #14                 // Field shape:Lcom/google/zxing/datamatrix/encoder/SymbolShapeHint;
       5: return

  public void setSizeConstraints(com.google.zxing.Dimension, com.google.zxing.Dimension);
    Code:
       0: aload_0
       1: aload_1
       2: putfield      #18                 // Field minSize:Lcom/google/zxing/Dimension;
       5: aload_0
       6: aload_2
       7: putfield      #19                 // Field maxSize:Lcom/google/zxing/Dimension;
      10: return

  public java.lang.String getMessage();
    Code:
       0: aload_0
       1: getfield      #12                 // Field msg:Ljava/lang/String;
       4: areturn

  public void setSkipAtEnd(int);
    Code:
       0: aload_0
       1: iload_1
       2: putfield      #20                 // Field skipAtEnd:I
       5: return

  public char getCurrentChar();
    Code:
       0: aload_0
       1: getfield      #12                 // Field msg:Ljava/lang/String;
       4: aload_0
       5: getfield      #21                 // Field pos:I
       8: invokevirtual #6                  // Method java/lang/String.charAt:(I)C
      11: ireturn

  public char getCurrent();
    Code:
       0: aload_0
       1: getfield      #12                 // Field msg:Ljava/lang/String;
       4: aload_0
       5: getfield      #21                 // Field pos:I
       8: invokevirtual #6                  // Method java/lang/String.charAt:(I)C
      11: ireturn

  public java.lang.StringBuilder getCodewords();
    Code:
       0: aload_0
       1: getfield      #16                 // Field codewords:Ljava/lang/StringBuilder;
       4: areturn

  public void writeCodewords(java.lang.String);
    Code:
       0: aload_0
       1: getfield      #16                 // Field codewords:Ljava/lang/StringBuilder;
       4: aload_1
       5: invokevirtual #22                 // Method java/lang/StringBuilder.append:(Ljava/lang/String;)Ljava/lang/StringBuilder;
       8: pop
       9: return

  public void writeCodeword(char);
    Code:
       0: aload_0
       1: getfield      #16                 // Field codewords:Ljava/lang/StringBuilder;
       4: iload_1
       5: invokevirtual #10                 // Method java/lang/StringBuilder.append:(C)Ljava/lang/StringBuilder;
       8: pop
       9: return

  public int getCodewordCount();
    Code:
       0: aload_0
       1: getfield      #16                 // Field codewords:Ljava/lang/StringBuilder;
       4: invokevirtual #23                 // Method java/lang/StringBuilder.length:()I
       7: ireturn

  public int getNewEncoding();
    Code:
       0: aload_0
       1: getfield      #17                 // Field newEncoding:I
       4: ireturn

  public void signalEncoderChange(int);
    Code:
       0: aload_0
       1: iload_1
       2: putfield      #17                 // Field newEncoding:I
       5: return

  public void resetEncoderSignal();
    Code:
       0: aload_0
       1: iconst_m1
       2: putfield      #17                 // Field newEncoding:I
       5: return

  public boolean hasMoreCharacters();
    Code:
       0: aload_0
       1: getfield      #21                 // Field pos:I
       4: aload_0
       5: invokespecial #24                 // Method getTotalMessageCharCount:()I
       8: if_icmpge     15
      11: iconst_1
      12: goto          16
      15: iconst_0
      16: ireturn

  private int getTotalMessageCharCount();
    Code:
       0: aload_0
       1: getfield      #12                 // Field msg:Ljava/lang/String;
       4: invokevirtual #15                 // Method java/lang/String.length:()I
       7: aload_0
       8: getfield      #20                 // Field skipAtEnd:I
      11: isub
      12: ireturn

  public int getRemainingCharacters();
    Code:
       0: aload_0
       1: invokespecial #24                 // Method getTotalMessageCharCount:()I
       4: aload_0
       5: getfield      #21                 // Field pos:I
       8: isub
       9: ireturn

  public com.google.zxing.datamatrix.encoder.SymbolInfo getSymbolInfo();
    Code:
       0: aload_0
       1: getfield      #25                 // Field symbolInfo:Lcom/google/zxing/datamatrix/encoder/SymbolInfo;
       4: areturn

  public void updateSymbolInfo();
    Code:
       0: aload_0
       1: aload_0
       2: invokevirtual #26                 // Method getCodewordCount:()I
       5: invokevirtual #27                 // Method updateSymbolInfo:(I)V
       8: return

  public void updateSymbolInfo(int);
    Code:
       0: aload_0
       1: getfield      #25                 // Field symbolInfo:Lcom/google/zxing/datamatrix/encoder/SymbolInfo;
       4: ifnull        18
       7: iload_1
       8: aload_0
       9: getfield      #25                 // Field symbolInfo:Lcom/google/zxing/datamatrix/encoder/SymbolInfo;
      12: invokevirtual #28                 // Method com/google/zxing/datamatrix/encoder/SymbolInfo.getDataCapacity:()I
      15: if_icmple     39
      18: aload_0
      19: iload_1
      20: aload_0
      21: getfield      #14                 // Field shape:Lcom/google/zxing/datamatrix/encoder/SymbolShapeHint;
      24: aload_0
      25: getfield      #18                 // Field minSize:Lcom/google/zxing/Dimension;
      28: aload_0
      29: getfield      #19                 // Field maxSize:Lcom/google/zxing/Dimension;
      32: iconst_1
      33: invokestatic  #29                 // Method com/google/zxing/datamatrix/encoder/SymbolInfo.lookup:(ILcom/google/zxing/datamatrix/encoder/SymbolShapeHint;Lcom/google/zxing/Dimension;Lcom/google/zxing/Dimension;Z)Lcom/google/zxing/datamatrix/encoder/SymbolInfo;
      36: putfield      #25                 // Field symbolInfo:Lcom/google/zxing/datamatrix/encoder/SymbolInfo;
      39: return

  public void resetSymbolInfo();
    Code:
       0: aload_0
       1: aconst_null
       2: putfield      #25                 // Field symbolInfo:Lcom/google/zxing/datamatrix/encoder/SymbolInfo;
       5: return
}
