Compiled from "HighLevelEncoder.java"
public final class com.google.zxing.datamatrix.encoder.HighLevelEncoder {
  private static final char PAD;

  static final char LATCH_TO_C40;

  static final char LATCH_TO_BASE256;

  static final char UPPER_SHIFT;

  private static final char MACRO_05;

  private static final char MACRO_06;

  static final char LATCH_TO_ANSIX12;

  static final char LATCH_TO_TEXT;

  static final char LATCH_TO_EDIFACT;

  static final char C40_UNLATCH;

  static final char X12_UNLATCH;

  static final java.lang.String MACRO_05_HEADER;

  static final java.lang.String MACRO_06_HEADER;

  static final java.lang.String MACRO_TRAILER;

  static final int ASCII_ENCODATION;

  static final int C40_ENCODATION;

  static final int TEXT_ENCODATION;

  static final int X12_ENCODATION;

  static final int EDIFACT_ENCODATION;

  static final int BASE256_ENCODATION;

  private com.google.zxing.datamatrix.encoder.HighLevelEncoder();
    Code:
       0: aload_0
       1: invokespecial #1                  // Method java/lang/Object."<init>":()V
       4: return

  private static char randomize253State(int);
    Code:
       0: sipush        149
       3: iload_0
       4: imul
       5: sipush        253
       8: irem
       9: iconst_1
      10: iadd
      11: istore_1
      12: sipush        129
      15: iload_1
      16: iadd
      17: istore_2
      18: iload_2
      19: sipush        254
      22: if_icmpgt     29
      25: iload_2
      26: goto          34
      29: iload_2
      30: sipush        254
      33: isub
      34: i2c
      35: ireturn

  public static java.lang.String encodeHighLevel(java.lang.String);
    Code:
       0: aload_0
       1: getstatic     #3                  // Field com/google/zxing/datamatrix/encoder/SymbolShapeHint.FORCE_NONE:Lcom/google/zxing/datamatrix/encoder/SymbolShapeHint;
       4: aconst_null
       5: aconst_null
       6: iconst_0
       7: invokestatic  #4                  // Method encodeHighLevel:(Ljava/lang/String;Lcom/google/zxing/datamatrix/encoder/SymbolShapeHint;Lcom/google/zxing/Dimension;Lcom/google/zxing/Dimension;Z)Ljava/lang/String;
      10: areturn

  public static java.lang.String encodeHighLevel(java.lang.String, com.google.zxing.datamatrix.encoder.SymbolShapeHint, com.google.zxing.Dimension, com.google.zxing.Dimension);
    Code:
       0: aload_0
       1: aload_1
       2: aload_2
       3: aload_3
       4: iconst_0
       5: invokestatic  #4                  // Method encodeHighLevel:(Ljava/lang/String;Lcom/google/zxing/datamatrix/encoder/SymbolShapeHint;Lcom/google/zxing/Dimension;Lcom/google/zxing/Dimension;Z)Ljava/lang/String;
       8: areturn

  public static java.lang.String encodeHighLevel(java.lang.String, com.google.zxing.datamatrix.encoder.SymbolShapeHint, com.google.zxing.Dimension, com.google.zxing.Dimension, boolean);
    Code:
       0: new           #5                  // class com/google/zxing/datamatrix/encoder/C40Encoder
       3: dup
       4: invokespecial #6                  // Method com/google/zxing/datamatrix/encoder/C40Encoder."<init>":()V
       7: astore        5
       9: bipush        6
      11: anewarray     #7                  // class com/google/zxing/datamatrix/encoder/Encoder
      14: dup
      15: iconst_0
      16: new           #8                  // class com/google/zxing/datamatrix/encoder/ASCIIEncoder
      19: dup
      20: invokespecial #9                  // Method com/google/zxing/datamatrix/encoder/ASCIIEncoder."<init>":()V
      23: aastore
      24: dup
      25: iconst_1
      26: aload         5
      28: aastore
      29: dup
      30: iconst_2
      31: new           #10                 // class com/google/zxing/datamatrix/encoder/TextEncoder
      34: dup
      35: invokespecial #11                 // Method com/google/zxing/datamatrix/encoder/TextEncoder."<init>":()V
      38: aastore
      39: dup
      40: iconst_3
      41: new           #12                 // class com/google/zxing/datamatrix/encoder/X12Encoder
      44: dup
      45: invokespecial #13                 // Method com/google/zxing/datamatrix/encoder/X12Encoder."<init>":()V
      48: aastore
      49: dup
      50: iconst_4
      51: new           #14                 // class com/google/zxing/datamatrix/encoder/EdifactEncoder
      54: dup
      55: invokespecial #15                 // Method com/google/zxing/datamatrix/encoder/EdifactEncoder."<init>":()V
      58: aastore
      59: dup
      60: iconst_5
      61: new           #16                 // class com/google/zxing/datamatrix/encoder/Base256Encoder
      64: dup
      65: invokespecial #17                 // Method com/google/zxing/datamatrix/encoder/Base256Encoder."<init>":()V
      68: aastore
      69: astore        6
      71: new           #18                 // class com/google/zxing/datamatrix/encoder/EncoderContext
      74: dup
      75: aload_0
      76: invokespecial #19                 // Method com/google/zxing/datamatrix/encoder/EncoderContext."<init>":(Ljava/lang/String;)V
      79: astore        7
      81: aload         7
      83: aload_1
      84: invokevirtual #20                 // Method com/google/zxing/datamatrix/encoder/EncoderContext.setSymbolShape:(Lcom/google/zxing/datamatrix/encoder/SymbolShapeHint;)V
      87: aload         7
      89: aload_2
      90: aload_3
      91: invokevirtual #21                 // Method com/google/zxing/datamatrix/encoder/EncoderContext.setSizeConstraints:(Lcom/google/zxing/Dimension;Lcom/google/zxing/Dimension;)V
      94: aload_0
      95: ldc           #22                 // String [)>\u001e05\u001d
      97: invokevirtual #23                 // Method java/lang/String.startsWith:(Ljava/lang/String;)Z
     100: ifeq          144
     103: aload_0
     104: ldc           #24                 // String \u001e\u0004
     106: invokevirtual #25                 // Method java/lang/String.endsWith:(Ljava/lang/String;)Z
     109: ifeq          144
     112: aload         7
     114: sipush        236
     117: invokevirtual #26                 // Method com/google/zxing/datamatrix/encoder/EncoderContext.writeCodeword:(C)V
     120: aload         7
     122: iconst_2
     123: invokevirtual #27                 // Method com/google/zxing/datamatrix/encoder/EncoderContext.setSkipAtEnd:(I)V
     126: aload         7
     128: dup
     129: getfield      #28                 // Field com/google/zxing/datamatrix/encoder/EncoderContext.pos:I
     132: ldc           #22                 // String [)>\u001e05\u001d
     134: invokevirtual #29                 // Method java/lang/String.length:()I
     137: iadd
     138: putfield      #28                 // Field com/google/zxing/datamatrix/encoder/EncoderContext.pos:I
     141: goto          191
     144: aload_0
     145: ldc           #30                 // String [)>\u001e06\u001d
     147: invokevirtual #23                 // Method java/lang/String.startsWith:(Ljava/lang/String;)Z
     150: ifeq          191
     153: aload_0
     154: ldc           #24                 // String \u001e\u0004
     156: invokevirtual #25                 // Method java/lang/String.endsWith:(Ljava/lang/String;)Z
     159: ifeq          191
     162: aload         7
     164: sipush        237
     167: invokevirtual #26                 // Method com/google/zxing/datamatrix/encoder/EncoderContext.writeCodeword:(C)V
     170: aload         7
     172: iconst_2
     173: invokevirtual #27                 // Method com/google/zxing/datamatrix/encoder/EncoderContext.setSkipAtEnd:(I)V
     176: aload         7
     178: dup
     179: getfield      #28                 // Field com/google/zxing/datamatrix/encoder/EncoderContext.pos:I
     182: ldc           #30                 // String [)>\u001e06\u001d
     184: invokevirtual #29                 // Method java/lang/String.length:()I
     187: iadd
     188: putfield      #28                 // Field com/google/zxing/datamatrix/encoder/EncoderContext.pos:I
     191: iconst_0
     192: istore        8
     194: iload         4
     196: ifeq          218
     199: aload         5
     201: aload         7
     203: invokevirtual #31                 // Method com/google/zxing/datamatrix/encoder/C40Encoder.encodeMaximal:(Lcom/google/zxing/datamatrix/encoder/EncoderContext;)V
     206: aload         7
     208: invokevirtual #32                 // Method com/google/zxing/datamatrix/encoder/EncoderContext.getNewEncoding:()I
     211: istore        8
     213: aload         7
     215: invokevirtual #33                 // Method com/google/zxing/datamatrix/encoder/EncoderContext.resetEncoderSignal:()V
     218: aload         7
     220: invokevirtual #34                 // Method com/google/zxing/datamatrix/encoder/EncoderContext.hasMoreCharacters:()Z
     223: ifeq          261
     226: aload         6
     228: iload         8
     230: aaload
     231: aload         7
     233: invokeinterface #35,  2           // InterfaceMethod com/google/zxing/datamatrix/encoder/Encoder.encode:(Lcom/google/zxing/datamatrix/encoder/EncoderContext;)V
     238: aload         7
     240: invokevirtual #32                 // Method com/google/zxing/datamatrix/encoder/EncoderContext.getNewEncoding:()I
     243: iflt          218
     246: aload         7
     248: invokevirtual #32                 // Method com/google/zxing/datamatrix/encoder/EncoderContext.getNewEncoding:()I
     251: istore        8
     253: aload         7
     255: invokevirtual #33                 // Method com/google/zxing/datamatrix/encoder/EncoderContext.resetEncoderSignal:()V
     258: goto          218
     261: aload         7
     263: invokevirtual #36                 // Method com/google/zxing/datamatrix/encoder/EncoderContext.getCodewordCount:()I
     266: istore        9
     268: aload         7
     270: invokevirtual #37                 // Method com/google/zxing/datamatrix/encoder/EncoderContext.updateSymbolInfo:()V
     273: aload         7
     275: invokevirtual #38                 // Method com/google/zxing/datamatrix/encoder/EncoderContext.getSymbolInfo:()Lcom/google/zxing/datamatrix/encoder/SymbolInfo;
     278: invokevirtual #39                 // Method com/google/zxing/datamatrix/encoder/SymbolInfo.getDataCapacity:()I
     281: istore        10
     283: iload         9
     285: iload         10
     287: if_icmpge     315
     290: iload         8
     292: ifeq          315
     295: iload         8
     297: iconst_5
     298: if_icmpeq     315
     301: iload         8
     303: iconst_4
     304: if_icmpeq     315
     307: aload         7
     309: sipush        254
     312: invokevirtual #26                 // Method com/google/zxing/datamatrix/encoder/EncoderContext.writeCodeword:(C)V
     315: aload         7
     317: invokevirtual #40                 // Method com/google/zxing/datamatrix/encoder/EncoderContext.getCodewords:()Ljava/lang/StringBuilder;
     320: astore        11
     322: aload         11
     324: invokevirtual #41                 // Method java/lang/StringBuilder.length:()I
     327: iload         10
     329: if_icmpge     341
     332: aload         11
     334: sipush        129
     337: invokevirtual #42                 // Method java/lang/StringBuilder.append:(C)Ljava/lang/StringBuilder;
     340: pop
     341: aload         11
     343: invokevirtual #41                 // Method java/lang/StringBuilder.length:()I
     346: iload         10
     348: if_icmpge     370
     351: aload         11
     353: aload         11
     355: invokevirtual #41                 // Method java/lang/StringBuilder.length:()I
     358: iconst_1
     359: iadd
     360: invokestatic  #43                 // Method randomize253State:(I)C
     363: invokevirtual #42                 // Method java/lang/StringBuilder.append:(C)Ljava/lang/StringBuilder;
     366: pop
     367: goto          341
     370: aload         7
     372: invokevirtual #40                 // Method com/google/zxing/datamatrix/encoder/EncoderContext.getCodewords:()Ljava/lang/StringBuilder;
     375: invokevirtual #44                 // Method java/lang/StringBuilder.toString:()Ljava/lang/String;
     378: areturn

  static int lookAheadTest(java.lang.CharSequence, int, int);
    Code:
       0: aload_0
       1: iload_1
       2: iload_2
       3: invokestatic  #45                 // Method lookAheadTestIntern:(Ljava/lang/CharSequence;II)I
       6: istore_3
       7: iload_2
       8: iconst_3
       9: if_icmpne     66
      12: iload_3
      13: iconst_3
      14: if_icmpne     66
      17: iload_1
      18: iconst_3
      19: iadd
      20: aload_0
      21: invokeinterface #46,  1           // InterfaceMethod java/lang/CharSequence.length:()I
      26: invokestatic  #47                 // Method java/lang/Math.min:(II)I
      29: istore        4
      31: iload_1
      32: istore        5
      34: iload         5
      36: iload         4
      38: if_icmpge     63
      41: aload_0
      42: iload         5
      44: invokeinterface #48,  2           // InterfaceMethod java/lang/CharSequence.charAt:(I)C
      49: invokestatic  #49                 // Method isNativeX12:(C)Z
      52: ifne          57
      55: iconst_0
      56: ireturn
      57: iinc          5, 1
      60: goto          34
      63: goto          122
      66: iload_2
      67: iconst_4
      68: if_icmpne     122
      71: iload_3
      72: iconst_4
      73: if_icmpne     122
      76: iload_1
      77: iconst_4
      78: iadd
      79: aload_0
      80: invokeinterface #46,  1           // InterfaceMethod java/lang/CharSequence.length:()I
      85: invokestatic  #47                 // Method java/lang/Math.min:(II)I
      88: istore        4
      90: iload_1
      91: istore        5
      93: iload         5
      95: iload         4
      97: if_icmpge     122
     100: aload_0
     101: iload         5
     103: invokeinterface #48,  2           // InterfaceMethod java/lang/CharSequence.charAt:(I)C
     108: invokestatic  #50                 // Method isNativeEDIFACT:(C)Z
     111: ifne          116
     114: iconst_0
     115: ireturn
     116: iinc          5, 1
     119: goto          93
     122: iload_3
     123: ireturn

  static int lookAheadTestIntern(java.lang.CharSequence, int, int);
    Code:
       0: iload_1
       1: aload_0
       2: invokeinterface #46,  1           // InterfaceMethod java/lang/CharSequence.length:()I
       7: if_icmplt     12
      10: iload_2
      11: ireturn
      12: iload_2
      13: ifne          49
      16: bipush        6
      18: newarray       float
      20: dup
      21: iconst_0
      22: fconst_0
      23: fastore
      24: dup
      25: iconst_1
      26: fconst_1
      27: fastore
      28: dup
      29: iconst_2
      30: fconst_1
      31: fastore
      32: dup
      33: iconst_3
      34: fconst_1
      35: fastore
      36: dup
      37: iconst_4
      38: fconst_1
      39: fastore
      40: dup
      41: iconst_5
      42: ldc           #51                 // float 1.25f
      44: fastore
      45: astore_3
      46: goto          83
      49: bipush        6
      51: newarray       float
      53: dup
      54: iconst_0
      55: fconst_1
      56: fastore
      57: dup
      58: iconst_1
      59: fconst_2
      60: fastore
      61: dup
      62: iconst_2
      63: fconst_2
      64: fastore
      65: dup
      66: iconst_3
      67: fconst_2
      68: fastore
      69: dup
      70: iconst_4
      71: fconst_2
      72: fastore
      73: dup
      74: iconst_5
      75: ldc           #52                 // float 2.25f
      77: fastore
      78: astore_3
      79: aload_3
      80: iload_2
      81: fconst_0
      82: fastore
      83: iconst_0
      84: istore        4
      86: bipush        6
      88: newarray       byte
      90: astore        5
      92: bipush        6
      94: newarray       int
      96: astore        6
      98: iload_1
      99: iload         4
     101: iadd
     102: aload_0
     103: invokeinterface #46,  1           // InterfaceMethod java/lang/CharSequence.length:()I
     108: if_icmpne     197
     111: aload         5
     113: iconst_0
     114: invokestatic  #53                 // Method java/util/Arrays.fill:([BB)V
     117: aload         6
     119: iconst_0
     120: invokestatic  #54                 // Method java/util/Arrays.fill:([II)V
     123: aload_3
     124: aload         6
     126: ldc           #56                 // int 2147483647
     128: aload         5
     130: invokestatic  #57                 // Method findMinimums:([F[II[B)I
     133: istore        7
     135: aload         5
     137: invokestatic  #58                 // Method getMinimumCount:([B)I
     140: istore        8
     142: aload         6
     144: iconst_0
     145: iaload
     146: iload         7
     148: if_icmpne     153
     151: iconst_0
     152: ireturn
     153: iload         8
     155: iconst_1
     156: if_icmpne     195
     159: aload         5
     161: iconst_5
     162: baload
     163: ifle          168
     166: iconst_5
     167: ireturn
     168: aload         5
     170: iconst_4
     171: baload
     172: ifle          177
     175: iconst_4
     176: ireturn
     177: aload         5
     179: iconst_2
     180: baload
     181: ifle          186
     184: iconst_2
     185: ireturn
     186: aload         5
     188: iconst_3
     189: baload
     190: ifle          195
     193: iconst_3
     194: ireturn
     195: iconst_1
     196: ireturn
     197: aload_0
     198: iload_1
     199: iload         4
     201: iadd
     202: invokeinterface #48,  2           // InterfaceMethod java/lang/CharSequence.charAt:(I)C
     207: istore        7
     209: iinc          4, 1
     212: iload         7
     214: invokestatic  #59                 // Method isDigit:(C)Z
     217: ifeq          231
     220: aload_3
     221: iconst_0
     222: dup2
     223: faload
     224: ldc           #60                 // float 0.5f
     226: fadd
     227: fastore
     228: goto          278
     231: iload         7
     233: invokestatic  #61                 // Method isExtendedASCII:(C)Z
     236: ifeq          260
     239: aload_3
     240: iconst_0
     241: aload_3
     242: iconst_0
     243: faload
     244: f2d
     245: invokestatic  #62                 // Method java/lang/Math.ceil:(D)D
     248: d2f
     249: fastore
     250: aload_3
     251: iconst_0
     252: dup2
     253: faload
     254: fconst_2
     255: fadd
     256: fastore
     257: goto          278
     260: aload_3
     261: iconst_0
     262: aload_3
     263: iconst_0
     264: faload
     265: f2d
     266: invokestatic  #62                 // Method java/lang/Math.ceil:(D)D
     269: d2f
     270: fastore
     271: aload_3
     272: iconst_0
     273: dup2
     274: faload
     275: fconst_1
     276: fadd
     277: fastore
     278: iload         7
     280: invokestatic  #63                 // Method isNativeC40:(C)Z
     283: ifeq          297
     286: aload_3
     287: iconst_1
     288: dup2
     289: faload
     290: ldc           #64                 // float 0.6666667f
     292: fadd
     293: fastore
     294: goto          324
     297: iload         7
     299: invokestatic  #61                 // Method isExtendedASCII:(C)Z
     302: ifeq          316
     305: aload_3
     306: iconst_1
     307: dup2
     308: faload
     309: ldc           #65                 // float 2.6666667f
     311: fadd
     312: fastore
     313: goto          324
     316: aload_3
     317: iconst_1
     318: dup2
     319: faload
     320: ldc           #66                 // float 1.3333334f
     322: fadd
     323: fastore
     324: iload         7
     326: invokestatic  #67                 // Method isNativeText:(C)Z
     329: ifeq          343
     332: aload_3
     333: iconst_2
     334: dup2
     335: faload
     336: ldc           #64                 // float 0.6666667f
     338: fadd
     339: fastore
     340: goto          370
     343: iload         7
     345: invokestatic  #61                 // Method isExtendedASCII:(C)Z
     348: ifeq          362
     351: aload_3
     352: iconst_2
     353: dup2
     354: faload
     355: ldc           #65                 // float 2.6666667f
     357: fadd
     358: fastore
     359: goto          370
     362: aload_3
     363: iconst_2
     364: dup2
     365: faload
     366: ldc           #66                 // float 1.3333334f
     368: fadd
     369: fastore
     370: iload         7
     372: invokestatic  #49                 // Method isNativeX12:(C)Z
     375: ifeq          389
     378: aload_3
     379: iconst_3
     380: dup2
     381: faload
     382: ldc           #64                 // float 0.6666667f
     384: fadd
     385: fastore
     386: goto          416
     389: iload         7
     391: invokestatic  #61                 // Method isExtendedASCII:(C)Z
     394: ifeq          408
     397: aload_3
     398: iconst_3
     399: dup2
     400: faload
     401: ldc           #68                 // float 4.3333335f
     403: fadd
     404: fastore
     405: goto          416
     408: aload_3
     409: iconst_3
     410: dup2
     411: faload
     412: ldc           #69                 // float 3.3333333f
     414: fadd
     415: fastore
     416: iload         7
     418: invokestatic  #50                 // Method isNativeEDIFACT:(C)Z
     421: ifeq          435
     424: aload_3
     425: iconst_4
     426: dup2
     427: faload
     428: ldc           #70                 // float 0.75f
     430: fadd
     431: fastore
     432: goto          462
     435: iload         7
     437: invokestatic  #61                 // Method isExtendedASCII:(C)Z
     440: ifeq          454
     443: aload_3
     444: iconst_4
     445: dup2
     446: faload
     447: ldc           #71                 // float 4.25f
     449: fadd
     450: fastore
     451: goto          462
     454: aload_3
     455: iconst_4
     456: dup2
     457: faload
     458: ldc           #72                 // float 3.25f
     460: fadd
     461: fastore
     462: iload         7
     464: invokestatic  #73                 // Method isSpecialB256:(C)Z
     467: ifeq          481
     470: aload_3
     471: iconst_5
     472: dup2
     473: faload
     474: ldc           #74                 // float 4.0f
     476: fadd
     477: fastore
     478: goto          488
     481: aload_3
     482: iconst_5
     483: dup2
     484: faload
     485: fconst_1
     486: fadd
     487: fastore
     488: iload         4
     490: iconst_4
     491: if_icmplt     802
     494: aload         5
     496: iconst_0
     497: invokestatic  #53                 // Method java/util/Arrays.fill:([BB)V
     500: aload         6
     502: iconst_0
     503: invokestatic  #54                 // Method java/util/Arrays.fill:([II)V
     506: aload_3
     507: aload         6
     509: ldc           #56                 // int 2147483647
     511: aload         5
     513: invokestatic  #57                 // Method findMinimums:([F[II[B)I
     516: pop
     517: aload         6
     519: iconst_0
     520: iaload
     521: aload         6
     523: iconst_5
     524: iaload
     525: aload         6
     527: iconst_1
     528: iaload
     529: aload         6
     531: iconst_2
     532: iaload
     533: aload         6
     535: iconst_3
     536: iaload
     537: aload         6
     539: iconst_4
     540: iaload
     541: invokestatic  #75                 // Method min:(IIIII)I
     544: if_icmpge     549
     547: iconst_0
     548: ireturn
     549: aload         6
     551: iconst_5
     552: iaload
     553: aload         6
     555: iconst_0
     556: iaload
     557: if_icmplt     588
     560: aload         6
     562: iconst_5
     563: iaload
     564: iconst_1
     565: iadd
     566: aload         6
     568: iconst_1
     569: iaload
     570: aload         6
     572: iconst_2
     573: iaload
     574: aload         6
     576: iconst_3
     577: iaload
     578: aload         6
     580: iconst_4
     581: iaload
     582: invokestatic  #76                 // Method min:(IIII)I
     585: if_icmpge     590
     588: iconst_5
     589: ireturn
     590: aload         6
     592: iconst_4
     593: iaload
     594: iconst_1
     595: iadd
     596: aload         6
     598: iconst_5
     599: iaload
     600: aload         6
     602: iconst_1
     603: iaload
     604: aload         6
     606: iconst_2
     607: iaload
     608: aload         6
     610: iconst_3
     611: iaload
     612: aload         6
     614: iconst_0
     615: iaload
     616: invokestatic  #75                 // Method min:(IIIII)I
     619: if_icmpge     624
     622: iconst_4
     623: ireturn
     624: aload         6
     626: iconst_2
     627: iaload
     628: iconst_1
     629: iadd
     630: aload         6
     632: iconst_5
     633: iaload
     634: aload         6
     636: iconst_1
     637: iaload
     638: aload         6
     640: iconst_4
     641: iaload
     642: aload         6
     644: iconst_3
     645: iaload
     646: aload         6
     648: iconst_0
     649: iaload
     650: invokestatic  #75                 // Method min:(IIIII)I
     653: if_icmpge     658
     656: iconst_2
     657: ireturn
     658: aload         6
     660: iconst_3
     661: iaload
     662: iconst_1
     663: iadd
     664: aload         6
     666: iconst_5
     667: iaload
     668: aload         6
     670: iconst_1
     671: iaload
     672: aload         6
     674: iconst_4
     675: iaload
     676: aload         6
     678: iconst_2
     679: iaload
     680: aload         6
     682: iconst_0
     683: iaload
     684: invokestatic  #75                 // Method min:(IIIII)I
     687: if_icmpge     692
     690: iconst_3
     691: ireturn
     692: aload         6
     694: iconst_1
     695: iaload
     696: iconst_1
     697: iadd
     698: aload         6
     700: iconst_0
     701: iaload
     702: aload         6
     704: iconst_5
     705: iaload
     706: aload         6
     708: iconst_4
     709: iaload
     710: aload         6
     712: iconst_2
     713: iaload
     714: invokestatic  #76                 // Method min:(IIII)I
     717: if_icmpge     802
     720: aload         6
     722: iconst_1
     723: iaload
     724: aload         6
     726: iconst_3
     727: iaload
     728: if_icmpge     733
     731: iconst_1
     732: ireturn
     733: aload         6
     735: iconst_1
     736: iaload
     737: aload         6
     739: iconst_3
     740: iaload
     741: if_icmpne     802
     744: iload_1
     745: iload         4
     747: iadd
     748: iconst_1
     749: iadd
     750: istore        8
     752: iload         8
     754: aload_0
     755: invokeinterface #46,  1           // InterfaceMethod java/lang/CharSequence.length:()I
     760: if_icmpge     800
     763: aload_0
     764: iload         8
     766: invokeinterface #48,  2           // InterfaceMethod java/lang/CharSequence.charAt:(I)C
     771: istore        9
     773: iload         9
     775: invokestatic  #77                 // Method isX12TermSep:(C)Z
     778: ifeq          783
     781: iconst_3
     782: ireturn
     783: iload         9
     785: invokestatic  #49                 // Method isNativeX12:(C)Z
     788: ifne          794
     791: goto          800
     794: iinc          8, 1
     797: goto          752
     800: iconst_1
     801: ireturn
     802: goto          98

  private static int min(int, int, int, int, int);
    Code:
       0: iload_0
       1: iload_1
       2: iload_2
       3: iload_3
       4: invokestatic  #76                 // Method min:(IIII)I
       7: iload         4
       9: invokestatic  #47                 // Method java/lang/Math.min:(II)I
      12: ireturn

  private static int min(int, int, int, int);
    Code:
       0: iload_0
       1: iload_1
       2: iload_2
       3: iload_3
       4: invokestatic  #47                 // Method java/lang/Math.min:(II)I
       7: invokestatic  #47                 // Method java/lang/Math.min:(II)I
      10: invokestatic  #47                 // Method java/lang/Math.min:(II)I
      13: ireturn

  private static int findMinimums(float[], int[], int, byte[]);
    Code:
       0: iconst_0
       1: istore        4
       3: iload         4
       5: bipush        6
       7: if_icmpge     61
      10: aload_1
      11: iload         4
      13: aload_0
      14: iload         4
      16: faload
      17: f2d
      18: invokestatic  #62                 // Method java/lang/Math.ceil:(D)D
      21: d2i
      22: dup_x2
      23: iastore
      24: istore        5
      26: iload_2
      27: iload         5
      29: if_icmple     40
      32: iload         5
      34: istore_2
      35: aload_3
      36: iconst_0
      37: invokestatic  #53                 // Method java/util/Arrays.fill:([BB)V
      40: iload_2
      41: iload         5
      43: if_icmpne     55
      46: aload_3
      47: iload         4
      49: dup2
      50: baload
      51: iconst_1
      52: iadd
      53: i2b
      54: bastore
      55: iinc          4, 1
      58: goto          3
      61: iload_2
      62: ireturn

  private static int getMinimumCount(byte[]);
    Code:
       0: iconst_0
       1: istore_1
       2: iconst_0
       3: istore_2
       4: iload_2
       5: bipush        6
       7: if_icmpge     22
      10: iload_1
      11: aload_0
      12: iload_2
      13: baload
      14: iadd
      15: istore_1
      16: iinc          2, 1
      19: goto          4
      22: iload_1
      23: ireturn

  static boolean isDigit(char);
    Code:
       0: iload_0
       1: bipush        48
       3: if_icmplt     16
       6: iload_0
       7: bipush        57
       9: if_icmpgt     16
      12: iconst_1
      13: goto          17
      16: iconst_0
      17: ireturn

  static boolean isExtendedASCII(char);
    Code:
       0: iload_0
       1: sipush        128
       4: if_icmplt     18
       7: iload_0
       8: sipush        255
      11: if_icmpgt     18
      14: iconst_1
      15: goto          19
      18: iconst_0
      19: ireturn

  static boolean isNativeC40(char);
    Code:
       0: iload_0
       1: bipush        32
       3: if_icmpeq     30
       6: iload_0
       7: bipush        48
       9: if_icmplt     18
      12: iload_0
      13: bipush        57
      15: if_icmple     30
      18: iload_0
      19: bipush        65
      21: if_icmplt     34
      24: iload_0
      25: bipush        90
      27: if_icmpgt     34
      30: iconst_1
      31: goto          35
      34: iconst_0
      35: ireturn

  static boolean isNativeText(char);
    Code:
       0: iload_0
       1: bipush        32
       3: if_icmpeq     30
       6: iload_0
       7: bipush        48
       9: if_icmplt     18
      12: iload_0
      13: bipush        57
      15: if_icmple     30
      18: iload_0
      19: bipush        97
      21: if_icmplt     34
      24: iload_0
      25: bipush        122
      27: if_icmpgt     34
      30: iconst_1
      31: goto          35
      34: iconst_0
      35: ireturn

  static boolean isNativeX12(char);
    Code:
       0: iload_0
       1: invokestatic  #77                 // Method isX12TermSep:(C)Z
       4: ifne          37
       7: iload_0
       8: bipush        32
      10: if_icmpeq     37
      13: iload_0
      14: bipush        48
      16: if_icmplt     25
      19: iload_0
      20: bipush        57
      22: if_icmple     37
      25: iload_0
      26: bipush        65
      28: if_icmplt     41
      31: iload_0
      32: bipush        90
      34: if_icmpgt     41
      37: iconst_1
      38: goto          42
      41: iconst_0
      42: ireturn

  private static boolean isX12TermSep(char);
    Code:
       0: iload_0
       1: bipush        13
       3: if_icmpeq     18
       6: iload_0
       7: bipush        42
       9: if_icmpeq     18
      12: iload_0
      13: bipush        62
      15: if_icmpne     22
      18: iconst_1
      19: goto          23
      22: iconst_0
      23: ireturn

  static boolean isNativeEDIFACT(char);
    Code:
       0: iload_0
       1: bipush        32
       3: if_icmplt     16
       6: iload_0
       7: bipush        94
       9: if_icmpgt     16
      12: iconst_1
      13: goto          17
      16: iconst_0
      17: ireturn

  private static boolean isSpecialB256(char);
    Code:
       0: iconst_0
       1: ireturn

  public static int determineConsecutiveDigitCount(java.lang.CharSequence, int);
    Code:
       0: aload_0
       1: invokeinterface #46,  1           // InterfaceMethod java/lang/CharSequence.length:()I
       6: istore_2
       7: iload_1
       8: istore_3
       9: iload_3
      10: iload_2
      11: if_icmpge     33
      14: aload_0
      15: iload_3
      16: invokeinterface #48,  2           // InterfaceMethod java/lang/CharSequence.charAt:(I)C
      21: invokestatic  #59                 // Method isDigit:(C)Z
      24: ifeq          33
      27: iinc          3, 1
      30: goto          9
      33: iload_3
      34: iload_1
      35: isub
      36: ireturn

  static void illegalCharacter(char);
    Code:
       0: iload_0
       1: invokestatic  #78                 // Method java/lang/Integer.toHexString:(I)Ljava/lang/String;
       4: astore_1
       5: new           #79                 // class java/lang/StringBuilder
       8: dup
       9: invokespecial #80                 // Method java/lang/StringBuilder."<init>":()V
      12: ldc           #81                 // String 0000
      14: iconst_0
      15: iconst_4
      16: aload_1
      17: invokevirtual #29                 // Method java/lang/String.length:()I
      20: isub
      21: invokevirtual #82                 // Method java/lang/String.substring:(II)Ljava/lang/String;
      24: invokevirtual #83                 // Method java/lang/StringBuilder.append:(Ljava/lang/String;)Ljava/lang/StringBuilder;
      27: aload_1
      28: invokevirtual #83                 // Method java/lang/StringBuilder.append:(Ljava/lang/String;)Ljava/lang/StringBuilder;
      31: invokevirtual #44                 // Method java/lang/StringBuilder.toString:()Ljava/lang/String;
      34: astore_1
      35: new           #84                 // class java/lang/IllegalArgumentException
      38: dup
      39: new           #79                 // class java/lang/StringBuilder
      42: dup
      43: invokespecial #80                 // Method java/lang/StringBuilder."<init>":()V
      46: ldc           #85                 // String Illegal character:
      48: invokevirtual #83                 // Method java/lang/StringBuilder.append:(Ljava/lang/String;)Ljava/lang/StringBuilder;
      51: iload_0
      52: invokevirtual #42                 // Method java/lang/StringBuilder.append:(C)Ljava/lang/StringBuilder;
      55: ldc           #86                 // String  (0x
      57: invokevirtual #83                 // Method java/lang/StringBuilder.append:(Ljava/lang/String;)Ljava/lang/StringBuilder;
      60: aload_1
      61: invokevirtual #83                 // Method java/lang/StringBuilder.append:(Ljava/lang/String;)Ljava/lang/StringBuilder;
      64: bipush        41
      66: invokevirtual #42                 // Method java/lang/StringBuilder.append:(C)Ljava/lang/StringBuilder;
      69: invokevirtual #44                 // Method java/lang/StringBuilder.toString:()Ljava/lang/String;
      72: invokespecial #87                 // Method java/lang/IllegalArgumentException."<init>":(Ljava/lang/String;)V
      75: athrow
}
