Compiled from "MinimalEncoder.java"
final class com.google.zxing.datamatrix.encoder.MinimalEncoder$Edge {
  private static final int[] allCodewordCapacities;

  private static final int[] squareCodewordCapacities;

  private static final int[] rectangularCodewordCapacities;

  private final com.google.zxing.datamatrix.encoder.MinimalEncoder$Input input;

  private final com.google.zxing.datamatrix.encoder.MinimalEncoder$Mode mode;

  private final int fromPosition;

  private final int characterLength;

  private final com.google.zxing.datamatrix.encoder.MinimalEncoder$Edge previous;

  private final int cachedTotalSize;

  static final boolean $assertionsDisabled;

  private com.google.zxing.datamatrix.encoder.MinimalEncoder$Edge(com.google.zxing.datamatrix.encoder.MinimalEncoder$Input, com.google.zxing.datamatrix.encoder.MinimalEncoder$Mode, int, int, com.google.zxing.datamatrix.encoder.MinimalEncoder$Edge);
    Code:
       0: aload_0
       1: invokespecial #8                  // Method java/lang/Object."<init>":()V
       4: aload_0
       5: aload_1
       6: putfield      #3                  // Field input:Lcom/google/zxing/datamatrix/encoder/MinimalEncoder$Input;
       9: aload_0
      10: aload_2
      11: putfield      #2                  // Field mode:Lcom/google/zxing/datamatrix/encoder/MinimalEncoder$Mode;
      14: aload_0
      15: iload_3
      16: putfield      #7                  // Field fromPosition:I
      19: aload_0
      20: iload         4
      22: putfield      #6                  // Field characterLength:I
      25: aload_0
      26: aload         5
      28: putfield      #1                  // Field previous:Lcom/google/zxing/datamatrix/encoder/MinimalEncoder$Edge;
      31: getstatic     #9                  // Field $assertionsDisabled:Z
      34: ifne          56
      37: iload_3
      38: iload         4
      40: iadd
      41: aload_1
      42: invokevirtual #10                 // Method com/google/zxing/datamatrix/encoder/MinimalEncoder$Input.length:()I
      45: if_icmple     56
      48: new           #11                 // class java/lang/AssertionError
      51: dup
      52: invokespecial #12                 // Method java/lang/AssertionError."<init>":()V
      55: athrow
      56: aload         5
      58: ifnull        69
      61: aload         5
      63: getfield      #5                  // Field cachedTotalSize:I
      66: goto          70
      69: iconst_0
      70: istore        6
      72: aload_0
      73: invokevirtual #13                 // Method getPreviousMode:()Lcom/google/zxing/datamatrix/encoder/MinimalEncoder$Mode;
      76: astore        7
      78: getstatic     #14                 // Field com/google/zxing/datamatrix/encoder/MinimalEncoder$1.$SwitchMap$com$google$zxing$datamatrix$encoder$MinimalEncoder$Mode:[I
      81: aload_2
      82: invokevirtual #15                 // Method com/google/zxing/datamatrix/encoder/MinimalEncoder$Mode.ordinal:()I
      85: iaload
      86: tableswitch   { // 1 to 6
                     1: 124
                     2: 183
                     3: 257
                     4: 257
                     5: 257
                     6: 359
               default: 411
          }
     124: iinc          6, 1
     127: aload_1
     128: iload_3
     129: invokevirtual #16                 // Method com/google/zxing/datamatrix/encoder/MinimalEncoder$Input.isECI:(I)Z
     132: ifne          150
     135: aload_1
     136: iload_3
     137: invokevirtual #17                 // Method com/google/zxing/datamatrix/encoder/MinimalEncoder$Input.charAt:(I)C
     140: aload_1
     141: invokevirtual #18                 // Method com/google/zxing/datamatrix/encoder/MinimalEncoder$Input.getFNC1Character:()I
     144: invokestatic  #19                 // Method com/google/zxing/datamatrix/encoder/MinimalEncoder.isExtendedASCII:(CI)Z
     147: ifeq          153
     150: iinc          6, 1
     153: aload         7
     155: getstatic     #20                 // Field com/google/zxing/datamatrix/encoder/MinimalEncoder$Mode.C40:Lcom/google/zxing/datamatrix/encoder/MinimalEncoder$Mode;
     158: if_acmpeq     177
     161: aload         7
     163: getstatic     #21                 // Field com/google/zxing/datamatrix/encoder/MinimalEncoder$Mode.TEXT:Lcom/google/zxing/datamatrix/encoder/MinimalEncoder$Mode;
     166: if_acmpeq     177
     169: aload         7
     171: getstatic     #22                 // Field com/google/zxing/datamatrix/encoder/MinimalEncoder$Mode.X12:Lcom/google/zxing/datamatrix/encoder/MinimalEncoder$Mode;
     174: if_acmpne     411
     177: iinc          6, 1
     180: goto          411
     183: iinc          6, 1
     186: aload         7
     188: getstatic     #23                 // Field com/google/zxing/datamatrix/encoder/MinimalEncoder$Mode.B256:Lcom/google/zxing/datamatrix/encoder/MinimalEncoder$Mode;
     191: if_acmpeq     200
     194: iinc          6, 1
     197: goto          213
     200: aload_0
     201: invokevirtual #24                 // Method getB256Size:()I
     204: sipush        250
     207: if_icmpne     213
     210: iinc          6, 1
     213: aload         7
     215: getstatic     #25                 // Field com/google/zxing/datamatrix/encoder/MinimalEncoder$Mode.ASCII:Lcom/google/zxing/datamatrix/encoder/MinimalEncoder$Mode;
     218: if_acmpne     227
     221: iinc          6, 1
     224: goto          411
     227: aload         7
     229: getstatic     #20                 // Field com/google/zxing/datamatrix/encoder/MinimalEncoder$Mode.C40:Lcom/google/zxing/datamatrix/encoder/MinimalEncoder$Mode;
     232: if_acmpeq     251
     235: aload         7
     237: getstatic     #21                 // Field com/google/zxing/datamatrix/encoder/MinimalEncoder$Mode.TEXT:Lcom/google/zxing/datamatrix/encoder/MinimalEncoder$Mode;
     240: if_acmpeq     251
     243: aload         7
     245: getstatic     #22                 // Field com/google/zxing/datamatrix/encoder/MinimalEncoder$Mode.X12:Lcom/google/zxing/datamatrix/encoder/MinimalEncoder$Mode;
     248: if_acmpne     411
     251: iinc          6, 2
     254: goto          411
     257: aload_2
     258: getstatic     #22                 // Field com/google/zxing/datamatrix/encoder/MinimalEncoder$Mode.X12:Lcom/google/zxing/datamatrix/encoder/MinimalEncoder$Mode;
     261: if_acmpne     270
     264: iinc          6, 2
     267: goto          301
     270: iconst_1
     271: newarray       int
     273: astore        8
     275: iload         6
     277: aload_1
     278: iload_3
     279: aload_2
     280: getstatic     #20                 // Field com/google/zxing/datamatrix/encoder/MinimalEncoder$Mode.C40:Lcom/google/zxing/datamatrix/encoder/MinimalEncoder$Mode;
     283: if_acmpne     290
     286: iconst_1
     287: goto          291
     290: iconst_0
     291: aload         8
     293: invokestatic  #26                 // Method com/google/zxing/datamatrix/encoder/MinimalEncoder.getNumberOfC40Words:(Lcom/google/zxing/datamatrix/encoder/MinimalEncoder$Input;IZ[I)I
     296: iconst_2
     297: imul
     298: iadd
     299: istore        6
     301: aload         7
     303: getstatic     #25                 // Field com/google/zxing/datamatrix/encoder/MinimalEncoder$Mode.ASCII:Lcom/google/zxing/datamatrix/encoder/MinimalEncoder$Mode;
     306: if_acmpeq     317
     309: aload         7
     311: getstatic     #23                 // Field com/google/zxing/datamatrix/encoder/MinimalEncoder$Mode.B256:Lcom/google/zxing/datamatrix/encoder/MinimalEncoder$Mode;
     314: if_acmpne     323
     317: iinc          6, 1
     320: goto          411
     323: aload         7
     325: aload_2
     326: if_acmpeq     411
     329: aload         7
     331: getstatic     #20                 // Field com/google/zxing/datamatrix/encoder/MinimalEncoder$Mode.C40:Lcom/google/zxing/datamatrix/encoder/MinimalEncoder$Mode;
     334: if_acmpeq     353
     337: aload         7
     339: getstatic     #21                 // Field com/google/zxing/datamatrix/encoder/MinimalEncoder$Mode.TEXT:Lcom/google/zxing/datamatrix/encoder/MinimalEncoder$Mode;
     342: if_acmpeq     353
     345: aload         7
     347: getstatic     #22                 // Field com/google/zxing/datamatrix/encoder/MinimalEncoder$Mode.X12:Lcom/google/zxing/datamatrix/encoder/MinimalEncoder$Mode;
     350: if_acmpne     411
     353: iinc          6, 2
     356: goto          411
     359: iinc          6, 3
     362: aload         7
     364: getstatic     #25                 // Field com/google/zxing/datamatrix/encoder/MinimalEncoder$Mode.ASCII:Lcom/google/zxing/datamatrix/encoder/MinimalEncoder$Mode;
     367: if_acmpeq     378
     370: aload         7
     372: getstatic     #23                 // Field com/google/zxing/datamatrix/encoder/MinimalEncoder$Mode.B256:Lcom/google/zxing/datamatrix/encoder/MinimalEncoder$Mode;
     375: if_acmpne     384
     378: iinc          6, 1
     381: goto          411
     384: aload         7
     386: getstatic     #20                 // Field com/google/zxing/datamatrix/encoder/MinimalEncoder$Mode.C40:Lcom/google/zxing/datamatrix/encoder/MinimalEncoder$Mode;
     389: if_acmpeq     408
     392: aload         7
     394: getstatic     #21                 // Field com/google/zxing/datamatrix/encoder/MinimalEncoder$Mode.TEXT:Lcom/google/zxing/datamatrix/encoder/MinimalEncoder$Mode;
     397: if_acmpeq     408
     400: aload         7
     402: getstatic     #22                 // Field com/google/zxing/datamatrix/encoder/MinimalEncoder$Mode.X12:Lcom/google/zxing/datamatrix/encoder/MinimalEncoder$Mode;
     405: if_acmpne     411
     408: iinc          6, 2
     411: aload_0
     412: iload         6
     414: putfield      #5                  // Field cachedTotalSize:I
     417: return

  int getB256Size();
    Code:
       0: iconst_0
       1: istore_1
       2: aload_0
       3: astore_2
       4: aload_2
       5: ifnull        36
       8: aload_2
       9: getfield      #2                  // Field mode:Lcom/google/zxing/datamatrix/encoder/MinimalEncoder$Mode;
      12: getstatic     #23                 // Field com/google/zxing/datamatrix/encoder/MinimalEncoder$Mode.B256:Lcom/google/zxing/datamatrix/encoder/MinimalEncoder$Mode;
      15: if_acmpne     36
      18: iload_1
      19: sipush        250
      22: if_icmpgt     36
      25: iinc          1, 1
      28: aload_2
      29: getfield      #1                  // Field previous:Lcom/google/zxing/datamatrix/encoder/MinimalEncoder$Edge;
      32: astore_2
      33: goto          4
      36: iload_1
      37: ireturn

  com.google.zxing.datamatrix.encoder.MinimalEncoder$Mode getPreviousStartMode();
    Code:
       0: aload_0
       1: getfield      #1                  // Field previous:Lcom/google/zxing/datamatrix/encoder/MinimalEncoder$Edge;
       4: ifnonnull     13
       7: getstatic     #25                 // Field com/google/zxing/datamatrix/encoder/MinimalEncoder$Mode.ASCII:Lcom/google/zxing/datamatrix/encoder/MinimalEncoder$Mode;
      10: goto          20
      13: aload_0
      14: getfield      #1                  // Field previous:Lcom/google/zxing/datamatrix/encoder/MinimalEncoder$Edge;
      17: getfield      #2                  // Field mode:Lcom/google/zxing/datamatrix/encoder/MinimalEncoder$Mode;
      20: areturn

  com.google.zxing.datamatrix.encoder.MinimalEncoder$Mode getPreviousMode();
    Code:
       0: aload_0
       1: getfield      #1                  // Field previous:Lcom/google/zxing/datamatrix/encoder/MinimalEncoder$Edge;
       4: ifnonnull     13
       7: getstatic     #25                 // Field com/google/zxing/datamatrix/encoder/MinimalEncoder$Mode.ASCII:Lcom/google/zxing/datamatrix/encoder/MinimalEncoder$Mode;
      10: goto          20
      13: aload_0
      14: getfield      #1                  // Field previous:Lcom/google/zxing/datamatrix/encoder/MinimalEncoder$Edge;
      17: invokevirtual #27                 // Method getEndMode:()Lcom/google/zxing/datamatrix/encoder/MinimalEncoder$Mode;
      20: areturn

  com.google.zxing.datamatrix.encoder.MinimalEncoder$Mode getEndMode();
    Code:
       0: aload_0
       1: getfield      #2                  // Field mode:Lcom/google/zxing/datamatrix/encoder/MinimalEncoder$Mode;
       4: getstatic     #28                 // Field com/google/zxing/datamatrix/encoder/MinimalEncoder$Mode.EDF:Lcom/google/zxing/datamatrix/encoder/MinimalEncoder$Mode;
       7: if_acmpne     51
      10: aload_0
      11: getfield      #6                  // Field characterLength:I
      14: iconst_4
      15: if_icmpge     22
      18: getstatic     #25                 // Field com/google/zxing/datamatrix/encoder/MinimalEncoder$Mode.ASCII:Lcom/google/zxing/datamatrix/encoder/MinimalEncoder$Mode;
      21: areturn
      22: aload_0
      23: invokevirtual #29                 // Method getLastASCII:()I
      26: istore_1
      27: iload_1
      28: ifle          51
      31: aload_0
      32: aload_0
      33: getfield      #5                  // Field cachedTotalSize:I
      36: iload_1
      37: iadd
      38: invokevirtual #30                 // Method getCodewordsRemaining:(I)I
      41: iconst_2
      42: iload_1
      43: isub
      44: if_icmpgt     51
      47: getstatic     #25                 // Field com/google/zxing/datamatrix/encoder/MinimalEncoder$Mode.ASCII:Lcom/google/zxing/datamatrix/encoder/MinimalEncoder$Mode;
      50: areturn
      51: aload_0
      52: getfield      #2                  // Field mode:Lcom/google/zxing/datamatrix/encoder/MinimalEncoder$Mode;
      55: getstatic     #20                 // Field com/google/zxing/datamatrix/encoder/MinimalEncoder$Mode.C40:Lcom/google/zxing/datamatrix/encoder/MinimalEncoder$Mode;
      58: if_acmpeq     81
      61: aload_0
      62: getfield      #2                  // Field mode:Lcom/google/zxing/datamatrix/encoder/MinimalEncoder$Mode;
      65: getstatic     #21                 // Field com/google/zxing/datamatrix/encoder/MinimalEncoder$Mode.TEXT:Lcom/google/zxing/datamatrix/encoder/MinimalEncoder$Mode;
      68: if_acmpeq     81
      71: aload_0
      72: getfield      #2                  // Field mode:Lcom/google/zxing/datamatrix/encoder/MinimalEncoder$Mode;
      75: getstatic     #22                 // Field com/google/zxing/datamatrix/encoder/MinimalEncoder$Mode.X12:Lcom/google/zxing/datamatrix/encoder/MinimalEncoder$Mode;
      78: if_acmpne     142
      81: aload_0
      82: getfield      #7                  // Field fromPosition:I
      85: aload_0
      86: getfield      #6                  // Field characterLength:I
      89: iadd
      90: aload_0
      91: getfield      #3                  // Field input:Lcom/google/zxing/datamatrix/encoder/MinimalEncoder$Input;
      94: invokevirtual #10                 // Method com/google/zxing/datamatrix/encoder/MinimalEncoder$Input.length:()I
      97: if_icmplt     115
     100: aload_0
     101: aload_0
     102: getfield      #5                  // Field cachedTotalSize:I
     105: invokevirtual #30                 // Method getCodewordsRemaining:(I)I
     108: ifne          115
     111: getstatic     #25                 // Field com/google/zxing/datamatrix/encoder/MinimalEncoder$Mode.ASCII:Lcom/google/zxing/datamatrix/encoder/MinimalEncoder$Mode;
     114: areturn
     115: aload_0
     116: invokevirtual #29                 // Method getLastASCII:()I
     119: istore_1
     120: iload_1
     121: iconst_1
     122: if_icmpne     142
     125: aload_0
     126: aload_0
     127: getfield      #5                  // Field cachedTotalSize:I
     130: iconst_1
     131: iadd
     132: invokevirtual #30                 // Method getCodewordsRemaining:(I)I
     135: ifne          142
     138: getstatic     #25                 // Field com/google/zxing/datamatrix/encoder/MinimalEncoder$Mode.ASCII:Lcom/google/zxing/datamatrix/encoder/MinimalEncoder$Mode;
     141: areturn
     142: aload_0
     143: getfield      #2                  // Field mode:Lcom/google/zxing/datamatrix/encoder/MinimalEncoder$Mode;
     146: areturn

  com.google.zxing.datamatrix.encoder.MinimalEncoder$Mode getMode();
    Code:
       0: aload_0
       1: getfield      #2                  // Field mode:Lcom/google/zxing/datamatrix/encoder/MinimalEncoder$Mode;
       4: areturn

  int getLastASCII();
    Code:
       0: aload_0
       1: getfield      #3                  // Field input:Lcom/google/zxing/datamatrix/encoder/MinimalEncoder$Input;
       4: invokevirtual #10                 // Method com/google/zxing/datamatrix/encoder/MinimalEncoder$Input.length:()I
       7: istore_1
       8: aload_0
       9: getfield      #7                  // Field fromPosition:I
      12: aload_0
      13: getfield      #6                  // Field characterLength:I
      16: iadd
      17: istore_2
      18: iload_1
      19: iload_2
      20: isub
      21: iconst_4
      22: if_icmpgt     30
      25: iload_2
      26: iload_1
      27: if_icmplt     32
      30: iconst_0
      31: ireturn
      32: iload_1
      33: iload_2
      34: isub
      35: iconst_1
      36: if_icmpne     64
      39: aload_0
      40: getfield      #3                  // Field input:Lcom/google/zxing/datamatrix/encoder/MinimalEncoder$Input;
      43: iload_2
      44: invokevirtual #17                 // Method com/google/zxing/datamatrix/encoder/MinimalEncoder$Input.charAt:(I)C
      47: aload_0
      48: getfield      #3                  // Field input:Lcom/google/zxing/datamatrix/encoder/MinimalEncoder$Input;
      51: invokevirtual #18                 // Method com/google/zxing/datamatrix/encoder/MinimalEncoder$Input.getFNC1Character:()I
      54: invokestatic  #19                 // Method com/google/zxing/datamatrix/encoder/MinimalEncoder.isExtendedASCII:(CI)Z
      57: ifeq          62
      60: iconst_0
      61: ireturn
      62: iconst_1
      63: ireturn
      64: iload_1
      65: iload_2
      66: isub
      67: iconst_2
      68: if_icmpne     151
      71: aload_0
      72: getfield      #3                  // Field input:Lcom/google/zxing/datamatrix/encoder/MinimalEncoder$Input;
      75: iload_2
      76: invokevirtual #17                 // Method com/google/zxing/datamatrix/encoder/MinimalEncoder$Input.charAt:(I)C
      79: aload_0
      80: getfield      #3                  // Field input:Lcom/google/zxing/datamatrix/encoder/MinimalEncoder$Input;
      83: invokevirtual #18                 // Method com/google/zxing/datamatrix/encoder/MinimalEncoder$Input.getFNC1Character:()I
      86: invokestatic  #19                 // Method com/google/zxing/datamatrix/encoder/MinimalEncoder.isExtendedASCII:(CI)Z
      89: ifne          115
      92: aload_0
      93: getfield      #3                  // Field input:Lcom/google/zxing/datamatrix/encoder/MinimalEncoder$Input;
      96: iload_2
      97: iconst_1
      98: iadd
      99: invokevirtual #17                 // Method com/google/zxing/datamatrix/encoder/MinimalEncoder$Input.charAt:(I)C
     102: aload_0
     103: getfield      #3                  // Field input:Lcom/google/zxing/datamatrix/encoder/MinimalEncoder$Input;
     106: invokevirtual #18                 // Method com/google/zxing/datamatrix/encoder/MinimalEncoder$Input.getFNC1Character:()I
     109: invokestatic  #19                 // Method com/google/zxing/datamatrix/encoder/MinimalEncoder.isExtendedASCII:(CI)Z
     112: ifeq          117
     115: iconst_0
     116: ireturn
     117: aload_0
     118: getfield      #3                  // Field input:Lcom/google/zxing/datamatrix/encoder/MinimalEncoder$Input;
     121: iload_2
     122: invokevirtual #17                 // Method com/google/zxing/datamatrix/encoder/MinimalEncoder$Input.charAt:(I)C
     125: invokestatic  #31                 // Method com/google/zxing/datamatrix/encoder/HighLevelEncoder.isDigit:(C)Z
     128: ifeq          149
     131: aload_0
     132: getfield      #3                  // Field input:Lcom/google/zxing/datamatrix/encoder/MinimalEncoder$Input;
     135: iload_2
     136: iconst_1
     137: iadd
     138: invokevirtual #17                 // Method com/google/zxing/datamatrix/encoder/MinimalEncoder$Input.charAt:(I)C
     141: invokestatic  #31                 // Method com/google/zxing/datamatrix/encoder/HighLevelEncoder.isDigit:(C)Z
     144: ifeq          149
     147: iconst_1
     148: ireturn
     149: iconst_2
     150: ireturn
     151: iload_1
     152: iload_2
     153: isub
     154: iconst_3
     155: if_icmpne     270
     158: aload_0
     159: getfield      #3                  // Field input:Lcom/google/zxing/datamatrix/encoder/MinimalEncoder$Input;
     162: iload_2
     163: invokevirtual #17                 // Method com/google/zxing/datamatrix/encoder/MinimalEncoder$Input.charAt:(I)C
     166: invokestatic  #31                 // Method com/google/zxing/datamatrix/encoder/HighLevelEncoder.isDigit:(C)Z
     169: ifeq          213
     172: aload_0
     173: getfield      #3                  // Field input:Lcom/google/zxing/datamatrix/encoder/MinimalEncoder$Input;
     176: iload_2
     177: iconst_1
     178: iadd
     179: invokevirtual #17                 // Method com/google/zxing/datamatrix/encoder/MinimalEncoder$Input.charAt:(I)C
     182: invokestatic  #31                 // Method com/google/zxing/datamatrix/encoder/HighLevelEncoder.isDigit:(C)Z
     185: ifeq          213
     188: aload_0
     189: getfield      #3                  // Field input:Lcom/google/zxing/datamatrix/encoder/MinimalEncoder$Input;
     192: iload_2
     193: iconst_2
     194: iadd
     195: invokevirtual #17                 // Method com/google/zxing/datamatrix/encoder/MinimalEncoder$Input.charAt:(I)C
     198: aload_0
     199: getfield      #3                  // Field input:Lcom/google/zxing/datamatrix/encoder/MinimalEncoder$Input;
     202: invokevirtual #18                 // Method com/google/zxing/datamatrix/encoder/MinimalEncoder$Input.getFNC1Character:()I
     205: invokestatic  #19                 // Method com/google/zxing/datamatrix/encoder/MinimalEncoder.isExtendedASCII:(CI)Z
     208: ifne          213
     211: iconst_2
     212: ireturn
     213: aload_0
     214: getfield      #3                  // Field input:Lcom/google/zxing/datamatrix/encoder/MinimalEncoder$Input;
     217: iload_2
     218: iconst_1
     219: iadd
     220: invokevirtual #17                 // Method com/google/zxing/datamatrix/encoder/MinimalEncoder$Input.charAt:(I)C
     223: invokestatic  #31                 // Method com/google/zxing/datamatrix/encoder/HighLevelEncoder.isDigit:(C)Z
     226: ifeq          268
     229: aload_0
     230: getfield      #3                  // Field input:Lcom/google/zxing/datamatrix/encoder/MinimalEncoder$Input;
     233: iload_2
     234: iconst_2
     235: iadd
     236: invokevirtual #17                 // Method com/google/zxing/datamatrix/encoder/MinimalEncoder$Input.charAt:(I)C
     239: invokestatic  #31                 // Method com/google/zxing/datamatrix/encoder/HighLevelEncoder.isDigit:(C)Z
     242: ifeq          268
     245: aload_0
     246: getfield      #3                  // Field input:Lcom/google/zxing/datamatrix/encoder/MinimalEncoder$Input;
     249: iload_2
     250: invokevirtual #17                 // Method com/google/zxing/datamatrix/encoder/MinimalEncoder$Input.charAt:(I)C
     253: aload_0
     254: getfield      #3                  // Field input:Lcom/google/zxing/datamatrix/encoder/MinimalEncoder$Input;
     257: invokevirtual #18                 // Method com/google/zxing/datamatrix/encoder/MinimalEncoder$Input.getFNC1Character:()I
     260: invokestatic  #19                 // Method com/google/zxing/datamatrix/encoder/MinimalEncoder.isExtendedASCII:(CI)Z
     263: ifne          268
     266: iconst_2
     267: ireturn
     268: iconst_0
     269: ireturn
     270: aload_0
     271: getfield      #3                  // Field input:Lcom/google/zxing/datamatrix/encoder/MinimalEncoder$Input;
     274: iload_2
     275: invokevirtual #17                 // Method com/google/zxing/datamatrix/encoder/MinimalEncoder$Input.charAt:(I)C
     278: invokestatic  #31                 // Method com/google/zxing/datamatrix/encoder/HighLevelEncoder.isDigit:(C)Z
     281: ifeq          334
     284: aload_0
     285: getfield      #3                  // Field input:Lcom/google/zxing/datamatrix/encoder/MinimalEncoder$Input;
     288: iload_2
     289: iconst_1
     290: iadd
     291: invokevirtual #17                 // Method com/google/zxing/datamatrix/encoder/MinimalEncoder$Input.charAt:(I)C
     294: invokestatic  #31                 // Method com/google/zxing/datamatrix/encoder/HighLevelEncoder.isDigit:(C)Z
     297: ifeq          334
     300: aload_0
     301: getfield      #3                  // Field input:Lcom/google/zxing/datamatrix/encoder/MinimalEncoder$Input;
     304: iload_2
     305: iconst_2
     306: iadd
     307: invokevirtual #17                 // Method com/google/zxing/datamatrix/encoder/MinimalEncoder$Input.charAt:(I)C
     310: invokestatic  #31                 // Method com/google/zxing/datamatrix/encoder/HighLevelEncoder.isDigit:(C)Z
     313: ifeq          334
     316: aload_0
     317: getfield      #3                  // Field input:Lcom/google/zxing/datamatrix/encoder/MinimalEncoder$Input;
     320: iload_2
     321: iconst_3
     322: iadd
     323: invokevirtual #17                 // Method com/google/zxing/datamatrix/encoder/MinimalEncoder$Input.charAt:(I)C
     326: invokestatic  #31                 // Method com/google/zxing/datamatrix/encoder/HighLevelEncoder.isDigit:(C)Z
     329: ifeq          334
     332: iconst_2
     333: ireturn
     334: iconst_0
     335: ireturn

  int getMinSymbolSize(int);
    Code:
       0: getstatic     #32                 // Field com/google/zxing/datamatrix/encoder/MinimalEncoder$1.$SwitchMap$com$google$zxing$datamatrix$encoder$SymbolShapeHint:[I
       3: aload_0
       4: getfield      #3                  // Field input:Lcom/google/zxing/datamatrix/encoder/MinimalEncoder$Input;
       7: invokestatic  #33                 // Method com/google/zxing/datamatrix/encoder/MinimalEncoder$Input.access$500:(Lcom/google/zxing/datamatrix/encoder/MinimalEncoder$Input;)Lcom/google/zxing/datamatrix/encoder/SymbolShapeHint;
      10: invokevirtual #34                 // Method com/google/zxing/datamatrix/encoder/SymbolShapeHint.ordinal:()I
      13: iaload
      14: lookupswitch  { // 2
                     1: 40
                     2: 80
               default: 117
          }
      40: getstatic     #35                 // Field squareCodewordCapacities:[I
      43: astore_2
      44: aload_2
      45: arraylength
      46: istore_3
      47: iconst_0
      48: istore        4
      50: iload         4
      52: iload_3
      53: if_icmpge     77
      56: aload_2
      57: iload         4
      59: iaload
      60: istore        5
      62: iload         5
      64: iload_1
      65: if_icmplt     71
      68: iload         5
      70: ireturn
      71: iinc          4, 1
      74: goto          50
      77: goto          117
      80: getstatic     #36                 // Field rectangularCodewordCapacities:[I
      83: astore_2
      84: aload_2
      85: arraylength
      86: istore_3
      87: iconst_0
      88: istore        4
      90: iload         4
      92: iload_3
      93: if_icmpge     117
      96: aload_2
      97: iload         4
      99: iaload
     100: istore        5
     102: iload         5
     104: iload_1
     105: if_icmplt     111
     108: iload         5
     110: ireturn
     111: iinc          4, 1
     114: goto          90
     117: getstatic     #37                 // Field allCodewordCapacities:[I
     120: astore_2
     121: aload_2
     122: arraylength
     123: istore_3
     124: iconst_0
     125: istore        4
     127: iload         4
     129: iload_3
     130: if_icmpge     154
     133: aload_2
     134: iload         4
     136: iaload
     137: istore        5
     139: iload         5
     141: iload_1
     142: if_icmplt     148
     145: iload         5
     147: ireturn
     148: iinc          4, 1
     151: goto          127
     154: getstatic     #37                 // Field allCodewordCapacities:[I
     157: getstatic     #37                 // Field allCodewordCapacities:[I
     160: arraylength
     161: iconst_1
     162: isub
     163: iaload
     164: ireturn

  int getCodewordsRemaining(int);
    Code:
       0: aload_0
       1: iload_1
       2: invokevirtual #38                 // Method getMinSymbolSize:(I)I
       5: iload_1
       6: isub
       7: ireturn

  static byte[] getBytes(int);
    Code:
       0: iconst_1
       1: newarray       byte
       3: astore_1
       4: aload_1
       5: iconst_0
       6: iload_0
       7: i2b
       8: bastore
       9: aload_1
      10: areturn

  static byte[] getBytes(int, int);
    Code:
       0: iconst_2
       1: newarray       byte
       3: astore_2
       4: aload_2
       5: iconst_0
       6: iload_0
       7: i2b
       8: bastore
       9: aload_2
      10: iconst_1
      11: iload_1
      12: i2b
      13: bastore
      14: aload_2
      15: areturn

  static void setC40Word(byte[], int, int, int, int);
    Code:
       0: sipush        1600
       3: iload_2
       4: sipush        255
       7: iand
       8: imul
       9: bipush        40
      11: iload_3
      12: sipush        255
      15: iand
      16: imul
      17: iadd
      18: iload         4
      20: sipush        255
      23: iand
      24: iadd
      25: iconst_1
      26: iadd
      27: istore        5
      29: aload_0
      30: iload_1
      31: iload         5
      33: sipush        256
      36: idiv
      37: i2b
      38: bastore
      39: aload_0
      40: iload_1
      41: iconst_1
      42: iadd
      43: iload         5
      45: sipush        256
      48: irem
      49: i2b
      50: bastore
      51: return

  private static int getX12Value(char);
    Code:
       0: iload_0
       1: bipush        13
       3: if_icmpne     10
       6: iconst_0
       7: goto          79
      10: iload_0
      11: bipush        42
      13: if_icmpne     20
      16: iconst_1
      17: goto          79
      20: iload_0
      21: bipush        62
      23: if_icmpne     30
      26: iconst_2
      27: goto          79
      30: iload_0
      31: bipush        32
      33: if_icmpne     40
      36: iconst_3
      37: goto          79
      40: iload_0
      41: bipush        48
      43: if_icmplt     59
      46: iload_0
      47: bipush        57
      49: if_icmpgt     59
      52: iload_0
      53: bipush        44
      55: isub
      56: goto          79
      59: iload_0
      60: bipush        65
      62: if_icmplt     78
      65: iload_0
      66: bipush        90
      68: if_icmpgt     78
      71: iload_0
      72: bipush        51
      74: isub
      75: goto          79
      78: iload_0
      79: ireturn

  byte[] getX12Words();
    Code:
       0: getstatic     #9                  // Field $assertionsDisabled:Z
       3: ifne          23
       6: aload_0
       7: getfield      #6                  // Field characterLength:I
      10: iconst_3
      11: irem
      12: ifeq          23
      15: new           #11                 // class java/lang/AssertionError
      18: dup
      19: invokespecial #12                 // Method java/lang/AssertionError."<init>":()V
      22: athrow
      23: aload_0
      24: getfield      #6                  // Field characterLength:I
      27: iconst_3
      28: idiv
      29: iconst_2
      30: imul
      31: newarray       byte
      33: astore_1
      34: iconst_0
      35: istore_2
      36: iload_2
      37: aload_1
      38: arraylength
      39: if_icmpge     117
      42: aload_1
      43: iload_2
      44: aload_0
      45: getfield      #3                  // Field input:Lcom/google/zxing/datamatrix/encoder/MinimalEncoder$Input;
      48: aload_0
      49: getfield      #7                  // Field fromPosition:I
      52: iload_2
      53: iconst_2
      54: idiv
      55: iconst_3
      56: imul
      57: iadd
      58: invokevirtual #17                 // Method com/google/zxing/datamatrix/encoder/MinimalEncoder$Input.charAt:(I)C
      61: invokestatic  #39                 // Method getX12Value:(C)I
      64: aload_0
      65: getfield      #3                  // Field input:Lcom/google/zxing/datamatrix/encoder/MinimalEncoder$Input;
      68: aload_0
      69: getfield      #7                  // Field fromPosition:I
      72: iload_2
      73: iconst_2
      74: idiv
      75: iconst_3
      76: imul
      77: iadd
      78: iconst_1
      79: iadd
      80: invokevirtual #17                 // Method com/google/zxing/datamatrix/encoder/MinimalEncoder$Input.charAt:(I)C
      83: invokestatic  #39                 // Method getX12Value:(C)I
      86: aload_0
      87: getfield      #3                  // Field input:Lcom/google/zxing/datamatrix/encoder/MinimalEncoder$Input;
      90: aload_0
      91: getfield      #7                  // Field fromPosition:I
      94: iload_2
      95: iconst_2
      96: idiv
      97: iconst_3
      98: imul
      99: iadd
     100: iconst_2
     101: iadd
     102: invokevirtual #17                 // Method com/google/zxing/datamatrix/encoder/MinimalEncoder$Input.charAt:(I)C
     105: invokestatic  #39                 // Method getX12Value:(C)I
     108: invokestatic  #40                 // Method setC40Word:([BIIII)V
     111: iinc          2, 2
     114: goto          36
     117: aload_1
     118: areturn

  static int getShiftValue(char, boolean, int);
    Code:
       0: iload_1
       1: ifeq          11
       4: iload_0
       5: invokestatic  #41                 // Method com/google/zxing/datamatrix/encoder/MinimalEncoder.access$600:(C)Z
       8: ifne          22
      11: iload_1
      12: ifne          26
      15: iload_0
      16: invokestatic  #42                 // Method com/google/zxing/datamatrix/encoder/MinimalEncoder.access$700:(C)Z
      19: ifeq          26
      22: iconst_0
      23: goto          55
      26: iload_1
      27: ifeq          38
      30: iload_0
      31: iload_2
      32: invokestatic  #43                 // Method com/google/zxing/datamatrix/encoder/MinimalEncoder.access$800:(CI)Z
      35: ifne          50
      38: iload_1
      39: ifne          54
      42: iload_0
      43: iload_2
      44: invokestatic  #44                 // Method com/google/zxing/datamatrix/encoder/MinimalEncoder.access$900:(CI)Z
      47: ifeq          54
      50: iconst_1
      51: goto          55
      54: iconst_2
      55: ireturn

  private static int getC40Value(boolean, int, char, int);
    Code:
       0: iload_2
       1: iload_3
       2: if_icmpne     27
       5: getstatic     #9                  // Field $assertionsDisabled:Z
       8: ifne          24
      11: iload_1
      12: iconst_2
      13: if_icmpeq     24
      16: new           #11                 // class java/lang/AssertionError
      19: dup
      20: invokespecial #12                 // Method java/lang/AssertionError."<init>":()V
      23: athrow
      24: bipush        27
      26: ireturn
      27: iload_0
      28: ifeq          131
      31: iload_2
      32: bipush        31
      34: if_icmpgt     41
      37: iload_2
      38: goto          130
      41: iload_2
      42: bipush        32
      44: if_icmpne     51
      47: iconst_3
      48: goto          130
      51: iload_2
      52: bipush        47
      54: if_icmpgt     64
      57: iload_2
      58: bipush        33
      60: isub
      61: goto          130
      64: iload_2
      65: bipush        57
      67: if_icmpgt     77
      70: iload_2
      71: bipush        44
      73: isub
      74: goto          130
      77: iload_2
      78: bipush        64
      80: if_icmpgt     90
      83: iload_2
      84: bipush        43
      86: isub
      87: goto          130
      90: iload_2
      91: bipush        90
      93: if_icmpgt     103
      96: iload_2
      97: bipush        51
      99: isub
     100: goto          130
     103: iload_2
     104: bipush        95
     106: if_icmpgt     116
     109: iload_2
     110: bipush        69
     112: isub
     113: goto          130
     116: iload_2
     117: bipush        127
     119: if_icmpgt     129
     122: iload_2
     123: bipush        96
     125: isub
     126: goto          130
     129: iload_2
     130: ireturn
     131: iload_2
     132: ifne          139
     135: iconst_0
     136: goto          323
     139: iload_1
     140: ifne          154
     143: iload_2
     144: iconst_3
     145: if_icmpgt     154
     148: iload_2
     149: iconst_1
     150: isub
     151: goto          323
     154: iload_1
     155: iconst_1
     156: if_icmpne     169
     159: iload_2
     160: bipush        31
     162: if_icmpgt     169
     165: iload_2
     166: goto          323
     169: iload_2
     170: bipush        32
     172: if_icmpne     179
     175: iconst_3
     176: goto          323
     179: iload_2
     180: bipush        33
     182: if_icmplt     198
     185: iload_2
     186: bipush        47
     188: if_icmpgt     198
     191: iload_2
     192: bipush        33
     194: isub
     195: goto          323
     198: iload_2
     199: bipush        48
     201: if_icmplt     217
     204: iload_2
     205: bipush        57
     207: if_icmpgt     217
     210: iload_2
     211: bipush        44
     213: isub
     214: goto          323
     217: iload_2
     218: bipush        58
     220: if_icmplt     236
     223: iload_2
     224: bipush        64
     226: if_icmpgt     236
     229: iload_2
     230: bipush        43
     232: isub
     233: goto          323
     236: iload_2
     237: bipush        65
     239: if_icmplt     255
     242: iload_2
     243: bipush        90
     245: if_icmpgt     255
     248: iload_2
     249: bipush        64
     251: isub
     252: goto          323
     255: iload_2
     256: bipush        91
     258: if_icmplt     274
     261: iload_2
     262: bipush        95
     264: if_icmpgt     274
     267: iload_2
     268: bipush        69
     270: isub
     271: goto          323
     274: iload_2
     275: bipush        96
     277: if_icmpne     284
     280: iconst_0
     281: goto          323
     284: iload_2
     285: bipush        97
     287: if_icmplt     303
     290: iload_2
     291: bipush        122
     293: if_icmpgt     303
     296: iload_2
     297: bipush        83
     299: isub
     300: goto          323
     303: iload_2
     304: bipush        123
     306: if_icmplt     322
     309: iload_2
     310: bipush        127
     312: if_icmpgt     322
     315: iload_2
     316: bipush        96
     318: isub
     319: goto          323
     322: iload_2
     323: ireturn

  byte[] getC40Words(boolean, int);
    Code:
       0: new           #45                 // class java/util/ArrayList
       3: dup
       4: invokespecial #46                 // Method java/util/ArrayList."<init>":()V
       7: astore_3
       8: iconst_0
       9: istore        4
      11: iload         4
      13: aload_0
      14: getfield      #6                  // Field characterLength:I
      17: if_icmpge     289
      20: aload_0
      21: getfield      #3                  // Field input:Lcom/google/zxing/datamatrix/encoder/MinimalEncoder$Input;
      24: aload_0
      25: getfield      #7                  // Field fromPosition:I
      28: iload         4
      30: iadd
      31: invokevirtual #17                 // Method com/google/zxing/datamatrix/encoder/MinimalEncoder$Input.charAt:(I)C
      34: istore        5
      36: iload_1
      37: ifeq          48
      40: iload         5
      42: invokestatic  #47                 // Method com/google/zxing/datamatrix/encoder/HighLevelEncoder.isNativeC40:(C)Z
      45: ifne          60
      48: iload_1
      49: ifne          82
      52: iload         5
      54: invokestatic  #48                 // Method com/google/zxing/datamatrix/encoder/HighLevelEncoder.isNativeText:(C)Z
      57: ifeq          82
      60: aload_3
      61: iload_1
      62: iconst_0
      63: iload         5
      65: iload_2
      66: invokestatic  #49                 // Method getC40Value:(ZICI)I
      69: i2b
      70: invokestatic  #50                 // Method java/lang/Byte.valueOf:(B)Ljava/lang/Byte;
      73: invokeinterface #51,  2           // InterfaceMethod java/util/List.add:(Ljava/lang/Object;)Z
      78: pop
      79: goto          283
      82: iload         5
      84: iload_2
      85: invokestatic  #19                 // Method com/google/zxing/datamatrix/encoder/MinimalEncoder.isExtendedASCII:(CI)Z
      88: ifne          136
      91: iload         5
      93: iload_1
      94: iload_2
      95: invokestatic  #52                 // Method getShiftValue:(CZI)I
      98: istore        6
     100: aload_3
     101: iload         6
     103: i2b
     104: invokestatic  #50                 // Method java/lang/Byte.valueOf:(B)Ljava/lang/Byte;
     107: invokeinterface #51,  2           // InterfaceMethod java/util/List.add:(Ljava/lang/Object;)Z
     112: pop
     113: aload_3
     114: iload_1
     115: iload         6
     117: iload         5
     119: iload_2
     120: invokestatic  #49                 // Method getC40Value:(ZICI)I
     123: i2b
     124: invokestatic  #50                 // Method java/lang/Byte.valueOf:(B)Ljava/lang/Byte;
     127: invokeinterface #51,  2           // InterfaceMethod java/util/List.add:(Ljava/lang/Object;)Z
     132: pop
     133: goto          283
     136: iload         5
     138: sipush        255
     141: iand
     142: sipush        128
     145: isub
     146: i2c
     147: istore        6
     149: iload_1
     150: ifeq          161
     153: iload         6
     155: invokestatic  #47                 // Method com/google/zxing/datamatrix/encoder/HighLevelEncoder.isNativeC40:(C)Z
     158: ifne          173
     161: iload_1
     162: ifne          218
     165: iload         6
     167: invokestatic  #48                 // Method com/google/zxing/datamatrix/encoder/HighLevelEncoder.isNativeText:(C)Z
     170: ifeq          218
     173: aload_3
     174: iconst_1
     175: invokestatic  #50                 // Method java/lang/Byte.valueOf:(B)Ljava/lang/Byte;
     178: invokeinterface #51,  2           // InterfaceMethod java/util/List.add:(Ljava/lang/Object;)Z
     183: pop
     184: aload_3
     185: bipush        30
     187: invokestatic  #50                 // Method java/lang/Byte.valueOf:(B)Ljava/lang/Byte;
     190: invokeinterface #51,  2           // InterfaceMethod java/util/List.add:(Ljava/lang/Object;)Z
     195: pop
     196: aload_3
     197: iload_1
     198: iconst_0
     199: iload         6
     201: iload_2
     202: invokestatic  #49                 // Method getC40Value:(ZICI)I
     205: i2b
     206: invokestatic  #50                 // Method java/lang/Byte.valueOf:(B)Ljava/lang/Byte;
     209: invokeinterface #51,  2           // InterfaceMethod java/util/List.add:(Ljava/lang/Object;)Z
     214: pop
     215: goto          283
     218: aload_3
     219: iconst_1
     220: invokestatic  #50                 // Method java/lang/Byte.valueOf:(B)Ljava/lang/Byte;
     223: invokeinterface #51,  2           // InterfaceMethod java/util/List.add:(Ljava/lang/Object;)Z
     228: pop
     229: aload_3
     230: bipush        30
     232: invokestatic  #50                 // Method java/lang/Byte.valueOf:(B)Ljava/lang/Byte;
     235: invokeinterface #51,  2           // InterfaceMethod java/util/List.add:(Ljava/lang/Object;)Z
     240: pop
     241: iload         6
     243: iload_1
     244: iload_2
     245: invokestatic  #52                 // Method getShiftValue:(CZI)I
     248: istore        7
     250: aload_3
     251: iload         7
     253: i2b
     254: invokestatic  #50                 // Method java/lang/Byte.valueOf:(B)Ljava/lang/Byte;
     257: invokeinterface #51,  2           // InterfaceMethod java/util/List.add:(Ljava/lang/Object;)Z
     262: pop
     263: aload_3
     264: iload_1
     265: iload         7
     267: iload         6
     269: iload_2
     270: invokestatic  #49                 // Method getC40Value:(ZICI)I
     273: i2b
     274: invokestatic  #50                 // Method java/lang/Byte.valueOf:(B)Ljava/lang/Byte;
     277: invokeinterface #51,  2           // InterfaceMethod java/util/List.add:(Ljava/lang/Object;)Z
     282: pop
     283: iinc          4, 1
     286: goto          11
     289: aload_3
     290: invokeinterface #53,  1           // InterfaceMethod java/util/List.size:()I
     295: iconst_3
     296: irem
     297: ifeq          357
     300: getstatic     #9                  // Field $assertionsDisabled:Z
     303: ifne          346
     306: aload_3
     307: invokeinterface #53,  1           // InterfaceMethod java/util/List.size:()I
     312: iconst_2
     313: isub
     314: iconst_3
     315: irem
     316: ifne          338
     319: aload_0
     320: getfield      #7                  // Field fromPosition:I
     323: aload_0
     324: getfield      #6                  // Field characterLength:I
     327: iadd
     328: aload_0
     329: getfield      #3                  // Field input:Lcom/google/zxing/datamatrix/encoder/MinimalEncoder$Input;
     332: invokevirtual #10                 // Method com/google/zxing/datamatrix/encoder/MinimalEncoder$Input.length:()I
     335: if_icmpeq     346
     338: new           #11                 // class java/lang/AssertionError
     341: dup
     342: invokespecial #12                 // Method java/lang/AssertionError."<init>":()V
     345: athrow
     346: aload_3
     347: iconst_0
     348: invokestatic  #50                 // Method java/lang/Byte.valueOf:(B)Ljava/lang/Byte;
     351: invokeinterface #51,  2           // InterfaceMethod java/util/List.add:(Ljava/lang/Object;)Z
     356: pop
     357: aload_3
     358: invokeinterface #53,  1           // InterfaceMethod java/util/List.size:()I
     363: iconst_3
     364: idiv
     365: iconst_2
     366: imul
     367: newarray       byte
     369: astore        4
     371: iconst_0
     372: istore        5
     374: iconst_0
     375: istore        6
     377: iload         6
     379: aload_3
     380: invokeinterface #53,  1           // InterfaceMethod java/util/List.size:()I
     385: if_icmpge     462
     388: aload         4
     390: iload         5
     392: aload_3
     393: iload         6
     395: invokeinterface #54,  2           // InterfaceMethod java/util/List.get:(I)Ljava/lang/Object;
     400: checkcast     #55                 // class java/lang/Byte
     403: invokevirtual #56                 // Method java/lang/Byte.byteValue:()B
     406: sipush        255
     409: iand
     410: aload_3
     411: iload         6
     413: iconst_1
     414: iadd
     415: invokeinterface #54,  2           // InterfaceMethod java/util/List.get:(I)Ljava/lang/Object;
     420: checkcast     #55                 // class java/lang/Byte
     423: invokevirtual #56                 // Method java/lang/Byte.byteValue:()B
     426: sipush        255
     429: iand
     430: aload_3
     431: iload         6
     433: iconst_2
     434: iadd
     435: invokeinterface #54,  2           // InterfaceMethod java/util/List.get:(I)Ljava/lang/Object;
     440: checkcast     #55                 // class java/lang/Byte
     443: invokevirtual #56                 // Method java/lang/Byte.byteValue:()B
     446: sipush        255
     449: iand
     450: invokestatic  #40                 // Method setC40Word:([BIIII)V
     453: iinc          5, 2
     456: iinc          6, 3
     459: goto          377
     462: aload         4
     464: areturn

  byte[] getEDFBytes();
    Code:
       0: aload_0
       1: getfield      #6                  // Field characterLength:I
       4: i2d
       5: ldc2_w        #57                 // double 4.0d
       8: ddiv
       9: invokestatic  #59                 // Method java/lang/Math.ceil:(D)D
      12: d2i
      13: istore_1
      14: iload_1
      15: iconst_3
      16: imul
      17: newarray       byte
      19: astore_2
      20: aload_0
      21: getfield      #7                  // Field fromPosition:I
      24: istore_3
      25: aload_0
      26: getfield      #7                  // Field fromPosition:I
      29: aload_0
      30: getfield      #6                  // Field characterLength:I
      33: iadd
      34: iconst_1
      35: isub
      36: aload_0
      37: getfield      #3                  // Field input:Lcom/google/zxing/datamatrix/encoder/MinimalEncoder$Input;
      40: invokevirtual #10                 // Method com/google/zxing/datamatrix/encoder/MinimalEncoder$Input.length:()I
      43: iconst_1
      44: isub
      45: invokestatic  #60                 // Method java/lang/Math.min:(II)I
      48: istore        4
      50: iconst_0
      51: istore        5
      53: iload         5
      55: iload_1
      56: if_icmpge     217
      59: iconst_4
      60: newarray       int
      62: astore        6
      64: iconst_0
      65: istore        7
      67: iload         7
      69: iconst_4
      70: if_icmpge     126
      73: iload_3
      74: iload         4
      76: if_icmpgt     101
      79: aload         6
      81: iload         7
      83: aload_0
      84: getfield      #3                  // Field input:Lcom/google/zxing/datamatrix/encoder/MinimalEncoder$Input;
      87: iload_3
      88: iinc          3, 1
      91: invokevirtual #17                 // Method com/google/zxing/datamatrix/encoder/MinimalEncoder$Input.charAt:(I)C
      94: bipush        63
      96: iand
      97: iastore
      98: goto          120
     101: aload         6
     103: iload         7
     105: iload_3
     106: iload         4
     108: iconst_1
     109: iadd
     110: if_icmpne     118
     113: bipush        31
     115: goto          119
     118: iconst_0
     119: iastore
     120: iinc          7, 1
     123: goto          67
     126: aload         6
     128: iconst_0
     129: iaload
     130: bipush        18
     132: ishl
     133: istore        7
     135: iload         7
     137: aload         6
     139: iconst_1
     140: iaload
     141: bipush        12
     143: ishl
     144: ior
     145: istore        7
     147: iload         7
     149: aload         6
     151: iconst_2
     152: iaload
     153: bipush        6
     155: ishl
     156: ior
     157: istore        7
     159: iload         7
     161: aload         6
     163: iconst_3
     164: iaload
     165: ior
     166: istore        7
     168: aload_2
     169: iload         5
     171: iload         7
     173: bipush        16
     175: ishr
     176: sipush        255
     179: iand
     180: i2b
     181: bastore
     182: aload_2
     183: iload         5
     185: iconst_1
     186: iadd
     187: iload         7
     189: bipush        8
     191: ishr
     192: sipush        255
     195: iand
     196: i2b
     197: bastore
     198: aload_2
     199: iload         5
     201: iconst_2
     202: iadd
     203: iload         7
     205: sipush        255
     208: iand
     209: i2b
     210: bastore
     211: iinc          5, 3
     214: goto          53
     217: aload_2
     218: areturn

  byte[] getLatchBytes();
    Code:
       0: getstatic     #14                 // Field com/google/zxing/datamatrix/encoder/MinimalEncoder$1.$SwitchMap$com$google$zxing$datamatrix$encoder$MinimalEncoder$Mode:[I
       3: aload_0
       4: invokevirtual #13                 // Method getPreviousMode:()Lcom/google/zxing/datamatrix/encoder/MinimalEncoder$Mode;
       7: invokevirtual #15                 // Method com/google/zxing/datamatrix/encoder/MinimalEncoder$Mode.ordinal:()I
      10: iaload
      11: tableswitch   { // 1 to 6
                     1: 48
                     2: 48
                     3: 130
                     4: 130
                     5: 130
                     6: 252
               default: 276
          }
      48: getstatic     #14                 // Field com/google/zxing/datamatrix/encoder/MinimalEncoder$1.$SwitchMap$com$google$zxing$datamatrix$encoder$MinimalEncoder$Mode:[I
      51: aload_0
      52: getfield      #2                  // Field mode:Lcom/google/zxing/datamatrix/encoder/MinimalEncoder$Mode;
      55: invokevirtual #15                 // Method com/google/zxing/datamatrix/encoder/MinimalEncoder$Mode.ordinal:()I
      58: iaload
      59: tableswitch   { // 2 to 6
                     2: 92
                     3: 99
                     4: 106
                     5: 113
                     6: 120
               default: 127
          }
      92: sipush        231
      95: invokestatic  #61                 // Method getBytes:(I)[B
      98: areturn
      99: sipush        230
     102: invokestatic  #61                 // Method getBytes:(I)[B
     105: areturn
     106: sipush        239
     109: invokestatic  #61                 // Method getBytes:(I)[B
     112: areturn
     113: sipush        238
     116: invokestatic  #61                 // Method getBytes:(I)[B
     119: areturn
     120: sipush        240
     123: invokestatic  #61                 // Method getBytes:(I)[B
     126: areturn
     127: goto          276
     130: aload_0
     131: getfield      #2                  // Field mode:Lcom/google/zxing/datamatrix/encoder/MinimalEncoder$Mode;
     134: aload_0
     135: invokevirtual #13                 // Method getPreviousMode:()Lcom/google/zxing/datamatrix/encoder/MinimalEncoder$Mode;
     138: if_acmpeq     276
     141: getstatic     #14                 // Field com/google/zxing/datamatrix/encoder/MinimalEncoder$1.$SwitchMap$com$google$zxing$datamatrix$encoder$MinimalEncoder$Mode:[I
     144: aload_0
     145: getfield      #2                  // Field mode:Lcom/google/zxing/datamatrix/encoder/MinimalEncoder$Mode;
     148: invokevirtual #15                 // Method com/google/zxing/datamatrix/encoder/MinimalEncoder$Mode.ordinal:()I
     151: iaload
     152: tableswitch   { // 1 to 6
                     1: 192
                     2: 199
                     3: 209
                     4: 219
                     5: 229
                     6: 239
               default: 249
          }
     192: sipush        254
     195: invokestatic  #61                 // Method getBytes:(I)[B
     198: areturn
     199: sipush        254
     202: sipush        231
     205: invokestatic  #62                 // Method getBytes:(II)[B
     208: areturn
     209: sipush        254
     212: sipush        230
     215: invokestatic  #62                 // Method getBytes:(II)[B
     218: areturn
     219: sipush        254
     222: sipush        239
     225: invokestatic  #62                 // Method getBytes:(II)[B
     228: areturn
     229: sipush        254
     232: sipush        238
     235: invokestatic  #62                 // Method getBytes:(II)[B
     238: areturn
     239: sipush        254
     242: sipush        240
     245: invokestatic  #62                 // Method getBytes:(II)[B
     248: areturn
     249: goto          276
     252: getstatic     #9                  // Field $assertionsDisabled:Z
     255: ifne          276
     258: aload_0
     259: getfield      #2                  // Field mode:Lcom/google/zxing/datamatrix/encoder/MinimalEncoder$Mode;
     262: getstatic     #28                 // Field com/google/zxing/datamatrix/encoder/MinimalEncoder$Mode.EDF:Lcom/google/zxing/datamatrix/encoder/MinimalEncoder$Mode;
     265: if_acmpeq     276
     268: new           #11                 // class java/lang/AssertionError
     271: dup
     272: invokespecial #12                 // Method java/lang/AssertionError."<init>":()V
     275: athrow
     276: iconst_0
     277: newarray       byte
     279: areturn

  byte[] getDataBytes();
    Code:
       0: getstatic     #14                 // Field com/google/zxing/datamatrix/encoder/MinimalEncoder$1.$SwitchMap$com$google$zxing$datamatrix$encoder$MinimalEncoder$Mode:[I
       3: aload_0
       4: getfield      #2                  // Field mode:Lcom/google/zxing/datamatrix/encoder/MinimalEncoder$Mode;
       7: invokevirtual #15                 // Method com/google/zxing/datamatrix/encoder/MinimalEncoder$Mode.ordinal:()I
      10: iaload
      11: tableswitch   { // 1 to 6
                     1: 48
                     2: 215
                     3: 230
                     4: 243
                     5: 256
                     6: 261
               default: 266
          }
      48: aload_0
      49: getfield      #3                  // Field input:Lcom/google/zxing/datamatrix/encoder/MinimalEncoder$Input;
      52: aload_0
      53: getfield      #7                  // Field fromPosition:I
      56: invokevirtual #16                 // Method com/google/zxing/datamatrix/encoder/MinimalEncoder$Input.isECI:(I)Z
      59: ifeq          82
      62: sipush        241
      65: aload_0
      66: getfield      #3                  // Field input:Lcom/google/zxing/datamatrix/encoder/MinimalEncoder$Input;
      69: aload_0
      70: getfield      #7                  // Field fromPosition:I
      73: invokevirtual #63                 // Method com/google/zxing/datamatrix/encoder/MinimalEncoder$Input.getECIValue:(I)I
      76: iconst_1
      77: iadd
      78: invokestatic  #62                 // Method getBytes:(II)[B
      81: areturn
      82: aload_0
      83: getfield      #3                  // Field input:Lcom/google/zxing/datamatrix/encoder/MinimalEncoder$Input;
      86: aload_0
      87: getfield      #7                  // Field fromPosition:I
      90: invokevirtual #17                 // Method com/google/zxing/datamatrix/encoder/MinimalEncoder$Input.charAt:(I)C
      93: aload_0
      94: getfield      #3                  // Field input:Lcom/google/zxing/datamatrix/encoder/MinimalEncoder$Input;
      97: invokevirtual #18                 // Method com/google/zxing/datamatrix/encoder/MinimalEncoder$Input.getFNC1Character:()I
     100: invokestatic  #19                 // Method com/google/zxing/datamatrix/encoder/MinimalEncoder.isExtendedASCII:(CI)Z
     103: ifeq          127
     106: sipush        235
     109: aload_0
     110: getfield      #3                  // Field input:Lcom/google/zxing/datamatrix/encoder/MinimalEncoder$Input;
     113: aload_0
     114: getfield      #7                  // Field fromPosition:I
     117: invokevirtual #17                 // Method com/google/zxing/datamatrix/encoder/MinimalEncoder$Input.charAt:(I)C
     120: bipush        127
     122: isub
     123: invokestatic  #62                 // Method getBytes:(II)[B
     126: areturn
     127: aload_0
     128: getfield      #6                  // Field characterLength:I
     131: iconst_2
     132: if_icmpne     177
     135: aload_0
     136: getfield      #3                  // Field input:Lcom/google/zxing/datamatrix/encoder/MinimalEncoder$Input;
     139: aload_0
     140: getfield      #7                  // Field fromPosition:I
     143: invokevirtual #17                 // Method com/google/zxing/datamatrix/encoder/MinimalEncoder$Input.charAt:(I)C
     146: bipush        48
     148: isub
     149: bipush        10
     151: imul
     152: aload_0
     153: getfield      #3                  // Field input:Lcom/google/zxing/datamatrix/encoder/MinimalEncoder$Input;
     156: aload_0
     157: getfield      #7                  // Field fromPosition:I
     160: iconst_1
     161: iadd
     162: invokevirtual #17                 // Method com/google/zxing/datamatrix/encoder/MinimalEncoder$Input.charAt:(I)C
     165: iadd
     166: bipush        48
     168: isub
     169: sipush        130
     172: iadd
     173: invokestatic  #61                 // Method getBytes:(I)[B
     176: areturn
     177: aload_0
     178: getfield      #3                  // Field input:Lcom/google/zxing/datamatrix/encoder/MinimalEncoder$Input;
     181: aload_0
     182: getfield      #7                  // Field fromPosition:I
     185: invokevirtual #64                 // Method com/google/zxing/datamatrix/encoder/MinimalEncoder$Input.isFNC1:(I)Z
     188: ifeq          198
     191: sipush        232
     194: invokestatic  #61                 // Method getBytes:(I)[B
     197: areturn
     198: aload_0
     199: getfield      #3                  // Field input:Lcom/google/zxing/datamatrix/encoder/MinimalEncoder$Input;
     202: aload_0
     203: getfield      #7                  // Field fromPosition:I
     206: invokevirtual #17                 // Method com/google/zxing/datamatrix/encoder/MinimalEncoder$Input.charAt:(I)C
     209: iconst_1
     210: iadd
     211: invokestatic  #61                 // Method getBytes:(I)[B
     214: areturn
     215: aload_0
     216: getfield      #3                  // Field input:Lcom/google/zxing/datamatrix/encoder/MinimalEncoder$Input;
     219: aload_0
     220: getfield      #7                  // Field fromPosition:I
     223: invokevirtual #17                 // Method com/google/zxing/datamatrix/encoder/MinimalEncoder$Input.charAt:(I)C
     226: invokestatic  #61                 // Method getBytes:(I)[B
     229: areturn
     230: aload_0
     231: iconst_1
     232: aload_0
     233: getfield      #3                  // Field input:Lcom/google/zxing/datamatrix/encoder/MinimalEncoder$Input;
     236: invokevirtual #18                 // Method com/google/zxing/datamatrix/encoder/MinimalEncoder$Input.getFNC1Character:()I
     239: invokevirtual #65                 // Method getC40Words:(ZI)[B
     242: areturn
     243: aload_0
     244: iconst_0
     245: aload_0
     246: getfield      #3                  // Field input:Lcom/google/zxing/datamatrix/encoder/MinimalEncoder$Input;
     249: invokevirtual #18                 // Method com/google/zxing/datamatrix/encoder/MinimalEncoder$Input.getFNC1Character:()I
     252: invokevirtual #65                 // Method getC40Words:(ZI)[B
     255: areturn
     256: aload_0
     257: invokevirtual #66                 // Method getX12Words:()[B
     260: areturn
     261: aload_0
     262: invokevirtual #67                 // Method getEDFBytes:()[B
     265: areturn
     266: getstatic     #9                  // Field $assertionsDisabled:Z
     269: ifne          280
     272: new           #11                 // class java/lang/AssertionError
     275: dup
     276: invokespecial #12                 // Method java/lang/AssertionError."<init>":()V
     279: athrow
     280: iconst_0
     281: newarray       byte
     283: areturn

  static int access$100(com.google.zxing.datamatrix.encoder.MinimalEncoder$Edge);
    Code:
       0: aload_0
       1: getfield      #7                  // Field fromPosition:I
       4: ireturn

  static int access$200(com.google.zxing.datamatrix.encoder.MinimalEncoder$Edge);
    Code:
       0: aload_0
       1: getfield      #6                  // Field characterLength:I
       4: ireturn

  static int access$300(com.google.zxing.datamatrix.encoder.MinimalEncoder$Edge);
    Code:
       0: aload_0
       1: getfield      #5                  // Field cachedTotalSize:I
       4: ireturn

  com.google.zxing.datamatrix.encoder.MinimalEncoder$Edge(com.google.zxing.datamatrix.encoder.MinimalEncoder$Input, com.google.zxing.datamatrix.encoder.MinimalEncoder$Mode, int, int, com.google.zxing.datamatrix.encoder.MinimalEncoder$Edge, com.google.zxing.datamatrix.encoder.MinimalEncoder$1);
    Code:
       0: aload_0
       1: aload_1
       2: aload_2
       3: iload_3
       4: iload         4
       6: aload         5
       8: invokespecial #4                  // Method "<init>":(Lcom/google/zxing/datamatrix/encoder/MinimalEncoder$Input;Lcom/google/zxing/datamatrix/encoder/MinimalEncoder$Mode;IILcom/google/zxing/datamatrix/encoder/MinimalEncoder$Edge;)V
      11: return

  static com.google.zxing.datamatrix.encoder.MinimalEncoder$Input access$1000(com.google.zxing.datamatrix.encoder.MinimalEncoder$Edge);
    Code:
       0: aload_0
       1: getfield      #3                  // Field input:Lcom/google/zxing/datamatrix/encoder/MinimalEncoder$Input;
       4: areturn

  static com.google.zxing.datamatrix.encoder.MinimalEncoder$Mode access$1100(com.google.zxing.datamatrix.encoder.MinimalEncoder$Edge);
    Code:
       0: aload_0
       1: getfield      #2                  // Field mode:Lcom/google/zxing/datamatrix/encoder/MinimalEncoder$Mode;
       4: areturn

  static com.google.zxing.datamatrix.encoder.MinimalEncoder$Edge access$1200(com.google.zxing.datamatrix.encoder.MinimalEncoder$Edge);
    Code:
       0: aload_0
       1: getfield      #1                  // Field previous:Lcom/google/zxing/datamatrix/encoder/MinimalEncoder$Edge;
       4: areturn

  static {};
    Code:
       0: ldc           #68                 // class com/google/zxing/datamatrix/encoder/MinimalEncoder
       2: invokevirtual #69                 // Method java/lang/Class.desiredAssertionStatus:()Z
       5: ifne          12
       8: iconst_1
       9: goto          13
      12: iconst_0
      13: putstatic     #9                  // Field $assertionsDisabled:Z
      16: bipush        28
      18: newarray       int
      20: dup
      21: iconst_0
      22: iconst_3
      23: iastore
      24: dup
      25: iconst_1
      26: iconst_5
      27: iastore
      28: dup
      29: iconst_2
      30: bipush        8
      32: iastore
      33: dup
      34: iconst_3
      35: bipush        10
      37: iastore
      38: dup
      39: iconst_4
      40: bipush        12
      42: iastore
      43: dup
      44: iconst_5
      45: bipush        16
      47: iastore
      48: dup
      49: bipush        6
      51: bipush        18
      53: iastore
      54: dup
      55: bipush        7
      57: bipush        22
      59: iastore
      60: dup
      61: bipush        8
      63: bipush        30
      65: iastore
      66: dup
      67: bipush        9
      69: bipush        32
      71: iastore
      72: dup
      73: bipush        10
      75: bipush        36
      77: iastore
      78: dup
      79: bipush        11
      81: bipush        44
      83: iastore
      84: dup
      85: bipush        12
      87: bipush        49
      89: iastore
      90: dup
      91: bipush        13
      93: bipush        62
      95: iastore
      96: dup
      97: bipush        14
      99: bipush        86
     101: iastore
     102: dup
     103: bipush        15
     105: bipush        114
     107: iastore
     108: dup
     109: bipush        16
     111: sipush        144
     114: iastore
     115: dup
     116: bipush        17
     118: sipush        174
     121: iastore
     122: dup
     123: bipush        18
     125: sipush        204
     128: iastore
     129: dup
     130: bipush        19
     132: sipush        280
     135: iastore
     136: dup
     137: bipush        20
     139: sipush        368
     142: iastore
     143: dup
     144: bipush        21
     146: sipush        456
     149: iastore
     150: dup
     151: bipush        22
     153: sipush        576
     156: iastore
     157: dup
     158: bipush        23
     160: sipush        696
     163: iastore
     164: dup
     165: bipush        24
     167: sipush        816
     170: iastore
     171: dup
     172: bipush        25
     174: sipush        1050
     177: iastore
     178: dup
     179: bipush        26
     181: sipush        1304
     184: iastore
     185: dup
     186: bipush        27
     188: sipush        1558
     191: iastore
     192: putstatic     #37                 // Field allCodewordCapacities:[I
     195: bipush        24
     197: newarray       int
     199: dup
     200: iconst_0
     201: iconst_3
     202: iastore
     203: dup
     204: iconst_1
     205: iconst_5
     206: iastore
     207: dup
     208: iconst_2
     209: bipush        8
     211: iastore
     212: dup
     213: iconst_3
     214: bipush        12
     216: iastore
     217: dup
     218: iconst_4
     219: bipush        18
     221: iastore
     222: dup
     223: iconst_5
     224: bipush        22
     226: iastore
     227: dup
     228: bipush        6
     230: bipush        30
     232: iastore
     233: dup
     234: bipush        7
     236: bipush        36
     238: iastore
     239: dup
     240: bipush        8
     242: bipush        44
     244: iastore
     245: dup
     246: bipush        9
     248: bipush        62
     250: iastore
     251: dup
     252: bipush        10
     254: bipush        86
     256: iastore
     257: dup
     258: bipush        11
     260: bipush        114
     262: iastore
     263: dup
     264: bipush        12
     266: sipush        144
     269: iastore
     270: dup
     271: bipush        13
     273: sipush        174
     276: iastore
     277: dup
     278: bipush        14
     280: sipush        204
     283: iastore
     284: dup
     285: bipush        15
     287: sipush        280
     290: iastore
     291: dup
     292: bipush        16
     294: sipush        368
     297: iastore
     298: dup
     299: bipush        17
     301: sipush        456
     304: iastore
     305: dup
     306: bipush        18
     308: sipush        576
     311: iastore
     312: dup
     313: bipush        19
     315: sipush        696
     318: iastore
     319: dup
     320: bipush        20
     322: sipush        816
     325: iastore
     326: dup
     327: bipush        21
     329: sipush        1050
     332: iastore
     333: dup
     334: bipush        22
     336: sipush        1304
     339: iastore
     340: dup
     341: bipush        23
     343: sipush        1558
     346: iastore
     347: putstatic     #35                 // Field squareCodewordCapacities:[I
     350: bipush        6
     352: newarray       int
     354: dup
     355: iconst_0
     356: iconst_5
     357: iastore
     358: dup
     359: iconst_1
     360: bipush        10
     362: iastore
     363: dup
     364: iconst_2
     365: bipush        16
     367: iastore
     368: dup
     369: iconst_3
     370: bipush        33
     372: iastore
     373: dup
     374: iconst_4
     375: bipush        32
     377: iastore
     378: dup
     379: iconst_5
     380: bipush        49
     382: iastore
     383: putstatic     #36                 // Field rectangularCodewordCapacities:[I
     386: return
}
