Compiled from "MinimalEncoder.java"
class com.google.zxing.datamatrix.encoder.MinimalEncoder$1 {
  static final int[] $SwitchMap$com$google$zxing$datamatrix$encoder$MinimalEncoder$Mode;

  static final int[] $SwitchMap$com$google$zxing$datamatrix$encoder$SymbolShapeHint;

  static {};
    Code:
       0: invokestatic  #1                  // Method com/google/zxing/datamatrix/encoder/SymbolShapeHint.values:()[Lcom/google/zxing/datamatrix/encoder/SymbolShapeHint;
       3: arraylength
       4: newarray       int
       6: putstatic     #2                  // Field $SwitchMap$com$google$zxing$datamatrix$encoder$SymbolShapeHint:[I
       9: getstatic     #2                  // Field $SwitchMap$com$google$zxing$datamatrix$encoder$SymbolShapeHint:[I
      12: getstatic     #3                  // Field com/google/zxing/datamatrix/encoder/SymbolShapeHint.FORCE_SQUARE:Lcom/google/zxing/datamatrix/encoder/SymbolShapeHint;
      15: invokevirtual #4                  // Method com/google/zxing/datamatrix/encoder/SymbolShapeHint.ordinal:()I
      18: iconst_1
      19: iastore
      20: goto          24
      23: astore_0
      24: getstatic     #2                  // Field $SwitchMap$com$google$zxing$datamatrix$encoder$SymbolShapeHint:[I
      27: getstatic     #6                  // Field com/google/zxing/datamatrix/encoder/SymbolShapeHint.FORCE_RECTANGLE:Lcom/google/zxing/datamatrix/encoder/SymbolShapeHint;
      30: invokevirtual #4                  // Method com/google/zxing/datamatrix/encoder/SymbolShapeHint.ordinal:()I
      33: iconst_2
      34: iastore
      35: goto          39
      38: astore_0
      39: invokestatic  #7                  // Method com/google/zxing/datamatrix/encoder/MinimalEncoder$Mode.values:()[Lcom/google/zxing/datamatrix/encoder/MinimalEncoder$Mode;
      42: arraylength
      43: newarray       int
      45: putstatic     #8                  // Field $SwitchMap$com$google$zxing$datamatrix$encoder$MinimalEncoder$Mode:[I
      48: getstatic     #8                  // Field $SwitchMap$com$google$zxing$datamatrix$encoder$MinimalEncoder$Mode:[I
      51: getstatic     #9                  // Field com/google/zxing/datamatrix/encoder/MinimalEncoder$Mode.ASCII:Lcom/google/zxing/datamatrix/encoder/MinimalEncoder$Mode;
      54: invokevirtual #10                 // Method com/google/zxing/datamatrix/encoder/MinimalEncoder$Mode.ordinal:()I
      57: iconst_1
      58: iastore
      59: goto          63
      62: astore_0
      63: getstatic     #8                  // Field $SwitchMap$com$google$zxing$datamatrix$encoder$MinimalEncoder$Mode:[I
      66: getstatic     #11                 // Field com/google/zxing/datamatrix/encoder/MinimalEncoder$Mode.B256:Lcom/google/zxing/datamatrix/encoder/MinimalEncoder$Mode;
      69: invokevirtual #10                 // Method com/google/zxing/datamatrix/encoder/MinimalEncoder$Mode.ordinal:()I
      72: iconst_2
      73: iastore
      74: goto          78
      77: astore_0
      78: getstatic     #8                  // Field $SwitchMap$com$google$zxing$datamatrix$encoder$MinimalEncoder$Mode:[I
      81: getstatic     #12                 // Field com/google/zxing/datamatrix/encoder/MinimalEncoder$Mode.C40:Lcom/google/zxing/datamatrix/encoder/MinimalEncoder$Mode;
      84: invokevirtual #10                 // Method com/google/zxing/datamatrix/encoder/MinimalEncoder$Mode.ordinal:()I
      87: iconst_3
      88: iastore
      89: goto          93
      92: astore_0
      93: getstatic     #8                  // Field $SwitchMap$com$google$zxing$datamatrix$encoder$MinimalEncoder$Mode:[I
      96: getstatic     #13                 // Field com/google/zxing/datamatrix/encoder/MinimalEncoder$Mode.TEXT:Lcom/google/zxing/datamatrix/encoder/MinimalEncoder$Mode;
      99: invokevirtual #10                 // Method com/google/zxing/datamatrix/encoder/MinimalEncoder$Mode.ordinal:()I
     102: iconst_4
     103: iastore
     104: goto          108
     107: astore_0
     108: getstatic     #8                  // Field $SwitchMap$com$google$zxing$datamatrix$encoder$MinimalEncoder$Mode:[I
     111: getstatic     #14                 // Field com/google/zxing/datamatrix/encoder/MinimalEncoder$Mode.X12:Lcom/google/zxing/datamatrix/encoder/MinimalEncoder$Mode;
     114: invokevirtual #10                 // Method com/google/zxing/datamatrix/encoder/MinimalEncoder$Mode.ordinal:()I
     117: iconst_5
     118: iastore
     119: goto          123
     122: astore_0
     123: getstatic     #8                  // Field $SwitchMap$com$google$zxing$datamatrix$encoder$MinimalEncoder$Mode:[I
     126: getstatic     #15                 // Field com/google/zxing/datamatrix/encoder/MinimalEncoder$Mode.EDF:Lcom/google/zxing/datamatrix/encoder/MinimalEncoder$Mode;
     129: invokevirtual #10                 // Method com/google/zxing/datamatrix/encoder/MinimalEncoder$Mode.ordinal:()I
     132: bipush        6
     134: iastore
     135: goto          139
     138: astore_0
     139: return
    Exception table:
       from    to  target type
           9    20    23   Class java/lang/NoSuchFieldError
          24    35    38   Class java/lang/NoSuchFieldError
          48    59    62   Class java/lang/NoSuchFieldError
          63    74    77   Class java/lang/NoSuchFieldError
          78    89    92   Class java/lang/NoSuchFieldError
          93   104   107   Class java/lang/NoSuchFieldError
         108   119   122   Class java/lang/NoSuchFieldError
         123   135   138   Class java/lang/NoSuchFieldError
}
