Compiled from "MinimalEncoder.java"
final class com.google.zxing.datamatrix.encoder.MinimalEncoder$Input extends com.google.zxing.common.MinimalECIInput {
  private final com.google.zxing.datamatrix.encoder.SymbolShapeHint shape;

  private final int macroId;

  private com.google.zxing.datamatrix.encoder.MinimalEncoder$Input(java.lang.String, java.nio.charset.Charset, int, com.google.zxing.datamatrix.encoder.SymbolShapeHint, int);
    Code:
       0: aload_0
       1: aload_1
       2: aload_2
       3: iload_3
       4: invokespecial #4                  // Method com/google/zxing/common/MinimalECIInput."<init>":(Ljava/lang/String;Ljava/nio/charset/Charset;I)V
       7: aload_0
       8: aload         4
      10: putfield      #5                  // Field shape:Lcom/google/zxing/datamatrix/encoder/SymbolShapeHint;
      13: aload_0
      14: iload         5
      16: putfield      #6                  // Field macroId:I
      19: return

  private int getMacroId();
    Code:
       0: aload_0
       1: getfield      #6                  // Field macroId:I
       4: ireturn

  private com.google.zxing.datamatrix.encoder.SymbolShapeHint getShapeHint();
    Code:
       0: aload_0
       1: getfield      #5                  // Field shape:Lcom/google/zxing/datamatrix/encoder/SymbolShapeHint;
       4: areturn

  com.google.zxing.datamatrix.encoder.MinimalEncoder$Input(java.lang.String, java.nio.charset.Charset, int, com.google.zxing.datamatrix.encoder.SymbolShapeHint, int, com.google.zxing.datamatrix.encoder.MinimalEncoder$1);
    Code:
       0: aload_0
       1: aload_1
       2: aload_2
       3: iload_3
       4: aload         4
       6: iload         5
       8: invokespecial #3                  // Method "<init>":(Ljava/lang/String;Ljava/nio/charset/Charset;ILcom/google/zxing/datamatrix/encoder/SymbolShapeHint;I)V
      11: return

  static com.google.zxing.datamatrix.encoder.SymbolShapeHint access$500(com.google.zxing.datamatrix.encoder.MinimalEncoder$Input);
    Code:
       0: aload_0
       1: invokespecial #2                  // Method getShapeHint:()Lcom/google/zxing/datamatrix/encoder/SymbolShapeHint;
       4: areturn

  static int access$1300(com.google.zxing.datamatrix.encoder.MinimalEncoder$Input);
    Code:
       0: aload_0
       1: invokespecial #1                  // Method getMacroId:()I
       4: ireturn
}
