Compiled from "MinimalEncoder.java"
final class com.google.zxing.datamatrix.encoder.MinimalEncoder$Result {
  private final byte[] bytes;

  com.google.zxing.datamatrix.encoder.MinimalEncoder$Result(com.google.zxing.datamatrix.encoder.MinimalEncoder$Edge);
    Code:
       0: aload_0
       1: invokespecial #1                  // Method java/lang/Object."<init>":()V
       4: aload_1
       5: invokestatic  #2                  // Method com/google/zxing/datamatrix/encoder/MinimalEncoder$Edge.access$1000:(Lcom/google/zxing/datamatrix/encoder/MinimalEncoder$Edge;)Lcom/google/zxing/datamatrix/encoder/MinimalEncoder$Input;
       8: astore_2
       9: iconst_0
      10: istore_3
      11: new           #3                  // class java/util/ArrayList
      14: dup
      15: invokespecial #4                  // Method java/util/ArrayList."<init>":()V
      18: astore        4
      20: new           #3                  // class java/util/ArrayList
      23: dup
      24: invokespecial #4                  // Method java/util/ArrayList."<init>":()V
      27: astore        5
      29: new           #3                  // class java/util/ArrayList
      32: dup
      33: invokespecial #4                  // Method java/util/ArrayList."<init>":()V
      36: astore        6
      38: aload_1
      39: invokestatic  #5                  // Method com/google/zxing/datamatrix/encoder/MinimalEncoder$Edge.access$1100:(Lcom/google/zxing/datamatrix/encoder/MinimalEncoder$Edge;)Lcom/google/zxing/datamatrix/encoder/MinimalEncoder$Mode;
      42: getstatic     #6                  // Field com/google/zxing/datamatrix/encoder/MinimalEncoder$Mode.C40:Lcom/google/zxing/datamatrix/encoder/MinimalEncoder$Mode;
      45: if_acmpeq     68
      48: aload_1
      49: invokestatic  #5                  // Method com/google/zxing/datamatrix/encoder/MinimalEncoder$Edge.access$1100:(Lcom/google/zxing/datamatrix/encoder/MinimalEncoder$Edge;)Lcom/google/zxing/datamatrix/encoder/MinimalEncoder$Mode;
      52: getstatic     #7                  // Field com/google/zxing/datamatrix/encoder/MinimalEncoder$Mode.TEXT:Lcom/google/zxing/datamatrix/encoder/MinimalEncoder$Mode;
      55: if_acmpeq     68
      58: aload_1
      59: invokestatic  #5                  // Method com/google/zxing/datamatrix/encoder/MinimalEncoder$Edge.access$1100:(Lcom/google/zxing/datamatrix/encoder/MinimalEncoder$Edge;)Lcom/google/zxing/datamatrix/encoder/MinimalEncoder$Mode;
      62: getstatic     #8                  // Field com/google/zxing/datamatrix/encoder/MinimalEncoder$Mode.X12:Lcom/google/zxing/datamatrix/encoder/MinimalEncoder$Mode;
      65: if_acmpne     92
      68: aload_1
      69: invokevirtual #9                  // Method com/google/zxing/datamatrix/encoder/MinimalEncoder$Edge.getEndMode:()Lcom/google/zxing/datamatrix/encoder/MinimalEncoder$Mode;
      72: getstatic     #10                 // Field com/google/zxing/datamatrix/encoder/MinimalEncoder$Mode.ASCII:Lcom/google/zxing/datamatrix/encoder/MinimalEncoder$Mode;
      75: if_acmpeq     92
      78: iload_3
      79: sipush        254
      82: invokestatic  #11                 // Method com/google/zxing/datamatrix/encoder/MinimalEncoder$Edge.getBytes:(I)[B
      85: aload         4
      87: invokestatic  #12                 // Method prepend:([BLjava/util/List;)I
      90: iadd
      91: istore_3
      92: aload_1
      93: astore        7
      95: aload         7
      97: ifnull        265
     100: iload_3
     101: aload         7
     103: invokevirtual #13                 // Method com/google/zxing/datamatrix/encoder/MinimalEncoder$Edge.getDataBytes:()[B
     106: aload         4
     108: invokestatic  #12                 // Method prepend:([BLjava/util/List;)I
     111: iadd
     112: istore_3
     113: aload         7
     115: invokestatic  #14                 // Method com/google/zxing/datamatrix/encoder/MinimalEncoder$Edge.access$1200:(Lcom/google/zxing/datamatrix/encoder/MinimalEncoder$Edge;)Lcom/google/zxing/datamatrix/encoder/MinimalEncoder$Edge;
     118: ifnull        134
     121: aload         7
     123: invokevirtual #15                 // Method com/google/zxing/datamatrix/encoder/MinimalEncoder$Edge.getPreviousStartMode:()Lcom/google/zxing/datamatrix/encoder/MinimalEncoder$Mode;
     126: aload         7
     128: invokevirtual #16                 // Method com/google/zxing/datamatrix/encoder/MinimalEncoder$Edge.getMode:()Lcom/google/zxing/datamatrix/encoder/MinimalEncoder$Mode;
     131: if_acmpeq     255
     134: aload         7
     136: invokevirtual #16                 // Method com/google/zxing/datamatrix/encoder/MinimalEncoder$Edge.getMode:()Lcom/google/zxing/datamatrix/encoder/MinimalEncoder$Mode;
     139: getstatic     #17                 // Field com/google/zxing/datamatrix/encoder/MinimalEncoder$Mode.B256:Lcom/google/zxing/datamatrix/encoder/MinimalEncoder$Mode;
     142: if_acmpne     242
     145: iload_3
     146: sipush        249
     149: if_icmpgt     171
     152: aload         4
     154: iconst_0
     155: iload_3
     156: i2b
     157: invokestatic  #18                 // Method java/lang/Byte.valueOf:(B)Ljava/lang/Byte;
     160: invokeinterface #19,  3           // InterfaceMethod java/util/List.add:(ILjava/lang/Object;)V
     165: iinc          3, 1
     168: goto          212
     171: aload         4
     173: iconst_0
     174: iload_3
     175: sipush        250
     178: irem
     179: i2b
     180: invokestatic  #18                 // Method java/lang/Byte.valueOf:(B)Ljava/lang/Byte;
     183: invokeinterface #19,  3           // InterfaceMethod java/util/List.add:(ILjava/lang/Object;)V
     188: aload         4
     190: iconst_0
     191: iload_3
     192: sipush        250
     195: idiv
     196: sipush        249
     199: iadd
     200: i2b
     201: invokestatic  #18                 // Method java/lang/Byte.valueOf:(B)Ljava/lang/Byte;
     204: invokeinterface #19,  3           // InterfaceMethod java/util/List.add:(ILjava/lang/Object;)V
     209: iinc          3, 2
     212: aload         5
     214: aload         4
     216: invokeinterface #20,  1           // InterfaceMethod java/util/List.size:()I
     221: invokestatic  #21                 // Method java/lang/Integer.valueOf:(I)Ljava/lang/Integer;
     224: invokeinterface #22,  2           // InterfaceMethod java/util/List.add:(Ljava/lang/Object;)Z
     229: pop
     230: aload         6
     232: iload_3
     233: invokestatic  #21                 // Method java/lang/Integer.valueOf:(I)Ljava/lang/Integer;
     236: invokeinterface #22,  2           // InterfaceMethod java/util/List.add:(Ljava/lang/Object;)Z
     241: pop
     242: aload         7
     244: invokevirtual #23                 // Method com/google/zxing/datamatrix/encoder/MinimalEncoder$Edge.getLatchBytes:()[B
     247: aload         4
     249: invokestatic  #12                 // Method prepend:([BLjava/util/List;)I
     252: pop
     253: iconst_0
     254: istore_3
     255: aload         7
     257: invokestatic  #14                 // Method com/google/zxing/datamatrix/encoder/MinimalEncoder$Edge.access$1200:(Lcom/google/zxing/datamatrix/encoder/MinimalEncoder$Edge;)Lcom/google/zxing/datamatrix/encoder/MinimalEncoder$Edge;
     260: astore        7
     262: goto          95
     265: aload_2
     266: invokestatic  #24                 // Method com/google/zxing/datamatrix/encoder/MinimalEncoder$Input.access$1300:(Lcom/google/zxing/datamatrix/encoder/MinimalEncoder$Input;)I
     269: iconst_5
     270: if_icmpne     290
     273: iload_3
     274: sipush        236
     277: invokestatic  #11                 // Method com/google/zxing/datamatrix/encoder/MinimalEncoder$Edge.getBytes:(I)[B
     280: aload         4
     282: invokestatic  #12                 // Method prepend:([BLjava/util/List;)I
     285: iadd
     286: istore_3
     287: goto          313
     290: aload_2
     291: invokestatic  #24                 // Method com/google/zxing/datamatrix/encoder/MinimalEncoder$Input.access$1300:(Lcom/google/zxing/datamatrix/encoder/MinimalEncoder$Input;)I
     294: bipush        6
     296: if_icmpne     313
     299: iload_3
     300: sipush        237
     303: invokestatic  #11                 // Method com/google/zxing/datamatrix/encoder/MinimalEncoder$Edge.getBytes:(I)[B
     306: aload         4
     308: invokestatic  #12                 // Method prepend:([BLjava/util/List;)I
     311: iadd
     312: istore_3
     313: aload_2
     314: invokevirtual #25                 // Method com/google/zxing/datamatrix/encoder/MinimalEncoder$Input.getFNC1Character:()I
     317: ifle          334
     320: iload_3
     321: sipush        232
     324: invokestatic  #11                 // Method com/google/zxing/datamatrix/encoder/MinimalEncoder$Edge.getBytes:(I)[B
     327: aload         4
     329: invokestatic  #12                 // Method prepend:([BLjava/util/List;)I
     332: iadd
     333: istore_3
     334: iconst_0
     335: istore        8
     337: iload         8
     339: aload         5
     341: invokeinterface #20,  1           // InterfaceMethod java/util/List.size:()I
     346: if_icmpge     398
     349: aload         4
     351: aload         4
     353: invokeinterface #20,  1           // InterfaceMethod java/util/List.size:()I
     358: aload         5
     360: iload         8
     362: invokeinterface #26,  2           // InterfaceMethod java/util/List.get:(I)Ljava/lang/Object;
     367: checkcast     #27                 // class java/lang/Integer
     370: invokevirtual #28                 // Method java/lang/Integer.intValue:()I
     373: isub
     374: aload         6
     376: iload         8
     378: invokeinterface #26,  2           // InterfaceMethod java/util/List.get:(I)Ljava/lang/Object;
     383: checkcast     #27                 // class java/lang/Integer
     386: invokevirtual #28                 // Method java/lang/Integer.intValue:()I
     389: invokestatic  #29                 // Method applyRandomPattern:(Ljava/util/List;II)V
     392: iinc          8, 1
     395: goto          337
     398: aload_1
     399: aload         4
     401: invokeinterface #20,  1           // InterfaceMethod java/util/List.size:()I
     406: invokevirtual #30                 // Method com/google/zxing/datamatrix/encoder/MinimalEncoder$Edge.getMinSymbolSize:(I)I
     409: istore        8
     411: aload         4
     413: invokeinterface #20,  1           // InterfaceMethod java/util/List.size:()I
     418: iload         8
     420: if_icmpge     436
     423: aload         4
     425: bipush        -127
     427: invokestatic  #18                 // Method java/lang/Byte.valueOf:(B)Ljava/lang/Byte;
     430: invokeinterface #22,  2           // InterfaceMethod java/util/List.add:(Ljava/lang/Object;)Z
     435: pop
     436: aload         4
     438: invokeinterface #20,  1           // InterfaceMethod java/util/List.size:()I
     443: iload         8
     445: if_icmpge     475
     448: aload         4
     450: aload         4
     452: invokeinterface #20,  1           // InterfaceMethod java/util/List.size:()I
     457: iconst_1
     458: iadd
     459: invokestatic  #31                 // Method randomize253State:(I)I
     462: i2b
     463: invokestatic  #18                 // Method java/lang/Byte.valueOf:(B)Ljava/lang/Byte;
     466: invokeinterface #22,  2           // InterfaceMethod java/util/List.add:(Ljava/lang/Object;)Z
     471: pop
     472: goto          436
     475: aload_0
     476: aload         4
     478: invokeinterface #20,  1           // InterfaceMethod java/util/List.size:()I
     483: newarray       byte
     485: putfield      #32                 // Field bytes:[B
     488: iconst_0
     489: istore        9
     491: iload         9
     493: aload_0
     494: getfield      #32                 // Field bytes:[B
     497: arraylength
     498: if_icmpge     529
     501: aload_0
     502: getfield      #32                 // Field bytes:[B
     505: iload         9
     507: aload         4
     509: iload         9
     511: invokeinterface #26,  2           // InterfaceMethod java/util/List.get:(I)Ljava/lang/Object;
     516: checkcast     #33                 // class java/lang/Byte
     519: invokevirtual #34                 // Method java/lang/Byte.byteValue:()B
     522: bastore
     523: iinc          9, 1
     526: goto          491
     529: return

  static int prepend(byte[], java.util.List<java.lang.Byte>);
    Code:
       0: aload_0
       1: arraylength
       2: iconst_1
       3: isub
       4: istore_2
       5: iload_2
       6: iflt          28
       9: aload_1
      10: iconst_0
      11: aload_0
      12: iload_2
      13: baload
      14: invokestatic  #18                 // Method java/lang/Byte.valueOf:(B)Ljava/lang/Byte;
      17: invokeinterface #19,  3           // InterfaceMethod java/util/List.add:(ILjava/lang/Object;)V
      22: iinc          2, -1
      25: goto          5
      28: aload_0
      29: arraylength
      30: ireturn

  private static int randomize253State(int);
    Code:
       0: sipush        149
       3: iload_0
       4: imul
       5: sipush        253
       8: irem
       9: iconst_1
      10: iadd
      11: istore_1
      12: sipush        129
      15: iload_1
      16: iadd
      17: istore_2
      18: iload_2
      19: sipush        254
      22: if_icmpgt     29
      25: iload_2
      26: goto          34
      29: iload_2
      30: sipush        254
      33: isub
      34: ireturn

  static void applyRandomPattern(java.util.List<java.lang.Byte>, int, int);
    Code:
       0: iconst_0
       1: istore_3
       2: iload_3
       3: iload_2
       4: if_icmpge     93
       7: iload_1
       8: iload_3
       9: iadd
      10: istore        4
      12: aload_0
      13: iload         4
      15: invokeinterface #26,  2           // InterfaceMethod java/util/List.get:(I)Ljava/lang/Object;
      20: checkcast     #33                 // class java/lang/Byte
      23: invokevirtual #34                 // Method java/lang/Byte.byteValue:()B
      26: sipush        255
      29: iand
      30: istore        5
      32: sipush        149
      35: iload         4
      37: iconst_1
      38: iadd
      39: imul
      40: sipush        255
      43: irem
      44: iconst_1
      45: iadd
      46: istore        6
      48: iload         5
      50: iload         6
      52: iadd
      53: istore        7
      55: aload_0
      56: iload         4
      58: iload         7
      60: sipush        255
      63: if_icmpgt     71
      66: iload         7
      68: goto          77
      71: iload         7
      73: sipush        256
      76: isub
      77: i2b
      78: invokestatic  #18                 // Method java/lang/Byte.valueOf:(B)Ljava/lang/Byte;
      81: invokeinterface #35,  3           // InterfaceMethod java/util/List.set:(ILjava/lang/Object;)Ljava/lang/Object;
      86: pop
      87: iinc          3, 1
      90: goto          2
      93: return

  public byte[] getBytes();
    Code:
       0: aload_0
       1: getfield      #32                 // Field bytes:[B
       4: areturn
}
