Compiled from "SymbolShapeHint.java"
public final class com.google.zxing.datamatrix.encoder.SymbolShapeHint extends java.lang.Enum<com.google.zxing.datamatrix.encoder.SymbolShapeHint> {
  public static final com.google.zxing.datamatrix.encoder.SymbolShapeHint FORCE_NONE;

  public static final com.google.zxing.datamatrix.encoder.SymbolShapeHint FORCE_SQUARE;

  public static final com.google.zxing.datamatrix.encoder.SymbolShapeHint FORCE_RECTANGLE;

  private static final com.google.zxing.datamatrix.encoder.SymbolShapeHint[] $VALUES;

  public static com.google.zxing.datamatrix.encoder.SymbolShapeHint[] values();
    Code:
       0: getstatic     #1                  // Field $VALUES:[Lcom/google/zxing/datamatrix/encoder/SymbolShapeHint;
       3: invokevirtual #2                  // Method "[Lcom/google/zxing/datamatrix/encoder/SymbolShapeHint;".clone:()Ljava/lang/Object;
       6: checkcast     #3                  // class "[Lcom/google/zxing/datamatrix/encoder/SymbolShapeHint;"
       9: areturn

  public static com.google.zxing.datamatrix.encoder.SymbolShapeHint valueOf(java.lang.String);
    Code:
       0: ldc           #4                  // class com/google/zxing/datamatrix/encoder/SymbolShapeHint
       2: aload_0
       3: invokestatic  #5                  // Method java/lang/Enum.valueOf:(Ljava/lang/Class;Ljava/lang/String;)Ljava/lang/Enum;
       6: checkcast     #4                  // class com/google/zxing/datamatrix/encoder/SymbolShapeHint
       9: areturn

  private com.google.zxing.datamatrix.encoder.SymbolShapeHint();
    Code:
       0: aload_0
       1: aload_1
       2: iload_2
       3: invokespecial #6                  // Method java/lang/Enum."<init>":(Ljava/lang/String;I)V
       6: return

  static {};
    Code:
       0: new           #4                  // class com/google/zxing/datamatrix/encoder/SymbolShapeHint
       3: dup
       4: ldc           #7                  // String FORCE_NONE
       6: iconst_0
       7: invokespecial #8                  // Method "<init>":(Ljava/lang/String;I)V
      10: putstatic     #9                  // Field FORCE_NONE:Lcom/google/zxing/datamatrix/encoder/SymbolShapeHint;
      13: new           #4                  // class com/google/zxing/datamatrix/encoder/SymbolShapeHint
      16: dup
      17: ldc           #10                 // String FORCE_SQUARE
      19: iconst_1
      20: invokespecial #8                  // Method "<init>":(Ljava/lang/String;I)V
      23: putstatic     #11                 // Field FORCE_SQUARE:Lcom/google/zxing/datamatrix/encoder/SymbolShapeHint;
      26: new           #4                  // class com/google/zxing/datamatrix/encoder/SymbolShapeHint
      29: dup
      30: ldc           #12                 // String FORCE_RECTANGLE
      32: iconst_2
      33: invokespecial #8                  // Method "<init>":(Ljava/lang/String;I)V
      36: putstatic     #13                 // Field FORCE_RECTANGLE:Lcom/google/zxing/datamatrix/encoder/SymbolShapeHint;
      39: iconst_3
      40: anewarray     #4                  // class com/google/zxing/datamatrix/encoder/SymbolShapeHint
      43: dup
      44: iconst_0
      45: getstatic     #9                  // Field FORCE_NONE:Lcom/google/zxing/datamatrix/encoder/SymbolShapeHint;
      48: aastore
      49: dup
      50: iconst_1
      51: getstatic     #11                 // Field FORCE_SQUARE:Lcom/google/zxing/datamatrix/encoder/SymbolShapeHint;
      54: aastore
      55: dup
      56: iconst_2
      57: getstatic     #13                 // Field FORCE_RECTANGLE:Lcom/google/zxing/datamatrix/encoder/SymbolShapeHint;
      60: aastore
      61: putstatic     #1                  // Field $VALUES:[Lcom/google/zxing/datamatrix/encoder/SymbolShapeHint;
      64: return
}
