Compiled from "SymbolInfo.java"
public class com.google.zxing.datamatrix.encoder.SymbolInfo {
  static final com.google.zxing.datamatrix.encoder.SymbolInfo[] PROD_SYMBOLS;

  private static com.google.zxing.datamatrix.encoder.SymbolInfo[] symbols;

  private final boolean rectangular;

  private final int dataCapacity;

  private final int errorCodewords;

  public final int matrixWidth;

  public final int matrixHeight;

  private final int dataRegions;

  private final int rsBlockData;

  private final int rsBlockError;

  public static void overrideSymbolSet(com.google.zxing.datamatrix.encoder.SymbolInfo[]);
    Code:
       0: aload_0
       1: putstatic     #1                  // Field symbols:[Lcom/google/zxing/datamatrix/encoder/SymbolInfo;
       4: return

  public com.google.zxing.datamatrix.encoder.SymbolInfo(boolean, int, int, int, int, int);
    Code:
       0: aload_0
       1: iload_1
       2: iload_2
       3: iload_3
       4: iload         4
       6: iload         5
       8: iload         6
      10: iload_2
      11: iload_3
      12: invokespecial #2                  // Method "<init>":(ZIIIIIII)V
      15: return

  com.google.zxing.datamatrix.encoder.SymbolInfo(boolean, int, int, int, int, int, int, int);
    Code:
       0: aload_0
       1: invokespecial #3                  // Method java/lang/Object."<init>":()V
       4: aload_0
       5: iload_1
       6: putfield      #4                  // Field rectangular:Z
       9: aload_0
      10: iload_2
      11: putfield      #5                  // Field dataCapacity:I
      14: aload_0
      15: iload_3
      16: putfield      #6                  // Field errorCodewords:I
      19: aload_0
      20: iload         4
      22: putfield      #7                  // Field matrixWidth:I
      25: aload_0
      26: iload         5
      28: putfield      #8                  // Field matrixHeight:I
      31: aload_0
      32: iload         6
      34: putfield      #9                  // Field dataRegions:I
      37: aload_0
      38: iload         7
      40: putfield      #10                 // Field rsBlockData:I
      43: aload_0
      44: iload         8
      46: putfield      #11                 // Field rsBlockError:I
      49: return

  public static com.google.zxing.datamatrix.encoder.SymbolInfo lookup(int);
    Code:
       0: iload_0
       1: getstatic     #12                 // Field com/google/zxing/datamatrix/encoder/SymbolShapeHint.FORCE_NONE:Lcom/google/zxing/datamatrix/encoder/SymbolShapeHint;
       4: iconst_1
       5: invokestatic  #13                 // Method lookup:(ILcom/google/zxing/datamatrix/encoder/SymbolShapeHint;Z)Lcom/google/zxing/datamatrix/encoder/SymbolInfo;
       8: areturn

  public static com.google.zxing.datamatrix.encoder.SymbolInfo lookup(int, com.google.zxing.datamatrix.encoder.SymbolShapeHint);
    Code:
       0: iload_0
       1: aload_1
       2: iconst_1
       3: invokestatic  #13                 // Method lookup:(ILcom/google/zxing/datamatrix/encoder/SymbolShapeHint;Z)Lcom/google/zxing/datamatrix/encoder/SymbolInfo;
       6: areturn

  public static com.google.zxing.datamatrix.encoder.SymbolInfo lookup(int, boolean, boolean);
    Code:
       0: iload_1
       1: ifeq          10
       4: getstatic     #12                 // Field com/google/zxing/datamatrix/encoder/SymbolShapeHint.FORCE_NONE:Lcom/google/zxing/datamatrix/encoder/SymbolShapeHint;
       7: goto          13
      10: getstatic     #14                 // Field com/google/zxing/datamatrix/encoder/SymbolShapeHint.FORCE_SQUARE:Lcom/google/zxing/datamatrix/encoder/SymbolShapeHint;
      13: astore_3
      14: iload_0
      15: aload_3
      16: iload_2
      17: invokestatic  #13                 // Method lookup:(ILcom/google/zxing/datamatrix/encoder/SymbolShapeHint;Z)Lcom/google/zxing/datamatrix/encoder/SymbolInfo;
      20: areturn

  private static com.google.zxing.datamatrix.encoder.SymbolInfo lookup(int, com.google.zxing.datamatrix.encoder.SymbolShapeHint, boolean);
    Code:
       0: iload_0
       1: aload_1
       2: aconst_null
       3: aconst_null
       4: iload_2
       5: invokestatic  #15                 // Method lookup:(ILcom/google/zxing/datamatrix/encoder/SymbolShapeHint;Lcom/google/zxing/Dimension;Lcom/google/zxing/Dimension;Z)Lcom/google/zxing/datamatrix/encoder/SymbolInfo;
       8: areturn

  public static com.google.zxing.datamatrix.encoder.SymbolInfo lookup(int, com.google.zxing.datamatrix.encoder.SymbolShapeHint, com.google.zxing.Dimension, com.google.zxing.Dimension, boolean);
    Code:
       0: getstatic     #1                  // Field symbols:[Lcom/google/zxing/datamatrix/encoder/SymbolInfo;
       3: astore        5
       5: aload         5
       7: arraylength
       8: istore        6
      10: iconst_0
      11: istore        7
      13: iload         7
      15: iload         6
      17: if_icmpge     143
      20: aload         5
      22: iload         7
      24: aaload
      25: astore        8
      27: aload_1
      28: getstatic     #14                 // Field com/google/zxing/datamatrix/encoder/SymbolShapeHint.FORCE_SQUARE:Lcom/google/zxing/datamatrix/encoder/SymbolShapeHint;
      31: if_acmpne     45
      34: aload         8
      36: getfield      #4                  // Field rectangular:Z
      39: ifeq          45
      42: goto          137
      45: aload_1
      46: getstatic     #16                 // Field com/google/zxing/datamatrix/encoder/SymbolShapeHint.FORCE_RECTANGLE:Lcom/google/zxing/datamatrix/encoder/SymbolShapeHint;
      49: if_acmpne     63
      52: aload         8
      54: getfield      #4                  // Field rectangular:Z
      57: ifne          63
      60: goto          137
      63: aload_2
      64: ifnull        94
      67: aload         8
      69: invokevirtual #17                 // Method getSymbolWidth:()I
      72: aload_2
      73: invokevirtual #18                 // Method com/google/zxing/Dimension.getWidth:()I
      76: if_icmplt     137
      79: aload         8
      81: invokevirtual #19                 // Method getSymbolHeight:()I
      84: aload_2
      85: invokevirtual #20                 // Method com/google/zxing/Dimension.getHeight:()I
      88: if_icmpge     94
      91: goto          137
      94: aload_3
      95: ifnull        125
      98: aload         8
     100: invokevirtual #17                 // Method getSymbolWidth:()I
     103: aload_3
     104: invokevirtual #18                 // Method com/google/zxing/Dimension.getWidth:()I
     107: if_icmpgt     137
     110: aload         8
     112: invokevirtual #19                 // Method getSymbolHeight:()I
     115: aload_3
     116: invokevirtual #20                 // Method com/google/zxing/Dimension.getHeight:()I
     119: if_icmple     125
     122: goto          137
     125: iload_0
     126: aload         8
     128: getfield      #5                  // Field dataCapacity:I
     131: if_icmpgt     137
     134: aload         8
     136: areturn
     137: iinc          7, 1
     140: goto          13
     143: iload         4
     145: ifeq          175
     148: new           #21                 // class java/lang/IllegalArgumentException
     151: dup
     152: new           #22                 // class java/lang/StringBuilder
     155: dup
     156: invokespecial #23                 // Method java/lang/StringBuilder."<init>":()V
     159: ldc           #24                 // String Can\'t find a symbol arrangement that matches the message. Data codewords:
     161: invokevirtual #25                 // Method java/lang/StringBuilder.append:(Ljava/lang/String;)Ljava/lang/StringBuilder;
     164: iload_0
     165: invokevirtual #26                 // Method java/lang/StringBuilder.append:(I)Ljava/lang/StringBuilder;
     168: invokevirtual #27                 // Method java/lang/StringBuilder.toString:()Ljava/lang/String;
     171: invokespecial #28                 // Method java/lang/IllegalArgumentException."<init>":(Ljava/lang/String;)V
     174: athrow
     175: aconst_null
     176: areturn

  private int getHorizontalDataRegions();
    Code:
       0: aload_0
       1: getfield      #9                  // Field dataRegions:I
       4: lookupswitch  { // 5
                     1: 56
                     2: 58
                     4: 58
                    16: 60
                    36: 62
               default: 65
          }
      56: iconst_1
      57: ireturn
      58: iconst_2
      59: ireturn
      60: iconst_4
      61: ireturn
      62: bipush        6
      64: ireturn
      65: new           #29                 // class java/lang/IllegalStateException
      68: dup
      69: ldc           #30                 // String Cannot handle this number of data regions
      71: invokespecial #31                 // Method java/lang/IllegalStateException."<init>":(Ljava/lang/String;)V
      74: athrow

  private int getVerticalDataRegions();
    Code:
       0: aload_0
       1: getfield      #9                  // Field dataRegions:I
       4: lookupswitch  { // 5
                     1: 56
                     2: 56
                     4: 58
                    16: 60
                    36: 62
               default: 65
          }
      56: iconst_1
      57: ireturn
      58: iconst_2
      59: ireturn
      60: iconst_4
      61: ireturn
      62: bipush        6
      64: ireturn
      65: new           #29                 // class java/lang/IllegalStateException
      68: dup
      69: ldc           #30                 // String Cannot handle this number of data regions
      71: invokespecial #31                 // Method java/lang/IllegalStateException."<init>":(Ljava/lang/String;)V
      74: athrow

  public final int getSymbolDataWidth();
    Code:
       0: aload_0
       1: invokespecial #32                 // Method getHorizontalDataRegions:()I
       4: aload_0
       5: getfield      #7                  // Field matrixWidth:I
       8: imul
       9: ireturn

  public final int getSymbolDataHeight();
    Code:
       0: aload_0
       1: invokespecial #33                 // Method getVerticalDataRegions:()I
       4: aload_0
       5: getfield      #8                  // Field matrixHeight:I
       8: imul
       9: ireturn

  public final int getSymbolWidth();
    Code:
       0: aload_0
       1: invokevirtual #34                 // Method getSymbolDataWidth:()I
       4: aload_0
       5: invokespecial #32                 // Method getHorizontalDataRegions:()I
       8: iconst_2
       9: imul
      10: iadd
      11: ireturn

  public final int getSymbolHeight();
    Code:
       0: aload_0
       1: invokevirtual #35                 // Method getSymbolDataHeight:()I
       4: aload_0
       5: invokespecial #33                 // Method getVerticalDataRegions:()I
       8: iconst_2
       9: imul
      10: iadd
      11: ireturn

  public int getCodewordCount();
    Code:
       0: aload_0
       1: getfield      #5                  // Field dataCapacity:I
       4: aload_0
       5: getfield      #6                  // Field errorCodewords:I
       8: iadd
       9: ireturn

  public int getInterleavedBlockCount();
    Code:
       0: aload_0
       1: getfield      #5                  // Field dataCapacity:I
       4: aload_0
       5: getfield      #10                 // Field rsBlockData:I
       8: idiv
       9: ireturn

  public final int getDataCapacity();
    Code:
       0: aload_0
       1: getfield      #5                  // Field dataCapacity:I
       4: ireturn

  public final int getErrorCodewords();
    Code:
       0: aload_0
       1: getfield      #6                  // Field errorCodewords:I
       4: ireturn

  public int getDataLengthForInterleavedBlock(int);
    Code:
       0: aload_0
       1: getfield      #10                 // Field rsBlockData:I
       4: ireturn

  public final int getErrorLengthForInterleavedBlock(int);
    Code:
       0: aload_0
       1: getfield      #11                 // Field rsBlockError:I
       4: ireturn

  public final java.lang.String toString();
    Code:
       0: new           #22                 // class java/lang/StringBuilder
       3: dup
       4: invokespecial #23                 // Method java/lang/StringBuilder."<init>":()V
       7: aload_0
       8: getfield      #4                  // Field rectangular:Z
      11: ifeq          19
      14: ldc           #36                 // String Rectangular Symbol:
      16: goto          21
      19: ldc           #37                 // String Square Symbol:
      21: invokevirtual #25                 // Method java/lang/StringBuilder.append:(Ljava/lang/String;)Ljava/lang/StringBuilder;
      24: ldc           #38                 // String  data region
      26: invokevirtual #25                 // Method java/lang/StringBuilder.append:(Ljava/lang/String;)Ljava/lang/StringBuilder;
      29: aload_0
      30: getfield      #7                  // Field matrixWidth:I
      33: invokevirtual #26                 // Method java/lang/StringBuilder.append:(I)Ljava/lang/StringBuilder;
      36: bipush        120
      38: invokevirtual #39                 // Method java/lang/StringBuilder.append:(C)Ljava/lang/StringBuilder;
      41: aload_0
      42: getfield      #8                  // Field matrixHeight:I
      45: invokevirtual #26                 // Method java/lang/StringBuilder.append:(I)Ljava/lang/StringBuilder;
      48: ldc           #40                 // String , symbol size
      50: invokevirtual #25                 // Method java/lang/StringBuilder.append:(Ljava/lang/String;)Ljava/lang/StringBuilder;
      53: aload_0
      54: invokevirtual #17                 // Method getSymbolWidth:()I
      57: invokevirtual #26                 // Method java/lang/StringBuilder.append:(I)Ljava/lang/StringBuilder;
      60: bipush        120
      62: invokevirtual #39                 // Method java/lang/StringBuilder.append:(C)Ljava/lang/StringBuilder;
      65: aload_0
      66: invokevirtual #19                 // Method getSymbolHeight:()I
      69: invokevirtual #26                 // Method java/lang/StringBuilder.append:(I)Ljava/lang/StringBuilder;
      72: ldc           #41                 // String , symbol data size
      74: invokevirtual #25                 // Method java/lang/StringBuilder.append:(Ljava/lang/String;)Ljava/lang/StringBuilder;
      77: aload_0
      78: invokevirtual #34                 // Method getSymbolDataWidth:()I
      81: invokevirtual #26                 // Method java/lang/StringBuilder.append:(I)Ljava/lang/StringBuilder;
      84: bipush        120
      86: invokevirtual #39                 // Method java/lang/StringBuilder.append:(C)Ljava/lang/StringBuilder;
      89: aload_0
      90: invokevirtual #35                 // Method getSymbolDataHeight:()I
      93: invokevirtual #26                 // Method java/lang/StringBuilder.append:(I)Ljava/lang/StringBuilder;
      96: ldc           #42                 // String , codewords
      98: invokevirtual #25                 // Method java/lang/StringBuilder.append:(Ljava/lang/String;)Ljava/lang/StringBuilder;
     101: aload_0
     102: getfield      #5                  // Field dataCapacity:I
     105: invokevirtual #26                 // Method java/lang/StringBuilder.append:(I)Ljava/lang/StringBuilder;
     108: bipush        43
     110: invokevirtual #39                 // Method java/lang/StringBuilder.append:(C)Ljava/lang/StringBuilder;
     113: aload_0
     114: getfield      #6                  // Field errorCodewords:I
     117: invokevirtual #26                 // Method java/lang/StringBuilder.append:(I)Ljava/lang/StringBuilder;
     120: invokevirtual #27                 // Method java/lang/StringBuilder.toString:()Ljava/lang/String;
     123: areturn

  static {};
    Code:
       0: bipush        30
       2: anewarray     #43                 // class com/google/zxing/datamatrix/encoder/SymbolInfo
       5: dup
       6: iconst_0
       7: new           #43                 // class com/google/zxing/datamatrix/encoder/SymbolInfo
      10: dup
      11: iconst_0
      12: iconst_3
      13: iconst_5
      14: bipush        8
      16: bipush        8
      18: iconst_1
      19: invokespecial #44                 // Method "<init>":(ZIIIII)V
      22: aastore
      23: dup
      24: iconst_1
      25: new           #43                 // class com/google/zxing/datamatrix/encoder/SymbolInfo
      28: dup
      29: iconst_0
      30: iconst_5
      31: bipush        7
      33: bipush        10
      35: bipush        10
      37: iconst_1
      38: invokespecial #44                 // Method "<init>":(ZIIIII)V
      41: aastore
      42: dup
      43: iconst_2
      44: new           #43                 // class com/google/zxing/datamatrix/encoder/SymbolInfo
      47: dup
      48: iconst_1
      49: iconst_5
      50: bipush        7
      52: bipush        16
      54: bipush        6
      56: iconst_1
      57: invokespecial #44                 // Method "<init>":(ZIIIII)V
      60: aastore
      61: dup
      62: iconst_3
      63: new           #43                 // class com/google/zxing/datamatrix/encoder/SymbolInfo
      66: dup
      67: iconst_0
      68: bipush        8
      70: bipush        10
      72: bipush        12
      74: bipush        12
      76: iconst_1
      77: invokespecial #44                 // Method "<init>":(ZIIIII)V
      80: aastore
      81: dup
      82: iconst_4
      83: new           #43                 // class com/google/zxing/datamatrix/encoder/SymbolInfo
      86: dup
      87: iconst_1
      88: bipush        10
      90: bipush        11
      92: bipush        14
      94: bipush        6
      96: iconst_2
      97: invokespecial #44                 // Method "<init>":(ZIIIII)V
     100: aastore
     101: dup
     102: iconst_5
     103: new           #43                 // class com/google/zxing/datamatrix/encoder/SymbolInfo
     106: dup
     107: iconst_0
     108: bipush        12
     110: bipush        12
     112: bipush        14
     114: bipush        14
     116: iconst_1
     117: invokespecial #44                 // Method "<init>":(ZIIIII)V
     120: aastore
     121: dup
     122: bipush        6
     124: new           #43                 // class com/google/zxing/datamatrix/encoder/SymbolInfo
     127: dup
     128: iconst_1
     129: bipush        16
     131: bipush        14
     133: bipush        24
     135: bipush        10
     137: iconst_1
     138: invokespecial #44                 // Method "<init>":(ZIIIII)V
     141: aastore
     142: dup
     143: bipush        7
     145: new           #43                 // class com/google/zxing/datamatrix/encoder/SymbolInfo
     148: dup
     149: iconst_0
     150: bipush        18
     152: bipush        14
     154: bipush        16
     156: bipush        16
     158: iconst_1
     159: invokespecial #44                 // Method "<init>":(ZIIIII)V
     162: aastore
     163: dup
     164: bipush        8
     166: new           #43                 // class com/google/zxing/datamatrix/encoder/SymbolInfo
     169: dup
     170: iconst_0
     171: bipush        22
     173: bipush        18
     175: bipush        18
     177: bipush        18
     179: iconst_1
     180: invokespecial #44                 // Method "<init>":(ZIIIII)V
     183: aastore
     184: dup
     185: bipush        9
     187: new           #43                 // class com/google/zxing/datamatrix/encoder/SymbolInfo
     190: dup
     191: iconst_1
     192: bipush        22
     194: bipush        18
     196: bipush        16
     198: bipush        10
     200: iconst_2
     201: invokespecial #44                 // Method "<init>":(ZIIIII)V
     204: aastore
     205: dup
     206: bipush        10
     208: new           #43                 // class com/google/zxing/datamatrix/encoder/SymbolInfo
     211: dup
     212: iconst_0
     213: bipush        30
     215: bipush        20
     217: bipush        20
     219: bipush        20
     221: iconst_1
     222: invokespecial #44                 // Method "<init>":(ZIIIII)V
     225: aastore
     226: dup
     227: bipush        11
     229: new           #43                 // class com/google/zxing/datamatrix/encoder/SymbolInfo
     232: dup
     233: iconst_1
     234: bipush        32
     236: bipush        24
     238: bipush        16
     240: bipush        14
     242: iconst_2
     243: invokespecial #44                 // Method "<init>":(ZIIIII)V
     246: aastore
     247: dup
     248: bipush        12
     250: new           #43                 // class com/google/zxing/datamatrix/encoder/SymbolInfo
     253: dup
     254: iconst_0
     255: bipush        36
     257: bipush        24
     259: bipush        22
     261: bipush        22
     263: iconst_1
     264: invokespecial #44                 // Method "<init>":(ZIIIII)V
     267: aastore
     268: dup
     269: bipush        13
     271: new           #43                 // class com/google/zxing/datamatrix/encoder/SymbolInfo
     274: dup
     275: iconst_0
     276: bipush        44
     278: bipush        28
     280: bipush        24
     282: bipush        24
     284: iconst_1
     285: invokespecial #44                 // Method "<init>":(ZIIIII)V
     288: aastore
     289: dup
     290: bipush        14
     292: new           #43                 // class com/google/zxing/datamatrix/encoder/SymbolInfo
     295: dup
     296: iconst_1
     297: bipush        49
     299: bipush        28
     301: bipush        22
     303: bipush        14
     305: iconst_2
     306: invokespecial #44                 // Method "<init>":(ZIIIII)V
     309: aastore
     310: dup
     311: bipush        15
     313: new           #43                 // class com/google/zxing/datamatrix/encoder/SymbolInfo
     316: dup
     317: iconst_0
     318: bipush        62
     320: bipush        36
     322: bipush        14
     324: bipush        14
     326: iconst_4
     327: invokespecial #44                 // Method "<init>":(ZIIIII)V
     330: aastore
     331: dup
     332: bipush        16
     334: new           #43                 // class com/google/zxing/datamatrix/encoder/SymbolInfo
     337: dup
     338: iconst_0
     339: bipush        86
     341: bipush        42
     343: bipush        16
     345: bipush        16
     347: iconst_4
     348: invokespecial #44                 // Method "<init>":(ZIIIII)V
     351: aastore
     352: dup
     353: bipush        17
     355: new           #43                 // class com/google/zxing/datamatrix/encoder/SymbolInfo
     358: dup
     359: iconst_0
     360: bipush        114
     362: bipush        48
     364: bipush        18
     366: bipush        18
     368: iconst_4
     369: invokespecial #44                 // Method "<init>":(ZIIIII)V
     372: aastore
     373: dup
     374: bipush        18
     376: new           #43                 // class com/google/zxing/datamatrix/encoder/SymbolInfo
     379: dup
     380: iconst_0
     381: sipush        144
     384: bipush        56
     386: bipush        20
     388: bipush        20
     390: iconst_4
     391: invokespecial #44                 // Method "<init>":(ZIIIII)V
     394: aastore
     395: dup
     396: bipush        19
     398: new           #43                 // class com/google/zxing/datamatrix/encoder/SymbolInfo
     401: dup
     402: iconst_0
     403: sipush        174
     406: bipush        68
     408: bipush        22
     410: bipush        22
     412: iconst_4
     413: invokespecial #44                 // Method "<init>":(ZIIIII)V
     416: aastore
     417: dup
     418: bipush        20
     420: new           #43                 // class com/google/zxing/datamatrix/encoder/SymbolInfo
     423: dup
     424: iconst_0
     425: sipush        204
     428: bipush        84
     430: bipush        24
     432: bipush        24
     434: iconst_4
     435: bipush        102
     437: bipush        42
     439: invokespecial #2                  // Method "<init>":(ZIIIIIII)V
     442: aastore
     443: dup
     444: bipush        21
     446: new           #43                 // class com/google/zxing/datamatrix/encoder/SymbolInfo
     449: dup
     450: iconst_0
     451: sipush        280
     454: bipush        112
     456: bipush        14
     458: bipush        14
     460: bipush        16
     462: sipush        140
     465: bipush        56
     467: invokespecial #2                  // Method "<init>":(ZIIIIIII)V
     470: aastore
     471: dup
     472: bipush        22
     474: new           #43                 // class com/google/zxing/datamatrix/encoder/SymbolInfo
     477: dup
     478: iconst_0
     479: sipush        368
     482: sipush        144
     485: bipush        16
     487: bipush        16
     489: bipush        16
     491: bipush        92
     493: bipush        36
     495: invokespecial #2                  // Method "<init>":(ZIIIIIII)V
     498: aastore
     499: dup
     500: bipush        23
     502: new           #43                 // class com/google/zxing/datamatrix/encoder/SymbolInfo
     505: dup
     506: iconst_0
     507: sipush        456
     510: sipush        192
     513: bipush        18
     515: bipush        18
     517: bipush        16
     519: bipush        114
     521: bipush        48
     523: invokespecial #2                  // Method "<init>":(ZIIIIIII)V
     526: aastore
     527: dup
     528: bipush        24
     530: new           #43                 // class com/google/zxing/datamatrix/encoder/SymbolInfo
     533: dup
     534: iconst_0
     535: sipush        576
     538: sipush        224
     541: bipush        20
     543: bipush        20
     545: bipush        16
     547: sipush        144
     550: bipush        56
     552: invokespecial #2                  // Method "<init>":(ZIIIIIII)V
     555: aastore
     556: dup
     557: bipush        25
     559: new           #43                 // class com/google/zxing/datamatrix/encoder/SymbolInfo
     562: dup
     563: iconst_0
     564: sipush        696
     567: sipush        272
     570: bipush        22
     572: bipush        22
     574: bipush        16
     576: sipush        174
     579: bipush        68
     581: invokespecial #2                  // Method "<init>":(ZIIIIIII)V
     584: aastore
     585: dup
     586: bipush        26
     588: new           #43                 // class com/google/zxing/datamatrix/encoder/SymbolInfo
     591: dup
     592: iconst_0
     593: sipush        816
     596: sipush        336
     599: bipush        24
     601: bipush        24
     603: bipush        16
     605: sipush        136
     608: bipush        56
     610: invokespecial #2                  // Method "<init>":(ZIIIIIII)V
     613: aastore
     614: dup
     615: bipush        27
     617: new           #43                 // class com/google/zxing/datamatrix/encoder/SymbolInfo
     620: dup
     621: iconst_0
     622: sipush        1050
     625: sipush        408
     628: bipush        18
     630: bipush        18
     632: bipush        36
     634: sipush        175
     637: bipush        68
     639: invokespecial #2                  // Method "<init>":(ZIIIIIII)V
     642: aastore
     643: dup
     644: bipush        28
     646: new           #43                 // class com/google/zxing/datamatrix/encoder/SymbolInfo
     649: dup
     650: iconst_0
     651: sipush        1304
     654: sipush        496
     657: bipush        20
     659: bipush        20
     661: bipush        36
     663: sipush        163
     666: bipush        62
     668: invokespecial #2                  // Method "<init>":(ZIIIIIII)V
     671: aastore
     672: dup
     673: bipush        29
     675: new           #45                 // class com/google/zxing/datamatrix/encoder/DataMatrixSymbolInfo144
     678: dup
     679: invokespecial #46                 // Method com/google/zxing/datamatrix/encoder/DataMatrixSymbolInfo144."<init>":()V
     682: aastore
     683: putstatic     #47                 // Field PROD_SYMBOLS:[Lcom/google/zxing/datamatrix/encoder/SymbolInfo;
     686: getstatic     #47                 // Field PROD_SYMBOLS:[Lcom/google/zxing/datamatrix/encoder/SymbolInfo;
     689: putstatic     #1                  // Field symbols:[Lcom/google/zxing/datamatrix/encoder/SymbolInfo;
     692: return
}
