Compiled from "InternalThread.java"
public class org.apache.dubbo.common.threadlocal.InternalThread extends java.lang.Thread {
  private org.apache.dubbo.common.threadlocal.InternalThreadLocalMap threadLocalMap;

  public org.apache.dubbo.common.threadlocal.InternalThread();
    Code:
       0: aload_0
       1: invokespecial #1                  // Method java/lang/Thread."<init>":()V
       4: return

  public org.apache.dubbo.common.threadlocal.InternalThread(java.lang.Runnable);
    Code:
       0: aload_0
       1: aload_1
       2: invokespecial #2                  // Method java/lang/Thread."<init>":(Ljava/lang/Runnable;)V
       5: return

  public org.apache.dubbo.common.threadlocal.InternalThread(java.lang.ThreadGroup, java.lang.Runnable);
    Code:
       0: aload_0
       1: aload_1
       2: aload_2
       3: invokespecial #3                  // Method java/lang/Thread."<init>":(Ljava/lang/ThreadGroup;Ljava/lang/Runnable;)V
       6: return

  public org.apache.dubbo.common.threadlocal.InternalThread(java.lang.String);
    Code:
       0: aload_0
       1: aload_1
       2: invokespecial #4                  // Method java/lang/Thread."<init>":(Ljava/lang/String;)V
       5: return

  public org.apache.dubbo.common.threadlocal.InternalThread(java.lang.ThreadGroup, java.lang.String);
    Code:
       0: aload_0
       1: aload_1
       2: aload_2
       3: invokespecial #5                  // Method java/lang/Thread."<init>":(Ljava/lang/ThreadGroup;Ljava/lang/String;)V
       6: return

  public org.apache.dubbo.common.threadlocal.InternalThread(java.lang.Runnable, java.lang.String);
    Code:
       0: aload_0
       1: aload_1
       2: aload_2
       3: invokespecial #6                  // Method java/lang/Thread."<init>":(Ljava/lang/Runnable;Ljava/lang/String;)V
       6: return

  public org.apache.dubbo.common.threadlocal.InternalThread(java.lang.ThreadGroup, java.lang.Runnable, java.lang.String);
    Code:
       0: aload_0
       1: aload_1
       2: aload_2
       3: aload_3
       4: invokespecial #7                  // Method java/lang/Thread."<init>":(Ljava/lang/ThreadGroup;Ljava/lang/Runnable;Ljava/lang/String;)V
       7: return

  public org.apache.dubbo.common.threadlocal.InternalThread(java.lang.ThreadGroup, java.lang.Runnable, java.lang.String, long);
    Code:
       0: aload_0
       1: aload_1
       2: aload_2
       3: aload_3
       4: lload         4
       6: invokespecial #8                  // Method java/lang/Thread."<init>":(Ljava/lang/ThreadGroup;Ljava/lang/Runnable;Ljava/lang/String;J)V
       9: return

  public final org.apache.dubbo.common.threadlocal.InternalThreadLocalMap threadLocalMap();
    Code:
       0: aload_0
       1: getfield      #9                  // Field threadLocalMap:Lorg/apache/dubbo/common/threadlocal/InternalThreadLocalMap;
       4: areturn

  public final void setThreadLocalMap(org.apache.dubbo.common.threadlocal.InternalThreadLocalMap);
    Code:
       0: aload_0
       1: aload_1
       2: putfield      #9                  // Field threadLocalMap:Lorg/apache/dubbo/common/threadlocal/InternalThreadLocalMap;
       5: return
}
