Compiled from "InternalRunnable.java"
public class org.apache.dubbo.common.threadlocal.InternalRunnable implements java.lang.Runnable {
  private final java.lang.Runnable runnable;

  public org.apache.dubbo.common.threadlocal.InternalRunnable(java.lang.Runnable);
    Code:
       0: aload_0
       1: invokespecial #1                  // Method java/lang/Object."<init>":()V
       4: aload_0
       5: aload_1
       6: putfield      #2                  // Field runnable:Ljava/lang/Runnable;
       9: return

  public void run();
    Code:
       0: aload_0
       1: getfield      #2                  // Field runnable:Ljava/lang/Runnable;
       4: invokeinterface #3,  1            // InterfaceMethod java/lang/Runnable.run:()V
       9: invokestatic  #4                  // Method org/apache/dubbo/common/threadlocal/InternalThreadLocal.removeAll:()V
      12: goto          21
      15: astore_1
      16: invokestatic  #4                  // Method org/apache/dubbo/common/threadlocal/InternalThreadLocal.removeAll:()V
      19: aload_1
      20: athrow
      21: return
    Exception table:
       from    to  target type
           0     9    15   any

  public static java.lang.Runnable Wrap(java.lang.Runnable);
    Code:
       0: aload_0
       1: instanceof    #5                  // class org/apache/dubbo/common/threadlocal/InternalRunnable
       4: ifeq          11
       7: aload_0
       8: goto          19
      11: new           #5                  // class org/apache/dubbo/common/threadlocal/InternalRunnable
      14: dup
      15: aload_0
      16: invokespecial #6                  // Method "<init>":(Ljava/lang/Runnable;)V
      19: areturn
}
