Compiled from "InternalThreadLocal.java"
public class org.apache.dubbo.common.threadlocal.InternalThreadLocal<V> extends java.lang.ThreadLocal<V> {
  private static final int VARIABLES_TO_REMOVE_INDEX;

  private final int index;

  public org.apache.dubbo.common.threadlocal.InternalThreadLocal();
    Code:
       0: aload_0
       1: invokespecial #1                  // Method java/lang/ThreadLocal."<init>":()V
       4: aload_0
       5: invokestatic  #2                  // Method org/apache/dubbo/common/threadlocal/InternalThreadLocalMap.nextVariableIndex:()I
       8: putfield      #3                  // Field index:I
      11: return

  public static void removeAll();
    Code:
       0: invokestatic  #4                  // Method org/apache/dubbo/common/threadlocal/InternalThreadLocalMap.getIfSet:()Lorg/apache/dubbo/common/threadlocal/InternalThreadLocalMap;
       3: astore_0
       4: aload_0
       5: ifnonnull     9
       8: return
       9: aload_0
      10: getstatic     #5                  // Field VARIABLES_TO_REMOVE_INDEX:I
      13: invokevirtual #6                  // Method org/apache/dubbo/common/threadlocal/InternalThreadLocalMap.indexedVariable:(I)Ljava/lang/Object;
      16: astore_1
      17: aload_1
      18: ifnull        84
      21: aload_1
      22: getstatic     #7                  // Field org/apache/dubbo/common/threadlocal/InternalThreadLocalMap.UNSET:Ljava/lang/Object;
      25: if_acmpeq     84
      28: aload_1
      29: checkcast     #8                  // class java/util/Set
      32: astore_2
      33: aload_2
      34: iconst_0
      35: anewarray     #9                  // class org/apache/dubbo/common/threadlocal/InternalThreadLocal
      38: invokeinterface #10,  2           // InterfaceMethod java/util/Set.toArray:([Ljava/lang/Object;)[Ljava/lang/Object;
      43: checkcast     #11                 // class "[Lorg/apache/dubbo/common/threadlocal/InternalThreadLocal;"
      46: astore_3
      47: aload_3
      48: astore        4
      50: aload         4
      52: arraylength
      53: istore        5
      55: iconst_0
      56: istore        6
      58: iload         6
      60: iload         5
      62: if_icmpge     84
      65: aload         4
      67: iload         6
      69: aaload
      70: astore        7
      72: aload         7
      74: aload_0
      75: invokevirtual #12                 // Method remove:(Lorg/apache/dubbo/common/threadlocal/InternalThreadLocalMap;)V
      78: iinc          6, 1
      81: goto          58
      84: invokestatic  #13                 // Method org/apache/dubbo/common/threadlocal/InternalThreadLocalMap.remove:()V
      87: goto          98
      90: astore        8
      92: invokestatic  #13                 // Method org/apache/dubbo/common/threadlocal/InternalThreadLocalMap.remove:()V
      95: aload         8
      97: athrow
      98: return
    Exception table:
       from    to  target type
           9    84    90   any
          90    92    90   any

  public static int size();
    Code:
       0: invokestatic  #4                  // Method org/apache/dubbo/common/threadlocal/InternalThreadLocalMap.getIfSet:()Lorg/apache/dubbo/common/threadlocal/InternalThreadLocalMap;
       3: astore_0
       4: aload_0
       5: ifnonnull     10
       8: iconst_0
       9: ireturn
      10: aload_0
      11: invokevirtual #14                 // Method org/apache/dubbo/common/threadlocal/InternalThreadLocalMap.size:()I
      14: ireturn

  public static void destroy();
    Code:
       0: invokestatic  #15                 // Method org/apache/dubbo/common/threadlocal/InternalThreadLocalMap.destroy:()V
       3: return

  private static void addToVariablesToRemove(org.apache.dubbo.common.threadlocal.InternalThreadLocalMap, org.apache.dubbo.common.threadlocal.InternalThreadLocal<?>);
    Code:
       0: aload_0
       1: getstatic     #5                  // Field VARIABLES_TO_REMOVE_INDEX:I
       4: invokevirtual #6                  // Method org/apache/dubbo/common/threadlocal/InternalThreadLocalMap.indexedVariable:(I)Ljava/lang/Object;
       7: astore_2
       8: aload_2
       9: getstatic     #7                  // Field org/apache/dubbo/common/threadlocal/InternalThreadLocalMap.UNSET:Ljava/lang/Object;
      12: if_acmpeq     19
      15: aload_2
      16: ifnonnull     42
      19: new           #16                 // class java/util/IdentityHashMap
      22: dup
      23: invokespecial #17                 // Method java/util/IdentityHashMap."<init>":()V
      26: invokestatic  #18                 // Method java/util/Collections.newSetFromMap:(Ljava/util/Map;)Ljava/util/Set;
      29: astore_3
      30: aload_0
      31: getstatic     #5                  // Field VARIABLES_TO_REMOVE_INDEX:I
      34: aload_3
      35: invokevirtual #19                 // Method org/apache/dubbo/common/threadlocal/InternalThreadLocalMap.setIndexedVariable:(ILjava/lang/Object;)Z
      38: pop
      39: goto          47
      42: aload_2
      43: checkcast     #8                  // class java/util/Set
      46: astore_3
      47: aload_3
      48: aload_1
      49: invokeinterface #20,  2           // InterfaceMethod java/util/Set.add:(Ljava/lang/Object;)Z
      54: pop
      55: return

  private static void removeFromVariablesToRemove(org.apache.dubbo.common.threadlocal.InternalThreadLocalMap, org.apache.dubbo.common.threadlocal.InternalThreadLocal<?>);
    Code:
       0: aload_0
       1: getstatic     #5                  // Field VARIABLES_TO_REMOVE_INDEX:I
       4: invokevirtual #6                  // Method org/apache/dubbo/common/threadlocal/InternalThreadLocalMap.indexedVariable:(I)Ljava/lang/Object;
       7: astore_2
       8: aload_2
       9: getstatic     #7                  // Field org/apache/dubbo/common/threadlocal/InternalThreadLocalMap.UNSET:Ljava/lang/Object;
      12: if_acmpeq     19
      15: aload_2
      16: ifnonnull     20
      19: return
      20: aload_2
      21: checkcast     #8                  // class java/util/Set
      24: astore_3
      25: aload_3
      26: aload_1
      27: invokeinterface #21,  2           // InterfaceMethod java/util/Set.remove:(Ljava/lang/Object;)Z
      32: pop
      33: return

  public final V get();
    Code:
       0: invokestatic  #22                 // Method org/apache/dubbo/common/threadlocal/InternalThreadLocalMap.get:()Lorg/apache/dubbo/common/threadlocal/InternalThreadLocalMap;
       3: astore_1
       4: aload_1
       5: aload_0
       6: getfield      #3                  // Field index:I
       9: invokevirtual #6                  // Method org/apache/dubbo/common/threadlocal/InternalThreadLocalMap.indexedVariable:(I)Ljava/lang/Object;
      12: astore_2
      13: aload_2
      14: getstatic     #7                  // Field org/apache/dubbo/common/threadlocal/InternalThreadLocalMap.UNSET:Ljava/lang/Object;
      17: if_acmpeq     22
      20: aload_2
      21: areturn
      22: aload_0
      23: aload_1
      24: invokespecial #23                 // Method initialize:(Lorg/apache/dubbo/common/threadlocal/InternalThreadLocalMap;)Ljava/lang/Object;
      27: areturn

  public final V getWithoutInitialize();
    Code:
       0: invokestatic  #22                 // Method org/apache/dubbo/common/threadlocal/InternalThreadLocalMap.get:()Lorg/apache/dubbo/common/threadlocal/InternalThreadLocalMap;
       3: astore_1
       4: aload_1
       5: aload_0
       6: getfield      #3                  // Field index:I
       9: invokevirtual #6                  // Method org/apache/dubbo/common/threadlocal/InternalThreadLocalMap.indexedVariable:(I)Ljava/lang/Object;
      12: astore_2
      13: aload_2
      14: getstatic     #7                  // Field org/apache/dubbo/common/threadlocal/InternalThreadLocalMap.UNSET:Ljava/lang/Object;
      17: if_acmpeq     22
      20: aload_2
      21: areturn
      22: aconst_null
      23: areturn

  private V initialize(org.apache.dubbo.common.threadlocal.InternalThreadLocalMap);
    Code:
       0: aconst_null
       1: astore_2
       2: aload_0
       3: invokevirtual #24                 // Method initialValue:()Ljava/lang/Object;
       6: astore_2
       7: goto          20
      10: astore_3
      11: new           #26                 // class java/lang/RuntimeException
      14: dup
      15: aload_3
      16: invokespecial #27                 // Method java/lang/RuntimeException."<init>":(Ljava/lang/Throwable;)V
      19: athrow
      20: aload_1
      21: aload_0
      22: getfield      #3                  // Field index:I
      25: aload_2
      26: invokevirtual #19                 // Method org/apache/dubbo/common/threadlocal/InternalThreadLocalMap.setIndexedVariable:(ILjava/lang/Object;)Z
      29: pop
      30: aload_1
      31: aload_0
      32: invokestatic  #28                 // Method addToVariablesToRemove:(Lorg/apache/dubbo/common/threadlocal/InternalThreadLocalMap;Lorg/apache/dubbo/common/threadlocal/InternalThreadLocal;)V
      35: aload_2
      36: areturn
    Exception table:
       from    to  target type
           2     7    10   Class java/lang/Exception

  public final void set(V);
    Code:
       0: aload_1
       1: ifnull        11
       4: aload_1
       5: getstatic     #7                  // Field org/apache/dubbo/common/threadlocal/InternalThreadLocalMap.UNSET:Ljava/lang/Object;
       8: if_acmpne     18
      11: aload_0
      12: invokevirtual #29                 // Method remove:()V
      15: goto          39
      18: invokestatic  #22                 // Method org/apache/dubbo/common/threadlocal/InternalThreadLocalMap.get:()Lorg/apache/dubbo/common/threadlocal/InternalThreadLocalMap;
      21: astore_2
      22: aload_2
      23: aload_0
      24: getfield      #3                  // Field index:I
      27: aload_1
      28: invokevirtual #19                 // Method org/apache/dubbo/common/threadlocal/InternalThreadLocalMap.setIndexedVariable:(ILjava/lang/Object;)Z
      31: ifeq          39
      34: aload_2
      35: aload_0
      36: invokestatic  #28                 // Method addToVariablesToRemove:(Lorg/apache/dubbo/common/threadlocal/InternalThreadLocalMap;Lorg/apache/dubbo/common/threadlocal/InternalThreadLocal;)V
      39: return

  public final void remove();
    Code:
       0: aload_0
       1: invokestatic  #4                  // Method org/apache/dubbo/common/threadlocal/InternalThreadLocalMap.getIfSet:()Lorg/apache/dubbo/common/threadlocal/InternalThreadLocalMap;
       4: invokevirtual #12                 // Method remove:(Lorg/apache/dubbo/common/threadlocal/InternalThreadLocalMap;)V
       7: return

  public final void remove(org.apache.dubbo.common.threadlocal.InternalThreadLocalMap);
    Code:
       0: aload_1
       1: ifnonnull     5
       4: return
       5: aload_1
       6: aload_0
       7: getfield      #3                  // Field index:I
      10: invokevirtual #30                 // Method org/apache/dubbo/common/threadlocal/InternalThreadLocalMap.removeIndexedVariable:(I)Ljava/lang/Object;
      13: astore_2
      14: aload_1
      15: aload_0
      16: invokestatic  #31                 // Method removeFromVariablesToRemove:(Lorg/apache/dubbo/common/threadlocal/InternalThreadLocalMap;Lorg/apache/dubbo/common/threadlocal/InternalThreadLocal;)V
      19: aload_2
      20: getstatic     #7                  // Field org/apache/dubbo/common/threadlocal/InternalThreadLocalMap.UNSET:Ljava/lang/Object;
      23: if_acmpeq     44
      26: aload_0
      27: aload_2
      28: invokevirtual #32                 // Method onRemoval:(Ljava/lang/Object;)V
      31: goto          44
      34: astore_3
      35: new           #26                 // class java/lang/RuntimeException
      38: dup
      39: aload_3
      40: invokespecial #27                 // Method java/lang/RuntimeException."<init>":(Ljava/lang/Throwable;)V
      43: athrow
      44: return
    Exception table:
       from    to  target type
          26    31    34   Class java/lang/Exception

  protected V initialValue();
    Code:
       0: aconst_null
       1: areturn

  protected void onRemoval(V) throws java.lang.Exception;
    Code:
       0: return

  static {};
    Code:
       0: invokestatic  #2                  // Method org/apache/dubbo/common/threadlocal/InternalThreadLocalMap.nextVariableIndex:()I
       3: putstatic     #5                  // Field VARIABLES_TO_REMOVE_INDEX:I
       6: return
}
