Compiled from "NamedInternalThreadFactory.java"
public class org.apache.dubbo.common.threadlocal.NamedInternalThreadFactory extends org.apache.dubbo.common.utils.NamedThreadFactory {
  public org.apache.dubbo.common.threadlocal.NamedInternalThreadFactory();
    Code:
       0: aload_0
       1: invokespecial #1                  // Method org/apache/dubbo/common/utils/NamedThreadFactory."<init>":()V
       4: return

  public org.apache.dubbo.common.threadlocal.NamedInternalThreadFactory(java.lang.String);
    Code:
       0: aload_0
       1: aload_1
       2: iconst_0
       3: invokespecial #2                  // Method org/apache/dubbo/common/utils/NamedThreadFactory."<init>":(Ljava/lang/String;Z)V
       6: return

  public org.apache.dubbo.common.threadlocal.NamedInternalThreadFactory(java.lang.String, boolean);
    Code:
       0: aload_0
       1: aload_1
       2: iload_2
       3: invokespecial #2                  // Method org/apache/dubbo/common/utils/NamedThreadFactory."<init>":(Ljava/lang/String;Z)V
       6: return

  public java.lang.Thread newThread(java.lang.Runnable);
    Code:
       0: new           #3                  // class java/lang/StringBuilder
       3: dup
       4: invokespecial #4                  // Method java/lang/StringBuilder."<init>":()V
       7: aload_0
       8: getfield      #5                  // Field mPrefix:Ljava/lang/String;
      11: invokevirtual #6                  // Method java/lang/StringBuilder.append:(Ljava/lang/String;)Ljava/lang/StringBuilder;
      14: aload_0
      15: getfield      #7                  // Field mThreadNum:Ljava/util/concurrent/atomic/AtomicInteger;
      18: invokevirtual #8                  // Method java/util/concurrent/atomic/AtomicInteger.getAndIncrement:()I
      21: invokevirtual #9                  // Method java/lang/StringBuilder.append:(I)Ljava/lang/StringBuilder;
      24: invokevirtual #10                 // Method java/lang/StringBuilder.toString:()Ljava/lang/String;
      27: astore_2
      28: new           #11                 // class org/apache/dubbo/common/threadlocal/InternalThread
      31: dup
      32: aload_0
      33: getfield      #12                 // Field mGroup:Ljava/lang/ThreadGroup;
      36: aload_1
      37: invokestatic  #13                 // Method org/apache/dubbo/common/threadlocal/InternalRunnable.Wrap:(Ljava/lang/Runnable;)Ljava/lang/Runnable;
      40: aload_2
      41: lconst_0
      42: invokespecial #14                 // Method org/apache/dubbo/common/threadlocal/InternalThread."<init>":(Ljava/lang/ThreadGroup;Ljava/lang/Runnable;Ljava/lang/String;J)V
      45: astore_3
      46: aload_3
      47: aload_0
      48: getfield      #15                 // Field mDaemon:Z
      51: invokevirtual #16                 // Method org/apache/dubbo/common/threadlocal/InternalThread.setDaemon:(Z)V
      54: aload_3
      55: areturn
}
