Compiled from "URLConnectionClientFactory.java"
public class org.apache.dubbo.remoting.http.factory.impl.URLConnectionClientFactory extends org.apache.dubbo.remoting.http.factory.AbstractHttpClientFactory {
  public org.apache.dubbo.remoting.http.factory.impl.URLConnectionClientFactory();
    Code:
       0: aload_0
       1: invokespecial #1                  // Method org/apache/dubbo/remoting/http/factory/AbstractHttpClientFactory."<init>":()V
       4: return

  protected org.apache.dubbo.remoting.http.RestClient doCreateRestClient(org.apache.dubbo.common.URL) throws org.apache.dubbo.rpc.RpcException;
    Code:
       0: new           #2                  // class org/apache/dubbo/remoting/http/restclient/URLConnectionRestClient
       3: dup
       4: aload_0
       5: getfield      #3                  // Field httpClientConfig:Lorg/apache/dubbo/remoting/http/config/HttpClientConfig;
       8: invokespecial #4                  // Method org/apache/dubbo/remoting/http/restclient/URLConnectionRestClient."<init>":(Lorg/apache/dubbo/remoting/http/config/HttpClientConfig;)V
      11: areturn
}
