Compiled from "HttpConnectionCreateContext.java"
public class org.apache.dubbo.rpc.protocol.rest.annotation.consumer.HttpConnectionCreateContext {
  private org.apache.dubbo.remoting.http.RequestTemplate requestTemplate;

  private org.apache.dubbo.metadata.rest.RestMethodMetadata restMethodMetadata;

  private org.apache.dubbo.metadata.rest.ServiceRestMetadata serviceRestMetadata;

  private org.apache.dubbo.rpc.Invocation invocation;

  private org.apache.dubbo.common.URL url;

  public org.apache.dubbo.rpc.protocol.rest.annotation.consumer.HttpConnectionCreateContext();
    Code:
       0: aload_0
       1: invokespecial #1                  // Method java/lang/Object."<init>":()V
       4: return

  public void setRequestTemplate(org.apache.dubbo.remoting.http.RequestTemplate);
    Code:
       0: aload_0
       1: aload_1
       2: putfield      #2                  // Field requestTemplate:Lorg/apache/dubbo/remoting/http/RequestTemplate;
       5: return

  public org.apache.dubbo.remoting.http.RequestTemplate getRequestTemplate();
    Code:
       0: aload_0
       1: getfield      #2                  // Field requestTemplate:Lorg/apache/dubbo/remoting/http/RequestTemplate;
       4: areturn

  public org.apache.dubbo.metadata.rest.ServiceRestMetadata getServiceRestMetadata();
    Code:
       0: aload_0
       1: getfield      #3                  // Field serviceRestMetadata:Lorg/apache/dubbo/metadata/rest/ServiceRestMetadata;
       4: areturn

  public org.apache.dubbo.metadata.rest.RestMethodMetadata getRestMethodMetadata();
    Code:
       0: aload_0
       1: getfield      #4                  // Field restMethodMetadata:Lorg/apache/dubbo/metadata/rest/RestMethodMetadata;
       4: areturn

  public void setRestMethodMetadata(org.apache.dubbo.metadata.rest.RestMethodMetadata);
    Code:
       0: aload_0
       1: aload_1
       2: putfield      #4                  // Field restMethodMetadata:Lorg/apache/dubbo/metadata/rest/RestMethodMetadata;
       5: return

  public org.apache.dubbo.rpc.Invocation getInvocation();
    Code:
       0: aload_0
       1: getfield      #5                  // Field invocation:Lorg/apache/dubbo/rpc/Invocation;
       4: areturn

  public void setInvocation(org.apache.dubbo.rpc.Invocation);
    Code:
       0: aload_0
       1: aload_1
       2: putfield      #5                  // Field invocation:Lorg/apache/dubbo/rpc/Invocation;
       5: return

  public org.apache.dubbo.common.URL getUrl();
    Code:
       0: aload_0
       1: getfield      #6                  // Field url:Lorg/apache/dubbo/common/URL;
       4: areturn

  public void setUrl(org.apache.dubbo.common.URL);
    Code:
       0: aload_0
       1: aload_1
       2: putfield      #6                  // Field url:Lorg/apache/dubbo/common/URL;
       5: return

  public void setServiceRestMetadata(org.apache.dubbo.metadata.rest.ServiceRestMetadata);
    Code:
       0: aload_0
       1: aload_1
       2: putfield      #3                  // Field serviceRestMetadata:Lorg/apache/dubbo/metadata/rest/ServiceRestMetadata;
       5: return
}
