Compiled from "RSocketPortInfoApplicationContextInitializer.java"
class org.springframework.boot.rsocket.context.RSocketPortInfoApplicationContextInitializer$Listener implements org.springframework.context.ApplicationListener<org.springframework.boot.rsocket.context.RSocketServerInitializedEvent> {
  private static final java.lang.String PROPERTY_NAME;

  private final org.springframework.context.ConfigurableApplicationContext applicationContext;

  org.springframework.boot.rsocket.context.RSocketPortInfoApplicationContextInitializer$Listener(org.springframework.context.ConfigurableApplicationContext);
    Code:
       0: aload_0
       1: invokespecial #1                  // Method java/lang/Object."<init>":()V
       4: aload_0
       5: aload_1
       6: putfield      #7                  // Field applicationContext:Lorg/springframework/context/ConfigurableApplicationContext;
       9: return

  public void onApplicationEvent(org.springframework.boot.rsocket.context.RSocketServerInitializedEvent);
    Code:
       0: aload_1
       1: invokevirtual #13                 // Method org/springframework/boot/rsocket/context/RSocketServerInitializedEvent.getServer:()Lorg/springframework/boot/rsocket/server/RSocketServer;
       4: invokeinterface #19,  1           // InterfaceMethod org/springframework/boot/rsocket/server/RSocketServer.address:()Ljava/net/InetSocketAddress;
       9: ifnull        32
      12: aload_0
      13: aload_0
      14: getfield      #7                  // Field applicationContext:Lorg/springframework/context/ConfigurableApplicationContext;
      17: aload_1
      18: invokevirtual #13                 // Method org/springframework/boot/rsocket/context/RSocketServerInitializedEvent.getServer:()Lorg/springframework/boot/rsocket/server/RSocketServer;
      21: invokeinterface #19,  1           // InterfaceMethod org/springframework/boot/rsocket/server/RSocketServer.address:()Ljava/net/InetSocketAddress;
      26: invokevirtual #25                 // Method java/net/InetSocketAddress.getPort:()I
      29: invokevirtual #31                 // Method setPortProperty:(Lorg/springframework/context/ApplicationContext;I)V
      32: return

  private void setPortProperty(org.springframework.context.ApplicationContext, int);
    Code:
       0: aload_1
       1: instanceof    #35                 // class org/springframework/context/ConfigurableApplicationContext
       4: ifeq          23
       7: aload_1
       8: checkcast     #35                 // class org/springframework/context/ConfigurableApplicationContext
      11: astore_3
      12: aload_0
      13: aload_3
      14: invokeinterface #37,  1           // InterfaceMethod org/springframework/context/ConfigurableApplicationContext.getEnvironment:()Lorg/springframework/core/env/ConfigurableEnvironment;
      19: iload_2
      20: invokevirtual #41                 // Method setPortProperty:(Lorg/springframework/core/env/ConfigurableEnvironment;I)V
      23: aload_1
      24: invokeinterface #44,  1           // InterfaceMethod org/springframework/context/ApplicationContext.getParent:()Lorg/springframework/context/ApplicationContext;
      29: ifnull        43
      32: aload_0
      33: aload_1
      34: invokeinterface #44,  1           // InterfaceMethod org/springframework/context/ApplicationContext.getParent:()Lorg/springframework/context/ApplicationContext;
      39: iload_2
      40: invokevirtual #31                 // Method setPortProperty:(Lorg/springframework/context/ApplicationContext;I)V
      43: return

  private void setPortProperty(org.springframework.core.env.ConfigurableEnvironment, int);
    Code:
       0: aload_1
       1: invokeinterface #50,  1           // InterfaceMethod org/springframework/core/env/ConfigurableEnvironment.getPropertySources:()Lorg/springframework/core/env/MutablePropertySources;
       6: astore_3
       7: aload_3
       8: ldc           #56                 // String server.ports
      10: invokevirtual #58                 // Method org/springframework/core/env/MutablePropertySources.get:(Ljava/lang/String;)Lorg/springframework/core/env/PropertySource;
      13: astore        4
      15: aload         4
      17: ifnonnull     44
      20: new           #64                 // class org/springframework/core/env/MapPropertySource
      23: dup
      24: ldc           #56                 // String server.ports
      26: new           #66                 // class java/util/HashMap
      29: dup
      30: invokespecial #68                 // Method java/util/HashMap."<init>":()V
      33: invokespecial #69                 // Method org/springframework/core/env/MapPropertySource."<init>":(Ljava/lang/String;Ljava/util/Map;)V
      36: astore        4
      38: aload_3
      39: aload         4
      41: invokevirtual #72                 // Method org/springframework/core/env/MutablePropertySources.addFirst:(Lorg/springframework/core/env/PropertySource;)V
      44: aload_0
      45: iload_2
      46: aload         4
      48: invokevirtual #76                 // Method setPortProperty:(ILorg/springframework/core/env/PropertySource;)V
      51: return

  private void setPortProperty(int, org.springframework.core.env.PropertySource<?>);
    Code:
       0: aload_2
       1: invokevirtual #79                 // Method org/springframework/core/env/PropertySource.getSource:()Ljava/lang/Object;
       4: checkcast     #85                 // class java/util/Map
       7: ldc           #87                 // String local.rsocket.server.port
       9: iload_1
      10: invokestatic  #89                 // Method java/lang/Integer.valueOf:(I)Ljava/lang/Integer;
      13: invokeinterface #95,  3           // InterfaceMethod java/util/Map.put:(Ljava/lang/Object;Ljava/lang/Object;)Ljava/lang/Object;
      18: pop
      19: return

  public void onApplicationEvent(org.springframework.context.ApplicationEvent);
    Code:
       0: aload_0
       1: aload_1
       2: checkcast     #14                 // class org/springframework/boot/rsocket/context/RSocketServerInitializedEvent
       5: invokevirtual #99                 // Method onApplicationEvent:(Lorg/springframework/boot/rsocket/context/RSocketServerInitializedEvent;)V
       8: return
}
