Compiled from "AbstractBeansOfTypeDatabaseInitializerDetector.java"
public abstract class org.springframework.boot.sql.init.dependency.AbstractBeansOfTypeDatabaseInitializerDetector implements org.springframework.boot.sql.init.dependency.DatabaseInitializerDetector {
  public org.springframework.boot.sql.init.dependency.AbstractBeansOfTypeDatabaseInitializerDetector();
    Code:
       0: aload_0
       1: invokespecial #1                  // Method java/lang/Object."<init>":()V
       4: return

  public java.util.Set<java.lang.String> detect(org.springframework.beans.factory.config.ConfigurableListableBeanFactory);
    Code:
       0: aload_0
       1: invokevirtual #7                  // Method getDatabaseInitializerBeanTypes:()Ljava/util/Set;
       4: astore_2
       5: new           #13                 // class org/springframework/boot/sql/init/dependency/BeansOfTypeDetector
       8: dup
       9: aload_2
      10: invokespecial #15                 // Method org/springframework/boot/sql/init/dependency/BeansOfTypeDetector."<init>":(Ljava/util/Set;)V
      13: aload_1
      14: invokevirtual #18                 // Method org/springframework/boot/sql/init/dependency/BeansOfTypeDetector.detect:(Lorg/springframework/beans/factory/ListableBeanFactory;)Ljava/util/Set;
      17: areturn
      18: astore_2
      19: invokestatic  #24                 // Method java/util/Collections.emptySet:()Ljava/util/Set;
      22: areturn
    Exception table:
       from    to  target type
           0    17    18   Class java/lang/Throwable

  protected abstract java.util.Set<java.lang.Class<?>> getDatabaseInitializerBeanTypes();
}
