Compiled from "AnnotationDependsOnDatabaseInitializationDetector.java"
class org.springframework.boot.sql.init.dependency.AnnotationDependsOnDatabaseInitializationDetector implements org.springframework.boot.sql.init.dependency.DependsOnDatabaseInitializationDetector {
  org.springframework.boot.sql.init.dependency.AnnotationDependsOnDatabaseInitializationDetector();
    Code:
       0: aload_0
       1: invokespecial #1                  // Method java/lang/Object."<init>":()V
       4: return

  public java.util.Set<java.lang.String> detect(org.springframework.beans.factory.config.ConfigurableListableBeanFactory);
    Code:
       0: new           #7                  // class java/util/HashSet
       3: dup
       4: invokespecial #9                  // Method java/util/HashSet."<init>":()V
       7: astore_2
       8: aload_1
       9: invokeinterface #10,  1           // InterfaceMethod org/springframework/beans/factory/config/ConfigurableListableBeanFactory.getBeanDefinitionNames:()[Ljava/lang/String;
      14: astore_3
      15: aload_3
      16: arraylength
      17: istore        4
      19: iconst_0
      20: istore        5
      22: iload         5
      24: iload         4
      26: if_icmpge     64
      29: aload_3
      30: iload         5
      32: aaload
      33: astore        6
      35: aload_1
      36: aload         6
      38: ldc           #16                 // class org/springframework/boot/sql/init/dependency/DependsOnDatabaseInitialization
      40: iconst_0
      41: invokeinterface #18,  4           // InterfaceMethod org/springframework/beans/factory/config/ConfigurableListableBeanFactory.findAnnotationOnBean:(Ljava/lang/String;Ljava/lang/Class;Z)Ljava/lang/annotation/Annotation;
      46: ifnull        58
      49: aload_2
      50: aload         6
      52: invokeinterface #22,  2           // InterfaceMethod java/util/Set.add:(Ljava/lang/Object;)Z
      57: pop
      58: iinc          5, 1
      61: goto          22
      64: aload_2
      65: areturn
}
