Compiled from "BeansOfTypeDetector.java"
class org.springframework.boot.sql.init.dependency.BeansOfTypeDetector {
  private final java.util.Set<java.lang.Class<?>> types;

  org.springframework.boot.sql.init.dependency.BeansOfTypeDetector(java.util.Set<java.lang.Class<?>>);
    Code:
       0: aload_0
       1: invokespecial #1                  // Method java/lang/Object."<init>":()V
       4: aload_0
       5: aload_1
       6: putfield      #7                  // Field types:Ljava/util/Set;
       9: return

  java.util.Set<java.lang.String> detect(org.springframework.beans.factory.ListableBeanFactory);
    Code:
       0: new           #13                 // class java/util/HashSet
       3: dup
       4: invokespecial #15                 // Method java/util/HashSet."<init>":()V
       7: astore_2
       8: aload_0
       9: getfield      #7                  // Field types:Ljava/util/Set;
      12: invokeinterface #16,  1           // InterfaceMethod java/util/Set.iterator:()Ljava/util/Iterator;
      17: astore_3
      18: aload_3
      19: invokeinterface #22,  1           // InterfaceMethod java/util/Iterator.hasNext:()Z
      24: ifeq          89
      27: aload_3
      28: invokeinterface #28,  1           // InterfaceMethod java/util/Iterator.next:()Ljava/lang/Object;
      33: checkcast     #32                 // class java/lang/Class
      36: astore        4
      38: aload_1
      39: aload         4
      41: iconst_1
      42: iconst_0
      43: invokeinterface #34,  4           // InterfaceMethod org/springframework/beans/factory/ListableBeanFactory.getBeanNamesForType:(Ljava/lang/Class;ZZ)[Ljava/lang/String;
      48: astore        5
      50: aload         5
      52: invokestatic  #40                 // Method java/util/Arrays.stream:([Ljava/lang/Object;)Ljava/util/stream/Stream;
      55: invokedynamic #46,  0             // InvokeDynamic #0:apply:()Ljava/util/function/Function;
      60: invokeinterface #50,  2           // InterfaceMethod java/util/stream/Stream.map:(Ljava/util/function/Function;)Ljava/util/stream/Stream;
      65: aload_2
      66: dup
      67: invokestatic  #56                 // Method java/util/Objects.requireNonNull:(Ljava/lang/Object;)Ljava/lang/Object;
      70: pop
      71: invokedynamic #62,  0             // InvokeDynamic #1:accept:(Ljava/util/Set;)Ljava/util/function/Consumer;
      76: invokeinterface #66,  2           // InterfaceMethod java/util/stream/Stream.forEach:(Ljava/util/function/Consumer;)V
      81: goto          86
      84: astore        5
      86: goto          18
      89: aload_2
      90: areturn
    Exception table:
       from    to  target type
          38    81    84   Class java/lang/Throwable
}
