Compiled from "DatabaseInitializationDependencyConfigurer.java"
class org.springframework.boot.sql.init.dependency.DatabaseInitializationDependencyConfigurer$DependsOnDatabaseInitializationPostProcessor implements org.springframework.beans.factory.config.BeanFactoryPostProcessor,org.springframework.context.EnvironmentAware,org.springframework.core.Ordered {
  private org.springframework.core.env.Environment environment;

  org.springframework.boot.sql.init.dependency.DatabaseInitializationDependencyConfigurer$DependsOnDatabaseInitializationPostProcessor();
    Code:
       0: aload_0
       1: invokespecial #1                  // Method java/lang/Object."<init>":()V
       4: return

  public void setEnvironment(org.springframework.core.env.Environment);
    Code:
       0: aload_0
       1: aload_1
       2: putfield      #7                  // Field environment:Lorg/springframework/core/env/Environment;
       5: return

  public int getOrder();
    Code:
       0: iconst_0
       1: ireturn

  public void postProcessBeanFactory(org.springframework.beans.factory.config.ConfigurableListableBeanFactory);
    Code:
       0: invokestatic  #13                 // Method org/springframework/aot/AotDetector.useGeneratedArtifacts:()Z
       3: ifeq          7
       6: return
       7: aload_0
       8: aload_1
       9: invokevirtual #19                 // Method detectInitializerBeanNames:(Lorg/springframework/beans/factory/config/ConfigurableListableBeanFactory;)Lorg/springframework/boot/sql/init/dependency/DatabaseInitializationDependencyConfigurer$DependsOnDatabaseInitializationPostProcessor$InitializerBeanNames;
      12: astore_2
      13: aload_2
      14: invokevirtual #23                 // Method org/springframework/boot/sql/init/dependency/DatabaseInitializationDependencyConfigurer$DependsOnDatabaseInitializationPostProcessor$InitializerBeanNames.isEmpty:()Z
      17: ifeq          21
      20: return
      21: aconst_null
      22: astore_3
      23: aload_2
      24: invokevirtual #28                 // Method org/springframework/boot/sql/init/dependency/DatabaseInitializationDependencyConfigurer$DependsOnDatabaseInitializationPostProcessor$InitializerBeanNames.batchedBeanNames:()Ljava/lang/Iterable;
      27: invokeinterface #32,  1           // InterfaceMethod java/lang/Iterable.iterator:()Ljava/util/Iterator;
      32: astore        4
      34: aload         4
      36: invokeinterface #38,  1           // InterfaceMethod java/util/Iterator.hasNext:()Z
      41: ifeq          123
      44: aload         4
      46: invokeinterface #43,  1           // InterfaceMethod java/util/Iterator.next:()Ljava/lang/Object;
      51: checkcast     #47                 // class java/util/Set
      54: astore        5
      56: aload         5
      58: invokeinterface #49,  1           // InterfaceMethod java/util/Set.iterator:()Ljava/util/Iterator;
      63: astore        6
      65: aload         6
      67: invokeinterface #38,  1           // InterfaceMethod java/util/Iterator.hasNext:()Z
      72: ifeq          117
      75: aload         6
      77: invokeinterface #43,  1           // InterfaceMethod java/util/Iterator.next:()Ljava/lang/Object;
      82: checkcast     #50                 // class java/lang/String
      85: astore        7
      87: aload         7
      89: aload_1
      90: invokestatic  #52                 // Method getBeanDefinition:(Ljava/lang/String;Lorg/springframework/beans/factory/config/ConfigurableListableBeanFactory;)Lorg/springframework/beans/factory/config/BeanDefinition;
      93: astore        8
      95: aload         8
      97: aload_0
      98: aload         8
     100: invokeinterface #56,  1           // InterfaceMethod org/springframework/beans/factory/config/BeanDefinition.getDependsOn:()[Ljava/lang/String;
     105: aload_3
     106: invokevirtual #62                 // Method merge:([Ljava/lang/String;Ljava/util/Set;)[Ljava/lang/String;
     109: invokeinterface #66,  2           // InterfaceMethod org/springframework/beans/factory/config/BeanDefinition.setDependsOn:([Ljava/lang/String;)V
     114: goto          65
     117: aload         5
     119: astore_3
     120: goto          34
     123: aload_0
     124: aload_1
     125: invokevirtual #70                 // Method detectDependsOnInitializationBeanNames:(Lorg/springframework/beans/factory/config/ConfigurableListableBeanFactory;)Ljava/util/Collection;
     128: invokeinterface #74,  1           // InterfaceMethod java/util/Collection.iterator:()Ljava/util/Iterator;
     133: astore        4
     135: aload         4
     137: invokeinterface #38,  1           // InterfaceMethod java/util/Iterator.hasNext:()Z
     142: ifeq          190
     145: aload         4
     147: invokeinterface #43,  1           // InterfaceMethod java/util/Iterator.next:()Ljava/lang/Object;
     152: checkcast     #50                 // class java/lang/String
     155: astore        5
     157: aload         5
     159: aload_1
     160: invokestatic  #52                 // Method getBeanDefinition:(Ljava/lang/String;Lorg/springframework/beans/factory/config/ConfigurableListableBeanFactory;)Lorg/springframework/beans/factory/config/BeanDefinition;
     163: astore        6
     165: aload         6
     167: aload_0
     168: aload         6
     170: invokeinterface #56,  1           // InterfaceMethod org/springframework/beans/factory/config/BeanDefinition.getDependsOn:()[Ljava/lang/String;
     175: aload_2
     176: invokevirtual #77                 // Method org/springframework/boot/sql/init/dependency/DatabaseInitializationDependencyConfigurer$DependsOnDatabaseInitializationPostProcessor$InitializerBeanNames.beanNames:()Ljava/util/Set;
     179: invokevirtual #62                 // Method merge:([Ljava/lang/String;Ljava/util/Set;)[Ljava/lang/String;
     182: invokeinterface #66,  2           // InterfaceMethod org/springframework/beans/factory/config/BeanDefinition.setDependsOn:([Ljava/lang/String;)V
     187: goto          135
     190: return

  private java.lang.String[] merge(java.lang.String[], java.util.Set<java.lang.String>);
    Code:
       0: aload_2
       1: invokestatic  #81                 // Method org/springframework/util/CollectionUtils.isEmpty:(Ljava/util/Collection;)Z
       4: ifeq          9
       7: aload_1
       8: areturn
       9: new           #86                 // class java/util/LinkedHashSet
      12: dup
      13: aload_1
      14: ifnull        24
      17: aload_1
      18: invokestatic  #88                 // Method java/util/Arrays.asList:([Ljava/lang/Object;)Ljava/util/List;
      21: goto          27
      24: invokestatic  #94                 // Method java/util/Collections.emptySet:()Ljava/util/Set;
      27: invokespecial #99                 // Method java/util/LinkedHashSet."<init>":(Ljava/util/Collection;)V
      30: astore_3
      31: aload_3
      32: aload_2
      33: invokeinterface #102,  2          // InterfaceMethod java/util/Set.addAll:(Ljava/util/Collection;)Z
      38: pop
      39: aload_3
      40: invokestatic  #105                // Method org/springframework/util/StringUtils.toStringArray:(Ljava/util/Collection;)[Ljava/lang/String;
      43: areturn

  private org.springframework.boot.sql.init.dependency.DatabaseInitializationDependencyConfigurer$DependsOnDatabaseInitializationPostProcessor$InitializerBeanNames detectInitializerBeanNames(org.springframework.beans.factory.config.ConfigurableListableBeanFactory);
    Code:
       0: aload_0
       1: aload_1
       2: ldc           #111                // class org/springframework/boot/sql/init/dependency/DatabaseInitializerDetector
       4: invokevirtual #113                // Method getDetectors:(Lorg/springframework/beans/factory/config/ConfigurableListableBeanFactory;Ljava/lang/Class;)Ljava/util/List;
       7: astore_2
       8: new           #24                 // class org/springframework/boot/sql/init/dependency/DatabaseInitializationDependencyConfigurer$DependsOnDatabaseInitializationPostProcessor$InitializerBeanNames
      11: dup
      12: invokespecial #117                // Method org/springframework/boot/sql/init/dependency/DatabaseInitializationDependencyConfigurer$DependsOnDatabaseInitializationPostProcessor$InitializerBeanNames."<init>":()V
      15: astore_3
      16: aload_2
      17: invokeinterface #118,  1          // InterfaceMethod java/util/List.iterator:()Ljava/util/Iterator;
      22: astore        4
      24: aload         4
      26: invokeinterface #38,  1           // InterfaceMethod java/util/Iterator.hasNext:()Z
      31: ifeq          127
      34: aload         4
      36: invokeinterface #43,  1           // InterfaceMethod java/util/Iterator.next:()Ljava/lang/Object;
      41: checkcast     #111                // class org/springframework/boot/sql/init/dependency/DatabaseInitializerDetector
      44: astore        5
      46: aload         5
      48: aload_1
      49: invokeinterface #121,  2          // InterfaceMethod org/springframework/boot/sql/init/dependency/DatabaseInitializerDetector.detect:(Lorg/springframework/beans/factory/config/ConfigurableListableBeanFactory;)Ljava/util/Set;
      54: invokeinterface #49,  1           // InterfaceMethod java/util/Set.iterator:()Ljava/util/Iterator;
      59: astore        6
      61: aload         6
      63: invokeinterface #38,  1           // InterfaceMethod java/util/Iterator.hasNext:()Z
      68: ifeq          124
      71: aload         6
      73: invokeinterface #43,  1           // InterfaceMethod java/util/Iterator.next:()Ljava/lang/Object;
      78: checkcast     #50                 // class java/lang/String
      81: astore        7
      83: aload_1
      84: aload         7
      86: invokeinterface #125,  2          // InterfaceMethod org/springframework/beans/factory/config/ConfigurableListableBeanFactory.getBeanDefinition:(Ljava/lang/String;)Lorg/springframework/beans/factory/config/BeanDefinition;
      91: astore        8
      93: aload         8
      95: ldc           #111                // class org/springframework/boot/sql/init/dependency/DatabaseInitializerDetector
      97: invokevirtual #130                // Method java/lang/Class.getName:()Ljava/lang/String;
     100: aload         5
     102: invokevirtual #136                // Method java/lang/Object.getClass:()Ljava/lang/Class;
     105: invokevirtual #130                // Method java/lang/Class.getName:()Ljava/lang/String;
     108: invokeinterface #140,  3          // InterfaceMethod org/springframework/beans/factory/config/BeanDefinition.setAttribute:(Ljava/lang/String;Ljava/lang/Object;)V
     113: aload_3
     114: aload         5
     116: aload         7
     118: invokevirtual #144                // Method org/springframework/boot/sql/init/dependency/DatabaseInitializationDependencyConfigurer$DependsOnDatabaseInitializationPostProcessor$InitializerBeanNames.detected:(Lorg/springframework/boot/sql/init/dependency/DatabaseInitializerDetector;Ljava/lang/String;)V
     121: goto          61
     124: goto          24
     127: aload_2
     128: invokeinterface #118,  1          // InterfaceMethod java/util/List.iterator:()Ljava/util/Iterator;
     133: astore        4
     135: aload         4
     137: invokeinterface #38,  1           // InterfaceMethod java/util/Iterator.hasNext:()Z
     142: ifeq          172
     145: aload         4
     147: invokeinterface #43,  1           // InterfaceMethod java/util/Iterator.next:()Ljava/lang/Object;
     152: checkcast     #111                // class org/springframework/boot/sql/init/dependency/DatabaseInitializerDetector
     155: astore        5
     157: aload         5
     159: aload_1
     160: aload_3
     161: invokevirtual #77                 // Method org/springframework/boot/sql/init/dependency/DatabaseInitializationDependencyConfigurer$DependsOnDatabaseInitializationPostProcessor$InitializerBeanNames.beanNames:()Ljava/util/Set;
     164: invokeinterface #148,  3          // InterfaceMethod org/springframework/boot/sql/init/dependency/DatabaseInitializerDetector.detectionComplete:(Lorg/springframework/beans/factory/config/ConfigurableListableBeanFactory;Ljava/util/Set;)V
     169: goto          135
     172: aload_3
     173: areturn

  private java.util.Collection<java.lang.String> detectDependsOnInitializationBeanNames(org.springframework.beans.factory.config.ConfigurableListableBeanFactory);
    Code:
       0: aload_0
       1: aload_1
       2: ldc           #152                // class org/springframework/boot/sql/init/dependency/DependsOnDatabaseInitializationDetector
       4: invokevirtual #113                // Method getDetectors:(Lorg/springframework/beans/factory/config/ConfigurableListableBeanFactory;Ljava/lang/Class;)Ljava/util/List;
       7: astore_2
       8: new           #154                // class java/util/HashSet
      11: dup
      12: invokespecial #156                // Method java/util/HashSet."<init>":()V
      15: astore_3
      16: aload_2
      17: invokeinterface #118,  1          // InterfaceMethod java/util/List.iterator:()Ljava/util/Iterator;
      22: astore        4
      24: aload         4
      26: invokeinterface #38,  1           // InterfaceMethod java/util/Iterator.hasNext:()Z
      31: ifeq          64
      34: aload         4
      36: invokeinterface #43,  1           // InterfaceMethod java/util/Iterator.next:()Ljava/lang/Object;
      41: checkcast     #152                // class org/springframework/boot/sql/init/dependency/DependsOnDatabaseInitializationDetector
      44: astore        5
      46: aload_3
      47: aload         5
      49: aload_1
      50: invokeinterface #157,  2          // InterfaceMethod org/springframework/boot/sql/init/dependency/DependsOnDatabaseInitializationDetector.detect:(Lorg/springframework/beans/factory/config/ConfigurableListableBeanFactory;)Ljava/util/Set;
      55: invokeinterface #102,  2          // InterfaceMethod java/util/Set.addAll:(Ljava/util/Collection;)Z
      60: pop
      61: goto          24
      64: aload_3
      65: areturn

  private <T> java.util.List<T> getDetectors(org.springframework.beans.factory.config.ConfigurableListableBeanFactory, java.lang.Class<T>);
    Code:
       0: ldc           #158                // class org/springframework/core/env/Environment
       2: aload_0
       3: getfield      #7                  // Field environment:Lorg/springframework/core/env/Environment;
       6: invokestatic  #160                // InterfaceMethod org/springframework/core/io/support/SpringFactoriesLoader$ArgumentResolver.of:(Ljava/lang/Class;Ljava/lang/Object;)Lorg/springframework/core/io/support/SpringFactoriesLoader$ArgumentResolver;
       9: astore_3
      10: aload_1
      11: invokeinterface #166,  1          // InterfaceMethod org/springframework/beans/factory/config/ConfigurableListableBeanFactory.getBeanClassLoader:()Ljava/lang/ClassLoader;
      16: invokestatic  #170                // Method org/springframework/core/io/support/SpringFactoriesLoader.forDefaultResourceLocation:(Ljava/lang/ClassLoader;)Lorg/springframework/core/io/support/SpringFactoriesLoader;
      19: aload_2
      20: aload_3
      21: invokevirtual #176                // Method org/springframework/core/io/support/SpringFactoriesLoader.load:(Ljava/lang/Class;Lorg/springframework/core/io/support/SpringFactoriesLoader$ArgumentResolver;)Ljava/util/List;
      24: areturn

  private static org.springframework.beans.factory.config.BeanDefinition getBeanDefinition(java.lang.String, org.springframework.beans.factory.config.ConfigurableListableBeanFactory);
    Code:
       0: aload_1
       1: aload_0
       2: invokeinterface #125,  2          // InterfaceMethod org/springframework/beans/factory/config/ConfigurableListableBeanFactory.getBeanDefinition:(Ljava/lang/String;)Lorg/springframework/beans/factory/config/BeanDefinition;
       7: areturn
       8: astore_2
       9: aload_1
      10: invokeinterface #182,  1          // InterfaceMethod org/springframework/beans/factory/config/ConfigurableListableBeanFactory.getParentBeanFactory:()Lorg/springframework/beans/factory/BeanFactory;
      15: astore_3
      16: aload_3
      17: instanceof    #126                // class org/springframework/beans/factory/config/ConfigurableListableBeanFactory
      20: ifeq          36
      23: aload_3
      24: checkcast     #126                // class org/springframework/beans/factory/config/ConfigurableListableBeanFactory
      27: astore        4
      29: aload_0
      30: aload         4
      32: invokestatic  #52                 // Method getBeanDefinition:(Ljava/lang/String;Lorg/springframework/beans/factory/config/ConfigurableListableBeanFactory;)Lorg/springframework/beans/factory/config/BeanDefinition;
      35: areturn
      36: aload_2
      37: athrow
    Exception table:
       from    to  target type
           0     7     8   Class org/springframework/beans/factory/NoSuchBeanDefinitionException
}
