Compiled from "DatabaseInitializationDependencyConfigurer.java"
public class org.springframework.boot.sql.init.dependency.DatabaseInitializationDependencyConfigurer implements org.springframework.context.annotation.ImportBeanDefinitionRegistrar {
  public org.springframework.boot.sql.init.dependency.DatabaseInitializationDependencyConfigurer();
    Code:
       0: aload_0
       1: invokespecial #1                  // Method java/lang/Object."<init>":()V
       4: return

  public void registerBeanDefinitions(org.springframework.core.type.AnnotationMetadata, org.springframework.beans.factory.support.BeanDefinitionRegistry);
    Code:
       0: ldc           #7                  // class org/springframework/boot/sql/init/dependency/DatabaseInitializationDependencyConfigurer$DependsOnDatabaseInitializationPostProcessor
       2: invokevirtual #9                  // Method java/lang/Class.getName:()Ljava/lang/String;
       5: astore_3
       6: aload_2
       7: aload_3
       8: invokeinterface #15,  2           // InterfaceMethod org/springframework/beans/factory/support/BeanDefinitionRegistry.containsBeanDefinition:(Ljava/lang/String;)Z
      13: ifne          35
      16: ldc           #7                  // class org/springframework/boot/sql/init/dependency/DatabaseInitializationDependencyConfigurer$DependsOnDatabaseInitializationPostProcessor
      18: invokestatic  #21                 // Method org/springframework/beans/factory/support/BeanDefinitionBuilder.rootBeanDefinition:(Ljava/lang/Class;)Lorg/springframework/beans/factory/support/BeanDefinitionBuilder;
      21: astore        4
      23: aload_2
      24: aload_3
      25: aload         4
      27: invokevirtual #27                 // Method org/springframework/beans/factory/support/BeanDefinitionBuilder.getBeanDefinition:()Lorg/springframework/beans/factory/support/AbstractBeanDefinition;
      30: invokeinterface #31,  3           // InterfaceMethod org/springframework/beans/factory/support/BeanDefinitionRegistry.registerBeanDefinition:(Ljava/lang/String;Lorg/springframework/beans/factory/config/BeanDefinition;)V
      35: return
}
