Compiled from "DatabaseInitializationDependencyConfigurer.java"
class org.springframework.boot.sql.init.dependency.DatabaseInitializationDependencyConfigurer$DependsOnDatabaseInitializationPostProcessor$InitializerBeanNames {
  private final java.util.Map<org.springframework.boot.sql.init.dependency.DatabaseInitializerDetector, java.util.Set<java.lang.String>> byDetectorBeanNames;

  private final java.util.Set<java.lang.String> beanNames;

  org.springframework.boot.sql.init.dependency.DatabaseInitializationDependencyConfigurer$DependsOnDatabaseInitializationPostProcessor$InitializerBeanNames();
    Code:
       0: aload_0
       1: invokespecial #1                  // Method java/lang/Object."<init>":()V
       4: aload_0
       5: new           #7                  // class java/util/LinkedHashMap
       8: dup
       9: invokespecial #9                  // Method java/util/LinkedHashMap."<init>":()V
      12: putfield      #10                 // Field byDetectorBeanNames:Ljava/util/Map;
      15: aload_0
      16: new           #16                 // class java/util/LinkedHashSet
      19: dup
      20: invokespecial #18                 // Method java/util/LinkedHashSet."<init>":()V
      23: putfield      #19                 // Field beanNames:Ljava/util/Set;
      26: return

  private void detected(org.springframework.boot.sql.init.dependency.DatabaseInitializerDetector, java.lang.String);
    Code:
       0: aload_0
       1: getfield      #10                 // Field byDetectorBeanNames:Ljava/util/Map;
       4: aload_1
       5: invokedynamic #23,  0             // InvokeDynamic #0:apply:()Ljava/util/function/Function;
      10: invokeinterface #27,  3           // InterfaceMethod java/util/Map.computeIfAbsent:(Ljava/lang/Object;Ljava/util/function/Function;)Ljava/lang/Object;
      15: checkcast     #33                 // class java/util/Set
      18: aload_2
      19: invokeinterface #35,  2           // InterfaceMethod java/util/Set.add:(Ljava/lang/Object;)Z
      24: pop
      25: aload_0
      26: getfield      #19                 // Field beanNames:Ljava/util/Set;
      29: aload_2
      30: invokeinterface #35,  2           // InterfaceMethod java/util/Set.add:(Ljava/lang/Object;)Z
      35: pop
      36: return

  private boolean isEmpty();
    Code:
       0: aload_0
       1: getfield      #19                 // Field beanNames:Ljava/util/Set;
       4: invokeinterface #39,  1           // InterfaceMethod java/util/Set.isEmpty:()Z
       9: ireturn

  private java.lang.Iterable<java.util.Set<java.lang.String>> batchedBeanNames();
    Code:
       0: aload_0
       1: getfield      #10                 // Field byDetectorBeanNames:Ljava/util/Map;
       4: invokeinterface #43,  1           // InterfaceMethod java/util/Map.values:()Ljava/util/Collection;
       9: areturn

  private java.util.Set<java.lang.String> beanNames();
    Code:
       0: aload_0
       1: getfield      #19                 // Field beanNames:Ljava/util/Set;
       4: invokestatic  #47                 // Method java/util/Collections.unmodifiableSet:(Ljava/util/Set;)Ljava/util/Set;
       7: areturn

  private static java.util.Set lambda$detected$0(org.springframework.boot.sql.init.dependency.DatabaseInitializerDetector);
    Code:
       0: new           #16                 // class java/util/LinkedHashSet
       3: dup
       4: invokespecial #18                 // Method java/util/LinkedHashSet."<init>":()V
       7: areturn
}
