Compiled from "JadxOptionDescription.java"
public class jadx.api.plugins.options.impl.JadxOptionDescription implements jadx.api.plugins.options.OptionDescription {
  private final java.lang.String name;

  private final java.lang.String desc;

  private final java.lang.String defaultValue;

  private final java.util.List<java.lang.String> values;

  public jadx.api.plugins.options.impl.JadxOptionDescription(java.lang.String, java.lang.String, java.lang.String, java.util.List<java.lang.String>);
    Code:
       0: aload_0
       1: invokespecial #1                  // Method java/lang/Object."<init>":()V
       4: aload_0
       5: aload_1
       6: putfield      #2                  // Field name:Ljava/lang/String;
       9: aload_0
      10: aload_2
      11: putfield      #3                  // Field desc:Ljava/lang/String;
      14: aload_0
      15: aload_3
      16: putfield      #4                  // Field defaultValue:Ljava/lang/String;
      19: aload_0
      20: aload         4
      22: putfield      #5                  // Field values:Ljava/util/List;
      25: return

  public java.lang.String name();
    Code:
       0: aload_0
       1: getfield      #2                  // Field name:Ljava/lang/String;
       4: areturn

  public java.lang.String description();
    Code:
       0: aload_0
       1: getfield      #3                  // Field desc:Ljava/lang/String;
       4: areturn

  public java.lang.String defaultValue();
    Code:
       0: aload_0
       1: getfield      #4                  // Field defaultValue:Ljava/lang/String;
       4: areturn

  public java.util.List<java.lang.String> values();
    Code:
       0: aload_0
       1: getfield      #5                  // Field values:Ljava/util/List;
       4: areturn

  public java.lang.String toString();
    Code:
       0: new           #6                  // class java/lang/StringBuilder
       3: dup
       4: invokespecial #7                  // Method java/lang/StringBuilder."<init>":()V
       7: ldc           #8                  // String OptionDescription{
       9: invokevirtual #9                  // Method java/lang/StringBuilder.append:(Ljava/lang/String;)Ljava/lang/StringBuilder;
      12: aload_0
      13: getfield      #3                  // Field desc:Ljava/lang/String;
      16: invokevirtual #9                  // Method java/lang/StringBuilder.append:(Ljava/lang/String;)Ljava/lang/StringBuilder;
      19: ldc           #10                 // String , values=
      21: invokevirtual #9                  // Method java/lang/StringBuilder.append:(Ljava/lang/String;)Ljava/lang/StringBuilder;
      24: aload_0
      25: getfield      #5                  // Field values:Ljava/util/List;
      28: invokevirtual #11                 // Method java/lang/StringBuilder.append:(Ljava/lang/Object;)Ljava/lang/StringBuilder;
      31: bipush        125
      33: invokevirtual #12                 // Method java/lang/StringBuilder.append:(C)Ljava/lang/StringBuilder;
      36: invokevirtual #13                 // Method java/lang/StringBuilder.toString:()Ljava/lang/String;
      39: areturn
}
