Compiled from "TrieParser.java"
final class com.google.thirdparty.publicsuffix.TrieParser {
  private static final com.google.common.base.Joiner DIRECT_JOINER;

  com.google.thirdparty.publicsuffix.TrieParser();
    Code:
       0: aload_0
       1: invokespecial #1                  // Method java/lang/Object."<init>":()V
       4: return

  static com.google.common.collect.ImmutableMap<java.lang.String, com.google.thirdparty.publicsuffix.PublicSuffixType> parseTrie(java.lang.CharSequence...);
    Code:
       0: getstatic     #2                  // Field DIRECT_JOINER:Lcom/google/common/base/Joiner;
       3: aload_0
       4: invokevirtual #3                  // Method com/google/common/base/Joiner.join:([Ljava/lang/Object;)Ljava/lang/String;
       7: astore_1
       8: aload_1
       9: invokestatic  #4                  // Method parseFullString:(Ljava/lang/String;)Lcom/google/common/collect/ImmutableMap;
      12: areturn

  static com.google.common.collect.ImmutableMap<java.lang.String, com.google.thirdparty.publicsuffix.PublicSuffixType> parseFullString(java.lang.String);
    Code:
       0: invokestatic  #5                  // Method com/google/common/collect/ImmutableMap.builder:()Lcom/google/common/collect/ImmutableMap$Builder;
       3: astore_1
       4: aload_0
       5: invokevirtual #6                  // Method java/lang/String.length:()I
       8: istore_2
       9: iconst_0
      10: istore_3
      11: iload_3
      12: iload_2
      13: if_icmpge     31
      16: iload_3
      17: invokestatic  #7                  // Method com/google/common/collect/Queues.newArrayDeque:()Ljava/util/ArrayDeque;
      20: aload_0
      21: iload_3
      22: aload_1
      23: invokestatic  #8                  // Method doParseTrieToBuilder:(Ljava/util/Deque;Ljava/lang/CharSequence;ILcom/google/common/collect/ImmutableMap$Builder;)I
      26: iadd
      27: istore_3
      28: goto          11
      31: aload_1
      32: invokevirtual #9                  // Method com/google/common/collect/ImmutableMap$Builder.buildOrThrow:()Lcom/google/common/collect/ImmutableMap;
      35: areturn

  private static int doParseTrieToBuilder(java.util.Deque<java.lang.CharSequence>, java.lang.CharSequence, int, com.google.common.collect.ImmutableMap$Builder<java.lang.String, com.google.thirdparty.publicsuffix.PublicSuffixType>);
    Code:
       0: aload_1
       1: invokeinterface #10,  1           // InterfaceMethod java/lang/CharSequence.length:()I
       6: istore        4
       8: iload_2
       9: istore        5
      11: iconst_0
      12: istore        6
      14: iload         5
      16: iload         4
      18: if_icmpge     75
      21: aload_1
      22: iload         5
      24: invokeinterface #11,  2           // InterfaceMethod java/lang/CharSequence.charAt:(I)C
      29: istore        6
      31: iload         6
      33: bipush        38
      35: if_icmpeq     75
      38: iload         6
      40: bipush        63
      42: if_icmpeq     75
      45: iload         6
      47: bipush        33
      49: if_icmpeq     75
      52: iload         6
      54: bipush        58
      56: if_icmpeq     75
      59: iload         6
      61: bipush        44
      63: if_icmpne     69
      66: goto          75
      69: iinc          5, 1
      72: goto          14
      75: aload_0
      76: aload_1
      77: iload_2
      78: iload         5
      80: invokeinterface #12,  3           // InterfaceMethod java/lang/CharSequence.subSequence:(II)Ljava/lang/CharSequence;
      85: invokestatic  #13                 // Method reverse:(Ljava/lang/CharSequence;)Ljava/lang/CharSequence;
      88: invokeinterface #14,  2           // InterfaceMethod java/util/Deque.push:(Ljava/lang/Object;)V
      93: iload         6
      95: bipush        33
      97: if_icmpeq     121
     100: iload         6
     102: bipush        63
     104: if_icmpeq     121
     107: iload         6
     109: bipush        58
     111: if_icmpeq     121
     114: iload         6
     116: bipush        44
     118: if_icmpne     150
     121: getstatic     #2                  // Field DIRECT_JOINER:Lcom/google/common/base/Joiner;
     124: aload_0
     125: invokevirtual #15                 // Method com/google/common/base/Joiner.join:(Ljava/lang/Iterable;)Ljava/lang/String;
     128: astore        7
     130: aload         7
     132: invokevirtual #6                  // Method java/lang/String.length:()I
     135: ifle          150
     138: aload_3
     139: aload         7
     141: iload         6
     143: invokestatic  #16                 // Method com/google/thirdparty/publicsuffix/PublicSuffixType.fromCode:(C)Lcom/google/thirdparty/publicsuffix/PublicSuffixType;
     146: invokevirtual #17                 // Method com/google/common/collect/ImmutableMap$Builder.put:(Ljava/lang/Object;Ljava/lang/Object;)Lcom/google/common/collect/ImmutableMap$Builder;
     149: pop
     150: iinc          5, 1
     153: iload         6
     155: bipush        63
     157: if_icmpeq     219
     160: iload         6
     162: bipush        44
     164: if_icmpeq     219
     167: iload         5
     169: iload         4
     171: if_icmpge     219
     174: iload         5
     176: aload_0
     177: aload_1
     178: iload         5
     180: aload_3
     181: invokestatic  #8                  // Method doParseTrieToBuilder:(Ljava/util/Deque;Ljava/lang/CharSequence;ILcom/google/common/collect/ImmutableMap$Builder;)I
     184: iadd
     185: istore        5
     187: aload_1
     188: iload         5
     190: invokeinterface #11,  2           // InterfaceMethod java/lang/CharSequence.charAt:(I)C
     195: bipush        63
     197: if_icmpeq     213
     200: aload_1
     201: iload         5
     203: invokeinterface #11,  2           // InterfaceMethod java/lang/CharSequence.charAt:(I)C
     208: bipush        44
     210: if_icmpne     167
     213: iinc          5, 1
     216: goto          219
     219: aload_0
     220: invokeinterface #18,  1           // InterfaceMethod java/util/Deque.pop:()Ljava/lang/Object;
     225: pop
     226: iload         5
     228: iload_2
     229: isub
     230: ireturn

  private static java.lang.CharSequence reverse(java.lang.CharSequence);
    Code:
       0: new           #19                 // class java/lang/StringBuilder
       3: dup
       4: aload_0
       5: invokespecial #20                 // Method java/lang/StringBuilder."<init>":(Ljava/lang/CharSequence;)V
       8: invokevirtual #21                 // Method java/lang/StringBuilder.reverse:()Ljava/lang/StringBuilder;
      11: areturn

  static {};
    Code:
       0: ldc           #22                 // String
       2: invokestatic  #23                 // Method com/google/common/base/Joiner.on:(Ljava/lang/String;)Lcom/google/common/base/Joiner;
       5: putstatic     #2                  // Field DIRECT_JOINER:Lcom/google/common/base/Joiner;
       8: return
}
