Compiled from "AggregateMetricsCollector.java"
public class org.apache.dubbo.metrics.collector.AggregateMetricsCollector implements org.apache.dubbo.metrics.collector.MetricsCollector<org.apache.dubbo.metrics.event.RequestEvent> {
  private int bucketNum;

  private int timeWindowSeconds;

  private final java.util.Map<org.apache.dubbo.metrics.model.key.MetricsKeyWrapper, java.util.concurrent.ConcurrentHashMap<org.apache.dubbo.metrics.model.MethodMetric, org.apache.dubbo.metrics.aggregate.TimeWindowCounter>> methodTypeCounter;

  private final java.util.concurrent.ConcurrentMap<org.apache.dubbo.metrics.model.MethodMetric, org.apache.dubbo.metrics.aggregate.TimeWindowQuantile> rt;

  private final java.util.concurrent.ConcurrentHashMap<org.apache.dubbo.metrics.model.MethodMetric, org.apache.dubbo.metrics.aggregate.TimeWindowCounter> qps;

  private final org.apache.dubbo.rpc.model.ApplicationModel applicationModel;

  private static final java.lang.Integer DEFAULT_COMPRESSION;

  private static final java.lang.Integer DEFAULT_BUCKET_NUM;

  private static final java.lang.Integer DEFAULT_TIME_WINDOW_SECONDS;

  private java.lang.Boolean collectEnabled;

  public org.apache.dubbo.metrics.collector.AggregateMetricsCollector(org.apache.dubbo.rpc.model.ApplicationModel);
    Code:
       0: aload_0
       1: invokespecial #3                  // Method java/lang/Object."<init>":()V
       4: aload_0
       5: new           #4                  // class java/util/concurrent/ConcurrentHashMap
       8: dup
       9: invokespecial #5                  // Method java/util/concurrent/ConcurrentHashMap."<init>":()V
      12: putfield      #6                  // Field methodTypeCounter:Ljava/util/Map;
      15: aload_0
      16: new           #4                  // class java/util/concurrent/ConcurrentHashMap
      19: dup
      20: invokespecial #5                  // Method java/util/concurrent/ConcurrentHashMap."<init>":()V
      23: putfield      #7                  // Field rt:Ljava/util/concurrent/ConcurrentMap;
      26: aload_0
      27: new           #4                  // class java/util/concurrent/ConcurrentHashMap
      30: dup
      31: invokespecial #5                  // Method java/util/concurrent/ConcurrentHashMap."<init>":()V
      34: putfield      #8                  // Field qps:Ljava/util/concurrent/ConcurrentHashMap;
      37: aload_0
      38: aconst_null
      39: putfield      #9                  // Field collectEnabled:Ljava/lang/Boolean;
      42: aload_0
      43: aload_1
      44: putfield      #10                 // Field applicationModel:Lorg/apache/dubbo/rpc/model/ApplicationModel;
      47: aload_1
      48: invokevirtual #11                 // Method org/apache/dubbo/rpc/model/ApplicationModel.getApplicationConfigManager:()Lorg/apache/dubbo/config/context/ConfigManager;
      51: astore_2
      52: aload_0
      53: invokevirtual #12                 // Method isCollectEnabled:()Z
      56: ifeq          139
      59: aload_2
      60: invokevirtual #13                 // Method org/apache/dubbo/config/context/ConfigManager.getMetrics:()Ljava/util/Optional;
      63: astore_3
      64: aload_3
      65: invokevirtual #14                 // Method java/util/Optional.isPresent:()Z
      68: ifeq          139
      71: aload_0
      72: invokespecial #15                 // Method registerListener:()V
      75: aload_3
      76: invokevirtual #16                 // Method java/util/Optional.get:()Ljava/lang/Object;
      79: checkcast     #17                 // class org/apache/dubbo/config/MetricsConfig
      82: invokevirtual #18                 // Method org/apache/dubbo/config/MetricsConfig.getAggregation:()Lorg/apache/dubbo/config/nested/AggregationConfig;
      85: astore        4
      87: aload_0
      88: aload         4
      90: invokevirtual #19                 // Method org/apache/dubbo/config/nested/AggregationConfig.getBucketNum:()Ljava/lang/Integer;
      93: ifnonnull     102
      96: getstatic     #20                 // Field DEFAULT_BUCKET_NUM:Ljava/lang/Integer;
      99: goto          107
     102: aload         4
     104: invokevirtual #19                 // Method org/apache/dubbo/config/nested/AggregationConfig.getBucketNum:()Ljava/lang/Integer;
     107: invokevirtual #21                 // Method java/lang/Integer.intValue:()I
     110: putfield      #22                 // Field bucketNum:I
     113: aload_0
     114: aload         4
     116: invokevirtual #23                 // Method org/apache/dubbo/config/nested/AggregationConfig.getTimeWindowSeconds:()Ljava/lang/Integer;
     119: ifnonnull     128
     122: getstatic     #24                 // Field DEFAULT_TIME_WINDOW_SECONDS:Ljava/lang/Integer;
     125: goto          133
     128: aload         4
     130: invokevirtual #23                 // Method org/apache/dubbo/config/nested/AggregationConfig.getTimeWindowSeconds:()Ljava/lang/Integer;
     133: invokevirtual #21                 // Method java/lang/Integer.intValue:()I
     136: putfield      #25                 // Field timeWindowSeconds:I
     139: return

  public void setCollectEnabled(java.lang.Boolean);
    Code:
       0: aload_1
       1: ifnull        9
       4: aload_0
       5: aload_1
       6: putfield      #9                  // Field collectEnabled:Ljava/lang/Boolean;
       9: return

  public boolean isCollectEnabled();
    Code:
       0: aload_0
       1: getfield      #9                  // Field collectEnabled:Ljava/lang/Boolean;
       4: ifnonnull     28
       7: aload_0
       8: getfield      #10                 // Field applicationModel:Lorg/apache/dubbo/rpc/model/ApplicationModel;
      11: invokevirtual #11                 // Method org/apache/dubbo/rpc/model/ApplicationModel.getApplicationConfigManager:()Lorg/apache/dubbo/config/context/ConfigManager;
      14: astore_1
      15: aload_1
      16: invokevirtual #13                 // Method org/apache/dubbo/config/context/ConfigManager.getMetrics:()Ljava/util/Optional;
      19: aload_0
      20: invokedynamic #26,  0             // InvokeDynamic #0:accept:(Lorg/apache/dubbo/metrics/collector/AggregateMetricsCollector;)Ljava/util/function/Consumer;
      25: invokevirtual #27                 // Method java/util/Optional.ifPresent:(Ljava/util/function/Consumer;)V
      28: aload_0
      29: getfield      #9                  // Field collectEnabled:Ljava/lang/Boolean;
      32: invokestatic  #28                 // Method java/util/Optional.ofNullable:(Ljava/lang/Object;)Ljava/util/Optional;
      35: iconst_1
      36: invokestatic  #29                 // Method java/lang/Boolean.valueOf:(Z)Ljava/lang/Boolean;
      39: invokevirtual #30                 // Method java/util/Optional.orElse:(Ljava/lang/Object;)Ljava/lang/Object;
      42: checkcast     #31                 // class java/lang/Boolean
      45: invokevirtual #32                 // Method java/lang/Boolean.booleanValue:()Z
      48: ireturn

  public boolean isSupport(org.apache.dubbo.metrics.event.MetricsEvent);
    Code:
       0: aload_1
       1: instanceof    #33                 // class org/apache/dubbo/metrics/event/RequestEvent
       4: ireturn

  public void onEvent(org.apache.dubbo.metrics.event.RequestEvent);
    Code:
       0: aload_0
       1: aload_1
       2: getstatic     #34                 // Field org/apache/dubbo/metrics/model/key/MetricsKey.METRIC_REQUESTS:Lorg/apache/dubbo/metrics/model/key/MetricsKey;
       5: invokespecial #35                 // Method calcWindowCounter:(Lorg/apache/dubbo/metrics/event/RequestEvent;Lorg/apache/dubbo/metrics/model/key/MetricsKey;)Lorg/apache/dubbo/metrics/model/MethodMetric;
       8: astore_2
       9: aload_0
      10: getfield      #8                  // Field qps:Ljava/util/concurrent/ConcurrentHashMap;
      13: aload_2
      14: aload_0
      15: invokedynamic #36,  0             // InvokeDynamic #1:apply:(Lorg/apache/dubbo/metrics/collector/AggregateMetricsCollector;)Ljava/util/function/Function;
      20: invokestatic  #37                 // Method org/apache/dubbo/common/utils/ConcurrentHashMapUtils.computeIfAbsent:(Ljava/util/concurrent/ConcurrentMap;Ljava/lang/Object;Ljava/util/function/Function;)Ljava/lang/Object;
      23: checkcast     #38                 // class org/apache/dubbo/metrics/aggregate/TimeWindowCounter
      26: astore_3
      27: aload_3
      28: invokevirtual #39                 // Method org/apache/dubbo/metrics/aggregate/TimeWindowCounter.increment:()V
      31: return

  public void onEventFinish(org.apache.dubbo.metrics.event.RequestEvent);
    Code:
       0: getstatic     #40                 // Field org/apache/dubbo/metrics/model/key/MetricsKey.METRIC_REQUESTS_SUCCEED:Lorg/apache/dubbo/metrics/model/key/MetricsKey;
       3: astore_2
       4: aload_1
       5: ldc           #41                 // String metric_filter_throwable
       7: invokevirtual #42                 // Method org/apache/dubbo/metrics/event/RequestEvent.getAttachmentValue:(Ljava/lang/String;)Ljava/lang/Object;
      10: astore_3
      11: aload_3
      12: ifnull        23
      15: aload_3
      16: checkcast     #43                 // class java/lang/Throwable
      19: invokestatic  #44                 // Method org/apache/dubbo/metrics/model/MetricsSupport.getAggMetricsKey:(Ljava/lang/Throwable;)Lorg/apache/dubbo/metrics/model/key/MetricsKey;
      22: astore_2
      23: aload_0
      24: aload_1
      25: aload_2
      26: invokespecial #35                 // Method calcWindowCounter:(Lorg/apache/dubbo/metrics/event/RequestEvent;Lorg/apache/dubbo/metrics/model/key/MetricsKey;)Lorg/apache/dubbo/metrics/model/MethodMetric;
      29: pop
      30: aload_0
      31: aload_1
      32: invokespecial #45                 // Method onRTEvent:(Lorg/apache/dubbo/metrics/event/RequestEvent;)V
      35: return

  public void onEventError(org.apache.dubbo.metrics.event.RequestEvent);
    Code:
       0: getstatic     #46                 // Field org/apache/dubbo/metrics/model/key/MetricsKey.METRIC_REQUESTS_FAILED:Lorg/apache/dubbo/metrics/model/key/MetricsKey;
       3: astore_2
       4: aload_1
       5: ldc           #41                 // String metric_filter_throwable
       7: invokevirtual #42                 // Method org/apache/dubbo/metrics/event/RequestEvent.getAttachmentValue:(Ljava/lang/String;)Ljava/lang/Object;
      10: astore_3
      11: aload_3
      12: ifnull        23
      15: aload_3
      16: checkcast     #43                 // class java/lang/Throwable
      19: invokestatic  #44                 // Method org/apache/dubbo/metrics/model/MetricsSupport.getAggMetricsKey:(Ljava/lang/Throwable;)Lorg/apache/dubbo/metrics/model/key/MetricsKey;
      22: astore_2
      23: aload_0
      24: aload_1
      25: aload_2
      26: invokespecial #35                 // Method calcWindowCounter:(Lorg/apache/dubbo/metrics/event/RequestEvent;Lorg/apache/dubbo/metrics/model/key/MetricsKey;)Lorg/apache/dubbo/metrics/model/MethodMetric;
      29: pop
      30: aload_0
      31: aload_1
      32: invokespecial #45                 // Method onRTEvent:(Lorg/apache/dubbo/metrics/event/RequestEvent;)V
      35: return

  private void onRTEvent(org.apache.dubbo.metrics.event.RequestEvent);
    Code:
       0: new           #47                 // class org/apache/dubbo/metrics/model/MethodMetric
       3: dup
       4: aload_0
       5: getfield      #10                 // Field applicationModel:Lorg/apache/dubbo/rpc/model/ApplicationModel;
       8: aload_1
       9: ldc           #49                 // String metric_filter_invocation
      11: invokevirtual #42                 // Method org/apache/dubbo/metrics/event/RequestEvent.getAttachmentValue:(Ljava/lang/String;)Ljava/lang/Object;
      14: checkcast     #50                 // class org/apache/dubbo/rpc/Invocation
      17: invokespecial #51                 // Method org/apache/dubbo/metrics/model/MethodMetric."<init>":(Lorg/apache/dubbo/rpc/model/ApplicationModel;Lorg/apache/dubbo/rpc/Invocation;)V
      20: astore_2
      21: aload_1
      22: invokevirtual #52                 // Method org/apache/dubbo/metrics/event/RequestEvent.getTimePair:()Lorg/apache/dubbo/metrics/model/TimePair;
      25: invokevirtual #53                 // Method org/apache/dubbo/metrics/model/TimePair.calc:()J
      28: lstore_3
      29: aload_0
      30: getfield      #7                  // Field rt:Ljava/util/concurrent/ConcurrentMap;
      33: aload_2
      34: aload_0
      35: invokedynamic #54,  0             // InvokeDynamic #2:apply:(Lorg/apache/dubbo/metrics/collector/AggregateMetricsCollector;)Ljava/util/function/Function;
      40: invokestatic  #37                 // Method org/apache/dubbo/common/utils/ConcurrentHashMapUtils.computeIfAbsent:(Ljava/util/concurrent/ConcurrentMap;Ljava/lang/Object;Ljava/util/function/Function;)Ljava/lang/Object;
      43: checkcast     #55                 // class org/apache/dubbo/metrics/aggregate/TimeWindowQuantile
      46: astore        5
      48: aload         5
      50: lload_3
      51: l2d
      52: invokevirtual #56                 // Method org/apache/dubbo/metrics/aggregate/TimeWindowQuantile.add:(D)V
      55: return

  private org.apache.dubbo.metrics.model.MethodMetric calcWindowCounter(org.apache.dubbo.metrics.event.RequestEvent, org.apache.dubbo.metrics.model.key.MetricsKey);
    Code:
       0: aload_1
       1: ldc           #57                 // String metric_filter_side
       3: invokevirtual #42                 // Method org/apache/dubbo/metrics/event/RequestEvent.getAttachmentValue:(Ljava/lang/String;)Ljava/lang/Object;
       6: checkcast     #58                 // class java/lang/String
       9: getstatic     #59                 // Field org/apache/dubbo/metrics/model/key/MetricsLevel.SERVICE:Lorg/apache/dubbo/metrics/model/key/MetricsLevel;
      12: invokestatic  #60                 // Method org/apache/dubbo/metrics/model/key/MetricsPlaceValue.of:(Ljava/lang/String;Lorg/apache/dubbo/metrics/model/key/MetricsLevel;)Lorg/apache/dubbo/metrics/model/key/MetricsPlaceValue;
      15: astore_3
      16: new           #61                 // class org/apache/dubbo/metrics/model/key/MetricsKeyWrapper
      19: dup
      20: aload_2
      21: aload_3
      22: invokespecial #62                 // Method org/apache/dubbo/metrics/model/key/MetricsKeyWrapper."<init>":(Lorg/apache/dubbo/metrics/model/key/MetricsKey;Lorg/apache/dubbo/metrics/model/key/MetricsPlaceValue;)V
      25: astore        4
      27: new           #47                 // class org/apache/dubbo/metrics/model/MethodMetric
      30: dup
      31: aload_0
      32: getfield      #10                 // Field applicationModel:Lorg/apache/dubbo/rpc/model/ApplicationModel;
      35: aload_1
      36: ldc           #49                 // String metric_filter_invocation
      38: invokevirtual #42                 // Method org/apache/dubbo/metrics/event/RequestEvent.getAttachmentValue:(Ljava/lang/String;)Ljava/lang/Object;
      41: checkcast     #50                 // class org/apache/dubbo/rpc/Invocation
      44: invokespecial #51                 // Method org/apache/dubbo/metrics/model/MethodMetric."<init>":(Lorg/apache/dubbo/rpc/model/ApplicationModel;Lorg/apache/dubbo/rpc/Invocation;)V
      47: astore        5
      49: aload_0
      50: getfield      #6                  // Field methodTypeCounter:Ljava/util/Map;
      53: aload         4
      55: invokedynamic #63,  0             // InvokeDynamic #3:apply:()Ljava/util/function/Function;
      60: invokeinterface #64,  3           // InterfaceMethod java/util/Map.computeIfAbsent:(Ljava/lang/Object;Ljava/util/function/Function;)Ljava/lang/Object;
      65: checkcast     #65                 // class java/util/concurrent/ConcurrentMap
      68: astore        6
      70: aload         6
      72: aload         5
      74: aload_0
      75: invokedynamic #66,  0             // InvokeDynamic #4:apply:(Lorg/apache/dubbo/metrics/collector/AggregateMetricsCollector;)Ljava/util/function/Function;
      80: invokestatic  #37                 // Method org/apache/dubbo/common/utils/ConcurrentHashMapUtils.computeIfAbsent:(Ljava/util/concurrent/ConcurrentMap;Ljava/lang/Object;Ljava/util/function/Function;)Ljava/lang/Object;
      83: checkcast     #38                 // class org/apache/dubbo/metrics/aggregate/TimeWindowCounter
      86: astore        7
      88: aload         7
      90: invokevirtual #39                 // Method org/apache/dubbo/metrics/aggregate/TimeWindowCounter.increment:()V
      93: aload         5
      95: areturn

  public java.util.List<org.apache.dubbo.metrics.model.sample.MetricSample> collect();
    Code:
       0: new           #67                 // class java/util/ArrayList
       3: dup
       4: invokespecial #68                 // Method java/util/ArrayList."<init>":()V
       7: astore_1
       8: aload_0
       9: aload_1
      10: invokespecial #69                 // Method collectRequests:(Ljava/util/List;)V
      13: aload_0
      14: aload_1
      15: invokespecial #70                 // Method collectQPS:(Ljava/util/List;)V
      18: aload_0
      19: aload_1
      20: invokespecial #71                 // Method collectRT:(Ljava/util/List;)V
      23: aload_1
      24: areturn

  private void collectRequests(java.util.List<org.apache.dubbo.metrics.model.sample.MetricSample>);
    Code:
       0: aload_0
       1: aload_1
       2: ldc           #72                 // String provider
       4: invokespecial #73                 // Method collectBySide:(Ljava/util/List;Ljava/lang/String;)V
       7: aload_0
       8: aload_1
       9: ldc           #74                 // String consumer
      11: invokespecial #73                 // Method collectBySide:(Ljava/util/List;Ljava/lang/String;)V
      14: return

  private void collectBySide(java.util.List<org.apache.dubbo.metrics.model.sample.MetricSample>, java.lang.String);
    Code:
       0: aload_0
       1: aload_1
       2: aload_2
       3: getstatic     #75                 // Field org/apache/dubbo/metrics/model/key/MetricsKey.METRIC_REQUESTS_TOTAL_AGG:Lorg/apache/dubbo/metrics/model/key/MetricsKey;
       6: invokespecial #76                 // Method collectMethod:(Ljava/util/List;Ljava/lang/String;Lorg/apache/dubbo/metrics/model/key/MetricsKey;)V
       9: aload_0
      10: aload_1
      11: aload_2
      12: getstatic     #77                 // Field org/apache/dubbo/metrics/model/key/MetricsKey.METRIC_REQUESTS_SUCCEED_AGG:Lorg/apache/dubbo/metrics/model/key/MetricsKey;
      15: invokespecial #76                 // Method collectMethod:(Ljava/util/List;Ljava/lang/String;Lorg/apache/dubbo/metrics/model/key/MetricsKey;)V
      18: aload_0
      19: aload_1
      20: aload_2
      21: getstatic     #78                 // Field org/apache/dubbo/metrics/model/key/MetricsKey.METRIC_REQUESTS_FAILED_AGG:Lorg/apache/dubbo/metrics/model/key/MetricsKey;
      24: invokespecial #76                 // Method collectMethod:(Ljava/util/List;Ljava/lang/String;Lorg/apache/dubbo/metrics/model/key/MetricsKey;)V
      27: aload_0
      28: aload_1
      29: aload_2
      30: getstatic     #79                 // Field org/apache/dubbo/metrics/model/key/MetricsKey.METRIC_REQUEST_BUSINESS_FAILED_AGG:Lorg/apache/dubbo/metrics/model/key/MetricsKey;
      33: invokespecial #76                 // Method collectMethod:(Ljava/util/List;Ljava/lang/String;Lorg/apache/dubbo/metrics/model/key/MetricsKey;)V
      36: aload_0
      37: aload_1
      38: aload_2
      39: getstatic     #80                 // Field org/apache/dubbo/metrics/model/key/MetricsKey.METRIC_REQUESTS_TIMEOUT_AGG:Lorg/apache/dubbo/metrics/model/key/MetricsKey;
      42: invokespecial #76                 // Method collectMethod:(Ljava/util/List;Ljava/lang/String;Lorg/apache/dubbo/metrics/model/key/MetricsKey;)V
      45: aload_0
      46: aload_1
      47: aload_2
      48: getstatic     #81                 // Field org/apache/dubbo/metrics/model/key/MetricsKey.METRIC_REQUESTS_LIMIT_AGG:Lorg/apache/dubbo/metrics/model/key/MetricsKey;
      51: invokespecial #76                 // Method collectMethod:(Ljava/util/List;Ljava/lang/String;Lorg/apache/dubbo/metrics/model/key/MetricsKey;)V
      54: aload_0
      55: aload_1
      56: aload_2
      57: getstatic     #82                 // Field org/apache/dubbo/metrics/model/key/MetricsKey.METRIC_REQUESTS_TOTAL_FAILED_AGG:Lorg/apache/dubbo/metrics/model/key/MetricsKey;
      60: invokespecial #76                 // Method collectMethod:(Ljava/util/List;Ljava/lang/String;Lorg/apache/dubbo/metrics/model/key/MetricsKey;)V
      63: aload_0
      64: aload_1
      65: aload_2
      66: getstatic     #83                 // Field org/apache/dubbo/metrics/model/key/MetricsKey.METRIC_REQUESTS_NETWORK_FAILED_AGG:Lorg/apache/dubbo/metrics/model/key/MetricsKey;
      69: invokespecial #76                 // Method collectMethod:(Ljava/util/List;Ljava/lang/String;Lorg/apache/dubbo/metrics/model/key/MetricsKey;)V
      72: aload_0
      73: aload_1
      74: aload_2
      75: getstatic     #84                 // Field org/apache/dubbo/metrics/model/key/MetricsKey.METRIC_REQUESTS_CODEC_FAILED_AGG:Lorg/apache/dubbo/metrics/model/key/MetricsKey;
      78: invokespecial #76                 // Method collectMethod:(Ljava/util/List;Ljava/lang/String;Lorg/apache/dubbo/metrics/model/key/MetricsKey;)V
      81: aload_0
      82: aload_1
      83: aload_2
      84: getstatic     #85                 // Field org/apache/dubbo/metrics/model/key/MetricsKey.METRIC_REQUESTS_TOTAL_SERVICE_UNAVAILABLE_FAILED_AGG:Lorg/apache/dubbo/metrics/model/key/MetricsKey;
      87: invokespecial #76                 // Method collectMethod:(Ljava/util/List;Ljava/lang/String;Lorg/apache/dubbo/metrics/model/key/MetricsKey;)V
      90: return

  private void collectMethod(java.util.List<org.apache.dubbo.metrics.model.sample.MetricSample>, java.lang.String, org.apache.dubbo.metrics.model.key.MetricsKey);
    Code:
       0: new           #61                 // class org/apache/dubbo/metrics/model/key/MetricsKeyWrapper
       3: dup
       4: aload_3
       5: aload_2
       6: getstatic     #59                 // Field org/apache/dubbo/metrics/model/key/MetricsLevel.SERVICE:Lorg/apache/dubbo/metrics/model/key/MetricsLevel;
       9: invokestatic  #60                 // Method org/apache/dubbo/metrics/model/key/MetricsPlaceValue.of:(Ljava/lang/String;Lorg/apache/dubbo/metrics/model/key/MetricsLevel;)Lorg/apache/dubbo/metrics/model/key/MetricsPlaceValue;
      12: invokespecial #62                 // Method org/apache/dubbo/metrics/model/key/MetricsKeyWrapper."<init>":(Lorg/apache/dubbo/metrics/model/key/MetricsKey;Lorg/apache/dubbo/metrics/model/key/MetricsPlaceValue;)V
      15: astore        4
      17: aload_0
      18: getfield      #6                  // Field methodTypeCounter:Ljava/util/Map;
      21: aload         4
      23: invokeinterface #86,  2           // InterfaceMethod java/util/Map.get:(Ljava/lang/Object;)Ljava/lang/Object;
      28: checkcast     #4                  // class java/util/concurrent/ConcurrentHashMap
      31: astore        5
      33: aload         5
      35: ifnull        50
      38: aload         5
      40: aload_1
      41: aload_3
      42: invokedynamic #87,  0             // InvokeDynamic #5:accept:(Ljava/util/List;Lorg/apache/dubbo/metrics/model/key/MetricsKey;)Ljava/util/function/BiConsumer;
      47: invokevirtual #88                 // Method java/util/concurrent/ConcurrentHashMap.forEach:(Ljava/util/function/BiConsumer;)V
      50: return

  private void collectQPS(java.util.List<org.apache.dubbo.metrics.model.sample.MetricSample>);
    Code:
       0: aload_0
       1: getfield      #8                  // Field qps:Ljava/util/concurrent/ConcurrentHashMap;
       4: aload_1
       5: invokedynamic #89,  0             // InvokeDynamic #6:accept:(Ljava/util/List;)Ljava/util/function/BiConsumer;
      10: invokevirtual #88                 // Method java/util/concurrent/ConcurrentHashMap.forEach:(Ljava/util/function/BiConsumer;)V
      13: return

  private void collectRT(java.util.List<org.apache.dubbo.metrics.model.sample.MetricSample>);
    Code:
       0: aload_0
       1: getfield      #7                  // Field rt:Ljava/util/concurrent/ConcurrentMap;
       4: aload_1
       5: invokedynamic #90,  0             // InvokeDynamic #7:accept:(Ljava/util/List;)Ljava/util/function/BiConsumer;
      10: invokeinterface #91,  2           // InterfaceMethod java/util/concurrent/ConcurrentMap.forEach:(Ljava/util/function/BiConsumer;)V
      15: return

  private void registerListener();
    Code:
       0: aload_0
       1: getfield      #10                 // Field applicationModel:Lorg/apache/dubbo/rpc/model/ApplicationModel;
       4: invokevirtual #92                 // Method org/apache/dubbo/rpc/model/ApplicationModel.getBeanFactory:()Lorg/apache/dubbo/common/beans/factory/ScopeBeanFactory;
       7: ldc           #93                 // class org/apache/dubbo/metrics/collector/DefaultMetricsCollector
       9: invokevirtual #94                 // Method org/apache/dubbo/common/beans/factory/ScopeBeanFactory.getBean:(Ljava/lang/Class;)Ljava/lang/Object;
      12: checkcast     #93                 // class org/apache/dubbo/metrics/collector/DefaultMetricsCollector
      15: invokevirtual #95                 // Method org/apache/dubbo/metrics/collector/DefaultMetricsCollector.getEventMulticaster:()Lorg/apache/dubbo/metrics/event/MetricsEventMulticaster;
      18: aload_0
      19: invokeinterface #96,  2           // InterfaceMethod org/apache/dubbo/metrics/event/MetricsEventMulticaster.addListener:(Lorg/apache/dubbo/metrics/listener/MetricsListener;)V
      24: return

  public void onEventError(org.apache.dubbo.metrics.event.TimeCounterEvent);
    Code:
       0: aload_0
       1: aload_1
       2: checkcast     #33                 // class org/apache/dubbo/metrics/event/RequestEvent
       5: invokevirtual #97                 // Method onEventError:(Lorg/apache/dubbo/metrics/event/RequestEvent;)V
       8: return

  public void onEventFinish(org.apache.dubbo.metrics.event.TimeCounterEvent);
    Code:
       0: aload_0
       1: aload_1
       2: checkcast     #33                 // class org/apache/dubbo/metrics/event/RequestEvent
       5: invokevirtual #98                 // Method onEventFinish:(Lorg/apache/dubbo/metrics/event/RequestEvent;)V
       8: return

  public void onEvent(org.apache.dubbo.metrics.event.MetricsEvent);
    Code:
       0: aload_0
       1: aload_1
       2: checkcast     #33                 // class org/apache/dubbo/metrics/event/RequestEvent
       5: invokevirtual #99                 // Method onEvent:(Lorg/apache/dubbo/metrics/event/RequestEvent;)V
       8: return

  private static void lambda$collectRT$12(java.util.List, org.apache.dubbo.metrics.model.MethodMetric, org.apache.dubbo.metrics.aggregate.TimeWindowQuantile);
    Code:
       0: aload_0
       1: new           #100                // class org/apache/dubbo/metrics/model/sample/GaugeMetricSample
       4: dup
       5: getstatic     #101                // Field org/apache/dubbo/metrics/model/key/MetricsKey.METRIC_RT_P99:Lorg/apache/dubbo/metrics/model/key/MetricsKey;
       8: aload_1
       9: invokevirtual #102                // Method org/apache/dubbo/metrics/model/MethodMetric.getSide:()Ljava/lang/String;
      12: invokevirtual #103                // Method org/apache/dubbo/metrics/model/key/MetricsKey.getNameByType:(Ljava/lang/String;)Ljava/lang/String;
      15: getstatic     #101                // Field org/apache/dubbo/metrics/model/key/MetricsKey.METRIC_RT_P99:Lorg/apache/dubbo/metrics/model/key/MetricsKey;
      18: invokevirtual #104                // Method org/apache/dubbo/metrics/model/key/MetricsKey.getDescription:()Ljava/lang/String;
      21: aload_1
      22: invokevirtual #105                // Method org/apache/dubbo/metrics/model/MethodMetric.getTags:()Ljava/util/Map;
      25: getstatic     #106                // Field org/apache/dubbo/metrics/model/MetricsCategory.RT:Lorg/apache/dubbo/metrics/model/MetricsCategory;
      28: aload_2
      29: invokedynamic #107,  0            // InvokeDynamic #8:applyAsDouble:()Ljava/util/function/ToDoubleFunction;
      34: invokespecial #108                // Method org/apache/dubbo/metrics/model/sample/GaugeMetricSample."<init>":(Ljava/lang/String;Ljava/lang/String;Ljava/util/Map;Lorg/apache/dubbo/metrics/model/MetricsCategory;Ljava/lang/Object;Ljava/util/function/ToDoubleFunction;)V
      37: invokeinterface #109,  2          // InterfaceMethod java/util/List.add:(Ljava/lang/Object;)Z
      42: pop
      43: aload_0
      44: new           #100                // class org/apache/dubbo/metrics/model/sample/GaugeMetricSample
      47: dup
      48: getstatic     #110                // Field org/apache/dubbo/metrics/model/key/MetricsKey.METRIC_RT_P95:Lorg/apache/dubbo/metrics/model/key/MetricsKey;
      51: aload_1
      52: invokevirtual #102                // Method org/apache/dubbo/metrics/model/MethodMetric.getSide:()Ljava/lang/String;
      55: invokevirtual #103                // Method org/apache/dubbo/metrics/model/key/MetricsKey.getNameByType:(Ljava/lang/String;)Ljava/lang/String;
      58: getstatic     #110                // Field org/apache/dubbo/metrics/model/key/MetricsKey.METRIC_RT_P95:Lorg/apache/dubbo/metrics/model/key/MetricsKey;
      61: invokevirtual #104                // Method org/apache/dubbo/metrics/model/key/MetricsKey.getDescription:()Ljava/lang/String;
      64: aload_1
      65: invokevirtual #105                // Method org/apache/dubbo/metrics/model/MethodMetric.getTags:()Ljava/util/Map;
      68: getstatic     #106                // Field org/apache/dubbo/metrics/model/MetricsCategory.RT:Lorg/apache/dubbo/metrics/model/MetricsCategory;
      71: aload_2
      72: invokedynamic #111,  0            // InvokeDynamic #9:applyAsDouble:()Ljava/util/function/ToDoubleFunction;
      77: invokespecial #108                // Method org/apache/dubbo/metrics/model/sample/GaugeMetricSample."<init>":(Ljava/lang/String;Ljava/lang/String;Ljava/util/Map;Lorg/apache/dubbo/metrics/model/MetricsCategory;Ljava/lang/Object;Ljava/util/function/ToDoubleFunction;)V
      80: invokeinterface #109,  2          // InterfaceMethod java/util/List.add:(Ljava/lang/Object;)Z
      85: pop
      86: aload_0
      87: new           #100                // class org/apache/dubbo/metrics/model/sample/GaugeMetricSample
      90: dup
      91: getstatic     #112                // Field org/apache/dubbo/metrics/model/key/MetricsKey.METRIC_RT_P90:Lorg/apache/dubbo/metrics/model/key/MetricsKey;
      94: aload_1
      95: invokevirtual #102                // Method org/apache/dubbo/metrics/model/MethodMetric.getSide:()Ljava/lang/String;
      98: invokevirtual #103                // Method org/apache/dubbo/metrics/model/key/MetricsKey.getNameByType:(Ljava/lang/String;)Ljava/lang/String;
     101: getstatic     #112                // Field org/apache/dubbo/metrics/model/key/MetricsKey.METRIC_RT_P90:Lorg/apache/dubbo/metrics/model/key/MetricsKey;
     104: invokevirtual #104                // Method org/apache/dubbo/metrics/model/key/MetricsKey.getDescription:()Ljava/lang/String;
     107: aload_1
     108: invokevirtual #105                // Method org/apache/dubbo/metrics/model/MethodMetric.getTags:()Ljava/util/Map;
     111: getstatic     #106                // Field org/apache/dubbo/metrics/model/MetricsCategory.RT:Lorg/apache/dubbo/metrics/model/MetricsCategory;
     114: aload_2
     115: invokedynamic #113,  0            // InvokeDynamic #10:applyAsDouble:()Ljava/util/function/ToDoubleFunction;
     120: invokespecial #108                // Method org/apache/dubbo/metrics/model/sample/GaugeMetricSample."<init>":(Ljava/lang/String;Ljava/lang/String;Ljava/util/Map;Lorg/apache/dubbo/metrics/model/MetricsCategory;Ljava/lang/Object;Ljava/util/function/ToDoubleFunction;)V
     123: invokeinterface #109,  2          // InterfaceMethod java/util/List.add:(Ljava/lang/Object;)Z
     128: pop
     129: aload_0
     130: new           #100                // class org/apache/dubbo/metrics/model/sample/GaugeMetricSample
     133: dup
     134: getstatic     #114                // Field org/apache/dubbo/metrics/model/key/MetricsKey.METRIC_RT_P50:Lorg/apache/dubbo/metrics/model/key/MetricsKey;
     137: aload_1
     138: invokevirtual #102                // Method org/apache/dubbo/metrics/model/MethodMetric.getSide:()Ljava/lang/String;
     141: invokevirtual #103                // Method org/apache/dubbo/metrics/model/key/MetricsKey.getNameByType:(Ljava/lang/String;)Ljava/lang/String;
     144: getstatic     #114                // Field org/apache/dubbo/metrics/model/key/MetricsKey.METRIC_RT_P50:Lorg/apache/dubbo/metrics/model/key/MetricsKey;
     147: invokevirtual #104                // Method org/apache/dubbo/metrics/model/key/MetricsKey.getDescription:()Ljava/lang/String;
     150: aload_1
     151: invokevirtual #105                // Method org/apache/dubbo/metrics/model/MethodMetric.getTags:()Ljava/util/Map;
     154: getstatic     #106                // Field org/apache/dubbo/metrics/model/MetricsCategory.RT:Lorg/apache/dubbo/metrics/model/MetricsCategory;
     157: aload_2
     158: invokedynamic #115,  0            // InvokeDynamic #11:applyAsDouble:()Ljava/util/function/ToDoubleFunction;
     163: invokespecial #108                // Method org/apache/dubbo/metrics/model/sample/GaugeMetricSample."<init>":(Ljava/lang/String;Ljava/lang/String;Ljava/util/Map;Lorg/apache/dubbo/metrics/model/MetricsCategory;Ljava/lang/Object;Ljava/util/function/ToDoubleFunction;)V
     166: invokeinterface #109,  2          // InterfaceMethod java/util/List.add:(Ljava/lang/Object;)Z
     171: pop
     172: return

  private static double lambda$null$11(org.apache.dubbo.metrics.aggregate.TimeWindowQuantile);
    Code:
       0: aload_0
       1: ldc2_w        #116                // double 0.5d
       4: invokevirtual #118                // Method org/apache/dubbo/metrics/aggregate/TimeWindowQuantile.quantile:(D)D
       7: dreturn

  private static double lambda$null$10(org.apache.dubbo.metrics.aggregate.TimeWindowQuantile);
    Code:
       0: aload_0
       1: ldc2_w        #119                // double 0.9d
       4: invokevirtual #118                // Method org/apache/dubbo/metrics/aggregate/TimeWindowQuantile.quantile:(D)D
       7: dreturn

  private static double lambda$null$9(org.apache.dubbo.metrics.aggregate.TimeWindowQuantile);
    Code:
       0: aload_0
       1: ldc2_w        #121                // double 0.95d
       4: invokevirtual #118                // Method org/apache/dubbo/metrics/aggregate/TimeWindowQuantile.quantile:(D)D
       7: dreturn

  private static double lambda$null$8(org.apache.dubbo.metrics.aggregate.TimeWindowQuantile);
    Code:
       0: aload_0
       1: ldc2_w        #123                // double 0.99d
       4: invokevirtual #118                // Method org/apache/dubbo/metrics/aggregate/TimeWindowQuantile.quantile:(D)D
       7: dreturn

  private static void lambda$collectQPS$7(java.util.List, org.apache.dubbo.metrics.model.MethodMetric, org.apache.dubbo.metrics.aggregate.TimeWindowCounter);
    Code:
       0: aload_0
       1: new           #100                // class org/apache/dubbo/metrics/model/sample/GaugeMetricSample
       4: dup
       5: getstatic     #125                // Field org/apache/dubbo/metrics/model/key/MetricsKey.METRIC_QPS:Lorg/apache/dubbo/metrics/model/key/MetricsKey;
       8: aload_1
       9: invokevirtual #102                // Method org/apache/dubbo/metrics/model/MethodMetric.getSide:()Ljava/lang/String;
      12: invokevirtual #103                // Method org/apache/dubbo/metrics/model/key/MetricsKey.getNameByType:(Ljava/lang/String;)Ljava/lang/String;
      15: getstatic     #125                // Field org/apache/dubbo/metrics/model/key/MetricsKey.METRIC_QPS:Lorg/apache/dubbo/metrics/model/key/MetricsKey;
      18: invokevirtual #104                // Method org/apache/dubbo/metrics/model/key/MetricsKey.getDescription:()Ljava/lang/String;
      21: aload_1
      22: invokevirtual #105                // Method org/apache/dubbo/metrics/model/MethodMetric.getTags:()Ljava/util/Map;
      25: getstatic     #126                // Field org/apache/dubbo/metrics/model/MetricsCategory.QPS:Lorg/apache/dubbo/metrics/model/MetricsCategory;
      28: aload_2
      29: invokedynamic #127,  0            // InvokeDynamic #12:applyAsDouble:()Ljava/util/function/ToDoubleFunction;
      34: invokespecial #108                // Method org/apache/dubbo/metrics/model/sample/GaugeMetricSample."<init>":(Ljava/lang/String;Ljava/lang/String;Ljava/util/Map;Lorg/apache/dubbo/metrics/model/MetricsCategory;Ljava/lang/Object;Ljava/util/function/ToDoubleFunction;)V
      37: invokeinterface #109,  2          // InterfaceMethod java/util/List.add:(Ljava/lang/Object;)Z
      42: pop
      43: return

  private static double lambda$null$6(org.apache.dubbo.metrics.aggregate.TimeWindowCounter);
    Code:
       0: aload_0
       1: invokevirtual #128                // Method org/apache/dubbo/metrics/aggregate/TimeWindowCounter.get:()D
       4: aload_0
       5: invokevirtual #129                // Method org/apache/dubbo/metrics/aggregate/TimeWindowCounter.bucketLivedSeconds:()J
       8: l2d
       9: ddiv
      10: dreturn

  private static void lambda$collectMethod$5(java.util.List, org.apache.dubbo.metrics.model.key.MetricsKey, org.apache.dubbo.metrics.model.MethodMetric, org.apache.dubbo.metrics.aggregate.TimeWindowCounter);
    Code:
       0: aload_0
       1: new           #100                // class org/apache/dubbo/metrics/model/sample/GaugeMetricSample
       4: dup
       5: aload_1
       6: aload_2
       7: invokevirtual #102                // Method org/apache/dubbo/metrics/model/MethodMetric.getSide:()Ljava/lang/String;
      10: invokevirtual #103                // Method org/apache/dubbo/metrics/model/key/MetricsKey.getNameByType:(Ljava/lang/String;)Ljava/lang/String;
      13: aload_1
      14: invokevirtual #104                // Method org/apache/dubbo/metrics/model/key/MetricsKey.getDescription:()Ljava/lang/String;
      17: aload_2
      18: invokevirtual #105                // Method org/apache/dubbo/metrics/model/MethodMetric.getTags:()Ljava/util/Map;
      21: getstatic     #130                // Field org/apache/dubbo/metrics/model/MetricsCategory.REQUESTS:Lorg/apache/dubbo/metrics/model/MetricsCategory;
      24: aload_3
      25: invokedynamic #131,  0            // InvokeDynamic #13:applyAsDouble:()Ljava/util/function/ToDoubleFunction;
      30: invokespecial #108                // Method org/apache/dubbo/metrics/model/sample/GaugeMetricSample."<init>":(Ljava/lang/String;Ljava/lang/String;Ljava/util/Map;Lorg/apache/dubbo/metrics/model/MetricsCategory;Ljava/lang/Object;Ljava/util/function/ToDoubleFunction;)V
      33: invokeinterface #109,  2          // InterfaceMethod java/util/List.add:(Ljava/lang/Object;)Z
      38: pop
      39: return

  private org.apache.dubbo.metrics.aggregate.TimeWindowCounter lambda$calcWindowCounter$4(org.apache.dubbo.metrics.model.MethodMetric);
    Code:
       0: new           #38                 // class org/apache/dubbo/metrics/aggregate/TimeWindowCounter
       3: dup
       4: aload_0
       5: getfield      #22                 // Field bucketNum:I
       8: aload_0
       9: getfield      #25                 // Field timeWindowSeconds:I
      12: invokespecial #132                // Method org/apache/dubbo/metrics/aggregate/TimeWindowCounter."<init>":(II)V
      15: areturn

  private static java.util.concurrent.ConcurrentHashMap lambda$calcWindowCounter$3(org.apache.dubbo.metrics.model.key.MetricsKeyWrapper);
    Code:
       0: new           #4                  // class java/util/concurrent/ConcurrentHashMap
       3: dup
       4: invokespecial #5                  // Method java/util/concurrent/ConcurrentHashMap."<init>":()V
       7: areturn

  private org.apache.dubbo.metrics.aggregate.TimeWindowQuantile lambda$onRTEvent$2(org.apache.dubbo.metrics.model.MethodMetric);
    Code:
       0: new           #55                 // class org/apache/dubbo/metrics/aggregate/TimeWindowQuantile
       3: dup
       4: getstatic     #133                // Field DEFAULT_COMPRESSION:Ljava/lang/Integer;
       7: invokevirtual #21                 // Method java/lang/Integer.intValue:()I
      10: i2d
      11: aload_0
      12: getfield      #22                 // Field bucketNum:I
      15: aload_0
      16: getfield      #25                 // Field timeWindowSeconds:I
      19: invokespecial #134                // Method org/apache/dubbo/metrics/aggregate/TimeWindowQuantile."<init>":(DII)V
      22: areturn

  private org.apache.dubbo.metrics.aggregate.TimeWindowCounter lambda$onEvent$1(org.apache.dubbo.metrics.model.MethodMetric);
    Code:
       0: new           #38                 // class org/apache/dubbo/metrics/aggregate/TimeWindowCounter
       3: dup
       4: aload_0
       5: getfield      #22                 // Field bucketNum:I
       8: aload_0
       9: getfield      #25                 // Field timeWindowSeconds:I
      12: invokespecial #132                // Method org/apache/dubbo/metrics/aggregate/TimeWindowCounter."<init>":(II)V
      15: areturn

  private void lambda$isCollectEnabled$0(org.apache.dubbo.config.MetricsConfig);
    Code:
       0: aload_0
       1: aload_1
       2: invokevirtual #18                 // Method org/apache/dubbo/config/MetricsConfig.getAggregation:()Lorg/apache/dubbo/config/nested/AggregationConfig;
       5: invokevirtual #135                // Method org/apache/dubbo/config/nested/AggregationConfig.getEnabled:()Ljava/lang/Boolean;
       8: invokevirtual #136                // Method setCollectEnabled:(Ljava/lang/Boolean;)V
      11: return

  static {};
    Code:
       0: bipush        100
       2: invokestatic  #137                // Method java/lang/Integer.valueOf:(I)Ljava/lang/Integer;
       5: putstatic     #133                // Field DEFAULT_COMPRESSION:Ljava/lang/Integer;
       8: bipush        10
      10: invokestatic  #137                // Method java/lang/Integer.valueOf:(I)Ljava/lang/Integer;
      13: putstatic     #20                 // Field DEFAULT_BUCKET_NUM:Ljava/lang/Integer;
      16: bipush        120
      18: invokestatic  #137                // Method java/lang/Integer.valueOf:(I)Ljava/lang/Integer;
      21: putstatic     #24                 // Field DEFAULT_TIME_WINDOW_SECONDS:Ljava/lang/Integer;
      24: return
}
