Compiled from "CombMetricsCollector.java"
public abstract class org.apache.dubbo.metrics.collector.CombMetricsCollector<E extends org.apache.dubbo.metrics.event.TimeCounterEvent> extends org.apache.dubbo.metrics.listener.AbstractMetricsListener<E> implements org.apache.dubbo.metrics.collector.ApplicationMetricsCollector<E>, org.apache.dubbo.metrics.collector.ServiceMetricsCollector<E>, org.apache.dubbo.metrics.collector.MethodMetricsCollector<E> {
  private final org.apache.dubbo.metrics.data.BaseStatComposite stats;

  private org.apache.dubbo.metrics.event.MetricsEventMulticaster eventMulticaster;

  public org.apache.dubbo.metrics.collector.CombMetricsCollector(org.apache.dubbo.metrics.data.BaseStatComposite);
    Code:
       0: aload_0
       1: invokespecial #2                  // Method org/apache/dubbo/metrics/listener/AbstractMetricsListener."<init>":()V
       4: aload_0
       5: aload_1
       6: putfield      #3                  // Field stats:Lorg/apache/dubbo/metrics/data/BaseStatComposite;
       9: return

  protected void setEventMulticaster(org.apache.dubbo.metrics.event.MetricsEventMulticaster);
    Code:
       0: aload_0
       1: aload_1
       2: putfield      #4                  // Field eventMulticaster:Lorg/apache/dubbo/metrics/event/MetricsEventMulticaster;
       5: return

  public void setNum(org.apache.dubbo.metrics.model.key.MetricsKeyWrapper, java.lang.String, int);
    Code:
       0: aload_0
       1: getfield      #3                  // Field stats:Lorg/apache/dubbo/metrics/data/BaseStatComposite;
       4: aload_1
       5: aload_2
       6: iload_3
       7: invokevirtual #5                  // Method org/apache/dubbo/metrics/data/BaseStatComposite.setServiceKey:(Lorg/apache/dubbo/metrics/model/key/MetricsKeyWrapper;Ljava/lang/String;I)V
      10: return

  public void increment(org.apache.dubbo.metrics.model.key.MetricsKey);
    Code:
       0: aload_0
       1: getfield      #3                  // Field stats:Lorg/apache/dubbo/metrics/data/BaseStatComposite;
       4: aload_1
       5: iconst_1
       6: invokevirtual #6                  // Method org/apache/dubbo/metrics/data/BaseStatComposite.incrementApp:(Lorg/apache/dubbo/metrics/model/key/MetricsKey;I)V
       9: return

  public void increment(java.lang.String, org.apache.dubbo.metrics.model.key.MetricsKeyWrapper, int);
    Code:
       0: aload_0
       1: getfield      #3                  // Field stats:Lorg/apache/dubbo/metrics/data/BaseStatComposite;
       4: aload_2
       5: aload_1
       6: iload_3
       7: invokevirtual #7                  // Method org/apache/dubbo/metrics/data/BaseStatComposite.incrementServiceKey:(Lorg/apache/dubbo/metrics/model/key/MetricsKeyWrapper;Ljava/lang/String;I)V
      10: return

  public void addRt(java.lang.String, java.lang.Long);
    Code:
       0: aload_0
       1: getfield      #3                  // Field stats:Lorg/apache/dubbo/metrics/data/BaseStatComposite;
       4: aload_1
       5: aload_2
       6: invokevirtual #8                  // Method org/apache/dubbo/metrics/data/BaseStatComposite.calcApplicationRt:(Ljava/lang/String;Ljava/lang/Long;)V
       9: return

  public void addRt(java.lang.String, java.lang.String, java.lang.Long);
    Code:
       0: aload_0
       1: getfield      #3                  // Field stats:Lorg/apache/dubbo/metrics/data/BaseStatComposite;
       4: aload_1
       5: aload_2
       6: aload_3
       7: invokevirtual #9                  // Method org/apache/dubbo/metrics/data/BaseStatComposite.calcServiceKeyRt:(Ljava/lang/String;Ljava/lang/String;Ljava/lang/Long;)V
      10: return

  public void increment(org.apache.dubbo.rpc.Invocation, org.apache.dubbo.metrics.model.key.MetricsKeyWrapper, int);
    Code:
       0: aload_0
       1: getfield      #3                  // Field stats:Lorg/apache/dubbo/metrics/data/BaseStatComposite;
       4: aload_2
       5: aload_1
       6: iload_3
       7: invokevirtual #10                 // Method org/apache/dubbo/metrics/data/BaseStatComposite.incrementMethodKey:(Lorg/apache/dubbo/metrics/model/key/MetricsKeyWrapper;Lorg/apache/dubbo/rpc/Invocation;I)V
      10: return

  public void addRt(org.apache.dubbo.rpc.Invocation, java.lang.String, java.lang.Long);
    Code:
       0: aload_0
       1: getfield      #3                  // Field stats:Lorg/apache/dubbo/metrics/data/BaseStatComposite;
       4: aload_1
       5: aload_2
       6: aload_3
       7: invokevirtual #11                 // Method org/apache/dubbo/metrics/data/BaseStatComposite.calcMethodKeyRt:(Lorg/apache/dubbo/rpc/Invocation;Ljava/lang/String;Ljava/lang/Long;)V
      10: return

  protected java.util.List<org.apache.dubbo.metrics.model.sample.MetricSample> export(org.apache.dubbo.metrics.model.MetricsCategory);
    Code:
       0: aload_0
       1: getfield      #3                  // Field stats:Lorg/apache/dubbo/metrics/data/BaseStatComposite;
       4: aload_1
       5: invokevirtual #12                 // Method org/apache/dubbo/metrics/data/BaseStatComposite.export:(Lorg/apache/dubbo/metrics/model/MetricsCategory;)Ljava/util/List;
       8: areturn

  public org.apache.dubbo.metrics.event.MetricsEventMulticaster getEventMulticaster();
    Code:
       0: aload_0
       1: getfield      #4                  // Field eventMulticaster:Lorg/apache/dubbo/metrics/event/MetricsEventMulticaster;
       4: areturn

  public void onEvent(org.apache.dubbo.metrics.event.TimeCounterEvent);
    Code:
       0: aload_0
       1: getfield      #4                  // Field eventMulticaster:Lorg/apache/dubbo/metrics/event/MetricsEventMulticaster;
       4: aload_1
       5: invokeinterface #13,  2           // InterfaceMethod org/apache/dubbo/metrics/event/MetricsEventMulticaster.publishEvent:(Lorg/apache/dubbo/metrics/event/MetricsEvent;)V
      10: return

  public void onEventFinish(org.apache.dubbo.metrics.event.TimeCounterEvent);
    Code:
       0: aload_0
       1: getfield      #4                  // Field eventMulticaster:Lorg/apache/dubbo/metrics/event/MetricsEventMulticaster;
       4: aload_1
       5: invokeinterface #14,  2           // InterfaceMethod org/apache/dubbo/metrics/event/MetricsEventMulticaster.publishFinishEvent:(Lorg/apache/dubbo/metrics/event/TimeCounterEvent;)V
      10: return

  public void onEventError(org.apache.dubbo.metrics.event.TimeCounterEvent);
    Code:
       0: aload_0
       1: getfield      #4                  // Field eventMulticaster:Lorg/apache/dubbo/metrics/event/MetricsEventMulticaster;
       4: aload_1
       5: invokeinterface #15,  2           // InterfaceMethod org/apache/dubbo/metrics/event/MetricsEventMulticaster.publishErrorEvent:(Lorg/apache/dubbo/metrics/event/TimeCounterEvent;)V
      10: return

  public void onEvent(org.apache.dubbo.metrics.event.MetricsEvent);
    Code:
       0: aload_0
       1: aload_1
       2: checkcast     #16                 // class org/apache/dubbo/metrics/event/TimeCounterEvent
       5: invokevirtual #17                 // Method onEvent:(Lorg/apache/dubbo/metrics/event/TimeCounterEvent;)V
       8: return
}
