Compiled from "DefaultMetricsCollector.java"
class org.apache.dubbo.metrics.collector.DefaultMetricsCollector$1 extends org.apache.dubbo.metrics.data.BaseStatComposite {
  org.apache.dubbo.metrics.collector.DefaultMetricsCollector$1(org.apache.dubbo.rpc.model.ApplicationModel);
    Code:
       0: aload_0
       1: aload_1
       2: invokespecial #1                  // Method org/apache/dubbo/metrics/data/BaseStatComposite."<init>":(Lorg/apache/dubbo/rpc/model/ApplicationModel;)V
       5: return

  protected void init(org.apache.dubbo.metrics.data.MethodStatComposite);
    Code:
       0: aload_0
       1: aload_1
       2: invokespecial #2                  // Method org/apache/dubbo/metrics/data/BaseStatComposite.init:(Lorg/apache/dubbo/metrics/data/MethodStatComposite;)V
       5: aload_1
       6: getstatic     #3                  // Field org/apache/dubbo/metrics/DefaultConstants.METHOD_LEVEL_KEYS:Ljava/util/List;
       9: invokevirtual #4                  // Method org/apache/dubbo/metrics/data/MethodStatComposite.initWrapper:(Ljava/util/List;)V
      12: return

  protected void init(org.apache.dubbo.metrics.data.RtStatComposite);
    Code:
       0: aload_0
       1: aload_1
       2: invokespecial #5                  // Method org/apache/dubbo/metrics/data/BaseStatComposite.init:(Lorg/apache/dubbo/metrics/data/RtStatComposite;)V
       5: aload_1
       6: iconst_2
       7: anewarray     #6                  // class org/apache/dubbo/metrics/model/key/MetricsPlaceValue
      10: dup
      11: iconst_0
      12: ldc           #8                  // String provider
      14: getstatic     #9                  // Field org/apache/dubbo/metrics/model/key/MetricsLevel.METHOD:Lorg/apache/dubbo/metrics/model/key/MetricsLevel;
      17: invokestatic  #10                 // Method org/apache/dubbo/metrics/model/key/MetricsPlaceValue.of:(Ljava/lang/String;Lorg/apache/dubbo/metrics/model/key/MetricsLevel;)Lorg/apache/dubbo/metrics/model/key/MetricsPlaceValue;
      20: aastore
      21: dup
      22: iconst_1
      23: ldc           #11                 // String consumer
      25: getstatic     #9                  // Field org/apache/dubbo/metrics/model/key/MetricsLevel.METHOD:Lorg/apache/dubbo/metrics/model/key/MetricsLevel;
      28: invokestatic  #10                 // Method org/apache/dubbo/metrics/model/key/MetricsPlaceValue.of:(Ljava/lang/String;Lorg/apache/dubbo/metrics/model/key/MetricsLevel;)Lorg/apache/dubbo/metrics/model/key/MetricsPlaceValue;
      31: aastore
      32: invokevirtual #12                 // Method org/apache/dubbo/metrics/data/RtStatComposite.init:([Lorg/apache/dubbo/metrics/model/key/MetricsPlaceValue;)V
      35: return
}
