Compiled from "HistogramMetricsCollector.java"
public class org.apache.dubbo.metrics.collector.HistogramMetricsCollector extends org.apache.dubbo.metrics.listener.AbstractMetricsListener<org.apache.dubbo.metrics.event.RequestEvent> implements org.apache.dubbo.metrics.collector.MetricsCollector<org.apache.dubbo.metrics.event.RequestEvent> {
  private final java.util.concurrent.ConcurrentHashMap<org.apache.dubbo.metrics.model.MethodMetric, io.micrometer.core.instrument.Timer> rt;

  private org.apache.dubbo.metrics.register.HistogramMetricRegister metricRegister;

  private final org.apache.dubbo.rpc.model.ApplicationModel applicationModel;

  private static final java.lang.Integer[] DEFAULT_BUCKETS_MS;

  public org.apache.dubbo.metrics.collector.HistogramMetricsCollector(org.apache.dubbo.rpc.model.ApplicationModel);
    Code:
       0: aload_0
       1: invokespecial #1                  // Method org/apache/dubbo/metrics/listener/AbstractMetricsListener."<init>":()V
       4: aload_0
       5: new           #2                  // class java/util/concurrent/ConcurrentHashMap
       8: dup
       9: invokespecial #3                  // Method java/util/concurrent/ConcurrentHashMap."<init>":()V
      12: putfield      #4                  // Field rt:Ljava/util/concurrent/ConcurrentHashMap;
      15: aload_0
      16: aload_1
      17: putfield      #5                  // Field applicationModel:Lorg/apache/dubbo/rpc/model/ApplicationModel;
      20: aload_1
      21: invokevirtual #6                  // Method org/apache/dubbo/rpc/model/ApplicationModel.getApplicationConfigManager:()Lorg/apache/dubbo/config/context/ConfigManager;
      24: astore_2
      25: aload_2
      26: invokevirtual #7                  // Method org/apache/dubbo/config/context/ConfigManager.getMetrics:()Ljava/util/Optional;
      29: aconst_null
      30: invokevirtual #8                  // Method java/util/Optional.orElse:(Ljava/lang/Object;)Ljava/lang/Object;
      33: checkcast     #9                  // class org/apache/dubbo/config/MetricsConfig
      36: astore_3
      37: aload_3
      38: ifnull        121
      41: aload_3
      42: invokevirtual #10                 // Method org/apache/dubbo/config/MetricsConfig.getHistogram:()Lorg/apache/dubbo/config/nested/HistogramConfig;
      45: ifnull        121
      48: getstatic     #11                 // Field java/lang/Boolean.TRUE:Ljava/lang/Boolean;
      51: aload_3
      52: invokevirtual #10                 // Method org/apache/dubbo/config/MetricsConfig.getHistogram:()Lorg/apache/dubbo/config/nested/HistogramConfig;
      55: invokevirtual #12                 // Method org/apache/dubbo/config/nested/HistogramConfig.getEnabled:()Ljava/lang/Boolean;
      58: invokevirtual #13                 // Method java/lang/Boolean.equals:(Ljava/lang/Object;)Z
      61: ifeq          121
      64: aload_0
      65: invokespecial #14                 // Method registerListener:()V
      68: aload_3
      69: invokevirtual #10                 // Method org/apache/dubbo/config/MetricsConfig.getHistogram:()Lorg/apache/dubbo/config/nested/HistogramConfig;
      72: astore        4
      74: getstatic     #11                 // Field java/lang/Boolean.TRUE:Ljava/lang/Boolean;
      77: aload         4
      79: invokevirtual #15                 // Method org/apache/dubbo/config/nested/HistogramConfig.getEnabledPercentiles:()Ljava/lang/Boolean;
      82: invokevirtual #13                 // Method java/lang/Boolean.equals:(Ljava/lang/Object;)Z
      85: ifne          104
      88: aload         4
      90: invokevirtual #16                 // Method org/apache/dubbo/config/nested/HistogramConfig.getBucketsMs:()[Ljava/lang/Integer;
      93: ifnonnull     104
      96: aload         4
      98: getstatic     #17                 // Field DEFAULT_BUCKETS_MS:[Ljava/lang/Integer;
     101: invokevirtual #18                 // Method org/apache/dubbo/config/nested/HistogramConfig.setBucketsMs:([Ljava/lang/Integer;)V
     104: aload_0
     105: new           #19                 // class org/apache/dubbo/metrics/register/HistogramMetricRegister
     108: dup
     109: aload_1
     110: invokestatic  #20                 // Method org/apache/dubbo/metrics/MetricsGlobalRegistry.getCompositeRegistry:(Lorg/apache/dubbo/rpc/model/ApplicationModel;)Lio/micrometer/core/instrument/composite/CompositeMeterRegistry;
     113: aload         4
     115: invokespecial #21                 // Method org/apache/dubbo/metrics/register/HistogramMetricRegister."<init>":(Lio/micrometer/core/instrument/MeterRegistry;Lorg/apache/dubbo/config/nested/HistogramConfig;)V
     118: putfield      #22                 // Field metricRegister:Lorg/apache/dubbo/metrics/register/HistogramMetricRegister;
     121: return

  private void registerListener();
    Code:
       0: aload_0
       1: getfield      #5                  // Field applicationModel:Lorg/apache/dubbo/rpc/model/ApplicationModel;
       4: invokevirtual #23                 // Method org/apache/dubbo/rpc/model/ApplicationModel.getBeanFactory:()Lorg/apache/dubbo/common/beans/factory/ScopeBeanFactory;
       7: ldc           #24                 // class org/apache/dubbo/metrics/collector/DefaultMetricsCollector
       9: invokevirtual #25                 // Method org/apache/dubbo/common/beans/factory/ScopeBeanFactory.getBean:(Ljava/lang/Class;)Ljava/lang/Object;
      12: checkcast     #24                 // class org/apache/dubbo/metrics/collector/DefaultMetricsCollector
      15: invokevirtual #26                 // Method org/apache/dubbo/metrics/collector/DefaultMetricsCollector.getEventMulticaster:()Lorg/apache/dubbo/metrics/event/MetricsEventMulticaster;
      18: aload_0
      19: invokeinterface #27,  2           // InterfaceMethod org/apache/dubbo/metrics/event/MetricsEventMulticaster.addListener:(Lorg/apache/dubbo/metrics/listener/MetricsListener;)V
      24: return

  public void onEvent(org.apache.dubbo.metrics.event.RequestEvent);
    Code:
       0: return

  public void onEventFinish(org.apache.dubbo.metrics.event.RequestEvent);
    Code:
       0: aload_0
       1: aload_1
       2: invokespecial #28                 // Method onRTEvent:(Lorg/apache/dubbo/metrics/event/RequestEvent;)V
       5: return

  public void onEventError(org.apache.dubbo.metrics.event.RequestEvent);
    Code:
       0: aload_0
       1: aload_1
       2: invokespecial #28                 // Method onRTEvent:(Lorg/apache/dubbo/metrics/event/RequestEvent;)V
       5: return

  private void onRTEvent(org.apache.dubbo.metrics.event.RequestEvent);
    Code:
       0: aload_0
       1: getfield      #22                 // Field metricRegister:Lorg/apache/dubbo/metrics/register/HistogramMetricRegister;
       4: ifnull        100
       7: new           #29                 // class org/apache/dubbo/metrics/model/MethodMetric
      10: dup
      11: aload_0
      12: getfield      #5                  // Field applicationModel:Lorg/apache/dubbo/rpc/model/ApplicationModel;
      15: aload_1
      16: ldc           #31                 // String metric_filter_invocation
      18: invokevirtual #32                 // Method org/apache/dubbo/metrics/event/RequestEvent.getAttachmentValue:(Ljava/lang/String;)Ljava/lang/Object;
      21: checkcast     #33                 // class org/apache/dubbo/rpc/Invocation
      24: invokespecial #34                 // Method org/apache/dubbo/metrics/model/MethodMetric."<init>":(Lorg/apache/dubbo/rpc/model/ApplicationModel;Lorg/apache/dubbo/rpc/Invocation;)V
      27: astore_2
      28: aload_1
      29: invokevirtual #35                 // Method org/apache/dubbo/metrics/event/RequestEvent.getTimePair:()Lorg/apache/dubbo/metrics/model/TimePair;
      32: invokevirtual #36                 // Method org/apache/dubbo/metrics/model/TimePair.calc:()J
      35: lstore_3
      36: new           #37                 // class org/apache/dubbo/metrics/sample/HistogramMetricSample
      39: dup
      40: getstatic     #38                 // Field org/apache/dubbo/metrics/model/key/MetricsKey.METRIC_RT_HISTOGRAM:Lorg/apache/dubbo/metrics/model/key/MetricsKey;
      43: aload_2
      44: invokevirtual #39                 // Method org/apache/dubbo/metrics/model/MethodMetric.getSide:()Ljava/lang/String;
      47: invokevirtual #40                 // Method org/apache/dubbo/metrics/model/key/MetricsKey.getNameByType:(Ljava/lang/String;)Ljava/lang/String;
      50: getstatic     #38                 // Field org/apache/dubbo/metrics/model/key/MetricsKey.METRIC_RT_HISTOGRAM:Lorg/apache/dubbo/metrics/model/key/MetricsKey;
      53: invokevirtual #41                 // Method org/apache/dubbo/metrics/model/key/MetricsKey.getDescription:()Ljava/lang/String;
      56: aload_2
      57: invokevirtual #42                 // Method org/apache/dubbo/metrics/model/MethodMetric.getTags:()Ljava/util/Map;
      60: getstatic     #43                 // Field org/apache/dubbo/metrics/model/MetricsCategory.RT:Lorg/apache/dubbo/metrics/model/MetricsCategory;
      63: invokespecial #44                 // Method org/apache/dubbo/metrics/sample/HistogramMetricSample."<init>":(Ljava/lang/String;Ljava/lang/String;Ljava/util/Map;Lorg/apache/dubbo/metrics/model/MetricsCategory;)V
      66: astore        5
      68: aload_0
      69: getfield      #4                  // Field rt:Ljava/util/concurrent/ConcurrentHashMap;
      72: aload_2
      73: aload_0
      74: aload         5
      76: invokedynamic #45,  0             // InvokeDynamic #0:apply:(Lorg/apache/dubbo/metrics/collector/HistogramMetricsCollector;Lorg/apache/dubbo/metrics/sample/HistogramMetricSample;)Ljava/util/function/Function;
      81: invokestatic  #46                 // Method org/apache/dubbo/common/utils/ConcurrentHashMapUtils.computeIfAbsent:(Ljava/util/concurrent/ConcurrentMap;Ljava/lang/Object;Ljava/util/function/Function;)Ljava/lang/Object;
      84: checkcast     #47                 // class io/micrometer/core/instrument/Timer
      87: astore        6
      89: aload         6
      91: lload_3
      92: getstatic     #48                 // Field java/util/concurrent/TimeUnit.MILLISECONDS:Ljava/util/concurrent/TimeUnit;
      95: invokeinterface #49,  4           // InterfaceMethod io/micrometer/core/instrument/Timer.record:(JLjava/util/concurrent/TimeUnit;)V
     100: return

  public java.util.List<org.apache.dubbo.metrics.model.sample.MetricSample> collect();
    Code:
       0: new           #50                 // class java/util/ArrayList
       3: dup
       4: invokespecial #51                 // Method java/util/ArrayList."<init>":()V
       7: areturn

  public void onEvent(org.apache.dubbo.metrics.event.MetricsEvent);
    Code:
       0: aload_0
       1: aload_1
       2: checkcast     #52                 // class org/apache/dubbo/metrics/event/RequestEvent
       5: invokevirtual #53                 // Method onEvent:(Lorg/apache/dubbo/metrics/event/RequestEvent;)V
       8: return

  public void onEventError(org.apache.dubbo.metrics.event.TimeCounterEvent);
    Code:
       0: aload_0
       1: aload_1
       2: checkcast     #52                 // class org/apache/dubbo/metrics/event/RequestEvent
       5: invokevirtual #54                 // Method onEventError:(Lorg/apache/dubbo/metrics/event/RequestEvent;)V
       8: return

  public void onEventFinish(org.apache.dubbo.metrics.event.TimeCounterEvent);
    Code:
       0: aload_0
       1: aload_1
       2: checkcast     #52                 // class org/apache/dubbo/metrics/event/RequestEvent
       5: invokevirtual #55                 // Method onEventFinish:(Lorg/apache/dubbo/metrics/event/RequestEvent;)V
       8: return

  private io.micrometer.core.instrument.Timer lambda$onRTEvent$0(org.apache.dubbo.metrics.sample.HistogramMetricSample, org.apache.dubbo.metrics.model.MethodMetric);
    Code:
       0: aload_0
       1: getfield      #22                 // Field metricRegister:Lorg/apache/dubbo/metrics/register/HistogramMetricRegister;
       4: aload_1
       5: invokevirtual #56                 // Method org/apache/dubbo/metrics/register/HistogramMetricRegister.register:(Lorg/apache/dubbo/metrics/sample/HistogramMetricSample;)Lio/micrometer/core/instrument/Timer;
       8: areturn

  static {};
    Code:
       0: bipush        7
       2: anewarray     #57                 // class java/lang/Integer
       5: dup
       6: iconst_0
       7: bipush        100
       9: invokestatic  #58                 // Method java/lang/Integer.valueOf:(I)Ljava/lang/Integer;
      12: aastore
      13: dup
      14: iconst_1
      15: sipush        300
      18: invokestatic  #58                 // Method java/lang/Integer.valueOf:(I)Ljava/lang/Integer;
      21: aastore
      22: dup
      23: iconst_2
      24: sipush        500
      27: invokestatic  #58                 // Method java/lang/Integer.valueOf:(I)Ljava/lang/Integer;
      30: aastore
      31: dup
      32: iconst_3
      33: sipush        1000
      36: invokestatic  #58                 // Method java/lang/Integer.valueOf:(I)Ljava/lang/Integer;
      39: aastore
      40: dup
      41: iconst_4
      42: sipush        3000
      45: invokestatic  #58                 // Method java/lang/Integer.valueOf:(I)Ljava/lang/Integer;
      48: aastore
      49: dup
      50: iconst_5
      51: sipush        5000
      54: invokestatic  #58                 // Method java/lang/Integer.valueOf:(I)Ljava/lang/Integer;
      57: aastore
      58: dup
      59: bipush        6
      61: sipush        10000
      64: invokestatic  #58                 // Method java/lang/Integer.valueOf:(I)Ljava/lang/Integer;
      67: aastore
      68: putstatic     #17                 // Field DEFAULT_BUCKETS_MS:[Ljava/lang/Integer;
      71: return
}
