Compiled from "DefaultSerializationSelector.java"
public class org.apache.dubbo.common.serialize.support.DefaultSerializationSelector {
  private static final java.lang.String DEFAULT_REMOTING_SERIALIZATION_PROPERTY_KEY;

  private static final java.lang.String DEFAULT_REMOTING_SERIALIZATION_PROPERTY;

  private static final java.lang.String DEFAULT_REMOTING_SERIALIZATION;

  public org.apache.dubbo.common.serialize.support.DefaultSerializationSelector();
    Code:
       0: aload_0
       1: invokespecial #1                  // Method java/lang/Object."<init>":()V
       4: return

  public static java.lang.String getDefaultRemotingSerialization();
    Code:
       0: getstatic     #2                  // Field DEFAULT_REMOTING_SERIALIZATION:Ljava/lang/String;
       3: areturn

  static {};
    Code:
       0: ldc           #4                  // String DUBBO_DEFAULT_SERIALIZATION
       2: invokestatic  #5                  // Method java/lang/System.getProperty:(Ljava/lang/String;)Ljava/lang/String;
       5: astore_0
       6: aload_0
       7: ifnull        17
      10: aload_0
      11: putstatic     #2                  // Field DEFAULT_REMOTING_SERIALIZATION:Ljava/lang/String;
      14: goto          39
      17: ldc           #4                  // String DUBBO_DEFAULT_SERIALIZATION
      19: invokestatic  #6                  // Method java/lang/System.getenv:(Ljava/lang/String;)Ljava/lang/String;
      22: astore_1
      23: aload_1
      24: ifnull        34
      27: aload_1
      28: putstatic     #2                  // Field DEFAULT_REMOTING_SERIALIZATION:Ljava/lang/String;
      31: goto          39
      34: ldc           #7                  // String hessian2
      36: putstatic     #2                  // Field DEFAULT_REMOTING_SERIALIZATION:Ljava/lang/String;
      39: return
}
