Compiled from "SerializableClassRegistry.java"
public abstract class org.apache.dubbo.common.serialize.support.SerializableClassRegistry {
  private static final java.util.Map<java.lang.Class<?>, java.lang.Object> REGISTRATIONS;

  public org.apache.dubbo.common.serialize.support.SerializableClassRegistry();
    Code:
       0: aload_0
       1: invokespecial #1                  // Method java/lang/Object."<init>":()V
       4: return

  public static void registerClass(java.lang.Class<?>);
    Code:
       0: aload_0
       1: aconst_null
       2: invokestatic  #2                  // Method registerClass:(Ljava/lang/Class;Ljava/lang/Object;)V
       5: return

  public static void registerClass(java.lang.Class<?>, java.lang.Object);
    Code:
       0: aload_0
       1: ifnonnull     14
       4: new           #3                  // class java/lang/IllegalArgumentException
       7: dup
       8: ldc           #4                  // String Class registered to kryo cannot be null!
      10: invokespecial #5                  // Method java/lang/IllegalArgumentException."<init>":(Ljava/lang/String;)V
      13: athrow
      14: getstatic     #6                  // Field REGISTRATIONS:Ljava/util/Map;
      17: aload_0
      18: aload_1
      19: invokeinterface #7,  3            // InterfaceMethod java/util/Map.put:(Ljava/lang/Object;Ljava/lang/Object;)Ljava/lang/Object;
      24: pop
      25: return

  public static java.util.Map<java.lang.Class<?>, java.lang.Object> getRegisteredClasses();
    Code:
       0: getstatic     #6                  // Field REGISTRATIONS:Ljava/util/Map;
       3: areturn

  static {};
    Code:
       0: new           #8                  // class java/util/HashMap
       3: dup
       4: invokespecial #9                  // Method java/util/HashMap."<init>":()V
       7: putstatic     #6                  // Field REGISTRATIONS:Ljava/util/Map;
      10: return
}
