Compiled from "AbstractScriptDatabaseInitializer.java"
class org.springframework.boot.sql.init.AbstractScriptDatabaseInitializer$ScriptLocationResolver {
  private final org.springframework.core.io.support.ResourcePatternResolver resourcePatternResolver;

  org.springframework.boot.sql.init.AbstractScriptDatabaseInitializer$ScriptLocationResolver(org.springframework.core.io.ResourceLoader);
    Code:
       0: aload_0
       1: invokespecial #1                  // Method java/lang/Object."<init>":()V
       4: aload_0
       5: aload_1
       6: invokestatic  #7                  // Method org/springframework/core/io/support/ResourcePatternUtils.getResourcePatternResolver:(Lorg/springframework/core/io/ResourceLoader;)Lorg/springframework/core/io/support/ResourcePatternResolver;
       9: putfield      #13                 // Field resourcePatternResolver:Lorg/springframework/core/io/support/ResourcePatternResolver;
      12: return

  private java.util.List<org.springframework.core.io.Resource> resolve(java.lang.String) throws java.io.IOException;
    Code:
       0: new           #19                 // class java/util/ArrayList
       3: dup
       4: aload_0
       5: getfield      #13                 // Field resourcePatternResolver:Lorg/springframework/core/io/support/ResourcePatternResolver;
       8: aload_1
       9: invokeinterface #21,  2           // InterfaceMethod org/springframework/core/io/support/ResourcePatternResolver.getResources:(Ljava/lang/String;)[Lorg/springframework/core/io/Resource;
      14: invokestatic  #27                 // Method java/util/Arrays.asList:([Ljava/lang/Object;)Ljava/util/List;
      17: invokespecial #33                 // Method java/util/ArrayList."<init>":(Ljava/util/Collection;)V
      20: astore_2
      21: aload_2
      22: invokedynamic #36,  0             // InvokeDynamic #0:compare:()Ljava/util/Comparator;
      27: invokeinterface #40,  2           // InterfaceMethod java/util/List.sort:(Ljava/util/Comparator;)V
      32: aload_2
      33: areturn

  private static int lambda$resolve$0(org.springframework.core.io.Resource, org.springframework.core.io.Resource);
    Code:
       0: aload_0
       1: invokeinterface #46,  1           // InterfaceMethod org/springframework/core/io/Resource.getURL:()Ljava/net/URL;
       6: invokevirtual #52                 // Method java/net/URL.toString:()Ljava/lang/String;
       9: aload_1
      10: invokeinterface #46,  1           // InterfaceMethod org/springframework/core/io/Resource.getURL:()Ljava/net/URL;
      15: invokevirtual #52                 // Method java/net/URL.toString:()Ljava/lang/String;
      18: invokevirtual #58                 // Method java/lang/String.compareTo:(Ljava/lang/String;)I
      21: ireturn
      22: astore_2
      23: iconst_0
      24: ireturn
    Exception table:
       from    to  target type
           0    21    22   Class java/io/IOException
}
