Compiled from "AbstractScriptDatabaseInitializer.java"
public class org.springframework.boot.sql.init.AbstractScriptDatabaseInitializer$Scripts implements java.lang.Iterable<org.springframework.core.io.Resource> {
  private final java.util.List<org.springframework.core.io.Resource> resources;

  private boolean continueOnError;

  private java.lang.String separator;

  private java.nio.charset.Charset encoding;

  public org.springframework.boot.sql.init.AbstractScriptDatabaseInitializer$Scripts(java.util.List<org.springframework.core.io.Resource>);
    Code:
       0: aload_0
       1: invokespecial #1                  // Method java/lang/Object."<init>":()V
       4: aload_0
       5: iconst_0
       6: putfield      #7                  // Field continueOnError:Z
       9: aload_0
      10: ldc           #13                 // String ;
      12: putfield      #15                 // Field separator:Ljava/lang/String;
      15: aload_0
      16: aload_1
      17: putfield      #19                 // Field resources:Ljava/util/List;
      20: return

  public java.util.Iterator<org.springframework.core.io.Resource> iterator();
    Code:
       0: aload_0
       1: getfield      #19                 // Field resources:Ljava/util/List;
       4: invokeinterface #23,  1           // InterfaceMethod java/util/List.iterator:()Ljava/util/Iterator;
       9: areturn

  public org.springframework.boot.sql.init.AbstractScriptDatabaseInitializer$Scripts continueOnError(boolean);
    Code:
       0: aload_0
       1: iload_1
       2: putfield      #7                  // Field continueOnError:Z
       5: aload_0
       6: areturn

  public boolean isContinueOnError();
    Code:
       0: aload_0
       1: getfield      #7                  // Field continueOnError:Z
       4: ireturn

  public org.springframework.boot.sql.init.AbstractScriptDatabaseInitializer$Scripts separator(java.lang.String);
    Code:
       0: aload_0
       1: aload_1
       2: putfield      #15                 // Field separator:Ljava/lang/String;
       5: aload_0
       6: areturn

  public java.lang.String getSeparator();
    Code:
       0: aload_0
       1: getfield      #15                 // Field separator:Ljava/lang/String;
       4: areturn

  public org.springframework.boot.sql.init.AbstractScriptDatabaseInitializer$Scripts encoding(java.nio.charset.Charset);
    Code:
       0: aload_0
       1: aload_1
       2: putfield      #29                 // Field encoding:Ljava/nio/charset/Charset;
       5: aload_0
       6: areturn

  public java.nio.charset.Charset getEncoding();
    Code:
       0: aload_0
       1: getfield      #29                 // Field encoding:Ljava/nio/charset/Charset;
       4: areturn
}
