Compiled from "DatabaseInitializationSettings.java"
public class org.springframework.boot.sql.init.DatabaseInitializationSettings {
  private java.util.List<java.lang.String> schemaLocations;

  private java.util.List<java.lang.String> dataLocations;

  private boolean continueOnError;

  private java.lang.String separator;

  private java.nio.charset.Charset encoding;

  private org.springframework.boot.sql.init.DatabaseInitializationMode mode;

  public org.springframework.boot.sql.init.DatabaseInitializationSettings();
    Code:
       0: aload_0
       1: invokespecial #1                  // Method java/lang/Object."<init>":()V
       4: aload_0
       5: iconst_0
       6: putfield      #7                  // Field continueOnError:Z
       9: aload_0
      10: ldc           #13                 // String ;
      12: putfield      #15                 // Field separator:Ljava/lang/String;
      15: aload_0
      16: getstatic     #19                 // Field org/springframework/boot/sql/init/DatabaseInitializationMode.EMBEDDED:Lorg/springframework/boot/sql/init/DatabaseInitializationMode;
      19: putfield      #25                 // Field mode:Lorg/springframework/boot/sql/init/DatabaseInitializationMode;
      22: return

  public java.util.List<java.lang.String> getSchemaLocations();
    Code:
       0: aload_0
       1: getfield      #28                 // Field schemaLocations:Ljava/util/List;
       4: areturn

  public void setSchemaLocations(java.util.List<java.lang.String>);
    Code:
       0: aload_0
       1: aload_1
       2: putfield      #28                 // Field schemaLocations:Ljava/util/List;
       5: return

  public java.util.List<java.lang.String> getDataLocations();
    Code:
       0: aload_0
       1: getfield      #32                 // Field dataLocations:Ljava/util/List;
       4: areturn

  public void setDataLocations(java.util.List<java.lang.String>);
    Code:
       0: aload_0
       1: aload_1
       2: putfield      #32                 // Field dataLocations:Ljava/util/List;
       5: return

  public boolean isContinueOnError();
    Code:
       0: aload_0
       1: getfield      #7                  // Field continueOnError:Z
       4: ireturn

  public void setContinueOnError(boolean);
    Code:
       0: aload_0
       1: iload_1
       2: putfield      #7                  // Field continueOnError:Z
       5: return

  public java.lang.String getSeparator();
    Code:
       0: aload_0
       1: getfield      #15                 // Field separator:Ljava/lang/String;
       4: areturn

  public void setSeparator(java.lang.String);
    Code:
       0: aload_0
       1: aload_1
       2: putfield      #15                 // Field separator:Ljava/lang/String;
       5: return

  public java.nio.charset.Charset getEncoding();
    Code:
       0: aload_0
       1: getfield      #35                 // Field encoding:Ljava/nio/charset/Charset;
       4: areturn

  public void setEncoding(java.nio.charset.Charset);
    Code:
       0: aload_0
       1: aload_1
       2: putfield      #35                 // Field encoding:Ljava/nio/charset/Charset;
       5: return

  public org.springframework.boot.sql.init.DatabaseInitializationMode getMode();
    Code:
       0: aload_0
       1: getfield      #25                 // Field mode:Lorg/springframework/boot/sql/init/DatabaseInitializationMode;
       4: areturn

  public void setMode(org.springframework.boot.sql.init.DatabaseInitializationMode);
    Code:
       0: aload_0
       1: aload_1
       2: putfield      #25                 // Field mode:Lorg/springframework/boot/sql/init/DatabaseInitializationMode;
       5: return
}
