Compiled from "CacheFactory.java"
public interface com.alibaba.dubbo.cache.CacheFactory extends org.apache.dubbo.cache.CacheFactory {
  public abstract com.alibaba.dubbo.cache.Cache getCache(com.alibaba.dubbo.common.URL, com.alibaba.dubbo.rpc.Invocation);

  public default org.apache.dubbo.cache.Cache getCache(org.apache.dubbo.common.URL, org.apache.dubbo.rpc.Invocation);
    Code:
       0: aload_0
       1: new           #1                  // class com/alibaba/dubbo/common/URL
       4: dup
       5: aload_1
       6: invokespecial #2                  // Method com/alibaba/dubbo/common/URL."<init>":(Lorg/apache/dubbo/common/URL;)V
       9: new           #3                  // class com/alibaba/dubbo/rpc/Invocation$CompatibleInvocation
      12: dup
      13: aload_2
      14: invokespecial #4                  // Method com/alibaba/dubbo/rpc/Invocation$CompatibleInvocation."<init>":(Lorg/apache/dubbo/rpc/Invocation;)V
      17: invokeinterface #5,  3            // InterfaceMethod getCache:(Lcom/alibaba/dubbo/common/URL;Lcom/alibaba/dubbo/rpc/Invocation;)Lcom/alibaba/dubbo/cache/Cache;
      22: areturn
}
