Compiled from "MediaType.java"
public final class org.apache.dubbo.metadata.rest.media.MediaType extends java.lang.Enum<org.apache.dubbo.metadata.rest.media.MediaType> {
  public static final org.apache.dubbo.metadata.rest.media.MediaType ALL_VALUE;

  public static final org.apache.dubbo.metadata.rest.media.MediaType APPLICATION_JSON_VALUE;

  public static final org.apache.dubbo.metadata.rest.media.MediaType APPLICATION_FORM_URLENCODED_VALUE;

  public static final org.apache.dubbo.metadata.rest.media.MediaType TEXT_PLAIN;

  public static final org.apache.dubbo.metadata.rest.media.MediaType TEXT_XML;

  public static final org.apache.dubbo.metadata.rest.media.MediaType OCTET_STREAM;

  public java.lang.String value;

  private static final org.apache.dubbo.metadata.rest.media.MediaType[] $VALUES;

  public static org.apache.dubbo.metadata.rest.media.MediaType[] values();
    Code:
       0: getstatic     #1                  // Field $VALUES:[Lorg/apache/dubbo/metadata/rest/media/MediaType;
       3: invokevirtual #2                  // Method "[Lorg/apache/dubbo/metadata/rest/media/MediaType;".clone:()Ljava/lang/Object;
       6: checkcast     #3                  // class "[Lorg/apache/dubbo/metadata/rest/media/MediaType;"
       9: areturn

  public static org.apache.dubbo.metadata.rest.media.MediaType valueOf(java.lang.String);
    Code:
       0: ldc           #4                  // class org/apache/dubbo/metadata/rest/media/MediaType
       2: aload_0
       3: invokestatic  #5                  // Method java/lang/Enum.valueOf:(Ljava/lang/Class;Ljava/lang/String;)Ljava/lang/Enum;
       6: checkcast     #4                  // class org/apache/dubbo/metadata/rest/media/MediaType
       9: areturn

  private org.apache.dubbo.metadata.rest.media.MediaType(java.lang.String);
    Code:
       0: aload_0
       1: aload_1
       2: iload_2
       3: invokespecial #6                  // Method java/lang/Enum."<init>":(Ljava/lang/String;I)V
       6: aload_0
       7: aload_3
       8: putfield      #7                  // Field value:Ljava/lang/String;
      11: return

  public static java.lang.String getAllContentType();
    Code:
       0: invokestatic  #8                  // Method values:()[Lorg/apache/dubbo/metadata/rest/media/MediaType;
       3: astore_0
       4: new           #9                  // class java/lang/StringBuilder
       7: dup
       8: invokespecial #10                 // Method java/lang/StringBuilder."<init>":()V
      11: astore_1
      12: aload_0
      13: astore_2
      14: aload_2
      15: arraylength
      16: istore_3
      17: iconst_0
      18: istore        4
      20: iload         4
      22: iload_3
      23: if_icmpge     66
      26: aload_2
      27: iload         4
      29: aaload
      30: astore        5
      32: aload_1
      33: new           #9                  // class java/lang/StringBuilder
      36: dup
      37: invokespecial #10                 // Method java/lang/StringBuilder."<init>":()V
      40: aload         5
      42: getfield      #7                  // Field value:Ljava/lang/String;
      45: invokevirtual #11                 // Method java/lang/StringBuilder.append:(Ljava/lang/String;)Ljava/lang/StringBuilder;
      48: ldc           #12                 // String
      50: invokevirtual #11                 // Method java/lang/StringBuilder.append:(Ljava/lang/String;)Ljava/lang/StringBuilder;
      53: invokevirtual #13                 // Method java/lang/StringBuilder.toString:()Ljava/lang/String;
      56: invokevirtual #11                 // Method java/lang/StringBuilder.append:(Ljava/lang/String;)Ljava/lang/StringBuilder;
      59: pop
      60: iinc          4, 1
      63: goto          20
      66: aload_1
      67: invokevirtual #13                 // Method java/lang/StringBuilder.toString:()Ljava/lang/String;
      70: areturn

  public static java.util.List<org.apache.dubbo.metadata.rest.media.MediaType> getSupportMediaTypes();
    Code:
       0: iconst_5
       1: anewarray     #4                  // class org/apache/dubbo/metadata/rest/media/MediaType
       4: dup
       5: iconst_0
       6: getstatic     #14                 // Field APPLICATION_JSON_VALUE:Lorg/apache/dubbo/metadata/rest/media/MediaType;
       9: aastore
      10: dup
      11: iconst_1
      12: getstatic     #15                 // Field APPLICATION_FORM_URLENCODED_VALUE:Lorg/apache/dubbo/metadata/rest/media/MediaType;
      15: aastore
      16: dup
      17: iconst_2
      18: getstatic     #16                 // Field TEXT_PLAIN:Lorg/apache/dubbo/metadata/rest/media/MediaType;
      21: aastore
      22: dup
      23: iconst_3
      24: getstatic     #17                 // Field TEXT_XML:Lorg/apache/dubbo/metadata/rest/media/MediaType;
      27: aastore
      28: dup
      29: iconst_4
      30: getstatic     #18                 // Field OCTET_STREAM:Lorg/apache/dubbo/metadata/rest/media/MediaType;
      33: aastore
      34: invokestatic  #19                 // Method java/util/Arrays.asList:([Ljava/lang/Object;)Ljava/util/List;
      37: areturn

  static {};
    Code:
       0: new           #4                  // class org/apache/dubbo/metadata/rest/media/MediaType
       3: dup
       4: ldc           #20                 // String ALL_VALUE
       6: iconst_0
       7: ldc           #21                 // String */*
       9: invokespecial #22                 // Method "<init>":(Ljava/lang/String;ILjava/lang/String;)V
      12: putstatic     #23                 // Field ALL_VALUE:Lorg/apache/dubbo/metadata/rest/media/MediaType;
      15: new           #4                  // class org/apache/dubbo/metadata/rest/media/MediaType
      18: dup
      19: ldc           #24                 // String APPLICATION_JSON_VALUE
      21: iconst_1
      22: ldc           #25                 // String application/json
      24: invokespecial #22                 // Method "<init>":(Ljava/lang/String;ILjava/lang/String;)V
      27: putstatic     #14                 // Field APPLICATION_JSON_VALUE:Lorg/apache/dubbo/metadata/rest/media/MediaType;
      30: new           #4                  // class org/apache/dubbo/metadata/rest/media/MediaType
      33: dup
      34: ldc           #26                 // String APPLICATION_FORM_URLENCODED_VALUE
      36: iconst_2
      37: ldc           #27                 // String application/x-www-form-urlencoded
      39: invokespecial #22                 // Method "<init>":(Ljava/lang/String;ILjava/lang/String;)V
      42: putstatic     #15                 // Field APPLICATION_FORM_URLENCODED_VALUE:Lorg/apache/dubbo/metadata/rest/media/MediaType;
      45: new           #4                  // class org/apache/dubbo/metadata/rest/media/MediaType
      48: dup
      49: ldc           #28                 // String TEXT_PLAIN
      51: iconst_3
      52: ldc           #29                 // String text/plain
      54: invokespecial #22                 // Method "<init>":(Ljava/lang/String;ILjava/lang/String;)V
      57: putstatic     #16                 // Field TEXT_PLAIN:Lorg/apache/dubbo/metadata/rest/media/MediaType;
      60: new           #4                  // class org/apache/dubbo/metadata/rest/media/MediaType
      63: dup
      64: ldc           #30                 // String TEXT_XML
      66: iconst_4
      67: ldc           #31                 // String text/xml
      69: invokespecial #22                 // Method "<init>":(Ljava/lang/String;ILjava/lang/String;)V
      72: putstatic     #17                 // Field TEXT_XML:Lorg/apache/dubbo/metadata/rest/media/MediaType;
      75: new           #4                  // class org/apache/dubbo/metadata/rest/media/MediaType
      78: dup
      79: ldc           #32                 // String OCTET_STREAM
      81: iconst_5
      82: ldc           #33                 // String application/octet-stream
      84: invokespecial #22                 // Method "<init>":(Ljava/lang/String;ILjava/lang/String;)V
      87: putstatic     #18                 // Field OCTET_STREAM:Lorg/apache/dubbo/metadata/rest/media/MediaType;
      90: bipush        6
      92: anewarray     #4                  // class org/apache/dubbo/metadata/rest/media/MediaType
      95: dup
      96: iconst_0
      97: getstatic     #23                 // Field ALL_VALUE:Lorg/apache/dubbo/metadata/rest/media/MediaType;
     100: aastore
     101: dup
     102: iconst_1
     103: getstatic     #14                 // Field APPLICATION_JSON_VALUE:Lorg/apache/dubbo/metadata/rest/media/MediaType;
     106: aastore
     107: dup
     108: iconst_2
     109: getstatic     #15                 // Field APPLICATION_FORM_URLENCODED_VALUE:Lorg/apache/dubbo/metadata/rest/media/MediaType;
     112: aastore
     113: dup
     114: iconst_3
     115: getstatic     #16                 // Field TEXT_PLAIN:Lorg/apache/dubbo/metadata/rest/media/MediaType;
     118: aastore
     119: dup
     120: iconst_4
     121: getstatic     #17                 // Field TEXT_XML:Lorg/apache/dubbo/metadata/rest/media/MediaType;
     124: aastore
     125: dup
     126: iconst_5
     127: getstatic     #18                 // Field OCTET_STREAM:Lorg/apache/dubbo/metadata/rest/media/MediaType;
     130: aastore
     131: putstatic     #1                  // Field $VALUES:[Lorg/apache/dubbo/metadata/rest/media/MediaType;
     134: return
}
