Compiled from "EdsEndpointManager.java"
public class org.apache.dubbo.rpc.cluster.router.xds.EdsEndpointManager {
  private static final java.util.concurrent.ConcurrentHashMap<java.lang.String, java.util.Set<org.apache.dubbo.rpc.cluster.router.xds.EdsEndpointListener>> ENDPOINT_LISTENERS;

  private static final java.util.concurrent.ConcurrentHashMap<java.lang.String, java.util.Set<org.apache.dubbo.registry.xds.util.protocol.message.Endpoint>> ENDPOINT_DATA_CACHE;

  private static final java.util.concurrent.ConcurrentHashMap<java.lang.String, java.util.function.Consumer<java.util.Map<java.lang.String, org.apache.dubbo.registry.xds.util.protocol.message.EndpointResult>>> EDS_LISTENERS;

  public org.apache.dubbo.rpc.cluster.router.xds.EdsEndpointManager();
    Code:
       0: aload_0
       1: invokespecial #1                  // Method java/lang/Object."<init>":()V
       4: return

  public synchronized void subscribeEds(java.lang.String, org.apache.dubbo.rpc.cluster.router.xds.EdsEndpointListener);
    Code:
       0: getstatic     #2                  // Field ENDPOINT_LISTENERS:Ljava/util/concurrent/ConcurrentHashMap;
       3: aload_1
       4: invokedynamic #3,  0              // InvokeDynamic #0:apply:()Ljava/util/function/Function;
       9: invokestatic  #4                  // Method org/apache/dubbo/common/utils/ConcurrentHashMapUtils.computeIfAbsent:(Ljava/util/concurrent/ConcurrentMap;Ljava/lang/Object;Ljava/util/function/Function;)Ljava/lang/Object;
      12: checkcast     #5                  // class java/util/Set
      15: astore_3
      16: aload_3
      17: invokestatic  #6                  // Method org/apache/dubbo/common/utils/CollectionUtils.isEmpty:(Ljava/util/Collection;)Z
      20: ifeq          28
      23: aload_0
      24: aload_1
      25: invokespecial #7                  // Method doSubscribeEds:(Ljava/lang/String;)V
      28: aload_3
      29: aload_2
      30: invokeinterface #8,  2            // InterfaceMethod java/util/Set.add:(Ljava/lang/Object;)Z
      35: pop
      36: getstatic     #9                  // Field ENDPOINT_DATA_CACHE:Ljava/util/concurrent/ConcurrentHashMap;
      39: aload_1
      40: invokevirtual #10                 // Method java/util/concurrent/ConcurrentHashMap.containsKey:(Ljava/lang/Object;)Z
      43: ifeq          63
      46: aload_2
      47: aload_1
      48: getstatic     #9                  // Field ENDPOINT_DATA_CACHE:Ljava/util/concurrent/ConcurrentHashMap;
      51: aload_1
      52: invokevirtual #11                 // Method java/util/concurrent/ConcurrentHashMap.get:(Ljava/lang/Object;)Ljava/lang/Object;
      55: checkcast     #5                  // class java/util/Set
      58: invokeinterface #12,  3           // InterfaceMethod org/apache/dubbo/rpc/cluster/router/xds/EdsEndpointListener.onEndPointChange:(Ljava/lang/String;Ljava/util/Set;)V
      63: return

  private void doSubscribeEds(java.lang.String);
    Code:
       0: getstatic     #13                 // Field EDS_LISTENERS:Ljava/util/concurrent/ConcurrentHashMap;
       3: aload_1
       4: aload_0
       5: aload_1
       6: invokedynamic #14,  0             // InvokeDynamic #1:apply:(Lorg/apache/dubbo/rpc/cluster/router/xds/EdsEndpointManager;Ljava/lang/String;)Ljava/util/function/Function;
      11: invokestatic  #4                  // Method org/apache/dubbo/common/utils/ConcurrentHashMapUtils.computeIfAbsent:(Ljava/util/concurrent/ConcurrentMap;Ljava/lang/Object;Ljava/util/function/Function;)Ljava/lang/Object;
      14: pop
      15: getstatic     #13                 // Field EDS_LISTENERS:Ljava/util/concurrent/ConcurrentHashMap;
      18: aload_1
      19: invokevirtual #11                 // Method java/util/concurrent/ConcurrentHashMap.get:(Ljava/lang/Object;)Ljava/lang/Object;
      22: checkcast     #15                 // class java/util/function/Consumer
      25: astore_2
      26: invokestatic  #16                 // Method org/apache/dubbo/registry/xds/util/PilotExchanger.isEnabled:()Z
      29: ifeq          62
      32: invokestatic  #17                 // Method org/apache/dubbo/rpc/model/FrameworkModel.defaultModel:()Lorg/apache/dubbo/rpc/model/FrameworkModel;
      35: invokevirtual #18                 // Method org/apache/dubbo/rpc/model/FrameworkModel.getBeanFactory:()Lorg/apache/dubbo/common/beans/factory/ScopeBeanFactory;
      38: ldc           #19                 // class org/apache/dubbo/common/threadpool/manager/FrameworkExecutorRepository
      40: invokevirtual #20                 // Method org/apache/dubbo/common/beans/factory/ScopeBeanFactory.getBean:(Ljava/lang/Class;)Ljava/lang/Object;
      43: checkcast     #19                 // class org/apache/dubbo/common/threadpool/manager/FrameworkExecutorRepository
      46: invokevirtual #21                 // Method org/apache/dubbo/common/threadpool/manager/FrameworkExecutorRepository.getSharedExecutor:()Ljava/util/concurrent/ExecutorService;
      49: aload_1
      50: aload_2
      51: invokedynamic #22,  0             // InvokeDynamic #2:run:(Ljava/lang/String;Ljava/util/function/Consumer;)Ljava/lang/Runnable;
      56: invokeinterface #23,  2           // InterfaceMethod java/util/concurrent/ExecutorService.submit:(Ljava/lang/Runnable;)Ljava/util/concurrent/Future;
      61: pop
      62: return

  public synchronized void unSubscribeEds(java.lang.String, org.apache.dubbo.rpc.cluster.router.xds.EdsEndpointListener);
    Code:
       0: getstatic     #2                  // Field ENDPOINT_LISTENERS:Ljava/util/concurrent/ConcurrentHashMap;
       3: aload_1
       4: invokevirtual #11                 // Method java/util/concurrent/ConcurrentHashMap.get:(Ljava/lang/Object;)Ljava/lang/Object;
       7: checkcast     #5                  // class java/util/Set
      10: astore_3
      11: aload_3
      12: invokestatic  #6                  // Method org/apache/dubbo/common/utils/CollectionUtils.isEmpty:(Ljava/util/Collection;)Z
      15: ifeq          19
      18: return
      19: aload_3
      20: aload_2
      21: invokeinterface #24,  2           // InterfaceMethod java/util/Set.remove:(Ljava/lang/Object;)Z
      26: pop
      27: aload_3
      28: invokeinterface #25,  1           // InterfaceMethod java/util/Set.isEmpty:()Z
      33: ifeq          49
      36: getstatic     #2                  // Field ENDPOINT_LISTENERS:Ljava/util/concurrent/ConcurrentHashMap;
      39: aload_1
      40: invokevirtual #26                 // Method java/util/concurrent/ConcurrentHashMap.remove:(Ljava/lang/Object;)Ljava/lang/Object;
      43: pop
      44: aload_0
      45: aload_1
      46: invokespecial #27                 // Method doUnsubscribeEds:(Ljava/lang/String;)V
      49: return

  private void doUnsubscribeEds(java.lang.String);
    Code:
       0: getstatic     #13                 // Field EDS_LISTENERS:Ljava/util/concurrent/ConcurrentHashMap;
       3: aload_1
       4: invokevirtual #26                 // Method java/util/concurrent/ConcurrentHashMap.remove:(Ljava/lang/Object;)Ljava/lang/Object;
       7: checkcast     #15                 // class java/util/function/Consumer
      10: astore_2
      11: aload_2
      12: ifnull        32
      15: invokestatic  #16                 // Method org/apache/dubbo/registry/xds/util/PilotExchanger.isEnabled:()Z
      18: ifeq          32
      21: invokestatic  #28                 // Method org/apache/dubbo/registry/xds/util/PilotExchanger.getInstance:()Lorg/apache/dubbo/registry/xds/util/PilotExchanger;
      24: aload_1
      25: invokestatic  #29                 // Method java/util/Collections.singleton:(Ljava/lang/Object;)Ljava/util/Set;
      28: aload_2
      29: invokevirtual #30                 // Method org/apache/dubbo/registry/xds/util/PilotExchanger.unObserveEds:(Ljava/util/Set;Ljava/util/function/Consumer;)V
      32: getstatic     #9                  // Field ENDPOINT_DATA_CACHE:Ljava/util/concurrent/ConcurrentHashMap;
      35: aload_1
      36: invokevirtual #26                 // Method java/util/concurrent/ConcurrentHashMap.remove:(Ljava/lang/Object;)Ljava/lang/Object;
      39: pop
      40: return

  public void notifyEndpointChange(java.lang.String, java.util.Set<org.apache.dubbo.registry.xds.util.protocol.message.Endpoint>);
    Code:
       0: getstatic     #9                  // Field ENDPOINT_DATA_CACHE:Ljava/util/concurrent/ConcurrentHashMap;
       3: aload_1
       4: aload_2
       5: invokevirtual #31                 // Method java/util/concurrent/ConcurrentHashMap.put:(Ljava/lang/Object;Ljava/lang/Object;)Ljava/lang/Object;
       8: pop
       9: getstatic     #2                  // Field ENDPOINT_LISTENERS:Ljava/util/concurrent/ConcurrentHashMap;
      12: aload_1
      13: invokevirtual #11                 // Method java/util/concurrent/ConcurrentHashMap.get:(Ljava/lang/Object;)Ljava/lang/Object;
      16: checkcast     #5                  // class java/util/Set
      19: astore_3
      20: aload_3
      21: invokestatic  #6                  // Method org/apache/dubbo/common/utils/CollectionUtils.isEmpty:(Ljava/util/Collection;)Z
      24: ifeq          28
      27: return
      28: aload_3
      29: invokeinterface #32,  1           // InterfaceMethod java/util/Set.iterator:()Ljava/util/Iterator;
      34: astore        4
      36: aload         4
      38: invokeinterface #33,  1           // InterfaceMethod java/util/Iterator.hasNext:()Z
      43: ifeq          70
      46: aload         4
      48: invokeinterface #34,  1           // InterfaceMethod java/util/Iterator.next:()Ljava/lang/Object;
      53: checkcast     #35                 // class org/apache/dubbo/rpc/cluster/router/xds/EdsEndpointListener
      56: astore        5
      58: aload         5
      60: aload_1
      61: aload_2
      62: invokeinterface #12,  3           // InterfaceMethod org/apache/dubbo/rpc/cluster/router/xds/EdsEndpointListener.onEndPointChange:(Ljava/lang/String;Ljava/util/Set;)V
      67: goto          36
      70: return

  static java.util.concurrent.ConcurrentHashMap<java.lang.String, java.util.Set<org.apache.dubbo.rpc.cluster.router.xds.EdsEndpointListener>> getEndpointListeners();
    Code:
       0: getstatic     #2                  // Field ENDPOINT_LISTENERS:Ljava/util/concurrent/ConcurrentHashMap;
       3: areturn

  static java.util.concurrent.ConcurrentHashMap<java.lang.String, java.util.Set<org.apache.dubbo.registry.xds.util.protocol.message.Endpoint>> getEndpointDataCache();
    Code:
       0: getstatic     #9                  // Field ENDPOINT_DATA_CACHE:Ljava/util/concurrent/ConcurrentHashMap;
       3: areturn

  static java.util.concurrent.ConcurrentHashMap<java.lang.String, java.util.function.Consumer<java.util.Map<java.lang.String, org.apache.dubbo.registry.xds.util.protocol.message.EndpointResult>>> getEdsListeners();
    Code:
       0: getstatic     #13                 // Field EDS_LISTENERS:Ljava/util/concurrent/ConcurrentHashMap;
       3: areturn

  private static void lambda$doSubscribeEds$3(java.lang.String, java.util.function.Consumer);
    Code:
       0: invokestatic  #28                 // Method org/apache/dubbo/registry/xds/util/PilotExchanger.getInstance:()Lorg/apache/dubbo/registry/xds/util/PilotExchanger;
       3: aload_0
       4: invokestatic  #29                 // Method java/util/Collections.singleton:(Ljava/lang/Object;)Ljava/util/Set;
       7: aload_1
       8: invokevirtual #36                 // Method org/apache/dubbo/registry/xds/util/PilotExchanger.observeEds:(Ljava/util/Set;Ljava/util/function/Consumer;)V
      11: return

  private java.util.function.Consumer lambda$doSubscribeEds$2(java.lang.String, java.lang.String);
    Code:
       0: aload_0
       1: aload_1
       2: invokedynamic #37,  0             // InvokeDynamic #3:accept:(Lorg/apache/dubbo/rpc/cluster/router/xds/EdsEndpointManager;Ljava/lang/String;)Ljava/util/function/Consumer;
       7: areturn

  private void lambda$null$1(java.lang.String, java.util.Map);
    Code:
       0: aload_2
       1: invokeinterface #38,  1           // InterfaceMethod java/util/Map.values:()Ljava/util/Collection;
       6: invokeinterface #39,  1           // InterfaceMethod java/util/Collection.stream:()Ljava/util/stream/Stream;
      11: invokedynamic #40,  0             // InvokeDynamic #4:apply:()Ljava/util/function/Function;
      16: invokeinterface #41,  2           // InterfaceMethod java/util/stream/Stream.map:(Ljava/util/function/Function;)Ljava/util/stream/Stream;
      21: invokedynamic #42,  0             // InvokeDynamic #5:apply:()Ljava/util/function/Function;
      26: invokeinterface #43,  2           // InterfaceMethod java/util/stream/Stream.flatMap:(Ljava/util/function/Function;)Ljava/util/stream/Stream;
      31: invokestatic  #44                 // Method java/util/stream/Collectors.toSet:()Ljava/util/stream/Collector;
      34: invokeinterface #45,  2           // InterfaceMethod java/util/stream/Stream.collect:(Ljava/util/stream/Collector;)Ljava/lang/Object;
      39: checkcast     #5                  // class java/util/Set
      42: astore_3
      43: aload_0
      44: aload_1
      45: aload_3
      46: invokevirtual #46                 // Method notifyEndpointChange:(Ljava/lang/String;Ljava/util/Set;)V
      49: return

  private static java.util.Set lambda$subscribeEds$0(java.lang.String);
    Code:
       0: new           #47                 // class org/apache/dubbo/common/utils/ConcurrentHashSet
       3: dup
       4: invokespecial #48                 // Method org/apache/dubbo/common/utils/ConcurrentHashSet."<init>":()V
       7: areturn

  static {};
    Code:
       0: new           #49                 // class java/util/concurrent/ConcurrentHashMap
       3: dup
       4: invokespecial #50                 // Method java/util/concurrent/ConcurrentHashMap."<init>":()V
       7: putstatic     #2                  // Field ENDPOINT_LISTENERS:Ljava/util/concurrent/ConcurrentHashMap;
      10: new           #49                 // class java/util/concurrent/ConcurrentHashMap
      13: dup
      14: invokespecial #50                 // Method java/util/concurrent/ConcurrentHashMap."<init>":()V
      17: putstatic     #9                  // Field ENDPOINT_DATA_CACHE:Ljava/util/concurrent/ConcurrentHashMap;
      20: new           #49                 // class java/util/concurrent/ConcurrentHashMap
      23: dup
      24: invokespecial #50                 // Method java/util/concurrent/ConcurrentHashMap."<init>":()V
      27: putstatic     #13                 // Field EDS_LISTENERS:Ljava/util/concurrent/ConcurrentHashMap;
      30: return
}
