Compiled from "RdsRouteRuleManager.java"
class org.apache.dubbo.rpc.cluster.router.xds.RdsRouteRuleManager$1 implements java.util.function.Consumer<java.util.Map<java.lang.String, org.apache.dubbo.registry.xds.util.protocol.message.ListenerResult>> {
  private volatile java.util.Set<java.lang.String> configNames;

  final org.apache.dubbo.rpc.cluster.router.xds.RdsRouteRuleManager this$0;

  org.apache.dubbo.rpc.cluster.router.xds.RdsRouteRuleManager$1(org.apache.dubbo.rpc.cluster.router.xds.RdsRouteRuleManager);
    Code:
       0: aload_0
       1: aload_1
       2: putfield      #1                  // Field this$0:Lorg/apache/dubbo/rpc/cluster/router/xds/RdsRouteRuleManager;
       5: aload_0
       6: invokespecial #2                  // Method java/lang/Object."<init>":()V
       9: aload_0
      10: aconst_null
      11: putfield      #3                  // Field configNames:Ljava/util/Set;
      14: return

  public void accept(java.util.Map<java.lang.String, org.apache.dubbo.registry.xds.util.protocol.message.ListenerResult>);
    Code:
       0: aload_1
       1: invokeinterface #4,  1            // InterfaceMethod java/util/Map.size:()I
       6: iconst_1
       7: if_icmpne     115
      10: aload_1
      11: invokeinterface #5,  1            // InterfaceMethod java/util/Map.values:()Ljava/util/Collection;
      16: invokeinterface #6,  1            // InterfaceMethod java/util/Collection.iterator:()Ljava/util/Iterator;
      21: astore_2
      22: aload_2
      23: invokeinterface #7,  1            // InterfaceMethod java/util/Iterator.hasNext:()Z
      28: ifeq          115
      31: aload_2
      32: invokeinterface #8,  1            // InterfaceMethod java/util/Iterator.next:()Ljava/lang/Object;
      37: checkcast     #9                  // class org/apache/dubbo/registry/xds/util/protocol/message/ListenerResult
      40: astore_3
      41: aload_3
      42: invokevirtual #10                 // Method org/apache/dubbo/registry/xds/util/protocol/message/ListenerResult.getRouteConfigNames:()Ljava/util/Set;
      45: astore        4
      47: aload_0
      48: getfield      #3                  // Field configNames:Ljava/util/Set;
      51: ifnonnull     68
      54: invokestatic  #11                 // Method org/apache/dubbo/registry/xds/util/PilotExchanger.getInstance:()Lorg/apache/dubbo/registry/xds/util/PilotExchanger;
      57: aload         4
      59: invokestatic  #12                 // Method org/apache/dubbo/rpc/cluster/router/xds/RdsRouteRuleManager.access$000:()Ljava/util/function/Consumer;
      62: invokevirtual #13                 // Method org/apache/dubbo/registry/xds/util/PilotExchanger.observeRds:(Ljava/util/Set;Ljava/util/function/Consumer;)V
      65: goto          106
      68: aload_0
      69: getfield      #3                  // Field configNames:Ljava/util/Set;
      72: aload         4
      74: invokeinterface #14,  2           // InterfaceMethod java/util/Set.equals:(Ljava/lang/Object;)Z
      79: ifne          106
      82: invokestatic  #11                 // Method org/apache/dubbo/registry/xds/util/PilotExchanger.getInstance:()Lorg/apache/dubbo/registry/xds/util/PilotExchanger;
      85: aload_0
      86: getfield      #3                  // Field configNames:Ljava/util/Set;
      89: invokestatic  #12                 // Method org/apache/dubbo/rpc/cluster/router/xds/RdsRouteRuleManager.access$000:()Ljava/util/function/Consumer;
      92: invokevirtual #15                 // Method org/apache/dubbo/registry/xds/util/PilotExchanger.unObserveRds:(Ljava/util/Set;Ljava/util/function/Consumer;)V
      95: invokestatic  #11                 // Method org/apache/dubbo/registry/xds/util/PilotExchanger.getInstance:()Lorg/apache/dubbo/registry/xds/util/PilotExchanger;
      98: aload         4
     100: invokestatic  #12                 // Method org/apache/dubbo/rpc/cluster/router/xds/RdsRouteRuleManager.access$000:()Ljava/util/function/Consumer;
     103: invokevirtual #13                 // Method org/apache/dubbo/registry/xds/util/PilotExchanger.observeRds:(Ljava/util/Set;Ljava/util/function/Consumer;)V
     106: aload_0
     107: aload         4
     109: putfield      #3                  // Field configNames:Ljava/util/Set;
     112: goto          22
     115: return

  public void accept(java.lang.Object);
    Code:
       0: aload_0
       1: aload_1
       2: checkcast     #16                 // class java/util/Map
       5: invokevirtual #17                 // Method accept:(Ljava/util/Map;)V
       8: return
}
