Compiled from "RdsVirtualHostListener.java"
class org.apache.dubbo.rpc.cluster.router.xds.RdsVirtualHostListener$1 {
  static final int[] $SwitchMap$io$envoyproxy$envoy$config$route$v3$RouteMatch$PathSpecifierCase;

  static final int[] $SwitchMap$io$envoyproxy$envoy$config$route$v3$HeaderMatcher$HeaderMatchSpecifierCase;

  static final int[] $SwitchMap$io$envoyproxy$envoy$config$route$v3$Route$ActionCase;

  static {};
    Code:
       0: invokestatic  #1                  // Method io/envoyproxy/envoy/config/route/v3/Route$ActionCase.values:()[Lio/envoyproxy/envoy/config/route/v3/Route$ActionCase;
       3: arraylength
       4: newarray       int
       6: putstatic     #2                  // Field $SwitchMap$io$envoyproxy$envoy$config$route$v3$Route$ActionCase:[I
       9: getstatic     #2                  // Field $SwitchMap$io$envoyproxy$envoy$config$route$v3$Route$ActionCase:[I
      12: getstatic     #3                  // Field io/envoyproxy/envoy/config/route/v3/Route$ActionCase.ROUTE:Lio/envoyproxy/envoy/config/route/v3/Route$ActionCase;
      15: invokevirtual #4                  // Method io/envoyproxy/envoy/config/route/v3/Route$ActionCase.ordinal:()I
      18: iconst_1
      19: iastore
      20: goto          24
      23: astore_0
      24: getstatic     #2                  // Field $SwitchMap$io$envoyproxy$envoy$config$route$v3$Route$ActionCase:[I
      27: getstatic     #6                  // Field io/envoyproxy/envoy/config/route/v3/Route$ActionCase.REDIRECT:Lio/envoyproxy/envoy/config/route/v3/Route$ActionCase;
      30: invokevirtual #4                  // Method io/envoyproxy/envoy/config/route/v3/Route$ActionCase.ordinal:()I
      33: iconst_2
      34: iastore
      35: goto          39
      38: astore_0
      39: getstatic     #2                  // Field $SwitchMap$io$envoyproxy$envoy$config$route$v3$Route$ActionCase:[I
      42: getstatic     #7                  // Field io/envoyproxy/envoy/config/route/v3/Route$ActionCase.DIRECT_RESPONSE:Lio/envoyproxy/envoy/config/route/v3/Route$ActionCase;
      45: invokevirtual #4                  // Method io/envoyproxy/envoy/config/route/v3/Route$ActionCase.ordinal:()I
      48: iconst_3
      49: iastore
      50: goto          54
      53: astore_0
      54: getstatic     #2                  // Field $SwitchMap$io$envoyproxy$envoy$config$route$v3$Route$ActionCase:[I
      57: getstatic     #8                  // Field io/envoyproxy/envoy/config/route/v3/Route$ActionCase.FILTER_ACTION:Lio/envoyproxy/envoy/config/route/v3/Route$ActionCase;
      60: invokevirtual #4                  // Method io/envoyproxy/envoy/config/route/v3/Route$ActionCase.ordinal:()I
      63: iconst_4
      64: iastore
      65: goto          69
      68: astore_0
      69: getstatic     #2                  // Field $SwitchMap$io$envoyproxy$envoy$config$route$v3$Route$ActionCase:[I
      72: getstatic     #9                  // Field io/envoyproxy/envoy/config/route/v3/Route$ActionCase.ACTION_NOT_SET:Lio/envoyproxy/envoy/config/route/v3/Route$ActionCase;
      75: invokevirtual #4                  // Method io/envoyproxy/envoy/config/route/v3/Route$ActionCase.ordinal:()I
      78: iconst_5
      79: iastore
      80: goto          84
      83: astore_0
      84: invokestatic  #10                 // Method io/envoyproxy/envoy/config/route/v3/HeaderMatcher$HeaderMatchSpecifierCase.values:()[Lio/envoyproxy/envoy/config/route/v3/HeaderMatcher$HeaderMatchSpecifierCase;
      87: arraylength
      88: newarray       int
      90: putstatic     #11                 // Field $SwitchMap$io$envoyproxy$envoy$config$route$v3$HeaderMatcher$HeaderMatchSpecifierCase:[I
      93: getstatic     #11                 // Field $SwitchMap$io$envoyproxy$envoy$config$route$v3$HeaderMatcher$HeaderMatchSpecifierCase:[I
      96: getstatic     #12                 // Field io/envoyproxy/envoy/config/route/v3/HeaderMatcher$HeaderMatchSpecifierCase.EXACT_MATCH:Lio/envoyproxy/envoy/config/route/v3/HeaderMatcher$HeaderMatchSpecifierCase;
      99: invokevirtual #13                 // Method io/envoyproxy/envoy/config/route/v3/HeaderMatcher$HeaderMatchSpecifierCase.ordinal:()I
     102: iconst_1
     103: iastore
     104: goto          108
     107: astore_0
     108: getstatic     #11                 // Field $SwitchMap$io$envoyproxy$envoy$config$route$v3$HeaderMatcher$HeaderMatchSpecifierCase:[I
     111: getstatic     #14                 // Field io/envoyproxy/envoy/config/route/v3/HeaderMatcher$HeaderMatchSpecifierCase.SAFE_REGEX_MATCH:Lio/envoyproxy/envoy/config/route/v3/HeaderMatcher$HeaderMatchSpecifierCase;
     114: invokevirtual #13                 // Method io/envoyproxy/envoy/config/route/v3/HeaderMatcher$HeaderMatchSpecifierCase.ordinal:()I
     117: iconst_2
     118: iastore
     119: goto          123
     122: astore_0
     123: getstatic     #11                 // Field $SwitchMap$io$envoyproxy$envoy$config$route$v3$HeaderMatcher$HeaderMatchSpecifierCase:[I
     126: getstatic     #15                 // Field io/envoyproxy/envoy/config/route/v3/HeaderMatcher$HeaderMatchSpecifierCase.RANGE_MATCH:Lio/envoyproxy/envoy/config/route/v3/HeaderMatcher$HeaderMatchSpecifierCase;
     129: invokevirtual #13                 // Method io/envoyproxy/envoy/config/route/v3/HeaderMatcher$HeaderMatchSpecifierCase.ordinal:()I
     132: iconst_3
     133: iastore
     134: goto          138
     137: astore_0
     138: getstatic     #11                 // Field $SwitchMap$io$envoyproxy$envoy$config$route$v3$HeaderMatcher$HeaderMatchSpecifierCase:[I
     141: getstatic     #16                 // Field io/envoyproxy/envoy/config/route/v3/HeaderMatcher$HeaderMatchSpecifierCase.PRESENT_MATCH:Lio/envoyproxy/envoy/config/route/v3/HeaderMatcher$HeaderMatchSpecifierCase;
     144: invokevirtual #13                 // Method io/envoyproxy/envoy/config/route/v3/HeaderMatcher$HeaderMatchSpecifierCase.ordinal:()I
     147: iconst_4
     148: iastore
     149: goto          153
     152: astore_0
     153: getstatic     #11                 // Field $SwitchMap$io$envoyproxy$envoy$config$route$v3$HeaderMatcher$HeaderMatchSpecifierCase:[I
     156: getstatic     #17                 // Field io/envoyproxy/envoy/config/route/v3/HeaderMatcher$HeaderMatchSpecifierCase.PREFIX_MATCH:Lio/envoyproxy/envoy/config/route/v3/HeaderMatcher$HeaderMatchSpecifierCase;
     159: invokevirtual #13                 // Method io/envoyproxy/envoy/config/route/v3/HeaderMatcher$HeaderMatchSpecifierCase.ordinal:()I
     162: iconst_5
     163: iastore
     164: goto          168
     167: astore_0
     168: getstatic     #11                 // Field $SwitchMap$io$envoyproxy$envoy$config$route$v3$HeaderMatcher$HeaderMatchSpecifierCase:[I
     171: getstatic     #18                 // Field io/envoyproxy/envoy/config/route/v3/HeaderMatcher$HeaderMatchSpecifierCase.SUFFIX_MATCH:Lio/envoyproxy/envoy/config/route/v3/HeaderMatcher$HeaderMatchSpecifierCase;
     174: invokevirtual #13                 // Method io/envoyproxy/envoy/config/route/v3/HeaderMatcher$HeaderMatchSpecifierCase.ordinal:()I
     177: bipush        6
     179: iastore
     180: goto          184
     183: astore_0
     184: getstatic     #11                 // Field $SwitchMap$io$envoyproxy$envoy$config$route$v3$HeaderMatcher$HeaderMatchSpecifierCase:[I
     187: getstatic     #19                 // Field io/envoyproxy/envoy/config/route/v3/HeaderMatcher$HeaderMatchSpecifierCase.HEADERMATCHSPECIFIER_NOT_SET:Lio/envoyproxy/envoy/config/route/v3/HeaderMatcher$HeaderMatchSpecifierCase;
     190: invokevirtual #13                 // Method io/envoyproxy/envoy/config/route/v3/HeaderMatcher$HeaderMatchSpecifierCase.ordinal:()I
     193: bipush        7
     195: iastore
     196: goto          200
     199: astore_0
     200: invokestatic  #20                 // Method io/envoyproxy/envoy/config/route/v3/RouteMatch$PathSpecifierCase.values:()[Lio/envoyproxy/envoy/config/route/v3/RouteMatch$PathSpecifierCase;
     203: arraylength
     204: newarray       int
     206: putstatic     #21                 // Field $SwitchMap$io$envoyproxy$envoy$config$route$v3$RouteMatch$PathSpecifierCase:[I
     209: getstatic     #21                 // Field $SwitchMap$io$envoyproxy$envoy$config$route$v3$RouteMatch$PathSpecifierCase:[I
     212: getstatic     #22                 // Field io/envoyproxy/envoy/config/route/v3/RouteMatch$PathSpecifierCase.PREFIX:Lio/envoyproxy/envoy/config/route/v3/RouteMatch$PathSpecifierCase;
     215: invokevirtual #23                 // Method io/envoyproxy/envoy/config/route/v3/RouteMatch$PathSpecifierCase.ordinal:()I
     218: iconst_1
     219: iastore
     220: goto          224
     223: astore_0
     224: getstatic     #21                 // Field $SwitchMap$io$envoyproxy$envoy$config$route$v3$RouteMatch$PathSpecifierCase:[I
     227: getstatic     #24                 // Field io/envoyproxy/envoy/config/route/v3/RouteMatch$PathSpecifierCase.PATH:Lio/envoyproxy/envoy/config/route/v3/RouteMatch$PathSpecifierCase;
     230: invokevirtual #23                 // Method io/envoyproxy/envoy/config/route/v3/RouteMatch$PathSpecifierCase.ordinal:()I
     233: iconst_2
     234: iastore
     235: goto          239
     238: astore_0
     239: getstatic     #21                 // Field $SwitchMap$io$envoyproxy$envoy$config$route$v3$RouteMatch$PathSpecifierCase:[I
     242: getstatic     #25                 // Field io/envoyproxy/envoy/config/route/v3/RouteMatch$PathSpecifierCase.SAFE_REGEX:Lio/envoyproxy/envoy/config/route/v3/RouteMatch$PathSpecifierCase;
     245: invokevirtual #23                 // Method io/envoyproxy/envoy/config/route/v3/RouteMatch$PathSpecifierCase.ordinal:()I
     248: iconst_3
     249: iastore
     250: goto          254
     253: astore_0
     254: getstatic     #21                 // Field $SwitchMap$io$envoyproxy$envoy$config$route$v3$RouteMatch$PathSpecifierCase:[I
     257: getstatic     #26                 // Field io/envoyproxy/envoy/config/route/v3/RouteMatch$PathSpecifierCase.PATHSPECIFIER_NOT_SET:Lio/envoyproxy/envoy/config/route/v3/RouteMatch$PathSpecifierCase;
     260: invokevirtual #23                 // Method io/envoyproxy/envoy/config/route/v3/RouteMatch$PathSpecifierCase.ordinal:()I
     263: iconst_4
     264: iastore
     265: goto          269
     268: astore_0
     269: return
    Exception table:
       from    to  target type
           9    20    23   Class java/lang/NoSuchFieldError
          24    35    38   Class java/lang/NoSuchFieldError
          39    50    53   Class java/lang/NoSuchFieldError
          54    65    68   Class java/lang/NoSuchFieldError
          69    80    83   Class java/lang/NoSuchFieldError
          93   104   107   Class java/lang/NoSuchFieldError
         108   119   122   Class java/lang/NoSuchFieldError
         123   134   137   Class java/lang/NoSuchFieldError
         138   149   152   Class java/lang/NoSuchFieldError
         153   164   167   Class java/lang/NoSuchFieldError
         168   180   183   Class java/lang/NoSuchFieldError
         184   196   199   Class java/lang/NoSuchFieldError
         209   220   223   Class java/lang/NoSuchFieldError
         224   235   238   Class java/lang/NoSuchFieldError
         239   250   253   Class java/lang/NoSuchFieldError
         254   265   268   Class java/lang/NoSuchFieldError
}
