Compiled from "RdsVirtualHostListener.java"
public class org.apache.dubbo.rpc.cluster.router.xds.RdsVirtualHostListener {
  private static final org.apache.dubbo.common.logger.ErrorTypeAwareLogger LOGGER;

  private final java.lang.String domain;

  private final org.apache.dubbo.rpc.cluster.router.xds.RdsRouteRuleManager routeRuleManager;

  public org.apache.dubbo.rpc.cluster.router.xds.RdsVirtualHostListener(java.lang.String, org.apache.dubbo.rpc.cluster.router.xds.RdsRouteRuleManager);
    Code:
       0: aload_0
       1: invokespecial #1                  // Method java/lang/Object."<init>":()V
       4: aload_0
       5: aload_1
       6: putfield      #2                  // Field domain:Ljava/lang/String;
       9: aload_0
      10: aload_2
      11: putfield      #3                  // Field routeRuleManager:Lorg/apache/dubbo/rpc/cluster/router/xds/RdsRouteRuleManager;
      14: return

  public void parseVirtualHost(io.envoyproxy.envoy.config.route.v3.VirtualHost);
    Code:
       0: aload_1
       1: ifnull        14
       4: aload_1
       5: invokevirtual #4                  // Method io/envoyproxy/envoy/config/route/v3/VirtualHost.getRoutesList:()Ljava/util/List;
       8: invokestatic  #5                  // Method org/apache/dubbo/common/utils/CollectionUtils.isEmpty:(Ljava/util/Collection;)Z
      11: ifeq          33
      14: aload_0
      15: getfield      #3                  // Field routeRuleManager:Lorg/apache/dubbo/rpc/cluster/router/xds/RdsRouteRuleManager;
      18: aload_0
      19: getfield      #2                  // Field domain:Ljava/lang/String;
      22: new           #6                  // class java/util/ArrayList
      25: dup
      26: invokespecial #7                  // Method java/util/ArrayList."<init>":()V
      29: invokevirtual #8                  // Method org/apache/dubbo/rpc/cluster/router/xds/RdsRouteRuleManager.notifyRuleChange:(Ljava/lang/String;Ljava/util/List;)V
      32: return
      33: aload_1
      34: invokevirtual #4                  // Method io/envoyproxy/envoy/config/route/v3/VirtualHost.getRoutesList:()Ljava/util/List;
      37: invokeinterface #9,  1            // InterfaceMethod java/util/List.stream:()Ljava/util/stream/Stream;
      42: aload_0
      43: invokedynamic #10,  0             // InvokeDynamic #0:apply:(Lorg/apache/dubbo/rpc/cluster/router/xds/RdsVirtualHostListener;)Ljava/util/function/Function;
      48: invokeinterface #11,  2           // InterfaceMethod java/util/stream/Stream.map:(Ljava/util/function/Function;)Ljava/util/stream/Stream;
      53: invokedynamic #12,  0             // InvokeDynamic #1:test:()Ljava/util/function/Predicate;
      58: invokeinterface #13,  2           // InterfaceMethod java/util/stream/Stream.filter:(Ljava/util/function/Predicate;)Ljava/util/stream/Stream;
      63: invokestatic  #14                 // Method java/util/stream/Collectors.toList:()Ljava/util/stream/Collector;
      66: invokeinterface #15,  2           // InterfaceMethod java/util/stream/Stream.collect:(Ljava/util/stream/Collector;)Ljava/lang/Object;
      71: checkcast     #16                 // class java/util/List
      74: astore_2
      75: aload_0
      76: getfield      #3                  // Field routeRuleManager:Lorg/apache/dubbo/rpc/cluster/router/xds/RdsRouteRuleManager;
      79: aload_0
      80: getfield      #2                  // Field domain:Ljava/lang/String;
      83: aload_2
      84: invokevirtual #8                  // Method org/apache/dubbo/rpc/cluster/router/xds/RdsRouteRuleManager.notifyRuleChange:(Ljava/lang/String;Ljava/util/List;)V
      87: goto          133
      90: astore_2
      91: getstatic     #18                 // Field LOGGER:Lorg/apache/dubbo/common/logger/ErrorTypeAwareLogger;
      94: ldc           #20                 // String 99-0
      96: ldc           #21                 // String
      98: ldc           #21                 // String
     100: new           #22                 // class java/lang/StringBuilder
     103: dup
     104: invokespecial #23                 // Method java/lang/StringBuilder."<init>":()V
     107: ldc           #24                 // String parse domain:
     109: invokevirtual #25                 // Method java/lang/StringBuilder.append:(Ljava/lang/String;)Ljava/lang/StringBuilder;
     112: aload_0
     113: getfield      #2                  // Field domain:Ljava/lang/String;
     116: invokevirtual #25                 // Method java/lang/StringBuilder.append:(Ljava/lang/String;)Ljava/lang/StringBuilder;
     119: ldc           #26                 // String  xds VirtualHost error
     121: invokevirtual #25                 // Method java/lang/StringBuilder.append:(Ljava/lang/String;)Ljava/lang/StringBuilder;
     124: invokevirtual #27                 // Method java/lang/StringBuilder.toString:()Ljava/lang/String;
     127: aload_2
     128: invokeinterface #28,  6           // InterfaceMethod org/apache/dubbo/common/logger/ErrorTypeAwareLogger.error:(Ljava/lang/String;Ljava/lang/String;Ljava/lang/String;Ljava/lang/String;Ljava/lang/Throwable;)V
     133: return
    Exception table:
       from    to  target type
          33    87    90   Class java/lang/Exception

  private org.apache.dubbo.rpc.cluster.router.xds.rule.HttpRequestMatch parseMatch(io.envoyproxy.envoy.config.route.v3.RouteMatch);
    Code:
       0: aload_0
       1: aload_1
       2: invokespecial #29                 // Method parsePathMatch:(Lio/envoyproxy/envoy/config/route/v3/RouteMatch;)Lorg/apache/dubbo/rpc/cluster/router/xds/rule/PathMatcher;
       5: astore_2
       6: aload_0
       7: aload_1
       8: invokespecial #30                 // Method parseHeadMatch:(Lio/envoyproxy/envoy/config/route/v3/RouteMatch;)Ljava/util/List;
      11: astore_3
      12: new           #31                 // class org/apache/dubbo/rpc/cluster/router/xds/rule/HttpRequestMatch
      15: dup
      16: aload_2
      17: aload_3
      18: invokespecial #32                 // Method org/apache/dubbo/rpc/cluster/router/xds/rule/HttpRequestMatch."<init>":(Lorg/apache/dubbo/rpc/cluster/router/xds/rule/PathMatcher;Ljava/util/List;)V
      21: areturn

  private org.apache.dubbo.rpc.cluster.router.xds.rule.PathMatcher parsePathMatch(io.envoyproxy.envoy.config.route.v3.RouteMatch);
    Code:
       0: aload_1
       1: invokevirtual #33                 // Method io/envoyproxy/envoy/config/route/v3/RouteMatch.getCaseSensitive:()Lcom/google/protobuf/BoolValue;
       4: invokevirtual #34                 // Method com/google/protobuf/BoolValue.getValue:()Z
       7: istore_2
       8: new           #35                 // class org/apache/dubbo/rpc/cluster/router/xds/rule/PathMatcher
      11: dup
      12: invokespecial #36                 // Method org/apache/dubbo/rpc/cluster/router/xds/rule/PathMatcher."<init>":()V
      15: astore_3
      16: aload_3
      17: iload_2
      18: invokevirtual #37                 // Method org/apache/dubbo/rpc/cluster/router/xds/rule/PathMatcher.setCaseSensitive:(Z)V
      21: getstatic     #38                 // Field org/apache/dubbo/rpc/cluster/router/xds/RdsVirtualHostListener$1.$SwitchMap$io$envoyproxy$envoy$config$route$v3$RouteMatch$PathSpecifierCase:[I
      24: aload_1
      25: invokevirtual #39                 // Method io/envoyproxy/envoy/config/route/v3/RouteMatch.getPathSpecifierCase:()Lio/envoyproxy/envoy/config/route/v3/RouteMatch$PathSpecifierCase;
      28: invokevirtual #40                 // Method io/envoyproxy/envoy/config/route/v3/RouteMatch$PathSpecifierCase.ordinal:()I
      31: iaload
      32: tableswitch   { // 1 to 4
                     1: 64
                     2: 74
                     3: 84
                     4: 101
               default: 103
          }
      64: aload_3
      65: aload_1
      66: invokevirtual #41                 // Method io/envoyproxy/envoy/config/route/v3/RouteMatch.getPrefix:()Ljava/lang/String;
      69: invokevirtual #42                 // Method org/apache/dubbo/rpc/cluster/router/xds/rule/PathMatcher.setPrefix:(Ljava/lang/String;)V
      72: aload_3
      73: areturn
      74: aload_3
      75: aload_1
      76: invokevirtual #43                 // Method io/envoyproxy/envoy/config/route/v3/RouteMatch.getPath:()Ljava/lang/String;
      79: invokevirtual #44                 // Method org/apache/dubbo/rpc/cluster/router/xds/rule/PathMatcher.setPath:(Ljava/lang/String;)V
      82: aload_3
      83: areturn
      84: aload_1
      85: invokevirtual #45                 // Method io/envoyproxy/envoy/config/route/v3/RouteMatch.getSafeRegex:()Lio/envoyproxy/envoy/type/matcher/v3/RegexMatcher;
      88: invokevirtual #46                 // Method io/envoyproxy/envoy/type/matcher/v3/RegexMatcher.getRegex:()Ljava/lang/String;
      91: astore        4
      93: aload_3
      94: aload         4
      96: invokevirtual #47                 // Method org/apache/dubbo/rpc/cluster/router/xds/rule/PathMatcher.setRegex:(Ljava/lang/String;)V
      99: aload_3
     100: areturn
     101: aconst_null
     102: areturn
     103: new           #48                 // class java/lang/IllegalArgumentException
     106: dup
     107: ldc           #49                 // String Path specifier is not expect
     109: invokespecial #50                 // Method java/lang/IllegalArgumentException."<init>":(Ljava/lang/String;)V
     112: athrow

  private java.util.List<org.apache.dubbo.rpc.cluster.router.xds.rule.HeaderMatcher> parseHeadMatch(io.envoyproxy.envoy.config.route.v3.RouteMatch);
    Code:
       0: new           #6                  // class java/util/ArrayList
       3: dup
       4: invokespecial #7                  // Method java/util/ArrayList."<init>":()V
       7: astore_2
       8: aload_1
       9: invokevirtual #51                 // Method io/envoyproxy/envoy/config/route/v3/RouteMatch.getHeadersList:()Ljava/util/List;
      12: astore_3
      13: aload_3
      14: invokeinterface #52,  1           // InterfaceMethod java/util/List.iterator:()Ljava/util/Iterator;
      19: astore        4
      21: aload         4
      23: invokeinterface #53,  1           // InterfaceMethod java/util/Iterator.hasNext:()Z
      28: ifeq          311
      31: aload         4
      33: invokeinterface #54,  1           // InterfaceMethod java/util/Iterator.next:()Ljava/lang/Object;
      38: checkcast     #55                 // class io/envoyproxy/envoy/config/route/v3/HeaderMatcher
      41: astore        5
      43: new           #56                 // class org/apache/dubbo/rpc/cluster/router/xds/rule/HeaderMatcher
      46: dup
      47: invokespecial #57                 // Method org/apache/dubbo/rpc/cluster/router/xds/rule/HeaderMatcher."<init>":()V
      50: astore        6
      52: aload         6
      54: aload         5
      56: invokevirtual #58                 // Method io/envoyproxy/envoy/config/route/v3/HeaderMatcher.getName:()Ljava/lang/String;
      59: invokevirtual #59                 // Method org/apache/dubbo/rpc/cluster/router/xds/rule/HeaderMatcher.setName:(Ljava/lang/String;)V
      62: aload         6
      64: aload         5
      66: invokevirtual #60                 // Method io/envoyproxy/envoy/config/route/v3/HeaderMatcher.getInvertMatch:()Z
      69: invokevirtual #61                 // Method org/apache/dubbo/rpc/cluster/router/xds/rule/HeaderMatcher.setInverted:(Z)V
      72: getstatic     #62                 // Field org/apache/dubbo/rpc/cluster/router/xds/RdsVirtualHostListener$1.$SwitchMap$io$envoyproxy$envoy$config$route$v3$HeaderMatcher$HeaderMatchSpecifierCase:[I
      75: aload         5
      77: invokevirtual #63                 // Method io/envoyproxy/envoy/config/route/v3/HeaderMatcher.getHeaderMatchSpecifierCase:()Lio/envoyproxy/envoy/config/route/v3/HeaderMatcher$HeaderMatchSpecifierCase;
      80: invokevirtual #64                 // Method io/envoyproxy/envoy/config/route/v3/HeaderMatcher$HeaderMatchSpecifierCase.ordinal:()I
      83: iaload
      84: tableswitch   { // 1 to 7
                     1: 128
                     2: 150
                     3: 175
                     4: 229
                     5: 254
                     6: 276
                     7: 298
               default: 298
          }
     128: aload         6
     130: aload         5
     132: invokevirtual #65                 // Method io/envoyproxy/envoy/config/route/v3/HeaderMatcher.getExactMatch:()Ljava/lang/String;
     135: invokevirtual #66                 // Method org/apache/dubbo/rpc/cluster/router/xds/rule/HeaderMatcher.setExactValue:(Ljava/lang/String;)V
     138: aload_2
     139: aload         6
     141: invokeinterface #67,  2           // InterfaceMethod java/util/List.add:(Ljava/lang/Object;)Z
     146: pop
     147: goto          308
     150: aload         6
     152: aload         5
     154: invokevirtual #68                 // Method io/envoyproxy/envoy/config/route/v3/HeaderMatcher.getSafeRegexMatch:()Lio/envoyproxy/envoy/type/matcher/v3/RegexMatcher;
     157: invokevirtual #46                 // Method io/envoyproxy/envoy/type/matcher/v3/RegexMatcher.getRegex:()Ljava/lang/String;
     160: invokevirtual #69                 // Method org/apache/dubbo/rpc/cluster/router/xds/rule/HeaderMatcher.setRegex:(Ljava/lang/String;)V
     163: aload_2
     164: aload         6
     166: invokeinterface #67,  2           // InterfaceMethod java/util/List.add:(Ljava/lang/Object;)Z
     171: pop
     172: goto          308
     175: new           #70                 // class org/apache/dubbo/rpc/cluster/router/xds/rule/LongRangeMatch
     178: dup
     179: invokespecial #71                 // Method org/apache/dubbo/rpc/cluster/router/xds/rule/LongRangeMatch."<init>":()V
     182: astore        7
     184: aload         7
     186: aload         5
     188: invokevirtual #72                 // Method io/envoyproxy/envoy/config/route/v3/HeaderMatcher.getRangeMatch:()Lio/envoyproxy/envoy/type/v3/Int64Range;
     191: invokevirtual #73                 // Method io/envoyproxy/envoy/type/v3/Int64Range.getStart:()J
     194: invokevirtual #74                 // Method org/apache/dubbo/rpc/cluster/router/xds/rule/LongRangeMatch.setStart:(J)V
     197: aload         7
     199: aload         5
     201: invokevirtual #72                 // Method io/envoyproxy/envoy/config/route/v3/HeaderMatcher.getRangeMatch:()Lio/envoyproxy/envoy/type/v3/Int64Range;
     204: invokevirtual #75                 // Method io/envoyproxy/envoy/type/v3/Int64Range.getEnd:()J
     207: invokevirtual #76                 // Method org/apache/dubbo/rpc/cluster/router/xds/rule/LongRangeMatch.setEnd:(J)V
     210: aload         6
     212: aload         7
     214: invokevirtual #77                 // Method org/apache/dubbo/rpc/cluster/router/xds/rule/HeaderMatcher.setRange:(Lorg/apache/dubbo/rpc/cluster/router/xds/rule/LongRangeMatch;)V
     217: aload_2
     218: aload         6
     220: invokeinterface #67,  2           // InterfaceMethod java/util/List.add:(Ljava/lang/Object;)Z
     225: pop
     226: goto          308
     229: aload         6
     231: aload         5
     233: invokevirtual #78                 // Method io/envoyproxy/envoy/config/route/v3/HeaderMatcher.getPresentMatch:()Z
     236: invokestatic  #79                 // Method java/lang/Boolean.valueOf:(Z)Ljava/lang/Boolean;
     239: invokevirtual #80                 // Method org/apache/dubbo/rpc/cluster/router/xds/rule/HeaderMatcher.setPresent:(Ljava/lang/Boolean;)V
     242: aload_2
     243: aload         6
     245: invokeinterface #67,  2           // InterfaceMethod java/util/List.add:(Ljava/lang/Object;)Z
     250: pop
     251: goto          308
     254: aload         6
     256: aload         5
     258: invokevirtual #81                 // Method io/envoyproxy/envoy/config/route/v3/HeaderMatcher.getPrefixMatch:()Ljava/lang/String;
     261: invokevirtual #82                 // Method org/apache/dubbo/rpc/cluster/router/xds/rule/HeaderMatcher.setPrefix:(Ljava/lang/String;)V
     264: aload_2
     265: aload         6
     267: invokeinterface #67,  2           // InterfaceMethod java/util/List.add:(Ljava/lang/Object;)Z
     272: pop
     273: goto          308
     276: aload         6
     278: aload         5
     280: invokevirtual #83                 // Method io/envoyproxy/envoy/config/route/v3/HeaderMatcher.getSuffixMatch:()Ljava/lang/String;
     283: invokevirtual #84                 // Method org/apache/dubbo/rpc/cluster/router/xds/rule/HeaderMatcher.setSuffix:(Ljava/lang/String;)V
     286: aload_2
     287: aload         6
     289: invokeinterface #67,  2           // InterfaceMethod java/util/List.add:(Ljava/lang/Object;)Z
     294: pop
     295: goto          308
     298: new           #48                 // class java/lang/IllegalArgumentException
     301: dup
     302: ldc           #85                 // String Header specifier is not expect
     304: invokespecial #50                 // Method java/lang/IllegalArgumentException."<init>":(Ljava/lang/String;)V
     307: athrow
     308: goto          21
     311: aload_2
     312: areturn

  private org.apache.dubbo.rpc.cluster.router.xds.rule.HTTPRouteDestination parseAction(io.envoyproxy.envoy.config.route.v3.Route);
    Code:
       0: getstatic     #86                 // Field org/apache/dubbo/rpc/cluster/router/xds/RdsVirtualHostListener$1.$SwitchMap$io$envoyproxy$envoy$config$route$v3$Route$ActionCase:[I
       3: aload_1
       4: invokevirtual #87                 // Method io/envoyproxy/envoy/config/route/v3/Route.getActionCase:()Lio/envoyproxy/envoy/config/route/v3/Route$ActionCase;
       7: invokevirtual #88                 // Method io/envoyproxy/envoy/config/route/v3/Route$ActionCase.ordinal:()I
      10: iaload
      11: tableswitch   { // 1 to 5
                     1: 44
                     2: 145
                     3: 145
                     4: 145
                     5: 145
               default: 145
          }
      44: new           #89                 // class org/apache/dubbo/rpc/cluster/router/xds/rule/HTTPRouteDestination
      47: dup
      48: invokespecial #90                 // Method org/apache/dubbo/rpc/cluster/router/xds/rule/HTTPRouteDestination."<init>":()V
      51: astore_2
      52: aload_1
      53: invokevirtual #91                 // Method io/envoyproxy/envoy/config/route/v3/Route.getRoute:()Lio/envoyproxy/envoy/config/route/v3/RouteAction;
      56: astore_3
      57: aload_3
      58: invokevirtual #92                 // Method io/envoyproxy/envoy/config/route/v3/RouteAction.getClusterSpecifierCase:()Lio/envoyproxy/envoy/config/route/v3/RouteAction$ClusterSpecifierCase;
      61: astore        4
      63: aload         4
      65: getstatic     #93                 // Field io/envoyproxy/envoy/config/route/v3/RouteAction$ClusterSpecifierCase.CLUSTER:Lio/envoyproxy/envoy/config/route/v3/RouteAction$ClusterSpecifierCase;
      68: if_acmpne     81
      71: aload_2
      72: aload_3
      73: invokevirtual #94                 // Method io/envoyproxy/envoy/config/route/v3/RouteAction.getCluster:()Ljava/lang/String;
      76: invokevirtual #95                 // Method org/apache/dubbo/rpc/cluster/router/xds/rule/HTTPRouteDestination.setCluster:(Ljava/lang/String;)V
      79: aload_2
      80: areturn
      81: aload         4
      83: getstatic     #96                 // Field io/envoyproxy/envoy/config/route/v3/RouteAction$ClusterSpecifierCase.WEIGHTED_CLUSTERS:Lio/envoyproxy/envoy/config/route/v3/RouteAction$ClusterSpecifierCase;
      86: if_acmpne     145
      89: aload_3
      90: invokevirtual #97                 // Method io/envoyproxy/envoy/config/route/v3/RouteAction.getWeightedClusters:()Lio/envoyproxy/envoy/config/route/v3/WeightedCluster;
      93: invokevirtual #98                 // Method io/envoyproxy/envoy/config/route/v3/WeightedCluster.getClustersList:()Ljava/util/List;
      96: invokeinterface #9,  1            // InterfaceMethod java/util/List.stream:()Ljava/util/stream/Stream;
     101: invokedynamic #99,  0             // InvokeDynamic #2:apply:()Ljava/util/function/Function;
     106: invokeinterface #11,  2           // InterfaceMethod java/util/stream/Stream.map:(Ljava/util/function/Function;)Ljava/util/stream/Stream;
     111: invokedynamic #100,  0            // InvokeDynamic #3:apply:()Ljava/util/function/Function;
     116: invokestatic  #101                // InterfaceMethod java/util/Comparator.comparing:(Ljava/util/function/Function;)Ljava/util/Comparator;
     119: invokeinterface #102,  2          // InterfaceMethod java/util/stream/Stream.sorted:(Ljava/util/Comparator;)Ljava/util/stream/Stream;
     124: invokestatic  #14                 // Method java/util/stream/Collectors.toList:()Ljava/util/stream/Collector;
     127: invokeinterface #15,  2           // InterfaceMethod java/util/stream/Stream.collect:(Ljava/util/stream/Collector;)Ljava/lang/Object;
     132: checkcast     #16                 // class java/util/List
     135: astore        5
     137: aload_2
     138: aload         5
     140: invokevirtual #103                // Method org/apache/dubbo/rpc/cluster/router/xds/rule/HTTPRouteDestination.setWeightedClusters:(Ljava/util/List;)V
     143: aload_2
     144: areturn
     145: new           #48                 // class java/lang/IllegalArgumentException
     148: dup
     149: ldc           #104                // String Cluster specifier is not expect
     151: invokespecial #50                 // Method java/lang/IllegalArgumentException."<init>":(Ljava/lang/String;)V
     154: athrow

  private static org.apache.dubbo.rpc.cluster.router.xds.rule.ClusterWeight lambda$parseAction$1(io.envoyproxy.envoy.config.route.v3.WeightedCluster$ClusterWeight);
    Code:
       0: new           #105                // class org/apache/dubbo/rpc/cluster/router/xds/rule/ClusterWeight
       3: dup
       4: aload_0
       5: invokevirtual #106                // Method io/envoyproxy/envoy/config/route/v3/WeightedCluster$ClusterWeight.getName:()Ljava/lang/String;
       8: aload_0
       9: invokevirtual #107                // Method io/envoyproxy/envoy/config/route/v3/WeightedCluster$ClusterWeight.getWeight:()Lcom/google/protobuf/UInt32Value;
      12: invokevirtual #108                // Method com/google/protobuf/UInt32Value.getValue:()I
      15: invokespecial #109                // Method org/apache/dubbo/rpc/cluster/router/xds/rule/ClusterWeight."<init>":(Ljava/lang/String;I)V
      18: areturn

  private org.apache.dubbo.rpc.cluster.router.xds.rule.XdsRouteRule lambda$parseVirtualHost$0(io.envoyproxy.envoy.config.route.v3.Route);
    Code:
       0: aload_1
       1: invokevirtual #110                // Method io/envoyproxy/envoy/config/route/v3/Route.getMatch:()Lio/envoyproxy/envoy/config/route/v3/RouteMatch;
       4: invokevirtual #111                // Method io/envoyproxy/envoy/config/route/v3/RouteMatch.getQueryParametersCount:()I
       7: ifeq          12
      10: aconst_null
      11: areturn
      12: aload_0
      13: aload_1
      14: invokevirtual #110                // Method io/envoyproxy/envoy/config/route/v3/Route.getMatch:()Lio/envoyproxy/envoy/config/route/v3/RouteMatch;
      17: invokespecial #112                // Method parseMatch:(Lio/envoyproxy/envoy/config/route/v3/RouteMatch;)Lorg/apache/dubbo/rpc/cluster/router/xds/rule/HttpRequestMatch;
      20: astore_2
      21: aload_0
      22: aload_1
      23: invokespecial #113                // Method parseAction:(Lio/envoyproxy/envoy/config/route/v3/Route;)Lorg/apache/dubbo/rpc/cluster/router/xds/rule/HTTPRouteDestination;
      26: astore_3
      27: new           #114                // class org/apache/dubbo/rpc/cluster/router/xds/rule/XdsRouteRule
      30: dup
      31: aload_2
      32: aload_3
      33: invokespecial #115                // Method org/apache/dubbo/rpc/cluster/router/xds/rule/XdsRouteRule."<init>":(Lorg/apache/dubbo/rpc/cluster/router/xds/rule/HttpRequestMatch;Lorg/apache/dubbo/rpc/cluster/router/xds/rule/HTTPRouteDestination;)V
      36: areturn

  static {};
    Code:
       0: ldc           #116                // class org/apache/dubbo/rpc/cluster/router/xds/RdsVirtualHostListener
       2: invokestatic  #117                // Method org/apache/dubbo/common/logger/LoggerFactory.getErrorTypeAwareLogger:(Ljava/lang/Class;)Lorg/apache/dubbo/common/logger/ErrorTypeAwareLogger;
       5: putstatic     #18                 // Field LOGGER:Lorg/apache/dubbo/common/logger/ErrorTypeAwareLogger;
       8: return
}
