Compiled from "XdsRouter.java"
public class org.apache.dubbo.rpc.cluster.router.xds.XdsRouter<T> extends org.apache.dubbo.rpc.cluster.router.state.AbstractStateRouter<T> implements org.apache.dubbo.rpc.cluster.router.xds.XdsRouteRuleListener, org.apache.dubbo.rpc.cluster.router.xds.EdsEndpointListener {
  private java.util.Set<java.lang.String> subscribeApplications;

  private final java.util.concurrent.ConcurrentHashMap<java.lang.String, java.util.List<org.apache.dubbo.rpc.cluster.router.xds.rule.XdsRouteRule>> xdsRouteRuleMap;

  private final java.util.concurrent.ConcurrentHashMap<java.lang.String, org.apache.dubbo.rpc.cluster.router.xds.rule.DestinationSubset<T>> destinationSubsetMap;

  private final org.apache.dubbo.rpc.cluster.router.xds.RdsRouteRuleManager rdsRouteRuleManager;

  private final org.apache.dubbo.rpc.cluster.router.xds.EdsEndpointManager edsEndpointManager;

  private volatile org.apache.dubbo.rpc.cluster.router.state.BitList<org.apache.dubbo.rpc.Invoker<T>> currentInvokeList;

  private static final java.lang.String BINARY_HEADER_SUFFIX;

  private final boolean isEnable;

  public org.apache.dubbo.rpc.cluster.router.xds.XdsRouter(org.apache.dubbo.common.URL);
    Code:
       0: aload_0
       1: aload_1
       2: invokespecial #1                  // Method org/apache/dubbo/rpc/cluster/router/state/AbstractStateRouter."<init>":(Lorg/apache/dubbo/common/URL;)V
       5: aload_0
       6: invokestatic  #2                  // Method org/apache/dubbo/registry/xds/util/PilotExchanger.isEnabled:()Z
       9: putfield      #3                  // Field isEnable:Z
      12: aload_0
      13: aload_1
      14: invokevirtual #4                  // Method org/apache/dubbo/common/URL.getOrDefaultApplicationModel:()Lorg/apache/dubbo/rpc/model/ApplicationModel;
      17: invokevirtual #5                  // Method org/apache/dubbo/rpc/model/ApplicationModel.getBeanFactory:()Lorg/apache/dubbo/common/beans/factory/ScopeBeanFactory;
      20: ldc           #6                  // class org/apache/dubbo/rpc/cluster/router/xds/RdsRouteRuleManager
      22: invokevirtual #7                  // Method org/apache/dubbo/common/beans/factory/ScopeBeanFactory.getBean:(Ljava/lang/Class;)Ljava/lang/Object;
      25: checkcast     #6                  // class org/apache/dubbo/rpc/cluster/router/xds/RdsRouteRuleManager
      28: putfield      #8                  // Field rdsRouteRuleManager:Lorg/apache/dubbo/rpc/cluster/router/xds/RdsRouteRuleManager;
      31: aload_0
      32: aload_1
      33: invokevirtual #4                  // Method org/apache/dubbo/common/URL.getOrDefaultApplicationModel:()Lorg/apache/dubbo/rpc/model/ApplicationModel;
      36: invokevirtual #5                  // Method org/apache/dubbo/rpc/model/ApplicationModel.getBeanFactory:()Lorg/apache/dubbo/common/beans/factory/ScopeBeanFactory;
      39: ldc           #9                  // class org/apache/dubbo/rpc/cluster/router/xds/EdsEndpointManager
      41: invokevirtual #7                  // Method org/apache/dubbo/common/beans/factory/ScopeBeanFactory.getBean:(Ljava/lang/Class;)Ljava/lang/Object;
      44: checkcast     #9                  // class org/apache/dubbo/rpc/cluster/router/xds/EdsEndpointManager
      47: putfield      #10                 // Field edsEndpointManager:Lorg/apache/dubbo/rpc/cluster/router/xds/EdsEndpointManager;
      50: aload_0
      51: new           #11                 // class org/apache/dubbo/common/utils/ConcurrentHashSet
      54: dup
      55: invokespecial #12                 // Method org/apache/dubbo/common/utils/ConcurrentHashSet."<init>":()V
      58: putfield      #13                 // Field subscribeApplications:Ljava/util/Set;
      61: aload_0
      62: new           #14                 // class java/util/concurrent/ConcurrentHashMap
      65: dup
      66: invokespecial #15                 // Method java/util/concurrent/ConcurrentHashMap."<init>":()V
      69: putfield      #16                 // Field destinationSubsetMap:Ljava/util/concurrent/ConcurrentHashMap;
      72: aload_0
      73: new           #14                 // class java/util/concurrent/ConcurrentHashMap
      76: dup
      77: invokespecial #15                 // Method java/util/concurrent/ConcurrentHashMap."<init>":()V
      80: putfield      #17                 // Field xdsRouteRuleMap:Ljava/util/concurrent/ConcurrentHashMap;
      83: aload_0
      84: new           #18                 // class org/apache/dubbo/rpc/cluster/router/state/BitList
      87: dup
      88: new           #19                 // class java/util/ArrayList
      91: dup
      92: invokespecial #20                 // Method java/util/ArrayList."<init>":()V
      95: invokespecial #21                 // Method org/apache/dubbo/rpc/cluster/router/state/BitList."<init>":(Ljava/util/List;)V
      98: putfield      #22                 // Field currentInvokeList:Lorg/apache/dubbo/rpc/cluster/router/state/BitList;
     101: return

  protected org.apache.dubbo.rpc.cluster.router.xds.XdsRouter(org.apache.dubbo.common.URL, org.apache.dubbo.rpc.cluster.router.xds.RdsRouteRuleManager, org.apache.dubbo.rpc.cluster.router.xds.EdsEndpointManager, boolean);
    Code:
       0: aload_0
       1: aload_1
       2: invokespecial #1                  // Method org/apache/dubbo/rpc/cluster/router/state/AbstractStateRouter."<init>":(Lorg/apache/dubbo/common/URL;)V
       5: aload_0
       6: iload         4
       8: putfield      #3                  // Field isEnable:Z
      11: aload_0
      12: aload_2
      13: putfield      #8                  // Field rdsRouteRuleManager:Lorg/apache/dubbo/rpc/cluster/router/xds/RdsRouteRuleManager;
      16: aload_0
      17: aload_3
      18: putfield      #10                 // Field edsEndpointManager:Lorg/apache/dubbo/rpc/cluster/router/xds/EdsEndpointManager;
      21: aload_0
      22: new           #11                 // class org/apache/dubbo/common/utils/ConcurrentHashSet
      25: dup
      26: invokespecial #12                 // Method org/apache/dubbo/common/utils/ConcurrentHashSet."<init>":()V
      29: putfield      #13                 // Field subscribeApplications:Ljava/util/Set;
      32: aload_0
      33: new           #14                 // class java/util/concurrent/ConcurrentHashMap
      36: dup
      37: invokespecial #15                 // Method java/util/concurrent/ConcurrentHashMap."<init>":()V
      40: putfield      #16                 // Field destinationSubsetMap:Ljava/util/concurrent/ConcurrentHashMap;
      43: aload_0
      44: new           #14                 // class java/util/concurrent/ConcurrentHashMap
      47: dup
      48: invokespecial #15                 // Method java/util/concurrent/ConcurrentHashMap."<init>":()V
      51: putfield      #17                 // Field xdsRouteRuleMap:Ljava/util/concurrent/ConcurrentHashMap;
      54: aload_0
      55: new           #18                 // class org/apache/dubbo/rpc/cluster/router/state/BitList
      58: dup
      59: new           #19                 // class java/util/ArrayList
      62: dup
      63: invokespecial #20                 // Method java/util/ArrayList."<init>":()V
      66: invokespecial #21                 // Method org/apache/dubbo/rpc/cluster/router/state/BitList."<init>":(Ljava/util/List;)V
      69: putfield      #22                 // Field currentInvokeList:Lorg/apache/dubbo/rpc/cluster/router/state/BitList;
      72: return

  protected org.apache.dubbo.rpc.cluster.router.state.BitList<org.apache.dubbo.rpc.Invoker<T>> doRoute(org.apache.dubbo.rpc.cluster.router.state.BitList<org.apache.dubbo.rpc.Invoker<T>>, org.apache.dubbo.common.URL, org.apache.dubbo.rpc.Invocation, boolean, org.apache.dubbo.common.utils.Holder<org.apache.dubbo.rpc.cluster.router.RouterSnapshotNode<T>>, org.apache.dubbo.common.utils.Holder<java.lang.String>) throws org.apache.dubbo.rpc.RpcException;
    Code:
       0: aload_0
       1: getfield      #3                  // Field isEnable:Z
       4: ifne          21
       7: iload         4
       9: ifeq          19
      12: aload         6
      14: ldc           #23                 // String Directly Return. Reason: Pilot exchanger has not been initialized, may not in mesh mode.
      16: invokevirtual #24                 // Method org/apache/dubbo/common/utils/Holder.set:(Ljava/lang/Object;)V
      19: aload_1
      20: areturn
      21: aload_1
      22: invokestatic  #25                 // Method org/apache/dubbo/common/utils/CollectionUtils.isEmpty:(Ljava/util/Collection;)Z
      25: ifeq          42
      28: iload         4
      30: ifeq          40
      33: aload         6
      35: ldc           #26                 // String Directly Return. Reason: Invokers from previous router is empty.
      37: invokevirtual #24                 // Method org/apache/dubbo/common/utils/Holder.set:(Ljava/lang/Object;)V
      40: aload_1
      41: areturn
      42: aload_0
      43: getfield      #17                 // Field xdsRouteRuleMap:Ljava/util/concurrent/ConcurrentHashMap;
      46: invokestatic  #27                 // Method org/apache/dubbo/common/utils/CollectionUtils.isEmptyMap:(Ljava/util/Map;)Z
      49: ifeq          66
      52: iload         4
      54: ifeq          64
      57: aload         6
      59: ldc           #28                 // String Directly Return. Reason: xds route rule is empty.
      61: invokevirtual #24                 // Method org/apache/dubbo/common/utils/Holder.set:(Ljava/lang/Object;)V
      64: aload_1
      65: areturn
      66: iload         4
      68: ifeq          81
      71: new           #29                 // class java/lang/StringBuilder
      74: dup
      75: invokespecial #30                 // Method java/lang/StringBuilder."<init>":()V
      78: goto          82
      81: aconst_null
      82: astore        7
      84: aconst_null
      85: astore        8
      87: aload_0
      88: getfield      #13                 // Field subscribeApplications:Ljava/util/Set;
      91: astore        9
      93: aload         9
      95: invokeinterface #31,  1           // InterfaceMethod java/util/Set.iterator:()Ljava/util/Iterator;
     100: astore        10
     102: aload         10
     104: invokeinterface #32,  1           // InterfaceMethod java/util/Iterator.hasNext:()Z
     109: ifeq          248
     112: aload         10
     114: invokeinterface #33,  1           // InterfaceMethod java/util/Iterator.next:()Ljava/lang/Object;
     119: checkcast     #34                 // class java/lang/String
     122: astore        11
     124: aload_0
     125: getfield      #17                 // Field xdsRouteRuleMap:Ljava/util/concurrent/ConcurrentHashMap;
     128: aload         11
     130: invokevirtual #35                 // Method java/util/concurrent/ConcurrentHashMap.get:(Ljava/lang/Object;)Ljava/lang/Object;
     133: checkcast     #36                 // class java/util/List
     136: astore        12
     138: aload         12
     140: invokestatic  #25                 // Method org/apache/dubbo/common/utils/CollectionUtils.isEmpty:(Ljava/util/Collection;)Z
     143: ifeq          149
     146: goto          102
     149: aload         12
     151: invokeinterface #37,  1           // InterfaceMethod java/util/List.iterator:()Ljava/util/Iterator;
     156: astore        13
     158: aload         13
     160: invokeinterface #32,  1           // InterfaceMethod java/util/Iterator.hasNext:()Z
     165: ifeq          204
     168: aload         13
     170: invokeinterface #33,  1           // InterfaceMethod java/util/Iterator.next:()Ljava/lang/Object;
     175: checkcast     #38                 // class org/apache/dubbo/rpc/cluster/router/xds/rule/XdsRouteRule
     178: astore        14
     180: aload_0
     181: aload_3
     182: aload         14
     184: invokespecial #39                 // Method computeMatchCluster:(Lorg/apache/dubbo/rpc/Invocation;Lorg/apache/dubbo/rpc/cluster/router/xds/rule/XdsRouteRule;)Ljava/lang/String;
     187: astore        15
     189: aload         15
     191: ifnull        201
     194: aload         15
     196: astore        8
     198: goto          204
     201: goto          158
     204: aload         8
     206: ifnull        245
     209: aload         7
     211: ifnull        248
     214: aload         7
     216: ldc           #40                 // String Match App:
     218: invokevirtual #41                 // Method java/lang/StringBuilder.append:(Ljava/lang/String;)Ljava/lang/StringBuilder;
     221: aload         11
     223: invokevirtual #41                 // Method java/lang/StringBuilder.append:(Ljava/lang/String;)Ljava/lang/StringBuilder;
     226: ldc           #42                 // String  Cluster:
     228: invokevirtual #41                 // Method java/lang/StringBuilder.append:(Ljava/lang/String;)Ljava/lang/StringBuilder;
     231: aload         8
     233: invokevirtual #41                 // Method java/lang/StringBuilder.append:(Ljava/lang/String;)Ljava/lang/StringBuilder;
     236: bipush        32
     238: invokevirtual #43                 // Method java/lang/StringBuilder.append:(C)Ljava/lang/StringBuilder;
     241: pop
     242: goto          248
     245: goto          102
     248: aload         8
     250: ifnonnull     267
     253: iload         4
     255: ifeq          265
     258: aload         6
     260: ldc           #44                 // String Directly Return. Reason: xds rule not match.
     262: invokevirtual #24                 // Method org/apache/dubbo/common/utils/Holder.set:(Ljava/lang/Object;)V
     265: aload_1
     266: areturn
     267: aload_0
     268: getfield      #16                 // Field destinationSubsetMap:Ljava/util/concurrent/ConcurrentHashMap;
     271: aload         8
     273: invokevirtual #35                 // Method java/util/concurrent/ConcurrentHashMap.get:(Ljava/lang/Object;)Ljava/lang/Object;
     276: checkcast     #45                 // class org/apache/dubbo/rpc/cluster/router/xds/rule/DestinationSubset
     279: astore        10
     281: aload         10
     283: ifnonnull     310
     286: iload         4
     288: ifeq          306
     291: aload         6
     293: aload         7
     295: ldc           #46                 // String no target subset
     297: invokevirtual #41                 // Method java/lang/StringBuilder.append:(Ljava/lang/String;)Ljava/lang/StringBuilder;
     300: invokevirtual #47                 // Method java/lang/StringBuilder.toString:()Ljava/lang/String;
     303: invokevirtual #24                 // Method org/apache/dubbo/common/utils/Holder.set:(Ljava/lang/Object;)V
     306: invokestatic  #48                 // Method org/apache/dubbo/rpc/cluster/router/state/BitList.emptyList:()Lorg/apache/dubbo/rpc/cluster/router/state/BitList;
     309: areturn
     310: iload         4
     312: ifeq          325
     315: aload         6
     317: aload         7
     319: invokevirtual #47                 // Method java/lang/StringBuilder.toString:()Ljava/lang/String;
     322: invokevirtual #24                 // Method org/apache/dubbo/common/utils/Holder.set:(Ljava/lang/Object;)V
     325: aload         10
     327: invokevirtual #49                 // Method org/apache/dubbo/rpc/cluster/router/xds/rule/DestinationSubset.getInvokers:()Lorg/apache/dubbo/rpc/cluster/router/state/BitList;
     330: ifnonnull     337
     333: invokestatic  #48                 // Method org/apache/dubbo/rpc/cluster/router/state/BitList.emptyList:()Lorg/apache/dubbo/rpc/cluster/router/state/BitList;
     336: areturn
     337: aload         10
     339: invokevirtual #49                 // Method org/apache/dubbo/rpc/cluster/router/xds/rule/DestinationSubset.getInvokers:()Lorg/apache/dubbo/rpc/cluster/router/state/BitList;
     342: aload_1
     343: invokevirtual #50                 // Method org/apache/dubbo/rpc/cluster/router/state/BitList.and:(Lorg/apache/dubbo/rpc/cluster/router/state/BitList;)Lorg/apache/dubbo/rpc/cluster/router/state/BitList;
     346: areturn

  private java.lang.String computeMatchCluster(org.apache.dubbo.rpc.Invocation, org.apache.dubbo.rpc.cluster.router.xds.rule.XdsRouteRule);
    Code:
       0: aload_2
       1: invokevirtual #51                 // Method org/apache/dubbo/rpc/cluster/router/xds/rule/XdsRouteRule.getMatch:()Lorg/apache/dubbo/rpc/cluster/router/xds/rule/HttpRequestMatch;
       4: astore_3
       5: aload_3
       6: invokevirtual #52                 // Method org/apache/dubbo/rpc/cluster/router/xds/rule/HttpRequestMatch.getPathMatcher:()Lorg/apache/dubbo/rpc/cluster/router/xds/rule/PathMatcher;
       9: ifnonnull     24
      12: aload_3
      13: invokevirtual #53                 // Method org/apache/dubbo/rpc/cluster/router/xds/rule/HttpRequestMatch.getHeaderMatcherList:()Ljava/util/List;
      16: invokestatic  #25                 // Method org/apache/dubbo/common/utils/CollectionUtils.isEmpty:(Ljava/util/Collection;)Z
      19: ifeq          24
      22: aconst_null
      23: areturn
      24: aload_3
      25: invokevirtual #52                 // Method org/apache/dubbo/rpc/cluster/router/xds/rule/HttpRequestMatch.getPathMatcher:()Lorg/apache/dubbo/rpc/cluster/router/xds/rule/PathMatcher;
      28: astore        4
      30: aload         4
      32: ifnull        95
      35: new           #29                 // class java/lang/StringBuilder
      38: dup
      39: invokespecial #30                 // Method java/lang/StringBuilder."<init>":()V
      42: ldc           #54                 // String /
      44: invokevirtual #41                 // Method java/lang/StringBuilder.append:(Ljava/lang/String;)Ljava/lang/StringBuilder;
      47: aload_1
      48: invokeinterface #55,  1           // InterfaceMethod org/apache/dubbo/rpc/Invocation.getInvoker:()Lorg/apache/dubbo/rpc/Invoker;
      53: invokeinterface #56,  1           // InterfaceMethod org/apache/dubbo/rpc/Invoker.getUrl:()Lorg/apache/dubbo/common/URL;
      58: invokevirtual #57                 // Method org/apache/dubbo/common/URL.getPath:()Ljava/lang/String;
      61: invokevirtual #41                 // Method java/lang/StringBuilder.append:(Ljava/lang/String;)Ljava/lang/StringBuilder;
      64: ldc           #54                 // String /
      66: invokevirtual #41                 // Method java/lang/StringBuilder.append:(Ljava/lang/String;)Ljava/lang/StringBuilder;
      69: aload_1
      70: invokeinterface #58,  1           // InterfaceMethod org/apache/dubbo/rpc/Invocation.getMethodName:()Ljava/lang/String;
      75: invokevirtual #41                 // Method java/lang/StringBuilder.append:(Ljava/lang/String;)Ljava/lang/StringBuilder;
      78: invokevirtual #47                 // Method java/lang/StringBuilder.toString:()Ljava/lang/String;
      81: astore        5
      83: aload         4
      85: aload         5
      87: invokevirtual #59                 // Method org/apache/dubbo/rpc/cluster/router/xds/rule/PathMatcher.isMatch:(Ljava/lang/String;)Z
      90: ifne          95
      93: aconst_null
      94: areturn
      95: aload_3
      96: invokevirtual #53                 // Method org/apache/dubbo/rpc/cluster/router/xds/rule/HttpRequestMatch.getHeaderMatcherList:()Ljava/util/List;
      99: astore        5
     101: aload         5
     103: invokeinterface #37,  1           // InterfaceMethod java/util/List.iterator:()Ljava/util/Iterator;
     108: astore        6
     110: aload         6
     112: invokeinterface #32,  1           // InterfaceMethod java/util/Iterator.hasNext:()Z
     117: ifeq          176
     120: aload         6
     122: invokeinterface #33,  1           // InterfaceMethod java/util/Iterator.next:()Ljava/lang/Object;
     127: checkcast     #60                 // class org/apache/dubbo/rpc/cluster/router/xds/rule/HeaderMatcher
     130: astore        7
     132: aload         7
     134: invokevirtual #61                 // Method org/apache/dubbo/rpc/cluster/router/xds/rule/HeaderMatcher.getName:()Ljava/lang/String;
     137: astore        8
     139: aload         8
     141: ldc           #63                 // String -bin
     143: invokevirtual #64                 // Method java/lang/String.endsWith:(Ljava/lang/String;)Z
     146: ifeq          151
     149: aconst_null
     150: areturn
     151: aload_1
     152: aload         8
     154: invokeinterface #65,  2           // InterfaceMethod org/apache/dubbo/rpc/Invocation.getAttachment:(Ljava/lang/String;)Ljava/lang/String;
     159: astore        9
     161: aload         7
     163: aload         9
     165: invokevirtual #66                 // Method org/apache/dubbo/rpc/cluster/router/xds/rule/HeaderMatcher.match:(Ljava/lang/String;)Z
     168: ifne          173
     171: aconst_null
     172: areturn
     173: goto          110
     176: aload_2
     177: invokevirtual #67                 // Method org/apache/dubbo/rpc/cluster/router/xds/rule/XdsRouteRule.getRoute:()Lorg/apache/dubbo/rpc/cluster/router/xds/rule/HTTPRouteDestination;
     180: astore        6
     182: aload         6
     184: invokevirtual #68                 // Method org/apache/dubbo/rpc/cluster/router/xds/rule/HTTPRouteDestination.getCluster:()Ljava/lang/String;
     187: ifnull        196
     190: aload         6
     192: invokevirtual #68                 // Method org/apache/dubbo/rpc/cluster/router/xds/rule/HTTPRouteDestination.getCluster:()Ljava/lang/String;
     195: areturn
     196: aload_0
     197: aload         6
     199: invokevirtual #69                 // Method org/apache/dubbo/rpc/cluster/router/xds/rule/HTTPRouteDestination.getWeightedClusters:()Ljava/util/List;
     202: invokespecial #70                 // Method computeWeightCluster:(Ljava/util/List;)Ljava/lang/String;
     205: areturn

  private java.lang.String computeWeightCluster(java.util.List<org.apache.dubbo.rpc.cluster.router.xds.rule.ClusterWeight>);
    Code:
       0: aload_1
       1: invokeinterface #71,  1           // InterfaceMethod java/util/List.stream:()Ljava/util/stream/Stream;
       6: invokedynamic #72,  0             // InvokeDynamic #0:applyAsInt:()Ljava/util/function/ToIntFunction;
      11: invokeinterface #73,  2           // InterfaceMethod java/util/stream/Stream.mapToInt:(Ljava/util/function/ToIntFunction;)Ljava/util/stream/IntStream;
      16: invokeinterface #74,  1           // InterfaceMethod java/util/stream/IntStream.sum:()I
      21: iconst_1
      22: invokestatic  #75                 // Method java/lang/Math.max:(II)I
      25: istore_2
      26: invokestatic  #76                 // Method java/util/concurrent/ThreadLocalRandom.current:()Ljava/util/concurrent/ThreadLocalRandom;
      29: iconst_1
      30: iload_2
      31: iconst_1
      32: iadd
      33: invokevirtual #77                 // Method java/util/concurrent/ThreadLocalRandom.nextInt:(II)I
      36: istore_3
      37: aload_1
      38: invokeinterface #37,  1           // InterfaceMethod java/util/List.iterator:()Ljava/util/Iterator;
      43: astore        4
      45: aload         4
      47: invokeinterface #32,  1           // InterfaceMethod java/util/Iterator.hasNext:()Z
      52: ifeq          92
      55: aload         4
      57: invokeinterface #33,  1           // InterfaceMethod java/util/Iterator.next:()Ljava/lang/Object;
      62: checkcast     #78                 // class org/apache/dubbo/rpc/cluster/router/xds/rule/ClusterWeight
      65: astore        5
      67: aload         5
      69: invokevirtual #79                 // Method org/apache/dubbo/rpc/cluster/router/xds/rule/ClusterWeight.getWeight:()I
      72: istore        6
      74: iload_3
      75: iload         6
      77: isub
      78: istore_3
      79: iload_3
      80: ifgt          89
      83: aload         5
      85: invokevirtual #80                 // Method org/apache/dubbo/rpc/cluster/router/xds/rule/ClusterWeight.getName:()Ljava/lang/String;
      88: areturn
      89: goto          45
      92: aconst_null
      93: areturn

  public void notify(org.apache.dubbo.rpc.cluster.router.state.BitList<org.apache.dubbo.rpc.Invoker<T>>);
    Code:
       0: aload_1
       1: ifnonnull     10
       4: invokestatic  #48                 // Method org/apache/dubbo/rpc/cluster/router/state/BitList.emptyList:()Lorg/apache/dubbo/rpc/cluster/router/state/BitList;
       7: goto          11
      10: aload_1
      11: astore_2
      12: aload_0
      13: aload_2
      14: invokevirtual #81                 // Method org/apache/dubbo/rpc/cluster/router/state/BitList.clone:()Lorg/apache/dubbo/rpc/cluster/router/state/BitList;
      17: putfield      #22                 // Field currentInvokeList:Lorg/apache/dubbo/rpc/cluster/router/state/BitList;
      20: new           #82                 // class java/util/HashSet
      23: dup
      24: invokespecial #83                 // Method java/util/HashSet."<init>":()V
      27: astore_3
      28: aload_2
      29: invokevirtual #84                 // Method org/apache/dubbo/rpc/cluster/router/state/BitList.iterator:()Ljava/util/Iterator;
      32: astore        4
      34: aload         4
      36: invokeinterface #32,  1           // InterfaceMethod java/util/Iterator.hasNext:()Z
      41: ifeq          88
      44: aload         4
      46: invokeinterface #33,  1           // InterfaceMethod java/util/Iterator.next:()Ljava/lang/Object;
      51: checkcast     #85                 // class org/apache/dubbo/rpc/Invoker
      54: astore        5
      56: aload         5
      58: invokeinterface #56,  1           // InterfaceMethod org/apache/dubbo/rpc/Invoker.getUrl:()Lorg/apache/dubbo/common/URL;
      63: invokevirtual #86                 // Method org/apache/dubbo/common/URL.getRemoteApplication:()Ljava/lang/String;
      66: astore        6
      68: aload         6
      70: invokestatic  #87                 // Method org/apache/dubbo/common/utils/StringUtils.isNotEmpty:(Ljava/lang/String;)Z
      73: ifeq          85
      76: aload_3
      77: aload         6
      79: invokeinterface #88,  2           // InterfaceMethod java/util/Set.add:(Ljava/lang/Object;)Z
      84: pop
      85: goto          34
      88: aload_0
      89: getfield      #13                 // Field subscribeApplications:Ljava/util/Set;
      92: aload_3
      93: invokeinterface #89,  2           // InterfaceMethod java/util/Set.equals:(Ljava/lang/Object;)Z
      98: ifne          239
     101: aload_0
     102: dup
     103: astore        4
     105: monitorenter
     106: aload_3
     107: invokeinterface #31,  1           // InterfaceMethod java/util/Set.iterator:()Ljava/util/Iterator;
     112: astore        5
     114: aload         5
     116: invokeinterface #32,  1           // InterfaceMethod java/util/Iterator.hasNext:()Z
     121: ifeq          163
     124: aload         5
     126: invokeinterface #33,  1           // InterfaceMethod java/util/Iterator.next:()Ljava/lang/Object;
     131: checkcast     #34                 // class java/lang/String
     134: astore        6
     136: aload_0
     137: getfield      #13                 // Field subscribeApplications:Ljava/util/Set;
     140: aload         6
     142: invokeinterface #90,  2           // InterfaceMethod java/util/Set.contains:(Ljava/lang/Object;)Z
     147: ifne          160
     150: aload_0
     151: getfield      #8                  // Field rdsRouteRuleManager:Lorg/apache/dubbo/rpc/cluster/router/xds/RdsRouteRuleManager;
     154: aload         6
     156: aload_0
     157: invokevirtual #91                 // Method org/apache/dubbo/rpc/cluster/router/xds/RdsRouteRuleManager.subscribeRds:(Ljava/lang/String;Lorg/apache/dubbo/rpc/cluster/router/xds/XdsRouteRuleListener;)V
     160: goto          114
     163: aload_0
     164: getfield      #13                 // Field subscribeApplications:Ljava/util/Set;
     167: invokeinterface #31,  1           // InterfaceMethod java/util/Set.iterator:()Ljava/util/Iterator;
     172: astore        5
     174: aload         5
     176: invokeinterface #32,  1           // InterfaceMethod java/util/Iterator.hasNext:()Z
     181: ifeq          220
     184: aload         5
     186: invokeinterface #33,  1           // InterfaceMethod java/util/Iterator.next:()Ljava/lang/Object;
     191: checkcast     #34                 // class java/lang/String
     194: astore        6
     196: aload_3
     197: aload         6
     199: invokeinterface #90,  2           // InterfaceMethod java/util/Set.contains:(Ljava/lang/Object;)Z
     204: ifne          217
     207: aload_0
     208: getfield      #8                  // Field rdsRouteRuleManager:Lorg/apache/dubbo/rpc/cluster/router/xds/RdsRouteRuleManager;
     211: aload         6
     213: aload_0
     214: invokevirtual #92                 // Method org/apache/dubbo/rpc/cluster/router/xds/RdsRouteRuleManager.unSubscribeRds:(Ljava/lang/String;Lorg/apache/dubbo/rpc/cluster/router/xds/XdsRouteRuleListener;)V
     217: goto          174
     220: aload_0
     221: aload_3
     222: putfield      #13                 // Field subscribeApplications:Ljava/util/Set;
     225: aload         4
     227: monitorexit
     228: goto          239
     231: astore        7
     233: aload         4
     235: monitorexit
     236: aload         7
     238: athrow
     239: aload_0
     240: dup
     241: astore        4
     243: monitorenter
     244: aload_0
     245: getfield      #22                 // Field currentInvokeList:Lorg/apache/dubbo/rpc/cluster/router/state/BitList;
     248: invokevirtual #81                 // Method org/apache/dubbo/rpc/cluster/router/state/BitList.clone:()Lorg/apache/dubbo/rpc/cluster/router/state/BitList;
     251: astore        5
     253: aload_0
     254: getfield      #16                 // Field destinationSubsetMap:Ljava/util/concurrent/ConcurrentHashMap;
     257: invokevirtual #93                 // Method java/util/concurrent/ConcurrentHashMap.values:()Ljava/util/Collection;
     260: invokeinterface #94,  1           // InterfaceMethod java/util/Collection.iterator:()Ljava/util/Iterator;
     265: astore        6
     267: aload         6
     269: invokeinterface #32,  1           // InterfaceMethod java/util/Iterator.hasNext:()Z
     274: ifeq          300
     277: aload         6
     279: invokeinterface #33,  1           // InterfaceMethod java/util/Iterator.next:()Ljava/lang/Object;
     284: checkcast     #45                 // class org/apache/dubbo/rpc/cluster/router/xds/rule/DestinationSubset
     287: astore        7
     289: aload_0
     290: aload         7
     292: aload         5
     294: invokespecial #95                 // Method computeSubset:(Lorg/apache/dubbo/rpc/cluster/router/xds/rule/DestinationSubset;Lorg/apache/dubbo/rpc/cluster/router/state/BitList;)V
     297: goto          267
     300: aload         4
     302: monitorexit
     303: goto          314
     306: astore        8
     308: aload         4
     310: monitorexit
     311: aload         8
     313: athrow
     314: return
    Exception table:
       from    to  target type
         106   228   231   any
         231   236   231   any
         244   303   306   any
         306   311   306   any

  private void computeSubset(org.apache.dubbo.rpc.cluster.router.xds.rule.DestinationSubset<T>, org.apache.dubbo.rpc.cluster.router.state.BitList<org.apache.dubbo.rpc.Invoker<T>>);
    Code:
       0: aload_1
       1: invokevirtual #96                 // Method org/apache/dubbo/rpc/cluster/router/xds/rule/DestinationSubset.getEndpoints:()Ljava/util/Set;
       4: astore_3
       5: aload_2
       6: invokevirtual #97                 // Method org/apache/dubbo/rpc/cluster/router/state/BitList.stream:()Ljava/util/stream/Stream;
       9: aload_3
      10: invokedynamic #98,  0             // InvokeDynamic #1:test:(Ljava/util/Set;)Ljava/util/function/Predicate;
      15: invokeinterface #99,  2           // InterfaceMethod java/util/stream/Stream.filter:(Ljava/util/function/Predicate;)Ljava/util/stream/Stream;
      20: invokestatic  #100                // Method java/util/stream/Collectors.toList:()Ljava/util/stream/Collector;
      23: invokeinterface #101,  2          // InterfaceMethod java/util/stream/Stream.collect:(Ljava/util/stream/Collector;)Ljava/lang/Object;
      28: checkcast     #36                 // class java/util/List
      31: astore        4
      33: aload_1
      34: new           #18                 // class org/apache/dubbo/rpc/cluster/router/state/BitList
      37: dup
      38: aload         4
      40: invokespecial #21                 // Method org/apache/dubbo/rpc/cluster/router/state/BitList."<init>":(Ljava/util/List;)V
      43: invokevirtual #102                // Method org/apache/dubbo/rpc/cluster/router/xds/rule/DestinationSubset.setInvokers:(Lorg/apache/dubbo/rpc/cluster/router/state/BitList;)V
      46: return

  public synchronized void onRuleChange(java.lang.String, java.util.List<org.apache.dubbo.rpc.cluster.router.xds.rule.XdsRouteRule>);
    Code:
       0: aload_2
       1: invokestatic  #25                 // Method org/apache/dubbo/common/utils/CollectionUtils.isEmpty:(Ljava/util/Collection;)Z
       4: ifeq          13
       7: aload_0
       8: aload_1
       9: invokevirtual #103                // Method clearRule:(Ljava/lang/String;)V
      12: return
      13: aload_0
      14: invokespecial #104                // Method getAllCluster:()Ljava/util/Set;
      17: astore_3
      18: aload_0
      19: getfield      #17                 // Field xdsRouteRuleMap:Ljava/util/concurrent/ConcurrentHashMap;
      22: aload_1
      23: aload_2
      24: invokevirtual #105                // Method java/util/concurrent/ConcurrentHashMap.put:(Ljava/lang/Object;Ljava/lang/Object;)Ljava/lang/Object;
      27: pop
      28: aload_0
      29: invokespecial #104                // Method getAllCluster:()Ljava/util/Set;
      32: astore        4
      34: aload_0
      35: aload_3
      36: aload         4
      38: invokespecial #106                // Method changeClusterSubscribe:(Ljava/util/Set;Ljava/util/Set;)V
      41: return

  private java.util.Set<java.lang.String> getAllCluster();
    Code:
       0: aload_0
       1: getfield      #17                 // Field xdsRouteRuleMap:Ljava/util/concurrent/ConcurrentHashMap;
       4: invokestatic  #27                 // Method org/apache/dubbo/common/utils/CollectionUtils.isEmptyMap:(Ljava/util/Map;)Z
       7: ifeq          18
      10: new           #82                 // class java/util/HashSet
      13: dup
      14: invokespecial #83                 // Method java/util/HashSet."<init>":()V
      17: areturn
      18: new           #82                 // class java/util/HashSet
      21: dup
      22: invokespecial #83                 // Method java/util/HashSet."<init>":()V
      25: astore_1
      26: aload_0
      27: getfield      #17                 // Field xdsRouteRuleMap:Ljava/util/concurrent/ConcurrentHashMap;
      30: aload_1
      31: invokedynamic #107,  0            // InvokeDynamic #2:accept:(Ljava/util/Set;)Ljava/util/function/BiConsumer;
      36: invokevirtual #108                // Method java/util/concurrent/ConcurrentHashMap.forEach:(Ljava/util/function/BiConsumer;)V
      39: aload_1
      40: areturn

  private void changeClusterSubscribe(java.util.Set<java.lang.String>, java.util.Set<java.lang.String>);
    Code:
       0: new           #82                 // class java/util/HashSet
       3: dup
       4: aload_1
       5: invokespecial #109                // Method java/util/HashSet."<init>":(Ljava/util/Collection;)V
       8: astore_3
       9: new           #82                 // class java/util/HashSet
      12: dup
      13: aload_2
      14: invokespecial #109                // Method java/util/HashSet."<init>":(Ljava/util/Collection;)V
      17: astore        4
      19: aload_3
      20: aload_2
      21: invokeinterface #110,  2          // InterfaceMethod java/util/Set.removeAll:(Ljava/util/Collection;)Z
      26: pop
      27: aload         4
      29: aload_1
      30: invokeinterface #110,  2          // InterfaceMethod java/util/Set.removeAll:(Ljava/util/Collection;)Z
      35: pop
      36: aload_3
      37: invokeinterface #31,  1           // InterfaceMethod java/util/Set.iterator:()Ljava/util/Iterator;
      42: astore        5
      44: aload         5
      46: invokeinterface #32,  1           // InterfaceMethod java/util/Iterator.hasNext:()Z
      51: ifeq          89
      54: aload         5
      56: invokeinterface #33,  1           // InterfaceMethod java/util/Iterator.next:()Ljava/lang/Object;
      61: checkcast     #34                 // class java/lang/String
      64: astore        6
      66: aload_0
      67: getfield      #10                 // Field edsEndpointManager:Lorg/apache/dubbo/rpc/cluster/router/xds/EdsEndpointManager;
      70: aload         6
      72: aload_0
      73: invokevirtual #111                // Method org/apache/dubbo/rpc/cluster/router/xds/EdsEndpointManager.unSubscribeEds:(Ljava/lang/String;Lorg/apache/dubbo/rpc/cluster/router/xds/EdsEndpointListener;)V
      76: aload_0
      77: getfield      #16                 // Field destinationSubsetMap:Ljava/util/concurrent/ConcurrentHashMap;
      80: aload         6
      82: invokevirtual #112                // Method java/util/concurrent/ConcurrentHashMap.remove:(Ljava/lang/Object;)Ljava/lang/Object;
      85: pop
      86: goto          44
      89: aload         4
      91: invokeinterface #31,  1           // InterfaceMethod java/util/Set.iterator:()Ljava/util/Iterator;
      96: astore        5
      98: aload         5
     100: invokeinterface #32,  1           // InterfaceMethod java/util/Iterator.hasNext:()Z
     105: ifeq          152
     108: aload         5
     110: invokeinterface #33,  1           // InterfaceMethod java/util/Iterator.next:()Ljava/lang/Object;
     115: checkcast     #34                 // class java/lang/String
     118: astore        6
     120: aload_0
     121: getfield      #16                 // Field destinationSubsetMap:Ljava/util/concurrent/ConcurrentHashMap;
     124: aload         6
     126: new           #45                 // class org/apache/dubbo/rpc/cluster/router/xds/rule/DestinationSubset
     129: dup
     130: aload         6
     132: invokespecial #113                // Method org/apache/dubbo/rpc/cluster/router/xds/rule/DestinationSubset."<init>":(Ljava/lang/String;)V
     135: invokevirtual #105                // Method java/util/concurrent/ConcurrentHashMap.put:(Ljava/lang/Object;Ljava/lang/Object;)Ljava/lang/Object;
     138: pop
     139: aload_0
     140: getfield      #10                 // Field edsEndpointManager:Lorg/apache/dubbo/rpc/cluster/router/xds/EdsEndpointManager;
     143: aload         6
     145: aload_0
     146: invokevirtual #114                // Method org/apache/dubbo/rpc/cluster/router/xds/EdsEndpointManager.subscribeEds:(Ljava/lang/String;Lorg/apache/dubbo/rpc/cluster/router/xds/EdsEndpointListener;)V
     149: goto          98
     152: return

  public synchronized void clearRule(java.lang.String);
    Code:
       0: aload_0
       1: invokespecial #104                // Method getAllCluster:()Ljava/util/Set;
       4: astore_2
       5: aload_0
       6: getfield      #17                 // Field xdsRouteRuleMap:Ljava/util/concurrent/ConcurrentHashMap;
       9: aload_1
      10: invokevirtual #112                // Method java/util/concurrent/ConcurrentHashMap.remove:(Ljava/lang/Object;)Ljava/lang/Object;
      13: checkcast     #36                 // class java/util/List
      16: astore_3
      17: aload_3
      18: invokestatic  #25                 // Method org/apache/dubbo/common/utils/CollectionUtils.isEmpty:(Ljava/util/Collection;)Z
      21: ifeq          25
      24: return
      25: aload_0
      26: invokespecial #104                // Method getAllCluster:()Ljava/util/Set;
      29: astore        4
      31: aload_0
      32: aload_2
      33: aload         4
      35: invokespecial #106                // Method changeClusterSubscribe:(Ljava/util/Set;Ljava/util/Set;)V
      38: return

  public synchronized void onEndPointChange(java.lang.String, java.util.Set<org.apache.dubbo.registry.xds.util.protocol.message.Endpoint>);
    Code:
       0: aload_0
       1: getfield      #16                 // Field destinationSubsetMap:Ljava/util/concurrent/ConcurrentHashMap;
       4: aload_1
       5: invokevirtual #35                 // Method java/util/concurrent/ConcurrentHashMap.get:(Ljava/lang/Object;)Ljava/lang/Object;
       8: checkcast     #45                 // class org/apache/dubbo/rpc/cluster/router/xds/rule/DestinationSubset
      11: astore_3
      12: aload_3
      13: ifnonnull     17
      16: return
      17: aload_3
      18: aload_2
      19: invokevirtual #115                // Method org/apache/dubbo/rpc/cluster/router/xds/rule/DestinationSubset.setEndpoints:(Ljava/util/Set;)V
      22: aload_0
      23: aload_3
      24: aload_0
      25: getfield      #22                 // Field currentInvokeList:Lorg/apache/dubbo/rpc/cluster/router/state/BitList;
      28: invokevirtual #81                 // Method org/apache/dubbo/rpc/cluster/router/state/BitList.clone:()Lorg/apache/dubbo/rpc/cluster/router/state/BitList;
      31: invokespecial #95                 // Method computeSubset:(Lorg/apache/dubbo/rpc/cluster/router/xds/rule/DestinationSubset;Lorg/apache/dubbo/rpc/cluster/router/state/BitList;)V
      34: return

  public void stop();
    Code:
       0: aload_0
       1: getfield      #13                 // Field subscribeApplications:Ljava/util/Set;
       4: invokeinterface #31,  1           // InterfaceMethod java/util/Set.iterator:()Ljava/util/Iterator;
       9: astore_1
      10: aload_1
      11: invokeinterface #32,  1           // InterfaceMethod java/util/Iterator.hasNext:()Z
      16: ifeq          41
      19: aload_1
      20: invokeinterface #33,  1           // InterfaceMethod java/util/Iterator.next:()Ljava/lang/Object;
      25: checkcast     #34                 // class java/lang/String
      28: astore_2
      29: aload_0
      30: getfield      #8                  // Field rdsRouteRuleManager:Lorg/apache/dubbo/rpc/cluster/router/xds/RdsRouteRuleManager;
      33: aload_2
      34: aload_0
      35: invokevirtual #92                 // Method org/apache/dubbo/rpc/cluster/router/xds/RdsRouteRuleManager.unSubscribeRds:(Ljava/lang/String;Lorg/apache/dubbo/rpc/cluster/router/xds/XdsRouteRuleListener;)V
      38: goto          10
      41: aload_0
      42: invokespecial #104                // Method getAllCluster:()Ljava/util/Set;
      45: invokeinterface #31,  1           // InterfaceMethod java/util/Set.iterator:()Ljava/util/Iterator;
      50: astore_1
      51: aload_1
      52: invokeinterface #32,  1           // InterfaceMethod java/util/Iterator.hasNext:()Z
      57: ifeq          82
      60: aload_1
      61: invokeinterface #33,  1           // InterfaceMethod java/util/Iterator.next:()Ljava/lang/Object;
      66: checkcast     #34                 // class java/lang/String
      69: astore_2
      70: aload_0
      71: getfield      #10                 // Field edsEndpointManager:Lorg/apache/dubbo/rpc/cluster/router/xds/EdsEndpointManager;
      74: aload_2
      75: aload_0
      76: invokevirtual #111                // Method org/apache/dubbo/rpc/cluster/router/xds/EdsEndpointManager.unSubscribeEds:(Ljava/lang/String;Lorg/apache/dubbo/rpc/cluster/router/xds/EdsEndpointListener;)V
      79: goto          51
      82: return

  java.util.Set<java.lang.String> getSubscribeApplications();
    Code:
       0: aload_0
       1: getfield      #13                 // Field subscribeApplications:Ljava/util/Set;
       4: areturn

  org.apache.dubbo.rpc.cluster.router.state.BitList<org.apache.dubbo.rpc.Invoker<T>> getInvokerList();
    Code:
       0: aload_0
       1: getfield      #22                 // Field currentInvokeList:Lorg/apache/dubbo/rpc/cluster/router/state/BitList;
       4: areturn

  java.util.concurrent.ConcurrentHashMap<java.lang.String, java.util.List<org.apache.dubbo.rpc.cluster.router.xds.rule.XdsRouteRule>> getXdsRouteRuleMap();
    Code:
       0: aload_0
       1: getfield      #17                 // Field xdsRouteRuleMap:Ljava/util/concurrent/ConcurrentHashMap;
       4: areturn

  java.util.concurrent.ConcurrentHashMap<java.lang.String, org.apache.dubbo.rpc.cluster.router.xds.rule.DestinationSubset<T>> getDestinationSubsetMap();
    Code:
       0: aload_0
       1: getfield      #16                 // Field destinationSubsetMap:Ljava/util/concurrent/ConcurrentHashMap;
       4: areturn

  private static void lambda$getAllCluster$2(java.util.Set, java.lang.String, java.util.List);
    Code:
       0: aload_2
       1: invokeinterface #37,  1           // InterfaceMethod java/util/List.iterator:()Ljava/util/Iterator;
       6: astore_3
       7: aload_3
       8: invokeinterface #32,  1           // InterfaceMethod java/util/Iterator.hasNext:()Z
      13: ifeq          120
      16: aload_3
      17: invokeinterface #33,  1           // InterfaceMethod java/util/Iterator.next:()Ljava/lang/Object;
      22: checkcast     #38                 // class org/apache/dubbo/rpc/cluster/router/xds/rule/XdsRouteRule
      25: astore        4
      27: aload         4
      29: invokevirtual #67                 // Method org/apache/dubbo/rpc/cluster/router/xds/rule/XdsRouteRule.getRoute:()Lorg/apache/dubbo/rpc/cluster/router/xds/rule/HTTPRouteDestination;
      32: astore        5
      34: aload         5
      36: invokevirtual #68                 // Method org/apache/dubbo/rpc/cluster/router/xds/rule/HTTPRouteDestination.getCluster:()Ljava/lang/String;
      39: ifnull        57
      42: aload_0
      43: aload         5
      45: invokevirtual #68                 // Method org/apache/dubbo/rpc/cluster/router/xds/rule/HTTPRouteDestination.getCluster:()Ljava/lang/String;
      48: invokeinterface #88,  2           // InterfaceMethod java/util/Set.add:(Ljava/lang/Object;)Z
      53: pop
      54: goto          117
      57: aload         5
      59: invokevirtual #69                 // Method org/apache/dubbo/rpc/cluster/router/xds/rule/HTTPRouteDestination.getWeightedClusters:()Ljava/util/List;
      62: invokestatic  #116                // Method org/apache/dubbo/common/utils/CollectionUtils.isNotEmpty:(Ljava/util/Collection;)Z
      65: ifeq          117
      68: aload         5
      70: invokevirtual #69                 // Method org/apache/dubbo/rpc/cluster/router/xds/rule/HTTPRouteDestination.getWeightedClusters:()Ljava/util/List;
      73: invokeinterface #37,  1           // InterfaceMethod java/util/List.iterator:()Ljava/util/Iterator;
      78: astore        6
      80: aload         6
      82: invokeinterface #32,  1           // InterfaceMethod java/util/Iterator.hasNext:()Z
      87: ifeq          117
      90: aload         6
      92: invokeinterface #33,  1           // InterfaceMethod java/util/Iterator.next:()Ljava/lang/Object;
      97: checkcast     #78                 // class org/apache/dubbo/rpc/cluster/router/xds/rule/ClusterWeight
     100: astore        7
     102: aload_0
     103: aload         7
     105: invokevirtual #80                 // Method org/apache/dubbo/rpc/cluster/router/xds/rule/ClusterWeight.getName:()Ljava/lang/String;
     108: invokeinterface #88,  2           // InterfaceMethod java/util/Set.add:(Ljava/lang/Object;)Z
     113: pop
     114: goto          80
     117: goto          7
     120: return

  private static boolean lambda$computeSubset$1(java.util.Set, org.apache.dubbo.rpc.Invoker);
    Code:
       0: aload_1
       1: invokeinterface #56,  1           // InterfaceMethod org/apache/dubbo/rpc/Invoker.getUrl:()Lorg/apache/dubbo/common/URL;
       6: invokevirtual #117                // Method org/apache/dubbo/common/URL.getHost:()Ljava/lang/String;
       9: astore_2
      10: aload_1
      11: invokeinterface #56,  1           // InterfaceMethod org/apache/dubbo/rpc/Invoker.getUrl:()Lorg/apache/dubbo/common/URL;
      16: invokevirtual #118                // Method org/apache/dubbo/common/URL.getPort:()I
      19: istore_3
      20: aload_0
      21: invokeinterface #119,  1          // InterfaceMethod java/util/Set.stream:()Ljava/util/stream/Stream;
      26: aload_2
      27: iload_3
      28: invokedynamic #120,  0            // InvokeDynamic #3:test:(Ljava/lang/String;I)Ljava/util/function/Predicate;
      33: invokeinterface #99,  2           // InterfaceMethod java/util/stream/Stream.filter:(Ljava/util/function/Predicate;)Ljava/util/stream/Stream;
      38: invokeinterface #121,  1          // InterfaceMethod java/util/stream/Stream.findAny:()Ljava/util/Optional;
      43: astore        4
      45: aload         4
      47: invokevirtual #122                // Method java/util/Optional.isPresent:()Z
      50: ireturn

  private static boolean lambda$null$0(java.lang.String, int, org.apache.dubbo.registry.xds.util.protocol.message.Endpoint);
    Code:
       0: aload_0
       1: aload_2
       2: invokevirtual #123                // Method org/apache/dubbo/registry/xds/util/protocol/message/Endpoint.getAddress:()Ljava/lang/String;
       5: invokevirtual #124                // Method java/lang/String.equals:(Ljava/lang/Object;)Z
       8: ifeq          23
      11: iload_1
      12: aload_2
      13: invokevirtual #125                // Method org/apache/dubbo/registry/xds/util/protocol/message/Endpoint.getPortValue:()I
      16: if_icmpne     23
      19: iconst_1
      20: goto          24
      23: iconst_0
      24: ireturn
}
