Compiled from "ArrayCompositeDisposable.java"
public final class io.reactivex.rxjava3.internal.disposables.ArrayCompositeDisposable extends java.util.concurrent.atomic.AtomicReferenceArray<io.reactivex.rxjava3.disposables.Disposable> implements io.reactivex.rxjava3.disposables.Disposable {
  private static final long serialVersionUID;

  public io.reactivex.rxjava3.internal.disposables.ArrayCompositeDisposable(int);
    Code:
       0: aload_0
       1: iload_1
       2: invokespecial #1                  // Method java/util/concurrent/atomic/AtomicReferenceArray."<init>":(I)V
       5: return

  public boolean setResource(int, io.reactivex.rxjava3.disposables.Disposable);
    Code:
       0: aload_0
       1: iload_1
       2: invokevirtual #2                  // Method get:(I)Ljava/lang/Object;
       5: checkcast     #3                  // class io/reactivex/rxjava3/disposables/Disposable
       8: astore_3
       9: aload_3
      10: getstatic     #4                  // Field io/reactivex/rxjava3/internal/disposables/DisposableHelper.DISPOSED:Lio/reactivex/rxjava3/internal/disposables/DisposableHelper;
      13: if_acmpne     24
      16: aload_2
      17: invokeinterface #5,  1            // InterfaceMethod io/reactivex/rxjava3/disposables/Disposable.dispose:()V
      22: iconst_0
      23: ireturn
      24: aload_0
      25: iload_1
      26: aload_3
      27: aload_2
      28: invokevirtual #6                  // Method compareAndSet:(ILjava/lang/Object;Ljava/lang/Object;)Z
      31: ifeq          46
      34: aload_3
      35: ifnull        44
      38: aload_3
      39: invokeinterface #5,  1            // InterfaceMethod io/reactivex/rxjava3/disposables/Disposable.dispose:()V
      44: iconst_1
      45: ireturn
      46: goto          0

  public io.reactivex.rxjava3.disposables.Disposable replaceResource(int, io.reactivex.rxjava3.disposables.Disposable);
    Code:
       0: aload_0
       1: iload_1
       2: invokevirtual #2                  // Method get:(I)Ljava/lang/Object;
       5: checkcast     #3                  // class io/reactivex/rxjava3/disposables/Disposable
       8: astore_3
       9: aload_3
      10: getstatic     #4                  // Field io/reactivex/rxjava3/internal/disposables/DisposableHelper.DISPOSED:Lio/reactivex/rxjava3/internal/disposables/DisposableHelper;
      13: if_acmpne     24
      16: aload_2
      17: invokeinterface #5,  1            // InterfaceMethod io/reactivex/rxjava3/disposables/Disposable.dispose:()V
      22: aconst_null
      23: areturn
      24: aload_0
      25: iload_1
      26: aload_3
      27: aload_2
      28: invokevirtual #6                  // Method compareAndSet:(ILjava/lang/Object;Ljava/lang/Object;)Z
      31: ifeq          36
      34: aload_3
      35: areturn
      36: goto          0

  public void dispose();
    Code:
       0: aload_0
       1: iconst_0
       2: invokevirtual #2                  // Method get:(I)Ljava/lang/Object;
       5: getstatic     #4                  // Field io/reactivex/rxjava3/internal/disposables/DisposableHelper.DISPOSED:Lio/reactivex/rxjava3/internal/disposables/DisposableHelper;
       8: if_acmpeq     74
      11: aload_0
      12: invokevirtual #7                  // Method length:()I
      15: istore_1
      16: iconst_0
      17: istore_2
      18: iload_2
      19: iload_1
      20: if_icmpge     74
      23: aload_0
      24: iload_2
      25: invokevirtual #2                  // Method get:(I)Ljava/lang/Object;
      28: checkcast     #3                  // class io/reactivex/rxjava3/disposables/Disposable
      31: astore_3
      32: aload_3
      33: getstatic     #4                  // Field io/reactivex/rxjava3/internal/disposables/DisposableHelper.DISPOSED:Lio/reactivex/rxjava3/internal/disposables/DisposableHelper;
      36: if_acmpeq     68
      39: aload_0
      40: iload_2
      41: getstatic     #4                  // Field io/reactivex/rxjava3/internal/disposables/DisposableHelper.DISPOSED:Lio/reactivex/rxjava3/internal/disposables/DisposableHelper;
      44: invokevirtual #8                  // Method getAndSet:(ILjava/lang/Object;)Ljava/lang/Object;
      47: checkcast     #3                  // class io/reactivex/rxjava3/disposables/Disposable
      50: astore_3
      51: aload_3
      52: getstatic     #4                  // Field io/reactivex/rxjava3/internal/disposables/DisposableHelper.DISPOSED:Lio/reactivex/rxjava3/internal/disposables/DisposableHelper;
      55: if_acmpeq     68
      58: aload_3
      59: ifnull        68
      62: aload_3
      63: invokeinterface #5,  1            // InterfaceMethod io/reactivex/rxjava3/disposables/Disposable.dispose:()V
      68: iinc          2, 1
      71: goto          18
      74: return

  public boolean isDisposed();
    Code:
       0: aload_0
       1: iconst_0
       2: invokevirtual #2                  // Method get:(I)Ljava/lang/Object;
       5: getstatic     #4                  // Field io/reactivex/rxjava3/internal/disposables/DisposableHelper.DISPOSED:Lio/reactivex/rxjava3/internal/disposables/DisposableHelper;
       8: if_acmpne     15
      11: iconst_1
      12: goto          16
      15: iconst_0
      16: ireturn
}
