Compiled from "CancellableDisposable.java"
public final class io.reactivex.rxjava3.internal.disposables.CancellableDisposable extends java.util.concurrent.atomic.AtomicReference<io.reactivex.rxjava3.functions.Cancellable> implements io.reactivex.rxjava3.disposables.Disposable {
  private static final long serialVersionUID;

  public io.reactivex.rxjava3.internal.disposables.CancellableDisposable(io.reactivex.rxjava3.functions.Cancellable);
    Code:
       0: aload_0
       1: aload_1
       2: invokespecial #1                  // Method java/util/concurrent/atomic/AtomicReference."<init>":(Ljava/lang/Object;)V
       5: return

  public boolean isDisposed();
    Code:
       0: aload_0
       1: invokevirtual #2                  // Method get:()Ljava/lang/Object;
       4: ifnonnull     11
       7: iconst_1
       8: goto          12
      11: iconst_0
      12: ireturn

  public void dispose();
    Code:
       0: aload_0
       1: invokevirtual #2                  // Method get:()Ljava/lang/Object;
       4: ifnull        38
       7: aload_0
       8: aconst_null
       9: invokevirtual #3                  // Method getAndSet:(Ljava/lang/Object;)Ljava/lang/Object;
      12: checkcast     #4                  // class io/reactivex/rxjava3/functions/Cancellable
      15: astore_1
      16: aload_1
      17: ifnull        38
      20: aload_1
      21: invokeinterface #5,  1            // InterfaceMethod io/reactivex/rxjava3/functions/Cancellable.cancel:()V
      26: goto          38
      29: astore_2
      30: aload_2
      31: invokestatic  #7                  // Method io/reactivex/rxjava3/exceptions/Exceptions.throwIfFatal:(Ljava/lang/Throwable;)V
      34: aload_2
      35: invokestatic  #8                  // Method io/reactivex/rxjava3/plugins/RxJavaPlugins.onError:(Ljava/lang/Throwable;)V
      38: return
    Exception table:
       from    to  target type
          20    26    29   Class java/lang/Throwable
}
