Compiled from "DisposableHelper.java"
public final class io.reactivex.rxjava3.internal.disposables.DisposableHelper extends java.lang.Enum<io.reactivex.rxjava3.internal.disposables.DisposableHelper> implements io.reactivex.rxjava3.disposables.Disposable {
  public static final io.reactivex.rxjava3.internal.disposables.DisposableHelper DISPOSED;

  private static final io.reactivex.rxjava3.internal.disposables.DisposableHelper[] $VALUES;

  public static io.reactivex.rxjava3.internal.disposables.DisposableHelper[] values();
    Code:
       0: getstatic     #1                  // Field $VALUES:[Lio/reactivex/rxjava3/internal/disposables/DisposableHelper;
       3: invokevirtual #2                  // Method "[Lio/reactivex/rxjava3/internal/disposables/DisposableHelper;".clone:()Ljava/lang/Object;
       6: checkcast     #3                  // class "[Lio/reactivex/rxjava3/internal/disposables/DisposableHelper;"
       9: areturn

  public static io.reactivex.rxjava3.internal.disposables.DisposableHelper valueOf(java.lang.String);
    Code:
       0: ldc           #4                  // class io/reactivex/rxjava3/internal/disposables/DisposableHelper
       2: aload_0
       3: invokestatic  #5                  // Method java/lang/Enum.valueOf:(Ljava/lang/Class;Ljava/lang/String;)Ljava/lang/Enum;
       6: checkcast     #4                  // class io/reactivex/rxjava3/internal/disposables/DisposableHelper
       9: areturn

  private io.reactivex.rxjava3.internal.disposables.DisposableHelper();
    Code:
       0: aload_0
       1: aload_1
       2: iload_2
       3: invokespecial #6                  // Method java/lang/Enum."<init>":(Ljava/lang/String;I)V
       6: return

  public static boolean isDisposed(io.reactivex.rxjava3.disposables.Disposable);
    Code:
       0: aload_0
       1: getstatic     #7                  // Field DISPOSED:Lio/reactivex/rxjava3/internal/disposables/DisposableHelper;
       4: if_acmpne     11
       7: iconst_1
       8: goto          12
      11: iconst_0
      12: ireturn

  public static boolean set(java.util.concurrent.atomic.AtomicReference<io.reactivex.rxjava3.disposables.Disposable>, io.reactivex.rxjava3.disposables.Disposable);
    Code:
       0: aload_0
       1: invokevirtual #8                  // Method java/util/concurrent/atomic/AtomicReference.get:()Ljava/lang/Object;
       4: checkcast     #9                  // class io/reactivex/rxjava3/disposables/Disposable
       7: astore_2
       8: aload_2
       9: getstatic     #7                  // Field DISPOSED:Lio/reactivex/rxjava3/internal/disposables/DisposableHelper;
      12: if_acmpne     27
      15: aload_1
      16: ifnull        25
      19: aload_1
      20: invokeinterface #10,  1           // InterfaceMethod io/reactivex/rxjava3/disposables/Disposable.dispose:()V
      25: iconst_0
      26: ireturn
      27: aload_0
      28: aload_2
      29: aload_1
      30: invokevirtual #11                 // Method java/util/concurrent/atomic/AtomicReference.compareAndSet:(Ljava/lang/Object;Ljava/lang/Object;)Z
      33: ifeq          48
      36: aload_2
      37: ifnull        46
      40: aload_2
      41: invokeinterface #10,  1           // InterfaceMethod io/reactivex/rxjava3/disposables/Disposable.dispose:()V
      46: iconst_1
      47: ireturn
      48: goto          0

  public static boolean setOnce(java.util.concurrent.atomic.AtomicReference<io.reactivex.rxjava3.disposables.Disposable>, io.reactivex.rxjava3.disposables.Disposable);
    Code:
       0: aload_1
       1: ldc           #12                 // String d is null
       3: invokestatic  #13                 // Method java/util/Objects.requireNonNull:(Ljava/lang/Object;Ljava/lang/String;)Ljava/lang/Object;
       6: pop
       7: aload_0
       8: aconst_null
       9: aload_1
      10: invokevirtual #11                 // Method java/util/concurrent/atomic/AtomicReference.compareAndSet:(Ljava/lang/Object;Ljava/lang/Object;)Z
      13: ifne          37
      16: aload_1
      17: invokeinterface #10,  1           // InterfaceMethod io/reactivex/rxjava3/disposables/Disposable.dispose:()V
      22: aload_0
      23: invokevirtual #8                  // Method java/util/concurrent/atomic/AtomicReference.get:()Ljava/lang/Object;
      26: getstatic     #7                  // Field DISPOSED:Lio/reactivex/rxjava3/internal/disposables/DisposableHelper;
      29: if_acmpeq     35
      32: invokestatic  #14                 // Method reportDisposableSet:()V
      35: iconst_0
      36: ireturn
      37: iconst_1
      38: ireturn

  public static boolean replace(java.util.concurrent.atomic.AtomicReference<io.reactivex.rxjava3.disposables.Disposable>, io.reactivex.rxjava3.disposables.Disposable);
    Code:
       0: aload_0
       1: invokevirtual #8                  // Method java/util/concurrent/atomic/AtomicReference.get:()Ljava/lang/Object;
       4: checkcast     #9                  // class io/reactivex/rxjava3/disposables/Disposable
       7: astore_2
       8: aload_2
       9: getstatic     #7                  // Field DISPOSED:Lio/reactivex/rxjava3/internal/disposables/DisposableHelper;
      12: if_acmpne     27
      15: aload_1
      16: ifnull        25
      19: aload_1
      20: invokeinterface #10,  1           // InterfaceMethod io/reactivex/rxjava3/disposables/Disposable.dispose:()V
      25: iconst_0
      26: ireturn
      27: aload_0
      28: aload_2
      29: aload_1
      30: invokevirtual #11                 // Method java/util/concurrent/atomic/AtomicReference.compareAndSet:(Ljava/lang/Object;Ljava/lang/Object;)Z
      33: ifeq          38
      36: iconst_1
      37: ireturn
      38: goto          0

  public static boolean dispose(java.util.concurrent.atomic.AtomicReference<io.reactivex.rxjava3.disposables.Disposable>);
    Code:
       0: aload_0
       1: invokevirtual #8                  // Method java/util/concurrent/atomic/AtomicReference.get:()Ljava/lang/Object;
       4: checkcast     #9                  // class io/reactivex/rxjava3/disposables/Disposable
       7: astore_1
       8: getstatic     #7                  // Field DISPOSED:Lio/reactivex/rxjava3/internal/disposables/DisposableHelper;
      11: astore_2
      12: aload_1
      13: aload_2
      14: if_acmpeq     43
      17: aload_0
      18: aload_2
      19: invokevirtual #15                 // Method java/util/concurrent/atomic/AtomicReference.getAndSet:(Ljava/lang/Object;)Ljava/lang/Object;
      22: checkcast     #9                  // class io/reactivex/rxjava3/disposables/Disposable
      25: astore_1
      26: aload_1
      27: aload_2
      28: if_acmpeq     43
      31: aload_1
      32: ifnull        41
      35: aload_1
      36: invokeinterface #10,  1           // InterfaceMethod io/reactivex/rxjava3/disposables/Disposable.dispose:()V
      41: iconst_1
      42: ireturn
      43: iconst_0
      44: ireturn

  public static boolean validate(io.reactivex.rxjava3.disposables.Disposable, io.reactivex.rxjava3.disposables.Disposable);
    Code:
       0: aload_1
       1: ifnonnull     18
       4: new           #16                 // class java/lang/NullPointerException
       7: dup
       8: ldc           #17                 // String next is null
      10: invokespecial #18                 // Method java/lang/NullPointerException."<init>":(Ljava/lang/String;)V
      13: invokestatic  #19                 // Method io/reactivex/rxjava3/plugins/RxJavaPlugins.onError:(Ljava/lang/Throwable;)V
      16: iconst_0
      17: ireturn
      18: aload_0
      19: ifnull        33
      22: aload_1
      23: invokeinterface #10,  1           // InterfaceMethod io/reactivex/rxjava3/disposables/Disposable.dispose:()V
      28: invokestatic  #14                 // Method reportDisposableSet:()V
      31: iconst_0
      32: ireturn
      33: iconst_1
      34: ireturn

  public static void reportDisposableSet();
    Code:
       0: new           #20                 // class io/reactivex/rxjava3/exceptions/ProtocolViolationException
       3: dup
       4: ldc           #21                 // String Disposable already set!
       6: invokespecial #22                 // Method io/reactivex/rxjava3/exceptions/ProtocolViolationException."<init>":(Ljava/lang/String;)V
       9: invokestatic  #19                 // Method io/reactivex/rxjava3/plugins/RxJavaPlugins.onError:(Ljava/lang/Throwable;)V
      12: return

  public static boolean trySet(java.util.concurrent.atomic.AtomicReference<io.reactivex.rxjava3.disposables.Disposable>, io.reactivex.rxjava3.disposables.Disposable);
    Code:
       0: aload_0
       1: aconst_null
       2: aload_1
       3: invokevirtual #11                 // Method java/util/concurrent/atomic/AtomicReference.compareAndSet:(Ljava/lang/Object;Ljava/lang/Object;)Z
       6: ifne          27
       9: aload_0
      10: invokevirtual #8                  // Method java/util/concurrent/atomic/AtomicReference.get:()Ljava/lang/Object;
      13: getstatic     #7                  // Field DISPOSED:Lio/reactivex/rxjava3/internal/disposables/DisposableHelper;
      16: if_acmpne     25
      19: aload_1
      20: invokeinterface #10,  1           // InterfaceMethod io/reactivex/rxjava3/disposables/Disposable.dispose:()V
      25: iconst_0
      26: ireturn
      27: iconst_1
      28: ireturn

  public void dispose();
    Code:
       0: return

  public boolean isDisposed();
    Code:
       0: iconst_1
       1: ireturn

  static {};
    Code:
       0: new           #4                  // class io/reactivex/rxjava3/internal/disposables/DisposableHelper
       3: dup
       4: ldc           #23                 // String DISPOSED
       6: iconst_0
       7: invokespecial #24                 // Method "<init>":(Ljava/lang/String;I)V
      10: putstatic     #7                  // Field DISPOSED:Lio/reactivex/rxjava3/internal/disposables/DisposableHelper;
      13: iconst_1
      14: anewarray     #4                  // class io/reactivex/rxjava3/internal/disposables/DisposableHelper
      17: dup
      18: iconst_0
      19: getstatic     #7                  // Field DISPOSED:Lio/reactivex/rxjava3/internal/disposables/DisposableHelper;
      22: aastore
      23: putstatic     #1                  // Field $VALUES:[Lio/reactivex/rxjava3/internal/disposables/DisposableHelper;
      26: return
}
