Compiled from "EmptyDisposable.java"
public final class io.reactivex.rxjava3.internal.disposables.EmptyDisposable extends java.lang.Enum<io.reactivex.rxjava3.internal.disposables.EmptyDisposable> implements io.reactivex.rxjava3.operators.QueueDisposable<java.lang.Object> {
  public static final io.reactivex.rxjava3.internal.disposables.EmptyDisposable INSTANCE;

  public static final io.reactivex.rxjava3.internal.disposables.EmptyDisposable NEVER;

  private static final io.reactivex.rxjava3.internal.disposables.EmptyDisposable[] $VALUES;

  public static io.reactivex.rxjava3.internal.disposables.EmptyDisposable[] values();
    Code:
       0: getstatic     #1                  // Field $VALUES:[Lio/reactivex/rxjava3/internal/disposables/EmptyDisposable;
       3: invokevirtual #2                  // Method "[Lio/reactivex/rxjava3/internal/disposables/EmptyDisposable;".clone:()Ljava/lang/Object;
       6: checkcast     #3                  // class "[Lio/reactivex/rxjava3/internal/disposables/EmptyDisposable;"
       9: areturn

  public static io.reactivex.rxjava3.internal.disposables.EmptyDisposable valueOf(java.lang.String);
    Code:
       0: ldc           #4                  // class io/reactivex/rxjava3/internal/disposables/EmptyDisposable
       2: aload_0
       3: invokestatic  #5                  // Method java/lang/Enum.valueOf:(Ljava/lang/Class;Ljava/lang/String;)Ljava/lang/Enum;
       6: checkcast     #4                  // class io/reactivex/rxjava3/internal/disposables/EmptyDisposable
       9: areturn

  private io.reactivex.rxjava3.internal.disposables.EmptyDisposable();
    Code:
       0: aload_0
       1: aload_1
       2: iload_2
       3: invokespecial #6                  // Method java/lang/Enum."<init>":(Ljava/lang/String;I)V
       6: return

  public void dispose();
    Code:
       0: return

  public boolean isDisposed();
    Code:
       0: aload_0
       1: getstatic     #7                  // Field INSTANCE:Lio/reactivex/rxjava3/internal/disposables/EmptyDisposable;
       4: if_acmpne     11
       7: iconst_1
       8: goto          12
      11: iconst_0
      12: ireturn

  public static void complete(io.reactivex.rxjava3.core.Observer<?>);
    Code:
       0: aload_0
       1: getstatic     #7                  // Field INSTANCE:Lio/reactivex/rxjava3/internal/disposables/EmptyDisposable;
       4: invokeinterface #8,  2            // InterfaceMethod io/reactivex/rxjava3/core/Observer.onSubscribe:(Lio/reactivex/rxjava3/disposables/Disposable;)V
       9: aload_0
      10: invokeinterface #9,  1            // InterfaceMethod io/reactivex/rxjava3/core/Observer.onComplete:()V
      15: return

  public static void complete(io.reactivex.rxjava3.core.MaybeObserver<?>);
    Code:
       0: aload_0
       1: getstatic     #7                  // Field INSTANCE:Lio/reactivex/rxjava3/internal/disposables/EmptyDisposable;
       4: invokeinterface #10,  2           // InterfaceMethod io/reactivex/rxjava3/core/MaybeObserver.onSubscribe:(Lio/reactivex/rxjava3/disposables/Disposable;)V
       9: aload_0
      10: invokeinterface #11,  1           // InterfaceMethod io/reactivex/rxjava3/core/MaybeObserver.onComplete:()V
      15: return

  public static void error(java.lang.Throwable, io.reactivex.rxjava3.core.Observer<?>);
    Code:
       0: aload_1
       1: getstatic     #7                  // Field INSTANCE:Lio/reactivex/rxjava3/internal/disposables/EmptyDisposable;
       4: invokeinterface #8,  2            // InterfaceMethod io/reactivex/rxjava3/core/Observer.onSubscribe:(Lio/reactivex/rxjava3/disposables/Disposable;)V
       9: aload_1
      10: aload_0
      11: invokeinterface #12,  2           // InterfaceMethod io/reactivex/rxjava3/core/Observer.onError:(Ljava/lang/Throwable;)V
      16: return

  public static void complete(io.reactivex.rxjava3.core.CompletableObserver);
    Code:
       0: aload_0
       1: getstatic     #7                  // Field INSTANCE:Lio/reactivex/rxjava3/internal/disposables/EmptyDisposable;
       4: invokeinterface #13,  2           // InterfaceMethod io/reactivex/rxjava3/core/CompletableObserver.onSubscribe:(Lio/reactivex/rxjava3/disposables/Disposable;)V
       9: aload_0
      10: invokeinterface #14,  1           // InterfaceMethod io/reactivex/rxjava3/core/CompletableObserver.onComplete:()V
      15: return

  public static void error(java.lang.Throwable, io.reactivex.rxjava3.core.CompletableObserver);
    Code:
       0: aload_1
       1: getstatic     #7                  // Field INSTANCE:Lio/reactivex/rxjava3/internal/disposables/EmptyDisposable;
       4: invokeinterface #13,  2           // InterfaceMethod io/reactivex/rxjava3/core/CompletableObserver.onSubscribe:(Lio/reactivex/rxjava3/disposables/Disposable;)V
       9: aload_1
      10: aload_0
      11: invokeinterface #15,  2           // InterfaceMethod io/reactivex/rxjava3/core/CompletableObserver.onError:(Ljava/lang/Throwable;)V
      16: return

  public static void error(java.lang.Throwable, io.reactivex.rxjava3.core.SingleObserver<?>);
    Code:
       0: aload_1
       1: getstatic     #7                  // Field INSTANCE:Lio/reactivex/rxjava3/internal/disposables/EmptyDisposable;
       4: invokeinterface #16,  2           // InterfaceMethod io/reactivex/rxjava3/core/SingleObserver.onSubscribe:(Lio/reactivex/rxjava3/disposables/Disposable;)V
       9: aload_1
      10: aload_0
      11: invokeinterface #17,  2           // InterfaceMethod io/reactivex/rxjava3/core/SingleObserver.onError:(Ljava/lang/Throwable;)V
      16: return

  public static void error(java.lang.Throwable, io.reactivex.rxjava3.core.MaybeObserver<?>);
    Code:
       0: aload_1
       1: getstatic     #7                  // Field INSTANCE:Lio/reactivex/rxjava3/internal/disposables/EmptyDisposable;
       4: invokeinterface #10,  2           // InterfaceMethod io/reactivex/rxjava3/core/MaybeObserver.onSubscribe:(Lio/reactivex/rxjava3/disposables/Disposable;)V
       9: aload_1
      10: aload_0
      11: invokeinterface #18,  2           // InterfaceMethod io/reactivex/rxjava3/core/MaybeObserver.onError:(Ljava/lang/Throwable;)V
      16: return

  public boolean offer(java.lang.Object);
    Code:
       0: new           #19                 // class java/lang/UnsupportedOperationException
       3: dup
       4: ldc           #20                 // String Should not be called!
       6: invokespecial #21                 // Method java/lang/UnsupportedOperationException."<init>":(Ljava/lang/String;)V
       9: athrow

  public boolean offer(java.lang.Object, java.lang.Object);
    Code:
       0: new           #19                 // class java/lang/UnsupportedOperationException
       3: dup
       4: ldc           #20                 // String Should not be called!
       6: invokespecial #21                 // Method java/lang/UnsupportedOperationException."<init>":(Ljava/lang/String;)V
       9: athrow

  public java.lang.Object poll();
    Code:
       0: aconst_null
       1: areturn

  public boolean isEmpty();
    Code:
       0: iconst_1
       1: ireturn

  public void clear();
    Code:
       0: return

  public int requestFusion(int);
    Code:
       0: iload_1
       1: iconst_2
       2: iand
       3: ireturn

  static {};
    Code:
       0: new           #4                  // class io/reactivex/rxjava3/internal/disposables/EmptyDisposable
       3: dup
       4: ldc           #23                 // String INSTANCE
       6: iconst_0
       7: invokespecial #24                 // Method "<init>":(Ljava/lang/String;I)V
      10: putstatic     #7                  // Field INSTANCE:Lio/reactivex/rxjava3/internal/disposables/EmptyDisposable;
      13: new           #4                  // class io/reactivex/rxjava3/internal/disposables/EmptyDisposable
      16: dup
      17: ldc           #25                 // String NEVER
      19: iconst_1
      20: invokespecial #24                 // Method "<init>":(Ljava/lang/String;I)V
      23: putstatic     #26                 // Field NEVER:Lio/reactivex/rxjava3/internal/disposables/EmptyDisposable;
      26: iconst_2
      27: anewarray     #4                  // class io/reactivex/rxjava3/internal/disposables/EmptyDisposable
      30: dup
      31: iconst_0
      32: getstatic     #7                  // Field INSTANCE:Lio/reactivex/rxjava3/internal/disposables/EmptyDisposable;
      35: aastore
      36: dup
      37: iconst_1
      38: getstatic     #26                 // Field NEVER:Lio/reactivex/rxjava3/internal/disposables/EmptyDisposable;
      41: aastore
      42: putstatic     #1                  // Field $VALUES:[Lio/reactivex/rxjava3/internal/disposables/EmptyDisposable;
      45: return
}
