Compiled from "SequentialDisposable.java"
public final class io.reactivex.rxjava3.internal.disposables.SequentialDisposable extends java.util.concurrent.atomic.AtomicReference<io.reactivex.rxjava3.disposables.Disposable> implements io.reactivex.rxjava3.disposables.Disposable {
  private static final long serialVersionUID;

  public io.reactivex.rxjava3.internal.disposables.SequentialDisposable();
    Code:
       0: aload_0
       1: invokespecial #1                  // Method java/util/concurrent/atomic/AtomicReference."<init>":()V
       4: return

  public io.reactivex.rxjava3.internal.disposables.SequentialDisposable(io.reactivex.rxjava3.disposables.Disposable);
    Code:
       0: aload_0
       1: invokespecial #1                  // Method java/util/concurrent/atomic/AtomicReference."<init>":()V
       4: aload_0
       5: aload_1
       6: invokevirtual #2                  // Method lazySet:(Ljava/lang/Object;)V
       9: return

  public boolean update(io.reactivex.rxjava3.disposables.Disposable);
    Code:
       0: aload_0
       1: aload_1
       2: invokestatic  #3                  // Method io/reactivex/rxjava3/internal/disposables/DisposableHelper.set:(Ljava/util/concurrent/atomic/AtomicReference;Lio/reactivex/rxjava3/disposables/Disposable;)Z
       5: ireturn

  public boolean replace(io.reactivex.rxjava3.disposables.Disposable);
    Code:
       0: aload_0
       1: aload_1
       2: invokestatic  #4                  // Method io/reactivex/rxjava3/internal/disposables/DisposableHelper.replace:(Ljava/util/concurrent/atomic/AtomicReference;Lio/reactivex/rxjava3/disposables/Disposable;)Z
       5: ireturn

  public void dispose();
    Code:
       0: aload_0
       1: invokestatic  #5                  // Method io/reactivex/rxjava3/internal/disposables/DisposableHelper.dispose:(Ljava/util/concurrent/atomic/AtomicReference;)Z
       4: pop
       5: return

  public boolean isDisposed();
    Code:
       0: aload_0
       1: invokevirtual #6                  // Method get:()Ljava/lang/Object;
       4: checkcast     #7                  // class io/reactivex/rxjava3/disposables/Disposable
       7: invokestatic  #8                  // Method io/reactivex/rxjava3/internal/disposables/DisposableHelper.isDisposed:(Lio/reactivex/rxjava3/disposables/Disposable;)Z
      10: ireturn
}
