Compiled from "CacheListener.java"
public class org.apache.dubbo.configcenter.support.zookeeper.CacheListener {
  private final java.util.concurrent.ConcurrentMap<java.lang.String, org.apache.dubbo.configcenter.support.zookeeper.ZookeeperDataListener> pathKeyListeners;

  public org.apache.dubbo.configcenter.support.zookeeper.CacheListener();
    Code:
       0: aload_0
       1: invokespecial #1                  // Method java/lang/Object."<init>":()V
       4: aload_0
       5: new           #2                  // class java/util/concurrent/ConcurrentHashMap
       8: dup
       9: invokespecial #3                  // Method java/util/concurrent/ConcurrentHashMap."<init>":()V
      12: putfield      #4                  // Field pathKeyListeners:Ljava/util/concurrent/ConcurrentMap;
      15: return

  public org.apache.dubbo.configcenter.support.zookeeper.ZookeeperDataListener addListener(java.lang.String, org.apache.dubbo.common.config.configcenter.ConfigurationListener, java.lang.String, java.lang.String, org.apache.dubbo.rpc.model.ApplicationModel);
    Code:
       0: aload_0
       1: getfield      #4                  // Field pathKeyListeners:Ljava/util/concurrent/ConcurrentMap;
       4: aload_1
       5: aload_3
       6: aload         4
       8: aload         5
      10: invokedynamic #5,  0              // InvokeDynamic #0:apply:(Ljava/lang/String;Ljava/lang/String;Lorg/apache/dubbo/rpc/model/ApplicationModel;)Ljava/util/function/Function;
      15: invokestatic  #6                  // Method org/apache/dubbo/common/utils/ConcurrentHashMapUtils.computeIfAbsent:(Ljava/util/concurrent/ConcurrentMap;Ljava/lang/Object;Ljava/util/function/Function;)Ljava/lang/Object;
      18: checkcast     #7                  // class org/apache/dubbo/configcenter/support/zookeeper/ZookeeperDataListener
      21: astore        6
      23: aload         6
      25: aload_2
      26: invokevirtual #8                  // Method org/apache/dubbo/configcenter/support/zookeeper/ZookeeperDataListener.addListener:(Lorg/apache/dubbo/common/config/configcenter/ConfigurationListener;)V
      29: aload         6
      31: areturn

  public org.apache.dubbo.configcenter.support.zookeeper.ZookeeperDataListener removeListener(java.lang.String, org.apache.dubbo.common.config.configcenter.ConfigurationListener);
    Code:
       0: aload_0
       1: getfield      #4                  // Field pathKeyListeners:Ljava/util/concurrent/ConcurrentMap;
       4: aload_1
       5: invokeinterface #9,  2            // InterfaceMethod java/util/concurrent/ConcurrentMap.get:(Ljava/lang/Object;)Ljava/lang/Object;
      10: checkcast     #7                  // class org/apache/dubbo/configcenter/support/zookeeper/ZookeeperDataListener
      13: astore_3
      14: aload_3
      15: ifnull        44
      18: aload_3
      19: aload_2
      20: invokevirtual #10                 // Method org/apache/dubbo/configcenter/support/zookeeper/ZookeeperDataListener.removeListener:(Lorg/apache/dubbo/common/config/configcenter/ConfigurationListener;)V
      23: aload_3
      24: invokevirtual #11                 // Method org/apache/dubbo/configcenter/support/zookeeper/ZookeeperDataListener.getListeners:()Ljava/util/Set;
      27: invokestatic  #12                 // Method org/apache/dubbo/common/utils/CollectionUtils.isEmpty:(Ljava/util/Collection;)Z
      30: ifeq          44
      33: aload_0
      34: getfield      #4                  // Field pathKeyListeners:Ljava/util/concurrent/ConcurrentMap;
      37: aload_1
      38: invokeinterface #13,  2           // InterfaceMethod java/util/concurrent/ConcurrentMap.remove:(Ljava/lang/Object;)Ljava/lang/Object;
      43: pop
      44: aload_3
      45: areturn

  public org.apache.dubbo.configcenter.support.zookeeper.ZookeeperDataListener getCachedListener(java.lang.String);
    Code:
       0: aload_0
       1: getfield      #4                  // Field pathKeyListeners:Ljava/util/concurrent/ConcurrentMap;
       4: aload_1
       5: invokeinterface #9,  2            // InterfaceMethod java/util/concurrent/ConcurrentMap.get:(Ljava/lang/Object;)Ljava/lang/Object;
      10: checkcast     #7                  // class org/apache/dubbo/configcenter/support/zookeeper/ZookeeperDataListener
      13: areturn

  public java.util.Map<java.lang.String, org.apache.dubbo.configcenter.support.zookeeper.ZookeeperDataListener> getPathKeyListeners();
    Code:
       0: aload_0
       1: getfield      #4                  // Field pathKeyListeners:Ljava/util/concurrent/ConcurrentMap;
       4: areturn

  public void clear();
    Code:
       0: aload_0
       1: getfield      #4                  // Field pathKeyListeners:Ljava/util/concurrent/ConcurrentMap;
       4: invokeinterface #14,  1           // InterfaceMethod java/util/concurrent/ConcurrentMap.clear:()V
       9: return

  private static org.apache.dubbo.configcenter.support.zookeeper.ZookeeperDataListener lambda$addListener$0(java.lang.String, java.lang.String, org.apache.dubbo.rpc.model.ApplicationModel, java.lang.String);
    Code:
       0: new           #7                  // class org/apache/dubbo/configcenter/support/zookeeper/ZookeeperDataListener
       3: dup
       4: aload_3
       5: aload_0
       6: aload_1
       7: aload_2
       8: invokespecial #15                 // Method org/apache/dubbo/configcenter/support/zookeeper/ZookeeperDataListener."<init>":(Ljava/lang/String;Ljava/lang/String;Ljava/lang/String;Lorg/apache/dubbo/rpc/model/ApplicationModel;)V
      11: areturn
}
