Compiled from "ZookeeperDataListener.java"
public class org.apache.dubbo.configcenter.support.zookeeper.ZookeeperDataListener implements org.apache.dubbo.remoting.zookeeper.DataListener {
  private java.lang.String path;

  private java.lang.String key;

  private java.lang.String group;

  private java.util.Set<org.apache.dubbo.common.config.configcenter.ConfigurationListener> listeners;

  private org.apache.dubbo.rpc.model.ApplicationModel applicationModel;

  public org.apache.dubbo.configcenter.support.zookeeper.ZookeeperDataListener(java.lang.String, java.lang.String, java.lang.String, org.apache.dubbo.rpc.model.ApplicationModel);
    Code:
       0: aload_0
       1: invokespecial #2                  // Method java/lang/Object."<init>":()V
       4: aload_0
       5: aload_1
       6: putfield      #3                  // Field path:Ljava/lang/String;
       9: aload_0
      10: aload_2
      11: putfield      #4                  // Field key:Ljava/lang/String;
      14: aload_0
      15: aload_3
      16: putfield      #5                  // Field group:Ljava/lang/String;
      19: aload_0
      20: new           #6                  // class java/util/concurrent/CopyOnWriteArraySet
      23: dup
      24: invokespecial #7                  // Method java/util/concurrent/CopyOnWriteArraySet."<init>":()V
      27: putfield      #8                  // Field listeners:Ljava/util/Set;
      30: aload_0
      31: aload         4
      33: putfield      #9                  // Field applicationModel:Lorg/apache/dubbo/rpc/model/ApplicationModel;
      36: return

  public void addListener(org.apache.dubbo.common.config.configcenter.ConfigurationListener);
    Code:
       0: aload_0
       1: getfield      #8                  // Field listeners:Ljava/util/Set;
       4: aload_1
       5: invokeinterface #10,  2           // InterfaceMethod java/util/Set.add:(Ljava/lang/Object;)Z
      10: pop
      11: return

  public void removeListener(org.apache.dubbo.common.config.configcenter.ConfigurationListener);
    Code:
       0: aload_0
       1: getfield      #8                  // Field listeners:Ljava/util/Set;
       4: aload_1
       5: invokeinterface #11,  2           // InterfaceMethod java/util/Set.remove:(Ljava/lang/Object;)Z
      10: pop
      11: return

  public java.util.Set<org.apache.dubbo.common.config.configcenter.ConfigurationListener> getListeners();
    Code:
       0: aload_0
       1: getfield      #8                  // Field listeners:Ljava/util/Set;
       4: areturn

  public void dataChanged(java.lang.String, java.lang.Object, org.apache.dubbo.remoting.zookeeper.EventType);
    Code:
       0: aload_0
       1: getfield      #3                  // Field path:Ljava/lang/String;
       4: aload_1
       5: invokevirtual #12                 // Method java/lang/String.equals:(Ljava/lang/Object;)Z
       8: ifne          12
      11: return
      12: getstatic     #13                 // Field org/apache/dubbo/remoting/zookeeper/EventType.NodeCreated:Lorg/apache/dubbo/remoting/zookeeper/EventType;
      15: aload_3
      16: invokevirtual #14                 // Method org/apache/dubbo/remoting/zookeeper/EventType.equals:(Ljava/lang/Object;)Z
      19: ifeq          30
      22: getstatic     #15                 // Field org/apache/dubbo/common/config/configcenter/ConfigChangeType.ADDED:Lorg/apache/dubbo/common/config/configcenter/ConfigChangeType;
      25: astore        4
      27: goto          47
      30: aload_2
      31: ifnonnull     42
      34: getstatic     #16                 // Field org/apache/dubbo/common/config/configcenter/ConfigChangeType.DELETED:Lorg/apache/dubbo/common/config/configcenter/ConfigChangeType;
      37: astore        4
      39: goto          47
      42: getstatic     #17                 // Field org/apache/dubbo/common/config/configcenter/ConfigChangeType.MODIFIED:Lorg/apache/dubbo/common/config/configcenter/ConfigChangeType;
      45: astore        4
      47: new           #18                 // class org/apache/dubbo/common/config/configcenter/ConfigChangedEvent
      50: dup
      51: aload_0
      52: getfield      #4                  // Field key:Ljava/lang/String;
      55: aload_0
      56: getfield      #5                  // Field group:Ljava/lang/String;
      59: aload_2
      60: checkcast     #19                 // class java/lang/String
      63: aload         4
      65: invokespecial #20                 // Method org/apache/dubbo/common/config/configcenter/ConfigChangedEvent."<init>":(Ljava/lang/String;Ljava/lang/String;Ljava/lang/String;Lorg/apache/dubbo/common/config/configcenter/ConfigChangeType;)V
      68: astore        5
      70: aload_0
      71: getfield      #8                  // Field listeners:Ljava/util/Set;
      74: invokestatic  #21                 // Method org/apache/dubbo/common/utils/CollectionUtils.isNotEmpty:(Ljava/util/Collection;)Z
      77: ifeq          96
      80: aload_0
      81: getfield      #8                  // Field listeners:Ljava/util/Set;
      84: aload         5
      86: invokedynamic #22,  0             // InvokeDynamic #0:accept:(Lorg/apache/dubbo/common/config/configcenter/ConfigChangedEvent;)Ljava/util/function/Consumer;
      91: invokeinterface #23,  2           // InterfaceMethod java/util/Set.forEach:(Ljava/util/function/Consumer;)V
      96: aload_0
      97: getfield      #9                  // Field applicationModel:Lorg/apache/dubbo/rpc/model/ApplicationModel;
     100: aload         5
     102: invokevirtual #24                 // Method org/apache/dubbo/common/config/configcenter/ConfigChangedEvent.getKey:()Ljava/lang/String;
     105: aload         5
     107: invokevirtual #25                 // Method org/apache/dubbo/common/config/configcenter/ConfigChangedEvent.getGroup:()Ljava/lang/String;
     110: ldc           #27                 // String zookeeper
     112: getstatic     #15                 // Field org/apache/dubbo/common/config/configcenter/ConfigChangeType.ADDED:Lorg/apache/dubbo/common/config/configcenter/ConfigChangeType;
     115: invokevirtual #28                 // Method org/apache/dubbo/common/config/configcenter/ConfigChangeType.name:()Ljava/lang/String;
     118: iconst_1
     119: invokestatic  #29                 // Method org/apache/dubbo/metrics/config/event/ConfigCenterEvent.toChangeEvent:(Lorg/apache/dubbo/rpc/model/ApplicationModel;Ljava/lang/String;Ljava/lang/String;Ljava/lang/String;Ljava/lang/String;I)Lorg/apache/dubbo/metrics/config/event/ConfigCenterEvent;
     122: invokestatic  #30                 // Method org/apache/dubbo/metrics/event/MetricsEventBus.publish:(Lorg/apache/dubbo/metrics/event/MetricsEvent;)V
     125: return

  private static void lambda$dataChanged$0(org.apache.dubbo.common.config.configcenter.ConfigChangedEvent, org.apache.dubbo.common.config.configcenter.ConfigurationListener);
    Code:
       0: aload_1
       1: aload_0
       2: invokeinterface #31,  2           // InterfaceMethod org/apache/dubbo/common/config/configcenter/ConfigurationListener.process:(Lorg/apache/dubbo/common/config/configcenter/ConfigChangedEvent;)V
       7: return
}
