Compiled from "ZookeeperDynamicConfigurationFactory.java"
public class org.apache.dubbo.configcenter.support.zookeeper.ZookeeperDynamicConfigurationFactory extends org.apache.dubbo.common.config.configcenter.AbstractDynamicConfigurationFactory {
  private final org.apache.dubbo.remoting.zookeeper.ZookeeperTransporter zookeeperTransporter;

  private final org.apache.dubbo.rpc.model.ApplicationModel applicationModel;

  public org.apache.dubbo.configcenter.support.zookeeper.ZookeeperDynamicConfigurationFactory(org.apache.dubbo.rpc.model.ApplicationModel);
    Code:
       0: aload_0
       1: invokespecial #1                  // Method org/apache/dubbo/common/config/configcenter/AbstractDynamicConfigurationFactory."<init>":()V
       4: aload_0
       5: aload_1
       6: putfield      #2                  // Field applicationModel:Lorg/apache/dubbo/rpc/model/ApplicationModel;
       9: aload_0
      10: aload_1
      11: invokestatic  #3                  // InterfaceMethod org/apache/dubbo/remoting/zookeeper/ZookeeperTransporter.getExtension:(Lorg/apache/dubbo/rpc/model/ApplicationModel;)Lorg/apache/dubbo/remoting/zookeeper/ZookeeperTransporter;
      14: putfield      #4                  // Field zookeeperTransporter:Lorg/apache/dubbo/remoting/zookeeper/ZookeeperTransporter;
      17: return

  protected org.apache.dubbo.common.config.configcenter.DynamicConfiguration createDynamicConfiguration(org.apache.dubbo.common.URL);
    Code:
       0: new           #5                  // class org/apache/dubbo/configcenter/support/zookeeper/ZookeeperDynamicConfiguration
       3: dup
       4: aload_1
       5: aload_0
       6: getfield      #4                  // Field zookeeperTransporter:Lorg/apache/dubbo/remoting/zookeeper/ZookeeperTransporter;
       9: aload_0
      10: getfield      #2                  // Field applicationModel:Lorg/apache/dubbo/rpc/model/ApplicationModel;
      13: invokespecial #6                  // Method org/apache/dubbo/configcenter/support/zookeeper/ZookeeperDynamicConfiguration."<init>":(Lorg/apache/dubbo/common/URL;Lorg/apache/dubbo/remoting/zookeeper/ZookeeperTransporter;Lorg/apache/dubbo/rpc/model/ApplicationModel;)V
      16: areturn
}
