Compiled from "ZookeeperDynamicConfiguration.java"
public class org.apache.dubbo.configcenter.support.zookeeper.ZookeeperDynamicConfiguration extends org.apache.dubbo.common.config.configcenter.TreePathDynamicConfiguration {
  private final java.util.concurrent.Executor executor;

  private org.apache.dubbo.remoting.zookeeper.ZookeeperClient zkClient;

  private final org.apache.dubbo.configcenter.support.zookeeper.CacheListener cacheListener;

  private static final int DEFAULT_ZK_EXECUTOR_THREADS_NUM;

  private static final int DEFAULT_QUEUE;

  private static final java.lang.Long THREAD_KEEP_ALIVE_TIME;

  private final org.apache.dubbo.rpc.model.ApplicationModel applicationModel;

  org.apache.dubbo.configcenter.support.zookeeper.ZookeeperDynamicConfiguration(org.apache.dubbo.common.URL, org.apache.dubbo.remoting.zookeeper.ZookeeperTransporter, org.apache.dubbo.rpc.model.ApplicationModel);
    Code:
       0: aload_0
       1: aload_1
       2: invokespecial #2                  // Method org/apache/dubbo/common/config/configcenter/TreePathDynamicConfiguration."<init>":(Lorg/apache/dubbo/common/URL;)V
       5: aload_0
       6: new           #3                  // class org/apache/dubbo/configcenter/support/zookeeper/CacheListener
       9: dup
      10: invokespecial #4                  // Method org/apache/dubbo/configcenter/support/zookeeper/CacheListener."<init>":()V
      13: putfield      #5                  // Field cacheListener:Lorg/apache/dubbo/configcenter/support/zookeeper/CacheListener;
      16: aload_0
      17: aload_3
      18: putfield      #6                  // Field applicationModel:Lorg/apache/dubbo/rpc/model/ApplicationModel;
      21: aload_0
      22: invokevirtual #7                  // Method java/lang/Object.getClass:()Ljava/lang/Class;
      25: invokevirtual #8                  // Method java/lang/Class.getSimpleName:()Ljava/lang/String;
      28: astore        4
      30: aload_0
      31: new           #9                  // class java/util/concurrent/ThreadPoolExecutor
      34: dup
      35: iconst_1
      36: iconst_1
      37: getstatic     #11                 // Field THREAD_KEEP_ALIVE_TIME:Ljava/lang/Long;
      40: invokevirtual #12                 // Method java/lang/Long.longValue:()J
      43: getstatic     #13                 // Field java/util/concurrent/TimeUnit.MILLISECONDS:Ljava/util/concurrent/TimeUnit;
      46: new           #14                 // class java/util/concurrent/LinkedBlockingQueue
      49: dup
      50: sipush        10000
      53: invokespecial #15                 // Method java/util/concurrent/LinkedBlockingQueue."<init>":(I)V
      56: new           #16                 // class org/apache/dubbo/common/utils/NamedThreadFactory
      59: dup
      60: aload         4
      62: iconst_1
      63: invokespecial #17                 // Method org/apache/dubbo/common/utils/NamedThreadFactory."<init>":(Ljava/lang/String;Z)V
      66: new           #18                 // class org/apache/dubbo/common/threadpool/support/AbortPolicyWithReport
      69: dup
      70: aload         4
      72: aload_1
      73: invokespecial #19                 // Method org/apache/dubbo/common/threadpool/support/AbortPolicyWithReport."<init>":(Ljava/lang/String;Lorg/apache/dubbo/common/URL;)V
      76: invokespecial #20                 // Method java/util/concurrent/ThreadPoolExecutor."<init>":(IIJLjava/util/concurrent/TimeUnit;Ljava/util/concurrent/BlockingQueue;Ljava/util/concurrent/ThreadFactory;Ljava/util/concurrent/RejectedExecutionHandler;)V
      79: putfield      #21                 // Field executor:Ljava/util/concurrent/Executor;
      82: aload_0
      83: aload_2
      84: aload_1
      85: invokeinterface #22,  2           // InterfaceMethod org/apache/dubbo/remoting/zookeeper/ZookeeperTransporter.connect:(Lorg/apache/dubbo/common/URL;)Lorg/apache/dubbo/remoting/zookeeper/ZookeeperClient;
      90: putfield      #23                 // Field zkClient:Lorg/apache/dubbo/remoting/zookeeper/ZookeeperClient;
      93: aload_0
      94: getfield      #23                 // Field zkClient:Lorg/apache/dubbo/remoting/zookeeper/ZookeeperClient;
      97: invokeinterface #24,  1           // InterfaceMethod org/apache/dubbo/remoting/zookeeper/ZookeeperClient.isConnected:()Z
     102: istore        5
     104: iload         5
     106: ifne          171
     109: new           #25                 // class java/lang/IllegalStateException
     112: dup
     113: new           #26                 // class java/lang/StringBuilder
     116: dup
     117: invokespecial #27                 // Method java/lang/StringBuilder."<init>":()V
     120: ldc           #28                 // String Failed to connect with zookeeper, pls check if url
     122: invokevirtual #29                 // Method java/lang/StringBuilder.append:(Ljava/lang/String;)Ljava/lang/StringBuilder;
     125: aload_1
     126: invokevirtual #30                 // Method java/lang/StringBuilder.append:(Ljava/lang/Object;)Ljava/lang/StringBuilder;
     129: ldc           #31                 // String  is correct.
     131: invokevirtual #29                 // Method java/lang/StringBuilder.append:(Ljava/lang/String;)Ljava/lang/StringBuilder;
     134: invokevirtual #32                 // Method java/lang/StringBuilder.toString:()Ljava/lang/String;
     137: invokespecial #33                 // Method java/lang/IllegalStateException."<init>":(Ljava/lang/String;)V
     140: astore        6
     142: aload_0
     143: getfield      #34                 // Field logger:Lorg/apache/dubbo/common/logger/ErrorTypeAwareLogger;
     146: ifnull        168
     149: aload_0
     150: getfield      #34                 // Field logger:Lorg/apache/dubbo/common/logger/ErrorTypeAwareLogger;
     153: ldc           #35                 // String 5-1
     155: ldc           #36                 // String configuration server offline
     157: ldc           #37                 // String
     159: ldc           #38                 // String Failed to connect with zookeeper
     161: aload         6
     163: invokeinterface #39,  6           // InterfaceMethod org/apache/dubbo/common/logger/ErrorTypeAwareLogger.error:(Ljava/lang/String;Ljava/lang/String;Ljava/lang/String;Ljava/lang/String;Ljava/lang/Throwable;)V
     168: aload         6
     170: athrow
     171: return

  public java.lang.String getInternalProperty(java.lang.String);
    Code:
       0: aload_0
       1: getfield      #23                 // Field zkClient:Lorg/apache/dubbo/remoting/zookeeper/ZookeeperClient;
       4: aload_0
       5: ldc           #37                 // String
       7: aload_1
       8: invokevirtual #40                 // Method buildPathKey:(Ljava/lang/String;Ljava/lang/String;)Ljava/lang/String;
      11: invokeinterface #41,  2           // InterfaceMethod org/apache/dubbo/remoting/zookeeper/ZookeeperClient.getContent:(Ljava/lang/String;)Ljava/lang/String;
      16: areturn

  protected void doClose() throws java.lang.Exception;
    Code:
       0: aload_0
       1: getfield      #5                  // Field cacheListener:Lorg/apache/dubbo/configcenter/support/zookeeper/CacheListener;
       4: invokevirtual #42                 // Method org/apache/dubbo/configcenter/support/zookeeper/CacheListener.getPathKeyListeners:()Ljava/util/Map;
       7: astore_1
       8: aload_1
       9: invokeinterface #43,  1           // InterfaceMethod java/util/Map.entrySet:()Ljava/util/Set;
      14: invokeinterface #44,  1           // InterfaceMethod java/util/Set.iterator:()Ljava/util/Iterator;
      19: astore_2
      20: aload_2
      21: invokeinterface #45,  1           // InterfaceMethod java/util/Iterator.hasNext:()Z
      26: ifeq          69
      29: aload_2
      30: invokeinterface #46,  1           // InterfaceMethod java/util/Iterator.next:()Ljava/lang/Object;
      35: checkcast     #47                 // class java/util/Map$Entry
      38: astore_3
      39: aload_0
      40: getfield      #23                 // Field zkClient:Lorg/apache/dubbo/remoting/zookeeper/ZookeeperClient;
      43: aload_3
      44: invokeinterface #48,  1           // InterfaceMethod java/util/Map$Entry.getKey:()Ljava/lang/Object;
      49: checkcast     #49                 // class java/lang/String
      52: aload_3
      53: invokeinterface #50,  1           // InterfaceMethod java/util/Map$Entry.getValue:()Ljava/lang/Object;
      58: checkcast     #51                 // class org/apache/dubbo/remoting/zookeeper/DataListener
      61: invokeinterface #52,  3           // InterfaceMethod org/apache/dubbo/remoting/zookeeper/ZookeeperClient.removeDataListener:(Ljava/lang/String;Lorg/apache/dubbo/remoting/zookeeper/DataListener;)V
      66: goto          20
      69: aload_0
      70: getfield      #5                  // Field cacheListener:Lorg/apache/dubbo/configcenter/support/zookeeper/CacheListener;
      73: invokevirtual #53                 // Method org/apache/dubbo/configcenter/support/zookeeper/CacheListener.clear:()V
      76: aload_0
      77: aconst_null
      78: putfield      #23                 // Field zkClient:Lorg/apache/dubbo/remoting/zookeeper/ZookeeperClient;
      81: return

  protected boolean doPublishConfig(java.lang.String, java.lang.String) throws java.lang.Exception;
    Code:
       0: aload_0
       1: getfield      #23                 // Field zkClient:Lorg/apache/dubbo/remoting/zookeeper/ZookeeperClient;
       4: aload_1
       5: aload_2
       6: iconst_0
       7: invokeinterface #54,  4           // InterfaceMethod org/apache/dubbo/remoting/zookeeper/ZookeeperClient.createOrUpdate:(Ljava/lang/String;Ljava/lang/String;Z)V
      12: iconst_1
      13: ireturn

  public boolean publishConfigCas(java.lang.String, java.lang.String, java.lang.String, java.lang.Object);
    Code:
       0: aload         4
       2: ifnull        23
       5: aload         4
       7: instanceof    #55                 // class org/apache/zookeeper/data/Stat
      10: ifne          23
      13: new           #56                 // class java/lang/IllegalArgumentException
      16: dup
      17: ldc           #57                 // String zookeeper publishConfigCas requires stat type ticket
      19: invokespecial #58                 // Method java/lang/IllegalArgumentException."<init>":(Ljava/lang/String;)V
      22: athrow
      23: aload_0
      24: aload_2
      25: aload_1
      26: invokevirtual #40                 // Method buildPathKey:(Ljava/lang/String;Ljava/lang/String;)Ljava/lang/String;
      29: astore        5
      31: aload_0
      32: getfield      #23                 // Field zkClient:Lorg/apache/dubbo/remoting/zookeeper/ZookeeperClient;
      35: aload         5
      37: aload_3
      38: iconst_0
      39: aload         4
      41: ifnonnull     48
      44: iconst_0
      45: goto          56
      48: aload         4
      50: checkcast     #55                 // class org/apache/zookeeper/data/Stat
      53: invokevirtual #59                 // Method org/apache/zookeeper/data/Stat.getVersion:()I
      56: invokestatic  #60                 // Method java/lang/Integer.valueOf:(I)Ljava/lang/Integer;
      59: invokeinterface #61,  5           // InterfaceMethod org/apache/dubbo/remoting/zookeeper/ZookeeperClient.createOrUpdate:(Ljava/lang/String;Ljava/lang/String;ZLjava/lang/Integer;)V
      64: iconst_1
      65: ireturn
      66: astore        5
      68: aload_0
      69: getfield      #34                 // Field logger:Lorg/apache/dubbo/common/logger/ErrorTypeAwareLogger;
      72: ldc           #63                 // String 1-35
      74: ldc           #37                 // String
      76: ldc           #37                 // String
      78: ldc           #64                 // String zookeeper publishConfigCas failed.
      80: aload         5
      82: invokeinterface #65,  6           // InterfaceMethod org/apache/dubbo/common/logger/ErrorTypeAwareLogger.warn:(Ljava/lang/String;Ljava/lang/String;Ljava/lang/String;Ljava/lang/String;Ljava/lang/Throwable;)V
      87: iconst_0
      88: ireturn
    Exception table:
       from    to  target type
           0    65    66   Class java/lang/Exception

  protected java.lang.String doGetConfig(java.lang.String) throws java.lang.Exception;
    Code:
       0: aload_0
       1: getfield      #23                 // Field zkClient:Lorg/apache/dubbo/remoting/zookeeper/ZookeeperClient;
       4: aload_1
       5: invokeinterface #41,  2           // InterfaceMethod org/apache/dubbo/remoting/zookeeper/ZookeeperClient.getContent:(Ljava/lang/String;)Ljava/lang/String;
      10: areturn

  public org.apache.dubbo.common.config.configcenter.ConfigItem getConfigItem(java.lang.String, java.lang.String);
    Code:
       0: aload_0
       1: aload_2
       2: aload_1
       3: invokevirtual #40                 // Method buildPathKey:(Ljava/lang/String;Ljava/lang/String;)Ljava/lang/String;
       6: astore_3
       7: aload_0
       8: getfield      #23                 // Field zkClient:Lorg/apache/dubbo/remoting/zookeeper/ZookeeperClient;
      11: aload_3
      12: invokeinterface #66,  2           // InterfaceMethod org/apache/dubbo/remoting/zookeeper/ZookeeperClient.getConfigItem:(Ljava/lang/String;)Lorg/apache/dubbo/common/config/configcenter/ConfigItem;
      17: areturn

  protected boolean doRemoveConfig(java.lang.String) throws java.lang.Exception;
    Code:
       0: aload_0
       1: getfield      #23                 // Field zkClient:Lorg/apache/dubbo/remoting/zookeeper/ZookeeperClient;
       4: aload_1
       5: invokeinterface #67,  2           // InterfaceMethod org/apache/dubbo/remoting/zookeeper/ZookeeperClient.delete:(Ljava/lang/String;)V
      10: iconst_1
      11: ireturn

  protected java.util.Collection<java.lang.String> doGetConfigKeys(java.lang.String);
    Code:
       0: aload_0
       1: getfield      #23                 // Field zkClient:Lorg/apache/dubbo/remoting/zookeeper/ZookeeperClient;
       4: aload_1
       5: invokeinterface #68,  2           // InterfaceMethod org/apache/dubbo/remoting/zookeeper/ZookeeperClient.getChildren:(Ljava/lang/String;)Ljava/util/List;
      10: areturn

  protected void doAddListener(java.lang.String, org.apache.dubbo.common.config.configcenter.ConfigurationListener, java.lang.String, java.lang.String);
    Code:
       0: aload_0
       1: getfield      #5                  // Field cacheListener:Lorg/apache/dubbo/configcenter/support/zookeeper/CacheListener;
       4: aload_1
       5: invokevirtual #69                 // Method org/apache/dubbo/configcenter/support/zookeeper/CacheListener.getCachedListener:(Ljava/lang/String;)Lorg/apache/dubbo/configcenter/support/zookeeper/ZookeeperDataListener;
       8: astore        5
      10: aload         5
      12: ifnull        24
      15: aload         5
      17: aload_2
      18: invokevirtual #70                 // Method org/apache/dubbo/configcenter/support/zookeeper/ZookeeperDataListener.addListener:(Lorg/apache/dubbo/common/config/configcenter/ConfigurationListener;)V
      21: goto          58
      24: aload_0
      25: getfield      #5                  // Field cacheListener:Lorg/apache/dubbo/configcenter/support/zookeeper/CacheListener;
      28: aload_1
      29: aload_2
      30: aload_3
      31: aload         4
      33: aload_0
      34: getfield      #6                  // Field applicationModel:Lorg/apache/dubbo/rpc/model/ApplicationModel;
      37: invokevirtual #71                 // Method org/apache/dubbo/configcenter/support/zookeeper/CacheListener.addListener:(Ljava/lang/String;Lorg/apache/dubbo/common/config/configcenter/ConfigurationListener;Ljava/lang/String;Ljava/lang/String;Lorg/apache/dubbo/rpc/model/ApplicationModel;)Lorg/apache/dubbo/configcenter/support/zookeeper/ZookeeperDataListener;
      40: astore        6
      42: aload_0
      43: getfield      #23                 // Field zkClient:Lorg/apache/dubbo/remoting/zookeeper/ZookeeperClient;
      46: aload_1
      47: aload         6
      49: aload_0
      50: getfield      #21                 // Field executor:Ljava/util/concurrent/Executor;
      53: invokeinterface #72,  4           // InterfaceMethod org/apache/dubbo/remoting/zookeeper/ZookeeperClient.addDataListener:(Ljava/lang/String;Lorg/apache/dubbo/remoting/zookeeper/DataListener;Ljava/util/concurrent/Executor;)V
      58: return

  protected void doRemoveListener(java.lang.String, org.apache.dubbo.common.config.configcenter.ConfigurationListener);
    Code:
       0: aload_0
       1: getfield      #5                  // Field cacheListener:Lorg/apache/dubbo/configcenter/support/zookeeper/CacheListener;
       4: aload_1
       5: aload_2
       6: invokevirtual #73                 // Method org/apache/dubbo/configcenter/support/zookeeper/CacheListener.removeListener:(Ljava/lang/String;Lorg/apache/dubbo/common/config/configcenter/ConfigurationListener;)Lorg/apache/dubbo/configcenter/support/zookeeper/ZookeeperDataListener;
       9: astore_3
      10: aload_3
      11: ifnull        35
      14: aload_3
      15: invokevirtual #74                 // Method org/apache/dubbo/configcenter/support/zookeeper/ZookeeperDataListener.getListeners:()Ljava/util/Set;
      18: invokestatic  #75                 // Method org/apache/dubbo/common/utils/CollectionUtils.isEmpty:(Ljava/util/Collection;)Z
      21: ifeq          35
      24: aload_0
      25: getfield      #23                 // Field zkClient:Lorg/apache/dubbo/remoting/zookeeper/ZookeeperClient;
      28: aload_1
      29: aload_3
      30: invokeinterface #52,  3           // InterfaceMethod org/apache/dubbo/remoting/zookeeper/ZookeeperClient.removeDataListener:(Ljava/lang/String;Lorg/apache/dubbo/remoting/zookeeper/DataListener;)V
      35: return

  public java.lang.Object getInternalProperty(java.lang.String);
    Code:
       0: aload_0
       1: aload_1
       2: invokevirtual #76                 // Method getInternalProperty:(Ljava/lang/String;)Ljava/lang/String;
       5: areturn

  static {};
    Code:
       0: lconst_0
       1: invokestatic  #77                 // Method java/lang/Long.valueOf:(J)Ljava/lang/Long;
       4: putstatic     #11                 // Field THREAD_KEEP_ALIVE_TIME:Ljava/lang/Long;
       7: return
}
