Compiled from "Decoder.java"
final class com.google.zxing.aztec.decoder.Decoder$Table extends java.lang.Enum<com.google.zxing.aztec.decoder.Decoder$Table> {
  public static final com.google.zxing.aztec.decoder.Decoder$Table UPPER;

  public static final com.google.zxing.aztec.decoder.Decoder$Table LOWER;

  public static final com.google.zxing.aztec.decoder.Decoder$Table MIXED;

  public static final com.google.zxing.aztec.decoder.Decoder$Table DIGIT;

  public static final com.google.zxing.aztec.decoder.Decoder$Table PUNCT;

  public static final com.google.zxing.aztec.decoder.Decoder$Table BINARY;

  private static final com.google.zxing.aztec.decoder.Decoder$Table[] $VALUES;

  public static com.google.zxing.aztec.decoder.Decoder$Table[] values();
    Code:
       0: getstatic     #1                  // Field $VALUES:[Lcom/google/zxing/aztec/decoder/Decoder$Table;
       3: invokevirtual #2                  // Method "[Lcom/google/zxing/aztec/decoder/Decoder$Table;".clone:()Ljava/lang/Object;
       6: checkcast     #3                  // class "[Lcom/google/zxing/aztec/decoder/Decoder$Table;"
       9: areturn

  public static com.google.zxing.aztec.decoder.Decoder$Table valueOf(java.lang.String);
    Code:
       0: ldc           #4                  // class com/google/zxing/aztec/decoder/Decoder$Table
       2: aload_0
       3: invokestatic  #5                  // Method java/lang/Enum.valueOf:(Ljava/lang/Class;Ljava/lang/String;)Ljava/lang/Enum;
       6: checkcast     #4                  // class com/google/zxing/aztec/decoder/Decoder$Table
       9: areturn

  private com.google.zxing.aztec.decoder.Decoder$Table();
    Code:
       0: aload_0
       1: aload_1
       2: iload_2
       3: invokespecial #6                  // Method java/lang/Enum."<init>":(Ljava/lang/String;I)V
       6: return

  static {};
    Code:
       0: new           #4                  // class com/google/zxing/aztec/decoder/Decoder$Table
       3: dup
       4: ldc           #7                  // String UPPER
       6: iconst_0
       7: invokespecial #8                  // Method "<init>":(Ljava/lang/String;I)V
      10: putstatic     #9                  // Field UPPER:Lcom/google/zxing/aztec/decoder/Decoder$Table;
      13: new           #4                  // class com/google/zxing/aztec/decoder/Decoder$Table
      16: dup
      17: ldc           #10                 // String LOWER
      19: iconst_1
      20: invokespecial #8                  // Method "<init>":(Ljava/lang/String;I)V
      23: putstatic     #11                 // Field LOWER:Lcom/google/zxing/aztec/decoder/Decoder$Table;
      26: new           #4                  // class com/google/zxing/aztec/decoder/Decoder$Table
      29: dup
      30: ldc           #12                 // String MIXED
      32: iconst_2
      33: invokespecial #8                  // Method "<init>":(Ljava/lang/String;I)V
      36: putstatic     #13                 // Field MIXED:Lcom/google/zxing/aztec/decoder/Decoder$Table;
      39: new           #4                  // class com/google/zxing/aztec/decoder/Decoder$Table
      42: dup
      43: ldc           #14                 // String DIGIT
      45: iconst_3
      46: invokespecial #8                  // Method "<init>":(Ljava/lang/String;I)V
      49: putstatic     #15                 // Field DIGIT:Lcom/google/zxing/aztec/decoder/Decoder$Table;
      52: new           #4                  // class com/google/zxing/aztec/decoder/Decoder$Table
      55: dup
      56: ldc           #16                 // String PUNCT
      58: iconst_4
      59: invokespecial #8                  // Method "<init>":(Ljava/lang/String;I)V
      62: putstatic     #17                 // Field PUNCT:Lcom/google/zxing/aztec/decoder/Decoder$Table;
      65: new           #4                  // class com/google/zxing/aztec/decoder/Decoder$Table
      68: dup
      69: ldc           #18                 // String BINARY
      71: iconst_5
      72: invokespecial #8                  // Method "<init>":(Ljava/lang/String;I)V
      75: putstatic     #19                 // Field BINARY:Lcom/google/zxing/aztec/decoder/Decoder$Table;
      78: bipush        6
      80: anewarray     #4                  // class com/google/zxing/aztec/decoder/Decoder$Table
      83: dup
      84: iconst_0
      85: getstatic     #9                  // Field UPPER:Lcom/google/zxing/aztec/decoder/Decoder$Table;
      88: aastore
      89: dup
      90: iconst_1
      91: getstatic     #11                 // Field LOWER:Lcom/google/zxing/aztec/decoder/Decoder$Table;
      94: aastore
      95: dup
      96: iconst_2
      97: getstatic     #13                 // Field MIXED:Lcom/google/zxing/aztec/decoder/Decoder$Table;
     100: aastore
     101: dup
     102: iconst_3
     103: getstatic     #15                 // Field DIGIT:Lcom/google/zxing/aztec/decoder/Decoder$Table;
     106: aastore
     107: dup
     108: iconst_4
     109: getstatic     #17                 // Field PUNCT:Lcom/google/zxing/aztec/decoder/Decoder$Table;
     112: aastore
     113: dup
     114: iconst_5
     115: getstatic     #19                 // Field BINARY:Lcom/google/zxing/aztec/decoder/Decoder$Table;
     118: aastore
     119: putstatic     #1                  // Field $VALUES:[Lcom/google/zxing/aztec/decoder/Decoder$Table;
     122: return
}
