Compiled from "Decoder.java"
final class com.google.zxing.aztec.decoder.Decoder$CorrectedBitsResult {
  private final boolean[] correctBits;

  private final int ecLevel;

  com.google.zxing.aztec.decoder.Decoder$CorrectedBitsResult(boolean[], int);
    Code:
       0: aload_0
       1: invokespecial #3                  // Method java/lang/Object."<init>":()V
       4: aload_0
       5: aload_1
       6: putfield      #2                  // Field correctBits:[Z
       9: aload_0
      10: iload_2
      11: putfield      #1                  // Field ecLevel:I
      14: return

  static boolean[] access$000(com.google.zxing.aztec.decoder.Decoder$CorrectedBitsResult);
    Code:
       0: aload_0
       1: getfield      #2                  // Field correctBits:[Z
       4: areturn

  static int access$100(com.google.zxing.aztec.decoder.Decoder$CorrectedBitsResult);
    Code:
       0: aload_0
       1: getfield      #1                  // Field ecLevel:I
       4: ireturn
}
