Compiled from "Decoder.java"
public final class com.google.zxing.aztec.decoder.Decoder {
  private static final java.lang.String[] UPPER_TABLE;

  private static final java.lang.String[] LOWER_TABLE;

  private static final java.lang.String[] MIXED_TABLE;

  private static final java.lang.String[] PUNCT_TABLE;

  private static final java.lang.String[] DIGIT_TABLE;

  private static final java.nio.charset.Charset DEFAULT_ENCODING;

  private com.google.zxing.aztec.AztecDetectorResult ddata;

  public com.google.zxing.aztec.decoder.Decoder();
    Code:
       0: aload_0
       1: invokespecial #1                  // Method java/lang/Object."<init>":()V
       4: return

  public com.google.zxing.common.DecoderResult decode(com.google.zxing.aztec.AztecDetectorResult) throws com.google.zxing.FormatException;
    Code:
       0: aload_0
       1: aload_1
       2: putfield      #2                  // Field ddata:Lcom/google/zxing/aztec/AztecDetectorResult;
       5: aload_1
       6: invokevirtual #3                  // Method com/google/zxing/aztec/AztecDetectorResult.getBits:()Lcom/google/zxing/common/BitMatrix;
       9: astore_2
      10: aload_0
      11: aload_2
      12: invokespecial #4                  // Method extractBits:(Lcom/google/zxing/common/BitMatrix;)[Z
      15: astore_3
      16: aload_0
      17: aload_3
      18: invokespecial #5                  // Method correctBits:([Z)Lcom/google/zxing/aztec/decoder/Decoder$CorrectedBitsResult;
      21: astore        4
      23: aload         4
      25: invokestatic  #6                  // Method com/google/zxing/aztec/decoder/Decoder$CorrectedBitsResult.access$000:(Lcom/google/zxing/aztec/decoder/Decoder$CorrectedBitsResult;)[Z
      28: invokestatic  #7                  // Method convertBoolArrayToByteArray:([Z)[B
      31: astore        5
      33: aload         4
      35: invokestatic  #6                  // Method com/google/zxing/aztec/decoder/Decoder$CorrectedBitsResult.access$000:(Lcom/google/zxing/aztec/decoder/Decoder$CorrectedBitsResult;)[Z
      38: invokestatic  #8                  // Method getEncodedData:([Z)Ljava/lang/String;
      41: astore        6
      43: new           #9                  // class com/google/zxing/common/DecoderResult
      46: dup
      47: aload         5
      49: aload         6
      51: aconst_null
      52: ldc           #10                 // String %d%%
      54: iconst_1
      55: anewarray     #11                 // class java/lang/Object
      58: dup
      59: iconst_0
      60: aload         4
      62: invokestatic  #12                 // Method com/google/zxing/aztec/decoder/Decoder$CorrectedBitsResult.access$100:(Lcom/google/zxing/aztec/decoder/Decoder$CorrectedBitsResult;)I
      65: invokestatic  #13                 // Method java/lang/Integer.valueOf:(I)Ljava/lang/Integer;
      68: aastore
      69: invokestatic  #14                 // Method java/lang/String.format:(Ljava/lang/String;[Ljava/lang/Object;)Ljava/lang/String;
      72: invokespecial #15                 // Method com/google/zxing/common/DecoderResult."<init>":([BLjava/lang/String;Ljava/util/List;Ljava/lang/String;)V
      75: astore        7
      77: aload         7
      79: aload         4
      81: invokestatic  #6                  // Method com/google/zxing/aztec/decoder/Decoder$CorrectedBitsResult.access$000:(Lcom/google/zxing/aztec/decoder/Decoder$CorrectedBitsResult;)[Z
      84: arraylength
      85: invokevirtual #16                 // Method com/google/zxing/common/DecoderResult.setNumBits:(I)V
      88: aload         7
      90: areturn

  public static java.lang.String highLevelDecode(boolean[]) throws com.google.zxing.FormatException;
    Code:
       0: aload_0
       1: invokestatic  #8                  // Method getEncodedData:([Z)Ljava/lang/String;
       4: areturn

  private static java.lang.String getEncodedData(boolean[]) throws com.google.zxing.FormatException;
    Code:
       0: aload_0
       1: arraylength
       2: istore_1
       3: getstatic     #17                 // Field com/google/zxing/aztec/decoder/Decoder$Table.UPPER:Lcom/google/zxing/aztec/decoder/Decoder$Table;
       6: astore_2
       7: getstatic     #17                 // Field com/google/zxing/aztec/decoder/Decoder$Table.UPPER:Lcom/google/zxing/aztec/decoder/Decoder$Table;
      10: astore_3
      11: new           #18                 // class java/lang/StringBuilder
      14: dup
      15: aload_0
      16: arraylength
      17: iconst_5
      18: isub
      19: iconst_4
      20: idiv
      21: invokespecial #19                 // Method java/lang/StringBuilder."<init>":(I)V
      24: astore        4
      26: new           #20                 // class java/io/ByteArrayOutputStream
      29: dup
      30: invokespecial #21                 // Method java/io/ByteArrayOutputStream."<init>":()V
      33: astore        5
      35: getstatic     #22                 // Field DEFAULT_ENCODING:Ljava/nio/charset/Charset;
      38: astore        6
      40: iconst_0
      41: istore        7
      43: iload         7
      45: iload_1
      46: if_icmpge     493
      49: aload_3
      50: getstatic     #23                 // Field com/google/zxing/aztec/decoder/Decoder$Table.BINARY:Lcom/google/zxing/aztec/decoder/Decoder$Table;
      53: if_acmpne     169
      56: iload_1
      57: iload         7
      59: isub
      60: iconst_5
      61: if_icmpge     67
      64: goto          493
      67: aload_0
      68: iload         7
      70: iconst_5
      71: invokestatic  #24                 // Method readCode:([ZII)I
      74: istore        8
      76: iinc          7, 5
      79: iload         8
      81: ifne          112
      84: iload_1
      85: iload         7
      87: isub
      88: bipush        11
      90: if_icmpge     96
      93: goto          493
      96: aload_0
      97: iload         7
      99: bipush        11
     101: invokestatic  #24                 // Method readCode:([ZII)I
     104: bipush        31
     106: iadd
     107: istore        8
     109: iinc          7, 11
     112: iconst_0
     113: istore        9
     115: iload         9
     117: iload         8
     119: if_icmpge     164
     122: iload_1
     123: iload         7
     125: isub
     126: bipush        8
     128: if_icmpge     137
     131: iload_1
     132: istore        7
     134: goto          164
     137: aload_0
     138: iload         7
     140: bipush        8
     142: invokestatic  #24                 // Method readCode:([ZII)I
     145: istore        10
     147: aload         5
     149: iload         10
     151: i2b
     152: invokevirtual #25                 // Method java/io/ByteArrayOutputStream.write:(I)V
     155: iinc          7, 8
     158: iinc          9, 1
     161: goto          115
     164: aload_2
     165: astore_3
     166: goto          43
     169: aload_3
     170: getstatic     #26                 // Field com/google/zxing/aztec/decoder/Decoder$Table.DIGIT:Lcom/google/zxing/aztec/decoder/Decoder$Table;
     173: if_acmpne     180
     176: iconst_4
     177: goto          181
     180: iconst_5
     181: istore        8
     183: iload_1
     184: iload         7
     186: isub
     187: iload         8
     189: if_icmpge     195
     192: goto          493
     195: aload_0
     196: iload         7
     198: iload         8
     200: invokestatic  #24                 // Method readCode:([ZII)I
     203: istore        9
     205: iload         7
     207: iload         8
     209: iadd
     210: istore        7
     212: aload_3
     213: iload         9
     215: invokestatic  #27                 // Method getCharacter:(Lcom/google/zxing/aztec/decoder/Decoder$Table;I)Ljava/lang/String;
     218: astore        10
     220: ldc           #28                 // String FLG(n)
     222: aload         10
     224: invokevirtual #29                 // Method java/lang/String.equals:(Ljava/lang/Object;)Z
     227: ifeq          428
     230: iload_1
     231: iload         7
     233: isub
     234: iconst_3
     235: if_icmpge     241
     238: goto          493
     241: aload_0
     242: iload         7
     244: iconst_3
     245: invokestatic  #24                 // Method readCode:([ZII)I
     248: istore        11
     250: iinc          7, 3
     253: aload         4
     255: aload         5
     257: aload         6
     259: invokevirtual #30                 // Method java/nio/charset/Charset.name:()Ljava/lang/String;
     262: invokevirtual #31                 // Method java/io/ByteArrayOutputStream.toString:(Ljava/lang/String;)Ljava/lang/String;
     265: invokevirtual #32                 // Method java/lang/StringBuilder.append:(Ljava/lang/String;)Ljava/lang/StringBuilder;
     268: pop
     269: goto          284
     272: astore        12
     274: new           #34                 // class java/lang/IllegalStateException
     277: dup
     278: aload         12
     280: invokespecial #35                 // Method java/lang/IllegalStateException."<init>":(Ljava/lang/Throwable;)V
     283: athrow
     284: aload         5
     286: invokevirtual #36                 // Method java/io/ByteArrayOutputStream.reset:()V
     289: iload         11
     291: lookupswitch  { // 2
                     0: 316
                     7: 327
               default: 331
          }
     316: aload         4
     318: bipush        29
     320: invokevirtual #37                 // Method java/lang/StringBuilder.append:(C)Ljava/lang/StringBuilder;
     323: pop
     324: goto          423
     327: invokestatic  #38                 // Method com/google/zxing/FormatException.getFormatInstance:()Lcom/google/zxing/FormatException;
     330: athrow
     331: iconst_0
     332: istore        12
     334: iload_1
     335: iload         7
     337: isub
     338: iconst_4
     339: iload         11
     341: imul
     342: if_icmpge     348
     345: goto          423
     348: iload         11
     350: iinc          11, -1
     353: ifle          400
     356: aload_0
     357: iload         7
     359: iconst_4
     360: invokestatic  #24                 // Method readCode:([ZII)I
     363: istore        13
     365: iinc          7, 4
     368: iload         13
     370: iconst_2
     371: if_icmplt     381
     374: iload         13
     376: bipush        11
     378: if_icmple     385
     381: invokestatic  #38                 // Method com/google/zxing/FormatException.getFormatInstance:()Lcom/google/zxing/FormatException;
     384: athrow
     385: iload         12
     387: bipush        10
     389: imul
     390: iload         13
     392: iconst_2
     393: isub
     394: iadd
     395: istore        12
     397: goto          348
     400: iload         12
     402: invokestatic  #39                 // Method com/google/zxing/common/CharacterSetECI.getCharacterSetECIByValue:(I)Lcom/google/zxing/common/CharacterSetECI;
     405: astore        13
     407: aload         13
     409: ifnonnull     416
     412: invokestatic  #38                 // Method com/google/zxing/FormatException.getFormatInstance:()Lcom/google/zxing/FormatException;
     415: athrow
     416: aload         13
     418: invokevirtual #40                 // Method com/google/zxing/common/CharacterSetECI.getCharset:()Ljava/nio/charset/Charset;
     421: astore        6
     423: aload_2
     424: astore_3
     425: goto          490
     428: aload         10
     430: ldc           #41                 // String CTRL_
     432: invokevirtual #42                 // Method java/lang/String.startsWith:(Ljava/lang/String;)Z
     435: ifeq          467
     438: aload_3
     439: astore_2
     440: aload         10
     442: iconst_5
     443: invokevirtual #43                 // Method java/lang/String.charAt:(I)C
     446: invokestatic  #44                 // Method getTable:(C)Lcom/google/zxing/aztec/decoder/Decoder$Table;
     449: astore_3
     450: aload         10
     452: bipush        6
     454: invokevirtual #43                 // Method java/lang/String.charAt:(I)C
     457: bipush        76
     459: if_icmpne     490
     462: aload_3
     463: astore_2
     464: goto          490
     467: aload         10
     469: getstatic     #45                 // Field java/nio/charset/StandardCharsets.US_ASCII:Ljava/nio/charset/Charset;
     472: invokevirtual #46                 // Method java/lang/String.getBytes:(Ljava/nio/charset/Charset;)[B
     475: astore        11
     477: aload         5
     479: aload         11
     481: iconst_0
     482: aload         11
     484: arraylength
     485: invokevirtual #47                 // Method java/io/ByteArrayOutputStream.write:([BII)V
     488: aload_2
     489: astore_3
     490: goto          43
     493: aload         4
     495: aload         5
     497: aload         6
     499: invokevirtual #30                 // Method java/nio/charset/Charset.name:()Ljava/lang/String;
     502: invokevirtual #31                 // Method java/io/ByteArrayOutputStream.toString:(Ljava/lang/String;)Ljava/lang/String;
     505: invokevirtual #32                 // Method java/lang/StringBuilder.append:(Ljava/lang/String;)Ljava/lang/StringBuilder;
     508: pop
     509: goto          524
     512: astore        8
     514: new           #34                 // class java/lang/IllegalStateException
     517: dup
     518: aload         8
     520: invokespecial #35                 // Method java/lang/IllegalStateException."<init>":(Ljava/lang/Throwable;)V
     523: athrow
     524: aload         4
     526: invokevirtual #48                 // Method java/lang/StringBuilder.toString:()Ljava/lang/String;
     529: areturn
    Exception table:
       from    to  target type
         253   269   272   Class java/io/UnsupportedEncodingException
         493   509   512   Class java/io/UnsupportedEncodingException

  private static com.google.zxing.aztec.decoder.Decoder$Table getTable(char);
    Code:
       0: iload_0
       1: tableswitch   { // 66 to 85
                    66: 112
                    67: 116
                    68: 108
                    69: 116
                    70: 116
                    71: 116
                    72: 116
                    73: 116
                    74: 116
                    75: 116
                    76: 96
                    77: 104
                    78: 116
                    79: 116
                    80: 100
                    81: 116
                    82: 116
                    83: 116
                    84: 116
                    85: 116
               default: 116
          }
      96: getstatic     #49                 // Field com/google/zxing/aztec/decoder/Decoder$Table.LOWER:Lcom/google/zxing/aztec/decoder/Decoder$Table;
      99: areturn
     100: getstatic     #50                 // Field com/google/zxing/aztec/decoder/Decoder$Table.PUNCT:Lcom/google/zxing/aztec/decoder/Decoder$Table;
     103: areturn
     104: getstatic     #51                 // Field com/google/zxing/aztec/decoder/Decoder$Table.MIXED:Lcom/google/zxing/aztec/decoder/Decoder$Table;
     107: areturn
     108: getstatic     #26                 // Field com/google/zxing/aztec/decoder/Decoder$Table.DIGIT:Lcom/google/zxing/aztec/decoder/Decoder$Table;
     111: areturn
     112: getstatic     #23                 // Field com/google/zxing/aztec/decoder/Decoder$Table.BINARY:Lcom/google/zxing/aztec/decoder/Decoder$Table;
     115: areturn
     116: getstatic     #17                 // Field com/google/zxing/aztec/decoder/Decoder$Table.UPPER:Lcom/google/zxing/aztec/decoder/Decoder$Table;
     119: areturn

  private static java.lang.String getCharacter(com.google.zxing.aztec.decoder.Decoder$Table, int);
    Code:
       0: getstatic     #52                 // Field com/google/zxing/aztec/decoder/Decoder$1.$SwitchMap$com$google$zxing$aztec$decoder$Decoder$Table:[I
       3: aload_0
       4: invokevirtual #53                 // Method com/google/zxing/aztec/decoder/Decoder$Table.ordinal:()I
       7: iaload
       8: tableswitch   { // 1 to 5
                     1: 44
                     2: 50
                     3: 56
                     4: 62
                     5: 68
               default: 74
          }
      44: getstatic     #54                 // Field UPPER_TABLE:[Ljava/lang/String;
      47: iload_1
      48: aaload
      49: areturn
      50: getstatic     #55                 // Field LOWER_TABLE:[Ljava/lang/String;
      53: iload_1
      54: aaload
      55: areturn
      56: getstatic     #56                 // Field MIXED_TABLE:[Ljava/lang/String;
      59: iload_1
      60: aaload
      61: areturn
      62: getstatic     #57                 // Field PUNCT_TABLE:[Ljava/lang/String;
      65: iload_1
      66: aaload
      67: areturn
      68: getstatic     #58                 // Field DIGIT_TABLE:[Ljava/lang/String;
      71: iload_1
      72: aaload
      73: areturn
      74: new           #34                 // class java/lang/IllegalStateException
      77: dup
      78: ldc           #59                 // String Bad table
      80: invokespecial #60                 // Method java/lang/IllegalStateException."<init>":(Ljava/lang/String;)V
      83: athrow

  private com.google.zxing.aztec.decoder.Decoder$CorrectedBitsResult correctBits(boolean[]) throws com.google.zxing.FormatException;
    Code:
       0: aload_0
       1: getfield      #2                  // Field ddata:Lcom/google/zxing/aztec/AztecDetectorResult;
       4: invokevirtual #61                 // Method com/google/zxing/aztec/AztecDetectorResult.getNbLayers:()I
       7: iconst_2
       8: if_icmpgt     21
      11: bipush        6
      13: istore_3
      14: getstatic     #62                 // Field com/google/zxing/common/reedsolomon/GenericGF.AZTEC_DATA_6:Lcom/google/zxing/common/reedsolomon/GenericGF;
      17: astore_2
      18: goto          72
      21: aload_0
      22: getfield      #2                  // Field ddata:Lcom/google/zxing/aztec/AztecDetectorResult;
      25: invokevirtual #61                 // Method com/google/zxing/aztec/AztecDetectorResult.getNbLayers:()I
      28: bipush        8
      30: if_icmpgt     43
      33: bipush        8
      35: istore_3
      36: getstatic     #63                 // Field com/google/zxing/common/reedsolomon/GenericGF.AZTEC_DATA_8:Lcom/google/zxing/common/reedsolomon/GenericGF;
      39: astore_2
      40: goto          72
      43: aload_0
      44: getfield      #2                  // Field ddata:Lcom/google/zxing/aztec/AztecDetectorResult;
      47: invokevirtual #61                 // Method com/google/zxing/aztec/AztecDetectorResult.getNbLayers:()I
      50: bipush        22
      52: if_icmpgt     65
      55: bipush        10
      57: istore_3
      58: getstatic     #64                 // Field com/google/zxing/common/reedsolomon/GenericGF.AZTEC_DATA_10:Lcom/google/zxing/common/reedsolomon/GenericGF;
      61: astore_2
      62: goto          72
      65: bipush        12
      67: istore_3
      68: getstatic     #65                 // Field com/google/zxing/common/reedsolomon/GenericGF.AZTEC_DATA_12:Lcom/google/zxing/common/reedsolomon/GenericGF;
      71: astore_2
      72: aload_0
      73: getfield      #2                  // Field ddata:Lcom/google/zxing/aztec/AztecDetectorResult;
      76: invokevirtual #66                 // Method com/google/zxing/aztec/AztecDetectorResult.getNbDatablocks:()I
      79: istore        4
      81: aload_1
      82: arraylength
      83: iload_3
      84: idiv
      85: istore        5
      87: iload         5
      89: iload         4
      91: if_icmpge     98
      94: invokestatic  #38                 // Method com/google/zxing/FormatException.getFormatInstance:()Lcom/google/zxing/FormatException;
      97: athrow
      98: aload_1
      99: arraylength
     100: iload_3
     101: irem
     102: istore        6
     104: iload         5
     106: newarray       int
     108: astore        7
     110: iconst_0
     111: istore        8
     113: iload         8
     115: iload         5
     117: if_icmpge     144
     120: aload         7
     122: iload         8
     124: aload_1
     125: iload         6
     127: iload_3
     128: invokestatic  #24                 // Method readCode:([ZII)I
     131: iastore
     132: iinc          8, 1
     135: iload         6
     137: iload_3
     138: iadd
     139: istore        6
     141: goto          113
     144: new           #67                 // class com/google/zxing/common/reedsolomon/ReedSolomonDecoder
     147: dup
     148: aload_2
     149: invokespecial #68                 // Method com/google/zxing/common/reedsolomon/ReedSolomonDecoder."<init>":(Lcom/google/zxing/common/reedsolomon/GenericGF;)V
     152: astore        8
     154: aload         8
     156: aload         7
     158: iload         5
     160: iload         4
     162: isub
     163: invokevirtual #69                 // Method com/google/zxing/common/reedsolomon/ReedSolomonDecoder.decode:([II)V
     166: goto          177
     169: astore        8
     171: aload         8
     173: invokestatic  #71                 // Method com/google/zxing/FormatException.getFormatInstance:(Ljava/lang/Throwable;)Lcom/google/zxing/FormatException;
     176: athrow
     177: iconst_1
     178: iload_3
     179: ishl
     180: iconst_1
     181: isub
     182: istore        8
     184: iconst_0
     185: istore        9
     187: iconst_0
     188: istore        10
     190: iload         10
     192: iload         4
     194: if_icmpge     244
     197: aload         7
     199: iload         10
     201: iaload
     202: istore        11
     204: iload         11
     206: ifeq          216
     209: iload         11
     211: iload         8
     213: if_icmpne     220
     216: invokestatic  #38                 // Method com/google/zxing/FormatException.getFormatInstance:()Lcom/google/zxing/FormatException;
     219: athrow
     220: iload         11
     222: iconst_1
     223: if_icmpeq     235
     226: iload         11
     228: iload         8
     230: iconst_1
     231: isub
     232: if_icmpne     238
     235: iinc          9, 1
     238: iinc          10, 1
     241: goto          190
     244: iload         4
     246: iload_3
     247: imul
     248: iload         9
     250: isub
     251: newarray       boolean
     253: astore        10
     255: iconst_0
     256: istore        11
     258: iconst_0
     259: istore        12
     261: iload         12
     263: iload         4
     265: if_icmpge     370
     268: aload         7
     270: iload         12
     272: iaload
     273: istore        13
     275: iload         13
     277: iconst_1
     278: if_icmpeq     290
     281: iload         13
     283: iload         8
     285: iconst_1
     286: isub
     287: if_icmpne     325
     290: aload         10
     292: iload         11
     294: iload         11
     296: iload_3
     297: iadd
     298: iconst_1
     299: isub
     300: iload         13
     302: iconst_1
     303: if_icmple     310
     306: iconst_1
     307: goto          311
     310: iconst_0
     311: invokestatic  #72                 // Method java/util/Arrays.fill:([ZIIZ)V
     314: iload         11
     316: iload_3
     317: iconst_1
     318: isub
     319: iadd
     320: istore        11
     322: goto          364
     325: iload_3
     326: iconst_1
     327: isub
     328: istore        14
     330: iload         14
     332: iflt          364
     335: aload         10
     337: iload         11
     339: iinc          11, 1
     342: iload         13
     344: iconst_1
     345: iload         14
     347: ishl
     348: iand
     349: ifeq          356
     352: iconst_1
     353: goto          357
     356: iconst_0
     357: bastore
     358: iinc          14, -1
     361: goto          330
     364: iinc          12, 1
     367: goto          261
     370: new           #73                 // class com/google/zxing/aztec/decoder/Decoder$CorrectedBitsResult
     373: dup
     374: aload         10
     376: bipush        100
     378: iload         5
     380: iload         4
     382: isub
     383: imul
     384: iload         5
     386: idiv
     387: invokespecial #74                 // Method com/google/zxing/aztec/decoder/Decoder$CorrectedBitsResult."<init>":([ZI)V
     390: areturn
    Exception table:
       from    to  target type
         144   166   169   Class com/google/zxing/common/reedsolomon/ReedSolomonException

  private boolean[] extractBits(com.google.zxing.common.BitMatrix);
    Code:
       0: aload_0
       1: getfield      #2                  // Field ddata:Lcom/google/zxing/aztec/AztecDetectorResult;
       4: invokevirtual #75                 // Method com/google/zxing/aztec/AztecDetectorResult.isCompact:()Z
       7: istore_2
       8: aload_0
       9: getfield      #2                  // Field ddata:Lcom/google/zxing/aztec/AztecDetectorResult;
      12: invokevirtual #61                 // Method com/google/zxing/aztec/AztecDetectorResult.getNbLayers:()I
      15: istore_3
      16: iload_2
      17: ifeq          25
      20: bipush        11
      22: goto          27
      25: bipush        14
      27: iload_3
      28: iconst_4
      29: imul
      30: iadd
      31: istore        4
      33: iload         4
      35: newarray       int
      37: astore        5
      39: iload_3
      40: iload_2
      41: invokestatic  #76                 // Method totalBitsInLayer:(IZ)I
      44: newarray       boolean
      46: astore        6
      48: iload_2
      49: ifeq          79
      52: iconst_0
      53: istore        7
      55: iload         7
      57: aload         5
      59: arraylength
      60: if_icmpge     76
      63: aload         5
      65: iload         7
      67: iload         7
      69: iastore
      70: iinc          7, 1
      73: goto          55
      76: goto          167
      79: iload         4
      81: iconst_1
      82: iadd
      83: iconst_2
      84: iload         4
      86: iconst_2
      87: idiv
      88: iconst_1
      89: isub
      90: bipush        15
      92: idiv
      93: imul
      94: iadd
      95: istore        7
      97: iload         4
      99: iconst_2
     100: idiv
     101: istore        8
     103: iload         7
     105: iconst_2
     106: idiv
     107: istore        9
     109: iconst_0
     110: istore        10
     112: iload         10
     114: iload         8
     116: if_icmpge     167
     119: iload         10
     121: iload         10
     123: bipush        15
     125: idiv
     126: iadd
     127: istore        11
     129: aload         5
     131: iload         8
     133: iload         10
     135: isub
     136: iconst_1
     137: isub
     138: iload         9
     140: iload         11
     142: isub
     143: iconst_1
     144: isub
     145: iastore
     146: aload         5
     148: iload         8
     150: iload         10
     152: iadd
     153: iload         9
     155: iload         11
     157: iadd
     158: iconst_1
     159: iadd
     160: iastore
     161: iinc          10, 1
     164: goto          112
     167: iconst_0
     168: istore        7
     170: iconst_0
     171: istore        8
     173: iload         7
     175: iload_3
     176: if_icmpge     407
     179: iload_3
     180: iload         7
     182: isub
     183: iconst_4
     184: imul
     185: iload_2
     186: ifeq          194
     189: bipush        9
     191: goto          196
     194: bipush        12
     196: iadd
     197: istore        9
     199: iload         7
     201: iconst_2
     202: imul
     203: istore        10
     205: iload         4
     207: iconst_1
     208: isub
     209: iload         10
     211: isub
     212: istore        11
     214: iconst_0
     215: istore        12
     217: iload         12
     219: iload         9
     221: if_icmpge     391
     224: iload         12
     226: iconst_2
     227: imul
     228: istore        13
     230: iconst_0
     231: istore        14
     233: iload         14
     235: iconst_2
     236: if_icmpge     385
     239: aload         6
     241: iload         8
     243: iload         13
     245: iadd
     246: iload         14
     248: iadd
     249: aload_1
     250: aload         5
     252: iload         10
     254: iload         14
     256: iadd
     257: iaload
     258: aload         5
     260: iload         10
     262: iload         12
     264: iadd
     265: iaload
     266: invokevirtual #77                 // Method com/google/zxing/common/BitMatrix.get:(II)Z
     269: bastore
     270: aload         6
     272: iload         8
     274: iconst_2
     275: iload         9
     277: imul
     278: iadd
     279: iload         13
     281: iadd
     282: iload         14
     284: iadd
     285: aload_1
     286: aload         5
     288: iload         10
     290: iload         12
     292: iadd
     293: iaload
     294: aload         5
     296: iload         11
     298: iload         14
     300: isub
     301: iaload
     302: invokevirtual #77                 // Method com/google/zxing/common/BitMatrix.get:(II)Z
     305: bastore
     306: aload         6
     308: iload         8
     310: iconst_4
     311: iload         9
     313: imul
     314: iadd
     315: iload         13
     317: iadd
     318: iload         14
     320: iadd
     321: aload_1
     322: aload         5
     324: iload         11
     326: iload         14
     328: isub
     329: iaload
     330: aload         5
     332: iload         11
     334: iload         12
     336: isub
     337: iaload
     338: invokevirtual #77                 // Method com/google/zxing/common/BitMatrix.get:(II)Z
     341: bastore
     342: aload         6
     344: iload         8
     346: bipush        6
     348: iload         9
     350: imul
     351: iadd
     352: iload         13
     354: iadd
     355: iload         14
     357: iadd
     358: aload_1
     359: aload         5
     361: iload         11
     363: iload         12
     365: isub
     366: iaload
     367: aload         5
     369: iload         10
     371: iload         14
     373: iadd
     374: iaload
     375: invokevirtual #77                 // Method com/google/zxing/common/BitMatrix.get:(II)Z
     378: bastore
     379: iinc          14, 1
     382: goto          233
     385: iinc          12, 1
     388: goto          217
     391: iload         8
     393: iload         9
     395: bipush        8
     397: imul
     398: iadd
     399: istore        8
     401: iinc          7, 1
     404: goto          173
     407: aload         6
     409: areturn

  private static int readCode(boolean[], int, int);
    Code:
       0: iconst_0
       1: istore_3
       2: iload_1
       3: istore        4
       5: iload         4
       7: iload_1
       8: iload_2
       9: iadd
      10: if_icmpge     34
      13: iload_3
      14: iconst_1
      15: ishl
      16: istore_3
      17: aload_0
      18: iload         4
      20: baload
      21: ifeq          28
      24: iload_3
      25: iconst_1
      26: ior
      27: istore_3
      28: iinc          4, 1
      31: goto          5
      34: iload_3
      35: ireturn

  private static byte readByte(boolean[], int);
    Code:
       0: aload_0
       1: arraylength
       2: iload_1
       3: isub
       4: istore_2
       5: iload_2
       6: bipush        8
       8: if_icmplt     20
      11: aload_0
      12: iload_1
      13: bipush        8
      15: invokestatic  #24                 // Method readCode:([ZII)I
      18: i2b
      19: ireturn
      20: aload_0
      21: iload_1
      22: iload_2
      23: invokestatic  #24                 // Method readCode:([ZII)I
      26: bipush        8
      28: iload_2
      29: isub
      30: ishl
      31: i2b
      32: ireturn

  static byte[] convertBoolArrayToByteArray(boolean[]);
    Code:
       0: aload_0
       1: arraylength
       2: bipush        7
       4: iadd
       5: bipush        8
       7: idiv
       8: newarray       byte
      10: astore_1
      11: iconst_0
      12: istore_2
      13: iload_2
      14: aload_1
      15: arraylength
      16: if_icmpge     36
      19: aload_1
      20: iload_2
      21: aload_0
      22: bipush        8
      24: iload_2
      25: imul
      26: invokestatic  #78                 // Method readByte:([ZI)B
      29: bastore
      30: iinc          2, 1
      33: goto          13
      36: aload_1
      37: areturn

  private static int totalBitsInLayer(int, boolean);
    Code:
       0: iload_1
       1: ifeq          9
       4: bipush        88
       6: goto          11
       9: bipush        112
      11: bipush        16
      13: iload_0
      14: imul
      15: iadd
      16: iload_0
      17: imul
      18: ireturn

  static {};
    Code:
       0: bipush        32
       2: anewarray     #79                 // class java/lang/String
       5: dup
       6: iconst_0
       7: ldc           #80                 // String CTRL_PS
       9: aastore
      10: dup
      11: iconst_1
      12: ldc           #81                 // String
      14: aastore
      15: dup
      16: iconst_2
      17: ldc           #82                 // String A
      19: aastore
      20: dup
      21: iconst_3
      22: ldc           #83                 // String B
      24: aastore
      25: dup
      26: iconst_4
      27: ldc           #84                 // String C
      29: aastore
      30: dup
      31: iconst_5
      32: ldc           #85                 // String D
      34: aastore
      35: dup
      36: bipush        6
      38: ldc           #86                 // String E
      40: aastore
      41: dup
      42: bipush        7
      44: ldc           #87                 // String F
      46: aastore
      47: dup
      48: bipush        8
      50: ldc           #88                 // String G
      52: aastore
      53: dup
      54: bipush        9
      56: ldc           #89                 // String H
      58: aastore
      59: dup
      60: bipush        10
      62: ldc           #90                 // String I
      64: aastore
      65: dup
      66: bipush        11
      68: ldc           #91                 // String J
      70: aastore
      71: dup
      72: bipush        12
      74: ldc           #92                 // String K
      76: aastore
      77: dup
      78: bipush        13
      80: ldc           #93                 // String L
      82: aastore
      83: dup
      84: bipush        14
      86: ldc           #94                 // String M
      88: aastore
      89: dup
      90: bipush        15
      92: ldc           #95                 // String N
      94: aastore
      95: dup
      96: bipush        16
      98: ldc           #96                 // String O
     100: aastore
     101: dup
     102: bipush        17
     104: ldc           #97                 // String P
     106: aastore
     107: dup
     108: bipush        18
     110: ldc           #98                 // String Q
     112: aastore
     113: dup
     114: bipush        19
     116: ldc           #99                 // String R
     118: aastore
     119: dup
     120: bipush        20
     122: ldc           #100                // String S
     124: aastore
     125: dup
     126: bipush        21
     128: ldc           #101                // String T
     130: aastore
     131: dup
     132: bipush        22
     134: ldc           #102                // String U
     136: aastore
     137: dup
     138: bipush        23
     140: ldc           #103                // String V
     142: aastore
     143: dup
     144: bipush        24
     146: ldc           #104                // String W
     148: aastore
     149: dup
     150: bipush        25
     152: ldc           #105                // String X
     154: aastore
     155: dup
     156: bipush        26
     158: ldc           #106                // String Y
     160: aastore
     161: dup
     162: bipush        27
     164: ldc           #107                // String Z
     166: aastore
     167: dup
     168: bipush        28
     170: ldc           #108                // String CTRL_LL
     172: aastore
     173: dup
     174: bipush        29
     176: ldc           #109                // String CTRL_ML
     178: aastore
     179: dup
     180: bipush        30
     182: ldc           #110                // String CTRL_DL
     184: aastore
     185: dup
     186: bipush        31
     188: ldc           #111                // String CTRL_BS
     190: aastore
     191: putstatic     #54                 // Field UPPER_TABLE:[Ljava/lang/String;
     194: bipush        32
     196: anewarray     #79                 // class java/lang/String
     199: dup
     200: iconst_0
     201: ldc           #80                 // String CTRL_PS
     203: aastore
     204: dup
     205: iconst_1
     206: ldc           #81                 // String
     208: aastore
     209: dup
     210: iconst_2
     211: ldc           #112                // String a
     213: aastore
     214: dup
     215: iconst_3
     216: ldc           #113                // String b
     218: aastore
     219: dup
     220: iconst_4
     221: ldc           #114                // String c
     223: aastore
     224: dup
     225: iconst_5
     226: ldc           #115                // String d
     228: aastore
     229: dup
     230: bipush        6
     232: ldc           #116                // String e
     234: aastore
     235: dup
     236: bipush        7
     238: ldc           #117                // String f
     240: aastore
     241: dup
     242: bipush        8
     244: ldc           #118                // String g
     246: aastore
     247: dup
     248: bipush        9
     250: ldc           #119                // String h
     252: aastore
     253: dup
     254: bipush        10
     256: ldc           #120                // String i
     258: aastore
     259: dup
     260: bipush        11
     262: ldc           #121                // String j
     264: aastore
     265: dup
     266: bipush        12
     268: ldc           #122                // String k
     270: aastore
     271: dup
     272: bipush        13
     274: ldc           #123                // String l
     276: aastore
     277: dup
     278: bipush        14
     280: ldc           #124                // String m
     282: aastore
     283: dup
     284: bipush        15
     286: ldc           #125                // String n
     288: aastore
     289: dup
     290: bipush        16
     292: ldc           #126                // String o
     294: aastore
     295: dup
     296: bipush        17
     298: ldc           #127                // String p
     300: aastore
     301: dup
     302: bipush        18
     304: ldc           #128                // String q
     306: aastore
     307: dup
     308: bipush        19
     310: ldc           #129                // String r
     312: aastore
     313: dup
     314: bipush        20
     316: ldc           #130                // String s
     318: aastore
     319: dup
     320: bipush        21
     322: ldc           #131                // String t
     324: aastore
     325: dup
     326: bipush        22
     328: ldc           #132                // String u
     330: aastore
     331: dup
     332: bipush        23
     334: ldc           #133                // String v
     336: aastore
     337: dup
     338: bipush        24
     340: ldc           #134                // String w
     342: aastore
     343: dup
     344: bipush        25
     346: ldc           #135                // String x
     348: aastore
     349: dup
     350: bipush        26
     352: ldc           #136                // String y
     354: aastore
     355: dup
     356: bipush        27
     358: ldc           #137                // String z
     360: aastore
     361: dup
     362: bipush        28
     364: ldc           #138                // String CTRL_US
     366: aastore
     367: dup
     368: bipush        29
     370: ldc           #109                // String CTRL_ML
     372: aastore
     373: dup
     374: bipush        30
     376: ldc           #110                // String CTRL_DL
     378: aastore
     379: dup
     380: bipush        31
     382: ldc           #111                // String CTRL_BS
     384: aastore
     385: putstatic     #55                 // Field LOWER_TABLE:[Ljava/lang/String;
     388: bipush        32
     390: anewarray     #79                 // class java/lang/String
     393: dup
     394: iconst_0
     395: ldc           #80                 // String CTRL_PS
     397: aastore
     398: dup
     399: iconst_1
     400: ldc           #81                 // String
     402: aastore
     403: dup
     404: iconst_2
     405: ldc           #139                // String \u0001
     407: aastore
     408: dup
     409: iconst_3
     410: ldc           #140                // String \u0002
     412: aastore
     413: dup
     414: iconst_4
     415: ldc           #141                // String \u0003
     417: aastore
     418: dup
     419: iconst_5
     420: ldc           #142                // String \u0004
     422: aastore
     423: dup
     424: bipush        6
     426: ldc           #143                // String \u0005
     428: aastore
     429: dup
     430: bipush        7
     432: ldc           #144                // String \u0006
     434: aastore
     435: dup
     436: bipush        8
     438: ldc           #145                // String \u0007
     440: aastore
     441: dup
     442: bipush        9
     444: ldc           #146                // String \b
     446: aastore
     447: dup
     448: bipush        10
     450: ldc           #147                // String \t
     452: aastore
     453: dup
     454: bipush        11
     456: ldc           #148                // String \n
     458: aastore
     459: dup
     460: bipush        12
     462: ldc           #149                // String \u000b
     464: aastore
     465: dup
     466: bipush        13
     468: ldc           #150                // String \f
     470: aastore
     471: dup
     472: bipush        14
     474: ldc           #151                // String \r
     476: aastore
     477: dup
     478: bipush        15
     480: ldc           #152                // String \u001b
     482: aastore
     483: dup
     484: bipush        16
     486: ldc           #153                // String \u001c
     488: aastore
     489: dup
     490: bipush        17
     492: ldc           #154                // String \u001d
     494: aastore
     495: dup
     496: bipush        18
     498: ldc           #155                // String \u001e
     500: aastore
     501: dup
     502: bipush        19
     504: ldc           #156                // String \u001f
     506: aastore
     507: dup
     508: bipush        20
     510: ldc           #157                // String @
     512: aastore
     513: dup
     514: bipush        21
     516: ldc           #158                // String \\
     518: aastore
     519: dup
     520: bipush        22
     522: ldc           #159                // String ^
     524: aastore
     525: dup
     526: bipush        23
     528: ldc           #160                // String _
     530: aastore
     531: dup
     532: bipush        24
     534: ldc           #161                // String `
     536: aastore
     537: dup
     538: bipush        25
     540: ldc           #162                // String |
     542: aastore
     543: dup
     544: bipush        26
     546: ldc           #163                // String ~
     548: aastore
     549: dup
     550: bipush        27
     552: ldc           #164                // String \u007f
     554: aastore
     555: dup
     556: bipush        28
     558: ldc           #108                // String CTRL_LL
     560: aastore
     561: dup
     562: bipush        29
     564: ldc           #165                // String CTRL_UL
     566: aastore
     567: dup
     568: bipush        30
     570: ldc           #166                // String CTRL_PL
     572: aastore
     573: dup
     574: bipush        31
     576: ldc           #111                // String CTRL_BS
     578: aastore
     579: putstatic     #56                 // Field MIXED_TABLE:[Ljava/lang/String;
     582: bipush        32
     584: anewarray     #79                 // class java/lang/String
     587: dup
     588: iconst_0
     589: ldc           #28                 // String FLG(n)
     591: aastore
     592: dup
     593: iconst_1
     594: ldc           #151                // String \r
     596: aastore
     597: dup
     598: iconst_2
     599: ldc           #167                // String \r\n
     601: aastore
     602: dup
     603: iconst_3
     604: ldc           #168                // String .
     606: aastore
     607: dup
     608: iconst_4
     609: ldc           #169                // String ,
     611: aastore
     612: dup
     613: iconst_5
     614: ldc           #170                // String :
     616: aastore
     617: dup
     618: bipush        6
     620: ldc           #171                // String !
     622: aastore
     623: dup
     624: bipush        7
     626: ldc           #172                // String \"
     628: aastore
     629: dup
     630: bipush        8
     632: ldc           #173                // String #
     634: aastore
     635: dup
     636: bipush        9
     638: ldc           #174                // String $
     640: aastore
     641: dup
     642: bipush        10
     644: ldc           #175                // String %
     646: aastore
     647: dup
     648: bipush        11
     650: ldc           #176                // String &
     652: aastore
     653: dup
     654: bipush        12
     656: ldc           #177                // String \'
     658: aastore
     659: dup
     660: bipush        13
     662: ldc           #178                // String (
     664: aastore
     665: dup
     666: bipush        14
     668: ldc           #179                // String )
     670: aastore
     671: dup
     672: bipush        15
     674: ldc           #180                // String *
     676: aastore
     677: dup
     678: bipush        16
     680: ldc           #181                // String +
     682: aastore
     683: dup
     684: bipush        17
     686: ldc           #182                // String ,
     688: aastore
     689: dup
     690: bipush        18
     692: ldc           #183                // String -
     694: aastore
     695: dup
     696: bipush        19
     698: ldc           #184                // String .
     700: aastore
     701: dup
     702: bipush        20
     704: ldc           #185                // String /
     706: aastore
     707: dup
     708: bipush        21
     710: ldc           #186                // String :
     712: aastore
     713: dup
     714: bipush        22
     716: ldc           #187                // String ;
     718: aastore
     719: dup
     720: bipush        23
     722: ldc           #188                // String <
     724: aastore
     725: dup
     726: bipush        24
     728: ldc           #189                // String =
     730: aastore
     731: dup
     732: bipush        25
     734: ldc           #190                // String >
     736: aastore
     737: dup
     738: bipush        26
     740: ldc           #191                // String ?
     742: aastore
     743: dup
     744: bipush        27
     746: ldc           #192                // String [
     748: aastore
     749: dup
     750: bipush        28
     752: ldc           #193                // String ]
     754: aastore
     755: dup
     756: bipush        29
     758: ldc           #194                // String {
     760: aastore
     761: dup
     762: bipush        30
     764: ldc           #195                // String }
     766: aastore
     767: dup
     768: bipush        31
     770: ldc           #165                // String CTRL_UL
     772: aastore
     773: putstatic     #57                 // Field PUNCT_TABLE:[Ljava/lang/String;
     776: bipush        16
     778: anewarray     #79                 // class java/lang/String
     781: dup
     782: iconst_0
     783: ldc           #80                 // String CTRL_PS
     785: aastore
     786: dup
     787: iconst_1
     788: ldc           #81                 // String
     790: aastore
     791: dup
     792: iconst_2
     793: ldc           #196                // String 0
     795: aastore
     796: dup
     797: iconst_3
     798: ldc           #197                // String 1
     800: aastore
     801: dup
     802: iconst_4
     803: ldc           #198                // String 2
     805: aastore
     806: dup
     807: iconst_5
     808: ldc           #199                // String 3
     810: aastore
     811: dup
     812: bipush        6
     814: ldc           #200                // String 4
     816: aastore
     817: dup
     818: bipush        7
     820: ldc           #201                // String 5
     822: aastore
     823: dup
     824: bipush        8
     826: ldc           #202                // String 6
     828: aastore
     829: dup
     830: bipush        9
     832: ldc           #203                // String 7
     834: aastore
     835: dup
     836: bipush        10
     838: ldc           #204                // String 8
     840: aastore
     841: dup
     842: bipush        11
     844: ldc           #205                // String 9
     846: aastore
     847: dup
     848: bipush        12
     850: ldc           #182                // String ,
     852: aastore
     853: dup
     854: bipush        13
     856: ldc           #184                // String .
     858: aastore
     859: dup
     860: bipush        14
     862: ldc           #165                // String CTRL_UL
     864: aastore
     865: dup
     866: bipush        15
     868: ldc           #138                // String CTRL_US
     870: aastore
     871: putstatic     #58                 // Field DIGIT_TABLE:[Ljava/lang/String;
     874: getstatic     #206                // Field java/nio/charset/StandardCharsets.ISO_8859_1:Ljava/nio/charset/Charset;
     877: putstatic     #22                 // Field DEFAULT_ENCODING:Ljava/nio/charset/Charset;
     880: return
}
