Compiled from "DecodedBitStreamParser.java"
final class com.google.zxing.datamatrix.decoder.DecodedBitStreamParser {
  private static final char[] C40_BASIC_SET_CHARS;

  private static final char[] C40_SHIFT2_SET_CHARS;

  private static final char[] TEXT_BASIC_SET_CHARS;

  private static final char[] TEXT_SHIFT2_SET_CHARS;

  private static final char[] TEXT_SHIFT3_SET_CHARS;

  private com.google.zxing.datamatrix.decoder.DecodedBitStreamParser();
    Code:
       0: aload_0
       1: invokespecial #1                  // Method java/lang/Object."<init>":()V
       4: return

  static com.google.zxing.common.DecoderResult decode(byte[]) throws com.google.zxing.FormatException;
    Code:
       0: new           #2                  // class com/google/zxing/common/BitSource
       3: dup
       4: aload_0
       5: invokespecial #3                  // Method com/google/zxing/common/BitSource."<init>":([B)V
       8: astore_1
       9: new           #4                  // class com/google/zxing/common/ECIStringBuilder
      12: dup
      13: bipush        100
      15: invokespecial #5                  // Method com/google/zxing/common/ECIStringBuilder."<init>":(I)V
      18: astore_2
      19: new           #6                  // class java/lang/StringBuilder
      22: dup
      23: iconst_0
      24: invokespecial #7                  // Method java/lang/StringBuilder."<init>":(I)V
      27: astore_3
      28: new           #8                  // class java/util/ArrayList
      31: dup
      32: iconst_1
      33: invokespecial #9                  // Method java/util/ArrayList."<init>":(I)V
      36: astore        4
      38: getstatic     #10                 // Field com/google/zxing/datamatrix/decoder/DecodedBitStreamParser$Mode.ASCII_ENCODE:Lcom/google/zxing/datamatrix/decoder/DecodedBitStreamParser$Mode;
      41: astore        5
      43: new           #11                 // class java/util/HashSet
      46: dup
      47: invokespecial #12                 // Method java/util/HashSet."<init>":()V
      50: astore        6
      52: iconst_0
      53: istore        8
      55: aload         5
      57: getstatic     #10                 // Field com/google/zxing/datamatrix/decoder/DecodedBitStreamParser$Mode.ASCII_ENCODE:Lcom/google/zxing/datamatrix/decoder/DecodedBitStreamParser$Mode;
      60: if_acmpne     76
      63: aload_1
      64: aload_2
      65: aload_3
      66: aload         6
      68: invokestatic  #13                 // Method decodeAsciiSegment:(Lcom/google/zxing/common/BitSource;Lcom/google/zxing/common/ECIStringBuilder;Ljava/lang/StringBuilder;Ljava/util/Set;)Lcom/google/zxing/datamatrix/decoder/DecodedBitStreamParser$Mode;
      71: astore        5
      73: goto          190
      76: getstatic     #14                 // Field com/google/zxing/datamatrix/decoder/DecodedBitStreamParser$1.$SwitchMap$com$google$zxing$datamatrix$decoder$DecodedBitStreamParser$Mode:[I
      79: aload         5
      81: invokevirtual #15                 // Method com/google/zxing/datamatrix/decoder/DecodedBitStreamParser$Mode.ordinal:()I
      84: iaload
      85: tableswitch   { // 1 to 6
                     1: 124
                     2: 134
                     3: 144
                     4: 152
                     5: 160
                     6: 170
               default: 181
          }
     124: aload_1
     125: aload_2
     126: aload         6
     128: invokestatic  #16                 // Method decodeC40Segment:(Lcom/google/zxing/common/BitSource;Lcom/google/zxing/common/ECIStringBuilder;Ljava/util/Set;)V
     131: goto          185
     134: aload_1
     135: aload_2
     136: aload         6
     138: invokestatic  #17                 // Method decodeTextSegment:(Lcom/google/zxing/common/BitSource;Lcom/google/zxing/common/ECIStringBuilder;Ljava/util/Set;)V
     141: goto          185
     144: aload_1
     145: aload_2
     146: invokestatic  #18                 // Method decodeAnsiX12Segment:(Lcom/google/zxing/common/BitSource;Lcom/google/zxing/common/ECIStringBuilder;)V
     149: goto          185
     152: aload_1
     153: aload_2
     154: invokestatic  #19                 // Method decodeEdifactSegment:(Lcom/google/zxing/common/BitSource;Lcom/google/zxing/common/ECIStringBuilder;)V
     157: goto          185
     160: aload_1
     161: aload_2
     162: aload         4
     164: invokestatic  #20                 // Method decodeBase256Segment:(Lcom/google/zxing/common/BitSource;Lcom/google/zxing/common/ECIStringBuilder;Ljava/util/Collection;)V
     167: goto          185
     170: aload_1
     171: aload_2
     172: invokestatic  #21                 // Method decodeECISegment:(Lcom/google/zxing/common/BitSource;Lcom/google/zxing/common/ECIStringBuilder;)V
     175: iconst_1
     176: istore        8
     178: goto          185
     181: invokestatic  #22                 // Method com/google/zxing/FormatException.getFormatInstance:()Lcom/google/zxing/FormatException;
     184: athrow
     185: getstatic     #10                 // Field com/google/zxing/datamatrix/decoder/DecodedBitStreamParser$Mode.ASCII_ENCODE:Lcom/google/zxing/datamatrix/decoder/DecodedBitStreamParser$Mode;
     188: astore        5
     190: aload         5
     192: getstatic     #23                 // Field com/google/zxing/datamatrix/decoder/DecodedBitStreamParser$Mode.PAD_ENCODE:Lcom/google/zxing/datamatrix/decoder/DecodedBitStreamParser$Mode;
     195: if_acmpeq     205
     198: aload_1
     199: invokevirtual #24                 // Method com/google/zxing/common/BitSource.available:()I
     202: ifgt          55
     205: aload_3
     206: invokevirtual #25                 // Method java/lang/StringBuilder.length:()I
     209: ifle          217
     212: aload_2
     213: aload_3
     214: invokevirtual #26                 // Method com/google/zxing/common/ECIStringBuilder.appendCharacters:(Ljava/lang/StringBuilder;)V
     217: iload         8
     219: ifeq          297
     222: aload         6
     224: iconst_0
     225: invokestatic  #27                 // Method java/lang/Integer.valueOf:(I)Ljava/lang/Integer;
     228: invokeinterface #28,  2           // InterfaceMethod java/util/Set.contains:(Ljava/lang/Object;)Z
     233: ifne          250
     236: aload         6
     238: iconst_4
     239: invokestatic  #27                 // Method java/lang/Integer.valueOf:(I)Ljava/lang/Integer;
     242: invokeinterface #28,  2           // InterfaceMethod java/util/Set.contains:(Ljava/lang/Object;)Z
     247: ifeq          256
     250: iconst_5
     251: istore        7
     253: goto          368
     256: aload         6
     258: iconst_1
     259: invokestatic  #27                 // Method java/lang/Integer.valueOf:(I)Ljava/lang/Integer;
     262: invokeinterface #28,  2           // InterfaceMethod java/util/Set.contains:(Ljava/lang/Object;)Z
     267: ifne          284
     270: aload         6
     272: iconst_5
     273: invokestatic  #27                 // Method java/lang/Integer.valueOf:(I)Ljava/lang/Integer;
     276: invokeinterface #28,  2           // InterfaceMethod java/util/Set.contains:(Ljava/lang/Object;)Z
     281: ifeq          291
     284: bipush        6
     286: istore        7
     288: goto          368
     291: iconst_4
     292: istore        7
     294: goto          368
     297: aload         6
     299: iconst_0
     300: invokestatic  #27                 // Method java/lang/Integer.valueOf:(I)Ljava/lang/Integer;
     303: invokeinterface #28,  2           // InterfaceMethod java/util/Set.contains:(Ljava/lang/Object;)Z
     308: ifne          325
     311: aload         6
     313: iconst_4
     314: invokestatic  #27                 // Method java/lang/Integer.valueOf:(I)Ljava/lang/Integer;
     317: invokeinterface #28,  2           // InterfaceMethod java/util/Set.contains:(Ljava/lang/Object;)Z
     322: ifeq          331
     325: iconst_2
     326: istore        7
     328: goto          368
     331: aload         6
     333: iconst_1
     334: invokestatic  #27                 // Method java/lang/Integer.valueOf:(I)Ljava/lang/Integer;
     337: invokeinterface #28,  2           // InterfaceMethod java/util/Set.contains:(Ljava/lang/Object;)Z
     342: ifne          359
     345: aload         6
     347: iconst_5
     348: invokestatic  #27                 // Method java/lang/Integer.valueOf:(I)Ljava/lang/Integer;
     351: invokeinterface #28,  2           // InterfaceMethod java/util/Set.contains:(Ljava/lang/Object;)Z
     356: ifeq          365
     359: iconst_3
     360: istore        7
     362: goto          368
     365: iconst_1
     366: istore        7
     368: new           #29                 // class com/google/zxing/common/DecoderResult
     371: dup
     372: aload_0
     373: aload_2
     374: invokevirtual #30                 // Method com/google/zxing/common/ECIStringBuilder.toString:()Ljava/lang/String;
     377: aload         4
     379: invokeinterface #31,  1           // InterfaceMethod java/util/List.isEmpty:()Z
     384: ifeq          391
     387: aconst_null
     388: goto          393
     391: aload         4
     393: aconst_null
     394: iload         7
     396: invokespecial #32                 // Method com/google/zxing/common/DecoderResult."<init>":([BLjava/lang/String;Ljava/util/List;Ljava/lang/String;I)V
     399: areturn

  private static com.google.zxing.datamatrix.decoder.DecodedBitStreamParser$Mode decodeAsciiSegment(com.google.zxing.common.BitSource, com.google.zxing.common.ECIStringBuilder, java.lang.StringBuilder, java.util.Set<java.lang.Integer>) throws com.google.zxing.FormatException;
    Code:
       0: iconst_0
       1: istore        4
       3: aload_0
       4: bipush        8
       6: invokevirtual #33                 // Method com/google/zxing/common/BitSource.readBits:(I)I
       9: istore        5
      11: iload         5
      13: ifne          20
      16: invokestatic  #22                 // Method com/google/zxing/FormatException.getFormatInstance:()Lcom/google/zxing/FormatException;
      19: athrow
      20: iload         5
      22: sipush        128
      25: if_icmpgt     52
      28: iload         4
      30: ifeq          39
      33: iinc_w        5, 128
      39: aload_1
      40: iload         5
      42: iconst_1
      43: isub
      44: i2c
      45: invokevirtual #34                 // Method com/google/zxing/common/ECIStringBuilder.append:(C)V
      48: getstatic     #10                 // Field com/google/zxing/datamatrix/decoder/DecodedBitStreamParser$Mode.ASCII_ENCODE:Lcom/google/zxing/datamatrix/decoder/DecodedBitStreamParser$Mode;
      51: areturn
      52: iload         5
      54: sipush        129
      57: if_icmpne     64
      60: getstatic     #23                 // Field com/google/zxing/datamatrix/decoder/DecodedBitStreamParser$Mode.PAD_ENCODE:Lcom/google/zxing/datamatrix/decoder/DecodedBitStreamParser$Mode;
      63: areturn
      64: iload         5
      66: sipush        229
      69: if_icmpgt     102
      72: iload         5
      74: sipush        130
      77: isub
      78: istore        6
      80: iload         6
      82: bipush        10
      84: if_icmpge     93
      87: aload_1
      88: bipush        48
      90: invokevirtual #34                 // Method com/google/zxing/common/ECIStringBuilder.append:(C)V
      93: aload_1
      94: iload         6
      96: invokevirtual #35                 // Method com/google/zxing/common/ECIStringBuilder.append:(I)V
      99: goto          277
     102: iload         5
     104: tableswitch   { // 230 to 241
                   230: 168
                   231: 172
                   232: 176
                   233: 199
                   234: 199
                   235: 202
                   236: 208
                   237: 225
                   238: 242
                   239: 246
                   240: 250
                   241: 254
               default: 258
          }
     168: getstatic     #36                 // Field com/google/zxing/datamatrix/decoder/DecodedBitStreamParser$Mode.C40_ENCODE:Lcom/google/zxing/datamatrix/decoder/DecodedBitStreamParser$Mode;
     171: areturn
     172: getstatic     #37                 // Field com/google/zxing/datamatrix/decoder/DecodedBitStreamParser$Mode.BASE256_ENCODE:Lcom/google/zxing/datamatrix/decoder/DecodedBitStreamParser$Mode;
     175: areturn
     176: aload_3
     177: aload_1
     178: invokevirtual #38                 // Method com/google/zxing/common/ECIStringBuilder.length:()I
     181: invokestatic  #27                 // Method java/lang/Integer.valueOf:(I)Ljava/lang/Integer;
     184: invokeinterface #39,  2           // InterfaceMethod java/util/Set.add:(Ljava/lang/Object;)Z
     189: pop
     190: aload_1
     191: bipush        29
     193: invokevirtual #34                 // Method com/google/zxing/common/ECIStringBuilder.append:(C)V
     196: goto          277
     199: goto          277
     202: iconst_1
     203: istore        4
     205: goto          277
     208: aload_1
     209: ldc           #40                 // String [)>\u001e05\u001d
     211: invokevirtual #41                 // Method com/google/zxing/common/ECIStringBuilder.append:(Ljava/lang/String;)V
     214: aload_2
     215: iconst_0
     216: ldc           #42                 // String \u001e\u0004
     218: invokevirtual #43                 // Method java/lang/StringBuilder.insert:(ILjava/lang/String;)Ljava/lang/StringBuilder;
     221: pop
     222: goto          277
     225: aload_1
     226: ldc           #44                 // String [)>\u001e06\u001d
     228: invokevirtual #41                 // Method com/google/zxing/common/ECIStringBuilder.append:(Ljava/lang/String;)V
     231: aload_2
     232: iconst_0
     233: ldc           #42                 // String \u001e\u0004
     235: invokevirtual #43                 // Method java/lang/StringBuilder.insert:(ILjava/lang/String;)Ljava/lang/StringBuilder;
     238: pop
     239: goto          277
     242: getstatic     #45                 // Field com/google/zxing/datamatrix/decoder/DecodedBitStreamParser$Mode.ANSIX12_ENCODE:Lcom/google/zxing/datamatrix/decoder/DecodedBitStreamParser$Mode;
     245: areturn
     246: getstatic     #46                 // Field com/google/zxing/datamatrix/decoder/DecodedBitStreamParser$Mode.TEXT_ENCODE:Lcom/google/zxing/datamatrix/decoder/DecodedBitStreamParser$Mode;
     249: areturn
     250: getstatic     #47                 // Field com/google/zxing/datamatrix/decoder/DecodedBitStreamParser$Mode.EDIFACT_ENCODE:Lcom/google/zxing/datamatrix/decoder/DecodedBitStreamParser$Mode;
     253: areturn
     254: getstatic     #48                 // Field com/google/zxing/datamatrix/decoder/DecodedBitStreamParser$Mode.ECI_ENCODE:Lcom/google/zxing/datamatrix/decoder/DecodedBitStreamParser$Mode;
     257: areturn
     258: iload         5
     260: sipush        254
     263: if_icmpne     273
     266: aload_0
     267: invokevirtual #24                 // Method com/google/zxing/common/BitSource.available:()I
     270: ifeq          277
     273: invokestatic  #22                 // Method com/google/zxing/FormatException.getFormatInstance:()Lcom/google/zxing/FormatException;
     276: athrow
     277: aload_0
     278: invokevirtual #24                 // Method com/google/zxing/common/BitSource.available:()I
     281: ifgt          3
     284: getstatic     #10                 // Field com/google/zxing/datamatrix/decoder/DecodedBitStreamParser$Mode.ASCII_ENCODE:Lcom/google/zxing/datamatrix/decoder/DecodedBitStreamParser$Mode;
     287: areturn

  private static void decodeC40Segment(com.google.zxing.common.BitSource, com.google.zxing.common.ECIStringBuilder, java.util.Set<java.lang.Integer>) throws com.google.zxing.FormatException;
    Code:
       0: iconst_0
       1: istore_3
       2: iconst_3
       3: newarray       int
       5: astore        4
       7: iconst_0
       8: istore        5
      10: aload_0
      11: invokevirtual #24                 // Method com/google/zxing/common/BitSource.available:()I
      14: bipush        8
      16: if_icmpne     20
      19: return
      20: aload_0
      21: bipush        8
      23: invokevirtual #33                 // Method com/google/zxing/common/BitSource.readBits:(I)I
      26: istore        6
      28: iload         6
      30: sipush        254
      33: if_icmpne     37
      36: return
      37: iload         6
      39: aload_0
      40: bipush        8
      42: invokevirtual #33                 // Method com/google/zxing/common/BitSource.readBits:(I)I
      45: aload         4
      47: invokestatic  #49                 // Method parseTwoBytes:(II[I)V
      50: iconst_0
      51: istore        7
      53: iload         7
      55: iconst_3
      56: if_icmpge     356
      59: aload         4
      61: iload         7
      63: iaload
      64: istore        8
      66: iload         5
      68: tableswitch   { // 0 to 3
                     0: 100
                     1: 165
                     2: 198
                     3: 310
               default: 346
          }
     100: iload         8
     102: iconst_3
     103: if_icmpge     115
     106: iload         8
     108: iconst_1
     109: iadd
     110: istore        5
     112: goto          350
     115: iload         8
     117: getstatic     #50                 // Field C40_BASIC_SET_CHARS:[C
     120: arraylength
     121: if_icmpge     161
     124: getstatic     #50                 // Field C40_BASIC_SET_CHARS:[C
     127: iload         8
     129: caload
     130: istore        9
     132: iload_3
     133: ifeq          152
     136: aload_1
     137: iload         9
     139: sipush        128
     142: iadd
     143: i2c
     144: invokevirtual #34                 // Method com/google/zxing/common/ECIStringBuilder.append:(C)V
     147: iconst_0
     148: istore_3
     149: goto          158
     152: aload_1
     153: iload         9
     155: invokevirtual #34                 // Method com/google/zxing/common/ECIStringBuilder.append:(C)V
     158: goto          350
     161: invokestatic  #22                 // Method com/google/zxing/FormatException.getFormatInstance:()Lcom/google/zxing/FormatException;
     164: athrow
     165: iload_3
     166: ifeq          185
     169: aload_1
     170: iload         8
     172: sipush        128
     175: iadd
     176: i2c
     177: invokevirtual #34                 // Method com/google/zxing/common/ECIStringBuilder.append:(C)V
     180: iconst_0
     181: istore_3
     182: goto          192
     185: aload_1
     186: iload         8
     188: i2c
     189: invokevirtual #34                 // Method com/google/zxing/common/ECIStringBuilder.append:(C)V
     192: iconst_0
     193: istore        5
     195: goto          350
     198: iload         8
     200: getstatic     #51                 // Field C40_SHIFT2_SET_CHARS:[C
     203: arraylength
     204: if_icmpge     244
     207: getstatic     #51                 // Field C40_SHIFT2_SET_CHARS:[C
     210: iload         8
     212: caload
     213: istore        9
     215: iload_3
     216: ifeq          235
     219: aload_1
     220: iload         9
     222: sipush        128
     225: iadd
     226: i2c
     227: invokevirtual #34                 // Method com/google/zxing/common/ECIStringBuilder.append:(C)V
     230: iconst_0
     231: istore_3
     232: goto          241
     235: aload_1
     236: iload         9
     238: invokevirtual #34                 // Method com/google/zxing/common/ECIStringBuilder.append:(C)V
     241: goto          304
     244: iload         8
     246: lookupswitch  { // 2
                    27: 272
                    30: 295
               default: 300
          }
     272: aload_2
     273: aload_1
     274: invokevirtual #38                 // Method com/google/zxing/common/ECIStringBuilder.length:()I
     277: invokestatic  #27                 // Method java/lang/Integer.valueOf:(I)Ljava/lang/Integer;
     280: invokeinterface #39,  2           // InterfaceMethod java/util/Set.add:(Ljava/lang/Object;)Z
     285: pop
     286: aload_1
     287: bipush        29
     289: invokevirtual #34                 // Method com/google/zxing/common/ECIStringBuilder.append:(C)V
     292: goto          304
     295: iconst_1
     296: istore_3
     297: goto          304
     300: invokestatic  #22                 // Method com/google/zxing/FormatException.getFormatInstance:()Lcom/google/zxing/FormatException;
     303: athrow
     304: iconst_0
     305: istore        5
     307: goto          350
     310: iload_3
     311: ifeq          330
     314: aload_1
     315: iload         8
     317: sipush        224
     320: iadd
     321: i2c
     322: invokevirtual #34                 // Method com/google/zxing/common/ECIStringBuilder.append:(C)V
     325: iconst_0
     326: istore_3
     327: goto          340
     330: aload_1
     331: iload         8
     333: bipush        96
     335: iadd
     336: i2c
     337: invokevirtual #34                 // Method com/google/zxing/common/ECIStringBuilder.append:(C)V
     340: iconst_0
     341: istore        5
     343: goto          350
     346: invokestatic  #22                 // Method com/google/zxing/FormatException.getFormatInstance:()Lcom/google/zxing/FormatException;
     349: athrow
     350: iinc          7, 1
     353: goto          53
     356: aload_0
     357: invokevirtual #24                 // Method com/google/zxing/common/BitSource.available:()I
     360: ifgt          10
     363: return

  private static void decodeTextSegment(com.google.zxing.common.BitSource, com.google.zxing.common.ECIStringBuilder, java.util.Set<java.lang.Integer>) throws com.google.zxing.FormatException;
    Code:
       0: iconst_0
       1: istore_3
       2: iconst_3
       3: newarray       int
       5: astore        4
       7: iconst_0
       8: istore        5
      10: aload_0
      11: invokevirtual #24                 // Method com/google/zxing/common/BitSource.available:()I
      14: bipush        8
      16: if_icmpne     20
      19: return
      20: aload_0
      21: bipush        8
      23: invokevirtual #33                 // Method com/google/zxing/common/BitSource.readBits:(I)I
      26: istore        6
      28: iload         6
      30: sipush        254
      33: if_icmpne     37
      36: return
      37: iload         6
      39: aload_0
      40: bipush        8
      42: invokevirtual #33                 // Method com/google/zxing/common/BitSource.readBits:(I)I
      45: aload         4
      47: invokestatic  #49                 // Method parseTwoBytes:(II[I)V
      50: iconst_0
      51: istore        7
      53: iload         7
      55: iconst_3
      56: if_icmpge     373
      59: aload         4
      61: iload         7
      63: iaload
      64: istore        8
      66: iload         5
      68: tableswitch   { // 0 to 3
                     0: 100
                     1: 165
                     2: 198
                     3: 310
               default: 363
          }
     100: iload         8
     102: iconst_3
     103: if_icmpge     115
     106: iload         8
     108: iconst_1
     109: iadd
     110: istore        5
     112: goto          367
     115: iload         8
     117: getstatic     #52                 // Field TEXT_BASIC_SET_CHARS:[C
     120: arraylength
     121: if_icmpge     161
     124: getstatic     #52                 // Field TEXT_BASIC_SET_CHARS:[C
     127: iload         8
     129: caload
     130: istore        9
     132: iload_3
     133: ifeq          152
     136: aload_1
     137: iload         9
     139: sipush        128
     142: iadd
     143: i2c
     144: invokevirtual #34                 // Method com/google/zxing/common/ECIStringBuilder.append:(C)V
     147: iconst_0
     148: istore_3
     149: goto          158
     152: aload_1
     153: iload         9
     155: invokevirtual #34                 // Method com/google/zxing/common/ECIStringBuilder.append:(C)V
     158: goto          367
     161: invokestatic  #22                 // Method com/google/zxing/FormatException.getFormatInstance:()Lcom/google/zxing/FormatException;
     164: athrow
     165: iload_3
     166: ifeq          185
     169: aload_1
     170: iload         8
     172: sipush        128
     175: iadd
     176: i2c
     177: invokevirtual #34                 // Method com/google/zxing/common/ECIStringBuilder.append:(C)V
     180: iconst_0
     181: istore_3
     182: goto          192
     185: aload_1
     186: iload         8
     188: i2c
     189: invokevirtual #34                 // Method com/google/zxing/common/ECIStringBuilder.append:(C)V
     192: iconst_0
     193: istore        5
     195: goto          367
     198: iload         8
     200: getstatic     #53                 // Field TEXT_SHIFT2_SET_CHARS:[C
     203: arraylength
     204: if_icmpge     244
     207: getstatic     #53                 // Field TEXT_SHIFT2_SET_CHARS:[C
     210: iload         8
     212: caload
     213: istore        9
     215: iload_3
     216: ifeq          235
     219: aload_1
     220: iload         9
     222: sipush        128
     225: iadd
     226: i2c
     227: invokevirtual #34                 // Method com/google/zxing/common/ECIStringBuilder.append:(C)V
     230: iconst_0
     231: istore_3
     232: goto          241
     235: aload_1
     236: iload         9
     238: invokevirtual #34                 // Method com/google/zxing/common/ECIStringBuilder.append:(C)V
     241: goto          304
     244: iload         8
     246: lookupswitch  { // 2
                    27: 272
                    30: 295
               default: 300
          }
     272: aload_2
     273: aload_1
     274: invokevirtual #38                 // Method com/google/zxing/common/ECIStringBuilder.length:()I
     277: invokestatic  #27                 // Method java/lang/Integer.valueOf:(I)Ljava/lang/Integer;
     280: invokeinterface #39,  2           // InterfaceMethod java/util/Set.add:(Ljava/lang/Object;)Z
     285: pop
     286: aload_1
     287: bipush        29
     289: invokevirtual #34                 // Method com/google/zxing/common/ECIStringBuilder.append:(C)V
     292: goto          304
     295: iconst_1
     296: istore_3
     297: goto          304
     300: invokestatic  #22                 // Method com/google/zxing/FormatException.getFormatInstance:()Lcom/google/zxing/FormatException;
     303: athrow
     304: iconst_0
     305: istore        5
     307: goto          367
     310: iload         8
     312: getstatic     #54                 // Field TEXT_SHIFT3_SET_CHARS:[C
     315: arraylength
     316: if_icmpge     359
     319: getstatic     #54                 // Field TEXT_SHIFT3_SET_CHARS:[C
     322: iload         8
     324: caload
     325: istore        9
     327: iload_3
     328: ifeq          347
     331: aload_1
     332: iload         9
     334: sipush        128
     337: iadd
     338: i2c
     339: invokevirtual #34                 // Method com/google/zxing/common/ECIStringBuilder.append:(C)V
     342: iconst_0
     343: istore_3
     344: goto          353
     347: aload_1
     348: iload         9
     350: invokevirtual #34                 // Method com/google/zxing/common/ECIStringBuilder.append:(C)V
     353: iconst_0
     354: istore        5
     356: goto          367
     359: invokestatic  #22                 // Method com/google/zxing/FormatException.getFormatInstance:()Lcom/google/zxing/FormatException;
     362: athrow
     363: invokestatic  #22                 // Method com/google/zxing/FormatException.getFormatInstance:()Lcom/google/zxing/FormatException;
     366: athrow
     367: iinc          7, 1
     370: goto          53
     373: aload_0
     374: invokevirtual #24                 // Method com/google/zxing/common/BitSource.available:()I
     377: ifgt          10
     380: return

  private static void decodeAnsiX12Segment(com.google.zxing.common.BitSource, com.google.zxing.common.ECIStringBuilder) throws com.google.zxing.FormatException;
    Code:
       0: iconst_3
       1: newarray       int
       3: astore_2
       4: aload_0
       5: invokevirtual #24                 // Method com/google/zxing/common/BitSource.available:()I
       8: bipush        8
      10: if_icmpne     14
      13: return
      14: aload_0
      15: bipush        8
      17: invokevirtual #33                 // Method com/google/zxing/common/BitSource.readBits:(I)I
      20: istore_3
      21: iload_3
      22: sipush        254
      25: if_icmpne     29
      28: return
      29: iload_3
      30: aload_0
      31: bipush        8
      33: invokevirtual #33                 // Method com/google/zxing/common/BitSource.readBits:(I)I
      36: aload_2
      37: invokestatic  #49                 // Method parseTwoBytes:(II[I)V
      40: iconst_0
      41: istore        4
      43: iload         4
      45: iconst_3
      46: if_icmpge     174
      49: aload_2
      50: iload         4
      52: iaload
      53: istore        5
      55: iload         5
      57: tableswitch   { // 0 to 3
                     0: 88
                     1: 97
                     2: 106
                     3: 115
               default: 124
          }
      88: aload_1
      89: bipush        13
      91: invokevirtual #34                 // Method com/google/zxing/common/ECIStringBuilder.append:(C)V
      94: goto          168
      97: aload_1
      98: bipush        42
     100: invokevirtual #34                 // Method com/google/zxing/common/ECIStringBuilder.append:(C)V
     103: goto          168
     106: aload_1
     107: bipush        62
     109: invokevirtual #34                 // Method com/google/zxing/common/ECIStringBuilder.append:(C)V
     112: goto          168
     115: aload_1
     116: bipush        32
     118: invokevirtual #34                 // Method com/google/zxing/common/ECIStringBuilder.append:(C)V
     121: goto          168
     124: iload         5
     126: bipush        14
     128: if_icmpge     144
     131: aload_1
     132: iload         5
     134: bipush        44
     136: iadd
     137: i2c
     138: invokevirtual #34                 // Method com/google/zxing/common/ECIStringBuilder.append:(C)V
     141: goto          168
     144: iload         5
     146: bipush        40
     148: if_icmpge     164
     151: aload_1
     152: iload         5
     154: bipush        51
     156: iadd
     157: i2c
     158: invokevirtual #34                 // Method com/google/zxing/common/ECIStringBuilder.append:(C)V
     161: goto          168
     164: invokestatic  #22                 // Method com/google/zxing/FormatException.getFormatInstance:()Lcom/google/zxing/FormatException;
     167: athrow
     168: iinc          4, 1
     171: goto          43
     174: aload_0
     175: invokevirtual #24                 // Method com/google/zxing/common/BitSource.available:()I
     178: ifgt          4
     181: return

  private static void parseTwoBytes(int, int, int[]);
    Code:
       0: iload_0
       1: bipush        8
       3: ishl
       4: iload_1
       5: iadd
       6: iconst_1
       7: isub
       8: istore_3
       9: iload_3
      10: sipush        1600
      13: idiv
      14: istore        4
      16: aload_2
      17: iconst_0
      18: iload         4
      20: iastore
      21: iload_3
      22: iload         4
      24: sipush        1600
      27: imul
      28: isub
      29: istore_3
      30: iload_3
      31: bipush        40
      33: idiv
      34: istore        4
      36: aload_2
      37: iconst_1
      38: iload         4
      40: iastore
      41: aload_2
      42: iconst_2
      43: iload_3
      44: iload         4
      46: bipush        40
      48: imul
      49: isub
      50: iastore
      51: return

  private static void decodeEdifactSegment(com.google.zxing.common.BitSource, com.google.zxing.common.ECIStringBuilder);
    Code:
       0: aload_0
       1: invokevirtual #24                 // Method com/google/zxing/common/BitSource.available:()I
       4: bipush        16
       6: if_icmpgt     10
       9: return
      10: iconst_0
      11: istore_2
      12: iload_2
      13: iconst_4
      14: if_icmpge     78
      17: aload_0
      18: bipush        6
      20: invokevirtual #33                 // Method com/google/zxing/common/BitSource.readBits:(I)I
      23: istore_3
      24: iload_3
      25: bipush        31
      27: if_icmpne     54
      30: bipush        8
      32: aload_0
      33: invokevirtual #55                 // Method com/google/zxing/common/BitSource.getBitOffset:()I
      36: isub
      37: istore        4
      39: iload         4
      41: bipush        8
      43: if_icmpeq     53
      46: aload_0
      47: iload         4
      49: invokevirtual #33                 // Method com/google/zxing/common/BitSource.readBits:(I)I
      52: pop
      53: return
      54: iload_3
      55: bipush        32
      57: iand
      58: ifne          66
      61: iload_3
      62: bipush        64
      64: ior
      65: istore_3
      66: aload_1
      67: iload_3
      68: i2c
      69: invokevirtual #34                 // Method com/google/zxing/common/ECIStringBuilder.append:(C)V
      72: iinc          2, 1
      75: goto          12
      78: aload_0
      79: invokevirtual #24                 // Method com/google/zxing/common/BitSource.available:()I
      82: ifgt          0
      85: return

  private static void decodeBase256Segment(com.google.zxing.common.BitSource, com.google.zxing.common.ECIStringBuilder, java.util.Collection<byte[]>) throws com.google.zxing.FormatException;
    Code:
       0: iconst_1
       1: aload_0
       2: invokevirtual #56                 // Method com/google/zxing/common/BitSource.getByteOffset:()I
       5: iadd
       6: istore_3
       7: aload_0
       8: bipush        8
      10: invokevirtual #33                 // Method com/google/zxing/common/BitSource.readBits:(I)I
      13: iload_3
      14: iinc          3, 1
      17: invokestatic  #57                 // Method unrandomize255State:(II)I
      20: istore        4
      22: iload         4
      24: ifne          39
      27: aload_0
      28: invokevirtual #24                 // Method com/google/zxing/common/BitSource.available:()I
      31: bipush        8
      33: idiv
      34: istore        5
      36: goto          80
      39: iload         4
      41: sipush        250
      44: if_icmpge     54
      47: iload         4
      49: istore        5
      51: goto          80
      54: sipush        250
      57: iload         4
      59: sipush        249
      62: isub
      63: imul
      64: aload_0
      65: bipush        8
      67: invokevirtual #33                 // Method com/google/zxing/common/BitSource.readBits:(I)I
      70: iload_3
      71: iinc          3, 1
      74: invokestatic  #57                 // Method unrandomize255State:(II)I
      77: iadd
      78: istore        5
      80: iload         5
      82: ifge          89
      85: invokestatic  #22                 // Method com/google/zxing/FormatException.getFormatInstance:()Lcom/google/zxing/FormatException;
      88: athrow
      89: iload         5
      91: newarray       byte
      93: astore        6
      95: iconst_0
      96: istore        7
      98: iload         7
     100: iload         5
     102: if_icmpge     143
     105: aload_0
     106: invokevirtual #24                 // Method com/google/zxing/common/BitSource.available:()I
     109: bipush        8
     111: if_icmpge     118
     114: invokestatic  #22                 // Method com/google/zxing/FormatException.getFormatInstance:()Lcom/google/zxing/FormatException;
     117: athrow
     118: aload         6
     120: iload         7
     122: aload_0
     123: bipush        8
     125: invokevirtual #33                 // Method com/google/zxing/common/BitSource.readBits:(I)I
     128: iload_3
     129: iinc          3, 1
     132: invokestatic  #57                 // Method unrandomize255State:(II)I
     135: i2b
     136: bastore
     137: iinc          7, 1
     140: goto          98
     143: aload_2
     144: aload         6
     146: invokeinterface #58,  2           // InterfaceMethod java/util/Collection.add:(Ljava/lang/Object;)Z
     151: pop
     152: aload_1
     153: new           #59                 // class java/lang/String
     156: dup
     157: aload         6
     159: getstatic     #60                 // Field java/nio/charset/StandardCharsets.ISO_8859_1:Ljava/nio/charset/Charset;
     162: invokespecial #61                 // Method java/lang/String."<init>":([BLjava/nio/charset/Charset;)V
     165: invokevirtual #41                 // Method com/google/zxing/common/ECIStringBuilder.append:(Ljava/lang/String;)V
     168: return

  private static void decodeECISegment(com.google.zxing.common.BitSource, com.google.zxing.common.ECIStringBuilder) throws com.google.zxing.FormatException;
    Code:
       0: aload_0
       1: invokevirtual #24                 // Method com/google/zxing/common/BitSource.available:()I
       4: bipush        8
       6: if_icmpge     13
       9: invokestatic  #22                 // Method com/google/zxing/FormatException.getFormatInstance:()Lcom/google/zxing/FormatException;
      12: athrow
      13: aload_0
      14: bipush        8
      16: invokevirtual #33                 // Method com/google/zxing/common/BitSource.readBits:(I)I
      19: istore_2
      20: iload_2
      21: bipush        127
      23: if_icmpgt     33
      26: aload_1
      27: iload_2
      28: iconst_1
      29: isub
      30: invokevirtual #62                 // Method com/google/zxing/common/ECIStringBuilder.appendECI:(I)V
      33: return

  private static int unrandomize255State(int, int);
    Code:
       0: sipush        149
       3: iload_1
       4: imul
       5: sipush        255
       8: irem
       9: iconst_1
      10: iadd
      11: istore_2
      12: iload_0
      13: iload_2
      14: isub
      15: istore_3
      16: iload_3
      17: iflt          24
      20: iload_3
      21: goto          29
      24: iload_3
      25: sipush        256
      28: iadd
      29: ireturn

  static {};
    Code:
       0: bipush        40
       2: newarray       char
       4: dup
       5: iconst_0
       6: bipush        42
       8: castore
       9: dup
      10: iconst_1
      11: bipush        42
      13: castore
      14: dup
      15: iconst_2
      16: bipush        42
      18: castore
      19: dup
      20: iconst_3
      21: bipush        32
      23: castore
      24: dup
      25: iconst_4
      26: bipush        48
      28: castore
      29: dup
      30: iconst_5
      31: bipush        49
      33: castore
      34: dup
      35: bipush        6
      37: bipush        50
      39: castore
      40: dup
      41: bipush        7
      43: bipush        51
      45: castore
      46: dup
      47: bipush        8
      49: bipush        52
      51: castore
      52: dup
      53: bipush        9
      55: bipush        53
      57: castore
      58: dup
      59: bipush        10
      61: bipush        54
      63: castore
      64: dup
      65: bipush        11
      67: bipush        55
      69: castore
      70: dup
      71: bipush        12
      73: bipush        56
      75: castore
      76: dup
      77: bipush        13
      79: bipush        57
      81: castore
      82: dup
      83: bipush        14
      85: bipush        65
      87: castore
      88: dup
      89: bipush        15
      91: bipush        66
      93: castore
      94: dup
      95: bipush        16
      97: bipush        67
      99: castore
     100: dup
     101: bipush        17
     103: bipush        68
     105: castore
     106: dup
     107: bipush        18
     109: bipush        69
     111: castore
     112: dup
     113: bipush        19
     115: bipush        70
     117: castore
     118: dup
     119: bipush        20
     121: bipush        71
     123: castore
     124: dup
     125: bipush        21
     127: bipush        72
     129: castore
     130: dup
     131: bipush        22
     133: bipush        73
     135: castore
     136: dup
     137: bipush        23
     139: bipush        74
     141: castore
     142: dup
     143: bipush        24
     145: bipush        75
     147: castore
     148: dup
     149: bipush        25
     151: bipush        76
     153: castore
     154: dup
     155: bipush        26
     157: bipush        77
     159: castore
     160: dup
     161: bipush        27
     163: bipush        78
     165: castore
     166: dup
     167: bipush        28
     169: bipush        79
     171: castore
     172: dup
     173: bipush        29
     175: bipush        80
     177: castore
     178: dup
     179: bipush        30
     181: bipush        81
     183: castore
     184: dup
     185: bipush        31
     187: bipush        82
     189: castore
     190: dup
     191: bipush        32
     193: bipush        83
     195: castore
     196: dup
     197: bipush        33
     199: bipush        84
     201: castore
     202: dup
     203: bipush        34
     205: bipush        85
     207: castore
     208: dup
     209: bipush        35
     211: bipush        86
     213: castore
     214: dup
     215: bipush        36
     217: bipush        87
     219: castore
     220: dup
     221: bipush        37
     223: bipush        88
     225: castore
     226: dup
     227: bipush        38
     229: bipush        89
     231: castore
     232: dup
     233: bipush        39
     235: bipush        90
     237: castore
     238: putstatic     #50                 // Field C40_BASIC_SET_CHARS:[C
     241: bipush        27
     243: newarray       char
     245: dup
     246: iconst_0
     247: bipush        33
     249: castore
     250: dup
     251: iconst_1
     252: bipush        34
     254: castore
     255: dup
     256: iconst_2
     257: bipush        35
     259: castore
     260: dup
     261: iconst_3
     262: bipush        36
     264: castore
     265: dup
     266: iconst_4
     267: bipush        37
     269: castore
     270: dup
     271: iconst_5
     272: bipush        38
     274: castore
     275: dup
     276: bipush        6
     278: bipush        39
     280: castore
     281: dup
     282: bipush        7
     284: bipush        40
     286: castore
     287: dup
     288: bipush        8
     290: bipush        41
     292: castore
     293: dup
     294: bipush        9
     296: bipush        42
     298: castore
     299: dup
     300: bipush        10
     302: bipush        43
     304: castore
     305: dup
     306: bipush        11
     308: bipush        44
     310: castore
     311: dup
     312: bipush        12
     314: bipush        45
     316: castore
     317: dup
     318: bipush        13
     320: bipush        46
     322: castore
     323: dup
     324: bipush        14
     326: bipush        47
     328: castore
     329: dup
     330: bipush        15
     332: bipush        58
     334: castore
     335: dup
     336: bipush        16
     338: bipush        59
     340: castore
     341: dup
     342: bipush        17
     344: bipush        60
     346: castore
     347: dup
     348: bipush        18
     350: bipush        61
     352: castore
     353: dup
     354: bipush        19
     356: bipush        62
     358: castore
     359: dup
     360: bipush        20
     362: bipush        63
     364: castore
     365: dup
     366: bipush        21
     368: bipush        64
     370: castore
     371: dup
     372: bipush        22
     374: bipush        91
     376: castore
     377: dup
     378: bipush        23
     380: bipush        92
     382: castore
     383: dup
     384: bipush        24
     386: bipush        93
     388: castore
     389: dup
     390: bipush        25
     392: bipush        94
     394: castore
     395: dup
     396: bipush        26
     398: bipush        95
     400: castore
     401: putstatic     #51                 // Field C40_SHIFT2_SET_CHARS:[C
     404: bipush        40
     406: newarray       char
     408: dup
     409: iconst_0
     410: bipush        42
     412: castore
     413: dup
     414: iconst_1
     415: bipush        42
     417: castore
     418: dup
     419: iconst_2
     420: bipush        42
     422: castore
     423: dup
     424: iconst_3
     425: bipush        32
     427: castore
     428: dup
     429: iconst_4
     430: bipush        48
     432: castore
     433: dup
     434: iconst_5
     435: bipush        49
     437: castore
     438: dup
     439: bipush        6
     441: bipush        50
     443: castore
     444: dup
     445: bipush        7
     447: bipush        51
     449: castore
     450: dup
     451: bipush        8
     453: bipush        52
     455: castore
     456: dup
     457: bipush        9
     459: bipush        53
     461: castore
     462: dup
     463: bipush        10
     465: bipush        54
     467: castore
     468: dup
     469: bipush        11
     471: bipush        55
     473: castore
     474: dup
     475: bipush        12
     477: bipush        56
     479: castore
     480: dup
     481: bipush        13
     483: bipush        57
     485: castore
     486: dup
     487: bipush        14
     489: bipush        97
     491: castore
     492: dup
     493: bipush        15
     495: bipush        98
     497: castore
     498: dup
     499: bipush        16
     501: bipush        99
     503: castore
     504: dup
     505: bipush        17
     507: bipush        100
     509: castore
     510: dup
     511: bipush        18
     513: bipush        101
     515: castore
     516: dup
     517: bipush        19
     519: bipush        102
     521: castore
     522: dup
     523: bipush        20
     525: bipush        103
     527: castore
     528: dup
     529: bipush        21
     531: bipush        104
     533: castore
     534: dup
     535: bipush        22
     537: bipush        105
     539: castore
     540: dup
     541: bipush        23
     543: bipush        106
     545: castore
     546: dup
     547: bipush        24
     549: bipush        107
     551: castore
     552: dup
     553: bipush        25
     555: bipush        108
     557: castore
     558: dup
     559: bipush        26
     561: bipush        109
     563: castore
     564: dup
     565: bipush        27
     567: bipush        110
     569: castore
     570: dup
     571: bipush        28
     573: bipush        111
     575: castore
     576: dup
     577: bipush        29
     579: bipush        112
     581: castore
     582: dup
     583: bipush        30
     585: bipush        113
     587: castore
     588: dup
     589: bipush        31
     591: bipush        114
     593: castore
     594: dup
     595: bipush        32
     597: bipush        115
     599: castore
     600: dup
     601: bipush        33
     603: bipush        116
     605: castore
     606: dup
     607: bipush        34
     609: bipush        117
     611: castore
     612: dup
     613: bipush        35
     615: bipush        118
     617: castore
     618: dup
     619: bipush        36
     621: bipush        119
     623: castore
     624: dup
     625: bipush        37
     627: bipush        120
     629: castore
     630: dup
     631: bipush        38
     633: bipush        121
     635: castore
     636: dup
     637: bipush        39
     639: bipush        122
     641: castore
     642: putstatic     #52                 // Field TEXT_BASIC_SET_CHARS:[C
     645: getstatic     #51                 // Field C40_SHIFT2_SET_CHARS:[C
     648: putstatic     #53                 // Field TEXT_SHIFT2_SET_CHARS:[C
     651: bipush        32
     653: newarray       char
     655: dup
     656: iconst_0
     657: bipush        96
     659: castore
     660: dup
     661: iconst_1
     662: bipush        65
     664: castore
     665: dup
     666: iconst_2
     667: bipush        66
     669: castore
     670: dup
     671: iconst_3
     672: bipush        67
     674: castore
     675: dup
     676: iconst_4
     677: bipush        68
     679: castore
     680: dup
     681: iconst_5
     682: bipush        69
     684: castore
     685: dup
     686: bipush        6
     688: bipush        70
     690: castore
     691: dup
     692: bipush        7
     694: bipush        71
     696: castore
     697: dup
     698: bipush        8
     700: bipush        72
     702: castore
     703: dup
     704: bipush        9
     706: bipush        73
     708: castore
     709: dup
     710: bipush        10
     712: bipush        74
     714: castore
     715: dup
     716: bipush        11
     718: bipush        75
     720: castore
     721: dup
     722: bipush        12
     724: bipush        76
     726: castore
     727: dup
     728: bipush        13
     730: bipush        77
     732: castore
     733: dup
     734: bipush        14
     736: bipush        78
     738: castore
     739: dup
     740: bipush        15
     742: bipush        79
     744: castore
     745: dup
     746: bipush        16
     748: bipush        80
     750: castore
     751: dup
     752: bipush        17
     754: bipush        81
     756: castore
     757: dup
     758: bipush        18
     760: bipush        82
     762: castore
     763: dup
     764: bipush        19
     766: bipush        83
     768: castore
     769: dup
     770: bipush        20
     772: bipush        84
     774: castore
     775: dup
     776: bipush        21
     778: bipush        85
     780: castore
     781: dup
     782: bipush        22
     784: bipush        86
     786: castore
     787: dup
     788: bipush        23
     790: bipush        87
     792: castore
     793: dup
     794: bipush        24
     796: bipush        88
     798: castore
     799: dup
     800: bipush        25
     802: bipush        89
     804: castore
     805: dup
     806: bipush        26
     808: bipush        90
     810: castore
     811: dup
     812: bipush        27
     814: bipush        123
     816: castore
     817: dup
     818: bipush        28
     820: bipush        124
     822: castore
     823: dup
     824: bipush        29
     826: bipush        125
     828: castore
     829: dup
     830: bipush        30
     832: bipush        126
     834: castore
     835: dup
     836: bipush        31
     838: bipush        127
     840: castore
     841: putstatic     #54                 // Field TEXT_SHIFT3_SET_CHARS:[C
     844: return
}
