Compiled from "DecodedBitStreamParser.java"
final class com.google.zxing.datamatrix.decoder.DecodedBitStreamParser$Mode extends java.lang.Enum<com.google.zxing.datamatrix.decoder.DecodedBitStreamParser$Mode> {
  public static final com.google.zxing.datamatrix.decoder.DecodedBitStreamParser$Mode PAD_ENCODE;

  public static final com.google.zxing.datamatrix.decoder.DecodedBitStreamParser$Mode ASCII_ENCODE;

  public static final com.google.zxing.datamatrix.decoder.DecodedBitStreamParser$Mode C40_ENCODE;

  public static final com.google.zxing.datamatrix.decoder.DecodedBitStreamParser$Mode TEXT_ENCODE;

  public static final com.google.zxing.datamatrix.decoder.DecodedBitStreamParser$Mode ANSIX12_ENCODE;

  public static final com.google.zxing.datamatrix.decoder.DecodedBitStreamParser$Mode EDIFACT_ENCODE;

  public static final com.google.zxing.datamatrix.decoder.DecodedBitStreamParser$Mode BASE256_ENCODE;

  public static final com.google.zxing.datamatrix.decoder.DecodedBitStreamParser$Mode ECI_ENCODE;

  private static final com.google.zxing.datamatrix.decoder.DecodedBitStreamParser$Mode[] $VALUES;

  public static com.google.zxing.datamatrix.decoder.DecodedBitStreamParser$Mode[] values();
    Code:
       0: getstatic     #1                  // Field $VALUES:[Lcom/google/zxing/datamatrix/decoder/DecodedBitStreamParser$Mode;
       3: invokevirtual #2                  // Method "[Lcom/google/zxing/datamatrix/decoder/DecodedBitStreamParser$Mode;".clone:()Ljava/lang/Object;
       6: checkcast     #3                  // class "[Lcom/google/zxing/datamatrix/decoder/DecodedBitStreamParser$Mode;"
       9: areturn

  public static com.google.zxing.datamatrix.decoder.DecodedBitStreamParser$Mode valueOf(java.lang.String);
    Code:
       0: ldc           #4                  // class com/google/zxing/datamatrix/decoder/DecodedBitStreamParser$Mode
       2: aload_0
       3: invokestatic  #5                  // Method java/lang/Enum.valueOf:(Ljava/lang/Class;Ljava/lang/String;)Ljava/lang/Enum;
       6: checkcast     #4                  // class com/google/zxing/datamatrix/decoder/DecodedBitStreamParser$Mode
       9: areturn

  private com.google.zxing.datamatrix.decoder.DecodedBitStreamParser$Mode();
    Code:
       0: aload_0
       1: aload_1
       2: iload_2
       3: invokespecial #6                  // Method java/lang/Enum."<init>":(Ljava/lang/String;I)V
       6: return

  static {};
    Code:
       0: new           #4                  // class com/google/zxing/datamatrix/decoder/DecodedBitStreamParser$Mode
       3: dup
       4: ldc           #7                  // String PAD_ENCODE
       6: iconst_0
       7: invokespecial #8                  // Method "<init>":(Ljava/lang/String;I)V
      10: putstatic     #9                  // Field PAD_ENCODE:Lcom/google/zxing/datamatrix/decoder/DecodedBitStreamParser$Mode;
      13: new           #4                  // class com/google/zxing/datamatrix/decoder/DecodedBitStreamParser$Mode
      16: dup
      17: ldc           #10                 // String ASCII_ENCODE
      19: iconst_1
      20: invokespecial #8                  // Method "<init>":(Ljava/lang/String;I)V
      23: putstatic     #11                 // Field ASCII_ENCODE:Lcom/google/zxing/datamatrix/decoder/DecodedBitStreamParser$Mode;
      26: new           #4                  // class com/google/zxing/datamatrix/decoder/DecodedBitStreamParser$Mode
      29: dup
      30: ldc           #12                 // String C40_ENCODE
      32: iconst_2
      33: invokespecial #8                  // Method "<init>":(Ljava/lang/String;I)V
      36: putstatic     #13                 // Field C40_ENCODE:Lcom/google/zxing/datamatrix/decoder/DecodedBitStreamParser$Mode;
      39: new           #4                  // class com/google/zxing/datamatrix/decoder/DecodedBitStreamParser$Mode
      42: dup
      43: ldc           #14                 // String TEXT_ENCODE
      45: iconst_3
      46: invokespecial #8                  // Method "<init>":(Ljava/lang/String;I)V
      49: putstatic     #15                 // Field TEXT_ENCODE:Lcom/google/zxing/datamatrix/decoder/DecodedBitStreamParser$Mode;
      52: new           #4                  // class com/google/zxing/datamatrix/decoder/DecodedBitStreamParser$Mode
      55: dup
      56: ldc           #16                 // String ANSIX12_ENCODE
      58: iconst_4
      59: invokespecial #8                  // Method "<init>":(Ljava/lang/String;I)V
      62: putstatic     #17                 // Field ANSIX12_ENCODE:Lcom/google/zxing/datamatrix/decoder/DecodedBitStreamParser$Mode;
      65: new           #4                  // class com/google/zxing/datamatrix/decoder/DecodedBitStreamParser$Mode
      68: dup
      69: ldc           #18                 // String EDIFACT_ENCODE
      71: iconst_5
      72: invokespecial #8                  // Method "<init>":(Ljava/lang/String;I)V
      75: putstatic     #19                 // Field EDIFACT_ENCODE:Lcom/google/zxing/datamatrix/decoder/DecodedBitStreamParser$Mode;
      78: new           #4                  // class com/google/zxing/datamatrix/decoder/DecodedBitStreamParser$Mode
      81: dup
      82: ldc           #20                 // String BASE256_ENCODE
      84: bipush        6
      86: invokespecial #8                  // Method "<init>":(Ljava/lang/String;I)V
      89: putstatic     #21                 // Field BASE256_ENCODE:Lcom/google/zxing/datamatrix/decoder/DecodedBitStreamParser$Mode;
      92: new           #4                  // class com/google/zxing/datamatrix/decoder/DecodedBitStreamParser$Mode
      95: dup
      96: ldc           #22                 // String ECI_ENCODE
      98: bipush        7
     100: invokespecial #8                  // Method "<init>":(Ljava/lang/String;I)V
     103: putstatic     #23                 // Field ECI_ENCODE:Lcom/google/zxing/datamatrix/decoder/DecodedBitStreamParser$Mode;
     106: bipush        8
     108: anewarray     #4                  // class com/google/zxing/datamatrix/decoder/DecodedBitStreamParser$Mode
     111: dup
     112: iconst_0
     113: getstatic     #9                  // Field PAD_ENCODE:Lcom/google/zxing/datamatrix/decoder/DecodedBitStreamParser$Mode;
     116: aastore
     117: dup
     118: iconst_1
     119: getstatic     #11                 // Field ASCII_ENCODE:Lcom/google/zxing/datamatrix/decoder/DecodedBitStreamParser$Mode;
     122: aastore
     123: dup
     124: iconst_2
     125: getstatic     #13                 // Field C40_ENCODE:Lcom/google/zxing/datamatrix/decoder/DecodedBitStreamParser$Mode;
     128: aastore
     129: dup
     130: iconst_3
     131: getstatic     #15                 // Field TEXT_ENCODE:Lcom/google/zxing/datamatrix/decoder/DecodedBitStreamParser$Mode;
     134: aastore
     135: dup
     136: iconst_4
     137: getstatic     #17                 // Field ANSIX12_ENCODE:Lcom/google/zxing/datamatrix/decoder/DecodedBitStreamParser$Mode;
     140: aastore
     141: dup
     142: iconst_5
     143: getstatic     #19                 // Field EDIFACT_ENCODE:Lcom/google/zxing/datamatrix/decoder/DecodedBitStreamParser$Mode;
     146: aastore
     147: dup
     148: bipush        6
     150: getstatic     #21                 // Field BASE256_ENCODE:Lcom/google/zxing/datamatrix/decoder/DecodedBitStreamParser$Mode;
     153: aastore
     154: dup
     155: bipush        7
     157: getstatic     #23                 // Field ECI_ENCODE:Lcom/google/zxing/datamatrix/decoder/DecodedBitStreamParser$Mode;
     160: aastore
     161: putstatic     #1                  // Field $VALUES:[Lcom/google/zxing/datamatrix/decoder/DecodedBitStreamParser$Mode;
     164: return
}
