Compiled from "Version.java"
final class com.google.zxing.datamatrix.decoder.Version$ECB {
  private final int count;

  private final int dataCodewords;

  private com.google.zxing.datamatrix.decoder.Version$ECB(int, int);
    Code:
       0: aload_0
       1: invokespecial #2                  // Method java/lang/Object."<init>":()V
       4: aload_0
       5: iload_1
       6: putfield      #3                  // Field count:I
       9: aload_0
      10: iload_2
      11: putfield      #4                  // Field dataCodewords:I
      14: return

  int getCount();
    Code:
       0: aload_0
       1: getfield      #3                  // Field count:I
       4: ireturn

  int getDataCodewords();
    Code:
       0: aload_0
       1: getfield      #4                  // Field dataCodewords:I
       4: ireturn

  com.google.zxing.datamatrix.decoder.Version$ECB(int, int, com.google.zxing.datamatrix.decoder.Version$1);
    Code:
       0: aload_0
       1: iload_1
       2: iload_2
       3: invokespecial #1                  // Method "<init>":(II)V
       6: return
}
