Compiled from "Version.java"
final class com.google.zxing.datamatrix.decoder.Version$ECBlocks {
  private final int ecCodewords;

  private final com.google.zxing.datamatrix.decoder.Version$ECB[] ecBlocks;

  private com.google.zxing.datamatrix.decoder.Version$ECBlocks(int, com.google.zxing.datamatrix.decoder.Version$ECB);
    Code:
       0: aload_0
       1: invokespecial #3                  // Method java/lang/Object."<init>":()V
       4: aload_0
       5: iload_1
       6: putfield      #4                  // Field ecCodewords:I
       9: aload_0
      10: iconst_1
      11: anewarray     #5                  // class com/google/zxing/datamatrix/decoder/Version$ECB
      14: dup
      15: iconst_0
      16: aload_2
      17: aastore
      18: putfield      #6                  // Field ecBlocks:[Lcom/google/zxing/datamatrix/decoder/Version$ECB;
      21: return

  private com.google.zxing.datamatrix.decoder.Version$ECBlocks(int, com.google.zxing.datamatrix.decoder.Version$ECB, com.google.zxing.datamatrix.decoder.Version$ECB);
    Code:
       0: aload_0
       1: invokespecial #3                  // Method java/lang/Object."<init>":()V
       4: aload_0
       5: iload_1
       6: putfield      #4                  // Field ecCodewords:I
       9: aload_0
      10: iconst_2
      11: anewarray     #5                  // class com/google/zxing/datamatrix/decoder/Version$ECB
      14: dup
      15: iconst_0
      16: aload_2
      17: aastore
      18: dup
      19: iconst_1
      20: aload_3
      21: aastore
      22: putfield      #6                  // Field ecBlocks:[Lcom/google/zxing/datamatrix/decoder/Version$ECB;
      25: return

  int getECCodewords();
    Code:
       0: aload_0
       1: getfield      #4                  // Field ecCodewords:I
       4: ireturn

  com.google.zxing.datamatrix.decoder.Version$ECB[] getECBlocks();
    Code:
       0: aload_0
       1: getfield      #6                  // Field ecBlocks:[Lcom/google/zxing/datamatrix/decoder/Version$ECB;
       4: areturn

  com.google.zxing.datamatrix.decoder.Version$ECBlocks(int, com.google.zxing.datamatrix.decoder.Version$ECB, com.google.zxing.datamatrix.decoder.Version$1);
    Code:
       0: aload_0
       1: iload_1
       2: aload_2
       3: invokespecial #2                  // Method "<init>":(ILcom/google/zxing/datamatrix/decoder/Version$ECB;)V
       6: return

  com.google.zxing.datamatrix.decoder.Version$ECBlocks(int, com.google.zxing.datamatrix.decoder.Version$ECB, com.google.zxing.datamatrix.decoder.Version$ECB, com.google.zxing.datamatrix.decoder.Version$1);
    Code:
       0: aload_0
       1: iload_1
       2: aload_2
       3: aload_3
       4: invokespecial #1                  // Method "<init>":(ILcom/google/zxing/datamatrix/decoder/Version$ECB;Lcom/google/zxing/datamatrix/decoder/Version$ECB;)V
       7: return
}
