Compiled from "Version.java"
public final class com.google.zxing.datamatrix.decoder.Version {
  private static final com.google.zxing.datamatrix.decoder.Version[] VERSIONS;

  private final int versionNumber;

  private final int symbolSizeRows;

  private final int symbolSizeColumns;

  private final int dataRegionSizeRows;

  private final int dataRegionSizeColumns;

  private final com.google.zxing.datamatrix.decoder.Version$ECBlocks ecBlocks;

  private final int totalCodewords;

  private com.google.zxing.datamatrix.decoder.Version(int, int, int, int, int, com.google.zxing.datamatrix.decoder.Version$ECBlocks);
    Code:
       0: aload_0
       1: invokespecial #1                  // Method java/lang/Object."<init>":()V
       4: aload_0
       5: iload_1
       6: putfield      #2                  // Field versionNumber:I
       9: aload_0
      10: iload_2
      11: putfield      #3                  // Field symbolSizeRows:I
      14: aload_0
      15: iload_3
      16: putfield      #4                  // Field symbolSizeColumns:I
      19: aload_0
      20: iload         4
      22: putfield      #5                  // Field dataRegionSizeRows:I
      25: aload_0
      26: iload         5
      28: putfield      #6                  // Field dataRegionSizeColumns:I
      31: aload_0
      32: aload         6
      34: putfield      #7                  // Field ecBlocks:Lcom/google/zxing/datamatrix/decoder/Version$ECBlocks;
      37: iconst_0
      38: istore        7
      40: aload         6
      42: invokevirtual #8                  // Method com/google/zxing/datamatrix/decoder/Version$ECBlocks.getECCodewords:()I
      45: istore        8
      47: aload         6
      49: invokevirtual #9                  // Method com/google/zxing/datamatrix/decoder/Version$ECBlocks.getECBlocks:()[Lcom/google/zxing/datamatrix/decoder/Version$ECB;
      52: astore        9
      54: aload         9
      56: astore        10
      58: aload         10
      60: arraylength
      61: istore        11
      63: iconst_0
      64: istore        12
      66: iload         12
      68: iload         11
      70: if_icmpge     105
      73: aload         10
      75: iload         12
      77: aaload
      78: astore        13
      80: iload         7
      82: aload         13
      84: invokevirtual #10                 // Method com/google/zxing/datamatrix/decoder/Version$ECB.getCount:()I
      87: aload         13
      89: invokevirtual #11                 // Method com/google/zxing/datamatrix/decoder/Version$ECB.getDataCodewords:()I
      92: iload         8
      94: iadd
      95: imul
      96: iadd
      97: istore        7
      99: iinc          12, 1
     102: goto          66
     105: aload_0
     106: iload         7
     108: putfield      #12                 // Field totalCodewords:I
     111: return

  public int getVersionNumber();
    Code:
       0: aload_0
       1: getfield      #2                  // Field versionNumber:I
       4: ireturn

  public int getSymbolSizeRows();
    Code:
       0: aload_0
       1: getfield      #3                  // Field symbolSizeRows:I
       4: ireturn

  public int getSymbolSizeColumns();
    Code:
       0: aload_0
       1: getfield      #4                  // Field symbolSizeColumns:I
       4: ireturn

  public int getDataRegionSizeRows();
    Code:
       0: aload_0
       1: getfield      #5                  // Field dataRegionSizeRows:I
       4: ireturn

  public int getDataRegionSizeColumns();
    Code:
       0: aload_0
       1: getfield      #6                  // Field dataRegionSizeColumns:I
       4: ireturn

  public int getTotalCodewords();
    Code:
       0: aload_0
       1: getfield      #12                 // Field totalCodewords:I
       4: ireturn

  com.google.zxing.datamatrix.decoder.Version$ECBlocks getECBlocks();
    Code:
       0: aload_0
       1: getfield      #7                  // Field ecBlocks:Lcom/google/zxing/datamatrix/decoder/Version$ECBlocks;
       4: areturn

  public static com.google.zxing.datamatrix.decoder.Version getVersionForDimensions(int, int) throws com.google.zxing.FormatException;
    Code:
       0: iload_0
       1: iconst_1
       2: iand
       3: ifne          12
       6: iload_1
       7: iconst_1
       8: iand
       9: ifeq          16
      12: invokestatic  #13                 // Method com/google/zxing/FormatException.getFormatInstance:()Lcom/google/zxing/FormatException;
      15: athrow
      16: getstatic     #14                 // Field VERSIONS:[Lcom/google/zxing/datamatrix/decoder/Version;
      19: astore_2
      20: aload_2
      21: arraylength
      22: istore_3
      23: iconst_0
      24: istore        4
      26: iload         4
      28: iload_3
      29: if_icmpge     65
      32: aload_2
      33: iload         4
      35: aaload
      36: astore        5
      38: aload         5
      40: getfield      #3                  // Field symbolSizeRows:I
      43: iload_0
      44: if_icmpne     59
      47: aload         5
      49: getfield      #4                  // Field symbolSizeColumns:I
      52: iload_1
      53: if_icmpne     59
      56: aload         5
      58: areturn
      59: iinc          4, 1
      62: goto          26
      65: invokestatic  #13                 // Method com/google/zxing/FormatException.getFormatInstance:()Lcom/google/zxing/FormatException;
      68: athrow

  public java.lang.String toString();
    Code:
       0: aload_0
       1: getfield      #2                  // Field versionNumber:I
       4: invokestatic  #15                 // Method java/lang/String.valueOf:(I)Ljava/lang/String;
       7: areturn

  private static com.google.zxing.datamatrix.decoder.Version[] buildVersions();
    Code:
       0: bipush        48
       2: anewarray     #16                 // class com/google/zxing/datamatrix/decoder/Version
       5: dup
       6: iconst_0
       7: new           #16                 // class com/google/zxing/datamatrix/decoder/Version
      10: dup
      11: iconst_1
      12: bipush        10
      14: bipush        10
      16: bipush        8
      18: bipush        8
      20: new           #17                 // class com/google/zxing/datamatrix/decoder/Version$ECBlocks
      23: dup
      24: iconst_5
      25: new           #18                 // class com/google/zxing/datamatrix/decoder/Version$ECB
      28: dup
      29: iconst_1
      30: iconst_3
      31: aconst_null
      32: invokespecial #19                 // Method com/google/zxing/datamatrix/decoder/Version$ECB."<init>":(IILcom/google/zxing/datamatrix/decoder/Version$1;)V
      35: aconst_null
      36: invokespecial #20                 // Method com/google/zxing/datamatrix/decoder/Version$ECBlocks."<init>":(ILcom/google/zxing/datamatrix/decoder/Version$ECB;Lcom/google/zxing/datamatrix/decoder/Version$1;)V
      39: invokespecial #21                 // Method "<init>":(IIIIILcom/google/zxing/datamatrix/decoder/Version$ECBlocks;)V
      42: aastore
      43: dup
      44: iconst_1
      45: new           #16                 // class com/google/zxing/datamatrix/decoder/Version
      48: dup
      49: iconst_2
      50: bipush        12
      52: bipush        12
      54: bipush        10
      56: bipush        10
      58: new           #17                 // class com/google/zxing/datamatrix/decoder/Version$ECBlocks
      61: dup
      62: bipush        7
      64: new           #18                 // class com/google/zxing/datamatrix/decoder/Version$ECB
      67: dup
      68: iconst_1
      69: iconst_5
      70: aconst_null
      71: invokespecial #19                 // Method com/google/zxing/datamatrix/decoder/Version$ECB."<init>":(IILcom/google/zxing/datamatrix/decoder/Version$1;)V
      74: aconst_null
      75: invokespecial #20                 // Method com/google/zxing/datamatrix/decoder/Version$ECBlocks."<init>":(ILcom/google/zxing/datamatrix/decoder/Version$ECB;Lcom/google/zxing/datamatrix/decoder/Version$1;)V
      78: invokespecial #21                 // Method "<init>":(IIIIILcom/google/zxing/datamatrix/decoder/Version$ECBlocks;)V
      81: aastore
      82: dup
      83: iconst_2
      84: new           #16                 // class com/google/zxing/datamatrix/decoder/Version
      87: dup
      88: iconst_3
      89: bipush        14
      91: bipush        14
      93: bipush        12
      95: bipush        12
      97: new           #17                 // class com/google/zxing/datamatrix/decoder/Version$ECBlocks
     100: dup
     101: bipush        10
     103: new           #18                 // class com/google/zxing/datamatrix/decoder/Version$ECB
     106: dup
     107: iconst_1
     108: bipush        8
     110: aconst_null
     111: invokespecial #19                 // Method com/google/zxing/datamatrix/decoder/Version$ECB."<init>":(IILcom/google/zxing/datamatrix/decoder/Version$1;)V
     114: aconst_null
     115: invokespecial #20                 // Method com/google/zxing/datamatrix/decoder/Version$ECBlocks."<init>":(ILcom/google/zxing/datamatrix/decoder/Version$ECB;Lcom/google/zxing/datamatrix/decoder/Version$1;)V
     118: invokespecial #21                 // Method "<init>":(IIIIILcom/google/zxing/datamatrix/decoder/Version$ECBlocks;)V
     121: aastore
     122: dup
     123: iconst_3
     124: new           #16                 // class com/google/zxing/datamatrix/decoder/Version
     127: dup
     128: iconst_4
     129: bipush        16
     131: bipush        16
     133: bipush        14
     135: bipush        14
     137: new           #17                 // class com/google/zxing/datamatrix/decoder/Version$ECBlocks
     140: dup
     141: bipush        12
     143: new           #18                 // class com/google/zxing/datamatrix/decoder/Version$ECB
     146: dup
     147: iconst_1
     148: bipush        12
     150: aconst_null
     151: invokespecial #19                 // Method com/google/zxing/datamatrix/decoder/Version$ECB."<init>":(IILcom/google/zxing/datamatrix/decoder/Version$1;)V
     154: aconst_null
     155: invokespecial #20                 // Method com/google/zxing/datamatrix/decoder/Version$ECBlocks."<init>":(ILcom/google/zxing/datamatrix/decoder/Version$ECB;Lcom/google/zxing/datamatrix/decoder/Version$1;)V
     158: invokespecial #21                 // Method "<init>":(IIIIILcom/google/zxing/datamatrix/decoder/Version$ECBlocks;)V
     161: aastore
     162: dup
     163: iconst_4
     164: new           #16                 // class com/google/zxing/datamatrix/decoder/Version
     167: dup
     168: iconst_5
     169: bipush        18
     171: bipush        18
     173: bipush        16
     175: bipush        16
     177: new           #17                 // class com/google/zxing/datamatrix/decoder/Version$ECBlocks
     180: dup
     181: bipush        14
     183: new           #18                 // class com/google/zxing/datamatrix/decoder/Version$ECB
     186: dup
     187: iconst_1
     188: bipush        18
     190: aconst_null
     191: invokespecial #19                 // Method com/google/zxing/datamatrix/decoder/Version$ECB."<init>":(IILcom/google/zxing/datamatrix/decoder/Version$1;)V
     194: aconst_null
     195: invokespecial #20                 // Method com/google/zxing/datamatrix/decoder/Version$ECBlocks."<init>":(ILcom/google/zxing/datamatrix/decoder/Version$ECB;Lcom/google/zxing/datamatrix/decoder/Version$1;)V
     198: invokespecial #21                 // Method "<init>":(IIIIILcom/google/zxing/datamatrix/decoder/Version$ECBlocks;)V
     201: aastore
     202: dup
     203: iconst_5
     204: new           #16                 // class com/google/zxing/datamatrix/decoder/Version
     207: dup
     208: bipush        6
     210: bipush        20
     212: bipush        20
     214: bipush        18
     216: bipush        18
     218: new           #17                 // class com/google/zxing/datamatrix/decoder/Version$ECBlocks
     221: dup
     222: bipush        18
     224: new           #18                 // class com/google/zxing/datamatrix/decoder/Version$ECB
     227: dup
     228: iconst_1
     229: bipush        22
     231: aconst_null
     232: invokespecial #19                 // Method com/google/zxing/datamatrix/decoder/Version$ECB."<init>":(IILcom/google/zxing/datamatrix/decoder/Version$1;)V
     235: aconst_null
     236: invokespecial #20                 // Method com/google/zxing/datamatrix/decoder/Version$ECBlocks."<init>":(ILcom/google/zxing/datamatrix/decoder/Version$ECB;Lcom/google/zxing/datamatrix/decoder/Version$1;)V
     239: invokespecial #21                 // Method "<init>":(IIIIILcom/google/zxing/datamatrix/decoder/Version$ECBlocks;)V
     242: aastore
     243: dup
     244: bipush        6
     246: new           #16                 // class com/google/zxing/datamatrix/decoder/Version
     249: dup
     250: bipush        7
     252: bipush        22
     254: bipush        22
     256: bipush        20
     258: bipush        20
     260: new           #17                 // class com/google/zxing/datamatrix/decoder/Version$ECBlocks
     263: dup
     264: bipush        20
     266: new           #18                 // class com/google/zxing/datamatrix/decoder/Version$ECB
     269: dup
     270: iconst_1
     271: bipush        30
     273: aconst_null
     274: invokespecial #19                 // Method com/google/zxing/datamatrix/decoder/Version$ECB."<init>":(IILcom/google/zxing/datamatrix/decoder/Version$1;)V
     277: aconst_null
     278: invokespecial #20                 // Method com/google/zxing/datamatrix/decoder/Version$ECBlocks."<init>":(ILcom/google/zxing/datamatrix/decoder/Version$ECB;Lcom/google/zxing/datamatrix/decoder/Version$1;)V
     281: invokespecial #21                 // Method "<init>":(IIIIILcom/google/zxing/datamatrix/decoder/Version$ECBlocks;)V
     284: aastore
     285: dup
     286: bipush        7
     288: new           #16                 // class com/google/zxing/datamatrix/decoder/Version
     291: dup
     292: bipush        8
     294: bipush        24
     296: bipush        24
     298: bipush        22
     300: bipush        22
     302: new           #17                 // class com/google/zxing/datamatrix/decoder/Version$ECBlocks
     305: dup
     306: bipush        24
     308: new           #18                 // class com/google/zxing/datamatrix/decoder/Version$ECB
     311: dup
     312: iconst_1
     313: bipush        36
     315: aconst_null
     316: invokespecial #19                 // Method com/google/zxing/datamatrix/decoder/Version$ECB."<init>":(IILcom/google/zxing/datamatrix/decoder/Version$1;)V
     319: aconst_null
     320: invokespecial #20                 // Method com/google/zxing/datamatrix/decoder/Version$ECBlocks."<init>":(ILcom/google/zxing/datamatrix/decoder/Version$ECB;Lcom/google/zxing/datamatrix/decoder/Version$1;)V
     323: invokespecial #21                 // Method "<init>":(IIIIILcom/google/zxing/datamatrix/decoder/Version$ECBlocks;)V
     326: aastore
     327: dup
     328: bipush        8
     330: new           #16                 // class com/google/zxing/datamatrix/decoder/Version
     333: dup
     334: bipush        9
     336: bipush        26
     338: bipush        26
     340: bipush        24
     342: bipush        24
     344: new           #17                 // class com/google/zxing/datamatrix/decoder/Version$ECBlocks
     347: dup
     348: bipush        28
     350: new           #18                 // class com/google/zxing/datamatrix/decoder/Version$ECB
     353: dup
     354: iconst_1
     355: bipush        44
     357: aconst_null
     358: invokespecial #19                 // Method com/google/zxing/datamatrix/decoder/Version$ECB."<init>":(IILcom/google/zxing/datamatrix/decoder/Version$1;)V
     361: aconst_null
     362: invokespecial #20                 // Method com/google/zxing/datamatrix/decoder/Version$ECBlocks."<init>":(ILcom/google/zxing/datamatrix/decoder/Version$ECB;Lcom/google/zxing/datamatrix/decoder/Version$1;)V
     365: invokespecial #21                 // Method "<init>":(IIIIILcom/google/zxing/datamatrix/decoder/Version$ECBlocks;)V
     368: aastore
     369: dup
     370: bipush        9
     372: new           #16                 // class com/google/zxing/datamatrix/decoder/Version
     375: dup
     376: bipush        10
     378: bipush        32
     380: bipush        32
     382: bipush        14
     384: bipush        14
     386: new           #17                 // class com/google/zxing/datamatrix/decoder/Version$ECBlocks
     389: dup
     390: bipush        36
     392: new           #18                 // class com/google/zxing/datamatrix/decoder/Version$ECB
     395: dup
     396: iconst_1
     397: bipush        62
     399: aconst_null
     400: invokespecial #19                 // Method com/google/zxing/datamatrix/decoder/Version$ECB."<init>":(IILcom/google/zxing/datamatrix/decoder/Version$1;)V
     403: aconst_null
     404: invokespecial #20                 // Method com/google/zxing/datamatrix/decoder/Version$ECBlocks."<init>":(ILcom/google/zxing/datamatrix/decoder/Version$ECB;Lcom/google/zxing/datamatrix/decoder/Version$1;)V
     407: invokespecial #21                 // Method "<init>":(IIIIILcom/google/zxing/datamatrix/decoder/Version$ECBlocks;)V
     410: aastore
     411: dup
     412: bipush        10
     414: new           #16                 // class com/google/zxing/datamatrix/decoder/Version
     417: dup
     418: bipush        11
     420: bipush        36
     422: bipush        36
     424: bipush        16
     426: bipush        16
     428: new           #17                 // class com/google/zxing/datamatrix/decoder/Version$ECBlocks
     431: dup
     432: bipush        42
     434: new           #18                 // class com/google/zxing/datamatrix/decoder/Version$ECB
     437: dup
     438: iconst_1
     439: bipush        86
     441: aconst_null
     442: invokespecial #19                 // Method com/google/zxing/datamatrix/decoder/Version$ECB."<init>":(IILcom/google/zxing/datamatrix/decoder/Version$1;)V
     445: aconst_null
     446: invokespecial #20                 // Method com/google/zxing/datamatrix/decoder/Version$ECBlocks."<init>":(ILcom/google/zxing/datamatrix/decoder/Version$ECB;Lcom/google/zxing/datamatrix/decoder/Version$1;)V
     449: invokespecial #21                 // Method "<init>":(IIIIILcom/google/zxing/datamatrix/decoder/Version$ECBlocks;)V
     452: aastore
     453: dup
     454: bipush        11
     456: new           #16                 // class com/google/zxing/datamatrix/decoder/Version
     459: dup
     460: bipush        12
     462: bipush        40
     464: bipush        40
     466: bipush        18
     468: bipush        18
     470: new           #17                 // class com/google/zxing/datamatrix/decoder/Version$ECBlocks
     473: dup
     474: bipush        48
     476: new           #18                 // class com/google/zxing/datamatrix/decoder/Version$ECB
     479: dup
     480: iconst_1
     481: bipush        114
     483: aconst_null
     484: invokespecial #19                 // Method com/google/zxing/datamatrix/decoder/Version$ECB."<init>":(IILcom/google/zxing/datamatrix/decoder/Version$1;)V
     487: aconst_null
     488: invokespecial #20                 // Method com/google/zxing/datamatrix/decoder/Version$ECBlocks."<init>":(ILcom/google/zxing/datamatrix/decoder/Version$ECB;Lcom/google/zxing/datamatrix/decoder/Version$1;)V
     491: invokespecial #21                 // Method "<init>":(IIIIILcom/google/zxing/datamatrix/decoder/Version$ECBlocks;)V
     494: aastore
     495: dup
     496: bipush        12
     498: new           #16                 // class com/google/zxing/datamatrix/decoder/Version
     501: dup
     502: bipush        13
     504: bipush        44
     506: bipush        44
     508: bipush        20
     510: bipush        20
     512: new           #17                 // class com/google/zxing/datamatrix/decoder/Version$ECBlocks
     515: dup
     516: bipush        56
     518: new           #18                 // class com/google/zxing/datamatrix/decoder/Version$ECB
     521: dup
     522: iconst_1
     523: sipush        144
     526: aconst_null
     527: invokespecial #19                 // Method com/google/zxing/datamatrix/decoder/Version$ECB."<init>":(IILcom/google/zxing/datamatrix/decoder/Version$1;)V
     530: aconst_null
     531: invokespecial #20                 // Method com/google/zxing/datamatrix/decoder/Version$ECBlocks."<init>":(ILcom/google/zxing/datamatrix/decoder/Version$ECB;Lcom/google/zxing/datamatrix/decoder/Version$1;)V
     534: invokespecial #21                 // Method "<init>":(IIIIILcom/google/zxing/datamatrix/decoder/Version$ECBlocks;)V
     537: aastore
     538: dup
     539: bipush        13
     541: new           #16                 // class com/google/zxing/datamatrix/decoder/Version
     544: dup
     545: bipush        14
     547: bipush        48
     549: bipush        48
     551: bipush        22
     553: bipush        22
     555: new           #17                 // class com/google/zxing/datamatrix/decoder/Version$ECBlocks
     558: dup
     559: bipush        68
     561: new           #18                 // class com/google/zxing/datamatrix/decoder/Version$ECB
     564: dup
     565: iconst_1
     566: sipush        174
     569: aconst_null
     570: invokespecial #19                 // Method com/google/zxing/datamatrix/decoder/Version$ECB."<init>":(IILcom/google/zxing/datamatrix/decoder/Version$1;)V
     573: aconst_null
     574: invokespecial #20                 // Method com/google/zxing/datamatrix/decoder/Version$ECBlocks."<init>":(ILcom/google/zxing/datamatrix/decoder/Version$ECB;Lcom/google/zxing/datamatrix/decoder/Version$1;)V
     577: invokespecial #21                 // Method "<init>":(IIIIILcom/google/zxing/datamatrix/decoder/Version$ECBlocks;)V
     580: aastore
     581: dup
     582: bipush        14
     584: new           #16                 // class com/google/zxing/datamatrix/decoder/Version
     587: dup
     588: bipush        15
     590: bipush        52
     592: bipush        52
     594: bipush        24
     596: bipush        24
     598: new           #17                 // class com/google/zxing/datamatrix/decoder/Version$ECBlocks
     601: dup
     602: bipush        42
     604: new           #18                 // class com/google/zxing/datamatrix/decoder/Version$ECB
     607: dup
     608: iconst_2
     609: bipush        102
     611: aconst_null
     612: invokespecial #19                 // Method com/google/zxing/datamatrix/decoder/Version$ECB."<init>":(IILcom/google/zxing/datamatrix/decoder/Version$1;)V
     615: aconst_null
     616: invokespecial #20                 // Method com/google/zxing/datamatrix/decoder/Version$ECBlocks."<init>":(ILcom/google/zxing/datamatrix/decoder/Version$ECB;Lcom/google/zxing/datamatrix/decoder/Version$1;)V
     619: invokespecial #21                 // Method "<init>":(IIIIILcom/google/zxing/datamatrix/decoder/Version$ECBlocks;)V
     622: aastore
     623: dup
     624: bipush        15
     626: new           #16                 // class com/google/zxing/datamatrix/decoder/Version
     629: dup
     630: bipush        16
     632: bipush        64
     634: bipush        64
     636: bipush        14
     638: bipush        14
     640: new           #17                 // class com/google/zxing/datamatrix/decoder/Version$ECBlocks
     643: dup
     644: bipush        56
     646: new           #18                 // class com/google/zxing/datamatrix/decoder/Version$ECB
     649: dup
     650: iconst_2
     651: sipush        140
     654: aconst_null
     655: invokespecial #19                 // Method com/google/zxing/datamatrix/decoder/Version$ECB."<init>":(IILcom/google/zxing/datamatrix/decoder/Version$1;)V
     658: aconst_null
     659: invokespecial #20                 // Method com/google/zxing/datamatrix/decoder/Version$ECBlocks."<init>":(ILcom/google/zxing/datamatrix/decoder/Version$ECB;Lcom/google/zxing/datamatrix/decoder/Version$1;)V
     662: invokespecial #21                 // Method "<init>":(IIIIILcom/google/zxing/datamatrix/decoder/Version$ECBlocks;)V
     665: aastore
     666: dup
     667: bipush        16
     669: new           #16                 // class com/google/zxing/datamatrix/decoder/Version
     672: dup
     673: bipush        17
     675: bipush        72
     677: bipush        72
     679: bipush        16
     681: bipush        16
     683: new           #17                 // class com/google/zxing/datamatrix/decoder/Version$ECBlocks
     686: dup
     687: bipush        36
     689: new           #18                 // class com/google/zxing/datamatrix/decoder/Version$ECB
     692: dup
     693: iconst_4
     694: bipush        92
     696: aconst_null
     697: invokespecial #19                 // Method com/google/zxing/datamatrix/decoder/Version$ECB."<init>":(IILcom/google/zxing/datamatrix/decoder/Version$1;)V
     700: aconst_null
     701: invokespecial #20                 // Method com/google/zxing/datamatrix/decoder/Version$ECBlocks."<init>":(ILcom/google/zxing/datamatrix/decoder/Version$ECB;Lcom/google/zxing/datamatrix/decoder/Version$1;)V
     704: invokespecial #21                 // Method "<init>":(IIIIILcom/google/zxing/datamatrix/decoder/Version$ECBlocks;)V
     707: aastore
     708: dup
     709: bipush        17
     711: new           #16                 // class com/google/zxing/datamatrix/decoder/Version
     714: dup
     715: bipush        18
     717: bipush        80
     719: bipush        80
     721: bipush        18
     723: bipush        18
     725: new           #17                 // class com/google/zxing/datamatrix/decoder/Version$ECBlocks
     728: dup
     729: bipush        48
     731: new           #18                 // class com/google/zxing/datamatrix/decoder/Version$ECB
     734: dup
     735: iconst_4
     736: bipush        114
     738: aconst_null
     739: invokespecial #19                 // Method com/google/zxing/datamatrix/decoder/Version$ECB."<init>":(IILcom/google/zxing/datamatrix/decoder/Version$1;)V
     742: aconst_null
     743: invokespecial #20                 // Method com/google/zxing/datamatrix/decoder/Version$ECBlocks."<init>":(ILcom/google/zxing/datamatrix/decoder/Version$ECB;Lcom/google/zxing/datamatrix/decoder/Version$1;)V
     746: invokespecial #21                 // Method "<init>":(IIIIILcom/google/zxing/datamatrix/decoder/Version$ECBlocks;)V
     749: aastore
     750: dup
     751: bipush        18
     753: new           #16                 // class com/google/zxing/datamatrix/decoder/Version
     756: dup
     757: bipush        19
     759: bipush        88
     761: bipush        88
     763: bipush        20
     765: bipush        20
     767: new           #17                 // class com/google/zxing/datamatrix/decoder/Version$ECBlocks
     770: dup
     771: bipush        56
     773: new           #18                 // class com/google/zxing/datamatrix/decoder/Version$ECB
     776: dup
     777: iconst_4
     778: sipush        144
     781: aconst_null
     782: invokespecial #19                 // Method com/google/zxing/datamatrix/decoder/Version$ECB."<init>":(IILcom/google/zxing/datamatrix/decoder/Version$1;)V
     785: aconst_null
     786: invokespecial #20                 // Method com/google/zxing/datamatrix/decoder/Version$ECBlocks."<init>":(ILcom/google/zxing/datamatrix/decoder/Version$ECB;Lcom/google/zxing/datamatrix/decoder/Version$1;)V
     789: invokespecial #21                 // Method "<init>":(IIIIILcom/google/zxing/datamatrix/decoder/Version$ECBlocks;)V
     792: aastore
     793: dup
     794: bipush        19
     796: new           #16                 // class com/google/zxing/datamatrix/decoder/Version
     799: dup
     800: bipush        20
     802: bipush        96
     804: bipush        96
     806: bipush        22
     808: bipush        22
     810: new           #17                 // class com/google/zxing/datamatrix/decoder/Version$ECBlocks
     813: dup
     814: bipush        68
     816: new           #18                 // class com/google/zxing/datamatrix/decoder/Version$ECB
     819: dup
     820: iconst_4
     821: sipush        174
     824: aconst_null
     825: invokespecial #19                 // Method com/google/zxing/datamatrix/decoder/Version$ECB."<init>":(IILcom/google/zxing/datamatrix/decoder/Version$1;)V
     828: aconst_null
     829: invokespecial #20                 // Method com/google/zxing/datamatrix/decoder/Version$ECBlocks."<init>":(ILcom/google/zxing/datamatrix/decoder/Version$ECB;Lcom/google/zxing/datamatrix/decoder/Version$1;)V
     832: invokespecial #21                 // Method "<init>":(IIIIILcom/google/zxing/datamatrix/decoder/Version$ECBlocks;)V
     835: aastore
     836: dup
     837: bipush        20
     839: new           #16                 // class com/google/zxing/datamatrix/decoder/Version
     842: dup
     843: bipush        21
     845: bipush        104
     847: bipush        104
     849: bipush        24
     851: bipush        24
     853: new           #17                 // class com/google/zxing/datamatrix/decoder/Version$ECBlocks
     856: dup
     857: bipush        56
     859: new           #18                 // class com/google/zxing/datamatrix/decoder/Version$ECB
     862: dup
     863: bipush        6
     865: sipush        136
     868: aconst_null
     869: invokespecial #19                 // Method com/google/zxing/datamatrix/decoder/Version$ECB."<init>":(IILcom/google/zxing/datamatrix/decoder/Version$1;)V
     872: aconst_null
     873: invokespecial #20                 // Method com/google/zxing/datamatrix/decoder/Version$ECBlocks."<init>":(ILcom/google/zxing/datamatrix/decoder/Version$ECB;Lcom/google/zxing/datamatrix/decoder/Version$1;)V
     876: invokespecial #21                 // Method "<init>":(IIIIILcom/google/zxing/datamatrix/decoder/Version$ECBlocks;)V
     879: aastore
     880: dup
     881: bipush        21
     883: new           #16                 // class com/google/zxing/datamatrix/decoder/Version
     886: dup
     887: bipush        22
     889: bipush        120
     891: bipush        120
     893: bipush        18
     895: bipush        18
     897: new           #17                 // class com/google/zxing/datamatrix/decoder/Version$ECBlocks
     900: dup
     901: bipush        68
     903: new           #18                 // class com/google/zxing/datamatrix/decoder/Version$ECB
     906: dup
     907: bipush        6
     909: sipush        175
     912: aconst_null
     913: invokespecial #19                 // Method com/google/zxing/datamatrix/decoder/Version$ECB."<init>":(IILcom/google/zxing/datamatrix/decoder/Version$1;)V
     916: aconst_null
     917: invokespecial #20                 // Method com/google/zxing/datamatrix/decoder/Version$ECBlocks."<init>":(ILcom/google/zxing/datamatrix/decoder/Version$ECB;Lcom/google/zxing/datamatrix/decoder/Version$1;)V
     920: invokespecial #21                 // Method "<init>":(IIIIILcom/google/zxing/datamatrix/decoder/Version$ECBlocks;)V
     923: aastore
     924: dup
     925: bipush        22
     927: new           #16                 // class com/google/zxing/datamatrix/decoder/Version
     930: dup
     931: bipush        23
     933: sipush        132
     936: sipush        132
     939: bipush        20
     941: bipush        20
     943: new           #17                 // class com/google/zxing/datamatrix/decoder/Version$ECBlocks
     946: dup
     947: bipush        62
     949: new           #18                 // class com/google/zxing/datamatrix/decoder/Version$ECB
     952: dup
     953: bipush        8
     955: sipush        163
     958: aconst_null
     959: invokespecial #19                 // Method com/google/zxing/datamatrix/decoder/Version$ECB."<init>":(IILcom/google/zxing/datamatrix/decoder/Version$1;)V
     962: aconst_null
     963: invokespecial #20                 // Method com/google/zxing/datamatrix/decoder/Version$ECBlocks."<init>":(ILcom/google/zxing/datamatrix/decoder/Version$ECB;Lcom/google/zxing/datamatrix/decoder/Version$1;)V
     966: invokespecial #21                 // Method "<init>":(IIIIILcom/google/zxing/datamatrix/decoder/Version$ECBlocks;)V
     969: aastore
     970: dup
     971: bipush        23
     973: new           #16                 // class com/google/zxing/datamatrix/decoder/Version
     976: dup
     977: bipush        24
     979: sipush        144
     982: sipush        144
     985: bipush        22
     987: bipush        22
     989: new           #17                 // class com/google/zxing/datamatrix/decoder/Version$ECBlocks
     992: dup
     993: bipush        62
     995: new           #18                 // class com/google/zxing/datamatrix/decoder/Version$ECB
     998: dup
     999: bipush        8
    1001: sipush        156
    1004: aconst_null
    1005: invokespecial #19                 // Method com/google/zxing/datamatrix/decoder/Version$ECB."<init>":(IILcom/google/zxing/datamatrix/decoder/Version$1;)V
    1008: new           #18                 // class com/google/zxing/datamatrix/decoder/Version$ECB
    1011: dup
    1012: iconst_2
    1013: sipush        155
    1016: aconst_null
    1017: invokespecial #19                 // Method com/google/zxing/datamatrix/decoder/Version$ECB."<init>":(IILcom/google/zxing/datamatrix/decoder/Version$1;)V
    1020: aconst_null
    1021: invokespecial #22                 // Method com/google/zxing/datamatrix/decoder/Version$ECBlocks."<init>":(ILcom/google/zxing/datamatrix/decoder/Version$ECB;Lcom/google/zxing/datamatrix/decoder/Version$ECB;Lcom/google/zxing/datamatrix/decoder/Version$1;)V
    1024: invokespecial #21                 // Method "<init>":(IIIIILcom/google/zxing/datamatrix/decoder/Version$ECBlocks;)V
    1027: aastore
    1028: dup
    1029: bipush        24
    1031: new           #16                 // class com/google/zxing/datamatrix/decoder/Version
    1034: dup
    1035: bipush        25
    1037: bipush        8
    1039: bipush        18
    1041: bipush        6
    1043: bipush        16
    1045: new           #17                 // class com/google/zxing/datamatrix/decoder/Version$ECBlocks
    1048: dup
    1049: bipush        7
    1051: new           #18                 // class com/google/zxing/datamatrix/decoder/Version$ECB
    1054: dup
    1055: iconst_1
    1056: iconst_5
    1057: aconst_null
    1058: invokespecial #19                 // Method com/google/zxing/datamatrix/decoder/Version$ECB."<init>":(IILcom/google/zxing/datamatrix/decoder/Version$1;)V
    1061: aconst_null
    1062: invokespecial #20                 // Method com/google/zxing/datamatrix/decoder/Version$ECBlocks."<init>":(ILcom/google/zxing/datamatrix/decoder/Version$ECB;Lcom/google/zxing/datamatrix/decoder/Version$1;)V
    1065: invokespecial #21                 // Method "<init>":(IIIIILcom/google/zxing/datamatrix/decoder/Version$ECBlocks;)V
    1068: aastore
    1069: dup
    1070: bipush        25
    1072: new           #16                 // class com/google/zxing/datamatrix/decoder/Version
    1075: dup
    1076: bipush        26
    1078: bipush        8
    1080: bipush        32
    1082: bipush        6
    1084: bipush        14
    1086: new           #17                 // class com/google/zxing/datamatrix/decoder/Version$ECBlocks
    1089: dup
    1090: bipush        11
    1092: new           #18                 // class com/google/zxing/datamatrix/decoder/Version$ECB
    1095: dup
    1096: iconst_1
    1097: bipush        10
    1099: aconst_null
    1100: invokespecial #19                 // Method com/google/zxing/datamatrix/decoder/Version$ECB."<init>":(IILcom/google/zxing/datamatrix/decoder/Version$1;)V
    1103: aconst_null
    1104: invokespecial #20                 // Method com/google/zxing/datamatrix/decoder/Version$ECBlocks."<init>":(ILcom/google/zxing/datamatrix/decoder/Version$ECB;Lcom/google/zxing/datamatrix/decoder/Version$1;)V
    1107: invokespecial #21                 // Method "<init>":(IIIIILcom/google/zxing/datamatrix/decoder/Version$ECBlocks;)V
    1110: aastore
    1111: dup
    1112: bipush        26
    1114: new           #16                 // class com/google/zxing/datamatrix/decoder/Version
    1117: dup
    1118: bipush        27
    1120: bipush        12
    1122: bipush        26
    1124: bipush        10
    1126: bipush        24
    1128: new           #17                 // class com/google/zxing/datamatrix/decoder/Version$ECBlocks
    1131: dup
    1132: bipush        14
    1134: new           #18                 // class com/google/zxing/datamatrix/decoder/Version$ECB
    1137: dup
    1138: iconst_1
    1139: bipush        16
    1141: aconst_null
    1142: invokespecial #19                 // Method com/google/zxing/datamatrix/decoder/Version$ECB."<init>":(IILcom/google/zxing/datamatrix/decoder/Version$1;)V
    1145: aconst_null
    1146: invokespecial #20                 // Method com/google/zxing/datamatrix/decoder/Version$ECBlocks."<init>":(ILcom/google/zxing/datamatrix/decoder/Version$ECB;Lcom/google/zxing/datamatrix/decoder/Version$1;)V
    1149: invokespecial #21                 // Method "<init>":(IIIIILcom/google/zxing/datamatrix/decoder/Version$ECBlocks;)V
    1152: aastore
    1153: dup
    1154: bipush        27
    1156: new           #16                 // class com/google/zxing/datamatrix/decoder/Version
    1159: dup
    1160: bipush        28
    1162: bipush        12
    1164: bipush        36
    1166: bipush        10
    1168: bipush        16
    1170: new           #17                 // class com/google/zxing/datamatrix/decoder/Version$ECBlocks
    1173: dup
    1174: bipush        18
    1176: new           #18                 // class com/google/zxing/datamatrix/decoder/Version$ECB
    1179: dup
    1180: iconst_1
    1181: bipush        22
    1183: aconst_null
    1184: invokespecial #19                 // Method com/google/zxing/datamatrix/decoder/Version$ECB."<init>":(IILcom/google/zxing/datamatrix/decoder/Version$1;)V
    1187: aconst_null
    1188: invokespecial #20                 // Method com/google/zxing/datamatrix/decoder/Version$ECBlocks."<init>":(ILcom/google/zxing/datamatrix/decoder/Version$ECB;Lcom/google/zxing/datamatrix/decoder/Version$1;)V
    1191: invokespecial #21                 // Method "<init>":(IIIIILcom/google/zxing/datamatrix/decoder/Version$ECBlocks;)V
    1194: aastore
    1195: dup
    1196: bipush        28
    1198: new           #16                 // class com/google/zxing/datamatrix/decoder/Version
    1201: dup
    1202: bipush        29
    1204: bipush        16
    1206: bipush        36
    1208: bipush        14
    1210: bipush        16
    1212: new           #17                 // class com/google/zxing/datamatrix/decoder/Version$ECBlocks
    1215: dup
    1216: bipush        24
    1218: new           #18                 // class com/google/zxing/datamatrix/decoder/Version$ECB
    1221: dup
    1222: iconst_1
    1223: bipush        32
    1225: aconst_null
    1226: invokespecial #19                 // Method com/google/zxing/datamatrix/decoder/Version$ECB."<init>":(IILcom/google/zxing/datamatrix/decoder/Version$1;)V
    1229: aconst_null
    1230: invokespecial #20                 // Method com/google/zxing/datamatrix/decoder/Version$ECBlocks."<init>":(ILcom/google/zxing/datamatrix/decoder/Version$ECB;Lcom/google/zxing/datamatrix/decoder/Version$1;)V
    1233: invokespecial #21                 // Method "<init>":(IIIIILcom/google/zxing/datamatrix/decoder/Version$ECBlocks;)V
    1236: aastore
    1237: dup
    1238: bipush        29
    1240: new           #16                 // class com/google/zxing/datamatrix/decoder/Version
    1243: dup
    1244: bipush        30
    1246: bipush        16
    1248: bipush        48
    1250: bipush        14
    1252: bipush        22
    1254: new           #17                 // class com/google/zxing/datamatrix/decoder/Version$ECBlocks
    1257: dup
    1258: bipush        28
    1260: new           #18                 // class com/google/zxing/datamatrix/decoder/Version$ECB
    1263: dup
    1264: iconst_1
    1265: bipush        49
    1267: aconst_null
    1268: invokespecial #19                 // Method com/google/zxing/datamatrix/decoder/Version$ECB."<init>":(IILcom/google/zxing/datamatrix/decoder/Version$1;)V
    1271: aconst_null
    1272: invokespecial #20                 // Method com/google/zxing/datamatrix/decoder/Version$ECBlocks."<init>":(ILcom/google/zxing/datamatrix/decoder/Version$ECB;Lcom/google/zxing/datamatrix/decoder/Version$1;)V
    1275: invokespecial #21                 // Method "<init>":(IIIIILcom/google/zxing/datamatrix/decoder/Version$ECBlocks;)V
    1278: aastore
    1279: dup
    1280: bipush        30
    1282: new           #16                 // class com/google/zxing/datamatrix/decoder/Version
    1285: dup
    1286: bipush        31
    1288: bipush        8
    1290: bipush        48
    1292: bipush        6
    1294: bipush        22
    1296: new           #17                 // class com/google/zxing/datamatrix/decoder/Version$ECBlocks
    1299: dup
    1300: bipush        15
    1302: new           #18                 // class com/google/zxing/datamatrix/decoder/Version$ECB
    1305: dup
    1306: iconst_1
    1307: bipush        18
    1309: aconst_null
    1310: invokespecial #19                 // Method com/google/zxing/datamatrix/decoder/Version$ECB."<init>":(IILcom/google/zxing/datamatrix/decoder/Version$1;)V
    1313: aconst_null
    1314: invokespecial #20                 // Method com/google/zxing/datamatrix/decoder/Version$ECBlocks."<init>":(ILcom/google/zxing/datamatrix/decoder/Version$ECB;Lcom/google/zxing/datamatrix/decoder/Version$1;)V
    1317: invokespecial #21                 // Method "<init>":(IIIIILcom/google/zxing/datamatrix/decoder/Version$ECBlocks;)V
    1320: aastore
    1321: dup
    1322: bipush        31
    1324: new           #16                 // class com/google/zxing/datamatrix/decoder/Version
    1327: dup
    1328: bipush        32
    1330: bipush        8
    1332: bipush        64
    1334: bipush        6
    1336: bipush        14
    1338: new           #17                 // class com/google/zxing/datamatrix/decoder/Version$ECBlocks
    1341: dup
    1342: bipush        18
    1344: new           #18                 // class com/google/zxing/datamatrix/decoder/Version$ECB
    1347: dup
    1348: iconst_1
    1349: bipush        24
    1351: aconst_null
    1352: invokespecial #19                 // Method com/google/zxing/datamatrix/decoder/Version$ECB."<init>":(IILcom/google/zxing/datamatrix/decoder/Version$1;)V
    1355: aconst_null
    1356: invokespecial #20                 // Method com/google/zxing/datamatrix/decoder/Version$ECBlocks."<init>":(ILcom/google/zxing/datamatrix/decoder/Version$ECB;Lcom/google/zxing/datamatrix/decoder/Version$1;)V
    1359: invokespecial #21                 // Method "<init>":(IIIIILcom/google/zxing/datamatrix/decoder/Version$ECBlocks;)V
    1362: aastore
    1363: dup
    1364: bipush        32
    1366: new           #16                 // class com/google/zxing/datamatrix/decoder/Version
    1369: dup
    1370: bipush        33
    1372: bipush        8
    1374: bipush        80
    1376: bipush        6
    1378: bipush        18
    1380: new           #17                 // class com/google/zxing/datamatrix/decoder/Version$ECBlocks
    1383: dup
    1384: bipush        22
    1386: new           #18                 // class com/google/zxing/datamatrix/decoder/Version$ECB
    1389: dup
    1390: iconst_1
    1391: bipush        32
    1393: aconst_null
    1394: invokespecial #19                 // Method com/google/zxing/datamatrix/decoder/Version$ECB."<init>":(IILcom/google/zxing/datamatrix/decoder/Version$1;)V
    1397: aconst_null
    1398: invokespecial #20                 // Method com/google/zxing/datamatrix/decoder/Version$ECBlocks."<init>":(ILcom/google/zxing/datamatrix/decoder/Version$ECB;Lcom/google/zxing/datamatrix/decoder/Version$1;)V
    1401: invokespecial #21                 // Method "<init>":(IIIIILcom/google/zxing/datamatrix/decoder/Version$ECBlocks;)V
    1404: aastore
    1405: dup
    1406: bipush        33
    1408: new           #16                 // class com/google/zxing/datamatrix/decoder/Version
    1411: dup
    1412: bipush        34
    1414: bipush        8
    1416: bipush        96
    1418: bipush        6
    1420: bipush        22
    1422: new           #17                 // class com/google/zxing/datamatrix/decoder/Version$ECBlocks
    1425: dup
    1426: bipush        28
    1428: new           #18                 // class com/google/zxing/datamatrix/decoder/Version$ECB
    1431: dup
    1432: iconst_1
    1433: bipush        38
    1435: aconst_null
    1436: invokespecial #19                 // Method com/google/zxing/datamatrix/decoder/Version$ECB."<init>":(IILcom/google/zxing/datamatrix/decoder/Version$1;)V
    1439: aconst_null
    1440: invokespecial #20                 // Method com/google/zxing/datamatrix/decoder/Version$ECBlocks."<init>":(ILcom/google/zxing/datamatrix/decoder/Version$ECB;Lcom/google/zxing/datamatrix/decoder/Version$1;)V
    1443: invokespecial #21                 // Method "<init>":(IIIIILcom/google/zxing/datamatrix/decoder/Version$ECBlocks;)V
    1446: aastore
    1447: dup
    1448: bipush        34
    1450: new           #16                 // class com/google/zxing/datamatrix/decoder/Version
    1453: dup
    1454: bipush        35
    1456: bipush        8
    1458: bipush        120
    1460: bipush        6
    1462: bipush        18
    1464: new           #17                 // class com/google/zxing/datamatrix/decoder/Version$ECBlocks
    1467: dup
    1468: bipush        32
    1470: new           #18                 // class com/google/zxing/datamatrix/decoder/Version$ECB
    1473: dup
    1474: iconst_1
    1475: bipush        49
    1477: aconst_null
    1478: invokespecial #19                 // Method com/google/zxing/datamatrix/decoder/Version$ECB."<init>":(IILcom/google/zxing/datamatrix/decoder/Version$1;)V
    1481: aconst_null
    1482: invokespecial #20                 // Method com/google/zxing/datamatrix/decoder/Version$ECBlocks."<init>":(ILcom/google/zxing/datamatrix/decoder/Version$ECB;Lcom/google/zxing/datamatrix/decoder/Version$1;)V
    1485: invokespecial #21                 // Method "<init>":(IIIIILcom/google/zxing/datamatrix/decoder/Version$ECBlocks;)V
    1488: aastore
    1489: dup
    1490: bipush        35
    1492: new           #16                 // class com/google/zxing/datamatrix/decoder/Version
    1495: dup
    1496: bipush        36
    1498: bipush        8
    1500: sipush        144
    1503: bipush        6
    1505: bipush        22
    1507: new           #17                 // class com/google/zxing/datamatrix/decoder/Version$ECBlocks
    1510: dup
    1511: bipush        36
    1513: new           #18                 // class com/google/zxing/datamatrix/decoder/Version$ECB
    1516: dup
    1517: iconst_1
    1518: bipush        63
    1520: aconst_null
    1521: invokespecial #19                 // Method com/google/zxing/datamatrix/decoder/Version$ECB."<init>":(IILcom/google/zxing/datamatrix/decoder/Version$1;)V
    1524: aconst_null
    1525: invokespecial #20                 // Method com/google/zxing/datamatrix/decoder/Version$ECBlocks."<init>":(ILcom/google/zxing/datamatrix/decoder/Version$ECB;Lcom/google/zxing/datamatrix/decoder/Version$1;)V
    1528: invokespecial #21                 // Method "<init>":(IIIIILcom/google/zxing/datamatrix/decoder/Version$ECBlocks;)V
    1531: aastore
    1532: dup
    1533: bipush        36
    1535: new           #16                 // class com/google/zxing/datamatrix/decoder/Version
    1538: dup
    1539: bipush        37
    1541: bipush        12
    1543: bipush        64
    1545: bipush        10
    1547: bipush        14
    1549: new           #17                 // class com/google/zxing/datamatrix/decoder/Version$ECBlocks
    1552: dup
    1553: bipush        27
    1555: new           #18                 // class com/google/zxing/datamatrix/decoder/Version$ECB
    1558: dup
    1559: iconst_1
    1560: bipush        43
    1562: aconst_null
    1563: invokespecial #19                 // Method com/google/zxing/datamatrix/decoder/Version$ECB."<init>":(IILcom/google/zxing/datamatrix/decoder/Version$1;)V
    1566: aconst_null
    1567: invokespecial #20                 // Method com/google/zxing/datamatrix/decoder/Version$ECBlocks."<init>":(ILcom/google/zxing/datamatrix/decoder/Version$ECB;Lcom/google/zxing/datamatrix/decoder/Version$1;)V
    1570: invokespecial #21                 // Method "<init>":(IIIIILcom/google/zxing/datamatrix/decoder/Version$ECBlocks;)V
    1573: aastore
    1574: dup
    1575: bipush        37
    1577: new           #16                 // class com/google/zxing/datamatrix/decoder/Version
    1580: dup
    1581: bipush        38
    1583: bipush        12
    1585: bipush        88
    1587: bipush        10
    1589: bipush        20
    1591: new           #17                 // class com/google/zxing/datamatrix/decoder/Version$ECBlocks
    1594: dup
    1595: bipush        36
    1597: new           #18                 // class com/google/zxing/datamatrix/decoder/Version$ECB
    1600: dup
    1601: iconst_1
    1602: bipush        64
    1604: aconst_null
    1605: invokespecial #19                 // Method com/google/zxing/datamatrix/decoder/Version$ECB."<init>":(IILcom/google/zxing/datamatrix/decoder/Version$1;)V
    1608: aconst_null
    1609: invokespecial #20                 // Method com/google/zxing/datamatrix/decoder/Version$ECBlocks."<init>":(ILcom/google/zxing/datamatrix/decoder/Version$ECB;Lcom/google/zxing/datamatrix/decoder/Version$1;)V
    1612: invokespecial #21                 // Method "<init>":(IIIIILcom/google/zxing/datamatrix/decoder/Version$ECBlocks;)V
    1615: aastore
    1616: dup
    1617: bipush        38
    1619: new           #16                 // class com/google/zxing/datamatrix/decoder/Version
    1622: dup
    1623: bipush        39
    1625: bipush        16
    1627: bipush        64
    1629: bipush        14
    1631: bipush        14
    1633: new           #17                 // class com/google/zxing/datamatrix/decoder/Version$ECBlocks
    1636: dup
    1637: bipush        36
    1639: new           #18                 // class com/google/zxing/datamatrix/decoder/Version$ECB
    1642: dup
    1643: iconst_1
    1644: bipush        62
    1646: aconst_null
    1647: invokespecial #19                 // Method com/google/zxing/datamatrix/decoder/Version$ECB."<init>":(IILcom/google/zxing/datamatrix/decoder/Version$1;)V
    1650: aconst_null
    1651: invokespecial #20                 // Method com/google/zxing/datamatrix/decoder/Version$ECBlocks."<init>":(ILcom/google/zxing/datamatrix/decoder/Version$ECB;Lcom/google/zxing/datamatrix/decoder/Version$1;)V
    1654: invokespecial #21                 // Method "<init>":(IIIIILcom/google/zxing/datamatrix/decoder/Version$ECBlocks;)V
    1657: aastore
    1658: dup
    1659: bipush        39
    1661: new           #16                 // class com/google/zxing/datamatrix/decoder/Version
    1664: dup
    1665: bipush        40
    1667: bipush        20
    1669: bipush        36
    1671: bipush        18
    1673: bipush        16
    1675: new           #17                 // class com/google/zxing/datamatrix/decoder/Version$ECBlocks
    1678: dup
    1679: bipush        28
    1681: new           #18                 // class com/google/zxing/datamatrix/decoder/Version$ECB
    1684: dup
    1685: iconst_1
    1686: bipush        44
    1688: aconst_null
    1689: invokespecial #19                 // Method com/google/zxing/datamatrix/decoder/Version$ECB."<init>":(IILcom/google/zxing/datamatrix/decoder/Version$1;)V
    1692: aconst_null
    1693: invokespecial #20                 // Method com/google/zxing/datamatrix/decoder/Version$ECBlocks."<init>":(ILcom/google/zxing/datamatrix/decoder/Version$ECB;Lcom/google/zxing/datamatrix/decoder/Version$1;)V
    1696: invokespecial #21                 // Method "<init>":(IIIIILcom/google/zxing/datamatrix/decoder/Version$ECBlocks;)V
    1699: aastore
    1700: dup
    1701: bipush        40
    1703: new           #16                 // class com/google/zxing/datamatrix/decoder/Version
    1706: dup
    1707: bipush        41
    1709: bipush        20
    1711: bipush        44
    1713: bipush        18
    1715: bipush        20
    1717: new           #17                 // class com/google/zxing/datamatrix/decoder/Version$ECBlocks
    1720: dup
    1721: bipush        34
    1723: new           #18                 // class com/google/zxing/datamatrix/decoder/Version$ECB
    1726: dup
    1727: iconst_1
    1728: bipush        56
    1730: aconst_null
    1731: invokespecial #19                 // Method com/google/zxing/datamatrix/decoder/Version$ECB."<init>":(IILcom/google/zxing/datamatrix/decoder/Version$1;)V
    1734: aconst_null
    1735: invokespecial #20                 // Method com/google/zxing/datamatrix/decoder/Version$ECBlocks."<init>":(ILcom/google/zxing/datamatrix/decoder/Version$ECB;Lcom/google/zxing/datamatrix/decoder/Version$1;)V
    1738: invokespecial #21                 // Method "<init>":(IIIIILcom/google/zxing/datamatrix/decoder/Version$ECBlocks;)V
    1741: aastore
    1742: dup
    1743: bipush        41
    1745: new           #16                 // class com/google/zxing/datamatrix/decoder/Version
    1748: dup
    1749: bipush        42
    1751: bipush        20
    1753: bipush        64
    1755: bipush        18
    1757: bipush        14
    1759: new           #17                 // class com/google/zxing/datamatrix/decoder/Version$ECBlocks
    1762: dup
    1763: bipush        42
    1765: new           #18                 // class com/google/zxing/datamatrix/decoder/Version$ECB
    1768: dup
    1769: iconst_1
    1770: bipush        84
    1772: aconst_null
    1773: invokespecial #19                 // Method com/google/zxing/datamatrix/decoder/Version$ECB."<init>":(IILcom/google/zxing/datamatrix/decoder/Version$1;)V
    1776: aconst_null
    1777: invokespecial #20                 // Method com/google/zxing/datamatrix/decoder/Version$ECBlocks."<init>":(ILcom/google/zxing/datamatrix/decoder/Version$ECB;Lcom/google/zxing/datamatrix/decoder/Version$1;)V
    1780: invokespecial #21                 // Method "<init>":(IIIIILcom/google/zxing/datamatrix/decoder/Version$ECBlocks;)V
    1783: aastore
    1784: dup
    1785: bipush        42
    1787: new           #16                 // class com/google/zxing/datamatrix/decoder/Version
    1790: dup
    1791: bipush        43
    1793: bipush        22
    1795: bipush        48
    1797: bipush        20
    1799: bipush        22
    1801: new           #17                 // class com/google/zxing/datamatrix/decoder/Version$ECBlocks
    1804: dup
    1805: bipush        38
    1807: new           #18                 // class com/google/zxing/datamatrix/decoder/Version$ECB
    1810: dup
    1811: iconst_1
    1812: bipush        72
    1814: aconst_null
    1815: invokespecial #19                 // Method com/google/zxing/datamatrix/decoder/Version$ECB."<init>":(IILcom/google/zxing/datamatrix/decoder/Version$1;)V
    1818: aconst_null
    1819: invokespecial #20                 // Method com/google/zxing/datamatrix/decoder/Version$ECBlocks."<init>":(ILcom/google/zxing/datamatrix/decoder/Version$ECB;Lcom/google/zxing/datamatrix/decoder/Version$1;)V
    1822: invokespecial #21                 // Method "<init>":(IIIIILcom/google/zxing/datamatrix/decoder/Version$ECBlocks;)V
    1825: aastore
    1826: dup
    1827: bipush        43
    1829: new           #16                 // class com/google/zxing/datamatrix/decoder/Version
    1832: dup
    1833: bipush        44
    1835: bipush        24
    1837: bipush        48
    1839: bipush        22
    1841: bipush        22
    1843: new           #17                 // class com/google/zxing/datamatrix/decoder/Version$ECBlocks
    1846: dup
    1847: bipush        41
    1849: new           #18                 // class com/google/zxing/datamatrix/decoder/Version$ECB
    1852: dup
    1853: iconst_1
    1854: bipush        80
    1856: aconst_null
    1857: invokespecial #19                 // Method com/google/zxing/datamatrix/decoder/Version$ECB."<init>":(IILcom/google/zxing/datamatrix/decoder/Version$1;)V
    1860: aconst_null
    1861: invokespecial #20                 // Method com/google/zxing/datamatrix/decoder/Version$ECBlocks."<init>":(ILcom/google/zxing/datamatrix/decoder/Version$ECB;Lcom/google/zxing/datamatrix/decoder/Version$1;)V
    1864: invokespecial #21                 // Method "<init>":(IIIIILcom/google/zxing/datamatrix/decoder/Version$ECBlocks;)V
    1867: aastore
    1868: dup
    1869: bipush        44
    1871: new           #16                 // class com/google/zxing/datamatrix/decoder/Version
    1874: dup
    1875: bipush        45
    1877: bipush        24
    1879: bipush        64
    1881: bipush        22
    1883: bipush        14
    1885: new           #17                 // class com/google/zxing/datamatrix/decoder/Version$ECBlocks
    1888: dup
    1889: bipush        46
    1891: new           #18                 // class com/google/zxing/datamatrix/decoder/Version$ECB
    1894: dup
    1895: iconst_1
    1896: bipush        108
    1898: aconst_null
    1899: invokespecial #19                 // Method com/google/zxing/datamatrix/decoder/Version$ECB."<init>":(IILcom/google/zxing/datamatrix/decoder/Version$1;)V
    1902: aconst_null
    1903: invokespecial #20                 // Method com/google/zxing/datamatrix/decoder/Version$ECBlocks."<init>":(ILcom/google/zxing/datamatrix/decoder/Version$ECB;Lcom/google/zxing/datamatrix/decoder/Version$1;)V
    1906: invokespecial #21                 // Method "<init>":(IIIIILcom/google/zxing/datamatrix/decoder/Version$ECBlocks;)V
    1909: aastore
    1910: dup
    1911: bipush        45
    1913: new           #16                 // class com/google/zxing/datamatrix/decoder/Version
    1916: dup
    1917: bipush        46
    1919: bipush        26
    1921: bipush        40
    1923: bipush        24
    1925: bipush        18
    1927: new           #17                 // class com/google/zxing/datamatrix/decoder/Version$ECBlocks
    1930: dup
    1931: bipush        38
    1933: new           #18                 // class com/google/zxing/datamatrix/decoder/Version$ECB
    1936: dup
    1937: iconst_1
    1938: bipush        70
    1940: aconst_null
    1941: invokespecial #19                 // Method com/google/zxing/datamatrix/decoder/Version$ECB."<init>":(IILcom/google/zxing/datamatrix/decoder/Version$1;)V
    1944: aconst_null
    1945: invokespecial #20                 // Method com/google/zxing/datamatrix/decoder/Version$ECBlocks."<init>":(ILcom/google/zxing/datamatrix/decoder/Version$ECB;Lcom/google/zxing/datamatrix/decoder/Version$1;)V
    1948: invokespecial #21                 // Method "<init>":(IIIIILcom/google/zxing/datamatrix/decoder/Version$ECBlocks;)V
    1951: aastore
    1952: dup
    1953: bipush        46
    1955: new           #16                 // class com/google/zxing/datamatrix/decoder/Version
    1958: dup
    1959: bipush        47
    1961: bipush        26
    1963: bipush        48
    1965: bipush        24
    1967: bipush        22
    1969: new           #17                 // class com/google/zxing/datamatrix/decoder/Version$ECBlocks
    1972: dup
    1973: bipush        42
    1975: new           #18                 // class com/google/zxing/datamatrix/decoder/Version$ECB
    1978: dup
    1979: iconst_1
    1980: bipush        90
    1982: aconst_null
    1983: invokespecial #19                 // Method com/google/zxing/datamatrix/decoder/Version$ECB."<init>":(IILcom/google/zxing/datamatrix/decoder/Version$1;)V
    1986: aconst_null
    1987: invokespecial #20                 // Method com/google/zxing/datamatrix/decoder/Version$ECBlocks."<init>":(ILcom/google/zxing/datamatrix/decoder/Version$ECB;Lcom/google/zxing/datamatrix/decoder/Version$1;)V
    1990: invokespecial #21                 // Method "<init>":(IIIIILcom/google/zxing/datamatrix/decoder/Version$ECBlocks;)V
    1993: aastore
    1994: dup
    1995: bipush        47
    1997: new           #16                 // class com/google/zxing/datamatrix/decoder/Version
    2000: dup
    2001: bipush        48
    2003: bipush        26
    2005: bipush        64
    2007: bipush        24
    2009: bipush        14
    2011: new           #17                 // class com/google/zxing/datamatrix/decoder/Version$ECBlocks
    2014: dup
    2015: bipush        50
    2017: new           #18                 // class com/google/zxing/datamatrix/decoder/Version$ECB
    2020: dup
    2021: iconst_1
    2022: bipush        118
    2024: aconst_null
    2025: invokespecial #19                 // Method com/google/zxing/datamatrix/decoder/Version$ECB."<init>":(IILcom/google/zxing/datamatrix/decoder/Version$1;)V
    2028: aconst_null
    2029: invokespecial #20                 // Method com/google/zxing/datamatrix/decoder/Version$ECBlocks."<init>":(ILcom/google/zxing/datamatrix/decoder/Version$ECB;Lcom/google/zxing/datamatrix/decoder/Version$1;)V
    2032: invokespecial #21                 // Method "<init>":(IIIIILcom/google/zxing/datamatrix/decoder/Version$ECBlocks;)V
    2035: aastore
    2036: areturn

  static {};
    Code:
       0: invokestatic  #23                 // Method buildVersions:()[Lcom/google/zxing/datamatrix/decoder/Version;
       3: putstatic     #14                 // Field VERSIONS:[Lcom/google/zxing/datamatrix/decoder/Version;
       6: return
}
