Compiled from "DubboAbstractTDigest.java"
public abstract class org.apache.dubbo.metrics.aggregate.DubboAbstractTDigest extends com.tdunning.math.stats.TDigest {
  boolean recordAllData;

  static final boolean $assertionsDisabled;

  public org.apache.dubbo.metrics.aggregate.DubboAbstractTDigest();
    Code:
       0: aload_0
       1: invokespecial #1                  // Method com/tdunning/math/stats/TDigest."<init>":()V
       4: aload_0
       5: iconst_0
       6: putfield      #2                  // Field recordAllData:Z
       9: return

  static double weightedAverage(double, double, double, double);
    Code:
       0: dload_0
       1: dload         4
       3: dcmpg
       4: ifgt          17
       7: dload_0
       8: dload_2
       9: dload         4
      11: dload         6
      13: invokestatic  #3                  // Method weightedAverageSorted:(DDDD)D
      16: dreturn
      17: dload         4
      19: dload         6
      21: dload_0
      22: dload_2
      23: invokestatic  #3                  // Method weightedAverageSorted:(DDDD)D
      26: dreturn

  private static double weightedAverageSorted(double, double, double, double);
    Code:
       0: getstatic     #4                  // Field $assertionsDisabled:Z
       3: ifne          21
       6: dload_0
       7: dload         4
       9: dcmpg
      10: ifle          21
      13: new           #5                  // class java/lang/AssertionError
      16: dup
      17: invokespecial #6                  // Method java/lang/AssertionError."<init>":()V
      20: athrow
      21: dload_0
      22: dload_2
      23: dmul
      24: dload         4
      26: dload         6
      28: dmul
      29: dadd
      30: dload_2
      31: dload         6
      33: dadd
      34: ddiv
      35: dstore        8
      37: dload_0
      38: dload         8
      40: dload         4
      42: invokestatic  #7                  // Method java/lang/Math.min:(DD)D
      45: invokestatic  #8                  // Method java/lang/Math.max:(DD)D
      48: dreturn

  abstract void add(double, int, com.tdunning.math.stats.Centroid);

  public com.tdunning.math.stats.TDigest recordAllData();
    Code:
       0: aload_0
       1: iconst_1
       2: putfield      #2                  // Field recordAllData:Z
       5: aload_0
       6: areturn

  public boolean isRecording();
    Code:
       0: aload_0
       1: getfield      #2                  // Field recordAllData:Z
       4: ireturn

  public void add(double);
    Code:
       0: aload_0
       1: dload_1
       2: iconst_1
       3: invokevirtual #9                  // Method add:(DI)V
       6: return

  public void add(com.tdunning.math.stats.TDigest);
    Code:
       0: aload_1
       1: invokevirtual #10                 // Method com/tdunning/math/stats/TDigest.centroids:()Ljava/util/Collection;
       4: invokeinterface #11,  1           // InterfaceMethod java/util/Collection.iterator:()Ljava/util/Iterator;
       9: astore_2
      10: aload_2
      11: invokeinterface #12,  1           // InterfaceMethod java/util/Iterator.hasNext:()Z
      16: ifeq          45
      19: aload_2
      20: invokeinterface #13,  1           // InterfaceMethod java/util/Iterator.next:()Ljava/lang/Object;
      25: checkcast     #14                 // class com/tdunning/math/stats/Centroid
      28: astore_3
      29: aload_0
      30: aload_3
      31: invokevirtual #15                 // Method com/tdunning/math/stats/Centroid.mean:()D
      34: aload_3
      35: invokevirtual #16                 // Method com/tdunning/math/stats/Centroid.count:()I
      38: aload_3
      39: invokevirtual #17                 // Method add:(DILcom/tdunning/math/stats/Centroid;)V
      42: goto          10
      45: return

  static {};
    Code:
       0: ldc           #18                 // class org/apache/dubbo/metrics/aggregate/DubboAbstractTDigest
       2: invokevirtual #19                 // Method java/lang/Class.desiredAssertionStatus:()Z
       5: ifne          12
       8: iconst_1
       9: goto          13
      12: iconst_0
      13: putstatic     #4                  // Field $assertionsDisabled:Z
      16: return
}
