Compiled from "DubboMergingDigest.java"
class org.apache.dubbo.metrics.aggregate.DubboMergingDigest$1$1 implements java.util.Iterator<com.tdunning.math.stats.Centroid> {
  int i;

  final org.apache.dubbo.metrics.aggregate.DubboMergingDigest$1 this$1;

  org.apache.dubbo.metrics.aggregate.DubboMergingDigest$1$1(org.apache.dubbo.metrics.aggregate.DubboMergingDigest$1);
    Code:
       0: aload_0
       1: aload_1
       2: putfield      #1                  // Field this$1:Lorg/apache/dubbo/metrics/aggregate/DubboMergingDigest$1;
       5: aload_0
       6: invokespecial #2                  // Method java/lang/Object."<init>":()V
       9: aload_0
      10: iconst_0
      11: putfield      #3                  // Field i:I
      14: return

  public boolean hasNext();
    Code:
       0: aload_0
       1: getfield      #3                  // Field i:I
       4: aload_0
       5: getfield      #1                  // Field this$1:Lorg/apache/dubbo/metrics/aggregate/DubboMergingDigest$1;
       8: getfield      #4                  // Field org/apache/dubbo/metrics/aggregate/DubboMergingDigest$1.this$0:Lorg/apache/dubbo/metrics/aggregate/DubboMergingDigest;
      11: invokestatic  #5                  // Method org/apache/dubbo/metrics/aggregate/DubboMergingDigest.access$000:(Lorg/apache/dubbo/metrics/aggregate/DubboMergingDigest;)Ljava/util/concurrent/atomic/AtomicInteger;
      14: invokevirtual #6                  // Method java/util/concurrent/atomic/AtomicInteger.get:()I
      17: if_icmpge     24
      20: iconst_1
      21: goto          25
      24: iconst_0
      25: ireturn

  public com.tdunning.math.stats.Centroid next();
    Code:
       0: aload_0
       1: invokevirtual #7                  // Method hasNext:()Z
       4: ifne          15
       7: new           #8                  // class java/util/NoSuchElementException
      10: dup
      11: invokespecial #9                  // Method java/util/NoSuchElementException."<init>":()V
      14: athrow
      15: new           #10                 // class com/tdunning/math/stats/Centroid
      18: dup
      19: aload_0
      20: getfield      #1                  // Field this$1:Lorg/apache/dubbo/metrics/aggregate/DubboMergingDigest$1;
      23: getfield      #4                  // Field org/apache/dubbo/metrics/aggregate/DubboMergingDigest$1.this$0:Lorg/apache/dubbo/metrics/aggregate/DubboMergingDigest;
      26: invokestatic  #11                 // Method org/apache/dubbo/metrics/aggregate/DubboMergingDigest.access$100:(Lorg/apache/dubbo/metrics/aggregate/DubboMergingDigest;)[D
      29: aload_0
      30: getfield      #3                  // Field i:I
      33: daload
      34: aload_0
      35: getfield      #1                  // Field this$1:Lorg/apache/dubbo/metrics/aggregate/DubboMergingDigest$1;
      38: getfield      #4                  // Field org/apache/dubbo/metrics/aggregate/DubboMergingDigest$1.this$0:Lorg/apache/dubbo/metrics/aggregate/DubboMergingDigest;
      41: invokestatic  #12                 // Method org/apache/dubbo/metrics/aggregate/DubboMergingDigest.access$200:(Lorg/apache/dubbo/metrics/aggregate/DubboMergingDigest;)[D
      44: aload_0
      45: getfield      #3                  // Field i:I
      48: daload
      49: d2i
      50: invokespecial #13                 // Method com/tdunning/math/stats/Centroid."<init>":(DI)V
      53: astore_1
      54: aload_0
      55: getfield      #1                  // Field this$1:Lorg/apache/dubbo/metrics/aggregate/DubboMergingDigest$1;
      58: getfield      #4                  // Field org/apache/dubbo/metrics/aggregate/DubboMergingDigest$1.this$0:Lorg/apache/dubbo/metrics/aggregate/DubboMergingDigest;
      61: invokestatic  #14                 // Method org/apache/dubbo/metrics/aggregate/DubboMergingDigest.access$300:(Lorg/apache/dubbo/metrics/aggregate/DubboMergingDigest;)Ljava/util/List;
      64: ifnull        92
      67: aload_0
      68: getfield      #1                  // Field this$1:Lorg/apache/dubbo/metrics/aggregate/DubboMergingDigest$1;
      71: getfield      #4                  // Field org/apache/dubbo/metrics/aggregate/DubboMergingDigest$1.this$0:Lorg/apache/dubbo/metrics/aggregate/DubboMergingDigest;
      74: invokestatic  #14                 // Method org/apache/dubbo/metrics/aggregate/DubboMergingDigest.access$300:(Lorg/apache/dubbo/metrics/aggregate/DubboMergingDigest;)Ljava/util/List;
      77: aload_0
      78: getfield      #3                  // Field i:I
      81: invokeinterface #15,  2           // InterfaceMethod java/util/List.get:(I)Ljava/lang/Object;
      86: checkcast     #16                 // class java/util/List
      89: goto          93
      92: aconst_null
      93: astore_2
      94: aload_2
      95: ifnull        115
      98: aload_2
      99: aload_1
     100: dup
     101: invokevirtual #17                 // Method java/lang/Object.getClass:()Ljava/lang/Class;
     104: pop
     105: invokedynamic #18,  0             // InvokeDynamic #0:accept:(Lcom/tdunning/math/stats/Centroid;)Ljava/util/function/Consumer;
     110: invokeinterface #19,  2           // InterfaceMethod java/util/List.forEach:(Ljava/util/function/Consumer;)V
     115: aload_0
     116: dup
     117: getfield      #3                  // Field i:I
     120: iconst_1
     121: iadd
     122: putfield      #3                  // Field i:I
     125: aload_1
     126: areturn

  public void remove();
    Code:
       0: new           #20                 // class java/lang/UnsupportedOperationException
       3: dup
       4: ldc           #21                 // String Default operation
       6: invokespecial #22                 // Method java/lang/UnsupportedOperationException."<init>":(Ljava/lang/String;)V
       9: athrow

  public java.lang.Object next();
    Code:
       0: aload_0
       1: invokevirtual #23                 // Method next:()Lcom/tdunning/math/stats/Centroid;
       4: areturn
}
