Compiled from "DubboMergingDigest.java"
public final class org.apache.dubbo.metrics.aggregate.DubboMergingDigest$Encoding extends java.lang.Enum<org.apache.dubbo.metrics.aggregate.DubboMergingDigest$Encoding> {
  public static final org.apache.dubbo.metrics.aggregate.DubboMergingDigest$Encoding VERBOSE_ENCODING;

  public static final org.apache.dubbo.metrics.aggregate.DubboMergingDigest$Encoding SMALL_ENCODING;

  private final int code;

  private static final org.apache.dubbo.metrics.aggregate.DubboMergingDigest$Encoding[] $VALUES;

  public static org.apache.dubbo.metrics.aggregate.DubboMergingDigest$Encoding[] values();
    Code:
       0: getstatic     #2                  // Field $VALUES:[Lorg/apache/dubbo/metrics/aggregate/DubboMergingDigest$Encoding;
       3: invokevirtual #3                  // Method "[Lorg/apache/dubbo/metrics/aggregate/DubboMergingDigest$Encoding;".clone:()Ljava/lang/Object;
       6: checkcast     #4                  // class "[Lorg/apache/dubbo/metrics/aggregate/DubboMergingDigest$Encoding;"
       9: areturn

  public static org.apache.dubbo.metrics.aggregate.DubboMergingDigest$Encoding valueOf(java.lang.String);
    Code:
       0: ldc           #5                  // class org/apache/dubbo/metrics/aggregate/DubboMergingDigest$Encoding
       2: aload_0
       3: invokestatic  #6                  // Method java/lang/Enum.valueOf:(Ljava/lang/Class;Ljava/lang/String;)Ljava/lang/Enum;
       6: checkcast     #5                  // class org/apache/dubbo/metrics/aggregate/DubboMergingDigest$Encoding
       9: areturn

  private org.apache.dubbo.metrics.aggregate.DubboMergingDigest$Encoding(int);
    Code:
       0: aload_0
       1: aload_1
       2: iload_2
       3: invokespecial #7                  // Method java/lang/Enum."<init>":(Ljava/lang/String;I)V
       6: aload_0
       7: iload_3
       8: putfield      #1                  // Field code:I
      11: return

  static int access$400(org.apache.dubbo.metrics.aggregate.DubboMergingDigest$Encoding);
    Code:
       0: aload_0
       1: getfield      #1                  // Field code:I
       4: ireturn

  static {};
    Code:
       0: new           #5                  // class org/apache/dubbo/metrics/aggregate/DubboMergingDigest$Encoding
       3: dup
       4: ldc           #8                  // String VERBOSE_ENCODING
       6: iconst_0
       7: iconst_1
       8: invokespecial #9                  // Method "<init>":(Ljava/lang/String;II)V
      11: putstatic     #10                 // Field VERBOSE_ENCODING:Lorg/apache/dubbo/metrics/aggregate/DubboMergingDigest$Encoding;
      14: new           #5                  // class org/apache/dubbo/metrics/aggregate/DubboMergingDigest$Encoding
      17: dup
      18: ldc           #11                 // String SMALL_ENCODING
      20: iconst_1
      21: iconst_2
      22: invokespecial #9                  // Method "<init>":(Ljava/lang/String;II)V
      25: putstatic     #12                 // Field SMALL_ENCODING:Lorg/apache/dubbo/metrics/aggregate/DubboMergingDigest$Encoding;
      28: iconst_2
      29: anewarray     #5                  // class org/apache/dubbo/metrics/aggregate/DubboMergingDigest$Encoding
      32: dup
      33: iconst_0
      34: getstatic     #10                 // Field VERBOSE_ENCODING:Lorg/apache/dubbo/metrics/aggregate/DubboMergingDigest$Encoding;
      37: aastore
      38: dup
      39: iconst_1
      40: getstatic     #12                 // Field SMALL_ENCODING:Lorg/apache/dubbo/metrics/aggregate/DubboMergingDigest$Encoding;
      43: aastore
      44: putstatic     #2                  // Field $VALUES:[Lorg/apache/dubbo/metrics/aggregate/DubboMergingDigest$Encoding;
      47: return
}
