Compiled from "DubboMergingDigest.java"
class org.apache.dubbo.metrics.aggregate.DubboMergingDigest$1 extends java.util.AbstractCollection<com.tdunning.math.stats.Centroid> {
  final org.apache.dubbo.metrics.aggregate.DubboMergingDigest this$0;

  org.apache.dubbo.metrics.aggregate.DubboMergingDigest$1(org.apache.dubbo.metrics.aggregate.DubboMergingDigest);
    Code:
       0: aload_0
       1: aload_1
       2: putfield      #1                  // Field this$0:Lorg/apache/dubbo/metrics/aggregate/DubboMergingDigest;
       5: aload_0
       6: invokespecial #2                  // Method java/util/AbstractCollection."<init>":()V
       9: return

  public java.util.Iterator<com.tdunning.math.stats.Centroid> iterator();
    Code:
       0: new           #3                  // class org/apache/dubbo/metrics/aggregate/DubboMergingDigest$1$1
       3: dup
       4: aload_0
       5: invokespecial #4                  // Method org/apache/dubbo/metrics/aggregate/DubboMergingDigest$1$1."<init>":(Lorg/apache/dubbo/metrics/aggregate/DubboMergingDigest$1;)V
       8: areturn

  public int size();
    Code:
       0: aload_0
       1: getfield      #1                  // Field this$0:Lorg/apache/dubbo/metrics/aggregate/DubboMergingDigest;
       4: invokestatic  #5                  // Method org/apache/dubbo/metrics/aggregate/DubboMergingDigest.access$000:(Lorg/apache/dubbo/metrics/aggregate/DubboMergingDigest;)Ljava/util/concurrent/atomic/AtomicInteger;
       7: invokevirtual #6                  // Method java/util/concurrent/atomic/AtomicInteger.get:()I
      10: ireturn
}
