Compiled from "SlidingWindow.java"
public abstract class org.apache.dubbo.metrics.aggregate.SlidingWindow<T> {
  protected int paneCount;

  protected long intervalInMs;

  protected long paneIntervalInMs;

  protected final java.util.concurrent.atomic.AtomicReferenceArray<org.apache.dubbo.metrics.aggregate.Pane<T>> referenceArray;

  private final java.util.concurrent.locks.ReentrantLock updateLock;

  protected org.apache.dubbo.metrics.aggregate.SlidingWindow(int, long);
    Code:
       0: aload_0
       1: invokespecial #1                  // Method java/lang/Object."<init>":()V
       4: aload_0
       5: new           #2                  // class java/util/concurrent/locks/ReentrantLock
       8: dup
       9: invokespecial #3                  // Method java/util/concurrent/locks/ReentrantLock."<init>":()V
      12: putfield      #4                  // Field updateLock:Ljava/util/concurrent/locks/ReentrantLock;
      15: iload_1
      16: ifle          23
      19: iconst_1
      20: goto          24
      23: iconst_0
      24: new           #5                  // class java/lang/StringBuilder
      27: dup
      28: invokespecial #6                  // Method java/lang/StringBuilder."<init>":()V
      31: ldc           #7                  // String pane count is invalid:
      33: invokevirtual #8                  // Method java/lang/StringBuilder.append:(Ljava/lang/String;)Ljava/lang/StringBuilder;
      36: iload_1
      37: invokevirtual #9                  // Method java/lang/StringBuilder.append:(I)Ljava/lang/StringBuilder;
      40: invokevirtual #10                 // Method java/lang/StringBuilder.toString:()Ljava/lang/String;
      43: invokestatic  #11                 // Method org/apache/dubbo/common/utils/Assert.assertTrue:(ZLjava/lang/String;)V
      46: lload_2
      47: lconst_0
      48: lcmp
      49: ifle          56
      52: iconst_1
      53: goto          57
      56: iconst_0
      57: ldc           #12                 // String total time interval of the sliding window should be positive
      59: invokestatic  #11                 // Method org/apache/dubbo/common/utils/Assert.assertTrue:(ZLjava/lang/String;)V
      62: lload_2
      63: iload_1
      64: i2l
      65: lrem
      66: lconst_0
      67: lcmp
      68: ifne          75
      71: iconst_1
      72: goto          76
      75: iconst_0
      76: ldc           #13                 // String total time interval needs to be evenly divided
      78: invokestatic  #11                 // Method org/apache/dubbo/common/utils/Assert.assertTrue:(ZLjava/lang/String;)V
      81: aload_0
      82: iload_1
      83: putfield      #14                 // Field paneCount:I
      86: aload_0
      87: lload_2
      88: putfield      #15                 // Field intervalInMs:J
      91: aload_0
      92: lload_2
      93: iload_1
      94: i2l
      95: ldiv
      96: putfield      #16                 // Field paneIntervalInMs:J
      99: aload_0
     100: new           #17                 // class java/util/concurrent/atomic/AtomicReferenceArray
     103: dup
     104: iload_1
     105: invokespecial #18                 // Method java/util/concurrent/atomic/AtomicReferenceArray."<init>":(I)V
     108: putfield      #19                 // Field referenceArray:Ljava/util/concurrent/atomic/AtomicReferenceArray;
     111: return

  public org.apache.dubbo.metrics.aggregate.Pane<T> currentPane();
    Code:
       0: aload_0
       1: invokestatic  #20                 // Method java/lang/System.currentTimeMillis:()J
       4: invokevirtual #21                 // Method currentPane:(J)Lorg/apache/dubbo/metrics/aggregate/Pane;
       7: areturn

  public org.apache.dubbo.metrics.aggregate.Pane<T> currentPane(long);
    Code:
       0: lload_1
       1: lconst_0
       2: lcmp
       3: ifge          8
       6: aconst_null
       7: areturn
       8: aload_0
       9: lload_1
      10: invokespecial #22                 // Method calculatePaneIdx:(J)I
      13: istore_3
      14: aload_0
      15: lload_1
      16: invokevirtual #23                 // Method calculatePaneStart:(J)J
      19: lstore        4
      21: aload_0
      22: getfield      #19                 // Field referenceArray:Ljava/util/concurrent/atomic/AtomicReferenceArray;
      25: iload_3
      26: invokevirtual #24                 // Method java/util/concurrent/atomic/AtomicReferenceArray.get:(I)Ljava/lang/Object;
      29: checkcast     #25                 // class org/apache/dubbo/metrics/aggregate/Pane
      32: astore        6
      34: aload         6
      36: ifnonnull     82
      39: new           #25                 // class org/apache/dubbo/metrics/aggregate/Pane
      42: dup
      43: aload_0
      44: getfield      #16                 // Field paneIntervalInMs:J
      47: lload         4
      49: aload_0
      50: lload_1
      51: invokevirtual #26                 // Method newEmptyValue:(J)Ljava/lang/Object;
      54: invokespecial #27                 // Method org/apache/dubbo/metrics/aggregate/Pane."<init>":(JJLjava/lang/Object;)V
      57: astore        7
      59: aload_0
      60: getfield      #19                 // Field referenceArray:Ljava/util/concurrent/atomic/AtomicReferenceArray;
      63: iload_3
      64: aconst_null
      65: aload         7
      67: invokevirtual #28                 // Method java/util/concurrent/atomic/AtomicReferenceArray.compareAndSet:(ILjava/lang/Object;Ljava/lang/Object;)Z
      70: ifeq          76
      73: aload         7
      75: areturn
      76: invokestatic  #29                 // Method java/lang/Thread.yield:()V
      79: goto          185
      82: lload         4
      84: aload         6
      86: invokevirtual #30                 // Method org/apache/dubbo/metrics/aggregate/Pane.getStartInMs:()J
      89: lcmp
      90: ifne          96
      93: aload         6
      95: areturn
      96: lload         4
      98: aload         6
     100: invokevirtual #30                 // Method org/apache/dubbo/metrics/aggregate/Pane.getStartInMs:()J
     103: lcmp
     104: ifle          155
     107: aload_0
     108: getfield      #4                  // Field updateLock:Ljava/util/concurrent/locks/ReentrantLock;
     111: invokevirtual #31                 // Method java/util/concurrent/locks/ReentrantLock.tryLock:()Z
     114: ifeq          149
     117: aload_0
     118: aload         6
     120: lload         4
     122: invokevirtual #32                 // Method resetPaneTo:(Lorg/apache/dubbo/metrics/aggregate/Pane;J)Lorg/apache/dubbo/metrics/aggregate/Pane;
     125: astore        7
     127: aload_0
     128: getfield      #4                  // Field updateLock:Ljava/util/concurrent/locks/ReentrantLock;
     131: invokevirtual #33                 // Method java/util/concurrent/locks/ReentrantLock.unlock:()V
     134: aload         7
     136: areturn
     137: astore        8
     139: aload_0
     140: getfield      #4                  // Field updateLock:Ljava/util/concurrent/locks/ReentrantLock;
     143: invokevirtual #33                 // Method java/util/concurrent/locks/ReentrantLock.unlock:()V
     146: aload         8
     148: athrow
     149: invokestatic  #29                 // Method java/lang/Thread.yield:()V
     152: goto          185
     155: lload         4
     157: aload         6
     159: invokevirtual #30                 // Method org/apache/dubbo/metrics/aggregate/Pane.getStartInMs:()J
     162: lcmp
     163: ifge          185
     166: new           #25                 // class org/apache/dubbo/metrics/aggregate/Pane
     169: dup
     170: aload_0
     171: getfield      #16                 // Field paneIntervalInMs:J
     174: lload         4
     176: aload_0
     177: lload_1
     178: invokevirtual #26                 // Method newEmptyValue:(J)Ljava/lang/Object;
     181: invokespecial #27                 // Method org/apache/dubbo/metrics/aggregate/Pane."<init>":(JJLjava/lang/Object;)V
     184: areturn
     185: goto          21
    Exception table:
       from    to  target type
         117   127   137   any
         137   139   137   any

  public T getPaneValue(long);
    Code:
       0: lload_1
       1: lconst_0
       2: lcmp
       3: ifge          8
       6: aconst_null
       7: areturn
       8: aload_0
       9: lload_1
      10: invokespecial #22                 // Method calculatePaneIdx:(J)I
      13: istore_3
      14: aload_0
      15: getfield      #19                 // Field referenceArray:Ljava/util/concurrent/atomic/AtomicReferenceArray;
      18: iload_3
      19: invokevirtual #24                 // Method java/util/concurrent/atomic/AtomicReferenceArray.get:(I)Ljava/lang/Object;
      22: checkcast     #25                 // class org/apache/dubbo/metrics/aggregate/Pane
      25: astore        4
      27: aload         4
      29: ifnull        41
      32: aload         4
      34: lload_1
      35: invokevirtual #34                 // Method org/apache/dubbo/metrics/aggregate/Pane.isTimeInWindow:(J)Z
      38: ifne          43
      41: aconst_null
      42: areturn
      43: aload         4
      45: invokevirtual #35                 // Method org/apache/dubbo/metrics/aggregate/Pane.getValue:()Ljava/lang/Object;
      48: areturn

  public abstract T newEmptyValue(long);

  protected abstract org.apache.dubbo.metrics.aggregate.Pane<T> resetPaneTo(org.apache.dubbo.metrics.aggregate.Pane<T>, long);

  private int calculatePaneIdx(long);
    Code:
       0: lload_1
       1: aload_0
       2: getfield      #16                 // Field paneIntervalInMs:J
       5: ldiv
       6: aload_0
       7: getfield      #14                 // Field paneCount:I
      10: i2l
      11: lrem
      12: l2i
      13: ireturn

  protected long calculatePaneStart(long);
    Code:
       0: lload_1
       1: lload_1
       2: aload_0
       3: getfield      #16                 // Field paneIntervalInMs:J
       6: lrem
       7: lsub
       8: lreturn

  public boolean isPaneDeprecated(org.apache.dubbo.metrics.aggregate.Pane<T>);
    Code:
       0: aload_0
       1: invokestatic  #20                 // Method java/lang/System.currentTimeMillis:()J
       4: aload_1
       5: invokevirtual #36                 // Method isPaneDeprecated:(JLorg/apache/dubbo/metrics/aggregate/Pane;)Z
       8: ireturn

  public boolean isPaneDeprecated(long, org.apache.dubbo.metrics.aggregate.Pane<T>);
    Code:
       0: lload_1
       1: aload_3
       2: invokevirtual #30                 // Method org/apache/dubbo/metrics/aggregate/Pane.getStartInMs:()J
       5: lsub
       6: aload_0
       7: getfield      #15                 // Field intervalInMs:J
      10: lcmp
      11: ifle          18
      14: iconst_1
      15: goto          19
      18: iconst_0
      19: ireturn

  public java.util.List<org.apache.dubbo.metrics.aggregate.Pane<T>> list();
    Code:
       0: aload_0
       1: invokestatic  #20                 // Method java/lang/System.currentTimeMillis:()J
       4: invokevirtual #37                 // Method list:(J)Ljava/util/List;
       7: areturn

  public java.util.List<org.apache.dubbo.metrics.aggregate.Pane<T>> list(long);
    Code:
       0: lload_1
       1: lconst_0
       2: lcmp
       3: ifge          14
       6: new           #38                 // class java/util/ArrayList
       9: dup
      10: invokespecial #39                 // Method java/util/ArrayList."<init>":()V
      13: areturn
      14: new           #38                 // class java/util/ArrayList
      17: dup
      18: aload_0
      19: getfield      #14                 // Field paneCount:I
      22: invokespecial #40                 // Method java/util/ArrayList."<init>":(I)V
      25: astore_3
      26: iconst_0
      27: istore        4
      29: iload         4
      31: aload_0
      32: getfield      #14                 // Field paneCount:I
      35: if_icmpge     85
      38: aload_0
      39: getfield      #19                 // Field referenceArray:Ljava/util/concurrent/atomic/AtomicReferenceArray;
      42: iload         4
      44: invokevirtual #24                 // Method java/util/concurrent/atomic/AtomicReferenceArray.get:(I)Ljava/lang/Object;
      47: checkcast     #25                 // class org/apache/dubbo/metrics/aggregate/Pane
      50: astore        5
      52: aload         5
      54: ifnull        79
      57: aload_0
      58: lload_1
      59: aload         5
      61: invokevirtual #36                 // Method isPaneDeprecated:(JLorg/apache/dubbo/metrics/aggregate/Pane;)Z
      64: ifeq          70
      67: goto          79
      70: aload_3
      71: aload         5
      73: invokeinterface #41,  2           // InterfaceMethod java/util/List.add:(Ljava/lang/Object;)Z
      78: pop
      79: iinc          4, 1
      82: goto          29
      85: aload_3
      86: areturn

  public java.util.List<T> values();
    Code:
       0: aload_0
       1: invokestatic  #20                 // Method java/lang/System.currentTimeMillis:()J
       4: invokevirtual #42                 // Method values:(J)Ljava/util/List;
       7: areturn

  public java.util.List<T> values(long);
    Code:
       0: lload_1
       1: lconst_0
       2: lcmp
       3: ifge          14
       6: new           #38                 // class java/util/ArrayList
       9: dup
      10: invokespecial #39                 // Method java/util/ArrayList."<init>":()V
      13: areturn
      14: new           #38                 // class java/util/ArrayList
      17: dup
      18: aload_0
      19: getfield      #14                 // Field paneCount:I
      22: invokespecial #40                 // Method java/util/ArrayList."<init>":(I)V
      25: astore_3
      26: iconst_0
      27: istore        4
      29: iload         4
      31: aload_0
      32: getfield      #14                 // Field paneCount:I
      35: if_icmpge     88
      38: aload_0
      39: getfield      #19                 // Field referenceArray:Ljava/util/concurrent/atomic/AtomicReferenceArray;
      42: iload         4
      44: invokevirtual #24                 // Method java/util/concurrent/atomic/AtomicReferenceArray.get:(I)Ljava/lang/Object;
      47: checkcast     #25                 // class org/apache/dubbo/metrics/aggregate/Pane
      50: astore        5
      52: aload         5
      54: ifnull        82
      57: aload_0
      58: lload_1
      59: aload         5
      61: invokevirtual #36                 // Method isPaneDeprecated:(JLorg/apache/dubbo/metrics/aggregate/Pane;)Z
      64: ifeq          70
      67: goto          82
      70: aload_3
      71: aload         5
      73: invokevirtual #35                 // Method org/apache/dubbo/metrics/aggregate/Pane.getValue:()Ljava/lang/Object;
      76: invokeinterface #41,  2           // InterfaceMethod java/util/List.add:(Ljava/lang/Object;)Z
      81: pop
      82: iinc          4, 1
      85: goto          29
      88: aload_3
      89: areturn

  public long getIntervalInMs();
    Code:
       0: aload_0
       1: getfield      #15                 // Field intervalInMs:J
       4: lreturn

  public long getPaneIntervalInMs();
    Code:
       0: aload_0
       1: getfield      #16                 // Field paneIntervalInMs:J
       4: lreturn
}
