Compiled from "TimeWindowQuantile.java"
class org.apache.dubbo.metrics.aggregate.TimeWindowQuantile$DigestSlidingWindow extends org.apache.dubbo.metrics.aggregate.SlidingWindow<com.tdunning.math.stats.TDigest> {
  private final double compression;

  public org.apache.dubbo.metrics.aggregate.TimeWindowQuantile$DigestSlidingWindow(double, int, long);
    Code:
       0: aload_0
       1: iload_3
       2: lload         4
       4: invokespecial #1                  // Method org/apache/dubbo/metrics/aggregate/SlidingWindow."<init>":(IJ)V
       7: aload_0
       8: dload_1
       9: putfield      #2                  // Field compression:D
      12: return

  public com.tdunning.math.stats.TDigest newEmptyValue(long);
    Code:
       0: new           #3                  // class org/apache/dubbo/metrics/aggregate/DubboMergingDigest
       3: dup
       4: aload_0
       5: getfield      #2                  // Field compression:D
       8: invokespecial #4                  // Method org/apache/dubbo/metrics/aggregate/DubboMergingDigest."<init>":(D)V
      11: areturn

  protected org.apache.dubbo.metrics.aggregate.Pane<com.tdunning.math.stats.TDigest> resetPaneTo(org.apache.dubbo.metrics.aggregate.Pane<com.tdunning.math.stats.TDigest>, long);
    Code:
       0: aload_1
       1: lload_2
       2: invokevirtual #5                  // Method org/apache/dubbo/metrics/aggregate/Pane.setStartInMs:(J)V
       5: aload_1
       6: new           #3                  // class org/apache/dubbo/metrics/aggregate/DubboMergingDigest
       9: dup
      10: aload_0
      11: getfield      #2                  // Field compression:D
      14: invokespecial #4                  // Method org/apache/dubbo/metrics/aggregate/DubboMergingDigest."<init>":(D)V
      17: invokevirtual #6                  // Method org/apache/dubbo/metrics/aggregate/Pane.setValue:(Ljava/lang/Object;)V
      20: aload_1
      21: areturn

  public java.lang.Object newEmptyValue(long);
    Code:
       0: aload_0
       1: lload_1
       2: invokevirtual #7                  // Method newEmptyValue:(J)Lcom/tdunning/math/stats/TDigest;
       5: areturn
}
