Compiled from "TimeWindowQuantile.java"
public class org.apache.dubbo.metrics.aggregate.TimeWindowQuantile {
  private final double compression;

  private final org.apache.dubbo.metrics.aggregate.TimeWindowQuantile$DigestSlidingWindow slidingWindow;

  public org.apache.dubbo.metrics.aggregate.TimeWindowQuantile(double, int, int);
    Code:
       0: aload_0
       1: invokespecial #1                  // Method java/lang/Object."<init>":()V
       4: aload_0
       5: dload_1
       6: putfield      #2                  // Field compression:D
       9: aload_0
      10: new           #3                  // class org/apache/dubbo/metrics/aggregate/TimeWindowQuantile$DigestSlidingWindow
      13: dup
      14: dload_1
      15: iload_3
      16: getstatic     #4                  // Field java/util/concurrent/TimeUnit.SECONDS:Ljava/util/concurrent/TimeUnit;
      19: iload         4
      21: i2l
      22: invokevirtual #5                  // Method java/util/concurrent/TimeUnit.toMillis:(J)J
      25: invokespecial #6                  // Method org/apache/dubbo/metrics/aggregate/TimeWindowQuantile$DigestSlidingWindow."<init>":(DIJ)V
      28: putfield      #7                  // Field slidingWindow:Lorg/apache/dubbo/metrics/aggregate/TimeWindowQuantile$DigestSlidingWindow;
      31: return

  public double quantile(double);
    Code:
       0: new           #8                  // class org/apache/dubbo/metrics/aggregate/DubboMergingDigest
       3: dup
       4: aload_0
       5: getfield      #2                  // Field compression:D
       8: invokespecial #9                  // Method org/apache/dubbo/metrics/aggregate/DubboMergingDigest."<init>":(D)V
      11: astore_3
      12: aload_0
      13: getfield      #7                  // Field slidingWindow:Lorg/apache/dubbo/metrics/aggregate/TimeWindowQuantile$DigestSlidingWindow;
      16: invokevirtual #10                 // Method org/apache/dubbo/metrics/aggregate/TimeWindowQuantile$DigestSlidingWindow.values:()Ljava/util/List;
      19: astore        4
      21: aload         4
      23: invokeinterface #11,  1           // InterfaceMethod java/util/List.iterator:()Ljava/util/Iterator;
      28: astore        5
      30: aload         5
      32: invokeinterface #12,  1           // InterfaceMethod java/util/Iterator.hasNext:()Z
      37: ifeq          61
      40: aload         5
      42: invokeinterface #13,  1           // InterfaceMethod java/util/Iterator.next:()Ljava/lang/Object;
      47: checkcast     #14                 // class com/tdunning/math/stats/TDigest
      50: astore        6
      52: aload_3
      53: aload         6
      55: invokevirtual #15                 // Method com/tdunning/math/stats/TDigest.add:(Lcom/tdunning/math/stats/TDigest;)V
      58: goto          30
      61: aload_3
      62: dload_1
      63: invokevirtual #16                 // Method com/tdunning/math/stats/TDigest.quantile:(D)D
      66: dreturn

  public void add(double);
    Code:
       0: aload_0
       1: getfield      #7                  // Field slidingWindow:Lorg/apache/dubbo/metrics/aggregate/TimeWindowQuantile$DigestSlidingWindow;
       4: invokevirtual #17                 // Method org/apache/dubbo/metrics/aggregate/TimeWindowQuantile$DigestSlidingWindow.currentPane:()Lorg/apache/dubbo/metrics/aggregate/Pane;
       7: invokevirtual #18                 // Method org/apache/dubbo/metrics/aggregate/Pane.getValue:()Ljava/lang/Object;
      10: checkcast     #14                 // class com/tdunning/math/stats/TDigest
      13: dload_1
      14: invokevirtual #19                 // Method com/tdunning/math/stats/TDigest.add:(D)V
      17: return
}
