Compiled from "TimeWindowCounter.java"
class org.apache.dubbo.metrics.aggregate.TimeWindowCounter$LongAdderSlidingWindow extends org.apache.dubbo.metrics.aggregate.SlidingWindow<java.util.concurrent.atomic.LongAdder> {
  public org.apache.dubbo.metrics.aggregate.TimeWindowCounter$LongAdderSlidingWindow(int, long);
    Code:
       0: aload_0
       1: iload_1
       2: lload_2
       3: invokespecial #1                  // Method org/apache/dubbo/metrics/aggregate/SlidingWindow."<init>":(IJ)V
       6: return

  public java.util.concurrent.atomic.LongAdder newEmptyValue(long);
    Code:
       0: new           #2                  // class java/util/concurrent/atomic/LongAdder
       3: dup
       4: invokespecial #3                  // Method java/util/concurrent/atomic/LongAdder."<init>":()V
       7: areturn

  protected org.apache.dubbo.metrics.aggregate.Pane<java.util.concurrent.atomic.LongAdder> resetPaneTo(org.apache.dubbo.metrics.aggregate.Pane<java.util.concurrent.atomic.LongAdder>, long);
    Code:
       0: aload_1
       1: lload_2
       2: invokevirtual #4                  // Method org/apache/dubbo/metrics/aggregate/Pane.setStartInMs:(J)V
       5: aload_1
       6: invokevirtual #5                  // Method org/apache/dubbo/metrics/aggregate/Pane.getValue:()Ljava/lang/Object;
       9: checkcast     #2                  // class java/util/concurrent/atomic/LongAdder
      12: invokevirtual #6                  // Method java/util/concurrent/atomic/LongAdder.reset:()V
      15: aload_1
      16: areturn

  public java.lang.Object newEmptyValue(long);
    Code:
       0: aload_0
       1: lload_1
       2: invokevirtual #7                  // Method newEmptyValue:(J)Ljava/util/concurrent/atomic/LongAdder;
       5: areturn
}
