Compiled from "AbstractMaybeWithUpstream.java"
abstract class io.reactivex.rxjava3.internal.operators.maybe.AbstractMaybeWithUpstream<T, R> extends io.reactivex.rxjava3.core.Maybe<R> implements io.reactivex.rxjava3.internal.fuseable.HasUpstreamMaybeSource<T> {
  protected final io.reactivex.rxjava3.core.MaybeSource<T> source;

  io.reactivex.rxjava3.internal.operators.maybe.AbstractMaybeWithUpstream(io.reactivex.rxjava3.core.MaybeSource<T>);
    Code:
       0: aload_0
       1: invokespecial #1                  // Method io/reactivex/rxjava3/core/Maybe."<init>":()V
       4: aload_0
       5: aload_1
       6: putfield      #2                  // Field source:Lio/reactivex/rxjava3/core/MaybeSource;
       9: return

  public final io.reactivex.rxjava3.core.MaybeSource<T> source();
    Code:
       0: aload_0
       1: getfield      #2                  // Field source:Lio/reactivex/rxjava3/core/MaybeSource;
       4: areturn
}
