Compiled from "MaybeDelayOtherPublisher.java"
public final class io.reactivex.rxjava3.internal.operators.maybe.MaybeDelayOtherPublisher<T, U> extends io.reactivex.rxjava3.internal.operators.maybe.AbstractMaybeWithUpstream<T, T> {
  final org.reactivestreams.Publisher<U> other;

  public io.reactivex.rxjava3.internal.operators.maybe.MaybeDelayOtherPublisher(io.reactivex.rxjava3.core.MaybeSource<T>, org.reactivestreams.Publisher<U>);
    Code:
       0: aload_0
       1: aload_1
       2: invokespecial #1                  // Method io/reactivex/rxjava3/internal/operators/maybe/AbstractMaybeWithUpstream."<init>":(Lio/reactivex/rxjava3/core/MaybeSource;)V
       5: aload_0
       6: aload_2
       7: putfield      #2                  // Field other:Lorg/reactivestreams/Publisher;
      10: return

  protected void subscribeActual(io.reactivex.rxjava3.core.MaybeObserver<? super T>);
    Code:
       0: aload_0
       1: getfield      #3                  // Field source:Lio/reactivex/rxjava3/core/MaybeSource;
       4: new           #4                  // class io/reactivex/rxjava3/internal/operators/maybe/MaybeDelayOtherPublisher$DelayMaybeObserver
       7: dup
       8: aload_1
       9: aload_0
      10: getfield      #2                  // Field other:Lorg/reactivestreams/Publisher;
      13: invokespecial #5                  // Method io/reactivex/rxjava3/internal/operators/maybe/MaybeDelayOtherPublisher$DelayMaybeObserver."<init>":(Lio/reactivex/rxjava3/core/MaybeObserver;Lorg/reactivestreams/Publisher;)V
      16: invokeinterface #6,  2            // InterfaceMethod io/reactivex/rxjava3/core/MaybeSource.subscribe:(Lio/reactivex/rxjava3/core/MaybeObserver;)V
      21: return
}
