Compiled from "MaybeDelayOtherPublisher.java"
final class io.reactivex.rxjava3.internal.operators.maybe.MaybeDelayOtherPublisher$OtherSubscriber<T> extends java.util.concurrent.atomic.AtomicReference<org.reactivestreams.Subscription> implements io.reactivex.rxjava3.core.FlowableSubscriber<java.lang.Object> {
  private static final long serialVersionUID;

  final io.reactivex.rxjava3.core.MaybeObserver<? super T> downstream;

  T value;

  java.lang.Throwable error;

  io.reactivex.rxjava3.internal.operators.maybe.MaybeDelayOtherPublisher$OtherSubscriber(io.reactivex.rxjava3.core.MaybeObserver<? super T>);
    Code:
       0: aload_0
       1: invokespecial #1                  // Method java/util/concurrent/atomic/AtomicReference."<init>":()V
       4: aload_0
       5: aload_1
       6: putfield      #2                  // Field downstream:Lio/reactivex/rxjava3/core/MaybeObserver;
       9: return

  public void onSubscribe(org.reactivestreams.Subscription);
    Code:
       0: aload_0
       1: aload_1
       2: ldc2_w        #4                  // long 9223372036854775807l
       5: invokestatic  #6                  // Method io/reactivex/rxjava3/internal/subscriptions/SubscriptionHelper.setOnce:(Ljava/util/concurrent/atomic/AtomicReference;Lorg/reactivestreams/Subscription;J)Z
       8: pop
       9: return

  public void onNext(java.lang.Object);
    Code:
       0: aload_0
       1: invokevirtual #7                  // Method get:()Ljava/lang/Object;
       4: checkcast     #8                  // class org/reactivestreams/Subscription
       7: astore_2
       8: aload_2
       9: getstatic     #9                  // Field io/reactivex/rxjava3/internal/subscriptions/SubscriptionHelper.CANCELLED:Lio/reactivex/rxjava3/internal/subscriptions/SubscriptionHelper;
      12: if_acmpeq     32
      15: aload_0
      16: getstatic     #9                  // Field io/reactivex/rxjava3/internal/subscriptions/SubscriptionHelper.CANCELLED:Lio/reactivex/rxjava3/internal/subscriptions/SubscriptionHelper;
      19: invokevirtual #10                 // Method lazySet:(Ljava/lang/Object;)V
      22: aload_2
      23: invokeinterface #11,  1           // InterfaceMethod org/reactivestreams/Subscription.cancel:()V
      28: aload_0
      29: invokevirtual #12                 // Method onComplete:()V
      32: return

  public void onError(java.lang.Throwable);
    Code:
       0: aload_0
       1: getfield      #13                 // Field error:Ljava/lang/Throwable;
       4: astore_2
       5: aload_2
       6: ifnonnull     22
       9: aload_0
      10: getfield      #2                  // Field downstream:Lio/reactivex/rxjava3/core/MaybeObserver;
      13: aload_1
      14: invokeinterface #14,  2           // InterfaceMethod io/reactivex/rxjava3/core/MaybeObserver.onError:(Ljava/lang/Throwable;)V
      19: goto          50
      22: aload_0
      23: getfield      #2                  // Field downstream:Lio/reactivex/rxjava3/core/MaybeObserver;
      26: new           #15                 // class io/reactivex/rxjava3/exceptions/CompositeException
      29: dup
      30: iconst_2
      31: anewarray     #16                 // class java/lang/Throwable
      34: dup
      35: iconst_0
      36: aload_2
      37: aastore
      38: dup
      39: iconst_1
      40: aload_1
      41: aastore
      42: invokespecial #17                 // Method io/reactivex/rxjava3/exceptions/CompositeException."<init>":([Ljava/lang/Throwable;)V
      45: invokeinterface #14,  2           // InterfaceMethod io/reactivex/rxjava3/core/MaybeObserver.onError:(Ljava/lang/Throwable;)V
      50: return

  public void onComplete();
    Code:
       0: aload_0
       1: getfield      #13                 // Field error:Ljava/lang/Throwable;
       4: astore_1
       5: aload_1
       6: ifnull        22
       9: aload_0
      10: getfield      #2                  // Field downstream:Lio/reactivex/rxjava3/core/MaybeObserver;
      13: aload_1
      14: invokeinterface #14,  2           // InterfaceMethod io/reactivex/rxjava3/core/MaybeObserver.onError:(Ljava/lang/Throwable;)V
      19: goto          53
      22: aload_0
      23: getfield      #18                 // Field value:Ljava/lang/Object;
      26: astore_2
      27: aload_2
      28: ifnull        44
      31: aload_0
      32: getfield      #2                  // Field downstream:Lio/reactivex/rxjava3/core/MaybeObserver;
      35: aload_2
      36: invokeinterface #19,  2           // InterfaceMethod io/reactivex/rxjava3/core/MaybeObserver.onSuccess:(Ljava/lang/Object;)V
      41: goto          53
      44: aload_0
      45: getfield      #2                  // Field downstream:Lio/reactivex/rxjava3/core/MaybeObserver;
      48: invokeinterface #20,  1           // InterfaceMethod io/reactivex/rxjava3/core/MaybeObserver.onComplete:()V
      53: return
}
