Compiled from "MaybeDoOnEvent.java"
public final class io.reactivex.rxjava3.internal.operators.maybe.MaybeDoOnEvent<T> extends io.reactivex.rxjava3.internal.operators.maybe.AbstractMaybeWithUpstream<T, T> {
  final io.reactivex.rxjava3.functions.BiConsumer<? super T, ? super java.lang.Throwable> onEvent;

  public io.reactivex.rxjava3.internal.operators.maybe.MaybeDoOnEvent(io.reactivex.rxjava3.core.MaybeSource<T>, io.reactivex.rxjava3.functions.BiConsumer<? super T, ? super java.lang.Throwable>);
    Code:
       0: aload_0
       1: aload_1
       2: invokespecial #1                  // Method io/reactivex/rxjava3/internal/operators/maybe/AbstractMaybeWithUpstream."<init>":(Lio/reactivex/rxjava3/core/MaybeSource;)V
       5: aload_0
       6: aload_2
       7: putfield      #2                  // Field onEvent:Lio/reactivex/rxjava3/functions/BiConsumer;
      10: return

  protected void subscribeActual(io.reactivex.rxjava3.core.MaybeObserver<? super T>);
    Code:
       0: aload_0
       1: getfield      #3                  // Field source:Lio/reactivex/rxjava3/core/MaybeSource;
       4: new           #4                  // class io/reactivex/rxjava3/internal/operators/maybe/MaybeDoOnEvent$DoOnEventMaybeObserver
       7: dup
       8: aload_1
       9: aload_0
      10: getfield      #2                  // Field onEvent:Lio/reactivex/rxjava3/functions/BiConsumer;
      13: invokespecial #5                  // Method io/reactivex/rxjava3/internal/operators/maybe/MaybeDoOnEvent$DoOnEventMaybeObserver."<init>":(Lio/reactivex/rxjava3/core/MaybeObserver;Lio/reactivex/rxjava3/functions/BiConsumer;)V
      16: invokeinterface #6,  2            // InterfaceMethod io/reactivex/rxjava3/core/MaybeSource.subscribe:(Lio/reactivex/rxjava3/core/MaybeObserver;)V
      21: return
}
