Compiled from "MaybeDoOnTerminate.java"
final class io.reactivex.rxjava3.internal.operators.maybe.MaybeDoOnTerminate$DoOnTerminate implements io.reactivex.rxjava3.core.MaybeObserver<T> {
  final io.reactivex.rxjava3.core.MaybeObserver<? super T> downstream;

  final io.reactivex.rxjava3.internal.operators.maybe.MaybeDoOnTerminate this$0;

  io.reactivex.rxjava3.internal.operators.maybe.MaybeDoOnTerminate$DoOnTerminate(io.reactivex.rxjava3.core.MaybeObserver<? super T>);
    Code:
       0: aload_0
       1: aload_1
       2: putfield      #1                  // Field this$0:Lio/reactivex/rxjava3/internal/operators/maybe/MaybeDoOnTerminate;
       5: aload_0
       6: invokespecial #2                  // Method java/lang/Object."<init>":()V
       9: aload_0
      10: aload_2
      11: putfield      #3                  // Field downstream:Lio/reactivex/rxjava3/core/MaybeObserver;
      14: return

  public void onSubscribe(io.reactivex.rxjava3.disposables.Disposable);
    Code:
       0: aload_0
       1: getfield      #3                  // Field downstream:Lio/reactivex/rxjava3/core/MaybeObserver;
       4: aload_1
       5: invokeinterface #4,  2            // InterfaceMethod io/reactivex/rxjava3/core/MaybeObserver.onSubscribe:(Lio/reactivex/rxjava3/disposables/Disposable;)V
      10: return

  public void onSuccess(T);
    Code:
       0: aload_0
       1: getfield      #1                  // Field this$0:Lio/reactivex/rxjava3/internal/operators/maybe/MaybeDoOnTerminate;
       4: getfield      #5                  // Field io/reactivex/rxjava3/internal/operators/maybe/MaybeDoOnTerminate.onTerminate:Lio/reactivex/rxjava3/functions/Action;
       7: invokeinterface #6,  1            // InterfaceMethod io/reactivex/rxjava3/functions/Action.run:()V
      12: goto          31
      15: astore_2
      16: aload_2
      17: invokestatic  #8                  // Method io/reactivex/rxjava3/exceptions/Exceptions.throwIfFatal:(Ljava/lang/Throwable;)V
      20: aload_0
      21: getfield      #3                  // Field downstream:Lio/reactivex/rxjava3/core/MaybeObserver;
      24: aload_2
      25: invokeinterface #9,  2            // InterfaceMethod io/reactivex/rxjava3/core/MaybeObserver.onError:(Ljava/lang/Throwable;)V
      30: return
      31: aload_0
      32: getfield      #3                  // Field downstream:Lio/reactivex/rxjava3/core/MaybeObserver;
      35: aload_1
      36: invokeinterface #10,  2           // InterfaceMethod io/reactivex/rxjava3/core/MaybeObserver.onSuccess:(Ljava/lang/Object;)V
      41: return
    Exception table:
       from    to  target type
           0    12    15   Class java/lang/Throwable

  public void onError(java.lang.Throwable);
    Code:
       0: aload_0
       1: getfield      #1                  // Field this$0:Lio/reactivex/rxjava3/internal/operators/maybe/MaybeDoOnTerminate;
       4: getfield      #5                  // Field io/reactivex/rxjava3/internal/operators/maybe/MaybeDoOnTerminate.onTerminate:Lio/reactivex/rxjava3/functions/Action;
       7: invokeinterface #6,  1            // InterfaceMethod io/reactivex/rxjava3/functions/Action.run:()V
      12: goto          40
      15: astore_2
      16: aload_2
      17: invokestatic  #8                  // Method io/reactivex/rxjava3/exceptions/Exceptions.throwIfFatal:(Ljava/lang/Throwable;)V
      20: new           #11                 // class io/reactivex/rxjava3/exceptions/CompositeException
      23: dup
      24: iconst_2
      25: anewarray     #12                 // class java/lang/Throwable
      28: dup
      29: iconst_0
      30: aload_1
      31: aastore
      32: dup
      33: iconst_1
      34: aload_2
      35: aastore
      36: invokespecial #13                 // Method io/reactivex/rxjava3/exceptions/CompositeException."<init>":([Ljava/lang/Throwable;)V
      39: astore_1
      40: aload_0
      41: getfield      #3                  // Field downstream:Lio/reactivex/rxjava3/core/MaybeObserver;
      44: aload_1
      45: invokeinterface #9,  2            // InterfaceMethod io/reactivex/rxjava3/core/MaybeObserver.onError:(Ljava/lang/Throwable;)V
      50: return
    Exception table:
       from    to  target type
           0    12    15   Class java/lang/Throwable

  public void onComplete();
    Code:
       0: aload_0
       1: getfield      #1                  // Field this$0:Lio/reactivex/rxjava3/internal/operators/maybe/MaybeDoOnTerminate;
       4: getfield      #5                  // Field io/reactivex/rxjava3/internal/operators/maybe/MaybeDoOnTerminate.onTerminate:Lio/reactivex/rxjava3/functions/Action;
       7: invokeinterface #6,  1            // InterfaceMethod io/reactivex/rxjava3/functions/Action.run:()V
      12: goto          31
      15: astore_1
      16: aload_1
      17: invokestatic  #8                  // Method io/reactivex/rxjava3/exceptions/Exceptions.throwIfFatal:(Ljava/lang/Throwable;)V
      20: aload_0
      21: getfield      #3                  // Field downstream:Lio/reactivex/rxjava3/core/MaybeObserver;
      24: aload_1
      25: invokeinterface #9,  2            // InterfaceMethod io/reactivex/rxjava3/core/MaybeObserver.onError:(Ljava/lang/Throwable;)V
      30: return
      31: aload_0
      32: getfield      #3                  // Field downstream:Lio/reactivex/rxjava3/core/MaybeObserver;
      35: invokeinterface #14,  1           // InterfaceMethod io/reactivex/rxjava3/core/MaybeObserver.onComplete:()V
      40: return
    Exception table:
       from    to  target type
           0    12    15   Class java/lang/Throwable
}
