Compiled from "MaybeEmpty.java"
public final class io.reactivex.rxjava3.internal.operators.maybe.MaybeEmpty extends io.reactivex.rxjava3.core.Maybe<java.lang.Object> implements io.reactivex.rxjava3.operators.ScalarSupplier<java.lang.Object> {
  public static final io.reactivex.rxjava3.internal.operators.maybe.MaybeEmpty INSTANCE;

  public io.reactivex.rxjava3.internal.operators.maybe.MaybeEmpty();
    Code:
       0: aload_0
       1: invokespecial #1                  // Method io/reactivex/rxjava3/core/Maybe."<init>":()V
       4: return

  protected void subscribeActual(io.reactivex.rxjava3.core.MaybeObserver<? super java.lang.Object>);
    Code:
       0: aload_1
       1: invokestatic  #2                  // Method io/reactivex/rxjava3/internal/disposables/EmptyDisposable.complete:(Lio/reactivex/rxjava3/core/MaybeObserver;)V
       4: return

  public java.lang.Object get();
    Code:
       0: aconst_null
       1: areturn

  static {};
    Code:
       0: new           #3                  // class io/reactivex/rxjava3/internal/operators/maybe/MaybeEmpty
       3: dup
       4: invokespecial #4                  // Method "<init>":()V
       7: putstatic     #5                  // Field INSTANCE:Lio/reactivex/rxjava3/internal/operators/maybe/MaybeEmpty;
      10: return
}
