Compiled from "MaybeTimeoutMaybe.java"
public final class io.reactivex.rxjava3.internal.operators.maybe.MaybeTimeoutMaybe<T, U> extends io.reactivex.rxjava3.internal.operators.maybe.AbstractMaybeWithUpstream<T, T> {
  final io.reactivex.rxjava3.core.MaybeSource<U> other;

  final io.reactivex.rxjava3.core.MaybeSource<? extends T> fallback;

  public io.reactivex.rxjava3.internal.operators.maybe.MaybeTimeoutMaybe(io.reactivex.rxjava3.core.MaybeSource<T>, io.reactivex.rxjava3.core.MaybeSource<U>, io.reactivex.rxjava3.core.MaybeSource<? extends T>);
    Code:
       0: aload_0
       1: aload_1
       2: invokespecial #1                  // Method io/reactivex/rxjava3/internal/operators/maybe/AbstractMaybeWithUpstream."<init>":(Lio/reactivex/rxjava3/core/MaybeSource;)V
       5: aload_0
       6: aload_2
       7: putfield      #2                  // Field other:Lio/reactivex/rxjava3/core/MaybeSource;
      10: aload_0
      11: aload_3
      12: putfield      #3                  // Field fallback:Lio/reactivex/rxjava3/core/MaybeSource;
      15: return

  protected void subscribeActual(io.reactivex.rxjava3.core.MaybeObserver<? super T>);
    Code:
       0: new           #4                  // class io/reactivex/rxjava3/internal/operators/maybe/MaybeTimeoutMaybe$TimeoutMainMaybeObserver
       3: dup
       4: aload_1
       5: aload_0
       6: getfield      #3                  // Field fallback:Lio/reactivex/rxjava3/core/MaybeSource;
       9: invokespecial #5                  // Method io/reactivex/rxjava3/internal/operators/maybe/MaybeTimeoutMaybe$TimeoutMainMaybeObserver."<init>":(Lio/reactivex/rxjava3/core/MaybeObserver;Lio/reactivex/rxjava3/core/MaybeSource;)V
      12: astore_2
      13: aload_1
      14: aload_2
      15: invokeinterface #6,  2            // InterfaceMethod io/reactivex/rxjava3/core/MaybeObserver.onSubscribe:(Lio/reactivex/rxjava3/disposables/Disposable;)V
      20: aload_0
      21: getfield      #2                  // Field other:Lio/reactivex/rxjava3/core/MaybeSource;
      24: aload_2
      25: getfield      #7                  // Field io/reactivex/rxjava3/internal/operators/maybe/MaybeTimeoutMaybe$TimeoutMainMaybeObserver.other:Lio/reactivex/rxjava3/internal/operators/maybe/MaybeTimeoutMaybe$TimeoutOtherMaybeObserver;
      28: invokeinterface #8,  2            // InterfaceMethod io/reactivex/rxjava3/core/MaybeSource.subscribe:(Lio/reactivex/rxjava3/core/MaybeObserver;)V
      33: aload_0
      34: getfield      #9                  // Field source:Lio/reactivex/rxjava3/core/MaybeSource;
      37: aload_2
      38: invokeinterface #8,  2            // InterfaceMethod io/reactivex/rxjava3/core/MaybeSource.subscribe:(Lio/reactivex/rxjava3/core/MaybeObserver;)V
      43: return
}
