Compiled from "MaybeFromSingle.java"
public final class io.reactivex.rxjava3.internal.operators.maybe.MaybeFromSingle<T> extends io.reactivex.rxjava3.core.Maybe<T> implements io.reactivex.rxjava3.internal.fuseable.HasUpstreamSingleSource<T> {
  final io.reactivex.rxjava3.core.SingleSource<T> source;

  public io.reactivex.rxjava3.internal.operators.maybe.MaybeFromSingle(io.reactivex.rxjava3.core.SingleSource<T>);
    Code:
       0: aload_0
       1: invokespecial #1                  // Method io/reactivex/rxjava3/core/Maybe."<init>":()V
       4: aload_0
       5: aload_1
       6: putfield      #2                  // Field source:Lio/reactivex/rxjava3/core/SingleSource;
       9: return

  public io.reactivex.rxjava3.core.SingleSource<T> source();
    Code:
       0: aload_0
       1: getfield      #2                  // Field source:Lio/reactivex/rxjava3/core/SingleSource;
       4: areturn

  protected void subscribeActual(io.reactivex.rxjava3.core.MaybeObserver<? super T>);
    Code:
       0: aload_0
       1: getfield      #2                  // Field source:Lio/reactivex/rxjava3/core/SingleSource;
       4: new           #3                  // class io/reactivex/rxjava3/internal/operators/maybe/MaybeFromSingle$FromSingleObserver
       7: dup
       8: aload_1
       9: invokespecial #4                  // Method io/reactivex/rxjava3/internal/operators/maybe/MaybeFromSingle$FromSingleObserver."<init>":(Lio/reactivex/rxjava3/core/MaybeObserver;)V
      12: invokeinterface #5,  2            // InterfaceMethod io/reactivex/rxjava3/core/SingleSource.subscribe:(Lio/reactivex/rxjava3/core/SingleObserver;)V
      17: return
}
