Compiled from "MaybeAmb.java"
final class io.reactivex.rxjava3.internal.operators.maybe.MaybeAmb$AmbMaybeObserver<T> implements io.reactivex.rxjava3.core.MaybeObserver<T> {
  final io.reactivex.rxjava3.core.MaybeObserver<? super T> downstream;

  final java.util.concurrent.atomic.AtomicBoolean winner;

  final io.reactivex.rxjava3.disposables.CompositeDisposable set;

  io.reactivex.rxjava3.disposables.Disposable upstream;

  io.reactivex.rxjava3.internal.operators.maybe.MaybeAmb$AmbMaybeObserver(io.reactivex.rxjava3.core.MaybeObserver<? super T>, io.reactivex.rxjava3.disposables.CompositeDisposable, java.util.concurrent.atomic.AtomicBoolean);
    Code:
       0: aload_0
       1: invokespecial #1                  // Method java/lang/Object."<init>":()V
       4: aload_0
       5: aload_1
       6: putfield      #2                  // Field downstream:Lio/reactivex/rxjava3/core/MaybeObserver;
       9: aload_0
      10: aload_2
      11: putfield      #3                  // Field set:Lio/reactivex/rxjava3/disposables/CompositeDisposable;
      14: aload_0
      15: aload_3
      16: putfield      #4                  // Field winner:Ljava/util/concurrent/atomic/AtomicBoolean;
      19: return

  public void onSubscribe(io.reactivex.rxjava3.disposables.Disposable);
    Code:
       0: aload_0
       1: aload_1
       2: putfield      #5                  // Field upstream:Lio/reactivex/rxjava3/disposables/Disposable;
       5: aload_0
       6: getfield      #3                  // Field set:Lio/reactivex/rxjava3/disposables/CompositeDisposable;
       9: aload_1
      10: invokevirtual #6                  // Method io/reactivex/rxjava3/disposables/CompositeDisposable.add:(Lio/reactivex/rxjava3/disposables/Disposable;)Z
      13: pop
      14: return

  public void onSuccess(T);
    Code:
       0: aload_0
       1: getfield      #4                  // Field winner:Ljava/util/concurrent/atomic/AtomicBoolean;
       4: iconst_0
       5: iconst_1
       6: invokevirtual #7                  // Method java/util/concurrent/atomic/AtomicBoolean.compareAndSet:(ZZ)Z
       9: ifeq          41
      12: aload_0
      13: getfield      #3                  // Field set:Lio/reactivex/rxjava3/disposables/CompositeDisposable;
      16: aload_0
      17: getfield      #5                  // Field upstream:Lio/reactivex/rxjava3/disposables/Disposable;
      20: invokevirtual #8                  // Method io/reactivex/rxjava3/disposables/CompositeDisposable.delete:(Lio/reactivex/rxjava3/disposables/Disposable;)Z
      23: pop
      24: aload_0
      25: getfield      #3                  // Field set:Lio/reactivex/rxjava3/disposables/CompositeDisposable;
      28: invokevirtual #9                  // Method io/reactivex/rxjava3/disposables/CompositeDisposable.dispose:()V
      31: aload_0
      32: getfield      #2                  // Field downstream:Lio/reactivex/rxjava3/core/MaybeObserver;
      35: aload_1
      36: invokeinterface #10,  2           // InterfaceMethod io/reactivex/rxjava3/core/MaybeObserver.onSuccess:(Ljava/lang/Object;)V
      41: return

  public void onError(java.lang.Throwable);
    Code:
       0: aload_0
       1: getfield      #4                  // Field winner:Ljava/util/concurrent/atomic/AtomicBoolean;
       4: iconst_0
       5: iconst_1
       6: invokevirtual #7                  // Method java/util/concurrent/atomic/AtomicBoolean.compareAndSet:(ZZ)Z
       9: ifeq          44
      12: aload_0
      13: getfield      #3                  // Field set:Lio/reactivex/rxjava3/disposables/CompositeDisposable;
      16: aload_0
      17: getfield      #5                  // Field upstream:Lio/reactivex/rxjava3/disposables/Disposable;
      20: invokevirtual #8                  // Method io/reactivex/rxjava3/disposables/CompositeDisposable.delete:(Lio/reactivex/rxjava3/disposables/Disposable;)Z
      23: pop
      24: aload_0
      25: getfield      #3                  // Field set:Lio/reactivex/rxjava3/disposables/CompositeDisposable;
      28: invokevirtual #9                  // Method io/reactivex/rxjava3/disposables/CompositeDisposable.dispose:()V
      31: aload_0
      32: getfield      #2                  // Field downstream:Lio/reactivex/rxjava3/core/MaybeObserver;
      35: aload_1
      36: invokeinterface #11,  2           // InterfaceMethod io/reactivex/rxjava3/core/MaybeObserver.onError:(Ljava/lang/Throwable;)V
      41: goto          48
      44: aload_1
      45: invokestatic  #12                 // Method io/reactivex/rxjava3/plugins/RxJavaPlugins.onError:(Ljava/lang/Throwable;)V
      48: return

  public void onComplete();
    Code:
       0: aload_0
       1: getfield      #4                  // Field winner:Ljava/util/concurrent/atomic/AtomicBoolean;
       4: iconst_0
       5: iconst_1
       6: invokevirtual #7                  // Method java/util/concurrent/atomic/AtomicBoolean.compareAndSet:(ZZ)Z
       9: ifeq          40
      12: aload_0
      13: getfield      #3                  // Field set:Lio/reactivex/rxjava3/disposables/CompositeDisposable;
      16: aload_0
      17: getfield      #5                  // Field upstream:Lio/reactivex/rxjava3/disposables/Disposable;
      20: invokevirtual #8                  // Method io/reactivex/rxjava3/disposables/CompositeDisposable.delete:(Lio/reactivex/rxjava3/disposables/Disposable;)Z
      23: pop
      24: aload_0
      25: getfield      #3                  // Field set:Lio/reactivex/rxjava3/disposables/CompositeDisposable;
      28: invokevirtual #9                  // Method io/reactivex/rxjava3/disposables/CompositeDisposable.dispose:()V
      31: aload_0
      32: getfield      #2                  // Field downstream:Lio/reactivex/rxjava3/core/MaybeObserver;
      35: invokeinterface #13,  1           // InterfaceMethod io/reactivex/rxjava3/core/MaybeObserver.onComplete:()V
      40: return
}
