Compiled from "MaybeToFlowable.java"
public final class io.reactivex.rxjava3.internal.operators.maybe.MaybeToFlowable<T> extends io.reactivex.rxjava3.core.Flowable<T> implements io.reactivex.rxjava3.internal.fuseable.HasUpstreamMaybeSource<T> {
  final io.reactivex.rxjava3.core.MaybeSource<T> source;

  public io.reactivex.rxjava3.internal.operators.maybe.MaybeToFlowable(io.reactivex.rxjava3.core.MaybeSource<T>);
    Code:
       0: aload_0
       1: invokespecial #1                  // Method io/reactivex/rxjava3/core/Flowable."<init>":()V
       4: aload_0
       5: aload_1
       6: putfield      #2                  // Field source:Lio/reactivex/rxjava3/core/MaybeSource;
       9: return

  public io.reactivex.rxjava3.core.MaybeSource<T> source();
    Code:
       0: aload_0
       1: getfield      #2                  // Field source:Lio/reactivex/rxjava3/core/MaybeSource;
       4: areturn

  protected void subscribeActual(org.reactivestreams.Subscriber<? super T>);
    Code:
       0: aload_0
       1: getfield      #2                  // Field source:Lio/reactivex/rxjava3/core/MaybeSource;
       4: new           #3                  // class io/reactivex/rxjava3/internal/operators/maybe/MaybeToFlowable$MaybeToFlowableSubscriber
       7: dup
       8: aload_1
       9: invokespecial #4                  // Method io/reactivex/rxjava3/internal/operators/maybe/MaybeToFlowable$MaybeToFlowableSubscriber."<init>":(Lorg/reactivestreams/Subscriber;)V
      12: invokeinterface #5,  2            // InterfaceMethod io/reactivex/rxjava3/core/MaybeSource.subscribe:(Lio/reactivex/rxjava3/core/MaybeObserver;)V
      17: return
}
