Compiled from "MaybeDelayOtherPublisher.java"
final class io.reactivex.rxjava3.internal.operators.maybe.MaybeDelayOtherPublisher$DelayMaybeObserver<T, U> implements io.reactivex.rxjava3.core.MaybeObserver<T>, io.reactivex.rxjava3.disposables.Disposable {
  final io.reactivex.rxjava3.internal.operators.maybe.MaybeDelayOtherPublisher$OtherSubscriber<T> other;

  final org.reactivestreams.Publisher<U> otherSource;

  io.reactivex.rxjava3.disposables.Disposable upstream;

  io.reactivex.rxjava3.internal.operators.maybe.MaybeDelayOtherPublisher$DelayMaybeObserver(io.reactivex.rxjava3.core.MaybeObserver<? super T>, org.reactivestreams.Publisher<U>);
    Code:
       0: aload_0
       1: invokespecial #1                  // Method java/lang/Object."<init>":()V
       4: aload_0
       5: new           #2                  // class io/reactivex/rxjava3/internal/operators/maybe/MaybeDelayOtherPublisher$OtherSubscriber
       8: dup
       9: aload_1
      10: invokespecial #3                  // Method io/reactivex/rxjava3/internal/operators/maybe/MaybeDelayOtherPublisher$OtherSubscriber."<init>":(Lio/reactivex/rxjava3/core/MaybeObserver;)V
      13: putfield      #4                  // Field other:Lio/reactivex/rxjava3/internal/operators/maybe/MaybeDelayOtherPublisher$OtherSubscriber;
      16: aload_0
      17: aload_2
      18: putfield      #5                  // Field otherSource:Lorg/reactivestreams/Publisher;
      21: return

  public void dispose();
    Code:
       0: aload_0
       1: getfield      #6                  // Field upstream:Lio/reactivex/rxjava3/disposables/Disposable;
       4: invokeinterface #7,  1            // InterfaceMethod io/reactivex/rxjava3/disposables/Disposable.dispose:()V
       9: aload_0
      10: getstatic     #8                  // Field io/reactivex/rxjava3/internal/disposables/DisposableHelper.DISPOSED:Lio/reactivex/rxjava3/internal/disposables/DisposableHelper;
      13: putfield      #6                  // Field upstream:Lio/reactivex/rxjava3/disposables/Disposable;
      16: aload_0
      17: getfield      #4                  // Field other:Lio/reactivex/rxjava3/internal/operators/maybe/MaybeDelayOtherPublisher$OtherSubscriber;
      20: invokestatic  #9                  // Method io/reactivex/rxjava3/internal/subscriptions/SubscriptionHelper.cancel:(Ljava/util/concurrent/atomic/AtomicReference;)Z
      23: pop
      24: return

  public boolean isDisposed();
    Code:
       0: aload_0
       1: getfield      #4                  // Field other:Lio/reactivex/rxjava3/internal/operators/maybe/MaybeDelayOtherPublisher$OtherSubscriber;
       4: invokevirtual #10                 // Method io/reactivex/rxjava3/internal/operators/maybe/MaybeDelayOtherPublisher$OtherSubscriber.get:()Ljava/lang/Object;
       7: getstatic     #11                 // Field io/reactivex/rxjava3/internal/subscriptions/SubscriptionHelper.CANCELLED:Lio/reactivex/rxjava3/internal/subscriptions/SubscriptionHelper;
      10: if_acmpne     17
      13: iconst_1
      14: goto          18
      17: iconst_0
      18: ireturn

  public void onSubscribe(io.reactivex.rxjava3.disposables.Disposable);
    Code:
       0: aload_0
       1: getfield      #6                  // Field upstream:Lio/reactivex/rxjava3/disposables/Disposable;
       4: aload_1
       5: invokestatic  #12                 // Method io/reactivex/rxjava3/internal/disposables/DisposableHelper.validate:(Lio/reactivex/rxjava3/disposables/Disposable;Lio/reactivex/rxjava3/disposables/Disposable;)Z
       8: ifeq          29
      11: aload_0
      12: aload_1
      13: putfield      #6                  // Field upstream:Lio/reactivex/rxjava3/disposables/Disposable;
      16: aload_0
      17: getfield      #4                  // Field other:Lio/reactivex/rxjava3/internal/operators/maybe/MaybeDelayOtherPublisher$OtherSubscriber;
      20: getfield      #13                 // Field io/reactivex/rxjava3/internal/operators/maybe/MaybeDelayOtherPublisher$OtherSubscriber.downstream:Lio/reactivex/rxjava3/core/MaybeObserver;
      23: aload_0
      24: invokeinterface #14,  2           // InterfaceMethod io/reactivex/rxjava3/core/MaybeObserver.onSubscribe:(Lio/reactivex/rxjava3/disposables/Disposable;)V
      29: return

  public void onSuccess(T);
    Code:
       0: aload_0
       1: getstatic     #8                  // Field io/reactivex/rxjava3/internal/disposables/DisposableHelper.DISPOSED:Lio/reactivex/rxjava3/internal/disposables/DisposableHelper;
       4: putfield      #6                  // Field upstream:Lio/reactivex/rxjava3/disposables/Disposable;
       7: aload_0
       8: getfield      #4                  // Field other:Lio/reactivex/rxjava3/internal/operators/maybe/MaybeDelayOtherPublisher$OtherSubscriber;
      11: aload_1
      12: putfield      #15                 // Field io/reactivex/rxjava3/internal/operators/maybe/MaybeDelayOtherPublisher$OtherSubscriber.value:Ljava/lang/Object;
      15: aload_0
      16: invokevirtual #16                 // Method subscribeNext:()V
      19: return

  public void onError(java.lang.Throwable);
    Code:
       0: aload_0
       1: getstatic     #8                  // Field io/reactivex/rxjava3/internal/disposables/DisposableHelper.DISPOSED:Lio/reactivex/rxjava3/internal/disposables/DisposableHelper;
       4: putfield      #6                  // Field upstream:Lio/reactivex/rxjava3/disposables/Disposable;
       7: aload_0
       8: getfield      #4                  // Field other:Lio/reactivex/rxjava3/internal/operators/maybe/MaybeDelayOtherPublisher$OtherSubscriber;
      11: aload_1
      12: putfield      #17                 // Field io/reactivex/rxjava3/internal/operators/maybe/MaybeDelayOtherPublisher$OtherSubscriber.error:Ljava/lang/Throwable;
      15: aload_0
      16: invokevirtual #16                 // Method subscribeNext:()V
      19: return

  public void onComplete();
    Code:
       0: aload_0
       1: getstatic     #8                  // Field io/reactivex/rxjava3/internal/disposables/DisposableHelper.DISPOSED:Lio/reactivex/rxjava3/internal/disposables/DisposableHelper;
       4: putfield      #6                  // Field upstream:Lio/reactivex/rxjava3/disposables/Disposable;
       7: aload_0
       8: invokevirtual #16                 // Method subscribeNext:()V
      11: return

  void subscribeNext();
    Code:
       0: aload_0
       1: getfield      #5                  // Field otherSource:Lorg/reactivestreams/Publisher;
       4: aload_0
       5: getfield      #4                  // Field other:Lio/reactivex/rxjava3/internal/operators/maybe/MaybeDelayOtherPublisher$OtherSubscriber;
       8: invokeinterface #18,  2           // InterfaceMethod org/reactivestreams/Publisher.subscribe:(Lorg/reactivestreams/Subscriber;)V
      13: return
}
