Compiled from "MaybeSwitchIfEmptySingle.java"
final class io.reactivex.rxjava3.internal.operators.maybe.MaybeSwitchIfEmptySingle$SwitchIfEmptyMaybeObserver$OtherSingleObserver<T> implements io.reactivex.rxjava3.core.SingleObserver<T> {
  final io.reactivex.rxjava3.core.SingleObserver<? super T> downstream;

  final java.util.concurrent.atomic.AtomicReference<io.reactivex.rxjava3.disposables.Disposable> parent;

  io.reactivex.rxjava3.internal.operators.maybe.MaybeSwitchIfEmptySingle$SwitchIfEmptyMaybeObserver$OtherSingleObserver(io.reactivex.rxjava3.core.SingleObserver<? super T>, java.util.concurrent.atomic.AtomicReference<io.reactivex.rxjava3.disposables.Disposable>);
    Code:
       0: aload_0
       1: invokespecial #1                  // Method java/lang/Object."<init>":()V
       4: aload_0
       5: aload_1
       6: putfield      #2                  // Field downstream:Lio/reactivex/rxjava3/core/SingleObserver;
       9: aload_0
      10: aload_2
      11: putfield      #3                  // Field parent:Ljava/util/concurrent/atomic/AtomicReference;
      14: return

  public void onSubscribe(io.reactivex.rxjava3.disposables.Disposable);
    Code:
       0: aload_0
       1: getfield      #3                  // Field parent:Ljava/util/concurrent/atomic/AtomicReference;
       4: aload_1
       5: invokestatic  #4                  // Method io/reactivex/rxjava3/internal/disposables/DisposableHelper.setOnce:(Ljava/util/concurrent/atomic/AtomicReference;Lio/reactivex/rxjava3/disposables/Disposable;)Z
       8: pop
       9: return

  public void onSuccess(T);
    Code:
       0: aload_0
       1: getfield      #2                  // Field downstream:Lio/reactivex/rxjava3/core/SingleObserver;
       4: aload_1
       5: invokeinterface #5,  2            // InterfaceMethod io/reactivex/rxjava3/core/SingleObserver.onSuccess:(Ljava/lang/Object;)V
      10: return

  public void onError(java.lang.Throwable);
    Code:
       0: aload_0
       1: getfield      #2                  // Field downstream:Lio/reactivex/rxjava3/core/SingleObserver;
       4: aload_1
       5: invokeinterface #6,  2            // InterfaceMethod io/reactivex/rxjava3/core/SingleObserver.onError:(Ljava/lang/Throwable;)V
      10: return
}
