Compiled from "MaybeTakeUntilMaybe.java"
public final class io.reactivex.rxjava3.internal.operators.maybe.MaybeTakeUntilMaybe<T, U> extends io.reactivex.rxjava3.internal.operators.maybe.AbstractMaybeWithUpstream<T, T> {
  final io.reactivex.rxjava3.core.MaybeSource<U> other;

  public io.reactivex.rxjava3.internal.operators.maybe.MaybeTakeUntilMaybe(io.reactivex.rxjava3.core.MaybeSource<T>, io.reactivex.rxjava3.core.MaybeSource<U>);
    Code:
       0: aload_0
       1: aload_1
       2: invokespecial #1                  // Method io/reactivex/rxjava3/internal/operators/maybe/AbstractMaybeWithUpstream."<init>":(Lio/reactivex/rxjava3/core/MaybeSource;)V
       5: aload_0
       6: aload_2
       7: putfield      #2                  // Field other:Lio/reactivex/rxjava3/core/MaybeSource;
      10: return

  protected void subscribeActual(io.reactivex.rxjava3.core.MaybeObserver<? super T>);
    Code:
       0: new           #3                  // class io/reactivex/rxjava3/internal/operators/maybe/MaybeTakeUntilMaybe$TakeUntilMainMaybeObserver
       3: dup
       4: aload_1
       5: invokespecial #4                  // Method io/reactivex/rxjava3/internal/operators/maybe/MaybeTakeUntilMaybe$TakeUntilMainMaybeObserver."<init>":(Lio/reactivex/rxjava3/core/MaybeObserver;)V
       8: astore_2
       9: aload_1
      10: aload_2
      11: invokeinterface #5,  2            // InterfaceMethod io/reactivex/rxjava3/core/MaybeObserver.onSubscribe:(Lio/reactivex/rxjava3/disposables/Disposable;)V
      16: aload_0
      17: getfield      #2                  // Field other:Lio/reactivex/rxjava3/core/MaybeSource;
      20: aload_2
      21: getfield      #6                  // Field io/reactivex/rxjava3/internal/operators/maybe/MaybeTakeUntilMaybe$TakeUntilMainMaybeObserver.other:Lio/reactivex/rxjava3/internal/operators/maybe/MaybeTakeUntilMaybe$TakeUntilMainMaybeObserver$TakeUntilOtherMaybeObserver;
      24: invokeinterface #7,  2            // InterfaceMethod io/reactivex/rxjava3/core/MaybeSource.subscribe:(Lio/reactivex/rxjava3/core/MaybeObserver;)V
      29: aload_0
      30: getfield      #8                  // Field source:Lio/reactivex/rxjava3/core/MaybeSource;
      33: aload_2
      34: invokeinterface #7,  2            // InterfaceMethod io/reactivex/rxjava3/core/MaybeSource.subscribe:(Lio/reactivex/rxjava3/core/MaybeObserver;)V
      39: return
}
