Compiled from "MaybeDetach.java"
final class io.reactivex.rxjava3.internal.operators.maybe.MaybeDetach$DetachMaybeObserver<T> implements io.reactivex.rxjava3.core.MaybeObserver<T>, io.reactivex.rxjava3.disposables.Disposable {
  io.reactivex.rxjava3.core.MaybeObserver<? super T> downstream;

  io.reactivex.rxjava3.disposables.Disposable upstream;

  io.reactivex.rxjava3.internal.operators.maybe.MaybeDetach$DetachMaybeObserver(io.reactivex.rxjava3.core.MaybeObserver<? super T>);
    Code:
       0: aload_0
       1: invokespecial #1                  // Method java/lang/Object."<init>":()V
       4: aload_0
       5: aload_1
       6: putfield      #2                  // Field downstream:Lio/reactivex/rxjava3/core/MaybeObserver;
       9: return

  public void dispose();
    Code:
       0: aload_0
       1: aconst_null
       2: putfield      #2                  // Field downstream:Lio/reactivex/rxjava3/core/MaybeObserver;
       5: aload_0
       6: getfield      #3                  // Field upstream:Lio/reactivex/rxjava3/disposables/Disposable;
       9: invokeinterface #4,  1            // InterfaceMethod io/reactivex/rxjava3/disposables/Disposable.dispose:()V
      14: aload_0
      15: getstatic     #5                  // Field io/reactivex/rxjava3/internal/disposables/DisposableHelper.DISPOSED:Lio/reactivex/rxjava3/internal/disposables/DisposableHelper;
      18: putfield      #3                  // Field upstream:Lio/reactivex/rxjava3/disposables/Disposable;
      21: return

  public boolean isDisposed();
    Code:
       0: aload_0
       1: getfield      #3                  // Field upstream:Lio/reactivex/rxjava3/disposables/Disposable;
       4: invokeinterface #6,  1            // InterfaceMethod io/reactivex/rxjava3/disposables/Disposable.isDisposed:()Z
       9: ireturn

  public void onSubscribe(io.reactivex.rxjava3.disposables.Disposable);
    Code:
       0: aload_0
       1: getfield      #3                  // Field upstream:Lio/reactivex/rxjava3/disposables/Disposable;
       4: aload_1
       5: invokestatic  #7                  // Method io/reactivex/rxjava3/internal/disposables/DisposableHelper.validate:(Lio/reactivex/rxjava3/disposables/Disposable;Lio/reactivex/rxjava3/disposables/Disposable;)Z
       8: ifeq          26
      11: aload_0
      12: aload_1
      13: putfield      #3                  // Field upstream:Lio/reactivex/rxjava3/disposables/Disposable;
      16: aload_0
      17: getfield      #2                  // Field downstream:Lio/reactivex/rxjava3/core/MaybeObserver;
      20: aload_0
      21: invokeinterface #8,  2            // InterfaceMethod io/reactivex/rxjava3/core/MaybeObserver.onSubscribe:(Lio/reactivex/rxjava3/disposables/Disposable;)V
      26: return

  public void onSuccess(T);
    Code:
       0: aload_0
       1: getstatic     #5                  // Field io/reactivex/rxjava3/internal/disposables/DisposableHelper.DISPOSED:Lio/reactivex/rxjava3/internal/disposables/DisposableHelper;
       4: putfield      #3                  // Field upstream:Lio/reactivex/rxjava3/disposables/Disposable;
       7: aload_0
       8: getfield      #2                  // Field downstream:Lio/reactivex/rxjava3/core/MaybeObserver;
      11: astore_2
      12: aload_2
      13: ifnull        28
      16: aload_0
      17: aconst_null
      18: putfield      #2                  // Field downstream:Lio/reactivex/rxjava3/core/MaybeObserver;
      21: aload_2
      22: aload_1
      23: invokeinterface #9,  2            // InterfaceMethod io/reactivex/rxjava3/core/MaybeObserver.onSuccess:(Ljava/lang/Object;)V
      28: return

  public void onError(java.lang.Throwable);
    Code:
       0: aload_0
       1: getstatic     #5                  // Field io/reactivex/rxjava3/internal/disposables/DisposableHelper.DISPOSED:Lio/reactivex/rxjava3/internal/disposables/DisposableHelper;
       4: putfield      #3                  // Field upstream:Lio/reactivex/rxjava3/disposables/Disposable;
       7: aload_0
       8: getfield      #2                  // Field downstream:Lio/reactivex/rxjava3/core/MaybeObserver;
      11: astore_2
      12: aload_2
      13: ifnull        28
      16: aload_0
      17: aconst_null
      18: putfield      #2                  // Field downstream:Lio/reactivex/rxjava3/core/MaybeObserver;
      21: aload_2
      22: aload_1
      23: invokeinterface #10,  2           // InterfaceMethod io/reactivex/rxjava3/core/MaybeObserver.onError:(Ljava/lang/Throwable;)V
      28: return

  public void onComplete();
    Code:
       0: aload_0
       1: getstatic     #5                  // Field io/reactivex/rxjava3/internal/disposables/DisposableHelper.DISPOSED:Lio/reactivex/rxjava3/internal/disposables/DisposableHelper;
       4: putfield      #3                  // Field upstream:Lio/reactivex/rxjava3/disposables/Disposable;
       7: aload_0
       8: getfield      #2                  // Field downstream:Lio/reactivex/rxjava3/core/MaybeObserver;
      11: astore_1
      12: aload_1
      13: ifnull        27
      16: aload_0
      17: aconst_null
      18: putfield      #2                  // Field downstream:Lio/reactivex/rxjava3/core/MaybeObserver;
      21: aload_1
      22: invokeinterface #11,  1           // InterfaceMethod io/reactivex/rxjava3/core/MaybeObserver.onComplete:()V
      27: return
}
