Compiled from "MaybeZipArray.java"
final class io.reactivex.rxjava3.internal.operators.maybe.MaybeZipArray$ZipCoordinator<T, R> extends java.util.concurrent.atomic.AtomicInteger implements io.reactivex.rxjava3.disposables.Disposable {
  private static final long serialVersionUID;

  final io.reactivex.rxjava3.core.MaybeObserver<? super R> downstream;

  final io.reactivex.rxjava3.functions.Function<? super java.lang.Object[], ? extends R> zipper;

  final io.reactivex.rxjava3.internal.operators.maybe.MaybeZipArray$ZipMaybeObserver<T>[] observers;

  java.lang.Object[] values;

  io.reactivex.rxjava3.internal.operators.maybe.MaybeZipArray$ZipCoordinator(io.reactivex.rxjava3.core.MaybeObserver<? super R>, int, io.reactivex.rxjava3.functions.Function<? super java.lang.Object[], ? extends R>);
    Code:
       0: aload_0
       1: iload_2
       2: invokespecial #1                  // Method java/util/concurrent/atomic/AtomicInteger."<init>":(I)V
       5: aload_0
       6: aload_1
       7: putfield      #2                  // Field downstream:Lio/reactivex/rxjava3/core/MaybeObserver;
      10: aload_0
      11: aload_3
      12: putfield      #3                  // Field zipper:Lio/reactivex/rxjava3/functions/Function;
      15: iload_2
      16: anewarray     #4                  // class io/reactivex/rxjava3/internal/operators/maybe/MaybeZipArray$ZipMaybeObserver
      19: astore        4
      21: iconst_0
      22: istore        5
      24: iload         5
      26: iload_2
      27: if_icmpge     51
      30: aload         4
      32: iload         5
      34: new           #4                  // class io/reactivex/rxjava3/internal/operators/maybe/MaybeZipArray$ZipMaybeObserver
      37: dup
      38: aload_0
      39: iload         5
      41: invokespecial #5                  // Method io/reactivex/rxjava3/internal/operators/maybe/MaybeZipArray$ZipMaybeObserver."<init>":(Lio/reactivex/rxjava3/internal/operators/maybe/MaybeZipArray$ZipCoordinator;I)V
      44: aastore
      45: iinc          5, 1
      48: goto          24
      51: aload_0
      52: aload         4
      54: putfield      #6                  // Field observers:[Lio/reactivex/rxjava3/internal/operators/maybe/MaybeZipArray$ZipMaybeObserver;
      57: aload_0
      58: iload_2
      59: anewarray     #7                  // class java/lang/Object
      62: putfield      #8                  // Field values:[Ljava/lang/Object;
      65: return

  public boolean isDisposed();
    Code:
       0: aload_0
       1: invokevirtual #9                  // Method get:()I
       4: ifgt          11
       7: iconst_1
       8: goto          12
      11: iconst_0
      12: ireturn

  public void dispose();
    Code:
       0: aload_0
       1: iconst_0
       2: invokevirtual #10                 // Method getAndSet:(I)I
       5: ifle          44
       8: aload_0
       9: getfield      #6                  // Field observers:[Lio/reactivex/rxjava3/internal/operators/maybe/MaybeZipArray$ZipMaybeObserver;
      12: astore_1
      13: aload_1
      14: arraylength
      15: istore_2
      16: iconst_0
      17: istore_3
      18: iload_3
      19: iload_2
      20: if_icmpge     39
      23: aload_1
      24: iload_3
      25: aaload
      26: astore        4
      28: aload         4
      30: invokevirtual #11                 // Method io/reactivex/rxjava3/internal/operators/maybe/MaybeZipArray$ZipMaybeObserver.dispose:()V
      33: iinc          3, 1
      36: goto          18
      39: aload_0
      40: aconst_null
      41: putfield      #8                  // Field values:[Ljava/lang/Object;
      44: return

  void innerSuccess(T, int);
    Code:
       0: aload_0
       1: getfield      #8                  // Field values:[Ljava/lang/Object;
       4: astore_3
       5: aload_3
       6: ifnull        13
       9: aload_3
      10: iload_2
      11: aload_1
      12: aastore
      13: aload_0
      14: invokevirtual #12                 // Method decrementAndGet:()I
      17: ifne          80
      20: aload_0
      21: getfield      #3                  // Field zipper:Lio/reactivex/rxjava3/functions/Function;
      24: aload_3
      25: invokeinterface #13,  2           // InterfaceMethod io/reactivex/rxjava3/functions/Function.apply:(Ljava/lang/Object;)Ljava/lang/Object;
      30: ldc           #14                 // String The zipper returned a null value
      32: invokestatic  #15                 // Method java/util/Objects.requireNonNull:(Ljava/lang/Object;Ljava/lang/String;)Ljava/lang/Object;
      35: astore        4
      37: goto          64
      40: astore        5
      42: aload         5
      44: invokestatic  #17                 // Method io/reactivex/rxjava3/exceptions/Exceptions.throwIfFatal:(Ljava/lang/Throwable;)V
      47: aload_0
      48: aconst_null
      49: putfield      #8                  // Field values:[Ljava/lang/Object;
      52: aload_0
      53: getfield      #2                  // Field downstream:Lio/reactivex/rxjava3/core/MaybeObserver;
      56: aload         5
      58: invokeinterface #18,  2           // InterfaceMethod io/reactivex/rxjava3/core/MaybeObserver.onError:(Ljava/lang/Throwable;)V
      63: return
      64: aload_0
      65: aconst_null
      66: putfield      #8                  // Field values:[Ljava/lang/Object;
      69: aload_0
      70: getfield      #2                  // Field downstream:Lio/reactivex/rxjava3/core/MaybeObserver;
      73: aload         4
      75: invokeinterface #19,  2           // InterfaceMethod io/reactivex/rxjava3/core/MaybeObserver.onSuccess:(Ljava/lang/Object;)V
      80: return
    Exception table:
       from    to  target type
          20    37    40   Class java/lang/Throwable

  void disposeExcept(int);
    Code:
       0: aload_0
       1: getfield      #6                  // Field observers:[Lio/reactivex/rxjava3/internal/operators/maybe/MaybeZipArray$ZipMaybeObserver;
       4: astore_2
       5: aload_2
       6: arraylength
       7: istore_3
       8: iconst_0
       9: istore        4
      11: iload         4
      13: iload_1
      14: if_icmpge     30
      17: aload_2
      18: iload         4
      20: aaload
      21: invokevirtual #11                 // Method io/reactivex/rxjava3/internal/operators/maybe/MaybeZipArray$ZipMaybeObserver.dispose:()V
      24: iinc          4, 1
      27: goto          11
      30: iload_1
      31: iconst_1
      32: iadd
      33: istore        4
      35: iload         4
      37: iload_3
      38: if_icmpge     54
      41: aload_2
      42: iload         4
      44: aaload
      45: invokevirtual #11                 // Method io/reactivex/rxjava3/internal/operators/maybe/MaybeZipArray$ZipMaybeObserver.dispose:()V
      48: iinc          4, 1
      51: goto          35
      54: return

  void innerError(java.lang.Throwable, int);
    Code:
       0: aload_0
       1: iconst_0
       2: invokevirtual #10                 // Method getAndSet:(I)I
       5: ifle          31
       8: aload_0
       9: iload_2
      10: invokevirtual #20                 // Method disposeExcept:(I)V
      13: aload_0
      14: aconst_null
      15: putfield      #8                  // Field values:[Ljava/lang/Object;
      18: aload_0
      19: getfield      #2                  // Field downstream:Lio/reactivex/rxjava3/core/MaybeObserver;
      22: aload_1
      23: invokeinterface #18,  2           // InterfaceMethod io/reactivex/rxjava3/core/MaybeObserver.onError:(Ljava/lang/Throwable;)V
      28: goto          35
      31: aload_1
      32: invokestatic  #21                 // Method io/reactivex/rxjava3/plugins/RxJavaPlugins.onError:(Ljava/lang/Throwable;)V
      35: return

  void innerComplete(int);
    Code:
       0: aload_0
       1: iconst_0
       2: invokevirtual #10                 // Method getAndSet:(I)I
       5: ifle          27
       8: aload_0
       9: iload_1
      10: invokevirtual #20                 // Method disposeExcept:(I)V
      13: aload_0
      14: aconst_null
      15: putfield      #8                  // Field values:[Ljava/lang/Object;
      18: aload_0
      19: getfield      #2                  // Field downstream:Lio/reactivex/rxjava3/core/MaybeObserver;
      22: invokeinterface #22,  1           // InterfaceMethod io/reactivex/rxjava3/core/MaybeObserver.onComplete:()V
      27: return
}
