Compiled from "MaybeError.java"
public final class io.reactivex.rxjava3.internal.operators.maybe.MaybeError<T> extends io.reactivex.rxjava3.core.Maybe<T> {
  final java.lang.Throwable error;

  public io.reactivex.rxjava3.internal.operators.maybe.MaybeError(java.lang.Throwable);
    Code:
       0: aload_0
       1: invokespecial #1                  // Method io/reactivex/rxjava3/core/Maybe."<init>":()V
       4: aload_0
       5: aload_1
       6: putfield      #2                  // Field error:Ljava/lang/Throwable;
       9: return

  protected void subscribeActual(io.reactivex.rxjava3.core.MaybeObserver<? super T>);
    Code:
       0: aload_1
       1: invokestatic  #3                  // InterfaceMethod io/reactivex/rxjava3/disposables/Disposable.disposed:()Lio/reactivex/rxjava3/disposables/Disposable;
       4: invokeinterface #4,  2            // InterfaceMethod io/reactivex/rxjava3/core/MaybeObserver.onSubscribe:(Lio/reactivex/rxjava3/disposables/Disposable;)V
       9: aload_1
      10: aload_0
      11: getfield      #2                  // Field error:Ljava/lang/Throwable;
      14: invokeinterface #5,  2            // InterfaceMethod io/reactivex/rxjava3/core/MaybeObserver.onError:(Ljava/lang/Throwable;)V
      19: return
}
