Compiled from "MaybeFlatMapBiSelector.java"
final class io.reactivex.rxjava3.internal.operators.maybe.MaybeFlatMapBiSelector$FlatMapBiMainObserver<T, U, R> implements io.reactivex.rxjava3.core.MaybeObserver<T>, io.reactivex.rxjava3.disposables.Disposable {
  final io.reactivex.rxjava3.functions.Function<? super T, ? extends io.reactivex.rxjava3.core.MaybeSource<? extends U>> mapper;

  final io.reactivex.rxjava3.internal.operators.maybe.MaybeFlatMapBiSelector$FlatMapBiMainObserver$InnerObserver<T, U, R> inner;

  io.reactivex.rxjava3.internal.operators.maybe.MaybeFlatMapBiSelector$FlatMapBiMainObserver(io.reactivex.rxjava3.core.MaybeObserver<? super R>, io.reactivex.rxjava3.functions.Function<? super T, ? extends io.reactivex.rxjava3.core.MaybeSource<? extends U>>, io.reactivex.rxjava3.functions.BiFunction<? super T, ? super U, ? extends R>);
    Code:
       0: aload_0
       1: invokespecial #1                  // Method java/lang/Object."<init>":()V
       4: aload_0
       5: new           #2                  // class io/reactivex/rxjava3/internal/operators/maybe/MaybeFlatMapBiSelector$FlatMapBiMainObserver$InnerObserver
       8: dup
       9: aload_1
      10: aload_3
      11: invokespecial #3                  // Method io/reactivex/rxjava3/internal/operators/maybe/MaybeFlatMapBiSelector$FlatMapBiMainObserver$InnerObserver."<init>":(Lio/reactivex/rxjava3/core/MaybeObserver;Lio/reactivex/rxjava3/functions/BiFunction;)V
      14: putfield      #4                  // Field inner:Lio/reactivex/rxjava3/internal/operators/maybe/MaybeFlatMapBiSelector$FlatMapBiMainObserver$InnerObserver;
      17: aload_0
      18: aload_2
      19: putfield      #5                  // Field mapper:Lio/reactivex/rxjava3/functions/Function;
      22: return

  public void dispose();
    Code:
       0: aload_0
       1: getfield      #4                  // Field inner:Lio/reactivex/rxjava3/internal/operators/maybe/MaybeFlatMapBiSelector$FlatMapBiMainObserver$InnerObserver;
       4: invokestatic  #6                  // Method io/reactivex/rxjava3/internal/disposables/DisposableHelper.dispose:(Ljava/util/concurrent/atomic/AtomicReference;)Z
       7: pop
       8: return

  public boolean isDisposed();
    Code:
       0: aload_0
       1: getfield      #4                  // Field inner:Lio/reactivex/rxjava3/internal/operators/maybe/MaybeFlatMapBiSelector$FlatMapBiMainObserver$InnerObserver;
       4: invokevirtual #7                  // Method io/reactivex/rxjava3/internal/operators/maybe/MaybeFlatMapBiSelector$FlatMapBiMainObserver$InnerObserver.get:()Ljava/lang/Object;
       7: checkcast     #8                  // class io/reactivex/rxjava3/disposables/Disposable
      10: invokestatic  #9                  // Method io/reactivex/rxjava3/internal/disposables/DisposableHelper.isDisposed:(Lio/reactivex/rxjava3/disposables/Disposable;)Z
      13: ireturn

  public void onSubscribe(io.reactivex.rxjava3.disposables.Disposable);
    Code:
       0: aload_0
       1: getfield      #4                  // Field inner:Lio/reactivex/rxjava3/internal/operators/maybe/MaybeFlatMapBiSelector$FlatMapBiMainObserver$InnerObserver;
       4: aload_1
       5: invokestatic  #10                 // Method io/reactivex/rxjava3/internal/disposables/DisposableHelper.setOnce:(Ljava/util/concurrent/atomic/AtomicReference;Lio/reactivex/rxjava3/disposables/Disposable;)Z
       8: ifeq          24
      11: aload_0
      12: getfield      #4                  // Field inner:Lio/reactivex/rxjava3/internal/operators/maybe/MaybeFlatMapBiSelector$FlatMapBiMainObserver$InnerObserver;
      15: getfield      #11                 // Field io/reactivex/rxjava3/internal/operators/maybe/MaybeFlatMapBiSelector$FlatMapBiMainObserver$InnerObserver.downstream:Lio/reactivex/rxjava3/core/MaybeObserver;
      18: aload_0
      19: invokeinterface #12,  2           // InterfaceMethod io/reactivex/rxjava3/core/MaybeObserver.onSubscribe:(Lio/reactivex/rxjava3/disposables/Disposable;)V
      24: return

  public void onSuccess(T);
    Code:
       0: aload_0
       1: getfield      #5                  // Field mapper:Lio/reactivex/rxjava3/functions/Function;
       4: aload_1
       5: invokeinterface #13,  2           // InterfaceMethod io/reactivex/rxjava3/functions/Function.apply:(Ljava/lang/Object;)Ljava/lang/Object;
      10: ldc           #14                 // String The mapper returned a null MaybeSource
      12: invokestatic  #15                 // Method java/util/Objects.requireNonNull:(Ljava/lang/Object;Ljava/lang/String;)Ljava/lang/Object;
      15: checkcast     #16                 // class io/reactivex/rxjava3/core/MaybeSource
      18: astore_2
      19: goto          41
      22: astore_3
      23: aload_3
      24: invokestatic  #18                 // Method io/reactivex/rxjava3/exceptions/Exceptions.throwIfFatal:(Ljava/lang/Throwable;)V
      27: aload_0
      28: getfield      #4                  // Field inner:Lio/reactivex/rxjava3/internal/operators/maybe/MaybeFlatMapBiSelector$FlatMapBiMainObserver$InnerObserver;
      31: getfield      #11                 // Field io/reactivex/rxjava3/internal/operators/maybe/MaybeFlatMapBiSelector$FlatMapBiMainObserver$InnerObserver.downstream:Lio/reactivex/rxjava3/core/MaybeObserver;
      34: aload_3
      35: invokeinterface #19,  2           // InterfaceMethod io/reactivex/rxjava3/core/MaybeObserver.onError:(Ljava/lang/Throwable;)V
      40: return
      41: aload_0
      42: getfield      #4                  // Field inner:Lio/reactivex/rxjava3/internal/operators/maybe/MaybeFlatMapBiSelector$FlatMapBiMainObserver$InnerObserver;
      45: aconst_null
      46: invokestatic  #20                 // Method io/reactivex/rxjava3/internal/disposables/DisposableHelper.replace:(Ljava/util/concurrent/atomic/AtomicReference;Lio/reactivex/rxjava3/disposables/Disposable;)Z
      49: ifeq          70
      52: aload_0
      53: getfield      #4                  // Field inner:Lio/reactivex/rxjava3/internal/operators/maybe/MaybeFlatMapBiSelector$FlatMapBiMainObserver$InnerObserver;
      56: aload_1
      57: putfield      #21                 // Field io/reactivex/rxjava3/internal/operators/maybe/MaybeFlatMapBiSelector$FlatMapBiMainObserver$InnerObserver.value:Ljava/lang/Object;
      60: aload_2
      61: aload_0
      62: getfield      #4                  // Field inner:Lio/reactivex/rxjava3/internal/operators/maybe/MaybeFlatMapBiSelector$FlatMapBiMainObserver$InnerObserver;
      65: invokeinterface #22,  2           // InterfaceMethod io/reactivex/rxjava3/core/MaybeSource.subscribe:(Lio/reactivex/rxjava3/core/MaybeObserver;)V
      70: return
    Exception table:
       from    to  target type
           0    19    22   Class java/lang/Throwable

  public void onError(java.lang.Throwable);
    Code:
       0: aload_0
       1: getfield      #4                  // Field inner:Lio/reactivex/rxjava3/internal/operators/maybe/MaybeFlatMapBiSelector$FlatMapBiMainObserver$InnerObserver;
       4: getfield      #11                 // Field io/reactivex/rxjava3/internal/operators/maybe/MaybeFlatMapBiSelector$FlatMapBiMainObserver$InnerObserver.downstream:Lio/reactivex/rxjava3/core/MaybeObserver;
       7: aload_1
       8: invokeinterface #19,  2           // InterfaceMethod io/reactivex/rxjava3/core/MaybeObserver.onError:(Ljava/lang/Throwable;)V
      13: return

  public void onComplete();
    Code:
       0: aload_0
       1: getfield      #4                  // Field inner:Lio/reactivex/rxjava3/internal/operators/maybe/MaybeFlatMapBiSelector$FlatMapBiMainObserver$InnerObserver;
       4: getfield      #11                 // Field io/reactivex/rxjava3/internal/operators/maybe/MaybeFlatMapBiSelector$FlatMapBiMainObserver$InnerObserver.downstream:Lio/reactivex/rxjava3/core/MaybeObserver;
       7: invokeinterface #23,  1           // InterfaceMethod io/reactivex/rxjava3/core/MaybeObserver.onComplete:()V
      12: return
}
