Compiled from "MaybePeek.java"
final class io.reactivex.rxjava3.internal.operators.maybe.MaybePeek$MaybePeekObserver<T> implements io.reactivex.rxjava3.core.MaybeObserver<T>, io.reactivex.rxjava3.disposables.Disposable {
  final io.reactivex.rxjava3.core.MaybeObserver<? super T> downstream;

  final io.reactivex.rxjava3.internal.operators.maybe.MaybePeek<T> parent;

  io.reactivex.rxjava3.disposables.Disposable upstream;

  io.reactivex.rxjava3.internal.operators.maybe.MaybePeek$MaybePeekObserver(io.reactivex.rxjava3.core.MaybeObserver<? super T>, io.reactivex.rxjava3.internal.operators.maybe.MaybePeek<T>);
    Code:
       0: aload_0
       1: invokespecial #1                  // Method java/lang/Object."<init>":()V
       4: aload_0
       5: aload_1
       6: putfield      #2                  // Field downstream:Lio/reactivex/rxjava3/core/MaybeObserver;
       9: aload_0
      10: aload_2
      11: putfield      #3                  // Field parent:Lio/reactivex/rxjava3/internal/operators/maybe/MaybePeek;
      14: return

  public void dispose();
    Code:
       0: aload_0
       1: getfield      #3                  // Field parent:Lio/reactivex/rxjava3/internal/operators/maybe/MaybePeek;
       4: getfield      #4                  // Field io/reactivex/rxjava3/internal/operators/maybe/MaybePeek.onDisposeCall:Lio/reactivex/rxjava3/functions/Action;
       7: invokeinterface #5,  1            // InterfaceMethod io/reactivex/rxjava3/functions/Action.run:()V
      12: goto          24
      15: astore_1
      16: aload_1
      17: invokestatic  #7                  // Method io/reactivex/rxjava3/exceptions/Exceptions.throwIfFatal:(Ljava/lang/Throwable;)V
      20: aload_1
      21: invokestatic  #8                  // Method io/reactivex/rxjava3/plugins/RxJavaPlugins.onError:(Ljava/lang/Throwable;)V
      24: aload_0
      25: getfield      #9                  // Field upstream:Lio/reactivex/rxjava3/disposables/Disposable;
      28: invokeinterface #10,  1           // InterfaceMethod io/reactivex/rxjava3/disposables/Disposable.dispose:()V
      33: aload_0
      34: getstatic     #11                 // Field io/reactivex/rxjava3/internal/disposables/DisposableHelper.DISPOSED:Lio/reactivex/rxjava3/internal/disposables/DisposableHelper;
      37: putfield      #9                  // Field upstream:Lio/reactivex/rxjava3/disposables/Disposable;
      40: return
    Exception table:
       from    to  target type
           0    12    15   Class java/lang/Throwable

  public boolean isDisposed();
    Code:
       0: aload_0
       1: getfield      #9                  // Field upstream:Lio/reactivex/rxjava3/disposables/Disposable;
       4: invokeinterface #12,  1           // InterfaceMethod io/reactivex/rxjava3/disposables/Disposable.isDisposed:()Z
       9: ireturn

  public void onSubscribe(io.reactivex.rxjava3.disposables.Disposable);
    Code:
       0: aload_0
       1: getfield      #9                  // Field upstream:Lio/reactivex/rxjava3/disposables/Disposable;
       4: aload_1
       5: invokestatic  #13                 // Method io/reactivex/rxjava3/internal/disposables/DisposableHelper.validate:(Lio/reactivex/rxjava3/disposables/Disposable;Lio/reactivex/rxjava3/disposables/Disposable;)Z
       8: ifeq          69
      11: aload_0
      12: getfield      #3                  // Field parent:Lio/reactivex/rxjava3/internal/operators/maybe/MaybePeek;
      15: getfield      #14                 // Field io/reactivex/rxjava3/internal/operators/maybe/MaybePeek.onSubscribeCall:Lio/reactivex/rxjava3/functions/Consumer;
      18: aload_1
      19: invokeinterface #15,  2           // InterfaceMethod io/reactivex/rxjava3/functions/Consumer.accept:(Ljava/lang/Object;)V
      24: goto          54
      27: astore_2
      28: aload_2
      29: invokestatic  #7                  // Method io/reactivex/rxjava3/exceptions/Exceptions.throwIfFatal:(Ljava/lang/Throwable;)V
      32: aload_1
      33: invokeinterface #10,  1           // InterfaceMethod io/reactivex/rxjava3/disposables/Disposable.dispose:()V
      38: aload_0
      39: getstatic     #11                 // Field io/reactivex/rxjava3/internal/disposables/DisposableHelper.DISPOSED:Lio/reactivex/rxjava3/internal/disposables/DisposableHelper;
      42: putfield      #9                  // Field upstream:Lio/reactivex/rxjava3/disposables/Disposable;
      45: aload_2
      46: aload_0
      47: getfield      #2                  // Field downstream:Lio/reactivex/rxjava3/core/MaybeObserver;
      50: invokestatic  #16                 // Method io/reactivex/rxjava3/internal/disposables/EmptyDisposable.error:(Ljava/lang/Throwable;Lio/reactivex/rxjava3/core/MaybeObserver;)V
      53: return
      54: aload_0
      55: aload_1
      56: putfield      #9                  // Field upstream:Lio/reactivex/rxjava3/disposables/Disposable;
      59: aload_0
      60: getfield      #2                  // Field downstream:Lio/reactivex/rxjava3/core/MaybeObserver;
      63: aload_0
      64: invokeinterface #17,  2           // InterfaceMethod io/reactivex/rxjava3/core/MaybeObserver.onSubscribe:(Lio/reactivex/rxjava3/disposables/Disposable;)V
      69: return
    Exception table:
       from    to  target type
          11    24    27   Class java/lang/Throwable

  public void onSuccess(T);
    Code:
       0: aload_0
       1: getfield      #9                  // Field upstream:Lio/reactivex/rxjava3/disposables/Disposable;
       4: getstatic     #11                 // Field io/reactivex/rxjava3/internal/disposables/DisposableHelper.DISPOSED:Lio/reactivex/rxjava3/internal/disposables/DisposableHelper;
       7: if_acmpne     11
      10: return
      11: aload_0
      12: getfield      #3                  // Field parent:Lio/reactivex/rxjava3/internal/operators/maybe/MaybePeek;
      15: getfield      #18                 // Field io/reactivex/rxjava3/internal/operators/maybe/MaybePeek.onSuccessCall:Lio/reactivex/rxjava3/functions/Consumer;
      18: aload_1
      19: invokeinterface #15,  2           // InterfaceMethod io/reactivex/rxjava3/functions/Consumer.accept:(Ljava/lang/Object;)V
      24: goto          38
      27: astore_2
      28: aload_2
      29: invokestatic  #7                  // Method io/reactivex/rxjava3/exceptions/Exceptions.throwIfFatal:(Ljava/lang/Throwable;)V
      32: aload_0
      33: aload_2
      34: invokevirtual #19                 // Method onErrorInner:(Ljava/lang/Throwable;)V
      37: return
      38: aload_0
      39: getstatic     #11                 // Field io/reactivex/rxjava3/internal/disposables/DisposableHelper.DISPOSED:Lio/reactivex/rxjava3/internal/disposables/DisposableHelper;
      42: putfield      #9                  // Field upstream:Lio/reactivex/rxjava3/disposables/Disposable;
      45: aload_0
      46: getfield      #2                  // Field downstream:Lio/reactivex/rxjava3/core/MaybeObserver;
      49: aload_1
      50: invokeinterface #20,  2           // InterfaceMethod io/reactivex/rxjava3/core/MaybeObserver.onSuccess:(Ljava/lang/Object;)V
      55: aload_0
      56: invokevirtual #21                 // Method onAfterTerminate:()V
      59: return
    Exception table:
       from    to  target type
          11    24    27   Class java/lang/Throwable

  public void onError(java.lang.Throwable);
    Code:
       0: aload_0
       1: getfield      #9                  // Field upstream:Lio/reactivex/rxjava3/disposables/Disposable;
       4: getstatic     #11                 // Field io/reactivex/rxjava3/internal/disposables/DisposableHelper.DISPOSED:Lio/reactivex/rxjava3/internal/disposables/DisposableHelper;
       7: if_acmpne     15
      10: aload_1
      11: invokestatic  #8                  // Method io/reactivex/rxjava3/plugins/RxJavaPlugins.onError:(Ljava/lang/Throwable;)V
      14: return
      15: aload_0
      16: aload_1
      17: invokevirtual #19                 // Method onErrorInner:(Ljava/lang/Throwable;)V
      20: return

  void onErrorInner(java.lang.Throwable);
    Code:
       0: aload_0
       1: getfield      #3                  // Field parent:Lio/reactivex/rxjava3/internal/operators/maybe/MaybePeek;
       4: getfield      #22                 // Field io/reactivex/rxjava3/internal/operators/maybe/MaybePeek.onErrorCall:Lio/reactivex/rxjava3/functions/Consumer;
       7: aload_1
       8: invokeinterface #15,  2           // InterfaceMethod io/reactivex/rxjava3/functions/Consumer.accept:(Ljava/lang/Object;)V
      13: goto          41
      16: astore_2
      17: aload_2
      18: invokestatic  #7                  // Method io/reactivex/rxjava3/exceptions/Exceptions.throwIfFatal:(Ljava/lang/Throwable;)V
      21: new           #23                 // class io/reactivex/rxjava3/exceptions/CompositeException
      24: dup
      25: iconst_2
      26: anewarray     #24                 // class java/lang/Throwable
      29: dup
      30: iconst_0
      31: aload_1
      32: aastore
      33: dup
      34: iconst_1
      35: aload_2
      36: aastore
      37: invokespecial #25                 // Method io/reactivex/rxjava3/exceptions/CompositeException."<init>":([Ljava/lang/Throwable;)V
      40: astore_1
      41: aload_0
      42: getstatic     #11                 // Field io/reactivex/rxjava3/internal/disposables/DisposableHelper.DISPOSED:Lio/reactivex/rxjava3/internal/disposables/DisposableHelper;
      45: putfield      #9                  // Field upstream:Lio/reactivex/rxjava3/disposables/Disposable;
      48: aload_0
      49: getfield      #2                  // Field downstream:Lio/reactivex/rxjava3/core/MaybeObserver;
      52: aload_1
      53: invokeinterface #26,  2           // InterfaceMethod io/reactivex/rxjava3/core/MaybeObserver.onError:(Ljava/lang/Throwable;)V
      58: aload_0
      59: invokevirtual #21                 // Method onAfterTerminate:()V
      62: return
    Exception table:
       from    to  target type
           0    13    16   Class java/lang/Throwable

  public void onComplete();
    Code:
       0: aload_0
       1: getfield      #9                  // Field upstream:Lio/reactivex/rxjava3/disposables/Disposable;
       4: getstatic     #11                 // Field io/reactivex/rxjava3/internal/disposables/DisposableHelper.DISPOSED:Lio/reactivex/rxjava3/internal/disposables/DisposableHelper;
       7: if_acmpne     11
      10: return
      11: aload_0
      12: getfield      #3                  // Field parent:Lio/reactivex/rxjava3/internal/operators/maybe/MaybePeek;
      15: getfield      #27                 // Field io/reactivex/rxjava3/internal/operators/maybe/MaybePeek.onCompleteCall:Lio/reactivex/rxjava3/functions/Action;
      18: invokeinterface #5,  1            // InterfaceMethod io/reactivex/rxjava3/functions/Action.run:()V
      23: goto          37
      26: astore_1
      27: aload_1
      28: invokestatic  #7                  // Method io/reactivex/rxjava3/exceptions/Exceptions.throwIfFatal:(Ljava/lang/Throwable;)V
      31: aload_0
      32: aload_1
      33: invokevirtual #19                 // Method onErrorInner:(Ljava/lang/Throwable;)V
      36: return
      37: aload_0
      38: getstatic     #11                 // Field io/reactivex/rxjava3/internal/disposables/DisposableHelper.DISPOSED:Lio/reactivex/rxjava3/internal/disposables/DisposableHelper;
      41: putfield      #9                  // Field upstream:Lio/reactivex/rxjava3/disposables/Disposable;
      44: aload_0
      45: getfield      #2                  // Field downstream:Lio/reactivex/rxjava3/core/MaybeObserver;
      48: invokeinterface #28,  1           // InterfaceMethod io/reactivex/rxjava3/core/MaybeObserver.onComplete:()V
      53: aload_0
      54: invokevirtual #21                 // Method onAfterTerminate:()V
      57: return
    Exception table:
       from    to  target type
          11    23    26   Class java/lang/Throwable

  void onAfterTerminate();
    Code:
       0: aload_0
       1: getfield      #3                  // Field parent:Lio/reactivex/rxjava3/internal/operators/maybe/MaybePeek;
       4: getfield      #29                 // Field io/reactivex/rxjava3/internal/operators/maybe/MaybePeek.onAfterTerminate:Lio/reactivex/rxjava3/functions/Action;
       7: invokeinterface #5,  1            // InterfaceMethod io/reactivex/rxjava3/functions/Action.run:()V
      12: goto          24
      15: astore_1
      16: aload_1
      17: invokestatic  #7                  // Method io/reactivex/rxjava3/exceptions/Exceptions.throwIfFatal:(Ljava/lang/Throwable;)V
      20: aload_1
      21: invokestatic  #8                  // Method io/reactivex/rxjava3/plugins/RxJavaPlugins.onError:(Ljava/lang/Throwable;)V
      24: return
    Exception table:
       from    to  target type
           0    12    15   Class java/lang/Throwable
}
