Compiled from "MaybeIgnoreElementCompletable.java"
public final class io.reactivex.rxjava3.internal.operators.maybe.MaybeIgnoreElementCompletable<T> extends io.reactivex.rxjava3.core.Completable implements io.reactivex.rxjava3.internal.fuseable.FuseToMaybe<T> {
  final io.reactivex.rxjava3.core.MaybeSource<T> source;

  public io.reactivex.rxjava3.internal.operators.maybe.MaybeIgnoreElementCompletable(io.reactivex.rxjava3.core.MaybeSource<T>);
    Code:
       0: aload_0
       1: invokespecial #1                  // Method io/reactivex/rxjava3/core/Completable."<init>":()V
       4: aload_0
       5: aload_1
       6: putfield      #2                  // Field source:Lio/reactivex/rxjava3/core/MaybeSource;
       9: return

  protected void subscribeActual(io.reactivex.rxjava3.core.CompletableObserver);
    Code:
       0: aload_0
       1: getfield      #2                  // Field source:Lio/reactivex/rxjava3/core/MaybeSource;
       4: new           #3                  // class io/reactivex/rxjava3/internal/operators/maybe/MaybeIgnoreElementCompletable$IgnoreMaybeObserver
       7: dup
       8: aload_1
       9: invokespecial #4                  // Method io/reactivex/rxjava3/internal/operators/maybe/MaybeIgnoreElementCompletable$IgnoreMaybeObserver."<init>":(Lio/reactivex/rxjava3/core/CompletableObserver;)V
      12: invokeinterface #5,  2            // InterfaceMethod io/reactivex/rxjava3/core/MaybeSource.subscribe:(Lio/reactivex/rxjava3/core/MaybeObserver;)V
      17: return

  public io.reactivex.rxjava3.core.Maybe<T> fuseToMaybe();
    Code:
       0: new           #6                  // class io/reactivex/rxjava3/internal/operators/maybe/MaybeIgnoreElement
       3: dup
       4: aload_0
       5: getfield      #2                  // Field source:Lio/reactivex/rxjava3/core/MaybeSource;
       8: invokespecial #7                  // Method io/reactivex/rxjava3/internal/operators/maybe/MaybeIgnoreElement."<init>":(Lio/reactivex/rxjava3/core/MaybeSource;)V
      11: invokestatic  #8                  // Method io/reactivex/rxjava3/plugins/RxJavaPlugins.onAssembly:(Lio/reactivex/rxjava3/core/Maybe;)Lio/reactivex/rxjava3/core/Maybe;
      14: areturn
}
