Compiled from "MaybeSubscribeOn.java"
public final class io.reactivex.rxjava3.internal.operators.maybe.MaybeSubscribeOn<T> extends io.reactivex.rxjava3.internal.operators.maybe.AbstractMaybeWithUpstream<T, T> {
  final io.reactivex.rxjava3.core.Scheduler scheduler;

  public io.reactivex.rxjava3.internal.operators.maybe.MaybeSubscribeOn(io.reactivex.rxjava3.core.MaybeSource<T>, io.reactivex.rxjava3.core.Scheduler);
    Code:
       0: aload_0
       1: aload_1
       2: invokespecial #1                  // Method io/reactivex/rxjava3/internal/operators/maybe/AbstractMaybeWithUpstream."<init>":(Lio/reactivex/rxjava3/core/MaybeSource;)V
       5: aload_0
       6: aload_2
       7: putfield      #2                  // Field scheduler:Lio/reactivex/rxjava3/core/Scheduler;
      10: return

  protected void subscribeActual(io.reactivex.rxjava3.core.MaybeObserver<? super T>);
    Code:
       0: new           #3                  // class io/reactivex/rxjava3/internal/operators/maybe/MaybeSubscribeOn$SubscribeOnMaybeObserver
       3: dup
       4: aload_1
       5: invokespecial #4                  // Method io/reactivex/rxjava3/internal/operators/maybe/MaybeSubscribeOn$SubscribeOnMaybeObserver."<init>":(Lio/reactivex/rxjava3/core/MaybeObserver;)V
       8: astore_2
       9: aload_1
      10: aload_2
      11: invokeinterface #5,  2            // InterfaceMethod io/reactivex/rxjava3/core/MaybeObserver.onSubscribe:(Lio/reactivex/rxjava3/disposables/Disposable;)V
      16: aload_2
      17: getfield      #6                  // Field io/reactivex/rxjava3/internal/operators/maybe/MaybeSubscribeOn$SubscribeOnMaybeObserver.task:Lio/reactivex/rxjava3/internal/disposables/SequentialDisposable;
      20: aload_0
      21: getfield      #2                  // Field scheduler:Lio/reactivex/rxjava3/core/Scheduler;
      24: new           #7                  // class io/reactivex/rxjava3/internal/operators/maybe/MaybeSubscribeOn$SubscribeTask
      27: dup
      28: aload_2
      29: aload_0
      30: getfield      #8                  // Field source:Lio/reactivex/rxjava3/core/MaybeSource;
      33: invokespecial #9                  // Method io/reactivex/rxjava3/internal/operators/maybe/MaybeSubscribeOn$SubscribeTask."<init>":(Lio/reactivex/rxjava3/core/MaybeObserver;Lio/reactivex/rxjava3/core/MaybeSource;)V
      36: invokevirtual #10                 // Method io/reactivex/rxjava3/core/Scheduler.scheduleDirect:(Ljava/lang/Runnable;)Lio/reactivex/rxjava3/disposables/Disposable;
      39: invokevirtual #11                 // Method io/reactivex/rxjava3/internal/disposables/SequentialDisposable.replace:(Lio/reactivex/rxjava3/disposables/Disposable;)Z
      42: pop
      43: return
}
