Compiled from "MaybeContains.java"
final class io.reactivex.rxjava3.internal.operators.maybe.MaybeContains$ContainsMaybeObserver implements io.reactivex.rxjava3.core.MaybeObserver<java.lang.Object>, io.reactivex.rxjava3.disposables.Disposable {
  final io.reactivex.rxjava3.core.SingleObserver<? super java.lang.Boolean> downstream;

  final java.lang.Object value;

  io.reactivex.rxjava3.disposables.Disposable upstream;

  io.reactivex.rxjava3.internal.operators.maybe.MaybeContains$ContainsMaybeObserver(io.reactivex.rxjava3.core.SingleObserver<? super java.lang.Boolean>, java.lang.Object);
    Code:
       0: aload_0
       1: invokespecial #1                  // Method java/lang/Object."<init>":()V
       4: aload_0
       5: aload_1
       6: putfield      #2                  // Field downstream:Lio/reactivex/rxjava3/core/SingleObserver;
       9: aload_0
      10: aload_2
      11: putfield      #3                  // Field value:Ljava/lang/Object;
      14: return

  public void dispose();
    Code:
       0: aload_0
       1: getfield      #4                  // Field upstream:Lio/reactivex/rxjava3/disposables/Disposable;
       4: invokeinterface #5,  1            // InterfaceMethod io/reactivex/rxjava3/disposables/Disposable.dispose:()V
       9: aload_0
      10: getstatic     #6                  // Field io/reactivex/rxjava3/internal/disposables/DisposableHelper.DISPOSED:Lio/reactivex/rxjava3/internal/disposables/DisposableHelper;
      13: putfield      #4                  // Field upstream:Lio/reactivex/rxjava3/disposables/Disposable;
      16: return

  public boolean isDisposed();
    Code:
       0: aload_0
       1: getfield      #4                  // Field upstream:Lio/reactivex/rxjava3/disposables/Disposable;
       4: invokeinterface #7,  1            // InterfaceMethod io/reactivex/rxjava3/disposables/Disposable.isDisposed:()Z
       9: ireturn

  public void onSubscribe(io.reactivex.rxjava3.disposables.Disposable);
    Code:
       0: aload_0
       1: getfield      #4                  // Field upstream:Lio/reactivex/rxjava3/disposables/Disposable;
       4: aload_1
       5: invokestatic  #8                  // Method io/reactivex/rxjava3/internal/disposables/DisposableHelper.validate:(Lio/reactivex/rxjava3/disposables/Disposable;Lio/reactivex/rxjava3/disposables/Disposable;)Z
       8: ifeq          26
      11: aload_0
      12: aload_1
      13: putfield      #4                  // Field upstream:Lio/reactivex/rxjava3/disposables/Disposable;
      16: aload_0
      17: getfield      #2                  // Field downstream:Lio/reactivex/rxjava3/core/SingleObserver;
      20: aload_0
      21: invokeinterface #9,  2            // InterfaceMethod io/reactivex/rxjava3/core/SingleObserver.onSubscribe:(Lio/reactivex/rxjava3/disposables/Disposable;)V
      26: return

  public void onSuccess(java.lang.Object);
    Code:
       0: aload_0
       1: getstatic     #6                  // Field io/reactivex/rxjava3/internal/disposables/DisposableHelper.DISPOSED:Lio/reactivex/rxjava3/internal/disposables/DisposableHelper;
       4: putfield      #4                  // Field upstream:Lio/reactivex/rxjava3/disposables/Disposable;
       7: aload_0
       8: getfield      #2                  // Field downstream:Lio/reactivex/rxjava3/core/SingleObserver;
      11: aload_1
      12: aload_0
      13: getfield      #3                  // Field value:Ljava/lang/Object;
      16: invokestatic  #10                 // Method java/util/Objects.equals:(Ljava/lang/Object;Ljava/lang/Object;)Z
      19: invokestatic  #11                 // Method java/lang/Boolean.valueOf:(Z)Ljava/lang/Boolean;
      22: invokeinterface #12,  2           // InterfaceMethod io/reactivex/rxjava3/core/SingleObserver.onSuccess:(Ljava/lang/Object;)V
      27: return

  public void onError(java.lang.Throwable);
    Code:
       0: aload_0
       1: getstatic     #6                  // Field io/reactivex/rxjava3/internal/disposables/DisposableHelper.DISPOSED:Lio/reactivex/rxjava3/internal/disposables/DisposableHelper;
       4: putfield      #4                  // Field upstream:Lio/reactivex/rxjava3/disposables/Disposable;
       7: aload_0
       8: getfield      #2                  // Field downstream:Lio/reactivex/rxjava3/core/SingleObserver;
      11: aload_1
      12: invokeinterface #13,  2           // InterfaceMethod io/reactivex/rxjava3/core/SingleObserver.onError:(Ljava/lang/Throwable;)V
      17: return

  public void onComplete();
    Code:
       0: aload_0
       1: getstatic     #6                  // Field io/reactivex/rxjava3/internal/disposables/DisposableHelper.DISPOSED:Lio/reactivex/rxjava3/internal/disposables/DisposableHelper;
       4: putfield      #4                  // Field upstream:Lio/reactivex/rxjava3/disposables/Disposable;
       7: aload_0
       8: getfield      #2                  // Field downstream:Lio/reactivex/rxjava3/core/SingleObserver;
      11: iconst_0
      12: invokestatic  #11                 // Method java/lang/Boolean.valueOf:(Z)Ljava/lang/Boolean;
      15: invokeinterface #12,  2           // InterfaceMethod io/reactivex/rxjava3/core/SingleObserver.onSuccess:(Ljava/lang/Object;)V
      20: return
}
