Compiled from "MaybeFlatMapBiSelector.java"
public final class io.reactivex.rxjava3.internal.operators.maybe.MaybeFlatMapBiSelector<T, U, R> extends io.reactivex.rxjava3.internal.operators.maybe.AbstractMaybeWithUpstream<T, R> {
  final io.reactivex.rxjava3.functions.Function<? super T, ? extends io.reactivex.rxjava3.core.MaybeSource<? extends U>> mapper;

  final io.reactivex.rxjava3.functions.BiFunction<? super T, ? super U, ? extends R> resultSelector;

  public io.reactivex.rxjava3.internal.operators.maybe.MaybeFlatMapBiSelector(io.reactivex.rxjava3.core.MaybeSource<T>, io.reactivex.rxjava3.functions.Function<? super T, ? extends io.reactivex.rxjava3.core.MaybeSource<? extends U>>, io.reactivex.rxjava3.functions.BiFunction<? super T, ? super U, ? extends R>);
    Code:
       0: aload_0
       1: aload_1
       2: invokespecial #1                  // Method io/reactivex/rxjava3/internal/operators/maybe/AbstractMaybeWithUpstream."<init>":(Lio/reactivex/rxjava3/core/MaybeSource;)V
       5: aload_0
       6: aload_2
       7: putfield      #2                  // Field mapper:Lio/reactivex/rxjava3/functions/Function;
      10: aload_0
      11: aload_3
      12: putfield      #3                  // Field resultSelector:Lio/reactivex/rxjava3/functions/BiFunction;
      15: return

  protected void subscribeActual(io.reactivex.rxjava3.core.MaybeObserver<? super R>);
    Code:
       0: aload_0
       1: getfield      #4                  // Field source:Lio/reactivex/rxjava3/core/MaybeSource;
       4: new           #5                  // class io/reactivex/rxjava3/internal/operators/maybe/MaybeFlatMapBiSelector$FlatMapBiMainObserver
       7: dup
       8: aload_1
       9: aload_0
      10: getfield      #2                  // Field mapper:Lio/reactivex/rxjava3/functions/Function;
      13: aload_0
      14: getfield      #3                  // Field resultSelector:Lio/reactivex/rxjava3/functions/BiFunction;
      17: invokespecial #6                  // Method io/reactivex/rxjava3/internal/operators/maybe/MaybeFlatMapBiSelector$FlatMapBiMainObserver."<init>":(Lio/reactivex/rxjava3/core/MaybeObserver;Lio/reactivex/rxjava3/functions/Function;Lio/reactivex/rxjava3/functions/BiFunction;)V
      20: invokeinterface #7,  2            // InterfaceMethod io/reactivex/rxjava3/core/MaybeSource.subscribe:(Lio/reactivex/rxjava3/core/MaybeObserver;)V
      25: return
}
