Compiled from "MaybeLift.java"
public final class io.reactivex.rxjava3.internal.operators.maybe.MaybeLift<T, R> extends io.reactivex.rxjava3.internal.operators.maybe.AbstractMaybeWithUpstream<T, R> {
  final io.reactivex.rxjava3.core.MaybeOperator<? extends R, ? super T> operator;

  public io.reactivex.rxjava3.internal.operators.maybe.MaybeLift(io.reactivex.rxjava3.core.MaybeSource<T>, io.reactivex.rxjava3.core.MaybeOperator<? extends R, ? super T>);
    Code:
       0: aload_0
       1: aload_1
       2: invokespecial #1                  // Method io/reactivex/rxjava3/internal/operators/maybe/AbstractMaybeWithUpstream."<init>":(Lio/reactivex/rxjava3/core/MaybeSource;)V
       5: aload_0
       6: aload_2
       7: putfield      #2                  // Field operator:Lio/reactivex/rxjava3/core/MaybeOperator;
      10: return

  protected void subscribeActual(io.reactivex.rxjava3.core.MaybeObserver<? super R>);
    Code:
       0: aload_0
       1: getfield      #2                  // Field operator:Lio/reactivex/rxjava3/core/MaybeOperator;
       4: aload_1
       5: invokeinterface #3,  2            // InterfaceMethod io/reactivex/rxjava3/core/MaybeOperator.apply:(Lio/reactivex/rxjava3/core/MaybeObserver;)Lio/reactivex/rxjava3/core/MaybeObserver;
      10: ldc           #4                  // String The operator returned a null MaybeObserver
      12: invokestatic  #5                  // Method java/util/Objects.requireNonNull:(Ljava/lang/Object;Ljava/lang/String;)Ljava/lang/Object;
      15: checkcast     #6                  // class io/reactivex/rxjava3/core/MaybeObserver
      18: astore_2
      19: goto          33
      22: astore_3
      23: aload_3
      24: invokestatic  #8                  // Method io/reactivex/rxjava3/exceptions/Exceptions.throwIfFatal:(Ljava/lang/Throwable;)V
      27: aload_3
      28: aload_1
      29: invokestatic  #9                  // Method io/reactivex/rxjava3/internal/disposables/EmptyDisposable.error:(Ljava/lang/Throwable;Lio/reactivex/rxjava3/core/MaybeObserver;)V
      32: return
      33: aload_0
      34: getfield      #10                 // Field source:Lio/reactivex/rxjava3/core/MaybeSource;
      37: aload_2
      38: invokeinterface #11,  2           // InterfaceMethod io/reactivex/rxjava3/core/MaybeSource.subscribe:(Lio/reactivex/rxjava3/core/MaybeObserver;)V
      43: return
    Exception table:
       from    to  target type
           0    19    22   Class java/lang/Throwable
}
