Compiled from "MaybeErrorCallable.java"
public final class io.reactivex.rxjava3.internal.operators.maybe.MaybeErrorCallable<T> extends io.reactivex.rxjava3.core.Maybe<T> {
  final io.reactivex.rxjava3.functions.Supplier<? extends java.lang.Throwable> errorSupplier;

  public io.reactivex.rxjava3.internal.operators.maybe.MaybeErrorCallable(io.reactivex.rxjava3.functions.Supplier<? extends java.lang.Throwable>);
    Code:
       0: aload_0
       1: invokespecial #1                  // Method io/reactivex/rxjava3/core/Maybe."<init>":()V
       4: aload_0
       5: aload_1
       6: putfield      #2                  // Field errorSupplier:Lio/reactivex/rxjava3/functions/Supplier;
       9: return

  protected void subscribeActual(io.reactivex.rxjava3.core.MaybeObserver<? super T>);
    Code:
       0: aload_1
       1: invokestatic  #3                  // InterfaceMethod io/reactivex/rxjava3/disposables/Disposable.disposed:()Lio/reactivex/rxjava3/disposables/Disposable;
       4: invokeinterface #4,  2            // InterfaceMethod io/reactivex/rxjava3/core/MaybeObserver.onSubscribe:(Lio/reactivex/rxjava3/disposables/Disposable;)V
       9: aload_0
      10: getfield      #2                  // Field errorSupplier:Lio/reactivex/rxjava3/functions/Supplier;
      13: invokeinterface #5,  1            // InterfaceMethod io/reactivex/rxjava3/functions/Supplier.get:()Ljava/lang/Object;
      18: ldc           #6                  // String Supplier returned a null Throwable.
      20: invokestatic  #7                  // Method io/reactivex/rxjava3/internal/util/ExceptionHelper.nullCheck:(Ljava/lang/Object;Ljava/lang/String;)Ljava/lang/Object;
      23: checkcast     #8                  // class java/lang/Throwable
      26: astore_2
      27: goto          37
      30: astore_3
      31: aload_3
      32: invokestatic  #9                  // Method io/reactivex/rxjava3/exceptions/Exceptions.throwIfFatal:(Ljava/lang/Throwable;)V
      35: aload_3
      36: astore_2
      37: aload_1
      38: aload_2
      39: invokeinterface #10,  2           // InterfaceMethod io/reactivex/rxjava3/core/MaybeObserver.onError:(Ljava/lang/Throwable;)V
      44: return
    Exception table:
       from    to  target type
           9    27    30   Class java/lang/Throwable
}
