Compiled from "MaybeContains.java"
public final class io.reactivex.rxjava3.internal.operators.maybe.MaybeContains<T> extends io.reactivex.rxjava3.core.Single<java.lang.Boolean> implements io.reactivex.rxjava3.internal.fuseable.HasUpstreamMaybeSource<T> {
  final io.reactivex.rxjava3.core.MaybeSource<T> source;

  final java.lang.Object value;

  public io.reactivex.rxjava3.internal.operators.maybe.MaybeContains(io.reactivex.rxjava3.core.MaybeSource<T>, java.lang.Object);
    Code:
       0: aload_0
       1: invokespecial #1                  // Method io/reactivex/rxjava3/core/Single."<init>":()V
       4: aload_0
       5: aload_1
       6: putfield      #2                  // Field source:Lio/reactivex/rxjava3/core/MaybeSource;
       9: aload_0
      10: aload_2
      11: putfield      #3                  // Field value:Ljava/lang/Object;
      14: return

  public io.reactivex.rxjava3.core.MaybeSource<T> source();
    Code:
       0: aload_0
       1: getfield      #2                  // Field source:Lio/reactivex/rxjava3/core/MaybeSource;
       4: areturn

  protected void subscribeActual(io.reactivex.rxjava3.core.SingleObserver<? super java.lang.Boolean>);
    Code:
       0: aload_0
       1: getfield      #2                  // Field source:Lio/reactivex/rxjava3/core/MaybeSource;
       4: new           #4                  // class io/reactivex/rxjava3/internal/operators/maybe/MaybeContains$ContainsMaybeObserver
       7: dup
       8: aload_1
       9: aload_0
      10: getfield      #3                  // Field value:Ljava/lang/Object;
      13: invokespecial #5                  // Method io/reactivex/rxjava3/internal/operators/maybe/MaybeContains$ContainsMaybeObserver."<init>":(Lio/reactivex/rxjava3/core/SingleObserver;Ljava/lang/Object;)V
      16: invokeinterface #6,  2            // InterfaceMethod io/reactivex/rxjava3/core/MaybeSource.subscribe:(Lio/reactivex/rxjava3/core/MaybeObserver;)V
      21: return
}
