Compiled from "MaybeConcatArrayDelayError.java"
final class io.reactivex.rxjava3.internal.operators.maybe.MaybeConcatArrayDelayError$ConcatMaybeObserver<T> extends java.util.concurrent.atomic.AtomicInteger implements io.reactivex.rxjava3.core.MaybeObserver<T>, org.reactivestreams.Subscription {
  private static final long serialVersionUID;

  final org.reactivestreams.Subscriber<? super T> downstream;

  final java.util.concurrent.atomic.AtomicLong requested;

  final java.util.concurrent.atomic.AtomicReference<java.lang.Object> current;

  final io.reactivex.rxjava3.internal.disposables.SequentialDisposable disposables;

  final io.reactivex.rxjava3.core.MaybeSource<? extends T>[] sources;

  final io.reactivex.rxjava3.internal.util.AtomicThrowable errors;

  int index;

  long produced;

  io.reactivex.rxjava3.internal.operators.maybe.MaybeConcatArrayDelayError$ConcatMaybeObserver(org.reactivestreams.Subscriber<? super T>, io.reactivex.rxjava3.core.MaybeSource<? extends T>[]);
    Code:
       0: aload_0
       1: invokespecial #1                  // Method java/util/concurrent/atomic/AtomicInteger."<init>":()V
       4: aload_0
       5: aload_1
       6: putfield      #2                  // Field downstream:Lorg/reactivestreams/Subscriber;
       9: aload_0
      10: aload_2
      11: putfield      #3                  // Field sources:[Lio/reactivex/rxjava3/core/MaybeSource;
      14: aload_0
      15: new           #4                  // class java/util/concurrent/atomic/AtomicLong
      18: dup
      19: invokespecial #5                  // Method java/util/concurrent/atomic/AtomicLong."<init>":()V
      22: putfield      #6                  // Field requested:Ljava/util/concurrent/atomic/AtomicLong;
      25: aload_0
      26: new           #7                  // class io/reactivex/rxjava3/internal/disposables/SequentialDisposable
      29: dup
      30: invokespecial #8                  // Method io/reactivex/rxjava3/internal/disposables/SequentialDisposable."<init>":()V
      33: putfield      #9                  // Field disposables:Lio/reactivex/rxjava3/internal/disposables/SequentialDisposable;
      36: aload_0
      37: new           #10                 // class java/util/concurrent/atomic/AtomicReference
      40: dup
      41: getstatic     #11                 // Field io/reactivex/rxjava3/internal/util/NotificationLite.COMPLETE:Lio/reactivex/rxjava3/internal/util/NotificationLite;
      44: invokespecial #12                 // Method java/util/concurrent/atomic/AtomicReference."<init>":(Ljava/lang/Object;)V
      47: putfield      #13                 // Field current:Ljava/util/concurrent/atomic/AtomicReference;
      50: aload_0
      51: new           #14                 // class io/reactivex/rxjava3/internal/util/AtomicThrowable
      54: dup
      55: invokespecial #15                 // Method io/reactivex/rxjava3/internal/util/AtomicThrowable."<init>":()V
      58: putfield      #16                 // Field errors:Lio/reactivex/rxjava3/internal/util/AtomicThrowable;
      61: return

  public void request(long);
    Code:
       0: lload_1
       1: invokestatic  #17                 // Method io/reactivex/rxjava3/internal/subscriptions/SubscriptionHelper.validate:(J)Z
       4: ifeq          20
       7: aload_0
       8: getfield      #6                  // Field requested:Ljava/util/concurrent/atomic/AtomicLong;
      11: lload_1
      12: invokestatic  #18                 // Method io/reactivex/rxjava3/internal/util/BackpressureHelper.add:(Ljava/util/concurrent/atomic/AtomicLong;J)J
      15: pop2
      16: aload_0
      17: invokevirtual #19                 // Method drain:()V
      20: return

  public void cancel();
    Code:
       0: aload_0
       1: getfield      #9                  // Field disposables:Lio/reactivex/rxjava3/internal/disposables/SequentialDisposable;
       4: invokevirtual #20                 // Method io/reactivex/rxjava3/internal/disposables/SequentialDisposable.dispose:()V
       7: aload_0
       8: getfield      #16                 // Field errors:Lio/reactivex/rxjava3/internal/util/AtomicThrowable;
      11: invokevirtual #21                 // Method io/reactivex/rxjava3/internal/util/AtomicThrowable.tryTerminateAndReport:()V
      14: return

  public void onSubscribe(io.reactivex.rxjava3.disposables.Disposable);
    Code:
       0: aload_0
       1: getfield      #9                  // Field disposables:Lio/reactivex/rxjava3/internal/disposables/SequentialDisposable;
       4: aload_1
       5: invokevirtual #22                 // Method io/reactivex/rxjava3/internal/disposables/SequentialDisposable.replace:(Lio/reactivex/rxjava3/disposables/Disposable;)Z
       8: pop
       9: return

  public void onSuccess(T);
    Code:
       0: aload_0
       1: getfield      #13                 // Field current:Ljava/util/concurrent/atomic/AtomicReference;
       4: aload_1
       5: invokevirtual #23                 // Method java/util/concurrent/atomic/AtomicReference.lazySet:(Ljava/lang/Object;)V
       8: aload_0
       9: invokevirtual #19                 // Method drain:()V
      12: return

  public void onError(java.lang.Throwable);
    Code:
       0: aload_0
       1: getfield      #13                 // Field current:Ljava/util/concurrent/atomic/AtomicReference;
       4: getstatic     #11                 // Field io/reactivex/rxjava3/internal/util/NotificationLite.COMPLETE:Lio/reactivex/rxjava3/internal/util/NotificationLite;
       7: invokevirtual #23                 // Method java/util/concurrent/atomic/AtomicReference.lazySet:(Ljava/lang/Object;)V
      10: aload_0
      11: getfield      #16                 // Field errors:Lio/reactivex/rxjava3/internal/util/AtomicThrowable;
      14: aload_1
      15: invokevirtual #24                 // Method io/reactivex/rxjava3/internal/util/AtomicThrowable.tryAddThrowableOrReport:(Ljava/lang/Throwable;)Z
      18: ifeq          25
      21: aload_0
      22: invokevirtual #19                 // Method drain:()V
      25: return

  public void onComplete();
    Code:
       0: aload_0
       1: getfield      #13                 // Field current:Ljava/util/concurrent/atomic/AtomicReference;
       4: getstatic     #11                 // Field io/reactivex/rxjava3/internal/util/NotificationLite.COMPLETE:Lio/reactivex/rxjava3/internal/util/NotificationLite;
       7: invokevirtual #23                 // Method java/util/concurrent/atomic/AtomicReference.lazySet:(Ljava/lang/Object;)V
      10: aload_0
      11: invokevirtual #19                 // Method drain:()V
      14: return

  void drain();
    Code:
       0: aload_0
       1: invokevirtual #25                 // Method getAndIncrement:()I
       4: ifeq          8
       7: return
       8: aload_0
       9: getfield      #13                 // Field current:Ljava/util/concurrent/atomic/AtomicReference;
      12: astore_1
      13: aload_0
      14: getfield      #2                  // Field downstream:Lorg/reactivestreams/Subscriber;
      17: astore_2
      18: aload_0
      19: getfield      #9                  // Field disposables:Lio/reactivex/rxjava3/internal/disposables/SequentialDisposable;
      22: astore_3
      23: aload_3
      24: invokeinterface #26,  1           // InterfaceMethod io/reactivex/rxjava3/disposables/Disposable.isDisposed:()Z
      29: ifeq          38
      32: aload_1
      33: aconst_null
      34: invokevirtual #23                 // Method java/util/concurrent/atomic/AtomicReference.lazySet:(Ljava/lang/Object;)V
      37: return
      38: aload_1
      39: invokevirtual #27                 // Method java/util/concurrent/atomic/AtomicReference.get:()Ljava/lang/Object;
      42: astore        4
      44: aload         4
      46: ifnull        180
      49: aload         4
      51: getstatic     #11                 // Field io/reactivex/rxjava3/internal/util/NotificationLite.COMPLETE:Lio/reactivex/rxjava3/internal/util/NotificationLite;
      54: if_acmpeq     109
      57: aload_0
      58: getfield      #28                 // Field produced:J
      61: lstore        6
      63: lload         6
      65: aload_0
      66: getfield      #6                  // Field requested:Ljava/util/concurrent/atomic/AtomicLong;
      69: invokevirtual #29                 // Method java/util/concurrent/atomic/AtomicLong.get:()J
      72: lcmp
      73: ifeq          103
      76: aload_0
      77: lload         6
      79: lconst_1
      80: ladd
      81: putfield      #28                 // Field produced:J
      84: aload_1
      85: aconst_null
      86: invokevirtual #23                 // Method java/util/concurrent/atomic/AtomicReference.lazySet:(Ljava/lang/Object;)V
      89: iconst_1
      90: istore        5
      92: aload_2
      93: aload         4
      95: invokeinterface #30,  2           // InterfaceMethod org/reactivestreams/Subscriber.onNext:(Ljava/lang/Object;)V
     100: goto          106
     103: iconst_0
     104: istore        5
     106: goto          117
     109: iconst_1
     110: istore        5
     112: aload_1
     113: aconst_null
     114: invokevirtual #23                 // Method java/util/concurrent/atomic/AtomicReference.lazySet:(Ljava/lang/Object;)V
     117: iload         5
     119: ifeq          180
     122: aload_3
     123: invokeinterface #26,  1           // InterfaceMethod io/reactivex/rxjava3/disposables/Disposable.isDisposed:()Z
     128: ifne          180
     131: aload_0
     132: getfield      #31                 // Field index:I
     135: istore        6
     137: iload         6
     139: aload_0
     140: getfield      #3                  // Field sources:[Lio/reactivex/rxjava3/core/MaybeSource;
     143: arraylength
     144: if_icmpne     159
     147: aload_0
     148: getfield      #16                 // Field errors:Lio/reactivex/rxjava3/internal/util/AtomicThrowable;
     151: aload_0
     152: getfield      #2                  // Field downstream:Lorg/reactivestreams/Subscriber;
     155: invokevirtual #32                 // Method io/reactivex/rxjava3/internal/util/AtomicThrowable.tryTerminateConsumer:(Lorg/reactivestreams/Subscriber;)V
     158: return
     159: aload_0
     160: iload         6
     162: iconst_1
     163: iadd
     164: putfield      #31                 // Field index:I
     167: aload_0
     168: getfield      #3                  // Field sources:[Lio/reactivex/rxjava3/core/MaybeSource;
     171: iload         6
     173: aaload
     174: aload_0
     175: invokeinterface #33,  2           // InterfaceMethod io/reactivex/rxjava3/core/MaybeSource.subscribe:(Lio/reactivex/rxjava3/core/MaybeObserver;)V
     180: aload_0
     181: invokevirtual #34                 // Method decrementAndGet:()I
     184: ifne          190
     187: goto          193
     190: goto          23
     193: return
}
