Compiled from "MaybeDoOnLifecycle.java"
public final class io.reactivex.rxjava3.internal.operators.maybe.MaybeDoOnLifecycle<T> extends io.reactivex.rxjava3.internal.operators.maybe.AbstractMaybeWithUpstream<T, T> {
  final io.reactivex.rxjava3.functions.Consumer<? super io.reactivex.rxjava3.disposables.Disposable> onSubscribe;

  final io.reactivex.rxjava3.functions.Action onDispose;

  public io.reactivex.rxjava3.internal.operators.maybe.MaybeDoOnLifecycle(io.reactivex.rxjava3.core.Maybe<T>, io.reactivex.rxjava3.functions.Consumer<? super io.reactivex.rxjava3.disposables.Disposable>, io.reactivex.rxjava3.functions.Action);
    Code:
       0: aload_0
       1: aload_1
       2: invokespecial #1                  // Method io/reactivex/rxjava3/internal/operators/maybe/AbstractMaybeWithUpstream."<init>":(Lio/reactivex/rxjava3/core/MaybeSource;)V
       5: aload_0
       6: aload_2
       7: putfield      #2                  // Field onSubscribe:Lio/reactivex/rxjava3/functions/Consumer;
      10: aload_0
      11: aload_3
      12: putfield      #3                  // Field onDispose:Lio/reactivex/rxjava3/functions/Action;
      15: return

  protected void subscribeActual(io.reactivex.rxjava3.core.MaybeObserver<? super T>);
    Code:
       0: aload_0
       1: getfield      #4                  // Field source:Lio/reactivex/rxjava3/core/MaybeSource;
       4: new           #5                  // class io/reactivex/rxjava3/internal/operators/maybe/MaybeDoOnLifecycle$MaybeLifecycleObserver
       7: dup
       8: aload_1
       9: aload_0
      10: getfield      #2                  // Field onSubscribe:Lio/reactivex/rxjava3/functions/Consumer;
      13: aload_0
      14: getfield      #3                  // Field onDispose:Lio/reactivex/rxjava3/functions/Action;
      17: invokespecial #6                  // Method io/reactivex/rxjava3/internal/operators/maybe/MaybeDoOnLifecycle$MaybeLifecycleObserver."<init>":(Lio/reactivex/rxjava3/core/MaybeObserver;Lio/reactivex/rxjava3/functions/Consumer;Lio/reactivex/rxjava3/functions/Action;)V
      20: invokeinterface #7,  2            // InterfaceMethod io/reactivex/rxjava3/core/MaybeSource.subscribe:(Lio/reactivex/rxjava3/core/MaybeObserver;)V
      25: return
}
