Compiled from "MaybeFlatMapBiSelector.java"
final class io.reactivex.rxjava3.internal.operators.maybe.MaybeFlatMapBiSelector$FlatMapBiMainObserver$InnerObserver<T, U, R> extends java.util.concurrent.atomic.AtomicReference<io.reactivex.rxjava3.disposables.Disposable> implements io.reactivex.rxjava3.core.MaybeObserver<U> {
  private static final long serialVersionUID;

  final io.reactivex.rxjava3.core.MaybeObserver<? super R> downstream;

  final io.reactivex.rxjava3.functions.BiFunction<? super T, ? super U, ? extends R> resultSelector;

  T value;

  io.reactivex.rxjava3.internal.operators.maybe.MaybeFlatMapBiSelector$FlatMapBiMainObserver$InnerObserver(io.reactivex.rxjava3.core.MaybeObserver<? super R>, io.reactivex.rxjava3.functions.BiFunction<? super T, ? super U, ? extends R>);
    Code:
       0: aload_0
       1: invokespecial #1                  // Method java/util/concurrent/atomic/AtomicReference."<init>":()V
       4: aload_0
       5: aload_1
       6: putfield      #2                  // Field downstream:Lio/reactivex/rxjava3/core/MaybeObserver;
       9: aload_0
      10: aload_2
      11: putfield      #3                  // Field resultSelector:Lio/reactivex/rxjava3/functions/BiFunction;
      14: return

  public void onSubscribe(io.reactivex.rxjava3.disposables.Disposable);
    Code:
       0: aload_0
       1: aload_1
       2: invokestatic  #4                  // Method io/reactivex/rxjava3/internal/disposables/DisposableHelper.setOnce:(Ljava/util/concurrent/atomic/AtomicReference;Lio/reactivex/rxjava3/disposables/Disposable;)Z
       5: pop
       6: return

  public void onSuccess(U);
    Code:
       0: aload_0
       1: getfield      #5                  // Field value:Ljava/lang/Object;
       4: astore_2
       5: aload_0
       6: aconst_null
       7: putfield      #5                  // Field value:Ljava/lang/Object;
      10: aload_0
      11: getfield      #3                  // Field resultSelector:Lio/reactivex/rxjava3/functions/BiFunction;
      14: aload_2
      15: aload_1
      16: invokeinterface #6,  3            // InterfaceMethod io/reactivex/rxjava3/functions/BiFunction.apply:(Ljava/lang/Object;Ljava/lang/Object;)Ljava/lang/Object;
      21: ldc           #7                  // String The resultSelector returned a null value
      23: invokestatic  #8                  // Method java/util/Objects.requireNonNull:(Ljava/lang/Object;Ljava/lang/String;)Ljava/lang/Object;
      26: astore_3
      27: goto          49
      30: astore        4
      32: aload         4
      34: invokestatic  #10                 // Method io/reactivex/rxjava3/exceptions/Exceptions.throwIfFatal:(Ljava/lang/Throwable;)V
      37: aload_0
      38: getfield      #2                  // Field downstream:Lio/reactivex/rxjava3/core/MaybeObserver;
      41: aload         4
      43: invokeinterface #11,  2           // InterfaceMethod io/reactivex/rxjava3/core/MaybeObserver.onError:(Ljava/lang/Throwable;)V
      48: return
      49: aload_0
      50: getfield      #2                  // Field downstream:Lio/reactivex/rxjava3/core/MaybeObserver;
      53: aload_3
      54: invokeinterface #12,  2           // InterfaceMethod io/reactivex/rxjava3/core/MaybeObserver.onSuccess:(Ljava/lang/Object;)V
      59: return
    Exception table:
       from    to  target type
          10    27    30   Class java/lang/Throwable

  public void onError(java.lang.Throwable);
    Code:
       0: aload_0
       1: getfield      #2                  // Field downstream:Lio/reactivex/rxjava3/core/MaybeObserver;
       4: aload_1
       5: invokeinterface #11,  2           // InterfaceMethod io/reactivex/rxjava3/core/MaybeObserver.onError:(Ljava/lang/Throwable;)V
      10: return

  public void onComplete();
    Code:
       0: aload_0
       1: getfield      #2                  // Field downstream:Lio/reactivex/rxjava3/core/MaybeObserver;
       4: invokeinterface #13,  1           // InterfaceMethod io/reactivex/rxjava3/core/MaybeObserver.onComplete:()V
       9: return
}
