Compiled from "MaybeIsEmptySingle.java"
public final class io.reactivex.rxjava3.internal.operators.maybe.MaybeIsEmptySingle<T> extends io.reactivex.rxjava3.core.Single<java.lang.Boolean> implements io.reactivex.rxjava3.internal.fuseable.HasUpstreamMaybeSource<T>, io.reactivex.rxjava3.internal.fuseable.FuseToMaybe<java.lang.Boolean> {
  final io.reactivex.rxjava3.core.MaybeSource<T> source;

  public io.reactivex.rxjava3.internal.operators.maybe.MaybeIsEmptySingle(io.reactivex.rxjava3.core.MaybeSource<T>);
    Code:
       0: aload_0
       1: invokespecial #1                  // Method io/reactivex/rxjava3/core/Single."<init>":()V
       4: aload_0
       5: aload_1
       6: putfield      #2                  // Field source:Lio/reactivex/rxjava3/core/MaybeSource;
       9: return

  public io.reactivex.rxjava3.core.MaybeSource<T> source();
    Code:
       0: aload_0
       1: getfield      #2                  // Field source:Lio/reactivex/rxjava3/core/MaybeSource;
       4: areturn

  public io.reactivex.rxjava3.core.Maybe<java.lang.Boolean> fuseToMaybe();
    Code:
       0: new           #3                  // class io/reactivex/rxjava3/internal/operators/maybe/MaybeIsEmpty
       3: dup
       4: aload_0
       5: getfield      #2                  // Field source:Lio/reactivex/rxjava3/core/MaybeSource;
       8: invokespecial #4                  // Method io/reactivex/rxjava3/internal/operators/maybe/MaybeIsEmpty."<init>":(Lio/reactivex/rxjava3/core/MaybeSource;)V
      11: invokestatic  #5                  // Method io/reactivex/rxjava3/plugins/RxJavaPlugins.onAssembly:(Lio/reactivex/rxjava3/core/Maybe;)Lio/reactivex/rxjava3/core/Maybe;
      14: areturn

  protected void subscribeActual(io.reactivex.rxjava3.core.SingleObserver<? super java.lang.Boolean>);
    Code:
       0: aload_0
       1: getfield      #2                  // Field source:Lio/reactivex/rxjava3/core/MaybeSource;
       4: new           #6                  // class io/reactivex/rxjava3/internal/operators/maybe/MaybeIsEmptySingle$IsEmptyMaybeObserver
       7: dup
       8: aload_1
       9: invokespecial #7                  // Method io/reactivex/rxjava3/internal/operators/maybe/MaybeIsEmptySingle$IsEmptyMaybeObserver."<init>":(Lio/reactivex/rxjava3/core/SingleObserver;)V
      12: invokeinterface #8,  2            // InterfaceMethod io/reactivex/rxjava3/core/MaybeSource.subscribe:(Lio/reactivex/rxjava3/core/MaybeObserver;)V
      17: return
}
