Compiled from "MaybeFlatMapNotification.java"
final class io.reactivex.rxjava3.internal.operators.maybe.MaybeFlatMapNotification$FlatMapMaybeObserver$InnerObserver implements io.reactivex.rxjava3.core.MaybeObserver<R> {
  final io.reactivex.rxjava3.internal.operators.maybe.MaybeFlatMapNotification$FlatMapMaybeObserver this$0;

  io.reactivex.rxjava3.internal.operators.maybe.MaybeFlatMapNotification$FlatMapMaybeObserver$InnerObserver(io.reactivex.rxjava3.internal.operators.maybe.MaybeFlatMapNotification$FlatMapMaybeObserver);
    Code:
       0: aload_0
       1: aload_1
       2: putfield      #1                  // Field this$0:Lio/reactivex/rxjava3/internal/operators/maybe/MaybeFlatMapNotification$FlatMapMaybeObserver;
       5: aload_0
       6: invokespecial #2                  // Method java/lang/Object."<init>":()V
       9: return

  public void onSubscribe(io.reactivex.rxjava3.disposables.Disposable);
    Code:
       0: aload_0
       1: getfield      #1                  // Field this$0:Lio/reactivex/rxjava3/internal/operators/maybe/MaybeFlatMapNotification$FlatMapMaybeObserver;
       4: aload_1
       5: invokestatic  #3                  // Method io/reactivex/rxjava3/internal/disposables/DisposableHelper.setOnce:(Ljava/util/concurrent/atomic/AtomicReference;Lio/reactivex/rxjava3/disposables/Disposable;)Z
       8: pop
       9: return

  public void onSuccess(R);
    Code:
       0: aload_0
       1: getfield      #1                  // Field this$0:Lio/reactivex/rxjava3/internal/operators/maybe/MaybeFlatMapNotification$FlatMapMaybeObserver;
       4: getfield      #4                  // Field io/reactivex/rxjava3/internal/operators/maybe/MaybeFlatMapNotification$FlatMapMaybeObserver.downstream:Lio/reactivex/rxjava3/core/MaybeObserver;
       7: aload_1
       8: invokeinterface #5,  2            // InterfaceMethod io/reactivex/rxjava3/core/MaybeObserver.onSuccess:(Ljava/lang/Object;)V
      13: return

  public void onError(java.lang.Throwable);
    Code:
       0: aload_0
       1: getfield      #1                  // Field this$0:Lio/reactivex/rxjava3/internal/operators/maybe/MaybeFlatMapNotification$FlatMapMaybeObserver;
       4: getfield      #4                  // Field io/reactivex/rxjava3/internal/operators/maybe/MaybeFlatMapNotification$FlatMapMaybeObserver.downstream:Lio/reactivex/rxjava3/core/MaybeObserver;
       7: aload_1
       8: invokeinterface #6,  2            // InterfaceMethod io/reactivex/rxjava3/core/MaybeObserver.onError:(Ljava/lang/Throwable;)V
      13: return

  public void onComplete();
    Code:
       0: aload_0
       1: getfield      #1                  // Field this$0:Lio/reactivex/rxjava3/internal/operators/maybe/MaybeFlatMapNotification$FlatMapMaybeObserver;
       4: getfield      #4                  // Field io/reactivex/rxjava3/internal/operators/maybe/MaybeFlatMapNotification$FlatMapMaybeObserver.downstream:Lio/reactivex/rxjava3/core/MaybeObserver;
       7: invokeinterface #7,  1            // InterfaceMethod io/reactivex/rxjava3/core/MaybeObserver.onComplete:()V
      12: return
}
