Compiled from "MaybeTimeoutPublisher.java"
final class io.reactivex.rxjava3.internal.operators.maybe.MaybeTimeoutPublisher$TimeoutMainMaybeObserver<T, U> extends java.util.concurrent.atomic.AtomicReference<io.reactivex.rxjava3.disposables.Disposable> implements io.reactivex.rxjava3.core.MaybeObserver<T>, io.reactivex.rxjava3.disposables.Disposable {
  private static final long serialVersionUID;

  final io.reactivex.rxjava3.core.MaybeObserver<? super T> downstream;

  final io.reactivex.rxjava3.internal.operators.maybe.MaybeTimeoutPublisher$TimeoutOtherMaybeObserver<T, U> other;

  final io.reactivex.rxjava3.core.MaybeSource<? extends T> fallback;

  final io.reactivex.rxjava3.internal.operators.maybe.MaybeTimeoutPublisher$TimeoutFallbackMaybeObserver<T> otherObserver;

  io.reactivex.rxjava3.internal.operators.maybe.MaybeTimeoutPublisher$TimeoutMainMaybeObserver(io.reactivex.rxjava3.core.MaybeObserver<? super T>, io.reactivex.rxjava3.core.MaybeSource<? extends T>);
    Code:
       0: aload_0
       1: invokespecial #1                  // Method java/util/concurrent/atomic/AtomicReference."<init>":()V
       4: aload_0
       5: aload_1
       6: putfield      #2                  // Field downstream:Lio/reactivex/rxjava3/core/MaybeObserver;
       9: aload_0
      10: new           #3                  // class io/reactivex/rxjava3/internal/operators/maybe/MaybeTimeoutPublisher$TimeoutOtherMaybeObserver
      13: dup
      14: aload_0
      15: invokespecial #4                  // Method io/reactivex/rxjava3/internal/operators/maybe/MaybeTimeoutPublisher$TimeoutOtherMaybeObserver."<init>":(Lio/reactivex/rxjava3/internal/operators/maybe/MaybeTimeoutPublisher$TimeoutMainMaybeObserver;)V
      18: putfield      #5                  // Field other:Lio/reactivex/rxjava3/internal/operators/maybe/MaybeTimeoutPublisher$TimeoutOtherMaybeObserver;
      21: aload_0
      22: aload_2
      23: putfield      #6                  // Field fallback:Lio/reactivex/rxjava3/core/MaybeSource;
      26: aload_0
      27: aload_2
      28: ifnull        42
      31: new           #7                  // class io/reactivex/rxjava3/internal/operators/maybe/MaybeTimeoutPublisher$TimeoutFallbackMaybeObserver
      34: dup
      35: aload_1
      36: invokespecial #8                  // Method io/reactivex/rxjava3/internal/operators/maybe/MaybeTimeoutPublisher$TimeoutFallbackMaybeObserver."<init>":(Lio/reactivex/rxjava3/core/MaybeObserver;)V
      39: goto          43
      42: aconst_null
      43: putfield      #9                  // Field otherObserver:Lio/reactivex/rxjava3/internal/operators/maybe/MaybeTimeoutPublisher$TimeoutFallbackMaybeObserver;
      46: return

  public void dispose();
    Code:
       0: aload_0
       1: invokestatic  #10                 // Method io/reactivex/rxjava3/internal/disposables/DisposableHelper.dispose:(Ljava/util/concurrent/atomic/AtomicReference;)Z
       4: pop
       5: aload_0
       6: getfield      #5                  // Field other:Lio/reactivex/rxjava3/internal/operators/maybe/MaybeTimeoutPublisher$TimeoutOtherMaybeObserver;
       9: invokestatic  #11                 // Method io/reactivex/rxjava3/internal/subscriptions/SubscriptionHelper.cancel:(Ljava/util/concurrent/atomic/AtomicReference;)Z
      12: pop
      13: aload_0
      14: getfield      #9                  // Field otherObserver:Lio/reactivex/rxjava3/internal/operators/maybe/MaybeTimeoutPublisher$TimeoutFallbackMaybeObserver;
      17: astore_1
      18: aload_1
      19: ifnull        27
      22: aload_1
      23: invokestatic  #10                 // Method io/reactivex/rxjava3/internal/disposables/DisposableHelper.dispose:(Ljava/util/concurrent/atomic/AtomicReference;)Z
      26: pop
      27: return

  public boolean isDisposed();
    Code:
       0: aload_0
       1: invokevirtual #12                 // Method get:()Ljava/lang/Object;
       4: checkcast     #13                 // class io/reactivex/rxjava3/disposables/Disposable
       7: invokestatic  #14                 // Method io/reactivex/rxjava3/internal/disposables/DisposableHelper.isDisposed:(Lio/reactivex/rxjava3/disposables/Disposable;)Z
      10: ireturn

  public void onSubscribe(io.reactivex.rxjava3.disposables.Disposable);
    Code:
       0: aload_0
       1: aload_1
       2: invokestatic  #15                 // Method io/reactivex/rxjava3/internal/disposables/DisposableHelper.setOnce:(Ljava/util/concurrent/atomic/AtomicReference;Lio/reactivex/rxjava3/disposables/Disposable;)Z
       5: pop
       6: return

  public void onSuccess(T);
    Code:
       0: aload_0
       1: getfield      #5                  // Field other:Lio/reactivex/rxjava3/internal/operators/maybe/MaybeTimeoutPublisher$TimeoutOtherMaybeObserver;
       4: invokestatic  #11                 // Method io/reactivex/rxjava3/internal/subscriptions/SubscriptionHelper.cancel:(Ljava/util/concurrent/atomic/AtomicReference;)Z
       7: pop
       8: aload_0
       9: getstatic     #16                 // Field io/reactivex/rxjava3/internal/disposables/DisposableHelper.DISPOSED:Lio/reactivex/rxjava3/internal/disposables/DisposableHelper;
      12: invokevirtual #17                 // Method getAndSet:(Ljava/lang/Object;)Ljava/lang/Object;
      15: getstatic     #16                 // Field io/reactivex/rxjava3/internal/disposables/DisposableHelper.DISPOSED:Lio/reactivex/rxjava3/internal/disposables/DisposableHelper;
      18: if_acmpeq     31
      21: aload_0
      22: getfield      #2                  // Field downstream:Lio/reactivex/rxjava3/core/MaybeObserver;
      25: aload_1
      26: invokeinterface #18,  2           // InterfaceMethod io/reactivex/rxjava3/core/MaybeObserver.onSuccess:(Ljava/lang/Object;)V
      31: return

  public void onError(java.lang.Throwable);
    Code:
       0: aload_0
       1: getfield      #5                  // Field other:Lio/reactivex/rxjava3/internal/operators/maybe/MaybeTimeoutPublisher$TimeoutOtherMaybeObserver;
       4: invokestatic  #11                 // Method io/reactivex/rxjava3/internal/subscriptions/SubscriptionHelper.cancel:(Ljava/util/concurrent/atomic/AtomicReference;)Z
       7: pop
       8: aload_0
       9: getstatic     #16                 // Field io/reactivex/rxjava3/internal/disposables/DisposableHelper.DISPOSED:Lio/reactivex/rxjava3/internal/disposables/DisposableHelper;
      12: invokevirtual #17                 // Method getAndSet:(Ljava/lang/Object;)Ljava/lang/Object;
      15: getstatic     #16                 // Field io/reactivex/rxjava3/internal/disposables/DisposableHelper.DISPOSED:Lio/reactivex/rxjava3/internal/disposables/DisposableHelper;
      18: if_acmpeq     34
      21: aload_0
      22: getfield      #2                  // Field downstream:Lio/reactivex/rxjava3/core/MaybeObserver;
      25: aload_1
      26: invokeinterface #19,  2           // InterfaceMethod io/reactivex/rxjava3/core/MaybeObserver.onError:(Ljava/lang/Throwable;)V
      31: goto          38
      34: aload_1
      35: invokestatic  #20                 // Method io/reactivex/rxjava3/plugins/RxJavaPlugins.onError:(Ljava/lang/Throwable;)V
      38: return

  public void onComplete();
    Code:
       0: aload_0
       1: getfield      #5                  // Field other:Lio/reactivex/rxjava3/internal/operators/maybe/MaybeTimeoutPublisher$TimeoutOtherMaybeObserver;
       4: invokestatic  #11                 // Method io/reactivex/rxjava3/internal/subscriptions/SubscriptionHelper.cancel:(Ljava/util/concurrent/atomic/AtomicReference;)Z
       7: pop
       8: aload_0
       9: getstatic     #16                 // Field io/reactivex/rxjava3/internal/disposables/DisposableHelper.DISPOSED:Lio/reactivex/rxjava3/internal/disposables/DisposableHelper;
      12: invokevirtual #17                 // Method getAndSet:(Ljava/lang/Object;)Ljava/lang/Object;
      15: getstatic     #16                 // Field io/reactivex/rxjava3/internal/disposables/DisposableHelper.DISPOSED:Lio/reactivex/rxjava3/internal/disposables/DisposableHelper;
      18: if_acmpeq     30
      21: aload_0
      22: getfield      #2                  // Field downstream:Lio/reactivex/rxjava3/core/MaybeObserver;
      25: invokeinterface #21,  1           // InterfaceMethod io/reactivex/rxjava3/core/MaybeObserver.onComplete:()V
      30: return

  public void otherError(java.lang.Throwable);
    Code:
       0: aload_0
       1: invokestatic  #10                 // Method io/reactivex/rxjava3/internal/disposables/DisposableHelper.dispose:(Ljava/util/concurrent/atomic/AtomicReference;)Z
       4: ifeq          20
       7: aload_0
       8: getfield      #2                  // Field downstream:Lio/reactivex/rxjava3/core/MaybeObserver;
      11: aload_1
      12: invokeinterface #19,  2           // InterfaceMethod io/reactivex/rxjava3/core/MaybeObserver.onError:(Ljava/lang/Throwable;)V
      17: goto          24
      20: aload_1
      21: invokestatic  #20                 // Method io/reactivex/rxjava3/plugins/RxJavaPlugins.onError:(Ljava/lang/Throwable;)V
      24: return

  public void otherComplete();
    Code:
       0: aload_0
       1: invokestatic  #10                 // Method io/reactivex/rxjava3/internal/disposables/DisposableHelper.dispose:(Ljava/util/concurrent/atomic/AtomicReference;)Z
       4: ifeq          46
       7: aload_0
       8: getfield      #6                  // Field fallback:Lio/reactivex/rxjava3/core/MaybeSource;
      11: ifnonnull     33
      14: aload_0
      15: getfield      #2                  // Field downstream:Lio/reactivex/rxjava3/core/MaybeObserver;
      18: new           #22                 // class java/util/concurrent/TimeoutException
      21: dup
      22: invokespecial #23                 // Method java/util/concurrent/TimeoutException."<init>":()V
      25: invokeinterface #19,  2           // InterfaceMethod io/reactivex/rxjava3/core/MaybeObserver.onError:(Ljava/lang/Throwable;)V
      30: goto          46
      33: aload_0
      34: getfield      #6                  // Field fallback:Lio/reactivex/rxjava3/core/MaybeSource;
      37: aload_0
      38: getfield      #9                  // Field otherObserver:Lio/reactivex/rxjava3/internal/operators/maybe/MaybeTimeoutPublisher$TimeoutFallbackMaybeObserver;
      41: invokeinterface #24,  2           // InterfaceMethod io/reactivex/rxjava3/core/MaybeSource.subscribe:(Lio/reactivex/rxjava3/core/MaybeObserver;)V
      46: return
}
