Compiled from "MaybeDelay.java"
public final class io.reactivex.rxjava3.internal.operators.maybe.MaybeDelay<T> extends io.reactivex.rxjava3.internal.operators.maybe.AbstractMaybeWithUpstream<T, T> {
  final long delay;

  final java.util.concurrent.TimeUnit unit;

  final io.reactivex.rxjava3.core.Scheduler scheduler;

  final boolean delayError;

  public io.reactivex.rxjava3.internal.operators.maybe.MaybeDelay(io.reactivex.rxjava3.core.MaybeSource<T>, long, java.util.concurrent.TimeUnit, io.reactivex.rxjava3.core.Scheduler, boolean);
    Code:
       0: aload_0
       1: aload_1
       2: invokespecial #1                  // Method io/reactivex/rxjava3/internal/operators/maybe/AbstractMaybeWithUpstream."<init>":(Lio/reactivex/rxjava3/core/MaybeSource;)V
       5: aload_0
       6: lload_2
       7: putfield      #2                  // Field delay:J
      10: aload_0
      11: aload         4
      13: putfield      #3                  // Field unit:Ljava/util/concurrent/TimeUnit;
      16: aload_0
      17: aload         5
      19: putfield      #4                  // Field scheduler:Lio/reactivex/rxjava3/core/Scheduler;
      22: aload_0
      23: iload         6
      25: putfield      #5                  // Field delayError:Z
      28: return

  protected void subscribeActual(io.reactivex.rxjava3.core.MaybeObserver<? super T>);
    Code:
       0: aload_0
       1: getfield      #6                  // Field source:Lio/reactivex/rxjava3/core/MaybeSource;
       4: new           #7                  // class io/reactivex/rxjava3/internal/operators/maybe/MaybeDelay$DelayMaybeObserver
       7: dup
       8: aload_1
       9: aload_0
      10: getfield      #2                  // Field delay:J
      13: aload_0
      14: getfield      #3                  // Field unit:Ljava/util/concurrent/TimeUnit;
      17: aload_0
      18: getfield      #4                  // Field scheduler:Lio/reactivex/rxjava3/core/Scheduler;
      21: aload_0
      22: getfield      #5                  // Field delayError:Z
      25: invokespecial #8                  // Method io/reactivex/rxjava3/internal/operators/maybe/MaybeDelay$DelayMaybeObserver."<init>":(Lio/reactivex/rxjava3/core/MaybeObserver;JLjava/util/concurrent/TimeUnit;Lio/reactivex/rxjava3/core/Scheduler;Z)V
      28: invokeinterface #9,  2            // InterfaceMethod io/reactivex/rxjava3/core/MaybeSource.subscribe:(Lio/reactivex/rxjava3/core/MaybeObserver;)V
      33: return
}
