Compiled from "MaybeToPublisher.java"
public final class io.reactivex.rxjava3.internal.operators.maybe.MaybeToPublisher extends java.lang.Enum<io.reactivex.rxjava3.internal.operators.maybe.MaybeToPublisher> implements io.reactivex.rxjava3.functions.Function<io.reactivex.rxjava3.core.MaybeSource<java.lang.Object>, org.reactivestreams.Publisher<java.lang.Object>> {
  public static final io.reactivex.rxjava3.internal.operators.maybe.MaybeToPublisher INSTANCE;

  private static final io.reactivex.rxjava3.internal.operators.maybe.MaybeToPublisher[] $VALUES;

  public static io.reactivex.rxjava3.internal.operators.maybe.MaybeToPublisher[] values();
    Code:
       0: getstatic     #1                  // Field $VALUES:[Lio/reactivex/rxjava3/internal/operators/maybe/MaybeToPublisher;
       3: invokevirtual #2                  // Method "[Lio/reactivex/rxjava3/internal/operators/maybe/MaybeToPublisher;".clone:()Ljava/lang/Object;
       6: checkcast     #3                  // class "[Lio/reactivex/rxjava3/internal/operators/maybe/MaybeToPublisher;"
       9: areturn

  public static io.reactivex.rxjava3.internal.operators.maybe.MaybeToPublisher valueOf(java.lang.String);
    Code:
       0: ldc           #4                  // class io/reactivex/rxjava3/internal/operators/maybe/MaybeToPublisher
       2: aload_0
       3: invokestatic  #5                  // Method java/lang/Enum.valueOf:(Ljava/lang/Class;Ljava/lang/String;)Ljava/lang/Enum;
       6: checkcast     #4                  // class io/reactivex/rxjava3/internal/operators/maybe/MaybeToPublisher
       9: areturn

  private io.reactivex.rxjava3.internal.operators.maybe.MaybeToPublisher();
    Code:
       0: aload_0
       1: aload_1
       2: iload_2
       3: invokespecial #6                  // Method java/lang/Enum."<init>":(Ljava/lang/String;I)V
       6: return

  public static <T> io.reactivex.rxjava3.functions.Function<io.reactivex.rxjava3.core.MaybeSource<T>, org.reactivestreams.Publisher<T>> instance();
    Code:
       0: getstatic     #7                  // Field INSTANCE:Lio/reactivex/rxjava3/internal/operators/maybe/MaybeToPublisher;
       3: areturn

  public org.reactivestreams.Publisher<java.lang.Object> apply(io.reactivex.rxjava3.core.MaybeSource<java.lang.Object>);
    Code:
       0: new           #8                  // class io/reactivex/rxjava3/internal/operators/maybe/MaybeToFlowable
       3: dup
       4: aload_1
       5: invokespecial #9                  // Method io/reactivex/rxjava3/internal/operators/maybe/MaybeToFlowable."<init>":(Lio/reactivex/rxjava3/core/MaybeSource;)V
       8: areturn

  public java.lang.Object apply(java.lang.Object) throws java.lang.Throwable;
    Code:
       0: aload_0
       1: aload_1
       2: checkcast     #10                 // class io/reactivex/rxjava3/core/MaybeSource
       5: invokevirtual #11                 // Method apply:(Lio/reactivex/rxjava3/core/MaybeSource;)Lorg/reactivestreams/Publisher;
       8: areturn

  static {};
    Code:
       0: new           #4                  // class io/reactivex/rxjava3/internal/operators/maybe/MaybeToPublisher
       3: dup
       4: ldc           #12                 // String INSTANCE
       6: iconst_0
       7: invokespecial #13                 // Method "<init>":(Ljava/lang/String;I)V
      10: putstatic     #7                  // Field INSTANCE:Lio/reactivex/rxjava3/internal/operators/maybe/MaybeToPublisher;
      13: iconst_1
      14: anewarray     #4                  // class io/reactivex/rxjava3/internal/operators/maybe/MaybeToPublisher
      17: dup
      18: iconst_0
      19: getstatic     #7                  // Field INSTANCE:Lio/reactivex/rxjava3/internal/operators/maybe/MaybeToPublisher;
      22: aastore
      23: putstatic     #1                  // Field $VALUES:[Lio/reactivex/rxjava3/internal/operators/maybe/MaybeToPublisher;
      26: return
}
