Compiled from "MaybeSubscribeOn.java"
final class io.reactivex.rxjava3.internal.operators.maybe.MaybeSubscribeOn$SubscribeTask<T> implements java.lang.Runnable {
  final io.reactivex.rxjava3.core.MaybeObserver<? super T> observer;

  final io.reactivex.rxjava3.core.MaybeSource<T> source;

  io.reactivex.rxjava3.internal.operators.maybe.MaybeSubscribeOn$SubscribeTask(io.reactivex.rxjava3.core.MaybeObserver<? super T>, io.reactivex.rxjava3.core.MaybeSource<T>);
    Code:
       0: aload_0
       1: invokespecial #1                  // Method java/lang/Object."<init>":()V
       4: aload_0
       5: aload_1
       6: putfield      #2                  // Field observer:Lio/reactivex/rxjava3/core/MaybeObserver;
       9: aload_0
      10: aload_2
      11: putfield      #3                  // Field source:Lio/reactivex/rxjava3/core/MaybeSource;
      14: return

  public void run();
    Code:
       0: aload_0
       1: getfield      #3                  // Field source:Lio/reactivex/rxjava3/core/MaybeSource;
       4: aload_0
       5: getfield      #2                  // Field observer:Lio/reactivex/rxjava3/core/MaybeObserver;
       8: invokeinterface #4,  2            // InterfaceMethod io/reactivex/rxjava3/core/MaybeSource.subscribe:(Lio/reactivex/rxjava3/core/MaybeObserver;)V
      13: return
}
