Compiled from "MaybeConcatIterable.java"
public final class io.reactivex.rxjava3.internal.operators.maybe.MaybeConcatIterable<T> extends io.reactivex.rxjava3.core.Flowable<T> {
  final java.lang.Iterable<? extends io.reactivex.rxjava3.core.MaybeSource<? extends T>> sources;

  public io.reactivex.rxjava3.internal.operators.maybe.MaybeConcatIterable(java.lang.Iterable<? extends io.reactivex.rxjava3.core.MaybeSource<? extends T>>);
    Code:
       0: aload_0
       1: invokespecial #1                  // Method io/reactivex/rxjava3/core/Flowable."<init>":()V
       4: aload_0
       5: aload_1
       6: putfield      #2                  // Field sources:Ljava/lang/Iterable;
       9: return

  protected void subscribeActual(org.reactivestreams.Subscriber<? super T>);
    Code:
       0: aload_0
       1: getfield      #2                  // Field sources:Ljava/lang/Iterable;
       4: invokeinterface #3,  1            // InterfaceMethod java/lang/Iterable.iterator:()Ljava/util/Iterator;
       9: ldc           #4                  // String The sources Iterable returned a null Iterator
      11: invokestatic  #5                  // Method java/util/Objects.requireNonNull:(Ljava/lang/Object;Ljava/lang/String;)Ljava/lang/Object;
      14: checkcast     #6                  // class java/util/Iterator
      17: astore_2
      18: goto          32
      21: astore_3
      22: aload_3
      23: invokestatic  #8                  // Method io/reactivex/rxjava3/exceptions/Exceptions.throwIfFatal:(Ljava/lang/Throwable;)V
      26: aload_3
      27: aload_1
      28: invokestatic  #9                  // Method io/reactivex/rxjava3/internal/subscriptions/EmptySubscription.error:(Ljava/lang/Throwable;Lorg/reactivestreams/Subscriber;)V
      31: return
      32: new           #10                 // class io/reactivex/rxjava3/internal/operators/maybe/MaybeConcatIterable$ConcatMaybeObserver
      35: dup
      36: aload_1
      37: aload_2
      38: invokespecial #11                 // Method io/reactivex/rxjava3/internal/operators/maybe/MaybeConcatIterable$ConcatMaybeObserver."<init>":(Lorg/reactivestreams/Subscriber;Ljava/util/Iterator;)V
      41: astore_3
      42: aload_1
      43: aload_3
      44: invokeinterface #12,  2           // InterfaceMethod org/reactivestreams/Subscriber.onSubscribe:(Lorg/reactivestreams/Subscription;)V
      49: aload_3
      50: invokevirtual #13                 // Method io/reactivex/rxjava3/internal/operators/maybe/MaybeConcatIterable$ConcatMaybeObserver.drain:()V
      53: return
    Exception table:
       from    to  target type
           0    18    21   Class java/lang/Throwable
}
