Compiled from "MaybeEqualSingle.java"
public final class io.reactivex.rxjava3.internal.operators.maybe.MaybeEqualSingle<T> extends io.reactivex.rxjava3.core.Single<java.lang.Boolean> {
  final io.reactivex.rxjava3.core.MaybeSource<? extends T> source1;

  final io.reactivex.rxjava3.core.MaybeSource<? extends T> source2;

  final io.reactivex.rxjava3.functions.BiPredicate<? super T, ? super T> isEqual;

  public io.reactivex.rxjava3.internal.operators.maybe.MaybeEqualSingle(io.reactivex.rxjava3.core.MaybeSource<? extends T>, io.reactivex.rxjava3.core.MaybeSource<? extends T>, io.reactivex.rxjava3.functions.BiPredicate<? super T, ? super T>);
    Code:
       0: aload_0
       1: invokespecial #1                  // Method io/reactivex/rxjava3/core/Single."<init>":()V
       4: aload_0
       5: aload_1
       6: putfield      #2                  // Field source1:Lio/reactivex/rxjava3/core/MaybeSource;
       9: aload_0
      10: aload_2
      11: putfield      #3                  // Field source2:Lio/reactivex/rxjava3/core/MaybeSource;
      14: aload_0
      15: aload_3
      16: putfield      #4                  // Field isEqual:Lio/reactivex/rxjava3/functions/BiPredicate;
      19: return

  protected void subscribeActual(io.reactivex.rxjava3.core.SingleObserver<? super java.lang.Boolean>);
    Code:
       0: new           #5                  // class io/reactivex/rxjava3/internal/operators/maybe/MaybeEqualSingle$EqualCoordinator
       3: dup
       4: aload_1
       5: aload_0
       6: getfield      #4                  // Field isEqual:Lio/reactivex/rxjava3/functions/BiPredicate;
       9: invokespecial #6                  // Method io/reactivex/rxjava3/internal/operators/maybe/MaybeEqualSingle$EqualCoordinator."<init>":(Lio/reactivex/rxjava3/core/SingleObserver;Lio/reactivex/rxjava3/functions/BiPredicate;)V
      12: astore_2
      13: aload_1
      14: aload_2
      15: invokeinterface #7,  2            // InterfaceMethod io/reactivex/rxjava3/core/SingleObserver.onSubscribe:(Lio/reactivex/rxjava3/disposables/Disposable;)V
      20: aload_2
      21: aload_0
      22: getfield      #2                  // Field source1:Lio/reactivex/rxjava3/core/MaybeSource;
      25: aload_0
      26: getfield      #3                  // Field source2:Lio/reactivex/rxjava3/core/MaybeSource;
      29: invokevirtual #8                  // Method io/reactivex/rxjava3/internal/operators/maybe/MaybeEqualSingle$EqualCoordinator.subscribe:(Lio/reactivex/rxjava3/core/MaybeSource;Lio/reactivex/rxjava3/core/MaybeSource;)V
      32: return
}
