Compiled from "MaybeZipArray.java"
public final class io.reactivex.rxjava3.internal.operators.maybe.MaybeZipArray<T, R> extends io.reactivex.rxjava3.core.Maybe<R> {
  final io.reactivex.rxjava3.core.MaybeSource<? extends T>[] sources;

  final io.reactivex.rxjava3.functions.Function<? super java.lang.Object[], ? extends R> zipper;

  public io.reactivex.rxjava3.internal.operators.maybe.MaybeZipArray(io.reactivex.rxjava3.core.MaybeSource<? extends T>[], io.reactivex.rxjava3.functions.Function<? super java.lang.Object[], ? extends R>);
    Code:
       0: aload_0
       1: invokespecial #1                  // Method io/reactivex/rxjava3/core/Maybe."<init>":()V
       4: aload_0
       5: aload_1
       6: putfield      #2                  // Field sources:[Lio/reactivex/rxjava3/core/MaybeSource;
       9: aload_0
      10: aload_2
      11: putfield      #3                  // Field zipper:Lio/reactivex/rxjava3/functions/Function;
      14: return

  protected void subscribeActual(io.reactivex.rxjava3.core.MaybeObserver<? super R>);
    Code:
       0: aload_0
       1: getfield      #2                  // Field sources:[Lio/reactivex/rxjava3/core/MaybeSource;
       4: astore_2
       5: aload_2
       6: arraylength
       7: istore_3
       8: iload_3
       9: iconst_1
      10: if_icmpne     38
      13: aload_2
      14: iconst_0
      15: aaload
      16: new           #4                  // class io/reactivex/rxjava3/internal/operators/maybe/MaybeMap$MapMaybeObserver
      19: dup
      20: aload_1
      21: new           #5                  // class io/reactivex/rxjava3/internal/operators/maybe/MaybeZipArray$SingletonArrayFunc
      24: dup
      25: aload_0
      26: invokespecial #6                  // Method io/reactivex/rxjava3/internal/operators/maybe/MaybeZipArray$SingletonArrayFunc."<init>":(Lio/reactivex/rxjava3/internal/operators/maybe/MaybeZipArray;)V
      29: invokespecial #7                  // Method io/reactivex/rxjava3/internal/operators/maybe/MaybeMap$MapMaybeObserver."<init>":(Lio/reactivex/rxjava3/core/MaybeObserver;Lio/reactivex/rxjava3/functions/Function;)V
      32: invokeinterface #8,  2            // InterfaceMethod io/reactivex/rxjava3/core/MaybeSource.subscribe:(Lio/reactivex/rxjava3/core/MaybeObserver;)V
      37: return
      38: new           #9                  // class io/reactivex/rxjava3/internal/operators/maybe/MaybeZipArray$ZipCoordinator
      41: dup
      42: aload_1
      43: iload_3
      44: aload_0
      45: getfield      #3                  // Field zipper:Lio/reactivex/rxjava3/functions/Function;
      48: invokespecial #10                 // Method io/reactivex/rxjava3/internal/operators/maybe/MaybeZipArray$ZipCoordinator."<init>":(Lio/reactivex/rxjava3/core/MaybeObserver;ILio/reactivex/rxjava3/functions/Function;)V
      51: astore        4
      53: aload_1
      54: aload         4
      56: invokeinterface #11,  2           // InterfaceMethod io/reactivex/rxjava3/core/MaybeObserver.onSubscribe:(Lio/reactivex/rxjava3/disposables/Disposable;)V
      61: iconst_0
      62: istore        5
      64: iload         5
      66: iload_3
      67: if_icmpge     128
      70: aload         4
      72: invokevirtual #12                 // Method io/reactivex/rxjava3/internal/operators/maybe/MaybeZipArray$ZipCoordinator.isDisposed:()Z
      75: ifeq          79
      78: return
      79: aload_2
      80: iload         5
      82: aaload
      83: astore        6
      85: aload         6
      87: ifnonnull     107
      90: aload         4
      92: new           #13                 // class java/lang/NullPointerException
      95: dup
      96: ldc           #14                 // String One of the sources is null
      98: invokespecial #15                 // Method java/lang/NullPointerException."<init>":(Ljava/lang/String;)V
     101: iload         5
     103: invokevirtual #16                 // Method io/reactivex/rxjava3/internal/operators/maybe/MaybeZipArray$ZipCoordinator.innerError:(Ljava/lang/Throwable;I)V
     106: return
     107: aload         6
     109: aload         4
     111: getfield      #17                 // Field io/reactivex/rxjava3/internal/operators/maybe/MaybeZipArray$ZipCoordinator.observers:[Lio/reactivex/rxjava3/internal/operators/maybe/MaybeZipArray$ZipMaybeObserver;
     114: iload         5
     116: aaload
     117: invokeinterface #8,  2            // InterfaceMethod io/reactivex/rxjava3/core/MaybeSource.subscribe:(Lio/reactivex/rxjava3/core/MaybeObserver;)V
     122: iinc          5, 1
     125: goto          64
     128: return
}
