Compiled from "MaybeFromFuture.java"
public final class io.reactivex.rxjava3.internal.operators.maybe.MaybeFromFuture<T> extends io.reactivex.rxjava3.core.Maybe<T> {
  final java.util.concurrent.Future<? extends T> future;

  final long timeout;

  final java.util.concurrent.TimeUnit unit;

  public io.reactivex.rxjava3.internal.operators.maybe.MaybeFromFuture(java.util.concurrent.Future<? extends T>, long, java.util.concurrent.TimeUnit);
    Code:
       0: aload_0
       1: invokespecial #1                  // Method io/reactivex/rxjava3/core/Maybe."<init>":()V
       4: aload_0
       5: aload_1
       6: putfield      #2                  // Field future:Ljava/util/concurrent/Future;
       9: aload_0
      10: lload_2
      11: putfield      #3                  // Field timeout:J
      14: aload_0
      15: aload         4
      17: putfield      #4                  // Field unit:Ljava/util/concurrent/TimeUnit;
      20: return

  protected void subscribeActual(io.reactivex.rxjava3.core.MaybeObserver<? super T>);
    Code:
       0: invokestatic  #5                  // InterfaceMethod io/reactivex/rxjava3/disposables/Disposable.empty:()Lio/reactivex/rxjava3/disposables/Disposable;
       3: astore_2
       4: aload_1
       5: aload_2
       6: invokeinterface #6,  2            // InterfaceMethod io/reactivex/rxjava3/core/MaybeObserver.onSubscribe:(Lio/reactivex/rxjava3/disposables/Disposable;)V
      11: aload_2
      12: invokeinterface #7,  1            // InterfaceMethod io/reactivex/rxjava3/disposables/Disposable.isDisposed:()Z
      17: ifne          137
      20: aload_0
      21: getfield      #3                  // Field timeout:J
      24: lconst_0
      25: lcmp
      26: ifgt          42
      29: aload_0
      30: getfield      #2                  // Field future:Ljava/util/concurrent/Future;
      33: invokeinterface #8,  1            // InterfaceMethod java/util/concurrent/Future.get:()Ljava/lang/Object;
      38: astore_3
      39: goto          60
      42: aload_0
      43: getfield      #2                  // Field future:Ljava/util/concurrent/Future;
      46: aload_0
      47: getfield      #3                  // Field timeout:J
      50: aload_0
      51: getfield      #4                  // Field unit:Ljava/util/concurrent/TimeUnit;
      54: invokeinterface #9,  4            // InterfaceMethod java/util/concurrent/Future.get:(JLjava/util/concurrent/TimeUnit;)Ljava/lang/Object;
      59: astore_3
      60: goto          108
      63: astore        4
      65: aload         4
      67: invokestatic  #11                 // Method io/reactivex/rxjava3/exceptions/Exceptions.throwIfFatal:(Ljava/lang/Throwable;)V
      70: aload         4
      72: instanceof    #12                 // class java/util/concurrent/ExecutionException
      75: ifeq          85
      78: aload         4
      80: invokevirtual #13                 // Method java/lang/Throwable.getCause:()Ljava/lang/Throwable;
      83: astore        4
      85: aload         4
      87: invokestatic  #11                 // Method io/reactivex/rxjava3/exceptions/Exceptions.throwIfFatal:(Ljava/lang/Throwable;)V
      90: aload_2
      91: invokeinterface #7,  1            // InterfaceMethod io/reactivex/rxjava3/disposables/Disposable.isDisposed:()Z
      96: ifne          107
      99: aload_1
     100: aload         4
     102: invokeinterface #14,  2           // InterfaceMethod io/reactivex/rxjava3/core/MaybeObserver.onError:(Ljava/lang/Throwable;)V
     107: return
     108: aload_2
     109: invokeinterface #7,  1            // InterfaceMethod io/reactivex/rxjava3/disposables/Disposable.isDisposed:()Z
     114: ifne          137
     117: aload_3
     118: ifnonnull     130
     121: aload_1
     122: invokeinterface #15,  1           // InterfaceMethod io/reactivex/rxjava3/core/MaybeObserver.onComplete:()V
     127: goto          137
     130: aload_1
     131: aload_3
     132: invokeinterface #16,  2           // InterfaceMethod io/reactivex/rxjava3/core/MaybeObserver.onSuccess:(Ljava/lang/Object;)V
     137: return
    Exception table:
       from    to  target type
          20    60    63   Class java/lang/Throwable
}
