Compiled from "MaybeMergeArray.java"
public final class io.reactivex.rxjava3.internal.operators.maybe.MaybeMergeArray<T> extends io.reactivex.rxjava3.core.Flowable<T> {
  final io.reactivex.rxjava3.core.MaybeSource<? extends T>[] sources;

  public io.reactivex.rxjava3.internal.operators.maybe.MaybeMergeArray(io.reactivex.rxjava3.core.MaybeSource<? extends T>[]);
    Code:
       0: aload_0
       1: invokespecial #1                  // Method io/reactivex/rxjava3/core/Flowable."<init>":()V
       4: aload_0
       5: aload_1
       6: putfield      #2                  // Field sources:[Lio/reactivex/rxjava3/core/MaybeSource;
       9: return

  protected void subscribeActual(org.reactivestreams.Subscriber<? super T>);
    Code:
       0: aload_0
       1: getfield      #2                  // Field sources:[Lio/reactivex/rxjava3/core/MaybeSource;
       4: astore_2
       5: aload_2
       6: arraylength
       7: istore_3
       8: iload_3
       9: invokestatic  #3                  // Method bufferSize:()I
      12: if_icmpgt     28
      15: new           #4                  // class io/reactivex/rxjava3/internal/operators/maybe/MaybeMergeArray$MpscFillOnceSimpleQueue
      18: dup
      19: iload_3
      20: invokespecial #5                  // Method io/reactivex/rxjava3/internal/operators/maybe/MaybeMergeArray$MpscFillOnceSimpleQueue."<init>":(I)V
      23: astore        4
      25: goto          37
      28: new           #6                  // class io/reactivex/rxjava3/internal/operators/maybe/MaybeMergeArray$ClqSimpleQueue
      31: dup
      32: invokespecial #7                  // Method io/reactivex/rxjava3/internal/operators/maybe/MaybeMergeArray$ClqSimpleQueue."<init>":()V
      35: astore        4
      37: new           #8                  // class io/reactivex/rxjava3/internal/operators/maybe/MaybeMergeArray$MergeMaybeObserver
      40: dup
      41: aload_1
      42: iload_3
      43: aload         4
      45: invokespecial #9                  // Method io/reactivex/rxjava3/internal/operators/maybe/MaybeMergeArray$MergeMaybeObserver."<init>":(Lorg/reactivestreams/Subscriber;ILio/reactivex/rxjava3/internal/operators/maybe/MaybeMergeArray$SimpleQueueWithConsumerIndex;)V
      48: astore        5
      50: aload_1
      51: aload         5
      53: invokeinterface #10,  2           // InterfaceMethod org/reactivestreams/Subscriber.onSubscribe:(Lorg/reactivestreams/Subscription;)V
      58: aload         5
      60: getfield      #11                 // Field io/reactivex/rxjava3/internal/operators/maybe/MaybeMergeArray$MergeMaybeObserver.errors:Lio/reactivex/rxjava3/internal/util/AtomicThrowable;
      63: astore        6
      65: aload_2
      66: astore        7
      68: aload         7
      70: arraylength
      71: istore        8
      73: iconst_0
      74: istore        9
      76: iload         9
      78: iload         8
      80: if_icmpge     122
      83: aload         7
      85: iload         9
      87: aaload
      88: astore        10
      90: aload         5
      92: invokevirtual #12                 // Method io/reactivex/rxjava3/internal/operators/maybe/MaybeMergeArray$MergeMaybeObserver.isCancelled:()Z
      95: ifne          106
      98: aload         6
     100: invokevirtual #13                 // Method io/reactivex/rxjava3/internal/util/AtomicThrowable.get:()Ljava/lang/Object;
     103: ifnull        107
     106: return
     107: aload         10
     109: aload         5
     111: invokeinterface #14,  2           // InterfaceMethod io/reactivex/rxjava3/core/MaybeSource.subscribe:(Lio/reactivex/rxjava3/core/MaybeObserver;)V
     116: iinc          9, 1
     119: goto          76
     122: return
}
