Compiled from "MaybePeek.java"
public final class io.reactivex.rxjava3.internal.operators.maybe.MaybePeek<T> extends io.reactivex.rxjava3.internal.operators.maybe.AbstractMaybeWithUpstream<T, T> {
  final io.reactivex.rxjava3.functions.Consumer<? super io.reactivex.rxjava3.disposables.Disposable> onSubscribeCall;

  final io.reactivex.rxjava3.functions.Consumer<? super T> onSuccessCall;

  final io.reactivex.rxjava3.functions.Consumer<? super java.lang.Throwable> onErrorCall;

  final io.reactivex.rxjava3.functions.Action onCompleteCall;

  final io.reactivex.rxjava3.functions.Action onAfterTerminate;

  final io.reactivex.rxjava3.functions.Action onDisposeCall;

  public io.reactivex.rxjava3.internal.operators.maybe.MaybePeek(io.reactivex.rxjava3.core.MaybeSource<T>, io.reactivex.rxjava3.functions.Consumer<? super io.reactivex.rxjava3.disposables.Disposable>, io.reactivex.rxjava3.functions.Consumer<? super T>, io.reactivex.rxjava3.functions.Consumer<? super java.lang.Throwable>, io.reactivex.rxjava3.functions.Action, io.reactivex.rxjava3.functions.Action, io.reactivex.rxjava3.functions.Action);
    Code:
       0: aload_0
       1: aload_1
       2: invokespecial #1                  // Method io/reactivex/rxjava3/internal/operators/maybe/AbstractMaybeWithUpstream."<init>":(Lio/reactivex/rxjava3/core/MaybeSource;)V
       5: aload_0
       6: aload_2
       7: putfield      #2                  // Field onSubscribeCall:Lio/reactivex/rxjava3/functions/Consumer;
      10: aload_0
      11: aload_3
      12: putfield      #3                  // Field onSuccessCall:Lio/reactivex/rxjava3/functions/Consumer;
      15: aload_0
      16: aload         4
      18: putfield      #4                  // Field onErrorCall:Lio/reactivex/rxjava3/functions/Consumer;
      21: aload_0
      22: aload         5
      24: putfield      #5                  // Field onCompleteCall:Lio/reactivex/rxjava3/functions/Action;
      27: aload_0
      28: aload         6
      30: putfield      #6                  // Field onAfterTerminate:Lio/reactivex/rxjava3/functions/Action;
      33: aload_0
      34: aload         7
      36: putfield      #7                  // Field onDisposeCall:Lio/reactivex/rxjava3/functions/Action;
      39: return

  protected void subscribeActual(io.reactivex.rxjava3.core.MaybeObserver<? super T>);
    Code:
       0: aload_0
       1: getfield      #8                  // Field source:Lio/reactivex/rxjava3/core/MaybeSource;
       4: new           #9                  // class io/reactivex/rxjava3/internal/operators/maybe/MaybePeek$MaybePeekObserver
       7: dup
       8: aload_1
       9: aload_0
      10: invokespecial #10                 // Method io/reactivex/rxjava3/internal/operators/maybe/MaybePeek$MaybePeekObserver."<init>":(Lio/reactivex/rxjava3/core/MaybeObserver;Lio/reactivex/rxjava3/internal/operators/maybe/MaybePeek;)V
      13: invokeinterface #11,  2           // InterfaceMethod io/reactivex/rxjava3/core/MaybeSource.subscribe:(Lio/reactivex/rxjava3/core/MaybeObserver;)V
      18: return
}
