Compiled from "MaybeToObservable.java"
public final class io.reactivex.rxjava3.internal.operators.maybe.MaybeToObservable<T> extends io.reactivex.rxjava3.core.Observable<T> implements io.reactivex.rxjava3.internal.fuseable.HasUpstreamMaybeSource<T> {
  final io.reactivex.rxjava3.core.MaybeSource<T> source;

  public io.reactivex.rxjava3.internal.operators.maybe.MaybeToObservable(io.reactivex.rxjava3.core.MaybeSource<T>);
    Code:
       0: aload_0
       1: invokespecial #1                  // Method io/reactivex/rxjava3/core/Observable."<init>":()V
       4: aload_0
       5: aload_1
       6: putfield      #2                  // Field source:Lio/reactivex/rxjava3/core/MaybeSource;
       9: return

  public io.reactivex.rxjava3.core.MaybeSource<T> source();
    Code:
       0: aload_0
       1: getfield      #2                  // Field source:Lio/reactivex/rxjava3/core/MaybeSource;
       4: areturn

  protected void subscribeActual(io.reactivex.rxjava3.core.Observer<? super T>);
    Code:
       0: aload_0
       1: getfield      #2                  // Field source:Lio/reactivex/rxjava3/core/MaybeSource;
       4: aload_1
       5: invokestatic  #3                  // Method create:(Lio/reactivex/rxjava3/core/Observer;)Lio/reactivex/rxjava3/core/MaybeObserver;
       8: invokeinterface #4,  2            // InterfaceMethod io/reactivex/rxjava3/core/MaybeSource.subscribe:(Lio/reactivex/rxjava3/core/MaybeObserver;)V
      13: return

  public static <T> io.reactivex.rxjava3.core.MaybeObserver<T> create(io.reactivex.rxjava3.core.Observer<? super T>);
    Code:
       0: new           #5                  // class io/reactivex/rxjava3/internal/operators/maybe/MaybeToObservable$MaybeToObservableObserver
       3: dup
       4: aload_0
       5: invokespecial #6                  // Method io/reactivex/rxjava3/internal/operators/maybe/MaybeToObservable$MaybeToObservableObserver."<init>":(Lio/reactivex/rxjava3/core/Observer;)V
       8: areturn
}
