Compiled from "MaybeUnsafeCreate.java"
public final class io.reactivex.rxjava3.internal.operators.maybe.MaybeUnsafeCreate<T> extends io.reactivex.rxjava3.internal.operators.maybe.AbstractMaybeWithUpstream<T, T> {
  public io.reactivex.rxjava3.internal.operators.maybe.MaybeUnsafeCreate(io.reactivex.rxjava3.core.MaybeSource<T>);
    Code:
       0: aload_0
       1: aload_1
       2: invokespecial #1                  // Method io/reactivex/rxjava3/internal/operators/maybe/AbstractMaybeWithUpstream."<init>":(Lio/reactivex/rxjava3/core/MaybeSource;)V
       5: return

  protected void subscribeActual(io.reactivex.rxjava3.core.MaybeObserver<? super T>);
    Code:
       0: aload_0
       1: getfield      #2                  // Field source:Lio/reactivex/rxjava3/core/MaybeSource;
       4: aload_1
       5: invokeinterface #3,  2            // InterfaceMethod io/reactivex/rxjava3/core/MaybeSource.subscribe:(Lio/reactivex/rxjava3/core/MaybeObserver;)V
      10: return
}
