Compiled from "MaybeSwitchIfEmptySingle.java"
public final class io.reactivex.rxjava3.internal.operators.maybe.MaybeSwitchIfEmptySingle<T> extends io.reactivex.rxjava3.core.Single<T> implements io.reactivex.rxjava3.internal.fuseable.HasUpstreamMaybeSource<T> {
  final io.reactivex.rxjava3.core.MaybeSource<T> source;

  final io.reactivex.rxjava3.core.SingleSource<? extends T> other;

  public io.reactivex.rxjava3.internal.operators.maybe.MaybeSwitchIfEmptySingle(io.reactivex.rxjava3.core.MaybeSource<T>, io.reactivex.rxjava3.core.SingleSource<? extends T>);
    Code:
       0: aload_0
       1: invokespecial #1                  // Method io/reactivex/rxjava3/core/Single."<init>":()V
       4: aload_0
       5: aload_1
       6: putfield      #2                  // Field source:Lio/reactivex/rxjava3/core/MaybeSource;
       9: aload_0
      10: aload_2
      11: putfield      #3                  // Field other:Lio/reactivex/rxjava3/core/SingleSource;
      14: return

  public io.reactivex.rxjava3.core.MaybeSource<T> source();
    Code:
       0: aload_0
       1: getfield      #2                  // Field source:Lio/reactivex/rxjava3/core/MaybeSource;
       4: areturn

  protected void subscribeActual(io.reactivex.rxjava3.core.SingleObserver<? super T>);
    Code:
       0: aload_0
       1: getfield      #2                  // Field source:Lio/reactivex/rxjava3/core/MaybeSource;
       4: new           #4                  // class io/reactivex/rxjava3/internal/operators/maybe/MaybeSwitchIfEmptySingle$SwitchIfEmptyMaybeObserver
       7: dup
       8: aload_1
       9: aload_0
      10: getfield      #3                  // Field other:Lio/reactivex/rxjava3/core/SingleSource;
      13: invokespecial #5                  // Method io/reactivex/rxjava3/internal/operators/maybe/MaybeSwitchIfEmptySingle$SwitchIfEmptyMaybeObserver."<init>":(Lio/reactivex/rxjava3/core/SingleObserver;Lio/reactivex/rxjava3/core/SingleSource;)V
      16: invokeinterface #6,  2            // InterfaceMethod io/reactivex/rxjava3/core/MaybeSource.subscribe:(Lio/reactivex/rxjava3/core/MaybeObserver;)V
      21: return
}
