Compiled from "DubboRouteDestination.java"
public class org.apache.dubbo.rpc.cluster.router.mesh.rule.virtualservice.destination.DubboRouteDestination {
  private org.apache.dubbo.rpc.cluster.router.mesh.rule.virtualservice.destination.DubboDestination destination;

  private int weight;

  public org.apache.dubbo.rpc.cluster.router.mesh.rule.virtualservice.destination.DubboRouteDestination();
    Code:
       0: aload_0
       1: invokespecial #1                  // Method java/lang/Object."<init>":()V
       4: return

  public org.apache.dubbo.rpc.cluster.router.mesh.rule.virtualservice.destination.DubboDestination getDestination();
    Code:
       0: aload_0
       1: getfield      #2                  // Field destination:Lorg/apache/dubbo/rpc/cluster/router/mesh/rule/virtualservice/destination/DubboDestination;
       4: areturn

  public void setDestination(org.apache.dubbo.rpc.cluster.router.mesh.rule.virtualservice.destination.DubboDestination);
    Code:
       0: aload_0
       1: aload_1
       2: putfield      #2                  // Field destination:Lorg/apache/dubbo/rpc/cluster/router/mesh/rule/virtualservice/destination/DubboDestination;
       5: return

  public int getWeight();
    Code:
       0: aload_0
       1: getfield      #3                  // Field weight:I
       4: ireturn

  public void setWeight(int);
    Code:
       0: aload_0
       1: iload_1
       2: putfield      #3                  // Field weight:I
       5: return
}
