Compiled from "DubboDestination.java"
public class org.apache.dubbo.rpc.cluster.router.mesh.rule.virtualservice.destination.DubboDestination {
  private java.lang.String host;

  private java.lang.String subset;

  private int port;

  private org.apache.dubbo.rpc.cluster.router.mesh.rule.virtualservice.destination.DubboRouteDestination fallback;

  public org.apache.dubbo.rpc.cluster.router.mesh.rule.virtualservice.destination.DubboDestination();
    Code:
       0: aload_0
       1: invokespecial #1                  // Method java/lang/Object."<init>":()V
       4: return

  public java.lang.String getHost();
    Code:
       0: aload_0
       1: getfield      #2                  // Field host:Ljava/lang/String;
       4: areturn

  public void setHost(java.lang.String);
    Code:
       0: aload_0
       1: aload_1
       2: putfield      #2                  // Field host:Ljava/lang/String;
       5: return

  public java.lang.String getSubset();
    Code:
       0: aload_0
       1: getfield      #3                  // Field subset:Ljava/lang/String;
       4: areturn

  public void setSubset(java.lang.String);
    Code:
       0: aload_0
       1: aload_1
       2: putfield      #3                  // Field subset:Ljava/lang/String;
       5: return

  public int getPort();
    Code:
       0: aload_0
       1: getfield      #4                  // Field port:I
       4: ireturn

  public void setPort(int);
    Code:
       0: aload_0
       1: iload_1
       2: putfield      #4                  // Field port:I
       5: return

  public org.apache.dubbo.rpc.cluster.router.mesh.rule.virtualservice.destination.DubboRouteDestination getFallback();
    Code:
       0: aload_0
       1: getfield      #5                  // Field fallback:Lorg/apache/dubbo/rpc/cluster/router/mesh/rule/virtualservice/destination/DubboRouteDestination;
       4: areturn

  public void setFallback(org.apache.dubbo.rpc.cluster.router.mesh.rule.virtualservice.destination.DubboRouteDestination);
    Code:
       0: aload_0
       1: aload_1
       2: putfield      #5                  // Field fallback:Lorg/apache/dubbo/rpc/cluster/router/mesh/rule/virtualservice/destination/DubboRouteDestination;
       5: return
}
