Compiled from "CounterMetricSample.java"
public class org.apache.dubbo.metrics.model.sample.CounterMetricSample<T extends java.lang.Number> extends org.apache.dubbo.metrics.model.sample.MetricSample {
  private final T value;

  public org.apache.dubbo.metrics.model.sample.CounterMetricSample(java.lang.String, java.lang.String, java.util.Map<java.lang.String, java.lang.String>, org.apache.dubbo.metrics.model.MetricsCategory, T);
    Code:
       0: aload_0
       1: aload_1
       2: aload_2
       3: aload_3
       4: getstatic     #1                  // Field org/apache/dubbo/metrics/model/sample/MetricSample$Type.COUNTER:Lorg/apache/dubbo/metrics/model/sample/MetricSample$Type;
       7: aload         4
       9: invokespecial #2                  // Method org/apache/dubbo/metrics/model/sample/MetricSample."<init>":(Ljava/lang/String;Ljava/lang/String;Ljava/util/Map;Lorg/apache/dubbo/metrics/model/sample/MetricSample$Type;Lorg/apache/dubbo/metrics/model/MetricsCategory;)V
      12: aload_0
      13: aload         5
      15: putfield      #3                  // Field value:Ljava/lang/Number;
      18: return

  public org.apache.dubbo.metrics.model.sample.CounterMetricSample(org.apache.dubbo.metrics.model.key.MetricsKeyWrapper, java.util.Map<java.lang.String, java.lang.String>, org.apache.dubbo.metrics.model.MetricsCategory, T);
    Code:
       0: aload_0
       1: aload_1
       2: invokevirtual #4                  // Method org/apache/dubbo/metrics/model/key/MetricsKeyWrapper.targetKey:()Ljava/lang/String;
       5: aload_1
       6: invokevirtual #5                  // Method org/apache/dubbo/metrics/model/key/MetricsKeyWrapper.targetDesc:()Ljava/lang/String;
       9: aload_2
      10: aload_3
      11: aload         4
      13: invokespecial #6                  // Method "<init>":(Ljava/lang/String;Ljava/lang/String;Ljava/util/Map;Lorg/apache/dubbo/metrics/model/MetricsCategory;Ljava/lang/Number;)V
      16: return

  public T getValue();
    Code:
       0: aload_0
       1: getfield      #3                  // Field value:Ljava/lang/Number;
       4: areturn
}
