Compiled from "GaugeMetricSample.java"
public class org.apache.dubbo.metrics.model.sample.GaugeMetricSample<T> extends org.apache.dubbo.metrics.model.sample.MetricSample {
  private final T value;

  private final java.util.function.ToDoubleFunction<T> apply;

  public org.apache.dubbo.metrics.model.sample.GaugeMetricSample(org.apache.dubbo.metrics.model.key.MetricsKey, java.util.Map<java.lang.String, java.lang.String>, org.apache.dubbo.metrics.model.MetricsCategory, T, java.util.function.ToDoubleFunction<T>);
    Code:
       0: aload_0
       1: aload_1
       2: invokevirtual #1                  // Method org/apache/dubbo/metrics/model/key/MetricsKey.getName:()Ljava/lang/String;
       5: aload_1
       6: invokevirtual #2                  // Method org/apache/dubbo/metrics/model/key/MetricsKey.getDescription:()Ljava/lang/String;
       9: aload_2
      10: aload_3
      11: aconst_null
      12: aload         4
      14: aload         5
      16: invokespecial #3                  // Method "<init>":(Ljava/lang/String;Ljava/lang/String;Ljava/util/Map;Lorg/apache/dubbo/metrics/model/MetricsCategory;Ljava/lang/String;Ljava/lang/Object;Ljava/util/function/ToDoubleFunction;)V
      19: return

  public org.apache.dubbo.metrics.model.sample.GaugeMetricSample(org.apache.dubbo.metrics.model.key.MetricsKeyWrapper, java.util.Map<java.lang.String, java.lang.String>, org.apache.dubbo.metrics.model.MetricsCategory, T, java.util.function.ToDoubleFunction<T>);
    Code:
       0: aload_0
       1: aload_1
       2: invokevirtual #4                  // Method org/apache/dubbo/metrics/model/key/MetricsKeyWrapper.targetKey:()Ljava/lang/String;
       5: aload_1
       6: invokevirtual #5                  // Method org/apache/dubbo/metrics/model/key/MetricsKeyWrapper.targetDesc:()Ljava/lang/String;
       9: aload_2
      10: aload_3
      11: aconst_null
      12: aload         4
      14: aload         5
      16: invokespecial #3                  // Method "<init>":(Ljava/lang/String;Ljava/lang/String;Ljava/util/Map;Lorg/apache/dubbo/metrics/model/MetricsCategory;Ljava/lang/String;Ljava/lang/Object;Ljava/util/function/ToDoubleFunction;)V
      19: return

  public org.apache.dubbo.metrics.model.sample.GaugeMetricSample(java.lang.String, java.lang.String, java.util.Map<java.lang.String, java.lang.String>, org.apache.dubbo.metrics.model.MetricsCategory, T, java.util.function.ToDoubleFunction<T>);
    Code:
       0: aload_0
       1: aload_1
       2: aload_2
       3: aload_3
       4: aload         4
       6: aconst_null
       7: aload         5
       9: aload         6
      11: invokespecial #3                  // Method "<init>":(Ljava/lang/String;Ljava/lang/String;Ljava/util/Map;Lorg/apache/dubbo/metrics/model/MetricsCategory;Ljava/lang/String;Ljava/lang/Object;Ljava/util/function/ToDoubleFunction;)V
      14: return

  public org.apache.dubbo.metrics.model.sample.GaugeMetricSample(java.lang.String, java.lang.String, java.util.Map<java.lang.String, java.lang.String>, org.apache.dubbo.metrics.model.MetricsCategory, java.lang.String, T, java.util.function.ToDoubleFunction<T>);
    Code:
       0: aload_0
       1: aload_1
       2: aload_2
       3: aload_3
       4: getstatic     #6                  // Field org/apache/dubbo/metrics/model/sample/MetricSample$Type.GAUGE:Lorg/apache/dubbo/metrics/model/sample/MetricSample$Type;
       7: aload         4
       9: aload         5
      11: invokespecial #7                  // Method org/apache/dubbo/metrics/model/sample/MetricSample."<init>":(Ljava/lang/String;Ljava/lang/String;Ljava/util/Map;Lorg/apache/dubbo/metrics/model/sample/MetricSample$Type;Lorg/apache/dubbo/metrics/model/MetricsCategory;Ljava/lang/String;)V
      14: aload_0
      15: aload         6
      17: ldc           #8                  // String The GaugeMetricSample value cannot be null
      19: invokestatic  #9                  // Method java/util/Objects.requireNonNull:(Ljava/lang/Object;Ljava/lang/String;)Ljava/lang/Object;
      22: putfield      #10                 // Field value:Ljava/lang/Object;
      25: aload_0
      26: aload         7
      28: ldc           #11                 // String The GaugeMetricSample apply cannot be null
      30: invokestatic  #9                  // Method java/util/Objects.requireNonNull:(Ljava/lang/Object;Ljava/lang/String;)Ljava/lang/Object;
      33: checkcast     #12                 // class java/util/function/ToDoubleFunction
      36: putfield      #13                 // Field apply:Ljava/util/function/ToDoubleFunction;
      39: return

  public T getValue();
    Code:
       0: aload_0
       1: getfield      #10                 // Field value:Ljava/lang/Object;
       4: areturn

  public java.util.function.ToDoubleFunction<T> getApply();
    Code:
       0: aload_0
       1: getfield      #13                 // Field apply:Ljava/util/function/ToDoubleFunction;
       4: areturn

  public long applyAsLong();
    Code:
       0: aload_0
       1: invokevirtual #14                 // Method getApply:()Ljava/util/function/ToDoubleFunction;
       4: aload_0
       5: invokevirtual #15                 // Method getValue:()Ljava/lang/Object;
       8: invokeinterface #16,  2           // InterfaceMethod java/util/function/ToDoubleFunction.applyAsDouble:(Ljava/lang/Object;)D
      13: d2l
      14: lreturn

  public double applyAsDouble();
    Code:
       0: aload_0
       1: invokevirtual #14                 // Method getApply:()Ljava/util/function/ToDoubleFunction;
       4: aload_0
       5: invokevirtual #15                 // Method getValue:()Ljava/lang/Object;
       8: invokeinterface #16,  2           // InterfaceMethod java/util/function/ToDoubleFunction.applyAsDouble:(Ljava/lang/Object;)D
      13: dreturn
}
