Compiled from "MetricSample.java"
public class org.apache.dubbo.metrics.model.sample.MetricSample {
  private java.lang.String name;

  private java.lang.String description;

  private java.util.Map<java.lang.String, java.lang.String> tags;

  private org.apache.dubbo.metrics.model.sample.MetricSample$Type type;

  private org.apache.dubbo.metrics.model.MetricsCategory category;

  private java.lang.String baseUnit;

  public org.apache.dubbo.metrics.model.sample.MetricSample(java.lang.String, java.lang.String, java.util.Map<java.lang.String, java.lang.String>, org.apache.dubbo.metrics.model.sample.MetricSample$Type, org.apache.dubbo.metrics.model.MetricsCategory);
    Code:
       0: aload_0
       1: aload_1
       2: aload_2
       3: aload_3
       4: aload         4
       6: aload         5
       8: aconst_null
       9: invokespecial #1                  // Method "<init>":(Ljava/lang/String;Ljava/lang/String;Ljava/util/Map;Lorg/apache/dubbo/metrics/model/sample/MetricSample$Type;Lorg/apache/dubbo/metrics/model/MetricsCategory;Ljava/lang/String;)V
      12: return

  public org.apache.dubbo.metrics.model.sample.MetricSample(java.lang.String, java.lang.String, java.util.Map<java.lang.String, java.lang.String>, org.apache.dubbo.metrics.model.sample.MetricSample$Type, org.apache.dubbo.metrics.model.MetricsCategory, java.lang.String);
    Code:
       0: aload_0
       1: invokespecial #2                  // Method java/lang/Object."<init>":()V
       4: aload_0
       5: aload_1
       6: putfield      #3                  // Field name:Ljava/lang/String;
       9: aload_0
      10: aload_2
      11: putfield      #4                  // Field description:Ljava/lang/String;
      14: aload_0
      15: aload_3
      16: putfield      #5                  // Field tags:Ljava/util/Map;
      19: aload_0
      20: aload         4
      22: putfield      #6                  // Field type:Lorg/apache/dubbo/metrics/model/sample/MetricSample$Type;
      25: aload_0
      26: aload         5
      28: putfield      #7                  // Field category:Lorg/apache/dubbo/metrics/model/MetricsCategory;
      31: aload_0
      32: aload         6
      34: putfield      #8                  // Field baseUnit:Ljava/lang/String;
      37: return

  public java.lang.String getName();
    Code:
       0: aload_0
       1: getfield      #3                  // Field name:Ljava/lang/String;
       4: areturn

  public void setName(java.lang.String);
    Code:
       0: aload_0
       1: aload_1
       2: putfield      #3                  // Field name:Ljava/lang/String;
       5: return

  public java.lang.String getDescription();
    Code:
       0: aload_0
       1: getfield      #4                  // Field description:Ljava/lang/String;
       4: areturn

  public void setDescription(java.lang.String);
    Code:
       0: aload_0
       1: aload_1
       2: putfield      #4                  // Field description:Ljava/lang/String;
       5: return

  public java.util.Map<java.lang.String, java.lang.String> getTags();
    Code:
       0: aload_0
       1: getfield      #5                  // Field tags:Ljava/util/Map;
       4: areturn

  public void setTags(java.util.Map<java.lang.String, java.lang.String>);
    Code:
       0: aload_0
       1: aload_1
       2: putfield      #5                  // Field tags:Ljava/util/Map;
       5: return

  public org.apache.dubbo.metrics.model.sample.MetricSample$Type getType();
    Code:
       0: aload_0
       1: getfield      #6                  // Field type:Lorg/apache/dubbo/metrics/model/sample/MetricSample$Type;
       4: areturn

  public void setType(org.apache.dubbo.metrics.model.sample.MetricSample$Type);
    Code:
       0: aload_0
       1: aload_1
       2: putfield      #6                  // Field type:Lorg/apache/dubbo/metrics/model/sample/MetricSample$Type;
       5: return

  public org.apache.dubbo.metrics.model.MetricsCategory getCategory();
    Code:
       0: aload_0
       1: getfield      #7                  // Field category:Lorg/apache/dubbo/metrics/model/MetricsCategory;
       4: areturn

  public void setCategory(org.apache.dubbo.metrics.model.MetricsCategory);
    Code:
       0: aload_0
       1: aload_1
       2: putfield      #7                  // Field category:Lorg/apache/dubbo/metrics/model/MetricsCategory;
       5: return

  public java.lang.String getBaseUnit();
    Code:
       0: aload_0
       1: getfield      #8                  // Field baseUnit:Ljava/lang/String;
       4: areturn

  public void setBaseUnit(java.lang.String);
    Code:
       0: aload_0
       1: aload_1
       2: putfield      #8                  // Field baseUnit:Ljava/lang/String;
       5: return

  public boolean equals(java.lang.Object);
    Code:
       0: aload_0
       1: aload_1
       2: if_acmpne     7
       5: iconst_1
       6: ireturn
       7: aload_1
       8: ifnull        22
      11: aload_0
      12: invokevirtual #9                  // Method java/lang/Object.getClass:()Ljava/lang/Class;
      15: aload_1
      16: invokevirtual #9                  // Method java/lang/Object.getClass:()Ljava/lang/Class;
      19: if_acmpeq     24
      22: iconst_0
      23: ireturn
      24: aload_1
      25: checkcast     #10                 // class org/apache/dubbo/metrics/model/sample/MetricSample
      28: astore_2
      29: aload_0
      30: getfield      #3                  // Field name:Ljava/lang/String;
      33: aload_2
      34: getfield      #3                  // Field name:Ljava/lang/String;
      37: invokestatic  #11                 // Method java/util/Objects.equals:(Ljava/lang/Object;Ljava/lang/Object;)Z
      40: ifeq          114
      43: aload_0
      44: getfield      #4                  // Field description:Ljava/lang/String;
      47: aload_2
      48: getfield      #4                  // Field description:Ljava/lang/String;
      51: invokestatic  #11                 // Method java/util/Objects.equals:(Ljava/lang/Object;Ljava/lang/Object;)Z
      54: ifeq          114
      57: aload_0
      58: getfield      #8                  // Field baseUnit:Ljava/lang/String;
      61: aload_2
      62: getfield      #8                  // Field baseUnit:Ljava/lang/String;
      65: invokestatic  #11                 // Method java/util/Objects.equals:(Ljava/lang/Object;Ljava/lang/Object;)Z
      68: ifeq          114
      71: aload_0
      72: getfield      #6                  // Field type:Lorg/apache/dubbo/metrics/model/sample/MetricSample$Type;
      75: aload_2
      76: getfield      #6                  // Field type:Lorg/apache/dubbo/metrics/model/sample/MetricSample$Type;
      79: if_acmpne     114
      82: aload_0
      83: getfield      #7                  // Field category:Lorg/apache/dubbo/metrics/model/MetricsCategory;
      86: aload_2
      87: getfield      #7                  // Field category:Lorg/apache/dubbo/metrics/model/MetricsCategory;
      90: invokestatic  #11                 // Method java/util/Objects.equals:(Ljava/lang/Object;Ljava/lang/Object;)Z
      93: ifeq          114
      96: aload_0
      97: getfield      #5                  // Field tags:Ljava/util/Map;
     100: aload_2
     101: getfield      #5                  // Field tags:Ljava/util/Map;
     104: invokestatic  #11                 // Method java/util/Objects.equals:(Ljava/lang/Object;Ljava/lang/Object;)Z
     107: ifeq          114
     110: iconst_1
     111: goto          115
     114: iconst_0
     115: ireturn

  public int hashCode();
    Code:
       0: bipush        6
       2: anewarray     #12                 // class java/lang/Object
       5: dup
       6: iconst_0
       7: aload_0
       8: getfield      #3                  // Field name:Ljava/lang/String;
      11: aastore
      12: dup
      13: iconst_1
      14: aload_0
      15: getfield      #4                  // Field description:Ljava/lang/String;
      18: aastore
      19: dup
      20: iconst_2
      21: aload_0
      22: getfield      #8                  // Field baseUnit:Ljava/lang/String;
      25: aastore
      26: dup
      27: iconst_3
      28: aload_0
      29: getfield      #6                  // Field type:Lorg/apache/dubbo/metrics/model/sample/MetricSample$Type;
      32: aastore
      33: dup
      34: iconst_4
      35: aload_0
      36: getfield      #7                  // Field category:Lorg/apache/dubbo/metrics/model/MetricsCategory;
      39: aastore
      40: dup
      41: iconst_5
      42: aload_0
      43: getfield      #5                  // Field tags:Ljava/util/Map;
      46: aastore
      47: invokestatic  #13                 // Method java/util/Objects.hash:([Ljava/lang/Object;)I
      50: ireturn

  public java.lang.String toString();
    Code:
       0: new           #14                 // class java/lang/StringBuilder
       3: dup
       4: invokespecial #15                 // Method java/lang/StringBuilder."<init>":()V
       7: ldc           #16                 // String MetricSample{name=\'
       9: invokevirtual #17                 // Method java/lang/StringBuilder.append:(Ljava/lang/String;)Ljava/lang/StringBuilder;
      12: aload_0
      13: getfield      #3                  // Field name:Ljava/lang/String;
      16: invokevirtual #17                 // Method java/lang/StringBuilder.append:(Ljava/lang/String;)Ljava/lang/StringBuilder;
      19: bipush        39
      21: invokevirtual #18                 // Method java/lang/StringBuilder.append:(C)Ljava/lang/StringBuilder;
      24: ldc           #19                 // String , description=\'
      26: invokevirtual #17                 // Method java/lang/StringBuilder.append:(Ljava/lang/String;)Ljava/lang/StringBuilder;
      29: aload_0
      30: getfield      #4                  // Field description:Ljava/lang/String;
      33: invokevirtual #17                 // Method java/lang/StringBuilder.append:(Ljava/lang/String;)Ljava/lang/StringBuilder;
      36: bipush        39
      38: invokevirtual #18                 // Method java/lang/StringBuilder.append:(C)Ljava/lang/StringBuilder;
      41: ldc           #20                 // String , baseUnit=\'
      43: invokevirtual #17                 // Method java/lang/StringBuilder.append:(Ljava/lang/String;)Ljava/lang/StringBuilder;
      46: aload_0
      47: getfield      #8                  // Field baseUnit:Ljava/lang/String;
      50: invokevirtual #17                 // Method java/lang/StringBuilder.append:(Ljava/lang/String;)Ljava/lang/StringBuilder;
      53: bipush        39
      55: invokevirtual #18                 // Method java/lang/StringBuilder.append:(C)Ljava/lang/StringBuilder;
      58: ldc           #21                 // String , type=
      60: invokevirtual #17                 // Method java/lang/StringBuilder.append:(Ljava/lang/String;)Ljava/lang/StringBuilder;
      63: aload_0
      64: getfield      #6                  // Field type:Lorg/apache/dubbo/metrics/model/sample/MetricSample$Type;
      67: invokevirtual #22                 // Method java/lang/StringBuilder.append:(Ljava/lang/Object;)Ljava/lang/StringBuilder;
      70: ldc           #23                 // String , category=
      72: invokevirtual #17                 // Method java/lang/StringBuilder.append:(Ljava/lang/String;)Ljava/lang/StringBuilder;
      75: aload_0
      76: getfield      #7                  // Field category:Lorg/apache/dubbo/metrics/model/MetricsCategory;
      79: invokevirtual #22                 // Method java/lang/StringBuilder.append:(Ljava/lang/Object;)Ljava/lang/StringBuilder;
      82: ldc           #24                 // String , tags=
      84: invokevirtual #17                 // Method java/lang/StringBuilder.append:(Ljava/lang/String;)Ljava/lang/StringBuilder;
      87: aload_0
      88: getfield      #5                  // Field tags:Ljava/util/Map;
      91: invokevirtual #22                 // Method java/lang/StringBuilder.append:(Ljava/lang/Object;)Ljava/lang/StringBuilder;
      94: bipush        125
      96: invokevirtual #18                 // Method java/lang/StringBuilder.append:(C)Ljava/lang/StringBuilder;
      99: invokevirtual #25                 // Method java/lang/StringBuilder.toString:()Ljava/lang/String;
     102: areturn
}
