Compiled from "MenuComparator.java"
public class com.alibaba.dubbo.container.page.MenuComparator implements java.util.Comparator<com.alibaba.dubbo.container.page.PageHandler>, java.io.Serializable {
  private static final long serialVersionUID;

  public com.alibaba.dubbo.container.page.MenuComparator();
    Code:
       0: aload_0
       1: invokespecial #1                  // Method java/lang/Object."<init>":()V
       4: return

  public int compare(com.alibaba.dubbo.container.page.PageHandler, com.alibaba.dubbo.container.page.PageHandler);
    Code:
       0: aload_1
       1: ifnonnull     10
       4: aload_2
       5: ifnonnull     10
       8: iconst_0
       9: ireturn
      10: aload_1
      11: ifnonnull     16
      14: iconst_m1
      15: ireturn
      16: aload_2
      17: ifnonnull     22
      20: iconst_1
      21: ireturn
      22: aload_1
      23: aload_2
      24: invokevirtual #2                  // Method java/lang/Object.equals:(Ljava/lang/Object;)Z
      27: ifeq          34
      30: iconst_0
      31: goto          76
      34: aload_1
      35: invokevirtual #3                  // Method java/lang/Object.getClass:()Ljava/lang/Class;
      38: ldc           #4                  // class com/alibaba/dubbo/container/page/Menu
      40: invokevirtual #5                  // Method java/lang/Class.getAnnotation:(Ljava/lang/Class;)Ljava/lang/annotation/Annotation;
      43: checkcast     #4                  // class com/alibaba/dubbo/container/page/Menu
      46: invokeinterface #6,  1            // InterfaceMethod com/alibaba/dubbo/container/page/Menu.order:()I
      51: aload_2
      52: invokevirtual #3                  // Method java/lang/Object.getClass:()Ljava/lang/Class;
      55: ldc           #4                  // class com/alibaba/dubbo/container/page/Menu
      57: invokevirtual #5                  // Method java/lang/Class.getAnnotation:(Ljava/lang/Class;)Ljava/lang/annotation/Annotation;
      60: checkcast     #4                  // class com/alibaba/dubbo/container/page/Menu
      63: invokeinterface #6,  1            // InterfaceMethod com/alibaba/dubbo/container/page/Menu.order:()I
      68: if_icmple     75
      71: iconst_1
      72: goto          76
      75: iconst_m1
      76: ireturn

  public int compare(java.lang.Object, java.lang.Object);
    Code:
       0: aload_0
       1: aload_1
       2: checkcast     #7                  // class com/alibaba/dubbo/container/page/PageHandler
       5: aload_2
       6: checkcast     #7                  // class com/alibaba/dubbo/container/page/PageHandler
       9: invokevirtual #8                  // Method compare:(Lcom/alibaba/dubbo/container/page/PageHandler;Lcom/alibaba/dubbo/container/page/PageHandler;)I
      12: ireturn
}
