Compiled from "PageServlet.java"
public class com.alibaba.dubbo.container.page.PageServlet extends javax.servlet.http.HttpServlet {
  protected static final org.apache.dubbo.common.logger.Logger logger;

  private static final long serialVersionUID;

  private static com.alibaba.dubbo.container.page.PageServlet INSTANCE;

  protected final java.util.Random random;

  protected final java.util.Map<java.lang.String, com.alibaba.dubbo.container.page.PageHandler> pages;

  protected final java.util.List<com.alibaba.dubbo.container.page.PageHandler> menus;

  public com.alibaba.dubbo.container.page.PageServlet();
    Code:
       0: aload_0
       1: invokespecial #1                  // Method javax/servlet/http/HttpServlet."<init>":()V
       4: aload_0
       5: new           #2                  // class java/util/Random
       8: dup
       9: invokespecial #3                  // Method java/util/Random."<init>":()V
      12: putfield      #4                  // Field random:Ljava/util/Random;
      15: aload_0
      16: new           #5                  // class java/util/concurrent/ConcurrentHashMap
      19: dup
      20: invokespecial #6                  // Method java/util/concurrent/ConcurrentHashMap."<init>":()V
      23: putfield      #7                  // Field pages:Ljava/util/Map;
      26: aload_0
      27: new           #8                  // class java/util/ArrayList
      30: dup
      31: invokespecial #9                  // Method java/util/ArrayList."<init>":()V
      34: putfield      #10                 // Field menus:Ljava/util/List;
      37: return

  public static com.alibaba.dubbo.container.page.PageServlet getInstance();
    Code:
       0: getstatic     #11                 // Field INSTANCE:Lcom/alibaba/dubbo/container/page/PageServlet;
       3: areturn

  public java.util.List<com.alibaba.dubbo.container.page.PageHandler> getMenus();
    Code:
       0: aload_0
       1: getfield      #10                 // Field menus:Ljava/util/List;
       4: invokestatic  #12                 // Method java/util/Collections.unmodifiableList:(Ljava/util/List;)Ljava/util/List;
       7: areturn

  public void init() throws javax.servlet.ServletException;
    Code:
       0: aload_0
       1: invokespecial #13                 // Method javax/servlet/http/HttpServlet.init:()V
       4: aload_0
       5: putstatic     #11                 // Field INSTANCE:Lcom/alibaba/dubbo/container/page/PageServlet;
       8: aload_0
       9: invokevirtual #14                 // Method getServletConfig:()Ljavax/servlet/ServletConfig;
      12: ldc           #15                 // String pages
      14: invokeinterface #16,  2           // InterfaceMethod javax/servlet/ServletConfig.getInitParameter:(Ljava/lang/String;)Ljava/lang/String;
      19: astore_1
      20: aload_1
      21: ifnull        45
      24: aload_1
      25: invokevirtual #17                 // Method java/lang/String.length:()I
      28: ifle          45
      31: getstatic     #18                 // Field com/alibaba/dubbo/common/Constants.COMMA_SPLIT_PATTERN:Ljava/util/regex/Pattern;
      34: aload_1
      35: invokevirtual #19                 // Method java/util/regex/Pattern.split:(Ljava/lang/CharSequence;)[Ljava/lang/String;
      38: invokestatic  #20                 // Method java/util/Arrays.asList:([Ljava/lang/Object;)Ljava/util/List;
      41: astore_2
      42: goto          54
      45: ldc           #21                 // class com/alibaba/dubbo/container/page/PageHandler
      47: invokestatic  #22                 // Method org/apache/dubbo/common/extension/ExtensionLoader.getExtensionLoader:(Ljava/lang/Class;)Lorg/apache/dubbo/common/extension/ExtensionLoader;
      50: invokevirtual #23                 // Method org/apache/dubbo/common/extension/ExtensionLoader.getSupportedExtensions:()Ljava/util/Set;
      53: astore_2
      54: aload_2
      55: invokeinterface #24,  1           // InterfaceMethod java/util/Collection.iterator:()Ljava/util/Iterator;
      60: astore_3
      61: aload_3
      62: invokeinterface #25,  1           // InterfaceMethod java/util/Iterator.hasNext:()Z
      67: ifeq          153
      70: aload_3
      71: invokeinterface #26,  1           // InterfaceMethod java/util/Iterator.next:()Ljava/lang/Object;
      76: checkcast     #27                 // class java/lang/String
      79: astore        4
      81: ldc           #21                 // class com/alibaba/dubbo/container/page/PageHandler
      83: invokestatic  #22                 // Method org/apache/dubbo/common/extension/ExtensionLoader.getExtensionLoader:(Ljava/lang/Class;)Lorg/apache/dubbo/common/extension/ExtensionLoader;
      86: aload         4
      88: invokevirtual #28                 // Method org/apache/dubbo/common/extension/ExtensionLoader.getExtension:(Ljava/lang/String;)Ljava/lang/Object;
      91: checkcast     #21                 // class com/alibaba/dubbo/container/page/PageHandler
      94: astore        5
      96: aload_0
      97: getfield      #7                  // Field pages:Ljava/util/Map;
     100: ldc           #21                 // class com/alibaba/dubbo/container/page/PageHandler
     102: invokestatic  #22                 // Method org/apache/dubbo/common/extension/ExtensionLoader.getExtensionLoader:(Ljava/lang/Class;)Lorg/apache/dubbo/common/extension/ExtensionLoader;
     105: aload         5
     107: invokevirtual #29                 // Method org/apache/dubbo/common/extension/ExtensionLoader.getExtensionName:(Ljava/lang/Object;)Ljava/lang/String;
     110: aload         5
     112: invokeinterface #30,  3           // InterfaceMethod java/util/Map.put:(Ljava/lang/Object;Ljava/lang/Object;)Ljava/lang/Object;
     117: pop
     118: aload         5
     120: invokevirtual #31                 // Method java/lang/Object.getClass:()Ljava/lang/Class;
     123: ldc           #32                 // class com/alibaba/dubbo/container/page/Menu
     125: invokevirtual #33                 // Method java/lang/Class.getAnnotation:(Ljava/lang/Class;)Ljava/lang/annotation/Annotation;
     128: checkcast     #32                 // class com/alibaba/dubbo/container/page/Menu
     131: astore        6
     133: aload         6
     135: ifnull        150
     138: aload_0
     139: getfield      #10                 // Field menus:Ljava/util/List;
     142: aload         5
     144: invokeinterface #34,  2           // InterfaceMethod java/util/List.add:(Ljava/lang/Object;)Z
     149: pop
     150: goto          61
     153: aload_0
     154: getfield      #10                 // Field menus:Ljava/util/List;
     157: new           #35                 // class com/alibaba/dubbo/container/page/MenuComparator
     160: dup
     161: invokespecial #36                 // Method com/alibaba/dubbo/container/page/MenuComparator."<init>":()V
     164: invokestatic  #37                 // Method java/util/Collections.sort:(Ljava/util/List;Ljava/util/Comparator;)V
     167: return

  protected final void doGet(javax.servlet.http.HttpServletRequest, javax.servlet.http.HttpServletResponse) throws javax.servlet.ServletException, java.io.IOException;
    Code:
       0: aload_0
       1: aload_1
       2: aload_2
       3: invokevirtual #38                 // Method doPost:(Ljavax/servlet/http/HttpServletRequest;Ljavax/servlet/http/HttpServletResponse;)V
       6: return

  protected final void doPost(javax.servlet.http.HttpServletRequest, javax.servlet.http.HttpServletResponse) throws javax.servlet.ServletException, java.io.IOException;
    Code:
       0: aload_2
       1: invokeinterface #39,  1           // InterfaceMethod javax/servlet/http/HttpServletResponse.isCommitted:()Z
       6: ifne          828
       9: aload_2
      10: invokeinterface #40,  1           // InterfaceMethod javax/servlet/http/HttpServletResponse.getWriter:()Ljava/io/PrintWriter;
      15: astore_3
      16: aload_1
      17: invokeinterface #41,  1           // InterfaceMethod javax/servlet/http/HttpServletRequest.getRequestURI:()Ljava/lang/String;
      22: astore        4
      24: iconst_0
      25: istore        5
      27: aload         4
      29: ifnull        50
      32: aload         4
      34: invokevirtual #17                 // Method java/lang/String.length:()I
      37: ifeq          50
      40: ldc           #42                 // String /
      42: aload         4
      44: invokevirtual #43                 // Method java/lang/String.equals:(Ljava/lang/Object;)Z
      47: ifeq          60
      50: ldc           #44                 // String index
      52: astore        4
      54: iconst_1
      55: istore        5
      57: goto          110
      60: aload         4
      62: ldc           #42                 // String /
      64: invokevirtual #45                 // Method java/lang/String.startsWith:(Ljava/lang/String;)Z
      67: ifeq          78
      70: aload         4
      72: iconst_1
      73: invokevirtual #46                 // Method java/lang/String.substring:(I)Ljava/lang/String;
      76: astore        4
      78: aload         4
      80: ldc           #47                 // String .html
      82: invokevirtual #48                 // Method java/lang/String.endsWith:(Ljava/lang/String;)Z
      85: ifeq          110
      88: aload         4
      90: iconst_0
      91: aload         4
      93: invokevirtual #17                 // Method java/lang/String.length:()I
      96: ldc           #47                 // String .html
      98: invokevirtual #17                 // Method java/lang/String.length:()I
     101: isub
     102: invokevirtual #49                 // Method java/lang/String.substring:(II)Ljava/lang/String;
     105: astore        4
     107: iconst_1
     108: istore        5
     110: aload         4
     112: ldc           #50                 // String favicon.ico
     114: invokevirtual #48                 // Method java/lang/String.endsWith:(Ljava/lang/String;)Z
     117: ifeq          130
     120: aload_2
     121: sipush        404
     124: invokeinterface #52,  2           // InterfaceMethod javax/servlet/http/HttpServletResponse.sendError:(I)V
     129: return
     130: ldc           #21                 // class com/alibaba/dubbo/container/page/PageHandler
     132: invokestatic  #22                 // Method org/apache/dubbo/common/extension/ExtensionLoader.getExtensionLoader:(Ljava/lang/Class;)Lorg/apache/dubbo/common/extension/ExtensionLoader;
     135: astore        6
     137: aload         6
     139: aload         4
     141: invokevirtual #53                 // Method org/apache/dubbo/common/extension/ExtensionLoader.hasExtension:(Ljava/lang/String;)Z
     144: ifeq          160
     147: aload         6
     149: aload         4
     151: invokevirtual #28                 // Method org/apache/dubbo/common/extension/ExtensionLoader.getExtension:(Ljava/lang/String;)Ljava/lang/Object;
     154: checkcast     #21                 // class com/alibaba/dubbo/container/page/PageHandler
     157: goto          161
     160: aconst_null
     161: astore        7
     163: iload         5
     165: ifeq          186
     168: aload_3
     169: ldc           #54                 // String <html><head><title>Dubbo</title>
     171: invokevirtual #55                 // Method java/io/PrintWriter.println:(Ljava/lang/String;)V
     174: aload_3
     175: ldc           #56                 // String <style type=\"text/css\">html, body {margin: 10;padding: 0;background-color: #6D838C;font-family: Arial, Verdana;font-size: 12px;color: #FFFFFF;text-align: center;vertical-align: middle;word-break: break-all; } table {width: 90%; margin: 0px auto;border-collapse: collapse;border: 8px solid #FFFFFF; } thead tr {background-color: #253c46; } tbody tr {background-color: #8da5af; } th {padding-top: 4px;padding-bottom: 4px;font-size: 14px;height: 20px; } td {margin: 3px;padding: 3px;border: 2px solid #FFFFFF;font-size: 14px;height: 25px; } a {color: #FFFFFF;cursor: pointer;text-decoration: underline; } a:hover {text-decoration: none; }</style>
     177: invokevirtual #55                 // Method java/io/PrintWriter.println:(Ljava/lang/String;)V
     180: aload_3
     181: ldc           #57                 // String </head><body>
     183: invokevirtual #55                 // Method java/io/PrintWriter.println:(Ljava/lang/String;)V
     186: aload         7
     188: ifnull        663
     191: aconst_null
     192: astore        8
     194: aload_1
     195: invokeinterface #58,  1           // InterfaceMethod javax/servlet/http/HttpServletRequest.getQueryString:()Ljava/lang/String;
     200: astore        9
     202: aload         7
     204: new           #59                 // class java/lang/StringBuilder
     207: dup
     208: invokespecial #60                 // Method java/lang/StringBuilder."<init>":()V
     211: aload_1
     212: invokeinterface #61,  1           // InterfaceMethod javax/servlet/http/HttpServletRequest.getRequestURL:()Ljava/lang/StringBuffer;
     217: invokevirtual #62                 // Method java/lang/StringBuffer.toString:()Ljava/lang/String;
     220: invokevirtual #63                 // Method java/lang/StringBuilder.append:(Ljava/lang/String;)Ljava/lang/StringBuilder;
     223: aload         9
     225: ifnull        236
     228: aload         9
     230: invokevirtual #17                 // Method java/lang/String.length:()I
     233: ifne          241
     236: ldc           #64                 // String
     238: goto          261
     241: new           #59                 // class java/lang/StringBuilder
     244: dup
     245: invokespecial #60                 // Method java/lang/StringBuilder."<init>":()V
     248: ldc           #65                 // String ?
     250: invokevirtual #63                 // Method java/lang/StringBuilder.append:(Ljava/lang/String;)Ljava/lang/StringBuilder;
     253: aload         9
     255: invokevirtual #63                 // Method java/lang/StringBuilder.append:(Ljava/lang/String;)Ljava/lang/StringBuilder;
     258: invokevirtual #66                 // Method java/lang/StringBuilder.toString:()Ljava/lang/String;
     261: invokevirtual #63                 // Method java/lang/StringBuilder.append:(Ljava/lang/String;)Ljava/lang/StringBuilder;
     264: invokevirtual #66                 // Method java/lang/StringBuilder.toString:()Ljava/lang/String;
     267: invokestatic  #67                 // Method com/alibaba/dubbo/common/URL.valueOf:(Ljava/lang/String;)Lcom/alibaba/dubbo/common/URL;
     270: invokeinterface #68,  2           // InterfaceMethod com/alibaba/dubbo/container/page/PageHandler.handle:(Lcom/alibaba/dubbo/common/URL;)Lcom/alibaba/dubbo/container/page/Page;
     275: astore        8
     277: goto          459
     280: astore        9
     282: getstatic     #70                 // Field logger:Lorg/apache/dubbo/common/logger/Logger;
     285: aload         9
     287: invokevirtual #71                 // Method java/lang/Throwable.getMessage:()Ljava/lang/String;
     290: aload         9
     292: invokeinterface #72,  3           // InterfaceMethod org/apache/dubbo/common/logger/Logger.warn:(Ljava/lang/String;Ljava/lang/Throwable;)V
     297: aload         9
     299: invokevirtual #71                 // Method java/lang/Throwable.getMessage:()Ljava/lang/String;
     302: astore        10
     304: aload         10
     306: ifnonnull     316
     309: aload         9
     311: invokestatic  #73                 // Method org/apache/dubbo/common/utils/StringUtils.toString:(Ljava/lang/Throwable;)Ljava/lang/String;
     314: astore        10
     316: iload         5
     318: ifeq          453
     321: aload_3
     322: ldc           #74                 // String <table>
     324: invokevirtual #55                 // Method java/io/PrintWriter.println:(Ljava/lang/String;)V
     327: aload_3
     328: ldc           #75                 // String <thead>
     330: invokevirtual #55                 // Method java/io/PrintWriter.println:(Ljava/lang/String;)V
     333: aload_3
     334: ldc           #76                 // String     <tr>
     336: invokevirtual #55                 // Method java/io/PrintWriter.println:(Ljava/lang/String;)V
     339: aload_3
     340: ldc           #77                 // String         <th>Error</th>
     342: invokevirtual #55                 // Method java/io/PrintWriter.println:(Ljava/lang/String;)V
     345: aload_3
     346: ldc           #78                 // String     </tr>
     348: invokevirtual #55                 // Method java/io/PrintWriter.println:(Ljava/lang/String;)V
     351: aload_3
     352: ldc           #79                 // String </thead>
     354: invokevirtual #55                 // Method java/io/PrintWriter.println:(Ljava/lang/String;)V
     357: aload_3
     358: ldc           #80                 // String <tbody>
     360: invokevirtual #55                 // Method java/io/PrintWriter.println:(Ljava/lang/String;)V
     363: aload_3
     364: ldc           #76                 // String     <tr>
     366: invokevirtual #55                 // Method java/io/PrintWriter.println:(Ljava/lang/String;)V
     369: aload_3
     370: ldc           #81                 // String         <td>
     372: invokevirtual #55                 // Method java/io/PrintWriter.println:(Ljava/lang/String;)V
     375: aload_3
     376: new           #59                 // class java/lang/StringBuilder
     379: dup
     380: invokespecial #60                 // Method java/lang/StringBuilder."<init>":()V
     383: ldc           #82                 // String
     385: invokevirtual #63                 // Method java/lang/StringBuilder.append:(Ljava/lang/String;)Ljava/lang/StringBuilder;
     388: aload         10
     390: ldc           #83                 // String <
     392: ldc           #84                 // String &lt;
     394: invokevirtual #85                 // Method java/lang/String.replace:(Ljava/lang/CharSequence;Ljava/lang/CharSequence;)Ljava/lang/String;
     397: ldc           #86                 // String >
     399: ldc           #84                 // String &lt;
     401: invokevirtual #85                 // Method java/lang/String.replace:(Ljava/lang/CharSequence;Ljava/lang/CharSequence;)Ljava/lang/String;
     404: ldc           #87                 // String \n
     406: ldc           #88                 // String <br/>
     408: invokevirtual #85                 // Method java/lang/String.replace:(Ljava/lang/CharSequence;Ljava/lang/CharSequence;)Ljava/lang/String;
     411: invokevirtual #63                 // Method java/lang/StringBuilder.append:(Ljava/lang/String;)Ljava/lang/StringBuilder;
     414: invokevirtual #66                 // Method java/lang/StringBuilder.toString:()Ljava/lang/String;
     417: invokevirtual #55                 // Method java/io/PrintWriter.println:(Ljava/lang/String;)V
     420: aload_3
     421: ldc           #89                 // String         </td>
     423: invokevirtual #55                 // Method java/io/PrintWriter.println:(Ljava/lang/String;)V
     426: aload_3
     427: ldc           #78                 // String     </tr>
     429: invokevirtual #55                 // Method java/io/PrintWriter.println:(Ljava/lang/String;)V
     432: aload_3
     433: ldc           #90                 // String </tbody>
     435: invokevirtual #55                 // Method java/io/PrintWriter.println:(Ljava/lang/String;)V
     438: aload_3
     439: ldc           #91                 // String </table>
     441: invokevirtual #55                 // Method java/io/PrintWriter.println:(Ljava/lang/String;)V
     444: aload_3
     445: ldc           #88                 // String <br/>
     447: invokevirtual #55                 // Method java/io/PrintWriter.println:(Ljava/lang/String;)V
     450: goto          459
     453: aload_3
     454: aload         10
     456: invokevirtual #55                 // Method java/io/PrintWriter.println:(Ljava/lang/String;)V
     459: aload         8
     461: ifnull        660
     464: iload         5
     466: ifeq          598
     469: aload         8
     471: invokevirtual #92                 // Method com/alibaba/dubbo/container/page/Page.getNavigation:()Ljava/lang/String;
     474: astore        9
     476: aload         9
     478: ifnull        489
     481: aload         9
     483: invokevirtual #17                 // Method java/lang/String.length:()I
     486: ifne          535
     489: ldc           #21                 // class com/alibaba/dubbo/container/page/PageHandler
     491: invokestatic  #22                 // Method org/apache/dubbo/common/extension/ExtensionLoader.getExtensionLoader:(Ljava/lang/Class;)Lorg/apache/dubbo/common/extension/ExtensionLoader;
     494: aload         7
     496: invokevirtual #29                 // Method org/apache/dubbo/common/extension/ExtensionLoader.getExtensionName:(Ljava/lang/Object;)Ljava/lang/String;
     499: astore        9
     501: new           #59                 // class java/lang/StringBuilder
     504: dup
     505: invokespecial #60                 // Method java/lang/StringBuilder."<init>":()V
     508: aload         9
     510: iconst_0
     511: iconst_1
     512: invokevirtual #49                 // Method java/lang/String.substring:(II)Ljava/lang/String;
     515: invokevirtual #93                 // Method java/lang/String.toUpperCase:()Ljava/lang/String;
     518: invokevirtual #63                 // Method java/lang/StringBuilder.append:(Ljava/lang/String;)Ljava/lang/StringBuilder;
     521: aload         9
     523: iconst_1
     524: invokevirtual #46                 // Method java/lang/String.substring:(I)Ljava/lang/String;
     527: invokevirtual #63                 // Method java/lang/StringBuilder.append:(Ljava/lang/String;)Ljava/lang/StringBuilder;
     530: invokevirtual #66                 // Method java/lang/StringBuilder.toString:()Ljava/lang/String;
     533: astore        9
     535: ldc           #44                 // String index
     537: aload         4
     539: invokevirtual #43                 // Method java/lang/String.equals:(Ljava/lang/Object;)Z
     542: ifne          567
     545: new           #59                 // class java/lang/StringBuilder
     548: dup
     549: invokespecial #60                 // Method java/lang/StringBuilder."<init>":()V
     552: ldc           #94                 // String <a href=\"/\">Home</a> &gt;
     554: invokevirtual #63                 // Method java/lang/StringBuilder.append:(Ljava/lang/String;)Ljava/lang/StringBuilder;
     557: aload         9
     559: invokevirtual #63                 // Method java/lang/StringBuilder.append:(Ljava/lang/String;)Ljava/lang/StringBuilder;
     562: invokevirtual #66                 // Method java/lang/StringBuilder.toString:()Ljava/lang/String;
     565: astore        9
     567: aload_0
     568: aload_1
     569: aload_3
     570: aload         9
     572: invokevirtual #95                 // Method writeMenu:(Ljavax/servlet/http/HttpServletRequest;Ljava/io/PrintWriter;Ljava/lang/String;)V
     575: aload_0
     576: aload_3
     577: aload         8
     579: invokevirtual #96                 // Method com/alibaba/dubbo/container/page/Page.getTitle:()Ljava/lang/String;
     582: aload         8
     584: invokevirtual #97                 // Method com/alibaba/dubbo/container/page/Page.getColumns:()Ljava/util/List;
     587: aload         8
     589: invokevirtual #98                 // Method com/alibaba/dubbo/container/page/Page.getRows:()Ljava/util/List;
     592: invokevirtual #99                 // Method writeTable:(Ljava/io/PrintWriter;Ljava/lang/String;Ljava/util/List;Ljava/util/List;)V
     595: goto          660
     598: aload         8
     600: invokevirtual #98                 // Method com/alibaba/dubbo/container/page/Page.getRows:()Ljava/util/List;
     603: invokeinterface #100,  1          // InterfaceMethod java/util/List.size:()I
     608: ifle          660
     611: aload         8
     613: invokevirtual #98                 // Method com/alibaba/dubbo/container/page/Page.getRows:()Ljava/util/List;
     616: iconst_0
     617: invokeinterface #101,  2          // InterfaceMethod java/util/List.get:(I)Ljava/lang/Object;
     622: checkcast     #102                // class java/util/List
     625: invokeinterface #100,  1          // InterfaceMethod java/util/List.size:()I
     630: ifle          660
     633: aload_3
     634: aload         8
     636: invokevirtual #98                 // Method com/alibaba/dubbo/container/page/Page.getRows:()Ljava/util/List;
     639: iconst_0
     640: invokeinterface #101,  2          // InterfaceMethod java/util/List.get:(I)Ljava/lang/Object;
     645: checkcast     #102                // class java/util/List
     648: iconst_0
     649: invokeinterface #101,  2          // InterfaceMethod java/util/List.get:(I)Ljava/lang/Object;
     654: checkcast     #27                 // class java/lang/String
     657: invokevirtual #55                 // Method java/io/PrintWriter.println:(Ljava/lang/String;)V
     660: goto          813
     663: iload         5
     665: ifeq          784
     668: aload_3
     669: ldc           #74                 // String <table>
     671: invokevirtual #55                 // Method java/io/PrintWriter.println:(Ljava/lang/String;)V
     674: aload_3
     675: ldc           #75                 // String <thead>
     677: invokevirtual #55                 // Method java/io/PrintWriter.println:(Ljava/lang/String;)V
     680: aload_3
     681: ldc           #76                 // String     <tr>
     683: invokevirtual #55                 // Method java/io/PrintWriter.println:(Ljava/lang/String;)V
     686: aload_3
     687: ldc           #77                 // String         <th>Error</th>
     689: invokevirtual #55                 // Method java/io/PrintWriter.println:(Ljava/lang/String;)V
     692: aload_3
     693: ldc           #78                 // String     </tr>
     695: invokevirtual #55                 // Method java/io/PrintWriter.println:(Ljava/lang/String;)V
     698: aload_3
     699: ldc           #79                 // String </thead>
     701: invokevirtual #55                 // Method java/io/PrintWriter.println:(Ljava/lang/String;)V
     704: aload_3
     705: ldc           #80                 // String <tbody>
     707: invokevirtual #55                 // Method java/io/PrintWriter.println:(Ljava/lang/String;)V
     710: aload_3
     711: ldc           #76                 // String     <tr>
     713: invokevirtual #55                 // Method java/io/PrintWriter.println:(Ljava/lang/String;)V
     716: aload_3
     717: ldc           #81                 // String         <td>
     719: invokevirtual #55                 // Method java/io/PrintWriter.println:(Ljava/lang/String;)V
     722: aload_3
     723: new           #59                 // class java/lang/StringBuilder
     726: dup
     727: invokespecial #60                 // Method java/lang/StringBuilder."<init>":()V
     730: ldc           #103                // String             Not found
     732: invokevirtual #63                 // Method java/lang/StringBuilder.append:(Ljava/lang/String;)Ljava/lang/StringBuilder;
     735: aload         4
     737: invokevirtual #63                 // Method java/lang/StringBuilder.append:(Ljava/lang/String;)Ljava/lang/StringBuilder;
     740: ldc           #104                // String  page. Please goto <a href=\"/\">Home</a> page.
     742: invokevirtual #63                 // Method java/lang/StringBuilder.append:(Ljava/lang/String;)Ljava/lang/StringBuilder;
     745: invokevirtual #66                 // Method java/lang/StringBuilder.toString:()Ljava/lang/String;
     748: invokevirtual #55                 // Method java/io/PrintWriter.println:(Ljava/lang/String;)V
     751: aload_3
     752: ldc           #89                 // String         </td>
     754: invokevirtual #55                 // Method java/io/PrintWriter.println:(Ljava/lang/String;)V
     757: aload_3
     758: ldc           #78                 // String     </tr>
     760: invokevirtual #55                 // Method java/io/PrintWriter.println:(Ljava/lang/String;)V
     763: aload_3
     764: ldc           #90                 // String </tbody>
     766: invokevirtual #55                 // Method java/io/PrintWriter.println:(Ljava/lang/String;)V
     769: aload_3
     770: ldc           #91                 // String </table>
     772: invokevirtual #55                 // Method java/io/PrintWriter.println:(Ljava/lang/String;)V
     775: aload_3
     776: ldc           #88                 // String <br/>
     778: invokevirtual #55                 // Method java/io/PrintWriter.println:(Ljava/lang/String;)V
     781: goto          813
     784: aload_3
     785: new           #59                 // class java/lang/StringBuilder
     788: dup
     789: invokespecial #60                 // Method java/lang/StringBuilder."<init>":()V
     792: ldc           #105                // String Not found
     794: invokevirtual #63                 // Method java/lang/StringBuilder.append:(Ljava/lang/String;)Ljava/lang/StringBuilder;
     797: aload         4
     799: invokevirtual #63                 // Method java/lang/StringBuilder.append:(Ljava/lang/String;)Ljava/lang/StringBuilder;
     802: ldc           #106                // String  page.
     804: invokevirtual #63                 // Method java/lang/StringBuilder.append:(Ljava/lang/String;)Ljava/lang/StringBuilder;
     807: invokevirtual #66                 // Method java/lang/StringBuilder.toString:()Ljava/lang/String;
     810: invokevirtual #55                 // Method java/io/PrintWriter.println:(Ljava/lang/String;)V
     813: iload         5
     815: ifeq          824
     818: aload_3
     819: ldc           #107                // String </body></html>
     821: invokevirtual #55                 // Method java/io/PrintWriter.println:(Ljava/lang/String;)V
     824: aload_3
     825: invokevirtual #108                // Method java/io/PrintWriter.flush:()V
     828: return
    Exception table:
       from    to  target type
         194   277   280   Class java/lang/Throwable

  protected final void writeMenu(javax.servlet.http.HttpServletRequest, java.io.PrintWriter, java.lang.String);
    Code:
       0: aload_2
       1: ldc           #74                 // String <table>
       3: invokevirtual #55                 // Method java/io/PrintWriter.println:(Ljava/lang/String;)V
       6: aload_2
       7: ldc           #75                 // String <thead>
       9: invokevirtual #55                 // Method java/io/PrintWriter.println:(Ljava/lang/String;)V
      12: aload_2
      13: ldc           #76                 // String     <tr>
      15: invokevirtual #55                 // Method java/io/PrintWriter.println:(Ljava/lang/String;)V
      18: aload_0
      19: getfield      #10                 // Field menus:Ljava/util/List;
      22: invokeinterface #109,  1          // InterfaceMethod java/util/List.iterator:()Ljava/util/Iterator;
      27: astore        4
      29: aload         4
      31: invokeinterface #25,  1           // InterfaceMethod java/util/Iterator.hasNext:()Z
      36: ifeq          125
      39: aload         4
      41: invokeinterface #26,  1           // InterfaceMethod java/util/Iterator.next:()Ljava/lang/Object;
      46: checkcast     #21                 // class com/alibaba/dubbo/container/page/PageHandler
      49: astore        5
      51: ldc           #21                 // class com/alibaba/dubbo/container/page/PageHandler
      53: invokestatic  #22                 // Method org/apache/dubbo/common/extension/ExtensionLoader.getExtensionLoader:(Ljava/lang/Class;)Lorg/apache/dubbo/common/extension/ExtensionLoader;
      56: aload         5
      58: invokevirtual #29                 // Method org/apache/dubbo/common/extension/ExtensionLoader.getExtensionName:(Ljava/lang/Object;)Ljava/lang/String;
      61: astore        6
      63: aload         5
      65: invokevirtual #31                 // Method java/lang/Object.getClass:()Ljava/lang/Class;
      68: ldc           #32                 // class com/alibaba/dubbo/container/page/Menu
      70: invokevirtual #33                 // Method java/lang/Class.getAnnotation:(Ljava/lang/Class;)Ljava/lang/annotation/Annotation;
      73: checkcast     #32                 // class com/alibaba/dubbo/container/page/Menu
      76: astore        7
      78: aload_2
      79: new           #59                 // class java/lang/StringBuilder
      82: dup
      83: invokespecial #60                 // Method java/lang/StringBuilder."<init>":()V
      86: ldc           #110                // String         <th><a href=\"
      88: invokevirtual #63                 // Method java/lang/StringBuilder.append:(Ljava/lang/String;)Ljava/lang/StringBuilder;
      91: aload         6
      93: invokevirtual #63                 // Method java/lang/StringBuilder.append:(Ljava/lang/String;)Ljava/lang/StringBuilder;
      96: ldc           #111                // String .html\">
      98: invokevirtual #63                 // Method java/lang/StringBuilder.append:(Ljava/lang/String;)Ljava/lang/StringBuilder;
     101: aload         7
     103: invokeinterface #112,  1          // InterfaceMethod com/alibaba/dubbo/container/page/Menu.name:()Ljava/lang/String;
     108: invokevirtual #63                 // Method java/lang/StringBuilder.append:(Ljava/lang/String;)Ljava/lang/StringBuilder;
     111: ldc           #113                // String </a></th>
     113: invokevirtual #63                 // Method java/lang/StringBuilder.append:(Ljava/lang/String;)Ljava/lang/StringBuilder;
     116: invokevirtual #66                 // Method java/lang/StringBuilder.toString:()Ljava/lang/String;
     119: invokevirtual #55                 // Method java/io/PrintWriter.println:(Ljava/lang/String;)V
     122: goto          29
     125: aload_2
     126: ldc           #78                 // String     </tr>
     128: invokevirtual #55                 // Method java/io/PrintWriter.println:(Ljava/lang/String;)V
     131: aload_2
     132: ldc           #79                 // String </thead>
     134: invokevirtual #55                 // Method java/io/PrintWriter.println:(Ljava/lang/String;)V
     137: aload_2
     138: ldc           #80                 // String <tbody>
     140: invokevirtual #55                 // Method java/io/PrintWriter.println:(Ljava/lang/String;)V
     143: aload_2
     144: ldc           #76                 // String     <tr>
     146: invokevirtual #55                 // Method java/io/PrintWriter.println:(Ljava/lang/String;)V
     149: aload_2
     150: new           #59                 // class java/lang/StringBuilder
     153: dup
     154: invokespecial #60                 // Method java/lang/StringBuilder."<init>":()V
     157: ldc           #114                // String         <td style=\"text-align: left\" colspan=\"
     159: invokevirtual #63                 // Method java/lang/StringBuilder.append:(Ljava/lang/String;)Ljava/lang/StringBuilder;
     162: aload_0
     163: getfield      #10                 // Field menus:Ljava/util/List;
     166: invokeinterface #100,  1          // InterfaceMethod java/util/List.size:()I
     171: invokevirtual #115                // Method java/lang/StringBuilder.append:(I)Ljava/lang/StringBuilder;
     174: ldc           #116                // String \">
     176: invokevirtual #63                 // Method java/lang/StringBuilder.append:(Ljava/lang/String;)Ljava/lang/StringBuilder;
     179: invokevirtual #66                 // Method java/lang/StringBuilder.toString:()Ljava/lang/String;
     182: invokevirtual #55                 // Method java/io/PrintWriter.println:(Ljava/lang/String;)V
     185: aload_2
     186: aload_3
     187: invokevirtual #55                 // Method java/io/PrintWriter.println:(Ljava/lang/String;)V
     190: aload_2
     191: ldc           #89                 // String         </td>
     193: invokevirtual #55                 // Method java/io/PrintWriter.println:(Ljava/lang/String;)V
     196: aload_2
     197: ldc           #78                 // String     </tr>
     199: invokevirtual #55                 // Method java/io/PrintWriter.println:(Ljava/lang/String;)V
     202: aload_2
     203: ldc           #90                 // String </tbody>
     205: invokevirtual #55                 // Method java/io/PrintWriter.println:(Ljava/lang/String;)V
     208: aload_2
     209: ldc           #91                 // String </table>
     211: invokevirtual #55                 // Method java/io/PrintWriter.println:(Ljava/lang/String;)V
     214: aload_2
     215: ldc           #88                 // String <br/>
     217: invokevirtual #55                 // Method java/io/PrintWriter.println:(Ljava/lang/String;)V
     220: return

  protected final void writeTable(java.io.PrintWriter, java.lang.String, java.util.List<java.lang.String>, java.util.List<java.util.List<java.lang.String>>);
    Code:
       0: aload_0
       1: getfield      #4                  // Field random:Ljava/util/Random;
       4: invokevirtual #117                // Method java/util/Random.nextInt:()I
       7: istore        5
       9: aload_3
      10: ifnonnull     51
      13: aload         4
      15: ifnull        28
      18: aload         4
      20: invokeinterface #100,  1          // InterfaceMethod java/util/List.size:()I
      25: ifne          32
      28: iconst_0
      29: goto          57
      32: aload         4
      34: iconst_0
      35: invokeinterface #101,  2          // InterfaceMethod java/util/List.get:(I)Ljava/lang/Object;
      40: checkcast     #102                // class java/util/List
      43: invokeinterface #100,  1          // InterfaceMethod java/util/List.size:()I
      48: goto          57
      51: aload_3
      52: invokeinterface #100,  1          // InterfaceMethod java/util/List.size:()I
      57: istore        6
      59: aload         4
      61: ifnonnull     68
      64: iconst_0
      65: goto          75
      68: aload         4
      70: invokeinterface #100,  1          // InterfaceMethod java/util/List.size:()I
      75: istore        7
      77: aload_1
      78: ldc           #74                 // String <table>
      80: invokevirtual #55                 // Method java/io/PrintWriter.println:(Ljava/lang/String;)V
      83: aload_1
      84: ldc           #75                 // String <thead>
      86: invokevirtual #55                 // Method java/io/PrintWriter.println:(Ljava/lang/String;)V
      89: aload_1
      90: ldc           #76                 // String     <tr>
      92: invokevirtual #55                 // Method java/io/PrintWriter.println:(Ljava/lang/String;)V
      95: aload_1
      96: new           #59                 // class java/lang/StringBuilder
      99: dup
     100: invokespecial #60                 // Method java/lang/StringBuilder."<init>":()V
     103: ldc           #118                // String         <th colspan=\"
     105: invokevirtual #63                 // Method java/lang/StringBuilder.append:(Ljava/lang/String;)Ljava/lang/StringBuilder;
     108: iload         6
     110: invokevirtual #115                // Method java/lang/StringBuilder.append:(I)Ljava/lang/StringBuilder;
     113: ldc           #116                // String \">
     115: invokevirtual #63                 // Method java/lang/StringBuilder.append:(Ljava/lang/String;)Ljava/lang/StringBuilder;
     118: aload_2
     119: invokevirtual #63                 // Method java/lang/StringBuilder.append:(Ljava/lang/String;)Ljava/lang/StringBuilder;
     122: ldc           #119                // String </th>
     124: invokevirtual #63                 // Method java/lang/StringBuilder.append:(Ljava/lang/String;)Ljava/lang/StringBuilder;
     127: invokevirtual #66                 // Method java/lang/StringBuilder.toString:()Ljava/lang/String;
     130: invokevirtual #55                 // Method java/io/PrintWriter.println:(Ljava/lang/String;)V
     133: aload_1
     134: ldc           #78                 // String     </tr>
     136: invokevirtual #55                 // Method java/io/PrintWriter.println:(Ljava/lang/String;)V
     139: aload_3
     140: ifnull        342
     143: aload_3
     144: invokeinterface #100,  1          // InterfaceMethod java/util/List.size:()I
     149: ifle          342
     152: aload_1
     153: ldc           #76                 // String     <tr>
     155: invokevirtual #55                 // Method java/io/PrintWriter.println:(Ljava/lang/String;)V
     158: iconst_0
     159: istore        8
     161: iload         8
     163: aload_3
     164: invokeinterface #100,  1          // InterfaceMethod java/util/List.size:()I
     169: if_icmpge     336
     172: aload_3
     173: iload         8
     175: invokeinterface #101,  2          // InterfaceMethod java/util/List.get:(I)Ljava/lang/Object;
     180: checkcast     #27                 // class java/lang/String
     183: astore        9
     185: aload         9
     187: ldc           #120                // String :
     189: invokevirtual #48                 // Method java/lang/String.endsWith:(Ljava/lang/String;)Z
     192: ifeq          301
     195: new           #59                 // class java/lang/StringBuilder
     198: dup
     199: invokespecial #60                 // Method java/lang/StringBuilder."<init>":()V
     202: aload         9
     204: invokevirtual #63                 // Method java/lang/StringBuilder.append:(Ljava/lang/String;)Ljava/lang/StringBuilder;
     207: ldc           #121                // String  <input type=\"text\" id=\"in_
     209: invokevirtual #63                 // Method java/lang/StringBuilder.append:(Ljava/lang/String;)Ljava/lang/StringBuilder;
     212: iload         5
     214: invokevirtual #115                // Method java/lang/StringBuilder.append:(I)Ljava/lang/StringBuilder;
     217: ldc           #122                // String _
     219: invokevirtual #63                 // Method java/lang/StringBuilder.append:(Ljava/lang/String;)Ljava/lang/StringBuilder;
     222: iload         8
     224: invokevirtual #115                // Method java/lang/StringBuilder.append:(I)Ljava/lang/StringBuilder;
     227: ldc           #123                // String \" onkeyup=\"for (var i = 0; i <
     229: invokevirtual #63                 // Method java/lang/StringBuilder.append:(Ljava/lang/String;)Ljava/lang/StringBuilder;
     232: iload         7
     234: invokevirtual #115                // Method java/lang/StringBuilder.append:(I)Ljava/lang/StringBuilder;
     237: ldc           #124                // String ; i ++) { var m = true; for (var j = 0; j <
     239: invokevirtual #63                 // Method java/lang/StringBuilder.append:(Ljava/lang/String;)Ljava/lang/StringBuilder;
     242: aload_3
     243: invokeinterface #100,  1          // InterfaceMethod java/util/List.size:()I
     248: invokevirtual #115                // Method java/lang/StringBuilder.append:(I)Ljava/lang/StringBuilder;
     251: ldc           #125                // String ; j ++) { if (document.getElementById(\'in_
     253: invokevirtual #63                 // Method java/lang/StringBuilder.append:(Ljava/lang/String;)Ljava/lang/StringBuilder;
     256: iload         5
     258: invokevirtual #115                // Method java/lang/StringBuilder.append:(I)Ljava/lang/StringBuilder;
     261: ldc           #126                // String _\' + j)) { var iv = document.getElementById(\'in_
     263: invokevirtual #63                 // Method java/lang/StringBuilder.append:(Ljava/lang/String;)Ljava/lang/StringBuilder;
     266: iload         5
     268: invokevirtual #115                // Method java/lang/StringBuilder.append:(I)Ljava/lang/StringBuilder;
     271: ldc           #127                // String _\' + j).value; var tv = document.getElementById(\'td_
     273: invokevirtual #63                 // Method java/lang/StringBuilder.append:(Ljava/lang/String;)Ljava/lang/StringBuilder;
     276: iload         5
     278: invokevirtual #115                // Method java/lang/StringBuilder.append:(I)Ljava/lang/StringBuilder;
     281: ldc           #128                // String _\' + i + \'_\' + j).innerHTML; if (iv.length > 0 && (tv.length < iv.length || tv.indexOf(iv) == -1)) { m = false; break; } } } document.getElementById(\'tr_
     283: invokevirtual #63                 // Method java/lang/StringBuilder.append:(Ljava/lang/String;)Ljava/lang/StringBuilder;
     286: iload         5
     288: invokevirtual #115                // Method java/lang/StringBuilder.append:(I)Ljava/lang/StringBuilder;
     291: ldc           #129                // String _\' + i).style.display = (m ? \'\' : \'none\');}\" sytle=\"width: 100%\" />
     293: invokevirtual #63                 // Method java/lang/StringBuilder.append:(Ljava/lang/String;)Ljava/lang/StringBuilder;
     296: invokevirtual #66                 // Method java/lang/StringBuilder.toString:()Ljava/lang/String;
     299: astore        9
     301: aload_1
     302: new           #59                 // class java/lang/StringBuilder
     305: dup
     306: invokespecial #60                 // Method java/lang/StringBuilder."<init>":()V
     309: ldc           #81                 // String         <td>
     311: invokevirtual #63                 // Method java/lang/StringBuilder.append:(Ljava/lang/String;)Ljava/lang/StringBuilder;
     314: aload         9
     316: invokevirtual #63                 // Method java/lang/StringBuilder.append:(Ljava/lang/String;)Ljava/lang/StringBuilder;
     319: ldc           #130                // String </td>
     321: invokevirtual #63                 // Method java/lang/StringBuilder.append:(Ljava/lang/String;)Ljava/lang/StringBuilder;
     324: invokevirtual #66                 // Method java/lang/StringBuilder.toString:()Ljava/lang/String;
     327: invokevirtual #55                 // Method java/io/PrintWriter.println:(Ljava/lang/String;)V
     330: iinc          8, 1
     333: goto          161
     336: aload_1
     337: ldc           #78                 // String     </tr>
     339: invokevirtual #55                 // Method java/io/PrintWriter.println:(Ljava/lang/String;)V
     342: aload_1
     343: ldc           #79                 // String </thead>
     345: invokevirtual #55                 // Method java/io/PrintWriter.println:(Ljava/lang/String;)V
     348: aload         4
     350: ifnull        559
     353: aload         4
     355: invokeinterface #100,  1          // InterfaceMethod java/util/List.size:()I
     360: ifle          559
     363: aload_1
     364: ldc           #80                 // String <tbody>
     366: invokevirtual #55                 // Method java/io/PrintWriter.println:(Ljava/lang/String;)V
     369: iconst_0
     370: istore        8
     372: aload         4
     374: invokeinterface #109,  1          // InterfaceMethod java/util/List.iterator:()Ljava/util/Iterator;
     379: astore        9
     381: aload         9
     383: invokeinterface #25,  1           // InterfaceMethod java/util/Iterator.hasNext:()Z
     388: ifeq          553
     391: aload         9
     393: invokeinterface #26,  1           // InterfaceMethod java/util/Iterator.next:()Ljava/lang/Object;
     398: checkcast     #131                // class java/util/Collection
     401: astore        10
     403: aload_1
     404: new           #59                 // class java/lang/StringBuilder
     407: dup
     408: invokespecial #60                 // Method java/lang/StringBuilder."<init>":()V
     411: ldc           #132                // String     <tr id=\"tr_
     413: invokevirtual #63                 // Method java/lang/StringBuilder.append:(Ljava/lang/String;)Ljava/lang/StringBuilder;
     416: iload         5
     418: invokevirtual #115                // Method java/lang/StringBuilder.append:(I)Ljava/lang/StringBuilder;
     421: ldc           #122                // String _
     423: invokevirtual #63                 // Method java/lang/StringBuilder.append:(Ljava/lang/String;)Ljava/lang/StringBuilder;
     426: iload         8
     428: invokevirtual #115                // Method java/lang/StringBuilder.append:(I)Ljava/lang/StringBuilder;
     431: ldc           #116                // String \">
     433: invokevirtual #63                 // Method java/lang/StringBuilder.append:(Ljava/lang/String;)Ljava/lang/StringBuilder;
     436: invokevirtual #66                 // Method java/lang/StringBuilder.toString:()Ljava/lang/String;
     439: invokevirtual #55                 // Method java/io/PrintWriter.println:(Ljava/lang/String;)V
     442: iconst_0
     443: istore        11
     445: aload         10
     447: invokeinterface #24,  1           // InterfaceMethod java/util/Collection.iterator:()Ljava/util/Iterator;
     452: astore        12
     454: aload         12
     456: invokeinterface #25,  1           // InterfaceMethod java/util/Iterator.hasNext:()Z
     461: ifeq          541
     464: aload         12
     466: invokeinterface #26,  1           // InterfaceMethod java/util/Iterator.next:()Ljava/lang/Object;
     471: checkcast     #27                 // class java/lang/String
     474: astore        13
     476: aload_1
     477: new           #59                 // class java/lang/StringBuilder
     480: dup
     481: invokespecial #60                 // Method java/lang/StringBuilder."<init>":()V
     484: ldc           #133                // String         <td id=\"td_
     486: invokevirtual #63                 // Method java/lang/StringBuilder.append:(Ljava/lang/String;)Ljava/lang/StringBuilder;
     489: iload         5
     491: invokevirtual #115                // Method java/lang/StringBuilder.append:(I)Ljava/lang/StringBuilder;
     494: ldc           #122                // String _
     496: invokevirtual #63                 // Method java/lang/StringBuilder.append:(Ljava/lang/String;)Ljava/lang/StringBuilder;
     499: iload         8
     501: invokevirtual #115                // Method java/lang/StringBuilder.append:(I)Ljava/lang/StringBuilder;
     504: ldc           #122                // String _
     506: invokevirtual #63                 // Method java/lang/StringBuilder.append:(Ljava/lang/String;)Ljava/lang/StringBuilder;
     509: iload         11
     511: invokevirtual #115                // Method java/lang/StringBuilder.append:(I)Ljava/lang/StringBuilder;
     514: ldc           #134                // String \" style=\"display: ;\">
     516: invokevirtual #63                 // Method java/lang/StringBuilder.append:(Ljava/lang/String;)Ljava/lang/StringBuilder;
     519: aload         13
     521: invokevirtual #63                 // Method java/lang/StringBuilder.append:(Ljava/lang/String;)Ljava/lang/StringBuilder;
     524: ldc           #130                // String </td>
     526: invokevirtual #63                 // Method java/lang/StringBuilder.append:(Ljava/lang/String;)Ljava/lang/StringBuilder;
     529: invokevirtual #66                 // Method java/lang/StringBuilder.toString:()Ljava/lang/String;
     532: invokevirtual #55                 // Method java/io/PrintWriter.println:(Ljava/lang/String;)V
     535: iinc          11, 1
     538: goto          454
     541: aload_1
     542: ldc           #78                 // String     </tr>
     544: invokevirtual #55                 // Method java/io/PrintWriter.println:(Ljava/lang/String;)V
     547: iinc          8, 1
     550: goto          381
     553: aload_1
     554: ldc           #90                 // String </tbody>
     556: invokevirtual #55                 // Method java/io/PrintWriter.println:(Ljava/lang/String;)V
     559: aload_1
     560: ldc           #91                 // String </table>
     562: invokevirtual #55                 // Method java/io/PrintWriter.println:(Ljava/lang/String;)V
     565: aload_1
     566: ldc           #88                 // String <br/>
     568: invokevirtual #55                 // Method java/io/PrintWriter.println:(Ljava/lang/String;)V
     571: return

  static {};
    Code:
       0: ldc           #135                // class com/alibaba/dubbo/container/page/PageServlet
       2: invokestatic  #136                // Method org/apache/dubbo/common/logger/LoggerFactory.getLogger:(Ljava/lang/Class;)Lorg/apache/dubbo/common/logger/Logger;
       5: putstatic     #70                 // Field logger:Lorg/apache/dubbo/common/logger/Logger;
       8: return
}
