Compiled from "CommonFileUtils.java"
public class jadx.api.plugins.utils.CommonFileUtils {
  private static final org.slf4j.Logger LOG;

  public static final java.io.File CWD;

  public static final java.nio.file.Path CWD_PATH;

  private static final java.util.Set<java.lang.String> ZIP_FILE_EXTS;

  public jadx.api.plugins.utils.CommonFileUtils();
    Code:
       0: aload_0
       1: invokespecial #1                  // Method java/lang/Object."<init>":()V
       4: return

  private static java.io.File getCWD();
    Code:
       0: new           #2                  // class java/io/File
       3: dup
       4: ldc           #3                  // String .
       6: invokespecial #4                  // Method java/io/File."<init>":(Ljava/lang/String;)V
       9: invokevirtual #5                  // Method java/io/File.getCanonicalFile:()Ljava/io/File;
      12: areturn
      13: astore_0
      14: new           #7                  // class java/lang/RuntimeException
      17: dup
      18: ldc           #8                  // String Failed to init current working dir constant
      20: aload_0
      21: invokespecial #9                  // Method java/lang/RuntimeException."<init>":(Ljava/lang/String;Ljava/lang/Throwable;)V
      24: athrow
    Exception table:
       from    to  target type
           0    12    13   Class java/io/IOException

  public static java.nio.file.Path saveToTempFile(java.io.InputStream, java.lang.String) throws java.io.IOException;
    Code:
       0: aconst_null
       1: aload_0
       2: aload_1
       3: invokestatic  #10                 // Method saveToTempFile:([BLjava/io/InputStream;Ljava/lang/String;)Ljava/nio/file/Path;
       6: areturn

  public static java.nio.file.Path saveToTempFile(byte[], java.io.InputStream, java.lang.String) throws java.io.IOException;
    Code:
       0: ldc           #11                 // String jadx-temp-
       2: aload_2
       3: iconst_0
       4: anewarray     #12                 // class java/nio/file/attribute/FileAttribute
       7: invokestatic  #13                 // Method java/nio/file/Files.createTempFile:(Ljava/lang/String;Ljava/lang/String;[Ljava/nio/file/attribute/FileAttribute;)Ljava/nio/file/Path;
      10: astore_3
      11: aload_3
      12: iconst_0
      13: anewarray     #14                 // class java/nio/file/OpenOption
      16: invokestatic  #15                 // Method java/nio/file/Files.newOutputStream:(Ljava/nio/file/Path;[Ljava/nio/file/OpenOption;)Ljava/io/OutputStream;
      19: astore        4
      21: aconst_null
      22: astore        5
      24: aload_0
      25: ifnull        34
      28: aload         4
      30: aload_0
      31: invokevirtual #16                 // Method java/io/OutputStream.write:([B)V
      34: aload_1
      35: aload         4
      37: invokestatic  #17                 // Method copyStream:(Ljava/io/InputStream;Ljava/io/OutputStream;)V
      40: aload         4
      42: ifnull        127
      45: aload         5
      47: ifnull        70
      50: aload         4
      52: invokevirtual #18                 // Method java/io/OutputStream.close:()V
      55: goto          127
      58: astore        6
      60: aload         5
      62: aload         6
      64: invokevirtual #20                 // Method java/lang/Throwable.addSuppressed:(Ljava/lang/Throwable;)V
      67: goto          127
      70: aload         4
      72: invokevirtual #18                 // Method java/io/OutputStream.close:()V
      75: goto          127
      78: astore        6
      80: aload         6
      82: astore        5
      84: aload         6
      86: athrow
      87: astore        7
      89: aload         4
      91: ifnull        124
      94: aload         5
      96: ifnull        119
      99: aload         4
     101: invokevirtual #18                 // Method java/io/OutputStream.close:()V
     104: goto          124
     107: astore        8
     109: aload         5
     111: aload         8
     113: invokevirtual #20                 // Method java/lang/Throwable.addSuppressed:(Ljava/lang/Throwable;)V
     116: goto          124
     119: aload         4
     121: invokevirtual #18                 // Method java/io/OutputStream.close:()V
     124: aload         7
     126: athrow
     127: goto          144
     130: astore        4
     132: new           #6                  // class java/io/IOException
     135: dup
     136: ldc           #22                 // String Failed to save temp file
     138: aload         4
     140: invokespecial #23                 // Method java/io/IOException."<init>":(Ljava/lang/String;Ljava/lang/Throwable;)V
     143: athrow
     144: aload_3
     145: areturn
    Exception table:
       from    to  target type
          50    55    58   Class java/lang/Throwable
          24    40    78   Class java/lang/Throwable
          24    40    87   any
          99   104   107   Class java/lang/Throwable
          78    89    87   any
          11   127   130   Class java/lang/Exception

  public static boolean safeDeleteFile(java.io.File);
    Code:
       0: aload_0
       1: invokevirtual #24                 // Method java/io/File.delete:()Z
       4: ireturn
       5: astore_1
       6: getstatic     #25                 // Field LOG:Lorg/slf4j/Logger;
       9: ldc           #26                 // String Failed to delete file: {}
      11: aload_0
      12: aload_1
      13: invokeinterface #27,  4           // InterfaceMethod org/slf4j/Logger.warn:(Ljava/lang/String;Ljava/lang/Object;Ljava/lang/Object;)V
      18: iconst_0
      19: ireturn
    Exception table:
       from    to  target type
           0     4     5   Class java/lang/Exception

  public static byte[] loadBytes(java.io.InputStream) throws java.io.IOException;
    Code:
       0: aconst_null
       1: aload_0
       2: invokestatic  #28                 // Method loadBytes:([BLjava/io/InputStream;)[B
       5: areturn

  public static byte[] loadBytes(byte[], java.io.InputStream) throws java.io.IOException;
    Code:
       0: aload_0
       1: ifnonnull     11
       4: aload_1
       5: invokevirtual #29                 // Method java/io/InputStream.available:()I
       8: goto          18
      11: aload_0
      12: arraylength
      13: aload_1
      14: invokevirtual #29                 // Method java/io/InputStream.available:()I
      17: iadd
      18: istore_2
      19: new           #30                 // class java/io/ByteArrayOutputStream
      22: dup
      23: iload_2
      24: invokespecial #31                 // Method java/io/ByteArrayOutputStream."<init>":(I)V
      27: astore_3
      28: aconst_null
      29: astore        4
      31: aload_0
      32: ifnull        40
      35: aload_3
      36: aload_0
      37: invokevirtual #32                 // Method java/io/ByteArrayOutputStream.write:([B)V
      40: aload_1
      41: aload_3
      42: invokestatic  #17                 // Method copyStream:(Ljava/io/InputStream;Ljava/io/OutputStream;)V
      45: aload_3
      46: invokevirtual #33                 // Method java/io/ByteArrayOutputStream.toByteArray:()[B
      49: astore        5
      51: aload_3
      52: ifnull        83
      55: aload         4
      57: ifnull        79
      60: aload_3
      61: invokevirtual #34                 // Method java/io/ByteArrayOutputStream.close:()V
      64: goto          83
      67: astore        6
      69: aload         4
      71: aload         6
      73: invokevirtual #20                 // Method java/lang/Throwable.addSuppressed:(Ljava/lang/Throwable;)V
      76: goto          83
      79: aload_3
      80: invokevirtual #34                 // Method java/io/ByteArrayOutputStream.close:()V
      83: aload         5
      85: areturn
      86: astore        5
      88: aload         5
      90: astore        4
      92: aload         5
      94: athrow
      95: astore        7
      97: aload_3
      98: ifnull        129
     101: aload         4
     103: ifnull        125
     106: aload_3
     107: invokevirtual #34                 // Method java/io/ByteArrayOutputStream.close:()V
     110: goto          129
     113: astore        8
     115: aload         4
     117: aload         8
     119: invokevirtual #20                 // Method java/lang/Throwable.addSuppressed:(Ljava/lang/Throwable;)V
     122: goto          129
     125: aload_3
     126: invokevirtual #34                 // Method java/io/ByteArrayOutputStream.close:()V
     129: aload         7
     131: athrow
     132: astore_3
     133: new           #6                  // class java/io/IOException
     136: dup
     137: ldc           #35                 // String Failed to read input stream to bytes array
     139: aload_3
     140: invokespecial #23                 // Method java/io/IOException."<init>":(Ljava/lang/String;Ljava/lang/Throwable;)V
     143: athrow
    Exception table:
       from    to  target type
          60    64    67   Class java/lang/Throwable
          31    51    86   Class java/lang/Throwable
          31    51    95   any
         106   110   113   Class java/lang/Throwable
          86    97    95   any
          19    83   132   Class java/lang/Exception
          86   132   132   Class java/lang/Exception

  public static void copyStream(java.io.InputStream, java.io.OutputStream) throws java.io.IOException;
    Code:
       0: sipush        8192
       3: newarray       byte
       5: astore_2
       6: aload_0
       7: aload_2
       8: invokevirtual #36                 // Method java/io/InputStream.read:([B)I
      11: istore_3
      12: iload_3
      13: iconst_m1
      14: if_icmpne     20
      17: goto          30
      20: aload_1
      21: aload_2
      22: iconst_0
      23: iload_3
      24: invokevirtual #37                 // Method java/io/OutputStream.write:([BII)V
      27: goto          6
      30: return

  public static java.lang.String getFileExtension(java.lang.String);
    Code:
       0: aload_0
       1: bipush        46
       3: invokevirtual #38                 // Method java/lang/String.lastIndexOf:(I)I
       6: istore_1
       7: iload_1
       8: iconst_m1
       9: if_icmpne     14
      12: aconst_null
      13: areturn
      14: aload_0
      15: iload_1
      16: iconst_1
      17: iadd
      18: invokevirtual #39                 // Method java/lang/String.substring:(I)Ljava/lang/String;
      21: areturn

  public static java.lang.String removeFileExtension(java.lang.String);
    Code:
       0: aload_0
       1: bipush        46
       3: invokevirtual #38                 // Method java/lang/String.lastIndexOf:(I)I
       6: istore_1
       7: iload_1
       8: iconst_m1
       9: if_icmpne     14
      12: aload_0
      13: areturn
      14: aload_0
      15: iconst_0
      16: iload_1
      17: invokevirtual #40                 // Method java/lang/String.substring:(II)Ljava/lang/String;
      20: areturn

  public static boolean isZipFileExt(java.lang.String);
    Code:
       0: aload_0
       1: invokestatic  #41                 // Method getFileExtension:(Ljava/lang/String;)Ljava/lang/String;
       4: astore_1
       5: aload_1
       6: ifnonnull     11
       9: iconst_0
      10: ireturn
      11: getstatic     #42                 // Field ZIP_FILE_EXTS:Ljava/util/Set;
      14: aload_1
      15: invokeinterface #43,  2           // InterfaceMethod java/util/Set.contains:(Ljava/lang/Object;)Z
      20: ireturn

  static {};
    Code:
       0: ldc           #44                 // class jadx/api/plugins/utils/CommonFileUtils
       2: invokestatic  #45                 // Method org/slf4j/LoggerFactory.getLogger:(Ljava/lang/Class;)Lorg/slf4j/Logger;
       5: putstatic     #25                 // Field LOG:Lorg/slf4j/Logger;
       8: invokestatic  #46                 // Method getCWD:()Ljava/io/File;
      11: putstatic     #47                 // Field CWD:Ljava/io/File;
      14: getstatic     #47                 // Field CWD:Ljava/io/File;
      17: invokevirtual #48                 // Method java/io/File.toPath:()Ljava/nio/file/Path;
      20: putstatic     #49                 // Field CWD_PATH:Ljava/nio/file/Path;
      23: iconst_3
      24: anewarray     #50                 // class java/lang/String
      27: dup
      28: iconst_0
      29: ldc           #51                 // String zip
      31: aastore
      32: dup
      33: iconst_1
      34: ldc           #52                 // String jar
      36: aastore
      37: dup
      38: iconst_2
      39: ldc           #53                 // String apk
      41: aastore
      42: invokestatic  #54                 // Method jadx/api/plugins/utils/Utils.constSet:([Ljava/lang/Object;)Ljava/util/Set;
      45: putstatic     #42                 // Field ZIP_FILE_EXTS:Ljava/util/Set;
      48: return
}
