Compiled from "AddressMatch.java"
public class org.apache.dubbo.rpc.cluster.router.mesh.rule.virtualservice.match.AddressMatch {
  public static final org.apache.dubbo.common.logger.ErrorTypeAwareLogger logger;

  private java.lang.String wildcard;

  private java.lang.String cird;

  private java.lang.String exact;

  public org.apache.dubbo.rpc.cluster.router.mesh.rule.virtualservice.match.AddressMatch();
    Code:
       0: aload_0
       1: invokespecial #3                  // Method java/lang/Object."<init>":()V
       4: return

  public java.lang.String getWildcard();
    Code:
       0: aload_0
       1: getfield      #4                  // Field wildcard:Ljava/lang/String;
       4: areturn

  public void setWildcard(java.lang.String);
    Code:
       0: aload_0
       1: aload_1
       2: putfield      #4                  // Field wildcard:Ljava/lang/String;
       5: return

  public java.lang.String getCird();
    Code:
       0: aload_0
       1: getfield      #5                  // Field cird:Ljava/lang/String;
       4: areturn

  public void setCird(java.lang.String);
    Code:
       0: aload_0
       1: aload_1
       2: putfield      #5                  // Field cird:Ljava/lang/String;
       5: return

  public java.lang.String getExact();
    Code:
       0: aload_0
       1: getfield      #6                  // Field exact:Ljava/lang/String;
       4: areturn

  public void setExact(java.lang.String);
    Code:
       0: aload_0
       1: aload_1
       2: putfield      #6                  // Field exact:Ljava/lang/String;
       5: return

  public boolean isMatch(java.lang.String);
    Code:
       0: aload_0
       1: invokevirtual #7                  // Method getCird:()Ljava/lang/String;
       4: ifnull        75
       7: aload_1
       8: ifnull        75
      11: aload_1
      12: aload_0
      13: invokevirtual #7                  // Method getCird:()Ljava/lang/String;
      16: invokevirtual #8                  // Method java/lang/String.equals:(Ljava/lang/Object;)Z
      19: ifne          33
      22: aload_0
      23: invokevirtual #7                  // Method getCird:()Ljava/lang/String;
      26: aload_1
      27: invokestatic  #9                  // Method org/apache/dubbo/common/utils/NetUtils.matchIpExpression:(Ljava/lang/String;Ljava/lang/String;)Z
      30: ifeq          37
      33: iconst_1
      34: goto          38
      37: iconst_0
      38: ireturn
      39: astore_2
      40: getstatic     #11                 // Field logger:Lorg/apache/dubbo/common/logger/ErrorTypeAwareLogger;
      43: ldc           #12                 // String 2-7
      45: ldc           #13                 // String Executing routing rule match expression error.
      47: ldc           #14                 // String
      49: ldc           #15                 // String Error trying to match cird formatted address %s with input %s in AddressMatch.
      51: iconst_2
      52: anewarray     #16                 // class java/lang/Object
      55: dup
      56: iconst_0
      57: aload_0
      58: invokevirtual #7                  // Method getCird:()Ljava/lang/String;
      61: aastore
      62: dup
      63: iconst_1
      64: aload_1
      65: aastore
      66: invokestatic  #17                 // Method java/lang/String.format:(Ljava/lang/String;[Ljava/lang/Object;)Ljava/lang/String;
      69: aload_2
      70: invokeinterface #18,  6           // InterfaceMethod org/apache/dubbo/common/logger/ErrorTypeAwareLogger.error:(Ljava/lang/String;Ljava/lang/String;Ljava/lang/String;Ljava/lang/String;Ljava/lang/Throwable;)V
      75: aload_0
      76: invokevirtual #19                 // Method getWildcard:()Ljava/lang/String;
      79: ifnull        121
      82: aload_1
      83: ifnull        121
      86: ldc           #20                 // String 0.0.0.0
      88: aload_0
      89: invokevirtual #19                 // Method getWildcard:()Ljava/lang/String;
      92: invokevirtual #8                  // Method java/lang/String.equals:(Ljava/lang/Object;)Z
      95: ifne          110
      98: ldc           #21                 // String *
     100: aload_0
     101: invokevirtual #19                 // Method getWildcard:()Ljava/lang/String;
     104: invokevirtual #8                  // Method java/lang/String.equals:(Ljava/lang/Object;)Z
     107: ifeq          112
     110: iconst_1
     111: ireturn
     112: aload_0
     113: invokevirtual #19                 // Method getWildcard:()Ljava/lang/String;
     116: aload_1
     117: invokestatic  #22                 // Method org/apache/dubbo/common/utils/UrlUtils.isMatchGlobPattern:(Ljava/lang/String;Ljava/lang/String;)Z
     120: ireturn
     121: aload_0
     122: invokevirtual #23                 // Method getExact:()Ljava/lang/String;
     125: ifnull        141
     128: aload_1
     129: ifnull        141
     132: aload_1
     133: aload_0
     134: invokevirtual #23                 // Method getExact:()Ljava/lang/String;
     137: invokevirtual #8                  // Method java/lang/String.equals:(Ljava/lang/Object;)Z
     140: ireturn
     141: iconst_0
     142: ireturn
    Exception table:
       from    to  target type
          11    38    39   Class java/net/UnknownHostException

  static {};
    Code:
       0: ldc           #24                 // class org/apache/dubbo/rpc/cluster/router/mesh/rule/virtualservice/match/AddressMatch
       2: invokestatic  #25                 // Method org/apache/dubbo/common/logger/LoggerFactory.getErrorTypeAwareLogger:(Ljava/lang/Class;)Lorg/apache/dubbo/common/logger/ErrorTypeAwareLogger;
       5: putstatic     #11                 // Field logger:Lorg/apache/dubbo/common/logger/ErrorTypeAwareLogger;
       8: return
}
