Compiled from "BoolMatch.java"
public class org.apache.dubbo.rpc.cluster.router.mesh.rule.virtualservice.match.BoolMatch {
  private java.lang.Boolean exact;

  public org.apache.dubbo.rpc.cluster.router.mesh.rule.virtualservice.match.BoolMatch();
    Code:
       0: aload_0
       1: invokespecial #1                  // Method java/lang/Object."<init>":()V
       4: return

  public java.lang.Boolean getExact();
    Code:
       0: aload_0
       1: getfield      #2                  // Field exact:Ljava/lang/Boolean;
       4: areturn

  public void setExact(java.lang.Boolean);
    Code:
       0: aload_0
       1: aload_1
       2: putfield      #2                  // Field exact:Ljava/lang/Boolean;
       5: return

  public boolean isMatch(boolean);
    Code:
       0: aload_0
       1: getfield      #2                  // Field exact:Ljava/lang/Boolean;
       4: ifnull        24
       7: iload_1
       8: aload_0
       9: getfield      #2                  // Field exact:Ljava/lang/Boolean;
      12: invokevirtual #3                  // Method java/lang/Boolean.booleanValue:()Z
      15: if_icmpne     22
      18: iconst_1
      19: goto          23
      22: iconst_0
      23: ireturn
      24: iconst_0
      25: ireturn
}
