Compiled from "DoubleMatch.java"
public class org.apache.dubbo.rpc.cluster.router.mesh.rule.virtualservice.match.DoubleMatch {
  private java.lang.Double exact;

  private org.apache.dubbo.rpc.cluster.router.mesh.rule.virtualservice.match.DoubleRangeMatch range;

  private java.lang.Double mod;

  public org.apache.dubbo.rpc.cluster.router.mesh.rule.virtualservice.match.DoubleMatch();
    Code:
       0: aload_0
       1: invokespecial #1                  // Method java/lang/Object."<init>":()V
       4: return

  public java.lang.Double getExact();
    Code:
       0: aload_0
       1: getfield      #2                  // Field exact:Ljava/lang/Double;
       4: areturn

  public void setExact(java.lang.Double);
    Code:
       0: aload_0
       1: aload_1
       2: putfield      #2                  // Field exact:Ljava/lang/Double;
       5: return

  public org.apache.dubbo.rpc.cluster.router.mesh.rule.virtualservice.match.DoubleRangeMatch getRange();
    Code:
       0: aload_0
       1: getfield      #3                  // Field range:Lorg/apache/dubbo/rpc/cluster/router/mesh/rule/virtualservice/match/DoubleRangeMatch;
       4: areturn

  public void setRange(org.apache.dubbo.rpc.cluster.router.mesh.rule.virtualservice.match.DoubleRangeMatch);
    Code:
       0: aload_0
       1: aload_1
       2: putfield      #3                  // Field range:Lorg/apache/dubbo/rpc/cluster/router/mesh/rule/virtualservice/match/DoubleRangeMatch;
       5: return

  public java.lang.Double getMod();
    Code:
       0: aload_0
       1: getfield      #4                  // Field mod:Ljava/lang/Double;
       4: areturn

  public void setMod(java.lang.Double);
    Code:
       0: aload_0
       1: aload_1
       2: putfield      #4                  // Field mod:Ljava/lang/Double;
       5: return

  public boolean isMatch(java.lang.Double);
    Code:
       0: aload_0
       1: getfield      #2                  // Field exact:Ljava/lang/Double;
       4: ifnull        23
       7: aload_0
       8: getfield      #4                  // Field mod:Ljava/lang/Double;
      11: ifnonnull     23
      14: aload_1
      15: aload_0
      16: getfield      #2                  // Field exact:Ljava/lang/Double;
      19: invokevirtual #5                  // Method java/lang/Double.equals:(Ljava/lang/Object;)Z
      22: ireturn
      23: aload_0
      24: getfield      #3                  // Field range:Lorg/apache/dubbo/rpc/cluster/router/mesh/rule/virtualservice/match/DoubleRangeMatch;
      27: ifnull        39
      30: aload_0
      31: getfield      #3                  // Field range:Lorg/apache/dubbo/rpc/cluster/router/mesh/rule/virtualservice/match/DoubleRangeMatch;
      34: aload_1
      35: invokevirtual #6                  // Method org/apache/dubbo/rpc/cluster/router/mesh/rule/virtualservice/match/DoubleRangeMatch.isMatch:(Ljava/lang/Double;)Z
      38: ireturn
      39: aload_0
      40: getfield      #2                  // Field exact:Ljava/lang/Double;
      43: ifnull        71
      46: aload_1
      47: invokevirtual #7                  // Method java/lang/Double.doubleValue:()D
      50: aload_0
      51: getfield      #4                  // Field mod:Ljava/lang/Double;
      54: invokevirtual #7                  // Method java/lang/Double.doubleValue:()D
      57: drem
      58: invokestatic  #8                  // Method java/lang/Double.valueOf:(D)Ljava/lang/Double;
      61: astore_2
      62: aload_2
      63: aload_0
      64: getfield      #2                  // Field exact:Ljava/lang/Double;
      67: invokevirtual #5                  // Method java/lang/Double.equals:(Ljava/lang/Object;)Z
      70: ireturn
      71: iconst_0
      72: ireturn
}
