Compiled from "DubboAttachmentMatch.java"
public class org.apache.dubbo.rpc.cluster.router.mesh.rule.virtualservice.match.DubboAttachmentMatch {
  private java.util.Map<java.lang.String, org.apache.dubbo.rpc.cluster.router.mesh.rule.virtualservice.match.StringMatch> tracingContext;

  private java.util.Map<java.lang.String, org.apache.dubbo.rpc.cluster.router.mesh.rule.virtualservice.match.StringMatch> dubboContext;

  public org.apache.dubbo.rpc.cluster.router.mesh.rule.virtualservice.match.DubboAttachmentMatch();
    Code:
       0: aload_0
       1: invokespecial #1                  // Method java/lang/Object."<init>":()V
       4: return

  public java.util.Map<java.lang.String, org.apache.dubbo.rpc.cluster.router.mesh.rule.virtualservice.match.StringMatch> getTracingContext();
    Code:
       0: aload_0
       1: getfield      #2                  // Field tracingContext:Ljava/util/Map;
       4: areturn

  public void setTracingContext(java.util.Map<java.lang.String, org.apache.dubbo.rpc.cluster.router.mesh.rule.virtualservice.match.StringMatch>);
    Code:
       0: aload_0
       1: aload_1
       2: putfield      #2                  // Field tracingContext:Ljava/util/Map;
       5: return

  public java.util.Map<java.lang.String, org.apache.dubbo.rpc.cluster.router.mesh.rule.virtualservice.match.StringMatch> getDubboContext();
    Code:
       0: aload_0
       1: getfield      #3                  // Field dubboContext:Ljava/util/Map;
       4: areturn

  public void setDubboContext(java.util.Map<java.lang.String, org.apache.dubbo.rpc.cluster.router.mesh.rule.virtualservice.match.StringMatch>);
    Code:
       0: aload_0
       1: aload_1
       2: putfield      #3                  // Field dubboContext:Ljava/util/Map;
       5: return

  public boolean isMatch(org.apache.dubbo.rpc.Invocation, java.util.Set<org.apache.dubbo.rpc.cluster.router.mesh.util.TracingContextProvider>);
    Code:
       0: aload_0
       1: getfield      #3                  // Field dubboContext:Ljava/util/Map;
       4: ifnull        83
       7: aload_0
       8: getfield      #3                  // Field dubboContext:Ljava/util/Map;
      11: invokeinterface #4,  1            // InterfaceMethod java/util/Map.entrySet:()Ljava/util/Set;
      16: invokeinterface #5,  1            // InterfaceMethod java/util/Set.iterator:()Ljava/util/Iterator;
      21: astore_3
      22: aload_3
      23: invokeinterface #6,  1            // InterfaceMethod java/util/Iterator.hasNext:()Z
      28: ifeq          83
      31: aload_3
      32: invokeinterface #7,  1            // InterfaceMethod java/util/Iterator.next:()Ljava/lang/Object;
      37: checkcast     #8                  // class java/util/Map$Entry
      40: astore        4
      42: aload         4
      44: invokeinterface #9,  1            // InterfaceMethod java/util/Map$Entry.getKey:()Ljava/lang/Object;
      49: checkcast     #10                 // class java/lang/String
      52: astore        5
      54: aload         4
      56: invokeinterface #11,  1           // InterfaceMethod java/util/Map$Entry.getValue:()Ljava/lang/Object;
      61: checkcast     #12                 // class org/apache/dubbo/rpc/cluster/router/mesh/rule/virtualservice/match/StringMatch
      64: aload_1
      65: aload         5
      67: invokeinterface #13,  2           // InterfaceMethod org/apache/dubbo/rpc/Invocation.getAttachment:(Ljava/lang/String;)Ljava/lang/String;
      72: invokevirtual #14                 // Method org/apache/dubbo/rpc/cluster/router/mesh/rule/virtualservice/match/StringMatch.isMatch:(Ljava/lang/String;)Z
      75: ifne          80
      78: iconst_0
      79: ireturn
      80: goto          22
      83: aload_0
      84: getfield      #2                  // Field tracingContext:Ljava/util/Map;
      87: ifnull        212
      90: aload_0
      91: getfield      #2                  // Field tracingContext:Ljava/util/Map;
      94: invokeinterface #4,  1            // InterfaceMethod java/util/Map.entrySet:()Ljava/util/Set;
      99: invokeinterface #5,  1            // InterfaceMethod java/util/Set.iterator:()Ljava/util/Iterator;
     104: astore_3
     105: aload_3
     106: invokeinterface #6,  1            // InterfaceMethod java/util/Iterator.hasNext:()Z
     111: ifeq          212
     114: aload_3
     115: invokeinterface #7,  1            // InterfaceMethod java/util/Iterator.next:()Ljava/lang/Object;
     120: checkcast     #8                  // class java/util/Map$Entry
     123: astore        4
     125: aload         4
     127: invokeinterface #9,  1            // InterfaceMethod java/util/Map$Entry.getKey:()Ljava/lang/Object;
     132: checkcast     #10                 // class java/lang/String
     135: astore        5
     137: iconst_0
     138: istore        6
     140: aload_2
     141: invokeinterface #5,  1            // InterfaceMethod java/util/Set.iterator:()Ljava/util/Iterator;
     146: astore        7
     148: aload         7
     150: invokeinterface #6,  1            // InterfaceMethod java/util/Iterator.hasNext:()Z
     155: ifeq          202
     158: aload         7
     160: invokeinterface #7,  1            // InterfaceMethod java/util/Iterator.next:()Ljava/lang/Object;
     165: checkcast     #15                 // class org/apache/dubbo/rpc/cluster/router/mesh/util/TracingContextProvider
     168: astore        8
     170: aload         4
     172: invokeinterface #11,  1           // InterfaceMethod java/util/Map$Entry.getValue:()Ljava/lang/Object;
     177: checkcast     #12                 // class org/apache/dubbo/rpc/cluster/router/mesh/rule/virtualservice/match/StringMatch
     180: aload         8
     182: aload_1
     183: aload         5
     185: invokeinterface #16,  3           // InterfaceMethod org/apache/dubbo/rpc/cluster/router/mesh/util/TracingContextProvider.getValue:(Lorg/apache/dubbo/rpc/Invocation;Ljava/lang/String;)Ljava/lang/String;
     190: invokevirtual #14                 // Method org/apache/dubbo/rpc/cluster/router/mesh/rule/virtualservice/match/StringMatch.isMatch:(Ljava/lang/String;)Z
     193: ifeq          199
     196: iconst_1
     197: istore        6
     199: goto          148
     202: iload         6
     204: ifne          209
     207: iconst_0
     208: ireturn
     209: goto          105
     212: iconst_1
     213: ireturn
}
