Compiled from "DubboMethodMatch.java"
public class org.apache.dubbo.rpc.cluster.router.mesh.rule.virtualservice.match.DubboMethodMatch {
  private org.apache.dubbo.rpc.cluster.router.mesh.rule.virtualservice.match.StringMatch name_match;

  private java.lang.Integer argc;

  private java.util.List<org.apache.dubbo.rpc.cluster.router.mesh.rule.virtualservice.match.DubboMethodArg> args;

  private java.util.List<org.apache.dubbo.rpc.cluster.router.mesh.rule.virtualservice.match.StringMatch> argp;

  private java.util.Map<java.lang.String, org.apache.dubbo.rpc.cluster.router.mesh.rule.virtualservice.match.StringMatch> headers;

  public org.apache.dubbo.rpc.cluster.router.mesh.rule.virtualservice.match.DubboMethodMatch();
    Code:
       0: aload_0
       1: invokespecial #1                  // Method java/lang/Object."<init>":()V
       4: return

  public org.apache.dubbo.rpc.cluster.router.mesh.rule.virtualservice.match.StringMatch getName_match();
    Code:
       0: aload_0
       1: getfield      #2                  // Field name_match:Lorg/apache/dubbo/rpc/cluster/router/mesh/rule/virtualservice/match/StringMatch;
       4: areturn

  public void setName_match(org.apache.dubbo.rpc.cluster.router.mesh.rule.virtualservice.match.StringMatch);
    Code:
       0: aload_0
       1: aload_1
       2: putfield      #2                  // Field name_match:Lorg/apache/dubbo/rpc/cluster/router/mesh/rule/virtualservice/match/StringMatch;
       5: return

  public java.lang.Integer getArgc();
    Code:
       0: aload_0
       1: getfield      #3                  // Field argc:Ljava/lang/Integer;
       4: areturn

  public void setArgc(java.lang.Integer);
    Code:
       0: aload_0
       1: aload_1
       2: putfield      #3                  // Field argc:Ljava/lang/Integer;
       5: return

  public java.util.List<org.apache.dubbo.rpc.cluster.router.mesh.rule.virtualservice.match.DubboMethodArg> getArgs();
    Code:
       0: aload_0
       1: getfield      #4                  // Field args:Ljava/util/List;
       4: areturn

  public void setArgs(java.util.List<org.apache.dubbo.rpc.cluster.router.mesh.rule.virtualservice.match.DubboMethodArg>);
    Code:
       0: aload_0
       1: aload_1
       2: putfield      #4                  // Field args:Ljava/util/List;
       5: return

  public java.util.List<org.apache.dubbo.rpc.cluster.router.mesh.rule.virtualservice.match.StringMatch> getArgp();
    Code:
       0: aload_0
       1: getfield      #5                  // Field argp:Ljava/util/List;
       4: areturn

  public void setArgp(java.util.List<org.apache.dubbo.rpc.cluster.router.mesh.rule.virtualservice.match.StringMatch>);
    Code:
       0: aload_0
       1: aload_1
       2: putfield      #5                  // Field argp:Ljava/util/List;
       5: return

  public java.util.Map<java.lang.String, org.apache.dubbo.rpc.cluster.router.mesh.rule.virtualservice.match.StringMatch> getHeaders();
    Code:
       0: aload_0
       1: getfield      #6                  // Field headers:Ljava/util/Map;
       4: areturn

  public void setHeaders(java.util.Map<java.lang.String, org.apache.dubbo.rpc.cluster.router.mesh.rule.virtualservice.match.StringMatch>);
    Code:
       0: aload_0
       1: aload_1
       2: putfield      #6                  // Field headers:Ljava/util/Map;
       5: return

  public java.lang.String toString();
    Code:
       0: new           #7                  // class java/lang/StringBuilder
       3: dup
       4: invokespecial #8                  // Method java/lang/StringBuilder."<init>":()V
       7: ldc           #9                  // String DubboMethodMatch{name_match=
       9: invokevirtual #10                 // Method java/lang/StringBuilder.append:(Ljava/lang/String;)Ljava/lang/StringBuilder;
      12: aload_0
      13: getfield      #2                  // Field name_match:Lorg/apache/dubbo/rpc/cluster/router/mesh/rule/virtualservice/match/StringMatch;
      16: invokevirtual #11                 // Method java/lang/StringBuilder.append:(Ljava/lang/Object;)Ljava/lang/StringBuilder;
      19: ldc           #12                 // String , argc=
      21: invokevirtual #10                 // Method java/lang/StringBuilder.append:(Ljava/lang/String;)Ljava/lang/StringBuilder;
      24: aload_0
      25: getfield      #3                  // Field argc:Ljava/lang/Integer;
      28: invokevirtual #11                 // Method java/lang/StringBuilder.append:(Ljava/lang/Object;)Ljava/lang/StringBuilder;
      31: ldc           #13                 // String , args=
      33: invokevirtual #10                 // Method java/lang/StringBuilder.append:(Ljava/lang/String;)Ljava/lang/StringBuilder;
      36: aload_0
      37: getfield      #4                  // Field args:Ljava/util/List;
      40: invokevirtual #11                 // Method java/lang/StringBuilder.append:(Ljava/lang/Object;)Ljava/lang/StringBuilder;
      43: ldc           #14                 // String , argp=
      45: invokevirtual #10                 // Method java/lang/StringBuilder.append:(Ljava/lang/String;)Ljava/lang/StringBuilder;
      48: aload_0
      49: getfield      #5                  // Field argp:Ljava/util/List;
      52: invokevirtual #11                 // Method java/lang/StringBuilder.append:(Ljava/lang/Object;)Ljava/lang/StringBuilder;
      55: ldc           #15                 // String , headers=
      57: invokevirtual #10                 // Method java/lang/StringBuilder.append:(Ljava/lang/String;)Ljava/lang/StringBuilder;
      60: aload_0
      61: getfield      #6                  // Field headers:Ljava/util/Map;
      64: invokevirtual #11                 // Method java/lang/StringBuilder.append:(Ljava/lang/Object;)Ljava/lang/StringBuilder;
      67: bipush        125
      69: invokevirtual #16                 // Method java/lang/StringBuilder.append:(C)Ljava/lang/StringBuilder;
      72: invokevirtual #17                 // Method java/lang/StringBuilder.toString:()Ljava/lang/String;
      75: areturn

  public boolean isMatch(org.apache.dubbo.rpc.Invocation);
    Code:
       0: aload_0
       1: invokevirtual #18                 // Method getName_match:()Lorg/apache/dubbo/rpc/cluster/router/mesh/rule/virtualservice/match/StringMatch;
       4: astore_2
       5: aload_2
       6: ifnull        24
       9: aload_2
      10: aload_1
      11: invokeinterface #19,  1           // InterfaceMethod org/apache/dubbo/rpc/Invocation.getMethodName:()Ljava/lang/String;
      16: invokevirtual #20                 // Method org/apache/dubbo/rpc/cluster/router/mesh/rule/virtualservice/match/StringMatch.isMatch:(Ljava/lang/String;)Z
      19: ifne          24
      22: iconst_0
      23: ireturn
      24: aload_0
      25: invokevirtual #21                 // Method getArgc:()Ljava/lang/Integer;
      28: astore_3
      29: aload_1
      30: invokeinterface #22,  1           // InterfaceMethod org/apache/dubbo/rpc/Invocation.getArguments:()[Ljava/lang/Object;
      35: astore        4
      37: aload_3
      38: ifnull        71
      41: aload_3
      42: invokevirtual #23                 // Method java/lang/Integer.intValue:()I
      45: ifeq          59
      48: aload         4
      50: ifnull        69
      53: aload         4
      55: arraylength
      56: ifeq          69
      59: aload_3
      60: invokevirtual #23                 // Method java/lang/Integer.intValue:()I
      63: aload         4
      65: arraylength
      66: if_icmpeq     71
      69: iconst_0
      70: ireturn
      71: aload_0
      72: invokevirtual #24                 // Method getArgp:()Ljava/util/List;
      75: astore        5
      77: aload_1
      78: invokeinterface #25,  1           // InterfaceMethod org/apache/dubbo/rpc/Invocation.getParameterTypes:()[Ljava/lang/Class;
      83: astore        6
      85: aload         5
      87: ifnull        215
      90: aload         5
      92: invokeinterface #26,  1           // InterfaceMethod java/util/List.size:()I
      97: ifle          215
     100: aload         6
     102: ifnull        111
     105: aload         6
     107: arraylength
     108: ifne          113
     111: iconst_0
     112: ireturn
     113: aload         5
     115: invokeinterface #26,  1           // InterfaceMethod java/util/List.size:()I
     120: aload         6
     122: arraylength
     123: if_icmpeq     128
     126: iconst_0
     127: ireturn
     128: iconst_0
     129: istore        7
     131: iload         7
     133: aload         5
     135: invokeinterface #26,  1           // InterfaceMethod java/util/List.size:()I
     140: if_icmpge     215
     143: aload         5
     145: iload         7
     147: invokeinterface #27,  2           // InterfaceMethod java/util/List.get:(I)Ljava/lang/Object;
     152: checkcast     #28                 // class org/apache/dubbo/rpc/cluster/router/mesh/rule/virtualservice/match/StringMatch
     155: aload         6
     157: iload         7
     159: aaload
     160: invokevirtual #29                 // Method java/lang/Class.getName:()Ljava/lang/String;
     163: invokevirtual #20                 // Method org/apache/dubbo/rpc/cluster/router/mesh/rule/virtualservice/match/StringMatch.isMatch:(Ljava/lang/String;)Z
     166: ifne          195
     169: aload         5
     171: iload         7
     173: invokeinterface #27,  2           // InterfaceMethod java/util/List.get:(I)Ljava/lang/Object;
     178: checkcast     #28                 // class org/apache/dubbo/rpc/cluster/router/mesh/rule/virtualservice/match/StringMatch
     181: aload         6
     183: iload         7
     185: aaload
     186: invokevirtual #30                 // Method java/lang/Class.getSimpleName:()Ljava/lang/String;
     189: invokevirtual #20                 // Method org/apache/dubbo/rpc/cluster/router/mesh/rule/virtualservice/match/StringMatch.isMatch:(Ljava/lang/String;)Z
     192: ifeq          199
     195: iconst_1
     196: goto          200
     199: iconst_0
     200: istore        8
     202: iload         8
     204: ifne          209
     207: iconst_0
     208: ireturn
     209: iinc          7, 1
     212: goto          131
     215: aload_0
     216: invokevirtual #31                 // Method getArgs:()Ljava/util/List;
     219: astore        7
     221: aload         7
     223: ifnull        323
     226: aload         7
     228: invokeinterface #26,  1           // InterfaceMethod java/util/List.size:()I
     233: ifle          323
     236: aload         4
     238: ifnull        247
     241: aload         4
     243: arraylength
     244: ifne          249
     247: iconst_0
     248: ireturn
     249: aload         7
     251: invokeinterface #32,  1           // InterfaceMethod java/util/List.iterator:()Ljava/util/Iterator;
     256: astore        8
     258: aload         8
     260: invokeinterface #33,  1           // InterfaceMethod java/util/Iterator.hasNext:()Z
     265: ifeq          323
     268: aload         8
     270: invokeinterface #34,  1           // InterfaceMethod java/util/Iterator.next:()Ljava/lang/Object;
     275: checkcast     #35                 // class org/apache/dubbo/rpc/cluster/router/mesh/rule/virtualservice/match/DubboMethodArg
     278: astore        9
     280: aload         9
     282: invokevirtual #36                 // Method org/apache/dubbo/rpc/cluster/router/mesh/rule/virtualservice/match/DubboMethodArg.getIndex:()I
     285: istore        10
     287: iload         10
     289: aload         4
     291: arraylength
     292: if_icmplt     305
     295: new           #37                 // class java/lang/IndexOutOfBoundsException
     298: dup
     299: ldc           #38                 // String DubboMethodArg index >= parameters.length
     301: invokespecial #39                 // Method java/lang/IndexOutOfBoundsException."<init>":(Ljava/lang/String;)V
     304: athrow
     305: aload         9
     307: aload         4
     309: iload         10
     311: aaload
     312: invokevirtual #40                 // Method org/apache/dubbo/rpc/cluster/router/mesh/rule/virtualservice/match/DubboMethodArg.isMatch:(Ljava/lang/Object;)Z
     315: ifne          320
     318: iconst_0
     319: ireturn
     320: goto          258
     323: iconst_1
     324: ireturn
}
