Compiled from "DubboMethodArg.java"
public class org.apache.dubbo.rpc.cluster.router.mesh.rule.virtualservice.match.DubboMethodArg {
  private int index;

  private java.lang.String type;

  private org.apache.dubbo.rpc.cluster.router.mesh.rule.virtualservice.match.ListStringMatch str_value;

  private org.apache.dubbo.rpc.cluster.router.mesh.rule.virtualservice.match.ListDoubleMatch num_value;

  private org.apache.dubbo.rpc.cluster.router.mesh.rule.virtualservice.match.BoolMatch bool_value;

  public org.apache.dubbo.rpc.cluster.router.mesh.rule.virtualservice.match.DubboMethodArg();
    Code:
       0: aload_0
       1: invokespecial #1                  // Method java/lang/Object."<init>":()V
       4: return

  public int getIndex();
    Code:
       0: aload_0
       1: getfield      #2                  // Field index:I
       4: ireturn

  public void setIndex(int);
    Code:
       0: aload_0
       1: iload_1
       2: putfield      #2                  // Field index:I
       5: return

  public java.lang.String getType();
    Code:
       0: aload_0
       1: getfield      #3                  // Field type:Ljava/lang/String;
       4: areturn

  public void setType(java.lang.String);
    Code:
       0: aload_0
       1: aload_1
       2: putfield      #3                  // Field type:Ljava/lang/String;
       5: return

  public org.apache.dubbo.rpc.cluster.router.mesh.rule.virtualservice.match.ListStringMatch getStr_value();
    Code:
       0: aload_0
       1: getfield      #4                  // Field str_value:Lorg/apache/dubbo/rpc/cluster/router/mesh/rule/virtualservice/match/ListStringMatch;
       4: areturn

  public void setStr_value(org.apache.dubbo.rpc.cluster.router.mesh.rule.virtualservice.match.ListStringMatch);
    Code:
       0: aload_0
       1: aload_1
       2: putfield      #4                  // Field str_value:Lorg/apache/dubbo/rpc/cluster/router/mesh/rule/virtualservice/match/ListStringMatch;
       5: return

  public org.apache.dubbo.rpc.cluster.router.mesh.rule.virtualservice.match.ListDoubleMatch getNum_value();
    Code:
       0: aload_0
       1: getfield      #5                  // Field num_value:Lorg/apache/dubbo/rpc/cluster/router/mesh/rule/virtualservice/match/ListDoubleMatch;
       4: areturn

  public void setNum_value(org.apache.dubbo.rpc.cluster.router.mesh.rule.virtualservice.match.ListDoubleMatch);
    Code:
       0: aload_0
       1: aload_1
       2: putfield      #5                  // Field num_value:Lorg/apache/dubbo/rpc/cluster/router/mesh/rule/virtualservice/match/ListDoubleMatch;
       5: return

  public org.apache.dubbo.rpc.cluster.router.mesh.rule.virtualservice.match.BoolMatch getBool_value();
    Code:
       0: aload_0
       1: getfield      #6                  // Field bool_value:Lorg/apache/dubbo/rpc/cluster/router/mesh/rule/virtualservice/match/BoolMatch;
       4: areturn

  public void setBool_value(org.apache.dubbo.rpc.cluster.router.mesh.rule.virtualservice.match.BoolMatch);
    Code:
       0: aload_0
       1: aload_1
       2: putfield      #6                  // Field bool_value:Lorg/apache/dubbo/rpc/cluster/router/mesh/rule/virtualservice/match/BoolMatch;
       5: return

  public boolean isMatch(java.lang.Object);
    Code:
       0: aload_0
       1: getfield      #4                  // Field str_value:Lorg/apache/dubbo/rpc/cluster/router/mesh/rule/virtualservice/match/ListStringMatch;
       4: ifnull        34
       7: aload_1
       8: instanceof    #7                  // class java/lang/String
      11: ifeq          32
      14: aload_0
      15: getfield      #4                  // Field str_value:Lorg/apache/dubbo/rpc/cluster/router/mesh/rule/virtualservice/match/ListStringMatch;
      18: aload_1
      19: checkcast     #7                  // class java/lang/String
      22: invokevirtual #8                  // Method org/apache/dubbo/rpc/cluster/router/mesh/rule/virtualservice/match/ListStringMatch.isMatch:(Ljava/lang/String;)Z
      25: ifeq          32
      28: iconst_1
      29: goto          33
      32: iconst_0
      33: ireturn
      34: aload_0
      35: getfield      #5                  // Field num_value:Lorg/apache/dubbo/rpc/cluster/router/mesh/rule/virtualservice/match/ListDoubleMatch;
      38: ifnull        56
      41: aload_0
      42: getfield      #5                  // Field num_value:Lorg/apache/dubbo/rpc/cluster/router/mesh/rule/virtualservice/match/ListDoubleMatch;
      45: aload_1
      46: invokevirtual #9                  // Method java/lang/Object.toString:()Ljava/lang/String;
      49: invokestatic  #10                 // Method java/lang/Double.valueOf:(Ljava/lang/String;)Ljava/lang/Double;
      52: invokevirtual #11                 // Method org/apache/dubbo/rpc/cluster/router/mesh/rule/virtualservice/match/ListDoubleMatch.isMatch:(Ljava/lang/Double;)Z
      55: ireturn
      56: aload_0
      57: getfield      #6                  // Field bool_value:Lorg/apache/dubbo/rpc/cluster/router/mesh/rule/virtualservice/match/BoolMatch;
      60: ifnull        93
      63: aload_1
      64: instanceof    #12                 // class java/lang/Boolean
      67: ifeq          91
      70: aload_0
      71: getfield      #6                  // Field bool_value:Lorg/apache/dubbo/rpc/cluster/router/mesh/rule/virtualservice/match/BoolMatch;
      74: aload_1
      75: checkcast     #12                 // class java/lang/Boolean
      78: invokevirtual #13                 // Method java/lang/Boolean.booleanValue:()Z
      81: invokevirtual #14                 // Method org/apache/dubbo/rpc/cluster/router/mesh/rule/virtualservice/match/BoolMatch.isMatch:(Z)Z
      84: ifeq          91
      87: iconst_1
      88: goto          92
      91: iconst_0
      92: ireturn
      93: iconst_0
      94: ireturn

  public java.lang.String toString();
    Code:
       0: new           #15                 // class java/lang/StringBuilder
       3: dup
       4: invokespecial #16                 // Method java/lang/StringBuilder."<init>":()V
       7: ldc           #17                 // String DubboMethodArg{index=
       9: invokevirtual #18                 // Method java/lang/StringBuilder.append:(Ljava/lang/String;)Ljava/lang/StringBuilder;
      12: aload_0
      13: getfield      #2                  // Field index:I
      16: invokevirtual #19                 // Method java/lang/StringBuilder.append:(I)Ljava/lang/StringBuilder;
      19: ldc           #20                 // String , type=\'
      21: invokevirtual #18                 // Method java/lang/StringBuilder.append:(Ljava/lang/String;)Ljava/lang/StringBuilder;
      24: aload_0
      25: getfield      #3                  // Field type:Ljava/lang/String;
      28: invokevirtual #18                 // Method java/lang/StringBuilder.append:(Ljava/lang/String;)Ljava/lang/StringBuilder;
      31: bipush        39
      33: invokevirtual #21                 // Method java/lang/StringBuilder.append:(C)Ljava/lang/StringBuilder;
      36: ldc           #22                 // String , str_value=
      38: invokevirtual #18                 // Method java/lang/StringBuilder.append:(Ljava/lang/String;)Ljava/lang/StringBuilder;
      41: aload_0
      42: getfield      #4                  // Field str_value:Lorg/apache/dubbo/rpc/cluster/router/mesh/rule/virtualservice/match/ListStringMatch;
      45: invokevirtual #23                 // Method java/lang/StringBuilder.append:(Ljava/lang/Object;)Ljava/lang/StringBuilder;
      48: ldc           #24                 // String , num_value=
      50: invokevirtual #18                 // Method java/lang/StringBuilder.append:(Ljava/lang/String;)Ljava/lang/StringBuilder;
      53: aload_0
      54: getfield      #5                  // Field num_value:Lorg/apache/dubbo/rpc/cluster/router/mesh/rule/virtualservice/match/ListDoubleMatch;
      57: invokevirtual #23                 // Method java/lang/StringBuilder.append:(Ljava/lang/Object;)Ljava/lang/StringBuilder;
      60: ldc           #25                 // String , bool_value=
      62: invokevirtual #18                 // Method java/lang/StringBuilder.append:(Ljava/lang/String;)Ljava/lang/StringBuilder;
      65: aload_0
      66: getfield      #6                  // Field bool_value:Lorg/apache/dubbo/rpc/cluster/router/mesh/rule/virtualservice/match/BoolMatch;
      69: invokevirtual #23                 // Method java/lang/StringBuilder.append:(Ljava/lang/Object;)Ljava/lang/StringBuilder;
      72: bipush        125
      74: invokevirtual #21                 // Method java/lang/StringBuilder.append:(C)Ljava/lang/StringBuilder;
      77: invokevirtual #26                 // Method java/lang/StringBuilder.toString:()Ljava/lang/String;
      80: areturn
}
