Compiled from "ListDoubleMatch.java"
public class org.apache.dubbo.rpc.cluster.router.mesh.rule.virtualservice.match.ListDoubleMatch {
  private java.util.List<org.apache.dubbo.rpc.cluster.router.mesh.rule.virtualservice.match.DoubleMatch> oneof;

  public org.apache.dubbo.rpc.cluster.router.mesh.rule.virtualservice.match.ListDoubleMatch();
    Code:
       0: aload_0
       1: invokespecial #1                  // Method java/lang/Object."<init>":()V
       4: return

  public java.util.List<org.apache.dubbo.rpc.cluster.router.mesh.rule.virtualservice.match.DoubleMatch> getOneof();
    Code:
       0: aload_0
       1: getfield      #2                  // Field oneof:Ljava/util/List;
       4: areturn

  public void setOneof(java.util.List<org.apache.dubbo.rpc.cluster.router.mesh.rule.virtualservice.match.DoubleMatch>);
    Code:
       0: aload_0
       1: aload_1
       2: putfield      #2                  // Field oneof:Ljava/util/List;
       5: return

  public boolean isMatch(java.lang.Double);
    Code:
       0: aload_0
       1: getfield      #2                  // Field oneof:Ljava/util/List;
       4: invokeinterface #3,  1            // InterfaceMethod java/util/List.iterator:()Ljava/util/Iterator;
       9: astore_2
      10: aload_2
      11: invokeinterface #4,  1            // InterfaceMethod java/util/Iterator.hasNext:()Z
      16: ifeq          42
      19: aload_2
      20: invokeinterface #5,  1            // InterfaceMethod java/util/Iterator.next:()Ljava/lang/Object;
      25: checkcast     #6                  // class org/apache/dubbo/rpc/cluster/router/mesh/rule/virtualservice/match/DoubleMatch
      28: astore_3
      29: aload_3
      30: aload_1
      31: invokevirtual #7                  // Method org/apache/dubbo/rpc/cluster/router/mesh/rule/virtualservice/match/DoubleMatch.isMatch:(Ljava/lang/Double;)Z
      34: ifeq          39
      37: iconst_1
      38: ireturn
      39: goto          10
      42: iconst_0
      43: ireturn
}
