Compiled from "JavaVersion.java"
public final class org.springframework.boot.system.JavaVersion extends java.lang.Enum<org.springframework.boot.system.JavaVersion> {
  public static final org.springframework.boot.system.JavaVersion SEVENTEEN;

  public static final org.springframework.boot.system.JavaVersion EIGHTEEN;

  public static final org.springframework.boot.system.JavaVersion NINETEEN;

  private final java.lang.String name;

  private final boolean available;

  private static final org.springframework.boot.system.JavaVersion[] $VALUES;

  public static org.springframework.boot.system.JavaVersion[] values();
    Code:
       0: getstatic     #13                 // Field $VALUES:[Lorg/springframework/boot/system/JavaVersion;
       3: invokevirtual #17                 // Method "[Lorg/springframework/boot/system/JavaVersion;".clone:()Ljava/lang/Object;
       6: checkcast     #18                 // class "[Lorg/springframework/boot/system/JavaVersion;"
       9: areturn

  public static org.springframework.boot.system.JavaVersion valueOf(java.lang.String);
    Code:
       0: ldc           #1                  // class org/springframework/boot/system/JavaVersion
       2: aload_0
       3: invokestatic  #22                 // Method java/lang/Enum.valueOf:(Ljava/lang/Class;Ljava/lang/String;)Ljava/lang/Enum;
       6: checkcast     #1                  // class org/springframework/boot/system/JavaVersion
       9: areturn

  private org.springframework.boot.system.JavaVersion(java.lang.String, java.lang.Class<?>, java.lang.String);
    Code:
       0: aload_0
       1: aload_1
       2: iload_2
       3: invokespecial #28                 // Method java/lang/Enum."<init>":(Ljava/lang/String;I)V
       6: aload_0
       7: aload_3
       8: putfield      #32                 // Field name:Ljava/lang/String;
      11: aload_0
      12: aload         4
      14: aload         5
      16: iconst_0
      17: anewarray     #36                 // class java/lang/Class
      20: invokestatic  #38                 // Method org/springframework/util/ClassUtils.hasMethod:(Ljava/lang/Class;Ljava/lang/String;[Ljava/lang/Class;)Z
      23: putfield      #44                 // Field available:Z
      26: return

  public java.lang.String toString();
    Code:
       0: aload_0
       1: getfield      #32                 // Field name:Ljava/lang/String;
       4: areturn

  public static org.springframework.boot.system.JavaVersion getJavaVersion();
    Code:
       0: invokestatic  #48                 // Method values:()[Lorg/springframework/boot/system/JavaVersion;
       3: invokestatic  #52                 // Method java/util/Arrays.asList:([Ljava/lang/Object;)Ljava/util/List;
       6: astore_0
       7: aload_0
       8: invokestatic  #58                 // Method java/util/Collections.reverse:(Ljava/util/List;)V
      11: aload_0
      12: invokeinterface #64,  1           // InterfaceMethod java/util/List.iterator:()Ljava/util/Iterator;
      17: astore_1
      18: aload_1
      19: invokeinterface #70,  1           // InterfaceMethod java/util/Iterator.hasNext:()Z
      24: ifeq          49
      27: aload_1
      28: invokeinterface #76,  1           // InterfaceMethod java/util/Iterator.next:()Ljava/lang/Object;
      33: checkcast     #1                  // class org/springframework/boot/system/JavaVersion
      36: astore_2
      37: aload_2
      38: getfield      #44                 // Field available:Z
      41: ifeq          46
      44: aload_2
      45: areturn
      46: goto          18
      49: getstatic     #3                  // Field SEVENTEEN:Lorg/springframework/boot/system/JavaVersion;
      52: areturn

  public boolean isEqualOrNewerThan(org.springframework.boot.system.JavaVersion);
    Code:
       0: aload_0
       1: aload_1
       2: invokevirtual #79                 // Method compareTo:(Ljava/lang/Enum;)I
       5: iflt          12
       8: iconst_1
       9: goto          13
      12: iconst_0
      13: ireturn

  public boolean isOlderThan(org.springframework.boot.system.JavaVersion);
    Code:
       0: aload_0
       1: aload_1
       2: invokevirtual #79                 // Method compareTo:(Ljava/lang/Enum;)I
       5: ifge          12
       8: iconst_1
       9: goto          13
      12: iconst_0
      13: ireturn

  private static org.springframework.boot.system.JavaVersion[] $values();
    Code:
       0: iconst_3
       1: anewarray     #1                  // class org/springframework/boot/system/JavaVersion
       4: dup
       5: iconst_0
       6: getstatic     #3                  // Field SEVENTEEN:Lorg/springframework/boot/system/JavaVersion;
       9: aastore
      10: dup
      11: iconst_1
      12: getstatic     #7                  // Field EIGHTEEN:Lorg/springframework/boot/system/JavaVersion;
      15: aastore
      16: dup
      17: iconst_2
      18: getstatic     #10                 // Field NINETEEN:Lorg/springframework/boot/system/JavaVersion;
      21: aastore
      22: areturn

  static {};
    Code:
       0: new           #1                  // class org/springframework/boot/system/JavaVersion
       3: dup
       4: ldc           #83                 // String SEVENTEEN
       6: iconst_0
       7: ldc           #84                 // String 17
       9: ldc           #86                 // class java/io/Console
      11: ldc           #88                 // String charset
      13: invokespecial #90                 // Method "<init>":(Ljava/lang/String;ILjava/lang/String;Ljava/lang/Class;Ljava/lang/String;)V
      16: putstatic     #3                  // Field SEVENTEEN:Lorg/springframework/boot/system/JavaVersion;
      19: new           #1                  // class org/springframework/boot/system/JavaVersion
      22: dup
      23: ldc           #93                 // String EIGHTEEN
      25: iconst_1
      26: ldc           #94                 // String 18
      28: ldc           #96                 // class java/time/Duration
      30: ldc           #98                 // String isPositive
      32: invokespecial #90                 // Method "<init>":(Ljava/lang/String;ILjava/lang/String;Ljava/lang/Class;Ljava/lang/String;)V
      35: putstatic     #7                  // Field EIGHTEEN:Lorg/springframework/boot/system/JavaVersion;
      38: new           #1                  // class org/springframework/boot/system/JavaVersion
      41: dup
      42: ldc           #100                // String NINETEEN
      44: iconst_2
      45: ldc           #101                // String 19
      47: ldc           #103                // class java/util/concurrent/Future
      49: ldc           #105                // String state
      51: invokespecial #90                 // Method "<init>":(Ljava/lang/String;ILjava/lang/String;Ljava/lang/Class;Ljava/lang/String;)V
      54: putstatic     #10                 // Field NINETEEN:Lorg/springframework/boot/system/JavaVersion;
      57: invokestatic  #107                // Method $values:()[Lorg/springframework/boot/system/JavaVersion;
      60: putstatic     #13                 // Field $VALUES:[Lorg/springframework/boot/system/JavaVersion;
      63: return
}
