Compiled from "AbstractTimerTask.java"
public abstract class org.apache.dubbo.remoting.exchange.support.header.AbstractTimerTask implements org.apache.dubbo.common.timer.TimerTask {
  private final org.apache.dubbo.remoting.exchange.support.header.AbstractTimerTask$ChannelProvider channelProvider;

  private final org.apache.dubbo.common.timer.HashedWheelTimer hashedWheelTimer;

  private final java.lang.Long tick;

  protected volatile boolean cancel;

  private volatile org.apache.dubbo.common.timer.Timeout timeout;

  org.apache.dubbo.remoting.exchange.support.header.AbstractTimerTask(org.apache.dubbo.remoting.exchange.support.header.AbstractTimerTask$ChannelProvider, org.apache.dubbo.common.timer.HashedWheelTimer, java.lang.Long);
    Code:
       0: aload_0
       1: invokespecial #1                  // Method java/lang/Object."<init>":()V
       4: aload_0
       5: iconst_0
       6: putfield      #2                  // Field cancel:Z
       9: aload_1
      10: ifnull        21
      13: aload_2
      14: ifnull        21
      17: aload_3
      18: ifnonnull     29
      21: new           #3                  // class java/lang/IllegalArgumentException
      24: dup
      25: invokespecial #4                  // Method java/lang/IllegalArgumentException."<init>":()V
      28: athrow
      29: aload_0
      30: aload_1
      31: putfield      #5                  // Field channelProvider:Lorg/apache/dubbo/remoting/exchange/support/header/AbstractTimerTask$ChannelProvider;
      34: aload_0
      35: aload_2
      36: putfield      #6                  // Field hashedWheelTimer:Lorg/apache/dubbo/common/timer/HashedWheelTimer;
      39: aload_0
      40: aload_3
      41: putfield      #7                  // Field tick:Ljava/lang/Long;
      44: aload_0
      45: invokespecial #8                  // Method start:()V
      48: return

  static java.lang.Long lastRead(org.apache.dubbo.remoting.Channel);
    Code:
       0: aload_0
       1: ldc           #10                 // String READ_TIMESTAMP
       3: invokeinterface #11,  2           // InterfaceMethod org/apache/dubbo/remoting/Channel.getAttribute:(Ljava/lang/String;)Ljava/lang/Object;
       8: checkcast     #12                 // class java/lang/Long
      11: areturn

  static java.lang.Long lastWrite(org.apache.dubbo.remoting.Channel);
    Code:
       0: aload_0
       1: ldc           #13                 // String WRITE_TIMESTAMP
       3: invokeinterface #11,  2           // InterfaceMethod org/apache/dubbo/remoting/Channel.getAttribute:(Ljava/lang/String;)Ljava/lang/Object;
       8: checkcast     #12                 // class java/lang/Long
      11: areturn

  static java.lang.Long now();
    Code:
       0: invokestatic  #14                 // Method java/lang/System.currentTimeMillis:()J
       3: invokestatic  #15                 // Method java/lang/Long.valueOf:(J)Ljava/lang/Long;
       6: areturn

  private void start();
    Code:
       0: aload_0
       1: aload_0
       2: getfield      #6                  // Field hashedWheelTimer:Lorg/apache/dubbo/common/timer/HashedWheelTimer;
       5: aload_0
       6: aload_0
       7: getfield      #7                  // Field tick:Ljava/lang/Long;
      10: invokevirtual #16                 // Method java/lang/Long.longValue:()J
      13: getstatic     #17                 // Field java/util/concurrent/TimeUnit.MILLISECONDS:Ljava/util/concurrent/TimeUnit;
      16: invokevirtual #18                 // Method org/apache/dubbo/common/timer/HashedWheelTimer.newTimeout:(Lorg/apache/dubbo/common/timer/TimerTask;JLjava/util/concurrent/TimeUnit;)Lorg/apache/dubbo/common/timer/Timeout;
      19: putfield      #19                 // Field timeout:Lorg/apache/dubbo/common/timer/Timeout;
      22: return

  public synchronized void cancel();
    Code:
       0: aload_0
       1: iconst_1
       2: putfield      #2                  // Field cancel:Z
       5: aload_0
       6: getfield      #19                 // Field timeout:Lorg/apache/dubbo/common/timer/Timeout;
       9: invokeinterface #20,  1           // InterfaceMethod org/apache/dubbo/common/timer/Timeout.cancel:()Z
      14: pop
      15: return

  private synchronized void reput(org.apache.dubbo.common.timer.Timeout);
    Code:
       0: aload_1
       1: ifnonnull     12
       4: new           #3                  // class java/lang/IllegalArgumentException
       7: dup
       8: invokespecial #4                  // Method java/lang/IllegalArgumentException."<init>":()V
      11: athrow
      12: aload_0
      13: getfield      #2                  // Field cancel:Z
      16: ifeq          20
      19: return
      20: aload_0
      21: getfield      #6                  // Field hashedWheelTimer:Lorg/apache/dubbo/common/timer/HashedWheelTimer;
      24: invokevirtual #21                 // Method org/apache/dubbo/common/timer/HashedWheelTimer.isStop:()Z
      27: ifne          39
      30: aload_1
      31: invokeinterface #22,  1           // InterfaceMethod org/apache/dubbo/common/timer/Timeout.isCancelled:()Z
      36: ifeq          40
      39: return
      40: aload_0
      41: aload_0
      42: getfield      #6                  // Field hashedWheelTimer:Lorg/apache/dubbo/common/timer/HashedWheelTimer;
      45: aload_1
      46: invokeinterface #23,  1           // InterfaceMethod org/apache/dubbo/common/timer/Timeout.task:()Lorg/apache/dubbo/common/timer/TimerTask;
      51: aload_0
      52: getfield      #7                  // Field tick:Ljava/lang/Long;
      55: invokevirtual #16                 // Method java/lang/Long.longValue:()J
      58: getstatic     #17                 // Field java/util/concurrent/TimeUnit.MILLISECONDS:Ljava/util/concurrent/TimeUnit;
      61: invokevirtual #18                 // Method org/apache/dubbo/common/timer/HashedWheelTimer.newTimeout:(Lorg/apache/dubbo/common/timer/TimerTask;JLjava/util/concurrent/TimeUnit;)Lorg/apache/dubbo/common/timer/Timeout;
      64: putfield      #19                 // Field timeout:Lorg/apache/dubbo/common/timer/Timeout;
      67: return

  public synchronized void run(org.apache.dubbo.common.timer.Timeout) throws java.lang.Exception;
    Code:
       0: aload_0
       1: getfield      #5                  // Field channelProvider:Lorg/apache/dubbo/remoting/exchange/support/header/AbstractTimerTask$ChannelProvider;
       4: invokeinterface #24,  1           // InterfaceMethod org/apache/dubbo/remoting/exchange/support/header/AbstractTimerTask$ChannelProvider.getChannels:()Ljava/util/Collection;
       9: astore_2
      10: aload_2
      11: invokeinterface #25,  1           // InterfaceMethod java/util/Collection.iterator:()Ljava/util/Iterator;
      16: astore_3
      17: aload_3
      18: invokeinterface #26,  1           // InterfaceMethod java/util/Iterator.hasNext:()Z
      23: ifeq          56
      26: aload_3
      27: invokeinterface #27,  1           // InterfaceMethod java/util/Iterator.next:()Ljava/lang/Object;
      32: checkcast     #28                 // class org/apache/dubbo/remoting/Channel
      35: astore        4
      37: aload         4
      39: invokeinterface #29,  1           // InterfaceMethod org/apache/dubbo/remoting/Channel.isClosed:()Z
      44: ifne          53
      47: aload_0
      48: aload         4
      50: invokevirtual #30                 // Method doTask:(Lorg/apache/dubbo/remoting/Channel;)V
      53: goto          17
      56: aload_0
      57: aload_1
      58: invokespecial #31                 // Method reput:(Lorg/apache/dubbo/common/timer/Timeout;)V
      61: return

  protected abstract void doTask(org.apache.dubbo.remoting.Channel);
}
