Compiled from "HeaderExchanger.java"
public class org.apache.dubbo.remoting.exchange.support.header.HeaderExchanger implements org.apache.dubbo.remoting.exchange.Exchanger {
  public static final java.lang.String NAME;

  public org.apache.dubbo.remoting.exchange.support.header.HeaderExchanger();
    Code:
       0: aload_0
       1: invokespecial #2                  // Method java/lang/Object."<init>":()V
       4: return

  public org.apache.dubbo.remoting.exchange.ExchangeClient connect(org.apache.dubbo.common.URL, org.apache.dubbo.remoting.exchange.ExchangeHandler) throws org.apache.dubbo.remoting.RemotingException;
    Code:
       0: new           #3                  // class org/apache/dubbo/remoting/exchange/support/header/HeaderExchangeClient
       3: dup
       4: aload_1
       5: iconst_1
       6: anewarray     #4                  // class org/apache/dubbo/remoting/ChannelHandler
       9: dup
      10: iconst_0
      11: new           #5                  // class org/apache/dubbo/remoting/transport/DecodeHandler
      14: dup
      15: new           #6                  // class org/apache/dubbo/remoting/exchange/support/header/HeaderExchangeHandler
      18: dup
      19: aload_2
      20: invokespecial #7                  // Method org/apache/dubbo/remoting/exchange/support/header/HeaderExchangeHandler."<init>":(Lorg/apache/dubbo/remoting/exchange/ExchangeHandler;)V
      23: invokespecial #8                  // Method org/apache/dubbo/remoting/transport/DecodeHandler."<init>":(Lorg/apache/dubbo/remoting/ChannelHandler;)V
      26: aastore
      27: invokestatic  #9                  // Method org/apache/dubbo/remoting/Transporters.connect:(Lorg/apache/dubbo/common/URL;[Lorg/apache/dubbo/remoting/ChannelHandler;)Lorg/apache/dubbo/remoting/Client;
      30: iconst_1
      31: invokespecial #10                 // Method org/apache/dubbo/remoting/exchange/support/header/HeaderExchangeClient."<init>":(Lorg/apache/dubbo/remoting/Client;Z)V
      34: areturn

  public org.apache.dubbo.remoting.exchange.ExchangeServer bind(org.apache.dubbo.common.URL, org.apache.dubbo.remoting.exchange.ExchangeHandler) throws org.apache.dubbo.remoting.RemotingException;
    Code:
       0: aload_1
       1: ldc           #11                 // String ispuserver
       3: iconst_0
       4: invokevirtual #12                 // Method org/apache/dubbo/common/URL.getParameter:(Ljava/lang/String;Z)Z
       7: istore        4
       9: iload         4
      11: ifeq          44
      14: new           #13                 // class org/apache/dubbo/remoting/exchange/support/header/HeaderExchangeServer
      17: dup
      18: aload_1
      19: new           #5                  // class org/apache/dubbo/remoting/transport/DecodeHandler
      22: dup
      23: new           #6                  // class org/apache/dubbo/remoting/exchange/support/header/HeaderExchangeHandler
      26: dup
      27: aload_2
      28: invokespecial #7                  // Method org/apache/dubbo/remoting/exchange/support/header/HeaderExchangeHandler."<init>":(Lorg/apache/dubbo/remoting/exchange/ExchangeHandler;)V
      31: invokespecial #8                  // Method org/apache/dubbo/remoting/transport/DecodeHandler."<init>":(Lorg/apache/dubbo/remoting/ChannelHandler;)V
      34: invokestatic  #14                 // Method org/apache/dubbo/remoting/exchange/PortUnificationExchanger.bind:(Lorg/apache/dubbo/common/URL;Lorg/apache/dubbo/remoting/ChannelHandler;)Lorg/apache/dubbo/remoting/RemotingServer;
      37: invokespecial #15                 // Method org/apache/dubbo/remoting/exchange/support/header/HeaderExchangeServer."<init>":(Lorg/apache/dubbo/remoting/RemotingServer;)V
      40: astore_3
      41: goto          78
      44: new           #13                 // class org/apache/dubbo/remoting/exchange/support/header/HeaderExchangeServer
      47: dup
      48: aload_1
      49: iconst_1
      50: anewarray     #4                  // class org/apache/dubbo/remoting/ChannelHandler
      53: dup
      54: iconst_0
      55: new           #5                  // class org/apache/dubbo/remoting/transport/DecodeHandler
      58: dup
      59: new           #6                  // class org/apache/dubbo/remoting/exchange/support/header/HeaderExchangeHandler
      62: dup
      63: aload_2
      64: invokespecial #7                  // Method org/apache/dubbo/remoting/exchange/support/header/HeaderExchangeHandler."<init>":(Lorg/apache/dubbo/remoting/exchange/ExchangeHandler;)V
      67: invokespecial #8                  // Method org/apache/dubbo/remoting/transport/DecodeHandler."<init>":(Lorg/apache/dubbo/remoting/ChannelHandler;)V
      70: aastore
      71: invokestatic  #16                 // Method org/apache/dubbo/remoting/Transporters.bind:(Lorg/apache/dubbo/common/URL;[Lorg/apache/dubbo/remoting/ChannelHandler;)Lorg/apache/dubbo/remoting/RemotingServer;
      74: invokespecial #15                 // Method org/apache/dubbo/remoting/exchange/support/header/HeaderExchangeServer."<init>":(Lorg/apache/dubbo/remoting/RemotingServer;)V
      77: astore_3
      78: aload_3
      79: areturn
}
