Compiled from "HeaderExchangeHandler.java"
public class org.apache.dubbo.remoting.exchange.support.header.HeaderExchangeHandler implements org.apache.dubbo.remoting.transport.ChannelHandlerDelegate {
  protected static final org.apache.dubbo.common.logger.ErrorTypeAwareLogger logger;

  private final org.apache.dubbo.remoting.exchange.ExchangeHandler handler;

  public org.apache.dubbo.remoting.exchange.support.header.HeaderExchangeHandler(org.apache.dubbo.remoting.exchange.ExchangeHandler);
    Code:
       0: aload_0
       1: invokespecial #3                  // Method java/lang/Object."<init>":()V
       4: aload_1
       5: ifnonnull     18
       8: new           #4                  // class java/lang/IllegalArgumentException
      11: dup
      12: ldc           #5                  // String handler == null
      14: invokespecial #6                  // Method java/lang/IllegalArgumentException."<init>":(Ljava/lang/String;)V
      17: athrow
      18: aload_0
      19: aload_1
      20: putfield      #7                  // Field handler:Lorg/apache/dubbo/remoting/exchange/ExchangeHandler;
      23: return

  static void handleResponse(org.apache.dubbo.remoting.Channel, org.apache.dubbo.remoting.exchange.Response) throws org.apache.dubbo.remoting.RemotingException;
    Code:
       0: aload_1
       1: ifnull        16
       4: aload_1
       5: invokevirtual #8                  // Method org/apache/dubbo/remoting/exchange/Response.isHeartbeat:()Z
       8: ifne          16
      11: aload_0
      12: aload_1
      13: invokestatic  #9                  // Method org/apache/dubbo/remoting/exchange/support/DefaultFuture.received:(Lorg/apache/dubbo/remoting/Channel;Lorg/apache/dubbo/remoting/exchange/Response;)V
      16: return

  private static boolean isClientSide(org.apache.dubbo.remoting.Channel);
    Code:
       0: aload_0
       1: invokeinterface #10,  1           // InterfaceMethod org/apache/dubbo/remoting/Channel.getRemoteAddress:()Ljava/net/InetSocketAddress;
       6: astore_1
       7: aload_0
       8: invokeinterface #11,  1           // InterfaceMethod org/apache/dubbo/remoting/Channel.getUrl:()Lorg/apache/dubbo/common/URL;
      13: astore_2
      14: aload_2
      15: invokevirtual #12                 // Method org/apache/dubbo/common/URL.getPort:()I
      18: aload_1
      19: invokevirtual #13                 // Method java/net/InetSocketAddress.getPort:()I
      22: if_icmpne     52
      25: aload_2
      26: invokevirtual #14                 // Method org/apache/dubbo/common/URL.getIp:()Ljava/lang/String;
      29: invokestatic  #15                 // Method org/apache/dubbo/common/utils/NetUtils.filterLocalHost:(Ljava/lang/String;)Ljava/lang/String;
      32: aload_1
      33: invokevirtual #16                 // Method java/net/InetSocketAddress.getAddress:()Ljava/net/InetAddress;
      36: invokevirtual #17                 // Method java/net/InetAddress.getHostAddress:()Ljava/lang/String;
      39: invokestatic  #15                 // Method org/apache/dubbo/common/utils/NetUtils.filterLocalHost:(Ljava/lang/String;)Ljava/lang/String;
      42: invokevirtual #18                 // Method java/lang/String.equals:(Ljava/lang/Object;)Z
      45: ifeq          52
      48: iconst_1
      49: goto          53
      52: iconst_0
      53: ireturn

  void handlerEvent(org.apache.dubbo.remoting.Channel, org.apache.dubbo.remoting.exchange.Request) throws org.apache.dubbo.remoting.RemotingException;
    Code:
       0: aload_2
       1: invokevirtual #19                 // Method org/apache/dubbo/remoting/exchange/Request.getData:()Ljava/lang/Object;
       4: ifnull        57
       7: aload_2
       8: invokevirtual #19                 // Method org/apache/dubbo/remoting/exchange/Request.getData:()Ljava/lang/Object;
      11: ldc           #20                 // String R
      13: invokevirtual #21                 // Method java/lang/Object.equals:(Ljava/lang/Object;)Z
      16: ifeq          57
      19: aload_1
      20: ldc           #23                 // String channel.readonly
      22: getstatic     #24                 // Field java/lang/Boolean.TRUE:Ljava/lang/Boolean;
      25: invokeinterface #25,  3           // InterfaceMethod org/apache/dubbo/remoting/Channel.setAttribute:(Ljava/lang/String;Ljava/lang/Object;)V
      30: getstatic     #26                 // Field logger:Lorg/apache/dubbo/common/logger/ErrorTypeAwareLogger;
      33: new           #27                 // class java/lang/StringBuilder
      36: dup
      37: invokespecial #28                 // Method java/lang/StringBuilder."<init>":()V
      40: ldc           #29                 // String ChannelReadOnly set true for channel:
      42: invokevirtual #30                 // Method java/lang/StringBuilder.append:(Ljava/lang/String;)Ljava/lang/StringBuilder;
      45: aload_1
      46: invokevirtual #31                 // Method java/lang/StringBuilder.append:(Ljava/lang/Object;)Ljava/lang/StringBuilder;
      49: invokevirtual #32                 // Method java/lang/StringBuilder.toString:()Ljava/lang/String;
      52: invokeinterface #33,  2           // InterfaceMethod org/apache/dubbo/common/logger/ErrorTypeAwareLogger.info:(Ljava/lang/String;)V
      57: aload_2
      58: invokevirtual #19                 // Method org/apache/dubbo/remoting/exchange/Request.getData:()Ljava/lang/Object;
      61: ifnull        111
      64: aload_2
      65: invokevirtual #19                 // Method org/apache/dubbo/remoting/exchange/Request.getData:()Ljava/lang/Object;
      68: ldc           #34                 // String W
      70: invokevirtual #21                 // Method java/lang/Object.equals:(Ljava/lang/Object;)Z
      73: ifeq          111
      76: aload_1
      77: ldc           #23                 // String channel.readonly
      79: invokeinterface #35,  2           // InterfaceMethod org/apache/dubbo/remoting/Channel.removeAttribute:(Ljava/lang/String;)V
      84: getstatic     #26                 // Field logger:Lorg/apache/dubbo/common/logger/ErrorTypeAwareLogger;
      87: new           #27                 // class java/lang/StringBuilder
      90: dup
      91: invokespecial #28                 // Method java/lang/StringBuilder."<init>":()V
      94: ldc           #36                 // String ChannelReadOnly set false for channel:
      96: invokevirtual #30                 // Method java/lang/StringBuilder.append:(Ljava/lang/String;)Ljava/lang/StringBuilder;
      99: aload_1
     100: invokevirtual #31                 // Method java/lang/StringBuilder.append:(Ljava/lang/Object;)Ljava/lang/StringBuilder;
     103: invokevirtual #32                 // Method java/lang/StringBuilder.toString:()Ljava/lang/String;
     106: invokeinterface #33,  2           // InterfaceMethod org/apache/dubbo/common/logger/ErrorTypeAwareLogger.info:(Ljava/lang/String;)V
     111: return

  void handleRequest(org.apache.dubbo.remoting.exchange.ExchangeChannel, org.apache.dubbo.remoting.exchange.Request) throws org.apache.dubbo.remoting.RemotingException;
    Code:
       0: new           #37                 // class org/apache/dubbo/remoting/exchange/Response
       3: dup
       4: aload_2
       5: invokevirtual #38                 // Method org/apache/dubbo/remoting/exchange/Request.getId:()J
       8: aload_2
       9: invokevirtual #39                 // Method org/apache/dubbo/remoting/exchange/Request.getVersion:()Ljava/lang/String;
      12: invokespecial #40                 // Method org/apache/dubbo/remoting/exchange/Response."<init>":(JLjava/lang/String;)V
      15: astore_3
      16: aload_2
      17: invokevirtual #41                 // Method org/apache/dubbo/remoting/exchange/Request.isBroken:()Z
      20: ifeq          106
      23: aload_2
      24: invokevirtual #19                 // Method org/apache/dubbo/remoting/exchange/Request.getData:()Ljava/lang/Object;
      27: astore        4
      29: aload         4
      31: ifnonnull     40
      34: aconst_null
      35: astore        5
      37: goto          68
      40: aload         4
      42: instanceof    #42                 // class java/lang/Throwable
      45: ifeq          61
      48: aload         4
      50: checkcast     #42                 // class java/lang/Throwable
      53: invokestatic  #43                 // Method org/apache/dubbo/common/utils/StringUtils.toString:(Ljava/lang/Throwable;)Ljava/lang/String;
      56: astore        5
      58: goto          68
      61: aload         4
      63: invokevirtual #44                 // Method java/lang/Object.toString:()Ljava/lang/String;
      66: astore        5
      68: aload_3
      69: new           #27                 // class java/lang/StringBuilder
      72: dup
      73: invokespecial #28                 // Method java/lang/StringBuilder."<init>":()V
      76: ldc           #45                 // String Fail to decode request due to:
      78: invokevirtual #30                 // Method java/lang/StringBuilder.append:(Ljava/lang/String;)Ljava/lang/StringBuilder;
      81: aload         5
      83: invokevirtual #30                 // Method java/lang/StringBuilder.append:(Ljava/lang/String;)Ljava/lang/StringBuilder;
      86: invokevirtual #32                 // Method java/lang/StringBuilder.toString:()Ljava/lang/String;
      89: invokevirtual #46                 // Method org/apache/dubbo/remoting/exchange/Response.setErrorMessage:(Ljava/lang/String;)V
      92: aload_3
      93: bipush        40
      95: invokevirtual #47                 // Method org/apache/dubbo/remoting/exchange/Response.setStatus:(B)V
      98: aload_1
      99: aload_3
     100: invokeinterface #48,  2           // InterfaceMethod org/apache/dubbo/remoting/exchange/ExchangeChannel.send:(Ljava/lang/Object;)V
     105: return
     106: aload_2
     107: invokevirtual #19                 // Method org/apache/dubbo/remoting/exchange/Request.getData:()Ljava/lang/Object;
     110: astore        4
     112: aload_0
     113: getfield      #7                  // Field handler:Lorg/apache/dubbo/remoting/exchange/ExchangeHandler;
     116: aload_1
     117: aload         4
     119: invokeinterface #49,  3           // InterfaceMethod org/apache/dubbo/remoting/exchange/ExchangeHandler.reply:(Lorg/apache/dubbo/remoting/exchange/ExchangeChannel;Ljava/lang/Object;)Ljava/util/concurrent/CompletableFuture;
     124: astore        5
     126: aload         5
     128: aload_3
     129: aload_1
     130: invokedynamic #50,  0             // InvokeDynamic #0:accept:(Lorg/apache/dubbo/remoting/exchange/Response;Lorg/apache/dubbo/remoting/exchange/ExchangeChannel;)Ljava/util/function/BiConsumer;
     135: invokeinterface #51,  2           // InterfaceMethod java/util/concurrent/CompletionStage.whenComplete:(Ljava/util/function/BiConsumer;)Ljava/util/concurrent/CompletionStage;
     140: pop
     141: goto          168
     144: astore        5
     146: aload_3
     147: bipush        70
     149: invokevirtual #47                 // Method org/apache/dubbo/remoting/exchange/Response.setStatus:(B)V
     152: aload_3
     153: aload         5
     155: invokestatic  #43                 // Method org/apache/dubbo/common/utils/StringUtils.toString:(Ljava/lang/Throwable;)Ljava/lang/String;
     158: invokevirtual #46                 // Method org/apache/dubbo/remoting/exchange/Response.setErrorMessage:(Ljava/lang/String;)V
     161: aload_1
     162: aload_3
     163: invokeinterface #48,  2           // InterfaceMethod org/apache/dubbo/remoting/exchange/ExchangeChannel.send:(Ljava/lang/Object;)V
     168: return
    Exception table:
       from    to  target type
         112   141   144   Class java/lang/Throwable

  public void connected(org.apache.dubbo.remoting.Channel) throws org.apache.dubbo.remoting.RemotingException;
    Code:
       0: aload_1
       1: invokestatic  #52                 // Method org/apache/dubbo/remoting/exchange/support/header/HeaderExchangeChannel.getOrAddChannel:(Lorg/apache/dubbo/remoting/Channel;)Lorg/apache/dubbo/remoting/exchange/support/header/HeaderExchangeChannel;
       4: astore_2
       5: aload_0
       6: getfield      #7                  // Field handler:Lorg/apache/dubbo/remoting/exchange/ExchangeHandler;
       9: aload_2
      10: invokeinterface #53,  2           // InterfaceMethod org/apache/dubbo/remoting/exchange/ExchangeHandler.connected:(Lorg/apache/dubbo/remoting/Channel;)V
      15: return

  public void disconnected(org.apache.dubbo.remoting.Channel) throws org.apache.dubbo.remoting.RemotingException;
    Code:
       0: aload_1
       1: invokestatic  #52                 // Method org/apache/dubbo/remoting/exchange/support/header/HeaderExchangeChannel.getOrAddChannel:(Lorg/apache/dubbo/remoting/Channel;)Lorg/apache/dubbo/remoting/exchange/support/header/HeaderExchangeChannel;
       4: astore_2
       5: aload_0
       6: getfield      #7                  // Field handler:Lorg/apache/dubbo/remoting/exchange/ExchangeHandler;
       9: aload_2
      10: invokeinterface #54,  2           // InterfaceMethod org/apache/dubbo/remoting/exchange/ExchangeHandler.disconnected:(Lorg/apache/dubbo/remoting/Channel;)V
      15: aload_1
      16: invokestatic  #55                 // Method org/apache/dubbo/remoting/exchange/support/DefaultFuture.closeChannel:(Lorg/apache/dubbo/remoting/Channel;)V
      19: aload_1
      20: invokestatic  #56                 // Method org/apache/dubbo/remoting/exchange/support/header/HeaderExchangeChannel.removeChannel:(Lorg/apache/dubbo/remoting/Channel;)V
      23: goto          37
      26: astore_3
      27: aload_1
      28: invokestatic  #55                 // Method org/apache/dubbo/remoting/exchange/support/DefaultFuture.closeChannel:(Lorg/apache/dubbo/remoting/Channel;)V
      31: aload_1
      32: invokestatic  #56                 // Method org/apache/dubbo/remoting/exchange/support/header/HeaderExchangeChannel.removeChannel:(Lorg/apache/dubbo/remoting/Channel;)V
      35: aload_3
      36: athrow
      37: return
    Exception table:
       from    to  target type
           5    15    26   any

  public void sent(org.apache.dubbo.remoting.Channel, java.lang.Object) throws org.apache.dubbo.remoting.RemotingException;
    Code:
       0: aconst_null
       1: astore_3
       2: aload_1
       3: invokestatic  #52                 // Method org/apache/dubbo/remoting/exchange/support/header/HeaderExchangeChannel.getOrAddChannel:(Lorg/apache/dubbo/remoting/Channel;)Lorg/apache/dubbo/remoting/exchange/support/header/HeaderExchangeChannel;
       6: astore        4
       8: aload_0
       9: getfield      #7                  // Field handler:Lorg/apache/dubbo/remoting/exchange/ExchangeHandler;
      12: aload         4
      14: aload_2
      15: invokeinterface #57,  3           // InterfaceMethod org/apache/dubbo/remoting/exchange/ExchangeHandler.sent:(Lorg/apache/dubbo/remoting/Channel;Ljava/lang/Object;)V
      20: goto          32
      23: astore        4
      25: aload         4
      27: astore_3
      28: aload_1
      29: invokestatic  #58                 // Method org/apache/dubbo/remoting/exchange/support/header/HeaderExchangeChannel.removeChannelIfDisconnected:(Lorg/apache/dubbo/remoting/Channel;)V
      32: aload_2
      33: instanceof    #59                 // class org/apache/dubbo/remoting/exchange/Request
      36: ifeq          51
      39: aload_2
      40: checkcast     #59                 // class org/apache/dubbo/remoting/exchange/Request
      43: astore        4
      45: aload_1
      46: aload         4
      48: invokestatic  #60                 // Method org/apache/dubbo/remoting/exchange/support/DefaultFuture.sent:(Lorg/apache/dubbo/remoting/Channel;Lorg/apache/dubbo/remoting/exchange/Request;)V
      51: aload_2
      52: instanceof    #61                 // class org/apache/dubbo/remoting/exchange/support/MultiMessage
      55: ifeq          110
      58: aload_2
      59: checkcast     #61                 // class org/apache/dubbo/remoting/exchange/support/MultiMessage
      62: astore        4
      64: aload         4
      66: invokevirtual #62                 // Method org/apache/dubbo/remoting/exchange/support/MultiMessage.iterator:()Ljava/util/Iterator;
      69: astore        5
      71: aload         5
      73: invokeinterface #63,  1           // InterfaceMethod java/util/Iterator.hasNext:()Z
      78: ifeq          110
      81: aload         5
      83: invokeinterface #64,  1           // InterfaceMethod java/util/Iterator.next:()Ljava/lang/Object;
      88: astore        6
      90: aload         6
      92: instanceof    #59                 // class org/apache/dubbo/remoting/exchange/Request
      95: ifeq          107
      98: aload_1
      99: aload         6
     101: checkcast     #59                 // class org/apache/dubbo/remoting/exchange/Request
     104: invokestatic  #60                 // Method org/apache/dubbo/remoting/exchange/support/DefaultFuture.sent:(Lorg/apache/dubbo/remoting/Channel;Lorg/apache/dubbo/remoting/exchange/Request;)V
     107: goto          71
     110: aload_3
     111: ifnull        163
     114: aload_3
     115: instanceof    #65                 // class java/lang/RuntimeException
     118: ifeq          126
     121: aload_3
     122: checkcast     #65                 // class java/lang/RuntimeException
     125: athrow
     126: aload_3
     127: instanceof    #66                 // class org/apache/dubbo/remoting/RemotingException
     130: ifeq          138
     133: aload_3
     134: checkcast     #66                 // class org/apache/dubbo/remoting/RemotingException
     137: athrow
     138: new           #66                 // class org/apache/dubbo/remoting/RemotingException
     141: dup
     142: aload_1
     143: invokeinterface #67,  1           // InterfaceMethod org/apache/dubbo/remoting/Channel.getLocalAddress:()Ljava/net/InetSocketAddress;
     148: aload_1
     149: invokeinterface #10,  1           // InterfaceMethod org/apache/dubbo/remoting/Channel.getRemoteAddress:()Ljava/net/InetSocketAddress;
     154: aload_3
     155: invokevirtual #68                 // Method java/lang/Throwable.getMessage:()Ljava/lang/String;
     158: aload_3
     159: invokespecial #69                 // Method org/apache/dubbo/remoting/RemotingException."<init>":(Ljava/net/InetSocketAddress;Ljava/net/InetSocketAddress;Ljava/lang/String;Ljava/lang/Throwable;)V
     162: athrow
     163: return
    Exception table:
       from    to  target type
           2    20    23   Class java/lang/Throwable

  public void received(org.apache.dubbo.remoting.Channel, java.lang.Object) throws org.apache.dubbo.remoting.RemotingException;
    Code:
       0: aload_1
       1: invokestatic  #52                 // Method org/apache/dubbo/remoting/exchange/support/header/HeaderExchangeChannel.getOrAddChannel:(Lorg/apache/dubbo/remoting/Channel;)Lorg/apache/dubbo/remoting/exchange/support/header/HeaderExchangeChannel;
       4: astore_3
       5: aload_2
       6: instanceof    #59                 // class org/apache/dubbo/remoting/exchange/Request
       9: ifeq          72
      12: aload_2
      13: checkcast     #59                 // class org/apache/dubbo/remoting/exchange/Request
      16: astore        4
      18: aload         4
      20: invokevirtual #70                 // Method org/apache/dubbo/remoting/exchange/Request.isEvent:()Z
      23: ifeq          36
      26: aload_0
      27: aload_1
      28: aload         4
      30: invokevirtual #71                 // Method handlerEvent:(Lorg/apache/dubbo/remoting/Channel;Lorg/apache/dubbo/remoting/exchange/Request;)V
      33: goto          69
      36: aload         4
      38: invokevirtual #72                 // Method org/apache/dubbo/remoting/exchange/Request.isTwoWay:()Z
      41: ifeq          54
      44: aload_0
      45: aload_3
      46: aload         4
      48: invokevirtual #73                 // Method handleRequest:(Lorg/apache/dubbo/remoting/exchange/ExchangeChannel;Lorg/apache/dubbo/remoting/exchange/Request;)V
      51: goto          69
      54: aload_0
      55: getfield      #7                  // Field handler:Lorg/apache/dubbo/remoting/exchange/ExchangeHandler;
      58: aload_3
      59: aload         4
      61: invokevirtual #19                 // Method org/apache/dubbo/remoting/exchange/Request.getData:()Ljava/lang/Object;
      64: invokeinterface #74,  3           // InterfaceMethod org/apache/dubbo/remoting/exchange/ExchangeHandler.received:(Lorg/apache/dubbo/remoting/Channel;Ljava/lang/Object;)V
      69: goto          225
      72: aload_2
      73: instanceof    #37                 // class org/apache/dubbo/remoting/exchange/Response
      76: ifeq          90
      79: aload_1
      80: aload_2
      81: checkcast     #37                 // class org/apache/dubbo/remoting/exchange/Response
      84: invokestatic  #75                 // Method handleResponse:(Lorg/apache/dubbo/remoting/Channel;Lorg/apache/dubbo/remoting/exchange/Response;)V
      87: goto          225
      90: aload_2
      91: instanceof    #76                 // class java/lang/String
      94: ifeq          214
      97: aload_1
      98: invokestatic  #77                 // Method isClientSide:(Lorg/apache/dubbo/remoting/Channel;)Z
     101: ifeq          179
     104: new           #78                 // class java/lang/Exception
     107: dup
     108: new           #27                 // class java/lang/StringBuilder
     111: dup
     112: invokespecial #28                 // Method java/lang/StringBuilder."<init>":()V
     115: ldc           #79                 // String Dubbo client can not supported string message:
     117: invokevirtual #30                 // Method java/lang/StringBuilder.append:(Ljava/lang/String;)Ljava/lang/StringBuilder;
     120: aload_2
     121: invokevirtual #31                 // Method java/lang/StringBuilder.append:(Ljava/lang/Object;)Ljava/lang/StringBuilder;
     124: ldc           #80                 // String  in channel:
     126: invokevirtual #30                 // Method java/lang/StringBuilder.append:(Ljava/lang/String;)Ljava/lang/StringBuilder;
     129: aload_1
     130: invokevirtual #31                 // Method java/lang/StringBuilder.append:(Ljava/lang/Object;)Ljava/lang/StringBuilder;
     133: ldc           #81                 // String , url:
     135: invokevirtual #30                 // Method java/lang/StringBuilder.append:(Ljava/lang/String;)Ljava/lang/StringBuilder;
     138: aload_1
     139: invokeinterface #11,  1           // InterfaceMethod org/apache/dubbo/remoting/Channel.getUrl:()Lorg/apache/dubbo/common/URL;
     144: invokevirtual #31                 // Method java/lang/StringBuilder.append:(Ljava/lang/Object;)Ljava/lang/StringBuilder;
     147: invokevirtual #32                 // Method java/lang/StringBuilder.toString:()Ljava/lang/String;
     150: invokespecial #82                 // Method java/lang/Exception."<init>":(Ljava/lang/String;)V
     153: astore        4
     155: getstatic     #26                 // Field logger:Lorg/apache/dubbo/common/logger/ErrorTypeAwareLogger;
     158: ldc           #83                 // String 6-6
     160: ldc           #84                 // String
     162: ldc           #84                 // String
     164: aload         4
     166: invokevirtual #85                 // Method java/lang/Exception.getMessage:()Ljava/lang/String;
     169: aload         4
     171: invokeinterface #86,  6           // InterfaceMethod org/apache/dubbo/common/logger/ErrorTypeAwareLogger.error:(Ljava/lang/String;Ljava/lang/String;Ljava/lang/String;Ljava/lang/String;Ljava/lang/Throwable;)V
     176: goto          225
     179: aload_0
     180: getfield      #7                  // Field handler:Lorg/apache/dubbo/remoting/exchange/ExchangeHandler;
     183: aload_1
     184: aload_2
     185: checkcast     #76                 // class java/lang/String
     188: invokeinterface #87,  3           // InterfaceMethod org/apache/dubbo/remoting/exchange/ExchangeHandler.telnet:(Lorg/apache/dubbo/remoting/Channel;Ljava/lang/String;)Ljava/lang/String;
     193: astore        4
     195: aload         4
     197: invokestatic  #88                 // Method org/apache/dubbo/common/utils/StringUtils.isNotEmpty:(Ljava/lang/String;)Z
     200: ifeq          211
     203: aload_1
     204: aload         4
     206: invokeinterface #89,  2           // InterfaceMethod org/apache/dubbo/remoting/Channel.send:(Ljava/lang/Object;)V
     211: goto          225
     214: aload_0
     215: getfield      #7                  // Field handler:Lorg/apache/dubbo/remoting/exchange/ExchangeHandler;
     218: aload_3
     219: aload_2
     220: invokeinterface #74,  3           // InterfaceMethod org/apache/dubbo/remoting/exchange/ExchangeHandler.received:(Lorg/apache/dubbo/remoting/Channel;Ljava/lang/Object;)V
     225: return

  public void caught(org.apache.dubbo.remoting.Channel, java.lang.Throwable) throws org.apache.dubbo.remoting.RemotingException;
    Code:
       0: aload_2
       1: instanceof    #90                 // class org/apache/dubbo/remoting/ExecutionException
       4: ifeq          93
       7: aload_2
       8: checkcast     #90                 // class org/apache/dubbo/remoting/ExecutionException
      11: astore_3
      12: aload_3
      13: invokevirtual #91                 // Method org/apache/dubbo/remoting/ExecutionException.getRequest:()Ljava/lang/Object;
      16: astore        4
      18: aload         4
      20: instanceof    #59                 // class org/apache/dubbo/remoting/exchange/Request
      23: ifeq          93
      26: aload         4
      28: checkcast     #59                 // class org/apache/dubbo/remoting/exchange/Request
      31: astore        5
      33: aload         5
      35: invokevirtual #72                 // Method org/apache/dubbo/remoting/exchange/Request.isTwoWay:()Z
      38: ifeq          93
      41: aload         5
      43: invokevirtual #92                 // Method org/apache/dubbo/remoting/exchange/Request.isHeartbeat:()Z
      46: ifne          93
      49: new           #37                 // class org/apache/dubbo/remoting/exchange/Response
      52: dup
      53: aload         5
      55: invokevirtual #38                 // Method org/apache/dubbo/remoting/exchange/Request.getId:()J
      58: aload         5
      60: invokevirtual #39                 // Method org/apache/dubbo/remoting/exchange/Request.getVersion:()Ljava/lang/String;
      63: invokespecial #40                 // Method org/apache/dubbo/remoting/exchange/Response."<init>":(JLjava/lang/String;)V
      66: astore        6
      68: aload         6
      70: bipush        80
      72: invokevirtual #47                 // Method org/apache/dubbo/remoting/exchange/Response.setStatus:(B)V
      75: aload         6
      77: aload_3
      78: invokestatic  #43                 // Method org/apache/dubbo/common/utils/StringUtils.toString:(Ljava/lang/Throwable;)Ljava/lang/String;
      81: invokevirtual #46                 // Method org/apache/dubbo/remoting/exchange/Response.setErrorMessage:(Ljava/lang/String;)V
      84: aload_1
      85: aload         6
      87: invokeinterface #89,  2           // InterfaceMethod org/apache/dubbo/remoting/Channel.send:(Ljava/lang/Object;)V
      92: return
      93: aload_1
      94: invokestatic  #52                 // Method org/apache/dubbo/remoting/exchange/support/header/HeaderExchangeChannel.getOrAddChannel:(Lorg/apache/dubbo/remoting/Channel;)Lorg/apache/dubbo/remoting/exchange/support/header/HeaderExchangeChannel;
      97: astore_3
      98: aload_0
      99: getfield      #7                  // Field handler:Lorg/apache/dubbo/remoting/exchange/ExchangeHandler;
     102: aload_3
     103: aload_2
     104: invokeinterface #93,  3           // InterfaceMethod org/apache/dubbo/remoting/exchange/ExchangeHandler.caught:(Lorg/apache/dubbo/remoting/Channel;Ljava/lang/Throwable;)V
     109: aload_1
     110: invokestatic  #58                 // Method org/apache/dubbo/remoting/exchange/support/header/HeaderExchangeChannel.removeChannelIfDisconnected:(Lorg/apache/dubbo/remoting/Channel;)V
     113: goto          125
     116: astore        7
     118: aload_1
     119: invokestatic  #58                 // Method org/apache/dubbo/remoting/exchange/support/header/HeaderExchangeChannel.removeChannelIfDisconnected:(Lorg/apache/dubbo/remoting/Channel;)V
     122: aload         7
     124: athrow
     125: return
    Exception table:
       from    to  target type
          98   109   116   any
         116   118   116   any

  public org.apache.dubbo.remoting.ChannelHandler getHandler();
    Code:
       0: aload_0
       1: getfield      #7                  // Field handler:Lorg/apache/dubbo/remoting/exchange/ExchangeHandler;
       4: instanceof    #94                 // class org/apache/dubbo/remoting/transport/ChannelHandlerDelegate
       7: ifeq          23
      10: aload_0
      11: getfield      #7                  // Field handler:Lorg/apache/dubbo/remoting/exchange/ExchangeHandler;
      14: checkcast     #94                 // class org/apache/dubbo/remoting/transport/ChannelHandlerDelegate
      17: invokeinterface #95,  1           // InterfaceMethod org/apache/dubbo/remoting/transport/ChannelHandlerDelegate.getHandler:()Lorg/apache/dubbo/remoting/ChannelHandler;
      22: areturn
      23: aload_0
      24: getfield      #7                  // Field handler:Lorg/apache/dubbo/remoting/exchange/ExchangeHandler;
      27: areturn

  private static void lambda$handleRequest$0(org.apache.dubbo.remoting.exchange.Response, org.apache.dubbo.remoting.exchange.ExchangeChannel, java.lang.Object, java.lang.Throwable);
    Code:
       0: aload_3
       1: ifnonnull     18
       4: aload_0
       5: bipush        20
       7: invokevirtual #47                 // Method org/apache/dubbo/remoting/exchange/Response.setStatus:(B)V
      10: aload_0
      11: aload_2
      12: invokevirtual #96                 // Method org/apache/dubbo/remoting/exchange/Response.setResult:(Ljava/lang/Object;)V
      15: goto          32
      18: aload_0
      19: bipush        70
      21: invokevirtual #47                 // Method org/apache/dubbo/remoting/exchange/Response.setStatus:(B)V
      24: aload_0
      25: aload_3
      26: invokestatic  #43                 // Method org/apache/dubbo/common/utils/StringUtils.toString:(Ljava/lang/Throwable;)Ljava/lang/String;
      29: invokevirtual #46                 // Method org/apache/dubbo/remoting/exchange/Response.setErrorMessage:(Ljava/lang/String;)V
      32: aload_1
      33: aload_0
      34: invokeinterface #48,  2           // InterfaceMethod org/apache/dubbo/remoting/exchange/ExchangeChannel.send:(Ljava/lang/Object;)V
      39: goto          87
      42: astore        4
      44: getstatic     #26                 // Field logger:Lorg/apache/dubbo/common/logger/ErrorTypeAwareLogger;
      47: ldc           #97                 // String 6-14
      49: ldc           #84                 // String
      51: ldc           #84                 // String
      53: new           #27                 // class java/lang/StringBuilder
      56: dup
      57: invokespecial #28                 // Method java/lang/StringBuilder."<init>":()V
      60: ldc           #98                 // String Send result to consumer failed, channel is
      62: invokevirtual #30                 // Method java/lang/StringBuilder.append:(Ljava/lang/String;)Ljava/lang/StringBuilder;
      65: aload_1
      66: invokevirtual #31                 // Method java/lang/StringBuilder.append:(Ljava/lang/Object;)Ljava/lang/StringBuilder;
      69: ldc           #99                 // String , msg is
      71: invokevirtual #30                 // Method java/lang/StringBuilder.append:(Ljava/lang/String;)Ljava/lang/StringBuilder;
      74: aload         4
      76: invokevirtual #31                 // Method java/lang/StringBuilder.append:(Ljava/lang/Object;)Ljava/lang/StringBuilder;
      79: invokevirtual #32                 // Method java/lang/StringBuilder.toString:()Ljava/lang/String;
      82: invokeinterface #100,  5          // InterfaceMethod org/apache/dubbo/common/logger/ErrorTypeAwareLogger.warn:(Ljava/lang/String;Ljava/lang/String;Ljava/lang/String;Ljava/lang/String;)V
      87: return
    Exception table:
       from    to  target type
           0    39    42   Class org/apache/dubbo/remoting/RemotingException

  static {};
    Code:
       0: ldc           #101                // class org/apache/dubbo/remoting/exchange/support/header/HeaderExchangeHandler
       2: invokestatic  #102                // Method org/apache/dubbo/common/logger/LoggerFactory.getErrorTypeAwareLogger:(Ljava/lang/Class;)Lorg/apache/dubbo/common/logger/ErrorTypeAwareLogger;
       5: putstatic     #26                 // Field logger:Lorg/apache/dubbo/common/logger/ErrorTypeAwareLogger;
       8: return
}
