Compiled from "ReconnectTimerTask.java"
public class org.apache.dubbo.remoting.exchange.support.header.ReconnectTimerTask extends org.apache.dubbo.remoting.exchange.support.header.AbstractTimerTask {
  private static final org.apache.dubbo.common.logger.ErrorTypeAwareLogger logger;

  private final int idleTimeout;

  public org.apache.dubbo.remoting.exchange.support.header.ReconnectTimerTask(org.apache.dubbo.remoting.exchange.support.header.AbstractTimerTask$ChannelProvider, org.apache.dubbo.common.timer.HashedWheelTimer, java.lang.Long, int);
    Code:
       0: aload_0
       1: aload_1
       2: aload_2
       3: aload_3
       4: invokespecial #2                  // Method org/apache/dubbo/remoting/exchange/support/header/AbstractTimerTask."<init>":(Lorg/apache/dubbo/remoting/exchange/support/header/AbstractTimerTask$ChannelProvider;Lorg/apache/dubbo/common/timer/HashedWheelTimer;Ljava/lang/Long;)V
       7: aload_0
       8: iload         4
      10: putfield      #3                  // Field idleTimeout:I
      13: return

  protected void doTask(org.apache.dubbo.remoting.Channel);
    Code:
       0: aload_1
       1: invokestatic  #4                  // Method lastRead:(Lorg/apache/dubbo/remoting/Channel;)Ljava/lang/Long;
       4: astore_2
       5: invokestatic  #5                  // Method now:()Ljava/lang/Long;
       8: astore_3
       9: aload_1
      10: invokeinterface #6,  1            // InterfaceMethod org/apache/dubbo/remoting/Channel.isConnected:()Z
      15: ifne          97
      18: getstatic     #7                  // Field logger:Lorg/apache/dubbo/common/logger/ErrorTypeAwareLogger;
      21: new           #8                  // class java/lang/StringBuilder
      24: dup
      25: invokespecial #9                  // Method java/lang/StringBuilder."<init>":()V
      28: ldc           #10                 // String Initial connection to
      30: invokevirtual #11                 // Method java/lang/StringBuilder.append:(Ljava/lang/String;)Ljava/lang/StringBuilder;
      33: aload_1
      34: invokevirtual #12                 // Method java/lang/StringBuilder.append:(Ljava/lang/Object;)Ljava/lang/StringBuilder;
      37: invokevirtual #13                 // Method java/lang/StringBuilder.toString:()Ljava/lang/String;
      40: invokeinterface #14,  2           // InterfaceMethod org/apache/dubbo/common/logger/ErrorTypeAwareLogger.info:(Ljava/lang/String;)V
      45: aload_1
      46: checkcast     #15                 // class org/apache/dubbo/remoting/Client
      49: invokeinterface #16,  1           // InterfaceMethod org/apache/dubbo/remoting/Client.reconnect:()V
      54: goto          218
      57: astore        4
      59: getstatic     #7                  // Field logger:Lorg/apache/dubbo/common/logger/ErrorTypeAwareLogger;
      62: ldc           #18                 // String 6-16
      64: ldc           #19                 // String
      66: ldc           #19                 // String
      68: new           #8                  // class java/lang/StringBuilder
      71: dup
      72: invokespecial #9                  // Method java/lang/StringBuilder."<init>":()V
      75: ldc           #20                 // String Fail to connect to
      77: invokevirtual #11                 // Method java/lang/StringBuilder.append:(Ljava/lang/String;)Ljava/lang/StringBuilder;
      80: aload_1
      81: invokevirtual #12                 // Method java/lang/StringBuilder.append:(Ljava/lang/Object;)Ljava/lang/StringBuilder;
      84: invokevirtual #13                 // Method java/lang/StringBuilder.toString:()Ljava/lang/String;
      87: aload         4
      89: invokeinterface #21,  6           // InterfaceMethod org/apache/dubbo/common/logger/ErrorTypeAwareLogger.error:(Ljava/lang/String;Ljava/lang/String;Ljava/lang/String;Ljava/lang/String;Ljava/lang/Throwable;)V
      94: goto          218
      97: aload_2
      98: ifnull        218
     101: aload_3
     102: invokevirtual #22                 // Method java/lang/Long.longValue:()J
     105: aload_2
     106: invokevirtual #22                 // Method java/lang/Long.longValue:()J
     109: lsub
     110: aload_0
     111: getfield      #3                  // Field idleTimeout:I
     114: i2l
     115: lcmp
     116: ifle          218
     119: getstatic     #7                  // Field logger:Lorg/apache/dubbo/common/logger/ErrorTypeAwareLogger;
     122: ldc           #18                 // String 6-16
     124: ldc           #19                 // String
     126: ldc           #19                 // String
     128: new           #8                  // class java/lang/StringBuilder
     131: dup
     132: invokespecial #9                  // Method java/lang/StringBuilder."<init>":()V
     135: ldc           #23                 // String Reconnect to channel
     137: invokevirtual #11                 // Method java/lang/StringBuilder.append:(Ljava/lang/String;)Ljava/lang/StringBuilder;
     140: aload_1
     141: invokevirtual #12                 // Method java/lang/StringBuilder.append:(Ljava/lang/Object;)Ljava/lang/StringBuilder;
     144: ldc           #24                 // String , because heartbeat read idle time out:
     146: invokevirtual #11                 // Method java/lang/StringBuilder.append:(Ljava/lang/String;)Ljava/lang/StringBuilder;
     149: aload_0
     150: getfield      #3                  // Field idleTimeout:I
     153: invokevirtual #25                 // Method java/lang/StringBuilder.append:(I)Ljava/lang/StringBuilder;
     156: ldc           #26                 // String ms
     158: invokevirtual #11                 // Method java/lang/StringBuilder.append:(Ljava/lang/String;)Ljava/lang/StringBuilder;
     161: invokevirtual #13                 // Method java/lang/StringBuilder.toString:()Ljava/lang/String;
     164: invokeinterface #27,  5           // InterfaceMethod org/apache/dubbo/common/logger/ErrorTypeAwareLogger.warn:(Ljava/lang/String;Ljava/lang/String;Ljava/lang/String;Ljava/lang/String;)V
     169: aload_1
     170: checkcast     #15                 // class org/apache/dubbo/remoting/Client
     173: invokeinterface #16,  1           // InterfaceMethod org/apache/dubbo/remoting/Client.reconnect:()V
     178: goto          218
     181: astore        4
     183: getstatic     #7                  // Field logger:Lorg/apache/dubbo/common/logger/ErrorTypeAwareLogger;
     186: ldc           #18                 // String 6-16
     188: ldc           #19                 // String
     190: ldc           #19                 // String
     192: new           #8                  // class java/lang/StringBuilder
     195: dup
     196: invokespecial #9                  // Method java/lang/StringBuilder."<init>":()V
     199: aload_1
     200: invokevirtual #12                 // Method java/lang/StringBuilder.append:(Ljava/lang/Object;)Ljava/lang/StringBuilder;
     203: ldc           #28                 // String reconnect failed during idle time.
     205: invokevirtual #11                 // Method java/lang/StringBuilder.append:(Ljava/lang/String;)Ljava/lang/StringBuilder;
     208: invokevirtual #13                 // Method java/lang/StringBuilder.toString:()Ljava/lang/String;
     211: aload         4
     213: invokeinterface #21,  6           // InterfaceMethod org/apache/dubbo/common/logger/ErrorTypeAwareLogger.error:(Ljava/lang/String;Ljava/lang/String;Ljava/lang/String;Ljava/lang/String;Ljava/lang/Throwable;)V
     218: goto          261
     221: astore_2
     222: getstatic     #7                  // Field logger:Lorg/apache/dubbo/common/logger/ErrorTypeAwareLogger;
     225: ldc           #30                 // String 99-0
     227: ldc           #31                 // String unknown error in remoting module
     229: ldc           #19                 // String
     231: new           #8                  // class java/lang/StringBuilder
     234: dup
     235: invokespecial #9                  // Method java/lang/StringBuilder."<init>":()V
     238: ldc           #32                 // String Exception when reconnect to remote channel
     240: invokevirtual #11                 // Method java/lang/StringBuilder.append:(Ljava/lang/String;)Ljava/lang/StringBuilder;
     243: aload_1
     244: invokeinterface #33,  1           // InterfaceMethod org/apache/dubbo/remoting/Channel.getRemoteAddress:()Ljava/net/InetSocketAddress;
     249: invokevirtual #12                 // Method java/lang/StringBuilder.append:(Ljava/lang/Object;)Ljava/lang/StringBuilder;
     252: invokevirtual #13                 // Method java/lang/StringBuilder.toString:()Ljava/lang/String;
     255: aload_2
     256: invokeinterface #34,  6           // InterfaceMethod org/apache/dubbo/common/logger/ErrorTypeAwareLogger.warn:(Ljava/lang/String;Ljava/lang/String;Ljava/lang/String;Ljava/lang/String;Ljava/lang/Throwable;)V
     261: return
    Exception table:
       from    to  target type
          18    54    57   Class java/lang/Exception
         169   178   181   Class java/lang/Exception
           0   218   221   Class java/lang/Throwable

  static {};
    Code:
       0: ldc           #35                 // class org/apache/dubbo/remoting/exchange/support/header/ReconnectTimerTask
       2: invokestatic  #36                 // Method org/apache/dubbo/common/logger/LoggerFactory.getErrorTypeAwareLogger:(Ljava/lang/Class;)Lorg/apache/dubbo/common/logger/ErrorTypeAwareLogger;
       5: putstatic     #7                  // Field logger:Lorg/apache/dubbo/common/logger/ErrorTypeAwareLogger;
       8: return
}
