Compiled from "RemotingException.java"
public class com.alibaba.dubbo.remoting.RemotingException extends org.apache.dubbo.remoting.RemotingException {
  public com.alibaba.dubbo.remoting.RemotingException(org.apache.dubbo.remoting.Channel, java.lang.String);
    Code:
       0: aload_0
       1: aload_1
       2: aload_2
       3: invokespecial #1                  // Method org/apache/dubbo/remoting/RemotingException."<init>":(Lorg/apache/dubbo/remoting/Channel;Ljava/lang/String;)V
       6: return

  public com.alibaba.dubbo.remoting.RemotingException(java.net.InetSocketAddress, java.net.InetSocketAddress, java.lang.String);
    Code:
       0: aload_0
       1: aload_1
       2: aload_2
       3: aload_3
       4: invokespecial #2                  // Method org/apache/dubbo/remoting/RemotingException."<init>":(Ljava/net/InetSocketAddress;Ljava/net/InetSocketAddress;Ljava/lang/String;)V
       7: return

  public com.alibaba.dubbo.remoting.RemotingException(org.apache.dubbo.remoting.Channel, java.lang.Throwable);
    Code:
       0: aload_0
       1: aload_1
       2: aload_2
       3: invokespecial #3                  // Method org/apache/dubbo/remoting/RemotingException."<init>":(Lorg/apache/dubbo/remoting/Channel;Ljava/lang/Throwable;)V
       6: return

  public com.alibaba.dubbo.remoting.RemotingException(java.net.InetSocketAddress, java.net.InetSocketAddress, java.lang.Throwable);
    Code:
       0: aload_0
       1: aload_1
       2: aload_2
       3: aload_3
       4: invokespecial #4                  // Method org/apache/dubbo/remoting/RemotingException."<init>":(Ljava/net/InetSocketAddress;Ljava/net/InetSocketAddress;Ljava/lang/Throwable;)V
       7: return

  public com.alibaba.dubbo.remoting.RemotingException(org.apache.dubbo.remoting.Channel, java.lang.String, java.lang.Throwable);
    Code:
       0: aload_0
       1: aload_1
       2: aload_2
       3: aload_3
       4: invokespecial #5                  // Method org/apache/dubbo/remoting/RemotingException."<init>":(Lorg/apache/dubbo/remoting/Channel;Ljava/lang/String;Ljava/lang/Throwable;)V
       7: return

  public com.alibaba.dubbo.remoting.RemotingException(java.net.InetSocketAddress, java.net.InetSocketAddress, java.lang.String, java.lang.Throwable);
    Code:
       0: aload_0
       1: aload_1
       2: aload_2
       3: aload_3
       4: aload         4
       6: invokespecial #6                  // Method org/apache/dubbo/remoting/RemotingException."<init>":(Ljava/net/InetSocketAddress;Ljava/net/InetSocketAddress;Ljava/lang/String;Ljava/lang/Throwable;)V
       9: return

  public com.alibaba.dubbo.remoting.RemotingException(java.lang.Exception);
    Code:
       0: aload_0
       1: aconst_null
       2: aload_1
       3: invokevirtual #7                  // Method java/lang/Exception.getMessage:()Ljava/lang/String;
       6: invokespecial #1                  // Method org/apache/dubbo/remoting/RemotingException."<init>":(Lorg/apache/dubbo/remoting/Channel;Ljava/lang/String;)V
       9: return
}
