Compiled from "Transporter.java"
class com.alibaba.dubbo.remoting.Transporter$1 implements com.alibaba.dubbo.remoting.ChannelHandler {
  final org.apache.dubbo.remoting.ChannelHandler val$handler;

  final com.alibaba.dubbo.remoting.Transporter this$0;

  com.alibaba.dubbo.remoting.Transporter$1(com.alibaba.dubbo.remoting.Transporter, org.apache.dubbo.remoting.ChannelHandler);
    Code:
       0: aload_0
       1: aload_1
       2: putfield      #1                  // Field this$0:Lcom/alibaba/dubbo/remoting/Transporter;
       5: aload_0
       6: aload_2
       7: putfield      #2                  // Field val$handler:Lorg/apache/dubbo/remoting/ChannelHandler;
      10: aload_0
      11: invokespecial #3                  // Method java/lang/Object."<init>":()V
      14: return

  public void connected(com.alibaba.dubbo.remoting.Channel) throws com.alibaba.dubbo.remoting.RemotingException;
    Code:
       0: aload_0
       1: getfield      #2                  // Field val$handler:Lorg/apache/dubbo/remoting/ChannelHandler;
       4: aload_1
       5: invokeinterface #4,  2            // InterfaceMethod org/apache/dubbo/remoting/ChannelHandler.connected:(Lorg/apache/dubbo/remoting/Channel;)V
      10: goto          23
      13: astore_2
      14: new           #6                  // class com/alibaba/dubbo/remoting/RemotingException
      17: dup
      18: aload_2
      19: invokespecial #7                  // Method com/alibaba/dubbo/remoting/RemotingException."<init>":(Ljava/lang/Exception;)V
      22: athrow
      23: return
    Exception table:
       from    to  target type
           0    10    13   Class org/apache/dubbo/remoting/RemotingException

  public void disconnected(com.alibaba.dubbo.remoting.Channel) throws com.alibaba.dubbo.remoting.RemotingException;
    Code:
       0: aload_0
       1: getfield      #2                  // Field val$handler:Lorg/apache/dubbo/remoting/ChannelHandler;
       4: aload_1
       5: invokeinterface #8,  2            // InterfaceMethod org/apache/dubbo/remoting/ChannelHandler.disconnected:(Lorg/apache/dubbo/remoting/Channel;)V
      10: goto          23
      13: astore_2
      14: new           #6                  // class com/alibaba/dubbo/remoting/RemotingException
      17: dup
      18: aload_2
      19: invokespecial #7                  // Method com/alibaba/dubbo/remoting/RemotingException."<init>":(Ljava/lang/Exception;)V
      22: athrow
      23: return
    Exception table:
       from    to  target type
           0    10    13   Class org/apache/dubbo/remoting/RemotingException

  public void sent(com.alibaba.dubbo.remoting.Channel, java.lang.Object) throws com.alibaba.dubbo.remoting.RemotingException;
    Code:
       0: aload_0
       1: getfield      #2                  // Field val$handler:Lorg/apache/dubbo/remoting/ChannelHandler;
       4: aload_1
       5: aload_2
       6: invokeinterface #9,  3            // InterfaceMethod org/apache/dubbo/remoting/ChannelHandler.sent:(Lorg/apache/dubbo/remoting/Channel;Ljava/lang/Object;)V
      11: goto          24
      14: astore_3
      15: new           #6                  // class com/alibaba/dubbo/remoting/RemotingException
      18: dup
      19: aload_3
      20: invokespecial #7                  // Method com/alibaba/dubbo/remoting/RemotingException."<init>":(Ljava/lang/Exception;)V
      23: athrow
      24: return
    Exception table:
       from    to  target type
           0    11    14   Class org/apache/dubbo/remoting/RemotingException

  public void received(com.alibaba.dubbo.remoting.Channel, java.lang.Object) throws com.alibaba.dubbo.remoting.RemotingException;
    Code:
       0: aload_0
       1: getfield      #2                  // Field val$handler:Lorg/apache/dubbo/remoting/ChannelHandler;
       4: aload_1
       5: aload_2
       6: invokeinterface #10,  3           // InterfaceMethod org/apache/dubbo/remoting/ChannelHandler.received:(Lorg/apache/dubbo/remoting/Channel;Ljava/lang/Object;)V
      11: goto          24
      14: astore_3
      15: new           #6                  // class com/alibaba/dubbo/remoting/RemotingException
      18: dup
      19: aload_3
      20: invokespecial #7                  // Method com/alibaba/dubbo/remoting/RemotingException."<init>":(Ljava/lang/Exception;)V
      23: athrow
      24: return
    Exception table:
       from    to  target type
           0    11    14   Class org/apache/dubbo/remoting/RemotingException

  public void caught(com.alibaba.dubbo.remoting.Channel, java.lang.Throwable) throws com.alibaba.dubbo.remoting.RemotingException;
    Code:
       0: aload_0
       1: getfield      #2                  // Field val$handler:Lorg/apache/dubbo/remoting/ChannelHandler;
       4: aload_1
       5: aload_2
       6: invokeinterface #11,  3           // InterfaceMethod org/apache/dubbo/remoting/ChannelHandler.caught:(Lorg/apache/dubbo/remoting/Channel;Ljava/lang/Throwable;)V
      11: goto          24
      14: astore_3
      15: new           #6                  // class com/alibaba/dubbo/remoting/RemotingException
      18: dup
      19: aload_3
      20: invokespecial #7                  // Method com/alibaba/dubbo/remoting/RemotingException."<init>":(Ljava/lang/Exception;)V
      23: athrow
      24: return
    Exception table:
       from    to  target type
           0    11    14   Class org/apache/dubbo/remoting/RemotingException
}
