Compiled from "Transporter.java"
public interface com.alibaba.dubbo.remoting.Transporter extends org.apache.dubbo.remoting.Transporter {
  public abstract com.alibaba.dubbo.remoting.Server bind(com.alibaba.dubbo.common.URL, com.alibaba.dubbo.remoting.ChannelHandler) throws com.alibaba.dubbo.remoting.RemotingException;

  public default org.apache.dubbo.remoting.RemotingServer bind(org.apache.dubbo.common.URL, org.apache.dubbo.remoting.ChannelHandler) throws org.apache.dubbo.remoting.RemotingException;
    Code:
       0: aload_0
       1: new           #1                  // class com/alibaba/dubbo/common/URL
       4: dup
       5: aload_1
       6: invokespecial #2                  // Method com/alibaba/dubbo/common/URL."<init>":(Lorg/apache/dubbo/common/URL;)V
       9: new           #3                  // class com/alibaba/dubbo/remoting/Transporter$1
      12: dup
      13: aload_0
      14: aload_2
      15: invokespecial #4                  // Method com/alibaba/dubbo/remoting/Transporter$1."<init>":(Lcom/alibaba/dubbo/remoting/Transporter;Lorg/apache/dubbo/remoting/ChannelHandler;)V
      18: invokeinterface #5,  3            // InterfaceMethod bind:(Lcom/alibaba/dubbo/common/URL;Lcom/alibaba/dubbo/remoting/ChannelHandler;)Lcom/alibaba/dubbo/remoting/Server;
      23: areturn
}
