Compiled from "TelnetHandlerAdapter.java"
public class org.apache.dubbo.remoting.telnet.support.TelnetHandlerAdapter extends org.apache.dubbo.remoting.transport.ChannelHandlerAdapter implements org.apache.dubbo.remoting.telnet.TelnetHandler {
  private final org.apache.dubbo.common.extension.ExtensionLoader<org.apache.dubbo.remoting.telnet.TelnetHandler> extensionLoader;

  public org.apache.dubbo.remoting.telnet.support.TelnetHandlerAdapter(org.apache.dubbo.rpc.model.FrameworkModel);
    Code:
       0: aload_0
       1: invokespecial #2                  // Method org/apache/dubbo/remoting/transport/ChannelHandlerAdapter."<init>":()V
       4: aload_0
       5: aload_1
       6: ldc           #3                  // class org/apache/dubbo/remoting/telnet/TelnetHandler
       8: invokevirtual #4                  // Method org/apache/dubbo/rpc/model/FrameworkModel.getExtensionLoader:(Ljava/lang/Class;)Lorg/apache/dubbo/common/extension/ExtensionLoader;
      11: putfield      #5                  // Field extensionLoader:Lorg/apache/dubbo/common/extension/ExtensionLoader;
      14: return

  public java.lang.String telnet(org.apache.dubbo.remoting.Channel, java.lang.String) throws org.apache.dubbo.remoting.RemotingException;
    Code:
       0: aload_1
       1: invokeinterface #6,  1            // InterfaceMethod org/apache/dubbo/remoting/Channel.getUrl:()Lorg/apache/dubbo/common/URL;
       6: ldc           #7                  // String prompt
       8: ldc           #8                  // String dubbo>
      10: invokevirtual #9                  // Method org/apache/dubbo/common/URL.getParameterAndDecoded:(Ljava/lang/String;Ljava/lang/String;)Ljava/lang/String;
      13: astore_3
      14: aload_2
      15: ldc           #10                 // String --no-prompt
      17: invokevirtual #11                 // Method java/lang/String.contains:(Ljava/lang/CharSequence;)Z
      20: istore        4
      22: aload_2
      23: ldc           #10                 // String --no-prompt
      25: ldc           #12                 // String
      27: invokevirtual #13                 // Method java/lang/String.replace:(Ljava/lang/CharSequence;Ljava/lang/CharSequence;)Ljava/lang/String;
      30: astore_2
      31: new           #14                 // class java/lang/StringBuilder
      34: dup
      35: invokespecial #15                 // Method java/lang/StringBuilder."<init>":()V
      38: astore        5
      40: aload_2
      41: invokevirtual #16                 // Method java/lang/String.trim:()Ljava/lang/String;
      44: astore_2
      45: aload_2
      46: invokevirtual #17                 // Method java/lang/String.length:()I
      49: ifle          101
      52: aload_2
      53: bipush        32
      55: invokevirtual #18                 // Method java/lang/String.indexOf:(I)I
      58: istore        7
      60: iload         7
      62: ifle          92
      65: aload_2
      66: iconst_0
      67: iload         7
      69: invokevirtual #19                 // Method java/lang/String.substring:(II)Ljava/lang/String;
      72: invokevirtual #16                 // Method java/lang/String.trim:()Ljava/lang/String;
      75: astore        6
      77: aload_2
      78: iload         7
      80: iconst_1
      81: iadd
      82: invokevirtual #20                 // Method java/lang/String.substring:(I)Ljava/lang/String;
      85: invokevirtual #16                 // Method java/lang/String.trim:()Ljava/lang/String;
      88: astore_2
      89: goto          98
      92: aload_2
      93: astore        6
      95: ldc           #12                 // String
      97: astore_2
      98: goto          105
     101: ldc           #12                 // String
     103: astore        6
     105: aload         6
     107: invokevirtual #17                 // Method java/lang/String.length:()I
     110: ifle          238
     113: aload_0
     114: getfield      #5                  // Field extensionLoader:Lorg/apache/dubbo/common/extension/ExtensionLoader;
     117: aload         6
     119: invokevirtual #21                 // Method org/apache/dubbo/common/extension/ExtensionLoader.hasExtension:(Ljava/lang/String;)Z
     122: ifeq          222
     125: aload_0
     126: aload_1
     127: invokeinterface #6,  1            // InterfaceMethod org/apache/dubbo/remoting/Channel.getUrl:()Lorg/apache/dubbo/common/URL;
     132: aload         6
     134: invokespecial #22                 // Method commandEnabled:(Lorg/apache/dubbo/common/URL;Ljava/lang/String;)Z
     137: ifeq          195
     140: aload_0
     141: getfield      #5                  // Field extensionLoader:Lorg/apache/dubbo/common/extension/ExtensionLoader;
     144: aload         6
     146: invokevirtual #23                 // Method org/apache/dubbo/common/extension/ExtensionLoader.getExtension:(Ljava/lang/String;)Ljava/lang/Object;
     149: checkcast     #3                  // class org/apache/dubbo/remoting/telnet/TelnetHandler
     152: aload_1
     153: aload_2
     154: invokeinterface #24,  3           // InterfaceMethod org/apache/dubbo/remoting/telnet/TelnetHandler.telnet:(Lorg/apache/dubbo/remoting/Channel;Ljava/lang/String;)Ljava/lang/String;
     159: astore        7
     161: aload         7
     163: ifnonnull     168
     166: aconst_null
     167: areturn
     168: aload         5
     170: aload         7
     172: invokevirtual #25                 // Method java/lang/StringBuilder.append:(Ljava/lang/String;)Ljava/lang/StringBuilder;
     175: pop
     176: goto          238
     179: astore        7
     181: aload         5
     183: aload         7
     185: invokevirtual #27                 // Method java/lang/Throwable.getMessage:()Ljava/lang/String;
     188: invokevirtual #25                 // Method java/lang/StringBuilder.append:(Ljava/lang/String;)Ljava/lang/StringBuilder;
     191: pop
     192: goto          238
     195: aload         5
     197: ldc           #28                 // String Command:
     199: invokevirtual #25                 // Method java/lang/StringBuilder.append:(Ljava/lang/String;)Ljava/lang/StringBuilder;
     202: pop
     203: aload         5
     205: aload         6
     207: invokevirtual #25                 // Method java/lang/StringBuilder.append:(Ljava/lang/String;)Ljava/lang/StringBuilder;
     210: pop
     211: aload         5
     213: ldc           #29                 // String  disabled for security reasons, please enable support by listing the commands through \'telnet\'
     215: invokevirtual #25                 // Method java/lang/StringBuilder.append:(Ljava/lang/String;)Ljava/lang/StringBuilder;
     218: pop
     219: goto          238
     222: aload         5
     224: ldc           #30                 // String Unsupported command:
     226: invokevirtual #25                 // Method java/lang/StringBuilder.append:(Ljava/lang/String;)Ljava/lang/StringBuilder;
     229: pop
     230: aload         5
     232: aload         6
     234: invokevirtual #25                 // Method java/lang/StringBuilder.append:(Ljava/lang/String;)Ljava/lang/StringBuilder;
     237: pop
     238: aload         5
     240: invokevirtual #31                 // Method java/lang/StringBuilder.length:()I
     243: ifle          254
     246: aload         5
     248: ldc           #32                 // String \r\n
     250: invokevirtual #25                 // Method java/lang/StringBuilder.append:(Ljava/lang/String;)Ljava/lang/StringBuilder;
     253: pop
     254: aload_3
     255: invokestatic  #33                 // Method org/apache/dubbo/common/utils/StringUtils.isNotEmpty:(Ljava/lang/String;)Z
     258: ifeq          273
     261: iload         4
     263: ifne          273
     266: aload         5
     268: aload_3
     269: invokevirtual #25                 // Method java/lang/StringBuilder.append:(Ljava/lang/String;)Ljava/lang/StringBuilder;
     272: pop
     273: aload         5
     275: invokevirtual #34                 // Method java/lang/StringBuilder.toString:()Ljava/lang/String;
     278: areturn
    Exception table:
       from    to  target type
         140   167   179   Class java/lang/Throwable
         168   176   179   Class java/lang/Throwable

  private boolean commandEnabled(org.apache.dubbo.common.URL, java.lang.String);
    Code:
       0: aload_1
       1: ldc           #35                 // String telnet
       3: invokevirtual #36                 // Method org/apache/dubbo/common/URL.getParameter:(Ljava/lang/String;)Ljava/lang/String;
       6: astore_3
       7: aload_3
       8: invokestatic  #37                 // Method org/apache/dubbo/common/utils/StringUtils.isEmpty:(Ljava/lang/String;)Z
      11: ifeq          16
      14: iconst_0
      15: ireturn
      16: getstatic     #38                 // Field org/apache/dubbo/common/constants/CommonConstants.COMMA_SPLIT_PATTERN:Ljava/util/regex/Pattern;
      19: aload_3
      20: invokevirtual #39                 // Method java/util/regex/Pattern.split:(Ljava/lang/CharSequence;)[Ljava/lang/String;
      23: astore        4
      25: aload         4
      27: astore        5
      29: aload         5
      31: arraylength
      32: istore        6
      34: iconst_0
      35: istore        7
      37: iload         7
      39: iload         6
      41: if_icmpge     68
      44: aload         5
      46: iload         7
      48: aaload
      49: astore        8
      51: aload_2
      52: aload         8
      54: invokevirtual #40                 // Method java/lang/String.equals:(Ljava/lang/Object;)Z
      57: ifeq          62
      60: iconst_1
      61: ireturn
      62: iinc          7, 1
      65: goto          37
      68: iconst_0
      69: ireturn
}
