Compiled from "CompletableFromSingle.java"
public final class io.reactivex.rxjava3.internal.operators.completable.CompletableFromSingle<T> extends io.reactivex.rxjava3.core.Completable {
  final io.reactivex.rxjava3.core.SingleSource<T> single;

  public io.reactivex.rxjava3.internal.operators.completable.CompletableFromSingle(io.reactivex.rxjava3.core.SingleSource<T>);
    Code:
       0: aload_0
       1: invokespecial #1                  // Method io/reactivex/rxjava3/core/Completable."<init>":()V
       4: aload_0
       5: aload_1
       6: putfield      #2                  // Field single:Lio/reactivex/rxjava3/core/SingleSource;
       9: return

  protected void subscribeActual(io.reactivex.rxjava3.core.CompletableObserver);
    Code:
       0: aload_0
       1: getfield      #2                  // Field single:Lio/reactivex/rxjava3/core/SingleSource;
       4: new           #3                  // class io/reactivex/rxjava3/internal/operators/completable/CompletableFromSingle$CompletableFromSingleObserver
       7: dup
       8: aload_1
       9: invokespecial #4                  // Method io/reactivex/rxjava3/internal/operators/completable/CompletableFromSingle$CompletableFromSingleObserver."<init>":(Lio/reactivex/rxjava3/core/CompletableObserver;)V
      12: invokeinterface #5,  2            // InterfaceMethod io/reactivex/rxjava3/core/SingleSource.subscribe:(Lio/reactivex/rxjava3/core/SingleObserver;)V
      17: return
}
