Compiled from "CompletableDoFinally.java"
final class io.reactivex.rxjava3.internal.operators.completable.CompletableDoFinally$DoFinallyObserver extends java.util.concurrent.atomic.AtomicInteger implements io.reactivex.rxjava3.core.CompletableObserver,io.reactivex.rxjava3.disposables.Disposable {
  private static final long serialVersionUID;

  final io.reactivex.rxjava3.core.CompletableObserver downstream;

  final io.reactivex.rxjava3.functions.Action onFinally;

  io.reactivex.rxjava3.disposables.Disposable upstream;

  io.reactivex.rxjava3.internal.operators.completable.CompletableDoFinally$DoFinallyObserver(io.reactivex.rxjava3.core.CompletableObserver, io.reactivex.rxjava3.functions.Action);
    Code:
       0: aload_0
       1: invokespecial #1                  // Method java/util/concurrent/atomic/AtomicInteger."<init>":()V
       4: aload_0
       5: aload_1
       6: putfield      #2                  // Field downstream:Lio/reactivex/rxjava3/core/CompletableObserver;
       9: aload_0
      10: aload_2
      11: putfield      #3                  // Field onFinally:Lio/reactivex/rxjava3/functions/Action;
      14: return

  public void onSubscribe(io.reactivex.rxjava3.disposables.Disposable);
    Code:
       0: aload_0
       1: getfield      #4                  // Field upstream:Lio/reactivex/rxjava3/disposables/Disposable;
       4: aload_1
       5: invokestatic  #5                  // Method io/reactivex/rxjava3/internal/disposables/DisposableHelper.validate:(Lio/reactivex/rxjava3/disposables/Disposable;Lio/reactivex/rxjava3/disposables/Disposable;)Z
       8: ifeq          26
      11: aload_0
      12: aload_1
      13: putfield      #4                  // Field upstream:Lio/reactivex/rxjava3/disposables/Disposable;
      16: aload_0
      17: getfield      #2                  // Field downstream:Lio/reactivex/rxjava3/core/CompletableObserver;
      20: aload_0
      21: invokeinterface #6,  2            // InterfaceMethod io/reactivex/rxjava3/core/CompletableObserver.onSubscribe:(Lio/reactivex/rxjava3/disposables/Disposable;)V
      26: return

  public void onError(java.lang.Throwable);
    Code:
       0: aload_0
       1: getfield      #2                  // Field downstream:Lio/reactivex/rxjava3/core/CompletableObserver;
       4: aload_1
       5: invokeinterface #7,  2            // InterfaceMethod io/reactivex/rxjava3/core/CompletableObserver.onError:(Ljava/lang/Throwable;)V
      10: aload_0
      11: invokevirtual #8                  // Method runFinally:()V
      14: return

  public void onComplete();
    Code:
       0: aload_0
       1: getfield      #2                  // Field downstream:Lio/reactivex/rxjava3/core/CompletableObserver;
       4: invokeinterface #9,  1            // InterfaceMethod io/reactivex/rxjava3/core/CompletableObserver.onComplete:()V
       9: aload_0
      10: invokevirtual #8                  // Method runFinally:()V
      13: return

  public void dispose();
    Code:
       0: aload_0
       1: getfield      #4                  // Field upstream:Lio/reactivex/rxjava3/disposables/Disposable;
       4: invokeinterface #10,  1           // InterfaceMethod io/reactivex/rxjava3/disposables/Disposable.dispose:()V
       9: aload_0
      10: invokevirtual #8                  // Method runFinally:()V
      13: return

  public boolean isDisposed();
    Code:
       0: aload_0
       1: getfield      #4                  // Field upstream:Lio/reactivex/rxjava3/disposables/Disposable;
       4: invokeinterface #11,  1           // InterfaceMethod io/reactivex/rxjava3/disposables/Disposable.isDisposed:()Z
       9: ireturn

  void runFinally();
    Code:
       0: aload_0
       1: iconst_0
       2: iconst_1
       3: invokevirtual #12                 // Method compareAndSet:(II)Z
       6: ifeq          30
       9: aload_0
      10: getfield      #3                  // Field onFinally:Lio/reactivex/rxjava3/functions/Action;
      13: invokeinterface #13,  1           // InterfaceMethod io/reactivex/rxjava3/functions/Action.run:()V
      18: goto          30
      21: astore_1
      22: aload_1
      23: invokestatic  #15                 // Method io/reactivex/rxjava3/exceptions/Exceptions.throwIfFatal:(Ljava/lang/Throwable;)V
      26: aload_1
      27: invokestatic  #16                 // Method io/reactivex/rxjava3/plugins/RxJavaPlugins.onError:(Ljava/lang/Throwable;)V
      30: return
    Exception table:
       from    to  target type
           9    18    21   Class java/lang/Throwable
}
