Compiled from "CompletableFromObservable.java"
final class io.reactivex.rxjava3.internal.operators.completable.CompletableFromObservable$CompletableFromObservableObserver<T> implements io.reactivex.rxjava3.core.Observer<T> {
  final io.reactivex.rxjava3.core.CompletableObserver co;

  io.reactivex.rxjava3.internal.operators.completable.CompletableFromObservable$CompletableFromObservableObserver(io.reactivex.rxjava3.core.CompletableObserver);
    Code:
       0: aload_0
       1: invokespecial #1                  // Method java/lang/Object."<init>":()V
       4: aload_0
       5: aload_1
       6: putfield      #2                  // Field co:Lio/reactivex/rxjava3/core/CompletableObserver;
       9: return

  public void onSubscribe(io.reactivex.rxjava3.disposables.Disposable);
    Code:
       0: aload_0
       1: getfield      #2                  // Field co:Lio/reactivex/rxjava3/core/CompletableObserver;
       4: aload_1
       5: invokeinterface #3,  2            // InterfaceMethod io/reactivex/rxjava3/core/CompletableObserver.onSubscribe:(Lio/reactivex/rxjava3/disposables/Disposable;)V
      10: return

  public void onNext(T);
    Code:
       0: return

  public void onError(java.lang.Throwable);
    Code:
       0: aload_0
       1: getfield      #2                  // Field co:Lio/reactivex/rxjava3/core/CompletableObserver;
       4: aload_1
       5: invokeinterface #4,  2            // InterfaceMethod io/reactivex/rxjava3/core/CompletableObserver.onError:(Ljava/lang/Throwable;)V
      10: return

  public void onComplete();
    Code:
       0: aload_0
       1: getfield      #2                  // Field co:Lio/reactivex/rxjava3/core/CompletableObserver;
       4: invokeinterface #5,  1            // InterfaceMethod io/reactivex/rxjava3/core/CompletableObserver.onComplete:()V
       9: return
}
