Compiled from "CompletableMerge.java"
public final class io.reactivex.rxjava3.internal.operators.completable.CompletableMerge extends io.reactivex.rxjava3.core.Completable {
  final org.reactivestreams.Publisher<? extends io.reactivex.rxjava3.core.CompletableSource> source;

  final int maxConcurrency;

  final boolean delayErrors;

  public io.reactivex.rxjava3.internal.operators.completable.CompletableMerge(org.reactivestreams.Publisher<? extends io.reactivex.rxjava3.core.CompletableSource>, int, boolean);
    Code:
       0: aload_0
       1: invokespecial #1                  // Method io/reactivex/rxjava3/core/Completable."<init>":()V
       4: aload_0
       5: aload_1
       6: putfield      #2                  // Field source:Lorg/reactivestreams/Publisher;
       9: aload_0
      10: iload_2
      11: putfield      #3                  // Field maxConcurrency:I
      14: aload_0
      15: iload_3
      16: putfield      #4                  // Field delayErrors:Z
      19: return

  public void subscribeActual(io.reactivex.rxjava3.core.CompletableObserver);
    Code:
       0: new           #5                  // class io/reactivex/rxjava3/internal/operators/completable/CompletableMerge$CompletableMergeSubscriber
       3: dup
       4: aload_1
       5: aload_0
       6: getfield      #3                  // Field maxConcurrency:I
       9: aload_0
      10: getfield      #4                  // Field delayErrors:Z
      13: invokespecial #6                  // Method io/reactivex/rxjava3/internal/operators/completable/CompletableMerge$CompletableMergeSubscriber."<init>":(Lio/reactivex/rxjava3/core/CompletableObserver;IZ)V
      16: astore_2
      17: aload_0
      18: getfield      #2                  // Field source:Lorg/reactivestreams/Publisher;
      21: aload_2
      22: invokeinterface #7,  2            // InterfaceMethod org/reactivestreams/Publisher.subscribe:(Lorg/reactivestreams/Subscriber;)V
      27: return
}
