Compiled from "CompletablePeek.java"
final class io.reactivex.rxjava3.internal.operators.completable.CompletablePeek$CompletableObserverImplementation implements io.reactivex.rxjava3.core.CompletableObserver,io.reactivex.rxjava3.disposables.Disposable {
  final io.reactivex.rxjava3.core.CompletableObserver downstream;

  io.reactivex.rxjava3.disposables.Disposable upstream;

  final io.reactivex.rxjava3.internal.operators.completable.CompletablePeek this$0;

  io.reactivex.rxjava3.internal.operators.completable.CompletablePeek$CompletableObserverImplementation(io.reactivex.rxjava3.internal.operators.completable.CompletablePeek, io.reactivex.rxjava3.core.CompletableObserver);
    Code:
       0: aload_0
       1: aload_1
       2: putfield      #1                  // Field this$0:Lio/reactivex/rxjava3/internal/operators/completable/CompletablePeek;
       5: aload_0
       6: invokespecial #2                  // Method java/lang/Object."<init>":()V
       9: aload_0
      10: aload_2
      11: putfield      #3                  // Field downstream:Lio/reactivex/rxjava3/core/CompletableObserver;
      14: return

  public void onSubscribe(io.reactivex.rxjava3.disposables.Disposable);
    Code:
       0: aload_0
       1: getfield      #1                  // Field this$0:Lio/reactivex/rxjava3/internal/operators/completable/CompletablePeek;
       4: getfield      #4                  // Field io/reactivex/rxjava3/internal/operators/completable/CompletablePeek.onSubscribe:Lio/reactivex/rxjava3/functions/Consumer;
       7: aload_1
       8: invokeinterface #5,  2            // InterfaceMethod io/reactivex/rxjava3/functions/Consumer.accept:(Ljava/lang/Object;)V
      13: goto          43
      16: astore_2
      17: aload_2
      18: invokestatic  #7                  // Method io/reactivex/rxjava3/exceptions/Exceptions.throwIfFatal:(Ljava/lang/Throwable;)V
      21: aload_1
      22: invokeinterface #8,  1            // InterfaceMethod io/reactivex/rxjava3/disposables/Disposable.dispose:()V
      27: aload_0
      28: getstatic     #9                  // Field io/reactivex/rxjava3/internal/disposables/DisposableHelper.DISPOSED:Lio/reactivex/rxjava3/internal/disposables/DisposableHelper;
      31: putfield      #10                 // Field upstream:Lio/reactivex/rxjava3/disposables/Disposable;
      34: aload_2
      35: aload_0
      36: getfield      #3                  // Field downstream:Lio/reactivex/rxjava3/core/CompletableObserver;
      39: invokestatic  #11                 // Method io/reactivex/rxjava3/internal/disposables/EmptyDisposable.error:(Ljava/lang/Throwable;Lio/reactivex/rxjava3/core/CompletableObserver;)V
      42: return
      43: aload_0
      44: getfield      #10                 // Field upstream:Lio/reactivex/rxjava3/disposables/Disposable;
      47: aload_1
      48: invokestatic  #12                 // Method io/reactivex/rxjava3/internal/disposables/DisposableHelper.validate:(Lio/reactivex/rxjava3/disposables/Disposable;Lio/reactivex/rxjava3/disposables/Disposable;)Z
      51: ifeq          69
      54: aload_0
      55: aload_1
      56: putfield      #10                 // Field upstream:Lio/reactivex/rxjava3/disposables/Disposable;
      59: aload_0
      60: getfield      #3                  // Field downstream:Lio/reactivex/rxjava3/core/CompletableObserver;
      63: aload_0
      64: invokeinterface #13,  2           // InterfaceMethod io/reactivex/rxjava3/core/CompletableObserver.onSubscribe:(Lio/reactivex/rxjava3/disposables/Disposable;)V
      69: return
    Exception table:
       from    to  target type
           0    13    16   Class java/lang/Throwable

  public void onError(java.lang.Throwable);
    Code:
       0: aload_0
       1: getfield      #10                 // Field upstream:Lio/reactivex/rxjava3/disposables/Disposable;
       4: getstatic     #9                  // Field io/reactivex/rxjava3/internal/disposables/DisposableHelper.DISPOSED:Lio/reactivex/rxjava3/internal/disposables/DisposableHelper;
       7: if_acmpne     15
      10: aload_1
      11: invokestatic  #14                 // Method io/reactivex/rxjava3/plugins/RxJavaPlugins.onError:(Ljava/lang/Throwable;)V
      14: return
      15: aload_0
      16: getfield      #1                  // Field this$0:Lio/reactivex/rxjava3/internal/operators/completable/CompletablePeek;
      19: getfield      #15                 // Field io/reactivex/rxjava3/internal/operators/completable/CompletablePeek.onError:Lio/reactivex/rxjava3/functions/Consumer;
      22: aload_1
      23: invokeinterface #5,  2            // InterfaceMethod io/reactivex/rxjava3/functions/Consumer.accept:(Ljava/lang/Object;)V
      28: aload_0
      29: getfield      #1                  // Field this$0:Lio/reactivex/rxjava3/internal/operators/completable/CompletablePeek;
      32: getfield      #16                 // Field io/reactivex/rxjava3/internal/operators/completable/CompletablePeek.onTerminate:Lio/reactivex/rxjava3/functions/Action;
      35: invokeinterface #17,  1           // InterfaceMethod io/reactivex/rxjava3/functions/Action.run:()V
      40: goto          68
      43: astore_2
      44: aload_2
      45: invokestatic  #7                  // Method io/reactivex/rxjava3/exceptions/Exceptions.throwIfFatal:(Ljava/lang/Throwable;)V
      48: new           #18                 // class io/reactivex/rxjava3/exceptions/CompositeException
      51: dup
      52: iconst_2
      53: anewarray     #19                 // class java/lang/Throwable
      56: dup
      57: iconst_0
      58: aload_1
      59: aastore
      60: dup
      61: iconst_1
      62: aload_2
      63: aastore
      64: invokespecial #20                 // Method io/reactivex/rxjava3/exceptions/CompositeException."<init>":([Ljava/lang/Throwable;)V
      67: astore_1
      68: aload_0
      69: getfield      #3                  // Field downstream:Lio/reactivex/rxjava3/core/CompletableObserver;
      72: aload_1
      73: invokeinterface #21,  2           // InterfaceMethod io/reactivex/rxjava3/core/CompletableObserver.onError:(Ljava/lang/Throwable;)V
      78: aload_0
      79: invokevirtual #22                 // Method doAfter:()V
      82: return
    Exception table:
       from    to  target type
          15    40    43   Class java/lang/Throwable

  public void onComplete();
    Code:
       0: aload_0
       1: getfield      #10                 // Field upstream:Lio/reactivex/rxjava3/disposables/Disposable;
       4: getstatic     #9                  // Field io/reactivex/rxjava3/internal/disposables/DisposableHelper.DISPOSED:Lio/reactivex/rxjava3/internal/disposables/DisposableHelper;
       7: if_acmpne     11
      10: return
      11: aload_0
      12: getfield      #1                  // Field this$0:Lio/reactivex/rxjava3/internal/operators/completable/CompletablePeek;
      15: getfield      #23                 // Field io/reactivex/rxjava3/internal/operators/completable/CompletablePeek.onComplete:Lio/reactivex/rxjava3/functions/Action;
      18: invokeinterface #17,  1           // InterfaceMethod io/reactivex/rxjava3/functions/Action.run:()V
      23: aload_0
      24: getfield      #1                  // Field this$0:Lio/reactivex/rxjava3/internal/operators/completable/CompletablePeek;
      27: getfield      #16                 // Field io/reactivex/rxjava3/internal/operators/completable/CompletablePeek.onTerminate:Lio/reactivex/rxjava3/functions/Action;
      30: invokeinterface #17,  1           // InterfaceMethod io/reactivex/rxjava3/functions/Action.run:()V
      35: goto          54
      38: astore_1
      39: aload_1
      40: invokestatic  #7                  // Method io/reactivex/rxjava3/exceptions/Exceptions.throwIfFatal:(Ljava/lang/Throwable;)V
      43: aload_0
      44: getfield      #3                  // Field downstream:Lio/reactivex/rxjava3/core/CompletableObserver;
      47: aload_1
      48: invokeinterface #21,  2           // InterfaceMethod io/reactivex/rxjava3/core/CompletableObserver.onError:(Ljava/lang/Throwable;)V
      53: return
      54: aload_0
      55: getfield      #3                  // Field downstream:Lio/reactivex/rxjava3/core/CompletableObserver;
      58: invokeinterface #24,  1           // InterfaceMethod io/reactivex/rxjava3/core/CompletableObserver.onComplete:()V
      63: aload_0
      64: invokevirtual #22                 // Method doAfter:()V
      67: return
    Exception table:
       from    to  target type
          11    35    38   Class java/lang/Throwable

  void doAfter();
    Code:
       0: aload_0
       1: getfield      #1                  // Field this$0:Lio/reactivex/rxjava3/internal/operators/completable/CompletablePeek;
       4: getfield      #25                 // Field io/reactivex/rxjava3/internal/operators/completable/CompletablePeek.onAfterTerminate:Lio/reactivex/rxjava3/functions/Action;
       7: invokeinterface #17,  1           // InterfaceMethod io/reactivex/rxjava3/functions/Action.run:()V
      12: goto          24
      15: astore_1
      16: aload_1
      17: invokestatic  #7                  // Method io/reactivex/rxjava3/exceptions/Exceptions.throwIfFatal:(Ljava/lang/Throwable;)V
      20: aload_1
      21: invokestatic  #14                 // Method io/reactivex/rxjava3/plugins/RxJavaPlugins.onError:(Ljava/lang/Throwable;)V
      24: return
    Exception table:
       from    to  target type
           0    12    15   Class java/lang/Throwable

  public void dispose();
    Code:
       0: aload_0
       1: getfield      #1                  // Field this$0:Lio/reactivex/rxjava3/internal/operators/completable/CompletablePeek;
       4: getfield      #26                 // Field io/reactivex/rxjava3/internal/operators/completable/CompletablePeek.onDispose:Lio/reactivex/rxjava3/functions/Action;
       7: invokeinterface #17,  1           // InterfaceMethod io/reactivex/rxjava3/functions/Action.run:()V
      12: goto          24
      15: astore_1
      16: aload_1
      17: invokestatic  #7                  // Method io/reactivex/rxjava3/exceptions/Exceptions.throwIfFatal:(Ljava/lang/Throwable;)V
      20: aload_1
      21: invokestatic  #14                 // Method io/reactivex/rxjava3/plugins/RxJavaPlugins.onError:(Ljava/lang/Throwable;)V
      24: aload_0
      25: getfield      #10                 // Field upstream:Lio/reactivex/rxjava3/disposables/Disposable;
      28: invokeinterface #8,  1            // InterfaceMethod io/reactivex/rxjava3/disposables/Disposable.dispose:()V
      33: return
    Exception table:
       from    to  target type
           0    12    15   Class java/lang/Throwable

  public boolean isDisposed();
    Code:
       0: aload_0
       1: getfield      #10                 // Field upstream:Lio/reactivex/rxjava3/disposables/Disposable;
       4: invokeinterface #27,  1           // InterfaceMethod io/reactivex/rxjava3/disposables/Disposable.isDisposed:()Z
       9: ireturn
}
