Compiled from "CompletableConcatIterable.java"
public final class io.reactivex.rxjava3.internal.operators.completable.CompletableConcatIterable extends io.reactivex.rxjava3.core.Completable {
  final java.lang.Iterable<? extends io.reactivex.rxjava3.core.CompletableSource> sources;

  public io.reactivex.rxjava3.internal.operators.completable.CompletableConcatIterable(java.lang.Iterable<? extends io.reactivex.rxjava3.core.CompletableSource>);
    Code:
       0: aload_0
       1: invokespecial #1                  // Method io/reactivex/rxjava3/core/Completable."<init>":()V
       4: aload_0
       5: aload_1
       6: putfield      #2                  // Field sources:Ljava/lang/Iterable;
       9: return

  public void subscribeActual(io.reactivex.rxjava3.core.CompletableObserver);
    Code:
       0: aload_0
       1: getfield      #2                  // Field sources:Ljava/lang/Iterable;
       4: invokeinterface #3,  1            // InterfaceMethod java/lang/Iterable.iterator:()Ljava/util/Iterator;
       9: ldc           #4                  // String The iterator returned is null
      11: invokestatic  #5                  // Method java/util/Objects.requireNonNull:(Ljava/lang/Object;Ljava/lang/String;)Ljava/lang/Object;
      14: checkcast     #6                  // class java/util/Iterator
      17: astore_2
      18: goto          32
      21: astore_3
      22: aload_3
      23: invokestatic  #8                  // Method io/reactivex/rxjava3/exceptions/Exceptions.throwIfFatal:(Ljava/lang/Throwable;)V
      26: aload_3
      27: aload_1
      28: invokestatic  #9                  // Method io/reactivex/rxjava3/internal/disposables/EmptyDisposable.error:(Ljava/lang/Throwable;Lio/reactivex/rxjava3/core/CompletableObserver;)V
      31: return
      32: new           #10                 // class io/reactivex/rxjava3/internal/operators/completable/CompletableConcatIterable$ConcatInnerObserver
      35: dup
      36: aload_1
      37: aload_2
      38: invokespecial #11                 // Method io/reactivex/rxjava3/internal/operators/completable/CompletableConcatIterable$ConcatInnerObserver."<init>":(Lio/reactivex/rxjava3/core/CompletableObserver;Ljava/util/Iterator;)V
      41: astore_3
      42: aload_1
      43: aload_3
      44: getfield      #12                 // Field io/reactivex/rxjava3/internal/operators/completable/CompletableConcatIterable$ConcatInnerObserver.sd:Lio/reactivex/rxjava3/internal/disposables/SequentialDisposable;
      47: invokeinterface #13,  2           // InterfaceMethod io/reactivex/rxjava3/core/CompletableObserver.onSubscribe:(Lio/reactivex/rxjava3/disposables/Disposable;)V
      52: aload_3
      53: invokevirtual #14                 // Method io/reactivex/rxjava3/internal/operators/completable/CompletableConcatIterable$ConcatInnerObserver.next:()V
      56: return
    Exception table:
       from    to  target type
           0    18    21   Class java/lang/Throwable
}
