Compiled from "CompletableError.java"
public final class io.reactivex.rxjava3.internal.operators.completable.CompletableError extends io.reactivex.rxjava3.core.Completable {
  final java.lang.Throwable error;

  public io.reactivex.rxjava3.internal.operators.completable.CompletableError(java.lang.Throwable);
    Code:
       0: aload_0
       1: invokespecial #1                  // Method io/reactivex/rxjava3/core/Completable."<init>":()V
       4: aload_0
       5: aload_1
       6: putfield      #2                  // Field error:Ljava/lang/Throwable;
       9: return

  protected void subscribeActual(io.reactivex.rxjava3.core.CompletableObserver);
    Code:
       0: aload_0
       1: getfield      #2                  // Field error:Ljava/lang/Throwable;
       4: aload_1
       5: invokestatic  #3                  // Method io/reactivex/rxjava3/internal/disposables/EmptyDisposable.error:(Ljava/lang/Throwable;Lio/reactivex/rxjava3/core/CompletableObserver;)V
       8: return
}
