Compiled from "CompletableDoOnEvent.java"
final class io.reactivex.rxjava3.internal.operators.completable.CompletableDoOnEvent$DoOnEvent implements io.reactivex.rxjava3.core.CompletableObserver {
  private final io.reactivex.rxjava3.core.CompletableObserver observer;

  final io.reactivex.rxjava3.internal.operators.completable.CompletableDoOnEvent this$0;

  io.reactivex.rxjava3.internal.operators.completable.CompletableDoOnEvent$DoOnEvent(io.reactivex.rxjava3.internal.operators.completable.CompletableDoOnEvent, io.reactivex.rxjava3.core.CompletableObserver);
    Code:
       0: aload_0
       1: aload_1
       2: putfield      #1                  // Field this$0:Lio/reactivex/rxjava3/internal/operators/completable/CompletableDoOnEvent;
       5: aload_0
       6: invokespecial #2                  // Method java/lang/Object."<init>":()V
       9: aload_0
      10: aload_2
      11: putfield      #3                  // Field observer:Lio/reactivex/rxjava3/core/CompletableObserver;
      14: return

  public void onComplete();
    Code:
       0: aload_0
       1: getfield      #1                  // Field this$0:Lio/reactivex/rxjava3/internal/operators/completable/CompletableDoOnEvent;
       4: getfield      #4                  // Field io/reactivex/rxjava3/internal/operators/completable/CompletableDoOnEvent.onEvent:Lio/reactivex/rxjava3/functions/Consumer;
       7: aconst_null
       8: invokeinterface #5,  2            // InterfaceMethod io/reactivex/rxjava3/functions/Consumer.accept:(Ljava/lang/Object;)V
      13: goto          32
      16: astore_1
      17: aload_1
      18: invokestatic  #7                  // Method io/reactivex/rxjava3/exceptions/Exceptions.throwIfFatal:(Ljava/lang/Throwable;)V
      21: aload_0
      22: getfield      #3                  // Field observer:Lio/reactivex/rxjava3/core/CompletableObserver;
      25: aload_1
      26: invokeinterface #8,  2            // InterfaceMethod io/reactivex/rxjava3/core/CompletableObserver.onError:(Ljava/lang/Throwable;)V
      31: return
      32: aload_0
      33: getfield      #3                  // Field observer:Lio/reactivex/rxjava3/core/CompletableObserver;
      36: invokeinterface #9,  1            // InterfaceMethod io/reactivex/rxjava3/core/CompletableObserver.onComplete:()V
      41: return
    Exception table:
       from    to  target type
           0    13    16   Class java/lang/Throwable

  public void onError(java.lang.Throwable);
    Code:
       0: aload_0
       1: getfield      #1                  // Field this$0:Lio/reactivex/rxjava3/internal/operators/completable/CompletableDoOnEvent;
       4: getfield      #4                  // Field io/reactivex/rxjava3/internal/operators/completable/CompletableDoOnEvent.onEvent:Lio/reactivex/rxjava3/functions/Consumer;
       7: aload_1
       8: invokeinterface #5,  2            // InterfaceMethod io/reactivex/rxjava3/functions/Consumer.accept:(Ljava/lang/Object;)V
      13: goto          41
      16: astore_2
      17: aload_2
      18: invokestatic  #7                  // Method io/reactivex/rxjava3/exceptions/Exceptions.throwIfFatal:(Ljava/lang/Throwable;)V
      21: new           #10                 // class io/reactivex/rxjava3/exceptions/CompositeException
      24: dup
      25: iconst_2
      26: anewarray     #11                 // class java/lang/Throwable
      29: dup
      30: iconst_0
      31: aload_1
      32: aastore
      33: dup
      34: iconst_1
      35: aload_2
      36: aastore
      37: invokespecial #12                 // Method io/reactivex/rxjava3/exceptions/CompositeException."<init>":([Ljava/lang/Throwable;)V
      40: astore_1
      41: aload_0
      42: getfield      #3                  // Field observer:Lio/reactivex/rxjava3/core/CompletableObserver;
      45: aload_1
      46: invokeinterface #8,  2            // InterfaceMethod io/reactivex/rxjava3/core/CompletableObserver.onError:(Ljava/lang/Throwable;)V
      51: return
    Exception table:
       from    to  target type
           0    13    16   Class java/lang/Throwable

  public void onSubscribe(io.reactivex.rxjava3.disposables.Disposable);
    Code:
       0: aload_0
       1: getfield      #3                  // Field observer:Lio/reactivex/rxjava3/core/CompletableObserver;
       4: aload_1
       5: invokeinterface #13,  2           // InterfaceMethod io/reactivex/rxjava3/core/CompletableObserver.onSubscribe:(Lio/reactivex/rxjava3/disposables/Disposable;)V
      10: return
}
