Compiled from "CompletableFromObservable.java"
public final class io.reactivex.rxjava3.internal.operators.completable.CompletableFromObservable<T> extends io.reactivex.rxjava3.core.Completable {
  final io.reactivex.rxjava3.core.ObservableSource<T> observable;

  public io.reactivex.rxjava3.internal.operators.completable.CompletableFromObservable(io.reactivex.rxjava3.core.ObservableSource<T>);
    Code:
       0: aload_0
       1: invokespecial #1                  // Method io/reactivex/rxjava3/core/Completable."<init>":()V
       4: aload_0
       5: aload_1
       6: putfield      #2                  // Field observable:Lio/reactivex/rxjava3/core/ObservableSource;
       9: return

  protected void subscribeActual(io.reactivex.rxjava3.core.CompletableObserver);
    Code:
       0: aload_0
       1: getfield      #2                  // Field observable:Lio/reactivex/rxjava3/core/ObservableSource;
       4: new           #3                  // class io/reactivex/rxjava3/internal/operators/completable/CompletableFromObservable$CompletableFromObservableObserver
       7: dup
       8: aload_1
       9: invokespecial #4                  // Method io/reactivex/rxjava3/internal/operators/completable/CompletableFromObservable$CompletableFromObservableObserver."<init>":(Lio/reactivex/rxjava3/core/CompletableObserver;)V
      12: invokeinterface #5,  2            // InterfaceMethod io/reactivex/rxjava3/core/ObservableSource.subscribe:(Lio/reactivex/rxjava3/core/Observer;)V
      17: return
}
