Compiled from "CompletableErrorSupplier.java"
public final class io.reactivex.rxjava3.internal.operators.completable.CompletableErrorSupplier extends io.reactivex.rxjava3.core.Completable {
  final io.reactivex.rxjava3.functions.Supplier<? extends java.lang.Throwable> errorSupplier;

  public io.reactivex.rxjava3.internal.operators.completable.CompletableErrorSupplier(io.reactivex.rxjava3.functions.Supplier<? extends java.lang.Throwable>);
    Code:
       0: aload_0
       1: invokespecial #1                  // Method io/reactivex/rxjava3/core/Completable."<init>":()V
       4: aload_0
       5: aload_1
       6: putfield      #2                  // Field errorSupplier:Lio/reactivex/rxjava3/functions/Supplier;
       9: return

  protected void subscribeActual(io.reactivex.rxjava3.core.CompletableObserver);
    Code:
       0: aload_0
       1: getfield      #2                  // Field errorSupplier:Lio/reactivex/rxjava3/functions/Supplier;
       4: invokeinterface #3,  1            // InterfaceMethod io/reactivex/rxjava3/functions/Supplier.get:()Ljava/lang/Object;
       9: ldc           #4                  // String The error returned is null
      11: invokestatic  #5                  // Method java/util/Objects.requireNonNull:(Ljava/lang/Object;Ljava/lang/String;)Ljava/lang/Object;
      14: checkcast     #6                  // class java/lang/Throwable
      17: astore_2
      18: goto          28
      21: astore_3
      22: aload_3
      23: invokestatic  #7                  // Method io/reactivex/rxjava3/exceptions/Exceptions.throwIfFatal:(Ljava/lang/Throwable;)V
      26: aload_3
      27: astore_2
      28: aload_2
      29: aload_1
      30: invokestatic  #8                  // Method io/reactivex/rxjava3/internal/disposables/EmptyDisposable.error:(Ljava/lang/Throwable;Lio/reactivex/rxjava3/core/CompletableObserver;)V
      33: return
    Exception table:
       from    to  target type
           0    18    21   Class java/lang/Throwable
}
