Compiled from "CompletableTakeUntilCompletable.java"
final class io.reactivex.rxjava3.internal.operators.completable.CompletableTakeUntilCompletable$TakeUntilMainObserver extends java.util.concurrent.atomic.AtomicReference<io.reactivex.rxjava3.disposables.Disposable> implements io.reactivex.rxjava3.core.CompletableObserver, io.reactivex.rxjava3.disposables.Disposable {
  private static final long serialVersionUID;

  final io.reactivex.rxjava3.core.CompletableObserver downstream;

  final io.reactivex.rxjava3.internal.operators.completable.CompletableTakeUntilCompletable$TakeUntilMainObserver$OtherObserver other;

  final java.util.concurrent.atomic.AtomicBoolean once;

  io.reactivex.rxjava3.internal.operators.completable.CompletableTakeUntilCompletable$TakeUntilMainObserver(io.reactivex.rxjava3.core.CompletableObserver);
    Code:
       0: aload_0
       1: invokespecial #1                  // Method java/util/concurrent/atomic/AtomicReference."<init>":()V
       4: aload_0
       5: aload_1
       6: putfield      #2                  // Field downstream:Lio/reactivex/rxjava3/core/CompletableObserver;
       9: aload_0
      10: new           #3                  // class io/reactivex/rxjava3/internal/operators/completable/CompletableTakeUntilCompletable$TakeUntilMainObserver$OtherObserver
      13: dup
      14: aload_0
      15: invokespecial #4                  // Method io/reactivex/rxjava3/internal/operators/completable/CompletableTakeUntilCompletable$TakeUntilMainObserver$OtherObserver."<init>":(Lio/reactivex/rxjava3/internal/operators/completable/CompletableTakeUntilCompletable$TakeUntilMainObserver;)V
      18: putfield      #5                  // Field other:Lio/reactivex/rxjava3/internal/operators/completable/CompletableTakeUntilCompletable$TakeUntilMainObserver$OtherObserver;
      21: aload_0
      22: new           #6                  // class java/util/concurrent/atomic/AtomicBoolean
      25: dup
      26: invokespecial #7                  // Method java/util/concurrent/atomic/AtomicBoolean."<init>":()V
      29: putfield      #8                  // Field once:Ljava/util/concurrent/atomic/AtomicBoolean;
      32: return

  public void dispose();
    Code:
       0: aload_0
       1: getfield      #8                  // Field once:Ljava/util/concurrent/atomic/AtomicBoolean;
       4: iconst_0
       5: iconst_1
       6: invokevirtual #9                  // Method java/util/concurrent/atomic/AtomicBoolean.compareAndSet:(ZZ)Z
       9: ifeq          25
      12: aload_0
      13: invokestatic  #10                 // Method io/reactivex/rxjava3/internal/disposables/DisposableHelper.dispose:(Ljava/util/concurrent/atomic/AtomicReference;)Z
      16: pop
      17: aload_0
      18: getfield      #5                  // Field other:Lio/reactivex/rxjava3/internal/operators/completable/CompletableTakeUntilCompletable$TakeUntilMainObserver$OtherObserver;
      21: invokestatic  #10                 // Method io/reactivex/rxjava3/internal/disposables/DisposableHelper.dispose:(Ljava/util/concurrent/atomic/AtomicReference;)Z
      24: pop
      25: return

  public boolean isDisposed();
    Code:
       0: aload_0
       1: getfield      #8                  // Field once:Ljava/util/concurrent/atomic/AtomicBoolean;
       4: invokevirtual #11                 // Method java/util/concurrent/atomic/AtomicBoolean.get:()Z
       7: ireturn

  public void onSubscribe(io.reactivex.rxjava3.disposables.Disposable);
    Code:
       0: aload_0
       1: aload_1
       2: invokestatic  #12                 // Method io/reactivex/rxjava3/internal/disposables/DisposableHelper.setOnce:(Ljava/util/concurrent/atomic/AtomicReference;Lio/reactivex/rxjava3/disposables/Disposable;)Z
       5: pop
       6: return

  public void onComplete();
    Code:
       0: aload_0
       1: getfield      #8                  // Field once:Ljava/util/concurrent/atomic/AtomicBoolean;
       4: iconst_0
       5: iconst_1
       6: invokevirtual #9                  // Method java/util/concurrent/atomic/AtomicBoolean.compareAndSet:(ZZ)Z
       9: ifeq          29
      12: aload_0
      13: getfield      #5                  // Field other:Lio/reactivex/rxjava3/internal/operators/completable/CompletableTakeUntilCompletable$TakeUntilMainObserver$OtherObserver;
      16: invokestatic  #10                 // Method io/reactivex/rxjava3/internal/disposables/DisposableHelper.dispose:(Ljava/util/concurrent/atomic/AtomicReference;)Z
      19: pop
      20: aload_0
      21: getfield      #2                  // Field downstream:Lio/reactivex/rxjava3/core/CompletableObserver;
      24: invokeinterface #13,  1           // InterfaceMethod io/reactivex/rxjava3/core/CompletableObserver.onComplete:()V
      29: return

  public void onError(java.lang.Throwable);
    Code:
       0: aload_0
       1: getfield      #8                  // Field once:Ljava/util/concurrent/atomic/AtomicBoolean;
       4: iconst_0
       5: iconst_1
       6: invokevirtual #9                  // Method java/util/concurrent/atomic/AtomicBoolean.compareAndSet:(ZZ)Z
       9: ifeq          33
      12: aload_0
      13: getfield      #5                  // Field other:Lio/reactivex/rxjava3/internal/operators/completable/CompletableTakeUntilCompletable$TakeUntilMainObserver$OtherObserver;
      16: invokestatic  #10                 // Method io/reactivex/rxjava3/internal/disposables/DisposableHelper.dispose:(Ljava/util/concurrent/atomic/AtomicReference;)Z
      19: pop
      20: aload_0
      21: getfield      #2                  // Field downstream:Lio/reactivex/rxjava3/core/CompletableObserver;
      24: aload_1
      25: invokeinterface #14,  2           // InterfaceMethod io/reactivex/rxjava3/core/CompletableObserver.onError:(Ljava/lang/Throwable;)V
      30: goto          37
      33: aload_1
      34: invokestatic  #15                 // Method io/reactivex/rxjava3/plugins/RxJavaPlugins.onError:(Ljava/lang/Throwable;)V
      37: return

  void innerComplete();
    Code:
       0: aload_0
       1: getfield      #8                  // Field once:Ljava/util/concurrent/atomic/AtomicBoolean;
       4: iconst_0
       5: iconst_1
       6: invokevirtual #9                  // Method java/util/concurrent/atomic/AtomicBoolean.compareAndSet:(ZZ)Z
       9: ifeq          26
      12: aload_0
      13: invokestatic  #10                 // Method io/reactivex/rxjava3/internal/disposables/DisposableHelper.dispose:(Ljava/util/concurrent/atomic/AtomicReference;)Z
      16: pop
      17: aload_0
      18: getfield      #2                  // Field downstream:Lio/reactivex/rxjava3/core/CompletableObserver;
      21: invokeinterface #13,  1           // InterfaceMethod io/reactivex/rxjava3/core/CompletableObserver.onComplete:()V
      26: return

  void innerError(java.lang.Throwable);
    Code:
       0: aload_0
       1: getfield      #8                  // Field once:Ljava/util/concurrent/atomic/AtomicBoolean;
       4: iconst_0
       5: iconst_1
       6: invokevirtual #9                  // Method java/util/concurrent/atomic/AtomicBoolean.compareAndSet:(ZZ)Z
       9: ifeq          30
      12: aload_0
      13: invokestatic  #10                 // Method io/reactivex/rxjava3/internal/disposables/DisposableHelper.dispose:(Ljava/util/concurrent/atomic/AtomicReference;)Z
      16: pop
      17: aload_0
      18: getfield      #2                  // Field downstream:Lio/reactivex/rxjava3/core/CompletableObserver;
      21: aload_1
      22: invokeinterface #14,  2           // InterfaceMethod io/reactivex/rxjava3/core/CompletableObserver.onError:(Ljava/lang/Throwable;)V
      27: goto          34
      30: aload_1
      31: invokestatic  #15                 // Method io/reactivex/rxjava3/plugins/RxJavaPlugins.onError:(Ljava/lang/Throwable;)V
      34: return
}
