Compiled from "CompletableSubscribeOn.java"
public final class io.reactivex.rxjava3.internal.operators.completable.CompletableSubscribeOn extends io.reactivex.rxjava3.core.Completable {
  final io.reactivex.rxjava3.core.CompletableSource source;

  final io.reactivex.rxjava3.core.Scheduler scheduler;

  public io.reactivex.rxjava3.internal.operators.completable.CompletableSubscribeOn(io.reactivex.rxjava3.core.CompletableSource, io.reactivex.rxjava3.core.Scheduler);
    Code:
       0: aload_0
       1: invokespecial #1                  // Method io/reactivex/rxjava3/core/Completable."<init>":()V
       4: aload_0
       5: aload_1
       6: putfield      #2                  // Field source:Lio/reactivex/rxjava3/core/CompletableSource;
       9: aload_0
      10: aload_2
      11: putfield      #3                  // Field scheduler:Lio/reactivex/rxjava3/core/Scheduler;
      14: return

  protected void subscribeActual(io.reactivex.rxjava3.core.CompletableObserver);
    Code:
       0: new           #4                  // class io/reactivex/rxjava3/internal/operators/completable/CompletableSubscribeOn$SubscribeOnObserver
       3: dup
       4: aload_1
       5: aload_0
       6: getfield      #2                  // Field source:Lio/reactivex/rxjava3/core/CompletableSource;
       9: invokespecial #5                  // Method io/reactivex/rxjava3/internal/operators/completable/CompletableSubscribeOn$SubscribeOnObserver."<init>":(Lio/reactivex/rxjava3/core/CompletableObserver;Lio/reactivex/rxjava3/core/CompletableSource;)V
      12: astore_2
      13: aload_1
      14: aload_2
      15: invokeinterface #6,  2            // InterfaceMethod io/reactivex/rxjava3/core/CompletableObserver.onSubscribe:(Lio/reactivex/rxjava3/disposables/Disposable;)V
      20: aload_0
      21: getfield      #3                  // Field scheduler:Lio/reactivex/rxjava3/core/Scheduler;
      24: aload_2
      25: invokevirtual #7                  // Method io/reactivex/rxjava3/core/Scheduler.scheduleDirect:(Ljava/lang/Runnable;)Lio/reactivex/rxjava3/disposables/Disposable;
      28: astore_3
      29: aload_2
      30: getfield      #8                  // Field io/reactivex/rxjava3/internal/operators/completable/CompletableSubscribeOn$SubscribeOnObserver.task:Lio/reactivex/rxjava3/internal/disposables/SequentialDisposable;
      33: aload_3
      34: invokevirtual #9                  // Method io/reactivex/rxjava3/internal/disposables/SequentialDisposable.replace:(Lio/reactivex/rxjava3/disposables/Disposable;)Z
      37: pop
      38: return
}
