Compiled from "CompletableAndThenCompletable.java"
final class io.reactivex.rxjava3.internal.operators.completable.CompletableAndThenCompletable$NextObserver implements io.reactivex.rxjava3.core.CompletableObserver {
  final java.util.concurrent.atomic.AtomicReference<io.reactivex.rxjava3.disposables.Disposable> parent;

  final io.reactivex.rxjava3.core.CompletableObserver downstream;

  io.reactivex.rxjava3.internal.operators.completable.CompletableAndThenCompletable$NextObserver(java.util.concurrent.atomic.AtomicReference<io.reactivex.rxjava3.disposables.Disposable>, io.reactivex.rxjava3.core.CompletableObserver);
    Code:
       0: aload_0
       1: invokespecial #1                  // Method java/lang/Object."<init>":()V
       4: aload_0
       5: aload_1
       6: putfield      #2                  // Field parent:Ljava/util/concurrent/atomic/AtomicReference;
       9: aload_0
      10: aload_2
      11: putfield      #3                  // Field downstream:Lio/reactivex/rxjava3/core/CompletableObserver;
      14: return

  public void onSubscribe(io.reactivex.rxjava3.disposables.Disposable);
    Code:
       0: aload_0
       1: getfield      #2                  // Field parent:Ljava/util/concurrent/atomic/AtomicReference;
       4: aload_1
       5: invokestatic  #4                  // Method io/reactivex/rxjava3/internal/disposables/DisposableHelper.replace:(Ljava/util/concurrent/atomic/AtomicReference;Lio/reactivex/rxjava3/disposables/Disposable;)Z
       8: pop
       9: return

  public void onComplete();
    Code:
       0: aload_0
       1: getfield      #3                  // Field downstream:Lio/reactivex/rxjava3/core/CompletableObserver;
       4: invokeinterface #5,  1            // InterfaceMethod io/reactivex/rxjava3/core/CompletableObserver.onComplete:()V
       9: return

  public void onError(java.lang.Throwable);
    Code:
       0: aload_0
       1: getfield      #3                  // Field downstream:Lio/reactivex/rxjava3/core/CompletableObserver;
       4: aload_1
       5: invokeinterface #6,  2            // InterfaceMethod io/reactivex/rxjava3/core/CompletableObserver.onError:(Ljava/lang/Throwable;)V
      10: return
}
