Compiled from "CompletableFromPublisher.java"
public final class io.reactivex.rxjava3.internal.operators.completable.CompletableFromPublisher<T> extends io.reactivex.rxjava3.core.Completable {
  final org.reactivestreams.Publisher<T> flowable;

  public io.reactivex.rxjava3.internal.operators.completable.CompletableFromPublisher(org.reactivestreams.Publisher<T>);
    Code:
       0: aload_0
       1: invokespecial #1                  // Method io/reactivex/rxjava3/core/Completable."<init>":()V
       4: aload_0
       5: aload_1
       6: putfield      #2                  // Field flowable:Lorg/reactivestreams/Publisher;
       9: return

  protected void subscribeActual(io.reactivex.rxjava3.core.CompletableObserver);
    Code:
       0: aload_0
       1: getfield      #2                  // Field flowable:Lorg/reactivestreams/Publisher;
       4: new           #3                  // class io/reactivex/rxjava3/internal/operators/completable/CompletableFromPublisher$FromPublisherSubscriber
       7: dup
       8: aload_1
       9: invokespecial #4                  // Method io/reactivex/rxjava3/internal/operators/completable/CompletableFromPublisher$FromPublisherSubscriber."<init>":(Lio/reactivex/rxjava3/core/CompletableObserver;)V
      12: invokeinterface #5,  2            // InterfaceMethod org/reactivestreams/Publisher.subscribe:(Lorg/reactivestreams/Subscriber;)V
      17: return
}
