Compiled from "CompletableAmb.java"
final class io.reactivex.rxjava3.internal.operators.completable.CompletableAmb$Amb implements io.reactivex.rxjava3.core.CompletableObserver {
  final java.util.concurrent.atomic.AtomicBoolean once;

  final io.reactivex.rxjava3.disposables.CompositeDisposable set;

  final io.reactivex.rxjava3.core.CompletableObserver downstream;

  io.reactivex.rxjava3.disposables.Disposable upstream;

  io.reactivex.rxjava3.internal.operators.completable.CompletableAmb$Amb(java.util.concurrent.atomic.AtomicBoolean, io.reactivex.rxjava3.disposables.CompositeDisposable, io.reactivex.rxjava3.core.CompletableObserver);
    Code:
       0: aload_0
       1: invokespecial #1                  // Method java/lang/Object."<init>":()V
       4: aload_0
       5: aload_1
       6: putfield      #2                  // Field once:Ljava/util/concurrent/atomic/AtomicBoolean;
       9: aload_0
      10: aload_2
      11: putfield      #3                  // Field set:Lio/reactivex/rxjava3/disposables/CompositeDisposable;
      14: aload_0
      15: aload_3
      16: putfield      #4                  // Field downstream:Lio/reactivex/rxjava3/core/CompletableObserver;
      19: return

  public void onComplete();
    Code:
       0: aload_0
       1: getfield      #2                  // Field once:Ljava/util/concurrent/atomic/AtomicBoolean;
       4: iconst_0
       5: iconst_1
       6: invokevirtual #5                  // Method java/util/concurrent/atomic/AtomicBoolean.compareAndSet:(ZZ)Z
       9: ifeq          40
      12: aload_0
      13: getfield      #3                  // Field set:Lio/reactivex/rxjava3/disposables/CompositeDisposable;
      16: aload_0
      17: getfield      #6                  // Field upstream:Lio/reactivex/rxjava3/disposables/Disposable;
      20: invokevirtual #7                  // Method io/reactivex/rxjava3/disposables/CompositeDisposable.delete:(Lio/reactivex/rxjava3/disposables/Disposable;)Z
      23: pop
      24: aload_0
      25: getfield      #3                  // Field set:Lio/reactivex/rxjava3/disposables/CompositeDisposable;
      28: invokevirtual #8                  // Method io/reactivex/rxjava3/disposables/CompositeDisposable.dispose:()V
      31: aload_0
      32: getfield      #4                  // Field downstream:Lio/reactivex/rxjava3/core/CompletableObserver;
      35: invokeinterface #9,  1            // InterfaceMethod io/reactivex/rxjava3/core/CompletableObserver.onComplete:()V
      40: return

  public void onError(java.lang.Throwable);
    Code:
       0: aload_0
       1: getfield      #2                  // Field once:Ljava/util/concurrent/atomic/AtomicBoolean;
       4: iconst_0
       5: iconst_1
       6: invokevirtual #5                  // Method java/util/concurrent/atomic/AtomicBoolean.compareAndSet:(ZZ)Z
       9: ifeq          44
      12: aload_0
      13: getfield      #3                  // Field set:Lio/reactivex/rxjava3/disposables/CompositeDisposable;
      16: aload_0
      17: getfield      #6                  // Field upstream:Lio/reactivex/rxjava3/disposables/Disposable;
      20: invokevirtual #7                  // Method io/reactivex/rxjava3/disposables/CompositeDisposable.delete:(Lio/reactivex/rxjava3/disposables/Disposable;)Z
      23: pop
      24: aload_0
      25: getfield      #3                  // Field set:Lio/reactivex/rxjava3/disposables/CompositeDisposable;
      28: invokevirtual #8                  // Method io/reactivex/rxjava3/disposables/CompositeDisposable.dispose:()V
      31: aload_0
      32: getfield      #4                  // Field downstream:Lio/reactivex/rxjava3/core/CompletableObserver;
      35: aload_1
      36: invokeinterface #10,  2           // InterfaceMethod io/reactivex/rxjava3/core/CompletableObserver.onError:(Ljava/lang/Throwable;)V
      41: goto          48
      44: aload_1
      45: invokestatic  #11                 // Method io/reactivex/rxjava3/plugins/RxJavaPlugins.onError:(Ljava/lang/Throwable;)V
      48: return

  public void onSubscribe(io.reactivex.rxjava3.disposables.Disposable);
    Code:
       0: aload_0
       1: aload_1
       2: putfield      #6                  // Field upstream:Lio/reactivex/rxjava3/disposables/Disposable;
       5: aload_0
       6: getfield      #3                  // Field set:Lio/reactivex/rxjava3/disposables/CompositeDisposable;
       9: aload_1
      10: invokevirtual #12                 // Method io/reactivex/rxjava3/disposables/CompositeDisposable.add:(Lio/reactivex/rxjava3/disposables/Disposable;)Z
      13: pop
      14: return
}
