Compiled from "CompletableMergeDelayErrorIterable.java"
public final class io.reactivex.rxjava3.internal.operators.completable.CompletableMergeDelayErrorIterable extends io.reactivex.rxjava3.core.Completable {
  final java.lang.Iterable<? extends io.reactivex.rxjava3.core.CompletableSource> sources;

  public io.reactivex.rxjava3.internal.operators.completable.CompletableMergeDelayErrorIterable(java.lang.Iterable<? extends io.reactivex.rxjava3.core.CompletableSource>);
    Code:
       0: aload_0
       1: invokespecial #1                  // Method io/reactivex/rxjava3/core/Completable."<init>":()V
       4: aload_0
       5: aload_1
       6: putfield      #2                  // Field sources:Ljava/lang/Iterable;
       9: return

  public void subscribeActual(io.reactivex.rxjava3.core.CompletableObserver);
    Code:
       0: new           #3                  // class io/reactivex/rxjava3/disposables/CompositeDisposable
       3: dup
       4: invokespecial #4                  // Method io/reactivex/rxjava3/disposables/CompositeDisposable."<init>":()V
       7: astore_2
       8: aload_1
       9: aload_2
      10: invokeinterface #5,  2            // InterfaceMethod io/reactivex/rxjava3/core/CompletableObserver.onSubscribe:(Lio/reactivex/rxjava3/disposables/Disposable;)V
      15: aload_0
      16: getfield      #2                  // Field sources:Ljava/lang/Iterable;
      19: invokeinterface #6,  1            // InterfaceMethod java/lang/Iterable.iterator:()Ljava/util/Iterator;
      24: ldc           #7                  // String The source iterator returned is null
      26: invokestatic  #8                  // Method java/util/Objects.requireNonNull:(Ljava/lang/Object;Ljava/lang/String;)Ljava/lang/Object;
      29: checkcast     #9                  // class java/util/Iterator
      32: astore_3
      33: goto          52
      36: astore        4
      38: aload         4
      40: invokestatic  #11                 // Method io/reactivex/rxjava3/exceptions/Exceptions.throwIfFatal:(Ljava/lang/Throwable;)V
      43: aload_1
      44: aload         4
      46: invokeinterface #12,  2           // InterfaceMethod io/reactivex/rxjava3/core/CompletableObserver.onError:(Ljava/lang/Throwable;)V
      51: return
      52: new           #13                 // class java/util/concurrent/atomic/AtomicInteger
      55: dup
      56: iconst_1
      57: invokespecial #14                 // Method java/util/concurrent/atomic/AtomicInteger."<init>":(I)V
      60: astore        4
      62: new           #15                 // class io/reactivex/rxjava3/internal/util/AtomicThrowable
      65: dup
      66: invokespecial #16                 // Method io/reactivex/rxjava3/internal/util/AtomicThrowable."<init>":()V
      69: astore        5
      71: aload_2
      72: new           #17                 // class io/reactivex/rxjava3/internal/operators/completable/CompletableMergeArrayDelayError$TryTerminateAndReportDisposable
      75: dup
      76: aload         5
      78: invokespecial #18                 // Method io/reactivex/rxjava3/internal/operators/completable/CompletableMergeArrayDelayError$TryTerminateAndReportDisposable."<init>":(Lio/reactivex/rxjava3/internal/util/AtomicThrowable;)V
      81: invokevirtual #19                 // Method io/reactivex/rxjava3/disposables/CompositeDisposable.add:(Lio/reactivex/rxjava3/disposables/Disposable;)Z
      84: pop
      85: aload_2
      86: invokevirtual #20                 // Method io/reactivex/rxjava3/disposables/CompositeDisposable.isDisposed:()Z
      89: ifeq          93
      92: return
      93: aload_3
      94: invokeinterface #21,  1           // InterfaceMethod java/util/Iterator.hasNext:()Z
      99: istore        6
     101: goto          122
     104: astore        7
     106: aload         7
     108: invokestatic  #11                 // Method io/reactivex/rxjava3/exceptions/Exceptions.throwIfFatal:(Ljava/lang/Throwable;)V
     111: aload         5
     113: aload         7
     115: invokevirtual #22                 // Method io/reactivex/rxjava3/internal/util/AtomicThrowable.tryAddThrowableOrReport:(Ljava/lang/Throwable;)Z
     118: pop
     119: goto          212
     122: iload         6
     124: ifne          130
     127: goto          212
     130: aload_2
     131: invokevirtual #20                 // Method io/reactivex/rxjava3/disposables/CompositeDisposable.isDisposed:()Z
     134: ifeq          138
     137: return
     138: aload_3
     139: invokeinterface #23,  1           // InterfaceMethod java/util/Iterator.next:()Ljava/lang/Object;
     144: ldc           #24                 // String The iterator returned a null CompletableSource
     146: invokestatic  #8                  // Method java/util/Objects.requireNonNull:(Ljava/lang/Object;Ljava/lang/String;)Ljava/lang/Object;
     149: checkcast     #25                 // class io/reactivex/rxjava3/core/CompletableSource
     152: astore        7
     154: goto          175
     157: astore        8
     159: aload         8
     161: invokestatic  #11                 // Method io/reactivex/rxjava3/exceptions/Exceptions.throwIfFatal:(Ljava/lang/Throwable;)V
     164: aload         5
     166: aload         8
     168: invokevirtual #22                 // Method io/reactivex/rxjava3/internal/util/AtomicThrowable.tryAddThrowableOrReport:(Ljava/lang/Throwable;)Z
     171: pop
     172: goto          212
     175: aload_2
     176: invokevirtual #20                 // Method io/reactivex/rxjava3/disposables/CompositeDisposable.isDisposed:()Z
     179: ifeq          183
     182: return
     183: aload         4
     185: invokevirtual #26                 // Method java/util/concurrent/atomic/AtomicInteger.getAndIncrement:()I
     188: pop
     189: aload         7
     191: new           #27                 // class io/reactivex/rxjava3/internal/operators/completable/CompletableMergeArrayDelayError$MergeInnerCompletableObserver
     194: dup
     195: aload_1
     196: aload_2
     197: aload         5
     199: aload         4
     201: invokespecial #28                 // Method io/reactivex/rxjava3/internal/operators/completable/CompletableMergeArrayDelayError$MergeInnerCompletableObserver."<init>":(Lio/reactivex/rxjava3/core/CompletableObserver;Lio/reactivex/rxjava3/disposables/CompositeDisposable;Lio/reactivex/rxjava3/internal/util/AtomicThrowable;Ljava/util/concurrent/atomic/AtomicInteger;)V
     204: invokeinterface #29,  2           // InterfaceMethod io/reactivex/rxjava3/core/CompletableSource.subscribe:(Lio/reactivex/rxjava3/core/CompletableObserver;)V
     209: goto          85
     212: aload         4
     214: invokevirtual #30                 // Method java/util/concurrent/atomic/AtomicInteger.decrementAndGet:()I
     217: ifne          226
     220: aload         5
     222: aload_1
     223: invokevirtual #31                 // Method io/reactivex/rxjava3/internal/util/AtomicThrowable.tryTerminateConsumer:(Lio/reactivex/rxjava3/core/CompletableObserver;)V
     226: return
    Exception table:
       from    to  target type
          15    33    36   Class java/lang/Throwable
          93   101   104   Class java/lang/Throwable
         138   154   157   Class java/lang/Throwable
}
