Compiled from "CompletableFromCallable.java"
public final class io.reactivex.rxjava3.internal.operators.completable.CompletableFromCallable extends io.reactivex.rxjava3.core.Completable {
  final java.util.concurrent.Callable<?> callable;

  public io.reactivex.rxjava3.internal.operators.completable.CompletableFromCallable(java.util.concurrent.Callable<?>);
    Code:
       0: aload_0
       1: invokespecial #1                  // Method io/reactivex/rxjava3/core/Completable."<init>":()V
       4: aload_0
       5: aload_1
       6: putfield      #2                  // Field callable:Ljava/util/concurrent/Callable;
       9: return

  protected void subscribeActual(io.reactivex.rxjava3.core.CompletableObserver);
    Code:
       0: invokestatic  #3                  // InterfaceMethod io/reactivex/rxjava3/disposables/Disposable.empty:()Lio/reactivex/rxjava3/disposables/Disposable;
       3: astore_2
       4: aload_1
       5: aload_2
       6: invokeinterface #4,  2            // InterfaceMethod io/reactivex/rxjava3/core/CompletableObserver.onSubscribe:(Lio/reactivex/rxjava3/disposables/Disposable;)V
      11: aload_0
      12: getfield      #2                  // Field callable:Ljava/util/concurrent/Callable;
      15: invokeinterface #5,  1            // InterfaceMethod java/util/concurrent/Callable.call:()Ljava/lang/Object;
      20: pop
      21: goto          53
      24: astore_3
      25: aload_3
      26: invokestatic  #7                  // Method io/reactivex/rxjava3/exceptions/Exceptions.throwIfFatal:(Ljava/lang/Throwable;)V
      29: aload_2
      30: invokeinterface #8,  1            // InterfaceMethod io/reactivex/rxjava3/disposables/Disposable.isDisposed:()Z
      35: ifne          48
      38: aload_1
      39: aload_3
      40: invokeinterface #9,  2            // InterfaceMethod io/reactivex/rxjava3/core/CompletableObserver.onError:(Ljava/lang/Throwable;)V
      45: goto          52
      48: aload_3
      49: invokestatic  #10                 // Method io/reactivex/rxjava3/plugins/RxJavaPlugins.onError:(Ljava/lang/Throwable;)V
      52: return
      53: aload_2
      54: invokeinterface #8,  1            // InterfaceMethod io/reactivex/rxjava3/disposables/Disposable.isDisposed:()Z
      59: ifne          68
      62: aload_1
      63: invokeinterface #11,  1           // InterfaceMethod io/reactivex/rxjava3/core/CompletableObserver.onComplete:()V
      68: return
    Exception table:
       from    to  target type
          11    21    24   Class java/lang/Throwable
}
