Compiled from "CompletableCache.java"
final class io.reactivex.rxjava3.internal.operators.completable.CompletableCache$InnerCompletableCache extends java.util.concurrent.atomic.AtomicBoolean implements io.reactivex.rxjava3.disposables.Disposable {
  private static final long serialVersionUID;

  final io.reactivex.rxjava3.core.CompletableObserver downstream;

  final io.reactivex.rxjava3.internal.operators.completable.CompletableCache this$0;

  io.reactivex.rxjava3.internal.operators.completable.CompletableCache$InnerCompletableCache(io.reactivex.rxjava3.internal.operators.completable.CompletableCache, io.reactivex.rxjava3.core.CompletableObserver);
    Code:
       0: aload_0
       1: aload_1
       2: putfield      #1                  // Field this$0:Lio/reactivex/rxjava3/internal/operators/completable/CompletableCache;
       5: aload_0
       6: invokespecial #2                  // Method java/util/concurrent/atomic/AtomicBoolean."<init>":()V
       9: aload_0
      10: aload_2
      11: putfield      #3                  // Field downstream:Lio/reactivex/rxjava3/core/CompletableObserver;
      14: return

  public boolean isDisposed();
    Code:
       0: aload_0
       1: invokevirtual #4                  // Method get:()Z
       4: ireturn

  public void dispose();
    Code:
       0: aload_0
       1: iconst_0
       2: iconst_1
       3: invokevirtual #5                  // Method compareAndSet:(ZZ)Z
       6: ifeq          17
       9: aload_0
      10: getfield      #1                  // Field this$0:Lio/reactivex/rxjava3/internal/operators/completable/CompletableCache;
      13: aload_0
      14: invokevirtual #6                  // Method io/reactivex/rxjava3/internal/operators/completable/CompletableCache.remove:(Lio/reactivex/rxjava3/internal/operators/completable/CompletableCache$InnerCompletableCache;)V
      17: return
}
