Compiled from "CompletableToObservable.java"
public final class io.reactivex.rxjava3.internal.operators.completable.CompletableToObservable<T> extends io.reactivex.rxjava3.core.Observable<T> {
  final io.reactivex.rxjava3.core.CompletableSource source;

  public io.reactivex.rxjava3.internal.operators.completable.CompletableToObservable(io.reactivex.rxjava3.core.CompletableSource);
    Code:
       0: aload_0
       1: invokespecial #1                  // Method io/reactivex/rxjava3/core/Observable."<init>":()V
       4: aload_0
       5: aload_1
       6: putfield      #2                  // Field source:Lio/reactivex/rxjava3/core/CompletableSource;
       9: return

  protected void subscribeActual(io.reactivex.rxjava3.core.Observer<? super T>);
    Code:
       0: aload_0
       1: getfield      #2                  // Field source:Lio/reactivex/rxjava3/core/CompletableSource;
       4: new           #3                  // class io/reactivex/rxjava3/internal/operators/observable/ObservableFromCompletable$FromCompletableObserver
       7: dup
       8: aload_1
       9: invokespecial #4                  // Method io/reactivex/rxjava3/internal/operators/observable/ObservableFromCompletable$FromCompletableObserver."<init>":(Lio/reactivex/rxjava3/core/Observer;)V
      12: invokeinterface #5,  2            // InterfaceMethod io/reactivex/rxjava3/core/CompletableSource.subscribe:(Lio/reactivex/rxjava3/core/CompletableObserver;)V
      17: return
}
