Compiled from "CompletableConcat.java"
public final class io.reactivex.rxjava3.internal.operators.completable.CompletableConcat extends io.reactivex.rxjava3.core.Completable {
  final org.reactivestreams.Publisher<? extends io.reactivex.rxjava3.core.CompletableSource> sources;

  final int prefetch;

  public io.reactivex.rxjava3.internal.operators.completable.CompletableConcat(org.reactivestreams.Publisher<? extends io.reactivex.rxjava3.core.CompletableSource>, int);
    Code:
       0: aload_0
       1: invokespecial #1                  // Method io/reactivex/rxjava3/core/Completable."<init>":()V
       4: aload_0
       5: aload_1
       6: putfield      #2                  // Field sources:Lorg/reactivestreams/Publisher;
       9: aload_0
      10: iload_2
      11: putfield      #3                  // Field prefetch:I
      14: return

  public void subscribeActual(io.reactivex.rxjava3.core.CompletableObserver);
    Code:
       0: aload_0
       1: getfield      #2                  // Field sources:Lorg/reactivestreams/Publisher;
       4: new           #4                  // class io/reactivex/rxjava3/internal/operators/completable/CompletableConcat$CompletableConcatSubscriber
       7: dup
       8: aload_1
       9: aload_0
      10: getfield      #3                  // Field prefetch:I
      13: invokespecial #5                  // Method io/reactivex/rxjava3/internal/operators/completable/CompletableConcat$CompletableConcatSubscriber."<init>":(Lio/reactivex/rxjava3/core/CompletableObserver;I)V
      16: invokeinterface #6,  2            // InterfaceMethod org/reactivestreams/Publisher.subscribe:(Lorg/reactivestreams/Subscriber;)V
      21: return
}
