Compiled from "CompletableCreate.java"
final class io.reactivex.rxjava3.internal.operators.completable.CompletableCreate$Emitter extends java.util.concurrent.atomic.AtomicReference<io.reactivex.rxjava3.disposables.Disposable> implements io.reactivex.rxjava3.core.CompletableEmitter, io.reactivex.rxjava3.disposables.Disposable {
  private static final long serialVersionUID;

  final io.reactivex.rxjava3.core.CompletableObserver downstream;

  io.reactivex.rxjava3.internal.operators.completable.CompletableCreate$Emitter(io.reactivex.rxjava3.core.CompletableObserver);
    Code:
       0: aload_0
       1: invokespecial #1                  // Method java/util/concurrent/atomic/AtomicReference."<init>":()V
       4: aload_0
       5: aload_1
       6: putfield      #2                  // Field downstream:Lio/reactivex/rxjava3/core/CompletableObserver;
       9: return

  public void onComplete();
    Code:
       0: aload_0
       1: invokevirtual #3                  // Method get:()Ljava/lang/Object;
       4: getstatic     #4                  // Field io/reactivex/rxjava3/internal/disposables/DisposableHelper.DISPOSED:Lio/reactivex/rxjava3/internal/disposables/DisposableHelper;
       7: if_acmpeq     63
      10: aload_0
      11: getstatic     #4                  // Field io/reactivex/rxjava3/internal/disposables/DisposableHelper.DISPOSED:Lio/reactivex/rxjava3/internal/disposables/DisposableHelper;
      14: invokevirtual #5                  // Method getAndSet:(Ljava/lang/Object;)Ljava/lang/Object;
      17: checkcast     #6                  // class io/reactivex/rxjava3/disposables/Disposable
      20: astore_1
      21: aload_1
      22: getstatic     #4                  // Field io/reactivex/rxjava3/internal/disposables/DisposableHelper.DISPOSED:Lio/reactivex/rxjava3/internal/disposables/DisposableHelper;
      25: if_acmpeq     63
      28: aload_0
      29: getfield      #2                  // Field downstream:Lio/reactivex/rxjava3/core/CompletableObserver;
      32: invokeinterface #7,  1            // InterfaceMethod io/reactivex/rxjava3/core/CompletableObserver.onComplete:()V
      37: aload_1
      38: ifnull        63
      41: aload_1
      42: invokeinterface #8,  1            // InterfaceMethod io/reactivex/rxjava3/disposables/Disposable.dispose:()V
      47: goto          63
      50: astore_2
      51: aload_1
      52: ifnull        61
      55: aload_1
      56: invokeinterface #8,  1            // InterfaceMethod io/reactivex/rxjava3/disposables/Disposable.dispose:()V
      61: aload_2
      62: athrow
      63: return
    Exception table:
       from    to  target type
          28    37    50   any

  public void onError(java.lang.Throwable);
    Code:
       0: aload_0
       1: aload_1
       2: invokevirtual #9                  // Method tryOnError:(Ljava/lang/Throwable;)Z
       5: ifne          12
       8: aload_1
       9: invokestatic  #10                 // Method io/reactivex/rxjava3/plugins/RxJavaPlugins.onError:(Ljava/lang/Throwable;)V
      12: return

  public boolean tryOnError(java.lang.Throwable);
    Code:
       0: aload_1
       1: ifnonnull     10
       4: ldc           #11                 // String onError called with a null Throwable.
       6: invokestatic  #12                 // Method io/reactivex/rxjava3/internal/util/ExceptionHelper.createNullPointerException:(Ljava/lang/String;)Ljava/lang/NullPointerException;
       9: astore_1
      10: aload_0
      11: invokevirtual #3                  // Method get:()Ljava/lang/Object;
      14: getstatic     #4                  // Field io/reactivex/rxjava3/internal/disposables/DisposableHelper.DISPOSED:Lio/reactivex/rxjava3/internal/disposables/DisposableHelper;
      17: if_acmpeq     76
      20: aload_0
      21: getstatic     #4                  // Field io/reactivex/rxjava3/internal/disposables/DisposableHelper.DISPOSED:Lio/reactivex/rxjava3/internal/disposables/DisposableHelper;
      24: invokevirtual #5                  // Method getAndSet:(Ljava/lang/Object;)Ljava/lang/Object;
      27: checkcast     #6                  // class io/reactivex/rxjava3/disposables/Disposable
      30: astore_2
      31: aload_2
      32: getstatic     #4                  // Field io/reactivex/rxjava3/internal/disposables/DisposableHelper.DISPOSED:Lio/reactivex/rxjava3/internal/disposables/DisposableHelper;
      35: if_acmpeq     76
      38: aload_0
      39: getfield      #2                  // Field downstream:Lio/reactivex/rxjava3/core/CompletableObserver;
      42: aload_1
      43: invokeinterface #13,  2           // InterfaceMethod io/reactivex/rxjava3/core/CompletableObserver.onError:(Ljava/lang/Throwable;)V
      48: aload_2
      49: ifnull        74
      52: aload_2
      53: invokeinterface #8,  1            // InterfaceMethod io/reactivex/rxjava3/disposables/Disposable.dispose:()V
      58: goto          74
      61: astore_3
      62: aload_2
      63: ifnull        72
      66: aload_2
      67: invokeinterface #8,  1            // InterfaceMethod io/reactivex/rxjava3/disposables/Disposable.dispose:()V
      72: aload_3
      73: athrow
      74: iconst_1
      75: ireturn
      76: iconst_0
      77: ireturn
    Exception table:
       from    to  target type
          38    48    61   any

  public void setDisposable(io.reactivex.rxjava3.disposables.Disposable);
    Code:
       0: aload_0
       1: aload_1
       2: invokestatic  #14                 // Method io/reactivex/rxjava3/internal/disposables/DisposableHelper.set:(Ljava/util/concurrent/atomic/AtomicReference;Lio/reactivex/rxjava3/disposables/Disposable;)Z
       5: pop
       6: return

  public void setCancellable(io.reactivex.rxjava3.functions.Cancellable);
    Code:
       0: aload_0
       1: new           #15                 // class io/reactivex/rxjava3/internal/disposables/CancellableDisposable
       4: dup
       5: aload_1
       6: invokespecial #16                 // Method io/reactivex/rxjava3/internal/disposables/CancellableDisposable."<init>":(Lio/reactivex/rxjava3/functions/Cancellable;)V
       9: invokevirtual #17                 // Method setDisposable:(Lio/reactivex/rxjava3/disposables/Disposable;)V
      12: return

  public void dispose();
    Code:
       0: aload_0
       1: invokestatic  #18                 // Method io/reactivex/rxjava3/internal/disposables/DisposableHelper.dispose:(Ljava/util/concurrent/atomic/AtomicReference;)Z
       4: pop
       5: return

  public boolean isDisposed();
    Code:
       0: aload_0
       1: invokevirtual #3                  // Method get:()Ljava/lang/Object;
       4: checkcast     #6                  // class io/reactivex/rxjava3/disposables/Disposable
       7: invokestatic  #19                 // Method io/reactivex/rxjava3/internal/disposables/DisposableHelper.isDisposed:(Lio/reactivex/rxjava3/disposables/Disposable;)Z
      10: ireturn

  public java.lang.String toString();
    Code:
       0: ldc           #20                 // String %s{%s}
       2: iconst_2
       3: anewarray     #21                 // class java/lang/Object
       6: dup
       7: iconst_0
       8: aload_0
       9: invokevirtual #22                 // Method java/lang/Object.getClass:()Ljava/lang/Class;
      12: invokevirtual #23                 // Method java/lang/Class.getSimpleName:()Ljava/lang/String;
      15: aastore
      16: dup
      17: iconst_1
      18: aload_0
      19: invokespecial #24                 // Method java/util/concurrent/atomic/AtomicReference.toString:()Ljava/lang/String;
      22: aastore
      23: invokestatic  #25                 // Method java/lang/String.format:(Ljava/lang/String;[Ljava/lang/Object;)Ljava/lang/String;
      26: areturn
}
