Compiled from "CompletableDelay.java"
public final class io.reactivex.rxjava3.internal.operators.completable.CompletableDelay extends io.reactivex.rxjava3.core.Completable {
  final io.reactivex.rxjava3.core.CompletableSource source;

  final long delay;

  final java.util.concurrent.TimeUnit unit;

  final io.reactivex.rxjava3.core.Scheduler scheduler;

  final boolean delayError;

  public io.reactivex.rxjava3.internal.operators.completable.CompletableDelay(io.reactivex.rxjava3.core.CompletableSource, long, java.util.concurrent.TimeUnit, io.reactivex.rxjava3.core.Scheduler, boolean);
    Code:
       0: aload_0
       1: invokespecial #1                  // Method io/reactivex/rxjava3/core/Completable."<init>":()V
       4: aload_0
       5: aload_1
       6: putfield      #2                  // Field source:Lio/reactivex/rxjava3/core/CompletableSource;
       9: aload_0
      10: lload_2
      11: putfield      #3                  // Field delay:J
      14: aload_0
      15: aload         4
      17: putfield      #4                  // Field unit:Ljava/util/concurrent/TimeUnit;
      20: aload_0
      21: aload         5
      23: putfield      #5                  // Field scheduler:Lio/reactivex/rxjava3/core/Scheduler;
      26: aload_0
      27: iload         6
      29: putfield      #6                  // Field delayError:Z
      32: return

  protected void subscribeActual(io.reactivex.rxjava3.core.CompletableObserver);
    Code:
       0: aload_0
       1: getfield      #2                  // Field source:Lio/reactivex/rxjava3/core/CompletableSource;
       4: new           #7                  // class io/reactivex/rxjava3/internal/operators/completable/CompletableDelay$Delay
       7: dup
       8: aload_1
       9: aload_0
      10: getfield      #3                  // Field delay:J
      13: aload_0
      14: getfield      #4                  // Field unit:Ljava/util/concurrent/TimeUnit;
      17: aload_0
      18: getfield      #5                  // Field scheduler:Lio/reactivex/rxjava3/core/Scheduler;
      21: aload_0
      22: getfield      #6                  // Field delayError:Z
      25: invokespecial #8                  // Method io/reactivex/rxjava3/internal/operators/completable/CompletableDelay$Delay."<init>":(Lio/reactivex/rxjava3/core/CompletableObserver;JLjava/util/concurrent/TimeUnit;Lio/reactivex/rxjava3/core/Scheduler;Z)V
      28: invokeinterface #9,  2            // InterfaceMethod io/reactivex/rxjava3/core/CompletableSource.subscribe:(Lio/reactivex/rxjava3/core/CompletableObserver;)V
      33: return
}
