Compiled from "CompletableOnErrorReturn.java"
public final class io.reactivex.rxjava3.internal.operators.completable.CompletableOnErrorReturn<T> extends io.reactivex.rxjava3.core.Maybe<T> {
  final io.reactivex.rxjava3.core.CompletableSource source;

  final io.reactivex.rxjava3.functions.Function<? super java.lang.Throwable, ? extends T> valueSupplier;

  public io.reactivex.rxjava3.internal.operators.completable.CompletableOnErrorReturn(io.reactivex.rxjava3.core.CompletableSource, io.reactivex.rxjava3.functions.Function<? super java.lang.Throwable, ? extends T>);
    Code:
       0: aload_0
       1: invokespecial #1                  // Method io/reactivex/rxjava3/core/Maybe."<init>":()V
       4: aload_0
       5: aload_1
       6: putfield      #2                  // Field source:Lio/reactivex/rxjava3/core/CompletableSource;
       9: aload_0
      10: aload_2
      11: putfield      #3                  // Field valueSupplier:Lio/reactivex/rxjava3/functions/Function;
      14: return

  protected void subscribeActual(io.reactivex.rxjava3.core.MaybeObserver<? super T>);
    Code:
       0: aload_0
       1: getfield      #2                  // Field source:Lio/reactivex/rxjava3/core/CompletableSource;
       4: new           #4                  // class io/reactivex/rxjava3/internal/operators/completable/CompletableOnErrorReturn$OnErrorReturnMaybeObserver
       7: dup
       8: aload_1
       9: aload_0
      10: getfield      #3                  // Field valueSupplier:Lio/reactivex/rxjava3/functions/Function;
      13: invokespecial #5                  // Method io/reactivex/rxjava3/internal/operators/completable/CompletableOnErrorReturn$OnErrorReturnMaybeObserver."<init>":(Lio/reactivex/rxjava3/core/MaybeObserver;Lio/reactivex/rxjava3/functions/Function;)V
      16: invokeinterface #6,  2            // InterfaceMethod io/reactivex/rxjava3/core/CompletableSource.subscribe:(Lio/reactivex/rxjava3/core/CompletableObserver;)V
      21: return
}
