Compiled from "CompletableDisposeOn.java"
final class io.reactivex.rxjava3.internal.operators.completable.CompletableDisposeOn$DisposeOnObserver implements io.reactivex.rxjava3.core.CompletableObserver,io.reactivex.rxjava3.disposables.Disposable,java.lang.Runnable {
  final io.reactivex.rxjava3.core.CompletableObserver downstream;

  final io.reactivex.rxjava3.core.Scheduler scheduler;

  io.reactivex.rxjava3.disposables.Disposable upstream;

  volatile boolean disposed;

  io.reactivex.rxjava3.internal.operators.completable.CompletableDisposeOn$DisposeOnObserver(io.reactivex.rxjava3.core.CompletableObserver, io.reactivex.rxjava3.core.Scheduler);
    Code:
       0: aload_0
       1: invokespecial #1                  // Method java/lang/Object."<init>":()V
       4: aload_0
       5: aload_1
       6: putfield      #2                  // Field downstream:Lio/reactivex/rxjava3/core/CompletableObserver;
       9: aload_0
      10: aload_2
      11: putfield      #3                  // Field scheduler:Lio/reactivex/rxjava3/core/Scheduler;
      14: return

  public void onComplete();
    Code:
       0: aload_0
       1: getfield      #4                  // Field disposed:Z
       4: ifeq          8
       7: return
       8: aload_0
       9: getfield      #2                  // Field downstream:Lio/reactivex/rxjava3/core/CompletableObserver;
      12: invokeinterface #5,  1            // InterfaceMethod io/reactivex/rxjava3/core/CompletableObserver.onComplete:()V
      17: return

  public void onError(java.lang.Throwable);
    Code:
       0: aload_0
       1: getfield      #4                  // Field disposed:Z
       4: ifeq          12
       7: aload_1
       8: invokestatic  #6                  // Method io/reactivex/rxjava3/plugins/RxJavaPlugins.onError:(Ljava/lang/Throwable;)V
      11: return
      12: aload_0
      13: getfield      #2                  // Field downstream:Lio/reactivex/rxjava3/core/CompletableObserver;
      16: aload_1
      17: invokeinterface #7,  2            // InterfaceMethod io/reactivex/rxjava3/core/CompletableObserver.onError:(Ljava/lang/Throwable;)V
      22: return

  public void onSubscribe(io.reactivex.rxjava3.disposables.Disposable);
    Code:
       0: aload_0
       1: getfield      #8                  // Field upstream:Lio/reactivex/rxjava3/disposables/Disposable;
       4: aload_1
       5: invokestatic  #9                  // Method io/reactivex/rxjava3/internal/disposables/DisposableHelper.validate:(Lio/reactivex/rxjava3/disposables/Disposable;Lio/reactivex/rxjava3/disposables/Disposable;)Z
       8: ifeq          26
      11: aload_0
      12: aload_1
      13: putfield      #8                  // Field upstream:Lio/reactivex/rxjava3/disposables/Disposable;
      16: aload_0
      17: getfield      #2                  // Field downstream:Lio/reactivex/rxjava3/core/CompletableObserver;
      20: aload_0
      21: invokeinterface #10,  2           // InterfaceMethod io/reactivex/rxjava3/core/CompletableObserver.onSubscribe:(Lio/reactivex/rxjava3/disposables/Disposable;)V
      26: return

  public void dispose();
    Code:
       0: aload_0
       1: iconst_1
       2: putfield      #4                  // Field disposed:Z
       5: aload_0
       6: getfield      #3                  // Field scheduler:Lio/reactivex/rxjava3/core/Scheduler;
       9: aload_0
      10: invokevirtual #11                 // Method io/reactivex/rxjava3/core/Scheduler.scheduleDirect:(Ljava/lang/Runnable;)Lio/reactivex/rxjava3/disposables/Disposable;
      13: pop
      14: return

  public boolean isDisposed();
    Code:
       0: aload_0
       1: getfield      #4                  // Field disposed:Z
       4: ireturn

  public void run();
    Code:
       0: aload_0
       1: getfield      #8                  // Field upstream:Lio/reactivex/rxjava3/disposables/Disposable;
       4: invokeinterface #12,  1           // InterfaceMethod io/reactivex/rxjava3/disposables/Disposable.dispose:()V
       9: aload_0
      10: getstatic     #13                 // Field io/reactivex/rxjava3/internal/disposables/DisposableHelper.DISPOSED:Lio/reactivex/rxjava3/internal/disposables/DisposableHelper;
      13: putfield      #8                  // Field upstream:Lio/reactivex/rxjava3/disposables/Disposable;
      16: return
}
