Compiled from "CompletableConcatArray.java"
final class io.reactivex.rxjava3.internal.operators.completable.CompletableConcatArray$ConcatInnerObserver extends java.util.concurrent.atomic.AtomicInteger implements io.reactivex.rxjava3.core.CompletableObserver {
  private static final long serialVersionUID;

  final io.reactivex.rxjava3.core.CompletableObserver downstream;

  final io.reactivex.rxjava3.core.CompletableSource[] sources;

  int index;

  final io.reactivex.rxjava3.internal.disposables.SequentialDisposable sd;

  io.reactivex.rxjava3.internal.operators.completable.CompletableConcatArray$ConcatInnerObserver(io.reactivex.rxjava3.core.CompletableObserver, io.reactivex.rxjava3.core.CompletableSource[]);
    Code:
       0: aload_0
       1: invokespecial #1                  // Method java/util/concurrent/atomic/AtomicInteger."<init>":()V
       4: aload_0
       5: aload_1
       6: putfield      #2                  // Field downstream:Lio/reactivex/rxjava3/core/CompletableObserver;
       9: aload_0
      10: aload_2
      11: putfield      #3                  // Field sources:[Lio/reactivex/rxjava3/core/CompletableSource;
      14: aload_0
      15: new           #4                  // class io/reactivex/rxjava3/internal/disposables/SequentialDisposable
      18: dup
      19: invokespecial #5                  // Method io/reactivex/rxjava3/internal/disposables/SequentialDisposable."<init>":()V
      22: putfield      #6                  // Field sd:Lio/reactivex/rxjava3/internal/disposables/SequentialDisposable;
      25: return

  public void onSubscribe(io.reactivex.rxjava3.disposables.Disposable);
    Code:
       0: aload_0
       1: getfield      #6                  // Field sd:Lio/reactivex/rxjava3/internal/disposables/SequentialDisposable;
       4: aload_1
       5: invokevirtual #7                  // Method io/reactivex/rxjava3/internal/disposables/SequentialDisposable.replace:(Lio/reactivex/rxjava3/disposables/Disposable;)Z
       8: pop
       9: return

  public void onError(java.lang.Throwable);
    Code:
       0: aload_0
       1: getfield      #2                  // Field downstream:Lio/reactivex/rxjava3/core/CompletableObserver;
       4: aload_1
       5: invokeinterface #8,  2            // InterfaceMethod io/reactivex/rxjava3/core/CompletableObserver.onError:(Ljava/lang/Throwable;)V
      10: return

  public void onComplete();
    Code:
       0: aload_0
       1: invokevirtual #9                  // Method next:()V
       4: return

  void next();
    Code:
       0: aload_0
       1: getfield      #6                  // Field sd:Lio/reactivex/rxjava3/internal/disposables/SequentialDisposable;
       4: invokevirtual #10                 // Method io/reactivex/rxjava3/internal/disposables/SequentialDisposable.isDisposed:()Z
       7: ifeq          11
      10: return
      11: aload_0
      12: invokevirtual #11                 // Method getAndIncrement:()I
      15: ifeq          19
      18: return
      19: aload_0
      20: getfield      #3                  // Field sources:[Lio/reactivex/rxjava3/core/CompletableSource;
      23: astore_1
      24: aload_0
      25: getfield      #6                  // Field sd:Lio/reactivex/rxjava3/internal/disposables/SequentialDisposable;
      28: invokevirtual #10                 // Method io/reactivex/rxjava3/internal/disposables/SequentialDisposable.isDisposed:()Z
      31: ifeq          35
      34: return
      35: aload_0
      36: dup
      37: getfield      #12                 // Field index:I
      40: dup_x1
      41: iconst_1
      42: iadd
      43: putfield      #12                 // Field index:I
      46: istore_2
      47: iload_2
      48: aload_1
      49: arraylength
      50: if_icmpne     63
      53: aload_0
      54: getfield      #2                  // Field downstream:Lio/reactivex/rxjava3/core/CompletableObserver;
      57: invokeinterface #13,  1           // InterfaceMethod io/reactivex/rxjava3/core/CompletableObserver.onComplete:()V
      62: return
      63: aload_1
      64: iload_2
      65: aaload
      66: aload_0
      67: invokeinterface #14,  2           // InterfaceMethod io/reactivex/rxjava3/core/CompletableSource.subscribe:(Lio/reactivex/rxjava3/core/CompletableObserver;)V
      72: aload_0
      73: invokevirtual #15                 // Method decrementAndGet:()I
      76: ifne          24
      79: return
}
