Compiled from "CompletableResumeNext.java"
final class io.reactivex.rxjava3.internal.operators.completable.CompletableResumeNext$ResumeNextObserver extends java.util.concurrent.atomic.AtomicReference<io.reactivex.rxjava3.disposables.Disposable> implements io.reactivex.rxjava3.core.CompletableObserver, io.reactivex.rxjava3.disposables.Disposable {
  private static final long serialVersionUID;

  final io.reactivex.rxjava3.core.CompletableObserver downstream;

  final io.reactivex.rxjava3.functions.Function<? super java.lang.Throwable, ? extends io.reactivex.rxjava3.core.CompletableSource> errorMapper;

  boolean once;

  io.reactivex.rxjava3.internal.operators.completable.CompletableResumeNext$ResumeNextObserver(io.reactivex.rxjava3.core.CompletableObserver, io.reactivex.rxjava3.functions.Function<? super java.lang.Throwable, ? extends io.reactivex.rxjava3.core.CompletableSource>);
    Code:
       0: aload_0
       1: invokespecial #1                  // Method java/util/concurrent/atomic/AtomicReference."<init>":()V
       4: aload_0
       5: aload_1
       6: putfield      #2                  // Field downstream:Lio/reactivex/rxjava3/core/CompletableObserver;
       9: aload_0
      10: aload_2
      11: putfield      #3                  // Field errorMapper:Lio/reactivex/rxjava3/functions/Function;
      14: return

  public void onSubscribe(io.reactivex.rxjava3.disposables.Disposable);
    Code:
       0: aload_0
       1: aload_1
       2: invokestatic  #4                  // Method io/reactivex/rxjava3/internal/disposables/DisposableHelper.replace:(Ljava/util/concurrent/atomic/AtomicReference;Lio/reactivex/rxjava3/disposables/Disposable;)Z
       5: pop
       6: return

  public void onComplete();
    Code:
       0: aload_0
       1: getfield      #2                  // Field downstream:Lio/reactivex/rxjava3/core/CompletableObserver;
       4: invokeinterface #5,  1            // InterfaceMethod io/reactivex/rxjava3/core/CompletableObserver.onComplete:()V
       9: return

  public void onError(java.lang.Throwable);
    Code:
       0: aload_0
       1: getfield      #6                  // Field once:Z
       4: ifeq          18
       7: aload_0
       8: getfield      #2                  // Field downstream:Lio/reactivex/rxjava3/core/CompletableObserver;
      11: aload_1
      12: invokeinterface #7,  2            // InterfaceMethod io/reactivex/rxjava3/core/CompletableObserver.onError:(Ljava/lang/Throwable;)V
      17: return
      18: aload_0
      19: iconst_1
      20: putfield      #6                  // Field once:Z
      23: aload_0
      24: getfield      #3                  // Field errorMapper:Lio/reactivex/rxjava3/functions/Function;
      27: aload_1
      28: invokeinterface #8,  2            // InterfaceMethod io/reactivex/rxjava3/functions/Function.apply:(Ljava/lang/Object;)Ljava/lang/Object;
      33: ldc           #9                  // String The errorMapper returned a null CompletableSource
      35: invokestatic  #10                 // Method java/util/Objects.requireNonNull:(Ljava/lang/Object;Ljava/lang/String;)Ljava/lang/Object;
      38: checkcast     #11                 // class io/reactivex/rxjava3/core/CompletableSource
      41: astore_2
      42: goto          79
      45: astore_3
      46: aload_3
      47: invokestatic  #13                 // Method io/reactivex/rxjava3/exceptions/Exceptions.throwIfFatal:(Ljava/lang/Throwable;)V
      50: aload_0
      51: getfield      #2                  // Field downstream:Lio/reactivex/rxjava3/core/CompletableObserver;
      54: new           #14                 // class io/reactivex/rxjava3/exceptions/CompositeException
      57: dup
      58: iconst_2
      59: anewarray     #15                 // class java/lang/Throwable
      62: dup
      63: iconst_0
      64: aload_1
      65: aastore
      66: dup
      67: iconst_1
      68: aload_3
      69: aastore
      70: invokespecial #16                 // Method io/reactivex/rxjava3/exceptions/CompositeException."<init>":([Ljava/lang/Throwable;)V
      73: invokeinterface #7,  2            // InterfaceMethod io/reactivex/rxjava3/core/CompletableObserver.onError:(Ljava/lang/Throwable;)V
      78: return
      79: aload_2
      80: aload_0
      81: invokeinterface #17,  2           // InterfaceMethod io/reactivex/rxjava3/core/CompletableSource.subscribe:(Lio/reactivex/rxjava3/core/CompletableObserver;)V
      86: return
    Exception table:
       from    to  target type
          23    42    45   Class java/lang/Throwable

  public boolean isDisposed();
    Code:
       0: aload_0
       1: invokevirtual #18                 // Method get:()Ljava/lang/Object;
       4: checkcast     #19                 // class io/reactivex/rxjava3/disposables/Disposable
       7: invokestatic  #20                 // Method io/reactivex/rxjava3/internal/disposables/DisposableHelper.isDisposed:(Lio/reactivex/rxjava3/disposables/Disposable;)Z
      10: ireturn

  public void dispose();
    Code:
       0: aload_0
       1: invokestatic  #21                 // Method io/reactivex/rxjava3/internal/disposables/DisposableHelper.dispose:(Ljava/util/concurrent/atomic/AtomicReference;)Z
       4: pop
       5: return
}
