Compiled from "CompletableMergeArrayDelayError.java"
final class io.reactivex.rxjava3.internal.operators.completable.CompletableMergeArrayDelayError$TryTerminateAndReportDisposable implements io.reactivex.rxjava3.disposables.Disposable {
  final io.reactivex.rxjava3.internal.util.AtomicThrowable errors;

  io.reactivex.rxjava3.internal.operators.completable.CompletableMergeArrayDelayError$TryTerminateAndReportDisposable(io.reactivex.rxjava3.internal.util.AtomicThrowable);
    Code:
       0: aload_0
       1: invokespecial #1                  // Method java/lang/Object."<init>":()V
       4: aload_0
       5: aload_1
       6: putfield      #2                  // Field errors:Lio/reactivex/rxjava3/internal/util/AtomicThrowable;
       9: return

  public void dispose();
    Code:
       0: aload_0
       1: getfield      #2                  // Field errors:Lio/reactivex/rxjava3/internal/util/AtomicThrowable;
       4: invokevirtual #3                  // Method io/reactivex/rxjava3/internal/util/AtomicThrowable.tryTerminateAndReport:()V
       7: return

  public boolean isDisposed();
    Code:
       0: aload_0
       1: getfield      #2                  // Field errors:Lio/reactivex/rxjava3/internal/util/AtomicThrowable;
       4: invokevirtual #4                  // Method io/reactivex/rxjava3/internal/util/AtomicThrowable.isTerminated:()Z
       7: ireturn
}
