Compiled from "CompletableConcatArray.java"
public final class io.reactivex.rxjava3.internal.operators.completable.CompletableConcatArray extends io.reactivex.rxjava3.core.Completable {
  final io.reactivex.rxjava3.core.CompletableSource[] sources;

  public io.reactivex.rxjava3.internal.operators.completable.CompletableConcatArray(io.reactivex.rxjava3.core.CompletableSource[]);
    Code:
       0: aload_0
       1: invokespecial #1                  // Method io/reactivex/rxjava3/core/Completable."<init>":()V
       4: aload_0
       5: aload_1
       6: putfield      #2                  // Field sources:[Lio/reactivex/rxjava3/core/CompletableSource;
       9: return

  public void subscribeActual(io.reactivex.rxjava3.core.CompletableObserver);
    Code:
       0: new           #3                  // class io/reactivex/rxjava3/internal/operators/completable/CompletableConcatArray$ConcatInnerObserver
       3: dup
       4: aload_1
       5: aload_0
       6: getfield      #2                  // Field sources:[Lio/reactivex/rxjava3/core/CompletableSource;
       9: invokespecial #4                  // Method io/reactivex/rxjava3/internal/operators/completable/CompletableConcatArray$ConcatInnerObserver."<init>":(Lio/reactivex/rxjava3/core/CompletableObserver;[Lio/reactivex/rxjava3/core/CompletableSource;)V
      12: astore_2
      13: aload_1
      14: aload_2
      15: getfield      #5                  // Field io/reactivex/rxjava3/internal/operators/completable/CompletableConcatArray$ConcatInnerObserver.sd:Lio/reactivex/rxjava3/internal/disposables/SequentialDisposable;
      18: invokeinterface #6,  2            // InterfaceMethod io/reactivex/rxjava3/core/CompletableObserver.onSubscribe:(Lio/reactivex/rxjava3/disposables/Disposable;)V
      23: aload_2
      24: invokevirtual #7                  // Method io/reactivex/rxjava3/internal/operators/completable/CompletableConcatArray$ConcatInnerObserver.next:()V
      27: return
}
