Compiled from "CompletableToSingle.java"
final class io.reactivex.rxjava3.internal.operators.completable.CompletableToSingle$ToSingle implements io.reactivex.rxjava3.core.CompletableObserver {
  private final io.reactivex.rxjava3.core.SingleObserver<? super T> observer;

  final io.reactivex.rxjava3.internal.operators.completable.CompletableToSingle this$0;

  io.reactivex.rxjava3.internal.operators.completable.CompletableToSingle$ToSingle(io.reactivex.rxjava3.core.SingleObserver<? super T>);
    Code:
       0: aload_0
       1: aload_1
       2: putfield      #1                  // Field this$0:Lio/reactivex/rxjava3/internal/operators/completable/CompletableToSingle;
       5: aload_0
       6: invokespecial #2                  // Method java/lang/Object."<init>":()V
       9: aload_0
      10: aload_2
      11: putfield      #3                  // Field observer:Lio/reactivex/rxjava3/core/SingleObserver;
      14: return

  public void onComplete();
    Code:
       0: aload_0
       1: getfield      #1                  // Field this$0:Lio/reactivex/rxjava3/internal/operators/completable/CompletableToSingle;
       4: getfield      #4                  // Field io/reactivex/rxjava3/internal/operators/completable/CompletableToSingle.completionValueSupplier:Lio/reactivex/rxjava3/functions/Supplier;
       7: ifnull        42
      10: aload_0
      11: getfield      #1                  // Field this$0:Lio/reactivex/rxjava3/internal/operators/completable/CompletableToSingle;
      14: getfield      #4                  // Field io/reactivex/rxjava3/internal/operators/completable/CompletableToSingle.completionValueSupplier:Lio/reactivex/rxjava3/functions/Supplier;
      17: invokeinterface #5,  1            // InterfaceMethod io/reactivex/rxjava3/functions/Supplier.get:()Ljava/lang/Object;
      22: astore_1
      23: goto          50
      26: astore_2
      27: aload_2
      28: invokestatic  #7                  // Method io/reactivex/rxjava3/exceptions/Exceptions.throwIfFatal:(Ljava/lang/Throwable;)V
      31: aload_0
      32: getfield      #3                  // Field observer:Lio/reactivex/rxjava3/core/SingleObserver;
      35: aload_2
      36: invokeinterface #8,  2            // InterfaceMethod io/reactivex/rxjava3/core/SingleObserver.onError:(Ljava/lang/Throwable;)V
      41: return
      42: aload_0
      43: getfield      #1                  // Field this$0:Lio/reactivex/rxjava3/internal/operators/completable/CompletableToSingle;
      46: getfield      #9                  // Field io/reactivex/rxjava3/internal/operators/completable/CompletableToSingle.completionValue:Ljava/lang/Object;
      49: astore_1
      50: aload_1
      51: ifnonnull     75
      54: aload_0
      55: getfield      #3                  // Field observer:Lio/reactivex/rxjava3/core/SingleObserver;
      58: new           #10                 // class java/lang/NullPointerException
      61: dup
      62: ldc           #11                 // String The value supplied is null
      64: invokespecial #12                 // Method java/lang/NullPointerException."<init>":(Ljava/lang/String;)V
      67: invokeinterface #8,  2            // InterfaceMethod io/reactivex/rxjava3/core/SingleObserver.onError:(Ljava/lang/Throwable;)V
      72: goto          85
      75: aload_0
      76: getfield      #3                  // Field observer:Lio/reactivex/rxjava3/core/SingleObserver;
      79: aload_1
      80: invokeinterface #13,  2           // InterfaceMethod io/reactivex/rxjava3/core/SingleObserver.onSuccess:(Ljava/lang/Object;)V
      85: return
    Exception table:
       from    to  target type
          10    23    26   Class java/lang/Throwable

  public void onError(java.lang.Throwable);
    Code:
       0: aload_0
       1: getfield      #3                  // Field observer:Lio/reactivex/rxjava3/core/SingleObserver;
       4: aload_1
       5: invokeinterface #8,  2            // InterfaceMethod io/reactivex/rxjava3/core/SingleObserver.onError:(Ljava/lang/Throwable;)V
      10: return

  public void onSubscribe(io.reactivex.rxjava3.disposables.Disposable);
    Code:
       0: aload_0
       1: getfield      #3                  // Field observer:Lio/reactivex/rxjava3/core/SingleObserver;
       4: aload_1
       5: invokeinterface #14,  2           // InterfaceMethod io/reactivex/rxjava3/core/SingleObserver.onSubscribe:(Lio/reactivex/rxjava3/disposables/Disposable;)V
      10: return
}
