Compiled from "CompletableMergeArrayDelayError.java"
public final class io.reactivex.rxjava3.internal.operators.completable.CompletableMergeArrayDelayError extends io.reactivex.rxjava3.core.Completable {
  final io.reactivex.rxjava3.core.CompletableSource[] sources;

  public io.reactivex.rxjava3.internal.operators.completable.CompletableMergeArrayDelayError(io.reactivex.rxjava3.core.CompletableSource[]);
    Code:
       0: aload_0
       1: invokespecial #1                  // Method io/reactivex/rxjava3/core/Completable."<init>":()V
       4: aload_0
       5: aload_1
       6: putfield      #2                  // Field sources:[Lio/reactivex/rxjava3/core/CompletableSource;
       9: return

  public void subscribeActual(io.reactivex.rxjava3.core.CompletableObserver);
    Code:
       0: new           #3                  // class io/reactivex/rxjava3/disposables/CompositeDisposable
       3: dup
       4: invokespecial #4                  // Method io/reactivex/rxjava3/disposables/CompositeDisposable."<init>":()V
       7: astore_2
       8: new           #5                  // class java/util/concurrent/atomic/AtomicInteger
      11: dup
      12: aload_0
      13: getfield      #2                  // Field sources:[Lio/reactivex/rxjava3/core/CompletableSource;
      16: arraylength
      17: iconst_1
      18: iadd
      19: invokespecial #6                  // Method java/util/concurrent/atomic/AtomicInteger."<init>":(I)V
      22: astore_3
      23: new           #7                  // class io/reactivex/rxjava3/internal/util/AtomicThrowable
      26: dup
      27: invokespecial #8                  // Method io/reactivex/rxjava3/internal/util/AtomicThrowable."<init>":()V
      30: astore        4
      32: aload_2
      33: new           #9                  // class io/reactivex/rxjava3/internal/operators/completable/CompletableMergeArrayDelayError$TryTerminateAndReportDisposable
      36: dup
      37: aload         4
      39: invokespecial #10                 // Method io/reactivex/rxjava3/internal/operators/completable/CompletableMergeArrayDelayError$TryTerminateAndReportDisposable."<init>":(Lio/reactivex/rxjava3/internal/util/AtomicThrowable;)V
      42: invokevirtual #11                 // Method io/reactivex/rxjava3/disposables/CompositeDisposable.add:(Lio/reactivex/rxjava3/disposables/Disposable;)Z
      45: pop
      46: aload_1
      47: aload_2
      48: invokeinterface #12,  2           // InterfaceMethod io/reactivex/rxjava3/core/CompletableObserver.onSubscribe:(Lio/reactivex/rxjava3/disposables/Disposable;)V
      53: aload_0
      54: getfield      #2                  // Field sources:[Lio/reactivex/rxjava3/core/CompletableSource;
      57: astore        5
      59: aload         5
      61: arraylength
      62: istore        6
      64: iconst_0
      65: istore        7
      67: iload         7
      69: iload         6
      71: if_icmpge     146
      74: aload         5
      76: iload         7
      78: aaload
      79: astore        8
      81: aload_2
      82: invokevirtual #13                 // Method io/reactivex/rxjava3/disposables/CompositeDisposable.isDisposed:()Z
      85: ifeq          89
      88: return
      89: aload         8
      91: ifnonnull     121
      94: new           #14                 // class java/lang/NullPointerException
      97: dup
      98: ldc           #15                 // String A completable source is null
     100: invokespecial #16                 // Method java/lang/NullPointerException."<init>":(Ljava/lang/String;)V
     103: astore        9
     105: aload         4
     107: aload         9
     109: invokevirtual #17                 // Method io/reactivex/rxjava3/internal/util/AtomicThrowable.tryAddThrowableOrReport:(Ljava/lang/Throwable;)Z
     112: pop
     113: aload_3
     114: invokevirtual #18                 // Method java/util/concurrent/atomic/AtomicInteger.decrementAndGet:()I
     117: pop
     118: goto          140
     121: aload         8
     123: new           #19                 // class io/reactivex/rxjava3/internal/operators/completable/CompletableMergeArrayDelayError$MergeInnerCompletableObserver
     126: dup
     127: aload_1
     128: aload_2
     129: aload         4
     131: aload_3
     132: invokespecial #20                 // Method io/reactivex/rxjava3/internal/operators/completable/CompletableMergeArrayDelayError$MergeInnerCompletableObserver."<init>":(Lio/reactivex/rxjava3/core/CompletableObserver;Lio/reactivex/rxjava3/disposables/CompositeDisposable;Lio/reactivex/rxjava3/internal/util/AtomicThrowable;Ljava/util/concurrent/atomic/AtomicInteger;)V
     135: invokeinterface #21,  2           // InterfaceMethod io/reactivex/rxjava3/core/CompletableSource.subscribe:(Lio/reactivex/rxjava3/core/CompletableObserver;)V
     140: iinc          7, 1
     143: goto          67
     146: aload_3
     147: invokevirtual #18                 // Method java/util/concurrent/atomic/AtomicInteger.decrementAndGet:()I
     150: ifne          159
     153: aload         4
     155: aload_1
     156: invokevirtual #22                 // Method io/reactivex/rxjava3/internal/util/AtomicThrowable.tryTerminateConsumer:(Lio/reactivex/rxjava3/core/CompletableObserver;)V
     159: return
}
