Compiled from "CompletableTimeout.java"
public final class io.reactivex.rxjava3.internal.operators.completable.CompletableTimeout extends io.reactivex.rxjava3.core.Completable {
  final io.reactivex.rxjava3.core.CompletableSource source;

  final long timeout;

  final java.util.concurrent.TimeUnit unit;

  final io.reactivex.rxjava3.core.Scheduler scheduler;

  final io.reactivex.rxjava3.core.CompletableSource other;

  public io.reactivex.rxjava3.internal.operators.completable.CompletableTimeout(io.reactivex.rxjava3.core.CompletableSource, long, java.util.concurrent.TimeUnit, io.reactivex.rxjava3.core.Scheduler, io.reactivex.rxjava3.core.CompletableSource);
    Code:
       0: aload_0
       1: invokespecial #1                  // Method io/reactivex/rxjava3/core/Completable."<init>":()V
       4: aload_0
       5: aload_1
       6: putfield      #2                  // Field source:Lio/reactivex/rxjava3/core/CompletableSource;
       9: aload_0
      10: lload_2
      11: putfield      #3                  // Field timeout:J
      14: aload_0
      15: aload         4
      17: putfield      #4                  // Field unit:Ljava/util/concurrent/TimeUnit;
      20: aload_0
      21: aload         5
      23: putfield      #5                  // Field scheduler:Lio/reactivex/rxjava3/core/Scheduler;
      26: aload_0
      27: aload         6
      29: putfield      #6                  // Field other:Lio/reactivex/rxjava3/core/CompletableSource;
      32: return

  public void subscribeActual(io.reactivex.rxjava3.core.CompletableObserver);
    Code:
       0: new           #7                  // class io/reactivex/rxjava3/disposables/CompositeDisposable
       3: dup
       4: invokespecial #8                  // Method io/reactivex/rxjava3/disposables/CompositeDisposable."<init>":()V
       7: astore_2
       8: aload_1
       9: aload_2
      10: invokeinterface #9,  2            // InterfaceMethod io/reactivex/rxjava3/core/CompletableObserver.onSubscribe:(Lio/reactivex/rxjava3/disposables/Disposable;)V
      15: new           #10                 // class java/util/concurrent/atomic/AtomicBoolean
      18: dup
      19: invokespecial #11                 // Method java/util/concurrent/atomic/AtomicBoolean."<init>":()V
      22: astore_3
      23: aload_0
      24: getfield      #5                  // Field scheduler:Lio/reactivex/rxjava3/core/Scheduler;
      27: new           #12                 // class io/reactivex/rxjava3/internal/operators/completable/CompletableTimeout$DisposeTask
      30: dup
      31: aload_0
      32: aload_3
      33: aload_2
      34: aload_1
      35: invokespecial #13                 // Method io/reactivex/rxjava3/internal/operators/completable/CompletableTimeout$DisposeTask."<init>":(Lio/reactivex/rxjava3/internal/operators/completable/CompletableTimeout;Ljava/util/concurrent/atomic/AtomicBoolean;Lio/reactivex/rxjava3/disposables/CompositeDisposable;Lio/reactivex/rxjava3/core/CompletableObserver;)V
      38: aload_0
      39: getfield      #3                  // Field timeout:J
      42: aload_0
      43: getfield      #4                  // Field unit:Ljava/util/concurrent/TimeUnit;
      46: invokevirtual #14                 // Method io/reactivex/rxjava3/core/Scheduler.scheduleDirect:(Ljava/lang/Runnable;JLjava/util/concurrent/TimeUnit;)Lio/reactivex/rxjava3/disposables/Disposable;
      49: astore        4
      51: aload_2
      52: aload         4
      54: invokevirtual #15                 // Method io/reactivex/rxjava3/disposables/CompositeDisposable.add:(Lio/reactivex/rxjava3/disposables/Disposable;)Z
      57: pop
      58: aload_0
      59: getfield      #2                  // Field source:Lio/reactivex/rxjava3/core/CompletableSource;
      62: new           #16                 // class io/reactivex/rxjava3/internal/operators/completable/CompletableTimeout$TimeOutObserver
      65: dup
      66: aload_2
      67: aload_3
      68: aload_1
      69: invokespecial #17                 // Method io/reactivex/rxjava3/internal/operators/completable/CompletableTimeout$TimeOutObserver."<init>":(Lio/reactivex/rxjava3/disposables/CompositeDisposable;Ljava/util/concurrent/atomic/AtomicBoolean;Lio/reactivex/rxjava3/core/CompletableObserver;)V
      72: invokeinterface #18,  2           // InterfaceMethod io/reactivex/rxjava3/core/CompletableSource.subscribe:(Lio/reactivex/rxjava3/core/CompletableObserver;)V
      77: return
}
