Compiled from "CompletableResumeNext.java"
public final class io.reactivex.rxjava3.internal.operators.completable.CompletableResumeNext extends io.reactivex.rxjava3.core.Completable {
  final io.reactivex.rxjava3.core.CompletableSource source;

  final io.reactivex.rxjava3.functions.Function<? super java.lang.Throwable, ? extends io.reactivex.rxjava3.core.CompletableSource> errorMapper;

  public io.reactivex.rxjava3.internal.operators.completable.CompletableResumeNext(io.reactivex.rxjava3.core.CompletableSource, io.reactivex.rxjava3.functions.Function<? super java.lang.Throwable, ? extends io.reactivex.rxjava3.core.CompletableSource>);
    Code:
       0: aload_0
       1: invokespecial #1                  // Method io/reactivex/rxjava3/core/Completable."<init>":()V
       4: aload_0
       5: aload_1
       6: putfield      #2                  // Field source:Lio/reactivex/rxjava3/core/CompletableSource;
       9: aload_0
      10: aload_2
      11: putfield      #3                  // Field errorMapper:Lio/reactivex/rxjava3/functions/Function;
      14: return

  protected void subscribeActual(io.reactivex.rxjava3.core.CompletableObserver);
    Code:
       0: new           #4                  // class io/reactivex/rxjava3/internal/operators/completable/CompletableResumeNext$ResumeNextObserver
       3: dup
       4: aload_1
       5: aload_0
       6: getfield      #3                  // Field errorMapper:Lio/reactivex/rxjava3/functions/Function;
       9: invokespecial #5                  // Method io/reactivex/rxjava3/internal/operators/completable/CompletableResumeNext$ResumeNextObserver."<init>":(Lio/reactivex/rxjava3/core/CompletableObserver;Lio/reactivex/rxjava3/functions/Function;)V
      12: astore_2
      13: aload_1
      14: aload_2
      15: invokeinterface #6,  2            // InterfaceMethod io/reactivex/rxjava3/core/CompletableObserver.onSubscribe:(Lio/reactivex/rxjava3/disposables/Disposable;)V
      20: aload_0
      21: getfield      #2                  // Field source:Lio/reactivex/rxjava3/core/CompletableSource;
      24: aload_2
      25: invokeinterface #7,  2            // InterfaceMethod io/reactivex/rxjava3/core/CompletableSource.subscribe:(Lio/reactivex/rxjava3/core/CompletableObserver;)V
      30: return
}
