Compiled from "CompletableEmpty.java"
public final class io.reactivex.rxjava3.internal.operators.completable.CompletableEmpty extends io.reactivex.rxjava3.core.Completable {
  public static final io.reactivex.rxjava3.core.Completable INSTANCE;

  private io.reactivex.rxjava3.internal.operators.completable.CompletableEmpty();
    Code:
       0: aload_0
       1: invokespecial #1                  // Method io/reactivex/rxjava3/core/Completable."<init>":()V
       4: return

  public void subscribeActual(io.reactivex.rxjava3.core.CompletableObserver);
    Code:
       0: aload_1
       1: invokestatic  #2                  // Method io/reactivex/rxjava3/internal/disposables/EmptyDisposable.complete:(Lio/reactivex/rxjava3/core/CompletableObserver;)V
       4: return

  static {};
    Code:
       0: new           #3                  // class io/reactivex/rxjava3/internal/operators/completable/CompletableEmpty
       3: dup
       4: invokespecial #4                  // Method "<init>":()V
       7: putstatic     #5                  // Field INSTANCE:Lio/reactivex/rxjava3/core/Completable;
      10: return
}
