Compiled from "CompletableTimeout.java"
final class io.reactivex.rxjava3.internal.operators.completable.CompletableTimeout$DisposeTask implements java.lang.Runnable {
  private final java.util.concurrent.atomic.AtomicBoolean once;

  final io.reactivex.rxjava3.disposables.CompositeDisposable set;

  final io.reactivex.rxjava3.core.CompletableObserver downstream;

  final io.reactivex.rxjava3.internal.operators.completable.CompletableTimeout this$0;

  io.reactivex.rxjava3.internal.operators.completable.CompletableTimeout$DisposeTask(io.reactivex.rxjava3.internal.operators.completable.CompletableTimeout, java.util.concurrent.atomic.AtomicBoolean, io.reactivex.rxjava3.disposables.CompositeDisposable, io.reactivex.rxjava3.core.CompletableObserver);
    Code:
       0: aload_0
       1: aload_1
       2: putfield      #1                  // Field this$0:Lio/reactivex/rxjava3/internal/operators/completable/CompletableTimeout;
       5: aload_0
       6: invokespecial #2                  // Method java/lang/Object."<init>":()V
       9: aload_0
      10: aload_2
      11: putfield      #3                  // Field once:Ljava/util/concurrent/atomic/AtomicBoolean;
      14: aload_0
      15: aload_3
      16: putfield      #4                  // Field set:Lio/reactivex/rxjava3/disposables/CompositeDisposable;
      19: aload_0
      20: aload         4
      22: putfield      #5                  // Field downstream:Lio/reactivex/rxjava3/core/CompletableObserver;
      25: return

  public void run();
    Code:
       0: aload_0
       1: getfield      #3                  // Field once:Ljava/util/concurrent/atomic/AtomicBoolean;
       4: iconst_0
       5: iconst_1
       6: invokevirtual #6                  // Method java/util/concurrent/atomic/AtomicBoolean.compareAndSet:(ZZ)Z
       9: ifeq          85
      12: aload_0
      13: getfield      #4                  // Field set:Lio/reactivex/rxjava3/disposables/CompositeDisposable;
      16: invokevirtual #7                  // Method io/reactivex/rxjava3/disposables/CompositeDisposable.clear:()V
      19: aload_0
      20: getfield      #1                  // Field this$0:Lio/reactivex/rxjava3/internal/operators/completable/CompletableTimeout;
      23: getfield      #8                  // Field io/reactivex/rxjava3/internal/operators/completable/CompletableTimeout.other:Lio/reactivex/rxjava3/core/CompletableSource;
      26: ifnonnull     65
      29: aload_0
      30: getfield      #5                  // Field downstream:Lio/reactivex/rxjava3/core/CompletableObserver;
      33: new           #9                  // class java/util/concurrent/TimeoutException
      36: dup
      37: aload_0
      38: getfield      #1                  // Field this$0:Lio/reactivex/rxjava3/internal/operators/completable/CompletableTimeout;
      41: getfield      #10                 // Field io/reactivex/rxjava3/internal/operators/completable/CompletableTimeout.timeout:J
      44: aload_0
      45: getfield      #1                  // Field this$0:Lio/reactivex/rxjava3/internal/operators/completable/CompletableTimeout;
      48: getfield      #11                 // Field io/reactivex/rxjava3/internal/operators/completable/CompletableTimeout.unit:Ljava/util/concurrent/TimeUnit;
      51: invokestatic  #12                 // Method io/reactivex/rxjava3/internal/util/ExceptionHelper.timeoutMessage:(JLjava/util/concurrent/TimeUnit;)Ljava/lang/String;
      54: invokespecial #13                 // Method java/util/concurrent/TimeoutException."<init>":(Ljava/lang/String;)V
      57: invokeinterface #14,  2           // InterfaceMethod io/reactivex/rxjava3/core/CompletableObserver.onError:(Ljava/lang/Throwable;)V
      62: goto          85
      65: aload_0
      66: getfield      #1                  // Field this$0:Lio/reactivex/rxjava3/internal/operators/completable/CompletableTimeout;
      69: getfield      #8                  // Field io/reactivex/rxjava3/internal/operators/completable/CompletableTimeout.other:Lio/reactivex/rxjava3/core/CompletableSource;
      72: new           #15                 // class io/reactivex/rxjava3/internal/operators/completable/CompletableTimeout$DisposeTask$DisposeObserver
      75: dup
      76: aload_0
      77: invokespecial #16                 // Method io/reactivex/rxjava3/internal/operators/completable/CompletableTimeout$DisposeTask$DisposeObserver."<init>":(Lio/reactivex/rxjava3/internal/operators/completable/CompletableTimeout$DisposeTask;)V
      80: invokeinterface #17,  2           // InterfaceMethod io/reactivex/rxjava3/core/CompletableSource.subscribe:(Lio/reactivex/rxjava3/core/CompletableObserver;)V
      85: return
}
