Compiled from "CompletableConcatIterable.java"
final class io.reactivex.rxjava3.internal.operators.completable.CompletableConcatIterable$ConcatInnerObserver extends java.util.concurrent.atomic.AtomicInteger implements io.reactivex.rxjava3.core.CompletableObserver {
  private static final long serialVersionUID;

  final io.reactivex.rxjava3.core.CompletableObserver downstream;

  final java.util.Iterator<? extends io.reactivex.rxjava3.core.CompletableSource> sources;

  final io.reactivex.rxjava3.internal.disposables.SequentialDisposable sd;

  io.reactivex.rxjava3.internal.operators.completable.CompletableConcatIterable$ConcatInnerObserver(io.reactivex.rxjava3.core.CompletableObserver, java.util.Iterator<? extends io.reactivex.rxjava3.core.CompletableSource>);
    Code:
       0: aload_0
       1: invokespecial #1                  // Method java/util/concurrent/atomic/AtomicInteger."<init>":()V
       4: aload_0
       5: aload_1
       6: putfield      #2                  // Field downstream:Lio/reactivex/rxjava3/core/CompletableObserver;
       9: aload_0
      10: aload_2
      11: putfield      #3                  // Field sources:Ljava/util/Iterator;
      14: aload_0
      15: new           #4                  // class io/reactivex/rxjava3/internal/disposables/SequentialDisposable
      18: dup
      19: invokespecial #5                  // Method io/reactivex/rxjava3/internal/disposables/SequentialDisposable."<init>":()V
      22: putfield      #6                  // Field sd:Lio/reactivex/rxjava3/internal/disposables/SequentialDisposable;
      25: return

  public void onSubscribe(io.reactivex.rxjava3.disposables.Disposable);
    Code:
       0: aload_0
       1: getfield      #6                  // Field sd:Lio/reactivex/rxjava3/internal/disposables/SequentialDisposable;
       4: aload_1
       5: invokevirtual #7                  // Method io/reactivex/rxjava3/internal/disposables/SequentialDisposable.replace:(Lio/reactivex/rxjava3/disposables/Disposable;)Z
       8: pop
       9: return

  public void onError(java.lang.Throwable);
    Code:
       0: aload_0
       1: getfield      #2                  // Field downstream:Lio/reactivex/rxjava3/core/CompletableObserver;
       4: aload_1
       5: invokeinterface #8,  2            // InterfaceMethod io/reactivex/rxjava3/core/CompletableObserver.onError:(Ljava/lang/Throwable;)V
      10: return

  public void onComplete();
    Code:
       0: aload_0
       1: invokevirtual #9                  // Method next:()V
       4: return

  void next();
    Code:
       0: aload_0
       1: getfield      #6                  // Field sd:Lio/reactivex/rxjava3/internal/disposables/SequentialDisposable;
       4: invokevirtual #10                 // Method io/reactivex/rxjava3/internal/disposables/SequentialDisposable.isDisposed:()Z
       7: ifeq          11
      10: return
      11: aload_0
      12: invokevirtual #11                 // Method getAndIncrement:()I
      15: ifeq          19
      18: return
      19: aload_0
      20: getfield      #3                  // Field sources:Ljava/util/Iterator;
      23: astore_1
      24: aload_0
      25: getfield      #6                  // Field sd:Lio/reactivex/rxjava3/internal/disposables/SequentialDisposable;
      28: invokevirtual #10                 // Method io/reactivex/rxjava3/internal/disposables/SequentialDisposable.isDisposed:()Z
      31: ifeq          35
      34: return
      35: aload_1
      36: invokeinterface #12,  1           // InterfaceMethod java/util/Iterator.hasNext:()Z
      41: istore_2
      42: goto          61
      45: astore_3
      46: aload_3
      47: invokestatic  #14                 // Method io/reactivex/rxjava3/exceptions/Exceptions.throwIfFatal:(Ljava/lang/Throwable;)V
      50: aload_0
      51: getfield      #2                  // Field downstream:Lio/reactivex/rxjava3/core/CompletableObserver;
      54: aload_3
      55: invokeinterface #8,  2            // InterfaceMethod io/reactivex/rxjava3/core/CompletableObserver.onError:(Ljava/lang/Throwable;)V
      60: return
      61: iload_2
      62: ifne          75
      65: aload_0
      66: getfield      #2                  // Field downstream:Lio/reactivex/rxjava3/core/CompletableObserver;
      69: invokeinterface #15,  1           // InterfaceMethod io/reactivex/rxjava3/core/CompletableObserver.onComplete:()V
      74: return
      75: aload_1
      76: invokeinterface #16,  1           // InterfaceMethod java/util/Iterator.next:()Ljava/lang/Object;
      81: ldc           #17                 // String The CompletableSource returned is null
      83: invokestatic  #18                 // Method java/util/Objects.requireNonNull:(Ljava/lang/Object;Ljava/lang/String;)Ljava/lang/Object;
      86: checkcast     #19                 // class io/reactivex/rxjava3/core/CompletableSource
      89: astore_3
      90: goto          112
      93: astore        4
      95: aload         4
      97: invokestatic  #14                 // Method io/reactivex/rxjava3/exceptions/Exceptions.throwIfFatal:(Ljava/lang/Throwable;)V
     100: aload_0
     101: getfield      #2                  // Field downstream:Lio/reactivex/rxjava3/core/CompletableObserver;
     104: aload         4
     106: invokeinterface #8,  2            // InterfaceMethod io/reactivex/rxjava3/core/CompletableObserver.onError:(Ljava/lang/Throwable;)V
     111: return
     112: aload_3
     113: aload_0
     114: invokeinterface #20,  2           // InterfaceMethod io/reactivex/rxjava3/core/CompletableSource.subscribe:(Lio/reactivex/rxjava3/core/CompletableObserver;)V
     119: aload_0
     120: invokevirtual #21                 // Method decrementAndGet:()I
     123: ifne          24
     126: return
    Exception table:
       from    to  target type
          35    42    45   Class java/lang/Throwable
          75    90    93   Class java/lang/Throwable
}
