Compiled from "CompletableToSingle.java"
public final class io.reactivex.rxjava3.internal.operators.completable.CompletableToSingle<T> extends io.reactivex.rxjava3.core.Single<T> {
  final io.reactivex.rxjava3.core.CompletableSource source;

  final io.reactivex.rxjava3.functions.Supplier<? extends T> completionValueSupplier;

  final T completionValue;

  public io.reactivex.rxjava3.internal.operators.completable.CompletableToSingle(io.reactivex.rxjava3.core.CompletableSource, io.reactivex.rxjava3.functions.Supplier<? extends T>, T);
    Code:
       0: aload_0
       1: invokespecial #1                  // Method io/reactivex/rxjava3/core/Single."<init>":()V
       4: aload_0
       5: aload_1
       6: putfield      #2                  // Field source:Lio/reactivex/rxjava3/core/CompletableSource;
       9: aload_0
      10: aload_3
      11: putfield      #3                  // Field completionValue:Ljava/lang/Object;
      14: aload_0
      15: aload_2
      16: putfield      #4                  // Field completionValueSupplier:Lio/reactivex/rxjava3/functions/Supplier;
      19: return

  protected void subscribeActual(io.reactivex.rxjava3.core.SingleObserver<? super T>);
    Code:
       0: aload_0
       1: getfield      #2                  // Field source:Lio/reactivex/rxjava3/core/CompletableSource;
       4: new           #5                  // class io/reactivex/rxjava3/internal/operators/completable/CompletableToSingle$ToSingle
       7: dup
       8: aload_0
       9: aload_1
      10: invokespecial #6                  // Method io/reactivex/rxjava3/internal/operators/completable/CompletableToSingle$ToSingle."<init>":(Lio/reactivex/rxjava3/internal/operators/completable/CompletableToSingle;Lio/reactivex/rxjava3/core/SingleObserver;)V
      13: invokeinterface #7,  2            // InterfaceMethod io/reactivex/rxjava3/core/CompletableSource.subscribe:(Lio/reactivex/rxjava3/core/CompletableObserver;)V
      18: return
}
