Compiled from "CompletablePeek.java"
public final class io.reactivex.rxjava3.internal.operators.completable.CompletablePeek extends io.reactivex.rxjava3.core.Completable {
  final io.reactivex.rxjava3.core.CompletableSource source;

  final io.reactivex.rxjava3.functions.Consumer<? super io.reactivex.rxjava3.disposables.Disposable> onSubscribe;

  final io.reactivex.rxjava3.functions.Consumer<? super java.lang.Throwable> onError;

  final io.reactivex.rxjava3.functions.Action onComplete;

  final io.reactivex.rxjava3.functions.Action onTerminate;

  final io.reactivex.rxjava3.functions.Action onAfterTerminate;

  final io.reactivex.rxjava3.functions.Action onDispose;

  public io.reactivex.rxjava3.internal.operators.completable.CompletablePeek(io.reactivex.rxjava3.core.CompletableSource, io.reactivex.rxjava3.functions.Consumer<? super io.reactivex.rxjava3.disposables.Disposable>, io.reactivex.rxjava3.functions.Consumer<? super java.lang.Throwable>, io.reactivex.rxjava3.functions.Action, io.reactivex.rxjava3.functions.Action, io.reactivex.rxjava3.functions.Action, io.reactivex.rxjava3.functions.Action);
    Code:
       0: aload_0
       1: invokespecial #1                  // Method io/reactivex/rxjava3/core/Completable."<init>":()V
       4: aload_0
       5: aload_1
       6: putfield      #2                  // Field source:Lio/reactivex/rxjava3/core/CompletableSource;
       9: aload_0
      10: aload_2
      11: putfield      #3                  // Field onSubscribe:Lio/reactivex/rxjava3/functions/Consumer;
      14: aload_0
      15: aload_3
      16: putfield      #4                  // Field onError:Lio/reactivex/rxjava3/functions/Consumer;
      19: aload_0
      20: aload         4
      22: putfield      #5                  // Field onComplete:Lio/reactivex/rxjava3/functions/Action;
      25: aload_0
      26: aload         5
      28: putfield      #6                  // Field onTerminate:Lio/reactivex/rxjava3/functions/Action;
      31: aload_0
      32: aload         6
      34: putfield      #7                  // Field onAfterTerminate:Lio/reactivex/rxjava3/functions/Action;
      37: aload_0
      38: aload         7
      40: putfield      #8                  // Field onDispose:Lio/reactivex/rxjava3/functions/Action;
      43: return

  protected void subscribeActual(io.reactivex.rxjava3.core.CompletableObserver);
    Code:
       0: aload_0
       1: getfield      #2                  // Field source:Lio/reactivex/rxjava3/core/CompletableSource;
       4: new           #9                  // class io/reactivex/rxjava3/internal/operators/completable/CompletablePeek$CompletableObserverImplementation
       7: dup
       8: aload_0
       9: aload_1
      10: invokespecial #10                 // Method io/reactivex/rxjava3/internal/operators/completable/CompletablePeek$CompletableObserverImplementation."<init>":(Lio/reactivex/rxjava3/internal/operators/completable/CompletablePeek;Lio/reactivex/rxjava3/core/CompletableObserver;)V
      13: invokeinterface #11,  2           // InterfaceMethod io/reactivex/rxjava3/core/CompletableSource.subscribe:(Lio/reactivex/rxjava3/core/CompletableObserver;)V
      18: return
}
