Compiled from "CompletableTimeout.java"
final class io.reactivex.rxjava3.internal.operators.completable.CompletableTimeout$DisposeTask$DisposeObserver implements io.reactivex.rxjava3.core.CompletableObserver {
  final io.reactivex.rxjava3.internal.operators.completable.CompletableTimeout$DisposeTask this$1;

  io.reactivex.rxjava3.internal.operators.completable.CompletableTimeout$DisposeTask$DisposeObserver(io.reactivex.rxjava3.internal.operators.completable.CompletableTimeout$DisposeTask);
    Code:
       0: aload_0
       1: aload_1
       2: putfield      #1                  // Field this$1:Lio/reactivex/rxjava3/internal/operators/completable/CompletableTimeout$DisposeTask;
       5: aload_0
       6: invokespecial #2                  // Method java/lang/Object."<init>":()V
       9: return

  public void onSubscribe(io.reactivex.rxjava3.disposables.Disposable);
    Code:
       0: aload_0
       1: getfield      #1                  // Field this$1:Lio/reactivex/rxjava3/internal/operators/completable/CompletableTimeout$DisposeTask;
       4: getfield      #3                  // Field io/reactivex/rxjava3/internal/operators/completable/CompletableTimeout$DisposeTask.set:Lio/reactivex/rxjava3/disposables/CompositeDisposable;
       7: aload_1
       8: invokevirtual #4                  // Method io/reactivex/rxjava3/disposables/CompositeDisposable.add:(Lio/reactivex/rxjava3/disposables/Disposable;)Z
      11: pop
      12: return

  public void onError(java.lang.Throwable);
    Code:
       0: aload_0
       1: getfield      #1                  // Field this$1:Lio/reactivex/rxjava3/internal/operators/completable/CompletableTimeout$DisposeTask;
       4: getfield      #3                  // Field io/reactivex/rxjava3/internal/operators/completable/CompletableTimeout$DisposeTask.set:Lio/reactivex/rxjava3/disposables/CompositeDisposable;
       7: invokevirtual #5                  // Method io/reactivex/rxjava3/disposables/CompositeDisposable.dispose:()V
      10: aload_0
      11: getfield      #1                  // Field this$1:Lio/reactivex/rxjava3/internal/operators/completable/CompletableTimeout$DisposeTask;
      14: getfield      #6                  // Field io/reactivex/rxjava3/internal/operators/completable/CompletableTimeout$DisposeTask.downstream:Lio/reactivex/rxjava3/core/CompletableObserver;
      17: aload_1
      18: invokeinterface #7,  2            // InterfaceMethod io/reactivex/rxjava3/core/CompletableObserver.onError:(Ljava/lang/Throwable;)V
      23: return

  public void onComplete();
    Code:
       0: aload_0
       1: getfield      #1                  // Field this$1:Lio/reactivex/rxjava3/internal/operators/completable/CompletableTimeout$DisposeTask;
       4: getfield      #3                  // Field io/reactivex/rxjava3/internal/operators/completable/CompletableTimeout$DisposeTask.set:Lio/reactivex/rxjava3/disposables/CompositeDisposable;
       7: invokevirtual #5                  // Method io/reactivex/rxjava3/disposables/CompositeDisposable.dispose:()V
      10: aload_0
      11: getfield      #1                  // Field this$1:Lio/reactivex/rxjava3/internal/operators/completable/CompletableTimeout$DisposeTask;
      14: getfield      #6                  // Field io/reactivex/rxjava3/internal/operators/completable/CompletableTimeout$DisposeTask.downstream:Lio/reactivex/rxjava3/core/CompletableObserver;
      17: invokeinterface #8,  1            // InterfaceMethod io/reactivex/rxjava3/core/CompletableObserver.onComplete:()V
      22: return
}
