Compiled from "CompletableTakeUntilCompletable.java"
public final class io.reactivex.rxjava3.internal.operators.completable.CompletableTakeUntilCompletable extends io.reactivex.rxjava3.core.Completable {
  final io.reactivex.rxjava3.core.Completable source;

  final io.reactivex.rxjava3.core.CompletableSource other;

  public io.reactivex.rxjava3.internal.operators.completable.CompletableTakeUntilCompletable(io.reactivex.rxjava3.core.Completable, io.reactivex.rxjava3.core.CompletableSource);
    Code:
       0: aload_0
       1: invokespecial #1                  // Method io/reactivex/rxjava3/core/Completable."<init>":()V
       4: aload_0
       5: aload_1
       6: putfield      #2                  // Field source:Lio/reactivex/rxjava3/core/Completable;
       9: aload_0
      10: aload_2
      11: putfield      #3                  // Field other:Lio/reactivex/rxjava3/core/CompletableSource;
      14: return

  protected void subscribeActual(io.reactivex.rxjava3.core.CompletableObserver);
    Code:
       0: new           #4                  // class io/reactivex/rxjava3/internal/operators/completable/CompletableTakeUntilCompletable$TakeUntilMainObserver
       3: dup
       4: aload_1
       5: invokespecial #5                  // Method io/reactivex/rxjava3/internal/operators/completable/CompletableTakeUntilCompletable$TakeUntilMainObserver."<init>":(Lio/reactivex/rxjava3/core/CompletableObserver;)V
       8: astore_2
       9: aload_1
      10: aload_2
      11: invokeinterface #6,  2            // InterfaceMethod io/reactivex/rxjava3/core/CompletableObserver.onSubscribe:(Lio/reactivex/rxjava3/disposables/Disposable;)V
      16: aload_0
      17: getfield      #3                  // Field other:Lio/reactivex/rxjava3/core/CompletableSource;
      20: aload_2
      21: getfield      #7                  // Field io/reactivex/rxjava3/internal/operators/completable/CompletableTakeUntilCompletable$TakeUntilMainObserver.other:Lio/reactivex/rxjava3/internal/operators/completable/CompletableTakeUntilCompletable$TakeUntilMainObserver$OtherObserver;
      24: invokeinterface #8,  2            // InterfaceMethod io/reactivex/rxjava3/core/CompletableSource.subscribe:(Lio/reactivex/rxjava3/core/CompletableObserver;)V
      29: aload_0
      30: getfield      #2                  // Field source:Lio/reactivex/rxjava3/core/Completable;
      33: aload_2
      34: invokevirtual #9                  // Method io/reactivex/rxjava3/core/Completable.subscribe:(Lio/reactivex/rxjava3/core/CompletableObserver;)V
      37: return
}
