Compiled from "CompletableLift.java"
public final class io.reactivex.rxjava3.internal.operators.completable.CompletableLift extends io.reactivex.rxjava3.core.Completable {
  final io.reactivex.rxjava3.core.CompletableSource source;

  final io.reactivex.rxjava3.core.CompletableOperator onLift;

  public io.reactivex.rxjava3.internal.operators.completable.CompletableLift(io.reactivex.rxjava3.core.CompletableSource, io.reactivex.rxjava3.core.CompletableOperator);
    Code:
       0: aload_0
       1: invokespecial #1                  // Method io/reactivex/rxjava3/core/Completable."<init>":()V
       4: aload_0
       5: aload_1
       6: putfield      #2                  // Field source:Lio/reactivex/rxjava3/core/CompletableSource;
       9: aload_0
      10: aload_2
      11: putfield      #3                  // Field onLift:Lio/reactivex/rxjava3/core/CompletableOperator;
      14: return

  protected void subscribeActual(io.reactivex.rxjava3.core.CompletableObserver);
    Code:
       0: aload_0
       1: getfield      #3                  // Field onLift:Lio/reactivex/rxjava3/core/CompletableOperator;
       4: aload_1
       5: invokeinterface #4,  2            // InterfaceMethod io/reactivex/rxjava3/core/CompletableOperator.apply:(Lio/reactivex/rxjava3/core/CompletableObserver;)Lio/reactivex/rxjava3/core/CompletableObserver;
      10: astore_2
      11: aload_0
      12: getfield      #2                  // Field source:Lio/reactivex/rxjava3/core/CompletableSource;
      15: aload_2
      16: invokeinterface #5,  2            // InterfaceMethod io/reactivex/rxjava3/core/CompletableSource.subscribe:(Lio/reactivex/rxjava3/core/CompletableObserver;)V
      21: goto          36
      24: astore_2
      25: aload_2
      26: athrow
      27: astore_2
      28: aload_2
      29: invokestatic  #8                  // Method io/reactivex/rxjava3/exceptions/Exceptions.throwIfFatal:(Ljava/lang/Throwable;)V
      32: aload_2
      33: invokestatic  #9                  // Method io/reactivex/rxjava3/plugins/RxJavaPlugins.onError:(Ljava/lang/Throwable;)V
      36: return
    Exception table:
       from    to  target type
           0    21    24   Class java/lang/NullPointerException
           0    21    27   Class java/lang/Throwable
}
