Compiled from "CompletableMaterialize.java"
public final class io.reactivex.rxjava3.internal.operators.completable.CompletableMaterialize<T> extends io.reactivex.rxjava3.core.Single<io.reactivex.rxjava3.core.Notification<T>> {
  final io.reactivex.rxjava3.core.Completable source;

  public io.reactivex.rxjava3.internal.operators.completable.CompletableMaterialize(io.reactivex.rxjava3.core.Completable);
    Code:
       0: aload_0
       1: invokespecial #1                  // Method io/reactivex/rxjava3/core/Single."<init>":()V
       4: aload_0
       5: aload_1
       6: putfield      #2                  // Field source:Lio/reactivex/rxjava3/core/Completable;
       9: return

  protected void subscribeActual(io.reactivex.rxjava3.core.SingleObserver<? super io.reactivex.rxjava3.core.Notification<T>>);
    Code:
       0: aload_0
       1: getfield      #2                  // Field source:Lio/reactivex/rxjava3/core/Completable;
       4: new           #3                  // class io/reactivex/rxjava3/internal/operators/mixed/MaterializeSingleObserver
       7: dup
       8: aload_1
       9: invokespecial #4                  // Method io/reactivex/rxjava3/internal/operators/mixed/MaterializeSingleObserver."<init>":(Lio/reactivex/rxjava3/core/SingleObserver;)V
      12: invokevirtual #5                  // Method io/reactivex/rxjava3/core/Completable.subscribe:(Lio/reactivex/rxjava3/core/CompletableObserver;)V
      15: return
}
