Compiled from "Log4j2Logger.java"
public class org.apache.dubbo.common.logger.log4j2.Log4j2Logger implements org.apache.dubbo.common.logger.Logger {
  private final org.apache.logging.log4j.Logger logger;

  public org.apache.dubbo.common.logger.log4j2.Log4j2Logger(org.apache.logging.log4j.Logger);
    Code:
       0: aload_0
       1: invokespecial #1                  // Method java/lang/Object."<init>":()V
       4: aload_0
       5: aload_1
       6: putfield      #2                  // Field logger:Lorg/apache/logging/log4j/Logger;
       9: return

  public void trace(java.lang.String);
    Code:
       0: aload_0
       1: getfield      #2                  // Field logger:Lorg/apache/logging/log4j/Logger;
       4: aload_1
       5: invokeinterface #3,  2            // InterfaceMethod org/apache/logging/log4j/Logger.trace:(Ljava/lang/String;)V
      10: return

  public void trace(java.lang.Throwable);
    Code:
       0: aload_0
       1: getfield      #2                  // Field logger:Lorg/apache/logging/log4j/Logger;
       4: aload_1
       5: ifnonnull     12
       8: aconst_null
       9: goto          16
      12: aload_1
      13: invokevirtual #4                  // Method java/lang/Throwable.getMessage:()Ljava/lang/String;
      16: aload_1
      17: invokeinterface #5,  3            // InterfaceMethod org/apache/logging/log4j/Logger.trace:(Ljava/lang/String;Ljava/lang/Throwable;)V
      22: return

  public void trace(java.lang.String, java.lang.Throwable);
    Code:
       0: aload_0
       1: getfield      #2                  // Field logger:Lorg/apache/logging/log4j/Logger;
       4: aload_1
       5: aload_2
       6: invokeinterface #5,  3            // InterfaceMethod org/apache/logging/log4j/Logger.trace:(Ljava/lang/String;Ljava/lang/Throwable;)V
      11: return

  public void debug(java.lang.String);
    Code:
       0: aload_0
       1: getfield      #2                  // Field logger:Lorg/apache/logging/log4j/Logger;
       4: aload_1
       5: invokeinterface #6,  2            // InterfaceMethod org/apache/logging/log4j/Logger.debug:(Ljava/lang/String;)V
      10: return

  public void debug(java.lang.Throwable);
    Code:
       0: aload_0
       1: getfield      #2                  // Field logger:Lorg/apache/logging/log4j/Logger;
       4: aload_1
       5: ifnonnull     12
       8: aconst_null
       9: goto          16
      12: aload_1
      13: invokevirtual #4                  // Method java/lang/Throwable.getMessage:()Ljava/lang/String;
      16: aload_1
      17: invokeinterface #7,  3            // InterfaceMethod org/apache/logging/log4j/Logger.debug:(Ljava/lang/String;Ljava/lang/Throwable;)V
      22: return

  public void debug(java.lang.String, java.lang.Throwable);
    Code:
       0: aload_0
       1: getfield      #2                  // Field logger:Lorg/apache/logging/log4j/Logger;
       4: aload_1
       5: aload_2
       6: invokeinterface #7,  3            // InterfaceMethod org/apache/logging/log4j/Logger.debug:(Ljava/lang/String;Ljava/lang/Throwable;)V
      11: return

  public void info(java.lang.String);
    Code:
       0: aload_0
       1: getfield      #2                  // Field logger:Lorg/apache/logging/log4j/Logger;
       4: aload_1
       5: invokeinterface #8,  2            // InterfaceMethod org/apache/logging/log4j/Logger.info:(Ljava/lang/String;)V
      10: return

  public void info(java.lang.Throwable);
    Code:
       0: aload_0
       1: getfield      #2                  // Field logger:Lorg/apache/logging/log4j/Logger;
       4: aload_1
       5: ifnonnull     12
       8: aconst_null
       9: goto          16
      12: aload_1
      13: invokevirtual #4                  // Method java/lang/Throwable.getMessage:()Ljava/lang/String;
      16: aload_1
      17: invokeinterface #9,  3            // InterfaceMethod org/apache/logging/log4j/Logger.info:(Ljava/lang/String;Ljava/lang/Throwable;)V
      22: return

  public void info(java.lang.String, java.lang.Throwable);
    Code:
       0: aload_0
       1: getfield      #2                  // Field logger:Lorg/apache/logging/log4j/Logger;
       4: aload_1
       5: aload_2
       6: invokeinterface #9,  3            // InterfaceMethod org/apache/logging/log4j/Logger.info:(Ljava/lang/String;Ljava/lang/Throwable;)V
      11: return

  public void warn(java.lang.String);
    Code:
       0: aload_0
       1: getfield      #2                  // Field logger:Lorg/apache/logging/log4j/Logger;
       4: aload_1
       5: invokeinterface #10,  2           // InterfaceMethod org/apache/logging/log4j/Logger.warn:(Ljava/lang/String;)V
      10: return

  public void warn(java.lang.Throwable);
    Code:
       0: aload_0
       1: getfield      #2                  // Field logger:Lorg/apache/logging/log4j/Logger;
       4: aload_1
       5: ifnonnull     12
       8: aconst_null
       9: goto          16
      12: aload_1
      13: invokevirtual #4                  // Method java/lang/Throwable.getMessage:()Ljava/lang/String;
      16: aload_1
      17: invokeinterface #11,  3           // InterfaceMethod org/apache/logging/log4j/Logger.warn:(Ljava/lang/String;Ljava/lang/Throwable;)V
      22: return

  public void warn(java.lang.String, java.lang.Throwable);
    Code:
       0: aload_0
       1: getfield      #2                  // Field logger:Lorg/apache/logging/log4j/Logger;
       4: aload_1
       5: aload_2
       6: invokeinterface #11,  3           // InterfaceMethod org/apache/logging/log4j/Logger.warn:(Ljava/lang/String;Ljava/lang/Throwable;)V
      11: return

  public void error(java.lang.String);
    Code:
       0: aload_0
       1: getfield      #2                  // Field logger:Lorg/apache/logging/log4j/Logger;
       4: aload_1
       5: invokeinterface #12,  2           // InterfaceMethod org/apache/logging/log4j/Logger.error:(Ljava/lang/String;)V
      10: return

  public void error(java.lang.Throwable);
    Code:
       0: aload_0
       1: getfield      #2                  // Field logger:Lorg/apache/logging/log4j/Logger;
       4: aload_1
       5: ifnonnull     12
       8: aconst_null
       9: goto          16
      12: aload_1
      13: invokevirtual #4                  // Method java/lang/Throwable.getMessage:()Ljava/lang/String;
      16: aload_1
      17: invokeinterface #13,  3           // InterfaceMethod org/apache/logging/log4j/Logger.error:(Ljava/lang/String;Ljava/lang/Throwable;)V
      22: return

  public void error(java.lang.String, java.lang.Throwable);
    Code:
       0: aload_0
       1: getfield      #2                  // Field logger:Lorg/apache/logging/log4j/Logger;
       4: aload_1
       5: aload_2
       6: invokeinterface #13,  3           // InterfaceMethod org/apache/logging/log4j/Logger.error:(Ljava/lang/String;Ljava/lang/Throwable;)V
      11: return

  public boolean isTraceEnabled();
    Code:
       0: aload_0
       1: getfield      #2                  // Field logger:Lorg/apache/logging/log4j/Logger;
       4: invokeinterface #14,  1           // InterfaceMethod org/apache/logging/log4j/Logger.isTraceEnabled:()Z
       9: ireturn

  public boolean isDebugEnabled();
    Code:
       0: aload_0
       1: getfield      #2                  // Field logger:Lorg/apache/logging/log4j/Logger;
       4: invokeinterface #15,  1           // InterfaceMethod org/apache/logging/log4j/Logger.isDebugEnabled:()Z
       9: ireturn

  public boolean isInfoEnabled();
    Code:
       0: aload_0
       1: getfield      #2                  // Field logger:Lorg/apache/logging/log4j/Logger;
       4: invokeinterface #16,  1           // InterfaceMethod org/apache/logging/log4j/Logger.isInfoEnabled:()Z
       9: ireturn

  public boolean isWarnEnabled();
    Code:
       0: aload_0
       1: getfield      #2                  // Field logger:Lorg/apache/logging/log4j/Logger;
       4: invokeinterface #17,  1           // InterfaceMethod org/apache/logging/log4j/Logger.isWarnEnabled:()Z
       9: ireturn

  public boolean isErrorEnabled();
    Code:
       0: aload_0
       1: getfield      #2                  // Field logger:Lorg/apache/logging/log4j/Logger;
       4: invokeinterface #18,  1           // InterfaceMethod org/apache/logging/log4j/Logger.isErrorEnabled:()Z
       9: ireturn
}
