Compiled from "Log4j2LoggerAdapter.java"
public class org.apache.dubbo.common.logger.log4j2.Log4j2LoggerAdapter implements org.apache.dubbo.common.logger.LoggerAdapter {
  public static final java.lang.String NAME;

  private org.apache.dubbo.common.logger.Level level;

  public org.apache.dubbo.common.logger.log4j2.Log4j2LoggerAdapter();
    Code:
       0: aload_0
       1: invokespecial #1                  // Method java/lang/Object."<init>":()V
       4: return

  private static org.apache.logging.log4j.Level toLog4j2Level(org.apache.dubbo.common.logger.Level);
    Code:
       0: aload_0
       1: getstatic     #2                  // Field org/apache/dubbo/common/logger/Level.ALL:Lorg/apache/dubbo/common/logger/Level;
       4: if_acmpne     11
       7: getstatic     #3                  // Field org/apache/logging/log4j/Level.ALL:Lorg/apache/logging/log4j/Level;
      10: areturn
      11: aload_0
      12: getstatic     #4                  // Field org/apache/dubbo/common/logger/Level.TRACE:Lorg/apache/dubbo/common/logger/Level;
      15: if_acmpne     22
      18: getstatic     #5                  // Field org/apache/logging/log4j/Level.TRACE:Lorg/apache/logging/log4j/Level;
      21: areturn
      22: aload_0
      23: getstatic     #6                  // Field org/apache/dubbo/common/logger/Level.DEBUG:Lorg/apache/dubbo/common/logger/Level;
      26: if_acmpne     33
      29: getstatic     #7                  // Field org/apache/logging/log4j/Level.DEBUG:Lorg/apache/logging/log4j/Level;
      32: areturn
      33: aload_0
      34: getstatic     #8                  // Field org/apache/dubbo/common/logger/Level.INFO:Lorg/apache/dubbo/common/logger/Level;
      37: if_acmpne     44
      40: getstatic     #9                  // Field org/apache/logging/log4j/Level.INFO:Lorg/apache/logging/log4j/Level;
      43: areturn
      44: aload_0
      45: getstatic     #10                 // Field org/apache/dubbo/common/logger/Level.WARN:Lorg/apache/dubbo/common/logger/Level;
      48: if_acmpne     55
      51: getstatic     #11                 // Field org/apache/logging/log4j/Level.WARN:Lorg/apache/logging/log4j/Level;
      54: areturn
      55: aload_0
      56: getstatic     #12                 // Field org/apache/dubbo/common/logger/Level.ERROR:Lorg/apache/dubbo/common/logger/Level;
      59: if_acmpne     66
      62: getstatic     #13                 // Field org/apache/logging/log4j/Level.ERROR:Lorg/apache/logging/log4j/Level;
      65: areturn
      66: getstatic     #14                 // Field org/apache/logging/log4j/Level.OFF:Lorg/apache/logging/log4j/Level;
      69: areturn

  private static org.apache.dubbo.common.logger.Level fromLog4j2Level(org.apache.logging.log4j.Level);
    Code:
       0: aload_0
       1: getstatic     #3                  // Field org/apache/logging/log4j/Level.ALL:Lorg/apache/logging/log4j/Level;
       4: if_acmpne     11
       7: getstatic     #2                  // Field org/apache/dubbo/common/logger/Level.ALL:Lorg/apache/dubbo/common/logger/Level;
      10: areturn
      11: aload_0
      12: getstatic     #5                  // Field org/apache/logging/log4j/Level.TRACE:Lorg/apache/logging/log4j/Level;
      15: if_acmpne     22
      18: getstatic     #4                  // Field org/apache/dubbo/common/logger/Level.TRACE:Lorg/apache/dubbo/common/logger/Level;
      21: areturn
      22: aload_0
      23: getstatic     #7                  // Field org/apache/logging/log4j/Level.DEBUG:Lorg/apache/logging/log4j/Level;
      26: if_acmpne     33
      29: getstatic     #6                  // Field org/apache/dubbo/common/logger/Level.DEBUG:Lorg/apache/dubbo/common/logger/Level;
      32: areturn
      33: aload_0
      34: getstatic     #9                  // Field org/apache/logging/log4j/Level.INFO:Lorg/apache/logging/log4j/Level;
      37: if_acmpne     44
      40: getstatic     #8                  // Field org/apache/dubbo/common/logger/Level.INFO:Lorg/apache/dubbo/common/logger/Level;
      43: areturn
      44: aload_0
      45: getstatic     #11                 // Field org/apache/logging/log4j/Level.WARN:Lorg/apache/logging/log4j/Level;
      48: if_acmpne     55
      51: getstatic     #10                 // Field org/apache/dubbo/common/logger/Level.WARN:Lorg/apache/dubbo/common/logger/Level;
      54: areturn
      55: aload_0
      56: getstatic     #13                 // Field org/apache/logging/log4j/Level.ERROR:Lorg/apache/logging/log4j/Level;
      59: if_acmpne     66
      62: getstatic     #12                 // Field org/apache/dubbo/common/logger/Level.ERROR:Lorg/apache/dubbo/common/logger/Level;
      65: areturn
      66: getstatic     #15                 // Field org/apache/dubbo/common/logger/Level.OFF:Lorg/apache/dubbo/common/logger/Level;
      69: areturn

  public org.apache.dubbo.common.logger.Logger getLogger(java.lang.Class<?>);
    Code:
       0: new           #16                 // class org/apache/dubbo/common/logger/log4j2/Log4j2Logger
       3: dup
       4: aload_1
       5: invokestatic  #17                 // Method org/apache/logging/log4j/LogManager.getLogger:(Ljava/lang/Class;)Lorg/apache/logging/log4j/Logger;
       8: invokespecial #18                 // Method org/apache/dubbo/common/logger/log4j2/Log4j2Logger."<init>":(Lorg/apache/logging/log4j/Logger;)V
      11: areturn

  public org.apache.dubbo.common.logger.Logger getLogger(java.lang.String);
    Code:
       0: new           #16                 // class org/apache/dubbo/common/logger/log4j2/Log4j2Logger
       3: dup
       4: aload_1
       5: invokestatic  #19                 // Method org/apache/logging/log4j/LogManager.getLogger:(Ljava/lang/String;)Lorg/apache/logging/log4j/Logger;
       8: invokespecial #18                 // Method org/apache/dubbo/common/logger/log4j2/Log4j2Logger."<init>":(Lorg/apache/logging/log4j/Logger;)V
      11: areturn

  public org.apache.dubbo.common.logger.Level getLevel();
    Code:
       0: aload_0
       1: getfield      #20                 // Field level:Lorg/apache/dubbo/common/logger/Level;
       4: areturn

  public void setLevel(org.apache.dubbo.common.logger.Level);
    Code:
       0: aload_0
       1: aload_1
       2: putfield      #20                 // Field level:Lorg/apache/dubbo/common/logger/Level;
       5: return

  public java.io.File getFile();
    Code:
       0: aconst_null
       1: areturn

  public void setFile(java.io.File);
    Code:
       0: return

  public boolean isConfigured();
    Code:
       0: iconst_1
       1: ireturn
}
