Compiled from "InvokerAndRestMethodMetadataPair.java"
public class org.apache.dubbo.rpc.protocol.rest.pair.InvokerAndRestMethodMetadataPair {
  org.apache.dubbo.rpc.Invoker invoker;

  org.apache.dubbo.metadata.rest.RestMethodMetadata restMethodMetadata;

  public org.apache.dubbo.rpc.protocol.rest.pair.InvokerAndRestMethodMetadataPair(org.apache.dubbo.rpc.Invoker, org.apache.dubbo.metadata.rest.RestMethodMetadata);
    Code:
       0: aload_0
       1: invokespecial #1                  // Method java/lang/Object."<init>":()V
       4: aload_0
       5: aload_1
       6: putfield      #2                  // Field invoker:Lorg/apache/dubbo/rpc/Invoker;
       9: aload_0
      10: aload_2
      11: putfield      #3                  // Field restMethodMetadata:Lorg/apache/dubbo/metadata/rest/RestMethodMetadata;
      14: return

  public org.apache.dubbo.rpc.Invoker getInvoker();
    Code:
       0: aload_0
       1: getfield      #2                  // Field invoker:Lorg/apache/dubbo/rpc/Invoker;
       4: areturn

  public org.apache.dubbo.metadata.rest.RestMethodMetadata getRestMethodMetadata();
    Code:
       0: aload_0
       1: getfield      #3                  // Field restMethodMetadata:Lorg/apache/dubbo/metadata/rest/RestMethodMetadata;
       4: areturn

  public static org.apache.dubbo.rpc.protocol.rest.pair.InvokerAndRestMethodMetadataPair pair(org.apache.dubbo.rpc.Invoker, org.apache.dubbo.metadata.rest.RestMethodMetadata);
    Code:
       0: new           #4                  // class org/apache/dubbo/rpc/protocol/rest/pair/InvokerAndRestMethodMetadataPair
       3: dup
       4: aload_0
       5: aload_1
       6: invokespecial #5                  // Method "<init>":(Lorg/apache/dubbo/rpc/Invoker;Lorg/apache/dubbo/metadata/rest/RestMethodMetadata;)V
       9: areturn
}
