Compiled from "MessageCodecResultPair.java"
public class org.apache.dubbo.rpc.protocol.rest.pair.MessageCodecResultPair {
  boolean coded;

  org.apache.dubbo.metadata.rest.media.MediaType mediaType;

  public org.apache.dubbo.rpc.protocol.rest.pair.MessageCodecResultPair(boolean, org.apache.dubbo.metadata.rest.media.MediaType);
    Code:
       0: aload_0
       1: invokespecial #1                  // Method java/lang/Object."<init>":()V
       4: aload_0
       5: iload_1
       6: putfield      #2                  // Field coded:Z
       9: aload_0
      10: aload_2
      11: putfield      #3                  // Field mediaType:Lorg/apache/dubbo/metadata/rest/media/MediaType;
      14: return

  public boolean isCoded();
    Code:
       0: aload_0
       1: getfield      #2                  // Field coded:Z
       4: ireturn

  public org.apache.dubbo.metadata.rest.media.MediaType getMediaType();
    Code:
       0: aload_0
       1: getfield      #3                  // Field mediaType:Lorg/apache/dubbo/metadata/rest/media/MediaType;
       4: areturn

  public static org.apache.dubbo.rpc.protocol.rest.pair.MessageCodecResultPair pair(boolean, org.apache.dubbo.metadata.rest.media.MediaType);
    Code:
       0: new           #4                  // class org/apache/dubbo/rpc/protocol/rest/pair/MessageCodecResultPair
       3: dup
       4: iload_0
       5: aload_1
       6: invokespecial #5                  // Method "<init>":(ZLorg/apache/dubbo/metadata/rest/media/MediaType;)V
       9: areturn
}
