Compiled from "ConfigurableMetadataServiceExporter.java"
public class org.apache.dubbo.config.metadata.ConfigurableMetadataServiceExporter {
  private final org.apache.dubbo.common.logger.ErrorTypeAwareLogger logger;

  private org.apache.dubbo.registry.client.metadata.MetadataServiceDelegation metadataService;

  private volatile org.apache.dubbo.config.ServiceConfig<org.apache.dubbo.metadata.MetadataService> serviceConfig;

  private final org.apache.dubbo.rpc.model.ApplicationModel applicationModel;

  public org.apache.dubbo.config.metadata.ConfigurableMetadataServiceExporter(org.apache.dubbo.rpc.model.ApplicationModel, org.apache.dubbo.registry.client.metadata.MetadataServiceDelegation);
    Code:
       0: aload_0
       1: invokespecial #3                  // Method java/lang/Object."<init>":()V
       4: aload_0
       5: aload_0
       6: invokevirtual #4                  // Method java/lang/Object.getClass:()Ljava/lang/Class;
       9: invokestatic  #5                  // Method org/apache/dubbo/common/logger/LoggerFactory.getErrorTypeAwareLogger:(Ljava/lang/Class;)Lorg/apache/dubbo/common/logger/ErrorTypeAwareLogger;
      12: putfield      #6                  // Field logger:Lorg/apache/dubbo/common/logger/ErrorTypeAwareLogger;
      15: aload_0
      16: aload_1
      17: putfield      #7                  // Field applicationModel:Lorg/apache/dubbo/rpc/model/ApplicationModel;
      20: aload_0
      21: aload_2
      22: putfield      #8                  // Field metadataService:Lorg/apache/dubbo/registry/client/metadata/MetadataServiceDelegation;
      25: return

  public synchronized org.apache.dubbo.config.metadata.ConfigurableMetadataServiceExporter export();
    Code:
       0: aload_0
       1: getfield      #9                  // Field serviceConfig:Lorg/apache/dubbo/config/ServiceConfig;
       4: ifnull        14
       7: aload_0
       8: invokevirtual #10                 // Method isExported:()Z
      11: ifne          180
      14: aload_0
      15: getfield      #7                  // Field applicationModel:Lorg/apache/dubbo/rpc/model/ApplicationModel;
      18: invokevirtual #11                 // Method org/apache/dubbo/rpc/model/ApplicationModel.getFrameworkModel:()Lorg/apache/dubbo/rpc/model/FrameworkModel;
      21: invokevirtual #12                 // Method org/apache/dubbo/rpc/model/FrameworkModel.getBeanFactory:()Lorg/apache/dubbo/common/beans/factory/ScopeBeanFactory;
      24: ldc           #13                 // class org/apache/dubbo/common/threadpool/manager/FrameworkExecutorRepository
      26: invokevirtual #14                 // Method org/apache/dubbo/common/beans/factory/ScopeBeanFactory.getBean:(Ljava/lang/Class;)Ljava/lang/Object;
      29: checkcast     #13                 // class org/apache/dubbo/common/threadpool/manager/FrameworkExecutorRepository
      32: invokevirtual #15                 // Method org/apache/dubbo/common/threadpool/manager/FrameworkExecutorRepository.getInternalServiceExecutor:()Ljava/util/concurrent/ExecutorService;
      35: astore_1
      36: aload_0
      37: aload_0
      38: getfield      #7                  // Field applicationModel:Lorg/apache/dubbo/rpc/model/ApplicationModel;
      41: invokestatic  #16                 // Method org/apache/dubbo/config/bootstrap/builders/InternalServiceConfigBuilder.newBuilder:(Lorg/apache/dubbo/rpc/model/ApplicationModel;)Lorg/apache/dubbo/config/bootstrap/builders/InternalServiceConfigBuilder;
      44: ldc           #17                 // class org/apache/dubbo/metadata/MetadataService
      46: invokevirtual #18                 // Method org/apache/dubbo/config/bootstrap/builders/InternalServiceConfigBuilder.interfaceClass:(Ljava/lang/Class;)Lorg/apache/dubbo/config/bootstrap/builders/InternalServiceConfigBuilder;
      49: aload_0
      50: invokespecial #19                 // Method getApplicationConfig:()Lorg/apache/dubbo/config/ApplicationConfig;
      53: invokevirtual #20                 // Method org/apache/dubbo/config/ApplicationConfig.getMetadataServiceProtocol:()Ljava/lang/String;
      56: ldc           #21                 // String metadata-service-protocol
      58: invokevirtual #22                 // Method org/apache/dubbo/config/bootstrap/builders/InternalServiceConfigBuilder.protocol:(Ljava/lang/String;Ljava/lang/String;)Lorg/apache/dubbo/config/bootstrap/builders/InternalServiceConfigBuilder;
      61: aload_0
      62: invokespecial #19                 // Method getApplicationConfig:()Lorg/apache/dubbo/config/ApplicationConfig;
      65: invokevirtual #23                 // Method org/apache/dubbo/config/ApplicationConfig.getMetadataServicePort:()Ljava/lang/Integer;
      68: ldc           #24                 // String metadata-service-port
      70: invokevirtual #25                 // Method org/apache/dubbo/config/bootstrap/builders/InternalServiceConfigBuilder.port:(Ljava/lang/Integer;Ljava/lang/String;)Lorg/apache/dubbo/config/bootstrap/builders/InternalServiceConfigBuilder;
      73: ldc           #26                 // String internal-metadata-registry
      75: invokevirtual #27                 // Method org/apache/dubbo/config/bootstrap/builders/InternalServiceConfigBuilder.registryId:(Ljava/lang/String;)Lorg/apache/dubbo/config/bootstrap/builders/InternalServiceConfigBuilder;
      78: aload_1
      79: invokevirtual #28                 // Method org/apache/dubbo/config/bootstrap/builders/InternalServiceConfigBuilder.executor:(Ljava/util/concurrent/Executor;)Lorg/apache/dubbo/config/bootstrap/builders/InternalServiceConfigBuilder;
      82: aload_0
      83: getfield      #8                  // Field metadataService:Lorg/apache/dubbo/registry/client/metadata/MetadataServiceDelegation;
      86: invokevirtual #29                 // Method org/apache/dubbo/config/bootstrap/builders/InternalServiceConfigBuilder.ref:(Ljava/lang/Object;)Lorg/apache/dubbo/config/bootstrap/builders/InternalServiceConfigBuilder;
      89: aload_0
      90: invokedynamic #30,  0             // InvokeDynamic #0:accept:(Lorg/apache/dubbo/config/metadata/ConfigurableMetadataServiceExporter;)Ljava/util/function/Consumer;
      95: invokevirtual #31                 // Method org/apache/dubbo/config/bootstrap/builders/InternalServiceConfigBuilder.build:(Ljava/util/function/Consumer;)Lorg/apache/dubbo/config/ServiceConfig;
      98: putfield      #9                  // Field serviceConfig:Lorg/apache/dubbo/config/ServiceConfig;
     101: aload_0
     102: getfield      #9                  // Field serviceConfig:Lorg/apache/dubbo/config/ServiceConfig;
     105: invokevirtual #32                 // Method org/apache/dubbo/config/ServiceConfig.export:()V
     108: aload_0
     109: getfield      #8                  // Field metadataService:Lorg/apache/dubbo/registry/client/metadata/MetadataServiceDelegation;
     112: aload_0
     113: getfield      #9                  // Field serviceConfig:Lorg/apache/dubbo/config/ServiceConfig;
     116: invokevirtual #33                 // Method org/apache/dubbo/config/ServiceConfig.getExportedUrls:()Ljava/util/List;
     119: iconst_0
     120: invokeinterface #34,  2           // InterfaceMethod java/util/List.get:(I)Ljava/lang/Object;
     125: checkcast     #35                 // class org/apache/dubbo/common/URL
     128: invokevirtual #36                 // Method org/apache/dubbo/registry/client/metadata/MetadataServiceDelegation.setMetadataURL:(Lorg/apache/dubbo/common/URL;)V
     131: aload_0
     132: getfield      #6                  // Field logger:Lorg/apache/dubbo/common/logger/ErrorTypeAwareLogger;
     135: invokeinterface #37,  1           // InterfaceMethod org/apache/dubbo/common/logger/ErrorTypeAwareLogger.isInfoEnabled:()Z
     140: ifeq          177
     143: aload_0
     144: getfield      #6                  // Field logger:Lorg/apache/dubbo/common/logger/ErrorTypeAwareLogger;
     147: new           #38                 // class java/lang/StringBuilder
     150: dup
     151: invokespecial #39                 // Method java/lang/StringBuilder."<init>":()V
     154: ldc           #40                 // String The MetadataService exports urls :
     156: invokevirtual #41                 // Method java/lang/StringBuilder.append:(Ljava/lang/String;)Ljava/lang/StringBuilder;
     159: aload_0
     160: getfield      #9                  // Field serviceConfig:Lorg/apache/dubbo/config/ServiceConfig;
     163: invokevirtual #33                 // Method org/apache/dubbo/config/ServiceConfig.getExportedUrls:()Ljava/util/List;
     166: invokevirtual #42                 // Method java/lang/StringBuilder.append:(Ljava/lang/Object;)Ljava/lang/StringBuilder;
     169: invokevirtual #43                 // Method java/lang/StringBuilder.toString:()Ljava/lang/String;
     172: invokeinterface #44,  2           // InterfaceMethod org/apache/dubbo/common/logger/ErrorTypeAwareLogger.info:(Ljava/lang/String;)V
     177: goto          232
     180: aload_0
     181: getfield      #6                  // Field logger:Lorg/apache/dubbo/common/logger/ErrorTypeAwareLogger;
     184: invokeinterface #45,  1           // InterfaceMethod org/apache/dubbo/common/logger/ErrorTypeAwareLogger.isWarnEnabled:()Z
     189: ifeq          232
     192: aload_0
     193: getfield      #6                  // Field logger:Lorg/apache/dubbo/common/logger/ErrorTypeAwareLogger;
     196: ldc           #46                 // String 5-26
     198: ldc           #47                 // String
     200: ldc           #47                 // String
     202: new           #38                 // class java/lang/StringBuilder
     205: dup
     206: invokespecial #39                 // Method java/lang/StringBuilder."<init>":()V
     209: ldc           #48                 // String The MetadataService has been exported :
     211: invokevirtual #41                 // Method java/lang/StringBuilder.append:(Ljava/lang/String;)Ljava/lang/StringBuilder;
     214: aload_0
     215: getfield      #9                  // Field serviceConfig:Lorg/apache/dubbo/config/ServiceConfig;
     218: invokevirtual #33                 // Method org/apache/dubbo/config/ServiceConfig.getExportedUrls:()Ljava/util/List;
     221: invokevirtual #42                 // Method java/lang/StringBuilder.append:(Ljava/lang/Object;)Ljava/lang/StringBuilder;
     224: invokevirtual #43                 // Method java/lang/StringBuilder.toString:()Ljava/lang/String;
     227: invokeinterface #49,  5           // InterfaceMethod org/apache/dubbo/common/logger/ErrorTypeAwareLogger.warn:(Ljava/lang/String;Ljava/lang/String;Ljava/lang/String;Ljava/lang/String;)V
     232: aload_0
     233: areturn

  public org.apache.dubbo.config.metadata.ConfigurableMetadataServiceExporter unexport();
    Code:
       0: aload_0
       1: invokevirtual #10                 // Method isExported:()Z
       4: ifeq          22
       7: aload_0
       8: getfield      #9                  // Field serviceConfig:Lorg/apache/dubbo/config/ServiceConfig;
      11: invokevirtual #50                 // Method org/apache/dubbo/config/ServiceConfig.unexport:()V
      14: aload_0
      15: getfield      #8                  // Field metadataService:Lorg/apache/dubbo/registry/client/metadata/MetadataServiceDelegation;
      18: aconst_null
      19: invokevirtual #36                 // Method org/apache/dubbo/registry/client/metadata/MetadataServiceDelegation.setMetadataURL:(Lorg/apache/dubbo/common/URL;)V
      22: aload_0
      23: areturn

  public boolean isExported();
    Code:
       0: aload_0
       1: getfield      #9                  // Field serviceConfig:Lorg/apache/dubbo/config/ServiceConfig;
       4: ifnull        31
       7: aload_0
       8: getfield      #9                  // Field serviceConfig:Lorg/apache/dubbo/config/ServiceConfig;
      11: invokevirtual #51                 // Method org/apache/dubbo/config/ServiceConfig.isExported:()Z
      14: ifeq          31
      17: aload_0
      18: getfield      #9                  // Field serviceConfig:Lorg/apache/dubbo/config/ServiceConfig;
      21: invokevirtual #52                 // Method org/apache/dubbo/config/ServiceConfig.isUnexported:()Z
      24: ifne          31
      27: iconst_1
      28: goto          32
      31: iconst_0
      32: ireturn

  private org.apache.dubbo.config.ApplicationConfig getApplicationConfig();
    Code:
       0: aload_0
       1: getfield      #7                  // Field applicationModel:Lorg/apache/dubbo/rpc/model/ApplicationModel;
       4: invokevirtual #53                 // Method org/apache/dubbo/rpc/model/ApplicationModel.getApplicationConfigManager:()Lorg/apache/dubbo/config/context/ConfigManager;
       7: invokevirtual #54                 // Method org/apache/dubbo/config/context/ConfigManager.getApplication:()Ljava/util/Optional;
      10: invokevirtual #55                 // Method java/util/Optional.get:()Ljava/lang/Object;
      13: checkcast     #56                 // class org/apache/dubbo/config/ApplicationConfig
      16: areturn

  private java.util.List<org.apache.dubbo.config.MethodConfig> generateMethodConfig();
    Code:
       0: new           #57                 // class org/apache/dubbo/config/MethodConfig
       3: dup
       4: invokespecial #58                 // Method org/apache/dubbo/config/MethodConfig."<init>":()V
       7: astore_1
       8: aload_1
       9: ldc           #59                 // String getAndListenInstanceMetadata
      11: invokevirtual #60                 // Method org/apache/dubbo/config/MethodConfig.setName:(Ljava/lang/String;)V
      14: new           #61                 // class org/apache/dubbo/config/ArgumentConfig
      17: dup
      18: invokespecial #62                 // Method org/apache/dubbo/config/ArgumentConfig."<init>":()V
      21: astore_2
      22: aload_2
      23: iconst_1
      24: invokestatic  #63                 // Method java/lang/Integer.valueOf:(I)Ljava/lang/Integer;
      27: invokevirtual #64                 // Method org/apache/dubbo/config/ArgumentConfig.setIndex:(Ljava/lang/Integer;)V
      30: aload_2
      31: iconst_1
      32: invokestatic  #65                 // Method java/lang/Boolean.valueOf:(Z)Ljava/lang/Boolean;
      35: invokevirtual #66                 // Method org/apache/dubbo/config/ArgumentConfig.setCallback:(Ljava/lang/Boolean;)V
      38: aload_1
      39: aload_2
      40: invokestatic  #67                 // Method java/util/Collections.singletonList:(Ljava/lang/Object;)Ljava/util/List;
      43: invokevirtual #68                 // Method org/apache/dubbo/config/MethodConfig.setArguments:(Ljava/util/List;)V
      46: aload_1
      47: invokestatic  #67                 // Method java/util/Collections.singletonList:(Ljava/lang/Object;)Ljava/util/List;
      50: areturn

  public void setMetadataService(org.apache.dubbo.registry.client.metadata.MetadataServiceDelegation);
    Code:
       0: aload_0
       1: aload_1
       2: putfield      #8                  // Field metadataService:Lorg/apache/dubbo/registry/client/metadata/MetadataServiceDelegation;
       5: return

  public java.util.List<org.apache.dubbo.common.URL> getExportedURLs();
    Code:
       0: aload_0
       1: getfield      #9                  // Field serviceConfig:Lorg/apache/dubbo/config/ServiceConfig;
       4: ifnull        17
       7: aload_0
       8: getfield      #9                  // Field serviceConfig:Lorg/apache/dubbo/config/ServiceConfig;
      11: invokevirtual #33                 // Method org/apache/dubbo/config/ServiceConfig.getExportedUrls:()Ljava/util/List;
      14: goto          20
      17: invokestatic  #69                 // Method java/util/Collections.emptyList:()Ljava/util/List;
      20: areturn

  private void lambda$export$0(org.apache.dubbo.config.ServiceConfig);
    Code:
       0: aload_1
       1: aload_0
       2: invokespecial #70                 // Method generateMethodConfig:()Ljava/util/List;
       5: invokevirtual #71                 // Method org/apache/dubbo/config/ServiceConfig.setMethods:(Ljava/util/List;)V
       8: return
}
