Compiled from "ExporterDeployListener.java"
public class org.apache.dubbo.config.metadata.ExporterDeployListener implements org.apache.dubbo.common.deploy.ApplicationDeployListener,org.apache.dubbo.common.lang.Prioritized {
  protected volatile org.apache.dubbo.config.metadata.ConfigurableMetadataServiceExporter metadataServiceExporter;

  public org.apache.dubbo.config.metadata.ExporterDeployListener();
    Code:
       0: aload_0
       1: invokespecial #2                  // Method java/lang/Object."<init>":()V
       4: return

  public void onInitialize(org.apache.dubbo.rpc.model.ApplicationModel);
    Code:
       0: return

  public void onStarting(org.apache.dubbo.rpc.model.ApplicationModel);
    Code:
       0: return

  public synchronized void onStarted(org.apache.dubbo.rpc.model.ApplicationModel);
    Code:
       0: return

  public synchronized void onStopping(org.apache.dubbo.rpc.model.ApplicationModel);
    Code:
       0: return

  private java.lang.String getMetadataType(org.apache.dubbo.rpc.model.ApplicationModel);
    Code:
       0: aload_1
       1: invokevirtual #3                  // Method org/apache/dubbo/rpc/model/ApplicationModel.getApplicationConfigManager:()Lorg/apache/dubbo/config/context/ConfigManager;
       4: invokevirtual #4                  // Method org/apache/dubbo/config/context/ConfigManager.getApplicationOrElseThrow:()Lorg/apache/dubbo/config/ApplicationConfig;
       7: invokevirtual #5                  // Method org/apache/dubbo/config/ApplicationConfig.getMetadataType:()Ljava/lang/String;
      10: astore_2
      11: aload_2
      12: invokestatic  #6                  // Method org/apache/dubbo/common/utils/StringUtils.isEmpty:(Ljava/lang/String;)Z
      15: ifeq          21
      18: ldc           #7                  // String local
      20: astore_2
      21: aload_2
      22: areturn

  private java.lang.String getRegisterMode(org.apache.dubbo.rpc.model.ApplicationModel);
    Code:
       0: aload_1
       1: invokevirtual #3                  // Method org/apache/dubbo/rpc/model/ApplicationModel.getApplicationConfigManager:()Lorg/apache/dubbo/config/context/ConfigManager;
       4: invokevirtual #4                  // Method org/apache/dubbo/config/context/ConfigManager.getApplicationOrElseThrow:()Lorg/apache/dubbo/config/ApplicationConfig;
       7: invokevirtual #8                  // Method org/apache/dubbo/config/ApplicationConfig.getRegisterMode:()Ljava/lang/String;
      10: astore_2
      11: aload_2
      12: invokestatic  #6                  // Method org/apache/dubbo/common/utils/StringUtils.isEmpty:(Ljava/lang/String;)Z
      15: ifeq          21
      18: ldc           #9                  // String all
      20: astore_2
      21: aload_2
      22: areturn

  public org.apache.dubbo.config.metadata.ConfigurableMetadataServiceExporter getMetadataServiceExporter();
    Code:
       0: aload_0
       1: getfield      #10                 // Field metadataServiceExporter:Lorg/apache/dubbo/config/metadata/ConfigurableMetadataServiceExporter;
       4: areturn

  public void setMetadataServiceExporter(org.apache.dubbo.config.metadata.ConfigurableMetadataServiceExporter);
    Code:
       0: aload_0
       1: aload_1
       2: putfield      #10                 // Field metadataServiceExporter:Lorg/apache/dubbo/config/metadata/ConfigurableMetadataServiceExporter;
       5: return

  public synchronized void onModuleStarted(org.apache.dubbo.rpc.model.ApplicationModel);
    Code:
       0: aload_1
       1: invokevirtual #11                 // Method org/apache/dubbo/rpc/model/ApplicationModel.getBeanFactory:()Lorg/apache/dubbo/common/beans/factory/ScopeBeanFactory;
       4: ldc           #12                 // class org/apache/dubbo/registry/client/metadata/MetadataServiceDelegation
       6: invokevirtual #13                 // Method org/apache/dubbo/common/beans/factory/ScopeBeanFactory.getOrRegisterBean:(Ljava/lang/Class;)Ljava/lang/Object;
       9: checkcast     #12                 // class org/apache/dubbo/registry/client/metadata/MetadataServiceDelegation
      12: astore_2
      13: aload_0
      14: getfield      #10                 // Field metadataServiceExporter:Lorg/apache/dubbo/config/metadata/ConfigurableMetadataServiceExporter;
      17: ifnonnull     67
      20: aload_0
      21: new           #14                 // class org/apache/dubbo/config/metadata/ConfigurableMetadataServiceExporter
      24: dup
      25: aload_1
      26: aload_2
      27: invokespecial #15                 // Method org/apache/dubbo/config/metadata/ConfigurableMetadataServiceExporter."<init>":(Lorg/apache/dubbo/rpc/model/ApplicationModel;Lorg/apache/dubbo/registry/client/metadata/MetadataServiceDelegation;)V
      30: putfield      #10                 // Field metadataServiceExporter:Lorg/apache/dubbo/config/metadata/ConfigurableMetadataServiceExporter;
      33: ldc           #16                 // String remote
      35: aload_0
      36: aload_1
      37: invokespecial #17                 // Method getMetadataType:(Lorg/apache/dubbo/rpc/model/ApplicationModel;)Ljava/lang/String;
      40: invokevirtual #18                 // Method java/lang/String.equals:(Ljava/lang/Object;)Z
      43: ifne          67
      46: ldc           #19                 // String interface
      48: aload_0
      49: aload_1
      50: invokespecial #20                 // Method getRegisterMode:(Lorg/apache/dubbo/rpc/model/ApplicationModel;)Ljava/lang/String;
      53: invokevirtual #18                 // Method java/lang/String.equals:(Ljava/lang/Object;)Z
      56: ifne          67
      59: aload_0
      60: getfield      #10                 // Field metadataServiceExporter:Lorg/apache/dubbo/config/metadata/ConfigurableMetadataServiceExporter;
      63: invokevirtual #21                 // Method org/apache/dubbo/config/metadata/ConfigurableMetadataServiceExporter.export:()Lorg/apache/dubbo/config/metadata/ConfigurableMetadataServiceExporter;
      66: pop
      67: return

  public synchronized void onStopped(org.apache.dubbo.rpc.model.ApplicationModel);
    Code:
       0: aload_0
       1: getfield      #10                 // Field metadataServiceExporter:Lorg/apache/dubbo/config/metadata/ConfigurableMetadataServiceExporter;
       4: ifnull        29
       7: aload_0
       8: getfield      #10                 // Field metadataServiceExporter:Lorg/apache/dubbo/config/metadata/ConfigurableMetadataServiceExporter;
      11: invokevirtual #22                 // Method org/apache/dubbo/config/metadata/ConfigurableMetadataServiceExporter.isExported:()Z
      14: ifeq          29
      17: aload_0
      18: getfield      #10                 // Field metadataServiceExporter:Lorg/apache/dubbo/config/metadata/ConfigurableMetadataServiceExporter;
      21: invokevirtual #23                 // Method org/apache/dubbo/config/metadata/ConfigurableMetadataServiceExporter.unexport:()Lorg/apache/dubbo/config/metadata/ConfigurableMetadataServiceExporter;
      24: pop
      25: goto          29
      28: astore_2
      29: return
    Exception table:
       from    to  target type
          17    25    28   Class java/lang/Exception

  public void onFailure(org.apache.dubbo.rpc.model.ApplicationModel, java.lang.Throwable);
    Code:
       0: return

  public int getPriority();
    Code:
       0: ldc           #26                 // int -2147483648
       2: ireturn

  public void onFailure(org.apache.dubbo.rpc.model.ScopeModel, java.lang.Throwable);
    Code:
       0: aload_0
       1: aload_1
       2: checkcast     #27                 // class org/apache/dubbo/rpc/model/ApplicationModel
       5: aload_2
       6: invokevirtual #28                 // Method onFailure:(Lorg/apache/dubbo/rpc/model/ApplicationModel;Ljava/lang/Throwable;)V
       9: return

  public void onStopped(org.apache.dubbo.rpc.model.ScopeModel);
    Code:
       0: aload_0
       1: aload_1
       2: checkcast     #27                 // class org/apache/dubbo/rpc/model/ApplicationModel
       5: invokevirtual #29                 // Method onStopped:(Lorg/apache/dubbo/rpc/model/ApplicationModel;)V
       8: return

  public void onStopping(org.apache.dubbo.rpc.model.ScopeModel);
    Code:
       0: aload_0
       1: aload_1
       2: checkcast     #27                 // class org/apache/dubbo/rpc/model/ApplicationModel
       5: invokevirtual #30                 // Method onStopping:(Lorg/apache/dubbo/rpc/model/ApplicationModel;)V
       8: return

  public void onStarted(org.apache.dubbo.rpc.model.ScopeModel);
    Code:
       0: aload_0
       1: aload_1
       2: checkcast     #27                 // class org/apache/dubbo/rpc/model/ApplicationModel
       5: invokevirtual #31                 // Method onStarted:(Lorg/apache/dubbo/rpc/model/ApplicationModel;)V
       8: return

  public void onStarting(org.apache.dubbo.rpc.model.ScopeModel);
    Code:
       0: aload_0
       1: aload_1
       2: checkcast     #27                 // class org/apache/dubbo/rpc/model/ApplicationModel
       5: invokevirtual #32                 // Method onStarting:(Lorg/apache/dubbo/rpc/model/ApplicationModel;)V
       8: return

  public void onInitialize(org.apache.dubbo.rpc.model.ScopeModel);
    Code:
       0: aload_0
       1: aload_1
       2: checkcast     #27                 // class org/apache/dubbo/rpc/model/ApplicationModel
       5: invokevirtual #33                 // Method onInitialize:(Lorg/apache/dubbo/rpc/model/ApplicationModel;)V
       8: return
}
