Compiled from "MetadataServiceURLParamsMetadataCustomizer.java"
public class org.apache.dubbo.config.metadata.MetadataServiceURLParamsMetadataCustomizer implements org.apache.dubbo.registry.client.ServiceInstanceCustomizer {
  public org.apache.dubbo.config.metadata.MetadataServiceURLParamsMetadataCustomizer();
    Code:
       0: aload_0
       1: invokespecial #2                  // Method java/lang/Object."<init>":()V
       4: return

  public void customize(org.apache.dubbo.registry.client.ServiceInstance, org.apache.dubbo.rpc.model.ApplicationModel);
    Code:
       0: aload_1
       1: invokeinterface #3,  1            // InterfaceMethod org/apache/dubbo/registry/client/ServiceInstance.getMetadata:()Ljava/util/Map;
       6: astore_3
       7: aload_0
       8: aload_1
       9: invokespecial #4                  // Method resolveMetadataPropertyName:(Lorg/apache/dubbo/registry/client/ServiceInstance;)Ljava/lang/String;
      12: astore        4
      14: aload_0
      15: aload_2
      16: invokespecial #5                  // Method resolveMetadataPropertyValue:(Lorg/apache/dubbo/rpc/model/ApplicationModel;)Ljava/lang/String;
      19: astore        5
      21: aload         4
      23: invokestatic  #6                  // Method org/apache/dubbo/common/utils/StringUtils.isBlank:(Ljava/lang/CharSequence;)Z
      26: ifne          48
      29: aload         5
      31: invokestatic  #6                  // Method org/apache/dubbo/common/utils/StringUtils.isBlank:(Ljava/lang/CharSequence;)Z
      34: ifne          48
      37: aload_3
      38: aload         4
      40: aload         5
      42: invokeinterface #7,  3            // InterfaceMethod java/util/Map.put:(Ljava/lang/Object;Ljava/lang/Object;)Ljava/lang/Object;
      47: pop
      48: return

  private java.lang.String resolveMetadataPropertyName(org.apache.dubbo.registry.client.ServiceInstance);
    Code:
       0: ldc           #8                  // String dubbo.metadata-service.url-params
       2: areturn

  private java.lang.String resolveMetadataPropertyValue(org.apache.dubbo.rpc.model.ApplicationModel);
    Code:
       0: aload_1
       1: invokevirtual #9                  // Method org/apache/dubbo/rpc/model/ApplicationModel.getInternalModule:()Lorg/apache/dubbo/rpc/model/ModuleModel;
       4: invokevirtual #10                 // Method org/apache/dubbo/rpc/model/ModuleModel.getServiceRepository:()Lorg/apache/dubbo/rpc/model/ModuleServiceRepository;
       7: astore_2
       8: ldc           #11                 // class org/apache/dubbo/metadata/MetadataService
      10: invokevirtual #12                 // Method java/lang/Class.getName:()Ljava/lang/String;
      13: aload_1
      14: invokevirtual #13                 // Method org/apache/dubbo/rpc/model/ApplicationModel.getApplicationName:()Ljava/lang/String;
      17: ldc           #14                 // String 1.0.0
      19: invokestatic  #15                 // Method org/apache/dubbo/common/BaseServiceMetadata.buildServiceKey:(Ljava/lang/String;Ljava/lang/String;Ljava/lang/String;)Ljava/lang/String;
      22: astore_3
      23: aload_2
      24: aload_3
      25: invokevirtual #16                 // Method org/apache/dubbo/rpc/model/ModuleServiceRepository.lookupExportedService:(Ljava/lang/String;)Lorg/apache/dubbo/rpc/model/ProviderModel;
      28: astore        4
      30: ldc           #17                 // String
      32: astore        5
      34: aload         4
      36: ifnull        70
      39: aload         4
      41: invokevirtual #18                 // Method org/apache/dubbo/rpc/model/ProviderModel.getServiceUrls:()Ljava/util/List;
      44: astore        6
      46: aload         6
      48: invokestatic  #19                 // Method org/apache/dubbo/common/utils/CollectionUtils.isNotEmpty:(Ljava/util/Collection;)Z
      51: ifeq          70
      54: aload         6
      56: iconst_0
      57: invokeinterface #20,  2           // InterfaceMethod java/util/List.get:(I)Ljava/lang/Object;
      62: checkcast     #21                 // class org/apache/dubbo/common/URL
      65: invokestatic  #22                 // Method org/apache/dubbo/registry/client/metadata/ServiceInstanceMetadataUtils.getMetadataServiceParameter:(Lorg/apache/dubbo/common/URL;)Ljava/lang/String;
      68: astore        5
      70: aload         5
      72: areturn
}
