Compiled from "ApplicationReadyEvent.java"
public class org.springframework.boot.context.event.ApplicationReadyEvent extends org.springframework.boot.context.event.SpringApplicationEvent {
  private final org.springframework.context.ConfigurableApplicationContext context;

  private final java.time.Duration timeTaken;

  public org.springframework.boot.context.event.ApplicationReadyEvent(org.springframework.boot.SpringApplication, java.lang.String[], org.springframework.context.ConfigurableApplicationContext, java.time.Duration);
    Code:
       0: aload_0
       1: aload_1
       2: aload_2
       3: invokespecial #1                  // Method org/springframework/boot/context/event/SpringApplicationEvent."<init>":(Lorg/springframework/boot/SpringApplication;[Ljava/lang/String;)V
       6: aload_0
       7: aload_3
       8: putfield      #7                  // Field context:Lorg/springframework/context/ConfigurableApplicationContext;
      11: aload_0
      12: aload         4
      14: putfield      #13                 // Field timeTaken:Ljava/time/Duration;
      17: return

  public org.springframework.context.ConfigurableApplicationContext getApplicationContext();
    Code:
       0: aload_0
       1: getfield      #7                  // Field context:Lorg/springframework/context/ConfigurableApplicationContext;
       4: areturn

  public java.time.Duration getTimeTaken();
    Code:
       0: aload_0
       1: getfield      #13                 // Field timeTaken:Ljava/time/Duration;
       4: areturn
}
