Compiled from "ApplicationStartingEvent.java"
public class org.springframework.boot.context.event.ApplicationStartingEvent extends org.springframework.boot.context.event.SpringApplicationEvent {
  private final org.springframework.boot.ConfigurableBootstrapContext bootstrapContext;

  public org.springframework.boot.context.event.ApplicationStartingEvent(org.springframework.boot.ConfigurableBootstrapContext, org.springframework.boot.SpringApplication, java.lang.String[]);
    Code:
       0: aload_0
       1: aload_2
       2: aload_3
       3: invokespecial #1                  // Method org/springframework/boot/context/event/SpringApplicationEvent."<init>":(Lorg/springframework/boot/SpringApplication;[Ljava/lang/String;)V
       6: aload_0
       7: aload_1
       8: putfield      #7                  // Field bootstrapContext:Lorg/springframework/boot/ConfigurableBootstrapContext;
      11: return

  public org.springframework.boot.ConfigurableBootstrapContext getBootstrapContext();
    Code:
       0: aload_0
       1: getfield      #7                  // Field bootstrapContext:Lorg/springframework/boot/ConfigurableBootstrapContext;
       4: areturn
}
