Compiled from "ApplicationEnvironmentPreparedEvent.java"
public class org.springframework.boot.context.event.ApplicationEnvironmentPreparedEvent extends org.springframework.boot.context.event.SpringApplicationEvent {
  private final org.springframework.boot.ConfigurableBootstrapContext bootstrapContext;

  private final org.springframework.core.env.ConfigurableEnvironment environment;

  public org.springframework.boot.context.event.ApplicationEnvironmentPreparedEvent(org.springframework.boot.ConfigurableBootstrapContext, org.springframework.boot.SpringApplication, java.lang.String[], org.springframework.core.env.ConfigurableEnvironment);
    Code:
       0: aload_0
       1: aload_2
       2: aload_3
       3: invokespecial #1                  // Method org/springframework/boot/context/event/SpringApplicationEvent."<init>":(Lorg/springframework/boot/SpringApplication;[Ljava/lang/String;)V
       6: aload_0
       7: aload_1
       8: putfield      #7                  // Field bootstrapContext:Lorg/springframework/boot/ConfigurableBootstrapContext;
      11: aload_0
      12: aload         4
      14: putfield      #13                 // Field environment:Lorg/springframework/core/env/ConfigurableEnvironment;
      17: return

  public org.springframework.boot.ConfigurableBootstrapContext getBootstrapContext();
    Code:
       0: aload_0
       1: getfield      #7                  // Field bootstrapContext:Lorg/springframework/boot/ConfigurableBootstrapContext;
       4: areturn

  public org.springframework.core.env.ConfigurableEnvironment getEnvironment();
    Code:
       0: aload_0
       1: getfield      #13                 // Field environment:Lorg/springframework/core/env/ConfigurableEnvironment;
       4: areturn
}
