Compiled from "EventPublishingRunListener.java"
class org.springframework.boot.context.event.EventPublishingRunListener implements org.springframework.boot.SpringApplicationRunListener,org.springframework.core.Ordered {
  private final org.springframework.boot.SpringApplication application;

  private final java.lang.String[] args;

  private final org.springframework.context.event.SimpleApplicationEventMulticaster initialMulticaster;

  org.springframework.boot.context.event.EventPublishingRunListener(org.springframework.boot.SpringApplication, java.lang.String[]);
    Code:
       0: aload_0
       1: invokespecial #1                  // Method java/lang/Object."<init>":()V
       4: aload_0
       5: aload_1
       6: putfield      #7                  // Field application:Lorg/springframework/boot/SpringApplication;
       9: aload_0
      10: aload_2
      11: putfield      #13                 // Field args:[Ljava/lang/String;
      14: aload_0
      15: new           #17                 // class org/springframework/context/event/SimpleApplicationEventMulticaster
      18: dup
      19: invokespecial #19                 // Method org/springframework/context/event/SimpleApplicationEventMulticaster."<init>":()V
      22: putfield      #20                 // Field initialMulticaster:Lorg/springframework/context/event/SimpleApplicationEventMulticaster;
      25: return

  public int getOrder();
    Code:
       0: iconst_0
       1: ireturn

  public void starting(org.springframework.boot.ConfigurableBootstrapContext);
    Code:
       0: aload_0
       1: new           #24                 // class org/springframework/boot/context/event/ApplicationStartingEvent
       4: dup
       5: aload_1
       6: aload_0
       7: getfield      #7                  // Field application:Lorg/springframework/boot/SpringApplication;
      10: aload_0
      11: getfield      #13                 // Field args:[Ljava/lang/String;
      14: invokespecial #26                 // Method org/springframework/boot/context/event/ApplicationStartingEvent."<init>":(Lorg/springframework/boot/ConfigurableBootstrapContext;Lorg/springframework/boot/SpringApplication;[Ljava/lang/String;)V
      17: invokevirtual #29                 // Method multicastInitialEvent:(Lorg/springframework/context/ApplicationEvent;)V
      20: return

  public void environmentPrepared(org.springframework.boot.ConfigurableBootstrapContext, org.springframework.core.env.ConfigurableEnvironment);
    Code:
       0: aload_0
       1: new           #33                 // class org/springframework/boot/context/event/ApplicationEnvironmentPreparedEvent
       4: dup
       5: aload_1
       6: aload_0
       7: getfield      #7                  // Field application:Lorg/springframework/boot/SpringApplication;
      10: aload_0
      11: getfield      #13                 // Field args:[Ljava/lang/String;
      14: aload_2
      15: invokespecial #35                 // Method org/springframework/boot/context/event/ApplicationEnvironmentPreparedEvent."<init>":(Lorg/springframework/boot/ConfigurableBootstrapContext;Lorg/springframework/boot/SpringApplication;[Ljava/lang/String;Lorg/springframework/core/env/ConfigurableEnvironment;)V
      18: invokevirtual #29                 // Method multicastInitialEvent:(Lorg/springframework/context/ApplicationEvent;)V
      21: return

  public void contextPrepared(org.springframework.context.ConfigurableApplicationContext);
    Code:
       0: aload_0
       1: new           #38                 // class org/springframework/boot/context/event/ApplicationContextInitializedEvent
       4: dup
       5: aload_0
       6: getfield      #7                  // Field application:Lorg/springframework/boot/SpringApplication;
       9: aload_0
      10: getfield      #13                 // Field args:[Ljava/lang/String;
      13: aload_1
      14: invokespecial #40                 // Method org/springframework/boot/context/event/ApplicationContextInitializedEvent."<init>":(Lorg/springframework/boot/SpringApplication;[Ljava/lang/String;Lorg/springframework/context/ConfigurableApplicationContext;)V
      17: invokevirtual #29                 // Method multicastInitialEvent:(Lorg/springframework/context/ApplicationEvent;)V
      20: return

  public void contextLoaded(org.springframework.context.ConfigurableApplicationContext);
    Code:
       0: aload_0
       1: getfield      #7                  // Field application:Lorg/springframework/boot/SpringApplication;
       4: invokevirtual #43                 // Method org/springframework/boot/SpringApplication.getListeners:()Ljava/util/Set;
       7: invokeinterface #49,  1           // InterfaceMethod java/util/Set.iterator:()Ljava/util/Iterator;
      12: astore_2
      13: aload_2
      14: invokeinterface #55,  1           // InterfaceMethod java/util/Iterator.hasNext:()Z
      19: ifeq          63
      22: aload_2
      23: invokeinterface #61,  1           // InterfaceMethod java/util/Iterator.next:()Ljava/lang/Object;
      28: checkcast     #65                 // class org/springframework/context/ApplicationListener
      31: astore_3
      32: aload_3
      33: instanceof    #67                 // class org/springframework/context/ApplicationContextAware
      36: ifeq          53
      39: aload_3
      40: checkcast     #67                 // class org/springframework/context/ApplicationContextAware
      43: astore        4
      45: aload         4
      47: aload_1
      48: invokeinterface #69,  2           // InterfaceMethod org/springframework/context/ApplicationContextAware.setApplicationContext:(Lorg/springframework/context/ApplicationContext;)V
      53: aload_1
      54: aload_3
      55: invokeinterface #73,  2           // InterfaceMethod org/springframework/context/ConfigurableApplicationContext.addApplicationListener:(Lorg/springframework/context/ApplicationListener;)V
      60: goto          13
      63: aload_0
      64: new           #79                 // class org/springframework/boot/context/event/ApplicationPreparedEvent
      67: dup
      68: aload_0
      69: getfield      #7                  // Field application:Lorg/springframework/boot/SpringApplication;
      72: aload_0
      73: getfield      #13                 // Field args:[Ljava/lang/String;
      76: aload_1
      77: invokespecial #81                 // Method org/springframework/boot/context/event/ApplicationPreparedEvent."<init>":(Lorg/springframework/boot/SpringApplication;[Ljava/lang/String;Lorg/springframework/context/ConfigurableApplicationContext;)V
      80: invokevirtual #29                 // Method multicastInitialEvent:(Lorg/springframework/context/ApplicationEvent;)V
      83: return

  public void started(org.springframework.context.ConfigurableApplicationContext, java.time.Duration);
    Code:
       0: aload_1
       1: new           #82                 // class org/springframework/boot/context/event/ApplicationStartedEvent
       4: dup
       5: aload_0
       6: getfield      #7                  // Field application:Lorg/springframework/boot/SpringApplication;
       9: aload_0
      10: getfield      #13                 // Field args:[Ljava/lang/String;
      13: aload_1
      14: aload_2
      15: invokespecial #84                 // Method org/springframework/boot/context/event/ApplicationStartedEvent."<init>":(Lorg/springframework/boot/SpringApplication;[Ljava/lang/String;Lorg/springframework/context/ConfigurableApplicationContext;Ljava/time/Duration;)V
      18: invokeinterface #87,  2           // InterfaceMethod org/springframework/context/ConfigurableApplicationContext.publishEvent:(Lorg/springframework/context/ApplicationEvent;)V
      23: aload_1
      24: getstatic     #90                 // Field org/springframework/boot/availability/LivenessState.CORRECT:Lorg/springframework/boot/availability/LivenessState;
      27: invokestatic  #96                 // Method org/springframework/boot/availability/AvailabilityChangeEvent.publish:(Lorg/springframework/context/ApplicationContext;Lorg/springframework/boot/availability/AvailabilityState;)V
      30: return

  public void ready(org.springframework.context.ConfigurableApplicationContext, java.time.Duration);
    Code:
       0: aload_1
       1: new           #102                // class org/springframework/boot/context/event/ApplicationReadyEvent
       4: dup
       5: aload_0
       6: getfield      #7                  // Field application:Lorg/springframework/boot/SpringApplication;
       9: aload_0
      10: getfield      #13                 // Field args:[Ljava/lang/String;
      13: aload_1
      14: aload_2
      15: invokespecial #104                // Method org/springframework/boot/context/event/ApplicationReadyEvent."<init>":(Lorg/springframework/boot/SpringApplication;[Ljava/lang/String;Lorg/springframework/context/ConfigurableApplicationContext;Ljava/time/Duration;)V
      18: invokeinterface #87,  2           // InterfaceMethod org/springframework/context/ConfigurableApplicationContext.publishEvent:(Lorg/springframework/context/ApplicationEvent;)V
      23: aload_1
      24: getstatic     #105                // Field org/springframework/boot/availability/ReadinessState.ACCEPTING_TRAFFIC:Lorg/springframework/boot/availability/ReadinessState;
      27: invokestatic  #96                 // Method org/springframework/boot/availability/AvailabilityChangeEvent.publish:(Lorg/springframework/context/ApplicationContext;Lorg/springframework/boot/availability/AvailabilityState;)V
      30: return

  public void failed(org.springframework.context.ConfigurableApplicationContext, java.lang.Throwable);
    Code:
       0: new           #111                // class org/springframework/boot/context/event/ApplicationFailedEvent
       3: dup
       4: aload_0
       5: getfield      #7                  // Field application:Lorg/springframework/boot/SpringApplication;
       8: aload_0
       9: getfield      #13                 // Field args:[Ljava/lang/String;
      12: aload_1
      13: aload_2
      14: invokespecial #113                // Method org/springframework/boot/context/event/ApplicationFailedEvent."<init>":(Lorg/springframework/boot/SpringApplication;[Ljava/lang/String;Lorg/springframework/context/ConfigurableApplicationContext;Ljava/lang/Throwable;)V
      17: astore_3
      18: aload_1
      19: ifnull        41
      22: aload_1
      23: invokeinterface #116,  1          // InterfaceMethod org/springframework/context/ConfigurableApplicationContext.isActive:()Z
      28: ifeq          41
      31: aload_1
      32: aload_3
      33: invokeinterface #87,  2           // InterfaceMethod org/springframework/context/ConfigurableApplicationContext.publishEvent:(Lorg/springframework/context/ApplicationEvent;)V
      38: goto          122
      41: aload_1
      42: instanceof    #119                // class org/springframework/context/support/AbstractApplicationContext
      45: ifeq          100
      48: aload_1
      49: checkcast     #119                // class org/springframework/context/support/AbstractApplicationContext
      52: astore        4
      54: aload         4
      56: invokevirtual #121                // Method org/springframework/context/support/AbstractApplicationContext.getApplicationListeners:()Ljava/util/Collection;
      59: invokeinterface #125,  1          // InterfaceMethod java/util/Collection.iterator:()Ljava/util/Iterator;
      64: astore        5
      66: aload         5
      68: invokeinterface #55,  1           // InterfaceMethod java/util/Iterator.hasNext:()Z
      73: ifeq          100
      76: aload         5
      78: invokeinterface #61,  1           // InterfaceMethod java/util/Iterator.next:()Ljava/lang/Object;
      83: checkcast     #65                 // class org/springframework/context/ApplicationListener
      86: astore        6
      88: aload_0
      89: getfield      #20                 // Field initialMulticaster:Lorg/springframework/context/event/SimpleApplicationEventMulticaster;
      92: aload         6
      94: invokevirtual #128                // Method org/springframework/context/event/SimpleApplicationEventMulticaster.addApplicationListener:(Lorg/springframework/context/ApplicationListener;)V
      97: goto          66
     100: aload_0
     101: getfield      #20                 // Field initialMulticaster:Lorg/springframework/context/event/SimpleApplicationEventMulticaster;
     104: new           #129                // class org/springframework/boot/context/event/EventPublishingRunListener$LoggingErrorHandler
     107: dup
     108: invokespecial #131                // Method org/springframework/boot/context/event/EventPublishingRunListener$LoggingErrorHandler."<init>":()V
     111: invokevirtual #132                // Method org/springframework/context/event/SimpleApplicationEventMulticaster.setErrorHandler:(Lorg/springframework/util/ErrorHandler;)V
     114: aload_0
     115: getfield      #20                 // Field initialMulticaster:Lorg/springframework/context/event/SimpleApplicationEventMulticaster;
     118: aload_3
     119: invokevirtual #136                // Method org/springframework/context/event/SimpleApplicationEventMulticaster.multicastEvent:(Lorg/springframework/context/ApplicationEvent;)V
     122: return

  private void multicastInitialEvent(org.springframework.context.ApplicationEvent);
    Code:
       0: aload_0
       1: invokevirtual #139                // Method refreshApplicationListeners:()V
       4: aload_0
       5: getfield      #20                 // Field initialMulticaster:Lorg/springframework/context/event/SimpleApplicationEventMulticaster;
       8: aload_1
       9: invokevirtual #136                // Method org/springframework/context/event/SimpleApplicationEventMulticaster.multicastEvent:(Lorg/springframework/context/ApplicationEvent;)V
      12: return

  private void refreshApplicationListeners();
    Code:
       0: aload_0
       1: getfield      #7                  // Field application:Lorg/springframework/boot/SpringApplication;
       4: invokevirtual #43                 // Method org/springframework/boot/SpringApplication.getListeners:()Ljava/util/Set;
       7: aload_0
       8: getfield      #20                 // Field initialMulticaster:Lorg/springframework/context/event/SimpleApplicationEventMulticaster;
      11: dup
      12: invokestatic  #142                // Method java/util/Objects.requireNonNull:(Ljava/lang/Object;)Ljava/lang/Object;
      15: pop
      16: invokedynamic #148,  0            // InvokeDynamic #0:accept:(Lorg/springframework/context/event/SimpleApplicationEventMulticaster;)Ljava/util/function/Consumer;
      21: invokeinterface #152,  2          // InterfaceMethod java/util/Set.forEach:(Ljava/util/function/Consumer;)V
      26: return
}
