Compiled from "CachingConfigurationPropertySource.java"
interface org.springframework.boot.context.properties.source.CachingConfigurationPropertySource {
  public abstract org.springframework.boot.context.properties.source.ConfigurationPropertyCaching getCaching();

  public static org.springframework.boot.context.properties.source.ConfigurationPropertyCaching find(org.springframework.boot.context.properties.source.ConfigurationPropertySource);
    Code:
       0: aload_0
       1: instanceof    #1                  // class org/springframework/boot/context/properties/source/CachingConfigurationPropertySource
       4: ifeq          19
       7: aload_0
       8: checkcast     #1                  // class org/springframework/boot/context/properties/source/CachingConfigurationPropertySource
      11: astore_1
      12: aload_1
      13: invokeinterface #3,  1            // InterfaceMethod getCaching:()Lorg/springframework/boot/context/properties/source/ConfigurationPropertyCaching;
      18: areturn
      19: aconst_null
      20: areturn
}
