Compiled from "ConfigurationPropertyNameAliases.java"
public final class org.springframework.boot.context.properties.source.ConfigurationPropertyNameAliases implements java.lang.Iterable<org.springframework.boot.context.properties.source.ConfigurationPropertyName> {
  private final org.springframework.util.MultiValueMap<org.springframework.boot.context.properties.source.ConfigurationPropertyName, org.springframework.boot.context.properties.source.ConfigurationPropertyName> aliases;

  public org.springframework.boot.context.properties.source.ConfigurationPropertyNameAliases();
    Code:
       0: aload_0
       1: invokespecial #1                  // Method java/lang/Object."<init>":()V
       4: aload_0
       5: new           #7                  // class org/springframework/util/LinkedMultiValueMap
       8: dup
       9: invokespecial #9                  // Method org/springframework/util/LinkedMultiValueMap."<init>":()V
      12: putfield      #10                 // Field aliases:Lorg/springframework/util/MultiValueMap;
      15: return

  public org.springframework.boot.context.properties.source.ConfigurationPropertyNameAliases(java.lang.String, java.lang.String...);
    Code:
       0: aload_0
       1: invokespecial #1                  // Method java/lang/Object."<init>":()V
       4: aload_0
       5: new           #7                  // class org/springframework/util/LinkedMultiValueMap
       8: dup
       9: invokespecial #9                  // Method org/springframework/util/LinkedMultiValueMap."<init>":()V
      12: putfield      #10                 // Field aliases:Lorg/springframework/util/MultiValueMap;
      15: aload_0
      16: aload_1
      17: aload_2
      18: invokevirtual #16                 // Method addAliases:(Ljava/lang/String;[Ljava/lang/String;)V
      21: return

  public org.springframework.boot.context.properties.source.ConfigurationPropertyNameAliases(org.springframework.boot.context.properties.source.ConfigurationPropertyName, org.springframework.boot.context.properties.source.ConfigurationPropertyName...);
    Code:
       0: aload_0
       1: invokespecial #1                  // Method java/lang/Object."<init>":()V
       4: aload_0
       5: new           #7                  // class org/springframework/util/LinkedMultiValueMap
       8: dup
       9: invokespecial #9                  // Method org/springframework/util/LinkedMultiValueMap."<init>":()V
      12: putfield      #10                 // Field aliases:Lorg/springframework/util/MultiValueMap;
      15: aload_0
      16: aload_1
      17: aload_2
      18: invokevirtual #20                 // Method addAliases:(Lorg/springframework/boot/context/properties/source/ConfigurationPropertyName;[Lorg/springframework/boot/context/properties/source/ConfigurationPropertyName;)V
      21: return

  public void addAliases(java.lang.String, java.lang.String...);
    Code:
       0: aload_1
       1: ldc           #23                 // String Name must not be null
       3: invokestatic  #25                 // Method org/springframework/util/Assert.notNull:(Ljava/lang/Object;Ljava/lang/String;)V
       6: aload_2
       7: ldc           #31                 // String Aliases must not be null
       9: invokestatic  #25                 // Method org/springframework/util/Assert.notNull:(Ljava/lang/Object;Ljava/lang/String;)V
      12: aload_0
      13: aload_1
      14: invokestatic  #33                 // Method org/springframework/boot/context/properties/source/ConfigurationPropertyName.of:(Ljava/lang/CharSequence;)Lorg/springframework/boot/context/properties/source/ConfigurationPropertyName;
      17: aload_2
      18: invokestatic  #39                 // Method java/util/Arrays.stream:([Ljava/lang/Object;)Ljava/util/stream/Stream;
      21: invokedynamic #45,  0             // InvokeDynamic #0:apply:()Ljava/util/function/Function;
      26: invokeinterface #49,  2           // InterfaceMethod java/util/stream/Stream.map:(Ljava/util/function/Function;)Ljava/util/stream/Stream;
      31: invokedynamic #55,  0             // InvokeDynamic #1:apply:()Ljava/util/function/IntFunction;
      36: invokeinterface #58,  2           // InterfaceMethod java/util/stream/Stream.toArray:(Ljava/util/function/IntFunction;)[Ljava/lang/Object;
      41: checkcast     #62                 // class "[Lorg/springframework/boot/context/properties/source/ConfigurationPropertyName;"
      44: invokevirtual #20                 // Method addAliases:(Lorg/springframework/boot/context/properties/source/ConfigurationPropertyName;[Lorg/springframework/boot/context/properties/source/ConfigurationPropertyName;)V
      47: return

  public void addAliases(org.springframework.boot.context.properties.source.ConfigurationPropertyName, org.springframework.boot.context.properties.source.ConfigurationPropertyName...);
    Code:
       0: aload_1
       1: ldc           #23                 // String Name must not be null
       3: invokestatic  #25                 // Method org/springframework/util/Assert.notNull:(Ljava/lang/Object;Ljava/lang/String;)V
       6: aload_2
       7: ldc           #31                 // String Aliases must not be null
       9: invokestatic  #25                 // Method org/springframework/util/Assert.notNull:(Ljava/lang/Object;Ljava/lang/String;)V
      12: aload_0
      13: getfield      #10                 // Field aliases:Lorg/springframework/util/MultiValueMap;
      16: aload_1
      17: aload_2
      18: invokestatic  #64                 // Method java/util/Arrays.asList:([Ljava/lang/Object;)Ljava/util/List;
      21: invokeinterface #68,  3           // InterfaceMethod org/springframework/util/MultiValueMap.addAll:(Ljava/lang/Object;Ljava/util/List;)V
      26: return

  public java.util.List<org.springframework.boot.context.properties.source.ConfigurationPropertyName> getAliases(org.springframework.boot.context.properties.source.ConfigurationPropertyName);
    Code:
       0: aload_0
       1: getfield      #10                 // Field aliases:Lorg/springframework/util/MultiValueMap;
       4: aload_1
       5: invokestatic  #74                 // Method java/util/Collections.emptyList:()Ljava/util/List;
       8: invokeinterface #80,  3           // InterfaceMethod org/springframework/util/MultiValueMap.getOrDefault:(Ljava/lang/Object;Ljava/lang/Object;)Ljava/lang/Object;
      13: checkcast     #84                 // class java/util/List
      16: areturn

  public org.springframework.boot.context.properties.source.ConfigurationPropertyName getNameForAlias(org.springframework.boot.context.properties.source.ConfigurationPropertyName);
    Code:
       0: aload_0
       1: getfield      #10                 // Field aliases:Lorg/springframework/util/MultiValueMap;
       4: invokeinterface #86,  1           // InterfaceMethod org/springframework/util/MultiValueMap.entrySet:()Ljava/util/Set;
       9: invokeinterface #90,  1           // InterfaceMethod java/util/Set.stream:()Ljava/util/stream/Stream;
      14: aload_1
      15: invokedynamic #95,  0             // InvokeDynamic #2:test:(Lorg/springframework/boot/context/properties/source/ConfigurationPropertyName;)Ljava/util/function/Predicate;
      20: invokeinterface #99,  2           // InterfaceMethod java/util/stream/Stream.filter:(Ljava/util/function/Predicate;)Ljava/util/stream/Stream;
      25: invokedynamic #103,  0            // InvokeDynamic #3:apply:()Ljava/util/function/Function;
      30: invokeinterface #49,  2           // InterfaceMethod java/util/stream/Stream.map:(Ljava/util/function/Function;)Ljava/util/stream/Stream;
      35: invokeinterface #104,  1          // InterfaceMethod java/util/stream/Stream.findFirst:()Ljava/util/Optional;
      40: aconst_null
      41: invokevirtual #108                // Method java/util/Optional.orElse:(Ljava/lang/Object;)Ljava/lang/Object;
      44: checkcast     #34                 // class org/springframework/boot/context/properties/source/ConfigurationPropertyName
      47: areturn

  public java.util.Iterator<org.springframework.boot.context.properties.source.ConfigurationPropertyName> iterator();
    Code:
       0: aload_0
       1: getfield      #10                 // Field aliases:Lorg/springframework/util/MultiValueMap;
       4: invokeinterface #114,  1          // InterfaceMethod org/springframework/util/MultiValueMap.keySet:()Ljava/util/Set;
       9: invokeinterface #117,  1          // InterfaceMethod java/util/Set.iterator:()Ljava/util/Iterator;
      14: areturn

  private static boolean lambda$getNameForAlias$1(org.springframework.boot.context.properties.source.ConfigurationPropertyName, java.util.Map$Entry);
    Code:
       0: aload_1
       1: invokeinterface #121,  1          // InterfaceMethod java/util/Map$Entry.getValue:()Ljava/lang/Object;
       6: checkcast     #84                 // class java/util/List
       9: aload_0
      10: invokeinterface #127,  2          // InterfaceMethod java/util/List.contains:(Ljava/lang/Object;)Z
      15: ireturn

  private static org.springframework.boot.context.properties.source.ConfigurationPropertyName[] lambda$addAliases$0(int);
    Code:
       0: iload_0
       1: anewarray     #34                 // class org/springframework/boot/context/properties/source/ConfigurationPropertyName
       4: areturn
}
