Compiled from "ConfigurationPropertySourcesPropertyResolver.java"
class org.springframework.boot.context.properties.source.ConfigurationPropertySourcesPropertyResolver$DefaultResolver extends org.springframework.core.env.PropertySourcesPropertyResolver {
  org.springframework.boot.context.properties.source.ConfigurationPropertySourcesPropertyResolver$DefaultResolver(org.springframework.core.env.PropertySources);
    Code:
       0: aload_0
       1: aload_1
       2: invokespecial #1                  // Method org/springframework/core/env/PropertySourcesPropertyResolver."<init>":(Lorg/springframework/core/env/PropertySources;)V
       5: return

  public <T> T getProperty(java.lang.String, java.lang.Class<T>, boolean);
    Code:
       0: aload_0
       1: aload_1
       2: aload_2
       3: iload_3
       4: invokespecial #7                  // Method org/springframework/core/env/PropertySourcesPropertyResolver.getProperty:(Ljava/lang/String;Ljava/lang/Class;Z)Ljava/lang/Object;
       7: areturn
}
