Compiled from "ConfigurationPropertySourcesPropertyResolver.java"
class org.springframework.boot.context.properties.source.ConfigurationPropertySourcesPropertyResolver extends org.springframework.core.env.AbstractPropertyResolver {
  private final org.springframework.core.env.MutablePropertySources propertySources;

  private final org.springframework.boot.context.properties.source.ConfigurationPropertySourcesPropertyResolver$DefaultResolver defaultResolver;

  org.springframework.boot.context.properties.source.ConfigurationPropertySourcesPropertyResolver(org.springframework.core.env.MutablePropertySources);
    Code:
       0: aload_0
       1: invokespecial #1                  // Method org/springframework/core/env/AbstractPropertyResolver."<init>":()V
       4: aload_0
       5: aload_1
       6: putfield      #7                  // Field propertySources:Lorg/springframework/core/env/MutablePropertySources;
       9: aload_0
      10: new           #13                 // class org/springframework/boot/context/properties/source/ConfigurationPropertySourcesPropertyResolver$DefaultResolver
      13: dup
      14: aload_1
      15: invokespecial #15                 // Method org/springframework/boot/context/properties/source/ConfigurationPropertySourcesPropertyResolver$DefaultResolver."<init>":(Lorg/springframework/core/env/PropertySources;)V
      18: putfield      #18                 // Field defaultResolver:Lorg/springframework/boot/context/properties/source/ConfigurationPropertySourcesPropertyResolver$DefaultResolver;
      21: return

  public boolean containsProperty(java.lang.String);
    Code:
       0: aload_0
       1: invokevirtual #22                 // Method getAttached:()Lorg/springframework/boot/context/properties/source/ConfigurationPropertySourcesPropertySource;
       4: astore_2
       5: aload_2
       6: ifnull        35
       9: aload_1
      10: iconst_1
      11: invokestatic  #26                 // Method org/springframework/boot/context/properties/source/ConfigurationPropertyName.of:(Ljava/lang/CharSequence;Z)Lorg/springframework/boot/context/properties/source/ConfigurationPropertyName;
      14: astore_3
      15: aload_3
      16: ifnull        35
      19: aload_2
      20: aload_3
      21: invokevirtual #32                 // Method org/springframework/boot/context/properties/source/ConfigurationPropertySourcesPropertySource.findConfigurationProperty:(Lorg/springframework/boot/context/properties/source/ConfigurationPropertyName;)Lorg/springframework/boot/context/properties/source/ConfigurationProperty;
      24: ifnull        31
      27: iconst_1
      28: goto          32
      31: iconst_0
      32: ireturn
      33: astore        4
      35: aload_0
      36: getfield      #18                 // Field defaultResolver:Lorg/springframework/boot/context/properties/source/ConfigurationPropertySourcesPropertyResolver$DefaultResolver;
      39: aload_1
      40: invokevirtual #40                 // Method org/springframework/boot/context/properties/source/ConfigurationPropertySourcesPropertyResolver$DefaultResolver.containsProperty:(Ljava/lang/String;)Z
      43: ireturn
    Exception table:
       from    to  target type
          19    32    33   Class java/lang/Exception

  public java.lang.String getProperty(java.lang.String);
    Code:
       0: aload_0
       1: aload_1
       2: ldc           #44                 // class java/lang/String
       4: iconst_1
       5: invokevirtual #46                 // Method getProperty:(Ljava/lang/String;Ljava/lang/Class;Z)Ljava/lang/Object;
       8: checkcast     #44                 // class java/lang/String
      11: areturn

  public <T> T getProperty(java.lang.String, java.lang.Class<T>);
    Code:
       0: aload_0
       1: aload_1
       2: aload_2
       3: iconst_1
       4: invokevirtual #46                 // Method getProperty:(Ljava/lang/String;Ljava/lang/Class;Z)Ljava/lang/Object;
       7: areturn

  protected java.lang.String getPropertyAsRawString(java.lang.String);
    Code:
       0: aload_0
       1: aload_1
       2: ldc           #44                 // class java/lang/String
       4: iconst_0
       5: invokevirtual #46                 // Method getProperty:(Ljava/lang/String;Ljava/lang/Class;Z)Ljava/lang/Object;
       8: checkcast     #44                 // class java/lang/String
      11: areturn

  private <T> T getProperty(java.lang.String, java.lang.Class<T>, boolean);
    Code:
       0: aload_0
       1: aload_1
       2: invokevirtual #50                 // Method findPropertyValue:(Ljava/lang/String;)Ljava/lang/Object;
       5: astore        4
       7: aload         4
       9: ifnonnull     14
      12: aconst_null
      13: areturn
      14: iload_3
      15: ifeq          41
      18: aload         4
      20: instanceof    #44                 // class java/lang/String
      23: ifeq          41
      26: aload         4
      28: checkcast     #44                 // class java/lang/String
      31: astore        5
      33: aload_0
      34: aload         5
      36: invokevirtual #54                 // Method resolveNestedPlaceholders:(Ljava/lang/String;)Ljava/lang/String;
      39: astore        4
      41: aload_0
      42: aload         4
      44: aload_2
      45: invokevirtual #58                 // Method convertValueIfNecessary:(Ljava/lang/Object;Ljava/lang/Class;)Ljava/lang/Object;
      48: areturn

  private java.lang.Object findPropertyValue(java.lang.String);
    Code:
       0: aload_0
       1: invokevirtual #22                 // Method getAttached:()Lorg/springframework/boot/context/properties/source/ConfigurationPropertySourcesPropertySource;
       4: astore_2
       5: aload_2
       6: ifnull        43
       9: aload_1
      10: iconst_1
      11: invokestatic  #26                 // Method org/springframework/boot/context/properties/source/ConfigurationPropertyName.of:(Ljava/lang/CharSequence;Z)Lorg/springframework/boot/context/properties/source/ConfigurationPropertyName;
      14: astore_3
      15: aload_3
      16: ifnull        43
      19: aload_2
      20: aload_3
      21: invokevirtual #32                 // Method org/springframework/boot/context/properties/source/ConfigurationPropertySourcesPropertySource.findConfigurationProperty:(Lorg/springframework/boot/context/properties/source/ConfigurationPropertyName;)Lorg/springframework/boot/context/properties/source/ConfigurationProperty;
      24: astore        4
      26: aload         4
      28: ifnull        39
      31: aload         4
      33: invokevirtual #62                 // Method org/springframework/boot/context/properties/source/ConfigurationProperty.getValue:()Ljava/lang/Object;
      36: goto          40
      39: aconst_null
      40: areturn
      41: astore        4
      43: aload_0
      44: getfield      #18                 // Field defaultResolver:Lorg/springframework/boot/context/properties/source/ConfigurationPropertySourcesPropertyResolver$DefaultResolver;
      47: aload_1
      48: ldc           #68                 // class java/lang/Object
      50: iconst_0
      51: invokevirtual #70                 // Method org/springframework/boot/context/properties/source/ConfigurationPropertySourcesPropertyResolver$DefaultResolver.getProperty:(Ljava/lang/String;Ljava/lang/Class;Z)Ljava/lang/Object;
      54: areturn
    Exception table:
       from    to  target type
          19    40    41   Class java/lang/Exception

  private org.springframework.boot.context.properties.source.ConfigurationPropertySourcesPropertySource getAttached();
    Code:
       0: aload_0
       1: getfield      #7                  // Field propertySources:Lorg/springframework/core/env/MutablePropertySources;
       4: invokestatic  #71                 // Method org/springframework/boot/context/properties/source/ConfigurationPropertySources.getAttached:(Lorg/springframework/core/env/MutablePropertySources;)Lorg/springframework/core/env/PropertySource;
       7: checkcast     #33                 // class org/springframework/boot/context/properties/source/ConfigurationPropertySourcesPropertySource
      10: astore_1
      11: aload_1
      12: ifnull        25
      15: aload_1
      16: invokevirtual #76                 // Method org/springframework/boot/context/properties/source/ConfigurationPropertySourcesPropertySource.getSource:()Ljava/lang/Object;
      19: checkcast     #79                 // class java/lang/Iterable
      22: goto          26
      25: aconst_null
      26: astore_2
      27: aload_2
      28: instanceof    #81                 // class org/springframework/boot/context/properties/source/SpringConfigurationPropertySources
      31: ifeq          52
      34: aload_2
      35: checkcast     #81                 // class org/springframework/boot/context/properties/source/SpringConfigurationPropertySources
      38: astore_3
      39: aload_3
      40: aload_0
      41: getfield      #7                  // Field propertySources:Lorg/springframework/core/env/MutablePropertySources;
      44: invokevirtual #83                 // Method org/springframework/boot/context/properties/source/SpringConfigurationPropertySources.isUsingSources:(Ljava/lang/Iterable;)Z
      47: ifeq          52
      50: aload_1
      51: areturn
      52: aconst_null
      53: areturn
}
