Compiled from "ConfigurationPropertyName.java"
public final class org.springframework.boot.context.properties.source.ConfigurationPropertyName implements java.lang.Comparable<org.springframework.boot.context.properties.source.ConfigurationPropertyName> {
  private static final java.lang.String EMPTY_STRING;

  public static final org.springframework.boot.context.properties.source.ConfigurationPropertyName EMPTY;

  private final org.springframework.boot.context.properties.source.ConfigurationPropertyName$Elements elements;

  private final java.lang.CharSequence[] uniformElements;

  private java.lang.String string;

  private int hashCode;

  private org.springframework.boot.context.properties.source.ConfigurationPropertyName(org.springframework.boot.context.properties.source.ConfigurationPropertyName$Elements);
    Code:
       0: aload_0
       1: invokespecial #1                  // Method java/lang/Object."<init>":()V
       4: aload_0
       5: aload_1
       6: putfield      #7                  // Field elements:Lorg/springframework/boot/context/properties/source/ConfigurationPropertyName$Elements;
       9: aload_0
      10: aload_1
      11: invokevirtual #13                 // Method org/springframework/boot/context/properties/source/ConfigurationPropertyName$Elements.getSize:()I
      14: anewarray     #19                 // class java/lang/CharSequence
      17: putfield      #21                 // Field uniformElements:[Ljava/lang/CharSequence;
      20: return

  public boolean isEmpty();
    Code:
       0: aload_0
       1: getfield      #7                  // Field elements:Lorg/springframework/boot/context/properties/source/ConfigurationPropertyName$Elements;
       4: invokevirtual #13                 // Method org/springframework/boot/context/properties/source/ConfigurationPropertyName$Elements.getSize:()I
       7: ifne          14
      10: iconst_1
      11: goto          15
      14: iconst_0
      15: ireturn

  public boolean isLastElementIndexed();
    Code:
       0: aload_0
       1: invokevirtual #25                 // Method getNumberOfElements:()I
       4: istore_1
       5: iload_1
       6: ifle          23
       9: aload_0
      10: iload_1
      11: iconst_1
      12: isub
      13: invokevirtual #28                 // Method isIndexed:(I)Z
      16: ifeq          23
      19: iconst_1
      20: goto          24
      23: iconst_0
      24: ireturn

  public boolean hasIndexedElement();
    Code:
       0: iconst_0
       1: istore_1
       2: iload_1
       3: aload_0
       4: invokevirtual #25                 // Method getNumberOfElements:()I
       7: if_icmpge     26
      10: aload_0
      11: iload_1
      12: invokevirtual #28                 // Method isIndexed:(I)Z
      15: ifeq          20
      18: iconst_1
      19: ireturn
      20: iinc          1, 1
      23: goto          2
      26: iconst_0
      27: ireturn

  boolean isIndexed(int);
    Code:
       0: aload_0
       1: getfield      #7                  // Field elements:Lorg/springframework/boot/context/properties/source/ConfigurationPropertyName$Elements;
       4: iload_1
       5: invokevirtual #32                 // Method org/springframework/boot/context/properties/source/ConfigurationPropertyName$Elements.getType:(I)Lorg/springframework/boot/context/properties/source/ConfigurationPropertyName$ElementType;
       8: invokevirtual #36                 // Method org/springframework/boot/context/properties/source/ConfigurationPropertyName$ElementType.isIndexed:()Z
      11: ireturn

  public boolean isNumericIndex(int);
    Code:
       0: aload_0
       1: getfield      #7                  // Field elements:Lorg/springframework/boot/context/properties/source/ConfigurationPropertyName$Elements;
       4: iload_1
       5: invokevirtual #32                 // Method org/springframework/boot/context/properties/source/ConfigurationPropertyName$Elements.getType:(I)Lorg/springframework/boot/context/properties/source/ConfigurationPropertyName$ElementType;
       8: getstatic     #41                 // Field org/springframework/boot/context/properties/source/ConfigurationPropertyName$ElementType.NUMERICALLY_INDEXED:Lorg/springframework/boot/context/properties/source/ConfigurationPropertyName$ElementType;
      11: if_acmpne     18
      14: iconst_1
      15: goto          19
      18: iconst_0
      19: ireturn

  public java.lang.String getLastElement(org.springframework.boot.context.properties.source.ConfigurationPropertyName$Form);
    Code:
       0: aload_0
       1: invokevirtual #25                 // Method getNumberOfElements:()I
       4: istore_2
       5: iload_2
       6: ifeq          20
       9: aload_0
      10: iload_2
      11: iconst_1
      12: isub
      13: aload_1
      14: invokevirtual #45                 // Method getElement:(ILorg/springframework/boot/context/properties/source/ConfigurationPropertyName$Form;)Ljava/lang/String;
      17: goto          22
      20: ldc           #49                 // String
      22: areturn

  public java.lang.String getElement(int, org.springframework.boot.context.properties.source.ConfigurationPropertyName$Form);
    Code:
       0: aload_0
       1: getfield      #7                  // Field elements:Lorg/springframework/boot/context/properties/source/ConfigurationPropertyName$Elements;
       4: iload_1
       5: invokevirtual #51                 // Method org/springframework/boot/context/properties/source/ConfigurationPropertyName$Elements.get:(I)Ljava/lang/CharSequence;
       8: astore_3
       9: aload_0
      10: getfield      #7                  // Field elements:Lorg/springframework/boot/context/properties/source/ConfigurationPropertyName$Elements;
      13: iload_1
      14: invokevirtual #32                 // Method org/springframework/boot/context/properties/source/ConfigurationPropertyName$Elements.getType:(I)Lorg/springframework/boot/context/properties/source/ConfigurationPropertyName$ElementType;
      17: astore        4
      19: aload         4
      21: invokevirtual #36                 // Method org/springframework/boot/context/properties/source/ConfigurationPropertyName$ElementType.isIndexed:()Z
      24: ifeq          34
      27: aload_3
      28: invokeinterface #55,  1           // InterfaceMethod java/lang/CharSequence.toString:()Ljava/lang/String;
      33: areturn
      34: aload_2
      35: getstatic     #59                 // Field org/springframework/boot/context/properties/source/ConfigurationPropertyName$Form.ORIGINAL:Lorg/springframework/boot/context/properties/source/ConfigurationPropertyName$Form;
      38: if_acmpne     67
      41: aload         4
      43: getstatic     #65                 // Field org/springframework/boot/context/properties/source/ConfigurationPropertyName$ElementType.NON_UNIFORM:Lorg/springframework/boot/context/properties/source/ConfigurationPropertyName$ElementType;
      46: if_acmpeq     56
      49: aload_3
      50: invokeinterface #55,  1           // InterfaceMethod java/lang/CharSequence.toString:()Ljava/lang/String;
      55: areturn
      56: aload_0
      57: aload_3
      58: invokevirtual #68                 // Method convertToOriginalForm:(Ljava/lang/CharSequence;)Ljava/lang/CharSequence;
      61: invokeinterface #55,  1           // InterfaceMethod java/lang/CharSequence.toString:()Ljava/lang/String;
      66: areturn
      67: aload_2
      68: getstatic     #72                 // Field org/springframework/boot/context/properties/source/ConfigurationPropertyName$Form.DASHED:Lorg/springframework/boot/context/properties/source/ConfigurationPropertyName$Form;
      71: if_acmpne     108
      74: aload         4
      76: getstatic     #75                 // Field org/springframework/boot/context/properties/source/ConfigurationPropertyName$ElementType.UNIFORM:Lorg/springframework/boot/context/properties/source/ConfigurationPropertyName$ElementType;
      79: if_acmpeq     90
      82: aload         4
      84: getstatic     #78                 // Field org/springframework/boot/context/properties/source/ConfigurationPropertyName$ElementType.DASHED:Lorg/springframework/boot/context/properties/source/ConfigurationPropertyName$ElementType;
      87: if_acmpne     97
      90: aload_3
      91: invokeinterface #55,  1           // InterfaceMethod java/lang/CharSequence.toString:()Ljava/lang/String;
      96: areturn
      97: aload_0
      98: aload_3
      99: invokevirtual #80                 // Method convertToDashedElement:(Ljava/lang/CharSequence;)Ljava/lang/CharSequence;
     102: invokeinterface #55,  1           // InterfaceMethod java/lang/CharSequence.toString:()Ljava/lang/String;
     107: areturn
     108: aload_0
     109: getfield      #21                 // Field uniformElements:[Ljava/lang/CharSequence;
     112: iload_1
     113: aaload
     114: astore        5
     116: aload         5
     118: ifnonnull     153
     121: aload         4
     123: getstatic     #75                 // Field org/springframework/boot/context/properties/source/ConfigurationPropertyName$ElementType.UNIFORM:Lorg/springframework/boot/context/properties/source/ConfigurationPropertyName$ElementType;
     126: if_acmpeq     137
     129: aload_0
     130: aload_3
     131: invokevirtual #83                 // Method convertToUniformElement:(Ljava/lang/CharSequence;)Ljava/lang/CharSequence;
     134: goto          138
     137: aload_3
     138: astore        5
     140: aload_0
     141: getfield      #21                 // Field uniformElements:[Ljava/lang/CharSequence;
     144: iload_1
     145: aload         5
     147: invokeinterface #55,  1           // InterfaceMethod java/lang/CharSequence.toString:()Ljava/lang/String;
     152: aastore
     153: aload         5
     155: invokeinterface #55,  1           // InterfaceMethod java/lang/CharSequence.toString:()Ljava/lang/String;
     160: areturn

  private java.lang.CharSequence convertToOriginalForm(java.lang.CharSequence);
    Code:
       0: aload_0
       1: aload_1
       2: iconst_0
       3: invokedynamic #86,  0             // InvokeDynamic #0:test:()Lorg/springframework/boot/context/properties/source/ConfigurationPropertyName$ElementCharPredicate;
       8: invokevirtual #90                 // Method convertElement:(Ljava/lang/CharSequence;ZLorg/springframework/boot/context/properties/source/ConfigurationPropertyName$ElementCharPredicate;)Ljava/lang/CharSequence;
      11: areturn

  private java.lang.CharSequence convertToDashedElement(java.lang.CharSequence);
    Code:
       0: aload_0
       1: aload_1
       2: iconst_1
       3: invokedynamic #94,  0             // InvokeDynamic #1:test:()Lorg/springframework/boot/context/properties/source/ConfigurationPropertyName$ElementCharPredicate;
       8: invokevirtual #90                 // Method convertElement:(Ljava/lang/CharSequence;ZLorg/springframework/boot/context/properties/source/ConfigurationPropertyName$ElementCharPredicate;)Ljava/lang/CharSequence;
      11: areturn

  private java.lang.CharSequence convertToUniformElement(java.lang.CharSequence);
    Code:
       0: aload_0
       1: aload_1
       2: iconst_1
       3: invokedynamic #95,  0             // InvokeDynamic #2:test:()Lorg/springframework/boot/context/properties/source/ConfigurationPropertyName$ElementCharPredicate;
       8: invokevirtual #90                 // Method convertElement:(Ljava/lang/CharSequence;ZLorg/springframework/boot/context/properties/source/ConfigurationPropertyName$ElementCharPredicate;)Ljava/lang/CharSequence;
      11: areturn

  private java.lang.CharSequence convertElement(java.lang.CharSequence, boolean, org.springframework.boot.context.properties.source.ConfigurationPropertyName$ElementCharPredicate);
    Code:
       0: new           #96                 // class java/lang/StringBuilder
       3: dup
       4: aload_1
       5: invokeinterface #98,  1           // InterfaceMethod java/lang/CharSequence.length:()I
      10: invokespecial #101                // Method java/lang/StringBuilder."<init>":(I)V
      13: astore        4
      15: iconst_0
      16: istore        5
      18: iload         5
      20: aload_1
      21: invokeinterface #98,  1           // InterfaceMethod java/lang/CharSequence.length:()I
      26: if_icmpge     84
      29: iload_2
      30: ifeq          47
      33: aload_1
      34: iload         5
      36: invokeinterface #104,  2          // InterfaceMethod java/lang/CharSequence.charAt:(I)C
      41: invokestatic  #108                // Method java/lang/Character.toLowerCase:(C)C
      44: goto          55
      47: aload_1
      48: iload         5
      50: invokeinterface #104,  2          // InterfaceMethod java/lang/CharSequence.charAt:(I)C
      55: istore        6
      57: aload_3
      58: iload         6
      60: iload         5
      62: invokeinterface #114,  3          // InterfaceMethod org/springframework/boot/context/properties/source/ConfigurationPropertyName$ElementCharPredicate.test:(CI)Z
      67: ifeq          78
      70: aload         4
      72: iload         6
      74: invokevirtual #119                // Method java/lang/StringBuilder.append:(C)Ljava/lang/StringBuilder;
      77: pop
      78: iinc          5, 1
      81: goto          18
      84: aload         4
      86: areturn

  public int getNumberOfElements();
    Code:
       0: aload_0
       1: getfield      #7                  // Field elements:Lorg/springframework/boot/context/properties/source/ConfigurationPropertyName$Elements;
       4: invokevirtual #13                 // Method org/springframework/boot/context/properties/source/ConfigurationPropertyName$Elements.getSize:()I
       7: ireturn

  public org.springframework.boot.context.properties.source.ConfigurationPropertyName append(java.lang.String);
    Code:
       0: aload_1
       1: invokestatic  #123                // Method org/springframework/util/StringUtils.hasLength:(Ljava/lang/String;)Z
       4: ifne          9
       7: aload_0
       8: areturn
       9: aload_1
      10: invokestatic  #129                // Method probablySingleElementOf:(Ljava/lang/CharSequence;)Lorg/springframework/boot/context/properties/source/ConfigurationPropertyName$Elements;
      13: astore_2
      14: new           #8                  // class org/springframework/boot/context/properties/source/ConfigurationPropertyName
      17: dup
      18: aload_0
      19: getfield      #7                  // Field elements:Lorg/springframework/boot/context/properties/source/ConfigurationPropertyName$Elements;
      22: aload_2
      23: invokevirtual #133                // Method org/springframework/boot/context/properties/source/ConfigurationPropertyName$Elements.append:(Lorg/springframework/boot/context/properties/source/ConfigurationPropertyName$Elements;)Lorg/springframework/boot/context/properties/source/ConfigurationPropertyName$Elements;
      26: invokespecial #136                // Method "<init>":(Lorg/springframework/boot/context/properties/source/ConfigurationPropertyName$Elements;)V
      29: areturn

  public org.springframework.boot.context.properties.source.ConfigurationPropertyName append(org.springframework.boot.context.properties.source.ConfigurationPropertyName);
    Code:
       0: aload_1
       1: ifnonnull     6
       4: aload_0
       5: areturn
       6: new           #8                  // class org/springframework/boot/context/properties/source/ConfigurationPropertyName
       9: dup
      10: aload_0
      11: getfield      #7                  // Field elements:Lorg/springframework/boot/context/properties/source/ConfigurationPropertyName$Elements;
      14: aload_1
      15: getfield      #7                  // Field elements:Lorg/springframework/boot/context/properties/source/ConfigurationPropertyName$Elements;
      18: invokevirtual #133                // Method org/springframework/boot/context/properties/source/ConfigurationPropertyName$Elements.append:(Lorg/springframework/boot/context/properties/source/ConfigurationPropertyName$Elements;)Lorg/springframework/boot/context/properties/source/ConfigurationPropertyName$Elements;
      21: invokespecial #136                // Method "<init>":(Lorg/springframework/boot/context/properties/source/ConfigurationPropertyName$Elements;)V
      24: areturn

  public org.springframework.boot.context.properties.source.ConfigurationPropertyName getParent();
    Code:
       0: aload_0
       1: invokevirtual #25                 // Method getNumberOfElements:()I
       4: istore_1
       5: iload_1
       6: iconst_1
       7: if_icmpgt     16
      10: getstatic     #139                // Field EMPTY:Lorg/springframework/boot/context/properties/source/ConfigurationPropertyName;
      13: goto          23
      16: aload_0
      17: iload_1
      18: iconst_1
      19: isub
      20: invokevirtual #143                // Method chop:(I)Lorg/springframework/boot/context/properties/source/ConfigurationPropertyName;
      23: areturn

  public org.springframework.boot.context.properties.source.ConfigurationPropertyName chop(int);
    Code:
       0: iload_1
       1: aload_0
       2: invokevirtual #25                 // Method getNumberOfElements:()I
       5: if_icmplt     10
       8: aload_0
       9: areturn
      10: new           #8                  // class org/springframework/boot/context/properties/source/ConfigurationPropertyName
      13: dup
      14: aload_0
      15: getfield      #7                  // Field elements:Lorg/springframework/boot/context/properties/source/ConfigurationPropertyName$Elements;
      18: iload_1
      19: invokevirtual #147                // Method org/springframework/boot/context/properties/source/ConfigurationPropertyName$Elements.chop:(I)Lorg/springframework/boot/context/properties/source/ConfigurationPropertyName$Elements;
      22: invokespecial #136                // Method "<init>":(Lorg/springframework/boot/context/properties/source/ConfigurationPropertyName$Elements;)V
      25: areturn

  public org.springframework.boot.context.properties.source.ConfigurationPropertyName subName(int);
    Code:
       0: iload_1
       1: ifne          6
       4: aload_0
       5: areturn
       6: iload_1
       7: aload_0
       8: invokevirtual #25                 // Method getNumberOfElements:()I
      11: if_icmpne     18
      14: getstatic     #139                // Field EMPTY:Lorg/springframework/boot/context/properties/source/ConfigurationPropertyName;
      17: areturn
      18: iload_1
      19: iflt          30
      22: iload_1
      23: aload_0
      24: invokevirtual #25                 // Method getNumberOfElements:()I
      27: if_icmple     48
      30: new           #150                // class java/lang/IndexOutOfBoundsException
      33: dup
      34: iload_1
      35: aload_0
      36: invokevirtual #25                 // Method getNumberOfElements:()I
      39: invokedynamic #152,  0            // InvokeDynamic #3:makeConcatWithConstants:(II)Ljava/lang/String;
      44: invokespecial #156                // Method java/lang/IndexOutOfBoundsException."<init>":(Ljava/lang/String;)V
      47: athrow
      48: new           #8                  // class org/springframework/boot/context/properties/source/ConfigurationPropertyName
      51: dup
      52: aload_0
      53: getfield      #7                  // Field elements:Lorg/springframework/boot/context/properties/source/ConfigurationPropertyName$Elements;
      56: iload_1
      57: invokevirtual #159                // Method org/springframework/boot/context/properties/source/ConfigurationPropertyName$Elements.subElements:(I)Lorg/springframework/boot/context/properties/source/ConfigurationPropertyName$Elements;
      60: invokespecial #136                // Method "<init>":(Lorg/springframework/boot/context/properties/source/ConfigurationPropertyName$Elements;)V
      63: areturn

  public boolean isParentOf(org.springframework.boot.context.properties.source.ConfigurationPropertyName);
    Code:
       0: aload_1
       1: ldc           #162                // String Name must not be null
       3: invokestatic  #164                // Method org/springframework/util/Assert.notNull:(Ljava/lang/Object;Ljava/lang/String;)V
       6: aload_0
       7: invokevirtual #25                 // Method getNumberOfElements:()I
      10: aload_1
      11: invokevirtual #25                 // Method getNumberOfElements:()I
      14: iconst_1
      15: isub
      16: if_icmpeq     21
      19: iconst_0
      20: ireturn
      21: aload_0
      22: aload_1
      23: invokevirtual #170                // Method isAncestorOf:(Lorg/springframework/boot/context/properties/source/ConfigurationPropertyName;)Z
      26: ireturn

  public boolean isAncestorOf(org.springframework.boot.context.properties.source.ConfigurationPropertyName);
    Code:
       0: aload_1
       1: ldc           #162                // String Name must not be null
       3: invokestatic  #164                // Method org/springframework/util/Assert.notNull:(Ljava/lang/Object;Ljava/lang/String;)V
       6: aload_0
       7: invokevirtual #25                 // Method getNumberOfElements:()I
      10: aload_1
      11: invokevirtual #25                 // Method getNumberOfElements:()I
      14: if_icmplt     19
      17: iconst_0
      18: ireturn
      19: aload_0
      20: aload_1
      21: invokevirtual #174                // Method elementsEqual:(Lorg/springframework/boot/context/properties/source/ConfigurationPropertyName;)Z
      24: ireturn

  public int compareTo(org.springframework.boot.context.properties.source.ConfigurationPropertyName);
    Code:
       0: aload_0
       1: aload_0
       2: aload_1
       3: invokevirtual #177                // Method compare:(Lorg/springframework/boot/context/properties/source/ConfigurationPropertyName;Lorg/springframework/boot/context/properties/source/ConfigurationPropertyName;)I
       6: ireturn

  private int compare(org.springframework.boot.context.properties.source.ConfigurationPropertyName, org.springframework.boot.context.properties.source.ConfigurationPropertyName);
    Code:
       0: aload_1
       1: invokevirtual #25                 // Method getNumberOfElements:()I
       4: istore_3
       5: aload_2
       6: invokevirtual #25                 // Method getNumberOfElements:()I
       9: istore        4
      11: iconst_0
      12: istore        5
      14: iconst_0
      15: istore        6
      17: iload         5
      19: iload_3
      20: if_icmplt     30
      23: iload         6
      25: iload         4
      27: if_icmpge     159
      30: iload         5
      32: iload_3
      33: if_icmpge     48
      36: aload_1
      37: getfield      #7                  // Field elements:Lorg/springframework/boot/context/properties/source/ConfigurationPropertyName$Elements;
      40: iload         5
      42: invokevirtual #32                 // Method org/springframework/boot/context/properties/source/ConfigurationPropertyName$Elements.getType:(I)Lorg/springframework/boot/context/properties/source/ConfigurationPropertyName$ElementType;
      45: goto          49
      48: aconst_null
      49: astore        7
      51: iload         6
      53: iload         4
      55: if_icmpge     70
      58: aload_2
      59: getfield      #7                  // Field elements:Lorg/springframework/boot/context/properties/source/ConfigurationPropertyName$Elements;
      62: iload         6
      64: invokevirtual #32                 // Method org/springframework/boot/context/properties/source/ConfigurationPropertyName$Elements.getType:(I)Lorg/springframework/boot/context/properties/source/ConfigurationPropertyName$ElementType;
      67: goto          71
      70: aconst_null
      71: astore        8
      73: iload         5
      75: iload_3
      76: if_icmpge     94
      79: aload_1
      80: iload         5
      82: iinc          5, 1
      85: getstatic     #181                // Field org/springframework/boot/context/properties/source/ConfigurationPropertyName$Form.UNIFORM:Lorg/springframework/boot/context/properties/source/ConfigurationPropertyName$Form;
      88: invokevirtual #45                 // Method getElement:(ILorg/springframework/boot/context/properties/source/ConfigurationPropertyName$Form;)Ljava/lang/String;
      91: goto          95
      94: aconst_null
      95: astore        9
      97: iload         6
      99: iload         4
     101: if_icmpge     119
     104: aload_2
     105: iload         6
     107: iinc          6, 1
     110: getstatic     #181                // Field org/springframework/boot/context/properties/source/ConfigurationPropertyName$Form.UNIFORM:Lorg/springframework/boot/context/properties/source/ConfigurationPropertyName$Form;
     113: invokevirtual #45                 // Method getElement:(ILorg/springframework/boot/context/properties/source/ConfigurationPropertyName$Form;)Ljava/lang/String;
     116: goto          120
     119: aconst_null
     120: astore        10
     122: aload_0
     123: aload         9
     125: aload         7
     127: aload         10
     129: aload         8
     131: invokevirtual #183                // Method compare:(Ljava/lang/String;Lorg/springframework/boot/context/properties/source/ConfigurationPropertyName$ElementType;Ljava/lang/String;Lorg/springframework/boot/context/properties/source/ConfigurationPropertyName$ElementType;)I
     134: istore        11
     136: iload         11
     138: ifeq          144
     141: iload         11
     143: ireturn
     144: goto          17
     147: astore        7
     149: new           #188                // class java/lang/RuntimeException
     152: dup
     153: aload         7
     155: invokespecial #190                // Method java/lang/RuntimeException."<init>":(Ljava/lang/Throwable;)V
     158: athrow
     159: iconst_0
     160: ireturn
    Exception table:
       from    to  target type
          30   143   147   Class java/lang/ArrayIndexOutOfBoundsException

  private int compare(java.lang.String, org.springframework.boot.context.properties.source.ConfigurationPropertyName$ElementType, java.lang.String, org.springframework.boot.context.properties.source.ConfigurationPropertyName$ElementType);
    Code:
       0: aload_1
       1: ifnonnull     6
       4: iconst_m1
       5: ireturn
       6: aload_3
       7: ifnonnull     12
      10: iconst_1
      11: ireturn
      12: aload         4
      14: invokevirtual #36                 // Method org/springframework/boot/context/properties/source/ConfigurationPropertyName$ElementType.isIndexed:()Z
      17: aload_2
      18: invokevirtual #36                 // Method org/springframework/boot/context/properties/source/ConfigurationPropertyName$ElementType.isIndexed:()Z
      21: invokestatic  #193                // Method java/lang/Boolean.compare:(ZZ)I
      24: istore        5
      26: iload         5
      28: ifeq          34
      31: iload         5
      33: ireturn
      34: aload_2
      35: getstatic     #41                 // Field org/springframework/boot/context/properties/source/ConfigurationPropertyName$ElementType.NUMERICALLY_INDEXED:Lorg/springframework/boot/context/properties/source/ConfigurationPropertyName$ElementType;
      38: if_acmpne     69
      41: aload         4
      43: getstatic     #41                 // Field org/springframework/boot/context/properties/source/ConfigurationPropertyName$ElementType.NUMERICALLY_INDEXED:Lorg/springframework/boot/context/properties/source/ConfigurationPropertyName$ElementType;
      46: if_acmpne     69
      49: aload_1
      50: invokestatic  #198                // Method java/lang/Long.parseLong:(Ljava/lang/String;)J
      53: lstore        6
      55: aload_3
      56: invokestatic  #198                // Method java/lang/Long.parseLong:(Ljava/lang/String;)J
      59: lstore        8
      61: lload         6
      63: lload         8
      65: invokestatic  #204                // Method java/lang/Long.compare:(JJ)I
      68: ireturn
      69: aload_1
      70: aload_3
      71: invokevirtual #207                // Method java/lang/String.compareTo:(Ljava/lang/String;)I
      74: ireturn

  public boolean equals(java.lang.Object);
    Code:
       0: aload_1
       1: aload_0
       2: if_acmpne     7
       5: iconst_1
       6: ireturn
       7: aload_1
       8: ifnull        22
      11: aload_1
      12: invokevirtual #213                // Method java/lang/Object.getClass:()Ljava/lang/Class;
      15: aload_0
      16: invokevirtual #213                // Method java/lang/Object.getClass:()Ljava/lang/Class;
      19: if_acmpeq     24
      22: iconst_0
      23: ireturn
      24: aload_1
      25: checkcast     #8                  // class org/springframework/boot/context/properties/source/ConfigurationPropertyName
      28: astore_2
      29: aload_0
      30: invokevirtual #25                 // Method getNumberOfElements:()I
      33: aload_2
      34: invokevirtual #25                 // Method getNumberOfElements:()I
      37: if_icmpeq     42
      40: iconst_0
      41: ireturn
      42: aload_0
      43: getfield      #7                  // Field elements:Lorg/springframework/boot/context/properties/source/ConfigurationPropertyName$Elements;
      46: getstatic     #75                 // Field org/springframework/boot/context/properties/source/ConfigurationPropertyName$ElementType.UNIFORM:Lorg/springframework/boot/context/properties/source/ConfigurationPropertyName$ElementType;
      49: invokevirtual #217                // Method org/springframework/boot/context/properties/source/ConfigurationPropertyName$Elements.canShortcutWithSource:(Lorg/springframework/boot/context/properties/source/ConfigurationPropertyName$ElementType;)Z
      52: ifeq          80
      55: aload_2
      56: getfield      #7                  // Field elements:Lorg/springframework/boot/context/properties/source/ConfigurationPropertyName$Elements;
      59: getstatic     #75                 // Field org/springframework/boot/context/properties/source/ConfigurationPropertyName$ElementType.UNIFORM:Lorg/springframework/boot/context/properties/source/ConfigurationPropertyName$ElementType;
      62: invokevirtual #217                // Method org/springframework/boot/context/properties/source/ConfigurationPropertyName$Elements.canShortcutWithSource:(Lorg/springframework/boot/context/properties/source/ConfigurationPropertyName$ElementType;)Z
      65: ifeq          80
      68: aload_0
      69: invokevirtual #221                // Method toString:()Ljava/lang/String;
      72: aload_2
      73: invokevirtual #221                // Method toString:()Ljava/lang/String;
      76: invokevirtual #222                // Method java/lang/String.equals:(Ljava/lang/Object;)Z
      79: ireturn
      80: aload_0
      81: aload_2
      82: invokevirtual #174                // Method elementsEqual:(Lorg/springframework/boot/context/properties/source/ConfigurationPropertyName;)Z
      85: ireturn

  private boolean elementsEqual(org.springframework.boot.context.properties.source.ConfigurationPropertyName);
    Code:
       0: aload_0
       1: getfield      #7                  // Field elements:Lorg/springframework/boot/context/properties/source/ConfigurationPropertyName$Elements;
       4: invokevirtual #13                 // Method org/springframework/boot/context/properties/source/ConfigurationPropertyName$Elements.getSize:()I
       7: iconst_1
       8: isub
       9: istore_2
      10: iload_2
      11: iflt          38
      14: aload_0
      15: aload_0
      16: getfield      #7                  // Field elements:Lorg/springframework/boot/context/properties/source/ConfigurationPropertyName$Elements;
      19: aload_1
      20: getfield      #7                  // Field elements:Lorg/springframework/boot/context/properties/source/ConfigurationPropertyName$Elements;
      23: iload_2
      24: invokevirtual #226                // Method elementDiffers:(Lorg/springframework/boot/context/properties/source/ConfigurationPropertyName$Elements;Lorg/springframework/boot/context/properties/source/ConfigurationPropertyName$Elements;I)Z
      27: ifeq          32
      30: iconst_0
      31: ireturn
      32: iinc          2, -1
      35: goto          10
      38: iconst_1
      39: ireturn

  private boolean elementDiffers(org.springframework.boot.context.properties.source.ConfigurationPropertyName$Elements, org.springframework.boot.context.properties.source.ConfigurationPropertyName$Elements, int);
    Code:
       0: aload_1
       1: iload_3
       2: invokevirtual #32                 // Method org/springframework/boot/context/properties/source/ConfigurationPropertyName$Elements.getType:(I)Lorg/springframework/boot/context/properties/source/ConfigurationPropertyName$ElementType;
       5: astore        4
       7: aload_2
       8: iload_3
       9: invokevirtual #32                 // Method org/springframework/boot/context/properties/source/ConfigurationPropertyName$Elements.getType:(I)Lorg/springframework/boot/context/properties/source/ConfigurationPropertyName$ElementType;
      12: astore        5
      14: aload         4
      16: invokevirtual #230                // Method org/springframework/boot/context/properties/source/ConfigurationPropertyName$ElementType.allowsFastEqualityCheck:()Z
      19: ifeq          46
      22: aload         5
      24: invokevirtual #230                // Method org/springframework/boot/context/properties/source/ConfigurationPropertyName$ElementType.allowsFastEqualityCheck:()Z
      27: ifeq          46
      30: aload_0
      31: aload_1
      32: aload_2
      33: iload_3
      34: invokevirtual #233                // Method fastElementEquals:(Lorg/springframework/boot/context/properties/source/ConfigurationPropertyName$Elements;Lorg/springframework/boot/context/properties/source/ConfigurationPropertyName$Elements;I)Z
      37: ifne          44
      40: iconst_1
      41: goto          45
      44: iconst_0
      45: ireturn
      46: aload         4
      48: invokevirtual #236                // Method org/springframework/boot/context/properties/source/ConfigurationPropertyName$ElementType.allowsDashIgnoringEqualityCheck:()Z
      51: ifeq          78
      54: aload         5
      56: invokevirtual #236                // Method org/springframework/boot/context/properties/source/ConfigurationPropertyName$ElementType.allowsDashIgnoringEqualityCheck:()Z
      59: ifeq          78
      62: aload_0
      63: aload_1
      64: aload_2
      65: iload_3
      66: invokevirtual #239                // Method dashIgnoringElementEquals:(Lorg/springframework/boot/context/properties/source/ConfigurationPropertyName$Elements;Lorg/springframework/boot/context/properties/source/ConfigurationPropertyName$Elements;I)Z
      69: ifne          76
      72: iconst_1
      73: goto          77
      76: iconst_0
      77: ireturn
      78: aload_0
      79: aload_1
      80: aload_2
      81: iload_3
      82: invokevirtual #242                // Method defaultElementEquals:(Lorg/springframework/boot/context/properties/source/ConfigurationPropertyName$Elements;Lorg/springframework/boot/context/properties/source/ConfigurationPropertyName$Elements;I)Z
      85: ifne          92
      88: iconst_1
      89: goto          93
      92: iconst_0
      93: ireturn

  private boolean fastElementEquals(org.springframework.boot.context.properties.source.ConfigurationPropertyName$Elements, org.springframework.boot.context.properties.source.ConfigurationPropertyName$Elements, int);
    Code:
       0: aload_1
       1: iload_3
       2: invokevirtual #245                // Method org/springframework/boot/context/properties/source/ConfigurationPropertyName$Elements.getLength:(I)I
       5: istore        4
       7: aload_2
       8: iload_3
       9: invokevirtual #245                // Method org/springframework/boot/context/properties/source/ConfigurationPropertyName$Elements.getLength:(I)I
      12: istore        5
      14: iload         4
      16: iload         5
      18: if_icmpne     67
      21: iconst_0
      22: istore        6
      24: iload         4
      26: iinc          4, -1
      29: ifeq          65
      32: aload_1
      33: iload_3
      34: iload         6
      36: invokevirtual #249                // Method org/springframework/boot/context/properties/source/ConfigurationPropertyName$Elements.charAt:(II)C
      39: istore        7
      41: aload_2
      42: iload_3
      43: iload         6
      45: invokevirtual #249                // Method org/springframework/boot/context/properties/source/ConfigurationPropertyName$Elements.charAt:(II)C
      48: istore        8
      50: iload         7
      52: iload         8
      54: if_icmpeq     59
      57: iconst_0
      58: ireturn
      59: iinc          6, 1
      62: goto          24
      65: iconst_1
      66: ireturn
      67: iconst_0
      68: ireturn

  private boolean dashIgnoringElementEquals(org.springframework.boot.context.properties.source.ConfigurationPropertyName$Elements, org.springframework.boot.context.properties.source.ConfigurationPropertyName$Elements, int);
    Code:
       0: aload_1
       1: iload_3
       2: invokevirtual #245                // Method org/springframework/boot/context/properties/source/ConfigurationPropertyName$Elements.getLength:(I)I
       5: istore        4
       7: aload_2
       8: iload_3
       9: invokevirtual #245                // Method org/springframework/boot/context/properties/source/ConfigurationPropertyName$Elements.getLength:(I)I
      12: istore        5
      14: iconst_0
      15: istore        6
      17: iconst_0
      18: istore        7
      20: iload         6
      22: iload         4
      24: if_icmpge     98
      27: iload         7
      29: iload         5
      31: if_icmplt     36
      34: iconst_0
      35: ireturn
      36: aload_1
      37: iload_3
      38: iload         6
      40: invokevirtual #249                // Method org/springframework/boot/context/properties/source/ConfigurationPropertyName$Elements.charAt:(II)C
      43: istore        8
      45: aload_2
      46: iload_3
      47: iload         7
      49: invokevirtual #249                // Method org/springframework/boot/context/properties/source/ConfigurationPropertyName$Elements.charAt:(II)C
      52: istore        9
      54: iload         8
      56: bipush        45
      58: if_icmpne     67
      61: iinc          6, 1
      64: goto          95
      67: iload         9
      69: bipush        45
      71: if_icmpne     80
      74: iinc          7, 1
      77: goto          95
      80: iload         8
      82: iload         9
      84: if_icmpeq     89
      87: iconst_0
      88: ireturn
      89: iinc          6, 1
      92: iinc          7, 1
      95: goto          20
      98: iload         7
     100: iload         5
     102: if_icmpge     146
     105: aload_2
     106: iload_3
     107: invokevirtual #32                 // Method org/springframework/boot/context/properties/source/ConfigurationPropertyName$Elements.getType:(I)Lorg/springframework/boot/context/properties/source/ConfigurationPropertyName$ElementType;
     110: invokevirtual #36                 // Method org/springframework/boot/context/properties/source/ConfigurationPropertyName$ElementType.isIndexed:()Z
     113: ifeq          118
     116: iconst_0
     117: ireturn
     118: aload_2
     119: iload_3
     120: iload         7
     122: iinc          7, 1
     125: invokevirtual #249                // Method org/springframework/boot/context/properties/source/ConfigurationPropertyName$Elements.charAt:(II)C
     128: istore        8
     130: iload         8
     132: bipush        45
     134: if_icmpeq     139
     137: iconst_0
     138: ireturn
     139: iload         7
     141: iload         5
     143: if_icmplt     118
     146: iconst_1
     147: ireturn

  private boolean defaultElementEquals(org.springframework.boot.context.properties.source.ConfigurationPropertyName$Elements, org.springframework.boot.context.properties.source.ConfigurationPropertyName$Elements, int);
    Code:
       0: aload_1
       1: iload_3
       2: invokevirtual #245                // Method org/springframework/boot/context/properties/source/ConfigurationPropertyName$Elements.getLength:(I)I
       5: istore        4
       7: aload_2
       8: iload_3
       9: invokevirtual #245                // Method org/springframework/boot/context/properties/source/ConfigurationPropertyName$Elements.getLength:(I)I
      12: istore        5
      14: aload_1
      15: iload_3
      16: invokevirtual #32                 // Method org/springframework/boot/context/properties/source/ConfigurationPropertyName$Elements.getType:(I)Lorg/springframework/boot/context/properties/source/ConfigurationPropertyName$ElementType;
      19: invokevirtual #36                 // Method org/springframework/boot/context/properties/source/ConfigurationPropertyName$ElementType.isIndexed:()Z
      22: istore        6
      24: aload_2
      25: iload_3
      26: invokevirtual #32                 // Method org/springframework/boot/context/properties/source/ConfigurationPropertyName$Elements.getType:(I)Lorg/springframework/boot/context/properties/source/ConfigurationPropertyName$ElementType;
      29: invokevirtual #36                 // Method org/springframework/boot/context/properties/source/ConfigurationPropertyName$ElementType.isIndexed:()Z
      32: istore        7
      34: iconst_0
      35: istore        8
      37: iconst_0
      38: istore        9
      40: iload         8
      42: iload         4
      44: if_icmpge     173
      47: iload         9
      49: iload         5
      51: if_icmplt     63
      54: aload_0
      55: aload_1
      56: iload_3
      57: iload         8
      59: invokevirtual #252                // Method remainderIsNotAlphanumeric:(Lorg/springframework/boot/context/properties/source/ConfigurationPropertyName$Elements;II)Z
      62: ireturn
      63: iload         6
      65: ifeq          78
      68: aload_1
      69: iload_3
      70: iload         8
      72: invokevirtual #249                // Method org/springframework/boot/context/properties/source/ConfigurationPropertyName$Elements.charAt:(II)C
      75: goto          88
      78: aload_1
      79: iload_3
      80: iload         8
      82: invokevirtual #249                // Method org/springframework/boot/context/properties/source/ConfigurationPropertyName$Elements.charAt:(II)C
      85: invokestatic  #108                // Method java/lang/Character.toLowerCase:(C)C
      88: istore        10
      90: iload         7
      92: ifeq          105
      95: aload_2
      96: iload_3
      97: iload         9
      99: invokevirtual #249                // Method org/springframework/boot/context/properties/source/ConfigurationPropertyName$Elements.charAt:(II)C
     102: goto          115
     105: aload_2
     106: iload_3
     107: iload         9
     109: invokevirtual #249                // Method org/springframework/boot/context/properties/source/ConfigurationPropertyName$Elements.charAt:(II)C
     112: invokestatic  #108                // Method java/lang/Character.toLowerCase:(C)C
     115: istore        11
     117: iload         6
     119: ifne          136
     122: iload         10
     124: invokestatic  #256                // Method org/springframework/boot/context/properties/source/ConfigurationPropertyName$ElementsParser.isAlphaNumeric:(C)Z
     127: ifne          136
     130: iinc          8, 1
     133: goto          170
     136: iload         7
     138: ifne          155
     141: iload         11
     143: invokestatic  #256                // Method org/springframework/boot/context/properties/source/ConfigurationPropertyName$ElementsParser.isAlphaNumeric:(C)Z
     146: ifne          155
     149: iinc          9, 1
     152: goto          170
     155: iload         10
     157: iload         11
     159: if_icmpeq     164
     162: iconst_0
     163: ireturn
     164: iinc          8, 1
     167: iinc          9, 1
     170: goto          40
     173: iload         9
     175: iload         5
     177: if_icmpge     189
     180: aload_0
     181: aload_2
     182: iload_3
     183: iload         9
     185: invokevirtual #252                // Method remainderIsNotAlphanumeric:(Lorg/springframework/boot/context/properties/source/ConfigurationPropertyName$Elements;II)Z
     188: ireturn
     189: iconst_1
     190: ireturn

  private boolean remainderIsNotAlphanumeric(org.springframework.boot.context.properties.source.ConfigurationPropertyName$Elements, int, int);
    Code:
       0: aload_1
       1: iload_2
       2: invokevirtual #32                 // Method org/springframework/boot/context/properties/source/ConfigurationPropertyName$Elements.getType:(I)Lorg/springframework/boot/context/properties/source/ConfigurationPropertyName$ElementType;
       5: invokevirtual #36                 // Method org/springframework/boot/context/properties/source/ConfigurationPropertyName$ElementType.isIndexed:()Z
       8: ifeq          13
      11: iconst_0
      12: ireturn
      13: aload_1
      14: iload_2
      15: invokevirtual #245                // Method org/springframework/boot/context/properties/source/ConfigurationPropertyName$Elements.getLength:(I)I
      18: istore        4
      20: aload_1
      21: iload_2
      22: iload_3
      23: iinc          3, 1
      26: invokevirtual #249                // Method org/springframework/boot/context/properties/source/ConfigurationPropertyName$Elements.charAt:(II)C
      29: invokestatic  #108                // Method java/lang/Character.toLowerCase:(C)C
      32: istore        5
      34: iload         5
      36: invokestatic  #256                // Method org/springframework/boot/context/properties/source/ConfigurationPropertyName$ElementsParser.isAlphaNumeric:(C)Z
      39: ifeq          44
      42: iconst_0
      43: ireturn
      44: iload_3
      45: iload         4
      47: if_icmplt     20
      50: iconst_1
      51: ireturn

  public int hashCode();
    Code:
       0: aload_0
       1: getfield      #262                // Field hashCode:I
       4: istore_1
       5: aload_0
       6: getfield      #7                  // Field elements:Lorg/springframework/boot/context/properties/source/ConfigurationPropertyName$Elements;
       9: astore_2
      10: iload_1
      11: ifne          125
      14: aload_2
      15: invokevirtual #13                 // Method org/springframework/boot/context/properties/source/ConfigurationPropertyName$Elements.getSize:()I
      18: ifeq          125
      21: iconst_0
      22: istore_3
      23: iload_3
      24: aload_2
      25: invokevirtual #13                 // Method org/springframework/boot/context/properties/source/ConfigurationPropertyName$Elements.getSize:()I
      28: if_icmpge     120
      31: iconst_0
      32: istore        4
      34: aload_2
      35: iload_3
      36: invokevirtual #32                 // Method org/springframework/boot/context/properties/source/ConfigurationPropertyName$Elements.getType:(I)Lorg/springframework/boot/context/properties/source/ConfigurationPropertyName$ElementType;
      39: invokevirtual #36                 // Method org/springframework/boot/context/properties/source/ConfigurationPropertyName$ElementType.isIndexed:()Z
      42: istore        5
      44: aload_2
      45: iload_3
      46: invokevirtual #245                // Method org/springframework/boot/context/properties/source/ConfigurationPropertyName$Elements.getLength:(I)I
      49: istore        6
      51: iconst_0
      52: istore        7
      54: iload         7
      56: iload         6
      58: if_icmpge     106
      61: aload_2
      62: iload_3
      63: iload         7
      65: invokevirtual #249                // Method org/springframework/boot/context/properties/source/ConfigurationPropertyName$Elements.charAt:(II)C
      68: istore        8
      70: iload         5
      72: ifne          82
      75: iload         8
      77: invokestatic  #108                // Method java/lang/Character.toLowerCase:(C)C
      80: istore        8
      82: iload         8
      84: invokestatic  #256                // Method org/springframework/boot/context/properties/source/ConfigurationPropertyName$ElementsParser.isAlphaNumeric:(C)Z
      87: ifeq          100
      90: bipush        31
      92: iload         4
      94: imul
      95: iload         8
      97: iadd
      98: istore        4
     100: iinc          7, 1
     103: goto          54
     106: bipush        31
     108: iload_1
     109: imul
     110: iload         4
     112: iadd
     113: istore_1
     114: iinc          3, 1
     117: goto          23
     120: aload_0
     121: iload_1
     122: putfield      #262                // Field hashCode:I
     125: iload_1
     126: ireturn

  public java.lang.String toString();
    Code:
       0: aload_0
       1: getfield      #266                // Field string:Ljava/lang/String;
       4: ifnonnull     15
       7: aload_0
       8: aload_0
       9: invokevirtual #270                // Method buildToString:()Ljava/lang/String;
      12: putfield      #266                // Field string:Ljava/lang/String;
      15: aload_0
      16: getfield      #266                // Field string:Ljava/lang/String;
      19: areturn

  private java.lang.String buildToString();
    Code:
       0: aload_0
       1: getfield      #7                  // Field elements:Lorg/springframework/boot/context/properties/source/ConfigurationPropertyName$Elements;
       4: getstatic     #75                 // Field org/springframework/boot/context/properties/source/ConfigurationPropertyName$ElementType.UNIFORM:Lorg/springframework/boot/context/properties/source/ConfigurationPropertyName$ElementType;
       7: getstatic     #78                 // Field org/springframework/boot/context/properties/source/ConfigurationPropertyName$ElementType.DASHED:Lorg/springframework/boot/context/properties/source/ConfigurationPropertyName$ElementType;
      10: invokevirtual #273                // Method org/springframework/boot/context/properties/source/ConfigurationPropertyName$Elements.canShortcutWithSource:(Lorg/springframework/boot/context/properties/source/ConfigurationPropertyName$ElementType;Lorg/springframework/boot/context/properties/source/ConfigurationPropertyName$ElementType;)Z
      13: ifeq          29
      16: aload_0
      17: getfield      #7                  // Field elements:Lorg/springframework/boot/context/properties/source/ConfigurationPropertyName$Elements;
      20: invokevirtual #276                // Method org/springframework/boot/context/properties/source/ConfigurationPropertyName$Elements.getSource:()Ljava/lang/CharSequence;
      23: invokeinterface #55,  1           // InterfaceMethod java/lang/CharSequence.toString:()Ljava/lang/String;
      28: areturn
      29: aload_0
      30: invokevirtual #25                 // Method getNumberOfElements:()I
      33: istore_1
      34: new           #96                 // class java/lang/StringBuilder
      37: dup
      38: iload_1
      39: bipush        8
      41: imul
      42: invokespecial #101                // Method java/lang/StringBuilder."<init>":(I)V
      45: astore_2
      46: iconst_0
      47: istore_3
      48: iload_3
      49: iload_1
      50: if_icmpge     133
      53: aload_0
      54: iload_3
      55: invokevirtual #28                 // Method isIndexed:(I)Z
      58: istore        4
      60: aload_2
      61: invokevirtual #280                // Method java/lang/StringBuilder.length:()I
      64: ifle          79
      67: iload         4
      69: ifne          79
      72: aload_2
      73: bipush        46
      75: invokevirtual #119                // Method java/lang/StringBuilder.append:(C)Ljava/lang/StringBuilder;
      78: pop
      79: iload         4
      81: ifeq          114
      84: aload_2
      85: bipush        91
      87: invokevirtual #119                // Method java/lang/StringBuilder.append:(C)Ljava/lang/StringBuilder;
      90: pop
      91: aload_2
      92: aload_0
      93: iload_3
      94: getstatic     #59                 // Field org/springframework/boot/context/properties/source/ConfigurationPropertyName$Form.ORIGINAL:Lorg/springframework/boot/context/properties/source/ConfigurationPropertyName$Form;
      97: invokevirtual #45                 // Method getElement:(ILorg/springframework/boot/context/properties/source/ConfigurationPropertyName$Form;)Ljava/lang/String;
     100: invokevirtual #281                // Method java/lang/StringBuilder.append:(Ljava/lang/String;)Ljava/lang/StringBuilder;
     103: pop
     104: aload_2
     105: bipush        93
     107: invokevirtual #119                // Method java/lang/StringBuilder.append:(C)Ljava/lang/StringBuilder;
     110: pop
     111: goto          127
     114: aload_2
     115: aload_0
     116: iload_3
     117: getstatic     #72                 // Field org/springframework/boot/context/properties/source/ConfigurationPropertyName$Form.DASHED:Lorg/springframework/boot/context/properties/source/ConfigurationPropertyName$Form;
     120: invokevirtual #45                 // Method getElement:(ILorg/springframework/boot/context/properties/source/ConfigurationPropertyName$Form;)Ljava/lang/String;
     123: invokevirtual #281                // Method java/lang/StringBuilder.append:(Ljava/lang/String;)Ljava/lang/StringBuilder;
     126: pop
     127: iinc          3, 1
     130: goto          48
     133: aload_2
     134: invokevirtual #284                // Method java/lang/StringBuilder.toString:()Ljava/lang/String;
     137: areturn

  public static boolean isValid(java.lang.CharSequence);
    Code:
       0: aload_0
       1: iconst_1
       2: invokestatic  #285                // Method of:(Ljava/lang/CharSequence;Z)Lorg/springframework/boot/context/properties/source/ConfigurationPropertyName;
       5: ifnull        12
       8: iconst_1
       9: goto          13
      12: iconst_0
      13: ireturn

  public static org.springframework.boot.context.properties.source.ConfigurationPropertyName of(java.lang.CharSequence);
    Code:
       0: aload_0
       1: iconst_0
       2: invokestatic  #285                // Method of:(Ljava/lang/CharSequence;Z)Lorg/springframework/boot/context/properties/source/ConfigurationPropertyName;
       5: areturn

  public static org.springframework.boot.context.properties.source.ConfigurationPropertyName ofIfValid(java.lang.CharSequence);
    Code:
       0: aload_0
       1: iconst_1
       2: invokestatic  #285                // Method of:(Ljava/lang/CharSequence;Z)Lorg/springframework/boot/context/properties/source/ConfigurationPropertyName;
       5: areturn

  static org.springframework.boot.context.properties.source.ConfigurationPropertyName of(java.lang.CharSequence, boolean);
    Code:
       0: aload_0
       1: iload_1
       2: invokestatic  #289                // Method elementsOf:(Ljava/lang/CharSequence;Z)Lorg/springframework/boot/context/properties/source/ConfigurationPropertyName$Elements;
       5: astore_2
       6: aload_2
       7: ifnull        21
      10: new           #8                  // class org/springframework/boot/context/properties/source/ConfigurationPropertyName
      13: dup
      14: aload_2
      15: invokespecial #136                // Method "<init>":(Lorg/springframework/boot/context/properties/source/ConfigurationPropertyName$Elements;)V
      18: goto          22
      21: aconst_null
      22: areturn

  private static org.springframework.boot.context.properties.source.ConfigurationPropertyName$Elements probablySingleElementOf(java.lang.CharSequence);
    Code:
       0: aload_0
       1: iconst_0
       2: iconst_1
       3: invokestatic  #293                // Method elementsOf:(Ljava/lang/CharSequence;ZI)Lorg/springframework/boot/context/properties/source/ConfigurationPropertyName$Elements;
       6: areturn

  private static org.springframework.boot.context.properties.source.ConfigurationPropertyName$Elements elementsOf(java.lang.CharSequence, boolean);
    Code:
       0: aload_0
       1: iload_1
       2: bipush        6
       4: invokestatic  #293                // Method elementsOf:(Ljava/lang/CharSequence;ZI)Lorg/springframework/boot/context/properties/source/ConfigurationPropertyName$Elements;
       7: areturn

  private static org.springframework.boot.context.properties.source.ConfigurationPropertyName$Elements elementsOf(java.lang.CharSequence, boolean, int);
    Code:
       0: aload_0
       1: ifnonnull     12
       4: iload_1
       5: ldc           #162                // String Name must not be null
       7: invokestatic  #296                // Method org/springframework/util/Assert.isTrue:(ZLjava/lang/String;)V
      10: aconst_null
      11: areturn
      12: aload_0
      13: invokeinterface #98,  1           // InterfaceMethod java/lang/CharSequence.length:()I
      18: ifne          25
      21: getstatic     #300                // Field org/springframework/boot/context/properties/source/ConfigurationPropertyName$Elements.EMPTY:Lorg/springframework/boot/context/properties/source/ConfigurationPropertyName$Elements;
      24: areturn
      25: aload_0
      26: iconst_0
      27: invokeinterface #104,  2          // InterfaceMethod java/lang/CharSequence.charAt:(I)C
      32: bipush        46
      34: if_icmpeq     56
      37: aload_0
      38: aload_0
      39: invokeinterface #98,  1           // InterfaceMethod java/lang/CharSequence.length:()I
      44: iconst_1
      45: isub
      46: invokeinterface #104,  2          // InterfaceMethod java/lang/CharSequence.charAt:(I)C
      51: bipush        46
      53: if_icmpne     79
      56: iload_1
      57: ifeq          62
      60: aconst_null
      61: areturn
      62: new           #302                // class org/springframework/boot/context/properties/source/InvalidConfigurationPropertyNameException
      65: dup
      66: aload_0
      67: bipush        46
      69: invokestatic  #304                // Method java/lang/Character.valueOf:(C)Ljava/lang/Character;
      72: invokestatic  #308                // Method java/util/Collections.singletonList:(Ljava/lang/Object;)Ljava/util/List;
      75: invokespecial #314                // Method org/springframework/boot/context/properties/source/InvalidConfigurationPropertyNameException."<init>":(Ljava/lang/CharSequence;Ljava/util/List;)V
      78: athrow
      79: new           #257                // class org/springframework/boot/context/properties/source/ConfigurationPropertyName$ElementsParser
      82: dup
      83: aload_0
      84: bipush        46
      86: iload_2
      87: invokespecial #317                // Method org/springframework/boot/context/properties/source/ConfigurationPropertyName$ElementsParser."<init>":(Ljava/lang/CharSequence;CI)V
      90: invokevirtual #320                // Method org/springframework/boot/context/properties/source/ConfigurationPropertyName$ElementsParser.parse:()Lorg/springframework/boot/context/properties/source/ConfigurationPropertyName$Elements;
      93: astore_3
      94: iconst_0
      95: istore        4
      97: iload         4
      99: aload_3
     100: invokevirtual #13                 // Method org/springframework/boot/context/properties/source/ConfigurationPropertyName$Elements.getSize:()I
     103: if_icmpge     145
     106: aload_3
     107: iload         4
     109: invokevirtual #32                 // Method org/springframework/boot/context/properties/source/ConfigurationPropertyName$Elements.getType:(I)Lorg/springframework/boot/context/properties/source/ConfigurationPropertyName$ElementType;
     112: getstatic     #65                 // Field org/springframework/boot/context/properties/source/ConfigurationPropertyName$ElementType.NON_UNIFORM:Lorg/springframework/boot/context/properties/source/ConfigurationPropertyName$ElementType;
     115: if_acmpne     139
     118: iload_1
     119: ifeq          124
     122: aconst_null
     123: areturn
     124: new           #302                // class org/springframework/boot/context/properties/source/InvalidConfigurationPropertyNameException
     127: dup
     128: aload_0
     129: aload_3
     130: iload         4
     132: invokestatic  #324                // Method getInvalidChars:(Lorg/springframework/boot/context/properties/source/ConfigurationPropertyName$Elements;I)Ljava/util/List;
     135: invokespecial #314                // Method org/springframework/boot/context/properties/source/InvalidConfigurationPropertyNameException."<init>":(Ljava/lang/CharSequence;Ljava/util/List;)V
     138: athrow
     139: iinc          4, 1
     142: goto          97
     145: aload_3
     146: areturn

  private static java.util.List<java.lang.Character> getInvalidChars(org.springframework.boot.context.properties.source.ConfigurationPropertyName$Elements, int);
    Code:
       0: new           #328                // class java/util/ArrayList
       3: dup
       4: invokespecial #330                // Method java/util/ArrayList."<init>":()V
       7: astore_2
       8: iconst_0
       9: istore_3
      10: iload_3
      11: aload_0
      12: iload_1
      13: invokevirtual #245                // Method org/springframework/boot/context/properties/source/ConfigurationPropertyName$Elements.getLength:(I)I
      16: if_icmpge     54
      19: aload_0
      20: iload_1
      21: iload_3
      22: invokevirtual #249                // Method org/springframework/boot/context/properties/source/ConfigurationPropertyName$Elements.charAt:(II)C
      25: istore        4
      27: iload         4
      29: iload_3
      30: invokestatic  #331                // Method org/springframework/boot/context/properties/source/ConfigurationPropertyName$ElementsParser.isValidChar:(CI)Z
      33: ifne          48
      36: aload_2
      37: iload         4
      39: invokestatic  #304                // Method java/lang/Character.valueOf:(C)Ljava/lang/Character;
      42: invokeinterface #334,  2          // InterfaceMethod java/util/List.add:(Ljava/lang/Object;)Z
      47: pop
      48: iinc          3, 1
      51: goto          10
      54: aload_2
      55: areturn

  public static org.springframework.boot.context.properties.source.ConfigurationPropertyName adapt(java.lang.CharSequence, char);
    Code:
       0: aload_0
       1: iload_1
       2: aconst_null
       3: invokestatic  #339                // Method adapt:(Ljava/lang/CharSequence;CLjava/util/function/Function;)Lorg/springframework/boot/context/properties/source/ConfigurationPropertyName;
       6: areturn

  static org.springframework.boot.context.properties.source.ConfigurationPropertyName adapt(java.lang.CharSequence, char, java.util.function.Function<java.lang.CharSequence, java.lang.CharSequence>);
    Code:
       0: aload_0
       1: ldc           #162                // String Name must not be null
       3: invokestatic  #164                // Method org/springframework/util/Assert.notNull:(Ljava/lang/Object;Ljava/lang/String;)V
       6: aload_0
       7: invokeinterface #98,  1           // InterfaceMethod java/lang/CharSequence.length:()I
      12: ifne          19
      15: getstatic     #139                // Field EMPTY:Lorg/springframework/boot/context/properties/source/ConfigurationPropertyName;
      18: areturn
      19: new           #257                // class org/springframework/boot/context/properties/source/ConfigurationPropertyName$ElementsParser
      22: dup
      23: aload_0
      24: iload_1
      25: invokespecial #343                // Method org/springframework/boot/context/properties/source/ConfigurationPropertyName$ElementsParser."<init>":(Ljava/lang/CharSequence;C)V
      28: aload_2
      29: invokevirtual #346                // Method org/springframework/boot/context/properties/source/ConfigurationPropertyName$ElementsParser.parse:(Ljava/util/function/Function;)Lorg/springframework/boot/context/properties/source/ConfigurationPropertyName$Elements;
      32: astore_3
      33: aload_3
      34: invokevirtual #13                 // Method org/springframework/boot/context/properties/source/ConfigurationPropertyName$Elements.getSize:()I
      37: ifne          44
      40: getstatic     #139                // Field EMPTY:Lorg/springframework/boot/context/properties/source/ConfigurationPropertyName;
      43: areturn
      44: new           #8                  // class org/springframework/boot/context/properties/source/ConfigurationPropertyName
      47: dup
      48: aload_3
      49: invokespecial #136                // Method "<init>":(Lorg/springframework/boot/context/properties/source/ConfigurationPropertyName$Elements;)V
      52: areturn

  public int compareTo(java.lang.Object);
    Code:
       0: aload_0
       1: aload_1
       2: checkcast     #8                  // class org/springframework/boot/context/properties/source/ConfigurationPropertyName
       5: invokevirtual #349                // Method compareTo:(Lorg/springframework/boot/context/properties/source/ConfigurationPropertyName;)I
       8: ireturn

  private static boolean lambda$convertToUniformElement$1(char, int);
    Code:
       0: iload_0
       1: invokestatic  #256                // Method org/springframework/boot/context/properties/source/ConfigurationPropertyName$ElementsParser.isAlphaNumeric:(C)Z
       4: ireturn

  private static boolean lambda$convertToOriginalForm$0(char, int);
    Code:
       0: iload_0
       1: bipush        95
       3: if_icmpeq     17
       6: iload_0
       7: invokestatic  #108                // Method java/lang/Character.toLowerCase:(C)C
      10: iload_1
      11: invokestatic  #331                // Method org/springframework/boot/context/properties/source/ConfigurationPropertyName$ElementsParser.isValidChar:(CI)Z
      14: ifeq          21
      17: iconst_1
      18: goto          22
      21: iconst_0
      22: ireturn

  static {};
    Code:
       0: new           #8                  // class org/springframework/boot/context/properties/source/ConfigurationPropertyName
       3: dup
       4: getstatic     #300                // Field org/springframework/boot/context/properties/source/ConfigurationPropertyName$Elements.EMPTY:Lorg/springframework/boot/context/properties/source/ConfigurationPropertyName$Elements;
       7: invokespecial #136                // Method "<init>":(Lorg/springframework/boot/context/properties/source/ConfigurationPropertyName$Elements;)V
      10: putstatic     #139                // Field EMPTY:Lorg/springframework/boot/context/properties/source/ConfigurationPropertyName;
      13: return
}
