Compiled from "ConfigurationPropertySource.java"
public interface org.springframework.boot.context.properties.source.ConfigurationPropertySource {
  public abstract org.springframework.boot.context.properties.source.ConfigurationProperty getConfigurationProperty(org.springframework.boot.context.properties.source.ConfigurationPropertyName);

  public default org.springframework.boot.context.properties.source.ConfigurationPropertyState containsDescendantOf(org.springframework.boot.context.properties.source.ConfigurationPropertyName);
    Code:
       0: getstatic     #1                  // Field org/springframework/boot/context/properties/source/ConfigurationPropertyState.UNKNOWN:Lorg/springframework/boot/context/properties/source/ConfigurationPropertyState;
       3: areturn

  public default org.springframework.boot.context.properties.source.ConfigurationPropertySource filter(java.util.function.Predicate<org.springframework.boot.context.properties.source.ConfigurationPropertyName>);
    Code:
       0: new           #7                  // class org/springframework/boot/context/properties/source/FilteredConfigurationPropertiesSource
       3: dup
       4: aload_0
       5: aload_1
       6: invokespecial #9                  // Method org/springframework/boot/context/properties/source/FilteredConfigurationPropertiesSource."<init>":(Lorg/springframework/boot/context/properties/source/ConfigurationPropertySource;Ljava/util/function/Predicate;)V
       9: areturn

  public default org.springframework.boot.context.properties.source.ConfigurationPropertySource withAliases(org.springframework.boot.context.properties.source.ConfigurationPropertyNameAliases);
    Code:
       0: new           #13                 // class org/springframework/boot/context/properties/source/AliasedConfigurationPropertySource
       3: dup
       4: aload_0
       5: aload_1
       6: invokespecial #15                 // Method org/springframework/boot/context/properties/source/AliasedConfigurationPropertySource."<init>":(Lorg/springframework/boot/context/properties/source/ConfigurationPropertySource;Lorg/springframework/boot/context/properties/source/ConfigurationPropertyNameAliases;)V
       9: areturn

  public default org.springframework.boot.context.properties.source.ConfigurationPropertySource withPrefix(java.lang.String);
    Code:
       0: aload_1
       1: invokestatic  #18                 // Method org/springframework/util/StringUtils.hasText:(Ljava/lang/String;)Z
       4: ifeq          19
       7: new           #24                 // class org/springframework/boot/context/properties/source/PrefixedConfigurationPropertySource
      10: dup
      11: aload_0
      12: aload_1
      13: invokespecial #26                 // Method org/springframework/boot/context/properties/source/PrefixedConfigurationPropertySource."<init>":(Lorg/springframework/boot/context/properties/source/ConfigurationPropertySource;Ljava/lang/String;)V
      16: goto          20
      19: aload_0
      20: areturn

  public default java.lang.Object getUnderlyingSource();
    Code:
       0: aconst_null
       1: areturn

  public static org.springframework.boot.context.properties.source.ConfigurationPropertySource from(org.springframework.core.env.PropertySource<?>);
    Code:
       0: aload_0
       1: instanceof    #29                 // class org/springframework/boot/context/properties/source/ConfigurationPropertySourcesPropertySource
       4: ifeq          9
       7: aconst_null
       8: areturn
       9: aload_0
      10: invokestatic  #31                 // Method org/springframework/boot/context/properties/source/SpringConfigurationPropertySource.from:(Lorg/springframework/core/env/PropertySource;)Lorg/springframework/boot/context/properties/source/SpringConfigurationPropertySource;
      13: areturn
}
