Compiled from "ConfigurationPropertySourcesCaching.java"
class org.springframework.boot.context.properties.source.ConfigurationPropertySourcesCaching implements org.springframework.boot.context.properties.source.ConfigurationPropertyCaching {
  private final java.lang.Iterable<org.springframework.boot.context.properties.source.ConfigurationPropertySource> sources;

  org.springframework.boot.context.properties.source.ConfigurationPropertySourcesCaching(java.lang.Iterable<org.springframework.boot.context.properties.source.ConfigurationPropertySource>);
    Code:
       0: aload_0
       1: invokespecial #1                  // Method java/lang/Object."<init>":()V
       4: aload_0
       5: aload_1
       6: putfield      #7                  // Field sources:Ljava/lang/Iterable;
       9: return

  public void enable();
    Code:
       0: aload_0
       1: invokedynamic #13,  0             // InvokeDynamic #0:accept:()Ljava/util/function/Consumer;
       6: invokevirtual #17                 // Method forEach:(Ljava/util/function/Consumer;)V
       9: return

  public void disable();
    Code:
       0: aload_0
       1: invokedynamic #21,  0             // InvokeDynamic #1:accept:()Ljava/util/function/Consumer;
       6: invokevirtual #17                 // Method forEach:(Ljava/util/function/Consumer;)V
       9: return

  public void setTimeToLive(java.time.Duration);
    Code:
       0: aload_0
       1: aload_1
       2: invokedynamic #22,  0             // InvokeDynamic #2:accept:(Ljava/time/Duration;)Ljava/util/function/Consumer;
       7: invokevirtual #17                 // Method forEach:(Ljava/util/function/Consumer;)V
      10: return

  public void clear();
    Code:
       0: aload_0
       1: invokedynamic #25,  0             // InvokeDynamic #3:accept:()Ljava/util/function/Consumer;
       6: invokevirtual #17                 // Method forEach:(Ljava/util/function/Consumer;)V
       9: return

  private void forEach(java.util.function.Consumer<org.springframework.boot.context.properties.source.ConfigurationPropertyCaching>);
    Code:
       0: aload_0
       1: getfield      #7                  // Field sources:Ljava/lang/Iterable;
       4: ifnull        58
       7: aload_0
       8: getfield      #7                  // Field sources:Ljava/lang/Iterable;
      11: invokeinterface #26,  1           // InterfaceMethod java/lang/Iterable.iterator:()Ljava/util/Iterator;
      16: astore_2
      17: aload_2
      18: invokeinterface #32,  1           // InterfaceMethod java/util/Iterator.hasNext:()Z
      23: ifeq          58
      26: aload_2
      27: invokeinterface #38,  1           // InterfaceMethod java/util/Iterator.next:()Ljava/lang/Object;
      32: checkcast     #42                 // class org/springframework/boot/context/properties/source/ConfigurationPropertySource
      35: astore_3
      36: aload_3
      37: invokestatic  #44                 // InterfaceMethod org/springframework/boot/context/properties/source/CachingConfigurationPropertySource.find:(Lorg/springframework/boot/context/properties/source/ConfigurationPropertySource;)Lorg/springframework/boot/context/properties/source/ConfigurationPropertyCaching;
      40: astore        4
      42: aload         4
      44: ifnull        55
      47: aload_1
      48: aload         4
      50: invokeinterface #50,  2           // InterfaceMethod java/util/function/Consumer.accept:(Ljava/lang/Object;)V
      55: goto          17
      58: return

  private static void lambda$setTimeToLive$0(java.time.Duration, org.springframework.boot.context.properties.source.ConfigurationPropertyCaching);
    Code:
       0: aload_1
       1: aload_0
       2: invokeinterface #55,  2           // InterfaceMethod org/springframework/boot/context/properties/source/ConfigurationPropertyCaching.setTimeToLive:(Ljava/time/Duration;)V
       7: return
}
