Compiled from "ConfigurationPropertyName.java"
final class org.springframework.boot.context.properties.source.ConfigurationPropertyName$ElementType extends java.lang.Enum<org.springframework.boot.context.properties.source.ConfigurationPropertyName$ElementType> {
  public static final org.springframework.boot.context.properties.source.ConfigurationPropertyName$ElementType EMPTY;

  public static final org.springframework.boot.context.properties.source.ConfigurationPropertyName$ElementType UNIFORM;

  public static final org.springframework.boot.context.properties.source.ConfigurationPropertyName$ElementType DASHED;

  public static final org.springframework.boot.context.properties.source.ConfigurationPropertyName$ElementType NON_UNIFORM;

  public static final org.springframework.boot.context.properties.source.ConfigurationPropertyName$ElementType INDEXED;

  public static final org.springframework.boot.context.properties.source.ConfigurationPropertyName$ElementType NUMERICALLY_INDEXED;

  private final boolean indexed;

  private static final org.springframework.boot.context.properties.source.ConfigurationPropertyName$ElementType[] $VALUES;

  public static org.springframework.boot.context.properties.source.ConfigurationPropertyName$ElementType[] values();
    Code:
       0: getstatic     #22                 // Field $VALUES:[Lorg/springframework/boot/context/properties/source/ConfigurationPropertyName$ElementType;
       3: invokevirtual #26                 // Method "[Lorg/springframework/boot/context/properties/source/ConfigurationPropertyName$ElementType;".clone:()Ljava/lang/Object;
       6: checkcast     #27                 // class "[Lorg/springframework/boot/context/properties/source/ConfigurationPropertyName$ElementType;"
       9: areturn

  public static org.springframework.boot.context.properties.source.ConfigurationPropertyName$ElementType valueOf(java.lang.String);
    Code:
       0: ldc           #1                  // class org/springframework/boot/context/properties/source/ConfigurationPropertyName$ElementType
       2: aload_0
       3: invokestatic  #31                 // Method java/lang/Enum.valueOf:(Ljava/lang/Class;Ljava/lang/String;)Ljava/lang/Enum;
       6: checkcast     #1                  // class org/springframework/boot/context/properties/source/ConfigurationPropertyName$ElementType
       9: areturn

  private org.springframework.boot.context.properties.source.ConfigurationPropertyName$ElementType(boolean);
    Code:
       0: aload_0
       1: aload_1
       2: iload_2
       3: invokespecial #37                 // Method java/lang/Enum."<init>":(Ljava/lang/String;I)V
       6: aload_0
       7: iload_3
       8: putfield      #41                 // Field indexed:Z
      11: return

  public boolean isIndexed();
    Code:
       0: aload_0
       1: getfield      #41                 // Field indexed:Z
       4: ireturn

  public boolean allowsFastEqualityCheck();
    Code:
       0: aload_0
       1: getstatic     #7                  // Field UNIFORM:Lorg/springframework/boot/context/properties/source/ConfigurationPropertyName$ElementType;
       4: if_acmpeq     14
       7: aload_0
       8: getstatic     #19                 // Field NUMERICALLY_INDEXED:Lorg/springframework/boot/context/properties/source/ConfigurationPropertyName$ElementType;
      11: if_acmpne     18
      14: iconst_1
      15: goto          19
      18: iconst_0
      19: ireturn

  public boolean allowsDashIgnoringEqualityCheck();
    Code:
       0: aload_0
       1: invokevirtual #45                 // Method allowsFastEqualityCheck:()Z
       4: ifne          14
       7: aload_0
       8: getstatic     #10                 // Field DASHED:Lorg/springframework/boot/context/properties/source/ConfigurationPropertyName$ElementType;
      11: if_acmpne     18
      14: iconst_1
      15: goto          19
      18: iconst_0
      19: ireturn

  private static org.springframework.boot.context.properties.source.ConfigurationPropertyName$ElementType[] $values();
    Code:
       0: bipush        6
       2: anewarray     #1                  // class org/springframework/boot/context/properties/source/ConfigurationPropertyName$ElementType
       5: dup
       6: iconst_0
       7: getstatic     #3                  // Field EMPTY:Lorg/springframework/boot/context/properties/source/ConfigurationPropertyName$ElementType;
      10: aastore
      11: dup
      12: iconst_1
      13: getstatic     #7                  // Field UNIFORM:Lorg/springframework/boot/context/properties/source/ConfigurationPropertyName$ElementType;
      16: aastore
      17: dup
      18: iconst_2
      19: getstatic     #10                 // Field DASHED:Lorg/springframework/boot/context/properties/source/ConfigurationPropertyName$ElementType;
      22: aastore
      23: dup
      24: iconst_3
      25: getstatic     #13                 // Field NON_UNIFORM:Lorg/springframework/boot/context/properties/source/ConfigurationPropertyName$ElementType;
      28: aastore
      29: dup
      30: iconst_4
      31: getstatic     #16                 // Field INDEXED:Lorg/springframework/boot/context/properties/source/ConfigurationPropertyName$ElementType;
      34: aastore
      35: dup
      36: iconst_5
      37: getstatic     #19                 // Field NUMERICALLY_INDEXED:Lorg/springframework/boot/context/properties/source/ConfigurationPropertyName$ElementType;
      40: aastore
      41: areturn

  static {};
    Code:
       0: new           #1                  // class org/springframework/boot/context/properties/source/ConfigurationPropertyName$ElementType
       3: dup
       4: ldc           #49                 // String EMPTY
       6: iconst_0
       7: iconst_0
       8: invokespecial #50                 // Method "<init>":(Ljava/lang/String;IZ)V
      11: putstatic     #3                  // Field EMPTY:Lorg/springframework/boot/context/properties/source/ConfigurationPropertyName$ElementType;
      14: new           #1                  // class org/springframework/boot/context/properties/source/ConfigurationPropertyName$ElementType
      17: dup
      18: ldc           #53                 // String UNIFORM
      20: iconst_1
      21: iconst_0
      22: invokespecial #50                 // Method "<init>":(Ljava/lang/String;IZ)V
      25: putstatic     #7                  // Field UNIFORM:Lorg/springframework/boot/context/properties/source/ConfigurationPropertyName$ElementType;
      28: new           #1                  // class org/springframework/boot/context/properties/source/ConfigurationPropertyName$ElementType
      31: dup
      32: ldc           #54                 // String DASHED
      34: iconst_2
      35: iconst_0
      36: invokespecial #50                 // Method "<init>":(Ljava/lang/String;IZ)V
      39: putstatic     #10                 // Field DASHED:Lorg/springframework/boot/context/properties/source/ConfigurationPropertyName$ElementType;
      42: new           #1                  // class org/springframework/boot/context/properties/source/ConfigurationPropertyName$ElementType
      45: dup
      46: ldc           #55                 // String NON_UNIFORM
      48: iconst_3
      49: iconst_0
      50: invokespecial #50                 // Method "<init>":(Ljava/lang/String;IZ)V
      53: putstatic     #13                 // Field NON_UNIFORM:Lorg/springframework/boot/context/properties/source/ConfigurationPropertyName$ElementType;
      56: new           #1                  // class org/springframework/boot/context/properties/source/ConfigurationPropertyName$ElementType
      59: dup
      60: ldc           #56                 // String INDEXED
      62: iconst_4
      63: iconst_1
      64: invokespecial #50                 // Method "<init>":(Ljava/lang/String;IZ)V
      67: putstatic     #16                 // Field INDEXED:Lorg/springframework/boot/context/properties/source/ConfigurationPropertyName$ElementType;
      70: new           #1                  // class org/springframework/boot/context/properties/source/ConfigurationPropertyName$ElementType
      73: dup
      74: ldc           #57                 // String NUMERICALLY_INDEXED
      76: iconst_5
      77: iconst_1
      78: invokespecial #50                 // Method "<init>":(Ljava/lang/String;IZ)V
      81: putstatic     #19                 // Field NUMERICALLY_INDEXED:Lorg/springframework/boot/context/properties/source/ConfigurationPropertyName$ElementType;
      84: invokestatic  #58                 // Method $values:()[Lorg/springframework/boot/context/properties/source/ConfigurationPropertyName$ElementType;
      87: putstatic     #22                 // Field $VALUES:[Lorg/springframework/boot/context/properties/source/ConfigurationPropertyName$ElementType;
      90: return
}
