Compiled from "ConfigurationProperty.java"
public final class org.springframework.boot.context.properties.source.ConfigurationProperty implements org.springframework.boot.origin.OriginProvider, java.lang.Comparable<org.springframework.boot.context.properties.source.ConfigurationProperty> {
  private final org.springframework.boot.context.properties.source.ConfigurationPropertyName name;

  private final java.lang.Object value;

  private final org.springframework.boot.context.properties.source.ConfigurationPropertySource source;

  private final org.springframework.boot.origin.Origin origin;

  public org.springframework.boot.context.properties.source.ConfigurationProperty(org.springframework.boot.context.properties.source.ConfigurationPropertyName, java.lang.Object, org.springframework.boot.origin.Origin);
    Code:
       0: aload_0
       1: aconst_null
       2: aload_1
       3: aload_2
       4: aload_3
       5: invokespecial #1                  // Method "<init>":(Lorg/springframework/boot/context/properties/source/ConfigurationPropertySource;Lorg/springframework/boot/context/properties/source/ConfigurationPropertyName;Ljava/lang/Object;Lorg/springframework/boot/origin/Origin;)V
       8: return

  private org.springframework.boot.context.properties.source.ConfigurationProperty(org.springframework.boot.context.properties.source.ConfigurationPropertySource, org.springframework.boot.context.properties.source.ConfigurationPropertyName, java.lang.Object, org.springframework.boot.origin.Origin);
    Code:
       0: aload_0
       1: invokespecial #7                  // Method java/lang/Object."<init>":()V
       4: aload_2
       5: ldc           #12                 // String Name must not be null
       7: invokestatic  #14                 // Method org/springframework/util/Assert.notNull:(Ljava/lang/Object;Ljava/lang/String;)V
      10: aload_3
      11: ldc           #20                 // String Value must not be null
      13: invokestatic  #14                 // Method org/springframework/util/Assert.notNull:(Ljava/lang/Object;Ljava/lang/String;)V
      16: aload_0
      17: aload_1
      18: putfield      #22                 // Field source:Lorg/springframework/boot/context/properties/source/ConfigurationPropertySource;
      21: aload_0
      22: aload_2
      23: putfield      #26                 // Field name:Lorg/springframework/boot/context/properties/source/ConfigurationPropertyName;
      26: aload_0
      27: aload_3
      28: putfield      #30                 // Field value:Ljava/lang/Object;
      31: aload_0
      32: aload         4
      34: putfield      #34                 // Field origin:Lorg/springframework/boot/origin/Origin;
      37: return

  public org.springframework.boot.context.properties.source.ConfigurationPropertySource getSource();
    Code:
       0: aload_0
       1: getfield      #22                 // Field source:Lorg/springframework/boot/context/properties/source/ConfigurationPropertySource;
       4: areturn

  public org.springframework.boot.context.properties.source.ConfigurationPropertyName getName();
    Code:
       0: aload_0
       1: getfield      #26                 // Field name:Lorg/springframework/boot/context/properties/source/ConfigurationPropertyName;
       4: areturn

  public java.lang.Object getValue();
    Code:
       0: aload_0
       1: getfield      #30                 // Field value:Ljava/lang/Object;
       4: areturn

  public org.springframework.boot.origin.Origin getOrigin();
    Code:
       0: aload_0
       1: getfield      #34                 // Field origin:Lorg/springframework/boot/origin/Origin;
       4: areturn

  public boolean equals(java.lang.Object);
    Code:
       0: aload_0
       1: aload_1
       2: if_acmpne     7
       5: iconst_1
       6: ireturn
       7: aload_1
       8: ifnull        22
      11: aload_0
      12: invokevirtual #38                 // Method java/lang/Object.getClass:()Ljava/lang/Class;
      15: aload_1
      16: invokevirtual #38                 // Method java/lang/Object.getClass:()Ljava/lang/Class;
      19: if_acmpeq     24
      22: iconst_0
      23: ireturn
      24: aload_1
      25: checkcast     #2                  // class org/springframework/boot/context/properties/source/ConfigurationProperty
      28: astore_2
      29: iconst_1
      30: istore_3
      31: iload_3
      32: ifeq          53
      35: aload_0
      36: getfield      #26                 // Field name:Lorg/springframework/boot/context/properties/source/ConfigurationPropertyName;
      39: aload_2
      40: getfield      #26                 // Field name:Lorg/springframework/boot/context/properties/source/ConfigurationPropertyName;
      43: invokestatic  #42                 // Method org/springframework/util/ObjectUtils.nullSafeEquals:(Ljava/lang/Object;Ljava/lang/Object;)Z
      46: ifeq          53
      49: iconst_1
      50: goto          54
      53: iconst_0
      54: istore_3
      55: iload_3
      56: ifeq          77
      59: aload_0
      60: getfield      #30                 // Field value:Ljava/lang/Object;
      63: aload_2
      64: getfield      #30                 // Field value:Ljava/lang/Object;
      67: invokestatic  #42                 // Method org/springframework/util/ObjectUtils.nullSafeEquals:(Ljava/lang/Object;Ljava/lang/Object;)Z
      70: ifeq          77
      73: iconst_1
      74: goto          78
      77: iconst_0
      78: istore_3
      79: iload_3
      80: ireturn

  public int hashCode();
    Code:
       0: aload_0
       1: getfield      #26                 // Field name:Lorg/springframework/boot/context/properties/source/ConfigurationPropertyName;
       4: invokestatic  #48                 // Method org/springframework/util/ObjectUtils.nullSafeHashCode:(Ljava/lang/Object;)I
       7: istore_1
       8: bipush        31
      10: iload_1
      11: imul
      12: aload_0
      13: getfield      #30                 // Field value:Ljava/lang/Object;
      16: invokestatic  #48                 // Method org/springframework/util/ObjectUtils.nullSafeHashCode:(Ljava/lang/Object;)I
      19: iadd
      20: istore_1
      21: iload_1
      22: ireturn

  public java.lang.String toString();
    Code:
       0: new           #52                 // class org/springframework/core/style/ToStringCreator
       3: dup
       4: aload_0
       5: invokespecial #54                 // Method org/springframework/core/style/ToStringCreator."<init>":(Ljava/lang/Object;)V
       8: ldc           #57                 // String name
      10: aload_0
      11: getfield      #26                 // Field name:Lorg/springframework/boot/context/properties/source/ConfigurationPropertyName;
      14: invokevirtual #58                 // Method org/springframework/core/style/ToStringCreator.append:(Ljava/lang/String;Ljava/lang/Object;)Lorg/springframework/core/style/ToStringCreator;
      17: ldc           #62                 // String value
      19: aload_0
      20: getfield      #30                 // Field value:Ljava/lang/Object;
      23: invokevirtual #58                 // Method org/springframework/core/style/ToStringCreator.append:(Ljava/lang/String;Ljava/lang/Object;)Lorg/springframework/core/style/ToStringCreator;
      26: ldc           #63                 // String origin
      28: aload_0
      29: getfield      #34                 // Field origin:Lorg/springframework/boot/origin/Origin;
      32: invokevirtual #58                 // Method org/springframework/core/style/ToStringCreator.append:(Ljava/lang/String;Ljava/lang/Object;)Lorg/springframework/core/style/ToStringCreator;
      35: invokevirtual #64                 // Method org/springframework/core/style/ToStringCreator.toString:()Ljava/lang/String;
      38: areturn

  public int compareTo(org.springframework.boot.context.properties.source.ConfigurationProperty);
    Code:
       0: aload_0
       1: getfield      #26                 // Field name:Lorg/springframework/boot/context/properties/source/ConfigurationPropertyName;
       4: aload_1
       5: getfield      #26                 // Field name:Lorg/springframework/boot/context/properties/source/ConfigurationPropertyName;
       8: invokevirtual #68                 // Method org/springframework/boot/context/properties/source/ConfigurationPropertyName.compareTo:(Lorg/springframework/boot/context/properties/source/ConfigurationPropertyName;)I
      11: ireturn

  static org.springframework.boot.context.properties.source.ConfigurationProperty of(org.springframework.boot.context.properties.source.ConfigurationPropertyName, org.springframework.boot.origin.OriginTrackedValue);
    Code:
       0: aload_1
       1: ifnonnull     6
       4: aconst_null
       5: areturn
       6: new           #2                  // class org/springframework/boot/context/properties/source/ConfigurationProperty
       9: dup
      10: aload_0
      11: aload_1
      12: invokevirtual #74                 // Method org/springframework/boot/origin/OriginTrackedValue.getValue:()Ljava/lang/Object;
      15: aload_1
      16: invokevirtual #80                 // Method org/springframework/boot/origin/OriginTrackedValue.getOrigin:()Lorg/springframework/boot/origin/Origin;
      19: invokespecial #84                 // Method "<init>":(Lorg/springframework/boot/context/properties/source/ConfigurationPropertyName;Ljava/lang/Object;Lorg/springframework/boot/origin/Origin;)V
      22: areturn

  static org.springframework.boot.context.properties.source.ConfigurationProperty of(org.springframework.boot.context.properties.source.ConfigurationPropertySource, org.springframework.boot.context.properties.source.ConfigurationPropertyName, java.lang.Object, org.springframework.boot.origin.Origin);
    Code:
       0: aload_2
       1: ifnonnull     6
       4: aconst_null
       5: areturn
       6: new           #2                  // class org/springframework/boot/context/properties/source/ConfigurationProperty
       9: dup
      10: aload_0
      11: aload_1
      12: aload_2
      13: aload_3
      14: invokespecial #1                  // Method "<init>":(Lorg/springframework/boot/context/properties/source/ConfigurationPropertySource;Lorg/springframework/boot/context/properties/source/ConfigurationPropertyName;Ljava/lang/Object;Lorg/springframework/boot/origin/Origin;)V
      17: areturn

  public int compareTo(java.lang.Object);
    Code:
       0: aload_0
       1: aload_1
       2: checkcast     #2                  // class org/springframework/boot/context/properties/source/ConfigurationProperty
       5: invokevirtual #87                 // Method compareTo:(Lorg/springframework/boot/context/properties/source/ConfigurationProperty;)I
       8: ireturn
}
