Compiled from "ConfigurationPropertyState.java"
public final class org.springframework.boot.context.properties.source.ConfigurationPropertyState extends java.lang.Enum<org.springframework.boot.context.properties.source.ConfigurationPropertyState> {
  public static final org.springframework.boot.context.properties.source.ConfigurationPropertyState PRESENT;

  public static final org.springframework.boot.context.properties.source.ConfigurationPropertyState ABSENT;

  public static final org.springframework.boot.context.properties.source.ConfigurationPropertyState UNKNOWN;

  private static final org.springframework.boot.context.properties.source.ConfigurationPropertyState[] $VALUES;

  public static org.springframework.boot.context.properties.source.ConfigurationPropertyState[] values();
    Code:
       0: getstatic     #13                 // Field $VALUES:[Lorg/springframework/boot/context/properties/source/ConfigurationPropertyState;
       3: invokevirtual #17                 // Method "[Lorg/springframework/boot/context/properties/source/ConfigurationPropertyState;".clone:()Ljava/lang/Object;
       6: checkcast     #18                 // class "[Lorg/springframework/boot/context/properties/source/ConfigurationPropertyState;"
       9: areturn

  public static org.springframework.boot.context.properties.source.ConfigurationPropertyState valueOf(java.lang.String);
    Code:
       0: ldc           #1                  // class org/springframework/boot/context/properties/source/ConfigurationPropertyState
       2: aload_0
       3: invokestatic  #22                 // Method java/lang/Enum.valueOf:(Ljava/lang/Class;Ljava/lang/String;)Ljava/lang/Enum;
       6: checkcast     #1                  // class org/springframework/boot/context/properties/source/ConfigurationPropertyState
       9: areturn

  private org.springframework.boot.context.properties.source.ConfigurationPropertyState();
    Code:
       0: aload_0
       1: aload_1
       2: iload_2
       3: invokespecial #28                 // Method java/lang/Enum."<init>":(Ljava/lang/String;I)V
       6: return

  static <T> org.springframework.boot.context.properties.source.ConfigurationPropertyState search(java.lang.Iterable<T>, java.util.function.Predicate<T>);
    Code:
       0: aload_0
       1: ldc           #32                 // String Source must not be null
       3: invokestatic  #34                 // Method org/springframework/util/Assert.notNull:(Ljava/lang/Object;Ljava/lang/String;)V
       6: aload_1
       7: ldc           #40                 // String Predicate must not be null
       9: invokestatic  #34                 // Method org/springframework/util/Assert.notNull:(Ljava/lang/Object;Ljava/lang/String;)V
      12: aload_0
      13: invokeinterface #42,  1           // InterfaceMethod java/lang/Iterable.iterator:()Ljava/util/Iterator;
      18: astore_2
      19: aload_2
      20: invokeinterface #48,  1           // InterfaceMethod java/util/Iterator.hasNext:()Z
      25: ifeq          52
      28: aload_2
      29: invokeinterface #54,  1           // InterfaceMethod java/util/Iterator.next:()Ljava/lang/Object;
      34: astore_3
      35: aload_1
      36: aload_3
      37: invokeinterface #57,  2           // InterfaceMethod java/util/function/Predicate.test:(Ljava/lang/Object;)Z
      42: ifeq          49
      45: getstatic     #3                  // Field PRESENT:Lorg/springframework/boot/context/properties/source/ConfigurationPropertyState;
      48: areturn
      49: goto          19
      52: getstatic     #7                  // Field ABSENT:Lorg/springframework/boot/context/properties/source/ConfigurationPropertyState;
      55: areturn

  private static org.springframework.boot.context.properties.source.ConfigurationPropertyState[] $values();
    Code:
       0: iconst_3
       1: anewarray     #1                  // class org/springframework/boot/context/properties/source/ConfigurationPropertyState
       4: dup
       5: iconst_0
       6: getstatic     #3                  // Field PRESENT:Lorg/springframework/boot/context/properties/source/ConfigurationPropertyState;
       9: aastore
      10: dup
      11: iconst_1
      12: getstatic     #7                  // Field ABSENT:Lorg/springframework/boot/context/properties/source/ConfigurationPropertyState;
      15: aastore
      16: dup
      17: iconst_2
      18: getstatic     #10                 // Field UNKNOWN:Lorg/springframework/boot/context/properties/source/ConfigurationPropertyState;
      21: aastore
      22: areturn

  static {};
    Code:
       0: new           #1                  // class org/springframework/boot/context/properties/source/ConfigurationPropertyState
       3: dup
       4: ldc           #63                 // String PRESENT
       6: iconst_0
       7: invokespecial #64                 // Method "<init>":(Ljava/lang/String;I)V
      10: putstatic     #3                  // Field PRESENT:Lorg/springframework/boot/context/properties/source/ConfigurationPropertyState;
      13: new           #1                  // class org/springframework/boot/context/properties/source/ConfigurationPropertyState
      16: dup
      17: ldc           #65                 // String ABSENT
      19: iconst_1
      20: invokespecial #64                 // Method "<init>":(Ljava/lang/String;I)V
      23: putstatic     #7                  // Field ABSENT:Lorg/springframework/boot/context/properties/source/ConfigurationPropertyState;
      26: new           #1                  // class org/springframework/boot/context/properties/source/ConfigurationPropertyState
      29: dup
      30: ldc           #66                 // String UNKNOWN
      32: iconst_2
      33: invokespecial #64                 // Method "<init>":(Ljava/lang/String;I)V
      36: putstatic     #10                 // Field UNKNOWN:Lorg/springframework/boot/context/properties/source/ConfigurationPropertyState;
      39: invokestatic  #67                 // Method $values:()[Lorg/springframework/boot/context/properties/source/ConfigurationPropertyState;
      42: putstatic     #13                 // Field $VALUES:[Lorg/springframework/boot/context/properties/source/ConfigurationPropertyState;
      45: return
}
