Compiled from "FilteredIterableConfigurationPropertiesSource.java"
class org.springframework.boot.context.properties.source.FilteredIterableConfigurationPropertiesSource extends org.springframework.boot.context.properties.source.FilteredConfigurationPropertiesSource implements org.springframework.boot.context.properties.source.IterableConfigurationPropertySource {
  org.springframework.boot.context.properties.source.FilteredIterableConfigurationPropertiesSource(org.springframework.boot.context.properties.source.IterableConfigurationPropertySource, java.util.function.Predicate<org.springframework.boot.context.properties.source.ConfigurationPropertyName>);
    Code:
       0: aload_0
       1: aload_1
       2: aload_2
       3: invokespecial #1                  // Method org/springframework/boot/context/properties/source/FilteredConfigurationPropertiesSource."<init>":(Lorg/springframework/boot/context/properties/source/ConfigurationPropertySource;Ljava/util/function/Predicate;)V
       6: return

  public java.util.stream.Stream<org.springframework.boot.context.properties.source.ConfigurationPropertyName> stream();
    Code:
       0: aload_0
       1: invokevirtual #7                  // Method getSource:()Lorg/springframework/boot/context/properties/source/IterableConfigurationPropertySource;
       4: invokeinterface #13,  1           // InterfaceMethod org/springframework/boot/context/properties/source/IterableConfigurationPropertySource.stream:()Ljava/util/stream/Stream;
       9: aload_0
      10: invokevirtual #19                 // Method getFilter:()Ljava/util/function/Predicate;
      13: invokeinterface #23,  2           // InterfaceMethod java/util/stream/Stream.filter:(Ljava/util/function/Predicate;)Ljava/util/stream/Stream;
      18: areturn

  protected org.springframework.boot.context.properties.source.IterableConfigurationPropertySource getSource();
    Code:
       0: aload_0
       1: invokespecial #29                 // Method org/springframework/boot/context/properties/source/FilteredConfigurationPropertiesSource.getSource:()Lorg/springframework/boot/context/properties/source/ConfigurationPropertySource;
       4: checkcast     #14                 // class org/springframework/boot/context/properties/source/IterableConfigurationPropertySource
       7: areturn

  public org.springframework.boot.context.properties.source.ConfigurationPropertyState containsDescendantOf(org.springframework.boot.context.properties.source.ConfigurationPropertyName);
    Code:
       0: aload_0
       1: aload_1
       2: dup
       3: invokestatic  #32                 // Method java/util/Objects.requireNonNull:(Ljava/lang/Object;)Ljava/lang/Object;
       6: pop
       7: invokedynamic #38,  0             // InvokeDynamic #0:test:(Lorg/springframework/boot/context/properties/source/ConfigurationPropertyName;)Ljava/util/function/Predicate;
      12: invokestatic  #42                 // Method org/springframework/boot/context/properties/source/ConfigurationPropertyState.search:(Ljava/lang/Iterable;Ljava/util/function/Predicate;)Lorg/springframework/boot/context/properties/source/ConfigurationPropertyState;
      15: areturn

  protected org.springframework.boot.context.properties.source.ConfigurationPropertySource getSource();
    Code:
       0: aload_0
       1: invokevirtual #7                  // Method getSource:()Lorg/springframework/boot/context/properties/source/IterableConfigurationPropertySource;
       4: areturn
}
