Compiled from "IterableConfigurationPropertySource.java"
public interface org.springframework.boot.context.properties.source.IterableConfigurationPropertySource extends org.springframework.boot.context.properties.source.ConfigurationPropertySource, java.lang.Iterable<org.springframework.boot.context.properties.source.ConfigurationPropertyName> {
  public default java.util.Iterator<org.springframework.boot.context.properties.source.ConfigurationPropertyName> iterator();
    Code:
       0: aload_0
       1: invokeinterface #1,  1            // InterfaceMethod stream:()Ljava/util/stream/Stream;
       6: invokeinterface #7,  1            // InterfaceMethod java/util/stream/Stream.iterator:()Ljava/util/Iterator;
      11: areturn

  public abstract java.util.stream.Stream<org.springframework.boot.context.properties.source.ConfigurationPropertyName> stream();

  public default org.springframework.boot.context.properties.source.ConfigurationPropertyState containsDescendantOf(org.springframework.boot.context.properties.source.ConfigurationPropertyName);
    Code:
       0: aload_0
       1: aload_1
       2: dup
       3: invokestatic  #13                 // Method java/util/Objects.requireNonNull:(Ljava/lang/Object;)Ljava/lang/Object;
       6: pop
       7: invokedynamic #19,  0             // InvokeDynamic #0:test:(Lorg/springframework/boot/context/properties/source/ConfigurationPropertyName;)Ljava/util/function/Predicate;
      12: invokestatic  #23                 // Method org/springframework/boot/context/properties/source/ConfigurationPropertyState.search:(Ljava/lang/Iterable;Ljava/util/function/Predicate;)Lorg/springframework/boot/context/properties/source/ConfigurationPropertyState;
      15: areturn

  public default org.springframework.boot.context.properties.source.IterableConfigurationPropertySource filter(java.util.function.Predicate<org.springframework.boot.context.properties.source.ConfigurationPropertyName>);
    Code:
       0: new           #29                 // class org/springframework/boot/context/properties/source/FilteredIterableConfigurationPropertiesSource
       3: dup
       4: aload_0
       5: aload_1
       6: invokespecial #31                 // Method org/springframework/boot/context/properties/source/FilteredIterableConfigurationPropertiesSource."<init>":(Lorg/springframework/boot/context/properties/source/IterableConfigurationPropertySource;Ljava/util/function/Predicate;)V
       9: areturn

  public default org.springframework.boot.context.properties.source.IterableConfigurationPropertySource withAliases(org.springframework.boot.context.properties.source.ConfigurationPropertyNameAliases);
    Code:
       0: new           #35                 // class org/springframework/boot/context/properties/source/AliasedIterableConfigurationPropertySource
       3: dup
       4: aload_0
       5: aload_1
       6: invokespecial #37                 // Method org/springframework/boot/context/properties/source/AliasedIterableConfigurationPropertySource."<init>":(Lorg/springframework/boot/context/properties/source/IterableConfigurationPropertySource;Lorg/springframework/boot/context/properties/source/ConfigurationPropertyNameAliases;)V
       9: areturn

  public default org.springframework.boot.context.properties.source.IterableConfigurationPropertySource withPrefix(java.lang.String);
    Code:
       0: aload_1
       1: invokestatic  #40                 // Method org/springframework/util/StringUtils.hasText:(Ljava/lang/String;)Z
       4: ifeq          19
       7: new           #46                 // class org/springframework/boot/context/properties/source/PrefixedIterableConfigurationPropertySource
      10: dup
      11: aload_0
      12: aload_1
      13: invokespecial #48                 // Method org/springframework/boot/context/properties/source/PrefixedIterableConfigurationPropertySource."<init>":(Lorg/springframework/boot/context/properties/source/IterableConfigurationPropertySource;Ljava/lang/String;)V
      16: goto          20
      19: aload_0
      20: areturn

  public default org.springframework.boot.context.properties.source.ConfigurationPropertySource withPrefix(java.lang.String);
    Code:
       0: aload_0
       1: aload_1
       2: invokeinterface #51,  2           // InterfaceMethod withPrefix:(Ljava/lang/String;)Lorg/springframework/boot/context/properties/source/IterableConfigurationPropertySource;
       7: areturn

  public default org.springframework.boot.context.properties.source.ConfigurationPropertySource withAliases(org.springframework.boot.context.properties.source.ConfigurationPropertyNameAliases);
    Code:
       0: aload_0
       1: aload_1
       2: invokeinterface #55,  2           // InterfaceMethod withAliases:(Lorg/springframework/boot/context/properties/source/ConfigurationPropertyNameAliases;)Lorg/springframework/boot/context/properties/source/IterableConfigurationPropertySource;
       7: areturn

  public default org.springframework.boot.context.properties.source.ConfigurationPropertySource filter(java.util.function.Predicate);
    Code:
       0: aload_0
       1: aload_1
       2: invokeinterface #59,  2           // InterfaceMethod filter:(Ljava/util/function/Predicate;)Lorg/springframework/boot/context/properties/source/IterableConfigurationPropertySource;
       7: areturn
}
