Compiled from "MutuallyExclusiveConfigurationPropertiesException.java"
public class org.springframework.boot.context.properties.source.MutuallyExclusiveConfigurationPropertiesException extends java.lang.RuntimeException {
  private final java.util.Set<java.lang.String> configuredNames;

  private final java.util.Set<java.lang.String> mutuallyExclusiveNames;

  public org.springframework.boot.context.properties.source.MutuallyExclusiveConfigurationPropertiesException(java.util.Collection<java.lang.String>, java.util.Collection<java.lang.String>);
    Code:
       0: aload_0
       1: aload_1
       2: invokestatic  #1                  // Method asSet:(Ljava/util/Collection;)Ljava/util/Set;
       5: aload_2
       6: invokestatic  #1                  // Method asSet:(Ljava/util/Collection;)Ljava/util/Set;
       9: invokespecial #7                  // Method "<init>":(Ljava/util/Set;Ljava/util/Set;)V
      12: return

  private org.springframework.boot.context.properties.source.MutuallyExclusiveConfigurationPropertiesException(java.util.Set<java.lang.String>, java.util.Set<java.lang.String>);
    Code:
       0: aload_0
       1: aload_2
       2: aload_1
       3: invokestatic  #11                 // Method buildMessage:(Ljava/util/Set;Ljava/util/Set;)Ljava/lang/String;
       6: invokespecial #15                 // Method java/lang/RuntimeException."<init>":(Ljava/lang/String;)V
       9: aload_0
      10: aload_1
      11: putfield      #20                 // Field configuredNames:Ljava/util/Set;
      14: aload_0
      15: aload_2
      16: putfield      #24                 // Field mutuallyExclusiveNames:Ljava/util/Set;
      19: return

  public java.util.Set<java.lang.String> getConfiguredNames();
    Code:
       0: aload_0
       1: getfield      #20                 // Field configuredNames:Ljava/util/Set;
       4: areturn

  public java.util.Set<java.lang.String> getMutuallyExclusiveNames();
    Code:
       0: aload_0
       1: getfield      #24                 // Field mutuallyExclusiveNames:Ljava/util/Set;
       4: areturn

  private static java.util.Set<java.lang.String> asSet(java.util.Collection<java.lang.String>);
    Code:
       0: aload_0
       1: ifnull        15
       4: new           #27                 // class java/util/LinkedHashSet
       7: dup
       8: aload_0
       9: invokespecial #29                 // Method java/util/LinkedHashSet."<init>":(Ljava/util/Collection;)V
      12: goto          16
      15: aconst_null
      16: areturn

  private static java.lang.String buildMessage(java.util.Set<java.lang.String>, java.util.Set<java.lang.String>);
    Code:
       0: aload_1
       1: ifnull        18
       4: aload_1
       5: invokeinterface #32,  1           // InterfaceMethod java/util/Set.size:()I
      10: iconst_1
      11: if_icmple     18
      14: iconst_1
      15: goto          19
      18: iconst_0
      19: ldc           #38                 // String ConfiguredNames must contain 2 or more names
      21: invokestatic  #40                 // Method org/springframework/util/Assert.isTrue:(ZLjava/lang/String;)V
      24: aload_0
      25: ifnull        42
      28: aload_0
      29: invokeinterface #32,  1           // InterfaceMethod java/util/Set.size:()I
      34: iconst_1
      35: if_icmple     42
      38: iconst_1
      39: goto          43
      42: iconst_0
      43: ldc           #46                 // String MutuallyExclusiveNames must contain 2 or more names
      45: invokestatic  #40                 // Method org/springframework/util/Assert.isTrue:(ZLjava/lang/String;)V
      48: ldc           #48                 // String ,
      50: aload_0
      51: invokestatic  #50                 // Method java/lang/String.join:(Ljava/lang/CharSequence;Ljava/lang/Iterable;)Ljava/lang/String;
      54: ldc           #48                 // String ,
      56: aload_1
      57: invokestatic  #50                 // Method java/lang/String.join:(Ljava/lang/CharSequence;Ljava/lang/Iterable;)Ljava/lang/String;
      60: invokedynamic #56,  0             // InvokeDynamic #0:makeConcatWithConstants:(Ljava/lang/String;Ljava/lang/String;)Ljava/lang/String;
      65: areturn

  public static void throwIfMultipleNonNullValuesIn(java.util.function.Consumer<java.util.Map<java.lang.String, java.lang.Object>>);
    Code:
       0: new           #60                 // class java/util/LinkedHashMap
       3: dup
       4: invokespecial #62                 // Method java/util/LinkedHashMap."<init>":()V
       7: astore_1
       8: aload_0
       9: aload_1
      10: invokeinterface #65,  2           // InterfaceMethod java/util/function/Consumer.accept:(Ljava/lang/Object;)V
      15: aload_1
      16: invokeinterface #71,  1           // InterfaceMethod java/util/Map.entrySet:()Ljava/util/Set;
      21: invokeinterface #77,  1           // InterfaceMethod java/util/Set.stream:()Ljava/util/stream/Stream;
      26: invokedynamic #81,  0             // InvokeDynamic #1:test:()Ljava/util/function/Predicate;
      31: invokeinterface #85,  2           // InterfaceMethod java/util/stream/Stream.filter:(Ljava/util/function/Predicate;)Ljava/util/stream/Stream;
      36: invokedynamic #91,  0             // InvokeDynamic #2:apply:()Ljava/util/function/Function;
      41: invokeinterface #95,  2           // InterfaceMethod java/util/stream/Stream.map:(Ljava/util/function/Function;)Ljava/util/stream/Stream;
      46: invokedynamic #99,  0             // InvokeDynamic #3:get:()Ljava/util/function/Supplier;
      51: invokestatic  #103                // Method java/util/stream/Collectors.toCollection:(Ljava/util/function/Supplier;)Ljava/util/stream/Collector;
      54: invokeinterface #109,  2          // InterfaceMethod java/util/stream/Stream.collect:(Ljava/util/stream/Collector;)Ljava/lang/Object;
      59: checkcast     #33                 // class java/util/Set
      62: astore_2
      63: aload_2
      64: invokeinterface #32,  1           // InterfaceMethod java/util/Set.size:()I
      69: iconst_1
      70: if_icmple     88
      73: new           #2                  // class org/springframework/boot/context/properties/source/MutuallyExclusiveConfigurationPropertiesException
      76: dup
      77: aload_2
      78: aload_1
      79: invokeinterface #113,  1          // InterfaceMethod java/util/Map.keySet:()Ljava/util/Set;
      84: invokespecial #7                  // Method "<init>":(Ljava/util/Set;Ljava/util/Set;)V
      87: athrow
      88: return

  private static boolean lambda$throwIfMultipleNonNullValuesIn$0(java.util.Map$Entry);
    Code:
       0: aload_0
       1: invokeinterface #116,  1          // InterfaceMethod java/util/Map$Entry.getValue:()Ljava/lang/Object;
       6: ifnull        13
       9: iconst_1
      10: goto          14
      13: iconst_0
      14: ireturn
}
