Compiled from "PrefixedIterableConfigurationPropertySource.java"
class org.springframework.boot.context.properties.source.PrefixedIterableConfigurationPropertySource extends org.springframework.boot.context.properties.source.PrefixedConfigurationPropertySource implements org.springframework.boot.context.properties.source.IterableConfigurationPropertySource {
  org.springframework.boot.context.properties.source.PrefixedIterableConfigurationPropertySource(org.springframework.boot.context.properties.source.IterableConfigurationPropertySource, java.lang.String);
    Code:
       0: aload_0
       1: aload_1
       2: aload_2
       3: invokespecial #1                  // Method org/springframework/boot/context/properties/source/PrefixedConfigurationPropertySource."<init>":(Lorg/springframework/boot/context/properties/source/ConfigurationPropertySource;Ljava/lang/String;)V
       6: return

  public java.util.stream.Stream<org.springframework.boot.context.properties.source.ConfigurationPropertyName> stream();
    Code:
       0: aload_0
       1: invokevirtual #7                  // Method getSource:()Lorg/springframework/boot/context/properties/source/IterableConfigurationPropertySource;
       4: invokeinterface #13,  1           // InterfaceMethod org/springframework/boot/context/properties/source/IterableConfigurationPropertySource.stream:()Ljava/util/stream/Stream;
       9: aload_0
      10: invokedynamic #19,  0             // InvokeDynamic #0:apply:(Lorg/springframework/boot/context/properties/source/PrefixedIterableConfigurationPropertySource;)Ljava/util/function/Function;
      15: invokeinterface #23,  2           // InterfaceMethod java/util/stream/Stream.map:(Ljava/util/function/Function;)Ljava/util/stream/Stream;
      20: areturn

  private org.springframework.boot.context.properties.source.ConfigurationPropertyName stripPrefix(org.springframework.boot.context.properties.source.ConfigurationPropertyName);
    Code:
       0: aload_0
       1: invokevirtual #29                 // Method getPrefix:()Lorg/springframework/boot/context/properties/source/ConfigurationPropertyName;
       4: aload_1
       5: invokevirtual #33                 // Method org/springframework/boot/context/properties/source/ConfigurationPropertyName.isAncestorOf:(Lorg/springframework/boot/context/properties/source/ConfigurationPropertyName;)Z
       8: ifeq          25
      11: aload_1
      12: aload_0
      13: invokevirtual #29                 // Method getPrefix:()Lorg/springframework/boot/context/properties/source/ConfigurationPropertyName;
      16: invokevirtual #39                 // Method org/springframework/boot/context/properties/source/ConfigurationPropertyName.getNumberOfElements:()I
      19: invokevirtual #43                 // Method org/springframework/boot/context/properties/source/ConfigurationPropertyName.subName:(I)Lorg/springframework/boot/context/properties/source/ConfigurationPropertyName;
      22: goto          26
      25: aload_1
      26: areturn

  protected org.springframework.boot.context.properties.source.IterableConfigurationPropertySource getSource();
    Code:
       0: aload_0
       1: invokespecial #47                 // Method org/springframework/boot/context/properties/source/PrefixedConfigurationPropertySource.getSource:()Lorg/springframework/boot/context/properties/source/ConfigurationPropertySource;
       4: checkcast     #14                 // class org/springframework/boot/context/properties/source/IterableConfigurationPropertySource
       7: areturn

  protected org.springframework.boot.context.properties.source.ConfigurationPropertySource getSource();
    Code:
       0: aload_0
       1: invokevirtual #7                  // Method getSource:()Lorg/springframework/boot/context/properties/source/IterableConfigurationPropertySource;
       4: areturn
}
