Compiled from "PrefixedConfigurationPropertySource.java"
class org.springframework.boot.context.properties.source.PrefixedConfigurationPropertySource implements org.springframework.boot.context.properties.source.ConfigurationPropertySource {
  private final org.springframework.boot.context.properties.source.ConfigurationPropertySource source;

  private final org.springframework.boot.context.properties.source.ConfigurationPropertyName prefix;

  org.springframework.boot.context.properties.source.PrefixedConfigurationPropertySource(org.springframework.boot.context.properties.source.ConfigurationPropertySource, java.lang.String);
    Code:
       0: aload_0
       1: invokespecial #1                  // Method java/lang/Object."<init>":()V
       4: aload_1
       5: ldc           #7                  // String Source must not be null
       7: invokestatic  #9                  // Method org/springframework/util/Assert.notNull:(Ljava/lang/Object;Ljava/lang/String;)V
      10: aload_2
      11: ldc           #15                 // String Prefix must not be empty
      13: invokestatic  #17                 // Method org/springframework/util/Assert.hasText:(Ljava/lang/String;Ljava/lang/String;)V
      16: aload_0
      17: aload_1
      18: putfield      #21                 // Field source:Lorg/springframework/boot/context/properties/source/ConfigurationPropertySource;
      21: aload_0
      22: aload_2
      23: invokestatic  #27                 // Method org/springframework/boot/context/properties/source/ConfigurationPropertyName.of:(Ljava/lang/CharSequence;)Lorg/springframework/boot/context/properties/source/ConfigurationPropertyName;
      26: putfield      #33                 // Field prefix:Lorg/springframework/boot/context/properties/source/ConfigurationPropertyName;
      29: return

  protected final org.springframework.boot.context.properties.source.ConfigurationPropertyName getPrefix();
    Code:
       0: aload_0
       1: getfield      #33                 // Field prefix:Lorg/springframework/boot/context/properties/source/ConfigurationPropertyName;
       4: areturn

  public org.springframework.boot.context.properties.source.ConfigurationProperty getConfigurationProperty(org.springframework.boot.context.properties.source.ConfigurationPropertyName);
    Code:
       0: aload_0
       1: getfield      #21                 // Field source:Lorg/springframework/boot/context/properties/source/ConfigurationPropertySource;
       4: aload_0
       5: aload_1
       6: invokevirtual #37                 // Method getPrefixedName:(Lorg/springframework/boot/context/properties/source/ConfigurationPropertyName;)Lorg/springframework/boot/context/properties/source/ConfigurationPropertyName;
       9: invokeinterface #41,  2           // InterfaceMethod org/springframework/boot/context/properties/source/ConfigurationPropertySource.getConfigurationProperty:(Lorg/springframework/boot/context/properties/source/ConfigurationPropertyName;)Lorg/springframework/boot/context/properties/source/ConfigurationProperty;
      14: astore_2
      15: aload_2
      16: ifnonnull     21
      19: aconst_null
      20: areturn
      21: aload_2
      22: invokevirtual #47                 // Method org/springframework/boot/context/properties/source/ConfigurationProperty.getSource:()Lorg/springframework/boot/context/properties/source/ConfigurationPropertySource;
      25: aload_1
      26: aload_2
      27: invokevirtual #53                 // Method org/springframework/boot/context/properties/source/ConfigurationProperty.getValue:()Ljava/lang/Object;
      30: aload_2
      31: invokevirtual #57                 // Method org/springframework/boot/context/properties/source/ConfigurationProperty.getOrigin:()Lorg/springframework/boot/origin/Origin;
      34: invokestatic  #61                 // Method org/springframework/boot/context/properties/source/ConfigurationProperty.of:(Lorg/springframework/boot/context/properties/source/ConfigurationPropertySource;Lorg/springframework/boot/context/properties/source/ConfigurationPropertyName;Ljava/lang/Object;Lorg/springframework/boot/origin/Origin;)Lorg/springframework/boot/context/properties/source/ConfigurationProperty;
      37: areturn

  private org.springframework.boot.context.properties.source.ConfigurationPropertyName getPrefixedName(org.springframework.boot.context.properties.source.ConfigurationPropertyName);
    Code:
       0: aload_0
       1: getfield      #33                 // Field prefix:Lorg/springframework/boot/context/properties/source/ConfigurationPropertyName;
       4: aload_1
       5: invokevirtual #64                 // Method org/springframework/boot/context/properties/source/ConfigurationPropertyName.append:(Lorg/springframework/boot/context/properties/source/ConfigurationPropertyName;)Lorg/springframework/boot/context/properties/source/ConfigurationPropertyName;
       8: areturn

  public org.springframework.boot.context.properties.source.ConfigurationPropertyState containsDescendantOf(org.springframework.boot.context.properties.source.ConfigurationPropertyName);
    Code:
       0: aload_0
       1: getfield      #21                 // Field source:Lorg/springframework/boot/context/properties/source/ConfigurationPropertySource;
       4: aload_0
       5: aload_1
       6: invokevirtual #37                 // Method getPrefixedName:(Lorg/springframework/boot/context/properties/source/ConfigurationPropertyName;)Lorg/springframework/boot/context/properties/source/ConfigurationPropertyName;
       9: invokeinterface #67,  2           // InterfaceMethod org/springframework/boot/context/properties/source/ConfigurationPropertySource.containsDescendantOf:(Lorg/springframework/boot/context/properties/source/ConfigurationPropertyName;)Lorg/springframework/boot/context/properties/source/ConfigurationPropertyState;
      14: areturn

  public java.lang.Object getUnderlyingSource();
    Code:
       0: aload_0
       1: getfield      #21                 // Field source:Lorg/springframework/boot/context/properties/source/ConfigurationPropertySource;
       4: invokeinterface #71,  1           // InterfaceMethod org/springframework/boot/context/properties/source/ConfigurationPropertySource.getUnderlyingSource:()Ljava/lang/Object;
       9: areturn

  protected org.springframework.boot.context.properties.source.ConfigurationPropertySource getSource();
    Code:
       0: aload_0
       1: getfield      #21                 // Field source:Lorg/springframework/boot/context/properties/source/ConfigurationPropertySource;
       4: areturn
}
