Compiled from "SystemEnvironmentPropertyMapper.java"
final class org.springframework.boot.context.properties.source.SystemEnvironmentPropertyMapper implements org.springframework.boot.context.properties.source.PropertyMapper {
  public static final org.springframework.boot.context.properties.source.PropertyMapper INSTANCE;

  org.springframework.boot.context.properties.source.SystemEnvironmentPropertyMapper();
    Code:
       0: aload_0
       1: invokespecial #1                  // Method java/lang/Object."<init>":()V
       4: return

  public java.util.List<java.lang.String> map(org.springframework.boot.context.properties.source.ConfigurationPropertyName);
    Code:
       0: aload_0
       1: aload_1
       2: invokevirtual #7                  // Method convertName:(Lorg/springframework/boot/context/properties/source/ConfigurationPropertyName;)Ljava/lang/String;
       5: astore_2
       6: aload_0
       7: aload_1
       8: invokevirtual #13                 // Method convertLegacyName:(Lorg/springframework/boot/context/properties/source/ConfigurationPropertyName;)Ljava/lang/String;
      11: astore_3
      12: aload_2
      13: aload_3
      14: invokevirtual #16                 // Method java/lang/String.equals:(Ljava/lang/Object;)Z
      17: ifeq          25
      20: aload_2
      21: invokestatic  #22                 // Method java/util/Collections.singletonList:(Ljava/lang/Object;)Ljava/util/List;
      24: areturn
      25: iconst_2
      26: anewarray     #17                 // class java/lang/String
      29: dup
      30: iconst_0
      31: aload_2
      32: aastore
      33: dup
      34: iconst_1
      35: aload_3
      36: aastore
      37: invokestatic  #28                 // Method java/util/Arrays.asList:([Ljava/lang/Object;)Ljava/util/List;
      40: areturn

  private java.lang.String convertName(org.springframework.boot.context.properties.source.ConfigurationPropertyName);
    Code:
       0: aload_0
       1: aload_1
       2: aload_1
       3: invokevirtual #34                 // Method org/springframework/boot/context/properties/source/ConfigurationPropertyName.getNumberOfElements:()I
       6: invokevirtual #40                 // Method convertName:(Lorg/springframework/boot/context/properties/source/ConfigurationPropertyName;I)Ljava/lang/String;
       9: areturn

  private java.lang.String convertName(org.springframework.boot.context.properties.source.ConfigurationPropertyName, int);
    Code:
       0: new           #43                 // class java/lang/StringBuilder
       3: dup
       4: invokespecial #45                 // Method java/lang/StringBuilder."<init>":()V
       7: astore_3
       8: iconst_0
       9: istore        4
      11: iload         4
      13: iload_2
      14: if_icmpge     57
      17: aload_3
      18: invokevirtual #46                 // Method java/lang/StringBuilder.length:()I
      21: ifle          31
      24: aload_3
      25: bipush        95
      27: invokevirtual #49                 // Method java/lang/StringBuilder.append:(C)Ljava/lang/StringBuilder;
      30: pop
      31: aload_3
      32: aload_1
      33: iload         4
      35: getstatic     #53                 // Field org/springframework/boot/context/properties/source/ConfigurationPropertyName$Form.UNIFORM:Lorg/springframework/boot/context/properties/source/ConfigurationPropertyName$Form;
      38: invokevirtual #59                 // Method org/springframework/boot/context/properties/source/ConfigurationPropertyName.getElement:(ILorg/springframework/boot/context/properties/source/ConfigurationPropertyName$Form;)Ljava/lang/String;
      41: getstatic     #63                 // Field java/util/Locale.ENGLISH:Ljava/util/Locale;
      44: invokevirtual #69                 // Method java/lang/String.toUpperCase:(Ljava/util/Locale;)Ljava/lang/String;
      47: invokevirtual #73                 // Method java/lang/StringBuilder.append:(Ljava/lang/String;)Ljava/lang/StringBuilder;
      50: pop
      51: iinc          4, 1
      54: goto          11
      57: aload_3
      58: invokevirtual #76                 // Method java/lang/StringBuilder.toString:()Ljava/lang/String;
      61: areturn

  private java.lang.String convertLegacyName(org.springframework.boot.context.properties.source.ConfigurationPropertyName);
    Code:
       0: new           #43                 // class java/lang/StringBuilder
       3: dup
       4: invokespecial #45                 // Method java/lang/StringBuilder."<init>":()V
       7: astore_2
       8: iconst_0
       9: istore_3
      10: iload_3
      11: aload_1
      12: invokevirtual #34                 // Method org/springframework/boot/context/properties/source/ConfigurationPropertyName.getNumberOfElements:()I
      15: if_icmpge     55
      18: aload_2
      19: invokevirtual #46                 // Method java/lang/StringBuilder.length:()I
      22: ifle          32
      25: aload_2
      26: bipush        95
      28: invokevirtual #49                 // Method java/lang/StringBuilder.append:(C)Ljava/lang/StringBuilder;
      31: pop
      32: aload_2
      33: aload_0
      34: aload_1
      35: iload_3
      36: getstatic     #80                 // Field org/springframework/boot/context/properties/source/ConfigurationPropertyName$Form.ORIGINAL:Lorg/springframework/boot/context/properties/source/ConfigurationPropertyName$Form;
      39: invokevirtual #59                 // Method org/springframework/boot/context/properties/source/ConfigurationPropertyName.getElement:(ILorg/springframework/boot/context/properties/source/ConfigurationPropertyName$Form;)Ljava/lang/String;
      42: invokevirtual #83                 // Method convertLegacyNameElement:(Ljava/lang/String;)Ljava/lang/Object;
      45: invokevirtual #87                 // Method java/lang/StringBuilder.append:(Ljava/lang/Object;)Ljava/lang/StringBuilder;
      48: pop
      49: iinc          3, 1
      52: goto          10
      55: aload_2
      56: invokevirtual #76                 // Method java/lang/StringBuilder.toString:()Ljava/lang/String;
      59: areturn

  private java.lang.Object convertLegacyNameElement(java.lang.String);
    Code:
       0: aload_1
       1: bipush        45
       3: bipush        95
       5: invokevirtual #90                 // Method java/lang/String.replace:(CC)Ljava/lang/String;
       8: getstatic     #63                 // Field java/util/Locale.ENGLISH:Ljava/util/Locale;
      11: invokevirtual #69                 // Method java/lang/String.toUpperCase:(Ljava/util/Locale;)Ljava/lang/String;
      14: areturn

  public org.springframework.boot.context.properties.source.ConfigurationPropertyName map(java.lang.String);
    Code:
       0: aload_0
       1: aload_1
       2: invokevirtual #94                 // Method convertName:(Ljava/lang/String;)Lorg/springframework/boot/context/properties/source/ConfigurationPropertyName;
       5: areturn

  private org.springframework.boot.context.properties.source.ConfigurationPropertyName convertName(java.lang.String);
    Code:
       0: aload_1
       1: bipush        95
       3: aload_0
       4: invokedynamic #97,  0             // InvokeDynamic #0:apply:(Lorg/springframework/boot/context/properties/source/SystemEnvironmentPropertyMapper;)Ljava/util/function/Function;
       9: invokestatic  #101                // Method org/springframework/boot/context/properties/source/ConfigurationPropertyName.adapt:(Ljava/lang/CharSequence;CLjava/util/function/Function;)Lorg/springframework/boot/context/properties/source/ConfigurationPropertyName;
      12: areturn
      13: astore_2
      14: getstatic     #107                // Field org/springframework/boot/context/properties/source/ConfigurationPropertyName.EMPTY:Lorg/springframework/boot/context/properties/source/ConfigurationPropertyName;
      17: areturn
    Exception table:
       from    to  target type
           0    12    13   Class java/lang/Exception

  private java.lang.CharSequence processElementValue(java.lang.CharSequence);
    Code:
       0: aload_1
       1: invokeinterface #111,  1          // InterfaceMethod java/lang/CharSequence.toString:()Ljava/lang/String;
       6: getstatic     #63                 // Field java/util/Locale.ENGLISH:Ljava/util/Locale;
       9: invokevirtual #114                // Method java/lang/String.toLowerCase:(Ljava/util/Locale;)Ljava/lang/String;
      12: astore_2
      13: aload_2
      14: invokestatic  #117                // Method isNumber:(Ljava/lang/String;)Z
      17: ifeq          29
      20: aload_2
      21: invokedynamic #121,  0            // InvokeDynamic #1:makeConcatWithConstants:(Ljava/lang/String;)Ljava/lang/String;
      26: goto          30
      29: aload_2
      30: areturn

  private static boolean isNumber(java.lang.String);
    Code:
       0: aload_0
       1: invokevirtual #125                // Method java/lang/String.chars:()Ljava/util/stream/IntStream;
       4: invokedynamic #129,  0            // InvokeDynamic #2:test:()Ljava/util/function/IntPredicate;
       9: invokeinterface #133,  2          // InterfaceMethod java/util/stream/IntStream.allMatch:(Ljava/util/function/IntPredicate;)Z
      14: ireturn

  public java.util.function.BiPredicate<org.springframework.boot.context.properties.source.ConfigurationPropertyName, org.springframework.boot.context.properties.source.ConfigurationPropertyName> getAncestorOfCheck();
    Code:
       0: aload_0
       1: invokedynamic #139,  0            // InvokeDynamic #3:test:(Lorg/springframework/boot/context/properties/source/SystemEnvironmentPropertyMapper;)Ljava/util/function/BiPredicate;
       6: areturn

  private boolean isAncestorOf(org.springframework.boot.context.properties.source.ConfigurationPropertyName, org.springframework.boot.context.properties.source.ConfigurationPropertyName);
    Code:
       0: aload_1
       1: aload_2
       2: invokevirtual #142                // Method org/springframework/boot/context/properties/source/ConfigurationPropertyName.isAncestorOf:(Lorg/springframework/boot/context/properties/source/ConfigurationPropertyName;)Z
       5: ifne          17
       8: aload_0
       9: aload_1
      10: aload_2
      11: invokevirtual #146                // Method isLegacyAncestorOf:(Lorg/springframework/boot/context/properties/source/ConfigurationPropertyName;Lorg/springframework/boot/context/properties/source/ConfigurationPropertyName;)Z
      14: ifeq          21
      17: iconst_1
      18: goto          22
      21: iconst_0
      22: ireturn

  private boolean isLegacyAncestorOf(org.springframework.boot.context.properties.source.ConfigurationPropertyName, org.springframework.boot.context.properties.source.ConfigurationPropertyName);
    Code:
       0: aload_0
       1: aload_1
       2: invokevirtual #150                // Method hasDashedEntries:(Lorg/springframework/boot/context/properties/source/ConfigurationPropertyName;)Z
       5: ifne          10
       8: iconst_0
       9: ireturn
      10: aload_0
      11: aload_1
      12: invokevirtual #153                // Method buildLegacyCompatibleName:(Lorg/springframework/boot/context/properties/source/ConfigurationPropertyName;)Lorg/springframework/boot/context/properties/source/ConfigurationPropertyName;
      15: astore_3
      16: aload_3
      17: ifnull        32
      20: aload_3
      21: aload_2
      22: invokevirtual #142                // Method org/springframework/boot/context/properties/source/ConfigurationPropertyName.isAncestorOf:(Lorg/springframework/boot/context/properties/source/ConfigurationPropertyName;)Z
      25: ifeq          32
      28: iconst_1
      29: goto          33
      32: iconst_0
      33: ireturn

  private org.springframework.boot.context.properties.source.ConfigurationPropertyName buildLegacyCompatibleName(org.springframework.boot.context.properties.source.ConfigurationPropertyName);
    Code:
       0: new           #43                 // class java/lang/StringBuilder
       3: dup
       4: invokespecial #45                 // Method java/lang/StringBuilder."<init>":()V
       7: astore_2
       8: iconst_0
       9: istore_3
      10: iload_3
      11: aload_1
      12: invokevirtual #34                 // Method org/springframework/boot/context/properties/source/ConfigurationPropertyName.getNumberOfElements:()I
      15: if_icmpge     55
      18: iload_3
      19: ifeq          29
      22: aload_2
      23: bipush        46
      25: invokevirtual #49                 // Method java/lang/StringBuilder.append:(C)Ljava/lang/StringBuilder;
      28: pop
      29: aload_2
      30: aload_1
      31: iload_3
      32: getstatic     #157                // Field org/springframework/boot/context/properties/source/ConfigurationPropertyName$Form.DASHED:Lorg/springframework/boot/context/properties/source/ConfigurationPropertyName$Form;
      35: invokevirtual #59                 // Method org/springframework/boot/context/properties/source/ConfigurationPropertyName.getElement:(ILorg/springframework/boot/context/properties/source/ConfigurationPropertyName$Form;)Ljava/lang/String;
      38: bipush        45
      40: bipush        46
      42: invokevirtual #90                 // Method java/lang/String.replace:(CC)Ljava/lang/String;
      45: invokevirtual #73                 // Method java/lang/StringBuilder.append:(Ljava/lang/String;)Ljava/lang/StringBuilder;
      48: pop
      49: iinc          3, 1
      52: goto          10
      55: aload_2
      56: invokestatic  #160                // Method org/springframework/boot/context/properties/source/ConfigurationPropertyName.ofIfValid:(Ljava/lang/CharSequence;)Lorg/springframework/boot/context/properties/source/ConfigurationPropertyName;
      59: areturn

  boolean hasDashedEntries(org.springframework.boot.context.properties.source.ConfigurationPropertyName);
    Code:
       0: iconst_0
       1: istore_2
       2: iload_2
       3: aload_1
       4: invokevirtual #34                 // Method org/springframework/boot/context/properties/source/ConfigurationPropertyName.getNumberOfElements:()I
       7: if_icmpge     35
      10: aload_1
      11: iload_2
      12: getstatic     #157                // Field org/springframework/boot/context/properties/source/ConfigurationPropertyName$Form.DASHED:Lorg/springframework/boot/context/properties/source/ConfigurationPropertyName$Form;
      15: invokevirtual #59                 // Method org/springframework/boot/context/properties/source/ConfigurationPropertyName.getElement:(ILorg/springframework/boot/context/properties/source/ConfigurationPropertyName$Form;)Ljava/lang/String;
      18: bipush        45
      20: invokevirtual #164                // Method java/lang/String.indexOf:(I)I
      23: iconst_m1
      24: if_icmpeq     29
      27: iconst_1
      28: ireturn
      29: iinc          2, 1
      32: goto          2
      35: iconst_0
      36: ireturn

  static {};
    Code:
       0: new           #8                  // class org/springframework/boot/context/properties/source/SystemEnvironmentPropertyMapper
       3: dup
       4: invokespecial #168                // Method "<init>":()V
       7: putstatic     #169                // Field INSTANCE:Lorg/springframework/boot/context/properties/source/PropertyMapper;
      10: return
}
