Compiled from "AsyncProcessor.java"
final class io.reactivex.rxjava3.processors.AsyncProcessor$AsyncSubscription<T> extends io.reactivex.rxjava3.internal.subscriptions.DeferredScalarSubscription<T> {
  private static final long serialVersionUID;

  final io.reactivex.rxjava3.processors.AsyncProcessor<T> parent;

  io.reactivex.rxjava3.processors.AsyncProcessor$AsyncSubscription(org.reactivestreams.Subscriber<? super T>, io.reactivex.rxjava3.processors.AsyncProcessor<T>);
    Code:
       0: aload_0
       1: aload_1
       2: invokespecial #1                  // Method io/reactivex/rxjava3/internal/subscriptions/DeferredScalarSubscription."<init>":(Lorg/reactivestreams/Subscriber;)V
       5: aload_0
       6: aload_2
       7: putfield      #2                  // Field parent:Lio/reactivex/rxjava3/processors/AsyncProcessor;
      10: return

  public void cancel();
    Code:
       0: aload_0
       1: invokespecial #3                  // Method io/reactivex/rxjava3/internal/subscriptions/DeferredScalarSubscription.tryCancel:()Z
       4: ifeq          15
       7: aload_0
       8: getfield      #2                  // Field parent:Lio/reactivex/rxjava3/processors/AsyncProcessor;
      11: aload_0
      12: invokevirtual #4                  // Method io/reactivex/rxjava3/processors/AsyncProcessor.remove:(Lio/reactivex/rxjava3/processors/AsyncProcessor$AsyncSubscription;)V
      15: return

  void onComplete();
    Code:
       0: aload_0
       1: invokevirtual #5                  // Method isCancelled:()Z
       4: ifne          16
       7: aload_0
       8: getfield      #6                  // Field downstream:Lorg/reactivestreams/Subscriber;
      11: invokeinterface #7,  1            // InterfaceMethod org/reactivestreams/Subscriber.onComplete:()V
      16: return

  void onError(java.lang.Throwable);
    Code:
       0: aload_0
       1: invokevirtual #5                  // Method isCancelled:()Z
       4: ifeq          14
       7: aload_1
       8: invokestatic  #8                  // Method io/reactivex/rxjava3/plugins/RxJavaPlugins.onError:(Ljava/lang/Throwable;)V
      11: goto          24
      14: aload_0
      15: getfield      #6                  // Field downstream:Lorg/reactivestreams/Subscriber;
      18: aload_1
      19: invokeinterface #9,  2            // InterfaceMethod org/reactivestreams/Subscriber.onError:(Ljava/lang/Throwable;)V
      24: return
}
