Compiled from "BehaviorProcessor.java"
public final class io.reactivex.rxjava3.processors.BehaviorProcessor<T> extends io.reactivex.rxjava3.processors.FlowableProcessor<T> {
  final java.util.concurrent.atomic.AtomicReference<io.reactivex.rxjava3.processors.BehaviorProcessor$BehaviorSubscription<T>[]> subscribers;

  static final java.lang.Object[] EMPTY_ARRAY;

  static final io.reactivex.rxjava3.processors.BehaviorProcessor$BehaviorSubscription[] EMPTY;

  static final io.reactivex.rxjava3.processors.BehaviorProcessor$BehaviorSubscription[] TERMINATED;

  final java.util.concurrent.locks.ReadWriteLock lock;

  final java.util.concurrent.locks.Lock readLock;

  final java.util.concurrent.locks.Lock writeLock;

  final java.util.concurrent.atomic.AtomicReference<java.lang.Object> value;

  final java.util.concurrent.atomic.AtomicReference<java.lang.Throwable> terminalEvent;

  long index;

  public static <T> io.reactivex.rxjava3.processors.BehaviorProcessor<T> create();
    Code:
       0: new           #1                  // class io/reactivex/rxjava3/processors/BehaviorProcessor
       3: dup
       4: invokespecial #2                  // Method "<init>":()V
       7: areturn

  public static <T> io.reactivex.rxjava3.processors.BehaviorProcessor<T> createDefault(T);
    Code:
       0: aload_0
       1: ldc           #3                  // String defaultValue is null
       3: invokestatic  #4                  // Method java/util/Objects.requireNonNull:(Ljava/lang/Object;Ljava/lang/String;)Ljava/lang/Object;
       6: pop
       7: new           #1                  // class io/reactivex/rxjava3/processors/BehaviorProcessor
      10: dup
      11: aload_0
      12: invokespecial #5                  // Method "<init>":(Ljava/lang/Object;)V
      15: areturn

  io.reactivex.rxjava3.processors.BehaviorProcessor();
    Code:
       0: aload_0
       1: invokespecial #6                  // Method io/reactivex/rxjava3/processors/FlowableProcessor."<init>":()V
       4: aload_0
       5: new           #7                  // class java/util/concurrent/atomic/AtomicReference
       8: dup
       9: invokespecial #8                  // Method java/util/concurrent/atomic/AtomicReference."<init>":()V
      12: putfield      #9                  // Field value:Ljava/util/concurrent/atomic/AtomicReference;
      15: aload_0
      16: new           #10                 // class java/util/concurrent/locks/ReentrantReadWriteLock
      19: dup
      20: invokespecial #11                 // Method java/util/concurrent/locks/ReentrantReadWriteLock."<init>":()V
      23: putfield      #12                 // Field lock:Ljava/util/concurrent/locks/ReadWriteLock;
      26: aload_0
      27: aload_0
      28: getfield      #12                 // Field lock:Ljava/util/concurrent/locks/ReadWriteLock;
      31: invokeinterface #13,  1           // InterfaceMethod java/util/concurrent/locks/ReadWriteLock.readLock:()Ljava/util/concurrent/locks/Lock;
      36: putfield      #14                 // Field readLock:Ljava/util/concurrent/locks/Lock;
      39: aload_0
      40: aload_0
      41: getfield      #12                 // Field lock:Ljava/util/concurrent/locks/ReadWriteLock;
      44: invokeinterface #15,  1           // InterfaceMethod java/util/concurrent/locks/ReadWriteLock.writeLock:()Ljava/util/concurrent/locks/Lock;
      49: putfield      #16                 // Field writeLock:Ljava/util/concurrent/locks/Lock;
      52: aload_0
      53: new           #7                  // class java/util/concurrent/atomic/AtomicReference
      56: dup
      57: getstatic     #17                 // Field EMPTY:[Lio/reactivex/rxjava3/processors/BehaviorProcessor$BehaviorSubscription;
      60: invokespecial #18                 // Method java/util/concurrent/atomic/AtomicReference."<init>":(Ljava/lang/Object;)V
      63: putfield      #19                 // Field subscribers:Ljava/util/concurrent/atomic/AtomicReference;
      66: aload_0
      67: new           #7                  // class java/util/concurrent/atomic/AtomicReference
      70: dup
      71: invokespecial #8                  // Method java/util/concurrent/atomic/AtomicReference."<init>":()V
      74: putfield      #20                 // Field terminalEvent:Ljava/util/concurrent/atomic/AtomicReference;
      77: return

  io.reactivex.rxjava3.processors.BehaviorProcessor(T);
    Code:
       0: aload_0
       1: invokespecial #2                  // Method "<init>":()V
       4: aload_0
       5: getfield      #9                  // Field value:Ljava/util/concurrent/atomic/AtomicReference;
       8: aload_1
       9: invokevirtual #21                 // Method java/util/concurrent/atomic/AtomicReference.lazySet:(Ljava/lang/Object;)V
      12: return

  protected void subscribeActual(org.reactivestreams.Subscriber<? super T>);
    Code:
       0: new           #22                 // class io/reactivex/rxjava3/processors/BehaviorProcessor$BehaviorSubscription
       3: dup
       4: aload_1
       5: aload_0
       6: invokespecial #23                 // Method io/reactivex/rxjava3/processors/BehaviorProcessor$BehaviorSubscription."<init>":(Lorg/reactivestreams/Subscriber;Lio/reactivex/rxjava3/processors/BehaviorProcessor;)V
       9: astore_2
      10: aload_1
      11: aload_2
      12: invokeinterface #24,  2           // InterfaceMethod org/reactivestreams/Subscriber.onSubscribe:(Lorg/reactivestreams/Subscription;)V
      17: aload_0
      18: aload_2
      19: invokevirtual #25                 // Method add:(Lio/reactivex/rxjava3/processors/BehaviorProcessor$BehaviorSubscription;)Z
      22: ifeq          47
      25: aload_2
      26: getfield      #26                 // Field io/reactivex/rxjava3/processors/BehaviorProcessor$BehaviorSubscription.cancelled:Z
      29: ifeq          40
      32: aload_0
      33: aload_2
      34: invokevirtual #27                 // Method remove:(Lio/reactivex/rxjava3/processors/BehaviorProcessor$BehaviorSubscription;)V
      37: goto          81
      40: aload_2
      41: invokevirtual #28                 // Method io/reactivex/rxjava3/processors/BehaviorProcessor$BehaviorSubscription.emitFirst:()V
      44: goto          81
      47: aload_0
      48: getfield      #20                 // Field terminalEvent:Ljava/util/concurrent/atomic/AtomicReference;
      51: invokevirtual #29                 // Method java/util/concurrent/atomic/AtomicReference.get:()Ljava/lang/Object;
      54: checkcast     #30                 // class java/lang/Throwable
      57: astore_3
      58: aload_3
      59: getstatic     #31                 // Field io/reactivex/rxjava3/internal/util/ExceptionHelper.TERMINATED:Ljava/lang/Throwable;
      62: if_acmpne     74
      65: aload_1
      66: invokeinterface #32,  1           // InterfaceMethod org/reactivestreams/Subscriber.onComplete:()V
      71: goto          81
      74: aload_1
      75: aload_3
      76: invokeinterface #33,  2           // InterfaceMethod org/reactivestreams/Subscriber.onError:(Ljava/lang/Throwable;)V
      81: return

  public void onSubscribe(org.reactivestreams.Subscription);
    Code:
       0: aload_0
       1: getfield      #20                 // Field terminalEvent:Ljava/util/concurrent/atomic/AtomicReference;
       4: invokevirtual #29                 // Method java/util/concurrent/atomic/AtomicReference.get:()Ljava/lang/Object;
       7: ifnull        17
      10: aload_1
      11: invokeinterface #34,  1           // InterfaceMethod org/reactivestreams/Subscription.cancel:()V
      16: return
      17: aload_1
      18: ldc2_w        #36                 // long 9223372036854775807l
      21: invokeinterface #38,  3           // InterfaceMethod org/reactivestreams/Subscription.request:(J)V
      26: return

  public void onNext(T);
    Code:
       0: aload_1
       1: ldc           #39                 // String onNext called with a null value.
       3: invokestatic  #40                 // Method io/reactivex/rxjava3/internal/util/ExceptionHelper.nullCheck:(Ljava/lang/Object;Ljava/lang/String;)Ljava/lang/Object;
       6: pop
       7: aload_0
       8: getfield      #20                 // Field terminalEvent:Ljava/util/concurrent/atomic/AtomicReference;
      11: invokevirtual #29                 // Method java/util/concurrent/atomic/AtomicReference.get:()Ljava/lang/Object;
      14: ifnull        18
      17: return
      18: aload_1
      19: invokestatic  #41                 // Method io/reactivex/rxjava3/internal/util/NotificationLite.next:(Ljava/lang/Object;)Ljava/lang/Object;
      22: astore_2
      23: aload_0
      24: aload_2
      25: invokevirtual #42                 // Method setCurrent:(Ljava/lang/Object;)V
      28: aload_0
      29: getfield      #19                 // Field subscribers:Ljava/util/concurrent/atomic/AtomicReference;
      32: invokevirtual #29                 // Method java/util/concurrent/atomic/AtomicReference.get:()Ljava/lang/Object;
      35: checkcast     #43                 // class "[Lio/reactivex/rxjava3/processors/BehaviorProcessor$BehaviorSubscription;"
      38: astore_3
      39: aload_3
      40: arraylength
      41: istore        4
      43: iconst_0
      44: istore        5
      46: iload         5
      48: iload         4
      50: if_icmpge     75
      53: aload_3
      54: iload         5
      56: aaload
      57: astore        6
      59: aload         6
      61: aload_2
      62: aload_0
      63: getfield      #44                 // Field index:J
      66: invokevirtual #45                 // Method io/reactivex/rxjava3/processors/BehaviorProcessor$BehaviorSubscription.emitNext:(Ljava/lang/Object;J)V
      69: iinc          5, 1
      72: goto          46
      75: return

  public void onError(java.lang.Throwable);
    Code:
       0: aload_1
       1: ldc           #46                 // String onError called with a null Throwable.
       3: invokestatic  #40                 // Method io/reactivex/rxjava3/internal/util/ExceptionHelper.nullCheck:(Ljava/lang/Object;Ljava/lang/String;)Ljava/lang/Object;
       6: pop
       7: aload_0
       8: getfield      #20                 // Field terminalEvent:Ljava/util/concurrent/atomic/AtomicReference;
      11: aconst_null
      12: aload_1
      13: invokevirtual #47                 // Method java/util/concurrent/atomic/AtomicReference.compareAndSet:(Ljava/lang/Object;Ljava/lang/Object;)Z
      16: ifne          24
      19: aload_1
      20: invokestatic  #48                 // Method io/reactivex/rxjava3/plugins/RxJavaPlugins.onError:(Ljava/lang/Throwable;)V
      23: return
      24: aload_1
      25: invokestatic  #49                 // Method io/reactivex/rxjava3/internal/util/NotificationLite.error:(Ljava/lang/Throwable;)Ljava/lang/Object;
      28: astore_2
      29: aload_0
      30: aload_2
      31: invokevirtual #50                 // Method terminate:(Ljava/lang/Object;)[Lio/reactivex/rxjava3/processors/BehaviorProcessor$BehaviorSubscription;
      34: astore_3
      35: aload_3
      36: arraylength
      37: istore        4
      39: iconst_0
      40: istore        5
      42: iload         5
      44: iload         4
      46: if_icmpge     71
      49: aload_3
      50: iload         5
      52: aaload
      53: astore        6
      55: aload         6
      57: aload_2
      58: aload_0
      59: getfield      #44                 // Field index:J
      62: invokevirtual #45                 // Method io/reactivex/rxjava3/processors/BehaviorProcessor$BehaviorSubscription.emitNext:(Ljava/lang/Object;J)V
      65: iinc          5, 1
      68: goto          42
      71: return

  public void onComplete();
    Code:
       0: aload_0
       1: getfield      #20                 // Field terminalEvent:Ljava/util/concurrent/atomic/AtomicReference;
       4: aconst_null
       5: getstatic     #31                 // Field io/reactivex/rxjava3/internal/util/ExceptionHelper.TERMINATED:Ljava/lang/Throwable;
       8: invokevirtual #47                 // Method java/util/concurrent/atomic/AtomicReference.compareAndSet:(Ljava/lang/Object;Ljava/lang/Object;)Z
      11: ifne          15
      14: return
      15: invokestatic  #51                 // Method io/reactivex/rxjava3/internal/util/NotificationLite.complete:()Ljava/lang/Object;
      18: astore_1
      19: aload_0
      20: aload_1
      21: invokevirtual #50                 // Method terminate:(Ljava/lang/Object;)[Lio/reactivex/rxjava3/processors/BehaviorProcessor$BehaviorSubscription;
      24: astore_2
      25: aload_2
      26: arraylength
      27: istore_3
      28: iconst_0
      29: istore        4
      31: iload         4
      33: iload_3
      34: if_icmpge     59
      37: aload_2
      38: iload         4
      40: aaload
      41: astore        5
      43: aload         5
      45: aload_1
      46: aload_0
      47: getfield      #44                 // Field index:J
      50: invokevirtual #45                 // Method io/reactivex/rxjava3/processors/BehaviorProcessor$BehaviorSubscription.emitNext:(Ljava/lang/Object;J)V
      53: iinc          4, 1
      56: goto          31
      59: return

  public boolean offer(T);
    Code:
       0: aload_1
       1: ldc           #52                 // String offer called with a null value.
       3: invokestatic  #40                 // Method io/reactivex/rxjava3/internal/util/ExceptionHelper.nullCheck:(Ljava/lang/Object;Ljava/lang/String;)Ljava/lang/Object;
       6: pop
       7: aload_0
       8: getfield      #19                 // Field subscribers:Ljava/util/concurrent/atomic/AtomicReference;
      11: invokevirtual #29                 // Method java/util/concurrent/atomic/AtomicReference.get:()Ljava/lang/Object;
      14: checkcast     #43                 // class "[Lio/reactivex/rxjava3/processors/BehaviorProcessor$BehaviorSubscription;"
      17: astore_2
      18: aload_2
      19: astore_3
      20: aload_3
      21: arraylength
      22: istore        4
      24: iconst_0
      25: istore        5
      27: iload         5
      29: iload         4
      31: if_icmpge     56
      34: aload_3
      35: iload         5
      37: aaload
      38: astore        6
      40: aload         6
      42: invokevirtual #53                 // Method io/reactivex/rxjava3/processors/BehaviorProcessor$BehaviorSubscription.isFull:()Z
      45: ifeq          50
      48: iconst_0
      49: ireturn
      50: iinc          5, 1
      53: goto          27
      56: aload_1
      57: invokestatic  #41                 // Method io/reactivex/rxjava3/internal/util/NotificationLite.next:(Ljava/lang/Object;)Ljava/lang/Object;
      60: astore_3
      61: aload_0
      62: aload_3
      63: invokevirtual #42                 // Method setCurrent:(Ljava/lang/Object;)V
      66: aload_2
      67: astore        4
      69: aload         4
      71: arraylength
      72: istore        5
      74: iconst_0
      75: istore        6
      77: iload         6
      79: iload         5
      81: if_icmpge     107
      84: aload         4
      86: iload         6
      88: aaload
      89: astore        7
      91: aload         7
      93: aload_3
      94: aload_0
      95: getfield      #44                 // Field index:J
      98: invokevirtual #45                 // Method io/reactivex/rxjava3/processors/BehaviorProcessor$BehaviorSubscription.emitNext:(Ljava/lang/Object;J)V
     101: iinc          6, 1
     104: goto          77
     107: iconst_1
     108: ireturn

  public boolean hasSubscribers();
    Code:
       0: aload_0
       1: getfield      #19                 // Field subscribers:Ljava/util/concurrent/atomic/AtomicReference;
       4: invokevirtual #29                 // Method java/util/concurrent/atomic/AtomicReference.get:()Ljava/lang/Object;
       7: checkcast     #43                 // class "[Lio/reactivex/rxjava3/processors/BehaviorProcessor$BehaviorSubscription;"
      10: arraylength
      11: ifeq          18
      14: iconst_1
      15: goto          19
      18: iconst_0
      19: ireturn

  int subscriberCount();
    Code:
       0: aload_0
       1: getfield      #19                 // Field subscribers:Ljava/util/concurrent/atomic/AtomicReference;
       4: invokevirtual #29                 // Method java/util/concurrent/atomic/AtomicReference.get:()Ljava/lang/Object;
       7: checkcast     #43                 // class "[Lio/reactivex/rxjava3/processors/BehaviorProcessor$BehaviorSubscription;"
      10: arraylength
      11: ireturn

  public java.lang.Throwable getThrowable();
    Code:
       0: aload_0
       1: getfield      #9                  // Field value:Ljava/util/concurrent/atomic/AtomicReference;
       4: invokevirtual #29                 // Method java/util/concurrent/atomic/AtomicReference.get:()Ljava/lang/Object;
       7: astore_1
       8: aload_1
       9: invokestatic  #54                 // Method io/reactivex/rxjava3/internal/util/NotificationLite.isError:(Ljava/lang/Object;)Z
      12: ifeq          20
      15: aload_1
      16: invokestatic  #55                 // Method io/reactivex/rxjava3/internal/util/NotificationLite.getError:(Ljava/lang/Object;)Ljava/lang/Throwable;
      19: areturn
      20: aconst_null
      21: areturn

  public T getValue();
    Code:
       0: aload_0
       1: getfield      #9                  // Field value:Ljava/util/concurrent/atomic/AtomicReference;
       4: invokevirtual #29                 // Method java/util/concurrent/atomic/AtomicReference.get:()Ljava/lang/Object;
       7: astore_1
       8: aload_1
       9: invokestatic  #56                 // Method io/reactivex/rxjava3/internal/util/NotificationLite.isComplete:(Ljava/lang/Object;)Z
      12: ifne          22
      15: aload_1
      16: invokestatic  #54                 // Method io/reactivex/rxjava3/internal/util/NotificationLite.isError:(Ljava/lang/Object;)Z
      19: ifeq          24
      22: aconst_null
      23: areturn
      24: aload_1
      25: invokestatic  #57                 // Method io/reactivex/rxjava3/internal/util/NotificationLite.getValue:(Ljava/lang/Object;)Ljava/lang/Object;
      28: areturn

  public boolean hasComplete();
    Code:
       0: aload_0
       1: getfield      #9                  // Field value:Ljava/util/concurrent/atomic/AtomicReference;
       4: invokevirtual #29                 // Method java/util/concurrent/atomic/AtomicReference.get:()Ljava/lang/Object;
       7: astore_1
       8: aload_1
       9: invokestatic  #56                 // Method io/reactivex/rxjava3/internal/util/NotificationLite.isComplete:(Ljava/lang/Object;)Z
      12: ireturn

  public boolean hasThrowable();
    Code:
       0: aload_0
       1: getfield      #9                  // Field value:Ljava/util/concurrent/atomic/AtomicReference;
       4: invokevirtual #29                 // Method java/util/concurrent/atomic/AtomicReference.get:()Ljava/lang/Object;
       7: astore_1
       8: aload_1
       9: invokestatic  #54                 // Method io/reactivex/rxjava3/internal/util/NotificationLite.isError:(Ljava/lang/Object;)Z
      12: ireturn

  public boolean hasValue();
    Code:
       0: aload_0
       1: getfield      #9                  // Field value:Ljava/util/concurrent/atomic/AtomicReference;
       4: invokevirtual #29                 // Method java/util/concurrent/atomic/AtomicReference.get:()Ljava/lang/Object;
       7: astore_1
       8: aload_1
       9: ifnull        30
      12: aload_1
      13: invokestatic  #56                 // Method io/reactivex/rxjava3/internal/util/NotificationLite.isComplete:(Ljava/lang/Object;)Z
      16: ifne          30
      19: aload_1
      20: invokestatic  #54                 // Method io/reactivex/rxjava3/internal/util/NotificationLite.isError:(Ljava/lang/Object;)Z
      23: ifne          30
      26: iconst_1
      27: goto          31
      30: iconst_0
      31: ireturn

  boolean add(io.reactivex.rxjava3.processors.BehaviorProcessor$BehaviorSubscription<T>);
    Code:
       0: aload_0
       1: getfield      #19                 // Field subscribers:Ljava/util/concurrent/atomic/AtomicReference;
       4: invokevirtual #29                 // Method java/util/concurrent/atomic/AtomicReference.get:()Ljava/lang/Object;
       7: checkcast     #43                 // class "[Lio/reactivex/rxjava3/processors/BehaviorProcessor$BehaviorSubscription;"
      10: astore_2
      11: aload_2
      12: getstatic     #58                 // Field TERMINATED:[Lio/reactivex/rxjava3/processors/BehaviorProcessor$BehaviorSubscription;
      15: if_acmpne     20
      18: iconst_0
      19: ireturn
      20: aload_2
      21: arraylength
      22: istore_3
      23: iload_3
      24: iconst_1
      25: iadd
      26: anewarray     #22                 // class io/reactivex/rxjava3/processors/BehaviorProcessor$BehaviorSubscription
      29: astore        4
      31: aload_2
      32: iconst_0
      33: aload         4
      35: iconst_0
      36: iload_3
      37: invokestatic  #59                 // Method java/lang/System.arraycopy:(Ljava/lang/Object;ILjava/lang/Object;II)V
      40: aload         4
      42: iload_3
      43: aload_1
      44: aastore
      45: aload_0
      46: getfield      #19                 // Field subscribers:Ljava/util/concurrent/atomic/AtomicReference;
      49: aload_2
      50: aload         4
      52: invokevirtual #47                 // Method java/util/concurrent/atomic/AtomicReference.compareAndSet:(Ljava/lang/Object;Ljava/lang/Object;)Z
      55: ifeq          60
      58: iconst_1
      59: ireturn
      60: goto          0

  void remove(io.reactivex.rxjava3.processors.BehaviorProcessor$BehaviorSubscription<T>);
    Code:
       0: aload_0
       1: getfield      #19                 // Field subscribers:Ljava/util/concurrent/atomic/AtomicReference;
       4: invokevirtual #29                 // Method java/util/concurrent/atomic/AtomicReference.get:()Ljava/lang/Object;
       7: checkcast     #43                 // class "[Lio/reactivex/rxjava3/processors/BehaviorProcessor$BehaviorSubscription;"
      10: astore_2
      11: aload_2
      12: arraylength
      13: istore_3
      14: iload_3
      15: ifne          19
      18: return
      19: iconst_m1
      20: istore        4
      22: iconst_0
      23: istore        5
      25: iload         5
      27: iload_3
      28: if_icmpge     52
      31: aload_2
      32: iload         5
      34: aaload
      35: aload_1
      36: if_acmpne     46
      39: iload         5
      41: istore        4
      43: goto          52
      46: iinc          5, 1
      49: goto          25
      52: iload         4
      54: ifge          58
      57: return
      58: iload_3
      59: iconst_1
      60: if_icmpne     71
      63: getstatic     #17                 // Field EMPTY:[Lio/reactivex/rxjava3/processors/BehaviorProcessor$BehaviorSubscription;
      66: astore        5
      68: goto          107
      71: iload_3
      72: iconst_1
      73: isub
      74: anewarray     #22                 // class io/reactivex/rxjava3/processors/BehaviorProcessor$BehaviorSubscription
      77: astore        5
      79: aload_2
      80: iconst_0
      81: aload         5
      83: iconst_0
      84: iload         4
      86: invokestatic  #59                 // Method java/lang/System.arraycopy:(Ljava/lang/Object;ILjava/lang/Object;II)V
      89: aload_2
      90: iload         4
      92: iconst_1
      93: iadd
      94: aload         5
      96: iload         4
      98: iload_3
      99: iload         4
     101: isub
     102: iconst_1
     103: isub
     104: invokestatic  #59                 // Method java/lang/System.arraycopy:(Ljava/lang/Object;ILjava/lang/Object;II)V
     107: aload_0
     108: getfield      #19                 // Field subscribers:Ljava/util/concurrent/atomic/AtomicReference;
     111: aload_2
     112: aload         5
     114: invokevirtual #47                 // Method java/util/concurrent/atomic/AtomicReference.compareAndSet:(Ljava/lang/Object;Ljava/lang/Object;)Z
     117: ifeq          121
     120: return
     121: goto          0

  io.reactivex.rxjava3.processors.BehaviorProcessor$BehaviorSubscription<T>[] terminate(java.lang.Object);
    Code:
       0: aload_0
       1: aload_1
       2: invokevirtual #42                 // Method setCurrent:(Ljava/lang/Object;)V
       5: aload_0
       6: getfield      #19                 // Field subscribers:Ljava/util/concurrent/atomic/AtomicReference;
       9: getstatic     #58                 // Field TERMINATED:[Lio/reactivex/rxjava3/processors/BehaviorProcessor$BehaviorSubscription;
      12: invokevirtual #60                 // Method java/util/concurrent/atomic/AtomicReference.getAndSet:(Ljava/lang/Object;)Ljava/lang/Object;
      15: checkcast     #43                 // class "[Lio/reactivex/rxjava3/processors/BehaviorProcessor$BehaviorSubscription;"
      18: areturn

  void setCurrent(java.lang.Object);
    Code:
       0: aload_0
       1: getfield      #16                 // Field writeLock:Ljava/util/concurrent/locks/Lock;
       4: astore_2
       5: aload_2
       6: invokeinterface #61,  1           // InterfaceMethod java/util/concurrent/locks/Lock.lock:()V
      11: aload_0
      12: dup
      13: getfield      #44                 // Field index:J
      16: lconst_1
      17: ladd
      18: putfield      #44                 // Field index:J
      21: aload_0
      22: getfield      #9                  // Field value:Ljava/util/concurrent/atomic/AtomicReference;
      25: aload_1
      26: invokevirtual #21                 // Method java/util/concurrent/atomic/AtomicReference.lazySet:(Ljava/lang/Object;)V
      29: aload_2
      30: invokeinterface #62,  1           // InterfaceMethod java/util/concurrent/locks/Lock.unlock:()V
      35: return

  static {};
    Code:
       0: iconst_0
       1: anewarray     #63                 // class java/lang/Object
       4: putstatic     #64                 // Field EMPTY_ARRAY:[Ljava/lang/Object;
       7: iconst_0
       8: anewarray     #22                 // class io/reactivex/rxjava3/processors/BehaviorProcessor$BehaviorSubscription
      11: putstatic     #17                 // Field EMPTY:[Lio/reactivex/rxjava3/processors/BehaviorProcessor$BehaviorSubscription;
      14: iconst_0
      15: anewarray     #22                 // class io/reactivex/rxjava3/processors/BehaviorProcessor$BehaviorSubscription
      18: putstatic     #58                 // Field TERMINATED:[Lio/reactivex/rxjava3/processors/BehaviorProcessor$BehaviorSubscription;
      21: return
}
