Compiled from "FlowableProcessor.java"
public abstract class io.reactivex.rxjava3.processors.FlowableProcessor<T> extends io.reactivex.rxjava3.core.Flowable<T> implements org.reactivestreams.Processor<T, T>, io.reactivex.rxjava3.core.FlowableSubscriber<T> {
  public io.reactivex.rxjava3.processors.FlowableProcessor();
    Code:
       0: aload_0
       1: invokespecial #1                  // Method io/reactivex/rxjava3/core/Flowable."<init>":()V
       4: return

  public abstract boolean hasSubscribers();

  public abstract boolean hasThrowable();

  public abstract boolean hasComplete();

  public abstract java.lang.Throwable getThrowable();

  public final io.reactivex.rxjava3.processors.FlowableProcessor<T> toSerialized();
    Code:
       0: aload_0
       1: instanceof    #2                  // class io/reactivex/rxjava3/processors/SerializedProcessor
       4: ifeq          9
       7: aload_0
       8: areturn
       9: new           #2                  // class io/reactivex/rxjava3/processors/SerializedProcessor
      12: dup
      13: aload_0
      14: invokespecial #3                  // Method io/reactivex/rxjava3/processors/SerializedProcessor."<init>":(Lio/reactivex/rxjava3/processors/FlowableProcessor;)V
      17: areturn
}
