Compiled from "MulticastProcessor.java"
public final class io.reactivex.rxjava3.processors.MulticastProcessor<T> extends io.reactivex.rxjava3.processors.FlowableProcessor<T> {
  final java.util.concurrent.atomic.AtomicInteger wip;

  final java.util.concurrent.atomic.AtomicReference<org.reactivestreams.Subscription> upstream;

  final java.util.concurrent.atomic.AtomicReference<io.reactivex.rxjava3.processors.MulticastProcessor$MulticastSubscription<T>[]> subscribers;

  final int bufferSize;

  final int limit;

  final boolean refcount;

  volatile io.reactivex.rxjava3.operators.SimpleQueue<T> queue;

  volatile boolean done;

  volatile java.lang.Throwable error;

  int consumed;

  int fusionMode;

  static final io.reactivex.rxjava3.processors.MulticastProcessor$MulticastSubscription[] EMPTY;

  static final io.reactivex.rxjava3.processors.MulticastProcessor$MulticastSubscription[] TERMINATED;

  public static <T> io.reactivex.rxjava3.processors.MulticastProcessor<T> create();
    Code:
       0: new           #1                  // class io/reactivex/rxjava3/processors/MulticastProcessor
       3: dup
       4: invokestatic  #2                  // Method bufferSize:()I
       7: iconst_0
       8: invokespecial #3                  // Method "<init>":(IZ)V
      11: areturn

  public static <T> io.reactivex.rxjava3.processors.MulticastProcessor<T> create(boolean);
    Code:
       0: new           #1                  // class io/reactivex/rxjava3/processors/MulticastProcessor
       3: dup
       4: invokestatic  #2                  // Method bufferSize:()I
       7: iload_0
       8: invokespecial #3                  // Method "<init>":(IZ)V
      11: areturn

  public static <T> io.reactivex.rxjava3.processors.MulticastProcessor<T> create(int);
    Code:
       0: iload_0
       1: ldc           #4                  // String bufferSize
       3: invokestatic  #5                  // Method io/reactivex/rxjava3/internal/functions/ObjectHelper.verifyPositive:(ILjava/lang/String;)I
       6: pop
       7: new           #1                  // class io/reactivex/rxjava3/processors/MulticastProcessor
      10: dup
      11: iload_0
      12: iconst_0
      13: invokespecial #3                  // Method "<init>":(IZ)V
      16: areturn

  public static <T> io.reactivex.rxjava3.processors.MulticastProcessor<T> create(int, boolean);
    Code:
       0: iload_0
       1: ldc           #4                  // String bufferSize
       3: invokestatic  #5                  // Method io/reactivex/rxjava3/internal/functions/ObjectHelper.verifyPositive:(ILjava/lang/String;)I
       6: pop
       7: new           #1                  // class io/reactivex/rxjava3/processors/MulticastProcessor
      10: dup
      11: iload_0
      12: iload_1
      13: invokespecial #3                  // Method "<init>":(IZ)V
      16: areturn

  io.reactivex.rxjava3.processors.MulticastProcessor(int, boolean);
    Code:
       0: aload_0
       1: invokespecial #6                  // Method io/reactivex/rxjava3/processors/FlowableProcessor."<init>":()V
       4: aload_0
       5: iload_1
       6: putfield      #7                  // Field bufferSize:I
       9: aload_0
      10: iload_1
      11: iload_1
      12: iconst_2
      13: ishr
      14: isub
      15: putfield      #8                  // Field limit:I
      18: aload_0
      19: new           #9                  // class java/util/concurrent/atomic/AtomicInteger
      22: dup
      23: invokespecial #10                 // Method java/util/concurrent/atomic/AtomicInteger."<init>":()V
      26: putfield      #11                 // Field wip:Ljava/util/concurrent/atomic/AtomicInteger;
      29: aload_0
      30: new           #12                 // class java/util/concurrent/atomic/AtomicReference
      33: dup
      34: getstatic     #13                 // Field EMPTY:[Lio/reactivex/rxjava3/processors/MulticastProcessor$MulticastSubscription;
      37: invokespecial #14                 // Method java/util/concurrent/atomic/AtomicReference."<init>":(Ljava/lang/Object;)V
      40: putfield      #15                 // Field subscribers:Ljava/util/concurrent/atomic/AtomicReference;
      43: aload_0
      44: new           #12                 // class java/util/concurrent/atomic/AtomicReference
      47: dup
      48: invokespecial #16                 // Method java/util/concurrent/atomic/AtomicReference."<init>":()V
      51: putfield      #17                 // Field upstream:Ljava/util/concurrent/atomic/AtomicReference;
      54: aload_0
      55: iload_2
      56: putfield      #18                 // Field refcount:Z
      59: return

  public void start();
    Code:
       0: aload_0
       1: getfield      #17                 // Field upstream:Ljava/util/concurrent/atomic/AtomicReference;
       4: getstatic     #19                 // Field io/reactivex/rxjava3/internal/subscriptions/EmptySubscription.INSTANCE:Lio/reactivex/rxjava3/internal/subscriptions/EmptySubscription;
       7: invokestatic  #20                 // Method io/reactivex/rxjava3/internal/subscriptions/SubscriptionHelper.setOnce:(Ljava/util/concurrent/atomic/AtomicReference;Lorg/reactivestreams/Subscription;)Z
      10: ifeq          28
      13: aload_0
      14: new           #21                 // class io/reactivex/rxjava3/operators/SpscArrayQueue
      17: dup
      18: aload_0
      19: getfield      #7                  // Field bufferSize:I
      22: invokespecial #22                 // Method io/reactivex/rxjava3/operators/SpscArrayQueue."<init>":(I)V
      25: putfield      #23                 // Field queue:Lio/reactivex/rxjava3/operators/SimpleQueue;
      28: return

  public void startUnbounded();
    Code:
       0: aload_0
       1: getfield      #17                 // Field upstream:Ljava/util/concurrent/atomic/AtomicReference;
       4: getstatic     #19                 // Field io/reactivex/rxjava3/internal/subscriptions/EmptySubscription.INSTANCE:Lio/reactivex/rxjava3/internal/subscriptions/EmptySubscription;
       7: invokestatic  #20                 // Method io/reactivex/rxjava3/internal/subscriptions/SubscriptionHelper.setOnce:(Ljava/util/concurrent/atomic/AtomicReference;Lorg/reactivestreams/Subscription;)Z
      10: ifeq          28
      13: aload_0
      14: new           #24                 // class io/reactivex/rxjava3/operators/SpscLinkedArrayQueue
      17: dup
      18: aload_0
      19: getfield      #7                  // Field bufferSize:I
      22: invokespecial #25                 // Method io/reactivex/rxjava3/operators/SpscLinkedArrayQueue."<init>":(I)V
      25: putfield      #23                 // Field queue:Lio/reactivex/rxjava3/operators/SimpleQueue;
      28: return

  public void onSubscribe(org.reactivestreams.Subscription);
    Code:
       0: aload_0
       1: getfield      #17                 // Field upstream:Ljava/util/concurrent/atomic/AtomicReference;
       4: aload_1
       5: invokestatic  #20                 // Method io/reactivex/rxjava3/internal/subscriptions/SubscriptionHelper.setOnce:(Ljava/util/concurrent/atomic/AtomicReference;Lorg/reactivestreams/Subscription;)Z
       8: ifeq          109
      11: aload_1
      12: instanceof    #26                 // class io/reactivex/rxjava3/operators/QueueSubscription
      15: ifeq          83
      18: aload_1
      19: checkcast     #26                 // class io/reactivex/rxjava3/operators/QueueSubscription
      22: astore_2
      23: aload_2
      24: iconst_3
      25: invokeinterface #27,  2           // InterfaceMethod io/reactivex/rxjava3/operators/QueueSubscription.requestFusion:(I)I
      30: istore_3
      31: iload_3
      32: iconst_1
      33: if_icmpne     56
      36: aload_0
      37: iload_3
      38: putfield      #28                 // Field fusionMode:I
      41: aload_0
      42: aload_2
      43: putfield      #23                 // Field queue:Lio/reactivex/rxjava3/operators/SimpleQueue;
      46: aload_0
      47: iconst_1
      48: putfield      #29                 // Field done:Z
      51: aload_0
      52: invokevirtual #30                 // Method drain:()V
      55: return
      56: iload_3
      57: iconst_2
      58: if_icmpne     83
      61: aload_0
      62: iload_3
      63: putfield      #28                 // Field fusionMode:I
      66: aload_0
      67: aload_2
      68: putfield      #23                 // Field queue:Lio/reactivex/rxjava3/operators/SimpleQueue;
      71: aload_1
      72: aload_0
      73: getfield      #7                  // Field bufferSize:I
      76: i2l
      77: invokeinterface #31,  3           // InterfaceMethod org/reactivestreams/Subscription.request:(J)V
      82: return
      83: aload_0
      84: new           #21                 // class io/reactivex/rxjava3/operators/SpscArrayQueue
      87: dup
      88: aload_0
      89: getfield      #7                  // Field bufferSize:I
      92: invokespecial #22                 // Method io/reactivex/rxjava3/operators/SpscArrayQueue."<init>":(I)V
      95: putfield      #23                 // Field queue:Lio/reactivex/rxjava3/operators/SimpleQueue;
      98: aload_1
      99: aload_0
     100: getfield      #7                  // Field bufferSize:I
     103: i2l
     104: invokeinterface #31,  3           // InterfaceMethod org/reactivestreams/Subscription.request:(J)V
     109: return

  public void onNext(T);
    Code:
       0: aload_0
       1: getfield      #29                 // Field done:Z
       4: ifeq          8
       7: return
       8: aload_0
       9: getfield      #28                 // Field fusionMode:I
      12: ifne          51
      15: aload_1
      16: ldc           #32                 // String onNext called with a null value.
      18: invokestatic  #33                 // Method io/reactivex/rxjava3/internal/util/ExceptionHelper.nullCheck:(Ljava/lang/Object;Ljava/lang/String;)Ljava/lang/Object;
      21: pop
      22: aload_0
      23: getfield      #23                 // Field queue:Lio/reactivex/rxjava3/operators/SimpleQueue;
      26: aload_1
      27: invokeinterface #34,  2           // InterfaceMethod io/reactivex/rxjava3/operators/SimpleQueue.offer:(Ljava/lang/Object;)Z
      32: ifne          51
      35: aload_0
      36: getfield      #17                 // Field upstream:Ljava/util/concurrent/atomic/AtomicReference;
      39: invokestatic  #35                 // Method io/reactivex/rxjava3/internal/subscriptions/SubscriptionHelper.cancel:(Ljava/util/concurrent/atomic/AtomicReference;)Z
      42: pop
      43: aload_0
      44: invokestatic  #36                 // Method io/reactivex/rxjava3/exceptions/MissingBackpressureException.createDefault:()Lio/reactivex/rxjava3/exceptions/MissingBackpressureException;
      47: invokevirtual #37                 // Method onError:(Ljava/lang/Throwable;)V
      50: return
      51: aload_0
      52: invokevirtual #30                 // Method drain:()V
      55: return

  public boolean offer(T);
    Code:
       0: aload_1
       1: ldc           #38                 // String offer called with a null value.
       3: invokestatic  #33                 // Method io/reactivex/rxjava3/internal/util/ExceptionHelper.nullCheck:(Ljava/lang/Object;Ljava/lang/String;)Ljava/lang/Object;
       6: pop
       7: aload_0
       8: getfield      #29                 // Field done:Z
      11: ifeq          16
      14: iconst_0
      15: ireturn
      16: aload_0
      17: getfield      #28                 // Field fusionMode:I
      20: ifne          44
      23: aload_0
      24: getfield      #23                 // Field queue:Lio/reactivex/rxjava3/operators/SimpleQueue;
      27: aload_1
      28: invokeinterface #34,  2           // InterfaceMethod io/reactivex/rxjava3/operators/SimpleQueue.offer:(Ljava/lang/Object;)Z
      33: ifeq          42
      36: aload_0
      37: invokevirtual #30                 // Method drain:()V
      40: iconst_1
      41: ireturn
      42: iconst_0
      43: ireturn
      44: new           #39                 // class java/lang/IllegalStateException
      47: dup
      48: ldc           #40                 // String offer() should not be called in fusion mode!
      50: invokespecial #41                 // Method java/lang/IllegalStateException."<init>":(Ljava/lang/String;)V
      53: athrow

  public void onError(java.lang.Throwable);
    Code:
       0: aload_1
       1: ldc           #42                 // String onError called with a null Throwable.
       3: invokestatic  #33                 // Method io/reactivex/rxjava3/internal/util/ExceptionHelper.nullCheck:(Ljava/lang/Object;Ljava/lang/String;)Ljava/lang/Object;
       6: pop
       7: aload_0
       8: getfield      #29                 // Field done:Z
      11: ifne          29
      14: aload_0
      15: aload_1
      16: putfield      #43                 // Field error:Ljava/lang/Throwable;
      19: aload_0
      20: iconst_1
      21: putfield      #29                 // Field done:Z
      24: aload_0
      25: invokevirtual #30                 // Method drain:()V
      28: return
      29: aload_1
      30: invokestatic  #44                 // Method io/reactivex/rxjava3/plugins/RxJavaPlugins.onError:(Ljava/lang/Throwable;)V
      33: return

  public void onComplete();
    Code:
       0: aload_0
       1: iconst_1
       2: putfield      #29                 // Field done:Z
       5: aload_0
       6: invokevirtual #30                 // Method drain:()V
       9: return

  public boolean hasSubscribers();
    Code:
       0: aload_0
       1: getfield      #15                 // Field subscribers:Ljava/util/concurrent/atomic/AtomicReference;
       4: invokevirtual #45                 // Method java/util/concurrent/atomic/AtomicReference.get:()Ljava/lang/Object;
       7: checkcast     #46                 // class "[Lio/reactivex/rxjava3/processors/MulticastProcessor$MulticastSubscription;"
      10: arraylength
      11: ifeq          18
      14: iconst_1
      15: goto          19
      18: iconst_0
      19: ireturn

  public boolean hasThrowable();
    Code:
       0: aload_0
       1: getfield      #29                 // Field done:Z
       4: ifeq          18
       7: aload_0
       8: getfield      #43                 // Field error:Ljava/lang/Throwable;
      11: ifnull        18
      14: iconst_1
      15: goto          19
      18: iconst_0
      19: ireturn

  public boolean hasComplete();
    Code:
       0: aload_0
       1: getfield      #29                 // Field done:Z
       4: ifeq          18
       7: aload_0
       8: getfield      #43                 // Field error:Ljava/lang/Throwable;
      11: ifnonnull     18
      14: iconst_1
      15: goto          19
      18: iconst_0
      19: ireturn

  public java.lang.Throwable getThrowable();
    Code:
       0: aload_0
       1: getfield      #29                 // Field done:Z
       4: ifeq          14
       7: aload_0
       8: getfield      #43                 // Field error:Ljava/lang/Throwable;
      11: goto          15
      14: aconst_null
      15: areturn

  protected void subscribeActual(org.reactivestreams.Subscriber<? super T>);
    Code:
       0: new           #47                 // class io/reactivex/rxjava3/processors/MulticastProcessor$MulticastSubscription
       3: dup
       4: aload_1
       5: aload_0
       6: invokespecial #48                 // Method io/reactivex/rxjava3/processors/MulticastProcessor$MulticastSubscription."<init>":(Lorg/reactivestreams/Subscriber;Lio/reactivex/rxjava3/processors/MulticastProcessor;)V
       9: astore_2
      10: aload_1
      11: aload_2
      12: invokeinterface #49,  2           // InterfaceMethod org/reactivestreams/Subscriber.onSubscribe:(Lorg/reactivestreams/Subscription;)V
      17: aload_0
      18: aload_2
      19: invokevirtual #50                 // Method add:(Lio/reactivex/rxjava3/processors/MulticastProcessor$MulticastSubscription;)Z
      22: ifeq          51
      25: aload_2
      26: invokevirtual #51                 // Method io/reactivex/rxjava3/processors/MulticastProcessor$MulticastSubscription.get:()J
      29: ldc2_w        #53                 // long -9223372036854775808l
      32: lcmp
      33: ifne          44
      36: aload_0
      37: aload_2
      38: invokevirtual #55                 // Method remove:(Lio/reactivex/rxjava3/processors/MulticastProcessor$MulticastSubscription;)V
      41: goto          81
      44: aload_0
      45: invokevirtual #30                 // Method drain:()V
      48: goto          81
      51: aload_0
      52: getfield      #29                 // Field done:Z
      55: ifeq          75
      58: aload_0
      59: getfield      #43                 // Field error:Ljava/lang/Throwable;
      62: astore_3
      63: aload_3
      64: ifnull        75
      67: aload_1
      68: aload_3
      69: invokeinterface #56,  2           // InterfaceMethod org/reactivestreams/Subscriber.onError:(Ljava/lang/Throwable;)V
      74: return
      75: aload_1
      76: invokeinterface #57,  1           // InterfaceMethod org/reactivestreams/Subscriber.onComplete:()V
      81: return

  boolean add(io.reactivex.rxjava3.processors.MulticastProcessor$MulticastSubscription<T>);
    Code:
       0: aload_0
       1: getfield      #15                 // Field subscribers:Ljava/util/concurrent/atomic/AtomicReference;
       4: invokevirtual #45                 // Method java/util/concurrent/atomic/AtomicReference.get:()Ljava/lang/Object;
       7: checkcast     #46                 // class "[Lio/reactivex/rxjava3/processors/MulticastProcessor$MulticastSubscription;"
      10: astore_2
      11: aload_2
      12: getstatic     #58                 // Field TERMINATED:[Lio/reactivex/rxjava3/processors/MulticastProcessor$MulticastSubscription;
      15: if_acmpne     20
      18: iconst_0
      19: ireturn
      20: aload_2
      21: arraylength
      22: istore_3
      23: iload_3
      24: iconst_1
      25: iadd
      26: anewarray     #47                 // class io/reactivex/rxjava3/processors/MulticastProcessor$MulticastSubscription
      29: astore        4
      31: aload_2
      32: iconst_0
      33: aload         4
      35: iconst_0
      36: iload_3
      37: invokestatic  #59                 // Method java/lang/System.arraycopy:(Ljava/lang/Object;ILjava/lang/Object;II)V
      40: aload         4
      42: iload_3
      43: aload_1
      44: aastore
      45: aload_0
      46: getfield      #15                 // Field subscribers:Ljava/util/concurrent/atomic/AtomicReference;
      49: aload_2
      50: aload         4
      52: invokevirtual #60                 // Method java/util/concurrent/atomic/AtomicReference.compareAndSet:(Ljava/lang/Object;Ljava/lang/Object;)Z
      55: ifeq          60
      58: iconst_1
      59: ireturn
      60: goto          0

  void remove(io.reactivex.rxjava3.processors.MulticastProcessor$MulticastSubscription<T>);
    Code:
       0: aload_0
       1: getfield      #15                 // Field subscribers:Ljava/util/concurrent/atomic/AtomicReference;
       4: invokevirtual #45                 // Method java/util/concurrent/atomic/AtomicReference.get:()Ljava/lang/Object;
       7: checkcast     #46                 // class "[Lio/reactivex/rxjava3/processors/MulticastProcessor$MulticastSubscription;"
      10: astore_2
      11: aload_2
      12: arraylength
      13: istore_3
      14: iload_3
      15: ifne          19
      18: return
      19: iconst_m1
      20: istore        4
      22: iconst_0
      23: istore        5
      25: iload         5
      27: iload_3
      28: if_icmpge     52
      31: aload_2
      32: iload         5
      34: aaload
      35: aload_1
      36: if_acmpne     46
      39: iload         5
      41: istore        4
      43: goto          52
      46: iinc          5, 1
      49: goto          25
      52: iload         4
      54: ifge          60
      57: goto          174
      60: iload_3
      61: iconst_1
      62: if_icmpne     119
      65: aload_0
      66: getfield      #18                 // Field refcount:Z
      69: ifeq          102
      72: aload_0
      73: getfield      #15                 // Field subscribers:Ljava/util/concurrent/atomic/AtomicReference;
      76: aload_2
      77: getstatic     #58                 // Field TERMINATED:[Lio/reactivex/rxjava3/processors/MulticastProcessor$MulticastSubscription;
      80: invokevirtual #60                 // Method java/util/concurrent/atomic/AtomicReference.compareAndSet:(Ljava/lang/Object;Ljava/lang/Object;)Z
      83: ifeq          171
      86: aload_0
      87: getfield      #17                 // Field upstream:Ljava/util/concurrent/atomic/AtomicReference;
      90: invokestatic  #35                 // Method io/reactivex/rxjava3/internal/subscriptions/SubscriptionHelper.cancel:(Ljava/util/concurrent/atomic/AtomicReference;)Z
      93: pop
      94: aload_0
      95: iconst_1
      96: putfield      #29                 // Field done:Z
      99: goto          174
     102: aload_0
     103: getfield      #15                 // Field subscribers:Ljava/util/concurrent/atomic/AtomicReference;
     106: aload_2
     107: getstatic     #13                 // Field EMPTY:[Lio/reactivex/rxjava3/processors/MulticastProcessor$MulticastSubscription;
     110: invokevirtual #60                 // Method java/util/concurrent/atomic/AtomicReference.compareAndSet:(Ljava/lang/Object;Ljava/lang/Object;)Z
     113: ifeq          171
     116: goto          174
     119: iload_3
     120: iconst_1
     121: isub
     122: anewarray     #47                 // class io/reactivex/rxjava3/processors/MulticastProcessor$MulticastSubscription
     125: astore        5
     127: aload_2
     128: iconst_0
     129: aload         5
     131: iconst_0
     132: iload         4
     134: invokestatic  #59                 // Method java/lang/System.arraycopy:(Ljava/lang/Object;ILjava/lang/Object;II)V
     137: aload_2
     138: iload         4
     140: iconst_1
     141: iadd
     142: aload         5
     144: iload         4
     146: iload_3
     147: iload         4
     149: isub
     150: iconst_1
     151: isub
     152: invokestatic  #59                 // Method java/lang/System.arraycopy:(Ljava/lang/Object;ILjava/lang/Object;II)V
     155: aload_0
     156: getfield      #15                 // Field subscribers:Ljava/util/concurrent/atomic/AtomicReference;
     159: aload_2
     160: aload         5
     162: invokevirtual #60                 // Method java/util/concurrent/atomic/AtomicReference.compareAndSet:(Ljava/lang/Object;Ljava/lang/Object;)Z
     165: ifeq          171
     168: goto          174
     171: goto          0
     174: return

  void drain();
    Code:
       0: aload_0
       1: getfield      #11                 // Field wip:Ljava/util/concurrent/atomic/AtomicInteger;
       4: invokevirtual #61                 // Method java/util/concurrent/atomic/AtomicInteger.getAndIncrement:()I
       7: ifeq          11
      10: return
      11: iconst_1
      12: istore_1
      13: aload_0
      14: getfield      #15                 // Field subscribers:Ljava/util/concurrent/atomic/AtomicReference;
      17: astore_2
      18: aload_0
      19: getfield      #62                 // Field consumed:I
      22: istore_3
      23: aload_0
      24: getfield      #8                  // Field limit:I
      27: istore        4
      29: aload_0
      30: getfield      #28                 // Field fusionMode:I
      33: istore        5
      35: aload_0
      36: getfield      #23                 // Field queue:Lio/reactivex/rxjava3/operators/SimpleQueue;
      39: astore        6
      41: aload         6
      43: ifnull        631
      46: aload_2
      47: invokevirtual #45                 // Method java/util/concurrent/atomic/AtomicReference.get:()Ljava/lang/Object;
      50: checkcast     #46                 // class "[Lio/reactivex/rxjava3/processors/MulticastProcessor$MulticastSubscription;"
      53: astore        7
      55: aload         7
      57: arraylength
      58: istore        8
      60: iload         8
      62: ifeq          631
      65: ldc2_w        #63                 // long -1l
      68: lstore        9
      70: aload         7
      72: astore        11
      74: aload         11
      76: arraylength
      77: istore        12
      79: iconst_0
      80: istore        13
      82: iload         13
      84: iload         12
      86: if_icmpge     153
      89: aload         11
      91: iload         13
      93: aaload
      94: astore        14
      96: aload         14
      98: invokevirtual #51                 // Method io/reactivex/rxjava3/processors/MulticastProcessor$MulticastSubscription.get:()J
     101: lstore        15
     103: lload         15
     105: lconst_0
     106: lcmp
     107: iflt          147
     110: lload         9
     112: ldc2_w        #63                 // long -1l
     115: lcmp
     116: ifne          132
     119: lload         15
     121: aload         14
     123: getfield      #65                 // Field io/reactivex/rxjava3/processors/MulticastProcessor$MulticastSubscription.emitted:J
     126: lsub
     127: lstore        9
     129: goto          147
     132: lload         9
     134: lload         15
     136: aload         14
     138: getfield      #65                 // Field io/reactivex/rxjava3/processors/MulticastProcessor$MulticastSubscription.emitted:J
     141: lsub
     142: invokestatic  #66                 // Method java/lang/Math.min:(JJ)J
     145: lstore        9
     147: iinc          13, 1
     150: goto          82
     153: lload         9
     155: lconst_0
     156: lcmp
     157: ifle          465
     160: aload_2
     161: invokevirtual #45                 // Method java/util/concurrent/atomic/AtomicReference.get:()Ljava/lang/Object;
     164: checkcast     #46                 // class "[Lio/reactivex/rxjava3/processors/MulticastProcessor$MulticastSubscription;"
     167: astore        11
     169: aload         11
     171: getstatic     #58                 // Field TERMINATED:[Lio/reactivex/rxjava3/processors/MulticastProcessor$MulticastSubscription;
     174: if_acmpne     185
     177: aload         6
     179: invokeinterface #67,  1           // InterfaceMethod io/reactivex/rxjava3/operators/SimpleQueue.clear:()V
     184: return
     185: aload         7
     187: aload         11
     189: if_acmpeq     195
     192: goto          35
     195: aload_0
     196: getfield      #29                 // Field done:Z
     199: istore        12
     201: aload         6
     203: invokeinterface #68,  1           // InterfaceMethod io/reactivex/rxjava3/operators/SimpleQueue.poll:()Ljava/lang/Object;
     208: astore        13
     210: goto          245
     213: astore        14
     215: aload         14
     217: invokestatic  #70                 // Method io/reactivex/rxjava3/exceptions/Exceptions.throwIfFatal:(Ljava/lang/Throwable;)V
     220: aload_0
     221: getfield      #17                 // Field upstream:Ljava/util/concurrent/atomic/AtomicReference;
     224: invokestatic  #35                 // Method io/reactivex/rxjava3/internal/subscriptions/SubscriptionHelper.cancel:(Ljava/util/concurrent/atomic/AtomicReference;)Z
     227: pop
     228: iconst_1
     229: istore        12
     231: aconst_null
     232: astore        13
     234: aload_0
     235: aload         14
     237: putfield      #43                 // Field error:Ljava/lang/Throwable;
     240: aload_0
     241: iconst_1
     242: putfield      #29                 // Field done:Z
     245: aload         13
     247: ifnonnull     254
     250: iconst_1
     251: goto          255
     254: iconst_0
     255: istore        14
     257: iload         12
     259: ifeq          374
     262: iload         14
     264: ifeq          374
     267: aload_0
     268: getfield      #43                 // Field error:Ljava/lang/Throwable;
     271: astore        15
     273: aload         15
     275: ifnull        328
     278: aload_2
     279: getstatic     #58                 // Field TERMINATED:[Lio/reactivex/rxjava3/processors/MulticastProcessor$MulticastSubscription;
     282: invokevirtual #71                 // Method java/util/concurrent/atomic/AtomicReference.getAndSet:(Ljava/lang/Object;)Ljava/lang/Object;
     285: checkcast     #46                 // class "[Lio/reactivex/rxjava3/processors/MulticastProcessor$MulticastSubscription;"
     288: astore        16
     290: aload         16
     292: arraylength
     293: istore        17
     295: iconst_0
     296: istore        18
     298: iload         18
     300: iload         17
     302: if_icmpge     325
     305: aload         16
     307: iload         18
     309: aaload
     310: astore        19
     312: aload         19
     314: aload         15
     316: invokevirtual #72                 // Method io/reactivex/rxjava3/processors/MulticastProcessor$MulticastSubscription.onError:(Ljava/lang/Throwable;)V
     319: iinc          18, 1
     322: goto          298
     325: goto          373
     328: aload_2
     329: getstatic     #58                 // Field TERMINATED:[Lio/reactivex/rxjava3/processors/MulticastProcessor$MulticastSubscription;
     332: invokevirtual #71                 // Method java/util/concurrent/atomic/AtomicReference.getAndSet:(Ljava/lang/Object;)Ljava/lang/Object;
     335: checkcast     #46                 // class "[Lio/reactivex/rxjava3/processors/MulticastProcessor$MulticastSubscription;"
     338: astore        16
     340: aload         16
     342: arraylength
     343: istore        17
     345: iconst_0
     346: istore        18
     348: iload         18
     350: iload         17
     352: if_icmpge     373
     355: aload         16
     357: iload         18
     359: aaload
     360: astore        19
     362: aload         19
     364: invokevirtual #73                 // Method io/reactivex/rxjava3/processors/MulticastProcessor$MulticastSubscription.onComplete:()V
     367: iinc          18, 1
     370: goto          348
     373: return
     374: iload         14
     376: ifeq          382
     379: goto          465
     382: aload         7
     384: astore        15
     386: aload         15
     388: arraylength
     389: istore        16
     391: iconst_0
     392: istore        17
     394: iload         17
     396: iload         16
     398: if_icmpge     421
     401: aload         15
     403: iload         17
     405: aaload
     406: astore        18
     408: aload         18
     410: aload         13
     412: invokevirtual #74                 // Method io/reactivex/rxjava3/processors/MulticastProcessor$MulticastSubscription.onNext:(Ljava/lang/Object;)V
     415: iinc          17, 1
     418: goto          394
     421: lload         9
     423: lconst_1
     424: lsub
     425: lstore        9
     427: iload         5
     429: iconst_1
     430: if_icmpeq     462
     433: iinc          3, 1
     436: iload_3
     437: iload         4
     439: if_icmpne     462
     442: iconst_0
     443: istore_3
     444: aload_0
     445: getfield      #17                 // Field upstream:Ljava/util/concurrent/atomic/AtomicReference;
     448: invokevirtual #45                 // Method java/util/concurrent/atomic/AtomicReference.get:()Ljava/lang/Object;
     451: checkcast     #75                 // class org/reactivestreams/Subscription
     454: iload         4
     456: i2l
     457: invokeinterface #31,  3           // InterfaceMethod org/reactivestreams/Subscription.request:(J)V
     462: goto          153
     465: lload         9
     467: lconst_0
     468: lcmp
     469: ifne          631
     472: aload_2
     473: invokevirtual #45                 // Method java/util/concurrent/atomic/AtomicReference.get:()Ljava/lang/Object;
     476: checkcast     #46                 // class "[Lio/reactivex/rxjava3/processors/MulticastProcessor$MulticastSubscription;"
     479: astore        11
     481: aload         11
     483: getstatic     #58                 // Field TERMINATED:[Lio/reactivex/rxjava3/processors/MulticastProcessor$MulticastSubscription;
     486: if_acmpne     497
     489: aload         6
     491: invokeinterface #67,  1           // InterfaceMethod io/reactivex/rxjava3/operators/SimpleQueue.clear:()V
     496: return
     497: aload         7
     499: aload         11
     501: if_acmpeq     507
     504: goto          35
     507: aload_0
     508: getfield      #29                 // Field done:Z
     511: ifeq          631
     514: aload         6
     516: invokeinterface #76,  1           // InterfaceMethod io/reactivex/rxjava3/operators/SimpleQueue.isEmpty:()Z
     521: ifeq          631
     524: aload_0
     525: getfield      #43                 // Field error:Ljava/lang/Throwable;
     528: astore        12
     530: aload         12
     532: ifnull        585
     535: aload_2
     536: getstatic     #58                 // Field TERMINATED:[Lio/reactivex/rxjava3/processors/MulticastProcessor$MulticastSubscription;
     539: invokevirtual #71                 // Method java/util/concurrent/atomic/AtomicReference.getAndSet:(Ljava/lang/Object;)Ljava/lang/Object;
     542: checkcast     #46                 // class "[Lio/reactivex/rxjava3/processors/MulticastProcessor$MulticastSubscription;"
     545: astore        13
     547: aload         13
     549: arraylength
     550: istore        14
     552: iconst_0
     553: istore        15
     555: iload         15
     557: iload         14
     559: if_icmpge     582
     562: aload         13
     564: iload         15
     566: aaload
     567: astore        16
     569: aload         16
     571: aload         12
     573: invokevirtual #72                 // Method io/reactivex/rxjava3/processors/MulticastProcessor$MulticastSubscription.onError:(Ljava/lang/Throwable;)V
     576: iinc          15, 1
     579: goto          555
     582: goto          630
     585: aload_2
     586: getstatic     #58                 // Field TERMINATED:[Lio/reactivex/rxjava3/processors/MulticastProcessor$MulticastSubscription;
     589: invokevirtual #71                 // Method java/util/concurrent/atomic/AtomicReference.getAndSet:(Ljava/lang/Object;)Ljava/lang/Object;
     592: checkcast     #46                 // class "[Lio/reactivex/rxjava3/processors/MulticastProcessor$MulticastSubscription;"
     595: astore        13
     597: aload         13
     599: arraylength
     600: istore        14
     602: iconst_0
     603: istore        15
     605: iload         15
     607: iload         14
     609: if_icmpge     630
     612: aload         13
     614: iload         15
     616: aaload
     617: astore        16
     619: aload         16
     621: invokevirtual #73                 // Method io/reactivex/rxjava3/processors/MulticastProcessor$MulticastSubscription.onComplete:()V
     624: iinc          15, 1
     627: goto          605
     630: return
     631: aload_0
     632: iload_3
     633: putfield      #62                 // Field consumed:I
     636: aload_0
     637: getfield      #11                 // Field wip:Ljava/util/concurrent/atomic/AtomicInteger;
     640: iload_1
     641: ineg
     642: invokevirtual #77                 // Method java/util/concurrent/atomic/AtomicInteger.addAndGet:(I)I
     645: istore_1
     646: iload_1
     647: ifne          653
     650: goto          656
     653: goto          35
     656: return
    Exception table:
       from    to  target type
         201   210   213   Class java/lang/Throwable

  static {};
    Code:
       0: iconst_0
       1: anewarray     #47                 // class io/reactivex/rxjava3/processors/MulticastProcessor$MulticastSubscription
       4: putstatic     #13                 // Field EMPTY:[Lio/reactivex/rxjava3/processors/MulticastProcessor$MulticastSubscription;
       7: iconst_0
       8: anewarray     #47                 // class io/reactivex/rxjava3/processors/MulticastProcessor$MulticastSubscription
      11: putstatic     #58                 // Field TERMINATED:[Lio/reactivex/rxjava3/processors/MulticastProcessor$MulticastSubscription;
      14: return
}
