Compiled from "PublishProcessor.java"
final class io.reactivex.rxjava3.processors.PublishProcessor$PublishSubscription<T> extends java.util.concurrent.atomic.AtomicLong implements org.reactivestreams.Subscription {
  private static final long serialVersionUID;

  final org.reactivestreams.Subscriber<? super T> downstream;

  final io.reactivex.rxjava3.processors.PublishProcessor<T> parent;

  io.reactivex.rxjava3.processors.PublishProcessor$PublishSubscription(org.reactivestreams.Subscriber<? super T>, io.reactivex.rxjava3.processors.PublishProcessor<T>);
    Code:
       0: aload_0
       1: invokespecial #1                  // Method java/util/concurrent/atomic/AtomicLong."<init>":()V
       4: aload_0
       5: aload_1
       6: putfield      #2                  // Field downstream:Lorg/reactivestreams/Subscriber;
       9: aload_0
      10: aload_2
      11: putfield      #3                  // Field parent:Lio/reactivex/rxjava3/processors/PublishProcessor;
      14: return

  public void onNext(T);
    Code:
       0: aload_0
       1: invokevirtual #4                  // Method get:()J
       4: lstore_2
       5: lload_2
       6: ldc2_w        #6                  // long -9223372036854775808l
       9: lcmp
      10: ifne          14
      13: return
      14: lload_2
      15: lconst_0
      16: lcmp
      17: ifeq          39
      20: aload_0
      21: getfield      #2                  // Field downstream:Lorg/reactivestreams/Subscriber;
      24: aload_1
      25: invokeinterface #8,  2            // InterfaceMethod org/reactivestreams/Subscriber.onNext:(Ljava/lang/Object;)V
      30: aload_0
      31: lconst_1
      32: invokestatic  #9                  // Method io/reactivex/rxjava3/internal/util/BackpressureHelper.producedCancel:(Ljava/util/concurrent/atomic/AtomicLong;J)J
      35: pop2
      36: goto          55
      39: aload_0
      40: invokevirtual #10                 // Method cancel:()V
      43: aload_0
      44: getfield      #2                  // Field downstream:Lorg/reactivestreams/Subscriber;
      47: invokestatic  #11                 // Method io/reactivex/rxjava3/exceptions/MissingBackpressureException.createDefault:()Lio/reactivex/rxjava3/exceptions/MissingBackpressureException;
      50: invokeinterface #12,  2           // InterfaceMethod org/reactivestreams/Subscriber.onError:(Ljava/lang/Throwable;)V
      55: return

  public void onError(java.lang.Throwable);
    Code:
       0: aload_0
       1: invokevirtual #4                  // Method get:()J
       4: ldc2_w        #6                  // long -9223372036854775808l
       7: lcmp
       8: ifeq          24
      11: aload_0
      12: getfield      #2                  // Field downstream:Lorg/reactivestreams/Subscriber;
      15: aload_1
      16: invokeinterface #12,  2           // InterfaceMethod org/reactivestreams/Subscriber.onError:(Ljava/lang/Throwable;)V
      21: goto          28
      24: aload_1
      25: invokestatic  #13                 // Method io/reactivex/rxjava3/plugins/RxJavaPlugins.onError:(Ljava/lang/Throwable;)V
      28: return

  public void onComplete();
    Code:
       0: aload_0
       1: invokevirtual #4                  // Method get:()J
       4: ldc2_w        #6                  // long -9223372036854775808l
       7: lcmp
       8: ifeq          20
      11: aload_0
      12: getfield      #2                  // Field downstream:Lorg/reactivestreams/Subscriber;
      15: invokeinterface #14,  1           // InterfaceMethod org/reactivestreams/Subscriber.onComplete:()V
      20: return

  public void request(long);
    Code:
       0: lload_1
       1: invokestatic  #15                 // Method io/reactivex/rxjava3/internal/subscriptions/SubscriptionHelper.validate:(J)Z
       4: ifeq          13
       7: aload_0
       8: lload_1
       9: invokestatic  #16                 // Method io/reactivex/rxjava3/internal/util/BackpressureHelper.addCancel:(Ljava/util/concurrent/atomic/AtomicLong;J)J
      12: pop2
      13: return

  public void cancel();
    Code:
       0: aload_0
       1: ldc2_w        #6                  // long -9223372036854775808l
       4: invokevirtual #17                 // Method getAndSet:(J)J
       7: ldc2_w        #6                  // long -9223372036854775808l
      10: lcmp
      11: ifeq          22
      14: aload_0
      15: getfield      #3                  // Field parent:Lio/reactivex/rxjava3/processors/PublishProcessor;
      18: aload_0
      19: invokevirtual #18                 // Method io/reactivex/rxjava3/processors/PublishProcessor.remove:(Lio/reactivex/rxjava3/processors/PublishProcessor$PublishSubscription;)V
      22: return

  public boolean isCancelled();
    Code:
       0: aload_0
       1: invokevirtual #4                  // Method get:()J
       4: ldc2_w        #6                  // long -9223372036854775808l
       7: lcmp
       8: ifne          15
      11: iconst_1
      12: goto          16
      15: iconst_0
      16: ireturn

  boolean isFull();
    Code:
       0: aload_0
       1: invokevirtual #4                  // Method get:()J
       4: lconst_0
       5: lcmp
       6: ifne          13
       9: iconst_1
      10: goto          14
      13: iconst_0
      14: ireturn
}
