Compiled from "PublishProcessor.java"
public final class io.reactivex.rxjava3.processors.PublishProcessor<T> extends io.reactivex.rxjava3.processors.FlowableProcessor<T> {
  static final io.reactivex.rxjava3.processors.PublishProcessor$PublishSubscription[] TERMINATED;

  static final io.reactivex.rxjava3.processors.PublishProcessor$PublishSubscription[] EMPTY;

  final java.util.concurrent.atomic.AtomicReference<io.reactivex.rxjava3.processors.PublishProcessor$PublishSubscription<T>[]> subscribers;

  java.lang.Throwable error;

  public static <T> io.reactivex.rxjava3.processors.PublishProcessor<T> create();
    Code:
       0: new           #1                  // class io/reactivex/rxjava3/processors/PublishProcessor
       3: dup
       4: invokespecial #2                  // Method "<init>":()V
       7: areturn

  io.reactivex.rxjava3.processors.PublishProcessor();
    Code:
       0: aload_0
       1: invokespecial #3                  // Method io/reactivex/rxjava3/processors/FlowableProcessor."<init>":()V
       4: aload_0
       5: new           #4                  // class java/util/concurrent/atomic/AtomicReference
       8: dup
       9: getstatic     #5                  // Field EMPTY:[Lio/reactivex/rxjava3/processors/PublishProcessor$PublishSubscription;
      12: invokespecial #6                  // Method java/util/concurrent/atomic/AtomicReference."<init>":(Ljava/lang/Object;)V
      15: putfield      #7                  // Field subscribers:Ljava/util/concurrent/atomic/AtomicReference;
      18: return

  protected void subscribeActual(org.reactivestreams.Subscriber<? super T>);
    Code:
       0: new           #8                  // class io/reactivex/rxjava3/processors/PublishProcessor$PublishSubscription
       3: dup
       4: aload_1
       5: aload_0
       6: invokespecial #9                  // Method io/reactivex/rxjava3/processors/PublishProcessor$PublishSubscription."<init>":(Lorg/reactivestreams/Subscriber;Lio/reactivex/rxjava3/processors/PublishProcessor;)V
       9: astore_2
      10: aload_1
      11: aload_2
      12: invokeinterface #10,  2           // InterfaceMethod org/reactivestreams/Subscriber.onSubscribe:(Lorg/reactivestreams/Subscription;)V
      17: aload_0
      18: aload_2
      19: invokevirtual #11                 // Method add:(Lio/reactivex/rxjava3/processors/PublishProcessor$PublishSubscription;)Z
      22: ifeq          40
      25: aload_2
      26: invokevirtual #12                 // Method io/reactivex/rxjava3/processors/PublishProcessor$PublishSubscription.isCancelled:()Z
      29: ifeq          65
      32: aload_0
      33: aload_2
      34: invokevirtual #13                 // Method remove:(Lio/reactivex/rxjava3/processors/PublishProcessor$PublishSubscription;)V
      37: goto          65
      40: aload_0
      41: getfield      #14                 // Field error:Ljava/lang/Throwable;
      44: astore_3
      45: aload_3
      46: ifnull        59
      49: aload_1
      50: aload_3
      51: invokeinterface #15,  2           // InterfaceMethod org/reactivestreams/Subscriber.onError:(Ljava/lang/Throwable;)V
      56: goto          65
      59: aload_1
      60: invokeinterface #16,  1           // InterfaceMethod org/reactivestreams/Subscriber.onComplete:()V
      65: return

  boolean add(io.reactivex.rxjava3.processors.PublishProcessor$PublishSubscription<T>);
    Code:
       0: aload_0
       1: getfield      #7                  // Field subscribers:Ljava/util/concurrent/atomic/AtomicReference;
       4: invokevirtual #17                 // Method java/util/concurrent/atomic/AtomicReference.get:()Ljava/lang/Object;
       7: checkcast     #18                 // class "[Lio/reactivex/rxjava3/processors/PublishProcessor$PublishSubscription;"
      10: astore_2
      11: aload_2
      12: getstatic     #19                 // Field TERMINATED:[Lio/reactivex/rxjava3/processors/PublishProcessor$PublishSubscription;
      15: if_acmpne     20
      18: iconst_0
      19: ireturn
      20: aload_2
      21: arraylength
      22: istore_3
      23: iload_3
      24: iconst_1
      25: iadd
      26: anewarray     #8                  // class io/reactivex/rxjava3/processors/PublishProcessor$PublishSubscription
      29: astore        4
      31: aload_2
      32: iconst_0
      33: aload         4
      35: iconst_0
      36: iload_3
      37: invokestatic  #20                 // Method java/lang/System.arraycopy:(Ljava/lang/Object;ILjava/lang/Object;II)V
      40: aload         4
      42: iload_3
      43: aload_1
      44: aastore
      45: aload_0
      46: getfield      #7                  // Field subscribers:Ljava/util/concurrent/atomic/AtomicReference;
      49: aload_2
      50: aload         4
      52: invokevirtual #21                 // Method java/util/concurrent/atomic/AtomicReference.compareAndSet:(Ljava/lang/Object;Ljava/lang/Object;)Z
      55: ifeq          60
      58: iconst_1
      59: ireturn
      60: goto          0

  void remove(io.reactivex.rxjava3.processors.PublishProcessor$PublishSubscription<T>);
    Code:
       0: aload_0
       1: getfield      #7                  // Field subscribers:Ljava/util/concurrent/atomic/AtomicReference;
       4: invokevirtual #17                 // Method java/util/concurrent/atomic/AtomicReference.get:()Ljava/lang/Object;
       7: checkcast     #18                 // class "[Lio/reactivex/rxjava3/processors/PublishProcessor$PublishSubscription;"
      10: astore_2
      11: aload_2
      12: getstatic     #19                 // Field TERMINATED:[Lio/reactivex/rxjava3/processors/PublishProcessor$PublishSubscription;
      15: if_acmpeq     25
      18: aload_2
      19: getstatic     #5                  // Field EMPTY:[Lio/reactivex/rxjava3/processors/PublishProcessor$PublishSubscription;
      22: if_acmpne     26
      25: return
      26: aload_2
      27: arraylength
      28: istore_3
      29: iconst_m1
      30: istore        4
      32: iconst_0
      33: istore        5
      35: iload         5
      37: iload_3
      38: if_icmpge     62
      41: aload_2
      42: iload         5
      44: aaload
      45: aload_1
      46: if_acmpne     56
      49: iload         5
      51: istore        4
      53: goto          62
      56: iinc          5, 1
      59: goto          35
      62: iload         4
      64: ifge          68
      67: return
      68: iload_3
      69: iconst_1
      70: if_icmpne     81
      73: getstatic     #5                  // Field EMPTY:[Lio/reactivex/rxjava3/processors/PublishProcessor$PublishSubscription;
      76: astore        5
      78: goto          117
      81: iload_3
      82: iconst_1
      83: isub
      84: anewarray     #8                  // class io/reactivex/rxjava3/processors/PublishProcessor$PublishSubscription
      87: astore        5
      89: aload_2
      90: iconst_0
      91: aload         5
      93: iconst_0
      94: iload         4
      96: invokestatic  #20                 // Method java/lang/System.arraycopy:(Ljava/lang/Object;ILjava/lang/Object;II)V
      99: aload_2
     100: iload         4
     102: iconst_1
     103: iadd
     104: aload         5
     106: iload         4
     108: iload_3
     109: iload         4
     111: isub
     112: iconst_1
     113: isub
     114: invokestatic  #20                 // Method java/lang/System.arraycopy:(Ljava/lang/Object;ILjava/lang/Object;II)V
     117: aload_0
     118: getfield      #7                  // Field subscribers:Ljava/util/concurrent/atomic/AtomicReference;
     121: aload_2
     122: aload         5
     124: invokevirtual #21                 // Method java/util/concurrent/atomic/AtomicReference.compareAndSet:(Ljava/lang/Object;Ljava/lang/Object;)Z
     127: ifeq          131
     130: return
     131: goto          0

  public void onSubscribe(org.reactivestreams.Subscription);
    Code:
       0: aload_0
       1: getfield      #7                  // Field subscribers:Ljava/util/concurrent/atomic/AtomicReference;
       4: invokevirtual #17                 // Method java/util/concurrent/atomic/AtomicReference.get:()Ljava/lang/Object;
       7: getstatic     #19                 // Field TERMINATED:[Lio/reactivex/rxjava3/processors/PublishProcessor$PublishSubscription;
      10: if_acmpne     20
      13: aload_1
      14: invokeinterface #22,  1           // InterfaceMethod org/reactivestreams/Subscription.cancel:()V
      19: return
      20: aload_1
      21: ldc2_w        #24                 // long 9223372036854775807l
      24: invokeinterface #26,  3           // InterfaceMethod org/reactivestreams/Subscription.request:(J)V
      29: return

  public void onNext(T);
    Code:
       0: aload_1
       1: ldc           #27                 // String onNext called with a null value.
       3: invokestatic  #28                 // Method io/reactivex/rxjava3/internal/util/ExceptionHelper.nullCheck:(Ljava/lang/Object;Ljava/lang/String;)Ljava/lang/Object;
       6: pop
       7: aload_0
       8: getfield      #7                  // Field subscribers:Ljava/util/concurrent/atomic/AtomicReference;
      11: invokevirtual #17                 // Method java/util/concurrent/atomic/AtomicReference.get:()Ljava/lang/Object;
      14: checkcast     #18                 // class "[Lio/reactivex/rxjava3/processors/PublishProcessor$PublishSubscription;"
      17: astore_2
      18: aload_2
      19: arraylength
      20: istore_3
      21: iconst_0
      22: istore        4
      24: iload         4
      26: iload_3
      27: if_icmpge     48
      30: aload_2
      31: iload         4
      33: aaload
      34: astore        5
      36: aload         5
      38: aload_1
      39: invokevirtual #29                 // Method io/reactivex/rxjava3/processors/PublishProcessor$PublishSubscription.onNext:(Ljava/lang/Object;)V
      42: iinc          4, 1
      45: goto          24
      48: return

  public void onError(java.lang.Throwable);
    Code:
       0: aload_1
       1: ldc           #30                 // String onError called with a null Throwable.
       3: invokestatic  #28                 // Method io/reactivex/rxjava3/internal/util/ExceptionHelper.nullCheck:(Ljava/lang/Object;Ljava/lang/String;)Ljava/lang/Object;
       6: pop
       7: aload_0
       8: getfield      #7                  // Field subscribers:Ljava/util/concurrent/atomic/AtomicReference;
      11: invokevirtual #17                 // Method java/util/concurrent/atomic/AtomicReference.get:()Ljava/lang/Object;
      14: getstatic     #19                 // Field TERMINATED:[Lio/reactivex/rxjava3/processors/PublishProcessor$PublishSubscription;
      17: if_acmpne     25
      20: aload_1
      21: invokestatic  #31                 // Method io/reactivex/rxjava3/plugins/RxJavaPlugins.onError:(Ljava/lang/Throwable;)V
      24: return
      25: aload_0
      26: aload_1
      27: putfield      #14                 // Field error:Ljava/lang/Throwable;
      30: aload_0
      31: getfield      #7                  // Field subscribers:Ljava/util/concurrent/atomic/AtomicReference;
      34: getstatic     #19                 // Field TERMINATED:[Lio/reactivex/rxjava3/processors/PublishProcessor$PublishSubscription;
      37: invokevirtual #32                 // Method java/util/concurrent/atomic/AtomicReference.getAndSet:(Ljava/lang/Object;)Ljava/lang/Object;
      40: checkcast     #18                 // class "[Lio/reactivex/rxjava3/processors/PublishProcessor$PublishSubscription;"
      43: astore_2
      44: aload_2
      45: arraylength
      46: istore_3
      47: iconst_0
      48: istore        4
      50: iload         4
      52: iload_3
      53: if_icmpge     74
      56: aload_2
      57: iload         4
      59: aaload
      60: astore        5
      62: aload         5
      64: aload_1
      65: invokevirtual #33                 // Method io/reactivex/rxjava3/processors/PublishProcessor$PublishSubscription.onError:(Ljava/lang/Throwable;)V
      68: iinc          4, 1
      71: goto          50
      74: return

  public void onComplete();
    Code:
       0: aload_0
       1: getfield      #7                  // Field subscribers:Ljava/util/concurrent/atomic/AtomicReference;
       4: invokevirtual #17                 // Method java/util/concurrent/atomic/AtomicReference.get:()Ljava/lang/Object;
       7: getstatic     #19                 // Field TERMINATED:[Lio/reactivex/rxjava3/processors/PublishProcessor$PublishSubscription;
      10: if_acmpne     14
      13: return
      14: aload_0
      15: getfield      #7                  // Field subscribers:Ljava/util/concurrent/atomic/AtomicReference;
      18: getstatic     #19                 // Field TERMINATED:[Lio/reactivex/rxjava3/processors/PublishProcessor$PublishSubscription;
      21: invokevirtual #32                 // Method java/util/concurrent/atomic/AtomicReference.getAndSet:(Ljava/lang/Object;)Ljava/lang/Object;
      24: checkcast     #18                 // class "[Lio/reactivex/rxjava3/processors/PublishProcessor$PublishSubscription;"
      27: astore_1
      28: aload_1
      29: arraylength
      30: istore_2
      31: iconst_0
      32: istore_3
      33: iload_3
      34: iload_2
      35: if_icmpge     54
      38: aload_1
      39: iload_3
      40: aaload
      41: astore        4
      43: aload         4
      45: invokevirtual #34                 // Method io/reactivex/rxjava3/processors/PublishProcessor$PublishSubscription.onComplete:()V
      48: iinc          3, 1
      51: goto          33
      54: return

  public boolean offer(T);
    Code:
       0: aload_1
       1: ldc           #35                 // String offer called with a null value.
       3: invokestatic  #28                 // Method io/reactivex/rxjava3/internal/util/ExceptionHelper.nullCheck:(Ljava/lang/Object;Ljava/lang/String;)Ljava/lang/Object;
       6: pop
       7: aload_0
       8: getfield      #7                  // Field subscribers:Ljava/util/concurrent/atomic/AtomicReference;
      11: invokevirtual #17                 // Method java/util/concurrent/atomic/AtomicReference.get:()Ljava/lang/Object;
      14: checkcast     #18                 // class "[Lio/reactivex/rxjava3/processors/PublishProcessor$PublishSubscription;"
      17: astore_2
      18: aload_2
      19: astore_3
      20: aload_3
      21: arraylength
      22: istore        4
      24: iconst_0
      25: istore        5
      27: iload         5
      29: iload         4
      31: if_icmpge     56
      34: aload_3
      35: iload         5
      37: aaload
      38: astore        6
      40: aload         6
      42: invokevirtual #36                 // Method io/reactivex/rxjava3/processors/PublishProcessor$PublishSubscription.isFull:()Z
      45: ifeq          50
      48: iconst_0
      49: ireturn
      50: iinc          5, 1
      53: goto          27
      56: aload_2
      57: astore_3
      58: aload_3
      59: arraylength
      60: istore        4
      62: iconst_0
      63: istore        5
      65: iload         5
      67: iload         4
      69: if_icmpge     90
      72: aload_3
      73: iload         5
      75: aaload
      76: astore        6
      78: aload         6
      80: aload_1
      81: invokevirtual #29                 // Method io/reactivex/rxjava3/processors/PublishProcessor$PublishSubscription.onNext:(Ljava/lang/Object;)V
      84: iinc          5, 1
      87: goto          65
      90: iconst_1
      91: ireturn

  public boolean hasSubscribers();
    Code:
       0: aload_0
       1: getfield      #7                  // Field subscribers:Ljava/util/concurrent/atomic/AtomicReference;
       4: invokevirtual #17                 // Method java/util/concurrent/atomic/AtomicReference.get:()Ljava/lang/Object;
       7: checkcast     #18                 // class "[Lio/reactivex/rxjava3/processors/PublishProcessor$PublishSubscription;"
      10: arraylength
      11: ifeq          18
      14: iconst_1
      15: goto          19
      18: iconst_0
      19: ireturn

  public java.lang.Throwable getThrowable();
    Code:
       0: aload_0
       1: getfield      #7                  // Field subscribers:Ljava/util/concurrent/atomic/AtomicReference;
       4: invokevirtual #17                 // Method java/util/concurrent/atomic/AtomicReference.get:()Ljava/lang/Object;
       7: getstatic     #19                 // Field TERMINATED:[Lio/reactivex/rxjava3/processors/PublishProcessor$PublishSubscription;
      10: if_acmpne     18
      13: aload_0
      14: getfield      #14                 // Field error:Ljava/lang/Throwable;
      17: areturn
      18: aconst_null
      19: areturn

  public boolean hasThrowable();
    Code:
       0: aload_0
       1: getfield      #7                  // Field subscribers:Ljava/util/concurrent/atomic/AtomicReference;
       4: invokevirtual #17                 // Method java/util/concurrent/atomic/AtomicReference.get:()Ljava/lang/Object;
       7: getstatic     #19                 // Field TERMINATED:[Lio/reactivex/rxjava3/processors/PublishProcessor$PublishSubscription;
      10: if_acmpne     24
      13: aload_0
      14: getfield      #14                 // Field error:Ljava/lang/Throwable;
      17: ifnull        24
      20: iconst_1
      21: goto          25
      24: iconst_0
      25: ireturn

  public boolean hasComplete();
    Code:
       0: aload_0
       1: getfield      #7                  // Field subscribers:Ljava/util/concurrent/atomic/AtomicReference;
       4: invokevirtual #17                 // Method java/util/concurrent/atomic/AtomicReference.get:()Ljava/lang/Object;
       7: getstatic     #19                 // Field TERMINATED:[Lio/reactivex/rxjava3/processors/PublishProcessor$PublishSubscription;
      10: if_acmpne     24
      13: aload_0
      14: getfield      #14                 // Field error:Ljava/lang/Throwable;
      17: ifnonnull     24
      20: iconst_1
      21: goto          25
      24: iconst_0
      25: ireturn

  static {};
    Code:
       0: iconst_0
       1: anewarray     #8                  // class io/reactivex/rxjava3/processors/PublishProcessor$PublishSubscription
       4: putstatic     #19                 // Field TERMINATED:[Lio/reactivex/rxjava3/processors/PublishProcessor$PublishSubscription;
       7: iconst_0
       8: anewarray     #8                  // class io/reactivex/rxjava3/processors/PublishProcessor$PublishSubscription
      11: putstatic     #5                  // Field EMPTY:[Lio/reactivex/rxjava3/processors/PublishProcessor$PublishSubscription;
      14: return
}
