Compiled from "UnicastProcessor.java"
final class io.reactivex.rxjava3.processors.UnicastProcessor$UnicastQueueSubscription extends io.reactivex.rxjava3.internal.subscriptions.BasicIntQueueSubscription<T> {
  private static final long serialVersionUID;

  final io.reactivex.rxjava3.processors.UnicastProcessor this$0;

  io.reactivex.rxjava3.processors.UnicastProcessor$UnicastQueueSubscription(io.reactivex.rxjava3.processors.UnicastProcessor);
    Code:
       0: aload_0
       1: aload_1
       2: putfield      #1                  // Field this$0:Lio/reactivex/rxjava3/processors/UnicastProcessor;
       5: aload_0
       6: invokespecial #2                  // Method io/reactivex/rxjava3/internal/subscriptions/BasicIntQueueSubscription."<init>":()V
       9: return

  public T poll();
    Code:
       0: aload_0
       1: getfield      #1                  // Field this$0:Lio/reactivex/rxjava3/processors/UnicastProcessor;
       4: getfield      #3                  // Field io/reactivex/rxjava3/processors/UnicastProcessor.queue:Lio/reactivex/rxjava3/operators/SpscLinkedArrayQueue;
       7: invokevirtual #4                  // Method io/reactivex/rxjava3/operators/SpscLinkedArrayQueue.poll:()Ljava/lang/Object;
      10: areturn

  public boolean isEmpty();
    Code:
       0: aload_0
       1: getfield      #1                  // Field this$0:Lio/reactivex/rxjava3/processors/UnicastProcessor;
       4: getfield      #3                  // Field io/reactivex/rxjava3/processors/UnicastProcessor.queue:Lio/reactivex/rxjava3/operators/SpscLinkedArrayQueue;
       7: invokevirtual #5                  // Method io/reactivex/rxjava3/operators/SpscLinkedArrayQueue.isEmpty:()Z
      10: ireturn

  public void clear();
    Code:
       0: aload_0
       1: getfield      #1                  // Field this$0:Lio/reactivex/rxjava3/processors/UnicastProcessor;
       4: getfield      #3                  // Field io/reactivex/rxjava3/processors/UnicastProcessor.queue:Lio/reactivex/rxjava3/operators/SpscLinkedArrayQueue;
       7: invokevirtual #6                  // Method io/reactivex/rxjava3/operators/SpscLinkedArrayQueue.clear:()V
      10: return

  public int requestFusion(int);
    Code:
       0: iload_1
       1: iconst_2
       2: iand
       3: ifeq          16
       6: aload_0
       7: getfield      #1                  // Field this$0:Lio/reactivex/rxjava3/processors/UnicastProcessor;
      10: iconst_1
      11: putfield      #8                  // Field io/reactivex/rxjava3/processors/UnicastProcessor.enableOperatorFusion:Z
      14: iconst_2
      15: ireturn
      16: iconst_0
      17: ireturn

  public void request(long);
    Code:
       0: lload_1
       1: invokestatic  #9                  // Method io/reactivex/rxjava3/internal/subscriptions/SubscriptionHelper.validate:(J)Z
       4: ifeq          26
       7: aload_0
       8: getfield      #1                  // Field this$0:Lio/reactivex/rxjava3/processors/UnicastProcessor;
      11: getfield      #10                 // Field io/reactivex/rxjava3/processors/UnicastProcessor.requested:Ljava/util/concurrent/atomic/AtomicLong;
      14: lload_1
      15: invokestatic  #11                 // Method io/reactivex/rxjava3/internal/util/BackpressureHelper.add:(Ljava/util/concurrent/atomic/AtomicLong;J)J
      18: pop2
      19: aload_0
      20: getfield      #1                  // Field this$0:Lio/reactivex/rxjava3/processors/UnicastProcessor;
      23: invokevirtual #12                 // Method io/reactivex/rxjava3/processors/UnicastProcessor.drain:()V
      26: return

  public void cancel();
    Code:
       0: aload_0
       1: getfield      #1                  // Field this$0:Lio/reactivex/rxjava3/processors/UnicastProcessor;
       4: getfield      #13                 // Field io/reactivex/rxjava3/processors/UnicastProcessor.cancelled:Z
       7: ifeq          11
      10: return
      11: aload_0
      12: getfield      #1                  // Field this$0:Lio/reactivex/rxjava3/processors/UnicastProcessor;
      15: iconst_1
      16: putfield      #13                 // Field io/reactivex/rxjava3/processors/UnicastProcessor.cancelled:Z
      19: aload_0
      20: getfield      #1                  // Field this$0:Lio/reactivex/rxjava3/processors/UnicastProcessor;
      23: invokevirtual #14                 // Method io/reactivex/rxjava3/processors/UnicastProcessor.doTerminate:()V
      26: aload_0
      27: getfield      #1                  // Field this$0:Lio/reactivex/rxjava3/processors/UnicastProcessor;
      30: getfield      #15                 // Field io/reactivex/rxjava3/processors/UnicastProcessor.downstream:Ljava/util/concurrent/atomic/AtomicReference;
      33: aconst_null
      34: invokevirtual #16                 // Method java/util/concurrent/atomic/AtomicReference.lazySet:(Ljava/lang/Object;)V
      37: aload_0
      38: getfield      #1                  // Field this$0:Lio/reactivex/rxjava3/processors/UnicastProcessor;
      41: getfield      #17                 // Field io/reactivex/rxjava3/processors/UnicastProcessor.wip:Lio/reactivex/rxjava3/internal/subscriptions/BasicIntQueueSubscription;
      44: invokevirtual #18                 // Method io/reactivex/rxjava3/internal/subscriptions/BasicIntQueueSubscription.getAndIncrement:()I
      47: ifne          81
      50: aload_0
      51: getfield      #1                  // Field this$0:Lio/reactivex/rxjava3/processors/UnicastProcessor;
      54: getfield      #15                 // Field io/reactivex/rxjava3/processors/UnicastProcessor.downstream:Ljava/util/concurrent/atomic/AtomicReference;
      57: aconst_null
      58: invokevirtual #16                 // Method java/util/concurrent/atomic/AtomicReference.lazySet:(Ljava/lang/Object;)V
      61: aload_0
      62: getfield      #1                  // Field this$0:Lio/reactivex/rxjava3/processors/UnicastProcessor;
      65: getfield      #8                  // Field io/reactivex/rxjava3/processors/UnicastProcessor.enableOperatorFusion:Z
      68: ifne          81
      71: aload_0
      72: getfield      #1                  // Field this$0:Lio/reactivex/rxjava3/processors/UnicastProcessor;
      75: getfield      #3                  // Field io/reactivex/rxjava3/processors/UnicastProcessor.queue:Lio/reactivex/rxjava3/operators/SpscLinkedArrayQueue;
      78: invokevirtual #6                  // Method io/reactivex/rxjava3/operators/SpscLinkedArrayQueue.clear:()V
      81: return
}
