Compiled from "AbstractObservableWithUpstream.java"
abstract class io.reactivex.rxjava3.internal.operators.observable.AbstractObservableWithUpstream<T, U> extends io.reactivex.rxjava3.core.Observable<U> implements io.reactivex.rxjava3.internal.fuseable.HasUpstreamObservableSource<T> {
  protected final io.reactivex.rxjava3.core.ObservableSource<T> source;

  io.reactivex.rxjava3.internal.operators.observable.AbstractObservableWithUpstream(io.reactivex.rxjava3.core.ObservableSource<T>);
    Code:
       0: aload_0
       1: invokespecial #1                  // Method io/reactivex/rxjava3/core/Observable."<init>":()V
       4: aload_0
       5: aload_1
       6: putfield      #2                  // Field source:Lio/reactivex/rxjava3/core/ObservableSource;
       9: return

  public final io.reactivex.rxjava3.core.ObservableSource<T> source();
    Code:
       0: aload_0
       1: getfield      #2                  // Field source:Lio/reactivex/rxjava3/core/ObservableSource;
       4: areturn
}
