Compiled from "BlockingObservableLatest.java"
public final class io.reactivex.rxjava3.internal.operators.observable.BlockingObservableLatest<T> implements java.lang.Iterable<T> {
  final io.reactivex.rxjava3.core.ObservableSource<T> source;

  public io.reactivex.rxjava3.internal.operators.observable.BlockingObservableLatest(io.reactivex.rxjava3.core.ObservableSource<T>);
    Code:
       0: aload_0
       1: invokespecial #1                  // Method java/lang/Object."<init>":()V
       4: aload_0
       5: aload_1
       6: putfield      #2                  // Field source:Lio/reactivex/rxjava3/core/ObservableSource;
       9: return

  public java.util.Iterator<T> iterator();
    Code:
       0: new           #3                  // class io/reactivex/rxjava3/internal/operators/observable/BlockingObservableLatest$BlockingObservableLatestIterator
       3: dup
       4: invokespecial #4                  // Method io/reactivex/rxjava3/internal/operators/observable/BlockingObservableLatest$BlockingObservableLatestIterator."<init>":()V
       7: astore_1
       8: aload_0
       9: getfield      #2                  // Field source:Lio/reactivex/rxjava3/core/ObservableSource;
      12: invokestatic  #5                  // Method io/reactivex/rxjava3/core/Observable.wrap:(Lio/reactivex/rxjava3/core/ObservableSource;)Lio/reactivex/rxjava3/core/Observable;
      15: invokevirtual #6                  // Method io/reactivex/rxjava3/core/Observable.materialize:()Lio/reactivex/rxjava3/core/Observable;
      18: astore_2
      19: aload_2
      20: aload_1
      21: invokevirtual #7                  // Method io/reactivex/rxjava3/core/Observable.subscribe:(Lio/reactivex/rxjava3/core/Observer;)V
      24: aload_1
      25: areturn
}
