Compiled from "BlockingObservableNext.java"
public final class io.reactivex.rxjava3.internal.operators.observable.BlockingObservableNext<T> implements java.lang.Iterable<T> {
  final io.reactivex.rxjava3.core.ObservableSource<T> source;

  public io.reactivex.rxjava3.internal.operators.observable.BlockingObservableNext(io.reactivex.rxjava3.core.ObservableSource<T>);
    Code:
       0: aload_0
       1: invokespecial #1                  // Method java/lang/Object."<init>":()V
       4: aload_0
       5: aload_1
       6: putfield      #2                  // Field source:Lio/reactivex/rxjava3/core/ObservableSource;
       9: return

  public java.util.Iterator<T> iterator();
    Code:
       0: new           #3                  // class io/reactivex/rxjava3/internal/operators/observable/BlockingObservableNext$NextObserver
       3: dup
       4: invokespecial #4                  // Method io/reactivex/rxjava3/internal/operators/observable/BlockingObservableNext$NextObserver."<init>":()V
       7: astore_1
       8: new           #5                  // class io/reactivex/rxjava3/internal/operators/observable/BlockingObservableNext$NextIterator
      11: dup
      12: aload_0
      13: getfield      #2                  // Field source:Lio/reactivex/rxjava3/core/ObservableSource;
      16: aload_1
      17: invokespecial #6                  // Method io/reactivex/rxjava3/internal/operators/observable/BlockingObservableNext$NextIterator."<init>":(Lio/reactivex/rxjava3/core/ObservableSource;Lio/reactivex/rxjava3/internal/operators/observable/BlockingObservableNext$NextObserver;)V
      20: areturn
}
