Compiled from "BlockingObservableIterable.java"
public final class io.reactivex.rxjava3.internal.operators.observable.BlockingObservableIterable<T> implements java.lang.Iterable<T> {
  final io.reactivex.rxjava3.core.ObservableSource<? extends T> source;

  final int bufferSize;

  public io.reactivex.rxjava3.internal.operators.observable.BlockingObservableIterable(io.reactivex.rxjava3.core.ObservableSource<? extends T>, int);
    Code:
       0: aload_0
       1: invokespecial #1                  // Method java/lang/Object."<init>":()V
       4: aload_0
       5: aload_1
       6: putfield      #2                  // Field source:Lio/reactivex/rxjava3/core/ObservableSource;
       9: aload_0
      10: iload_2
      11: putfield      #3                  // Field bufferSize:I
      14: return

  public java.util.Iterator<T> iterator();
    Code:
       0: new           #4                  // class io/reactivex/rxjava3/internal/operators/observable/BlockingObservableIterable$BlockingObservableIterator
       3: dup
       4: aload_0
       5: getfield      #3                  // Field bufferSize:I
       8: invokespecial #5                  // Method io/reactivex/rxjava3/internal/operators/observable/BlockingObservableIterable$BlockingObservableIterator."<init>":(I)V
      11: astore_1
      12: aload_0
      13: getfield      #2                  // Field source:Lio/reactivex/rxjava3/core/ObservableSource;
      16: aload_1
      17: invokeinterface #6,  2            // InterfaceMethod io/reactivex/rxjava3/core/ObservableSource.subscribe:(Lio/reactivex/rxjava3/core/Observer;)V
      22: aload_1
      23: areturn
}
