Compiled from "BlockingObservableMostRecent.java"
final class io.reactivex.rxjava3.internal.operators.observable.BlockingObservableMostRecent$MostRecentObserver<T> extends io.reactivex.rxjava3.observers.DefaultObserver<T> {
  volatile java.lang.Object value;

  io.reactivex.rxjava3.internal.operators.observable.BlockingObservableMostRecent$MostRecentObserver(T);
    Code:
       0: aload_0
       1: invokespecial #1                  // Method io/reactivex/rxjava3/observers/DefaultObserver."<init>":()V
       4: aload_0
       5: aload_1
       6: invokestatic  #2                  // Method io/reactivex/rxjava3/internal/util/NotificationLite.next:(Ljava/lang/Object;)Ljava/lang/Object;
       9: putfield      #3                  // Field value:Ljava/lang/Object;
      12: return

  public void onComplete();
    Code:
       0: aload_0
       1: invokestatic  #4                  // Method io/reactivex/rxjava3/internal/util/NotificationLite.complete:()Ljava/lang/Object;
       4: putfield      #3                  // Field value:Ljava/lang/Object;
       7: return

  public void onError(java.lang.Throwable);
    Code:
       0: aload_0
       1: aload_1
       2: invokestatic  #5                  // Method io/reactivex/rxjava3/internal/util/NotificationLite.error:(Ljava/lang/Throwable;)Ljava/lang/Object;
       5: putfield      #3                  // Field value:Ljava/lang/Object;
       8: return

  public void onNext(T);
    Code:
       0: aload_0
       1: aload_1
       2: invokestatic  #2                  // Method io/reactivex/rxjava3/internal/util/NotificationLite.next:(Ljava/lang/Object;)Ljava/lang/Object;
       5: putfield      #3                  // Field value:Ljava/lang/Object;
       8: return

  public io.reactivex.rxjava3.internal.operators.observable.BlockingObservableMostRecent$MostRecentObserver<T>.MostRecentIterator getIterable();
    Code:
       0: new           #6                  // class io/reactivex/rxjava3/internal/operators/observable/BlockingObservableMostRecent$MostRecentObserver$MostRecentIterator
       3: dup
       4: aload_0
       5: invokespecial #7                  // Method io/reactivex/rxjava3/internal/operators/observable/BlockingObservableMostRecent$MostRecentObserver$MostRecentIterator."<init>":(Lio/reactivex/rxjava3/internal/operators/observable/BlockingObservableMostRecent$MostRecentObserver;)V
       8: areturn
}
