Compiled from "ObservableLift.java"
public final class io.reactivex.rxjava3.internal.operators.observable.ObservableLift<R, T> extends io.reactivex.rxjava3.internal.operators.observable.AbstractObservableWithUpstream<T, R> {
  final io.reactivex.rxjava3.core.ObservableOperator<? extends R, ? super T> operator;

  public io.reactivex.rxjava3.internal.operators.observable.ObservableLift(io.reactivex.rxjava3.core.ObservableSource<T>, io.reactivex.rxjava3.core.ObservableOperator<? extends R, ? super T>);
    Code:
       0: aload_0
       1: aload_1
       2: invokespecial #1                  // Method io/reactivex/rxjava3/internal/operators/observable/AbstractObservableWithUpstream."<init>":(Lio/reactivex/rxjava3/core/ObservableSource;)V
       5: aload_0
       6: aload_2
       7: putfield      #2                  // Field operator:Lio/reactivex/rxjava3/core/ObservableOperator;
      10: return

  public void subscribeActual(io.reactivex.rxjava3.core.Observer<? super R>);
    Code:
       0: aload_0
       1: getfield      #2                  // Field operator:Lio/reactivex/rxjava3/core/ObservableOperator;
       4: aload_1
       5: invokeinterface #3,  2            // InterfaceMethod io/reactivex/rxjava3/core/ObservableOperator.apply:(Lio/reactivex/rxjava3/core/Observer;)Lio/reactivex/rxjava3/core/Observer;
      10: new           #4                  // class java/lang/StringBuilder
      13: dup
      14: invokespecial #5                  // Method java/lang/StringBuilder."<init>":()V
      17: ldc           #6                  // String Operator
      19: invokevirtual #7                  // Method java/lang/StringBuilder.append:(Ljava/lang/String;)Ljava/lang/StringBuilder;
      22: aload_0
      23: getfield      #2                  // Field operator:Lio/reactivex/rxjava3/core/ObservableOperator;
      26: invokevirtual #8                  // Method java/lang/StringBuilder.append:(Ljava/lang/Object;)Ljava/lang/StringBuilder;
      29: ldc           #9                  // String  returned a null Observer
      31: invokevirtual #7                  // Method java/lang/StringBuilder.append:(Ljava/lang/String;)Ljava/lang/StringBuilder;
      34: invokevirtual #10                 // Method java/lang/StringBuilder.toString:()Ljava/lang/String;
      37: invokestatic  #11                 // Method java/util/Objects.requireNonNull:(Ljava/lang/Object;Ljava/lang/String;)Ljava/lang/Object;
      40: checkcast     #12                 // class io/reactivex/rxjava3/core/Observer
      43: astore_2
      44: goto          80
      47: astore_3
      48: aload_3
      49: athrow
      50: astore_3
      51: aload_3
      52: invokestatic  #15                 // Method io/reactivex/rxjava3/exceptions/Exceptions.throwIfFatal:(Ljava/lang/Throwable;)V
      55: aload_3
      56: invokestatic  #16                 // Method io/reactivex/rxjava3/plugins/RxJavaPlugins.onError:(Ljava/lang/Throwable;)V
      59: new           #13                 // class java/lang/NullPointerException
      62: dup
      63: ldc           #17                 // String Actually not, but can\'t throw other exceptions due to RS
      65: invokespecial #18                 // Method java/lang/NullPointerException."<init>":(Ljava/lang/String;)V
      68: astore        4
      70: aload         4
      72: aload_3
      73: invokevirtual #19                 // Method java/lang/NullPointerException.initCause:(Ljava/lang/Throwable;)Ljava/lang/Throwable;
      76: pop
      77: aload         4
      79: athrow
      80: aload_0
      81: getfield      #20                 // Field source:Lio/reactivex/rxjava3/core/ObservableSource;
      84: aload_2
      85: invokeinterface #21,  2           // InterfaceMethod io/reactivex/rxjava3/core/ObservableSource.subscribe:(Lio/reactivex/rxjava3/core/Observer;)V
      90: return
    Exception table:
       from    to  target type
           0    44    47   Class java/lang/NullPointerException
           0    44    50   Class java/lang/Throwable
}
