Compiled from "ObservableReplay.java"
final class io.reactivex.rxjava3.internal.operators.observable.ObservableReplay$UnboundedReplayBuffer<T> extends java.util.ArrayList<java.lang.Object> implements io.reactivex.rxjava3.internal.operators.observable.ObservableReplay$ReplayBuffer<T> {
  private static final long serialVersionUID;

  volatile int size;

  io.reactivex.rxjava3.internal.operators.observable.ObservableReplay$UnboundedReplayBuffer(int);
    Code:
       0: aload_0
       1: iload_1
       2: invokespecial #1                  // Method java/util/ArrayList."<init>":(I)V
       5: return

  public void next(T);
    Code:
       0: aload_0
       1: aload_1
       2: invokestatic  #2                  // Method io/reactivex/rxjava3/internal/util/NotificationLite.next:(Ljava/lang/Object;)Ljava/lang/Object;
       5: invokevirtual #3                  // Method add:(Ljava/lang/Object;)Z
       8: pop
       9: aload_0
      10: dup
      11: getfield      #4                  // Field size:I
      14: iconst_1
      15: iadd
      16: putfield      #4                  // Field size:I
      19: return

  public void error(java.lang.Throwable);
    Code:
       0: aload_0
       1: aload_1
       2: invokestatic  #5                  // Method io/reactivex/rxjava3/internal/util/NotificationLite.error:(Ljava/lang/Throwable;)Ljava/lang/Object;
       5: invokevirtual #3                  // Method add:(Ljava/lang/Object;)Z
       8: pop
       9: aload_0
      10: dup
      11: getfield      #4                  // Field size:I
      14: iconst_1
      15: iadd
      16: putfield      #4                  // Field size:I
      19: return

  public void complete();
    Code:
       0: aload_0
       1: invokestatic  #6                  // Method io/reactivex/rxjava3/internal/util/NotificationLite.complete:()Ljava/lang/Object;
       4: invokevirtual #3                  // Method add:(Ljava/lang/Object;)Z
       7: pop
       8: aload_0
       9: dup
      10: getfield      #4                  // Field size:I
      13: iconst_1
      14: iadd
      15: putfield      #4                  // Field size:I
      18: return

  public void replay(io.reactivex.rxjava3.internal.operators.observable.ObservableReplay$InnerDisposable<T>);
    Code:
       0: aload_1
       1: invokevirtual #7                  // Method io/reactivex/rxjava3/internal/operators/observable/ObservableReplay$InnerDisposable.getAndIncrement:()I
       4: ifeq          8
       7: return
       8: aload_1
       9: getfield      #8                  // Field io/reactivex/rxjava3/internal/operators/observable/ObservableReplay$InnerDisposable.child:Lio/reactivex/rxjava3/core/Observer;
      12: astore_2
      13: iconst_1
      14: istore_3
      15: aload_1
      16: invokevirtual #9                  // Method io/reactivex/rxjava3/internal/operators/observable/ObservableReplay$InnerDisposable.isDisposed:()Z
      19: ifeq          23
      22: return
      23: aload_0
      24: getfield      #4                  // Field size:I
      27: istore        4
      29: aload_1
      30: invokevirtual #10                 // Method io/reactivex/rxjava3/internal/operators/observable/ObservableReplay$InnerDisposable.index:()Ljava/lang/Object;
      33: checkcast     #11                 // class java/lang/Integer
      36: astore        5
      38: aload         5
      40: ifnull        51
      43: aload         5
      45: invokevirtual #12                 // Method java/lang/Integer.intValue:()I
      48: goto          52
      51: iconst_0
      52: istore        6
      54: iload         6
      56: iload         4
      58: if_icmpge     93
      61: aload_0
      62: iload         6
      64: invokevirtual #13                 // Method get:(I)Ljava/lang/Object;
      67: astore        7
      69: aload         7
      71: aload_2
      72: invokestatic  #14                 // Method io/reactivex/rxjava3/internal/util/NotificationLite.accept:(Ljava/lang/Object;Lio/reactivex/rxjava3/core/Observer;)Z
      75: ifeq          79
      78: return
      79: aload_1
      80: invokevirtual #9                  // Method io/reactivex/rxjava3/internal/operators/observable/ObservableReplay$InnerDisposable.isDisposed:()Z
      83: ifeq          87
      86: return
      87: iinc          6, 1
      90: goto          54
      93: aload_1
      94: iload         6
      96: invokestatic  #15                 // Method java/lang/Integer.valueOf:(I)Ljava/lang/Integer;
      99: putfield      #16                 // Field io/reactivex/rxjava3/internal/operators/observable/ObservableReplay$InnerDisposable.index:Ljava/lang/Object;
     102: aload_1
     103: iload_3
     104: ineg
     105: invokevirtual #17                 // Method io/reactivex/rxjava3/internal/operators/observable/ObservableReplay$InnerDisposable.addAndGet:(I)I
     108: istore_3
     109: iload_3
     110: ifne          116
     113: goto          119
     116: goto          15
     119: return
}
