Compiled from "ObservableRetryWhen.java"
public final class io.reactivex.rxjava3.internal.operators.observable.ObservableRetryWhen<T> extends io.reactivex.rxjava3.internal.operators.observable.AbstractObservableWithUpstream<T, T> {
  final io.reactivex.rxjava3.functions.Function<? super io.reactivex.rxjava3.core.Observable<java.lang.Throwable>, ? extends io.reactivex.rxjava3.core.ObservableSource<?>> handler;

  public io.reactivex.rxjava3.internal.operators.observable.ObservableRetryWhen(io.reactivex.rxjava3.core.ObservableSource<T>, io.reactivex.rxjava3.functions.Function<? super io.reactivex.rxjava3.core.Observable<java.lang.Throwable>, ? extends io.reactivex.rxjava3.core.ObservableSource<?>>);
    Code:
       0: aload_0
       1: aload_1
       2: invokespecial #1                  // Method io/reactivex/rxjava3/internal/operators/observable/AbstractObservableWithUpstream."<init>":(Lio/reactivex/rxjava3/core/ObservableSource;)V
       5: aload_0
       6: aload_2
       7: putfield      #2                  // Field handler:Lio/reactivex/rxjava3/functions/Function;
      10: return

  protected void subscribeActual(io.reactivex.rxjava3.core.Observer<? super T>);
    Code:
       0: invokestatic  #3                  // Method io/reactivex/rxjava3/subjects/PublishSubject.create:()Lio/reactivex/rxjava3/subjects/PublishSubject;
       3: invokevirtual #4                  // Method io/reactivex/rxjava3/subjects/PublishSubject.toSerialized:()Lio/reactivex/rxjava3/subjects/Subject;
       6: astore_2
       7: aload_0
       8: getfield      #2                  // Field handler:Lio/reactivex/rxjava3/functions/Function;
      11: aload_2
      12: invokeinterface #5,  2            // InterfaceMethod io/reactivex/rxjava3/functions/Function.apply:(Ljava/lang/Object;)Ljava/lang/Object;
      17: ldc           #6                  // String The handler returned a null ObservableSource
      19: invokestatic  #7                  // Method java/util/Objects.requireNonNull:(Ljava/lang/Object;Ljava/lang/String;)Ljava/lang/Object;
      22: checkcast     #8                  // class io/reactivex/rxjava3/core/ObservableSource
      25: astore_3
      26: goto          43
      29: astore        4
      31: aload         4
      33: invokestatic  #10                 // Method io/reactivex/rxjava3/exceptions/Exceptions.throwIfFatal:(Ljava/lang/Throwable;)V
      36: aload         4
      38: aload_1
      39: invokestatic  #11                 // Method io/reactivex/rxjava3/internal/disposables/EmptyDisposable.error:(Ljava/lang/Throwable;Lio/reactivex/rxjava3/core/Observer;)V
      42: return
      43: new           #12                 // class io/reactivex/rxjava3/internal/operators/observable/ObservableRetryWhen$RepeatWhenObserver
      46: dup
      47: aload_1
      48: aload_2
      49: aload_0
      50: getfield      #13                 // Field source:Lio/reactivex/rxjava3/core/ObservableSource;
      53: invokespecial #14                 // Method io/reactivex/rxjava3/internal/operators/observable/ObservableRetryWhen$RepeatWhenObserver."<init>":(Lio/reactivex/rxjava3/core/Observer;Lio/reactivex/rxjava3/subjects/Subject;Lio/reactivex/rxjava3/core/ObservableSource;)V
      56: astore        4
      58: aload_1
      59: aload         4
      61: invokeinterface #15,  2           // InterfaceMethod io/reactivex/rxjava3/core/Observer.onSubscribe:(Lio/reactivex/rxjava3/disposables/Disposable;)V
      66: aload_3
      67: aload         4
      69: getfield      #16                 // Field io/reactivex/rxjava3/internal/operators/observable/ObservableRetryWhen$RepeatWhenObserver.inner:Lio/reactivex/rxjava3/internal/operators/observable/ObservableRetryWhen$RepeatWhenObserver$InnerRepeatObserver;
      72: invokeinterface #17,  2           // InterfaceMethod io/reactivex/rxjava3/core/ObservableSource.subscribe:(Lio/reactivex/rxjava3/core/Observer;)V
      77: aload         4
      79: invokevirtual #18                 // Method io/reactivex/rxjava3/internal/operators/observable/ObservableRetryWhen$RepeatWhenObserver.subscribeNext:()V
      82: return
    Exception table:
       from    to  target type
           7    26    29   Class java/lang/Throwable
}
