Compiled from "ObservableInternalHelper.java"
final class io.reactivex.rxjava3.internal.operators.observable.ObservableInternalHelper$ObserverOnNext<T> implements io.reactivex.rxjava3.functions.Consumer<T> {
  final io.reactivex.rxjava3.core.Observer<T> observer;

  io.reactivex.rxjava3.internal.operators.observable.ObservableInternalHelper$ObserverOnNext(io.reactivex.rxjava3.core.Observer<T>);
    Code:
       0: aload_0
       1: invokespecial #1                  // Method java/lang/Object."<init>":()V
       4: aload_0
       5: aload_1
       6: putfield      #2                  // Field observer:Lio/reactivex/rxjava3/core/Observer;
       9: return

  public void accept(T);
    Code:
       0: aload_0
       1: getfield      #2                  // Field observer:Lio/reactivex/rxjava3/core/Observer;
       4: aload_1
       5: invokeinterface #3,  2            // InterfaceMethod io/reactivex/rxjava3/core/Observer.onNext:(Ljava/lang/Object;)V
      10: return
}
