Compiled from "ObservableReduceMaybe.java"
public final class io.reactivex.rxjava3.internal.operators.observable.ObservableReduceMaybe<T> extends io.reactivex.rxjava3.core.Maybe<T> {
  final io.reactivex.rxjava3.core.ObservableSource<T> source;

  final io.reactivex.rxjava3.functions.BiFunction<T, T, T> reducer;

  public io.reactivex.rxjava3.internal.operators.observable.ObservableReduceMaybe(io.reactivex.rxjava3.core.ObservableSource<T>, io.reactivex.rxjava3.functions.BiFunction<T, T, T>);
    Code:
       0: aload_0
       1: invokespecial #1                  // Method io/reactivex/rxjava3/core/Maybe."<init>":()V
       4: aload_0
       5: aload_1
       6: putfield      #2                  // Field source:Lio/reactivex/rxjava3/core/ObservableSource;
       9: aload_0
      10: aload_2
      11: putfield      #3                  // Field reducer:Lio/reactivex/rxjava3/functions/BiFunction;
      14: return

  protected void subscribeActual(io.reactivex.rxjava3.core.MaybeObserver<? super T>);
    Code:
       0: aload_0
       1: getfield      #2                  // Field source:Lio/reactivex/rxjava3/core/ObservableSource;
       4: new           #4                  // class io/reactivex/rxjava3/internal/operators/observable/ObservableReduceMaybe$ReduceObserver
       7: dup
       8: aload_1
       9: aload_0
      10: getfield      #3                  // Field reducer:Lio/reactivex/rxjava3/functions/BiFunction;
      13: invokespecial #5                  // Method io/reactivex/rxjava3/internal/operators/observable/ObservableReduceMaybe$ReduceObserver."<init>":(Lio/reactivex/rxjava3/core/MaybeObserver;Lio/reactivex/rxjava3/functions/BiFunction;)V
      16: invokeinterface #6,  2            // InterfaceMethod io/reactivex/rxjava3/core/ObservableSource.subscribe:(Lio/reactivex/rxjava3/core/Observer;)V
      21: return
}
