Compiled from "ObservableFlatMapCompletableCompletable.java"
public final class io.reactivex.rxjava3.internal.operators.observable.ObservableFlatMapCompletableCompletable<T> extends io.reactivex.rxjava3.core.Completable implements io.reactivex.rxjava3.internal.fuseable.FuseToObservable<T> {
  final io.reactivex.rxjava3.core.ObservableSource<T> source;

  final io.reactivex.rxjava3.functions.Function<? super T, ? extends io.reactivex.rxjava3.core.CompletableSource> mapper;

  final boolean delayErrors;

  public io.reactivex.rxjava3.internal.operators.observable.ObservableFlatMapCompletableCompletable(io.reactivex.rxjava3.core.ObservableSource<T>, io.reactivex.rxjava3.functions.Function<? super T, ? extends io.reactivex.rxjava3.core.CompletableSource>, boolean);
    Code:
       0: aload_0
       1: invokespecial #1                  // Method io/reactivex/rxjava3/core/Completable."<init>":()V
       4: aload_0
       5: aload_1
       6: putfield      #2                  // Field source:Lio/reactivex/rxjava3/core/ObservableSource;
       9: aload_0
      10: aload_2
      11: putfield      #3                  // Field mapper:Lio/reactivex/rxjava3/functions/Function;
      14: aload_0
      15: iload_3
      16: putfield      #4                  // Field delayErrors:Z
      19: return

  protected void subscribeActual(io.reactivex.rxjava3.core.CompletableObserver);
    Code:
       0: aload_0
       1: getfield      #2                  // Field source:Lio/reactivex/rxjava3/core/ObservableSource;
       4: new           #5                  // class io/reactivex/rxjava3/internal/operators/observable/ObservableFlatMapCompletableCompletable$FlatMapCompletableMainObserver
       7: dup
       8: aload_1
       9: aload_0
      10: getfield      #3                  // Field mapper:Lio/reactivex/rxjava3/functions/Function;
      13: aload_0
      14: getfield      #4                  // Field delayErrors:Z
      17: invokespecial #6                  // Method io/reactivex/rxjava3/internal/operators/observable/ObservableFlatMapCompletableCompletable$FlatMapCompletableMainObserver."<init>":(Lio/reactivex/rxjava3/core/CompletableObserver;Lio/reactivex/rxjava3/functions/Function;Z)V
      20: invokeinterface #7,  2            // InterfaceMethod io/reactivex/rxjava3/core/ObservableSource.subscribe:(Lio/reactivex/rxjava3/core/Observer;)V
      25: return

  public io.reactivex.rxjava3.core.Observable<T> fuseToObservable();
    Code:
       0: new           #8                  // class io/reactivex/rxjava3/internal/operators/observable/ObservableFlatMapCompletable
       3: dup
       4: aload_0
       5: getfield      #2                  // Field source:Lio/reactivex/rxjava3/core/ObservableSource;
       8: aload_0
       9: getfield      #3                  // Field mapper:Lio/reactivex/rxjava3/functions/Function;
      12: aload_0
      13: getfield      #4                  // Field delayErrors:Z
      16: invokespecial #9                  // Method io/reactivex/rxjava3/internal/operators/observable/ObservableFlatMapCompletable."<init>":(Lio/reactivex/rxjava3/core/ObservableSource;Lio/reactivex/rxjava3/functions/Function;Z)V
      19: invokestatic  #10                 // Method io/reactivex/rxjava3/plugins/RxJavaPlugins.onAssembly:(Lio/reactivex/rxjava3/core/Observable;)Lio/reactivex/rxjava3/core/Observable;
      22: areturn
}
