Compiled from "ObservableMergeWithCompletable.java"
public final class io.reactivex.rxjava3.internal.operators.observable.ObservableMergeWithCompletable<T> extends io.reactivex.rxjava3.internal.operators.observable.AbstractObservableWithUpstream<T, T> {
  final io.reactivex.rxjava3.core.CompletableSource other;

  public io.reactivex.rxjava3.internal.operators.observable.ObservableMergeWithCompletable(io.reactivex.rxjava3.core.Observable<T>, io.reactivex.rxjava3.core.CompletableSource);
    Code:
       0: aload_0
       1: aload_1
       2: invokespecial #1                  // Method io/reactivex/rxjava3/internal/operators/observable/AbstractObservableWithUpstream."<init>":(Lio/reactivex/rxjava3/core/ObservableSource;)V
       5: aload_0
       6: aload_2
       7: putfield      #2                  // Field other:Lio/reactivex/rxjava3/core/CompletableSource;
      10: return

  protected void subscribeActual(io.reactivex.rxjava3.core.Observer<? super T>);
    Code:
       0: new           #3                  // class io/reactivex/rxjava3/internal/operators/observable/ObservableMergeWithCompletable$MergeWithObserver
       3: dup
       4: aload_1
       5: invokespecial #4                  // Method io/reactivex/rxjava3/internal/operators/observable/ObservableMergeWithCompletable$MergeWithObserver."<init>":(Lio/reactivex/rxjava3/core/Observer;)V
       8: astore_2
       9: aload_1
      10: aload_2
      11: invokeinterface #5,  2            // InterfaceMethod io/reactivex/rxjava3/core/Observer.onSubscribe:(Lio/reactivex/rxjava3/disposables/Disposable;)V
      16: aload_0
      17: getfield      #6                  // Field source:Lio/reactivex/rxjava3/core/ObservableSource;
      20: aload_2
      21: invokeinterface #7,  2            // InterfaceMethod io/reactivex/rxjava3/core/ObservableSource.subscribe:(Lio/reactivex/rxjava3/core/Observer;)V
      26: aload_0
      27: getfield      #2                  // Field other:Lio/reactivex/rxjava3/core/CompletableSource;
      30: aload_2
      31: getfield      #8                  // Field io/reactivex/rxjava3/internal/operators/observable/ObservableMergeWithCompletable$MergeWithObserver.otherObserver:Lio/reactivex/rxjava3/internal/operators/observable/ObservableMergeWithCompletable$MergeWithObserver$OtherObserver;
      34: invokeinterface #9,  2            // InterfaceMethod io/reactivex/rxjava3/core/CompletableSource.subscribe:(Lio/reactivex/rxjava3/core/CompletableObserver;)V
      39: return
}
