Compiled from "ObservableInternalHelper.java"
final class io.reactivex.rxjava3.internal.operators.observable.ObservableInternalHelper$FlatMapWithCombinerInner<U, R, T> implements io.reactivex.rxjava3.functions.Function<U, R> {
  private final io.reactivex.rxjava3.functions.BiFunction<? super T, ? super U, ? extends R> combiner;

  private final T t;

  io.reactivex.rxjava3.internal.operators.observable.ObservableInternalHelper$FlatMapWithCombinerInner(io.reactivex.rxjava3.functions.BiFunction<? super T, ? super U, ? extends R>, T);
    Code:
       0: aload_0
       1: invokespecial #1                  // Method java/lang/Object."<init>":()V
       4: aload_0
       5: aload_1
       6: putfield      #2                  // Field combiner:Lio/reactivex/rxjava3/functions/BiFunction;
       9: aload_0
      10: aload_2
      11: putfield      #3                  // Field t:Ljava/lang/Object;
      14: return

  public R apply(U) throws java.lang.Throwable;
    Code:
       0: aload_0
       1: getfield      #2                  // Field combiner:Lio/reactivex/rxjava3/functions/BiFunction;
       4: aload_0
       5: getfield      #3                  // Field t:Ljava/lang/Object;
       8: aload_1
       9: invokeinterface #4,  3            // InterfaceMethod io/reactivex/rxjava3/functions/BiFunction.apply:(Ljava/lang/Object;Ljava/lang/Object;)Ljava/lang/Object;
      14: areturn
}
