Compiled from "ObservableElementAt.java"
public final class io.reactivex.rxjava3.internal.operators.observable.ObservableElementAt<T> extends io.reactivex.rxjava3.internal.operators.observable.AbstractObservableWithUpstream<T, T> {
  final long index;

  final T defaultValue;

  final boolean errorOnFewer;

  public io.reactivex.rxjava3.internal.operators.observable.ObservableElementAt(io.reactivex.rxjava3.core.ObservableSource<T>, long, T, boolean);
    Code:
       0: aload_0
       1: aload_1
       2: invokespecial #1                  // Method io/reactivex/rxjava3/internal/operators/observable/AbstractObservableWithUpstream."<init>":(Lio/reactivex/rxjava3/core/ObservableSource;)V
       5: aload_0
       6: lload_2
       7: putfield      #2                  // Field index:J
      10: aload_0
      11: aload         4
      13: putfield      #3                  // Field defaultValue:Ljava/lang/Object;
      16: aload_0
      17: iload         5
      19: putfield      #4                  // Field errorOnFewer:Z
      22: return

  public void subscribeActual(io.reactivex.rxjava3.core.Observer<? super T>);
    Code:
       0: aload_0
       1: getfield      #5                  // Field source:Lio/reactivex/rxjava3/core/ObservableSource;
       4: new           #6                  // class io/reactivex/rxjava3/internal/operators/observable/ObservableElementAt$ElementAtObserver
       7: dup
       8: aload_1
       9: aload_0
      10: getfield      #2                  // Field index:J
      13: aload_0
      14: getfield      #3                  // Field defaultValue:Ljava/lang/Object;
      17: aload_0
      18: getfield      #4                  // Field errorOnFewer:Z
      21: invokespecial #7                  // Method io/reactivex/rxjava3/internal/operators/observable/ObservableElementAt$ElementAtObserver."<init>":(Lio/reactivex/rxjava3/core/Observer;JLjava/lang/Object;Z)V
      24: invokeinterface #8,  2            // InterfaceMethod io/reactivex/rxjava3/core/ObservableSource.subscribe:(Lio/reactivex/rxjava3/core/Observer;)V
      29: return
}
