Compiled from "ObservableReplay.java"
abstract class io.reactivex.rxjava3.internal.operators.observable.ObservableReplay$BoundedReplayBuffer<T> extends java.util.concurrent.atomic.AtomicReference<io.reactivex.rxjava3.internal.operators.observable.ObservableReplay$Node> implements io.reactivex.rxjava3.internal.operators.observable.ObservableReplay$ReplayBuffer<T> {
  private static final long serialVersionUID;

  io.reactivex.rxjava3.internal.operators.observable.ObservableReplay$Node tail;

  int size;

  final boolean eagerTruncate;

  io.reactivex.rxjava3.internal.operators.observable.ObservableReplay$BoundedReplayBuffer(boolean);
    Code:
       0: aload_0
       1: invokespecial #1                  // Method java/util/concurrent/atomic/AtomicReference."<init>":()V
       4: aload_0
       5: iload_1
       6: putfield      #2                  // Field eagerTruncate:Z
       9: new           #3                  // class io/reactivex/rxjava3/internal/operators/observable/ObservableReplay$Node
      12: dup
      13: aconst_null
      14: invokespecial #4                  // Method io/reactivex/rxjava3/internal/operators/observable/ObservableReplay$Node."<init>":(Ljava/lang/Object;)V
      17: astore_2
      18: aload_0
      19: aload_2
      20: putfield      #5                  // Field tail:Lio/reactivex/rxjava3/internal/operators/observable/ObservableReplay$Node;
      23: aload_0
      24: aload_2
      25: invokevirtual #6                  // Method set:(Ljava/lang/Object;)V
      28: return

  final void addLast(io.reactivex.rxjava3.internal.operators.observable.ObservableReplay$Node);
    Code:
       0: aload_0
       1: getfield      #5                  // Field tail:Lio/reactivex/rxjava3/internal/operators/observable/ObservableReplay$Node;
       4: aload_1
       5: invokevirtual #7                  // Method io/reactivex/rxjava3/internal/operators/observable/ObservableReplay$Node.set:(Ljava/lang/Object;)V
       8: aload_0
       9: aload_1
      10: putfield      #5                  // Field tail:Lio/reactivex/rxjava3/internal/operators/observable/ObservableReplay$Node;
      13: aload_0
      14: dup
      15: getfield      #8                  // Field size:I
      18: iconst_1
      19: iadd
      20: putfield      #8                  // Field size:I
      23: return

  final void removeFirst();
    Code:
       0: aload_0
       1: invokevirtual #9                  // Method get:()Ljava/lang/Object;
       4: checkcast     #3                  // class io/reactivex/rxjava3/internal/operators/observable/ObservableReplay$Node
       7: astore_1
       8: aload_1
       9: invokevirtual #10                 // Method io/reactivex/rxjava3/internal/operators/observable/ObservableReplay$Node.get:()Ljava/lang/Object;
      12: checkcast     #3                  // class io/reactivex/rxjava3/internal/operators/observable/ObservableReplay$Node
      15: astore_2
      16: aload_0
      17: dup
      18: getfield      #8                  // Field size:I
      21: iconst_1
      22: isub
      23: putfield      #8                  // Field size:I
      26: aload_0
      27: aload_2
      28: invokevirtual #11                 // Method setFirst:(Lio/reactivex/rxjava3/internal/operators/observable/ObservableReplay$Node;)V
      31: return

  final void trimHead();
    Code:
       0: aload_0
       1: invokevirtual #9                  // Method get:()Ljava/lang/Object;
       4: checkcast     #3                  // class io/reactivex/rxjava3/internal/operators/observable/ObservableReplay$Node
       7: astore_1
       8: aload_1
       9: getfield      #12                 // Field io/reactivex/rxjava3/internal/operators/observable/ObservableReplay$Node.value:Ljava/lang/Object;
      12: ifnull        37
      15: new           #3                  // class io/reactivex/rxjava3/internal/operators/observable/ObservableReplay$Node
      18: dup
      19: aconst_null
      20: invokespecial #4                  // Method io/reactivex/rxjava3/internal/operators/observable/ObservableReplay$Node."<init>":(Ljava/lang/Object;)V
      23: astore_2
      24: aload_2
      25: aload_1
      26: invokevirtual #10                 // Method io/reactivex/rxjava3/internal/operators/observable/ObservableReplay$Node.get:()Ljava/lang/Object;
      29: invokevirtual #13                 // Method io/reactivex/rxjava3/internal/operators/observable/ObservableReplay$Node.lazySet:(Ljava/lang/Object;)V
      32: aload_0
      33: aload_2
      34: invokevirtual #6                  // Method set:(Ljava/lang/Object;)V
      37: return

  final void removeSome(int);
    Code:
       0: aload_0
       1: invokevirtual #9                  // Method get:()Ljava/lang/Object;
       4: checkcast     #3                  // class io/reactivex/rxjava3/internal/operators/observable/ObservableReplay$Node
       7: astore_2
       8: iload_1
       9: ifle          36
      12: aload_2
      13: invokevirtual #10                 // Method io/reactivex/rxjava3/internal/operators/observable/ObservableReplay$Node.get:()Ljava/lang/Object;
      16: checkcast     #3                  // class io/reactivex/rxjava3/internal/operators/observable/ObservableReplay$Node
      19: astore_2
      20: iinc          1, -1
      23: aload_0
      24: dup
      25: getfield      #8                  // Field size:I
      28: iconst_1
      29: isub
      30: putfield      #8                  // Field size:I
      33: goto          8
      36: aload_0
      37: aload_2
      38: invokevirtual #11                 // Method setFirst:(Lio/reactivex/rxjava3/internal/operators/observable/ObservableReplay$Node;)V
      41: aload_0
      42: invokevirtual #9                  // Method get:()Ljava/lang/Object;
      45: checkcast     #3                  // class io/reactivex/rxjava3/internal/operators/observable/ObservableReplay$Node
      48: astore_2
      49: aload_2
      50: invokevirtual #10                 // Method io/reactivex/rxjava3/internal/operators/observable/ObservableReplay$Node.get:()Ljava/lang/Object;
      53: ifnonnull     61
      56: aload_0
      57: aload_2
      58: putfield      #5                  // Field tail:Lio/reactivex/rxjava3/internal/operators/observable/ObservableReplay$Node;
      61: return

  final void setFirst(io.reactivex.rxjava3.internal.operators.observable.ObservableReplay$Node);
    Code:
       0: aload_0
       1: getfield      #2                  // Field eagerTruncate:Z
       4: ifeq          26
       7: new           #3                  // class io/reactivex/rxjava3/internal/operators/observable/ObservableReplay$Node
      10: dup
      11: aconst_null
      12: invokespecial #4                  // Method io/reactivex/rxjava3/internal/operators/observable/ObservableReplay$Node."<init>":(Ljava/lang/Object;)V
      15: astore_2
      16: aload_2
      17: aload_1
      18: invokevirtual #10                 // Method io/reactivex/rxjava3/internal/operators/observable/ObservableReplay$Node.get:()Ljava/lang/Object;
      21: invokevirtual #13                 // Method io/reactivex/rxjava3/internal/operators/observable/ObservableReplay$Node.lazySet:(Ljava/lang/Object;)V
      24: aload_2
      25: astore_1
      26: aload_0
      27: aload_1
      28: invokevirtual #6                  // Method set:(Ljava/lang/Object;)V
      31: return

  public final void next(T);
    Code:
       0: aload_0
       1: aload_1
       2: invokestatic  #14                 // Method io/reactivex/rxjava3/internal/util/NotificationLite.next:(Ljava/lang/Object;)Ljava/lang/Object;
       5: invokevirtual #15                 // Method enterTransform:(Ljava/lang/Object;)Ljava/lang/Object;
       8: astore_2
       9: new           #3                  // class io/reactivex/rxjava3/internal/operators/observable/ObservableReplay$Node
      12: dup
      13: aload_2
      14: invokespecial #4                  // Method io/reactivex/rxjava3/internal/operators/observable/ObservableReplay$Node."<init>":(Ljava/lang/Object;)V
      17: astore_3
      18: aload_0
      19: aload_3
      20: invokevirtual #16                 // Method addLast:(Lio/reactivex/rxjava3/internal/operators/observable/ObservableReplay$Node;)V
      23: aload_0
      24: invokevirtual #17                 // Method truncate:()V
      27: return

  public final void error(java.lang.Throwable);
    Code:
       0: aload_0
       1: aload_1
       2: invokestatic  #18                 // Method io/reactivex/rxjava3/internal/util/NotificationLite.error:(Ljava/lang/Throwable;)Ljava/lang/Object;
       5: invokevirtual #15                 // Method enterTransform:(Ljava/lang/Object;)Ljava/lang/Object;
       8: astore_2
       9: new           #3                  // class io/reactivex/rxjava3/internal/operators/observable/ObservableReplay$Node
      12: dup
      13: aload_2
      14: invokespecial #4                  // Method io/reactivex/rxjava3/internal/operators/observable/ObservableReplay$Node."<init>":(Ljava/lang/Object;)V
      17: astore_3
      18: aload_0
      19: aload_3
      20: invokevirtual #16                 // Method addLast:(Lio/reactivex/rxjava3/internal/operators/observable/ObservableReplay$Node;)V
      23: aload_0
      24: invokevirtual #19                 // Method truncateFinal:()V
      27: return

  public final void complete();
    Code:
       0: aload_0
       1: invokestatic  #20                 // Method io/reactivex/rxjava3/internal/util/NotificationLite.complete:()Ljava/lang/Object;
       4: invokevirtual #15                 // Method enterTransform:(Ljava/lang/Object;)Ljava/lang/Object;
       7: astore_1
       8: new           #3                  // class io/reactivex/rxjava3/internal/operators/observable/ObservableReplay$Node
      11: dup
      12: aload_1
      13: invokespecial #4                  // Method io/reactivex/rxjava3/internal/operators/observable/ObservableReplay$Node."<init>":(Ljava/lang/Object;)V
      16: astore_2
      17: aload_0
      18: aload_2
      19: invokevirtual #16                 // Method addLast:(Lio/reactivex/rxjava3/internal/operators/observable/ObservableReplay$Node;)V
      22: aload_0
      23: invokevirtual #19                 // Method truncateFinal:()V
      26: return

  public final void replay(io.reactivex.rxjava3.internal.operators.observable.ObservableReplay$InnerDisposable<T>);
    Code:
       0: aload_1
       1: invokevirtual #21                 // Method io/reactivex/rxjava3/internal/operators/observable/ObservableReplay$InnerDisposable.getAndIncrement:()I
       4: ifeq          8
       7: return
       8: iconst_1
       9: istore_2
      10: aload_1
      11: invokevirtual #22                 // Method io/reactivex/rxjava3/internal/operators/observable/ObservableReplay$InnerDisposable.index:()Ljava/lang/Object;
      14: checkcast     #3                  // class io/reactivex/rxjava3/internal/operators/observable/ObservableReplay$Node
      17: astore_3
      18: aload_3
      19: ifnonnull     32
      22: aload_0
      23: invokevirtual #23                 // Method getHead:()Lio/reactivex/rxjava3/internal/operators/observable/ObservableReplay$Node;
      26: astore_3
      27: aload_1
      28: aload_3
      29: putfield      #24                 // Field io/reactivex/rxjava3/internal/operators/observable/ObservableReplay$InnerDisposable.index:Ljava/lang/Object;
      32: aload_1
      33: invokevirtual #25                 // Method io/reactivex/rxjava3/internal/operators/observable/ObservableReplay$InnerDisposable.isDisposed:()Z
      36: ifeq          45
      39: aload_1
      40: aconst_null
      41: putfield      #24                 // Field io/reactivex/rxjava3/internal/operators/observable/ObservableReplay$InnerDisposable.index:Ljava/lang/Object;
      44: return
      45: aload_3
      46: invokevirtual #10                 // Method io/reactivex/rxjava3/internal/operators/observable/ObservableReplay$Node.get:()Ljava/lang/Object;
      49: checkcast     #3                  // class io/reactivex/rxjava3/internal/operators/observable/ObservableReplay$Node
      52: astore        4
      54: aload         4
      56: ifnull        94
      59: aload_0
      60: aload         4
      62: getfield      #12                 // Field io/reactivex/rxjava3/internal/operators/observable/ObservableReplay$Node.value:Ljava/lang/Object;
      65: invokevirtual #26                 // Method leaveTransform:(Ljava/lang/Object;)Ljava/lang/Object;
      68: astore        5
      70: aload         5
      72: aload_1
      73: getfield      #27                 // Field io/reactivex/rxjava3/internal/operators/observable/ObservableReplay$InnerDisposable.child:Lio/reactivex/rxjava3/core/Observer;
      76: invokestatic  #28                 // Method io/reactivex/rxjava3/internal/util/NotificationLite.accept:(Ljava/lang/Object;Lio/reactivex/rxjava3/core/Observer;)Z
      79: ifeq          88
      82: aload_1
      83: aconst_null
      84: putfield      #24                 // Field io/reactivex/rxjava3/internal/operators/observable/ObservableReplay$InnerDisposable.index:Ljava/lang/Object;
      87: return
      88: aload         4
      90: astore_3
      91: goto          32
      94: aload_1
      95: aload_3
      96: putfield      #24                 // Field io/reactivex/rxjava3/internal/operators/observable/ObservableReplay$InnerDisposable.index:Ljava/lang/Object;
      99: aload_1
     100: iload_2
     101: ineg
     102: invokevirtual #29                 // Method io/reactivex/rxjava3/internal/operators/observable/ObservableReplay$InnerDisposable.addAndGet:(I)I
     105: istore_2
     106: iload_2
     107: ifne          113
     110: goto          116
     113: goto          10
     116: return

  java.lang.Object enterTransform(java.lang.Object);
    Code:
       0: aload_1
       1: areturn

  java.lang.Object leaveTransform(java.lang.Object);
    Code:
       0: aload_1
       1: areturn

  abstract void truncate();

  void truncateFinal();
    Code:
       0: aload_0
       1: invokevirtual #30                 // Method trimHead:()V
       4: return

  final void collect(java.util.Collection<? super T>);
    Code:
       0: aload_0
       1: invokevirtual #23                 // Method getHead:()Lio/reactivex/rxjava3/internal/operators/observable/ObservableReplay$Node;
       4: astore_2
       5: aload_2
       6: invokevirtual #10                 // Method io/reactivex/rxjava3/internal/operators/observable/ObservableReplay$Node.get:()Ljava/lang/Object;
       9: checkcast     #3                  // class io/reactivex/rxjava3/internal/operators/observable/ObservableReplay$Node
      12: astore_3
      13: aload_3
      14: ifnull        67
      17: aload_3
      18: getfield      #12                 // Field io/reactivex/rxjava3/internal/operators/observable/ObservableReplay$Node.value:Ljava/lang/Object;
      21: astore        4
      23: aload_0
      24: aload         4
      26: invokevirtual #26                 // Method leaveTransform:(Ljava/lang/Object;)Ljava/lang/Object;
      29: astore        5
      31: aload         5
      33: invokestatic  #31                 // Method io/reactivex/rxjava3/internal/util/NotificationLite.isComplete:(Ljava/lang/Object;)Z
      36: ifne          67
      39: aload         5
      41: invokestatic  #32                 // Method io/reactivex/rxjava3/internal/util/NotificationLite.isError:(Ljava/lang/Object;)Z
      44: ifeq          50
      47: goto          67
      50: aload_1
      51: aload         5
      53: invokestatic  #33                 // Method io/reactivex/rxjava3/internal/util/NotificationLite.getValue:(Ljava/lang/Object;)Ljava/lang/Object;
      56: invokeinterface #34,  2           // InterfaceMethod java/util/Collection.add:(Ljava/lang/Object;)Z
      61: pop
      62: aload_3
      63: astore_2
      64: goto          5
      67: return

  boolean hasError();
    Code:
       0: aload_0
       1: getfield      #5                  // Field tail:Lio/reactivex/rxjava3/internal/operators/observable/ObservableReplay$Node;
       4: getfield      #12                 // Field io/reactivex/rxjava3/internal/operators/observable/ObservableReplay$Node.value:Ljava/lang/Object;
       7: ifnull        31
      10: aload_0
      11: aload_0
      12: getfield      #5                  // Field tail:Lio/reactivex/rxjava3/internal/operators/observable/ObservableReplay$Node;
      15: getfield      #12                 // Field io/reactivex/rxjava3/internal/operators/observable/ObservableReplay$Node.value:Ljava/lang/Object;
      18: invokevirtual #26                 // Method leaveTransform:(Ljava/lang/Object;)Ljava/lang/Object;
      21: invokestatic  #32                 // Method io/reactivex/rxjava3/internal/util/NotificationLite.isError:(Ljava/lang/Object;)Z
      24: ifeq          31
      27: iconst_1
      28: goto          32
      31: iconst_0
      32: ireturn

  boolean hasCompleted();
    Code:
       0: aload_0
       1: getfield      #5                  // Field tail:Lio/reactivex/rxjava3/internal/operators/observable/ObservableReplay$Node;
       4: getfield      #12                 // Field io/reactivex/rxjava3/internal/operators/observable/ObservableReplay$Node.value:Ljava/lang/Object;
       7: ifnull        31
      10: aload_0
      11: aload_0
      12: getfield      #5                  // Field tail:Lio/reactivex/rxjava3/internal/operators/observable/ObservableReplay$Node;
      15: getfield      #12                 // Field io/reactivex/rxjava3/internal/operators/observable/ObservableReplay$Node.value:Ljava/lang/Object;
      18: invokevirtual #26                 // Method leaveTransform:(Ljava/lang/Object;)Ljava/lang/Object;
      21: invokestatic  #31                 // Method io/reactivex/rxjava3/internal/util/NotificationLite.isComplete:(Ljava/lang/Object;)Z
      24: ifeq          31
      27: iconst_1
      28: goto          32
      31: iconst_0
      32: ireturn

  io.reactivex.rxjava3.internal.operators.observable.ObservableReplay$Node getHead();
    Code:
       0: aload_0
       1: invokevirtual #9                  // Method get:()Ljava/lang/Object;
       4: checkcast     #3                  // class io/reactivex/rxjava3/internal/operators/observable/ObservableReplay$Node
       7: areturn
}
