Compiled from "ObservableTimeoutTimed.java"
final class io.reactivex.rxjava3.internal.operators.observable.ObservableTimeoutTimed$TimeoutTask implements java.lang.Runnable {
  final io.reactivex.rxjava3.internal.operators.observable.ObservableTimeoutTimed$TimeoutSupport parent;

  final long idx;

  io.reactivex.rxjava3.internal.operators.observable.ObservableTimeoutTimed$TimeoutTask(long, io.reactivex.rxjava3.internal.operators.observable.ObservableTimeoutTimed$TimeoutSupport);
    Code:
       0: aload_0
       1: invokespecial #1                  // Method java/lang/Object."<init>":()V
       4: aload_0
       5: lload_1
       6: putfield      #2                  // Field idx:J
       9: aload_0
      10: aload_3
      11: putfield      #3                  // Field parent:Lio/reactivex/rxjava3/internal/operators/observable/ObservableTimeoutTimed$TimeoutSupport;
      14: return

  public void run();
    Code:
       0: aload_0
       1: getfield      #3                  // Field parent:Lio/reactivex/rxjava3/internal/operators/observable/ObservableTimeoutTimed$TimeoutSupport;
       4: aload_0
       5: getfield      #2                  // Field idx:J
       8: invokeinterface #4,  3            // InterfaceMethod io/reactivex/rxjava3/internal/operators/observable/ObservableTimeoutTimed$TimeoutSupport.onTimeout:(J)V
      13: return
}
