Compiled from "ObservableReplay.java"
final class io.reactivex.rxjava3.internal.operators.observable.ObservableReplay$MulticastReplay<R, U> extends io.reactivex.rxjava3.core.Observable<R> {
  private final io.reactivex.rxjava3.functions.Supplier<? extends io.reactivex.rxjava3.observables.ConnectableObservable<U>> connectableFactory;

  private final io.reactivex.rxjava3.functions.Function<? super io.reactivex.rxjava3.core.Observable<U>, ? extends io.reactivex.rxjava3.core.ObservableSource<R>> selector;

  io.reactivex.rxjava3.internal.operators.observable.ObservableReplay$MulticastReplay(io.reactivex.rxjava3.functions.Supplier<? extends io.reactivex.rxjava3.observables.ConnectableObservable<U>>, io.reactivex.rxjava3.functions.Function<? super io.reactivex.rxjava3.core.Observable<U>, ? extends io.reactivex.rxjava3.core.ObservableSource<R>>);
    Code:
       0: aload_0
       1: invokespecial #1                  // Method io/reactivex/rxjava3/core/Observable."<init>":()V
       4: aload_0
       5: aload_1
       6: putfield      #2                  // Field connectableFactory:Lio/reactivex/rxjava3/functions/Supplier;
       9: aload_0
      10: aload_2
      11: putfield      #3                  // Field selector:Lio/reactivex/rxjava3/functions/Function;
      14: return

  protected void subscribeActual(io.reactivex.rxjava3.core.Observer<? super R>);
    Code:
       0: aload_0
       1: getfield      #2                  // Field connectableFactory:Lio/reactivex/rxjava3/functions/Supplier;
       4: invokeinterface #4,  1            // InterfaceMethod io/reactivex/rxjava3/functions/Supplier.get:()Ljava/lang/Object;
       9: ldc           #5                  // String The connectableFactory returned a null ConnectableObservable
      11: invokestatic  #6                  // Method java/util/Objects.requireNonNull:(Ljava/lang/Object;Ljava/lang/String;)Ljava/lang/Object;
      14: checkcast     #7                  // class io/reactivex/rxjava3/observables/ConnectableObservable
      17: astore_2
      18: aload_0
      19: getfield      #3                  // Field selector:Lio/reactivex/rxjava3/functions/Function;
      22: aload_2
      23: invokeinterface #8,  2            // InterfaceMethod io/reactivex/rxjava3/functions/Function.apply:(Ljava/lang/Object;)Ljava/lang/Object;
      28: ldc           #9                  // String The selector returned a null ObservableSource
      30: invokestatic  #6                  // Method java/util/Objects.requireNonNull:(Ljava/lang/Object;Ljava/lang/String;)Ljava/lang/Object;
      33: checkcast     #10                 // class io/reactivex/rxjava3/core/ObservableSource
      36: astore_3
      37: goto          54
      40: astore        4
      42: aload         4
      44: invokestatic  #12                 // Method io/reactivex/rxjava3/exceptions/Exceptions.throwIfFatal:(Ljava/lang/Throwable;)V
      47: aload         4
      49: aload_1
      50: invokestatic  #13                 // Method io/reactivex/rxjava3/internal/disposables/EmptyDisposable.error:(Ljava/lang/Throwable;Lio/reactivex/rxjava3/core/Observer;)V
      53: return
      54: new           #14                 // class io/reactivex/rxjava3/internal/operators/observable/ObserverResourceWrapper
      57: dup
      58: aload_1
      59: invokespecial #15                 // Method io/reactivex/rxjava3/internal/operators/observable/ObserverResourceWrapper."<init>":(Lio/reactivex/rxjava3/core/Observer;)V
      62: astore        4
      64: aload_3
      65: aload         4
      67: invokeinterface #16,  2           // InterfaceMethod io/reactivex/rxjava3/core/ObservableSource.subscribe:(Lio/reactivex/rxjava3/core/Observer;)V
      72: aload_2
      73: new           #17                 // class io/reactivex/rxjava3/internal/operators/observable/ObservableReplay$DisposeConsumer
      76: dup
      77: aload         4
      79: invokespecial #18                 // Method io/reactivex/rxjava3/internal/operators/observable/ObservableReplay$DisposeConsumer."<init>":(Lio/reactivex/rxjava3/internal/operators/observable/ObserverResourceWrapper;)V
      82: invokevirtual #19                 // Method io/reactivex/rxjava3/observables/ConnectableObservable.connect:(Lio/reactivex/rxjava3/functions/Consumer;)V
      85: return
    Exception table:
       from    to  target type
           0    37    40   Class java/lang/Throwable
}
