Compiled from "ObservableSampleTimed.java"
abstract class io.reactivex.rxjava3.internal.operators.observable.ObservableSampleTimed$SampleTimedObserver<T> extends java.util.concurrent.atomic.AtomicReference<T> implements io.reactivex.rxjava3.core.Observer<T>, io.reactivex.rxjava3.disposables.Disposable, java.lang.Runnable {
  private static final long serialVersionUID;

  final io.reactivex.rxjava3.core.Observer<? super T> downstream;

  final long period;

  final java.util.concurrent.TimeUnit unit;

  final io.reactivex.rxjava3.core.Scheduler scheduler;

  final io.reactivex.rxjava3.functions.Consumer<? super T> onDropped;

  final java.util.concurrent.atomic.AtomicReference<io.reactivex.rxjava3.disposables.Disposable> timer;

  io.reactivex.rxjava3.disposables.Disposable upstream;

  io.reactivex.rxjava3.internal.operators.observable.ObservableSampleTimed$SampleTimedObserver(io.reactivex.rxjava3.core.Observer<? super T>, long, java.util.concurrent.TimeUnit, io.reactivex.rxjava3.core.Scheduler, io.reactivex.rxjava3.functions.Consumer<? super T>);
    Code:
       0: aload_0
       1: invokespecial #1                  // Method java/util/concurrent/atomic/AtomicReference."<init>":()V
       4: aload_0
       5: new           #2                  // class java/util/concurrent/atomic/AtomicReference
       8: dup
       9: invokespecial #1                  // Method java/util/concurrent/atomic/AtomicReference."<init>":()V
      12: putfield      #3                  // Field timer:Ljava/util/concurrent/atomic/AtomicReference;
      15: aload_0
      16: aload_1
      17: putfield      #4                  // Field downstream:Lio/reactivex/rxjava3/core/Observer;
      20: aload_0
      21: lload_2
      22: putfield      #5                  // Field period:J
      25: aload_0
      26: aload         4
      28: putfield      #6                  // Field unit:Ljava/util/concurrent/TimeUnit;
      31: aload_0
      32: aload         5
      34: putfield      #7                  // Field scheduler:Lio/reactivex/rxjava3/core/Scheduler;
      37: aload_0
      38: aload         6
      40: putfield      #8                  // Field onDropped:Lio/reactivex/rxjava3/functions/Consumer;
      43: return

  public void onSubscribe(io.reactivex.rxjava3.disposables.Disposable);
    Code:
       0: aload_0
       1: getfield      #9                  // Field upstream:Lio/reactivex/rxjava3/disposables/Disposable;
       4: aload_1
       5: invokestatic  #10                 // Method io/reactivex/rxjava3/internal/disposables/DisposableHelper.validate:(Lio/reactivex/rxjava3/disposables/Disposable;Lio/reactivex/rxjava3/disposables/Disposable;)Z
       8: ifeq          56
      11: aload_0
      12: aload_1
      13: putfield      #9                  // Field upstream:Lio/reactivex/rxjava3/disposables/Disposable;
      16: aload_0
      17: getfield      #4                  // Field downstream:Lio/reactivex/rxjava3/core/Observer;
      20: aload_0
      21: invokeinterface #11,  2           // InterfaceMethod io/reactivex/rxjava3/core/Observer.onSubscribe:(Lio/reactivex/rxjava3/disposables/Disposable;)V
      26: aload_0
      27: getfield      #7                  // Field scheduler:Lio/reactivex/rxjava3/core/Scheduler;
      30: aload_0
      31: aload_0
      32: getfield      #5                  // Field period:J
      35: aload_0
      36: getfield      #5                  // Field period:J
      39: aload_0
      40: getfield      #6                  // Field unit:Ljava/util/concurrent/TimeUnit;
      43: invokevirtual #12                 // Method io/reactivex/rxjava3/core/Scheduler.schedulePeriodicallyDirect:(Ljava/lang/Runnable;JJLjava/util/concurrent/TimeUnit;)Lio/reactivex/rxjava3/disposables/Disposable;
      46: astore_2
      47: aload_0
      48: getfield      #3                  // Field timer:Ljava/util/concurrent/atomic/AtomicReference;
      51: aload_2
      52: invokestatic  #13                 // Method io/reactivex/rxjava3/internal/disposables/DisposableHelper.replace:(Ljava/util/concurrent/atomic/AtomicReference;Lio/reactivex/rxjava3/disposables/Disposable;)Z
      55: pop
      56: return

  public void onNext(T);
    Code:
       0: aload_0
       1: aload_1
       2: invokevirtual #14                 // Method getAndSet:(Ljava/lang/Object;)Ljava/lang/Object;
       5: astore_2
       6: aload_2
       7: ifnull        58
      10: aload_0
      11: getfield      #8                  // Field onDropped:Lio/reactivex/rxjava3/functions/Consumer;
      14: ifnull        58
      17: aload_0
      18: getfield      #8                  // Field onDropped:Lio/reactivex/rxjava3/functions/Consumer;
      21: aload_2
      22: invokeinterface #15,  2           // InterfaceMethod io/reactivex/rxjava3/functions/Consumer.accept:(Ljava/lang/Object;)V
      27: goto          58
      30: astore_3
      31: aload_3
      32: invokestatic  #17                 // Method io/reactivex/rxjava3/exceptions/Exceptions.throwIfFatal:(Ljava/lang/Throwable;)V
      35: aload_0
      36: invokevirtual #18                 // Method cancelTimer:()V
      39: aload_0
      40: getfield      #9                  // Field upstream:Lio/reactivex/rxjava3/disposables/Disposable;
      43: invokeinterface #19,  1           // InterfaceMethod io/reactivex/rxjava3/disposables/Disposable.dispose:()V
      48: aload_0
      49: getfield      #4                  // Field downstream:Lio/reactivex/rxjava3/core/Observer;
      52: aload_3
      53: invokeinterface #20,  2           // InterfaceMethod io/reactivex/rxjava3/core/Observer.onError:(Ljava/lang/Throwable;)V
      58: return
    Exception table:
       from    to  target type
          17    27    30   Class java/lang/Throwable

  public void onError(java.lang.Throwable);
    Code:
       0: aload_0
       1: invokevirtual #18                 // Method cancelTimer:()V
       4: aload_0
       5: getfield      #4                  // Field downstream:Lio/reactivex/rxjava3/core/Observer;
       8: aload_1
       9: invokeinterface #20,  2           // InterfaceMethod io/reactivex/rxjava3/core/Observer.onError:(Ljava/lang/Throwable;)V
      14: return

  public void onComplete();
    Code:
       0: aload_0
       1: invokevirtual #18                 // Method cancelTimer:()V
       4: aload_0
       5: invokevirtual #21                 // Method complete:()V
       8: return

  void cancelTimer();
    Code:
       0: aload_0
       1: getfield      #3                  // Field timer:Ljava/util/concurrent/atomic/AtomicReference;
       4: invokestatic  #22                 // Method io/reactivex/rxjava3/internal/disposables/DisposableHelper.dispose:(Ljava/util/concurrent/atomic/AtomicReference;)Z
       7: pop
       8: return

  public void dispose();
    Code:
       0: aload_0
       1: invokevirtual #18                 // Method cancelTimer:()V
       4: aload_0
       5: getfield      #9                  // Field upstream:Lio/reactivex/rxjava3/disposables/Disposable;
       8: invokeinterface #19,  1           // InterfaceMethod io/reactivex/rxjava3/disposables/Disposable.dispose:()V
      13: return

  public boolean isDisposed();
    Code:
       0: aload_0
       1: getfield      #9                  // Field upstream:Lio/reactivex/rxjava3/disposables/Disposable;
       4: invokeinterface #23,  1           // InterfaceMethod io/reactivex/rxjava3/disposables/Disposable.isDisposed:()Z
       9: ireturn

  void emit();
    Code:
       0: aload_0
       1: aconst_null
       2: invokevirtual #14                 // Method getAndSet:(Ljava/lang/Object;)Ljava/lang/Object;
       5: astore_1
       6: aload_1
       7: ifnull        20
      10: aload_0
      11: getfield      #4                  // Field downstream:Lio/reactivex/rxjava3/core/Observer;
      14: aload_1
      15: invokeinterface #24,  2           // InterfaceMethod io/reactivex/rxjava3/core/Observer.onNext:(Ljava/lang/Object;)V
      20: return

  abstract void complete();
}
