Compiled from "ObservableOnErrorNext.java"
public final class io.reactivex.rxjava3.internal.operators.observable.ObservableOnErrorNext<T> extends io.reactivex.rxjava3.internal.operators.observable.AbstractObservableWithUpstream<T, T> {
  final io.reactivex.rxjava3.functions.Function<? super java.lang.Throwable, ? extends io.reactivex.rxjava3.core.ObservableSource<? extends T>> nextSupplier;

  public io.reactivex.rxjava3.internal.operators.observable.ObservableOnErrorNext(io.reactivex.rxjava3.core.ObservableSource<T>, io.reactivex.rxjava3.functions.Function<? super java.lang.Throwable, ? extends io.reactivex.rxjava3.core.ObservableSource<? extends T>>);
    Code:
       0: aload_0
       1: aload_1
       2: invokespecial #1                  // Method io/reactivex/rxjava3/internal/operators/observable/AbstractObservableWithUpstream."<init>":(Lio/reactivex/rxjava3/core/ObservableSource;)V
       5: aload_0
       6: aload_2
       7: putfield      #2                  // Field nextSupplier:Lio/reactivex/rxjava3/functions/Function;
      10: return

  public void subscribeActual(io.reactivex.rxjava3.core.Observer<? super T>);
    Code:
       0: new           #3                  // class io/reactivex/rxjava3/internal/operators/observable/ObservableOnErrorNext$OnErrorNextObserver
       3: dup
       4: aload_1
       5: aload_0
       6: getfield      #2                  // Field nextSupplier:Lio/reactivex/rxjava3/functions/Function;
       9: invokespecial #4                  // Method io/reactivex/rxjava3/internal/operators/observable/ObservableOnErrorNext$OnErrorNextObserver."<init>":(Lio/reactivex/rxjava3/core/Observer;Lio/reactivex/rxjava3/functions/Function;)V
      12: astore_2
      13: aload_1
      14: aload_2
      15: getfield      #5                  // Field io/reactivex/rxjava3/internal/operators/observable/ObservableOnErrorNext$OnErrorNextObserver.arbiter:Lio/reactivex/rxjava3/internal/disposables/SequentialDisposable;
      18: invokeinterface #6,  2            // InterfaceMethod io/reactivex/rxjava3/core/Observer.onSubscribe:(Lio/reactivex/rxjava3/disposables/Disposable;)V
      23: aload_0
      24: getfield      #7                  // Field source:Lio/reactivex/rxjava3/core/ObservableSource;
      27: aload_2
      28: invokeinterface #8,  2            // InterfaceMethod io/reactivex/rxjava3/core/ObservableSource.subscribe:(Lio/reactivex/rxjava3/core/Observer;)V
      33: return
}
