Compiled from "ObservableSkipUntil.java"
public final class io.reactivex.rxjava3.internal.operators.observable.ObservableSkipUntil<T, U> extends io.reactivex.rxjava3.internal.operators.observable.AbstractObservableWithUpstream<T, T> {
  final io.reactivex.rxjava3.core.ObservableSource<U> other;

  public io.reactivex.rxjava3.internal.operators.observable.ObservableSkipUntil(io.reactivex.rxjava3.core.ObservableSource<T>, io.reactivex.rxjava3.core.ObservableSource<U>);
    Code:
       0: aload_0
       1: aload_1
       2: invokespecial #1                  // Method io/reactivex/rxjava3/internal/operators/observable/AbstractObservableWithUpstream."<init>":(Lio/reactivex/rxjava3/core/ObservableSource;)V
       5: aload_0
       6: aload_2
       7: putfield      #2                  // Field other:Lio/reactivex/rxjava3/core/ObservableSource;
      10: return

  public void subscribeActual(io.reactivex.rxjava3.core.Observer<? super T>);
    Code:
       0: new           #3                  // class io/reactivex/rxjava3/observers/SerializedObserver
       3: dup
       4: aload_1
       5: invokespecial #4                  // Method io/reactivex/rxjava3/observers/SerializedObserver."<init>":(Lio/reactivex/rxjava3/core/Observer;)V
       8: astore_2
       9: new           #5                  // class io/reactivex/rxjava3/internal/disposables/ArrayCompositeDisposable
      12: dup
      13: iconst_2
      14: invokespecial #6                  // Method io/reactivex/rxjava3/internal/disposables/ArrayCompositeDisposable."<init>":(I)V
      17: astore_3
      18: aload_2
      19: aload_3
      20: invokevirtual #7                  // Method io/reactivex/rxjava3/observers/SerializedObserver.onSubscribe:(Lio/reactivex/rxjava3/disposables/Disposable;)V
      23: new           #8                  // class io/reactivex/rxjava3/internal/operators/observable/ObservableSkipUntil$SkipUntilObserver
      26: dup
      27: aload_2
      28: aload_3
      29: invokespecial #9                  // Method io/reactivex/rxjava3/internal/operators/observable/ObservableSkipUntil$SkipUntilObserver."<init>":(Lio/reactivex/rxjava3/core/Observer;Lio/reactivex/rxjava3/internal/disposables/ArrayCompositeDisposable;)V
      32: astore        4
      34: aload_0
      35: getfield      #2                  // Field other:Lio/reactivex/rxjava3/core/ObservableSource;
      38: new           #10                 // class io/reactivex/rxjava3/internal/operators/observable/ObservableSkipUntil$SkipUntil
      41: dup
      42: aload_0
      43: aload_3
      44: aload         4
      46: aload_2
      47: invokespecial #11                 // Method io/reactivex/rxjava3/internal/operators/observable/ObservableSkipUntil$SkipUntil."<init>":(Lio/reactivex/rxjava3/internal/operators/observable/ObservableSkipUntil;Lio/reactivex/rxjava3/internal/disposables/ArrayCompositeDisposable;Lio/reactivex/rxjava3/internal/operators/observable/ObservableSkipUntil$SkipUntilObserver;Lio/reactivex/rxjava3/observers/SerializedObserver;)V
      50: invokeinterface #12,  2           // InterfaceMethod io/reactivex/rxjava3/core/ObservableSource.subscribe:(Lio/reactivex/rxjava3/core/Observer;)V
      55: aload_0
      56: getfield      #13                 // Field source:Lio/reactivex/rxjava3/core/ObservableSource;
      59: aload         4
      61: invokeinterface #12,  2           // InterfaceMethod io/reactivex/rxjava3/core/ObservableSource.subscribe:(Lio/reactivex/rxjava3/core/Observer;)V
      66: return
}
