Compiled from "ObservableWindowTimed.java"
final class io.reactivex.rxjava3.internal.operators.observable.ObservableWindowTimed$WindowSkipObserver$WindowBoundaryRunnable implements java.lang.Runnable {
  final io.reactivex.rxjava3.internal.operators.observable.ObservableWindowTimed$WindowSkipObserver<?> parent;

  final boolean isOpen;

  io.reactivex.rxjava3.internal.operators.observable.ObservableWindowTimed$WindowSkipObserver$WindowBoundaryRunnable(io.reactivex.rxjava3.internal.operators.observable.ObservableWindowTimed$WindowSkipObserver<?>, boolean);
    Code:
       0: aload_0
       1: invokespecial #1                  // Method java/lang/Object."<init>":()V
       4: aload_0
       5: aload_1
       6: putfield      #2                  // Field parent:Lio/reactivex/rxjava3/internal/operators/observable/ObservableWindowTimed$WindowSkipObserver;
       9: aload_0
      10: iload_2
      11: putfield      #3                  // Field isOpen:Z
      14: return

  public void run();
    Code:
       0: aload_0
       1: getfield      #2                  // Field parent:Lio/reactivex/rxjava3/internal/operators/observable/ObservableWindowTimed$WindowSkipObserver;
       4: aload_0
       5: getfield      #3                  // Field isOpen:Z
       8: invokevirtual #4                  // Method io/reactivex/rxjava3/internal/operators/observable/ObservableWindowTimed$WindowSkipObserver.boundary:(Z)V
      11: return
}
