Compiled from "ObservableReplay.java"
final class io.reactivex.rxjava3.internal.operators.observable.ObservableReplay$UnBoundedFactory implements io.reactivex.rxjava3.internal.operators.observable.ObservableReplay$BufferSupplier<java.lang.Object> {
  io.reactivex.rxjava3.internal.operators.observable.ObservableReplay$UnBoundedFactory();
    Code:
       0: aload_0
       1: invokespecial #1                  // Method java/lang/Object."<init>":()V
       4: return

  public io.reactivex.rxjava3.internal.operators.observable.ObservableReplay$ReplayBuffer<java.lang.Object> call();
    Code:
       0: new           #2                  // class io/reactivex/rxjava3/internal/operators/observable/ObservableReplay$UnboundedReplayBuffer
       3: dup
       4: bipush        16
       6: invokespecial #3                  // Method io/reactivex/rxjava3/internal/operators/observable/ObservableReplay$UnboundedReplayBuffer."<init>":(I)V
       9: areturn
}
