Compiled from "ObservableBuffer.java"
public final class io.reactivex.rxjava3.internal.operators.observable.ObservableBuffer<T, U extends java.util.Collection<? super T>> extends io.reactivex.rxjava3.internal.operators.observable.AbstractObservableWithUpstream<T, U> {
  final int count;

  final int skip;

  final io.reactivex.rxjava3.functions.Supplier<U> bufferSupplier;

  public io.reactivex.rxjava3.internal.operators.observable.ObservableBuffer(io.reactivex.rxjava3.core.ObservableSource<T>, int, int, io.reactivex.rxjava3.functions.Supplier<U>);
    Code:
       0: aload_0
       1: aload_1
       2: invokespecial #1                  // Method io/reactivex/rxjava3/internal/operators/observable/AbstractObservableWithUpstream."<init>":(Lio/reactivex/rxjava3/core/ObservableSource;)V
       5: aload_0
       6: iload_2
       7: putfield      #2                  // Field count:I
      10: aload_0
      11: iload_3
      12: putfield      #3                  // Field skip:I
      15: aload_0
      16: aload         4
      18: putfield      #4                  // Field bufferSupplier:Lio/reactivex/rxjava3/functions/Supplier;
      21: return

  protected void subscribeActual(io.reactivex.rxjava3.core.Observer<? super U>);
    Code:
       0: aload_0
       1: getfield      #3                  // Field skip:I
       4: aload_0
       5: getfield      #2                  // Field count:I
       8: if_icmpne     48
      11: new           #5                  // class io/reactivex/rxjava3/internal/operators/observable/ObservableBuffer$BufferExactObserver
      14: dup
      15: aload_1
      16: aload_0
      17: getfield      #2                  // Field count:I
      20: aload_0
      21: getfield      #4                  // Field bufferSupplier:Lio/reactivex/rxjava3/functions/Supplier;
      24: invokespecial #6                  // Method io/reactivex/rxjava3/internal/operators/observable/ObservableBuffer$BufferExactObserver."<init>":(Lio/reactivex/rxjava3/core/Observer;ILio/reactivex/rxjava3/functions/Supplier;)V
      27: astore_2
      28: aload_2
      29: invokevirtual #7                  // Method io/reactivex/rxjava3/internal/operators/observable/ObservableBuffer$BufferExactObserver.createBuffer:()Z
      32: ifeq          45
      35: aload_0
      36: getfield      #8                  // Field source:Lio/reactivex/rxjava3/core/ObservableSource;
      39: aload_2
      40: invokeinterface #9,  2            // InterfaceMethod io/reactivex/rxjava3/core/ObservableSource.subscribe:(Lio/reactivex/rxjava3/core/Observer;)V
      45: goto          77
      48: aload_0
      49: getfield      #8                  // Field source:Lio/reactivex/rxjava3/core/ObservableSource;
      52: new           #10                 // class io/reactivex/rxjava3/internal/operators/observable/ObservableBuffer$BufferSkipObserver
      55: dup
      56: aload_1
      57: aload_0
      58: getfield      #2                  // Field count:I
      61: aload_0
      62: getfield      #3                  // Field skip:I
      65: aload_0
      66: getfield      #4                  // Field bufferSupplier:Lio/reactivex/rxjava3/functions/Supplier;
      69: invokespecial #11                 // Method io/reactivex/rxjava3/internal/operators/observable/ObservableBuffer$BufferSkipObserver."<init>":(Lio/reactivex/rxjava3/core/Observer;IILio/reactivex/rxjava3/functions/Supplier;)V
      72: invokeinterface #9,  2            // InterfaceMethod io/reactivex/rxjava3/core/ObservableSource.subscribe:(Lio/reactivex/rxjava3/core/Observer;)V
      77: return
}
