Compiled from "ObservableFromUnsafeSource.java"
public final class io.reactivex.rxjava3.internal.operators.observable.ObservableFromUnsafeSource<T> extends io.reactivex.rxjava3.core.Observable<T> {
  final io.reactivex.rxjava3.core.ObservableSource<T> source;

  public io.reactivex.rxjava3.internal.operators.observable.ObservableFromUnsafeSource(io.reactivex.rxjava3.core.ObservableSource<T>);
    Code:
       0: aload_0
       1: invokespecial #1                  // Method io/reactivex/rxjava3/core/Observable."<init>":()V
       4: aload_0
       5: aload_1
       6: putfield      #2                  // Field source:Lio/reactivex/rxjava3/core/ObservableSource;
       9: return

  protected void subscribeActual(io.reactivex.rxjava3.core.Observer<? super T>);
    Code:
       0: aload_0
       1: getfield      #2                  // Field source:Lio/reactivex/rxjava3/core/ObservableSource;
       4: aload_1
       5: invokeinterface #3,  2            // InterfaceMethod io/reactivex/rxjava3/core/ObservableSource.subscribe:(Lio/reactivex/rxjava3/core/Observer;)V
      10: return
}
