Compiled from "ObservableDistinctUntilChanged.java"
public final class io.reactivex.rxjava3.internal.operators.observable.ObservableDistinctUntilChanged<T, K> extends io.reactivex.rxjava3.internal.operators.observable.AbstractObservableWithUpstream<T, T> {
  final io.reactivex.rxjava3.functions.Function<? super T, K> keySelector;

  final io.reactivex.rxjava3.functions.BiPredicate<? super K, ? super K> comparer;

  public io.reactivex.rxjava3.internal.operators.observable.ObservableDistinctUntilChanged(io.reactivex.rxjava3.core.ObservableSource<T>, io.reactivex.rxjava3.functions.Function<? super T, K>, io.reactivex.rxjava3.functions.BiPredicate<? super K, ? super K>);
    Code:
       0: aload_0
       1: aload_1
       2: invokespecial #1                  // Method io/reactivex/rxjava3/internal/operators/observable/AbstractObservableWithUpstream."<init>":(Lio/reactivex/rxjava3/core/ObservableSource;)V
       5: aload_0
       6: aload_2
       7: putfield      #2                  // Field keySelector:Lio/reactivex/rxjava3/functions/Function;
      10: aload_0
      11: aload_3
      12: putfield      #3                  // Field comparer:Lio/reactivex/rxjava3/functions/BiPredicate;
      15: return

  protected void subscribeActual(io.reactivex.rxjava3.core.Observer<? super T>);
    Code:
       0: aload_0
       1: getfield      #4                  // Field source:Lio/reactivex/rxjava3/core/ObservableSource;
       4: new           #5                  // class io/reactivex/rxjava3/internal/operators/observable/ObservableDistinctUntilChanged$DistinctUntilChangedObserver
       7: dup
       8: aload_1
       9: aload_0
      10: getfield      #2                  // Field keySelector:Lio/reactivex/rxjava3/functions/Function;
      13: aload_0
      14: getfield      #3                  // Field comparer:Lio/reactivex/rxjava3/functions/BiPredicate;
      17: invokespecial #6                  // Method io/reactivex/rxjava3/internal/operators/observable/ObservableDistinctUntilChanged$DistinctUntilChangedObserver."<init>":(Lio/reactivex/rxjava3/core/Observer;Lio/reactivex/rxjava3/functions/Function;Lio/reactivex/rxjava3/functions/BiPredicate;)V
      20: invokeinterface #7,  2            // InterfaceMethod io/reactivex/rxjava3/core/ObservableSource.subscribe:(Lio/reactivex/rxjava3/core/Observer;)V
      25: return
}
