Compiled from "ObservableReplay.java"
final class io.reactivex.rxjava3.internal.operators.observable.ObservableReplay$SizeBoundReplayBuffer<T> extends io.reactivex.rxjava3.internal.operators.observable.ObservableReplay$BoundedReplayBuffer<T> {
  private static final long serialVersionUID;

  final int limit;

  io.reactivex.rxjava3.internal.operators.observable.ObservableReplay$SizeBoundReplayBuffer(int, boolean);
    Code:
       0: aload_0
       1: iload_2
       2: invokespecial #1                  // Method io/reactivex/rxjava3/internal/operators/observable/ObservableReplay$BoundedReplayBuffer."<init>":(Z)V
       5: aload_0
       6: iload_1
       7: putfield      #2                  // Field limit:I
      10: return

  void truncate();
    Code:
       0: aload_0
       1: getfield      #3                  // Field size:I
       4: aload_0
       5: getfield      #2                  // Field limit:I
       8: if_icmple     15
      11: aload_0
      12: invokevirtual #4                  // Method removeFirst:()V
      15: return
}
