Compiled from "ObservableInternalHelper.java"
final class io.reactivex.rxjava3.internal.operators.observable.ObservableInternalHelper$ObserverOnError<T> implements io.reactivex.rxjava3.functions.Consumer<java.lang.Throwable> {
  final io.reactivex.rxjava3.core.Observer<T> observer;

  io.reactivex.rxjava3.internal.operators.observable.ObservableInternalHelper$ObserverOnError(io.reactivex.rxjava3.core.Observer<T>);
    Code:
       0: aload_0
       1: invokespecial #1                  // Method java/lang/Object."<init>":()V
       4: aload_0
       5: aload_1
       6: putfield      #2                  // Field observer:Lio/reactivex/rxjava3/core/Observer;
       9: return

  public void accept(java.lang.Throwable);
    Code:
       0: aload_0
       1: getfield      #2                  // Field observer:Lio/reactivex/rxjava3/core/Observer;
       4: aload_1
       5: invokeinterface #3,  2            // InterfaceMethod io/reactivex/rxjava3/core/Observer.onError:(Ljava/lang/Throwable;)V
      10: return

  public void accept(java.lang.Object) throws java.lang.Throwable;
    Code:
       0: aload_0
       1: aload_1
       2: checkcast     #4                  // class java/lang/Throwable
       5: invokevirtual #5                  // Method accept:(Ljava/lang/Throwable;)V
       8: return
}
