Compiled from "ObservableWindowTimed.java"
final class io.reactivex.rxjava3.internal.operators.observable.ObservableWindowTimed$WindowExactUnboundedObserver$WindowRunnable implements java.lang.Runnable {
  final io.reactivex.rxjava3.internal.operators.observable.ObservableWindowTimed$WindowExactUnboundedObserver this$0;

  io.reactivex.rxjava3.internal.operators.observable.ObservableWindowTimed$WindowExactUnboundedObserver$WindowRunnable(io.reactivex.rxjava3.internal.operators.observable.ObservableWindowTimed$WindowExactUnboundedObserver);
    Code:
       0: aload_0
       1: aload_1
       2: putfield      #1                  // Field this$0:Lio/reactivex/rxjava3/internal/operators/observable/ObservableWindowTimed$WindowExactUnboundedObserver;
       5: aload_0
       6: invokespecial #2                  // Method java/lang/Object."<init>":()V
       9: return

  public void run();
    Code:
       0: aload_0
       1: getfield      #1                  // Field this$0:Lio/reactivex/rxjava3/internal/operators/observable/ObservableWindowTimed$WindowExactUnboundedObserver;
       4: invokevirtual #3                  // Method io/reactivex/rxjava3/internal/operators/observable/ObservableWindowTimed$WindowExactUnboundedObserver.windowDone:()V
       7: return
}
