Compiled from "ObservableSampleWithObservable.java"
public final class io.reactivex.rxjava3.internal.operators.observable.ObservableSampleWithObservable<T> extends io.reactivex.rxjava3.internal.operators.observable.AbstractObservableWithUpstream<T, T> {
  final io.reactivex.rxjava3.core.ObservableSource<?> other;

  final boolean emitLast;

  public io.reactivex.rxjava3.internal.operators.observable.ObservableSampleWithObservable(io.reactivex.rxjava3.core.ObservableSource<T>, io.reactivex.rxjava3.core.ObservableSource<?>, boolean);
    Code:
       0: aload_0
       1: aload_1
       2: invokespecial #1                  // Method io/reactivex/rxjava3/internal/operators/observable/AbstractObservableWithUpstream."<init>":(Lio/reactivex/rxjava3/core/ObservableSource;)V
       5: aload_0
       6: aload_2
       7: putfield      #2                  // Field other:Lio/reactivex/rxjava3/core/ObservableSource;
      10: aload_0
      11: iload_3
      12: putfield      #3                  // Field emitLast:Z
      15: return

  public void subscribeActual(io.reactivex.rxjava3.core.Observer<? super T>);
    Code:
       0: new           #4                  // class io/reactivex/rxjava3/observers/SerializedObserver
       3: dup
       4: aload_1
       5: invokespecial #5                  // Method io/reactivex/rxjava3/observers/SerializedObserver."<init>":(Lio/reactivex/rxjava3/core/Observer;)V
       8: astore_2
       9: aload_0
      10: getfield      #3                  // Field emitLast:Z
      13: ifeq          40
      16: aload_0
      17: getfield      #6                  // Field source:Lio/reactivex/rxjava3/core/ObservableSource;
      20: new           #7                  // class io/reactivex/rxjava3/internal/operators/observable/ObservableSampleWithObservable$SampleMainEmitLast
      23: dup
      24: aload_2
      25: aload_0
      26: getfield      #2                  // Field other:Lio/reactivex/rxjava3/core/ObservableSource;
      29: invokespecial #8                  // Method io/reactivex/rxjava3/internal/operators/observable/ObservableSampleWithObservable$SampleMainEmitLast."<init>":(Lio/reactivex/rxjava3/core/Observer;Lio/reactivex/rxjava3/core/ObservableSource;)V
      32: invokeinterface #9,  2            // InterfaceMethod io/reactivex/rxjava3/core/ObservableSource.subscribe:(Lio/reactivex/rxjava3/core/Observer;)V
      37: goto          61
      40: aload_0
      41: getfield      #6                  // Field source:Lio/reactivex/rxjava3/core/ObservableSource;
      44: new           #10                 // class io/reactivex/rxjava3/internal/operators/observable/ObservableSampleWithObservable$SampleMainNoLast
      47: dup
      48: aload_2
      49: aload_0
      50: getfield      #2                  // Field other:Lio/reactivex/rxjava3/core/ObservableSource;
      53: invokespecial #11                 // Method io/reactivex/rxjava3/internal/operators/observable/ObservableSampleWithObservable$SampleMainNoLast."<init>":(Lio/reactivex/rxjava3/core/Observer;Lio/reactivex/rxjava3/core/ObservableSource;)V
      56: invokeinterface #9,  2            // InterfaceMethod io/reactivex/rxjava3/core/ObservableSource.subscribe:(Lio/reactivex/rxjava3/core/Observer;)V
      61: return
}
