Compiled from "ObservableTimeout.java"
final class io.reactivex.rxjava3.internal.operators.observable.ObservableTimeout$TimeoutFallbackObserver<T> extends java.util.concurrent.atomic.AtomicReference<io.reactivex.rxjava3.disposables.Disposable> implements io.reactivex.rxjava3.core.Observer<T>, io.reactivex.rxjava3.disposables.Disposable, io.reactivex.rxjava3.internal.operators.observable.ObservableTimeout$TimeoutSelectorSupport {
  private static final long serialVersionUID;

  final io.reactivex.rxjava3.core.Observer<? super T> downstream;

  final io.reactivex.rxjava3.functions.Function<? super T, ? extends io.reactivex.rxjava3.core.ObservableSource<?>> itemTimeoutIndicator;

  final io.reactivex.rxjava3.internal.disposables.SequentialDisposable task;

  final java.util.concurrent.atomic.AtomicLong index;

  final java.util.concurrent.atomic.AtomicReference<io.reactivex.rxjava3.disposables.Disposable> upstream;

  io.reactivex.rxjava3.core.ObservableSource<? extends T> fallback;

  io.reactivex.rxjava3.internal.operators.observable.ObservableTimeout$TimeoutFallbackObserver(io.reactivex.rxjava3.core.Observer<? super T>, io.reactivex.rxjava3.functions.Function<? super T, ? extends io.reactivex.rxjava3.core.ObservableSource<?>>, io.reactivex.rxjava3.core.ObservableSource<? extends T>);
    Code:
       0: aload_0
       1: invokespecial #1                  // Method java/util/concurrent/atomic/AtomicReference."<init>":()V
       4: aload_0
       5: aload_1
       6: putfield      #2                  // Field downstream:Lio/reactivex/rxjava3/core/Observer;
       9: aload_0
      10: aload_2
      11: putfield      #3                  // Field itemTimeoutIndicator:Lio/reactivex/rxjava3/functions/Function;
      14: aload_0
      15: new           #4                  // class io/reactivex/rxjava3/internal/disposables/SequentialDisposable
      18: dup
      19: invokespecial #5                  // Method io/reactivex/rxjava3/internal/disposables/SequentialDisposable."<init>":()V
      22: putfield      #6                  // Field task:Lio/reactivex/rxjava3/internal/disposables/SequentialDisposable;
      25: aload_0
      26: aload_3
      27: putfield      #7                  // Field fallback:Lio/reactivex/rxjava3/core/ObservableSource;
      30: aload_0
      31: new           #8                  // class java/util/concurrent/atomic/AtomicLong
      34: dup
      35: invokespecial #9                  // Method java/util/concurrent/atomic/AtomicLong."<init>":()V
      38: putfield      #10                 // Field index:Ljava/util/concurrent/atomic/AtomicLong;
      41: aload_0
      42: new           #11                 // class java/util/concurrent/atomic/AtomicReference
      45: dup
      46: invokespecial #1                  // Method java/util/concurrent/atomic/AtomicReference."<init>":()V
      49: putfield      #12                 // Field upstream:Ljava/util/concurrent/atomic/AtomicReference;
      52: return

  public void onSubscribe(io.reactivex.rxjava3.disposables.Disposable);
    Code:
       0: aload_0
       1: getfield      #12                 // Field upstream:Ljava/util/concurrent/atomic/AtomicReference;
       4: aload_1
       5: invokestatic  #13                 // Method io/reactivex/rxjava3/internal/disposables/DisposableHelper.setOnce:(Ljava/util/concurrent/atomic/AtomicReference;Lio/reactivex/rxjava3/disposables/Disposable;)Z
       8: pop
       9: return

  public void onNext(T);
    Code:
       0: aload_0
       1: getfield      #10                 // Field index:Ljava/util/concurrent/atomic/AtomicLong;
       4: invokevirtual #14                 // Method java/util/concurrent/atomic/AtomicLong.get:()J
       7: lstore_2
       8: lload_2
       9: ldc2_w        #16                 // long 9223372036854775807l
      12: lcmp
      13: ifeq          30
      16: aload_0
      17: getfield      #10                 // Field index:Ljava/util/concurrent/atomic/AtomicLong;
      20: lload_2
      21: lload_2
      22: lconst_1
      23: ladd
      24: invokevirtual #18                 // Method java/util/concurrent/atomic/AtomicLong.compareAndSet:(JJ)Z
      27: ifne          31
      30: return
      31: aload_0
      32: getfield      #6                  // Field task:Lio/reactivex/rxjava3/internal/disposables/SequentialDisposable;
      35: invokevirtual #19                 // Method io/reactivex/rxjava3/internal/disposables/SequentialDisposable.get:()Ljava/lang/Object;
      38: checkcast     #20                 // class io/reactivex/rxjava3/disposables/Disposable
      41: astore        4
      43: aload         4
      45: ifnull        55
      48: aload         4
      50: invokeinterface #21,  1           // InterfaceMethod io/reactivex/rxjava3/disposables/Disposable.dispose:()V
      55: aload_0
      56: getfield      #2                  // Field downstream:Lio/reactivex/rxjava3/core/Observer;
      59: aload_1
      60: invokeinterface #22,  2           // InterfaceMethod io/reactivex/rxjava3/core/Observer.onNext:(Ljava/lang/Object;)V
      65: aload_0
      66: getfield      #3                  // Field itemTimeoutIndicator:Lio/reactivex/rxjava3/functions/Function;
      69: aload_1
      70: invokeinterface #23,  2           // InterfaceMethod io/reactivex/rxjava3/functions/Function.apply:(Ljava/lang/Object;)Ljava/lang/Object;
      75: ldc           #24                 // String The itemTimeoutIndicator returned a null ObservableSource.
      77: invokestatic  #25                 // Method java/util/Objects.requireNonNull:(Ljava/lang/Object;Ljava/lang/String;)Ljava/lang/Object;
      80: checkcast     #26                 // class io/reactivex/rxjava3/core/ObservableSource
      83: astore        5
      85: goto          133
      88: astore        6
      90: aload         6
      92: invokestatic  #28                 // Method io/reactivex/rxjava3/exceptions/Exceptions.throwIfFatal:(Ljava/lang/Throwable;)V
      95: aload_0
      96: getfield      #12                 // Field upstream:Ljava/util/concurrent/atomic/AtomicReference;
      99: invokevirtual #29                 // Method java/util/concurrent/atomic/AtomicReference.get:()Ljava/lang/Object;
     102: checkcast     #20                 // class io/reactivex/rxjava3/disposables/Disposable
     105: invokeinterface #21,  1           // InterfaceMethod io/reactivex/rxjava3/disposables/Disposable.dispose:()V
     110: aload_0
     111: getfield      #10                 // Field index:Ljava/util/concurrent/atomic/AtomicLong;
     114: ldc2_w        #16                 // long 9223372036854775807l
     117: invokevirtual #30                 // Method java/util/concurrent/atomic/AtomicLong.getAndSet:(J)J
     120: pop2
     121: aload_0
     122: getfield      #2                  // Field downstream:Lio/reactivex/rxjava3/core/Observer;
     125: aload         6
     127: invokeinterface #31,  2           // InterfaceMethod io/reactivex/rxjava3/core/Observer.onError:(Ljava/lang/Throwable;)V
     132: return
     133: new           #32                 // class io/reactivex/rxjava3/internal/operators/observable/ObservableTimeout$TimeoutConsumer
     136: dup
     137: lload_2
     138: lconst_1
     139: ladd
     140: aload_0
     141: invokespecial #33                 // Method io/reactivex/rxjava3/internal/operators/observable/ObservableTimeout$TimeoutConsumer."<init>":(JLio/reactivex/rxjava3/internal/operators/observable/ObservableTimeout$TimeoutSelectorSupport;)V
     144: astore        6
     146: aload_0
     147: getfield      #6                  // Field task:Lio/reactivex/rxjava3/internal/disposables/SequentialDisposable;
     150: aload         6
     152: invokevirtual #34                 // Method io/reactivex/rxjava3/internal/disposables/SequentialDisposable.replace:(Lio/reactivex/rxjava3/disposables/Disposable;)Z
     155: ifeq          167
     158: aload         5
     160: aload         6
     162: invokeinterface #35,  2           // InterfaceMethod io/reactivex/rxjava3/core/ObservableSource.subscribe:(Lio/reactivex/rxjava3/core/Observer;)V
     167: return
    Exception table:
       from    to  target type
          65    85    88   Class java/lang/Throwable

  void startFirstTimeout(io.reactivex.rxjava3.core.ObservableSource<?>);
    Code:
       0: aload_1
       1: ifnull        32
       4: new           #32                 // class io/reactivex/rxjava3/internal/operators/observable/ObservableTimeout$TimeoutConsumer
       7: dup
       8: lconst_0
       9: aload_0
      10: invokespecial #33                 // Method io/reactivex/rxjava3/internal/operators/observable/ObservableTimeout$TimeoutConsumer."<init>":(JLio/reactivex/rxjava3/internal/operators/observable/ObservableTimeout$TimeoutSelectorSupport;)V
      13: astore_2
      14: aload_0
      15: getfield      #6                  // Field task:Lio/reactivex/rxjava3/internal/disposables/SequentialDisposable;
      18: aload_2
      19: invokevirtual #34                 // Method io/reactivex/rxjava3/internal/disposables/SequentialDisposable.replace:(Lio/reactivex/rxjava3/disposables/Disposable;)Z
      22: ifeq          32
      25: aload_1
      26: aload_2
      27: invokeinterface #35,  2           // InterfaceMethod io/reactivex/rxjava3/core/ObservableSource.subscribe:(Lio/reactivex/rxjava3/core/Observer;)V
      32: return

  public void onError(java.lang.Throwable);
    Code:
       0: aload_0
       1: getfield      #10                 // Field index:Ljava/util/concurrent/atomic/AtomicLong;
       4: ldc2_w        #16                 // long 9223372036854775807l
       7: invokevirtual #30                 // Method java/util/concurrent/atomic/AtomicLong.getAndSet:(J)J
      10: ldc2_w        #16                 // long 9223372036854775807l
      13: lcmp
      14: ifeq          44
      17: aload_0
      18: getfield      #6                  // Field task:Lio/reactivex/rxjava3/internal/disposables/SequentialDisposable;
      21: invokevirtual #36                 // Method io/reactivex/rxjava3/internal/disposables/SequentialDisposable.dispose:()V
      24: aload_0
      25: getfield      #2                  // Field downstream:Lio/reactivex/rxjava3/core/Observer;
      28: aload_1
      29: invokeinterface #31,  2           // InterfaceMethod io/reactivex/rxjava3/core/Observer.onError:(Ljava/lang/Throwable;)V
      34: aload_0
      35: getfield      #6                  // Field task:Lio/reactivex/rxjava3/internal/disposables/SequentialDisposable;
      38: invokevirtual #36                 // Method io/reactivex/rxjava3/internal/disposables/SequentialDisposable.dispose:()V
      41: goto          48
      44: aload_1
      45: invokestatic  #37                 // Method io/reactivex/rxjava3/plugins/RxJavaPlugins.onError:(Ljava/lang/Throwable;)V
      48: return

  public void onComplete();
    Code:
       0: aload_0
       1: getfield      #10                 // Field index:Ljava/util/concurrent/atomic/AtomicLong;
       4: ldc2_w        #16                 // long 9223372036854775807l
       7: invokevirtual #30                 // Method java/util/concurrent/atomic/AtomicLong.getAndSet:(J)J
      10: ldc2_w        #16                 // long 9223372036854775807l
      13: lcmp
      14: ifeq          40
      17: aload_0
      18: getfield      #6                  // Field task:Lio/reactivex/rxjava3/internal/disposables/SequentialDisposable;
      21: invokevirtual #36                 // Method io/reactivex/rxjava3/internal/disposables/SequentialDisposable.dispose:()V
      24: aload_0
      25: getfield      #2                  // Field downstream:Lio/reactivex/rxjava3/core/Observer;
      28: invokeinterface #38,  1           // InterfaceMethod io/reactivex/rxjava3/core/Observer.onComplete:()V
      33: aload_0
      34: getfield      #6                  // Field task:Lio/reactivex/rxjava3/internal/disposables/SequentialDisposable;
      37: invokevirtual #36                 // Method io/reactivex/rxjava3/internal/disposables/SequentialDisposable.dispose:()V
      40: return

  public void onTimeout(long);
    Code:
       0: aload_0
       1: getfield      #10                 // Field index:Ljava/util/concurrent/atomic/AtomicLong;
       4: lload_1
       5: ldc2_w        #16                 // long 9223372036854775807l
       8: invokevirtual #18                 // Method java/util/concurrent/atomic/AtomicLong.compareAndSet:(JJ)Z
      11: ifeq          50
      14: aload_0
      15: getfield      #12                 // Field upstream:Ljava/util/concurrent/atomic/AtomicReference;
      18: invokestatic  #39                 // Method io/reactivex/rxjava3/internal/disposables/DisposableHelper.dispose:(Ljava/util/concurrent/atomic/AtomicReference;)Z
      21: pop
      22: aload_0
      23: getfield      #7                  // Field fallback:Lio/reactivex/rxjava3/core/ObservableSource;
      26: astore_3
      27: aload_0
      28: aconst_null
      29: putfield      #7                  // Field fallback:Lio/reactivex/rxjava3/core/ObservableSource;
      32: aload_3
      33: new           #40                 // class io/reactivex/rxjava3/internal/operators/observable/ObservableTimeoutTimed$FallbackObserver
      36: dup
      37: aload_0
      38: getfield      #2                  // Field downstream:Lio/reactivex/rxjava3/core/Observer;
      41: aload_0
      42: invokespecial #41                 // Method io/reactivex/rxjava3/internal/operators/observable/ObservableTimeoutTimed$FallbackObserver."<init>":(Lio/reactivex/rxjava3/core/Observer;Ljava/util/concurrent/atomic/AtomicReference;)V
      45: invokeinterface #35,  2           // InterfaceMethod io/reactivex/rxjava3/core/ObservableSource.subscribe:(Lio/reactivex/rxjava3/core/Observer;)V
      50: return

  public void onTimeoutError(long, java.lang.Throwable);
    Code:
       0: aload_0
       1: getfield      #10                 // Field index:Ljava/util/concurrent/atomic/AtomicLong;
       4: lload_1
       5: ldc2_w        #16                 // long 9223372036854775807l
       8: invokevirtual #18                 // Method java/util/concurrent/atomic/AtomicLong.compareAndSet:(JJ)Z
      11: ifeq          32
      14: aload_0
      15: invokestatic  #39                 // Method io/reactivex/rxjava3/internal/disposables/DisposableHelper.dispose:(Ljava/util/concurrent/atomic/AtomicReference;)Z
      18: pop
      19: aload_0
      20: getfield      #2                  // Field downstream:Lio/reactivex/rxjava3/core/Observer;
      23: aload_3
      24: invokeinterface #31,  2           // InterfaceMethod io/reactivex/rxjava3/core/Observer.onError:(Ljava/lang/Throwable;)V
      29: goto          36
      32: aload_3
      33: invokestatic  #37                 // Method io/reactivex/rxjava3/plugins/RxJavaPlugins.onError:(Ljava/lang/Throwable;)V
      36: return

  public void dispose();
    Code:
       0: aload_0
       1: getfield      #12                 // Field upstream:Ljava/util/concurrent/atomic/AtomicReference;
       4: invokestatic  #39                 // Method io/reactivex/rxjava3/internal/disposables/DisposableHelper.dispose:(Ljava/util/concurrent/atomic/AtomicReference;)Z
       7: pop
       8: aload_0
       9: invokestatic  #39                 // Method io/reactivex/rxjava3/internal/disposables/DisposableHelper.dispose:(Ljava/util/concurrent/atomic/AtomicReference;)Z
      12: pop
      13: aload_0
      14: getfield      #6                  // Field task:Lio/reactivex/rxjava3/internal/disposables/SequentialDisposable;
      17: invokevirtual #36                 // Method io/reactivex/rxjava3/internal/disposables/SequentialDisposable.dispose:()V
      20: return

  public boolean isDisposed();
    Code:
       0: aload_0
       1: invokevirtual #42                 // Method get:()Ljava/lang/Object;
       4: checkcast     #20                 // class io/reactivex/rxjava3/disposables/Disposable
       7: invokestatic  #43                 // Method io/reactivex/rxjava3/internal/disposables/DisposableHelper.isDisposed:(Lio/reactivex/rxjava3/disposables/Disposable;)Z
      10: ireturn
}
