Compiled from "ObservablePublishSelector.java"
final class io.reactivex.rxjava3.internal.operators.observable.ObservablePublishSelector$SourceObserver<T> implements io.reactivex.rxjava3.core.Observer<T> {
  final io.reactivex.rxjava3.subjects.PublishSubject<T> subject;

  final java.util.concurrent.atomic.AtomicReference<io.reactivex.rxjava3.disposables.Disposable> target;

  io.reactivex.rxjava3.internal.operators.observable.ObservablePublishSelector$SourceObserver(io.reactivex.rxjava3.subjects.PublishSubject<T>, java.util.concurrent.atomic.AtomicReference<io.reactivex.rxjava3.disposables.Disposable>);
    Code:
       0: aload_0
       1: invokespecial #1                  // Method java/lang/Object."<init>":()V
       4: aload_0
       5: aload_1
       6: putfield      #2                  // Field subject:Lio/reactivex/rxjava3/subjects/PublishSubject;
       9: aload_0
      10: aload_2
      11: putfield      #3                  // Field target:Ljava/util/concurrent/atomic/AtomicReference;
      14: return

  public void onSubscribe(io.reactivex.rxjava3.disposables.Disposable);
    Code:
       0: aload_0
       1: getfield      #3                  // Field target:Ljava/util/concurrent/atomic/AtomicReference;
       4: aload_1
       5: invokestatic  #4                  // Method io/reactivex/rxjava3/internal/disposables/DisposableHelper.setOnce:(Ljava/util/concurrent/atomic/AtomicReference;Lio/reactivex/rxjava3/disposables/Disposable;)Z
       8: pop
       9: return

  public void onNext(T);
    Code:
       0: aload_0
       1: getfield      #2                  // Field subject:Lio/reactivex/rxjava3/subjects/PublishSubject;
       4: aload_1
       5: invokevirtual #5                  // Method io/reactivex/rxjava3/subjects/PublishSubject.onNext:(Ljava/lang/Object;)V
       8: return

  public void onError(java.lang.Throwable);
    Code:
       0: aload_0
       1: getfield      #2                  // Field subject:Lio/reactivex/rxjava3/subjects/PublishSubject;
       4: aload_1
       5: invokevirtual #6                  // Method io/reactivex/rxjava3/subjects/PublishSubject.onError:(Ljava/lang/Throwable;)V
       8: return

  public void onComplete();
    Code:
       0: aload_0
       1: getfield      #2                  // Field subject:Lio/reactivex/rxjava3/subjects/PublishSubject;
       4: invokevirtual #7                  // Method io/reactivex/rxjava3/subjects/PublishSubject.onComplete:()V
       7: return
}
