Compiled from "ObservableInternalHelper.java"
final class io.reactivex.rxjava3.internal.operators.observable.ObservableInternalHelper$ItemDelayFunction<T, U> implements io.reactivex.rxjava3.functions.Function<T, io.reactivex.rxjava3.core.ObservableSource<T>> {
  final io.reactivex.rxjava3.functions.Function<? super T, ? extends io.reactivex.rxjava3.core.ObservableSource<U>> itemDelay;

  io.reactivex.rxjava3.internal.operators.observable.ObservableInternalHelper$ItemDelayFunction(io.reactivex.rxjava3.functions.Function<? super T, ? extends io.reactivex.rxjava3.core.ObservableSource<U>>);
    Code:
       0: aload_0
       1: invokespecial #1                  // Method java/lang/Object."<init>":()V
       4: aload_0
       5: aload_1
       6: putfield      #2                  // Field itemDelay:Lio/reactivex/rxjava3/functions/Function;
       9: return

  public io.reactivex.rxjava3.core.ObservableSource<T> apply(T) throws java.lang.Throwable;
    Code:
       0: aload_0
       1: getfield      #2                  // Field itemDelay:Lio/reactivex/rxjava3/functions/Function;
       4: aload_1
       5: invokeinterface #3,  2            // InterfaceMethod io/reactivex/rxjava3/functions/Function.apply:(Ljava/lang/Object;)Ljava/lang/Object;
      10: ldc           #4                  // String The itemDelay returned a null ObservableSource
      12: invokestatic  #5                  // Method java/util/Objects.requireNonNull:(Ljava/lang/Object;Ljava/lang/String;)Ljava/lang/Object;
      15: checkcast     #6                  // class io/reactivex/rxjava3/core/ObservableSource
      18: astore_2
      19: new           #7                  // class io/reactivex/rxjava3/internal/operators/observable/ObservableTake
      22: dup
      23: aload_2
      24: lconst_1
      25: invokespecial #8                  // Method io/reactivex/rxjava3/internal/operators/observable/ObservableTake."<init>":(Lio/reactivex/rxjava3/core/ObservableSource;J)V
      28: aload_1
      29: invokestatic  #9                  // Method io/reactivex/rxjava3/internal/functions/Functions.justFunction:(Ljava/lang/Object;)Lio/reactivex/rxjava3/functions/Function;
      32: invokevirtual #10                 // Method io/reactivex/rxjava3/internal/operators/observable/ObservableTake.map:(Lio/reactivex/rxjava3/functions/Function;)Lio/reactivex/rxjava3/core/Observable;
      35: aload_1
      36: invokevirtual #11                 // Method io/reactivex/rxjava3/core/Observable.defaultIfEmpty:(Ljava/lang/Object;)Lio/reactivex/rxjava3/core/Observable;
      39: areturn

  public java.lang.Object apply(java.lang.Object) throws java.lang.Throwable;
    Code:
       0: aload_0
       1: aload_1
       2: invokevirtual #12                 // Method apply:(Ljava/lang/Object;)Lio/reactivex/rxjava3/core/ObservableSource;
       5: areturn
}
