Compiled from "ObservableZipIterable.java"
public final class io.reactivex.rxjava3.internal.operators.observable.ObservableZipIterable<T, U, V> extends io.reactivex.rxjava3.core.Observable<V> {
  final io.reactivex.rxjava3.core.Observable<? extends T> source;

  final java.lang.Iterable<U> other;

  final io.reactivex.rxjava3.functions.BiFunction<? super T, ? super U, ? extends V> zipper;

  public io.reactivex.rxjava3.internal.operators.observable.ObservableZipIterable(io.reactivex.rxjava3.core.Observable<? extends T>, java.lang.Iterable<U>, io.reactivex.rxjava3.functions.BiFunction<? super T, ? super U, ? extends V>);
    Code:
       0: aload_0
       1: invokespecial #1                  // Method io/reactivex/rxjava3/core/Observable."<init>":()V
       4: aload_0
       5: aload_1
       6: putfield      #2                  // Field source:Lio/reactivex/rxjava3/core/Observable;
       9: aload_0
      10: aload_2
      11: putfield      #3                  // Field other:Ljava/lang/Iterable;
      14: aload_0
      15: aload_3
      16: putfield      #4                  // Field zipper:Lio/reactivex/rxjava3/functions/BiFunction;
      19: return

  public void subscribeActual(io.reactivex.rxjava3.core.Observer<? super V>);
    Code:
       0: aload_0
       1: getfield      #3                  // Field other:Ljava/lang/Iterable;
       4: invokeinterface #5,  1            // InterfaceMethod java/lang/Iterable.iterator:()Ljava/util/Iterator;
       9: ldc           #6                  // String The iterator returned by other is null
      11: invokestatic  #7                  // Method java/util/Objects.requireNonNull:(Ljava/lang/Object;Ljava/lang/String;)Ljava/lang/Object;
      14: checkcast     #8                  // class java/util/Iterator
      17: astore_2
      18: goto          32
      21: astore_3
      22: aload_3
      23: invokestatic  #10                 // Method io/reactivex/rxjava3/exceptions/Exceptions.throwIfFatal:(Ljava/lang/Throwable;)V
      26: aload_3
      27: aload_1
      28: invokestatic  #11                 // Method io/reactivex/rxjava3/internal/disposables/EmptyDisposable.error:(Ljava/lang/Throwable;Lio/reactivex/rxjava3/core/Observer;)V
      31: return
      32: aload_2
      33: invokeinterface #12,  1           // InterfaceMethod java/util/Iterator.hasNext:()Z
      38: istore_3
      39: goto          56
      42: astore        4
      44: aload         4
      46: invokestatic  #10                 // Method io/reactivex/rxjava3/exceptions/Exceptions.throwIfFatal:(Ljava/lang/Throwable;)V
      49: aload         4
      51: aload_1
      52: invokestatic  #11                 // Method io/reactivex/rxjava3/internal/disposables/EmptyDisposable.error:(Ljava/lang/Throwable;Lio/reactivex/rxjava3/core/Observer;)V
      55: return
      56: iload_3
      57: ifne          65
      60: aload_1
      61: invokestatic  #13                 // Method io/reactivex/rxjava3/internal/disposables/EmptyDisposable.complete:(Lio/reactivex/rxjava3/core/Observer;)V
      64: return
      65: aload_0
      66: getfield      #2                  // Field source:Lio/reactivex/rxjava3/core/Observable;
      69: new           #14                 // class io/reactivex/rxjava3/internal/operators/observable/ObservableZipIterable$ZipIterableObserver
      72: dup
      73: aload_1
      74: aload_2
      75: aload_0
      76: getfield      #4                  // Field zipper:Lio/reactivex/rxjava3/functions/BiFunction;
      79: invokespecial #15                 // Method io/reactivex/rxjava3/internal/operators/observable/ObservableZipIterable$ZipIterableObserver."<init>":(Lio/reactivex/rxjava3/core/Observer;Ljava/util/Iterator;Lio/reactivex/rxjava3/functions/BiFunction;)V
      82: invokevirtual #16                 // Method io/reactivex/rxjava3/core/Observable.subscribe:(Lio/reactivex/rxjava3/core/Observer;)V
      85: return
    Exception table:
       from    to  target type
           0    18    21   Class java/lang/Throwable
          32    39    42   Class java/lang/Throwable
}
