Compiled from "ObservableRetryWhen.java"
final class io.reactivex.rxjava3.internal.operators.observable.ObservableRetryWhen$RepeatWhenObserver$InnerRepeatObserver extends java.util.concurrent.atomic.AtomicReference<io.reactivex.rxjava3.disposables.Disposable> implements io.reactivex.rxjava3.core.Observer<java.lang.Object> {
  private static final long serialVersionUID;

  final io.reactivex.rxjava3.internal.operators.observable.ObservableRetryWhen$RepeatWhenObserver this$0;

  io.reactivex.rxjava3.internal.operators.observable.ObservableRetryWhen$RepeatWhenObserver$InnerRepeatObserver(io.reactivex.rxjava3.internal.operators.observable.ObservableRetryWhen$RepeatWhenObserver);
    Code:
       0: aload_0
       1: aload_1
       2: putfield      #1                  // Field this$0:Lio/reactivex/rxjava3/internal/operators/observable/ObservableRetryWhen$RepeatWhenObserver;
       5: aload_0
       6: invokespecial #2                  // Method java/util/concurrent/atomic/AtomicReference."<init>":()V
       9: return

  public void onSubscribe(io.reactivex.rxjava3.disposables.Disposable);
    Code:
       0: aload_0
       1: aload_1
       2: invokestatic  #3                  // Method io/reactivex/rxjava3/internal/disposables/DisposableHelper.setOnce:(Ljava/util/concurrent/atomic/AtomicReference;Lio/reactivex/rxjava3/disposables/Disposable;)Z
       5: pop
       6: return

  public void onNext(java.lang.Object);
    Code:
       0: aload_0
       1: getfield      #1                  // Field this$0:Lio/reactivex/rxjava3/internal/operators/observable/ObservableRetryWhen$RepeatWhenObserver;
       4: invokevirtual #4                  // Method io/reactivex/rxjava3/internal/operators/observable/ObservableRetryWhen$RepeatWhenObserver.innerNext:()V
       7: return

  public void onError(java.lang.Throwable);
    Code:
       0: aload_0
       1: getfield      #1                  // Field this$0:Lio/reactivex/rxjava3/internal/operators/observable/ObservableRetryWhen$RepeatWhenObserver;
       4: aload_1
       5: invokevirtual #5                  // Method io/reactivex/rxjava3/internal/operators/observable/ObservableRetryWhen$RepeatWhenObserver.innerError:(Ljava/lang/Throwable;)V
       8: return

  public void onComplete();
    Code:
       0: aload_0
       1: getfield      #1                  // Field this$0:Lio/reactivex/rxjava3/internal/operators/observable/ObservableRetryWhen$RepeatWhenObserver;
       4: invokevirtual #6                  // Method io/reactivex/rxjava3/internal/operators/observable/ObservableRetryWhen$RepeatWhenObserver.innerComplete:()V
       7: return
}
