Compiled from "ObservableSampleTimed.java"
public final class io.reactivex.rxjava3.internal.operators.observable.ObservableSampleTimed<T> extends io.reactivex.rxjava3.internal.operators.observable.AbstractObservableWithUpstream<T, T> {
  final long period;

  final java.util.concurrent.TimeUnit unit;

  final io.reactivex.rxjava3.core.Scheduler scheduler;

  final io.reactivex.rxjava3.functions.Consumer<? super T> onDropped;

  final boolean emitLast;

  public io.reactivex.rxjava3.internal.operators.observable.ObservableSampleTimed(io.reactivex.rxjava3.core.ObservableSource<T>, long, java.util.concurrent.TimeUnit, io.reactivex.rxjava3.core.Scheduler, boolean, io.reactivex.rxjava3.functions.Consumer<? super T>);
    Code:
       0: aload_0
       1: aload_1
       2: invokespecial #1                  // Method io/reactivex/rxjava3/internal/operators/observable/AbstractObservableWithUpstream."<init>":(Lio/reactivex/rxjava3/core/ObservableSource;)V
       5: aload_0
       6: lload_2
       7: putfield      #2                  // Field period:J
      10: aload_0
      11: aload         4
      13: putfield      #3                  // Field unit:Ljava/util/concurrent/TimeUnit;
      16: aload_0
      17: aload         5
      19: putfield      #4                  // Field scheduler:Lio/reactivex/rxjava3/core/Scheduler;
      22: aload_0
      23: iload         6
      25: putfield      #5                  // Field emitLast:Z
      28: aload_0
      29: aload         7
      31: putfield      #6                  // Field onDropped:Lio/reactivex/rxjava3/functions/Consumer;
      34: return

  public void subscribeActual(io.reactivex.rxjava3.core.Observer<? super T>);
    Code:
       0: new           #7                  // class io/reactivex/rxjava3/observers/SerializedObserver
       3: dup
       4: aload_1
       5: invokespecial #8                  // Method io/reactivex/rxjava3/observers/SerializedObserver."<init>":(Lio/reactivex/rxjava3/core/Observer;)V
       8: astore_2
       9: aload_0
      10: getfield      #5                  // Field emitLast:Z
      13: ifeq          52
      16: aload_0
      17: getfield      #9                  // Field source:Lio/reactivex/rxjava3/core/ObservableSource;
      20: new           #10                 // class io/reactivex/rxjava3/internal/operators/observable/ObservableSampleTimed$SampleTimedEmitLast
      23: dup
      24: aload_2
      25: aload_0
      26: getfield      #2                  // Field period:J
      29: aload_0
      30: getfield      #3                  // Field unit:Ljava/util/concurrent/TimeUnit;
      33: aload_0
      34: getfield      #4                  // Field scheduler:Lio/reactivex/rxjava3/core/Scheduler;
      37: aload_0
      38: getfield      #6                  // Field onDropped:Lio/reactivex/rxjava3/functions/Consumer;
      41: invokespecial #11                 // Method io/reactivex/rxjava3/internal/operators/observable/ObservableSampleTimed$SampleTimedEmitLast."<init>":(Lio/reactivex/rxjava3/core/Observer;JLjava/util/concurrent/TimeUnit;Lio/reactivex/rxjava3/core/Scheduler;Lio/reactivex/rxjava3/functions/Consumer;)V
      44: invokeinterface #12,  2           // InterfaceMethod io/reactivex/rxjava3/core/ObservableSource.subscribe:(Lio/reactivex/rxjava3/core/Observer;)V
      49: goto          85
      52: aload_0
      53: getfield      #9                  // Field source:Lio/reactivex/rxjava3/core/ObservableSource;
      56: new           #13                 // class io/reactivex/rxjava3/internal/operators/observable/ObservableSampleTimed$SampleTimedNoLast
      59: dup
      60: aload_2
      61: aload_0
      62: getfield      #2                  // Field period:J
      65: aload_0
      66: getfield      #3                  // Field unit:Ljava/util/concurrent/TimeUnit;
      69: aload_0
      70: getfield      #4                  // Field scheduler:Lio/reactivex/rxjava3/core/Scheduler;
      73: aload_0
      74: getfield      #6                  // Field onDropped:Lio/reactivex/rxjava3/functions/Consumer;
      77: invokespecial #14                 // Method io/reactivex/rxjava3/internal/operators/observable/ObservableSampleTimed$SampleTimedNoLast."<init>":(Lio/reactivex/rxjava3/core/Observer;JLjava/util/concurrent/TimeUnit;Lio/reactivex/rxjava3/core/Scheduler;Lio/reactivex/rxjava3/functions/Consumer;)V
      80: invokeinterface #12,  2           // InterfaceMethod io/reactivex/rxjava3/core/ObservableSource.subscribe:(Lio/reactivex/rxjava3/core/Observer;)V
      85: return
}
