Compiled from "ObservableTimeout.java"
public final class io.reactivex.rxjava3.internal.operators.observable.ObservableTimeout<T, U, V> extends io.reactivex.rxjava3.internal.operators.observable.AbstractObservableWithUpstream<T, T> {
  final io.reactivex.rxjava3.core.ObservableSource<U> firstTimeoutIndicator;

  final io.reactivex.rxjava3.functions.Function<? super T, ? extends io.reactivex.rxjava3.core.ObservableSource<V>> itemTimeoutIndicator;

  final io.reactivex.rxjava3.core.ObservableSource<? extends T> other;

  public io.reactivex.rxjava3.internal.operators.observable.ObservableTimeout(io.reactivex.rxjava3.core.Observable<T>, io.reactivex.rxjava3.core.ObservableSource<U>, io.reactivex.rxjava3.functions.Function<? super T, ? extends io.reactivex.rxjava3.core.ObservableSource<V>>, io.reactivex.rxjava3.core.ObservableSource<? extends T>);
    Code:
       0: aload_0
       1: aload_1
       2: invokespecial #1                  // Method io/reactivex/rxjava3/internal/operators/observable/AbstractObservableWithUpstream."<init>":(Lio/reactivex/rxjava3/core/ObservableSource;)V
       5: aload_0
       6: aload_2
       7: putfield      #2                  // Field firstTimeoutIndicator:Lio/reactivex/rxjava3/core/ObservableSource;
      10: aload_0
      11: aload_3
      12: putfield      #3                  // Field itemTimeoutIndicator:Lio/reactivex/rxjava3/functions/Function;
      15: aload_0
      16: aload         4
      18: putfield      #4                  // Field other:Lio/reactivex/rxjava3/core/ObservableSource;
      21: return

  protected void subscribeActual(io.reactivex.rxjava3.core.Observer<? super T>);
    Code:
       0: aload_0
       1: getfield      #4                  // Field other:Lio/reactivex/rxjava3/core/ObservableSource;
       4: ifnonnull     48
       7: new           #5                  // class io/reactivex/rxjava3/internal/operators/observable/ObservableTimeout$TimeoutObserver
      10: dup
      11: aload_1
      12: aload_0
      13: getfield      #3                  // Field itemTimeoutIndicator:Lio/reactivex/rxjava3/functions/Function;
      16: invokespecial #6                  // Method io/reactivex/rxjava3/internal/operators/observable/ObservableTimeout$TimeoutObserver."<init>":(Lio/reactivex/rxjava3/core/Observer;Lio/reactivex/rxjava3/functions/Function;)V
      19: astore_2
      20: aload_1
      21: aload_2
      22: invokeinterface #7,  2            // InterfaceMethod io/reactivex/rxjava3/core/Observer.onSubscribe:(Lio/reactivex/rxjava3/disposables/Disposable;)V
      27: aload_2
      28: aload_0
      29: getfield      #2                  // Field firstTimeoutIndicator:Lio/reactivex/rxjava3/core/ObservableSource;
      32: invokevirtual #8                  // Method io/reactivex/rxjava3/internal/operators/observable/ObservableTimeout$TimeoutObserver.startFirstTimeout:(Lio/reactivex/rxjava3/core/ObservableSource;)V
      35: aload_0
      36: getfield      #9                  // Field source:Lio/reactivex/rxjava3/core/ObservableSource;
      39: aload_2
      40: invokeinterface #10,  2           // InterfaceMethod io/reactivex/rxjava3/core/ObservableSource.subscribe:(Lio/reactivex/rxjava3/core/Observer;)V
      45: goto          90
      48: new           #11                 // class io/reactivex/rxjava3/internal/operators/observable/ObservableTimeout$TimeoutFallbackObserver
      51: dup
      52: aload_1
      53: aload_0
      54: getfield      #3                  // Field itemTimeoutIndicator:Lio/reactivex/rxjava3/functions/Function;
      57: aload_0
      58: getfield      #4                  // Field other:Lio/reactivex/rxjava3/core/ObservableSource;
      61: invokespecial #12                 // Method io/reactivex/rxjava3/internal/operators/observable/ObservableTimeout$TimeoutFallbackObserver."<init>":(Lio/reactivex/rxjava3/core/Observer;Lio/reactivex/rxjava3/functions/Function;Lio/reactivex/rxjava3/core/ObservableSource;)V
      64: astore_2
      65: aload_1
      66: aload_2
      67: invokeinterface #7,  2            // InterfaceMethod io/reactivex/rxjava3/core/Observer.onSubscribe:(Lio/reactivex/rxjava3/disposables/Disposable;)V
      72: aload_2
      73: aload_0
      74: getfield      #2                  // Field firstTimeoutIndicator:Lio/reactivex/rxjava3/core/ObservableSource;
      77: invokevirtual #13                 // Method io/reactivex/rxjava3/internal/operators/observable/ObservableTimeout$TimeoutFallbackObserver.startFirstTimeout:(Lio/reactivex/rxjava3/core/ObservableSource;)V
      80: aload_0
      81: getfield      #9                  // Field source:Lio/reactivex/rxjava3/core/ObservableSource;
      84: aload_2
      85: invokeinterface #10,  2           // InterfaceMethod io/reactivex/rxjava3/core/ObservableSource.subscribe:(Lio/reactivex/rxjava3/core/Observer;)V
      90: return
}
