Compiled from "ObservableBufferExactBoundary.java"
final class io.reactivex.rxjava3.internal.operators.observable.ObservableBufferExactBoundary$BufferBoundaryObserver<T, U extends java.util.Collection<? super T>, B> extends io.reactivex.rxjava3.observers.DisposableObserver<B> {
  final io.reactivex.rxjava3.internal.operators.observable.ObservableBufferExactBoundary$BufferExactBoundaryObserver<T, U, B> parent;

  io.reactivex.rxjava3.internal.operators.observable.ObservableBufferExactBoundary$BufferBoundaryObserver(io.reactivex.rxjava3.internal.operators.observable.ObservableBufferExactBoundary$BufferExactBoundaryObserver<T, U, B>);
    Code:
       0: aload_0
       1: invokespecial #1                  // Method io/reactivex/rxjava3/observers/DisposableObserver."<init>":()V
       4: aload_0
       5: aload_1
       6: putfield      #2                  // Field parent:Lio/reactivex/rxjava3/internal/operators/observable/ObservableBufferExactBoundary$BufferExactBoundaryObserver;
       9: return

  public void onNext(B);
    Code:
       0: aload_0
       1: getfield      #2                  // Field parent:Lio/reactivex/rxjava3/internal/operators/observable/ObservableBufferExactBoundary$BufferExactBoundaryObserver;
       4: invokevirtual #3                  // Method io/reactivex/rxjava3/internal/operators/observable/ObservableBufferExactBoundary$BufferExactBoundaryObserver.next:()V
       7: return

  public void onError(java.lang.Throwable);
    Code:
       0: aload_0
       1: getfield      #2                  // Field parent:Lio/reactivex/rxjava3/internal/operators/observable/ObservableBufferExactBoundary$BufferExactBoundaryObserver;
       4: aload_1
       5: invokevirtual #4                  // Method io/reactivex/rxjava3/internal/operators/observable/ObservableBufferExactBoundary$BufferExactBoundaryObserver.onError:(Ljava/lang/Throwable;)V
       8: return

  public void onComplete();
    Code:
       0: aload_0
       1: getfield      #2                  // Field parent:Lio/reactivex/rxjava3/internal/operators/observable/ObservableBufferExactBoundary$BufferExactBoundaryObserver;
       4: invokevirtual #5                  // Method io/reactivex/rxjava3/internal/operators/observable/ObservableBufferExactBoundary$BufferExactBoundaryObserver.onComplete:()V
       7: return
}
