Compiled from "ObservableWithLatestFrom.java"
public final class io.reactivex.rxjava3.internal.operators.observable.ObservableWithLatestFrom<T, U, R> extends io.reactivex.rxjava3.internal.operators.observable.AbstractObservableWithUpstream<T, R> {
  final io.reactivex.rxjava3.functions.BiFunction<? super T, ? super U, ? extends R> combiner;

  final io.reactivex.rxjava3.core.ObservableSource<? extends U> other;

  public io.reactivex.rxjava3.internal.operators.observable.ObservableWithLatestFrom(io.reactivex.rxjava3.core.ObservableSource<T>, io.reactivex.rxjava3.functions.BiFunction<? super T, ? super U, ? extends R>, io.reactivex.rxjava3.core.ObservableSource<? extends U>);
    Code:
       0: aload_0
       1: aload_1
       2: invokespecial #1                  // Method io/reactivex/rxjava3/internal/operators/observable/AbstractObservableWithUpstream."<init>":(Lio/reactivex/rxjava3/core/ObservableSource;)V
       5: aload_0
       6: aload_2
       7: putfield      #2                  // Field combiner:Lio/reactivex/rxjava3/functions/BiFunction;
      10: aload_0
      11: aload_3
      12: putfield      #3                  // Field other:Lio/reactivex/rxjava3/core/ObservableSource;
      15: return

  public void subscribeActual(io.reactivex.rxjava3.core.Observer<? super R>);
    Code:
       0: new           #4                  // class io/reactivex/rxjava3/observers/SerializedObserver
       3: dup
       4: aload_1
       5: invokespecial #5                  // Method io/reactivex/rxjava3/observers/SerializedObserver."<init>":(Lio/reactivex/rxjava3/core/Observer;)V
       8: astore_2
       9: new           #6                  // class io/reactivex/rxjava3/internal/operators/observable/ObservableWithLatestFrom$WithLatestFromObserver
      12: dup
      13: aload_2
      14: aload_0
      15: getfield      #2                  // Field combiner:Lio/reactivex/rxjava3/functions/BiFunction;
      18: invokespecial #7                  // Method io/reactivex/rxjava3/internal/operators/observable/ObservableWithLatestFrom$WithLatestFromObserver."<init>":(Lio/reactivex/rxjava3/core/Observer;Lio/reactivex/rxjava3/functions/BiFunction;)V
      21: astore_3
      22: aload_2
      23: aload_3
      24: invokevirtual #8                  // Method io/reactivex/rxjava3/observers/SerializedObserver.onSubscribe:(Lio/reactivex/rxjava3/disposables/Disposable;)V
      27: aload_0
      28: getfield      #3                  // Field other:Lio/reactivex/rxjava3/core/ObservableSource;
      31: new           #9                  // class io/reactivex/rxjava3/internal/operators/observable/ObservableWithLatestFrom$WithLatestFromOtherObserver
      34: dup
      35: aload_0
      36: aload_3
      37: invokespecial #10                 // Method io/reactivex/rxjava3/internal/operators/observable/ObservableWithLatestFrom$WithLatestFromOtherObserver."<init>":(Lio/reactivex/rxjava3/internal/operators/observable/ObservableWithLatestFrom;Lio/reactivex/rxjava3/internal/operators/observable/ObservableWithLatestFrom$WithLatestFromObserver;)V
      40: invokeinterface #11,  2           // InterfaceMethod io/reactivex/rxjava3/core/ObservableSource.subscribe:(Lio/reactivex/rxjava3/core/Observer;)V
      45: aload_0
      46: getfield      #12                 // Field source:Lio/reactivex/rxjava3/core/ObservableSource;
      49: aload_3
      50: invokeinterface #11,  2           // InterfaceMethod io/reactivex/rxjava3/core/ObservableSource.subscribe:(Lio/reactivex/rxjava3/core/Observer;)V
      55: return
}
