Compiled from "ObservableReduceMaybe.java"
final class io.reactivex.rxjava3.internal.operators.observable.ObservableReduceMaybe$ReduceObserver<T> implements io.reactivex.rxjava3.core.Observer<T>, io.reactivex.rxjava3.disposables.Disposable {
  final io.reactivex.rxjava3.core.MaybeObserver<? super T> downstream;

  final io.reactivex.rxjava3.functions.BiFunction<T, T, T> reducer;

  boolean done;

  T value;

  io.reactivex.rxjava3.disposables.Disposable upstream;

  io.reactivex.rxjava3.internal.operators.observable.ObservableReduceMaybe$ReduceObserver(io.reactivex.rxjava3.core.MaybeObserver<? super T>, io.reactivex.rxjava3.functions.BiFunction<T, T, T>);
    Code:
       0: aload_0
       1: invokespecial #1                  // Method java/lang/Object."<init>":()V
       4: aload_0
       5: aload_1
       6: putfield      #2                  // Field downstream:Lio/reactivex/rxjava3/core/MaybeObserver;
       9: aload_0
      10: aload_2
      11: putfield      #3                  // Field reducer:Lio/reactivex/rxjava3/functions/BiFunction;
      14: return

  public void onSubscribe(io.reactivex.rxjava3.disposables.Disposable);
    Code:
       0: aload_0
       1: getfield      #4                  // Field upstream:Lio/reactivex/rxjava3/disposables/Disposable;
       4: aload_1
       5: invokestatic  #5                  // Method io/reactivex/rxjava3/internal/disposables/DisposableHelper.validate:(Lio/reactivex/rxjava3/disposables/Disposable;Lio/reactivex/rxjava3/disposables/Disposable;)Z
       8: ifeq          26
      11: aload_0
      12: aload_1
      13: putfield      #4                  // Field upstream:Lio/reactivex/rxjava3/disposables/Disposable;
      16: aload_0
      17: getfield      #2                  // Field downstream:Lio/reactivex/rxjava3/core/MaybeObserver;
      20: aload_0
      21: invokeinterface #6,  2            // InterfaceMethod io/reactivex/rxjava3/core/MaybeObserver.onSubscribe:(Lio/reactivex/rxjava3/disposables/Disposable;)V
      26: return

  public void onNext(T);
    Code:
       0: aload_0
       1: getfield      #7                  // Field done:Z
       4: ifne          66
       7: aload_0
       8: getfield      #8                  // Field value:Ljava/lang/Object;
      11: astore_2
      12: aload_2
      13: ifnonnull     24
      16: aload_0
      17: aload_1
      18: putfield      #8                  // Field value:Ljava/lang/Object;
      21: goto          66
      24: aload_0
      25: aload_0
      26: getfield      #3                  // Field reducer:Lio/reactivex/rxjava3/functions/BiFunction;
      29: aload_2
      30: aload_1
      31: invokeinterface #9,  3            // InterfaceMethod io/reactivex/rxjava3/functions/BiFunction.apply:(Ljava/lang/Object;Ljava/lang/Object;)Ljava/lang/Object;
      36: ldc           #10                 // String The reducer returned a null value
      38: invokestatic  #11                 // Method java/util/Objects.requireNonNull:(Ljava/lang/Object;Ljava/lang/String;)Ljava/lang/Object;
      41: putfield      #8                  // Field value:Ljava/lang/Object;
      44: goto          66
      47: astore_3
      48: aload_3
      49: invokestatic  #13                 // Method io/reactivex/rxjava3/exceptions/Exceptions.throwIfFatal:(Ljava/lang/Throwable;)V
      52: aload_0
      53: getfield      #4                  // Field upstream:Lio/reactivex/rxjava3/disposables/Disposable;
      56: invokeinterface #14,  1           // InterfaceMethod io/reactivex/rxjava3/disposables/Disposable.dispose:()V
      61: aload_0
      62: aload_3
      63: invokevirtual #15                 // Method onError:(Ljava/lang/Throwable;)V
      66: return
    Exception table:
       from    to  target type
          24    44    47   Class java/lang/Throwable

  public void onError(java.lang.Throwable);
    Code:
       0: aload_0
       1: getfield      #7                  // Field done:Z
       4: ifeq          12
       7: aload_1
       8: invokestatic  #16                 // Method io/reactivex/rxjava3/plugins/RxJavaPlugins.onError:(Ljava/lang/Throwable;)V
      11: return
      12: aload_0
      13: iconst_1
      14: putfield      #7                  // Field done:Z
      17: aload_0
      18: aconst_null
      19: putfield      #8                  // Field value:Ljava/lang/Object;
      22: aload_0
      23: getfield      #2                  // Field downstream:Lio/reactivex/rxjava3/core/MaybeObserver;
      26: aload_1
      27: invokeinterface #17,  2           // InterfaceMethod io/reactivex/rxjava3/core/MaybeObserver.onError:(Ljava/lang/Throwable;)V
      32: return

  public void onComplete();
    Code:
       0: aload_0
       1: getfield      #7                  // Field done:Z
       4: ifeq          8
       7: return
       8: aload_0
       9: iconst_1
      10: putfield      #7                  // Field done:Z
      13: aload_0
      14: getfield      #8                  // Field value:Ljava/lang/Object;
      17: astore_1
      18: aload_0
      19: aconst_null
      20: putfield      #8                  // Field value:Ljava/lang/Object;
      23: aload_1
      24: ifnull        40
      27: aload_0
      28: getfield      #2                  // Field downstream:Lio/reactivex/rxjava3/core/MaybeObserver;
      31: aload_1
      32: invokeinterface #18,  2           // InterfaceMethod io/reactivex/rxjava3/core/MaybeObserver.onSuccess:(Ljava/lang/Object;)V
      37: goto          49
      40: aload_0
      41: getfield      #2                  // Field downstream:Lio/reactivex/rxjava3/core/MaybeObserver;
      44: invokeinterface #19,  1           // InterfaceMethod io/reactivex/rxjava3/core/MaybeObserver.onComplete:()V
      49: return

  public void dispose();
    Code:
       0: aload_0
       1: getfield      #4                  // Field upstream:Lio/reactivex/rxjava3/disposables/Disposable;
       4: invokeinterface #14,  1           // InterfaceMethod io/reactivex/rxjava3/disposables/Disposable.dispose:()V
       9: return

  public boolean isDisposed();
    Code:
       0: aload_0
       1: getfield      #4                  // Field upstream:Lio/reactivex/rxjava3/disposables/Disposable;
       4: invokeinterface #20,  1           // InterfaceMethod io/reactivex/rxjava3/disposables/Disposable.isDisposed:()Z
       9: ireturn
}
