Compiled from "ObservableNever.java"
public final class io.reactivex.rxjava3.internal.operators.observable.ObservableNever extends io.reactivex.rxjava3.core.Observable<java.lang.Object> {
  public static final io.reactivex.rxjava3.core.Observable<java.lang.Object> INSTANCE;

  private io.reactivex.rxjava3.internal.operators.observable.ObservableNever();
    Code:
       0: aload_0
       1: invokespecial #1                  // Method io/reactivex/rxjava3/core/Observable."<init>":()V
       4: return

  protected void subscribeActual(io.reactivex.rxjava3.core.Observer<? super java.lang.Object>);
    Code:
       0: aload_1
       1: getstatic     #2                  // Field io/reactivex/rxjava3/internal/disposables/EmptyDisposable.NEVER:Lio/reactivex/rxjava3/internal/disposables/EmptyDisposable;
       4: invokeinterface #3,  2            // InterfaceMethod io/reactivex/rxjava3/core/Observer.onSubscribe:(Lio/reactivex/rxjava3/disposables/Disposable;)V
       9: return

  static {};
    Code:
       0: new           #4                  // class io/reactivex/rxjava3/internal/operators/observable/ObservableNever
       3: dup
       4: invokespecial #5                  // Method "<init>":()V
       7: putstatic     #6                  // Field INSTANCE:Lio/reactivex/rxjava3/core/Observable;
      10: return
}
