Compiled from "ObservableInternalHelper.java"
final class io.reactivex.rxjava3.internal.operators.observable.ObservableInternalHelper$SimpleBiGenerator<T, S> implements io.reactivex.rxjava3.functions.BiFunction<S, io.reactivex.rxjava3.core.Emitter<T>, S> {
  final io.reactivex.rxjava3.functions.BiConsumer<S, io.reactivex.rxjava3.core.Emitter<T>> consumer;

  io.reactivex.rxjava3.internal.operators.observable.ObservableInternalHelper$SimpleBiGenerator(io.reactivex.rxjava3.functions.BiConsumer<S, io.reactivex.rxjava3.core.Emitter<T>>);
    Code:
       0: aload_0
       1: invokespecial #1                  // Method java/lang/Object."<init>":()V
       4: aload_0
       5: aload_1
       6: putfield      #2                  // Field consumer:Lio/reactivex/rxjava3/functions/BiConsumer;
       9: return

  public S apply(S, io.reactivex.rxjava3.core.Emitter<T>) throws java.lang.Throwable;
    Code:
       0: aload_0
       1: getfield      #2                  // Field consumer:Lio/reactivex/rxjava3/functions/BiConsumer;
       4: aload_1
       5: aload_2
       6: invokeinterface #3,  3            // InterfaceMethod io/reactivex/rxjava3/functions/BiConsumer.accept:(Ljava/lang/Object;Ljava/lang/Object;)V
      11: aload_1
      12: areturn

  public java.lang.Object apply(java.lang.Object, java.lang.Object) throws java.lang.Throwable;
    Code:
       0: aload_0
       1: aload_1
       2: aload_2
       3: checkcast     #4                  // class io/reactivex/rxjava3/core/Emitter
       6: invokevirtual #5                  // Method apply:(Ljava/lang/Object;Lio/reactivex/rxjava3/core/Emitter;)Ljava/lang/Object;
       9: areturn
}
