Compiled from "ObservableWithLatestFromMany.java"
public final class io.reactivex.rxjava3.internal.operators.observable.ObservableWithLatestFromMany<T, R> extends io.reactivex.rxjava3.internal.operators.observable.AbstractObservableWithUpstream<T, R> {
  final io.reactivex.rxjava3.core.ObservableSource<?>[] otherArray;

  final java.lang.Iterable<? extends io.reactivex.rxjava3.core.ObservableSource<?>> otherIterable;

  final io.reactivex.rxjava3.functions.Function<? super java.lang.Object[], R> combiner;

  public io.reactivex.rxjava3.internal.operators.observable.ObservableWithLatestFromMany(io.reactivex.rxjava3.core.ObservableSource<T>, io.reactivex.rxjava3.core.ObservableSource<?>[], io.reactivex.rxjava3.functions.Function<? super java.lang.Object[], R>);
    Code:
       0: aload_0
       1: aload_1
       2: invokespecial #1                  // Method io/reactivex/rxjava3/internal/operators/observable/AbstractObservableWithUpstream."<init>":(Lio/reactivex/rxjava3/core/ObservableSource;)V
       5: aload_0
       6: aload_2
       7: putfield      #2                  // Field otherArray:[Lio/reactivex/rxjava3/core/ObservableSource;
      10: aload_0
      11: aconst_null
      12: putfield      #3                  // Field otherIterable:Ljava/lang/Iterable;
      15: aload_0
      16: aload_3
      17: putfield      #4                  // Field combiner:Lio/reactivex/rxjava3/functions/Function;
      20: return

  public io.reactivex.rxjava3.internal.operators.observable.ObservableWithLatestFromMany(io.reactivex.rxjava3.core.ObservableSource<T>, java.lang.Iterable<? extends io.reactivex.rxjava3.core.ObservableSource<?>>, io.reactivex.rxjava3.functions.Function<? super java.lang.Object[], R>);
    Code:
       0: aload_0
       1: aload_1
       2: invokespecial #1                  // Method io/reactivex/rxjava3/internal/operators/observable/AbstractObservableWithUpstream."<init>":(Lio/reactivex/rxjava3/core/ObservableSource;)V
       5: aload_0
       6: aconst_null
       7: putfield      #2                  // Field otherArray:[Lio/reactivex/rxjava3/core/ObservableSource;
      10: aload_0
      11: aload_2
      12: putfield      #3                  // Field otherIterable:Ljava/lang/Iterable;
      15: aload_0
      16: aload_3
      17: putfield      #4                  // Field combiner:Lio/reactivex/rxjava3/functions/Function;
      20: return

  protected void subscribeActual(io.reactivex.rxjava3.core.Observer<? super R>);
    Code:
       0: aload_0
       1: getfield      #2                  // Field otherArray:[Lio/reactivex/rxjava3/core/ObservableSource;
       4: astore_2
       5: iconst_0
       6: istore_3
       7: aload_2
       8: ifnonnull     97
      11: bipush        8
      13: anewarray     #5                  // class io/reactivex/rxjava3/core/ObservableSource
      16: astore_2
      17: aload_0
      18: getfield      #3                  // Field otherIterable:Ljava/lang/Iterable;
      21: invokeinterface #6,  1            // InterfaceMethod java/lang/Iterable.iterator:()Ljava/util/Iterator;
      26: astore        4
      28: aload         4
      30: invokeinterface #7,  1            // InterfaceMethod java/util/Iterator.hasNext:()Z
      35: ifeq          80
      38: aload         4
      40: invokeinterface #8,  1            // InterfaceMethod java/util/Iterator.next:()Ljava/lang/Object;
      45: checkcast     #5                  // class io/reactivex/rxjava3/core/ObservableSource
      48: astore        5
      50: iload_3
      51: aload_2
      52: arraylength
      53: if_icmpne     69
      56: aload_2
      57: iload_3
      58: iload_3
      59: iconst_1
      60: ishr
      61: iadd
      62: invokestatic  #9                  // Method java/util/Arrays.copyOf:([Ljava/lang/Object;I)[Ljava/lang/Object;
      65: checkcast     #10                 // class "[Lio/reactivex/rxjava3/core/ObservableSource;"
      68: astore_2
      69: aload_2
      70: iload_3
      71: iinc          3, 1
      74: aload         5
      76: aastore
      77: goto          28
      80: goto          100
      83: astore        4
      85: aload         4
      87: invokestatic  #12                 // Method io/reactivex/rxjava3/exceptions/Exceptions.throwIfFatal:(Ljava/lang/Throwable;)V
      90: aload         4
      92: aload_1
      93: invokestatic  #13                 // Method io/reactivex/rxjava3/internal/disposables/EmptyDisposable.error:(Ljava/lang/Throwable;Lio/reactivex/rxjava3/core/Observer;)V
      96: return
      97: aload_2
      98: arraylength
      99: istore_3
     100: iload_3
     101: ifne          128
     104: new           #14                 // class io/reactivex/rxjava3/internal/operators/observable/ObservableMap
     107: dup
     108: aload_0
     109: getfield      #15                 // Field source:Lio/reactivex/rxjava3/core/ObservableSource;
     112: new           #16                 // class io/reactivex/rxjava3/internal/operators/observable/ObservableWithLatestFromMany$SingletonArrayFunc
     115: dup
     116: aload_0
     117: invokespecial #17                 // Method io/reactivex/rxjava3/internal/operators/observable/ObservableWithLatestFromMany$SingletonArrayFunc."<init>":(Lio/reactivex/rxjava3/internal/operators/observable/ObservableWithLatestFromMany;)V
     120: invokespecial #18                 // Method io/reactivex/rxjava3/internal/operators/observable/ObservableMap."<init>":(Lio/reactivex/rxjava3/core/ObservableSource;Lio/reactivex/rxjava3/functions/Function;)V
     123: aload_1
     124: invokevirtual #19                 // Method io/reactivex/rxjava3/internal/operators/observable/ObservableMap.subscribeActual:(Lio/reactivex/rxjava3/core/Observer;)V
     127: return
     128: new           #20                 // class io/reactivex/rxjava3/internal/operators/observable/ObservableWithLatestFromMany$WithLatestFromObserver
     131: dup
     132: aload_1
     133: aload_0
     134: getfield      #4                  // Field combiner:Lio/reactivex/rxjava3/functions/Function;
     137: iload_3
     138: invokespecial #21                 // Method io/reactivex/rxjava3/internal/operators/observable/ObservableWithLatestFromMany$WithLatestFromObserver."<init>":(Lio/reactivex/rxjava3/core/Observer;Lio/reactivex/rxjava3/functions/Function;I)V
     141: astore        4
     143: aload_1
     144: aload         4
     146: invokeinterface #22,  2           // InterfaceMethod io/reactivex/rxjava3/core/Observer.onSubscribe:(Lio/reactivex/rxjava3/disposables/Disposable;)V
     151: aload         4
     153: aload_2
     154: iload_3
     155: invokevirtual #23                 // Method io/reactivex/rxjava3/internal/operators/observable/ObservableWithLatestFromMany$WithLatestFromObserver.subscribe:([Lio/reactivex/rxjava3/core/ObservableSource;I)V
     158: aload_0
     159: getfield      #15                 // Field source:Lio/reactivex/rxjava3/core/ObservableSource;
     162: aload         4
     164: invokeinterface #24,  2           // InterfaceMethod io/reactivex/rxjava3/core/ObservableSource.subscribe:(Lio/reactivex/rxjava3/core/Observer;)V
     169: return
    Exception table:
       from    to  target type
          17    80    83   Class java/lang/Throwable
}
