Compiled from "ObservableDoOnEach.java"
final class io.reactivex.rxjava3.internal.operators.observable.ObservableDoOnEach$DoOnEachObserver<T> implements io.reactivex.rxjava3.core.Observer<T>, io.reactivex.rxjava3.disposables.Disposable {
  final io.reactivex.rxjava3.core.Observer<? super T> downstream;

  final io.reactivex.rxjava3.functions.Consumer<? super T> onNext;

  final io.reactivex.rxjava3.functions.Consumer<? super java.lang.Throwable> onError;

  final io.reactivex.rxjava3.functions.Action onComplete;

  final io.reactivex.rxjava3.functions.Action onAfterTerminate;

  io.reactivex.rxjava3.disposables.Disposable upstream;

  boolean done;

  io.reactivex.rxjava3.internal.operators.observable.ObservableDoOnEach$DoOnEachObserver(io.reactivex.rxjava3.core.Observer<? super T>, io.reactivex.rxjava3.functions.Consumer<? super T>, io.reactivex.rxjava3.functions.Consumer<? super java.lang.Throwable>, io.reactivex.rxjava3.functions.Action, io.reactivex.rxjava3.functions.Action);
    Code:
       0: aload_0
       1: invokespecial #1                  // Method java/lang/Object."<init>":()V
       4: aload_0
       5: aload_1
       6: putfield      #2                  // Field downstream:Lio/reactivex/rxjava3/core/Observer;
       9: aload_0
      10: aload_2
      11: putfield      #3                  // Field onNext:Lio/reactivex/rxjava3/functions/Consumer;
      14: aload_0
      15: aload_3
      16: putfield      #4                  // Field onError:Lio/reactivex/rxjava3/functions/Consumer;
      19: aload_0
      20: aload         4
      22: putfield      #5                  // Field onComplete:Lio/reactivex/rxjava3/functions/Action;
      25: aload_0
      26: aload         5
      28: putfield      #6                  // Field onAfterTerminate:Lio/reactivex/rxjava3/functions/Action;
      31: return

  public void onSubscribe(io.reactivex.rxjava3.disposables.Disposable);
    Code:
       0: aload_0
       1: getfield      #7                  // Field upstream:Lio/reactivex/rxjava3/disposables/Disposable;
       4: aload_1
       5: invokestatic  #8                  // Method io/reactivex/rxjava3/internal/disposables/DisposableHelper.validate:(Lio/reactivex/rxjava3/disposables/Disposable;Lio/reactivex/rxjava3/disposables/Disposable;)Z
       8: ifeq          26
      11: aload_0
      12: aload_1
      13: putfield      #7                  // Field upstream:Lio/reactivex/rxjava3/disposables/Disposable;
      16: aload_0
      17: getfield      #2                  // Field downstream:Lio/reactivex/rxjava3/core/Observer;
      20: aload_0
      21: invokeinterface #9,  2            // InterfaceMethod io/reactivex/rxjava3/core/Observer.onSubscribe:(Lio/reactivex/rxjava3/disposables/Disposable;)V
      26: return

  public void dispose();
    Code:
       0: aload_0
       1: getfield      #7                  // Field upstream:Lio/reactivex/rxjava3/disposables/Disposable;
       4: invokeinterface #10,  1           // InterfaceMethod io/reactivex/rxjava3/disposables/Disposable.dispose:()V
       9: return

  public boolean isDisposed();
    Code:
       0: aload_0
       1: getfield      #7                  // Field upstream:Lio/reactivex/rxjava3/disposables/Disposable;
       4: invokeinterface #11,  1           // InterfaceMethod io/reactivex/rxjava3/disposables/Disposable.isDisposed:()Z
       9: ireturn

  public void onNext(T);
    Code:
       0: aload_0
       1: getfield      #12                 // Field done:Z
       4: ifeq          8
       7: return
       8: aload_0
       9: getfield      #3                  // Field onNext:Lio/reactivex/rxjava3/functions/Consumer;
      12: aload_1
      13: invokeinterface #13,  2           // InterfaceMethod io/reactivex/rxjava3/functions/Consumer.accept:(Ljava/lang/Object;)V
      18: goto          41
      21: astore_2
      22: aload_2
      23: invokestatic  #15                 // Method io/reactivex/rxjava3/exceptions/Exceptions.throwIfFatal:(Ljava/lang/Throwable;)V
      26: aload_0
      27: getfield      #7                  // Field upstream:Lio/reactivex/rxjava3/disposables/Disposable;
      30: invokeinterface #10,  1           // InterfaceMethod io/reactivex/rxjava3/disposables/Disposable.dispose:()V
      35: aload_0
      36: aload_2
      37: invokevirtual #16                 // Method onError:(Ljava/lang/Throwable;)V
      40: return
      41: aload_0
      42: getfield      #2                  // Field downstream:Lio/reactivex/rxjava3/core/Observer;
      45: aload_1
      46: invokeinterface #17,  2           // InterfaceMethod io/reactivex/rxjava3/core/Observer.onNext:(Ljava/lang/Object;)V
      51: return
    Exception table:
       from    to  target type
           8    18    21   Class java/lang/Throwable

  public void onError(java.lang.Throwable);
    Code:
       0: aload_0
       1: getfield      #12                 // Field done:Z
       4: ifeq          12
       7: aload_1
       8: invokestatic  #18                 // Method io/reactivex/rxjava3/plugins/RxJavaPlugins.onError:(Ljava/lang/Throwable;)V
      11: return
      12: aload_0
      13: iconst_1
      14: putfield      #12                 // Field done:Z
      17: aload_0
      18: getfield      #4                  // Field onError:Lio/reactivex/rxjava3/functions/Consumer;
      21: aload_1
      22: invokeinterface #13,  2           // InterfaceMethod io/reactivex/rxjava3/functions/Consumer.accept:(Ljava/lang/Object;)V
      27: goto          55
      30: astore_2
      31: aload_2
      32: invokestatic  #15                 // Method io/reactivex/rxjava3/exceptions/Exceptions.throwIfFatal:(Ljava/lang/Throwable;)V
      35: new           #19                 // class io/reactivex/rxjava3/exceptions/CompositeException
      38: dup
      39: iconst_2
      40: anewarray     #20                 // class java/lang/Throwable
      43: dup
      44: iconst_0
      45: aload_1
      46: aastore
      47: dup
      48: iconst_1
      49: aload_2
      50: aastore
      51: invokespecial #21                 // Method io/reactivex/rxjava3/exceptions/CompositeException."<init>":([Ljava/lang/Throwable;)V
      54: astore_1
      55: aload_0
      56: getfield      #2                  // Field downstream:Lio/reactivex/rxjava3/core/Observer;
      59: aload_1
      60: invokeinterface #22,  2           // InterfaceMethod io/reactivex/rxjava3/core/Observer.onError:(Ljava/lang/Throwable;)V
      65: aload_0
      66: getfield      #6                  // Field onAfterTerminate:Lio/reactivex/rxjava3/functions/Action;
      69: invokeinterface #23,  1           // InterfaceMethod io/reactivex/rxjava3/functions/Action.run:()V
      74: goto          86
      77: astore_2
      78: aload_2
      79: invokestatic  #15                 // Method io/reactivex/rxjava3/exceptions/Exceptions.throwIfFatal:(Ljava/lang/Throwable;)V
      82: aload_2
      83: invokestatic  #18                 // Method io/reactivex/rxjava3/plugins/RxJavaPlugins.onError:(Ljava/lang/Throwable;)V
      86: return
    Exception table:
       from    to  target type
          17    27    30   Class java/lang/Throwable
          65    74    77   Class java/lang/Throwable

  public void onComplete();
    Code:
       0: aload_0
       1: getfield      #12                 // Field done:Z
       4: ifeq          8
       7: return
       8: aload_0
       9: getfield      #5                  // Field onComplete:Lio/reactivex/rxjava3/functions/Action;
      12: invokeinterface #23,  1           // InterfaceMethod io/reactivex/rxjava3/functions/Action.run:()V
      17: goto          31
      20: astore_1
      21: aload_1
      22: invokestatic  #15                 // Method io/reactivex/rxjava3/exceptions/Exceptions.throwIfFatal:(Ljava/lang/Throwable;)V
      25: aload_0
      26: aload_1
      27: invokevirtual #16                 // Method onError:(Ljava/lang/Throwable;)V
      30: return
      31: aload_0
      32: iconst_1
      33: putfield      #12                 // Field done:Z
      36: aload_0
      37: getfield      #2                  // Field downstream:Lio/reactivex/rxjava3/core/Observer;
      40: invokeinterface #24,  1           // InterfaceMethod io/reactivex/rxjava3/core/Observer.onComplete:()V
      45: aload_0
      46: getfield      #6                  // Field onAfterTerminate:Lio/reactivex/rxjava3/functions/Action;
      49: invokeinterface #23,  1           // InterfaceMethod io/reactivex/rxjava3/functions/Action.run:()V
      54: goto          66
      57: astore_1
      58: aload_1
      59: invokestatic  #15                 // Method io/reactivex/rxjava3/exceptions/Exceptions.throwIfFatal:(Ljava/lang/Throwable;)V
      62: aload_1
      63: invokestatic  #18                 // Method io/reactivex/rxjava3/plugins/RxJavaPlugins.onError:(Ljava/lang/Throwable;)V
      66: return
    Exception table:
       from    to  target type
           8    17    20   Class java/lang/Throwable
          45    54    57   Class java/lang/Throwable
}
