Compiled from "ObservableInternalHelper.java"
final class io.reactivex.rxjava3.internal.operators.observable.ObservableInternalHelper$FlatMapWithCombinerOuter<T, R, U> implements io.reactivex.rxjava3.functions.Function<T, io.reactivex.rxjava3.core.ObservableSource<R>> {
  private final io.reactivex.rxjava3.functions.BiFunction<? super T, ? super U, ? extends R> combiner;

  private final io.reactivex.rxjava3.functions.Function<? super T, ? extends io.reactivex.rxjava3.core.ObservableSource<? extends U>> mapper;

  io.reactivex.rxjava3.internal.operators.observable.ObservableInternalHelper$FlatMapWithCombinerOuter(io.reactivex.rxjava3.functions.BiFunction<? super T, ? super U, ? extends R>, io.reactivex.rxjava3.functions.Function<? super T, ? extends io.reactivex.rxjava3.core.ObservableSource<? extends U>>);
    Code:
       0: aload_0
       1: invokespecial #1                  // Method java/lang/Object."<init>":()V
       4: aload_0
       5: aload_1
       6: putfield      #2                  // Field combiner:Lio/reactivex/rxjava3/functions/BiFunction;
       9: aload_0
      10: aload_2
      11: putfield      #3                  // Field mapper:Lio/reactivex/rxjava3/functions/Function;
      14: return

  public io.reactivex.rxjava3.core.ObservableSource<R> apply(T) throws java.lang.Throwable;
    Code:
       0: aload_0
       1: getfield      #3                  // Field mapper:Lio/reactivex/rxjava3/functions/Function;
       4: aload_1
       5: invokeinterface #4,  2            // InterfaceMethod io/reactivex/rxjava3/functions/Function.apply:(Ljava/lang/Object;)Ljava/lang/Object;
      10: ldc           #5                  // String The mapper returned a null ObservableSource
      12: invokestatic  #6                  // Method java/util/Objects.requireNonNull:(Ljava/lang/Object;Ljava/lang/String;)Ljava/lang/Object;
      15: checkcast     #7                  // class io/reactivex/rxjava3/core/ObservableSource
      18: astore_2
      19: new           #8                  // class io/reactivex/rxjava3/internal/operators/observable/ObservableMap
      22: dup
      23: aload_2
      24: new           #9                  // class io/reactivex/rxjava3/internal/operators/observable/ObservableInternalHelper$FlatMapWithCombinerInner
      27: dup
      28: aload_0
      29: getfield      #2                  // Field combiner:Lio/reactivex/rxjava3/functions/BiFunction;
      32: aload_1
      33: invokespecial #10                 // Method io/reactivex/rxjava3/internal/operators/observable/ObservableInternalHelper$FlatMapWithCombinerInner."<init>":(Lio/reactivex/rxjava3/functions/BiFunction;Ljava/lang/Object;)V
      36: invokespecial #11                 // Method io/reactivex/rxjava3/internal/operators/observable/ObservableMap."<init>":(Lio/reactivex/rxjava3/core/ObservableSource;Lio/reactivex/rxjava3/functions/Function;)V
      39: areturn

  public java.lang.Object apply(java.lang.Object) throws java.lang.Throwable;
    Code:
       0: aload_0
       1: aload_1
       2: invokevirtual #12                 // Method apply:(Ljava/lang/Object;)Lio/reactivex/rxjava3/core/ObservableSource;
       5: areturn
}
