Compiled from "ObservableAmb.java"
final class io.reactivex.rxjava3.internal.operators.observable.ObservableAmb$AmbInnerObserver<T> extends java.util.concurrent.atomic.AtomicReference<io.reactivex.rxjava3.disposables.Disposable> implements io.reactivex.rxjava3.core.Observer<T> {
  private static final long serialVersionUID;

  final io.reactivex.rxjava3.internal.operators.observable.ObservableAmb$AmbCoordinator<T> parent;

  final int index;

  final io.reactivex.rxjava3.core.Observer<? super T> downstream;

  boolean won;

  io.reactivex.rxjava3.internal.operators.observable.ObservableAmb$AmbInnerObserver(io.reactivex.rxjava3.internal.operators.observable.ObservableAmb$AmbCoordinator<T>, int, io.reactivex.rxjava3.core.Observer<? super T>);
    Code:
       0: aload_0
       1: invokespecial #1                  // Method java/util/concurrent/atomic/AtomicReference."<init>":()V
       4: aload_0
       5: aload_1
       6: putfield      #2                  // Field parent:Lio/reactivex/rxjava3/internal/operators/observable/ObservableAmb$AmbCoordinator;
       9: aload_0
      10: iload_2
      11: putfield      #3                  // Field index:I
      14: aload_0
      15: aload_3
      16: putfield      #4                  // Field downstream:Lio/reactivex/rxjava3/core/Observer;
      19: return

  public void onSubscribe(io.reactivex.rxjava3.disposables.Disposable);
    Code:
       0: aload_0
       1: aload_1
       2: invokestatic  #5                  // Method io/reactivex/rxjava3/internal/disposables/DisposableHelper.setOnce:(Ljava/util/concurrent/atomic/AtomicReference;Lio/reactivex/rxjava3/disposables/Disposable;)Z
       5: pop
       6: return

  public void onNext(T);
    Code:
       0: aload_0
       1: getfield      #6                  // Field won:Z
       4: ifeq          20
       7: aload_0
       8: getfield      #4                  // Field downstream:Lio/reactivex/rxjava3/core/Observer;
      11: aload_1
      12: invokeinterface #7,  2            // InterfaceMethod io/reactivex/rxjava3/core/Observer.onNext:(Ljava/lang/Object;)V
      17: goto          64
      20: aload_0
      21: getfield      #2                  // Field parent:Lio/reactivex/rxjava3/internal/operators/observable/ObservableAmb$AmbCoordinator;
      24: aload_0
      25: getfield      #3                  // Field index:I
      28: invokevirtual #8                  // Method io/reactivex/rxjava3/internal/operators/observable/ObservableAmb$AmbCoordinator.win:(I)Z
      31: ifeq          52
      34: aload_0
      35: iconst_1
      36: putfield      #6                  // Field won:Z
      39: aload_0
      40: getfield      #4                  // Field downstream:Lio/reactivex/rxjava3/core/Observer;
      43: aload_1
      44: invokeinterface #7,  2            // InterfaceMethod io/reactivex/rxjava3/core/Observer.onNext:(Ljava/lang/Object;)V
      49: goto          64
      52: aload_0
      53: invokevirtual #9                  // Method get:()Ljava/lang/Object;
      56: checkcast     #10                 // class io/reactivex/rxjava3/disposables/Disposable
      59: invokeinterface #11,  1           // InterfaceMethod io/reactivex/rxjava3/disposables/Disposable.dispose:()V
      64: return

  public void onError(java.lang.Throwable);
    Code:
       0: aload_0
       1: getfield      #6                  // Field won:Z
       4: ifeq          20
       7: aload_0
       8: getfield      #4                  // Field downstream:Lio/reactivex/rxjava3/core/Observer;
      11: aload_1
      12: invokeinterface #12,  2           // InterfaceMethod io/reactivex/rxjava3/core/Observer.onError:(Ljava/lang/Throwable;)V
      17: goto          56
      20: aload_0
      21: getfield      #2                  // Field parent:Lio/reactivex/rxjava3/internal/operators/observable/ObservableAmb$AmbCoordinator;
      24: aload_0
      25: getfield      #3                  // Field index:I
      28: invokevirtual #8                  // Method io/reactivex/rxjava3/internal/operators/observable/ObservableAmb$AmbCoordinator.win:(I)Z
      31: ifeq          52
      34: aload_0
      35: iconst_1
      36: putfield      #6                  // Field won:Z
      39: aload_0
      40: getfield      #4                  // Field downstream:Lio/reactivex/rxjava3/core/Observer;
      43: aload_1
      44: invokeinterface #12,  2           // InterfaceMethod io/reactivex/rxjava3/core/Observer.onError:(Ljava/lang/Throwable;)V
      49: goto          56
      52: aload_1
      53: invokestatic  #13                 // Method io/reactivex/rxjava3/plugins/RxJavaPlugins.onError:(Ljava/lang/Throwable;)V
      56: return

  public void onComplete();
    Code:
       0: aload_0
       1: getfield      #6                  // Field won:Z
       4: ifeq          19
       7: aload_0
       8: getfield      #4                  // Field downstream:Lio/reactivex/rxjava3/core/Observer;
      11: invokeinterface #14,  1           // InterfaceMethod io/reactivex/rxjava3/core/Observer.onComplete:()V
      16: goto          47
      19: aload_0
      20: getfield      #2                  // Field parent:Lio/reactivex/rxjava3/internal/operators/observable/ObservableAmb$AmbCoordinator;
      23: aload_0
      24: getfield      #3                  // Field index:I
      27: invokevirtual #8                  // Method io/reactivex/rxjava3/internal/operators/observable/ObservableAmb$AmbCoordinator.win:(I)Z
      30: ifeq          47
      33: aload_0
      34: iconst_1
      35: putfield      #6                  // Field won:Z
      38: aload_0
      39: getfield      #4                  // Field downstream:Lio/reactivex/rxjava3/core/Observer;
      42: invokeinterface #14,  1           // InterfaceMethod io/reactivex/rxjava3/core/Observer.onComplete:()V
      47: return

  public void dispose();
    Code:
       0: aload_0
       1: invokestatic  #15                 // Method io/reactivex/rxjava3/internal/disposables/DisposableHelper.dispose:(Ljava/util/concurrent/atomic/AtomicReference;)Z
       4: pop
       5: return
}
