Compiled from "ObservableObserveOn.java"
public final class io.reactivex.rxjava3.internal.operators.observable.ObservableObserveOn<T> extends io.reactivex.rxjava3.internal.operators.observable.AbstractObservableWithUpstream<T, T> {
  final io.reactivex.rxjava3.core.Scheduler scheduler;

  final boolean delayError;

  final int bufferSize;

  public io.reactivex.rxjava3.internal.operators.observable.ObservableObserveOn(io.reactivex.rxjava3.core.ObservableSource<T>, io.reactivex.rxjava3.core.Scheduler, boolean, int);
    Code:
       0: aload_0
       1: aload_1
       2: invokespecial #1                  // Method io/reactivex/rxjava3/internal/operators/observable/AbstractObservableWithUpstream."<init>":(Lio/reactivex/rxjava3/core/ObservableSource;)V
       5: aload_0
       6: aload_2
       7: putfield      #2                  // Field scheduler:Lio/reactivex/rxjava3/core/Scheduler;
      10: aload_0
      11: iload_3
      12: putfield      #3                  // Field delayError:Z
      15: aload_0
      16: iload         4
      18: putfield      #4                  // Field bufferSize:I
      21: return

  protected void subscribeActual(io.reactivex.rxjava3.core.Observer<? super T>);
    Code:
       0: aload_0
       1: getfield      #2                  // Field scheduler:Lio/reactivex/rxjava3/core/Scheduler;
       4: instanceof    #5                  // class io/reactivex/rxjava3/internal/schedulers/TrampolineScheduler
       7: ifeq          23
      10: aload_0
      11: getfield      #6                  // Field source:Lio/reactivex/rxjava3/core/ObservableSource;
      14: aload_1
      15: invokeinterface #7,  2            // InterfaceMethod io/reactivex/rxjava3/core/ObservableSource.subscribe:(Lio/reactivex/rxjava3/core/Observer;)V
      20: goto          57
      23: aload_0
      24: getfield      #2                  // Field scheduler:Lio/reactivex/rxjava3/core/Scheduler;
      27: invokevirtual #8                  // Method io/reactivex/rxjava3/core/Scheduler.createWorker:()Lio/reactivex/rxjava3/core/Scheduler$Worker;
      30: astore_2
      31: aload_0
      32: getfield      #6                  // Field source:Lio/reactivex/rxjava3/core/ObservableSource;
      35: new           #9                  // class io/reactivex/rxjava3/internal/operators/observable/ObservableObserveOn$ObserveOnObserver
      38: dup
      39: aload_1
      40: aload_2
      41: aload_0
      42: getfield      #3                  // Field delayError:Z
      45: aload_0
      46: getfield      #4                  // Field bufferSize:I
      49: invokespecial #10                 // Method io/reactivex/rxjava3/internal/operators/observable/ObservableObserveOn$ObserveOnObserver."<init>":(Lio/reactivex/rxjava3/core/Observer;Lio/reactivex/rxjava3/core/Scheduler$Worker;ZI)V
      52: invokeinterface #7,  2            // InterfaceMethod io/reactivex/rxjava3/core/ObservableSource.subscribe:(Lio/reactivex/rxjava3/core/Observer;)V
      57: return
}
