Compiled from "ObservableWindowBoundary.java"
public final class io.reactivex.rxjava3.internal.operators.observable.ObservableWindowBoundary<T, B> extends io.reactivex.rxjava3.internal.operators.observable.AbstractObservableWithUpstream<T, io.reactivex.rxjava3.core.Observable<T>> {
  final io.reactivex.rxjava3.core.ObservableSource<B> other;

  final int capacityHint;

  public io.reactivex.rxjava3.internal.operators.observable.ObservableWindowBoundary(io.reactivex.rxjava3.core.ObservableSource<T>, io.reactivex.rxjava3.core.ObservableSource<B>, int);
    Code:
       0: aload_0
       1: aload_1
       2: invokespecial #1                  // Method io/reactivex/rxjava3/internal/operators/observable/AbstractObservableWithUpstream."<init>":(Lio/reactivex/rxjava3/core/ObservableSource;)V
       5: aload_0
       6: aload_2
       7: putfield      #2                  // Field other:Lio/reactivex/rxjava3/core/ObservableSource;
      10: aload_0
      11: iload_3
      12: putfield      #3                  // Field capacityHint:I
      15: return

  public void subscribeActual(io.reactivex.rxjava3.core.Observer<? super io.reactivex.rxjava3.core.Observable<T>>);
    Code:
       0: new           #4                  // class io/reactivex/rxjava3/internal/operators/observable/ObservableWindowBoundary$WindowBoundaryMainObserver
       3: dup
       4: aload_1
       5: aload_0
       6: getfield      #3                  // Field capacityHint:I
       9: invokespecial #5                  // Method io/reactivex/rxjava3/internal/operators/observable/ObservableWindowBoundary$WindowBoundaryMainObserver."<init>":(Lio/reactivex/rxjava3/core/Observer;I)V
      12: astore_2
      13: aload_1
      14: aload_2
      15: invokeinterface #6,  2            // InterfaceMethod io/reactivex/rxjava3/core/Observer.onSubscribe:(Lio/reactivex/rxjava3/disposables/Disposable;)V
      20: aload_0
      21: getfield      #2                  // Field other:Lio/reactivex/rxjava3/core/ObservableSource;
      24: aload_2
      25: getfield      #7                  // Field io/reactivex/rxjava3/internal/operators/observable/ObservableWindowBoundary$WindowBoundaryMainObserver.boundaryObserver:Lio/reactivex/rxjava3/internal/operators/observable/ObservableWindowBoundary$WindowBoundaryInnerObserver;
      28: invokeinterface #8,  2            // InterfaceMethod io/reactivex/rxjava3/core/ObservableSource.subscribe:(Lio/reactivex/rxjava3/core/Observer;)V
      33: aload_0
      34: getfield      #9                  // Field source:Lio/reactivex/rxjava3/core/ObservableSource;
      37: aload_2
      38: invokeinterface #8,  2            // InterfaceMethod io/reactivex/rxjava3/core/ObservableSource.subscribe:(Lio/reactivex/rxjava3/core/Observer;)V
      43: return
}
