Compiled from "ObservableCreate.java"
public final class io.reactivex.rxjava3.internal.operators.observable.ObservableCreate<T> extends io.reactivex.rxjava3.core.Observable<T> {
  final io.reactivex.rxjava3.core.ObservableOnSubscribe<T> source;

  public io.reactivex.rxjava3.internal.operators.observable.ObservableCreate(io.reactivex.rxjava3.core.ObservableOnSubscribe<T>);
    Code:
       0: aload_0
       1: invokespecial #1                  // Method io/reactivex/rxjava3/core/Observable."<init>":()V
       4: aload_0
       5: aload_1
       6: putfield      #2                  // Field source:Lio/reactivex/rxjava3/core/ObservableOnSubscribe;
       9: return

  protected void subscribeActual(io.reactivex.rxjava3.core.Observer<? super T>);
    Code:
       0: new           #3                  // class io/reactivex/rxjava3/internal/operators/observable/ObservableCreate$CreateEmitter
       3: dup
       4: aload_1
       5: invokespecial #4                  // Method io/reactivex/rxjava3/internal/operators/observable/ObservableCreate$CreateEmitter."<init>":(Lio/reactivex/rxjava3/core/Observer;)V
       8: astore_2
       9: aload_1
      10: aload_2
      11: invokeinterface #5,  2            // InterfaceMethod io/reactivex/rxjava3/core/Observer.onSubscribe:(Lio/reactivex/rxjava3/disposables/Disposable;)V
      16: aload_0
      17: getfield      #2                  // Field source:Lio/reactivex/rxjava3/core/ObservableOnSubscribe;
      20: aload_2
      21: invokeinterface #6,  2            // InterfaceMethod io/reactivex/rxjava3/core/ObservableOnSubscribe.subscribe:(Lio/reactivex/rxjava3/core/ObservableEmitter;)V
      26: goto          39
      29: astore_3
      30: aload_3
      31: invokestatic  #8                  // Method io/reactivex/rxjava3/exceptions/Exceptions.throwIfFatal:(Ljava/lang/Throwable;)V
      34: aload_2
      35: aload_3
      36: invokevirtual #9                  // Method io/reactivex/rxjava3/internal/operators/observable/ObservableCreate$CreateEmitter.onError:(Ljava/lang/Throwable;)V
      39: return
    Exception table:
       from    to  target type
          16    26    29   Class java/lang/Throwable
}
