Compiled from "ObservableCollectSingle.java"
public final class io.reactivex.rxjava3.internal.operators.observable.ObservableCollectSingle<T, U> extends io.reactivex.rxjava3.core.Single<U> implements io.reactivex.rxjava3.internal.fuseable.FuseToObservable<U> {
  final io.reactivex.rxjava3.core.ObservableSource<T> source;

  final io.reactivex.rxjava3.functions.Supplier<? extends U> initialSupplier;

  final io.reactivex.rxjava3.functions.BiConsumer<? super U, ? super T> collector;

  public io.reactivex.rxjava3.internal.operators.observable.ObservableCollectSingle(io.reactivex.rxjava3.core.ObservableSource<T>, io.reactivex.rxjava3.functions.Supplier<? extends U>, io.reactivex.rxjava3.functions.BiConsumer<? super U, ? super T>);
    Code:
       0: aload_0
       1: invokespecial #1                  // Method io/reactivex/rxjava3/core/Single."<init>":()V
       4: aload_0
       5: aload_1
       6: putfield      #2                  // Field source:Lio/reactivex/rxjava3/core/ObservableSource;
       9: aload_0
      10: aload_2
      11: putfield      #3                  // Field initialSupplier:Lio/reactivex/rxjava3/functions/Supplier;
      14: aload_0
      15: aload_3
      16: putfield      #4                  // Field collector:Lio/reactivex/rxjava3/functions/BiConsumer;
      19: return

  protected void subscribeActual(io.reactivex.rxjava3.core.SingleObserver<? super U>);
    Code:
       0: aload_0
       1: getfield      #3                  // Field initialSupplier:Lio/reactivex/rxjava3/functions/Supplier;
       4: invokeinterface #5,  1            // InterfaceMethod io/reactivex/rxjava3/functions/Supplier.get:()Ljava/lang/Object;
       9: ldc           #6                  // String The initialSupplier returned a null value
      11: invokestatic  #7                  // Method java/util/Objects.requireNonNull:(Ljava/lang/Object;Ljava/lang/String;)Ljava/lang/Object;
      14: astore_2
      15: goto          29
      18: astore_3
      19: aload_3
      20: invokestatic  #9                  // Method io/reactivex/rxjava3/exceptions/Exceptions.throwIfFatal:(Ljava/lang/Throwable;)V
      23: aload_3
      24: aload_1
      25: invokestatic  #10                 // Method io/reactivex/rxjava3/internal/disposables/EmptyDisposable.error:(Ljava/lang/Throwable;Lio/reactivex/rxjava3/core/SingleObserver;)V
      28: return
      29: aload_0
      30: getfield      #2                  // Field source:Lio/reactivex/rxjava3/core/ObservableSource;
      33: new           #11                 // class io/reactivex/rxjava3/internal/operators/observable/ObservableCollectSingle$CollectObserver
      36: dup
      37: aload_1
      38: aload_2
      39: aload_0
      40: getfield      #4                  // Field collector:Lio/reactivex/rxjava3/functions/BiConsumer;
      43: invokespecial #12                 // Method io/reactivex/rxjava3/internal/operators/observable/ObservableCollectSingle$CollectObserver."<init>":(Lio/reactivex/rxjava3/core/SingleObserver;Ljava/lang/Object;Lio/reactivex/rxjava3/functions/BiConsumer;)V
      46: invokeinterface #13,  2           // InterfaceMethod io/reactivex/rxjava3/core/ObservableSource.subscribe:(Lio/reactivex/rxjava3/core/Observer;)V
      51: return
    Exception table:
       from    to  target type
           0    15    18   Class java/lang/Throwable

  public io.reactivex.rxjava3.core.Observable<U> fuseToObservable();
    Code:
       0: new           #14                 // class io/reactivex/rxjava3/internal/operators/observable/ObservableCollect
       3: dup
       4: aload_0
       5: getfield      #2                  // Field source:Lio/reactivex/rxjava3/core/ObservableSource;
       8: aload_0
       9: getfield      #3                  // Field initialSupplier:Lio/reactivex/rxjava3/functions/Supplier;
      12: aload_0
      13: getfield      #4                  // Field collector:Lio/reactivex/rxjava3/functions/BiConsumer;
      16: invokespecial #15                 // Method io/reactivex/rxjava3/internal/operators/observable/ObservableCollect."<init>":(Lio/reactivex/rxjava3/core/ObservableSource;Lio/reactivex/rxjava3/functions/Supplier;Lio/reactivex/rxjava3/functions/BiConsumer;)V
      19: invokestatic  #16                 // Method io/reactivex/rxjava3/plugins/RxJavaPlugins.onAssembly:(Lio/reactivex/rxjava3/core/Observable;)Lio/reactivex/rxjava3/core/Observable;
      22: areturn
}
