Compiled from "ObservableFlatMapCompletableCompletable.java"
final class io.reactivex.rxjava3.internal.operators.observable.ObservableFlatMapCompletableCompletable$FlatMapCompletableMainObserver<T> extends java.util.concurrent.atomic.AtomicInteger implements io.reactivex.rxjava3.disposables.Disposable, io.reactivex.rxjava3.core.Observer<T> {
  private static final long serialVersionUID;

  final io.reactivex.rxjava3.core.CompletableObserver downstream;

  final io.reactivex.rxjava3.internal.util.AtomicThrowable errors;

  final io.reactivex.rxjava3.functions.Function<? super T, ? extends io.reactivex.rxjava3.core.CompletableSource> mapper;

  final boolean delayErrors;

  final io.reactivex.rxjava3.disposables.CompositeDisposable set;

  io.reactivex.rxjava3.disposables.Disposable upstream;

  volatile boolean disposed;

  io.reactivex.rxjava3.internal.operators.observable.ObservableFlatMapCompletableCompletable$FlatMapCompletableMainObserver(io.reactivex.rxjava3.core.CompletableObserver, io.reactivex.rxjava3.functions.Function<? super T, ? extends io.reactivex.rxjava3.core.CompletableSource>, boolean);
    Code:
       0: aload_0
       1: invokespecial #1                  // Method java/util/concurrent/atomic/AtomicInteger."<init>":()V
       4: aload_0
       5: aload_1
       6: putfield      #2                  // Field downstream:Lio/reactivex/rxjava3/core/CompletableObserver;
       9: aload_0
      10: aload_2
      11: putfield      #3                  // Field mapper:Lio/reactivex/rxjava3/functions/Function;
      14: aload_0
      15: iload_3
      16: putfield      #4                  // Field delayErrors:Z
      19: aload_0
      20: new           #5                  // class io/reactivex/rxjava3/internal/util/AtomicThrowable
      23: dup
      24: invokespecial #6                  // Method io/reactivex/rxjava3/internal/util/AtomicThrowable."<init>":()V
      27: putfield      #7                  // Field errors:Lio/reactivex/rxjava3/internal/util/AtomicThrowable;
      30: aload_0
      31: new           #8                  // class io/reactivex/rxjava3/disposables/CompositeDisposable
      34: dup
      35: invokespecial #9                  // Method io/reactivex/rxjava3/disposables/CompositeDisposable."<init>":()V
      38: putfield      #10                 // Field set:Lio/reactivex/rxjava3/disposables/CompositeDisposable;
      41: aload_0
      42: iconst_1
      43: invokevirtual #11                 // Method lazySet:(I)V
      46: return

  public void onSubscribe(io.reactivex.rxjava3.disposables.Disposable);
    Code:
       0: aload_0
       1: getfield      #12                 // Field upstream:Lio/reactivex/rxjava3/disposables/Disposable;
       4: aload_1
       5: invokestatic  #13                 // Method io/reactivex/rxjava3/internal/disposables/DisposableHelper.validate:(Lio/reactivex/rxjava3/disposables/Disposable;Lio/reactivex/rxjava3/disposables/Disposable;)Z
       8: ifeq          26
      11: aload_0
      12: aload_1
      13: putfield      #12                 // Field upstream:Lio/reactivex/rxjava3/disposables/Disposable;
      16: aload_0
      17: getfield      #2                  // Field downstream:Lio/reactivex/rxjava3/core/CompletableObserver;
      20: aload_0
      21: invokeinterface #14,  2           // InterfaceMethod io/reactivex/rxjava3/core/CompletableObserver.onSubscribe:(Lio/reactivex/rxjava3/disposables/Disposable;)V
      26: return

  public void onNext(T);
    Code:
       0: aload_0
       1: getfield      #3                  // Field mapper:Lio/reactivex/rxjava3/functions/Function;
       4: aload_1
       5: invokeinterface #15,  2           // InterfaceMethod io/reactivex/rxjava3/functions/Function.apply:(Ljava/lang/Object;)Ljava/lang/Object;
      10: ldc           #16                 // String The mapper returned a null CompletableSource
      12: invokestatic  #17                 // Method java/util/Objects.requireNonNull:(Ljava/lang/Object;Ljava/lang/String;)Ljava/lang/Object;
      15: checkcast     #18                 // class io/reactivex/rxjava3/core/CompletableSource
      18: astore_2
      19: goto          42
      22: astore_3
      23: aload_3
      24: invokestatic  #20                 // Method io/reactivex/rxjava3/exceptions/Exceptions.throwIfFatal:(Ljava/lang/Throwable;)V
      27: aload_0
      28: getfield      #12                 // Field upstream:Lio/reactivex/rxjava3/disposables/Disposable;
      31: invokeinterface #21,  1           // InterfaceMethod io/reactivex/rxjava3/disposables/Disposable.dispose:()V
      36: aload_0
      37: aload_3
      38: invokevirtual #22                 // Method onError:(Ljava/lang/Throwable;)V
      41: return
      42: aload_0
      43: invokevirtual #23                 // Method getAndIncrement:()I
      46: pop
      47: new           #24                 // class io/reactivex/rxjava3/internal/operators/observable/ObservableFlatMapCompletableCompletable$FlatMapCompletableMainObserver$InnerObserver
      50: dup
      51: aload_0
      52: invokespecial #25                 // Method io/reactivex/rxjava3/internal/operators/observable/ObservableFlatMapCompletableCompletable$FlatMapCompletableMainObserver$InnerObserver."<init>":(Lio/reactivex/rxjava3/internal/operators/observable/ObservableFlatMapCompletableCompletable$FlatMapCompletableMainObserver;)V
      55: astore_3
      56: aload_0
      57: getfield      #26                 // Field disposed:Z
      60: ifne          81
      63: aload_0
      64: getfield      #10                 // Field set:Lio/reactivex/rxjava3/disposables/CompositeDisposable;
      67: aload_3
      68: invokevirtual #27                 // Method io/reactivex/rxjava3/disposables/CompositeDisposable.add:(Lio/reactivex/rxjava3/disposables/Disposable;)Z
      71: ifeq          81
      74: aload_2
      75: aload_3
      76: invokeinterface #28,  2           // InterfaceMethod io/reactivex/rxjava3/core/CompletableSource.subscribe:(Lio/reactivex/rxjava3/core/CompletableObserver;)V
      81: return
    Exception table:
       from    to  target type
           0    19    22   Class java/lang/Throwable

  public void onError(java.lang.Throwable);
    Code:
       0: aload_0
       1: getfield      #7                  // Field errors:Lio/reactivex/rxjava3/internal/util/AtomicThrowable;
       4: aload_1
       5: invokevirtual #29                 // Method io/reactivex/rxjava3/internal/util/AtomicThrowable.tryAddThrowableOrReport:(Ljava/lang/Throwable;)Z
       8: ifeq          71
      11: aload_0
      12: getfield      #4                  // Field delayErrors:Z
      15: ifeq          39
      18: aload_0
      19: invokevirtual #30                 // Method decrementAndGet:()I
      22: ifne          71
      25: aload_0
      26: getfield      #7                  // Field errors:Lio/reactivex/rxjava3/internal/util/AtomicThrowable;
      29: aload_0
      30: getfield      #2                  // Field downstream:Lio/reactivex/rxjava3/core/CompletableObserver;
      33: invokevirtual #31                 // Method io/reactivex/rxjava3/internal/util/AtomicThrowable.tryTerminateConsumer:(Lio/reactivex/rxjava3/core/CompletableObserver;)V
      36: goto          71
      39: aload_0
      40: iconst_1
      41: putfield      #26                 // Field disposed:Z
      44: aload_0
      45: getfield      #12                 // Field upstream:Lio/reactivex/rxjava3/disposables/Disposable;
      48: invokeinterface #21,  1           // InterfaceMethod io/reactivex/rxjava3/disposables/Disposable.dispose:()V
      53: aload_0
      54: getfield      #10                 // Field set:Lio/reactivex/rxjava3/disposables/CompositeDisposable;
      57: invokevirtual #32                 // Method io/reactivex/rxjava3/disposables/CompositeDisposable.dispose:()V
      60: aload_0
      61: getfield      #7                  // Field errors:Lio/reactivex/rxjava3/internal/util/AtomicThrowable;
      64: aload_0
      65: getfield      #2                  // Field downstream:Lio/reactivex/rxjava3/core/CompletableObserver;
      68: invokevirtual #31                 // Method io/reactivex/rxjava3/internal/util/AtomicThrowable.tryTerminateConsumer:(Lio/reactivex/rxjava3/core/CompletableObserver;)V
      71: return

  public void onComplete();
    Code:
       0: aload_0
       1: invokevirtual #30                 // Method decrementAndGet:()I
       4: ifne          18
       7: aload_0
       8: getfield      #7                  // Field errors:Lio/reactivex/rxjava3/internal/util/AtomicThrowable;
      11: aload_0
      12: getfield      #2                  // Field downstream:Lio/reactivex/rxjava3/core/CompletableObserver;
      15: invokevirtual #31                 // Method io/reactivex/rxjava3/internal/util/AtomicThrowable.tryTerminateConsumer:(Lio/reactivex/rxjava3/core/CompletableObserver;)V
      18: return

  public void dispose();
    Code:
       0: aload_0
       1: iconst_1
       2: putfield      #26                 // Field disposed:Z
       5: aload_0
       6: getfield      #12                 // Field upstream:Lio/reactivex/rxjava3/disposables/Disposable;
       9: invokeinterface #21,  1           // InterfaceMethod io/reactivex/rxjava3/disposables/Disposable.dispose:()V
      14: aload_0
      15: getfield      #10                 // Field set:Lio/reactivex/rxjava3/disposables/CompositeDisposable;
      18: invokevirtual #32                 // Method io/reactivex/rxjava3/disposables/CompositeDisposable.dispose:()V
      21: aload_0
      22: getfield      #7                  // Field errors:Lio/reactivex/rxjava3/internal/util/AtomicThrowable;
      25: invokevirtual #33                 // Method io/reactivex/rxjava3/internal/util/AtomicThrowable.tryTerminateAndReport:()V
      28: return

  public boolean isDisposed();
    Code:
       0: aload_0
       1: getfield      #12                 // Field upstream:Lio/reactivex/rxjava3/disposables/Disposable;
       4: invokeinterface #34,  1           // InterfaceMethod io/reactivex/rxjava3/disposables/Disposable.isDisposed:()Z
       9: ireturn

  void innerComplete(io.reactivex.rxjava3.internal.operators.observable.ObservableFlatMapCompletableCompletable$FlatMapCompletableMainObserver<T>.InnerObserver);
    Code:
       0: aload_0
       1: getfield      #10                 // Field set:Lio/reactivex/rxjava3/disposables/CompositeDisposable;
       4: aload_1
       5: invokevirtual #35                 // Method io/reactivex/rxjava3/disposables/CompositeDisposable.delete:(Lio/reactivex/rxjava3/disposables/Disposable;)Z
       8: pop
       9: aload_0
      10: invokevirtual #36                 // Method onComplete:()V
      13: return

  void innerError(io.reactivex.rxjava3.internal.operators.observable.ObservableFlatMapCompletableCompletable$FlatMapCompletableMainObserver<T>.InnerObserver, java.lang.Throwable);
    Code:
       0: aload_0
       1: getfield      #10                 // Field set:Lio/reactivex/rxjava3/disposables/CompositeDisposable;
       4: aload_1
       5: invokevirtual #35                 // Method io/reactivex/rxjava3/disposables/CompositeDisposable.delete:(Lio/reactivex/rxjava3/disposables/Disposable;)Z
       8: pop
       9: aload_0
      10: aload_2
      11: invokevirtual #22                 // Method onError:(Ljava/lang/Throwable;)V
      14: return
}
