Compiled from "ObservableMergeWithCompletable.java"
final class io.reactivex.rxjava3.internal.operators.observable.ObservableMergeWithCompletable$MergeWithObserver<T> extends java.util.concurrent.atomic.AtomicInteger implements io.reactivex.rxjava3.core.Observer<T>, io.reactivex.rxjava3.disposables.Disposable {
  private static final long serialVersionUID;

  final io.reactivex.rxjava3.core.Observer<? super T> downstream;

  final java.util.concurrent.atomic.AtomicReference<io.reactivex.rxjava3.disposables.Disposable> mainDisposable;

  final io.reactivex.rxjava3.internal.operators.observable.ObservableMergeWithCompletable$MergeWithObserver$OtherObserver otherObserver;

  final io.reactivex.rxjava3.internal.util.AtomicThrowable errors;

  volatile boolean mainDone;

  volatile boolean otherDone;

  io.reactivex.rxjava3.internal.operators.observable.ObservableMergeWithCompletable$MergeWithObserver(io.reactivex.rxjava3.core.Observer<? super T>);
    Code:
       0: aload_0
       1: invokespecial #1                  // Method java/util/concurrent/atomic/AtomicInteger."<init>":()V
       4: aload_0
       5: aload_1
       6: putfield      #2                  // Field downstream:Lio/reactivex/rxjava3/core/Observer;
       9: aload_0
      10: new           #3                  // class java/util/concurrent/atomic/AtomicReference
      13: dup
      14: invokespecial #4                  // Method java/util/concurrent/atomic/AtomicReference."<init>":()V
      17: putfield      #5                  // Field mainDisposable:Ljava/util/concurrent/atomic/AtomicReference;
      20: aload_0
      21: new           #6                  // class io/reactivex/rxjava3/internal/operators/observable/ObservableMergeWithCompletable$MergeWithObserver$OtherObserver
      24: dup
      25: aload_0
      26: invokespecial #7                  // Method io/reactivex/rxjava3/internal/operators/observable/ObservableMergeWithCompletable$MergeWithObserver$OtherObserver."<init>":(Lio/reactivex/rxjava3/internal/operators/observable/ObservableMergeWithCompletable$MergeWithObserver;)V
      29: putfield      #8                  // Field otherObserver:Lio/reactivex/rxjava3/internal/operators/observable/ObservableMergeWithCompletable$MergeWithObserver$OtherObserver;
      32: aload_0
      33: new           #9                  // class io/reactivex/rxjava3/internal/util/AtomicThrowable
      36: dup
      37: invokespecial #10                 // Method io/reactivex/rxjava3/internal/util/AtomicThrowable."<init>":()V
      40: putfield      #11                 // Field errors:Lio/reactivex/rxjava3/internal/util/AtomicThrowable;
      43: return

  public void onSubscribe(io.reactivex.rxjava3.disposables.Disposable);
    Code:
       0: aload_0
       1: getfield      #5                  // Field mainDisposable:Ljava/util/concurrent/atomic/AtomicReference;
       4: aload_1
       5: invokestatic  #12                 // Method io/reactivex/rxjava3/internal/disposables/DisposableHelper.setOnce:(Ljava/util/concurrent/atomic/AtomicReference;Lio/reactivex/rxjava3/disposables/Disposable;)Z
       8: pop
       9: return

  public void onNext(T);
    Code:
       0: aload_0
       1: getfield      #2                  // Field downstream:Lio/reactivex/rxjava3/core/Observer;
       4: aload_1
       5: aload_0
       6: aload_0
       7: getfield      #11                 // Field errors:Lio/reactivex/rxjava3/internal/util/AtomicThrowable;
      10: invokestatic  #13                 // Method io/reactivex/rxjava3/internal/util/HalfSerializer.onNext:(Lio/reactivex/rxjava3/core/Observer;Ljava/lang/Object;Ljava/util/concurrent/atomic/AtomicInteger;Lio/reactivex/rxjava3/internal/util/AtomicThrowable;)V
      13: return

  public void onError(java.lang.Throwable);
    Code:
       0: aload_0
       1: getfield      #8                  // Field otherObserver:Lio/reactivex/rxjava3/internal/operators/observable/ObservableMergeWithCompletable$MergeWithObserver$OtherObserver;
       4: invokestatic  #14                 // Method io/reactivex/rxjava3/internal/disposables/DisposableHelper.dispose:(Ljava/util/concurrent/atomic/AtomicReference;)Z
       7: pop
       8: aload_0
       9: getfield      #2                  // Field downstream:Lio/reactivex/rxjava3/core/Observer;
      12: aload_1
      13: aload_0
      14: aload_0
      15: getfield      #11                 // Field errors:Lio/reactivex/rxjava3/internal/util/AtomicThrowable;
      18: invokestatic  #15                 // Method io/reactivex/rxjava3/internal/util/HalfSerializer.onError:(Lio/reactivex/rxjava3/core/Observer;Ljava/lang/Throwable;Ljava/util/concurrent/atomic/AtomicInteger;Lio/reactivex/rxjava3/internal/util/AtomicThrowable;)V
      21: return

  public void onComplete();
    Code:
       0: aload_0
       1: iconst_1
       2: putfield      #16                 // Field mainDone:Z
       5: aload_0
       6: getfield      #17                 // Field otherDone:Z
       9: ifeq          24
      12: aload_0
      13: getfield      #2                  // Field downstream:Lio/reactivex/rxjava3/core/Observer;
      16: aload_0
      17: aload_0
      18: getfield      #11                 // Field errors:Lio/reactivex/rxjava3/internal/util/AtomicThrowable;
      21: invokestatic  #18                 // Method io/reactivex/rxjava3/internal/util/HalfSerializer.onComplete:(Lio/reactivex/rxjava3/core/Observer;Ljava/util/concurrent/atomic/AtomicInteger;Lio/reactivex/rxjava3/internal/util/AtomicThrowable;)V
      24: return

  public boolean isDisposed();
    Code:
       0: aload_0
       1: getfield      #5                  // Field mainDisposable:Ljava/util/concurrent/atomic/AtomicReference;
       4: invokevirtual #19                 // Method java/util/concurrent/atomic/AtomicReference.get:()Ljava/lang/Object;
       7: checkcast     #20                 // class io/reactivex/rxjava3/disposables/Disposable
      10: invokestatic  #21                 // Method io/reactivex/rxjava3/internal/disposables/DisposableHelper.isDisposed:(Lio/reactivex/rxjava3/disposables/Disposable;)Z
      13: ireturn

  public void dispose();
    Code:
       0: aload_0
       1: getfield      #5                  // Field mainDisposable:Ljava/util/concurrent/atomic/AtomicReference;
       4: invokestatic  #14                 // Method io/reactivex/rxjava3/internal/disposables/DisposableHelper.dispose:(Ljava/util/concurrent/atomic/AtomicReference;)Z
       7: pop
       8: aload_0
       9: getfield      #8                  // Field otherObserver:Lio/reactivex/rxjava3/internal/operators/observable/ObservableMergeWithCompletable$MergeWithObserver$OtherObserver;
      12: invokestatic  #14                 // Method io/reactivex/rxjava3/internal/disposables/DisposableHelper.dispose:(Ljava/util/concurrent/atomic/AtomicReference;)Z
      15: pop
      16: aload_0
      17: getfield      #11                 // Field errors:Lio/reactivex/rxjava3/internal/util/AtomicThrowable;
      20: invokevirtual #22                 // Method io/reactivex/rxjava3/internal/util/AtomicThrowable.tryTerminateAndReport:()V
      23: return

  void otherError(java.lang.Throwable);
    Code:
       0: aload_0
       1: getfield      #5                  // Field mainDisposable:Ljava/util/concurrent/atomic/AtomicReference;
       4: invokestatic  #14                 // Method io/reactivex/rxjava3/internal/disposables/DisposableHelper.dispose:(Ljava/util/concurrent/atomic/AtomicReference;)Z
       7: pop
       8: aload_0
       9: getfield      #2                  // Field downstream:Lio/reactivex/rxjava3/core/Observer;
      12: aload_1
      13: aload_0
      14: aload_0
      15: getfield      #11                 // Field errors:Lio/reactivex/rxjava3/internal/util/AtomicThrowable;
      18: invokestatic  #15                 // Method io/reactivex/rxjava3/internal/util/HalfSerializer.onError:(Lio/reactivex/rxjava3/core/Observer;Ljava/lang/Throwable;Ljava/util/concurrent/atomic/AtomicInteger;Lio/reactivex/rxjava3/internal/util/AtomicThrowable;)V
      21: return

  void otherComplete();
    Code:
       0: aload_0
       1: iconst_1
       2: putfield      #17                 // Field otherDone:Z
       5: aload_0
       6: getfield      #16                 // Field mainDone:Z
       9: ifeq          24
      12: aload_0
      13: getfield      #2                  // Field downstream:Lio/reactivex/rxjava3/core/Observer;
      16: aload_0
      17: aload_0
      18: getfield      #11                 // Field errors:Lio/reactivex/rxjava3/internal/util/AtomicThrowable;
      21: invokestatic  #18                 // Method io/reactivex/rxjava3/internal/util/HalfSerializer.onComplete:(Lio/reactivex/rxjava3/core/Observer;Ljava/util/concurrent/atomic/AtomicInteger;Lio/reactivex/rxjava3/internal/util/AtomicThrowable;)V
      24: return
}
