Compiled from "ObservableTimeInterval.java"
final class io.reactivex.rxjava3.internal.operators.observable.ObservableTimeInterval$TimeIntervalObserver<T> implements io.reactivex.rxjava3.core.Observer<T>, io.reactivex.rxjava3.disposables.Disposable {
  final io.reactivex.rxjava3.core.Observer<? super io.reactivex.rxjava3.schedulers.Timed<T>> downstream;

  final java.util.concurrent.TimeUnit unit;

  final io.reactivex.rxjava3.core.Scheduler scheduler;

  long lastTime;

  io.reactivex.rxjava3.disposables.Disposable upstream;

  io.reactivex.rxjava3.internal.operators.observable.ObservableTimeInterval$TimeIntervalObserver(io.reactivex.rxjava3.core.Observer<? super io.reactivex.rxjava3.schedulers.Timed<T>>, java.util.concurrent.TimeUnit, io.reactivex.rxjava3.core.Scheduler);
    Code:
       0: aload_0
       1: invokespecial #1                  // Method java/lang/Object."<init>":()V
       4: aload_0
       5: aload_1
       6: putfield      #2                  // Field downstream:Lio/reactivex/rxjava3/core/Observer;
       9: aload_0
      10: aload_3
      11: putfield      #3                  // Field scheduler:Lio/reactivex/rxjava3/core/Scheduler;
      14: aload_0
      15: aload_2
      16: putfield      #4                  // Field unit:Ljava/util/concurrent/TimeUnit;
      19: return

  public void onSubscribe(io.reactivex.rxjava3.disposables.Disposable);
    Code:
       0: aload_0
       1: getfield      #5                  // Field upstream:Lio/reactivex/rxjava3/disposables/Disposable;
       4: aload_1
       5: invokestatic  #6                  // Method io/reactivex/rxjava3/internal/disposables/DisposableHelper.validate:(Lio/reactivex/rxjava3/disposables/Disposable;Lio/reactivex/rxjava3/disposables/Disposable;)Z
       8: ifeq          41
      11: aload_0
      12: aload_1
      13: putfield      #5                  // Field upstream:Lio/reactivex/rxjava3/disposables/Disposable;
      16: aload_0
      17: aload_0
      18: getfield      #3                  // Field scheduler:Lio/reactivex/rxjava3/core/Scheduler;
      21: aload_0
      22: getfield      #4                  // Field unit:Ljava/util/concurrent/TimeUnit;
      25: invokevirtual #7                  // Method io/reactivex/rxjava3/core/Scheduler.now:(Ljava/util/concurrent/TimeUnit;)J
      28: putfield      #8                  // Field lastTime:J
      31: aload_0
      32: getfield      #2                  // Field downstream:Lio/reactivex/rxjava3/core/Observer;
      35: aload_0
      36: invokeinterface #9,  2            // InterfaceMethod io/reactivex/rxjava3/core/Observer.onSubscribe:(Lio/reactivex/rxjava3/disposables/Disposable;)V
      41: return

  public void dispose();
    Code:
       0: aload_0
       1: getfield      #5                  // Field upstream:Lio/reactivex/rxjava3/disposables/Disposable;
       4: invokeinterface #10,  1           // InterfaceMethod io/reactivex/rxjava3/disposables/Disposable.dispose:()V
       9: return

  public boolean isDisposed();
    Code:
       0: aload_0
       1: getfield      #5                  // Field upstream:Lio/reactivex/rxjava3/disposables/Disposable;
       4: invokeinterface #11,  1           // InterfaceMethod io/reactivex/rxjava3/disposables/Disposable.isDisposed:()Z
       9: ireturn

  public void onNext(T);
    Code:
       0: aload_0
       1: getfield      #3                  // Field scheduler:Lio/reactivex/rxjava3/core/Scheduler;
       4: aload_0
       5: getfield      #4                  // Field unit:Ljava/util/concurrent/TimeUnit;
       8: invokevirtual #7                  // Method io/reactivex/rxjava3/core/Scheduler.now:(Ljava/util/concurrent/TimeUnit;)J
      11: lstore_2
      12: aload_0
      13: getfield      #8                  // Field lastTime:J
      16: lstore        4
      18: aload_0
      19: lload_2
      20: putfield      #8                  // Field lastTime:J
      23: lload_2
      24: lload         4
      26: lsub
      27: lstore        6
      29: aload_0
      30: getfield      #2                  // Field downstream:Lio/reactivex/rxjava3/core/Observer;
      33: new           #12                 // class io/reactivex/rxjava3/schedulers/Timed
      36: dup
      37: aload_1
      38: lload         6
      40: aload_0
      41: getfield      #4                  // Field unit:Ljava/util/concurrent/TimeUnit;
      44: invokespecial #13                 // Method io/reactivex/rxjava3/schedulers/Timed."<init>":(Ljava/lang/Object;JLjava/util/concurrent/TimeUnit;)V
      47: invokeinterface #14,  2           // InterfaceMethod io/reactivex/rxjava3/core/Observer.onNext:(Ljava/lang/Object;)V
      52: return

  public void onError(java.lang.Throwable);
    Code:
       0: aload_0
       1: getfield      #2                  // Field downstream:Lio/reactivex/rxjava3/core/Observer;
       4: aload_1
       5: invokeinterface #15,  2           // InterfaceMethod io/reactivex/rxjava3/core/Observer.onError:(Ljava/lang/Throwable;)V
      10: return

  public void onComplete();
    Code:
       0: aload_0
       1: getfield      #2                  // Field downstream:Lio/reactivex/rxjava3/core/Observer;
       4: invokeinterface #16,  1           // InterfaceMethod io/reactivex/rxjava3/core/Observer.onComplete:()V
       9: return
}
