Compiled from "ObservableSampleWithObservable.java"
final class io.reactivex.rxjava3.internal.operators.observable.ObservableSampleWithObservable$SamplerObserver<T> implements io.reactivex.rxjava3.core.Observer<java.lang.Object> {
  final io.reactivex.rxjava3.internal.operators.observable.ObservableSampleWithObservable$SampleMainObserver<T> parent;

  io.reactivex.rxjava3.internal.operators.observable.ObservableSampleWithObservable$SamplerObserver(io.reactivex.rxjava3.internal.operators.observable.ObservableSampleWithObservable$SampleMainObserver<T>);
    Code:
       0: aload_0
       1: invokespecial #1                  // Method java/lang/Object."<init>":()V
       4: aload_0
       5: aload_1
       6: putfield      #2                  // Field parent:Lio/reactivex/rxjava3/internal/operators/observable/ObservableSampleWithObservable$SampleMainObserver;
       9: return

  public void onSubscribe(io.reactivex.rxjava3.disposables.Disposable);
    Code:
       0: aload_0
       1: getfield      #2                  // Field parent:Lio/reactivex/rxjava3/internal/operators/observable/ObservableSampleWithObservable$SampleMainObserver;
       4: aload_1
       5: invokevirtual #3                  // Method io/reactivex/rxjava3/internal/operators/observable/ObservableSampleWithObservable$SampleMainObserver.setOther:(Lio/reactivex/rxjava3/disposables/Disposable;)Z
       8: pop
       9: return

  public void onNext(java.lang.Object);
    Code:
       0: aload_0
       1: getfield      #2                  // Field parent:Lio/reactivex/rxjava3/internal/operators/observable/ObservableSampleWithObservable$SampleMainObserver;
       4: invokevirtual #4                  // Method io/reactivex/rxjava3/internal/operators/observable/ObservableSampleWithObservable$SampleMainObserver.run:()V
       7: return

  public void onError(java.lang.Throwable);
    Code:
       0: aload_0
       1: getfield      #2                  // Field parent:Lio/reactivex/rxjava3/internal/operators/observable/ObservableSampleWithObservable$SampleMainObserver;
       4: aload_1
       5: invokevirtual #5                  // Method io/reactivex/rxjava3/internal/operators/observable/ObservableSampleWithObservable$SampleMainObserver.error:(Ljava/lang/Throwable;)V
       8: return

  public void onComplete();
    Code:
       0: aload_0
       1: getfield      #2                  // Field parent:Lio/reactivex/rxjava3/internal/operators/observable/ObservableSampleWithObservable$SampleMainObserver;
       4: invokevirtual #6                  // Method io/reactivex/rxjava3/internal/operators/observable/ObservableSampleWithObservable$SampleMainObserver.complete:()V
       7: return
}
