Compiled from "ObservableReplay.java"
final class io.reactivex.rxjava3.internal.operators.observable.ObservableReplay$InnerDisposable<T> extends java.util.concurrent.atomic.AtomicInteger implements io.reactivex.rxjava3.disposables.Disposable {
  private static final long serialVersionUID;

  final io.reactivex.rxjava3.internal.operators.observable.ObservableReplay$ReplayObserver<T> parent;

  final io.reactivex.rxjava3.core.Observer<? super T> child;

  java.lang.Object index;

  volatile boolean cancelled;

  io.reactivex.rxjava3.internal.operators.observable.ObservableReplay$InnerDisposable(io.reactivex.rxjava3.internal.operators.observable.ObservableReplay$ReplayObserver<T>, io.reactivex.rxjava3.core.Observer<? super T>);
    Code:
       0: aload_0
       1: invokespecial #1                  // Method java/util/concurrent/atomic/AtomicInteger."<init>":()V
       4: aload_0
       5: aload_1
       6: putfield      #2                  // Field parent:Lio/reactivex/rxjava3/internal/operators/observable/ObservableReplay$ReplayObserver;
       9: aload_0
      10: aload_2
      11: putfield      #3                  // Field child:Lio/reactivex/rxjava3/core/Observer;
      14: return

  public boolean isDisposed();
    Code:
       0: aload_0
       1: getfield      #4                  // Field cancelled:Z
       4: ireturn

  public void dispose();
    Code:
       0: aload_0
       1: getfield      #4                  // Field cancelled:Z
       4: ifne          25
       7: aload_0
       8: iconst_1
       9: putfield      #4                  // Field cancelled:Z
      12: aload_0
      13: getfield      #2                  // Field parent:Lio/reactivex/rxjava3/internal/operators/observable/ObservableReplay$ReplayObserver;
      16: aload_0
      17: invokevirtual #5                  // Method io/reactivex/rxjava3/internal/operators/observable/ObservableReplay$ReplayObserver.remove:(Lio/reactivex/rxjava3/internal/operators/observable/ObservableReplay$InnerDisposable;)V
      20: aload_0
      21: aconst_null
      22: putfield      #6                  // Field index:Ljava/lang/Object;
      25: return

  <U> U index();
    Code:
       0: aload_0
       1: getfield      #6                  // Field index:Ljava/lang/Object;
       4: areturn
}
