Compiled from "ObservableDelay.java"
final class io.reactivex.rxjava3.internal.operators.observable.ObservableDelay$DelayObserver$OnNext implements java.lang.Runnable {
  private final T t;

  final io.reactivex.rxjava3.internal.operators.observable.ObservableDelay$DelayObserver this$0;

  io.reactivex.rxjava3.internal.operators.observable.ObservableDelay$DelayObserver$OnNext(T);
    Code:
       0: aload_0
       1: aload_1
       2: putfield      #1                  // Field this$0:Lio/reactivex/rxjava3/internal/operators/observable/ObservableDelay$DelayObserver;
       5: aload_0
       6: invokespecial #2                  // Method java/lang/Object."<init>":()V
       9: aload_0
      10: aload_2
      11: putfield      #3                  // Field t:Ljava/lang/Object;
      14: return

  public void run();
    Code:
       0: aload_0
       1: getfield      #1                  // Field this$0:Lio/reactivex/rxjava3/internal/operators/observable/ObservableDelay$DelayObserver;
       4: getfield      #4                  // Field io/reactivex/rxjava3/internal/operators/observable/ObservableDelay$DelayObserver.downstream:Lio/reactivex/rxjava3/core/Observer;
       7: aload_0
       8: getfield      #3                  // Field t:Ljava/lang/Object;
      11: invokeinterface #5,  2            // InterfaceMethod io/reactivex/rxjava3/core/Observer.onNext:(Ljava/lang/Object;)V
      16: return
}
