Compiled from "ObservableTakeUntil.java"
final class io.reactivex.rxjava3.internal.operators.observable.ObservableTakeUntil$TakeUntilMainObserver$OtherObserver extends java.util.concurrent.atomic.AtomicReference<io.reactivex.rxjava3.disposables.Disposable> implements io.reactivex.rxjava3.core.Observer<U> {
  private static final long serialVersionUID;

  final io.reactivex.rxjava3.internal.operators.observable.ObservableTakeUntil$TakeUntilMainObserver this$0;

  io.reactivex.rxjava3.internal.operators.observable.ObservableTakeUntil$TakeUntilMainObserver$OtherObserver(io.reactivex.rxjava3.internal.operators.observable.ObservableTakeUntil$TakeUntilMainObserver);
    Code:
       0: aload_0
       1: aload_1
       2: putfield      #1                  // Field this$0:Lio/reactivex/rxjava3/internal/operators/observable/ObservableTakeUntil$TakeUntilMainObserver;
       5: aload_0
       6: invokespecial #2                  // Method java/util/concurrent/atomic/AtomicReference."<init>":()V
       9: return

  public void onSubscribe(io.reactivex.rxjava3.disposables.Disposable);
    Code:
       0: aload_0
       1: aload_1
       2: invokestatic  #3                  // Method io/reactivex/rxjava3/internal/disposables/DisposableHelper.setOnce:(Ljava/util/concurrent/atomic/AtomicReference;Lio/reactivex/rxjava3/disposables/Disposable;)Z
       5: pop
       6: return

  public void onNext(U);
    Code:
       0: aload_0
       1: invokestatic  #4                  // Method io/reactivex/rxjava3/internal/disposables/DisposableHelper.dispose:(Ljava/util/concurrent/atomic/AtomicReference;)Z
       4: pop
       5: aload_0
       6: getfield      #1                  // Field this$0:Lio/reactivex/rxjava3/internal/operators/observable/ObservableTakeUntil$TakeUntilMainObserver;
       9: invokevirtual #5                  // Method io/reactivex/rxjava3/internal/operators/observable/ObservableTakeUntil$TakeUntilMainObserver.otherComplete:()V
      12: return

  public void onError(java.lang.Throwable);
    Code:
       0: aload_0
       1: getfield      #1                  // Field this$0:Lio/reactivex/rxjava3/internal/operators/observable/ObservableTakeUntil$TakeUntilMainObserver;
       4: aload_1
       5: invokevirtual #6                  // Method io/reactivex/rxjava3/internal/operators/observable/ObservableTakeUntil$TakeUntilMainObserver.otherError:(Ljava/lang/Throwable;)V
       8: return

  public void onComplete();
    Code:
       0: aload_0
       1: getfield      #1                  // Field this$0:Lio/reactivex/rxjava3/internal/operators/observable/ObservableTakeUntil$TakeUntilMainObserver;
       4: invokevirtual #5                  // Method io/reactivex/rxjava3/internal/operators/observable/ObservableTakeUntil$TakeUntilMainObserver.otherComplete:()V
       7: return
}
