Compiled from "ObservableBuffer.java"
final class io.reactivex.rxjava3.internal.operators.observable.ObservableBuffer$BufferExactObserver<T, U extends java.util.Collection<? super T>> implements io.reactivex.rxjava3.core.Observer<T>, io.reactivex.rxjava3.disposables.Disposable {
  final io.reactivex.rxjava3.core.Observer<? super U> downstream;

  final int count;

  final io.reactivex.rxjava3.functions.Supplier<U> bufferSupplier;

  U buffer;

  int size;

  io.reactivex.rxjava3.disposables.Disposable upstream;

  io.reactivex.rxjava3.internal.operators.observable.ObservableBuffer$BufferExactObserver(io.reactivex.rxjava3.core.Observer<? super U>, int, io.reactivex.rxjava3.functions.Supplier<U>);
    Code:
       0: aload_0
       1: invokespecial #1                  // Method java/lang/Object."<init>":()V
       4: aload_0
       5: aload_1
       6: putfield      #2                  // Field downstream:Lio/reactivex/rxjava3/core/Observer;
       9: aload_0
      10: iload_2
      11: putfield      #3                  // Field count:I
      14: aload_0
      15: aload_3
      16: putfield      #4                  // Field bufferSupplier:Lio/reactivex/rxjava3/functions/Supplier;
      19: return

  boolean createBuffer();
    Code:
       0: aload_0
       1: getfield      #4                  // Field bufferSupplier:Lio/reactivex/rxjava3/functions/Supplier;
       4: invokeinterface #5,  1            // InterfaceMethod io/reactivex/rxjava3/functions/Supplier.get:()Ljava/lang/Object;
       9: ldc           #6                  // String Empty buffer supplied
      11: invokestatic  #7                  // Method java/util/Objects.requireNonNull:(Ljava/lang/Object;Ljava/lang/String;)Ljava/lang/Object;
      14: checkcast     #8                  // class java/util/Collection
      17: astore_1
      18: goto          70
      21: astore_2
      22: aload_2
      23: invokestatic  #10                 // Method io/reactivex/rxjava3/exceptions/Exceptions.throwIfFatal:(Ljava/lang/Throwable;)V
      26: aload_0
      27: aconst_null
      28: putfield      #11                 // Field buffer:Ljava/util/Collection;
      31: aload_0
      32: getfield      #12                 // Field upstream:Lio/reactivex/rxjava3/disposables/Disposable;
      35: ifnonnull     49
      38: aload_2
      39: aload_0
      40: getfield      #2                  // Field downstream:Lio/reactivex/rxjava3/core/Observer;
      43: invokestatic  #13                 // Method io/reactivex/rxjava3/internal/disposables/EmptyDisposable.error:(Ljava/lang/Throwable;Lio/reactivex/rxjava3/core/Observer;)V
      46: goto          68
      49: aload_0
      50: getfield      #12                 // Field upstream:Lio/reactivex/rxjava3/disposables/Disposable;
      53: invokeinterface #14,  1           // InterfaceMethod io/reactivex/rxjava3/disposables/Disposable.dispose:()V
      58: aload_0
      59: getfield      #2                  // Field downstream:Lio/reactivex/rxjava3/core/Observer;
      62: aload_2
      63: invokeinterface #15,  2           // InterfaceMethod io/reactivex/rxjava3/core/Observer.onError:(Ljava/lang/Throwable;)V
      68: iconst_0
      69: ireturn
      70: aload_0
      71: aload_1
      72: putfield      #11                 // Field buffer:Ljava/util/Collection;
      75: iconst_1
      76: ireturn
    Exception table:
       from    to  target type
           0    18    21   Class java/lang/Throwable

  public void onSubscribe(io.reactivex.rxjava3.disposables.Disposable);
    Code:
       0: aload_0
       1: getfield      #12                 // Field upstream:Lio/reactivex/rxjava3/disposables/Disposable;
       4: aload_1
       5: invokestatic  #16                 // Method io/reactivex/rxjava3/internal/disposables/DisposableHelper.validate:(Lio/reactivex/rxjava3/disposables/Disposable;Lio/reactivex/rxjava3/disposables/Disposable;)Z
       8: ifeq          26
      11: aload_0
      12: aload_1
      13: putfield      #12                 // Field upstream:Lio/reactivex/rxjava3/disposables/Disposable;
      16: aload_0
      17: getfield      #2                  // Field downstream:Lio/reactivex/rxjava3/core/Observer;
      20: aload_0
      21: invokeinterface #17,  2           // InterfaceMethod io/reactivex/rxjava3/core/Observer.onSubscribe:(Lio/reactivex/rxjava3/disposables/Disposable;)V
      26: return

  public void dispose();
    Code:
       0: aload_0
       1: getfield      #12                 // Field upstream:Lio/reactivex/rxjava3/disposables/Disposable;
       4: invokeinterface #14,  1           // InterfaceMethod io/reactivex/rxjava3/disposables/Disposable.dispose:()V
       9: return

  public boolean isDisposed();
    Code:
       0: aload_0
       1: getfield      #12                 // Field upstream:Lio/reactivex/rxjava3/disposables/Disposable;
       4: invokeinterface #18,  1           // InterfaceMethod io/reactivex/rxjava3/disposables/Disposable.isDisposed:()Z
       9: ireturn

  public void onNext(T);
    Code:
       0: aload_0
       1: getfield      #11                 // Field buffer:Ljava/util/Collection;
       4: astore_2
       5: aload_2
       6: ifnull        55
       9: aload_2
      10: aload_1
      11: invokeinterface #19,  2           // InterfaceMethod java/util/Collection.add:(Ljava/lang/Object;)Z
      16: pop
      17: aload_0
      18: dup
      19: getfield      #20                 // Field size:I
      22: iconst_1
      23: iadd
      24: dup_x1
      25: putfield      #20                 // Field size:I
      28: aload_0
      29: getfield      #3                  // Field count:I
      32: if_icmplt     55
      35: aload_0
      36: getfield      #2                  // Field downstream:Lio/reactivex/rxjava3/core/Observer;
      39: aload_2
      40: invokeinterface #21,  2           // InterfaceMethod io/reactivex/rxjava3/core/Observer.onNext:(Ljava/lang/Object;)V
      45: aload_0
      46: iconst_0
      47: putfield      #20                 // Field size:I
      50: aload_0
      51: invokevirtual #22                 // Method createBuffer:()Z
      54: pop
      55: return

  public void onError(java.lang.Throwable);
    Code:
       0: aload_0
       1: aconst_null
       2: putfield      #11                 // Field buffer:Ljava/util/Collection;
       5: aload_0
       6: getfield      #2                  // Field downstream:Lio/reactivex/rxjava3/core/Observer;
       9: aload_1
      10: invokeinterface #15,  2           // InterfaceMethod io/reactivex/rxjava3/core/Observer.onError:(Ljava/lang/Throwable;)V
      15: return

  public void onComplete();
    Code:
       0: aload_0
       1: getfield      #11                 // Field buffer:Ljava/util/Collection;
       4: astore_1
       5: aload_1
       6: ifnull        42
       9: aload_0
      10: aconst_null
      11: putfield      #11                 // Field buffer:Ljava/util/Collection;
      14: aload_1
      15: invokeinterface #23,  1           // InterfaceMethod java/util/Collection.isEmpty:()Z
      20: ifne          33
      23: aload_0
      24: getfield      #2                  // Field downstream:Lio/reactivex/rxjava3/core/Observer;
      27: aload_1
      28: invokeinterface #21,  2           // InterfaceMethod io/reactivex/rxjava3/core/Observer.onNext:(Ljava/lang/Object;)V
      33: aload_0
      34: getfield      #2                  // Field downstream:Lio/reactivex/rxjava3/core/Observer;
      37: invokeinterface #24,  1           // InterfaceMethod io/reactivex/rxjava3/core/Observer.onComplete:()V
      42: return
}
