Compiled from "ObservableSingleMaybe.java"
public final class io.reactivex.rxjava3.internal.operators.observable.ObservableSingleMaybe<T> extends io.reactivex.rxjava3.core.Maybe<T> {
  final io.reactivex.rxjava3.core.ObservableSource<T> source;

  public io.reactivex.rxjava3.internal.operators.observable.ObservableSingleMaybe(io.reactivex.rxjava3.core.ObservableSource<T>);
    Code:
       0: aload_0
       1: invokespecial #1                  // Method io/reactivex/rxjava3/core/Maybe."<init>":()V
       4: aload_0
       5: aload_1
       6: putfield      #2                  // Field source:Lio/reactivex/rxjava3/core/ObservableSource;
       9: return

  public void subscribeActual(io.reactivex.rxjava3.core.MaybeObserver<? super T>);
    Code:
       0: aload_0
       1: getfield      #2                  // Field source:Lio/reactivex/rxjava3/core/ObservableSource;
       4: new           #3                  // class io/reactivex/rxjava3/internal/operators/observable/ObservableSingleMaybe$SingleElementObserver
       7: dup
       8: aload_1
       9: invokespecial #4                  // Method io/reactivex/rxjava3/internal/operators/observable/ObservableSingleMaybe$SingleElementObserver."<init>":(Lio/reactivex/rxjava3/core/MaybeObserver;)V
      12: invokeinterface #5,  2            // InterfaceMethod io/reactivex/rxjava3/core/ObservableSource.subscribe:(Lio/reactivex/rxjava3/core/Observer;)V
      17: return
}
