Compiled from "ObservableBufferTimed.java"
public final class io.reactivex.rxjava3.internal.operators.observable.ObservableBufferTimed<T, U extends java.util.Collection<? super T>> extends io.reactivex.rxjava3.internal.operators.observable.AbstractObservableWithUpstream<T, U> {
  final long timespan;

  final long timeskip;

  final java.util.concurrent.TimeUnit unit;

  final io.reactivex.rxjava3.core.Scheduler scheduler;

  final io.reactivex.rxjava3.functions.Supplier<U> bufferSupplier;

  final int maxSize;

  final boolean restartTimerOnMaxSize;

  public io.reactivex.rxjava3.internal.operators.observable.ObservableBufferTimed(io.reactivex.rxjava3.core.ObservableSource<T>, long, long, java.util.concurrent.TimeUnit, io.reactivex.rxjava3.core.Scheduler, io.reactivex.rxjava3.functions.Supplier<U>, int, boolean);
    Code:
       0: aload_0
       1: aload_1
       2: invokespecial #1                  // Method io/reactivex/rxjava3/internal/operators/observable/AbstractObservableWithUpstream."<init>":(Lio/reactivex/rxjava3/core/ObservableSource;)V
       5: aload_0
       6: lload_2
       7: putfield      #2                  // Field timespan:J
      10: aload_0
      11: lload         4
      13: putfield      #3                  // Field timeskip:J
      16: aload_0
      17: aload         6
      19: putfield      #4                  // Field unit:Ljava/util/concurrent/TimeUnit;
      22: aload_0
      23: aload         7
      25: putfield      #5                  // Field scheduler:Lio/reactivex/rxjava3/core/Scheduler;
      28: aload_0
      29: aload         8
      31: putfield      #6                  // Field bufferSupplier:Lio/reactivex/rxjava3/functions/Supplier;
      34: aload_0
      35: iload         9
      37: putfield      #7                  // Field maxSize:I
      40: aload_0
      41: iload         10
      43: putfield      #8                  // Field restartTimerOnMaxSize:Z
      46: return

  protected void subscribeActual(io.reactivex.rxjava3.core.Observer<? super U>);
    Code:
       0: aload_0
       1: getfield      #2                  // Field timespan:J
       4: aload_0
       5: getfield      #3                  // Field timeskip:J
       8: lcmp
       9: ifne          62
      12: aload_0
      13: getfield      #7                  // Field maxSize:I
      16: ldc           #10                 // int 2147483647
      18: if_icmpne     62
      21: aload_0
      22: getfield      #11                 // Field source:Lio/reactivex/rxjava3/core/ObservableSource;
      25: new           #12                 // class io/reactivex/rxjava3/internal/operators/observable/ObservableBufferTimed$BufferExactUnboundedObserver
      28: dup
      29: new           #13                 // class io/reactivex/rxjava3/observers/SerializedObserver
      32: dup
      33: aload_1
      34: invokespecial #14                 // Method io/reactivex/rxjava3/observers/SerializedObserver."<init>":(Lio/reactivex/rxjava3/core/Observer;)V
      37: aload_0
      38: getfield      #6                  // Field bufferSupplier:Lio/reactivex/rxjava3/functions/Supplier;
      41: aload_0
      42: getfield      #2                  // Field timespan:J
      45: aload_0
      46: getfield      #4                  // Field unit:Ljava/util/concurrent/TimeUnit;
      49: aload_0
      50: getfield      #5                  // Field scheduler:Lio/reactivex/rxjava3/core/Scheduler;
      53: invokespecial #15                 // Method io/reactivex/rxjava3/internal/operators/observable/ObservableBufferTimed$BufferExactUnboundedObserver."<init>":(Lio/reactivex/rxjava3/core/Observer;Lio/reactivex/rxjava3/functions/Supplier;JLjava/util/concurrent/TimeUnit;Lio/reactivex/rxjava3/core/Scheduler;)V
      56: invokeinterface #16,  2           // InterfaceMethod io/reactivex/rxjava3/core/ObservableSource.subscribe:(Lio/reactivex/rxjava3/core/Observer;)V
      61: return
      62: aload_0
      63: getfield      #5                  // Field scheduler:Lio/reactivex/rxjava3/core/Scheduler;
      66: invokevirtual #17                 // Method io/reactivex/rxjava3/core/Scheduler.createWorker:()Lio/reactivex/rxjava3/core/Scheduler$Worker;
      69: astore_2
      70: aload_0
      71: getfield      #2                  // Field timespan:J
      74: aload_0
      75: getfield      #3                  // Field timeskip:J
      78: lcmp
      79: ifne          128
      82: aload_0
      83: getfield      #11                 // Field source:Lio/reactivex/rxjava3/core/ObservableSource;
      86: new           #18                 // class io/reactivex/rxjava3/internal/operators/observable/ObservableBufferTimed$BufferExactBoundedObserver
      89: dup
      90: new           #13                 // class io/reactivex/rxjava3/observers/SerializedObserver
      93: dup
      94: aload_1
      95: invokespecial #14                 // Method io/reactivex/rxjava3/observers/SerializedObserver."<init>":(Lio/reactivex/rxjava3/core/Observer;)V
      98: aload_0
      99: getfield      #6                  // Field bufferSupplier:Lio/reactivex/rxjava3/functions/Supplier;
     102: aload_0
     103: getfield      #2                  // Field timespan:J
     106: aload_0
     107: getfield      #4                  // Field unit:Ljava/util/concurrent/TimeUnit;
     110: aload_0
     111: getfield      #7                  // Field maxSize:I
     114: aload_0
     115: getfield      #8                  // Field restartTimerOnMaxSize:Z
     118: aload_2
     119: invokespecial #19                 // Method io/reactivex/rxjava3/internal/operators/observable/ObservableBufferTimed$BufferExactBoundedObserver."<init>":(Lio/reactivex/rxjava3/core/Observer;Lio/reactivex/rxjava3/functions/Supplier;JLjava/util/concurrent/TimeUnit;IZLio/reactivex/rxjava3/core/Scheduler$Worker;)V
     122: invokeinterface #16,  2           // InterfaceMethod io/reactivex/rxjava3/core/ObservableSource.subscribe:(Lio/reactivex/rxjava3/core/Observer;)V
     127: return
     128: aload_0
     129: getfield      #11                 // Field source:Lio/reactivex/rxjava3/core/ObservableSource;
     132: new           #20                 // class io/reactivex/rxjava3/internal/operators/observable/ObservableBufferTimed$BufferSkipBoundedObserver
     135: dup
     136: new           #13                 // class io/reactivex/rxjava3/observers/SerializedObserver
     139: dup
     140: aload_1
     141: invokespecial #14                 // Method io/reactivex/rxjava3/observers/SerializedObserver."<init>":(Lio/reactivex/rxjava3/core/Observer;)V
     144: aload_0
     145: getfield      #6                  // Field bufferSupplier:Lio/reactivex/rxjava3/functions/Supplier;
     148: aload_0
     149: getfield      #2                  // Field timespan:J
     152: aload_0
     153: getfield      #3                  // Field timeskip:J
     156: aload_0
     157: getfield      #4                  // Field unit:Ljava/util/concurrent/TimeUnit;
     160: aload_2
     161: invokespecial #21                 // Method io/reactivex/rxjava3/internal/operators/observable/ObservableBufferTimed$BufferSkipBoundedObserver."<init>":(Lio/reactivex/rxjava3/core/Observer;Lio/reactivex/rxjava3/functions/Supplier;JJLjava/util/concurrent/TimeUnit;Lio/reactivex/rxjava3/core/Scheduler$Worker;)V
     164: invokeinterface #16,  2           // InterfaceMethod io/reactivex/rxjava3/core/ObservableSource.subscribe:(Lio/reactivex/rxjava3/core/Observer;)V
     169: return
}
