Compiled from "ObservableTimeout.java"
final class io.reactivex.rxjava3.internal.operators.observable.ObservableTimeout$TimeoutConsumer extends java.util.concurrent.atomic.AtomicReference<io.reactivex.rxjava3.disposables.Disposable> implements io.reactivex.rxjava3.core.Observer<java.lang.Object>, io.reactivex.rxjava3.disposables.Disposable {
  private static final long serialVersionUID;

  final io.reactivex.rxjava3.internal.operators.observable.ObservableTimeout$TimeoutSelectorSupport parent;

  final long idx;

  io.reactivex.rxjava3.internal.operators.observable.ObservableTimeout$TimeoutConsumer(long, io.reactivex.rxjava3.internal.operators.observable.ObservableTimeout$TimeoutSelectorSupport);
    Code:
       0: aload_0
       1: invokespecial #1                  // Method java/util/concurrent/atomic/AtomicReference."<init>":()V
       4: aload_0
       5: lload_1
       6: putfield      #2                  // Field idx:J
       9: aload_0
      10: aload_3
      11: putfield      #3                  // Field parent:Lio/reactivex/rxjava3/internal/operators/observable/ObservableTimeout$TimeoutSelectorSupport;
      14: return

  public void onSubscribe(io.reactivex.rxjava3.disposables.Disposable);
    Code:
       0: aload_0
       1: aload_1
       2: invokestatic  #4                  // Method io/reactivex/rxjava3/internal/disposables/DisposableHelper.setOnce:(Ljava/util/concurrent/atomic/AtomicReference;Lio/reactivex/rxjava3/disposables/Disposable;)Z
       5: pop
       6: return

  public void onNext(java.lang.Object);
    Code:
       0: aload_0
       1: invokevirtual #5                  // Method get:()Ljava/lang/Object;
       4: checkcast     #6                  // class io/reactivex/rxjava3/disposables/Disposable
       7: astore_2
       8: aload_2
       9: getstatic     #7                  // Field io/reactivex/rxjava3/internal/disposables/DisposableHelper.DISPOSED:Lio/reactivex/rxjava3/internal/disposables/DisposableHelper;
      12: if_acmpeq     41
      15: aload_2
      16: invokeinterface #8,  1            // InterfaceMethod io/reactivex/rxjava3/disposables/Disposable.dispose:()V
      21: aload_0
      22: getstatic     #7                  // Field io/reactivex/rxjava3/internal/disposables/DisposableHelper.DISPOSED:Lio/reactivex/rxjava3/internal/disposables/DisposableHelper;
      25: invokevirtual #9                  // Method lazySet:(Ljava/lang/Object;)V
      28: aload_0
      29: getfield      #3                  // Field parent:Lio/reactivex/rxjava3/internal/operators/observable/ObservableTimeout$TimeoutSelectorSupport;
      32: aload_0
      33: getfield      #2                  // Field idx:J
      36: invokeinterface #10,  3           // InterfaceMethod io/reactivex/rxjava3/internal/operators/observable/ObservableTimeout$TimeoutSelectorSupport.onTimeout:(J)V
      41: return

  public void onError(java.lang.Throwable);
    Code:
       0: aload_0
       1: invokevirtual #5                  // Method get:()Ljava/lang/Object;
       4: getstatic     #7                  // Field io/reactivex/rxjava3/internal/disposables/DisposableHelper.DISPOSED:Lio/reactivex/rxjava3/internal/disposables/DisposableHelper;
       7: if_acmpeq     34
      10: aload_0
      11: getstatic     #7                  // Field io/reactivex/rxjava3/internal/disposables/DisposableHelper.DISPOSED:Lio/reactivex/rxjava3/internal/disposables/DisposableHelper;
      14: invokevirtual #9                  // Method lazySet:(Ljava/lang/Object;)V
      17: aload_0
      18: getfield      #3                  // Field parent:Lio/reactivex/rxjava3/internal/operators/observable/ObservableTimeout$TimeoutSelectorSupport;
      21: aload_0
      22: getfield      #2                  // Field idx:J
      25: aload_1
      26: invokeinterface #11,  4           // InterfaceMethod io/reactivex/rxjava3/internal/operators/observable/ObservableTimeout$TimeoutSelectorSupport.onTimeoutError:(JLjava/lang/Throwable;)V
      31: goto          38
      34: aload_1
      35: invokestatic  #12                 // Method io/reactivex/rxjava3/plugins/RxJavaPlugins.onError:(Ljava/lang/Throwable;)V
      38: return

  public void onComplete();
    Code:
       0: aload_0
       1: invokevirtual #5                  // Method get:()Ljava/lang/Object;
       4: getstatic     #7                  // Field io/reactivex/rxjava3/internal/disposables/DisposableHelper.DISPOSED:Lio/reactivex/rxjava3/internal/disposables/DisposableHelper;
       7: if_acmpeq     30
      10: aload_0
      11: getstatic     #7                  // Field io/reactivex/rxjava3/internal/disposables/DisposableHelper.DISPOSED:Lio/reactivex/rxjava3/internal/disposables/DisposableHelper;
      14: invokevirtual #9                  // Method lazySet:(Ljava/lang/Object;)V
      17: aload_0
      18: getfield      #3                  // Field parent:Lio/reactivex/rxjava3/internal/operators/observable/ObservableTimeout$TimeoutSelectorSupport;
      21: aload_0
      22: getfield      #2                  // Field idx:J
      25: invokeinterface #10,  3           // InterfaceMethod io/reactivex/rxjava3/internal/operators/observable/ObservableTimeout$TimeoutSelectorSupport.onTimeout:(J)V
      30: return

  public void dispose();
    Code:
       0: aload_0
       1: invokestatic  #13                 // Method io/reactivex/rxjava3/internal/disposables/DisposableHelper.dispose:(Ljava/util/concurrent/atomic/AtomicReference;)Z
       4: pop
       5: return

  public boolean isDisposed();
    Code:
       0: aload_0
       1: invokevirtual #5                  // Method get:()Ljava/lang/Object;
       4: checkcast     #6                  // class io/reactivex/rxjava3/disposables/Disposable
       7: invokestatic  #14                 // Method io/reactivex/rxjava3/internal/disposables/DisposableHelper.isDisposed:(Lio/reactivex/rxjava3/disposables/Disposable;)Z
      10: ireturn
}
