Compiled from "ObservableBufferExactBoundary.java"
public final class io.reactivex.rxjava3.internal.operators.observable.ObservableBufferExactBoundary<T, U extends java.util.Collection<? super T>, B> extends io.reactivex.rxjava3.internal.operators.observable.AbstractObservableWithUpstream<T, U> {
  final io.reactivex.rxjava3.core.ObservableSource<B> boundary;

  final io.reactivex.rxjava3.functions.Supplier<U> bufferSupplier;

  public io.reactivex.rxjava3.internal.operators.observable.ObservableBufferExactBoundary(io.reactivex.rxjava3.core.ObservableSource<T>, io.reactivex.rxjava3.core.ObservableSource<B>, io.reactivex.rxjava3.functions.Supplier<U>);
    Code:
       0: aload_0
       1: aload_1
       2: invokespecial #1                  // Method io/reactivex/rxjava3/internal/operators/observable/AbstractObservableWithUpstream."<init>":(Lio/reactivex/rxjava3/core/ObservableSource;)V
       5: aload_0
       6: aload_2
       7: putfield      #2                  // Field boundary:Lio/reactivex/rxjava3/core/ObservableSource;
      10: aload_0
      11: aload_3
      12: putfield      #3                  // Field bufferSupplier:Lio/reactivex/rxjava3/functions/Supplier;
      15: return

  protected void subscribeActual(io.reactivex.rxjava3.core.Observer<? super U>);
    Code:
       0: aload_0
       1: getfield      #4                  // Field source:Lio/reactivex/rxjava3/core/ObservableSource;
       4: new           #5                  // class io/reactivex/rxjava3/internal/operators/observable/ObservableBufferExactBoundary$BufferExactBoundaryObserver
       7: dup
       8: new           #6                  // class io/reactivex/rxjava3/observers/SerializedObserver
      11: dup
      12: aload_1
      13: invokespecial #7                  // Method io/reactivex/rxjava3/observers/SerializedObserver."<init>":(Lio/reactivex/rxjava3/core/Observer;)V
      16: aload_0
      17: getfield      #3                  // Field bufferSupplier:Lio/reactivex/rxjava3/functions/Supplier;
      20: aload_0
      21: getfield      #2                  // Field boundary:Lio/reactivex/rxjava3/core/ObservableSource;
      24: invokespecial #8                  // Method io/reactivex/rxjava3/internal/operators/observable/ObservableBufferExactBoundary$BufferExactBoundaryObserver."<init>":(Lio/reactivex/rxjava3/core/Observer;Lio/reactivex/rxjava3/functions/Supplier;Lio/reactivex/rxjava3/core/ObservableSource;)V
      27: invokeinterface #9,  2            // InterfaceMethod io/reactivex/rxjava3/core/ObservableSource.subscribe:(Lio/reactivex/rxjava3/core/Observer;)V
      32: return
}
