Compiled from "ObservableAnySingle.java"
public final class io.reactivex.rxjava3.internal.operators.observable.ObservableAnySingle<T> extends io.reactivex.rxjava3.core.Single<java.lang.Boolean> implements io.reactivex.rxjava3.internal.fuseable.FuseToObservable<java.lang.Boolean> {
  final io.reactivex.rxjava3.core.ObservableSource<T> source;

  final io.reactivex.rxjava3.functions.Predicate<? super T> predicate;

  public io.reactivex.rxjava3.internal.operators.observable.ObservableAnySingle(io.reactivex.rxjava3.core.ObservableSource<T>, io.reactivex.rxjava3.functions.Predicate<? super T>);
    Code:
       0: aload_0
       1: invokespecial #1                  // Method io/reactivex/rxjava3/core/Single."<init>":()V
       4: aload_0
       5: aload_1
       6: putfield      #2                  // Field source:Lio/reactivex/rxjava3/core/ObservableSource;
       9: aload_0
      10: aload_2
      11: putfield      #3                  // Field predicate:Lio/reactivex/rxjava3/functions/Predicate;
      14: return

  protected void subscribeActual(io.reactivex.rxjava3.core.SingleObserver<? super java.lang.Boolean>);
    Code:
       0: aload_0
       1: getfield      #2                  // Field source:Lio/reactivex/rxjava3/core/ObservableSource;
       4: new           #4                  // class io/reactivex/rxjava3/internal/operators/observable/ObservableAnySingle$AnyObserver
       7: dup
       8: aload_1
       9: aload_0
      10: getfield      #3                  // Field predicate:Lio/reactivex/rxjava3/functions/Predicate;
      13: invokespecial #5                  // Method io/reactivex/rxjava3/internal/operators/observable/ObservableAnySingle$AnyObserver."<init>":(Lio/reactivex/rxjava3/core/SingleObserver;Lio/reactivex/rxjava3/functions/Predicate;)V
      16: invokeinterface #6,  2            // InterfaceMethod io/reactivex/rxjava3/core/ObservableSource.subscribe:(Lio/reactivex/rxjava3/core/Observer;)V
      21: return

  public io.reactivex.rxjava3.core.Observable<java.lang.Boolean> fuseToObservable();
    Code:
       0: new           #7                  // class io/reactivex/rxjava3/internal/operators/observable/ObservableAny
       3: dup
       4: aload_0
       5: getfield      #2                  // Field source:Lio/reactivex/rxjava3/core/ObservableSource;
       8: aload_0
       9: getfield      #3                  // Field predicate:Lio/reactivex/rxjava3/functions/Predicate;
      12: invokespecial #8                  // Method io/reactivex/rxjava3/internal/operators/observable/ObservableAny."<init>":(Lio/reactivex/rxjava3/core/ObservableSource;Lio/reactivex/rxjava3/functions/Predicate;)V
      15: invokestatic  #9                  // Method io/reactivex/rxjava3/plugins/RxJavaPlugins.onAssembly:(Lio/reactivex/rxjava3/core/Observable;)Lio/reactivex/rxjava3/core/Observable;
      18: areturn
}
