Compiled from "ObservableFromRunnable.java"
public final class io.reactivex.rxjava3.internal.operators.observable.ObservableFromRunnable<T> extends io.reactivex.rxjava3.core.Observable<T> implements io.reactivex.rxjava3.functions.Supplier<T> {
  final java.lang.Runnable run;

  public io.reactivex.rxjava3.internal.operators.observable.ObservableFromRunnable(java.lang.Runnable);
    Code:
       0: aload_0
       1: invokespecial #1                  // Method io/reactivex/rxjava3/core/Observable."<init>":()V
       4: aload_0
       5: aload_1
       6: putfield      #2                  // Field run:Ljava/lang/Runnable;
       9: return

  protected void subscribeActual(io.reactivex.rxjava3.core.Observer<? super T>);
    Code:
       0: new           #3                  // class io/reactivex/rxjava3/internal/fuseable/CancellableQueueFuseable
       3: dup
       4: invokespecial #4                  // Method io/reactivex/rxjava3/internal/fuseable/CancellableQueueFuseable."<init>":()V
       7: astore_2
       8: aload_1
       9: aload_2
      10: invokeinterface #5,  2            // InterfaceMethod io/reactivex/rxjava3/core/Observer.onSubscribe:(Lio/reactivex/rxjava3/disposables/Disposable;)V
      15: aload_2
      16: invokevirtual #6                  // Method io/reactivex/rxjava3/internal/fuseable/CancellableQueueFuseable.isDisposed:()Z
      19: ifne          74
      22: aload_0
      23: getfield      #2                  // Field run:Ljava/lang/Runnable;
      26: invokeinterface #7,  1            // InterfaceMethod java/lang/Runnable.run:()V
      31: goto          61
      34: astore_3
      35: aload_3
      36: invokestatic  #9                  // Method io/reactivex/rxjava3/exceptions/Exceptions.throwIfFatal:(Ljava/lang/Throwable;)V
      39: aload_2
      40: invokevirtual #6                  // Method io/reactivex/rxjava3/internal/fuseable/CancellableQueueFuseable.isDisposed:()Z
      43: ifne          56
      46: aload_1
      47: aload_3
      48: invokeinterface #10,  2           // InterfaceMethod io/reactivex/rxjava3/core/Observer.onError:(Ljava/lang/Throwable;)V
      53: goto          60
      56: aload_3
      57: invokestatic  #11                 // Method io/reactivex/rxjava3/plugins/RxJavaPlugins.onError:(Ljava/lang/Throwable;)V
      60: return
      61: aload_2
      62: invokevirtual #6                  // Method io/reactivex/rxjava3/internal/fuseable/CancellableQueueFuseable.isDisposed:()Z
      65: ifne          74
      68: aload_1
      69: invokeinterface #12,  1           // InterfaceMethod io/reactivex/rxjava3/core/Observer.onComplete:()V
      74: return
    Exception table:
       from    to  target type
          22    31    34   Class java/lang/Throwable

  public T get() throws java.lang.Throwable;
    Code:
       0: aload_0
       1: getfield      #2                  // Field run:Ljava/lang/Runnable;
       4: invokeinterface #7,  1            // InterfaceMethod java/lang/Runnable.run:()V
       9: aconst_null
      10: areturn
}
