Compiled from "ObservableDelaySubscriptionOther.java"
public final class io.reactivex.rxjava3.internal.operators.observable.ObservableDelaySubscriptionOther<T, U> extends io.reactivex.rxjava3.core.Observable<T> {
  final io.reactivex.rxjava3.core.ObservableSource<? extends T> main;

  final io.reactivex.rxjava3.core.ObservableSource<U> other;

  public io.reactivex.rxjava3.internal.operators.observable.ObservableDelaySubscriptionOther(io.reactivex.rxjava3.core.ObservableSource<? extends T>, io.reactivex.rxjava3.core.ObservableSource<U>);
    Code:
       0: aload_0
       1: invokespecial #1                  // Method io/reactivex/rxjava3/core/Observable."<init>":()V
       4: aload_0
       5: aload_1
       6: putfield      #2                  // Field main:Lio/reactivex/rxjava3/core/ObservableSource;
       9: aload_0
      10: aload_2
      11: putfield      #3                  // Field other:Lio/reactivex/rxjava3/core/ObservableSource;
      14: return

  public void subscribeActual(io.reactivex.rxjava3.core.Observer<? super T>);
    Code:
       0: new           #4                  // class io/reactivex/rxjava3/internal/disposables/SequentialDisposable
       3: dup
       4: invokespecial #5                  // Method io/reactivex/rxjava3/internal/disposables/SequentialDisposable."<init>":()V
       7: astore_2
       8: aload_1
       9: aload_2
      10: invokeinterface #6,  2            // InterfaceMethod io/reactivex/rxjava3/core/Observer.onSubscribe:(Lio/reactivex/rxjava3/disposables/Disposable;)V
      15: new           #7                  // class io/reactivex/rxjava3/internal/operators/observable/ObservableDelaySubscriptionOther$DelayObserver
      18: dup
      19: aload_0
      20: aload_2
      21: aload_1
      22: invokespecial #8                  // Method io/reactivex/rxjava3/internal/operators/observable/ObservableDelaySubscriptionOther$DelayObserver."<init>":(Lio/reactivex/rxjava3/internal/operators/observable/ObservableDelaySubscriptionOther;Lio/reactivex/rxjava3/internal/disposables/SequentialDisposable;Lio/reactivex/rxjava3/core/Observer;)V
      25: astore_3
      26: aload_0
      27: getfield      #3                  // Field other:Lio/reactivex/rxjava3/core/ObservableSource;
      30: aload_3
      31: invokeinterface #9,  2            // InterfaceMethod io/reactivex/rxjava3/core/ObservableSource.subscribe:(Lio/reactivex/rxjava3/core/Observer;)V
      36: return
}
