Compiled from "ObservableAmb.java"
final class io.reactivex.rxjava3.internal.operators.observable.ObservableAmb$AmbCoordinator<T> implements io.reactivex.rxjava3.disposables.Disposable {
  final io.reactivex.rxjava3.core.Observer<? super T> downstream;

  final io.reactivex.rxjava3.internal.operators.observable.ObservableAmb$AmbInnerObserver<T>[] observers;

  final java.util.concurrent.atomic.AtomicInteger winner;

  io.reactivex.rxjava3.internal.operators.observable.ObservableAmb$AmbCoordinator(io.reactivex.rxjava3.core.Observer<? super T>, int);
    Code:
       0: aload_0
       1: invokespecial #1                  // Method java/lang/Object."<init>":()V
       4: aload_0
       5: new           #2                  // class java/util/concurrent/atomic/AtomicInteger
       8: dup
       9: invokespecial #3                  // Method java/util/concurrent/atomic/AtomicInteger."<init>":()V
      12: putfield      #4                  // Field winner:Ljava/util/concurrent/atomic/AtomicInteger;
      15: aload_0
      16: aload_1
      17: putfield      #5                  // Field downstream:Lio/reactivex/rxjava3/core/Observer;
      20: aload_0
      21: iload_2
      22: anewarray     #6                  // class io/reactivex/rxjava3/internal/operators/observable/ObservableAmb$AmbInnerObserver
      25: putfield      #7                  // Field observers:[Lio/reactivex/rxjava3/internal/operators/observable/ObservableAmb$AmbInnerObserver;
      28: return

  public void subscribe(io.reactivex.rxjava3.core.ObservableSource<? extends T>[]);
    Code:
       0: aload_0
       1: getfield      #7                  // Field observers:[Lio/reactivex/rxjava3/internal/operators/observable/ObservableAmb$AmbInnerObserver;
       4: astore_2
       5: aload_2
       6: arraylength
       7: istore_3
       8: iconst_0
       9: istore        4
      11: iload         4
      13: iload_3
      14: if_icmpge     43
      17: aload_2
      18: iload         4
      20: new           #6                  // class io/reactivex/rxjava3/internal/operators/observable/ObservableAmb$AmbInnerObserver
      23: dup
      24: aload_0
      25: iload         4
      27: iconst_1
      28: iadd
      29: aload_0
      30: getfield      #5                  // Field downstream:Lio/reactivex/rxjava3/core/Observer;
      33: invokespecial #8                  // Method io/reactivex/rxjava3/internal/operators/observable/ObservableAmb$AmbInnerObserver."<init>":(Lio/reactivex/rxjava3/internal/operators/observable/ObservableAmb$AmbCoordinator;ILio/reactivex/rxjava3/core/Observer;)V
      36: aastore
      37: iinc          4, 1
      40: goto          11
      43: aload_0
      44: getfield      #4                  // Field winner:Ljava/util/concurrent/atomic/AtomicInteger;
      47: iconst_0
      48: invokevirtual #9                  // Method java/util/concurrent/atomic/AtomicInteger.lazySet:(I)V
      51: aload_0
      52: getfield      #5                  // Field downstream:Lio/reactivex/rxjava3/core/Observer;
      55: aload_0
      56: invokeinterface #10,  2           // InterfaceMethod io/reactivex/rxjava3/core/Observer.onSubscribe:(Lio/reactivex/rxjava3/disposables/Disposable;)V
      61: iconst_0
      62: istore        4
      64: iload         4
      66: iload_3
      67: if_icmpge     100
      70: aload_0
      71: getfield      #4                  // Field winner:Ljava/util/concurrent/atomic/AtomicInteger;
      74: invokevirtual #11                 // Method java/util/concurrent/atomic/AtomicInteger.get:()I
      77: ifeq          81
      80: return
      81: aload_1
      82: iload         4
      84: aaload
      85: aload_2
      86: iload         4
      88: aaload
      89: invokeinterface #12,  2           // InterfaceMethod io/reactivex/rxjava3/core/ObservableSource.subscribe:(Lio/reactivex/rxjava3/core/Observer;)V
      94: iinc          4, 1
      97: goto          64
     100: return

  public boolean win(int);
    Code:
       0: aload_0
       1: getfield      #4                  // Field winner:Ljava/util/concurrent/atomic/AtomicInteger;
       4: invokevirtual #11                 // Method java/util/concurrent/atomic/AtomicInteger.get:()I
       7: istore_2
       8: iload_2
       9: ifne          66
      12: aload_0
      13: getfield      #4                  // Field winner:Ljava/util/concurrent/atomic/AtomicInteger;
      16: iconst_0
      17: iload_1
      18: invokevirtual #13                 // Method java/util/concurrent/atomic/AtomicInteger.compareAndSet:(II)Z
      21: ifeq          66
      24: aload_0
      25: getfield      #7                  // Field observers:[Lio/reactivex/rxjava3/internal/operators/observable/ObservableAmb$AmbInnerObserver;
      28: astore_3
      29: aload_3
      30: arraylength
      31: istore        4
      33: iconst_0
      34: istore        5
      36: iload         5
      38: iload         4
      40: if_icmpge     64
      43: iload         5
      45: iconst_1
      46: iadd
      47: iload_1
      48: if_icmpeq     58
      51: aload_3
      52: iload         5
      54: aaload
      55: invokevirtual #14                 // Method io/reactivex/rxjava3/internal/operators/observable/ObservableAmb$AmbInnerObserver.dispose:()V
      58: iinc          5, 1
      61: goto          36
      64: iconst_1
      65: ireturn
      66: iconst_0
      67: ireturn

  public void dispose();
    Code:
       0: aload_0
       1: getfield      #4                  // Field winner:Ljava/util/concurrent/atomic/AtomicInteger;
       4: invokevirtual #11                 // Method java/util/concurrent/atomic/AtomicInteger.get:()I
       7: iconst_m1
       8: if_icmpeq     50
      11: aload_0
      12: getfield      #4                  // Field winner:Ljava/util/concurrent/atomic/AtomicInteger;
      15: iconst_m1
      16: invokevirtual #9                  // Method java/util/concurrent/atomic/AtomicInteger.lazySet:(I)V
      19: aload_0
      20: getfield      #7                  // Field observers:[Lio/reactivex/rxjava3/internal/operators/observable/ObservableAmb$AmbInnerObserver;
      23: astore_1
      24: aload_1
      25: arraylength
      26: istore_2
      27: iconst_0
      28: istore_3
      29: iload_3
      30: iload_2
      31: if_icmpge     50
      34: aload_1
      35: iload_3
      36: aaload
      37: astore        4
      39: aload         4
      41: invokevirtual #14                 // Method io/reactivex/rxjava3/internal/operators/observable/ObservableAmb$AmbInnerObserver.dispose:()V
      44: iinc          3, 1
      47: goto          29
      50: return

  public boolean isDisposed();
    Code:
       0: aload_0
       1: getfield      #4                  // Field winner:Ljava/util/concurrent/atomic/AtomicInteger;
       4: invokevirtual #11                 // Method java/util/concurrent/atomic/AtomicInteger.get:()I
       7: iconst_m1
       8: if_icmpne     15
      11: iconst_1
      12: goto          16
      15: iconst_0
      16: ireturn
}
