Compiled from "ObservableReplay.java"
final class io.reactivex.rxjava3.internal.operators.observable.ObservableReplay$ReplaySource<T> implements io.reactivex.rxjava3.core.ObservableSource<T> {
  private final java.util.concurrent.atomic.AtomicReference<io.reactivex.rxjava3.internal.operators.observable.ObservableReplay$ReplayObserver<T>> curr;

  private final io.reactivex.rxjava3.internal.operators.observable.ObservableReplay$BufferSupplier<T> bufferFactory;

  io.reactivex.rxjava3.internal.operators.observable.ObservableReplay$ReplaySource(java.util.concurrent.atomic.AtomicReference<io.reactivex.rxjava3.internal.operators.observable.ObservableReplay$ReplayObserver<T>>, io.reactivex.rxjava3.internal.operators.observable.ObservableReplay$BufferSupplier<T>);
    Code:
       0: aload_0
       1: invokespecial #1                  // Method java/lang/Object."<init>":()V
       4: aload_0
       5: aload_1
       6: putfield      #2                  // Field curr:Ljava/util/concurrent/atomic/AtomicReference;
       9: aload_0
      10: aload_2
      11: putfield      #3                  // Field bufferFactory:Lio/reactivex/rxjava3/internal/operators/observable/ObservableReplay$BufferSupplier;
      14: return

  public void subscribe(io.reactivex.rxjava3.core.Observer<? super T>);
    Code:
       0: aload_0
       1: getfield      #2                  // Field curr:Ljava/util/concurrent/atomic/AtomicReference;
       4: invokevirtual #4                  // Method java/util/concurrent/atomic/AtomicReference.get:()Ljava/lang/Object;
       7: checkcast     #5                  // class io/reactivex/rxjava3/internal/operators/observable/ObservableReplay$ReplayObserver
      10: astore_2
      11: aload_2
      12: ifnonnull     58
      15: aload_0
      16: getfield      #3                  // Field bufferFactory:Lio/reactivex/rxjava3/internal/operators/observable/ObservableReplay$BufferSupplier;
      19: invokeinterface #6,  1            // InterfaceMethod io/reactivex/rxjava3/internal/operators/observable/ObservableReplay$BufferSupplier.call:()Lio/reactivex/rxjava3/internal/operators/observable/ObservableReplay$ReplayBuffer;
      24: astore_3
      25: new           #5                  // class io/reactivex/rxjava3/internal/operators/observable/ObservableReplay$ReplayObserver
      28: dup
      29: aload_3
      30: aload_0
      31: getfield      #2                  // Field curr:Ljava/util/concurrent/atomic/AtomicReference;
      34: invokespecial #7                  // Method io/reactivex/rxjava3/internal/operators/observable/ObservableReplay$ReplayObserver."<init>":(Lio/reactivex/rxjava3/internal/operators/observable/ObservableReplay$ReplayBuffer;Ljava/util/concurrent/atomic/AtomicReference;)V
      37: astore        4
      39: aload_0
      40: getfield      #2                  // Field curr:Ljava/util/concurrent/atomic/AtomicReference;
      43: aconst_null
      44: aload         4
      46: invokevirtual #8                  // Method java/util/concurrent/atomic/AtomicReference.compareAndSet:(Ljava/lang/Object;Ljava/lang/Object;)Z
      49: ifne          55
      52: goto          0
      55: aload         4
      57: astore_2
      58: new           #9                  // class io/reactivex/rxjava3/internal/operators/observable/ObservableReplay$InnerDisposable
      61: dup
      62: aload_2
      63: aload_1
      64: invokespecial #10                 // Method io/reactivex/rxjava3/internal/operators/observable/ObservableReplay$InnerDisposable."<init>":(Lio/reactivex/rxjava3/internal/operators/observable/ObservableReplay$ReplayObserver;Lio/reactivex/rxjava3/core/Observer;)V
      67: astore_3
      68: aload_1
      69: aload_3
      70: invokeinterface #11,  2           // InterfaceMethod io/reactivex/rxjava3/core/Observer.onSubscribe:(Lio/reactivex/rxjava3/disposables/Disposable;)V
      75: aload_2
      76: aload_3
      77: invokevirtual #12                 // Method io/reactivex/rxjava3/internal/operators/observable/ObservableReplay$ReplayObserver.add:(Lio/reactivex/rxjava3/internal/operators/observable/ObservableReplay$InnerDisposable;)Z
      80: pop
      81: aload_3
      82: invokevirtual #13                 // Method io/reactivex/rxjava3/internal/operators/observable/ObservableReplay$InnerDisposable.isDisposed:()Z
      85: ifeq          94
      88: aload_2
      89: aload_3
      90: invokevirtual #14                 // Method io/reactivex/rxjava3/internal/operators/observable/ObservableReplay$ReplayObserver.remove:(Lio/reactivex/rxjava3/internal/operators/observable/ObservableReplay$InnerDisposable;)V
      93: return
      94: aload_2
      95: getfield      #15                 // Field io/reactivex/rxjava3/internal/operators/observable/ObservableReplay$ReplayObserver.buffer:Lio/reactivex/rxjava3/internal/operators/observable/ObservableReplay$ReplayBuffer;
      98: aload_3
      99: invokeinterface #16,  2           // InterfaceMethod io/reactivex/rxjava3/internal/operators/observable/ObservableReplay$ReplayBuffer.replay:(Lio/reactivex/rxjava3/internal/operators/observable/ObservableReplay$InnerDisposable;)V
     104: goto          107
     107: return
}
