Compiled from "ObservableRetryPredicate.java"
public final class io.reactivex.rxjava3.internal.operators.observable.ObservableRetryPredicate<T> extends io.reactivex.rxjava3.internal.operators.observable.AbstractObservableWithUpstream<T, T> {
  final io.reactivex.rxjava3.functions.Predicate<? super java.lang.Throwable> predicate;

  final long count;

  public io.reactivex.rxjava3.internal.operators.observable.ObservableRetryPredicate(io.reactivex.rxjava3.core.Observable<T>, long, io.reactivex.rxjava3.functions.Predicate<? super java.lang.Throwable>);
    Code:
       0: aload_0
       1: aload_1
       2: invokespecial #1                  // Method io/reactivex/rxjava3/internal/operators/observable/AbstractObservableWithUpstream."<init>":(Lio/reactivex/rxjava3/core/ObservableSource;)V
       5: aload_0
       6: aload         4
       8: putfield      #2                  // Field predicate:Lio/reactivex/rxjava3/functions/Predicate;
      11: aload_0
      12: lload_2
      13: putfield      #3                  // Field count:J
      16: return

  public void subscribeActual(io.reactivex.rxjava3.core.Observer<? super T>);
    Code:
       0: new           #4                  // class io/reactivex/rxjava3/internal/disposables/SequentialDisposable
       3: dup
       4: invokespecial #5                  // Method io/reactivex/rxjava3/internal/disposables/SequentialDisposable."<init>":()V
       7: astore_2
       8: aload_1
       9: aload_2
      10: invokeinterface #6,  2            // InterfaceMethod io/reactivex/rxjava3/core/Observer.onSubscribe:(Lio/reactivex/rxjava3/disposables/Disposable;)V
      15: new           #7                  // class io/reactivex/rxjava3/internal/operators/observable/ObservableRetryPredicate$RepeatObserver
      18: dup
      19: aload_1
      20: aload_0
      21: getfield      #3                  // Field count:J
      24: aload_0
      25: getfield      #2                  // Field predicate:Lio/reactivex/rxjava3/functions/Predicate;
      28: aload_2
      29: aload_0
      30: getfield      #8                  // Field source:Lio/reactivex/rxjava3/core/ObservableSource;
      33: invokespecial #9                  // Method io/reactivex/rxjava3/internal/operators/observable/ObservableRetryPredicate$RepeatObserver."<init>":(Lio/reactivex/rxjava3/core/Observer;JLio/reactivex/rxjava3/functions/Predicate;Lio/reactivex/rxjava3/internal/disposables/SequentialDisposable;Lio/reactivex/rxjava3/core/ObservableSource;)V
      36: astore_3
      37: aload_3
      38: invokevirtual #10                 // Method io/reactivex/rxjava3/internal/operators/observable/ObservableRetryPredicate$RepeatObserver.subscribeNext:()V
      41: return
}
