Compiled from "ObservableSkipUntil.java"
final class io.reactivex.rxjava3.internal.operators.observable.ObservableSkipUntil$SkipUntilObserver<T> implements io.reactivex.rxjava3.core.Observer<T> {
  final io.reactivex.rxjava3.core.Observer<? super T> downstream;

  final io.reactivex.rxjava3.internal.disposables.ArrayCompositeDisposable frc;

  io.reactivex.rxjava3.disposables.Disposable upstream;

  volatile boolean notSkipping;

  boolean notSkippingLocal;

  io.reactivex.rxjava3.internal.operators.observable.ObservableSkipUntil$SkipUntilObserver(io.reactivex.rxjava3.core.Observer<? super T>, io.reactivex.rxjava3.internal.disposables.ArrayCompositeDisposable);
    Code:
       0: aload_0
       1: invokespecial #1                  // Method java/lang/Object."<init>":()V
       4: aload_0
       5: aload_1
       6: putfield      #2                  // Field downstream:Lio/reactivex/rxjava3/core/Observer;
       9: aload_0
      10: aload_2
      11: putfield      #3                  // Field frc:Lio/reactivex/rxjava3/internal/disposables/ArrayCompositeDisposable;
      14: return

  public void onSubscribe(io.reactivex.rxjava3.disposables.Disposable);
    Code:
       0: aload_0
       1: getfield      #4                  // Field upstream:Lio/reactivex/rxjava3/disposables/Disposable;
       4: aload_1
       5: invokestatic  #5                  // Method io/reactivex/rxjava3/internal/disposables/DisposableHelper.validate:(Lio/reactivex/rxjava3/disposables/Disposable;Lio/reactivex/rxjava3/disposables/Disposable;)Z
       8: ifeq          26
      11: aload_0
      12: aload_1
      13: putfield      #4                  // Field upstream:Lio/reactivex/rxjava3/disposables/Disposable;
      16: aload_0
      17: getfield      #3                  // Field frc:Lio/reactivex/rxjava3/internal/disposables/ArrayCompositeDisposable;
      20: iconst_0
      21: aload_1
      22: invokevirtual #6                  // Method io/reactivex/rxjava3/internal/disposables/ArrayCompositeDisposable.setResource:(ILio/reactivex/rxjava3/disposables/Disposable;)Z
      25: pop
      26: return

  public void onNext(T);
    Code:
       0: aload_0
       1: getfield      #7                  // Field notSkippingLocal:Z
       4: ifeq          20
       7: aload_0
       8: getfield      #2                  // Field downstream:Lio/reactivex/rxjava3/core/Observer;
      11: aload_1
      12: invokeinterface #8,  2            // InterfaceMethod io/reactivex/rxjava3/core/Observer.onNext:(Ljava/lang/Object;)V
      17: goto          42
      20: aload_0
      21: getfield      #9                  // Field notSkipping:Z
      24: ifeq          42
      27: aload_0
      28: iconst_1
      29: putfield      #7                  // Field notSkippingLocal:Z
      32: aload_0
      33: getfield      #2                  // Field downstream:Lio/reactivex/rxjava3/core/Observer;
      36: aload_1
      37: invokeinterface #8,  2            // InterfaceMethod io/reactivex/rxjava3/core/Observer.onNext:(Ljava/lang/Object;)V
      42: return

  public void onError(java.lang.Throwable);
    Code:
       0: aload_0
       1: getfield      #3                  // Field frc:Lio/reactivex/rxjava3/internal/disposables/ArrayCompositeDisposable;
       4: invokevirtual #10                 // Method io/reactivex/rxjava3/internal/disposables/ArrayCompositeDisposable.dispose:()V
       7: aload_0
       8: getfield      #2                  // Field downstream:Lio/reactivex/rxjava3/core/Observer;
      11: aload_1
      12: invokeinterface #11,  2           // InterfaceMethod io/reactivex/rxjava3/core/Observer.onError:(Ljava/lang/Throwable;)V
      17: return

  public void onComplete();
    Code:
       0: aload_0
       1: getfield      #3                  // Field frc:Lio/reactivex/rxjava3/internal/disposables/ArrayCompositeDisposable;
       4: invokevirtual #10                 // Method io/reactivex/rxjava3/internal/disposables/ArrayCompositeDisposable.dispose:()V
       7: aload_0
       8: getfield      #2                  // Field downstream:Lio/reactivex/rxjava3/core/Observer;
      11: invokeinterface #12,  1           // InterfaceMethod io/reactivex/rxjava3/core/Observer.onComplete:()V
      16: return
}
