Compiled from "ObservableGroupBy.java"
public final class io.reactivex.rxjava3.internal.operators.observable.ObservableGroupBy$GroupByObserver<T, K, V> extends java.util.concurrent.atomic.AtomicInteger implements io.reactivex.rxjava3.core.Observer<T>, io.reactivex.rxjava3.disposables.Disposable {
  private static final long serialVersionUID;

  final io.reactivex.rxjava3.core.Observer<? super io.reactivex.rxjava3.observables.GroupedObservable<K, V>> downstream;

  final io.reactivex.rxjava3.functions.Function<? super T, ? extends K> keySelector;

  final io.reactivex.rxjava3.functions.Function<? super T, ? extends V> valueSelector;

  final int bufferSize;

  final boolean delayError;

  final java.util.Map<java.lang.Object, io.reactivex.rxjava3.internal.operators.observable.ObservableGroupBy$GroupedUnicast<K, V>> groups;

  static final java.lang.Object NULL_KEY;

  io.reactivex.rxjava3.disposables.Disposable upstream;

  final java.util.concurrent.atomic.AtomicBoolean cancelled;

  public io.reactivex.rxjava3.internal.operators.observable.ObservableGroupBy$GroupByObserver(io.reactivex.rxjava3.core.Observer<? super io.reactivex.rxjava3.observables.GroupedObservable<K, V>>, io.reactivex.rxjava3.functions.Function<? super T, ? extends K>, io.reactivex.rxjava3.functions.Function<? super T, ? extends V>, int, boolean);
    Code:
       0: aload_0
       1: invokespecial #1                  // Method java/util/concurrent/atomic/AtomicInteger."<init>":()V
       4: aload_0
       5: new           #2                  // class java/util/concurrent/atomic/AtomicBoolean
       8: dup
       9: invokespecial #3                  // Method java/util/concurrent/atomic/AtomicBoolean."<init>":()V
      12: putfield      #4                  // Field cancelled:Ljava/util/concurrent/atomic/AtomicBoolean;
      15: aload_0
      16: aload_1
      17: putfield      #5                  // Field downstream:Lio/reactivex/rxjava3/core/Observer;
      20: aload_0
      21: aload_2
      22: putfield      #6                  // Field keySelector:Lio/reactivex/rxjava3/functions/Function;
      25: aload_0
      26: aload_3
      27: putfield      #7                  // Field valueSelector:Lio/reactivex/rxjava3/functions/Function;
      30: aload_0
      31: iload         4
      33: putfield      #8                  // Field bufferSize:I
      36: aload_0
      37: iload         5
      39: putfield      #9                  // Field delayError:Z
      42: aload_0
      43: new           #10                 // class java/util/concurrent/ConcurrentHashMap
      46: dup
      47: invokespecial #11                 // Method java/util/concurrent/ConcurrentHashMap."<init>":()V
      50: putfield      #12                 // Field groups:Ljava/util/Map;
      53: aload_0
      54: iconst_1
      55: invokevirtual #13                 // Method lazySet:(I)V
      58: return

  public void onSubscribe(io.reactivex.rxjava3.disposables.Disposable);
    Code:
       0: aload_0
       1: getfield      #14                 // Field upstream:Lio/reactivex/rxjava3/disposables/Disposable;
       4: aload_1
       5: invokestatic  #15                 // Method io/reactivex/rxjava3/internal/disposables/DisposableHelper.validate:(Lio/reactivex/rxjava3/disposables/Disposable;Lio/reactivex/rxjava3/disposables/Disposable;)Z
       8: ifeq          26
      11: aload_0
      12: aload_1
      13: putfield      #14                 // Field upstream:Lio/reactivex/rxjava3/disposables/Disposable;
      16: aload_0
      17: getfield      #5                  // Field downstream:Lio/reactivex/rxjava3/core/Observer;
      20: aload_0
      21: invokeinterface #16,  2           // InterfaceMethod io/reactivex/rxjava3/core/Observer.onSubscribe:(Lio/reactivex/rxjava3/disposables/Disposable;)V
      26: return

  public void onNext(T);
    Code:
       0: aload_0
       1: getfield      #6                  // Field keySelector:Lio/reactivex/rxjava3/functions/Function;
       4: aload_1
       5: invokeinterface #17,  2           // InterfaceMethod io/reactivex/rxjava3/functions/Function.apply:(Ljava/lang/Object;)Ljava/lang/Object;
      10: astore_2
      11: goto          34
      14: astore_3
      15: aload_3
      16: invokestatic  #19                 // Method io/reactivex/rxjava3/exceptions/Exceptions.throwIfFatal:(Ljava/lang/Throwable;)V
      19: aload_0
      20: getfield      #14                 // Field upstream:Lio/reactivex/rxjava3/disposables/Disposable;
      23: invokeinterface #20,  1           // InterfaceMethod io/reactivex/rxjava3/disposables/Disposable.dispose:()V
      28: aload_0
      29: aload_3
      30: invokevirtual #21                 // Method onError:(Ljava/lang/Throwable;)V
      33: return
      34: aload_2
      35: ifnull        42
      38: aload_2
      39: goto          45
      42: getstatic     #22                 // Field NULL_KEY:Ljava/lang/Object;
      45: astore_3
      46: aload_0
      47: getfield      #12                 // Field groups:Ljava/util/Map;
      50: aload_3
      51: invokeinterface #23,  2           // InterfaceMethod java/util/Map.get:(Ljava/lang/Object;)Ljava/lang/Object;
      56: checkcast     #24                 // class io/reactivex/rxjava3/internal/operators/observable/ObservableGroupBy$GroupedUnicast
      59: astore        4
      61: iconst_0
      62: istore        5
      64: aload         4
      66: ifnonnull     116
      69: aload_0
      70: getfield      #4                  // Field cancelled:Ljava/util/concurrent/atomic/AtomicBoolean;
      73: invokevirtual #25                 // Method java/util/concurrent/atomic/AtomicBoolean.get:()Z
      76: ifeq          80
      79: return
      80: aload_2
      81: aload_0
      82: getfield      #8                  // Field bufferSize:I
      85: aload_0
      86: aload_0
      87: getfield      #9                  // Field delayError:Z
      90: invokestatic  #26                 // Method io/reactivex/rxjava3/internal/operators/observable/ObservableGroupBy$GroupedUnicast.createWith:(Ljava/lang/Object;ILio/reactivex/rxjava3/internal/operators/observable/ObservableGroupBy$GroupByObserver;Z)Lio/reactivex/rxjava3/internal/operators/observable/ObservableGroupBy$GroupedUnicast;
      93: astore        4
      95: aload_0
      96: getfield      #12                 // Field groups:Ljava/util/Map;
      99: aload_3
     100: aload         4
     102: invokeinterface #27,  3           // InterfaceMethod java/util/Map.put:(Ljava/lang/Object;Ljava/lang/Object;)Ljava/lang/Object;
     107: pop
     108: aload_0
     109: invokevirtual #28                 // Method getAndIncrement:()I
     112: pop
     113: iconst_1
     114: istore        5
     116: aload_0
     117: getfield      #7                  // Field valueSelector:Lio/reactivex/rxjava3/functions/Function;
     120: aload_1
     121: invokeinterface #17,  2           // InterfaceMethod io/reactivex/rxjava3/functions/Function.apply:(Ljava/lang/Object;)Ljava/lang/Object;
     126: ldc           #29                 // String The value supplied is null
     128: invokestatic  #30                 // Method java/util/Objects.requireNonNull:(Ljava/lang/Object;Ljava/lang/String;)Ljava/lang/Object;
     131: astore        6
     133: goto          175
     136: astore        7
     138: aload         7
     140: invokestatic  #19                 // Method io/reactivex/rxjava3/exceptions/Exceptions.throwIfFatal:(Ljava/lang/Throwable;)V
     143: aload_0
     144: getfield      #14                 // Field upstream:Lio/reactivex/rxjava3/disposables/Disposable;
     147: invokeinterface #20,  1           // InterfaceMethod io/reactivex/rxjava3/disposables/Disposable.dispose:()V
     152: iload         5
     154: ifeq          168
     157: aload_0
     158: getfield      #5                  // Field downstream:Lio/reactivex/rxjava3/core/Observer;
     161: aload         4
     163: invokeinterface #31,  2           // InterfaceMethod io/reactivex/rxjava3/core/Observer.onNext:(Ljava/lang/Object;)V
     168: aload_0
     169: aload         7
     171: invokevirtual #21                 // Method onError:(Ljava/lang/Throwable;)V
     174: return
     175: aload         4
     177: aload         6
     179: invokevirtual #32                 // Method io/reactivex/rxjava3/internal/operators/observable/ObservableGroupBy$GroupedUnicast.onNext:(Ljava/lang/Object;)V
     182: iload         5
     184: ifeq          219
     187: aload_0
     188: getfield      #5                  // Field downstream:Lio/reactivex/rxjava3/core/Observer;
     191: aload         4
     193: invokeinterface #31,  2           // InterfaceMethod io/reactivex/rxjava3/core/Observer.onNext:(Ljava/lang/Object;)V
     198: aload         4
     200: getfield      #33                 // Field io/reactivex/rxjava3/internal/operators/observable/ObservableGroupBy$GroupedUnicast.state:Lio/reactivex/rxjava3/internal/operators/observable/ObservableGroupBy$State;
     203: invokevirtual #34                 // Method io/reactivex/rxjava3/internal/operators/observable/ObservableGroupBy$State.tryAbandon:()Z
     206: ifeq          219
     209: aload_0
     210: aload_2
     211: invokevirtual #35                 // Method cancel:(Ljava/lang/Object;)V
     214: aload         4
     216: invokevirtual #36                 // Method io/reactivex/rxjava3/internal/operators/observable/ObservableGroupBy$GroupedUnicast.onComplete:()V
     219: return
    Exception table:
       from    to  target type
           0    11    14   Class java/lang/Throwable
         116   133   136   Class java/lang/Throwable

  public void onError(java.lang.Throwable);
    Code:
       0: new           #37                 // class java/util/ArrayList
       3: dup
       4: aload_0
       5: getfield      #12                 // Field groups:Ljava/util/Map;
       8: invokeinterface #38,  1           // InterfaceMethod java/util/Map.values:()Ljava/util/Collection;
      13: invokespecial #39                 // Method java/util/ArrayList."<init>":(Ljava/util/Collection;)V
      16: astore_2
      17: aload_0
      18: getfield      #12                 // Field groups:Ljava/util/Map;
      21: invokeinterface #40,  1           // InterfaceMethod java/util/Map.clear:()V
      26: aload_2
      27: invokeinterface #41,  1           // InterfaceMethod java/util/List.iterator:()Ljava/util/Iterator;
      32: astore_3
      33: aload_3
      34: invokeinterface #42,  1           // InterfaceMethod java/util/Iterator.hasNext:()Z
      39: ifeq          62
      42: aload_3
      43: invokeinterface #43,  1           // InterfaceMethod java/util/Iterator.next:()Ljava/lang/Object;
      48: checkcast     #24                 // class io/reactivex/rxjava3/internal/operators/observable/ObservableGroupBy$GroupedUnicast
      51: astore        4
      53: aload         4
      55: aload_1
      56: invokevirtual #44                 // Method io/reactivex/rxjava3/internal/operators/observable/ObservableGroupBy$GroupedUnicast.onError:(Ljava/lang/Throwable;)V
      59: goto          33
      62: aload_0
      63: getfield      #5                  // Field downstream:Lio/reactivex/rxjava3/core/Observer;
      66: aload_1
      67: invokeinterface #45,  2           // InterfaceMethod io/reactivex/rxjava3/core/Observer.onError:(Ljava/lang/Throwable;)V
      72: return

  public void onComplete();
    Code:
       0: new           #37                 // class java/util/ArrayList
       3: dup
       4: aload_0
       5: getfield      #12                 // Field groups:Ljava/util/Map;
       8: invokeinterface #38,  1           // InterfaceMethod java/util/Map.values:()Ljava/util/Collection;
      13: invokespecial #39                 // Method java/util/ArrayList."<init>":(Ljava/util/Collection;)V
      16: astore_1
      17: aload_0
      18: getfield      #12                 // Field groups:Ljava/util/Map;
      21: invokeinterface #40,  1           // InterfaceMethod java/util/Map.clear:()V
      26: aload_1
      27: invokeinterface #41,  1           // InterfaceMethod java/util/List.iterator:()Ljava/util/Iterator;
      32: astore_2
      33: aload_2
      34: invokeinterface #42,  1           // InterfaceMethod java/util/Iterator.hasNext:()Z
      39: ifeq          59
      42: aload_2
      43: invokeinterface #43,  1           // InterfaceMethod java/util/Iterator.next:()Ljava/lang/Object;
      48: checkcast     #24                 // class io/reactivex/rxjava3/internal/operators/observable/ObservableGroupBy$GroupedUnicast
      51: astore_3
      52: aload_3
      53: invokevirtual #36                 // Method io/reactivex/rxjava3/internal/operators/observable/ObservableGroupBy$GroupedUnicast.onComplete:()V
      56: goto          33
      59: aload_0
      60: getfield      #5                  // Field downstream:Lio/reactivex/rxjava3/core/Observer;
      63: invokeinterface #46,  1           // InterfaceMethod io/reactivex/rxjava3/core/Observer.onComplete:()V
      68: return

  public void dispose();
    Code:
       0: aload_0
       1: getfield      #4                  // Field cancelled:Ljava/util/concurrent/atomic/AtomicBoolean;
       4: iconst_0
       5: iconst_1
       6: invokevirtual #47                 // Method java/util/concurrent/atomic/AtomicBoolean.compareAndSet:(ZZ)Z
       9: ifeq          28
      12: aload_0
      13: invokevirtual #48                 // Method decrementAndGet:()I
      16: ifne          28
      19: aload_0
      20: getfield      #14                 // Field upstream:Lio/reactivex/rxjava3/disposables/Disposable;
      23: invokeinterface #20,  1           // InterfaceMethod io/reactivex/rxjava3/disposables/Disposable.dispose:()V
      28: return

  public boolean isDisposed();
    Code:
       0: aload_0
       1: getfield      #4                  // Field cancelled:Ljava/util/concurrent/atomic/AtomicBoolean;
       4: invokevirtual #25                 // Method java/util/concurrent/atomic/AtomicBoolean.get:()Z
       7: ireturn

  public void cancel(K);
    Code:
       0: aload_1
       1: ifnull        8
       4: aload_1
       5: goto          11
       8: getstatic     #22                 // Field NULL_KEY:Ljava/lang/Object;
      11: astore_2
      12: aload_0
      13: getfield      #12                 // Field groups:Ljava/util/Map;
      16: aload_2
      17: invokeinterface #49,  2           // InterfaceMethod java/util/Map.remove:(Ljava/lang/Object;)Ljava/lang/Object;
      22: pop
      23: aload_0
      24: invokevirtual #48                 // Method decrementAndGet:()I
      27: ifne          39
      30: aload_0
      31: getfield      #14                 // Field upstream:Lio/reactivex/rxjava3/disposables/Disposable;
      34: invokeinterface #20,  1           // InterfaceMethod io/reactivex/rxjava3/disposables/Disposable.dispose:()V
      39: return

  static {};
    Code:
       0: new           #50                 // class java/lang/Object
       3: dup
       4: invokespecial #51                 // Method java/lang/Object."<init>":()V
       7: putstatic     #22                 // Field NULL_KEY:Ljava/lang/Object;
      10: return
}
