Compiled from "ObservableAny.java"
public final class io.reactivex.rxjava3.internal.operators.observable.ObservableAny<T> extends io.reactivex.rxjava3.internal.operators.observable.AbstractObservableWithUpstream<T, java.lang.Boolean> {
  final io.reactivex.rxjava3.functions.Predicate<? super T> predicate;

  public io.reactivex.rxjava3.internal.operators.observable.ObservableAny(io.reactivex.rxjava3.core.ObservableSource<T>, io.reactivex.rxjava3.functions.Predicate<? super T>);
    Code:
       0: aload_0
       1: aload_1
       2: invokespecial #1                  // Method io/reactivex/rxjava3/internal/operators/observable/AbstractObservableWithUpstream."<init>":(Lio/reactivex/rxjava3/core/ObservableSource;)V
       5: aload_0
       6: aload_2
       7: putfield      #2                  // Field predicate:Lio/reactivex/rxjava3/functions/Predicate;
      10: return

  protected void subscribeActual(io.reactivex.rxjava3.core.Observer<? super java.lang.Boolean>);
    Code:
       0: aload_0
       1: getfield      #3                  // Field source:Lio/reactivex/rxjava3/core/ObservableSource;
       4: new           #4                  // class io/reactivex/rxjava3/internal/operators/observable/ObservableAny$AnyObserver
       7: dup
       8: aload_1
       9: aload_0
      10: getfield      #2                  // Field predicate:Lio/reactivex/rxjava3/functions/Predicate;
      13: invokespecial #5                  // Method io/reactivex/rxjava3/internal/operators/observable/ObservableAny$AnyObserver."<init>":(Lio/reactivex/rxjava3/core/Observer;Lio/reactivex/rxjava3/functions/Predicate;)V
      16: invokeinterface #6,  2            // InterfaceMethod io/reactivex/rxjava3/core/ObservableSource.subscribe:(Lio/reactivex/rxjava3/core/Observer;)V
      21: return
}
