Compiled from "ObservableTimeoutTimed.java"
public final class io.reactivex.rxjava3.internal.operators.observable.ObservableTimeoutTimed<T> extends io.reactivex.rxjava3.internal.operators.observable.AbstractObservableWithUpstream<T, T> {
  final long timeout;

  final java.util.concurrent.TimeUnit unit;

  final io.reactivex.rxjava3.core.Scheduler scheduler;

  final io.reactivex.rxjava3.core.ObservableSource<? extends T> other;

  public io.reactivex.rxjava3.internal.operators.observable.ObservableTimeoutTimed(io.reactivex.rxjava3.core.Observable<T>, long, java.util.concurrent.TimeUnit, io.reactivex.rxjava3.core.Scheduler, io.reactivex.rxjava3.core.ObservableSource<? extends T>);
    Code:
       0: aload_0
       1: aload_1
       2: invokespecial #1                  // Method io/reactivex/rxjava3/internal/operators/observable/AbstractObservableWithUpstream."<init>":(Lio/reactivex/rxjava3/core/ObservableSource;)V
       5: aload_0
       6: lload_2
       7: putfield      #2                  // Field timeout:J
      10: aload_0
      11: aload         4
      13: putfield      #3                  // Field unit:Ljava/util/concurrent/TimeUnit;
      16: aload_0
      17: aload         5
      19: putfield      #4                  // Field scheduler:Lio/reactivex/rxjava3/core/Scheduler;
      22: aload_0
      23: aload         6
      25: putfield      #5                  // Field other:Lio/reactivex/rxjava3/core/ObservableSource;
      28: return

  protected void subscribeActual(io.reactivex.rxjava3.core.Observer<? super T>);
    Code:
       0: aload_0
       1: getfield      #5                  // Field other:Lio/reactivex/rxjava3/core/ObservableSource;
       4: ifnonnull     56
       7: new           #6                  // class io/reactivex/rxjava3/internal/operators/observable/ObservableTimeoutTimed$TimeoutObserver
      10: dup
      11: aload_1
      12: aload_0
      13: getfield      #2                  // Field timeout:J
      16: aload_0
      17: getfield      #3                  // Field unit:Ljava/util/concurrent/TimeUnit;
      20: aload_0
      21: getfield      #4                  // Field scheduler:Lio/reactivex/rxjava3/core/Scheduler;
      24: invokevirtual #7                  // Method io/reactivex/rxjava3/core/Scheduler.createWorker:()Lio/reactivex/rxjava3/core/Scheduler$Worker;
      27: invokespecial #8                  // Method io/reactivex/rxjava3/internal/operators/observable/ObservableTimeoutTimed$TimeoutObserver."<init>":(Lio/reactivex/rxjava3/core/Observer;JLjava/util/concurrent/TimeUnit;Lio/reactivex/rxjava3/core/Scheduler$Worker;)V
      30: astore_2
      31: aload_1
      32: aload_2
      33: invokeinterface #9,  2            // InterfaceMethod io/reactivex/rxjava3/core/Observer.onSubscribe:(Lio/reactivex/rxjava3/disposables/Disposable;)V
      38: aload_2
      39: lconst_0
      40: invokevirtual #10                 // Method io/reactivex/rxjava3/internal/operators/observable/ObservableTimeoutTimed$TimeoutObserver.startTimeout:(J)V
      43: aload_0
      44: getfield      #11                 // Field source:Lio/reactivex/rxjava3/core/ObservableSource;
      47: aload_2
      48: invokeinterface #12,  2           // InterfaceMethod io/reactivex/rxjava3/core/ObservableSource.subscribe:(Lio/reactivex/rxjava3/core/Observer;)V
      53: goto          106
      56: new           #13                 // class io/reactivex/rxjava3/internal/operators/observable/ObservableTimeoutTimed$TimeoutFallbackObserver
      59: dup
      60: aload_1
      61: aload_0
      62: getfield      #2                  // Field timeout:J
      65: aload_0
      66: getfield      #3                  // Field unit:Ljava/util/concurrent/TimeUnit;
      69: aload_0
      70: getfield      #4                  // Field scheduler:Lio/reactivex/rxjava3/core/Scheduler;
      73: invokevirtual #7                  // Method io/reactivex/rxjava3/core/Scheduler.createWorker:()Lio/reactivex/rxjava3/core/Scheduler$Worker;
      76: aload_0
      77: getfield      #5                  // Field other:Lio/reactivex/rxjava3/core/ObservableSource;
      80: invokespecial #14                 // Method io/reactivex/rxjava3/internal/operators/observable/ObservableTimeoutTimed$TimeoutFallbackObserver."<init>":(Lio/reactivex/rxjava3/core/Observer;JLjava/util/concurrent/TimeUnit;Lio/reactivex/rxjava3/core/Scheduler$Worker;Lio/reactivex/rxjava3/core/ObservableSource;)V
      83: astore_2
      84: aload_1
      85: aload_2
      86: invokeinterface #9,  2            // InterfaceMethod io/reactivex/rxjava3/core/Observer.onSubscribe:(Lio/reactivex/rxjava3/disposables/Disposable;)V
      91: aload_2
      92: lconst_0
      93: invokevirtual #15                 // Method io/reactivex/rxjava3/internal/operators/observable/ObservableTimeoutTimed$TimeoutFallbackObserver.startTimeout:(J)V
      96: aload_0
      97: getfield      #11                 // Field source:Lio/reactivex/rxjava3/core/ObservableSource;
     100: aload_2
     101: invokeinterface #12,  2           // InterfaceMethod io/reactivex/rxjava3/core/ObservableSource.subscribe:(Lio/reactivex/rxjava3/core/Observer;)V
     106: return
}
