Compiled from "ObservableSubscribeOn.java"
final class io.reactivex.rxjava3.internal.operators.observable.ObservableSubscribeOn$SubscribeTask implements java.lang.Runnable {
  private final io.reactivex.rxjava3.internal.operators.observable.ObservableSubscribeOn$SubscribeOnObserver<T> parent;

  final io.reactivex.rxjava3.internal.operators.observable.ObservableSubscribeOn this$0;

  io.reactivex.rxjava3.internal.operators.observable.ObservableSubscribeOn$SubscribeTask(io.reactivex.rxjava3.internal.operators.observable.ObservableSubscribeOn$SubscribeOnObserver<T>);
    Code:
       0: aload_0
       1: aload_1
       2: putfield      #1                  // Field this$0:Lio/reactivex/rxjava3/internal/operators/observable/ObservableSubscribeOn;
       5: aload_0
       6: invokespecial #2                  // Method java/lang/Object."<init>":()V
       9: aload_0
      10: aload_2
      11: putfield      #3                  // Field parent:Lio/reactivex/rxjava3/internal/operators/observable/ObservableSubscribeOn$SubscribeOnObserver;
      14: return

  public void run();
    Code:
       0: aload_0
       1: getfield      #1                  // Field this$0:Lio/reactivex/rxjava3/internal/operators/observable/ObservableSubscribeOn;
       4: getfield      #4                  // Field io/reactivex/rxjava3/internal/operators/observable/ObservableSubscribeOn.source:Lio/reactivex/rxjava3/core/ObservableSource;
       7: aload_0
       8: getfield      #3                  // Field parent:Lio/reactivex/rxjava3/internal/operators/observable/ObservableSubscribeOn$SubscribeOnObserver;
      11: invokeinterface #5,  2            // InterfaceMethod io/reactivex/rxjava3/core/ObservableSource.subscribe:(Lio/reactivex/rxjava3/core/Observer;)V
      16: return
}
