Compiled from "ObservableGroupJoin.java"
public final class io.reactivex.rxjava3.internal.operators.observable.ObservableGroupJoin<TLeft, TRight, TLeftEnd, TRightEnd, R> extends io.reactivex.rxjava3.internal.operators.observable.AbstractObservableWithUpstream<TLeft, R> {
  final io.reactivex.rxjava3.core.ObservableSource<? extends TRight> other;

  final io.reactivex.rxjava3.functions.Function<? super TLeft, ? extends io.reactivex.rxjava3.core.ObservableSource<TLeftEnd>> leftEnd;

  final io.reactivex.rxjava3.functions.Function<? super TRight, ? extends io.reactivex.rxjava3.core.ObservableSource<TRightEnd>> rightEnd;

  final io.reactivex.rxjava3.functions.BiFunction<? super TLeft, ? super io.reactivex.rxjava3.core.Observable<TRight>, ? extends R> resultSelector;

  public io.reactivex.rxjava3.internal.operators.observable.ObservableGroupJoin(io.reactivex.rxjava3.core.ObservableSource<TLeft>, io.reactivex.rxjava3.core.ObservableSource<? extends TRight>, io.reactivex.rxjava3.functions.Function<? super TLeft, ? extends io.reactivex.rxjava3.core.ObservableSource<TLeftEnd>>, io.reactivex.rxjava3.functions.Function<? super TRight, ? extends io.reactivex.rxjava3.core.ObservableSource<TRightEnd>>, io.reactivex.rxjava3.functions.BiFunction<? super TLeft, ? super io.reactivex.rxjava3.core.Observable<TRight>, ? extends R>);
    Code:
       0: aload_0
       1: aload_1
       2: invokespecial #1                  // Method io/reactivex/rxjava3/internal/operators/observable/AbstractObservableWithUpstream."<init>":(Lio/reactivex/rxjava3/core/ObservableSource;)V
       5: aload_0
       6: aload_2
       7: putfield      #2                  // Field other:Lio/reactivex/rxjava3/core/ObservableSource;
      10: aload_0
      11: aload_3
      12: putfield      #3                  // Field leftEnd:Lio/reactivex/rxjava3/functions/Function;
      15: aload_0
      16: aload         4
      18: putfield      #4                  // Field rightEnd:Lio/reactivex/rxjava3/functions/Function;
      21: aload_0
      22: aload         5
      24: putfield      #5                  // Field resultSelector:Lio/reactivex/rxjava3/functions/BiFunction;
      27: return

  protected void subscribeActual(io.reactivex.rxjava3.core.Observer<? super R>);
    Code:
       0: new           #6                  // class io/reactivex/rxjava3/internal/operators/observable/ObservableGroupJoin$GroupJoinDisposable
       3: dup
       4: aload_1
       5: aload_0
       6: getfield      #3                  // Field leftEnd:Lio/reactivex/rxjava3/functions/Function;
       9: aload_0
      10: getfield      #4                  // Field rightEnd:Lio/reactivex/rxjava3/functions/Function;
      13: aload_0
      14: getfield      #5                  // Field resultSelector:Lio/reactivex/rxjava3/functions/BiFunction;
      17: invokespecial #7                  // Method io/reactivex/rxjava3/internal/operators/observable/ObservableGroupJoin$GroupJoinDisposable."<init>":(Lio/reactivex/rxjava3/core/Observer;Lio/reactivex/rxjava3/functions/Function;Lio/reactivex/rxjava3/functions/Function;Lio/reactivex/rxjava3/functions/BiFunction;)V
      20: astore_2
      21: aload_1
      22: aload_2
      23: invokeinterface #8,  2            // InterfaceMethod io/reactivex/rxjava3/core/Observer.onSubscribe:(Lio/reactivex/rxjava3/disposables/Disposable;)V
      28: new           #9                  // class io/reactivex/rxjava3/internal/operators/observable/ObservableGroupJoin$LeftRightObserver
      31: dup
      32: aload_2
      33: iconst_1
      34: invokespecial #10                 // Method io/reactivex/rxjava3/internal/operators/observable/ObservableGroupJoin$LeftRightObserver."<init>":(Lio/reactivex/rxjava3/internal/operators/observable/ObservableGroupJoin$JoinSupport;Z)V
      37: astore_3
      38: aload_2
      39: getfield      #11                 // Field io/reactivex/rxjava3/internal/operators/observable/ObservableGroupJoin$GroupJoinDisposable.disposables:Lio/reactivex/rxjava3/disposables/CompositeDisposable;
      42: aload_3
      43: invokevirtual #12                 // Method io/reactivex/rxjava3/disposables/CompositeDisposable.add:(Lio/reactivex/rxjava3/disposables/Disposable;)Z
      46: pop
      47: new           #9                  // class io/reactivex/rxjava3/internal/operators/observable/ObservableGroupJoin$LeftRightObserver
      50: dup
      51: aload_2
      52: iconst_0
      53: invokespecial #10                 // Method io/reactivex/rxjava3/internal/operators/observable/ObservableGroupJoin$LeftRightObserver."<init>":(Lio/reactivex/rxjava3/internal/operators/observable/ObservableGroupJoin$JoinSupport;Z)V
      56: astore        4
      58: aload_2
      59: getfield      #11                 // Field io/reactivex/rxjava3/internal/operators/observable/ObservableGroupJoin$GroupJoinDisposable.disposables:Lio/reactivex/rxjava3/disposables/CompositeDisposable;
      62: aload         4
      64: invokevirtual #12                 // Method io/reactivex/rxjava3/disposables/CompositeDisposable.add:(Lio/reactivex/rxjava3/disposables/Disposable;)Z
      67: pop
      68: aload_0
      69: getfield      #13                 // Field source:Lio/reactivex/rxjava3/core/ObservableSource;
      72: aload_3
      73: invokeinterface #14,  2           // InterfaceMethod io/reactivex/rxjava3/core/ObservableSource.subscribe:(Lio/reactivex/rxjava3/core/Observer;)V
      78: aload_0
      79: getfield      #2                  // Field other:Lio/reactivex/rxjava3/core/ObservableSource;
      82: aload         4
      84: invokeinterface #14,  2           // InterfaceMethod io/reactivex/rxjava3/core/ObservableSource.subscribe:(Lio/reactivex/rxjava3/core/Observer;)V
      89: return
}
