Compiled from "ObservableFromArray.java"
public final class io.reactivex.rxjava3.internal.operators.observable.ObservableFromArray<T> extends io.reactivex.rxjava3.core.Observable<T> {
  final T[] array;

  public io.reactivex.rxjava3.internal.operators.observable.ObservableFromArray(T[]);
    Code:
       0: aload_0
       1: invokespecial #1                  // Method io/reactivex/rxjava3/core/Observable."<init>":()V
       4: aload_0
       5: aload_1
       6: putfield      #2                  // Field array:[Ljava/lang/Object;
       9: return

  public void subscribeActual(io.reactivex.rxjava3.core.Observer<? super T>);
    Code:
       0: new           #3                  // class io/reactivex/rxjava3/internal/operators/observable/ObservableFromArray$FromArrayDisposable
       3: dup
       4: aload_1
       5: aload_0
       6: getfield      #2                  // Field array:[Ljava/lang/Object;
       9: invokespecial #4                  // Method io/reactivex/rxjava3/internal/operators/observable/ObservableFromArray$FromArrayDisposable."<init>":(Lio/reactivex/rxjava3/core/Observer;[Ljava/lang/Object;)V
      12: astore_2
      13: aload_1
      14: aload_2
      15: invokeinterface #5,  2            // InterfaceMethod io/reactivex/rxjava3/core/Observer.onSubscribe:(Lio/reactivex/rxjava3/disposables/Disposable;)V
      20: aload_2
      21: getfield      #6                  // Field io/reactivex/rxjava3/internal/operators/observable/ObservableFromArray$FromArrayDisposable.fusionMode:Z
      24: ifeq          28
      27: return
      28: aload_2
      29: invokevirtual #7                  // Method io/reactivex/rxjava3/internal/operators/observable/ObservableFromArray$FromArrayDisposable.run:()V
      32: return
}
