Compiled from "ObservableWindowTimed.java"
final class io.reactivex.rxjava3.internal.operators.observable.ObservableWindowTimed$WindowExactBoundedObserver$WindowBoundaryRunnable implements java.lang.Runnable {
  final io.reactivex.rxjava3.internal.operators.observable.ObservableWindowTimed$WindowExactBoundedObserver<?> parent;

  final long index;

  io.reactivex.rxjava3.internal.operators.observable.ObservableWindowTimed$WindowExactBoundedObserver$WindowBoundaryRunnable(io.reactivex.rxjava3.internal.operators.observable.ObservableWindowTimed$WindowExactBoundedObserver<?>, long);
    Code:
       0: aload_0
       1: invokespecial #1                  // Method java/lang/Object."<init>":()V
       4: aload_0
       5: aload_1
       6: putfield      #2                  // Field parent:Lio/reactivex/rxjava3/internal/operators/observable/ObservableWindowTimed$WindowExactBoundedObserver;
       9: aload_0
      10: lload_2
      11: putfield      #3                  // Field index:J
      14: return

  public void run();
    Code:
       0: aload_0
       1: getfield      #2                  // Field parent:Lio/reactivex/rxjava3/internal/operators/observable/ObservableWindowTimed$WindowExactBoundedObserver;
       4: aload_0
       5: invokevirtual #4                  // Method io/reactivex/rxjava3/internal/operators/observable/ObservableWindowTimed$WindowExactBoundedObserver.boundary:(Lio/reactivex/rxjava3/internal/operators/observable/ObservableWindowTimed$WindowExactBoundedObserver$WindowBoundaryRunnable;)V
       8: return
}
