Compiled from "ObservableElementAtSingle.java"
public final class io.reactivex.rxjava3.internal.operators.observable.ObservableElementAtSingle<T> extends io.reactivex.rxjava3.core.Single<T> implements io.reactivex.rxjava3.internal.fuseable.FuseToObservable<T> {
  final io.reactivex.rxjava3.core.ObservableSource<T> source;

  final long index;

  final T defaultValue;

  public io.reactivex.rxjava3.internal.operators.observable.ObservableElementAtSingle(io.reactivex.rxjava3.core.ObservableSource<T>, long, T);
    Code:
       0: aload_0
       1: invokespecial #1                  // Method io/reactivex/rxjava3/core/Single."<init>":()V
       4: aload_0
       5: aload_1
       6: putfield      #2                  // Field source:Lio/reactivex/rxjava3/core/ObservableSource;
       9: aload_0
      10: lload_2
      11: putfield      #3                  // Field index:J
      14: aload_0
      15: aload         4
      17: putfield      #4                  // Field defaultValue:Ljava/lang/Object;
      20: return

  public void subscribeActual(io.reactivex.rxjava3.core.SingleObserver<? super T>);
    Code:
       0: aload_0
       1: getfield      #2                  // Field source:Lio/reactivex/rxjava3/core/ObservableSource;
       4: new           #5                  // class io/reactivex/rxjava3/internal/operators/observable/ObservableElementAtSingle$ElementAtObserver
       7: dup
       8: aload_1
       9: aload_0
      10: getfield      #3                  // Field index:J
      13: aload_0
      14: getfield      #4                  // Field defaultValue:Ljava/lang/Object;
      17: invokespecial #6                  // Method io/reactivex/rxjava3/internal/operators/observable/ObservableElementAtSingle$ElementAtObserver."<init>":(Lio/reactivex/rxjava3/core/SingleObserver;JLjava/lang/Object;)V
      20: invokeinterface #7,  2            // InterfaceMethod io/reactivex/rxjava3/core/ObservableSource.subscribe:(Lio/reactivex/rxjava3/core/Observer;)V
      25: return

  public io.reactivex.rxjava3.core.Observable<T> fuseToObservable();
    Code:
       0: new           #8                  // class io/reactivex/rxjava3/internal/operators/observable/ObservableElementAt
       3: dup
       4: aload_0
       5: getfield      #2                  // Field source:Lio/reactivex/rxjava3/core/ObservableSource;
       8: aload_0
       9: getfield      #3                  // Field index:J
      12: aload_0
      13: getfield      #4                  // Field defaultValue:Ljava/lang/Object;
      16: iconst_1
      17: invokespecial #9                  // Method io/reactivex/rxjava3/internal/operators/observable/ObservableElementAt."<init>":(Lio/reactivex/rxjava3/core/ObservableSource;JLjava/lang/Object;Z)V
      20: invokestatic  #10                 // Method io/reactivex/rxjava3/plugins/RxJavaPlugins.onAssembly:(Lio/reactivex/rxjava3/core/Observable;)Lio/reactivex/rxjava3/core/Observable;
      23: areturn
}
