Compiled from "ObservableGenerate.java"
public final class io.reactivex.rxjava3.internal.operators.observable.ObservableGenerate<T, S> extends io.reactivex.rxjava3.core.Observable<T> {
  final io.reactivex.rxjava3.functions.Supplier<S> stateSupplier;

  final io.reactivex.rxjava3.functions.BiFunction<S, io.reactivex.rxjava3.core.Emitter<T>, S> generator;

  final io.reactivex.rxjava3.functions.Consumer<? super S> disposeState;

  public io.reactivex.rxjava3.internal.operators.observable.ObservableGenerate(io.reactivex.rxjava3.functions.Supplier<S>, io.reactivex.rxjava3.functions.BiFunction<S, io.reactivex.rxjava3.core.Emitter<T>, S>, io.reactivex.rxjava3.functions.Consumer<? super S>);
    Code:
       0: aload_0
       1: invokespecial #1                  // Method io/reactivex/rxjava3/core/Observable."<init>":()V
       4: aload_0
       5: aload_1
       6: putfield      #2                  // Field stateSupplier:Lio/reactivex/rxjava3/functions/Supplier;
       9: aload_0
      10: aload_2
      11: putfield      #3                  // Field generator:Lio/reactivex/rxjava3/functions/BiFunction;
      14: aload_0
      15: aload_3
      16: putfield      #4                  // Field disposeState:Lio/reactivex/rxjava3/functions/Consumer;
      19: return

  public void subscribeActual(io.reactivex.rxjava3.core.Observer<? super T>);
    Code:
       0: aload_0
       1: getfield      #2                  // Field stateSupplier:Lio/reactivex/rxjava3/functions/Supplier;
       4: invokeinterface #5,  1            // InterfaceMethod io/reactivex/rxjava3/functions/Supplier.get:()Ljava/lang/Object;
       9: astore_2
      10: goto          24
      13: astore_3
      14: aload_3
      15: invokestatic  #7                  // Method io/reactivex/rxjava3/exceptions/Exceptions.throwIfFatal:(Ljava/lang/Throwable;)V
      18: aload_3
      19: aload_1
      20: invokestatic  #8                  // Method io/reactivex/rxjava3/internal/disposables/EmptyDisposable.error:(Ljava/lang/Throwable;Lio/reactivex/rxjava3/core/Observer;)V
      23: return
      24: new           #9                  // class io/reactivex/rxjava3/internal/operators/observable/ObservableGenerate$GeneratorDisposable
      27: dup
      28: aload_1
      29: aload_0
      30: getfield      #3                  // Field generator:Lio/reactivex/rxjava3/functions/BiFunction;
      33: aload_0
      34: getfield      #4                  // Field disposeState:Lio/reactivex/rxjava3/functions/Consumer;
      37: aload_2
      38: invokespecial #10                 // Method io/reactivex/rxjava3/internal/operators/observable/ObservableGenerate$GeneratorDisposable."<init>":(Lio/reactivex/rxjava3/core/Observer;Lio/reactivex/rxjava3/functions/BiFunction;Lio/reactivex/rxjava3/functions/Consumer;Ljava/lang/Object;)V
      41: astore_3
      42: aload_1
      43: aload_3
      44: invokeinterface #11,  2           // InterfaceMethod io/reactivex/rxjava3/core/Observer.onSubscribe:(Lio/reactivex/rxjava3/disposables/Disposable;)V
      49: aload_3
      50: invokevirtual #12                 // Method io/reactivex/rxjava3/internal/operators/observable/ObservableGenerate$GeneratorDisposable.run:()V
      53: return
    Exception table:
       from    to  target type
           0    10    13   Class java/lang/Throwable
}
