Compiled from "ObserverResourceWrapper.java"
public final class io.reactivex.rxjava3.internal.operators.observable.ObserverResourceWrapper<T> extends java.util.concurrent.atomic.AtomicReference<io.reactivex.rxjava3.disposables.Disposable> implements io.reactivex.rxjava3.core.Observer<T>, io.reactivex.rxjava3.disposables.Disposable {
  private static final long serialVersionUID;

  final io.reactivex.rxjava3.core.Observer<? super T> downstream;

  final java.util.concurrent.atomic.AtomicReference<io.reactivex.rxjava3.disposables.Disposable> upstream;

  public io.reactivex.rxjava3.internal.operators.observable.ObserverResourceWrapper(io.reactivex.rxjava3.core.Observer<? super T>);
    Code:
       0: aload_0
       1: invokespecial #1                  // Method java/util/concurrent/atomic/AtomicReference."<init>":()V
       4: aload_0
       5: new           #2                  // class java/util/concurrent/atomic/AtomicReference
       8: dup
       9: invokespecial #1                  // Method java/util/concurrent/atomic/AtomicReference."<init>":()V
      12: putfield      #3                  // Field upstream:Ljava/util/concurrent/atomic/AtomicReference;
      15: aload_0
      16: aload_1
      17: putfield      #4                  // Field downstream:Lio/reactivex/rxjava3/core/Observer;
      20: return

  public void onSubscribe(io.reactivex.rxjava3.disposables.Disposable);
    Code:
       0: aload_0
       1: getfield      #3                  // Field upstream:Ljava/util/concurrent/atomic/AtomicReference;
       4: aload_1
       5: invokestatic  #5                  // Method io/reactivex/rxjava3/internal/disposables/DisposableHelper.setOnce:(Ljava/util/concurrent/atomic/AtomicReference;Lio/reactivex/rxjava3/disposables/Disposable;)Z
       8: ifeq          21
      11: aload_0
      12: getfield      #4                  // Field downstream:Lio/reactivex/rxjava3/core/Observer;
      15: aload_0
      16: invokeinterface #6,  2            // InterfaceMethod io/reactivex/rxjava3/core/Observer.onSubscribe:(Lio/reactivex/rxjava3/disposables/Disposable;)V
      21: return

  public void onNext(T);
    Code:
       0: aload_0
       1: getfield      #4                  // Field downstream:Lio/reactivex/rxjava3/core/Observer;
       4: aload_1
       5: invokeinterface #7,  2            // InterfaceMethod io/reactivex/rxjava3/core/Observer.onNext:(Ljava/lang/Object;)V
      10: return

  public void onError(java.lang.Throwable);
    Code:
       0: aload_0
       1: invokevirtual #8                  // Method dispose:()V
       4: aload_0
       5: getfield      #4                  // Field downstream:Lio/reactivex/rxjava3/core/Observer;
       8: aload_1
       9: invokeinterface #9,  2            // InterfaceMethod io/reactivex/rxjava3/core/Observer.onError:(Ljava/lang/Throwable;)V
      14: return

  public void onComplete();
    Code:
       0: aload_0
       1: invokevirtual #8                  // Method dispose:()V
       4: aload_0
       5: getfield      #4                  // Field downstream:Lio/reactivex/rxjava3/core/Observer;
       8: invokeinterface #10,  1           // InterfaceMethod io/reactivex/rxjava3/core/Observer.onComplete:()V
      13: return

  public void dispose();
    Code:
       0: aload_0
       1: getfield      #3                  // Field upstream:Ljava/util/concurrent/atomic/AtomicReference;
       4: invokestatic  #11                 // Method io/reactivex/rxjava3/internal/disposables/DisposableHelper.dispose:(Ljava/util/concurrent/atomic/AtomicReference;)Z
       7: pop
       8: aload_0
       9: invokestatic  #11                 // Method io/reactivex/rxjava3/internal/disposables/DisposableHelper.dispose:(Ljava/util/concurrent/atomic/AtomicReference;)Z
      12: pop
      13: return

  public boolean isDisposed();
    Code:
       0: aload_0
       1: getfield      #3                  // Field upstream:Ljava/util/concurrent/atomic/AtomicReference;
       4: invokevirtual #12                 // Method java/util/concurrent/atomic/AtomicReference.get:()Ljava/lang/Object;
       7: getstatic     #13                 // Field io/reactivex/rxjava3/internal/disposables/DisposableHelper.DISPOSED:Lio/reactivex/rxjava3/internal/disposables/DisposableHelper;
      10: if_acmpne     17
      13: iconst_1
      14: goto          18
      17: iconst_0
      18: ireturn

  public void setResource(io.reactivex.rxjava3.disposables.Disposable);
    Code:
       0: aload_0
       1: aload_1
       2: invokestatic  #14                 // Method io/reactivex/rxjava3/internal/disposables/DisposableHelper.set:(Ljava/util/concurrent/atomic/AtomicReference;Lio/reactivex/rxjava3/disposables/Disposable;)Z
       5: pop
       6: return
}
