Compiled from "ObservableUnsubscribeOn.java"
final class io.reactivex.rxjava3.internal.operators.observable.ObservableUnsubscribeOn$UnsubscribeObserver$DisposeTask implements java.lang.Runnable {
  final io.reactivex.rxjava3.internal.operators.observable.ObservableUnsubscribeOn$UnsubscribeObserver this$0;

  io.reactivex.rxjava3.internal.operators.observable.ObservableUnsubscribeOn$UnsubscribeObserver$DisposeTask(io.reactivex.rxjava3.internal.operators.observable.ObservableUnsubscribeOn$UnsubscribeObserver);
    Code:
       0: aload_0
       1: aload_1
       2: putfield      #1                  // Field this$0:Lio/reactivex/rxjava3/internal/operators/observable/ObservableUnsubscribeOn$UnsubscribeObserver;
       5: aload_0
       6: invokespecial #2                  // Method java/lang/Object."<init>":()V
       9: return

  public void run();
    Code:
       0: aload_0
       1: getfield      #1                  // Field this$0:Lio/reactivex/rxjava3/internal/operators/observable/ObservableUnsubscribeOn$UnsubscribeObserver;
       4: getfield      #3                  // Field io/reactivex/rxjava3/internal/operators/observable/ObservableUnsubscribeOn$UnsubscribeObserver.upstream:Lio/reactivex/rxjava3/disposables/Disposable;
       7: invokeinterface #4,  1            // InterfaceMethod io/reactivex/rxjava3/disposables/Disposable.dispose:()V
      12: return
}
