Compiled from "ObservableDoOnEach.java"
public final class io.reactivex.rxjava3.internal.operators.observable.ObservableDoOnEach<T> extends io.reactivex.rxjava3.internal.operators.observable.AbstractObservableWithUpstream<T, T> {
  final io.reactivex.rxjava3.functions.Consumer<? super T> onNext;

  final io.reactivex.rxjava3.functions.Consumer<? super java.lang.Throwable> onError;

  final io.reactivex.rxjava3.functions.Action onComplete;

  final io.reactivex.rxjava3.functions.Action onAfterTerminate;

  public io.reactivex.rxjava3.internal.operators.observable.ObservableDoOnEach(io.reactivex.rxjava3.core.ObservableSource<T>, io.reactivex.rxjava3.functions.Consumer<? super T>, io.reactivex.rxjava3.functions.Consumer<? super java.lang.Throwable>, io.reactivex.rxjava3.functions.Action, io.reactivex.rxjava3.functions.Action);
    Code:
       0: aload_0
       1: aload_1
       2: invokespecial #1                  // Method io/reactivex/rxjava3/internal/operators/observable/AbstractObservableWithUpstream."<init>":(Lio/reactivex/rxjava3/core/ObservableSource;)V
       5: aload_0
       6: aload_2
       7: putfield      #2                  // Field onNext:Lio/reactivex/rxjava3/functions/Consumer;
      10: aload_0
      11: aload_3
      12: putfield      #3                  // Field onError:Lio/reactivex/rxjava3/functions/Consumer;
      15: aload_0
      16: aload         4
      18: putfield      #4                  // Field onComplete:Lio/reactivex/rxjava3/functions/Action;
      21: aload_0
      22: aload         5
      24: putfield      #5                  // Field onAfterTerminate:Lio/reactivex/rxjava3/functions/Action;
      27: return

  public void subscribeActual(io.reactivex.rxjava3.core.Observer<? super T>);
    Code:
       0: aload_0
       1: getfield      #6                  // Field source:Lio/reactivex/rxjava3/core/ObservableSource;
       4: new           #7                  // class io/reactivex/rxjava3/internal/operators/observable/ObservableDoOnEach$DoOnEachObserver
       7: dup
       8: aload_1
       9: aload_0
      10: getfield      #2                  // Field onNext:Lio/reactivex/rxjava3/functions/Consumer;
      13: aload_0
      14: getfield      #3                  // Field onError:Lio/reactivex/rxjava3/functions/Consumer;
      17: aload_0
      18: getfield      #4                  // Field onComplete:Lio/reactivex/rxjava3/functions/Action;
      21: aload_0
      22: getfield      #5                  // Field onAfterTerminate:Lio/reactivex/rxjava3/functions/Action;
      25: invokespecial #8                  // Method io/reactivex/rxjava3/internal/operators/observable/ObservableDoOnEach$DoOnEachObserver."<init>":(Lio/reactivex/rxjava3/core/Observer;Lio/reactivex/rxjava3/functions/Consumer;Lio/reactivex/rxjava3/functions/Consumer;Lio/reactivex/rxjava3/functions/Action;Lio/reactivex/rxjava3/functions/Action;)V
      28: invokeinterface #9,  2            // InterfaceMethod io/reactivex/rxjava3/core/ObservableSource.subscribe:(Lio/reactivex/rxjava3/core/Observer;)V
      33: return
}
