Compiled from "ObservableSwitchIfEmpty.java"
final class io.reactivex.rxjava3.internal.operators.observable.ObservableSwitchIfEmpty$SwitchIfEmptyObserver<T> implements io.reactivex.rxjava3.core.Observer<T> {
  final io.reactivex.rxjava3.core.Observer<? super T> downstream;

  final io.reactivex.rxjava3.core.ObservableSource<? extends T> other;

  final io.reactivex.rxjava3.internal.disposables.SequentialDisposable arbiter;

  boolean empty;

  io.reactivex.rxjava3.internal.operators.observable.ObservableSwitchIfEmpty$SwitchIfEmptyObserver(io.reactivex.rxjava3.core.Observer<? super T>, io.reactivex.rxjava3.core.ObservableSource<? extends T>);
    Code:
       0: aload_0
       1: invokespecial #1                  // Method java/lang/Object."<init>":()V
       4: aload_0
       5: aload_1
       6: putfield      #2                  // Field downstream:Lio/reactivex/rxjava3/core/Observer;
       9: aload_0
      10: aload_2
      11: putfield      #3                  // Field other:Lio/reactivex/rxjava3/core/ObservableSource;
      14: aload_0
      15: iconst_1
      16: putfield      #4                  // Field empty:Z
      19: aload_0
      20: new           #5                  // class io/reactivex/rxjava3/internal/disposables/SequentialDisposable
      23: dup
      24: invokespecial #6                  // Method io/reactivex/rxjava3/internal/disposables/SequentialDisposable."<init>":()V
      27: putfield      #7                  // Field arbiter:Lio/reactivex/rxjava3/internal/disposables/SequentialDisposable;
      30: return

  public void onSubscribe(io.reactivex.rxjava3.disposables.Disposable);
    Code:
       0: aload_0
       1: getfield      #7                  // Field arbiter:Lio/reactivex/rxjava3/internal/disposables/SequentialDisposable;
       4: aload_1
       5: invokevirtual #8                  // Method io/reactivex/rxjava3/internal/disposables/SequentialDisposable.update:(Lio/reactivex/rxjava3/disposables/Disposable;)Z
       8: pop
       9: return

  public void onNext(T);
    Code:
       0: aload_0
       1: getfield      #4                  // Field empty:Z
       4: ifeq          12
       7: aload_0
       8: iconst_0
       9: putfield      #4                  // Field empty:Z
      12: aload_0
      13: getfield      #2                  // Field downstream:Lio/reactivex/rxjava3/core/Observer;
      16: aload_1
      17: invokeinterface #9,  2            // InterfaceMethod io/reactivex/rxjava3/core/Observer.onNext:(Ljava/lang/Object;)V
      22: return

  public void onError(java.lang.Throwable);
    Code:
       0: aload_0
       1: getfield      #2                  // Field downstream:Lio/reactivex/rxjava3/core/Observer;
       4: aload_1
       5: invokeinterface #10,  2           // InterfaceMethod io/reactivex/rxjava3/core/Observer.onError:(Ljava/lang/Throwable;)V
      10: return

  public void onComplete();
    Code:
       0: aload_0
       1: getfield      #4                  // Field empty:Z
       4: ifeq          25
       7: aload_0
       8: iconst_0
       9: putfield      #4                  // Field empty:Z
      12: aload_0
      13: getfield      #3                  // Field other:Lio/reactivex/rxjava3/core/ObservableSource;
      16: aload_0
      17: invokeinterface #11,  2           // InterfaceMethod io/reactivex/rxjava3/core/ObservableSource.subscribe:(Lio/reactivex/rxjava3/core/Observer;)V
      22: goto          34
      25: aload_0
      26: getfield      #2                  // Field downstream:Lio/reactivex/rxjava3/core/Observer;
      29: invokeinterface #12,  1           // InterfaceMethod io/reactivex/rxjava3/core/Observer.onComplete:()V
      34: return
}
