Compiled from "ObservableBufferBoundary.java"
final class io.reactivex.rxjava3.internal.operators.observable.ObservableBufferBoundary$BufferCloseObserver<T, C extends java.util.Collection<? super T>> extends java.util.concurrent.atomic.AtomicReference<io.reactivex.rxjava3.disposables.Disposable> implements io.reactivex.rxjava3.core.Observer<java.lang.Object>, io.reactivex.rxjava3.disposables.Disposable {
  private static final long serialVersionUID;

  final io.reactivex.rxjava3.internal.operators.observable.ObservableBufferBoundary$BufferBoundaryObserver<T, C, ?, ?> parent;

  final long index;

  io.reactivex.rxjava3.internal.operators.observable.ObservableBufferBoundary$BufferCloseObserver(io.reactivex.rxjava3.internal.operators.observable.ObservableBufferBoundary$BufferBoundaryObserver<T, C, ?, ?>, long);
    Code:
       0: aload_0
       1: invokespecial #1                  // Method java/util/concurrent/atomic/AtomicReference."<init>":()V
       4: aload_0
       5: aload_1
       6: putfield      #2                  // Field parent:Lio/reactivex/rxjava3/internal/operators/observable/ObservableBufferBoundary$BufferBoundaryObserver;
       9: aload_0
      10: lload_2
      11: putfield      #3                  // Field index:J
      14: return

  public void onSubscribe(io.reactivex.rxjava3.disposables.Disposable);
    Code:
       0: aload_0
       1: aload_1
       2: invokestatic  #4                  // Method io/reactivex/rxjava3/internal/disposables/DisposableHelper.setOnce:(Ljava/util/concurrent/atomic/AtomicReference;Lio/reactivex/rxjava3/disposables/Disposable;)Z
       5: pop
       6: return

  public void onNext(java.lang.Object);
    Code:
       0: aload_0
       1: invokevirtual #5                  // Method get:()Ljava/lang/Object;
       4: checkcast     #6                  // class io/reactivex/rxjava3/disposables/Disposable
       7: astore_2
       8: aload_2
       9: getstatic     #7                  // Field io/reactivex/rxjava3/internal/disposables/DisposableHelper.DISPOSED:Lio/reactivex/rxjava3/internal/disposables/DisposableHelper;
      12: if_acmpeq     40
      15: aload_0
      16: getstatic     #7                  // Field io/reactivex/rxjava3/internal/disposables/DisposableHelper.DISPOSED:Lio/reactivex/rxjava3/internal/disposables/DisposableHelper;
      19: invokevirtual #8                  // Method lazySet:(Ljava/lang/Object;)V
      22: aload_2
      23: invokeinterface #9,  1            // InterfaceMethod io/reactivex/rxjava3/disposables/Disposable.dispose:()V
      28: aload_0
      29: getfield      #2                  // Field parent:Lio/reactivex/rxjava3/internal/operators/observable/ObservableBufferBoundary$BufferBoundaryObserver;
      32: aload_0
      33: aload_0
      34: getfield      #3                  // Field index:J
      37: invokevirtual #10                 // Method io/reactivex/rxjava3/internal/operators/observable/ObservableBufferBoundary$BufferBoundaryObserver.close:(Lio/reactivex/rxjava3/internal/operators/observable/ObservableBufferBoundary$BufferCloseObserver;J)V
      40: return

  public void onError(java.lang.Throwable);
    Code:
       0: aload_0
       1: invokevirtual #5                  // Method get:()Ljava/lang/Object;
       4: getstatic     #7                  // Field io/reactivex/rxjava3/internal/disposables/DisposableHelper.DISPOSED:Lio/reactivex/rxjava3/internal/disposables/DisposableHelper;
       7: if_acmpeq     29
      10: aload_0
      11: getstatic     #7                  // Field io/reactivex/rxjava3/internal/disposables/DisposableHelper.DISPOSED:Lio/reactivex/rxjava3/internal/disposables/DisposableHelper;
      14: invokevirtual #8                  // Method lazySet:(Ljava/lang/Object;)V
      17: aload_0
      18: getfield      #2                  // Field parent:Lio/reactivex/rxjava3/internal/operators/observable/ObservableBufferBoundary$BufferBoundaryObserver;
      21: aload_0
      22: aload_1
      23: invokevirtual #11                 // Method io/reactivex/rxjava3/internal/operators/observable/ObservableBufferBoundary$BufferBoundaryObserver.boundaryError:(Lio/reactivex/rxjava3/disposables/Disposable;Ljava/lang/Throwable;)V
      26: goto          33
      29: aload_1
      30: invokestatic  #12                 // Method io/reactivex/rxjava3/plugins/RxJavaPlugins.onError:(Ljava/lang/Throwable;)V
      33: return

  public void onComplete();
    Code:
       0: aload_0
       1: invokevirtual #5                  // Method get:()Ljava/lang/Object;
       4: getstatic     #7                  // Field io/reactivex/rxjava3/internal/disposables/DisposableHelper.DISPOSED:Lio/reactivex/rxjava3/internal/disposables/DisposableHelper;
       7: if_acmpeq     29
      10: aload_0
      11: getstatic     #7                  // Field io/reactivex/rxjava3/internal/disposables/DisposableHelper.DISPOSED:Lio/reactivex/rxjava3/internal/disposables/DisposableHelper;
      14: invokevirtual #8                  // Method lazySet:(Ljava/lang/Object;)V
      17: aload_0
      18: getfield      #2                  // Field parent:Lio/reactivex/rxjava3/internal/operators/observable/ObservableBufferBoundary$BufferBoundaryObserver;
      21: aload_0
      22: aload_0
      23: getfield      #3                  // Field index:J
      26: invokevirtual #10                 // Method io/reactivex/rxjava3/internal/operators/observable/ObservableBufferBoundary$BufferBoundaryObserver.close:(Lio/reactivex/rxjava3/internal/operators/observable/ObservableBufferBoundary$BufferCloseObserver;J)V
      29: return

  public void dispose();
    Code:
       0: aload_0
       1: invokestatic  #13                 // Method io/reactivex/rxjava3/internal/disposables/DisposableHelper.dispose:(Ljava/util/concurrent/atomic/AtomicReference;)Z
       4: pop
       5: return

  public boolean isDisposed();
    Code:
       0: aload_0
       1: invokevirtual #5                  // Method get:()Ljava/lang/Object;
       4: getstatic     #7                  // Field io/reactivex/rxjava3/internal/disposables/DisposableHelper.DISPOSED:Lio/reactivex/rxjava3/internal/disposables/DisposableHelper;
       7: if_acmpne     14
      10: iconst_1
      11: goto          15
      14: iconst_0
      15: ireturn
}
