Compiled from "ObservableRetryBiPredicate.java"
public final class io.reactivex.rxjava3.internal.operators.observable.ObservableRetryBiPredicate<T> extends io.reactivex.rxjava3.internal.operators.observable.AbstractObservableWithUpstream<T, T> {
  final io.reactivex.rxjava3.functions.BiPredicate<? super java.lang.Integer, ? super java.lang.Throwable> predicate;

  public io.reactivex.rxjava3.internal.operators.observable.ObservableRetryBiPredicate(io.reactivex.rxjava3.core.Observable<T>, io.reactivex.rxjava3.functions.BiPredicate<? super java.lang.Integer, ? super java.lang.Throwable>);
    Code:
       0: aload_0
       1: aload_1
       2: invokespecial #1                  // Method io/reactivex/rxjava3/internal/operators/observable/AbstractObservableWithUpstream."<init>":(Lio/reactivex/rxjava3/core/ObservableSource;)V
       5: aload_0
       6: aload_2
       7: putfield      #2                  // Field predicate:Lio/reactivex/rxjava3/functions/BiPredicate;
      10: return

  public void subscribeActual(io.reactivex.rxjava3.core.Observer<? super T>);
    Code:
       0: new           #3                  // class io/reactivex/rxjava3/internal/disposables/SequentialDisposable
       3: dup
       4: invokespecial #4                  // Method io/reactivex/rxjava3/internal/disposables/SequentialDisposable."<init>":()V
       7: astore_2
       8: aload_1
       9: aload_2
      10: invokeinterface #5,  2            // InterfaceMethod io/reactivex/rxjava3/core/Observer.onSubscribe:(Lio/reactivex/rxjava3/disposables/Disposable;)V
      15: new           #6                  // class io/reactivex/rxjava3/internal/operators/observable/ObservableRetryBiPredicate$RetryBiObserver
      18: dup
      19: aload_1
      20: aload_0
      21: getfield      #2                  // Field predicate:Lio/reactivex/rxjava3/functions/BiPredicate;
      24: aload_2
      25: aload_0
      26: getfield      #7                  // Field source:Lio/reactivex/rxjava3/core/ObservableSource;
      29: invokespecial #8                  // Method io/reactivex/rxjava3/internal/operators/observable/ObservableRetryBiPredicate$RetryBiObserver."<init>":(Lio/reactivex/rxjava3/core/Observer;Lio/reactivex/rxjava3/functions/BiPredicate;Lio/reactivex/rxjava3/internal/disposables/SequentialDisposable;Lio/reactivex/rxjava3/core/ObservableSource;)V
      32: astore_3
      33: aload_3
      34: invokevirtual #9                  // Method io/reactivex/rxjava3/internal/operators/observable/ObservableRetryBiPredicate$RetryBiObserver.subscribeNext:()V
      37: return
}
