Compiled from "ObservableScalarXMap.java"
public final class io.reactivex.rxjava3.internal.operators.observable.ObservableScalarXMap {
  private io.reactivex.rxjava3.internal.operators.observable.ObservableScalarXMap();
    Code:
       0: aload_0
       1: invokespecial #1                  // Method java/lang/Object."<init>":()V
       4: new           #2                  // class java/lang/IllegalStateException
       7: dup
       8: ldc           #3                  // String No instances!
      10: invokespecial #4                  // Method java/lang/IllegalStateException."<init>":(Ljava/lang/String;)V
      13: athrow

  public static <T, R> boolean tryScalarXMapSubscribe(io.reactivex.rxjava3.core.ObservableSource<T>, io.reactivex.rxjava3.core.Observer<? super R>, io.reactivex.rxjava3.functions.Function<? super T, ? extends io.reactivex.rxjava3.core.ObservableSource<? extends R>>);
    Code:
       0: aload_0
       1: instanceof    #5                  // class io/reactivex/rxjava3/functions/Supplier
       4: ifeq          167
       7: aload_0
       8: checkcast     #5                  // class io/reactivex/rxjava3/functions/Supplier
      11: invokeinterface #6,  1            // InterfaceMethod io/reactivex/rxjava3/functions/Supplier.get:()Ljava/lang/Object;
      16: astore_3
      17: goto          35
      20: astore        4
      22: aload         4
      24: invokestatic  #8                  // Method io/reactivex/rxjava3/exceptions/Exceptions.throwIfFatal:(Ljava/lang/Throwable;)V
      27: aload         4
      29: aload_1
      30: invokestatic  #9                  // Method io/reactivex/rxjava3/internal/disposables/EmptyDisposable.error:(Ljava/lang/Throwable;Lio/reactivex/rxjava3/core/Observer;)V
      33: iconst_1
      34: ireturn
      35: aload_3
      36: ifnonnull     45
      39: aload_1
      40: invokestatic  #10                 // Method io/reactivex/rxjava3/internal/disposables/EmptyDisposable.complete:(Lio/reactivex/rxjava3/core/Observer;)V
      43: iconst_1
      44: ireturn
      45: aload_2
      46: aload_3
      47: invokeinterface #11,  2           // InterfaceMethod io/reactivex/rxjava3/functions/Function.apply:(Ljava/lang/Object;)Ljava/lang/Object;
      52: ldc           #12                 // String The mapper returned a null ObservableSource
      54: invokestatic  #13                 // Method java/util/Objects.requireNonNull:(Ljava/lang/Object;Ljava/lang/String;)Ljava/lang/Object;
      57: checkcast     #14                 // class io/reactivex/rxjava3/core/ObservableSource
      60: astore        4
      62: goto          80
      65: astore        5
      67: aload         5
      69: invokestatic  #8                  // Method io/reactivex/rxjava3/exceptions/Exceptions.throwIfFatal:(Ljava/lang/Throwable;)V
      72: aload         5
      74: aload_1
      75: invokestatic  #9                  // Method io/reactivex/rxjava3/internal/disposables/EmptyDisposable.error:(Ljava/lang/Throwable;Lio/reactivex/rxjava3/core/Observer;)V
      78: iconst_1
      79: ireturn
      80: aload         4
      82: instanceof    #5                  // class io/reactivex/rxjava3/functions/Supplier
      85: ifeq          157
      88: aload         4
      90: checkcast     #5                  // class io/reactivex/rxjava3/functions/Supplier
      93: invokeinterface #6,  1            // InterfaceMethod io/reactivex/rxjava3/functions/Supplier.get:()Ljava/lang/Object;
      98: astore        5
     100: goto          118
     103: astore        6
     105: aload         6
     107: invokestatic  #8                  // Method io/reactivex/rxjava3/exceptions/Exceptions.throwIfFatal:(Ljava/lang/Throwable;)V
     110: aload         6
     112: aload_1
     113: invokestatic  #9                  // Method io/reactivex/rxjava3/internal/disposables/EmptyDisposable.error:(Ljava/lang/Throwable;Lio/reactivex/rxjava3/core/Observer;)V
     116: iconst_1
     117: ireturn
     118: aload         5
     120: ifnonnull     129
     123: aload_1
     124: invokestatic  #10                 // Method io/reactivex/rxjava3/internal/disposables/EmptyDisposable.complete:(Lio/reactivex/rxjava3/core/Observer;)V
     127: iconst_1
     128: ireturn
     129: new           #15                 // class io/reactivex/rxjava3/internal/operators/observable/ObservableScalarXMap$ScalarDisposable
     132: dup
     133: aload_1
     134: aload         5
     136: invokespecial #16                 // Method io/reactivex/rxjava3/internal/operators/observable/ObservableScalarXMap$ScalarDisposable."<init>":(Lio/reactivex/rxjava3/core/Observer;Ljava/lang/Object;)V
     139: astore        6
     141: aload_1
     142: aload         6
     144: invokeinterface #17,  2           // InterfaceMethod io/reactivex/rxjava3/core/Observer.onSubscribe:(Lio/reactivex/rxjava3/disposables/Disposable;)V
     149: aload         6
     151: invokevirtual #18                 // Method io/reactivex/rxjava3/internal/operators/observable/ObservableScalarXMap$ScalarDisposable.run:()V
     154: goto          165
     157: aload         4
     159: aload_1
     160: invokeinterface #19,  2           // InterfaceMethod io/reactivex/rxjava3/core/ObservableSource.subscribe:(Lio/reactivex/rxjava3/core/Observer;)V
     165: iconst_1
     166: ireturn
     167: iconst_0
     168: ireturn
    Exception table:
       from    to  target type
           7    17    20   Class java/lang/Throwable
          45    62    65   Class java/lang/Throwable
          88   100   103   Class java/lang/Throwable

  public static <T, U> io.reactivex.rxjava3.core.Observable<U> scalarXMap(T, io.reactivex.rxjava3.functions.Function<? super T, ? extends io.reactivex.rxjava3.core.ObservableSource<? extends U>>);
    Code:
       0: new           #20                 // class io/reactivex/rxjava3/internal/operators/observable/ObservableScalarXMap$ScalarXMapObservable
       3: dup
       4: aload_0
       5: aload_1
       6: invokespecial #21                 // Method io/reactivex/rxjava3/internal/operators/observable/ObservableScalarXMap$ScalarXMapObservable."<init>":(Ljava/lang/Object;Lio/reactivex/rxjava3/functions/Function;)V
       9: invokestatic  #22                 // Method io/reactivex/rxjava3/plugins/RxJavaPlugins.onAssembly:(Lio/reactivex/rxjava3/core/Observable;)Lio/reactivex/rxjava3/core/Observable;
      12: areturn
}
