Compiled from "ObservableReduceWithSingle.java"
public final class io.reactivex.rxjava3.internal.operators.observable.ObservableReduceWithSingle<T, R> extends io.reactivex.rxjava3.core.Single<R> {
  final io.reactivex.rxjava3.core.ObservableSource<T> source;

  final io.reactivex.rxjava3.functions.Supplier<R> seedSupplier;

  final io.reactivex.rxjava3.functions.BiFunction<R, ? super T, R> reducer;

  public io.reactivex.rxjava3.internal.operators.observable.ObservableReduceWithSingle(io.reactivex.rxjava3.core.ObservableSource<T>, io.reactivex.rxjava3.functions.Supplier<R>, io.reactivex.rxjava3.functions.BiFunction<R, ? super T, R>);
    Code:
       0: aload_0
       1: invokespecial #1                  // Method io/reactivex/rxjava3/core/Single."<init>":()V
       4: aload_0
       5: aload_1
       6: putfield      #2                  // Field source:Lio/reactivex/rxjava3/core/ObservableSource;
       9: aload_0
      10: aload_2
      11: putfield      #3                  // Field seedSupplier:Lio/reactivex/rxjava3/functions/Supplier;
      14: aload_0
      15: aload_3
      16: putfield      #4                  // Field reducer:Lio/reactivex/rxjava3/functions/BiFunction;
      19: return

  protected void subscribeActual(io.reactivex.rxjava3.core.SingleObserver<? super R>);
    Code:
       0: aload_0
       1: getfield      #3                  // Field seedSupplier:Lio/reactivex/rxjava3/functions/Supplier;
       4: invokeinterface #5,  1            // InterfaceMethod io/reactivex/rxjava3/functions/Supplier.get:()Ljava/lang/Object;
       9: ldc           #6                  // String The seedSupplier returned a null value
      11: invokestatic  #7                  // Method java/util/Objects.requireNonNull:(Ljava/lang/Object;Ljava/lang/String;)Ljava/lang/Object;
      14: astore_2
      15: goto          29
      18: astore_3
      19: aload_3
      20: invokestatic  #9                  // Method io/reactivex/rxjava3/exceptions/Exceptions.throwIfFatal:(Ljava/lang/Throwable;)V
      23: aload_3
      24: aload_1
      25: invokestatic  #10                 // Method io/reactivex/rxjava3/internal/disposables/EmptyDisposable.error:(Ljava/lang/Throwable;Lio/reactivex/rxjava3/core/SingleObserver;)V
      28: return
      29: aload_0
      30: getfield      #2                  // Field source:Lio/reactivex/rxjava3/core/ObservableSource;
      33: new           #11                 // class io/reactivex/rxjava3/internal/operators/observable/ObservableReduceSeedSingle$ReduceSeedObserver
      36: dup
      37: aload_1
      38: aload_0
      39: getfield      #4                  // Field reducer:Lio/reactivex/rxjava3/functions/BiFunction;
      42: aload_2
      43: invokespecial #12                 // Method io/reactivex/rxjava3/internal/operators/observable/ObservableReduceSeedSingle$ReduceSeedObserver."<init>":(Lio/reactivex/rxjava3/core/SingleObserver;Lio/reactivex/rxjava3/functions/BiFunction;Ljava/lang/Object;)V
      46: invokeinterface #13,  2           // InterfaceMethod io/reactivex/rxjava3/core/ObservableSource.subscribe:(Lio/reactivex/rxjava3/core/Observer;)V
      51: return
    Exception table:
       from    to  target type
           0    15    18   Class java/lang/Throwable
}
