Compiled from "ObservableWithLatestFrom.java"
final class io.reactivex.rxjava3.internal.operators.observable.ObservableWithLatestFrom$WithLatestFromOtherObserver implements io.reactivex.rxjava3.core.Observer<U> {
  private final io.reactivex.rxjava3.internal.operators.observable.ObservableWithLatestFrom$WithLatestFromObserver<T, U, R> parent;

  final io.reactivex.rxjava3.internal.operators.observable.ObservableWithLatestFrom this$0;

  io.reactivex.rxjava3.internal.operators.observable.ObservableWithLatestFrom$WithLatestFromOtherObserver(io.reactivex.rxjava3.internal.operators.observable.ObservableWithLatestFrom$WithLatestFromObserver<T, U, R>);
    Code:
       0: aload_0
       1: aload_1
       2: putfield      #1                  // Field this$0:Lio/reactivex/rxjava3/internal/operators/observable/ObservableWithLatestFrom;
       5: aload_0
       6: invokespecial #2                  // Method java/lang/Object."<init>":()V
       9: aload_0
      10: aload_2
      11: putfield      #3                  // Field parent:Lio/reactivex/rxjava3/internal/operators/observable/ObservableWithLatestFrom$WithLatestFromObserver;
      14: return

  public void onSubscribe(io.reactivex.rxjava3.disposables.Disposable);
    Code:
       0: aload_0
       1: getfield      #3                  // Field parent:Lio/reactivex/rxjava3/internal/operators/observable/ObservableWithLatestFrom$WithLatestFromObserver;
       4: aload_1
       5: invokevirtual #4                  // Method io/reactivex/rxjava3/internal/operators/observable/ObservableWithLatestFrom$WithLatestFromObserver.setOther:(Lio/reactivex/rxjava3/disposables/Disposable;)Z
       8: pop
       9: return

  public void onNext(U);
    Code:
       0: aload_0
       1: getfield      #3                  // Field parent:Lio/reactivex/rxjava3/internal/operators/observable/ObservableWithLatestFrom$WithLatestFromObserver;
       4: aload_1
       5: invokevirtual #5                  // Method io/reactivex/rxjava3/internal/operators/observable/ObservableWithLatestFrom$WithLatestFromObserver.lazySet:(Ljava/lang/Object;)V
       8: return

  public void onError(java.lang.Throwable);
    Code:
       0: aload_0
       1: getfield      #3                  // Field parent:Lio/reactivex/rxjava3/internal/operators/observable/ObservableWithLatestFrom$WithLatestFromObserver;
       4: aload_1
       5: invokevirtual #6                  // Method io/reactivex/rxjava3/internal/operators/observable/ObservableWithLatestFrom$WithLatestFromObserver.otherError:(Ljava/lang/Throwable;)V
       8: return

  public void onComplete();
    Code:
       0: return
}
