Compiled from "ObservableConcatMap.java"
public final class io.reactivex.rxjava3.internal.operators.observable.ObservableConcatMap<T, U> extends io.reactivex.rxjava3.internal.operators.observable.AbstractObservableWithUpstream<T, U> {
  final io.reactivex.rxjava3.functions.Function<? super T, ? extends io.reactivex.rxjava3.core.ObservableSource<? extends U>> mapper;

  final int bufferSize;

  final io.reactivex.rxjava3.internal.util.ErrorMode delayErrors;

  public io.reactivex.rxjava3.internal.operators.observable.ObservableConcatMap(io.reactivex.rxjava3.core.ObservableSource<T>, io.reactivex.rxjava3.functions.Function<? super T, ? extends io.reactivex.rxjava3.core.ObservableSource<? extends U>>, int, io.reactivex.rxjava3.internal.util.ErrorMode);
    Code:
       0: aload_0
       1: aload_1
       2: invokespecial #1                  // Method io/reactivex/rxjava3/internal/operators/observable/AbstractObservableWithUpstream."<init>":(Lio/reactivex/rxjava3/core/ObservableSource;)V
       5: aload_0
       6: aload_2
       7: putfield      #2                  // Field mapper:Lio/reactivex/rxjava3/functions/Function;
      10: aload_0
      11: aload         4
      13: putfield      #3                  // Field delayErrors:Lio/reactivex/rxjava3/internal/util/ErrorMode;
      16: aload_0
      17: bipush        8
      19: iload_3
      20: invokestatic  #4                  // Method java/lang/Math.max:(II)I
      23: putfield      #5                  // Field bufferSize:I
      26: return

  public void subscribeActual(io.reactivex.rxjava3.core.Observer<? super U>);
    Code:
       0: aload_0
       1: getfield      #6                  // Field source:Lio/reactivex/rxjava3/core/ObservableSource;
       4: aload_1
       5: aload_0
       6: getfield      #2                  // Field mapper:Lio/reactivex/rxjava3/functions/Function;
       9: invokestatic  #7                  // Method io/reactivex/rxjava3/internal/operators/observable/ObservableScalarXMap.tryScalarXMapSubscribe:(Lio/reactivex/rxjava3/core/ObservableSource;Lio/reactivex/rxjava3/core/Observer;Lio/reactivex/rxjava3/functions/Function;)Z
      12: ifeq          16
      15: return
      16: aload_0
      17: getfield      #3                  // Field delayErrors:Lio/reactivex/rxjava3/internal/util/ErrorMode;
      20: getstatic     #8                  // Field io/reactivex/rxjava3/internal/util/ErrorMode.IMMEDIATE:Lio/reactivex/rxjava3/internal/util/ErrorMode;
      23: if_acmpne     63
      26: new           #9                  // class io/reactivex/rxjava3/observers/SerializedObserver
      29: dup
      30: aload_1
      31: invokespecial #10                 // Method io/reactivex/rxjava3/observers/SerializedObserver."<init>":(Lio/reactivex/rxjava3/core/Observer;)V
      34: astore_2
      35: aload_0
      36: getfield      #6                  // Field source:Lio/reactivex/rxjava3/core/ObservableSource;
      39: new           #11                 // class io/reactivex/rxjava3/internal/operators/observable/ObservableConcatMap$SourceObserver
      42: dup
      43: aload_2
      44: aload_0
      45: getfield      #2                  // Field mapper:Lio/reactivex/rxjava3/functions/Function;
      48: aload_0
      49: getfield      #5                  // Field bufferSize:I
      52: invokespecial #12                 // Method io/reactivex/rxjava3/internal/operators/observable/ObservableConcatMap$SourceObserver."<init>":(Lio/reactivex/rxjava3/core/Observer;Lio/reactivex/rxjava3/functions/Function;I)V
      55: invokeinterface #13,  2           // InterfaceMethod io/reactivex/rxjava3/core/ObservableSource.subscribe:(Lio/reactivex/rxjava3/core/Observer;)V
      60: goto          103
      63: aload_0
      64: getfield      #6                  // Field source:Lio/reactivex/rxjava3/core/ObservableSource;
      67: new           #14                 // class io/reactivex/rxjava3/internal/operators/observable/ObservableConcatMap$ConcatMapDelayErrorObserver
      70: dup
      71: aload_1
      72: aload_0
      73: getfield      #2                  // Field mapper:Lio/reactivex/rxjava3/functions/Function;
      76: aload_0
      77: getfield      #5                  // Field bufferSize:I
      80: aload_0
      81: getfield      #3                  // Field delayErrors:Lio/reactivex/rxjava3/internal/util/ErrorMode;
      84: getstatic     #15                 // Field io/reactivex/rxjava3/internal/util/ErrorMode.END:Lio/reactivex/rxjava3/internal/util/ErrorMode;
      87: if_acmpne     94
      90: iconst_1
      91: goto          95
      94: iconst_0
      95: invokespecial #16                 // Method io/reactivex/rxjava3/internal/operators/observable/ObservableConcatMap$ConcatMapDelayErrorObserver."<init>":(Lio/reactivex/rxjava3/core/Observer;Lio/reactivex/rxjava3/functions/Function;IZ)V
      98: invokeinterface #13,  2           // InterfaceMethod io/reactivex/rxjava3/core/ObservableSource.subscribe:(Lio/reactivex/rxjava3/core/Observer;)V
     103: return
}
