Compiled from "ObservableWithLatestFromMany.java"
final class io.reactivex.rxjava3.internal.operators.observable.ObservableWithLatestFromMany$SingletonArrayFunc implements io.reactivex.rxjava3.functions.Function<T, R> {
  final io.reactivex.rxjava3.internal.operators.observable.ObservableWithLatestFromMany this$0;

  io.reactivex.rxjava3.internal.operators.observable.ObservableWithLatestFromMany$SingletonArrayFunc(io.reactivex.rxjava3.internal.operators.observable.ObservableWithLatestFromMany);
    Code:
       0: aload_0
       1: aload_1
       2: putfield      #1                  // Field this$0:Lio/reactivex/rxjava3/internal/operators/observable/ObservableWithLatestFromMany;
       5: aload_0
       6: invokespecial #2                  // Method java/lang/Object."<init>":()V
       9: return

  public R apply(T) throws java.lang.Throwable;
    Code:
       0: aload_0
       1: getfield      #1                  // Field this$0:Lio/reactivex/rxjava3/internal/operators/observable/ObservableWithLatestFromMany;
       4: getfield      #3                  // Field io/reactivex/rxjava3/internal/operators/observable/ObservableWithLatestFromMany.combiner:Lio/reactivex/rxjava3/functions/Function;
       7: iconst_1
       8: anewarray     #4                  // class java/lang/Object
      11: dup
      12: iconst_0
      13: aload_1
      14: aastore
      15: invokeinterface #5,  2            // InterfaceMethod io/reactivex/rxjava3/functions/Function.apply:(Ljava/lang/Object;)Ljava/lang/Object;
      20: ldc           #6                  // String The combiner returned a null value
      22: invokestatic  #7                  // Method java/util/Objects.requireNonNull:(Ljava/lang/Object;Ljava/lang/String;)Ljava/lang/Object;
      25: areturn
}
