Compiled from "ObservableDoOnLifecycle.java"
public final class io.reactivex.rxjava3.internal.operators.observable.ObservableDoOnLifecycle<T> extends io.reactivex.rxjava3.internal.operators.observable.AbstractObservableWithUpstream<T, T> {
  private final io.reactivex.rxjava3.functions.Consumer<? super io.reactivex.rxjava3.disposables.Disposable> onSubscribe;

  private final io.reactivex.rxjava3.functions.Action onDispose;

  public io.reactivex.rxjava3.internal.operators.observable.ObservableDoOnLifecycle(io.reactivex.rxjava3.core.Observable<T>, io.reactivex.rxjava3.functions.Consumer<? super io.reactivex.rxjava3.disposables.Disposable>, io.reactivex.rxjava3.functions.Action);
    Code:
       0: aload_0
       1: aload_1
       2: invokespecial #1                  // Method io/reactivex/rxjava3/internal/operators/observable/AbstractObservableWithUpstream."<init>":(Lio/reactivex/rxjava3/core/ObservableSource;)V
       5: aload_0
       6: aload_2
       7: putfield      #2                  // Field onSubscribe:Lio/reactivex/rxjava3/functions/Consumer;
      10: aload_0
      11: aload_3
      12: putfield      #3                  // Field onDispose:Lio/reactivex/rxjava3/functions/Action;
      15: return

  protected void subscribeActual(io.reactivex.rxjava3.core.Observer<? super T>);
    Code:
       0: aload_0
       1: getfield      #4                  // Field source:Lio/reactivex/rxjava3/core/ObservableSource;
       4: new           #5                  // class io/reactivex/rxjava3/internal/observers/DisposableLambdaObserver
       7: dup
       8: aload_1
       9: aload_0
      10: getfield      #2                  // Field onSubscribe:Lio/reactivex/rxjava3/functions/Consumer;
      13: aload_0
      14: getfield      #3                  // Field onDispose:Lio/reactivex/rxjava3/functions/Action;
      17: invokespecial #6                  // Method io/reactivex/rxjava3/internal/observers/DisposableLambdaObserver."<init>":(Lio/reactivex/rxjava3/core/Observer;Lio/reactivex/rxjava3/functions/Consumer;Lio/reactivex/rxjava3/functions/Action;)V
      20: invokeinterface #7,  2            // InterfaceMethod io/reactivex/rxjava3/core/ObservableSource.subscribe:(Lio/reactivex/rxjava3/core/Observer;)V
      25: return
}
