Compiled from "ObservableDebounceTimed.java"
final class io.reactivex.rxjava3.internal.operators.observable.ObservableDebounceTimed$DebounceEmitter<T> extends java.util.concurrent.atomic.AtomicReference<io.reactivex.rxjava3.disposables.Disposable> implements java.lang.Runnable, io.reactivex.rxjava3.disposables.Disposable {
  private static final long serialVersionUID;

  final T value;

  final long idx;

  final io.reactivex.rxjava3.internal.operators.observable.ObservableDebounceTimed$DebounceTimedObserver<T> parent;

  final java.util.concurrent.atomic.AtomicBoolean once;

  io.reactivex.rxjava3.internal.operators.observable.ObservableDebounceTimed$DebounceEmitter(T, long, io.reactivex.rxjava3.internal.operators.observable.ObservableDebounceTimed$DebounceTimedObserver<T>);
    Code:
       0: aload_0
       1: invokespecial #1                  // Method java/util/concurrent/atomic/AtomicReference."<init>":()V
       4: aload_0
       5: new           #2                  // class java/util/concurrent/atomic/AtomicBoolean
       8: dup
       9: invokespecial #3                  // Method java/util/concurrent/atomic/AtomicBoolean."<init>":()V
      12: putfield      #4                  // Field once:Ljava/util/concurrent/atomic/AtomicBoolean;
      15: aload_0
      16: aload_1
      17: putfield      #5                  // Field value:Ljava/lang/Object;
      20: aload_0
      21: lload_2
      22: putfield      #6                  // Field idx:J
      25: aload_0
      26: aload         4
      28: putfield      #7                  // Field parent:Lio/reactivex/rxjava3/internal/operators/observable/ObservableDebounceTimed$DebounceTimedObserver;
      31: return

  public void run();
    Code:
       0: aload_0
       1: getfield      #4                  // Field once:Ljava/util/concurrent/atomic/AtomicBoolean;
       4: iconst_0
       5: iconst_1
       6: invokevirtual #8                  // Method java/util/concurrent/atomic/AtomicBoolean.compareAndSet:(ZZ)Z
       9: ifeq          28
      12: aload_0
      13: getfield      #7                  // Field parent:Lio/reactivex/rxjava3/internal/operators/observable/ObservableDebounceTimed$DebounceTimedObserver;
      16: aload_0
      17: getfield      #6                  // Field idx:J
      20: aload_0
      21: getfield      #5                  // Field value:Ljava/lang/Object;
      24: aload_0
      25: invokevirtual #9                  // Method io/reactivex/rxjava3/internal/operators/observable/ObservableDebounceTimed$DebounceTimedObserver.emit:(JLjava/lang/Object;Lio/reactivex/rxjava3/internal/operators/observable/ObservableDebounceTimed$DebounceEmitter;)V
      28: return

  public void dispose();
    Code:
       0: aload_0
       1: invokestatic  #10                 // Method io/reactivex/rxjava3/internal/disposables/DisposableHelper.dispose:(Ljava/util/concurrent/atomic/AtomicReference;)Z
       4: pop
       5: return

  public boolean isDisposed();
    Code:
       0: aload_0
       1: invokevirtual #11                 // Method get:()Ljava/lang/Object;
       4: getstatic     #12                 // Field io/reactivex/rxjava3/internal/disposables/DisposableHelper.DISPOSED:Lio/reactivex/rxjava3/internal/disposables/DisposableHelper;
       7: if_acmpne     14
      10: iconst_1
      11: goto          15
      14: iconst_0
      15: ireturn

  public void setResource(io.reactivex.rxjava3.disposables.Disposable);
    Code:
       0: aload_0
       1: aload_1
       2: invokestatic  #13                 // Method io/reactivex/rxjava3/internal/disposables/DisposableHelper.replace:(Ljava/util/concurrent/atomic/AtomicReference;Lio/reactivex/rxjava3/disposables/Disposable;)Z
       5: pop
       6: return
}
