Compiled from "ObservableIgnoreElementsCompletable.java"
public final class io.reactivex.rxjava3.internal.operators.observable.ObservableIgnoreElementsCompletable<T> extends io.reactivex.rxjava3.core.Completable implements io.reactivex.rxjava3.internal.fuseable.FuseToObservable<T> {
  final io.reactivex.rxjava3.core.ObservableSource<T> source;

  public io.reactivex.rxjava3.internal.operators.observable.ObservableIgnoreElementsCompletable(io.reactivex.rxjava3.core.ObservableSource<T>);
    Code:
       0: aload_0
       1: invokespecial #1                  // Method io/reactivex/rxjava3/core/Completable."<init>":()V
       4: aload_0
       5: aload_1
       6: putfield      #2                  // Field source:Lio/reactivex/rxjava3/core/ObservableSource;
       9: return

  public void subscribeActual(io.reactivex.rxjava3.core.CompletableObserver);
    Code:
       0: aload_0
       1: getfield      #2                  // Field source:Lio/reactivex/rxjava3/core/ObservableSource;
       4: new           #3                  // class io/reactivex/rxjava3/internal/operators/observable/ObservableIgnoreElementsCompletable$IgnoreObservable
       7: dup
       8: aload_1
       9: invokespecial #4                  // Method io/reactivex/rxjava3/internal/operators/observable/ObservableIgnoreElementsCompletable$IgnoreObservable."<init>":(Lio/reactivex/rxjava3/core/CompletableObserver;)V
      12: invokeinterface #5,  2            // InterfaceMethod io/reactivex/rxjava3/core/ObservableSource.subscribe:(Lio/reactivex/rxjava3/core/Observer;)V
      17: return

  public io.reactivex.rxjava3.core.Observable<T> fuseToObservable();
    Code:
       0: new           #6                  // class io/reactivex/rxjava3/internal/operators/observable/ObservableIgnoreElements
       3: dup
       4: aload_0
       5: getfield      #2                  // Field source:Lio/reactivex/rxjava3/core/ObservableSource;
       8: invokespecial #7                  // Method io/reactivex/rxjava3/internal/operators/observable/ObservableIgnoreElements."<init>":(Lio/reactivex/rxjava3/core/ObservableSource;)V
      11: invokestatic  #8                  // Method io/reactivex/rxjava3/plugins/RxJavaPlugins.onAssembly:(Lio/reactivex/rxjava3/core/Observable;)Lio/reactivex/rxjava3/core/Observable;
      14: areturn
}
