Compiled from "ObservableConcatWithMaybe.java"
final class io.reactivex.rxjava3.internal.operators.observable.ObservableConcatWithMaybe$ConcatWithObserver<T> extends java.util.concurrent.atomic.AtomicReference<io.reactivex.rxjava3.disposables.Disposable> implements io.reactivex.rxjava3.core.Observer<T>, io.reactivex.rxjava3.core.MaybeObserver<T>, io.reactivex.rxjava3.disposables.Disposable {
  private static final long serialVersionUID;

  final io.reactivex.rxjava3.core.Observer<? super T> downstream;

  io.reactivex.rxjava3.core.MaybeSource<? extends T> other;

  boolean inMaybe;

  io.reactivex.rxjava3.internal.operators.observable.ObservableConcatWithMaybe$ConcatWithObserver(io.reactivex.rxjava3.core.Observer<? super T>, io.reactivex.rxjava3.core.MaybeSource<? extends T>);
    Code:
       0: aload_0
       1: invokespecial #1                  // Method java/util/concurrent/atomic/AtomicReference."<init>":()V
       4: aload_0
       5: aload_1
       6: putfield      #2                  // Field downstream:Lio/reactivex/rxjava3/core/Observer;
       9: aload_0
      10: aload_2
      11: putfield      #3                  // Field other:Lio/reactivex/rxjava3/core/MaybeSource;
      14: return

  public void onSubscribe(io.reactivex.rxjava3.disposables.Disposable);
    Code:
       0: aload_0
       1: aload_1
       2: invokestatic  #4                  // Method io/reactivex/rxjava3/internal/disposables/DisposableHelper.setOnce:(Ljava/util/concurrent/atomic/AtomicReference;Lio/reactivex/rxjava3/disposables/Disposable;)Z
       5: ifeq          25
       8: aload_0
       9: getfield      #5                  // Field inMaybe:Z
      12: ifne          25
      15: aload_0
      16: getfield      #2                  // Field downstream:Lio/reactivex/rxjava3/core/Observer;
      19: aload_0
      20: invokeinterface #6,  2            // InterfaceMethod io/reactivex/rxjava3/core/Observer.onSubscribe:(Lio/reactivex/rxjava3/disposables/Disposable;)V
      25: return

  public void onNext(T);
    Code:
       0: aload_0
       1: getfield      #2                  // Field downstream:Lio/reactivex/rxjava3/core/Observer;
       4: aload_1
       5: invokeinterface #7,  2            // InterfaceMethod io/reactivex/rxjava3/core/Observer.onNext:(Ljava/lang/Object;)V
      10: return

  public void onSuccess(T);
    Code:
       0: aload_0
       1: getfield      #2                  // Field downstream:Lio/reactivex/rxjava3/core/Observer;
       4: aload_1
       5: invokeinterface #7,  2            // InterfaceMethod io/reactivex/rxjava3/core/Observer.onNext:(Ljava/lang/Object;)V
      10: aload_0
      11: getfield      #2                  // Field downstream:Lio/reactivex/rxjava3/core/Observer;
      14: invokeinterface #8,  1            // InterfaceMethod io/reactivex/rxjava3/core/Observer.onComplete:()V
      19: return

  public void onError(java.lang.Throwable);
    Code:
       0: aload_0
       1: getfield      #2                  // Field downstream:Lio/reactivex/rxjava3/core/Observer;
       4: aload_1
       5: invokeinterface #9,  2            // InterfaceMethod io/reactivex/rxjava3/core/Observer.onError:(Ljava/lang/Throwable;)V
      10: return

  public void onComplete();
    Code:
       0: aload_0
       1: getfield      #5                  // Field inMaybe:Z
       4: ifeq          19
       7: aload_0
       8: getfield      #2                  // Field downstream:Lio/reactivex/rxjava3/core/Observer;
      11: invokeinterface #8,  1            // InterfaceMethod io/reactivex/rxjava3/core/Observer.onComplete:()V
      16: goto          47
      19: aload_0
      20: iconst_1
      21: putfield      #5                  // Field inMaybe:Z
      24: aload_0
      25: aconst_null
      26: invokestatic  #10                 // Method io/reactivex/rxjava3/internal/disposables/DisposableHelper.replace:(Ljava/util/concurrent/atomic/AtomicReference;Lio/reactivex/rxjava3/disposables/Disposable;)Z
      29: pop
      30: aload_0
      31: getfield      #3                  // Field other:Lio/reactivex/rxjava3/core/MaybeSource;
      34: astore_1
      35: aload_0
      36: aconst_null
      37: putfield      #3                  // Field other:Lio/reactivex/rxjava3/core/MaybeSource;
      40: aload_1
      41: aload_0
      42: invokeinterface #11,  2           // InterfaceMethod io/reactivex/rxjava3/core/MaybeSource.subscribe:(Lio/reactivex/rxjava3/core/MaybeObserver;)V
      47: return

  public void dispose();
    Code:
       0: aload_0
       1: invokestatic  #12                 // Method io/reactivex/rxjava3/internal/disposables/DisposableHelper.dispose:(Ljava/util/concurrent/atomic/AtomicReference;)Z
       4: pop
       5: return

  public boolean isDisposed();
    Code:
       0: aload_0
       1: invokevirtual #13                 // Method get:()Ljava/lang/Object;
       4: checkcast     #14                 // class io/reactivex/rxjava3/disposables/Disposable
       7: invokestatic  #15                 // Method io/reactivex/rxjava3/internal/disposables/DisposableHelper.isDisposed:(Lio/reactivex/rxjava3/disposables/Disposable;)Z
      10: ireturn
}
