Compiled from "ObservableAllSingle.java"
final class io.reactivex.rxjava3.internal.operators.observable.ObservableAllSingle$AllObserver<T> implements io.reactivex.rxjava3.core.Observer<T>, io.reactivex.rxjava3.disposables.Disposable {
  final io.reactivex.rxjava3.core.SingleObserver<? super java.lang.Boolean> downstream;

  final io.reactivex.rxjava3.functions.Predicate<? super T> predicate;

  io.reactivex.rxjava3.disposables.Disposable upstream;

  boolean done;

  io.reactivex.rxjava3.internal.operators.observable.ObservableAllSingle$AllObserver(io.reactivex.rxjava3.core.SingleObserver<? super java.lang.Boolean>, io.reactivex.rxjava3.functions.Predicate<? super T>);
    Code:
       0: aload_0
       1: invokespecial #1                  // Method java/lang/Object."<init>":()V
       4: aload_0
       5: aload_1
       6: putfield      #2                  // Field downstream:Lio/reactivex/rxjava3/core/SingleObserver;
       9: aload_0
      10: aload_2
      11: putfield      #3                  // Field predicate:Lio/reactivex/rxjava3/functions/Predicate;
      14: return

  public void onSubscribe(io.reactivex.rxjava3.disposables.Disposable);
    Code:
       0: aload_0
       1: getfield      #4                  // Field upstream:Lio/reactivex/rxjava3/disposables/Disposable;
       4: aload_1
       5: invokestatic  #5                  // Method io/reactivex/rxjava3/internal/disposables/DisposableHelper.validate:(Lio/reactivex/rxjava3/disposables/Disposable;Lio/reactivex/rxjava3/disposables/Disposable;)Z
       8: ifeq          26
      11: aload_0
      12: aload_1
      13: putfield      #4                  // Field upstream:Lio/reactivex/rxjava3/disposables/Disposable;
      16: aload_0
      17: getfield      #2                  // Field downstream:Lio/reactivex/rxjava3/core/SingleObserver;
      20: aload_0
      21: invokeinterface #6,  2            // InterfaceMethod io/reactivex/rxjava3/core/SingleObserver.onSubscribe:(Lio/reactivex/rxjava3/disposables/Disposable;)V
      26: return

  public void onNext(T);
    Code:
       0: aload_0
       1: getfield      #7                  // Field done:Z
       4: ifeq          8
       7: return
       8: aload_0
       9: getfield      #3                  // Field predicate:Lio/reactivex/rxjava3/functions/Predicate;
      12: aload_1
      13: invokeinterface #8,  2            // InterfaceMethod io/reactivex/rxjava3/functions/Predicate.test:(Ljava/lang/Object;)Z
      18: istore_2
      19: goto          42
      22: astore_3
      23: aload_3
      24: invokestatic  #10                 // Method io/reactivex/rxjava3/exceptions/Exceptions.throwIfFatal:(Ljava/lang/Throwable;)V
      27: aload_0
      28: getfield      #4                  // Field upstream:Lio/reactivex/rxjava3/disposables/Disposable;
      31: invokeinterface #11,  1           // InterfaceMethod io/reactivex/rxjava3/disposables/Disposable.dispose:()V
      36: aload_0
      37: aload_3
      38: invokevirtual #12                 // Method onError:(Ljava/lang/Throwable;)V
      41: return
      42: iload_2
      43: ifne          73
      46: aload_0
      47: iconst_1
      48: putfield      #7                  // Field done:Z
      51: aload_0
      52: getfield      #4                  // Field upstream:Lio/reactivex/rxjava3/disposables/Disposable;
      55: invokeinterface #11,  1           // InterfaceMethod io/reactivex/rxjava3/disposables/Disposable.dispose:()V
      60: aload_0
      61: getfield      #2                  // Field downstream:Lio/reactivex/rxjava3/core/SingleObserver;
      64: iconst_0
      65: invokestatic  #13                 // Method java/lang/Boolean.valueOf:(Z)Ljava/lang/Boolean;
      68: invokeinterface #14,  2           // InterfaceMethod io/reactivex/rxjava3/core/SingleObserver.onSuccess:(Ljava/lang/Object;)V
      73: return
    Exception table:
       from    to  target type
           8    19    22   Class java/lang/Throwable

  public void onError(java.lang.Throwable);
    Code:
       0: aload_0
       1: getfield      #7                  // Field done:Z
       4: ifeq          12
       7: aload_1
       8: invokestatic  #15                 // Method io/reactivex/rxjava3/plugins/RxJavaPlugins.onError:(Ljava/lang/Throwable;)V
      11: return
      12: aload_0
      13: iconst_1
      14: putfield      #7                  // Field done:Z
      17: aload_0
      18: getfield      #2                  // Field downstream:Lio/reactivex/rxjava3/core/SingleObserver;
      21: aload_1
      22: invokeinterface #16,  2           // InterfaceMethod io/reactivex/rxjava3/core/SingleObserver.onError:(Ljava/lang/Throwable;)V
      27: return

  public void onComplete();
    Code:
       0: aload_0
       1: getfield      #7                  // Field done:Z
       4: ifeq          8
       7: return
       8: aload_0
       9: iconst_1
      10: putfield      #7                  // Field done:Z
      13: aload_0
      14: getfield      #2                  // Field downstream:Lio/reactivex/rxjava3/core/SingleObserver;
      17: iconst_1
      18: invokestatic  #13                 // Method java/lang/Boolean.valueOf:(Z)Ljava/lang/Boolean;
      21: invokeinterface #14,  2           // InterfaceMethod io/reactivex/rxjava3/core/SingleObserver.onSuccess:(Ljava/lang/Object;)V
      26: return

  public void dispose();
    Code:
       0: aload_0
       1: getfield      #4                  // Field upstream:Lio/reactivex/rxjava3/disposables/Disposable;
       4: invokeinterface #11,  1           // InterfaceMethod io/reactivex/rxjava3/disposables/Disposable.dispose:()V
       9: return

  public boolean isDisposed();
    Code:
       0: aload_0
       1: getfield      #4                  // Field upstream:Lio/reactivex/rxjava3/disposables/Disposable;
       4: invokeinterface #17,  1           // InterfaceMethod io/reactivex/rxjava3/disposables/Disposable.isDisposed:()Z
       9: ireturn
}
