Compiled from "ObservableJust.java"
public final class io.reactivex.rxjava3.internal.operators.observable.ObservableJust<T> extends io.reactivex.rxjava3.core.Observable<T> implements io.reactivex.rxjava3.operators.ScalarSupplier<T> {
  private final T value;

  public io.reactivex.rxjava3.internal.operators.observable.ObservableJust(T);
    Code:
       0: aload_0
       1: invokespecial #1                  // Method io/reactivex/rxjava3/core/Observable."<init>":()V
       4: aload_0
       5: aload_1
       6: putfield      #2                  // Field value:Ljava/lang/Object;
       9: return

  protected void subscribeActual(io.reactivex.rxjava3.core.Observer<? super T>);
    Code:
       0: new           #3                  // class io/reactivex/rxjava3/internal/operators/observable/ObservableScalarXMap$ScalarDisposable
       3: dup
       4: aload_1
       5: aload_0
       6: getfield      #2                  // Field value:Ljava/lang/Object;
       9: invokespecial #4                  // Method io/reactivex/rxjava3/internal/operators/observable/ObservableScalarXMap$ScalarDisposable."<init>":(Lio/reactivex/rxjava3/core/Observer;Ljava/lang/Object;)V
      12: astore_2
      13: aload_1
      14: aload_2
      15: invokeinterface #5,  2            // InterfaceMethod io/reactivex/rxjava3/core/Observer.onSubscribe:(Lio/reactivex/rxjava3/disposables/Disposable;)V
      20: aload_2
      21: invokevirtual #6                  // Method io/reactivex/rxjava3/internal/operators/observable/ObservableScalarXMap$ScalarDisposable.run:()V
      24: return

  public T get();
    Code:
       0: aload_0
       1: getfield      #2                  // Field value:Ljava/lang/Object;
       4: areturn
}
