Compiled from "ObservableDistinct.java"
public final class io.reactivex.rxjava3.internal.operators.observable.ObservableDistinct<T, K> extends io.reactivex.rxjava3.internal.operators.observable.AbstractObservableWithUpstream<T, T> {
  final io.reactivex.rxjava3.functions.Function<? super T, K> keySelector;

  final io.reactivex.rxjava3.functions.Supplier<? extends java.util.Collection<? super K>> collectionSupplier;

  public io.reactivex.rxjava3.internal.operators.observable.ObservableDistinct(io.reactivex.rxjava3.core.ObservableSource<T>, io.reactivex.rxjava3.functions.Function<? super T, K>, io.reactivex.rxjava3.functions.Supplier<? extends java.util.Collection<? super K>>);
    Code:
       0: aload_0
       1: aload_1
       2: invokespecial #1                  // Method io/reactivex/rxjava3/internal/operators/observable/AbstractObservableWithUpstream."<init>":(Lio/reactivex/rxjava3/core/ObservableSource;)V
       5: aload_0
       6: aload_2
       7: putfield      #2                  // Field keySelector:Lio/reactivex/rxjava3/functions/Function;
      10: aload_0
      11: aload_3
      12: putfield      #3                  // Field collectionSupplier:Lio/reactivex/rxjava3/functions/Supplier;
      15: return

  protected void subscribeActual(io.reactivex.rxjava3.core.Observer<? super T>);
    Code:
       0: aload_0
       1: getfield      #3                  // Field collectionSupplier:Lio/reactivex/rxjava3/functions/Supplier;
       4: invokeinterface #4,  1            // InterfaceMethod io/reactivex/rxjava3/functions/Supplier.get:()Ljava/lang/Object;
       9: ldc           #5                  // String The collectionSupplier returned a null Collection.
      11: invokestatic  #6                  // Method io/reactivex/rxjava3/internal/util/ExceptionHelper.nullCheck:(Ljava/lang/Object;Ljava/lang/String;)Ljava/lang/Object;
      14: checkcast     #7                  // class java/util/Collection
      17: astore_2
      18: goto          32
      21: astore_3
      22: aload_3
      23: invokestatic  #9                  // Method io/reactivex/rxjava3/exceptions/Exceptions.throwIfFatal:(Ljava/lang/Throwable;)V
      26: aload_3
      27: aload_1
      28: invokestatic  #10                 // Method io/reactivex/rxjava3/internal/disposables/EmptyDisposable.error:(Ljava/lang/Throwable;Lio/reactivex/rxjava3/core/Observer;)V
      31: return
      32: aload_0
      33: getfield      #11                 // Field source:Lio/reactivex/rxjava3/core/ObservableSource;
      36: new           #12                 // class io/reactivex/rxjava3/internal/operators/observable/ObservableDistinct$DistinctObserver
      39: dup
      40: aload_1
      41: aload_0
      42: getfield      #2                  // Field keySelector:Lio/reactivex/rxjava3/functions/Function;
      45: aload_2
      46: invokespecial #13                 // Method io/reactivex/rxjava3/internal/operators/observable/ObservableDistinct$DistinctObserver."<init>":(Lio/reactivex/rxjava3/core/Observer;Lio/reactivex/rxjava3/functions/Function;Ljava/util/Collection;)V
      49: invokeinterface #14,  2           // InterfaceMethod io/reactivex/rxjava3/core/ObservableSource.subscribe:(Lio/reactivex/rxjava3/core/Observer;)V
      54: return
    Exception table:
       from    to  target type
           0    18    21   Class java/lang/Throwable
}
