Compiled from "ObservableBufferTimed.java"
final class io.reactivex.rxjava3.internal.operators.observable.ObservableBufferTimed$BufferSkipBoundedObserver$RemoveFromBufferEmit implements java.lang.Runnable {
  private final U buffer;

  final io.reactivex.rxjava3.internal.operators.observable.ObservableBufferTimed$BufferSkipBoundedObserver this$0;

  io.reactivex.rxjava3.internal.operators.observable.ObservableBufferTimed$BufferSkipBoundedObserver$RemoveFromBufferEmit(U);
    Code:
       0: aload_0
       1: aload_1
       2: putfield      #1                  // Field this$0:Lio/reactivex/rxjava3/internal/operators/observable/ObservableBufferTimed$BufferSkipBoundedObserver;
       5: aload_0
       6: invokespecial #2                  // Method java/lang/Object."<init>":()V
       9: aload_0
      10: aload_2
      11: putfield      #3                  // Field buffer:Ljava/util/Collection;
      14: return

  public void run();
    Code:
       0: aload_0
       1: getfield      #1                  // Field this$0:Lio/reactivex/rxjava3/internal/operators/observable/ObservableBufferTimed$BufferSkipBoundedObserver;
       4: dup
       5: astore_1
       6: monitorenter
       7: aload_0
       8: getfield      #1                  // Field this$0:Lio/reactivex/rxjava3/internal/operators/observable/ObservableBufferTimed$BufferSkipBoundedObserver;
      11: getfield      #4                  // Field io/reactivex/rxjava3/internal/operators/observable/ObservableBufferTimed$BufferSkipBoundedObserver.buffers:Ljava/util/List;
      14: aload_0
      15: getfield      #3                  // Field buffer:Ljava/util/Collection;
      18: invokeinterface #5,  2            // InterfaceMethod java/util/List.remove:(Ljava/lang/Object;)Z
      23: pop
      24: aload_1
      25: monitorexit
      26: goto          34
      29: astore_2
      30: aload_1
      31: monitorexit
      32: aload_2
      33: athrow
      34: aload_0
      35: getfield      #1                  // Field this$0:Lio/reactivex/rxjava3/internal/operators/observable/ObservableBufferTimed$BufferSkipBoundedObserver;
      38: aload_0
      39: getfield      #3                  // Field buffer:Ljava/util/Collection;
      42: iconst_0
      43: aload_0
      44: getfield      #1                  // Field this$0:Lio/reactivex/rxjava3/internal/operators/observable/ObservableBufferTimed$BufferSkipBoundedObserver;
      47: getfield      #6                  // Field io/reactivex/rxjava3/internal/operators/observable/ObservableBufferTimed$BufferSkipBoundedObserver.w:Lio/reactivex/rxjava3/core/Scheduler$Worker;
      50: invokestatic  #7                  // Method io/reactivex/rxjava3/internal/operators/observable/ObservableBufferTimed$BufferSkipBoundedObserver.access$100:(Lio/reactivex/rxjava3/internal/operators/observable/ObservableBufferTimed$BufferSkipBoundedObserver;Ljava/lang/Object;ZLio/reactivex/rxjava3/disposables/Disposable;)V
      53: return
    Exception table:
       from    to  target type
           7    26    29   any
          29    32    29   any
}
