Compiled from "ObservableRangeLong.java"
public final class io.reactivex.rxjava3.internal.operators.observable.ObservableRangeLong extends io.reactivex.rxjava3.core.Observable<java.lang.Long> {
  private final long start;

  private final long count;

  public io.reactivex.rxjava3.internal.operators.observable.ObservableRangeLong(long, long);
    Code:
       0: aload_0
       1: invokespecial #1                  // Method io/reactivex/rxjava3/core/Observable."<init>":()V
       4: aload_0
       5: lload_1
       6: putfield      #2                  // Field start:J
       9: aload_0
      10: lload_3
      11: putfield      #3                  // Field count:J
      14: return

  protected void subscribeActual(io.reactivex.rxjava3.core.Observer<? super java.lang.Long>);
    Code:
       0: new           #4                  // class io/reactivex/rxjava3/internal/operators/observable/ObservableRangeLong$RangeDisposable
       3: dup
       4: aload_1
       5: aload_0
       6: getfield      #2                  // Field start:J
       9: aload_0
      10: getfield      #2                  // Field start:J
      13: aload_0
      14: getfield      #3                  // Field count:J
      17: ladd
      18: invokespecial #5                  // Method io/reactivex/rxjava3/internal/operators/observable/ObservableRangeLong$RangeDisposable."<init>":(Lio/reactivex/rxjava3/core/Observer;JJ)V
      21: astore_2
      22: aload_1
      23: aload_2
      24: invokeinterface #6,  2            // InterfaceMethod io/reactivex/rxjava3/core/Observer.onSubscribe:(Lio/reactivex/rxjava3/disposables/Disposable;)V
      29: aload_2
      30: invokevirtual #7                  // Method io/reactivex/rxjava3/internal/operators/observable/ObservableRangeLong$RangeDisposable.run:()V
      33: return
}
