Compiled from "ObservableSampleTimed.java"
final class io.reactivex.rxjava3.internal.operators.observable.ObservableSampleTimed$SampleTimedEmitLast<T> extends io.reactivex.rxjava3.internal.operators.observable.ObservableSampleTimed$SampleTimedObserver<T> {
  private static final long serialVersionUID;

  final java.util.concurrent.atomic.AtomicInteger wip;

  io.reactivex.rxjava3.internal.operators.observable.ObservableSampleTimed$SampleTimedEmitLast(io.reactivex.rxjava3.core.Observer<? super T>, long, java.util.concurrent.TimeUnit, io.reactivex.rxjava3.core.Scheduler, io.reactivex.rxjava3.functions.Consumer<? super T>);
    Code:
       0: aload_0
       1: aload_1
       2: lload_2
       3: aload         4
       5: aload         5
       7: aload         6
       9: invokespecial #1                  // Method io/reactivex/rxjava3/internal/operators/observable/ObservableSampleTimed$SampleTimedObserver."<init>":(Lio/reactivex/rxjava3/core/Observer;JLjava/util/concurrent/TimeUnit;Lio/reactivex/rxjava3/core/Scheduler;Lio/reactivex/rxjava3/functions/Consumer;)V
      12: aload_0
      13: new           #2                  // class java/util/concurrent/atomic/AtomicInteger
      16: dup
      17: iconst_1
      18: invokespecial #3                  // Method java/util/concurrent/atomic/AtomicInteger."<init>":(I)V
      21: putfield      #4                  // Field wip:Ljava/util/concurrent/atomic/AtomicInteger;
      24: return

  void complete();
    Code:
       0: aload_0
       1: invokevirtual #5                  // Method emit:()V
       4: aload_0
       5: getfield      #4                  // Field wip:Ljava/util/concurrent/atomic/AtomicInteger;
       8: invokevirtual #6                  // Method java/util/concurrent/atomic/AtomicInteger.decrementAndGet:()I
      11: ifne          23
      14: aload_0
      15: getfield      #7                  // Field downstream:Lio/reactivex/rxjava3/core/Observer;
      18: invokeinterface #8,  1            // InterfaceMethod io/reactivex/rxjava3/core/Observer.onComplete:()V
      23: return

  public void run();
    Code:
       0: aload_0
       1: getfield      #4                  // Field wip:Ljava/util/concurrent/atomic/AtomicInteger;
       4: invokevirtual #9                  // Method java/util/concurrent/atomic/AtomicInteger.incrementAndGet:()I
       7: iconst_2
       8: if_icmpne     34
      11: aload_0
      12: invokevirtual #5                  // Method emit:()V
      15: aload_0
      16: getfield      #4                  // Field wip:Ljava/util/concurrent/atomic/AtomicInteger;
      19: invokevirtual #6                  // Method java/util/concurrent/atomic/AtomicInteger.decrementAndGet:()I
      22: ifne          34
      25: aload_0
      26: getfield      #7                  // Field downstream:Lio/reactivex/rxjava3/core/Observer;
      29: invokeinterface #8,  1            // InterfaceMethod io/reactivex/rxjava3/core/Observer.onComplete:()V
      34: return
}
