Compiled from "ObservableTimer.java"
public final class io.reactivex.rxjava3.internal.operators.observable.ObservableTimer extends io.reactivex.rxjava3.core.Observable<java.lang.Long> {
  final io.reactivex.rxjava3.core.Scheduler scheduler;

  final long delay;

  final java.util.concurrent.TimeUnit unit;

  public io.reactivex.rxjava3.internal.operators.observable.ObservableTimer(long, java.util.concurrent.TimeUnit, io.reactivex.rxjava3.core.Scheduler);
    Code:
       0: aload_0
       1: invokespecial #1                  // Method io/reactivex/rxjava3/core/Observable."<init>":()V
       4: aload_0
       5: lload_1
       6: putfield      #2                  // Field delay:J
       9: aload_0
      10: aload_3
      11: putfield      #3                  // Field unit:Ljava/util/concurrent/TimeUnit;
      14: aload_0
      15: aload         4
      17: putfield      #4                  // Field scheduler:Lio/reactivex/rxjava3/core/Scheduler;
      20: return

  public void subscribeActual(io.reactivex.rxjava3.core.Observer<? super java.lang.Long>);
    Code:
       0: new           #5                  // class io/reactivex/rxjava3/internal/operators/observable/ObservableTimer$TimerObserver
       3: dup
       4: aload_1
       5: invokespecial #6                  // Method io/reactivex/rxjava3/internal/operators/observable/ObservableTimer$TimerObserver."<init>":(Lio/reactivex/rxjava3/core/Observer;)V
       8: astore_2
       9: aload_1
      10: aload_2
      11: invokeinterface #7,  2            // InterfaceMethod io/reactivex/rxjava3/core/Observer.onSubscribe:(Lio/reactivex/rxjava3/disposables/Disposable;)V
      16: aload_0
      17: getfield      #4                  // Field scheduler:Lio/reactivex/rxjava3/core/Scheduler;
      20: aload_2
      21: aload_0
      22: getfield      #2                  // Field delay:J
      25: aload_0
      26: getfield      #3                  // Field unit:Ljava/util/concurrent/TimeUnit;
      29: invokevirtual #8                  // Method io/reactivex/rxjava3/core/Scheduler.scheduleDirect:(Ljava/lang/Runnable;JLjava/util/concurrent/TimeUnit;)Lio/reactivex/rxjava3/disposables/Disposable;
      32: astore_3
      33: aload_2
      34: aload_3
      35: invokevirtual #9                  // Method io/reactivex/rxjava3/internal/operators/observable/ObservableTimer$TimerObserver.setResource:(Lio/reactivex/rxjava3/disposables/Disposable;)V
      38: return
}
