Compiled from "ObservableIntervalRange.java"
public final class io.reactivex.rxjava3.internal.operators.observable.ObservableIntervalRange extends io.reactivex.rxjava3.core.Observable<java.lang.Long> {
  final io.reactivex.rxjava3.core.Scheduler scheduler;

  final long start;

  final long end;

  final long initialDelay;

  final long period;

  final java.util.concurrent.TimeUnit unit;

  public io.reactivex.rxjava3.internal.operators.observable.ObservableIntervalRange(long, long, long, long, java.util.concurrent.TimeUnit, io.reactivex.rxjava3.core.Scheduler);
    Code:
       0: aload_0
       1: invokespecial #1                  // Method io/reactivex/rxjava3/core/Observable."<init>":()V
       4: aload_0
       5: lload         5
       7: putfield      #2                  // Field initialDelay:J
      10: aload_0
      11: lload         7
      13: putfield      #3                  // Field period:J
      16: aload_0
      17: aload         9
      19: putfield      #4                  // Field unit:Ljava/util/concurrent/TimeUnit;
      22: aload_0
      23: aload         10
      25: putfield      #5                  // Field scheduler:Lio/reactivex/rxjava3/core/Scheduler;
      28: aload_0
      29: lload_1
      30: putfield      #6                  // Field start:J
      33: aload_0
      34: lload_3
      35: putfield      #7                  // Field end:J
      38: return

  public void subscribeActual(io.reactivex.rxjava3.core.Observer<? super java.lang.Long>);
    Code:
       0: new           #8                  // class io/reactivex/rxjava3/internal/operators/observable/ObservableIntervalRange$IntervalRangeObserver
       3: dup
       4: aload_1
       5: aload_0
       6: getfield      #6                  // Field start:J
       9: aload_0
      10: getfield      #7                  // Field end:J
      13: invokespecial #9                  // Method io/reactivex/rxjava3/internal/operators/observable/ObservableIntervalRange$IntervalRangeObserver."<init>":(Lio/reactivex/rxjava3/core/Observer;JJ)V
      16: astore_2
      17: aload_1
      18: aload_2
      19: invokeinterface #10,  2           // InterfaceMethod io/reactivex/rxjava3/core/Observer.onSubscribe:(Lio/reactivex/rxjava3/disposables/Disposable;)V
      24: aload_0
      25: getfield      #5                  // Field scheduler:Lio/reactivex/rxjava3/core/Scheduler;
      28: astore_3
      29: aload_3
      30: instanceof    #11                 // class io/reactivex/rxjava3/internal/schedulers/TrampolineScheduler
      33: ifeq          70
      36: aload_3
      37: invokevirtual #12                 // Method io/reactivex/rxjava3/core/Scheduler.createWorker:()Lio/reactivex/rxjava3/core/Scheduler$Worker;
      40: astore        4
      42: aload_2
      43: aload         4
      45: invokevirtual #13                 // Method io/reactivex/rxjava3/internal/operators/observable/ObservableIntervalRange$IntervalRangeObserver.setResource:(Lio/reactivex/rxjava3/disposables/Disposable;)V
      48: aload         4
      50: aload_2
      51: aload_0
      52: getfield      #2                  // Field initialDelay:J
      55: aload_0
      56: getfield      #3                  // Field period:J
      59: aload_0
      60: getfield      #4                  // Field unit:Ljava/util/concurrent/TimeUnit;
      63: invokevirtual #14                 // Method io/reactivex/rxjava3/core/Scheduler$Worker.schedulePeriodically:(Ljava/lang/Runnable;JJLjava/util/concurrent/TimeUnit;)Lio/reactivex/rxjava3/disposables/Disposable;
      66: pop
      67: goto          95
      70: aload_3
      71: aload_2
      72: aload_0
      73: getfield      #2                  // Field initialDelay:J
      76: aload_0
      77: getfield      #3                  // Field period:J
      80: aload_0
      81: getfield      #4                  // Field unit:Ljava/util/concurrent/TimeUnit;
      84: invokevirtual #15                 // Method io/reactivex/rxjava3/core/Scheduler.schedulePeriodicallyDirect:(Ljava/lang/Runnable;JJLjava/util/concurrent/TimeUnit;)Lio/reactivex/rxjava3/disposables/Disposable;
      87: astore        4
      89: aload_2
      90: aload         4
      92: invokevirtual #13                 // Method io/reactivex/rxjava3/internal/operators/observable/ObservableIntervalRange$IntervalRangeObserver.setResource:(Lio/reactivex/rxjava3/disposables/Disposable;)V
      95: return
}
