Compiled from "ObservableTimeInterval.java"
public final class io.reactivex.rxjava3.internal.operators.observable.ObservableTimeInterval<T> extends io.reactivex.rxjava3.internal.operators.observable.AbstractObservableWithUpstream<T, io.reactivex.rxjava3.schedulers.Timed<T>> {
  final io.reactivex.rxjava3.core.Scheduler scheduler;

  final java.util.concurrent.TimeUnit unit;

  public io.reactivex.rxjava3.internal.operators.observable.ObservableTimeInterval(io.reactivex.rxjava3.core.ObservableSource<T>, java.util.concurrent.TimeUnit, io.reactivex.rxjava3.core.Scheduler);
    Code:
       0: aload_0
       1: aload_1
       2: invokespecial #1                  // Method io/reactivex/rxjava3/internal/operators/observable/AbstractObservableWithUpstream."<init>":(Lio/reactivex/rxjava3/core/ObservableSource;)V
       5: aload_0
       6: aload_3
       7: putfield      #2                  // Field scheduler:Lio/reactivex/rxjava3/core/Scheduler;
      10: aload_0
      11: aload_2
      12: putfield      #3                  // Field unit:Ljava/util/concurrent/TimeUnit;
      15: return

  public void subscribeActual(io.reactivex.rxjava3.core.Observer<? super io.reactivex.rxjava3.schedulers.Timed<T>>);
    Code:
       0: aload_0
       1: getfield      #4                  // Field source:Lio/reactivex/rxjava3/core/ObservableSource;
       4: new           #5                  // class io/reactivex/rxjava3/internal/operators/observable/ObservableTimeInterval$TimeIntervalObserver
       7: dup
       8: aload_1
       9: aload_0
      10: getfield      #3                  // Field unit:Ljava/util/concurrent/TimeUnit;
      13: aload_0
      14: getfield      #2                  // Field scheduler:Lio/reactivex/rxjava3/core/Scheduler;
      17: invokespecial #6                  // Method io/reactivex/rxjava3/internal/operators/observable/ObservableTimeInterval$TimeIntervalObserver."<init>":(Lio/reactivex/rxjava3/core/Observer;Ljava/util/concurrent/TimeUnit;Lio/reactivex/rxjava3/core/Scheduler;)V
      20: invokeinterface #7,  2            // InterfaceMethod io/reactivex/rxjava3/core/ObservableSource.subscribe:(Lio/reactivex/rxjava3/core/Observer;)V
      25: return
}
