Compiled from "ObservableRefCount.java"
final class io.reactivex.rxjava3.internal.operators.observable.ObservableRefCount$RefCountObserver<T> extends java.util.concurrent.atomic.AtomicBoolean implements io.reactivex.rxjava3.core.Observer<T>, io.reactivex.rxjava3.disposables.Disposable {
  private static final long serialVersionUID;

  final io.reactivex.rxjava3.core.Observer<? super T> downstream;

  final io.reactivex.rxjava3.internal.operators.observable.ObservableRefCount<T> parent;

  final io.reactivex.rxjava3.internal.operators.observable.ObservableRefCount$RefConnection connection;

  io.reactivex.rxjava3.disposables.Disposable upstream;

  io.reactivex.rxjava3.internal.operators.observable.ObservableRefCount$RefCountObserver(io.reactivex.rxjava3.core.Observer<? super T>, io.reactivex.rxjava3.internal.operators.observable.ObservableRefCount<T>, io.reactivex.rxjava3.internal.operators.observable.ObservableRefCount$RefConnection);
    Code:
       0: aload_0
       1: invokespecial #1                  // Method java/util/concurrent/atomic/AtomicBoolean."<init>":()V
       4: aload_0
       5: aload_1
       6: putfield      #2                  // Field downstream:Lio/reactivex/rxjava3/core/Observer;
       9: aload_0
      10: aload_2
      11: putfield      #3                  // Field parent:Lio/reactivex/rxjava3/internal/operators/observable/ObservableRefCount;
      14: aload_0
      15: aload_3
      16: putfield      #4                  // Field connection:Lio/reactivex/rxjava3/internal/operators/observable/ObservableRefCount$RefConnection;
      19: return

  public void onNext(T);
    Code:
       0: aload_0
       1: getfield      #2                  // Field downstream:Lio/reactivex/rxjava3/core/Observer;
       4: aload_1
       5: invokeinterface #5,  2            // InterfaceMethod io/reactivex/rxjava3/core/Observer.onNext:(Ljava/lang/Object;)V
      10: return

  public void onError(java.lang.Throwable);
    Code:
       0: aload_0
       1: iconst_0
       2: iconst_1
       3: invokevirtual #6                  // Method compareAndSet:(ZZ)Z
       6: ifeq          33
       9: aload_0
      10: getfield      #3                  // Field parent:Lio/reactivex/rxjava3/internal/operators/observable/ObservableRefCount;
      13: aload_0
      14: getfield      #4                  // Field connection:Lio/reactivex/rxjava3/internal/operators/observable/ObservableRefCount$RefConnection;
      17: invokevirtual #7                  // Method io/reactivex/rxjava3/internal/operators/observable/ObservableRefCount.terminated:(Lio/reactivex/rxjava3/internal/operators/observable/ObservableRefCount$RefConnection;)V
      20: aload_0
      21: getfield      #2                  // Field downstream:Lio/reactivex/rxjava3/core/Observer;
      24: aload_1
      25: invokeinterface #8,  2            // InterfaceMethod io/reactivex/rxjava3/core/Observer.onError:(Ljava/lang/Throwable;)V
      30: goto          37
      33: aload_1
      34: invokestatic  #9                  // Method io/reactivex/rxjava3/plugins/RxJavaPlugins.onError:(Ljava/lang/Throwable;)V
      37: return

  public void onComplete();
    Code:
       0: aload_0
       1: iconst_0
       2: iconst_1
       3: invokevirtual #6                  // Method compareAndSet:(ZZ)Z
       6: ifeq          29
       9: aload_0
      10: getfield      #3                  // Field parent:Lio/reactivex/rxjava3/internal/operators/observable/ObservableRefCount;
      13: aload_0
      14: getfield      #4                  // Field connection:Lio/reactivex/rxjava3/internal/operators/observable/ObservableRefCount$RefConnection;
      17: invokevirtual #7                  // Method io/reactivex/rxjava3/internal/operators/observable/ObservableRefCount.terminated:(Lio/reactivex/rxjava3/internal/operators/observable/ObservableRefCount$RefConnection;)V
      20: aload_0
      21: getfield      #2                  // Field downstream:Lio/reactivex/rxjava3/core/Observer;
      24: invokeinterface #10,  1           // InterfaceMethod io/reactivex/rxjava3/core/Observer.onComplete:()V
      29: return

  public void dispose();
    Code:
       0: aload_0
       1: getfield      #11                 // Field upstream:Lio/reactivex/rxjava3/disposables/Disposable;
       4: invokeinterface #12,  1           // InterfaceMethod io/reactivex/rxjava3/disposables/Disposable.dispose:()V
       9: aload_0
      10: iconst_0
      11: iconst_1
      12: invokevirtual #6                  // Method compareAndSet:(ZZ)Z
      15: ifeq          29
      18: aload_0
      19: getfield      #3                  // Field parent:Lio/reactivex/rxjava3/internal/operators/observable/ObservableRefCount;
      22: aload_0
      23: getfield      #4                  // Field connection:Lio/reactivex/rxjava3/internal/operators/observable/ObservableRefCount$RefConnection;
      26: invokevirtual #13                 // Method io/reactivex/rxjava3/internal/operators/observable/ObservableRefCount.cancel:(Lio/reactivex/rxjava3/internal/operators/observable/ObservableRefCount$RefConnection;)V
      29: return

  public boolean isDisposed();
    Code:
       0: aload_0
       1: getfield      #11                 // Field upstream:Lio/reactivex/rxjava3/disposables/Disposable;
       4: invokeinterface #14,  1           // InterfaceMethod io/reactivex/rxjava3/disposables/Disposable.isDisposed:()Z
       9: ireturn

  public void onSubscribe(io.reactivex.rxjava3.disposables.Disposable);
    Code:
       0: aload_0
       1: getfield      #11                 // Field upstream:Lio/reactivex/rxjava3/disposables/Disposable;
       4: aload_1
       5: invokestatic  #15                 // Method io/reactivex/rxjava3/internal/disposables/DisposableHelper.validate:(Lio/reactivex/rxjava3/disposables/Disposable;Lio/reactivex/rxjava3/disposables/Disposable;)Z
       8: ifeq          26
      11: aload_0
      12: aload_1
      13: putfield      #11                 // Field upstream:Lio/reactivex/rxjava3/disposables/Disposable;
      16: aload_0
      17: getfield      #2                  // Field downstream:Lio/reactivex/rxjava3/core/Observer;
      20: aload_0
      21: invokeinterface #16,  2           // InterfaceMethod io/reactivex/rxjava3/core/Observer.onSubscribe:(Lio/reactivex/rxjava3/disposables/Disposable;)V
      26: return
}
