Compiled from "ObservableWindowBoundarySelector.java"
final class io.reactivex.rxjava3.internal.operators.observable.ObservableWindowBoundarySelector$WindowBoundaryMainObserver<T, B, V> extends java.util.concurrent.atomic.AtomicInteger implements io.reactivex.rxjava3.core.Observer<T>, io.reactivex.rxjava3.disposables.Disposable, java.lang.Runnable {
  private static final long serialVersionUID;

  final io.reactivex.rxjava3.core.Observer<? super io.reactivex.rxjava3.core.Observable<T>> downstream;

  final io.reactivex.rxjava3.core.ObservableSource<B> open;

  final io.reactivex.rxjava3.functions.Function<? super B, ? extends io.reactivex.rxjava3.core.ObservableSource<V>> closingIndicator;

  final int bufferSize;

  final io.reactivex.rxjava3.disposables.CompositeDisposable resources;

  final io.reactivex.rxjava3.internal.operators.observable.ObservableWindowBoundarySelector$WindowBoundaryMainObserver$WindowStartObserver<B> startObserver;

  final java.util.List<io.reactivex.rxjava3.subjects.UnicastSubject<T>> windows;

  final io.reactivex.rxjava3.operators.SimplePlainQueue<java.lang.Object> queue;

  final java.util.concurrent.atomic.AtomicLong windowCount;

  final java.util.concurrent.atomic.AtomicBoolean downstreamDisposed;

  final java.util.concurrent.atomic.AtomicLong requested;

  long emitted;

  volatile boolean upstreamCanceled;

  volatile boolean upstreamDone;

  volatile boolean openDone;

  final io.reactivex.rxjava3.internal.util.AtomicThrowable error;

  io.reactivex.rxjava3.disposables.Disposable upstream;

  io.reactivex.rxjava3.internal.operators.observable.ObservableWindowBoundarySelector$WindowBoundaryMainObserver(io.reactivex.rxjava3.core.Observer<? super io.reactivex.rxjava3.core.Observable<T>>, io.reactivex.rxjava3.core.ObservableSource<B>, io.reactivex.rxjava3.functions.Function<? super B, ? extends io.reactivex.rxjava3.core.ObservableSource<V>>, int);
    Code:
       0: aload_0
       1: invokespecial #1                  // Method java/util/concurrent/atomic/AtomicInteger."<init>":()V
       4: aload_0
       5: aload_1
       6: putfield      #2                  // Field downstream:Lio/reactivex/rxjava3/core/Observer;
       9: aload_0
      10: new           #3                  // class io/reactivex/rxjava3/internal/queue/MpscLinkedQueue
      13: dup
      14: invokespecial #4                  // Method io/reactivex/rxjava3/internal/queue/MpscLinkedQueue."<init>":()V
      17: putfield      #5                  // Field queue:Lio/reactivex/rxjava3/operators/SimplePlainQueue;
      20: aload_0
      21: aload_2
      22: putfield      #6                  // Field open:Lio/reactivex/rxjava3/core/ObservableSource;
      25: aload_0
      26: aload_3
      27: putfield      #7                  // Field closingIndicator:Lio/reactivex/rxjava3/functions/Function;
      30: aload_0
      31: iload         4
      33: putfield      #8                  // Field bufferSize:I
      36: aload_0
      37: new           #9                  // class io/reactivex/rxjava3/disposables/CompositeDisposable
      40: dup
      41: invokespecial #10                 // Method io/reactivex/rxjava3/disposables/CompositeDisposable."<init>":()V
      44: putfield      #11                 // Field resources:Lio/reactivex/rxjava3/disposables/CompositeDisposable;
      47: aload_0
      48: new           #12                 // class java/util/ArrayList
      51: dup
      52: invokespecial #13                 // Method java/util/ArrayList."<init>":()V
      55: putfield      #14                 // Field windows:Ljava/util/List;
      58: aload_0
      59: new           #15                 // class java/util/concurrent/atomic/AtomicLong
      62: dup
      63: lconst_1
      64: invokespecial #16                 // Method java/util/concurrent/atomic/AtomicLong."<init>":(J)V
      67: putfield      #17                 // Field windowCount:Ljava/util/concurrent/atomic/AtomicLong;
      70: aload_0
      71: new           #18                 // class java/util/concurrent/atomic/AtomicBoolean
      74: dup
      75: invokespecial #19                 // Method java/util/concurrent/atomic/AtomicBoolean."<init>":()V
      78: putfield      #20                 // Field downstreamDisposed:Ljava/util/concurrent/atomic/AtomicBoolean;
      81: aload_0
      82: new           #21                 // class io/reactivex/rxjava3/internal/util/AtomicThrowable
      85: dup
      86: invokespecial #22                 // Method io/reactivex/rxjava3/internal/util/AtomicThrowable."<init>":()V
      89: putfield      #23                 // Field error:Lio/reactivex/rxjava3/internal/util/AtomicThrowable;
      92: aload_0
      93: new           #24                 // class io/reactivex/rxjava3/internal/operators/observable/ObservableWindowBoundarySelector$WindowBoundaryMainObserver$WindowStartObserver
      96: dup
      97: aload_0
      98: invokespecial #25                 // Method io/reactivex/rxjava3/internal/operators/observable/ObservableWindowBoundarySelector$WindowBoundaryMainObserver$WindowStartObserver."<init>":(Lio/reactivex/rxjava3/internal/operators/observable/ObservableWindowBoundarySelector$WindowBoundaryMainObserver;)V
     101: putfield      #26                 // Field startObserver:Lio/reactivex/rxjava3/internal/operators/observable/ObservableWindowBoundarySelector$WindowBoundaryMainObserver$WindowStartObserver;
     104: aload_0
     105: new           #15                 // class java/util/concurrent/atomic/AtomicLong
     108: dup
     109: invokespecial #27                 // Method java/util/concurrent/atomic/AtomicLong."<init>":()V
     112: putfield      #28                 // Field requested:Ljava/util/concurrent/atomic/AtomicLong;
     115: return

  public void onSubscribe(io.reactivex.rxjava3.disposables.Disposable);
    Code:
       0: aload_0
       1: getfield      #29                 // Field upstream:Lio/reactivex/rxjava3/disposables/Disposable;
       4: aload_1
       5: invokestatic  #30                 // Method io/reactivex/rxjava3/internal/disposables/DisposableHelper.validate:(Lio/reactivex/rxjava3/disposables/Disposable;Lio/reactivex/rxjava3/disposables/Disposable;)Z
       8: ifeq          39
      11: aload_0
      12: aload_1
      13: putfield      #29                 // Field upstream:Lio/reactivex/rxjava3/disposables/Disposable;
      16: aload_0
      17: getfield      #2                  // Field downstream:Lio/reactivex/rxjava3/core/Observer;
      20: aload_0
      21: invokeinterface #31,  2           // InterfaceMethod io/reactivex/rxjava3/core/Observer.onSubscribe:(Lio/reactivex/rxjava3/disposables/Disposable;)V
      26: aload_0
      27: getfield      #6                  // Field open:Lio/reactivex/rxjava3/core/ObservableSource;
      30: aload_0
      31: getfield      #26                 // Field startObserver:Lio/reactivex/rxjava3/internal/operators/observable/ObservableWindowBoundarySelector$WindowBoundaryMainObserver$WindowStartObserver;
      34: invokeinterface #32,  2           // InterfaceMethod io/reactivex/rxjava3/core/ObservableSource.subscribe:(Lio/reactivex/rxjava3/core/Observer;)V
      39: return

  public void onNext(T);
    Code:
       0: aload_0
       1: getfield      #5                  // Field queue:Lio/reactivex/rxjava3/operators/SimplePlainQueue;
       4: aload_1
       5: invokeinterface #33,  2           // InterfaceMethod io/reactivex/rxjava3/operators/SimplePlainQueue.offer:(Ljava/lang/Object;)Z
      10: pop
      11: aload_0
      12: invokevirtual #34                 // Method drain:()V
      15: return

  public void onError(java.lang.Throwable);
    Code:
       0: aload_0
       1: getfield      #26                 // Field startObserver:Lio/reactivex/rxjava3/internal/operators/observable/ObservableWindowBoundarySelector$WindowBoundaryMainObserver$WindowStartObserver;
       4: invokevirtual #35                 // Method io/reactivex/rxjava3/internal/operators/observable/ObservableWindowBoundarySelector$WindowBoundaryMainObserver$WindowStartObserver.dispose:()V
       7: aload_0
       8: getfield      #11                 // Field resources:Lio/reactivex/rxjava3/disposables/CompositeDisposable;
      11: invokevirtual #36                 // Method io/reactivex/rxjava3/disposables/CompositeDisposable.dispose:()V
      14: aload_0
      15: getfield      #23                 // Field error:Lio/reactivex/rxjava3/internal/util/AtomicThrowable;
      18: aload_1
      19: invokevirtual #37                 // Method io/reactivex/rxjava3/internal/util/AtomicThrowable.tryAddThrowableOrReport:(Ljava/lang/Throwable;)Z
      22: ifeq          34
      25: aload_0
      26: iconst_1
      27: putfield      #38                 // Field upstreamDone:Z
      30: aload_0
      31: invokevirtual #34                 // Method drain:()V
      34: return

  public void onComplete();
    Code:
       0: aload_0
       1: getfield      #26                 // Field startObserver:Lio/reactivex/rxjava3/internal/operators/observable/ObservableWindowBoundarySelector$WindowBoundaryMainObserver$WindowStartObserver;
       4: invokevirtual #35                 // Method io/reactivex/rxjava3/internal/operators/observable/ObservableWindowBoundarySelector$WindowBoundaryMainObserver$WindowStartObserver.dispose:()V
       7: aload_0
       8: getfield      #11                 // Field resources:Lio/reactivex/rxjava3/disposables/CompositeDisposable;
      11: invokevirtual #36                 // Method io/reactivex/rxjava3/disposables/CompositeDisposable.dispose:()V
      14: aload_0
      15: iconst_1
      16: putfield      #38                 // Field upstreamDone:Z
      19: aload_0
      20: invokevirtual #34                 // Method drain:()V
      23: return

  public void dispose();
    Code:
       0: aload_0
       1: getfield      #20                 // Field downstreamDisposed:Ljava/util/concurrent/atomic/AtomicBoolean;
       4: iconst_0
       5: iconst_1
       6: invokevirtual #39                 // Method java/util/concurrent/atomic/AtomicBoolean.compareAndSet:(ZZ)Z
       9: ifeq          73
      12: aload_0
      13: getfield      #17                 // Field windowCount:Ljava/util/concurrent/atomic/AtomicLong;
      16: invokevirtual #40                 // Method java/util/concurrent/atomic/AtomicLong.decrementAndGet:()J
      19: lconst_0
      20: lcmp
      21: ifne          66
      24: aload_0
      25: getfield      #29                 // Field upstream:Lio/reactivex/rxjava3/disposables/Disposable;
      28: invokeinterface #41,  1           // InterfaceMethod io/reactivex/rxjava3/disposables/Disposable.dispose:()V
      33: aload_0
      34: getfield      #26                 // Field startObserver:Lio/reactivex/rxjava3/internal/operators/observable/ObservableWindowBoundarySelector$WindowBoundaryMainObserver$WindowStartObserver;
      37: invokevirtual #35                 // Method io/reactivex/rxjava3/internal/operators/observable/ObservableWindowBoundarySelector$WindowBoundaryMainObserver$WindowStartObserver.dispose:()V
      40: aload_0
      41: getfield      #11                 // Field resources:Lio/reactivex/rxjava3/disposables/CompositeDisposable;
      44: invokevirtual #36                 // Method io/reactivex/rxjava3/disposables/CompositeDisposable.dispose:()V
      47: aload_0
      48: getfield      #23                 // Field error:Lio/reactivex/rxjava3/internal/util/AtomicThrowable;
      51: invokevirtual #42                 // Method io/reactivex/rxjava3/internal/util/AtomicThrowable.tryTerminateAndReport:()V
      54: aload_0
      55: iconst_1
      56: putfield      #43                 // Field upstreamCanceled:Z
      59: aload_0
      60: invokevirtual #34                 // Method drain:()V
      63: goto          73
      66: aload_0
      67: getfield      #26                 // Field startObserver:Lio/reactivex/rxjava3/internal/operators/observable/ObservableWindowBoundarySelector$WindowBoundaryMainObserver$WindowStartObserver;
      70: invokevirtual #35                 // Method io/reactivex/rxjava3/internal/operators/observable/ObservableWindowBoundarySelector$WindowBoundaryMainObserver$WindowStartObserver.dispose:()V
      73: return

  public boolean isDisposed();
    Code:
       0: aload_0
       1: getfield      #20                 // Field downstreamDisposed:Ljava/util/concurrent/atomic/AtomicBoolean;
       4: invokevirtual #44                 // Method java/util/concurrent/atomic/AtomicBoolean.get:()Z
       7: ireturn

  public void run();
    Code:
       0: aload_0
       1: getfield      #17                 // Field windowCount:Ljava/util/concurrent/atomic/AtomicLong;
       4: invokevirtual #40                 // Method java/util/concurrent/atomic/AtomicLong.decrementAndGet:()J
       7: lconst_0
       8: lcmp
       9: ifne          51
      12: aload_0
      13: getfield      #29                 // Field upstream:Lio/reactivex/rxjava3/disposables/Disposable;
      16: invokeinterface #41,  1           // InterfaceMethod io/reactivex/rxjava3/disposables/Disposable.dispose:()V
      21: aload_0
      22: getfield      #26                 // Field startObserver:Lio/reactivex/rxjava3/internal/operators/observable/ObservableWindowBoundarySelector$WindowBoundaryMainObserver$WindowStartObserver;
      25: invokevirtual #35                 // Method io/reactivex/rxjava3/internal/operators/observable/ObservableWindowBoundarySelector$WindowBoundaryMainObserver$WindowStartObserver.dispose:()V
      28: aload_0
      29: getfield      #11                 // Field resources:Lio/reactivex/rxjava3/disposables/CompositeDisposable;
      32: invokevirtual #36                 // Method io/reactivex/rxjava3/disposables/CompositeDisposable.dispose:()V
      35: aload_0
      36: getfield      #23                 // Field error:Lio/reactivex/rxjava3/internal/util/AtomicThrowable;
      39: invokevirtual #42                 // Method io/reactivex/rxjava3/internal/util/AtomicThrowable.tryTerminateAndReport:()V
      42: aload_0
      43: iconst_1
      44: putfield      #43                 // Field upstreamCanceled:Z
      47: aload_0
      48: invokevirtual #34                 // Method drain:()V
      51: return

  void open(B);
    Code:
       0: aload_0
       1: getfield      #5                  // Field queue:Lio/reactivex/rxjava3/operators/SimplePlainQueue;
       4: new           #45                 // class io/reactivex/rxjava3/internal/operators/observable/ObservableWindowBoundarySelector$WindowBoundaryMainObserver$WindowStartItem
       7: dup
       8: aload_1
       9: invokespecial #46                 // Method io/reactivex/rxjava3/internal/operators/observable/ObservableWindowBoundarySelector$WindowBoundaryMainObserver$WindowStartItem."<init>":(Ljava/lang/Object;)V
      12: invokeinterface #33,  2           // InterfaceMethod io/reactivex/rxjava3/operators/SimplePlainQueue.offer:(Ljava/lang/Object;)Z
      17: pop
      18: aload_0
      19: invokevirtual #34                 // Method drain:()V
      22: return

  void openError(java.lang.Throwable);
    Code:
       0: aload_0
       1: getfield      #29                 // Field upstream:Lio/reactivex/rxjava3/disposables/Disposable;
       4: invokeinterface #41,  1           // InterfaceMethod io/reactivex/rxjava3/disposables/Disposable.dispose:()V
       9: aload_0
      10: getfield      #11                 // Field resources:Lio/reactivex/rxjava3/disposables/CompositeDisposable;
      13: invokevirtual #36                 // Method io/reactivex/rxjava3/disposables/CompositeDisposable.dispose:()V
      16: aload_0
      17: getfield      #23                 // Field error:Lio/reactivex/rxjava3/internal/util/AtomicThrowable;
      20: aload_1
      21: invokevirtual #37                 // Method io/reactivex/rxjava3/internal/util/AtomicThrowable.tryAddThrowableOrReport:(Ljava/lang/Throwable;)Z
      24: ifeq          36
      27: aload_0
      28: iconst_1
      29: putfield      #38                 // Field upstreamDone:Z
      32: aload_0
      33: invokevirtual #34                 // Method drain:()V
      36: return

  void openComplete();
    Code:
       0: aload_0
       1: iconst_1
       2: putfield      #47                 // Field openDone:Z
       5: aload_0
       6: invokevirtual #34                 // Method drain:()V
       9: return

  void close(io.reactivex.rxjava3.internal.operators.observable.ObservableWindowBoundarySelector$WindowBoundaryMainObserver$WindowEndObserverIntercept<T, V>);
    Code:
       0: aload_0
       1: getfield      #5                  // Field queue:Lio/reactivex/rxjava3/operators/SimplePlainQueue;
       4: aload_1
       5: invokeinterface #33,  2           // InterfaceMethod io/reactivex/rxjava3/operators/SimplePlainQueue.offer:(Ljava/lang/Object;)Z
      10: pop
      11: aload_0
      12: invokevirtual #34                 // Method drain:()V
      15: return

  void closeError(java.lang.Throwable);
    Code:
       0: aload_0
       1: getfield      #29                 // Field upstream:Lio/reactivex/rxjava3/disposables/Disposable;
       4: invokeinterface #41,  1           // InterfaceMethod io/reactivex/rxjava3/disposables/Disposable.dispose:()V
       9: aload_0
      10: getfield      #26                 // Field startObserver:Lio/reactivex/rxjava3/internal/operators/observable/ObservableWindowBoundarySelector$WindowBoundaryMainObserver$WindowStartObserver;
      13: invokevirtual #35                 // Method io/reactivex/rxjava3/internal/operators/observable/ObservableWindowBoundarySelector$WindowBoundaryMainObserver$WindowStartObserver.dispose:()V
      16: aload_0
      17: getfield      #11                 // Field resources:Lio/reactivex/rxjava3/disposables/CompositeDisposable;
      20: invokevirtual #36                 // Method io/reactivex/rxjava3/disposables/CompositeDisposable.dispose:()V
      23: aload_0
      24: getfield      #23                 // Field error:Lio/reactivex/rxjava3/internal/util/AtomicThrowable;
      27: aload_1
      28: invokevirtual #37                 // Method io/reactivex/rxjava3/internal/util/AtomicThrowable.tryAddThrowableOrReport:(Ljava/lang/Throwable;)Z
      31: ifeq          43
      34: aload_0
      35: iconst_1
      36: putfield      #38                 // Field upstreamDone:Z
      39: aload_0
      40: invokevirtual #34                 // Method drain:()V
      43: return

  void drain();
    Code:
       0: aload_0
       1: invokevirtual #48                 // Method getAndIncrement:()I
       4: ifeq          8
       7: return
       8: iconst_1
       9: istore_1
      10: aload_0
      11: getfield      #2                  // Field downstream:Lio/reactivex/rxjava3/core/Observer;
      14: astore_2
      15: aload_0
      16: getfield      #5                  // Field queue:Lio/reactivex/rxjava3/operators/SimplePlainQueue;
      19: astore_3
      20: aload_0
      21: getfield      #14                 // Field windows:Ljava/util/List;
      24: astore        4
      26: aload_0
      27: getfield      #43                 // Field upstreamCanceled:Z
      30: ifeq          49
      33: aload_3
      34: invokeinterface #49,  1           // InterfaceMethod io/reactivex/rxjava3/operators/SimplePlainQueue.clear:()V
      39: aload         4
      41: invokeinterface #50,  1           // InterfaceMethod java/util/List.clear:()V
      46: goto          454
      49: aload_0
      50: getfield      #38                 // Field upstreamDone:Z
      53: istore        5
      55: aload_3
      56: invokeinterface #51,  1           // InterfaceMethod io/reactivex/rxjava3/operators/SimplePlainQueue.poll:()Ljava/lang/Object;
      61: astore        6
      63: aload         6
      65: ifnonnull     72
      68: iconst_1
      69: goto          73
      72: iconst_0
      73: istore        7
      75: iload         5
      77: ifeq          108
      80: iload         7
      82: ifne          95
      85: aload_0
      86: getfield      #23                 // Field error:Lio/reactivex/rxjava3/internal/util/AtomicThrowable;
      89: invokevirtual #52                 // Method io/reactivex/rxjava3/internal/util/AtomicThrowable.get:()Ljava/lang/Object;
      92: ifnull        108
      95: aload_0
      96: aload_2
      97: invokevirtual #53                 // Method terminateDownstream:(Lio/reactivex/rxjava3/core/Observer;)V
     100: aload_0
     101: iconst_1
     102: putfield      #43                 // Field upstreamCanceled:Z
     105: goto          26
     108: iload         7
     110: ifne          401
     113: aload         6
     115: instanceof    #45                 // class io/reactivex/rxjava3/internal/operators/observable/ObservableWindowBoundarySelector$WindowBoundaryMainObserver$WindowStartItem
     118: ifeq          304
     121: aload_0
     122: getfield      #20                 // Field downstreamDisposed:Ljava/util/concurrent/atomic/AtomicBoolean;
     125: invokevirtual #44                 // Method java/util/concurrent/atomic/AtomicBoolean.get:()Z
     128: ifne          26
     131: aload         6
     133: checkcast     #45                 // class io/reactivex/rxjava3/internal/operators/observable/ObservableWindowBoundarySelector$WindowBoundaryMainObserver$WindowStartItem
     136: getfield      #54                 // Field io/reactivex/rxjava3/internal/operators/observable/ObservableWindowBoundarySelector$WindowBoundaryMainObserver$WindowStartItem.item:Ljava/lang/Object;
     139: astore        8
     141: aload_0
     142: getfield      #7                  // Field closingIndicator:Lio/reactivex/rxjava3/functions/Function;
     145: aload         8
     147: invokeinterface #55,  2           // InterfaceMethod io/reactivex/rxjava3/functions/Function.apply:(Ljava/lang/Object;)Ljava/lang/Object;
     152: ldc           #56                 // String The closingIndicator returned a null ObservableSource
     154: invokestatic  #57                 // Method java/util/Objects.requireNonNull:(Ljava/lang/Object;Ljava/lang/String;)Ljava/lang/Object;
     157: checkcast     #58                 // class io/reactivex/rxjava3/core/ObservableSource
     160: astore        9
     162: goto          218
     165: astore        10
     167: aload         10
     169: invokestatic  #60                 // Method io/reactivex/rxjava3/exceptions/Exceptions.throwIfFatal:(Ljava/lang/Throwable;)V
     172: aload_0
     173: getfield      #29                 // Field upstream:Lio/reactivex/rxjava3/disposables/Disposable;
     176: invokeinterface #41,  1           // InterfaceMethod io/reactivex/rxjava3/disposables/Disposable.dispose:()V
     181: aload_0
     182: getfield      #26                 // Field startObserver:Lio/reactivex/rxjava3/internal/operators/observable/ObservableWindowBoundarySelector$WindowBoundaryMainObserver$WindowStartObserver;
     185: invokevirtual #35                 // Method io/reactivex/rxjava3/internal/operators/observable/ObservableWindowBoundarySelector$WindowBoundaryMainObserver$WindowStartObserver.dispose:()V
     188: aload_0
     189: getfield      #11                 // Field resources:Lio/reactivex/rxjava3/disposables/CompositeDisposable;
     192: invokevirtual #36                 // Method io/reactivex/rxjava3/disposables/CompositeDisposable.dispose:()V
     195: aload         10
     197: invokestatic  #60                 // Method io/reactivex/rxjava3/exceptions/Exceptions.throwIfFatal:(Ljava/lang/Throwable;)V
     200: aload_0
     201: getfield      #23                 // Field error:Lio/reactivex/rxjava3/internal/util/AtomicThrowable;
     204: aload         10
     206: invokevirtual #37                 // Method io/reactivex/rxjava3/internal/util/AtomicThrowable.tryAddThrowableOrReport:(Ljava/lang/Throwable;)Z
     209: pop
     210: aload_0
     211: iconst_1
     212: putfield      #38                 // Field upstreamDone:Z
     215: goto          26
     218: aload_0
     219: getfield      #17                 // Field windowCount:Ljava/util/concurrent/atomic/AtomicLong;
     222: invokevirtual #61                 // Method java/util/concurrent/atomic/AtomicLong.getAndIncrement:()J
     225: pop2
     226: aload_0
     227: getfield      #8                  // Field bufferSize:I
     230: aload_0
     231: invokestatic  #62                 // Method io/reactivex/rxjava3/subjects/UnicastSubject.create:(ILjava/lang/Runnable;)Lio/reactivex/rxjava3/subjects/UnicastSubject;
     234: astore        10
     236: new           #63                 // class io/reactivex/rxjava3/internal/operators/observable/ObservableWindowBoundarySelector$WindowBoundaryMainObserver$WindowEndObserverIntercept
     239: dup
     240: aload_0
     241: aload         10
     243: invokespecial #64                 // Method io/reactivex/rxjava3/internal/operators/observable/ObservableWindowBoundarySelector$WindowBoundaryMainObserver$WindowEndObserverIntercept."<init>":(Lio/reactivex/rxjava3/internal/operators/observable/ObservableWindowBoundarySelector$WindowBoundaryMainObserver;Lio/reactivex/rxjava3/subjects/UnicastSubject;)V
     246: astore        11
     248: aload_2
     249: aload         11
     251: invokeinterface #65,  2           // InterfaceMethod io/reactivex/rxjava3/core/Observer.onNext:(Ljava/lang/Object;)V
     256: aload         11
     258: invokevirtual #66                 // Method io/reactivex/rxjava3/internal/operators/observable/ObservableWindowBoundarySelector$WindowBoundaryMainObserver$WindowEndObserverIntercept.tryAbandon:()Z
     261: ifeq          272
     264: aload         10
     266: invokevirtual #67                 // Method io/reactivex/rxjava3/subjects/UnicastSubject.onComplete:()V
     269: goto          301
     272: aload         4
     274: aload         10
     276: invokeinterface #68,  2           // InterfaceMethod java/util/List.add:(Ljava/lang/Object;)Z
     281: pop
     282: aload_0
     283: getfield      #11                 // Field resources:Lio/reactivex/rxjava3/disposables/CompositeDisposable;
     286: aload         11
     288: invokevirtual #69                 // Method io/reactivex/rxjava3/disposables/CompositeDisposable.add:(Lio/reactivex/rxjava3/disposables/Disposable;)Z
     291: pop
     292: aload         9
     294: aload         11
     296: invokeinterface #32,  2           // InterfaceMethod io/reactivex/rxjava3/core/ObservableSource.subscribe:(Lio/reactivex/rxjava3/core/Observer;)V
     301: goto          26
     304: aload         6
     306: instanceof    #63                 // class io/reactivex/rxjava3/internal/operators/observable/ObservableWindowBoundarySelector$WindowBoundaryMainObserver$WindowEndObserverIntercept
     309: ifeq          353
     312: aload         6
     314: checkcast     #63                 // class io/reactivex/rxjava3/internal/operators/observable/ObservableWindowBoundarySelector$WindowBoundaryMainObserver$WindowEndObserverIntercept
     317: getfield      #70                 // Field io/reactivex/rxjava3/internal/operators/observable/ObservableWindowBoundarySelector$WindowBoundaryMainObserver$WindowEndObserverIntercept.window:Lio/reactivex/rxjava3/subjects/UnicastSubject;
     320: astore        8
     322: aload         4
     324: aload         8
     326: invokeinterface #71,  2           // InterfaceMethod java/util/List.remove:(Ljava/lang/Object;)Z
     331: pop
     332: aload_0
     333: getfield      #11                 // Field resources:Lio/reactivex/rxjava3/disposables/CompositeDisposable;
     336: aload         6
     338: checkcast     #72                 // class io/reactivex/rxjava3/disposables/Disposable
     341: invokevirtual #73                 // Method io/reactivex/rxjava3/disposables/CompositeDisposable.delete:(Lio/reactivex/rxjava3/disposables/Disposable;)Z
     344: pop
     345: aload         8
     347: invokevirtual #67                 // Method io/reactivex/rxjava3/subjects/UnicastSubject.onComplete:()V
     350: goto          26
     353: aload         6
     355: astore        8
     357: aload         4
     359: invokeinterface #74,  1           // InterfaceMethod java/util/List.iterator:()Ljava/util/Iterator;
     364: astore        9
     366: aload         9
     368: invokeinterface #75,  1           // InterfaceMethod java/util/Iterator.hasNext:()Z
     373: ifeq          398
     376: aload         9
     378: invokeinterface #76,  1           // InterfaceMethod java/util/Iterator.next:()Ljava/lang/Object;
     383: checkcast     #77                 // class io/reactivex/rxjava3/subjects/UnicastSubject
     386: astore        10
     388: aload         10
     390: aload         8
     392: invokevirtual #78                 // Method io/reactivex/rxjava3/subjects/UnicastSubject.onNext:(Ljava/lang/Object;)V
     395: goto          366
     398: goto          26
     401: aload_0
     402: getfield      #47                 // Field openDone:Z
     405: ifeq          454
     408: aload         4
     410: invokeinterface #79,  1           // InterfaceMethod java/util/List.size:()I
     415: ifne          454
     418: aload_0
     419: getfield      #29                 // Field upstream:Lio/reactivex/rxjava3/disposables/Disposable;
     422: invokeinterface #41,  1           // InterfaceMethod io/reactivex/rxjava3/disposables/Disposable.dispose:()V
     427: aload_0
     428: getfield      #26                 // Field startObserver:Lio/reactivex/rxjava3/internal/operators/observable/ObservableWindowBoundarySelector$WindowBoundaryMainObserver$WindowStartObserver;
     431: invokevirtual #35                 // Method io/reactivex/rxjava3/internal/operators/observable/ObservableWindowBoundarySelector$WindowBoundaryMainObserver$WindowStartObserver.dispose:()V
     434: aload_0
     435: getfield      #11                 // Field resources:Lio/reactivex/rxjava3/disposables/CompositeDisposable;
     438: invokevirtual #36                 // Method io/reactivex/rxjava3/disposables/CompositeDisposable.dispose:()V
     441: aload_0
     442: aload_2
     443: invokevirtual #53                 // Method terminateDownstream:(Lio/reactivex/rxjava3/core/Observer;)V
     446: aload_0
     447: iconst_1
     448: putfield      #43                 // Field upstreamCanceled:Z
     451: goto          26
     454: aload_0
     455: iload_1
     456: ineg
     457: invokevirtual #80                 // Method addAndGet:(I)I
     460: istore_1
     461: iload_1
     462: ifne          26
     465: goto          468
     468: return
    Exception table:
       from    to  target type
         141   162   165   Class java/lang/Throwable

  void terminateDownstream(io.reactivex.rxjava3.core.Observer<?>);
    Code:
       0: aload_0
       1: getfield      #23                 // Field error:Lio/reactivex/rxjava3/internal/util/AtomicThrowable;
       4: invokevirtual #81                 // Method io/reactivex/rxjava3/internal/util/AtomicThrowable.terminate:()Ljava/lang/Throwable;
       7: astore_2
       8: aload_2
       9: ifnonnull     59
      12: aload_0
      13: getfield      #14                 // Field windows:Ljava/util/List;
      16: invokeinterface #74,  1           // InterfaceMethod java/util/List.iterator:()Ljava/util/Iterator;
      21: astore_3
      22: aload_3
      23: invokeinterface #75,  1           // InterfaceMethod java/util/Iterator.hasNext:()Z
      28: ifeq          50
      31: aload_3
      32: invokeinterface #76,  1           // InterfaceMethod java/util/Iterator.next:()Ljava/lang/Object;
      37: checkcast     #77                 // class io/reactivex/rxjava3/subjects/UnicastSubject
      40: astore        4
      42: aload         4
      44: invokevirtual #67                 // Method io/reactivex/rxjava3/subjects/UnicastSubject.onComplete:()V
      47: goto          22
      50: aload_1
      51: invokeinterface #82,  1           // InterfaceMethod io/reactivex/rxjava3/core/Observer.onComplete:()V
      56: goto          112
      59: aload_2
      60: getstatic     #83                 // Field io/reactivex/rxjava3/internal/util/ExceptionHelper.TERMINATED:Ljava/lang/Throwable;
      63: if_acmpeq     112
      66: aload_0
      67: getfield      #14                 // Field windows:Ljava/util/List;
      70: invokeinterface #74,  1           // InterfaceMethod java/util/List.iterator:()Ljava/util/Iterator;
      75: astore_3
      76: aload_3
      77: invokeinterface #75,  1           // InterfaceMethod java/util/Iterator.hasNext:()Z
      82: ifeq          105
      85: aload_3
      86: invokeinterface #76,  1           // InterfaceMethod java/util/Iterator.next:()Ljava/lang/Object;
      91: checkcast     #77                 // class io/reactivex/rxjava3/subjects/UnicastSubject
      94: astore        4
      96: aload         4
      98: aload_2
      99: invokevirtual #84                 // Method io/reactivex/rxjava3/subjects/UnicastSubject.onError:(Ljava/lang/Throwable;)V
     102: goto          76
     105: aload_1
     106: aload_2
     107: invokeinterface #85,  2           // InterfaceMethod io/reactivex/rxjava3/core/Observer.onError:(Ljava/lang/Throwable;)V
     112: return
}
