Compiled from "ObservableElementAt.java"
final class io.reactivex.rxjava3.internal.operators.observable.ObservableElementAt$ElementAtObserver<T> implements io.reactivex.rxjava3.core.Observer<T>, io.reactivex.rxjava3.disposables.Disposable {
  final io.reactivex.rxjava3.core.Observer<? super T> downstream;

  final long index;

  final T defaultValue;

  final boolean errorOnFewer;

  io.reactivex.rxjava3.disposables.Disposable upstream;

  long count;

  boolean done;

  io.reactivex.rxjava3.internal.operators.observable.ObservableElementAt$ElementAtObserver(io.reactivex.rxjava3.core.Observer<? super T>, long, T, boolean);
    Code:
       0: aload_0
       1: invokespecial #1                  // Method java/lang/Object."<init>":()V
       4: aload_0
       5: aload_1
       6: putfield      #2                  // Field downstream:Lio/reactivex/rxjava3/core/Observer;
       9: aload_0
      10: lload_2
      11: putfield      #3                  // Field index:J
      14: aload_0
      15: aload         4
      17: putfield      #4                  // Field defaultValue:Ljava/lang/Object;
      20: aload_0
      21: iload         5
      23: putfield      #5                  // Field errorOnFewer:Z
      26: return

  public void onSubscribe(io.reactivex.rxjava3.disposables.Disposable);
    Code:
       0: aload_0
       1: getfield      #6                  // Field upstream:Lio/reactivex/rxjava3/disposables/Disposable;
       4: aload_1
       5: invokestatic  #7                  // Method io/reactivex/rxjava3/internal/disposables/DisposableHelper.validate:(Lio/reactivex/rxjava3/disposables/Disposable;Lio/reactivex/rxjava3/disposables/Disposable;)Z
       8: ifeq          26
      11: aload_0
      12: aload_1
      13: putfield      #6                  // Field upstream:Lio/reactivex/rxjava3/disposables/Disposable;
      16: aload_0
      17: getfield      #2                  // Field downstream:Lio/reactivex/rxjava3/core/Observer;
      20: aload_0
      21: invokeinterface #8,  2            // InterfaceMethod io/reactivex/rxjava3/core/Observer.onSubscribe:(Lio/reactivex/rxjava3/disposables/Disposable;)V
      26: return

  public void dispose();
    Code:
       0: aload_0
       1: getfield      #6                  // Field upstream:Lio/reactivex/rxjava3/disposables/Disposable;
       4: invokeinterface #9,  1            // InterfaceMethod io/reactivex/rxjava3/disposables/Disposable.dispose:()V
       9: return

  public boolean isDisposed();
    Code:
       0: aload_0
       1: getfield      #6                  // Field upstream:Lio/reactivex/rxjava3/disposables/Disposable;
       4: invokeinterface #10,  1           // InterfaceMethod io/reactivex/rxjava3/disposables/Disposable.isDisposed:()Z
       9: ireturn

  public void onNext(T);
    Code:
       0: aload_0
       1: getfield      #11                 // Field done:Z
       4: ifeq          8
       7: return
       8: aload_0
       9: getfield      #12                 // Field count:J
      12: lstore_2
      13: lload_2
      14: aload_0
      15: getfield      #3                  // Field index:J
      18: lcmp
      19: ifne          56
      22: aload_0
      23: iconst_1
      24: putfield      #11                 // Field done:Z
      27: aload_0
      28: getfield      #6                  // Field upstream:Lio/reactivex/rxjava3/disposables/Disposable;
      31: invokeinterface #9,  1            // InterfaceMethod io/reactivex/rxjava3/disposables/Disposable.dispose:()V
      36: aload_0
      37: getfield      #2                  // Field downstream:Lio/reactivex/rxjava3/core/Observer;
      40: aload_1
      41: invokeinterface #13,  2           // InterfaceMethod io/reactivex/rxjava3/core/Observer.onNext:(Ljava/lang/Object;)V
      46: aload_0
      47: getfield      #2                  // Field downstream:Lio/reactivex/rxjava3/core/Observer;
      50: invokeinterface #14,  1           // InterfaceMethod io/reactivex/rxjava3/core/Observer.onComplete:()V
      55: return
      56: aload_0
      57: lload_2
      58: lconst_1
      59: ladd
      60: putfield      #12                 // Field count:J
      63: return

  public void onError(java.lang.Throwable);
    Code:
       0: aload_0
       1: getfield      #11                 // Field done:Z
       4: ifeq          12
       7: aload_1
       8: invokestatic  #15                 // Method io/reactivex/rxjava3/plugins/RxJavaPlugins.onError:(Ljava/lang/Throwable;)V
      11: return
      12: aload_0
      13: iconst_1
      14: putfield      #11                 // Field done:Z
      17: aload_0
      18: getfield      #2                  // Field downstream:Lio/reactivex/rxjava3/core/Observer;
      21: aload_1
      22: invokeinterface #16,  2           // InterfaceMethod io/reactivex/rxjava3/core/Observer.onError:(Ljava/lang/Throwable;)V
      27: return

  public void onComplete();
    Code:
       0: aload_0
       1: getfield      #11                 // Field done:Z
       4: ifne          70
       7: aload_0
       8: iconst_1
       9: putfield      #11                 // Field done:Z
      12: aload_0
      13: getfield      #4                  // Field defaultValue:Ljava/lang/Object;
      16: astore_1
      17: aload_1
      18: ifnonnull     47
      21: aload_0
      22: getfield      #5                  // Field errorOnFewer:Z
      25: ifeq          47
      28: aload_0
      29: getfield      #2                  // Field downstream:Lio/reactivex/rxjava3/core/Observer;
      32: new           #17                 // class java/util/NoSuchElementException
      35: dup
      36: invokespecial #18                 // Method java/util/NoSuchElementException."<init>":()V
      39: invokeinterface #16,  2           // InterfaceMethod io/reactivex/rxjava3/core/Observer.onError:(Ljava/lang/Throwable;)V
      44: goto          70
      47: aload_1
      48: ifnull        61
      51: aload_0
      52: getfield      #2                  // Field downstream:Lio/reactivex/rxjava3/core/Observer;
      55: aload_1
      56: invokeinterface #13,  2           // InterfaceMethod io/reactivex/rxjava3/core/Observer.onNext:(Ljava/lang/Object;)V
      61: aload_0
      62: getfield      #2                  // Field downstream:Lio/reactivex/rxjava3/core/Observer;
      65: invokeinterface #14,  1           // InterfaceMethod io/reactivex/rxjava3/core/Observer.onComplete:()V
      70: return
}
