Compiled from "ObservableWindowBoundarySelector.java"
public final class io.reactivex.rxjava3.internal.operators.observable.ObservableWindowBoundarySelector<T, B, V> extends io.reactivex.rxjava3.internal.operators.observable.AbstractObservableWithUpstream<T, io.reactivex.rxjava3.core.Observable<T>> {
  final io.reactivex.rxjava3.core.ObservableSource<B> open;

  final io.reactivex.rxjava3.functions.Function<? super B, ? extends io.reactivex.rxjava3.core.ObservableSource<V>> closingIndicator;

  final int bufferSize;

  public io.reactivex.rxjava3.internal.operators.observable.ObservableWindowBoundarySelector(io.reactivex.rxjava3.core.ObservableSource<T>, io.reactivex.rxjava3.core.ObservableSource<B>, io.reactivex.rxjava3.functions.Function<? super B, ? extends io.reactivex.rxjava3.core.ObservableSource<V>>, int);
    Code:
       0: aload_0
       1: aload_1
       2: invokespecial #1                  // Method io/reactivex/rxjava3/internal/operators/observable/AbstractObservableWithUpstream."<init>":(Lio/reactivex/rxjava3/core/ObservableSource;)V
       5: aload_0
       6: aload_2
       7: putfield      #2                  // Field open:Lio/reactivex/rxjava3/core/ObservableSource;
      10: aload_0
      11: aload_3
      12: putfield      #3                  // Field closingIndicator:Lio/reactivex/rxjava3/functions/Function;
      15: aload_0
      16: iload         4
      18: putfield      #4                  // Field bufferSize:I
      21: return

  public void subscribeActual(io.reactivex.rxjava3.core.Observer<? super io.reactivex.rxjava3.core.Observable<T>>);
    Code:
       0: aload_0
       1: getfield      #5                  // Field source:Lio/reactivex/rxjava3/core/ObservableSource;
       4: new           #6                  // class io/reactivex/rxjava3/internal/operators/observable/ObservableWindowBoundarySelector$WindowBoundaryMainObserver
       7: dup
       8: aload_1
       9: aload_0
      10: getfield      #2                  // Field open:Lio/reactivex/rxjava3/core/ObservableSource;
      13: aload_0
      14: getfield      #3                  // Field closingIndicator:Lio/reactivex/rxjava3/functions/Function;
      17: aload_0
      18: getfield      #4                  // Field bufferSize:I
      21: invokespecial #7                  // Method io/reactivex/rxjava3/internal/operators/observable/ObservableWindowBoundarySelector$WindowBoundaryMainObserver."<init>":(Lio/reactivex/rxjava3/core/Observer;Lio/reactivex/rxjava3/core/ObservableSource;Lio/reactivex/rxjava3/functions/Function;I)V
      24: invokeinterface #8,  2            // InterfaceMethod io/reactivex/rxjava3/core/ObservableSource.subscribe:(Lio/reactivex/rxjava3/core/Observer;)V
      29: return
}
