Compiled from "ObservableWithLatestFrom.java"
final class io.reactivex.rxjava3.internal.operators.observable.ObservableWithLatestFrom$WithLatestFromObserver<T, U, R> extends java.util.concurrent.atomic.AtomicReference<U> implements io.reactivex.rxjava3.core.Observer<T>, io.reactivex.rxjava3.disposables.Disposable {
  private static final long serialVersionUID;

  final io.reactivex.rxjava3.core.Observer<? super R> downstream;

  final io.reactivex.rxjava3.functions.BiFunction<? super T, ? super U, ? extends R> combiner;

  final java.util.concurrent.atomic.AtomicReference<io.reactivex.rxjava3.disposables.Disposable> upstream;

  final java.util.concurrent.atomic.AtomicReference<io.reactivex.rxjava3.disposables.Disposable> other;

  io.reactivex.rxjava3.internal.operators.observable.ObservableWithLatestFrom$WithLatestFromObserver(io.reactivex.rxjava3.core.Observer<? super R>, io.reactivex.rxjava3.functions.BiFunction<? super T, ? super U, ? extends R>);
    Code:
       0: aload_0
       1: invokespecial #1                  // Method java/util/concurrent/atomic/AtomicReference."<init>":()V
       4: aload_0
       5: new           #2                  // class java/util/concurrent/atomic/AtomicReference
       8: dup
       9: invokespecial #1                  // Method java/util/concurrent/atomic/AtomicReference."<init>":()V
      12: putfield      #3                  // Field upstream:Ljava/util/concurrent/atomic/AtomicReference;
      15: aload_0
      16: new           #2                  // class java/util/concurrent/atomic/AtomicReference
      19: dup
      20: invokespecial #1                  // Method java/util/concurrent/atomic/AtomicReference."<init>":()V
      23: putfield      #4                  // Field other:Ljava/util/concurrent/atomic/AtomicReference;
      26: aload_0
      27: aload_1
      28: putfield      #5                  // Field downstream:Lio/reactivex/rxjava3/core/Observer;
      31: aload_0
      32: aload_2
      33: putfield      #6                  // Field combiner:Lio/reactivex/rxjava3/functions/BiFunction;
      36: return

  public void onSubscribe(io.reactivex.rxjava3.disposables.Disposable);
    Code:
       0: aload_0
       1: getfield      #3                  // Field upstream:Ljava/util/concurrent/atomic/AtomicReference;
       4: aload_1
       5: invokestatic  #7                  // Method io/reactivex/rxjava3/internal/disposables/DisposableHelper.setOnce:(Ljava/util/concurrent/atomic/AtomicReference;Lio/reactivex/rxjava3/disposables/Disposable;)Z
       8: pop
       9: return

  public void onNext(T);
    Code:
       0: aload_0
       1: invokevirtual #8                  // Method get:()Ljava/lang/Object;
       4: astore_2
       5: aload_2
       6: ifnull        62
       9: aload_0
      10: getfield      #6                  // Field combiner:Lio/reactivex/rxjava3/functions/BiFunction;
      13: aload_1
      14: aload_2
      15: invokeinterface #9,  3            // InterfaceMethod io/reactivex/rxjava3/functions/BiFunction.apply:(Ljava/lang/Object;Ljava/lang/Object;)Ljava/lang/Object;
      20: ldc           #10                 // String The combiner returned a null value
      22: invokestatic  #11                 // Method java/util/Objects.requireNonNull:(Ljava/lang/Object;Ljava/lang/String;)Ljava/lang/Object;
      25: astore_3
      26: goto          52
      29: astore        4
      31: aload         4
      33: invokestatic  #13                 // Method io/reactivex/rxjava3/exceptions/Exceptions.throwIfFatal:(Ljava/lang/Throwable;)V
      36: aload_0
      37: invokevirtual #14                 // Method dispose:()V
      40: aload_0
      41: getfield      #5                  // Field downstream:Lio/reactivex/rxjava3/core/Observer;
      44: aload         4
      46: invokeinterface #15,  2           // InterfaceMethod io/reactivex/rxjava3/core/Observer.onError:(Ljava/lang/Throwable;)V
      51: return
      52: aload_0
      53: getfield      #5                  // Field downstream:Lio/reactivex/rxjava3/core/Observer;
      56: aload_3
      57: invokeinterface #16,  2           // InterfaceMethod io/reactivex/rxjava3/core/Observer.onNext:(Ljava/lang/Object;)V
      62: return
    Exception table:
       from    to  target type
           9    26    29   Class java/lang/Throwable

  public void onError(java.lang.Throwable);
    Code:
       0: aload_0
       1: getfield      #4                  // Field other:Ljava/util/concurrent/atomic/AtomicReference;
       4: invokestatic  #17                 // Method io/reactivex/rxjava3/internal/disposables/DisposableHelper.dispose:(Ljava/util/concurrent/atomic/AtomicReference;)Z
       7: pop
       8: aload_0
       9: getfield      #5                  // Field downstream:Lio/reactivex/rxjava3/core/Observer;
      12: aload_1
      13: invokeinterface #15,  2           // InterfaceMethod io/reactivex/rxjava3/core/Observer.onError:(Ljava/lang/Throwable;)V
      18: return

  public void onComplete();
    Code:
       0: aload_0
       1: getfield      #4                  // Field other:Ljava/util/concurrent/atomic/AtomicReference;
       4: invokestatic  #17                 // Method io/reactivex/rxjava3/internal/disposables/DisposableHelper.dispose:(Ljava/util/concurrent/atomic/AtomicReference;)Z
       7: pop
       8: aload_0
       9: getfield      #5                  // Field downstream:Lio/reactivex/rxjava3/core/Observer;
      12: invokeinterface #18,  1           // InterfaceMethod io/reactivex/rxjava3/core/Observer.onComplete:()V
      17: return

  public void dispose();
    Code:
       0: aload_0
       1: getfield      #3                  // Field upstream:Ljava/util/concurrent/atomic/AtomicReference;
       4: invokestatic  #17                 // Method io/reactivex/rxjava3/internal/disposables/DisposableHelper.dispose:(Ljava/util/concurrent/atomic/AtomicReference;)Z
       7: pop
       8: aload_0
       9: getfield      #4                  // Field other:Ljava/util/concurrent/atomic/AtomicReference;
      12: invokestatic  #17                 // Method io/reactivex/rxjava3/internal/disposables/DisposableHelper.dispose:(Ljava/util/concurrent/atomic/AtomicReference;)Z
      15: pop
      16: return

  public boolean isDisposed();
    Code:
       0: aload_0
       1: getfield      #3                  // Field upstream:Ljava/util/concurrent/atomic/AtomicReference;
       4: invokevirtual #19                 // Method java/util/concurrent/atomic/AtomicReference.get:()Ljava/lang/Object;
       7: checkcast     #20                 // class io/reactivex/rxjava3/disposables/Disposable
      10: invokestatic  #21                 // Method io/reactivex/rxjava3/internal/disposables/DisposableHelper.isDisposed:(Lio/reactivex/rxjava3/disposables/Disposable;)Z
      13: ireturn

  public boolean setOther(io.reactivex.rxjava3.disposables.Disposable);
    Code:
       0: aload_0
       1: getfield      #4                  // Field other:Ljava/util/concurrent/atomic/AtomicReference;
       4: aload_1
       5: invokestatic  #7                  // Method io/reactivex/rxjava3/internal/disposables/DisposableHelper.setOnce:(Ljava/util/concurrent/atomic/AtomicReference;Lio/reactivex/rxjava3/disposables/Disposable;)Z
       8: ireturn

  public void otherError(java.lang.Throwable);
    Code:
       0: aload_0
       1: getfield      #3                  // Field upstream:Ljava/util/concurrent/atomic/AtomicReference;
       4: invokestatic  #17                 // Method io/reactivex/rxjava3/internal/disposables/DisposableHelper.dispose:(Ljava/util/concurrent/atomic/AtomicReference;)Z
       7: pop
       8: aload_0
       9: getfield      #5                  // Field downstream:Lio/reactivex/rxjava3/core/Observer;
      12: aload_1
      13: invokeinterface #15,  2           // InterfaceMethod io/reactivex/rxjava3/core/Observer.onError:(Ljava/lang/Throwable;)V
      18: return
}
