Compiled from "ObservableSkipLast.java"
public final class io.reactivex.rxjava3.internal.operators.observable.ObservableSkipLast<T> extends io.reactivex.rxjava3.internal.operators.observable.AbstractObservableWithUpstream<T, T> {
  final int skip;

  public io.reactivex.rxjava3.internal.operators.observable.ObservableSkipLast(io.reactivex.rxjava3.core.ObservableSource<T>, int);
    Code:
       0: aload_0
       1: aload_1
       2: invokespecial #1                  // Method io/reactivex/rxjava3/internal/operators/observable/AbstractObservableWithUpstream."<init>":(Lio/reactivex/rxjava3/core/ObservableSource;)V
       5: aload_0
       6: iload_2
       7: putfield      #2                  // Field skip:I
      10: return

  public void subscribeActual(io.reactivex.rxjava3.core.Observer<? super T>);
    Code:
       0: aload_0
       1: getfield      #3                  // Field source:Lio/reactivex/rxjava3/core/ObservableSource;
       4: new           #4                  // class io/reactivex/rxjava3/internal/operators/observable/ObservableSkipLast$SkipLastObserver
       7: dup
       8: aload_1
       9: aload_0
      10: getfield      #2                  // Field skip:I
      13: invokespecial #5                  // Method io/reactivex/rxjava3/internal/operators/observable/ObservableSkipLast$SkipLastObserver."<init>":(Lio/reactivex/rxjava3/core/Observer;I)V
      16: invokeinterface #6,  2            // InterfaceMethod io/reactivex/rxjava3/core/ObservableSource.subscribe:(Lio/reactivex/rxjava3/core/Observer;)V
      21: return
}
