Compiled from "ObservableSequenceEqual.java"
public final class io.reactivex.rxjava3.internal.operators.observable.ObservableSequenceEqual<T> extends io.reactivex.rxjava3.core.Observable<java.lang.Boolean> {
  final io.reactivex.rxjava3.core.ObservableSource<? extends T> first;

  final io.reactivex.rxjava3.core.ObservableSource<? extends T> second;

  final io.reactivex.rxjava3.functions.BiPredicate<? super T, ? super T> comparer;

  final int bufferSize;

  public io.reactivex.rxjava3.internal.operators.observable.ObservableSequenceEqual(io.reactivex.rxjava3.core.ObservableSource<? extends T>, io.reactivex.rxjava3.core.ObservableSource<? extends T>, io.reactivex.rxjava3.functions.BiPredicate<? super T, ? super T>, int);
    Code:
       0: aload_0
       1: invokespecial #1                  // Method io/reactivex/rxjava3/core/Observable."<init>":()V
       4: aload_0
       5: aload_1
       6: putfield      #2                  // Field first:Lio/reactivex/rxjava3/core/ObservableSource;
       9: aload_0
      10: aload_2
      11: putfield      #3                  // Field second:Lio/reactivex/rxjava3/core/ObservableSource;
      14: aload_0
      15: aload_3
      16: putfield      #4                  // Field comparer:Lio/reactivex/rxjava3/functions/BiPredicate;
      19: aload_0
      20: iload         4
      22: putfield      #5                  // Field bufferSize:I
      25: return

  public void subscribeActual(io.reactivex.rxjava3.core.Observer<? super java.lang.Boolean>);
    Code:
       0: new           #6                  // class io/reactivex/rxjava3/internal/operators/observable/ObservableSequenceEqual$EqualCoordinator
       3: dup
       4: aload_1
       5: aload_0
       6: getfield      #5                  // Field bufferSize:I
       9: aload_0
      10: getfield      #2                  // Field first:Lio/reactivex/rxjava3/core/ObservableSource;
      13: aload_0
      14: getfield      #3                  // Field second:Lio/reactivex/rxjava3/core/ObservableSource;
      17: aload_0
      18: getfield      #4                  // Field comparer:Lio/reactivex/rxjava3/functions/BiPredicate;
      21: invokespecial #7                  // Method io/reactivex/rxjava3/internal/operators/observable/ObservableSequenceEqual$EqualCoordinator."<init>":(Lio/reactivex/rxjava3/core/Observer;ILio/reactivex/rxjava3/core/ObservableSource;Lio/reactivex/rxjava3/core/ObservableSource;Lio/reactivex/rxjava3/functions/BiPredicate;)V
      24: astore_2
      25: aload_1
      26: aload_2
      27: invokeinterface #8,  2            // InterfaceMethod io/reactivex/rxjava3/core/Observer.onSubscribe:(Lio/reactivex/rxjava3/disposables/Disposable;)V
      32: aload_2
      33: invokevirtual #9                  // Method io/reactivex/rxjava3/internal/operators/observable/ObservableSequenceEqual$EqualCoordinator.subscribe:()V
      36: return
}
