Compiled from "ObservableFlatMapCompletable.java"
public final class io.reactivex.rxjava3.internal.operators.observable.ObservableFlatMapCompletable<T> extends io.reactivex.rxjava3.internal.operators.observable.AbstractObservableWithUpstream<T, T> {
  final io.reactivex.rxjava3.functions.Function<? super T, ? extends io.reactivex.rxjava3.core.CompletableSource> mapper;

  final boolean delayErrors;

  public io.reactivex.rxjava3.internal.operators.observable.ObservableFlatMapCompletable(io.reactivex.rxjava3.core.ObservableSource<T>, io.reactivex.rxjava3.functions.Function<? super T, ? extends io.reactivex.rxjava3.core.CompletableSource>, boolean);
    Code:
       0: aload_0
       1: aload_1
       2: invokespecial #1                  // Method io/reactivex/rxjava3/internal/operators/observable/AbstractObservableWithUpstream."<init>":(Lio/reactivex/rxjava3/core/ObservableSource;)V
       5: aload_0
       6: aload_2
       7: putfield      #2                  // Field mapper:Lio/reactivex/rxjava3/functions/Function;
      10: aload_0
      11: iload_3
      12: putfield      #3                  // Field delayErrors:Z
      15: return

  protected void subscribeActual(io.reactivex.rxjava3.core.Observer<? super T>);
    Code:
       0: aload_0
       1: getfield      #4                  // Field source:Lio/reactivex/rxjava3/core/ObservableSource;
       4: new           #5                  // class io/reactivex/rxjava3/internal/operators/observable/ObservableFlatMapCompletable$FlatMapCompletableMainObserver
       7: dup
       8: aload_1
       9: aload_0
      10: getfield      #2                  // Field mapper:Lio/reactivex/rxjava3/functions/Function;
      13: aload_0
      14: getfield      #3                  // Field delayErrors:Z
      17: invokespecial #6                  // Method io/reactivex/rxjava3/internal/operators/observable/ObservableFlatMapCompletable$FlatMapCompletableMainObserver."<init>":(Lio/reactivex/rxjava3/core/Observer;Lio/reactivex/rxjava3/functions/Function;Z)V
      20: invokeinterface #7,  2            // InterfaceMethod io/reactivex/rxjava3/core/ObservableSource.subscribe:(Lio/reactivex/rxjava3/core/Observer;)V
      25: return
}
