Compiled from "ObservableWindowTimed.java"
public final class io.reactivex.rxjava3.internal.operators.observable.ObservableWindowTimed<T> extends io.reactivex.rxjava3.internal.operators.observable.AbstractObservableWithUpstream<T, io.reactivex.rxjava3.core.Observable<T>> {
  final long timespan;

  final long timeskip;

  final java.util.concurrent.TimeUnit unit;

  final io.reactivex.rxjava3.core.Scheduler scheduler;

  final long maxSize;

  final int bufferSize;

  final boolean restartTimerOnMaxSize;

  public io.reactivex.rxjava3.internal.operators.observable.ObservableWindowTimed(io.reactivex.rxjava3.core.Observable<T>, long, long, java.util.concurrent.TimeUnit, io.reactivex.rxjava3.core.Scheduler, long, int, boolean);
    Code:
       0: aload_0
       1: aload_1
       2: invokespecial #1                  // Method io/reactivex/rxjava3/internal/operators/observable/AbstractObservableWithUpstream."<init>":(Lio/reactivex/rxjava3/core/ObservableSource;)V
       5: aload_0
       6: lload_2
       7: putfield      #2                  // Field timespan:J
      10: aload_0
      11: lload         4
      13: putfield      #3                  // Field timeskip:J
      16: aload_0
      17: aload         6
      19: putfield      #4                  // Field unit:Ljava/util/concurrent/TimeUnit;
      22: aload_0
      23: aload         7
      25: putfield      #5                  // Field scheduler:Lio/reactivex/rxjava3/core/Scheduler;
      28: aload_0
      29: lload         8
      31: putfield      #6                  // Field maxSize:J
      34: aload_0
      35: iload         10
      37: putfield      #7                  // Field bufferSize:I
      40: aload_0
      41: iload         11
      43: putfield      #8                  // Field restartTimerOnMaxSize:Z
      46: return

  protected void subscribeActual(io.reactivex.rxjava3.core.Observer<? super io.reactivex.rxjava3.core.Observable<T>>);
    Code:
       0: aload_0
       1: getfield      #2                  // Field timespan:J
       4: aload_0
       5: getfield      #3                  // Field timeskip:J
       8: lcmp
       9: ifne          99
      12: aload_0
      13: getfield      #6                  // Field maxSize:J
      16: ldc2_w        #10                 // long 9223372036854775807l
      19: lcmp
      20: ifne          57
      23: aload_0
      24: getfield      #12                 // Field source:Lio/reactivex/rxjava3/core/ObservableSource;
      27: new           #13                 // class io/reactivex/rxjava3/internal/operators/observable/ObservableWindowTimed$WindowExactUnboundedObserver
      30: dup
      31: aload_1
      32: aload_0
      33: getfield      #2                  // Field timespan:J
      36: aload_0
      37: getfield      #4                  // Field unit:Ljava/util/concurrent/TimeUnit;
      40: aload_0
      41: getfield      #5                  // Field scheduler:Lio/reactivex/rxjava3/core/Scheduler;
      44: aload_0
      45: getfield      #7                  // Field bufferSize:I
      48: invokespecial #14                 // Method io/reactivex/rxjava3/internal/operators/observable/ObservableWindowTimed$WindowExactUnboundedObserver."<init>":(Lio/reactivex/rxjava3/core/Observer;JLjava/util/concurrent/TimeUnit;Lio/reactivex/rxjava3/core/Scheduler;I)V
      51: invokeinterface #15,  2           // InterfaceMethod io/reactivex/rxjava3/core/ObservableSource.subscribe:(Lio/reactivex/rxjava3/core/Observer;)V
      56: return
      57: aload_0
      58: getfield      #12                 // Field source:Lio/reactivex/rxjava3/core/ObservableSource;
      61: new           #16                 // class io/reactivex/rxjava3/internal/operators/observable/ObservableWindowTimed$WindowExactBoundedObserver
      64: dup
      65: aload_1
      66: aload_0
      67: getfield      #2                  // Field timespan:J
      70: aload_0
      71: getfield      #4                  // Field unit:Ljava/util/concurrent/TimeUnit;
      74: aload_0
      75: getfield      #5                  // Field scheduler:Lio/reactivex/rxjava3/core/Scheduler;
      78: aload_0
      79: getfield      #7                  // Field bufferSize:I
      82: aload_0
      83: getfield      #6                  // Field maxSize:J
      86: aload_0
      87: getfield      #8                  // Field restartTimerOnMaxSize:Z
      90: invokespecial #17                 // Method io/reactivex/rxjava3/internal/operators/observable/ObservableWindowTimed$WindowExactBoundedObserver."<init>":(Lio/reactivex/rxjava3/core/Observer;JLjava/util/concurrent/TimeUnit;Lio/reactivex/rxjava3/core/Scheduler;IJZ)V
      93: invokeinterface #15,  2           // InterfaceMethod io/reactivex/rxjava3/core/ObservableSource.subscribe:(Lio/reactivex/rxjava3/core/Observer;)V
      98: return
      99: aload_0
     100: getfield      #12                 // Field source:Lio/reactivex/rxjava3/core/ObservableSource;
     103: new           #18                 // class io/reactivex/rxjava3/internal/operators/observable/ObservableWindowTimed$WindowSkipObserver
     106: dup
     107: aload_1
     108: aload_0
     109: getfield      #2                  // Field timespan:J
     112: aload_0
     113: getfield      #3                  // Field timeskip:J
     116: aload_0
     117: getfield      #4                  // Field unit:Ljava/util/concurrent/TimeUnit;
     120: aload_0
     121: getfield      #5                  // Field scheduler:Lio/reactivex/rxjava3/core/Scheduler;
     124: invokevirtual #19                 // Method io/reactivex/rxjava3/core/Scheduler.createWorker:()Lio/reactivex/rxjava3/core/Scheduler$Worker;
     127: aload_0
     128: getfield      #7                  // Field bufferSize:I
     131: invokespecial #20                 // Method io/reactivex/rxjava3/internal/operators/observable/ObservableWindowTimed$WindowSkipObserver."<init>":(Lio/reactivex/rxjava3/core/Observer;JJLjava/util/concurrent/TimeUnit;Lio/reactivex/rxjava3/core/Scheduler$Worker;I)V
     134: invokeinterface #15,  2           // InterfaceMethod io/reactivex/rxjava3/core/ObservableSource.subscribe:(Lio/reactivex/rxjava3/core/Observer;)V
     139: return
}
