Compiled from "ObservableScalarXMap.java"
public final class io.reactivex.rxjava3.internal.operators.observable.ObservableScalarXMap$ScalarDisposable<T> extends java.util.concurrent.atomic.AtomicInteger implements io.reactivex.rxjava3.operators.QueueDisposable<T>, java.lang.Runnable {
  private static final long serialVersionUID;

  final io.reactivex.rxjava3.core.Observer<? super T> observer;

  final T value;

  static final int START;

  static final int FUSED;

  static final int ON_NEXT;

  static final int ON_COMPLETE;

  public io.reactivex.rxjava3.internal.operators.observable.ObservableScalarXMap$ScalarDisposable(io.reactivex.rxjava3.core.Observer<? super T>, T);
    Code:
       0: aload_0
       1: invokespecial #1                  // Method java/util/concurrent/atomic/AtomicInteger."<init>":()V
       4: aload_0
       5: aload_1
       6: putfield      #2                  // Field observer:Lio/reactivex/rxjava3/core/Observer;
       9: aload_0
      10: aload_2
      11: putfield      #3                  // Field value:Ljava/lang/Object;
      14: return

  public boolean offer(T);
    Code:
       0: new           #4                  // class java/lang/UnsupportedOperationException
       3: dup
       4: ldc           #5                  // String Should not be called!
       6: invokespecial #6                  // Method java/lang/UnsupportedOperationException."<init>":(Ljava/lang/String;)V
       9: athrow

  public boolean offer(T, T);
    Code:
       0: new           #4                  // class java/lang/UnsupportedOperationException
       3: dup
       4: ldc           #5                  // String Should not be called!
       6: invokespecial #6                  // Method java/lang/UnsupportedOperationException."<init>":(Ljava/lang/String;)V
       9: athrow

  public T poll();
    Code:
       0: aload_0
       1: invokevirtual #7                  // Method get:()I
       4: iconst_1
       5: if_icmpne     18
       8: aload_0
       9: iconst_3
      10: invokevirtual #9                  // Method lazySet:(I)V
      13: aload_0
      14: getfield      #3                  // Field value:Ljava/lang/Object;
      17: areturn
      18: aconst_null
      19: areturn

  public boolean isEmpty();
    Code:
       0: aload_0
       1: invokevirtual #7                  // Method get:()I
       4: iconst_1
       5: if_icmpeq     12
       8: iconst_1
       9: goto          13
      12: iconst_0
      13: ireturn

  public void clear();
    Code:
       0: aload_0
       1: iconst_3
       2: invokevirtual #9                  // Method lazySet:(I)V
       5: return

  public void dispose();
    Code:
       0: aload_0
       1: iconst_3
       2: invokevirtual #10                 // Method set:(I)V
       5: return

  public boolean isDisposed();
    Code:
       0: aload_0
       1: invokevirtual #7                  // Method get:()I
       4: iconst_3
       5: if_icmpne     12
       8: iconst_1
       9: goto          13
      12: iconst_0
      13: ireturn

  public int requestFusion(int);
    Code:
       0: iload_1
       1: iconst_1
       2: iand
       3: ifeq          13
       6: aload_0
       7: iconst_1
       8: invokevirtual #9                  // Method lazySet:(I)V
      11: iconst_1
      12: ireturn
      13: iconst_0
      14: ireturn

  public void run();
    Code:
       0: aload_0
       1: invokevirtual #7                  // Method get:()I
       4: ifne          51
       7: aload_0
       8: iconst_0
       9: iconst_2
      10: invokevirtual #12                 // Method compareAndSet:(II)Z
      13: ifeq          51
      16: aload_0
      17: getfield      #2                  // Field observer:Lio/reactivex/rxjava3/core/Observer;
      20: aload_0
      21: getfield      #3                  // Field value:Ljava/lang/Object;
      24: invokeinterface #13,  2           // InterfaceMethod io/reactivex/rxjava3/core/Observer.onNext:(Ljava/lang/Object;)V
      29: aload_0
      30: invokevirtual #7                  // Method get:()I
      33: iconst_2
      34: if_icmpne     51
      37: aload_0
      38: iconst_3
      39: invokevirtual #9                  // Method lazySet:(I)V
      42: aload_0
      43: getfield      #2                  // Field observer:Lio/reactivex/rxjava3/core/Observer;
      46: invokeinterface #14,  1           // InterfaceMethod io/reactivex/rxjava3/core/Observer.onComplete:()V
      51: return
}
