Compiled from "ObservableRange.java"
public final class io.reactivex.rxjava3.internal.operators.observable.ObservableRange extends io.reactivex.rxjava3.core.Observable<java.lang.Integer> {
  private final int start;

  private final long end;

  public io.reactivex.rxjava3.internal.operators.observable.ObservableRange(int, int);
    Code:
       0: aload_0
       1: invokespecial #1                  // Method io/reactivex/rxjava3/core/Observable."<init>":()V
       4: aload_0
       5: iload_1
       6: putfield      #2                  // Field start:I
       9: aload_0
      10: iload_1
      11: i2l
      12: iload_2
      13: i2l
      14: ladd
      15: putfield      #3                  // Field end:J
      18: return

  protected void subscribeActual(io.reactivex.rxjava3.core.Observer<? super java.lang.Integer>);
    Code:
       0: new           #4                  // class io/reactivex/rxjava3/internal/operators/observable/ObservableRange$RangeDisposable
       3: dup
       4: aload_1
       5: aload_0
       6: getfield      #2                  // Field start:I
       9: i2l
      10: aload_0
      11: getfield      #3                  // Field end:J
      14: invokespecial #5                  // Method io/reactivex/rxjava3/internal/operators/observable/ObservableRange$RangeDisposable."<init>":(Lio/reactivex/rxjava3/core/Observer;JJ)V
      17: astore_2
      18: aload_1
      19: aload_2
      20: invokeinterface #6,  2            // InterfaceMethod io/reactivex/rxjava3/core/Observer.onSubscribe:(Lio/reactivex/rxjava3/disposables/Disposable;)V
      25: aload_2
      26: invokevirtual #7                  // Method io/reactivex/rxjava3/internal/operators/observable/ObservableRange$RangeDisposable.run:()V
      29: return
}
