Compiled from "ObservableSampleWithObservable.java"
final class io.reactivex.rxjava3.internal.operators.observable.ObservableSampleWithObservable$SampleMainNoLast<T> extends io.reactivex.rxjava3.internal.operators.observable.ObservableSampleWithObservable$SampleMainObserver<T> {
  private static final long serialVersionUID;

  io.reactivex.rxjava3.internal.operators.observable.ObservableSampleWithObservable$SampleMainNoLast(io.reactivex.rxjava3.core.Observer<? super T>, io.reactivex.rxjava3.core.ObservableSource<?>);
    Code:
       0: aload_0
       1: aload_1
       2: aload_2
       3: invokespecial #1                  // Method io/reactivex/rxjava3/internal/operators/observable/ObservableSampleWithObservable$SampleMainObserver."<init>":(Lio/reactivex/rxjava3/core/Observer;Lio/reactivex/rxjava3/core/ObservableSource;)V
       6: return

  void completion();
    Code:
       0: aload_0
       1: getfield      #2                  // Field downstream:Lio/reactivex/rxjava3/core/Observer;
       4: invokeinterface #3,  1            // InterfaceMethod io/reactivex/rxjava3/core/Observer.onComplete:()V
       9: return

  void run();
    Code:
       0: aload_0
       1: invokevirtual #4                  // Method emit:()V
       4: return
}
