Compiled from "ObservableInternalHelper.java"
final class io.reactivex.rxjava3.internal.operators.observable.ObservableInternalHelper$MapToInt extends java.lang.Enum<io.reactivex.rxjava3.internal.operators.observable.ObservableInternalHelper$MapToInt> implements io.reactivex.rxjava3.functions.Function<java.lang.Object, java.lang.Object> {
  public static final io.reactivex.rxjava3.internal.operators.observable.ObservableInternalHelper$MapToInt INSTANCE;

  private static final io.reactivex.rxjava3.internal.operators.observable.ObservableInternalHelper$MapToInt[] $VALUES;

  public static io.reactivex.rxjava3.internal.operators.observable.ObservableInternalHelper$MapToInt[] values();
    Code:
       0: getstatic     #1                  // Field $VALUES:[Lio/reactivex/rxjava3/internal/operators/observable/ObservableInternalHelper$MapToInt;
       3: invokevirtual #2                  // Method "[Lio/reactivex/rxjava3/internal/operators/observable/ObservableInternalHelper$MapToInt;".clone:()Ljava/lang/Object;
       6: checkcast     #3                  // class "[Lio/reactivex/rxjava3/internal/operators/observable/ObservableInternalHelper$MapToInt;"
       9: areturn

  public static io.reactivex.rxjava3.internal.operators.observable.ObservableInternalHelper$MapToInt valueOf(java.lang.String);
    Code:
       0: ldc           #4                  // class io/reactivex/rxjava3/internal/operators/observable/ObservableInternalHelper$MapToInt
       2: aload_0
       3: invokestatic  #5                  // Method java/lang/Enum.valueOf:(Ljava/lang/Class;Ljava/lang/String;)Ljava/lang/Enum;
       6: checkcast     #4                  // class io/reactivex/rxjava3/internal/operators/observable/ObservableInternalHelper$MapToInt
       9: areturn

  private io.reactivex.rxjava3.internal.operators.observable.ObservableInternalHelper$MapToInt();
    Code:
       0: aload_0
       1: aload_1
       2: iload_2
       3: invokespecial #6                  // Method java/lang/Enum."<init>":(Ljava/lang/String;I)V
       6: return

  public java.lang.Object apply(java.lang.Object);
    Code:
       0: iconst_0
       1: invokestatic  #7                  // Method java/lang/Integer.valueOf:(I)Ljava/lang/Integer;
       4: areturn

  static {};
    Code:
       0: new           #4                  // class io/reactivex/rxjava3/internal/operators/observable/ObservableInternalHelper$MapToInt
       3: dup
       4: ldc           #8                  // String INSTANCE
       6: iconst_0
       7: invokespecial #9                  // Method "<init>":(Ljava/lang/String;I)V
      10: putstatic     #10                 // Field INSTANCE:Lio/reactivex/rxjava3/internal/operators/observable/ObservableInternalHelper$MapToInt;
      13: iconst_1
      14: anewarray     #4                  // class io/reactivex/rxjava3/internal/operators/observable/ObservableInternalHelper$MapToInt
      17: dup
      18: iconst_0
      19: getstatic     #10                 // Field INSTANCE:Lio/reactivex/rxjava3/internal/operators/observable/ObservableInternalHelper$MapToInt;
      22: aastore
      23: putstatic     #1                  // Field $VALUES:[Lio/reactivex/rxjava3/internal/operators/observable/ObservableInternalHelper$MapToInt;
      26: return
}
