Compiled from "ObservableWithLatestFromMany.java"
final class io.reactivex.rxjava3.internal.operators.observable.ObservableWithLatestFromMany$WithLatestFromObserver<T, R> extends java.util.concurrent.atomic.AtomicInteger implements io.reactivex.rxjava3.core.Observer<T>, io.reactivex.rxjava3.disposables.Disposable {
  private static final long serialVersionUID;

  final io.reactivex.rxjava3.core.Observer<? super R> downstream;

  final io.reactivex.rxjava3.functions.Function<? super java.lang.Object[], R> combiner;

  final io.reactivex.rxjava3.internal.operators.observable.ObservableWithLatestFromMany$WithLatestInnerObserver[] observers;

  final java.util.concurrent.atomic.AtomicReferenceArray<java.lang.Object> values;

  final java.util.concurrent.atomic.AtomicReference<io.reactivex.rxjava3.disposables.Disposable> upstream;

  final io.reactivex.rxjava3.internal.util.AtomicThrowable error;

  volatile boolean done;

  io.reactivex.rxjava3.internal.operators.observable.ObservableWithLatestFromMany$WithLatestFromObserver(io.reactivex.rxjava3.core.Observer<? super R>, io.reactivex.rxjava3.functions.Function<? super java.lang.Object[], R>, int);
    Code:
       0: aload_0
       1: invokespecial #1                  // Method java/util/concurrent/atomic/AtomicInteger."<init>":()V
       4: aload_0
       5: aload_1
       6: putfield      #2                  // Field downstream:Lio/reactivex/rxjava3/core/Observer;
       9: aload_0
      10: aload_2
      11: putfield      #3                  // Field combiner:Lio/reactivex/rxjava3/functions/Function;
      14: iload_3
      15: anewarray     #4                  // class io/reactivex/rxjava3/internal/operators/observable/ObservableWithLatestFromMany$WithLatestInnerObserver
      18: astore        4
      20: iconst_0
      21: istore        5
      23: iload         5
      25: iload_3
      26: if_icmpge     50
      29: aload         4
      31: iload         5
      33: new           #4                  // class io/reactivex/rxjava3/internal/operators/observable/ObservableWithLatestFromMany$WithLatestInnerObserver
      36: dup
      37: aload_0
      38: iload         5
      40: invokespecial #5                  // Method io/reactivex/rxjava3/internal/operators/observable/ObservableWithLatestFromMany$WithLatestInnerObserver."<init>":(Lio/reactivex/rxjava3/internal/operators/observable/ObservableWithLatestFromMany$WithLatestFromObserver;I)V
      43: aastore
      44: iinc          5, 1
      47: goto          23
      50: aload_0
      51: aload         4
      53: putfield      #6                  // Field observers:[Lio/reactivex/rxjava3/internal/operators/observable/ObservableWithLatestFromMany$WithLatestInnerObserver;
      56: aload_0
      57: new           #7                  // class java/util/concurrent/atomic/AtomicReferenceArray
      60: dup
      61: iload_3
      62: invokespecial #8                  // Method java/util/concurrent/atomic/AtomicReferenceArray."<init>":(I)V
      65: putfield      #9                  // Field values:Ljava/util/concurrent/atomic/AtomicReferenceArray;
      68: aload_0
      69: new           #10                 // class java/util/concurrent/atomic/AtomicReference
      72: dup
      73: invokespecial #11                 // Method java/util/concurrent/atomic/AtomicReference."<init>":()V
      76: putfield      #12                 // Field upstream:Ljava/util/concurrent/atomic/AtomicReference;
      79: aload_0
      80: new           #13                 // class io/reactivex/rxjava3/internal/util/AtomicThrowable
      83: dup
      84: invokespecial #14                 // Method io/reactivex/rxjava3/internal/util/AtomicThrowable."<init>":()V
      87: putfield      #15                 // Field error:Lio/reactivex/rxjava3/internal/util/AtomicThrowable;
      90: return

  void subscribe(io.reactivex.rxjava3.core.ObservableSource<?>[], int);
    Code:
       0: aload_0
       1: getfield      #6                  // Field observers:[Lio/reactivex/rxjava3/internal/operators/observable/ObservableWithLatestFromMany$WithLatestInnerObserver;
       4: astore_3
       5: aload_0
       6: getfield      #12                 // Field upstream:Ljava/util/concurrent/atomic/AtomicReference;
       9: astore        4
      11: iconst_0
      12: istore        5
      14: iload         5
      16: iload_2
      17: if_icmpge     61
      20: aload         4
      22: invokevirtual #16                 // Method java/util/concurrent/atomic/AtomicReference.get:()Ljava/lang/Object;
      25: checkcast     #17                 // class io/reactivex/rxjava3/disposables/Disposable
      28: invokestatic  #18                 // Method io/reactivex/rxjava3/internal/disposables/DisposableHelper.isDisposed:(Lio/reactivex/rxjava3/disposables/Disposable;)Z
      31: ifne          41
      34: aload_0
      35: getfield      #19                 // Field done:Z
      38: ifeq          42
      41: return
      42: aload_1
      43: iload         5
      45: aaload
      46: aload_3
      47: iload         5
      49: aaload
      50: invokeinterface #20,  2           // InterfaceMethod io/reactivex/rxjava3/core/ObservableSource.subscribe:(Lio/reactivex/rxjava3/core/Observer;)V
      55: iinc          5, 1
      58: goto          14
      61: return

  public void onSubscribe(io.reactivex.rxjava3.disposables.Disposable);
    Code:
       0: aload_0
       1: getfield      #12                 // Field upstream:Ljava/util/concurrent/atomic/AtomicReference;
       4: aload_1
       5: invokestatic  #21                 // Method io/reactivex/rxjava3/internal/disposables/DisposableHelper.setOnce:(Ljava/util/concurrent/atomic/AtomicReference;Lio/reactivex/rxjava3/disposables/Disposable;)Z
       8: pop
       9: return

  public void onNext(T);
    Code:
       0: aload_0
       1: getfield      #19                 // Field done:Z
       4: ifeq          8
       7: return
       8: aload_0
       9: getfield      #9                  // Field values:Ljava/util/concurrent/atomic/AtomicReferenceArray;
      12: astore_2
      13: aload_2
      14: invokevirtual #22                 // Method java/util/concurrent/atomic/AtomicReferenceArray.length:()I
      17: istore_3
      18: iload_3
      19: iconst_1
      20: iadd
      21: anewarray     #23                 // class java/lang/Object
      24: astore        4
      26: aload         4
      28: iconst_0
      29: aload_1
      30: aastore
      31: iconst_0
      32: istore        5
      34: iload         5
      36: iload_3
      37: if_icmpge     69
      40: aload_2
      41: iload         5
      43: invokevirtual #24                 // Method java/util/concurrent/atomic/AtomicReferenceArray.get:(I)Ljava/lang/Object;
      46: astore        6
      48: aload         6
      50: ifnonnull     54
      53: return
      54: aload         4
      56: iload         5
      58: iconst_1
      59: iadd
      60: aload         6
      62: aastore
      63: iinc          5, 1
      66: goto          34
      69: aload_0
      70: getfield      #3                  // Field combiner:Lio/reactivex/rxjava3/functions/Function;
      73: aload         4
      75: invokeinterface #25,  2           // InterfaceMethod io/reactivex/rxjava3/functions/Function.apply:(Ljava/lang/Object;)Ljava/lang/Object;
      80: ldc           #26                 // String combiner returned a null value
      82: invokestatic  #27                 // Method java/util/Objects.requireNonNull:(Ljava/lang/Object;Ljava/lang/String;)Ljava/lang/Object;
      85: astore        5
      87: goto          108
      90: astore        6
      92: aload         6
      94: invokestatic  #29                 // Method io/reactivex/rxjava3/exceptions/Exceptions.throwIfFatal:(Ljava/lang/Throwable;)V
      97: aload_0
      98: invokevirtual #30                 // Method dispose:()V
     101: aload_0
     102: aload         6
     104: invokevirtual #31                 // Method onError:(Ljava/lang/Throwable;)V
     107: return
     108: aload_0
     109: getfield      #2                  // Field downstream:Lio/reactivex/rxjava3/core/Observer;
     112: aload         5
     114: aload_0
     115: aload_0
     116: getfield      #15                 // Field error:Lio/reactivex/rxjava3/internal/util/AtomicThrowable;
     119: invokestatic  #32                 // Method io/reactivex/rxjava3/internal/util/HalfSerializer.onNext:(Lio/reactivex/rxjava3/core/Observer;Ljava/lang/Object;Ljava/util/concurrent/atomic/AtomicInteger;Lio/reactivex/rxjava3/internal/util/AtomicThrowable;)V
     122: return
    Exception table:
       from    to  target type
          69    87    90   Class java/lang/Throwable

  public void onError(java.lang.Throwable);
    Code:
       0: aload_0
       1: getfield      #19                 // Field done:Z
       4: ifeq          12
       7: aload_1
       8: invokestatic  #33                 // Method io/reactivex/rxjava3/plugins/RxJavaPlugins.onError:(Ljava/lang/Throwable;)V
      11: return
      12: aload_0
      13: iconst_1
      14: putfield      #19                 // Field done:Z
      17: aload_0
      18: iconst_m1
      19: invokevirtual #34                 // Method cancelAllBut:(I)V
      22: aload_0
      23: getfield      #2                  // Field downstream:Lio/reactivex/rxjava3/core/Observer;
      26: aload_1
      27: aload_0
      28: aload_0
      29: getfield      #15                 // Field error:Lio/reactivex/rxjava3/internal/util/AtomicThrowable;
      32: invokestatic  #35                 // Method io/reactivex/rxjava3/internal/util/HalfSerializer.onError:(Lio/reactivex/rxjava3/core/Observer;Ljava/lang/Throwable;Ljava/util/concurrent/atomic/AtomicInteger;Lio/reactivex/rxjava3/internal/util/AtomicThrowable;)V
      35: return

  public void onComplete();
    Code:
       0: aload_0
       1: getfield      #19                 // Field done:Z
       4: ifne          29
       7: aload_0
       8: iconst_1
       9: putfield      #19                 // Field done:Z
      12: aload_0
      13: iconst_m1
      14: invokevirtual #34                 // Method cancelAllBut:(I)V
      17: aload_0
      18: getfield      #2                  // Field downstream:Lio/reactivex/rxjava3/core/Observer;
      21: aload_0
      22: aload_0
      23: getfield      #15                 // Field error:Lio/reactivex/rxjava3/internal/util/AtomicThrowable;
      26: invokestatic  #36                 // Method io/reactivex/rxjava3/internal/util/HalfSerializer.onComplete:(Lio/reactivex/rxjava3/core/Observer;Ljava/util/concurrent/atomic/AtomicInteger;Lio/reactivex/rxjava3/internal/util/AtomicThrowable;)V
      29: return

  public boolean isDisposed();
    Code:
       0: aload_0
       1: getfield      #12                 // Field upstream:Ljava/util/concurrent/atomic/AtomicReference;
       4: invokevirtual #16                 // Method java/util/concurrent/atomic/AtomicReference.get:()Ljava/lang/Object;
       7: checkcast     #17                 // class io/reactivex/rxjava3/disposables/Disposable
      10: invokestatic  #18                 // Method io/reactivex/rxjava3/internal/disposables/DisposableHelper.isDisposed:(Lio/reactivex/rxjava3/disposables/Disposable;)Z
      13: ireturn

  public void dispose();
    Code:
       0: aload_0
       1: getfield      #12                 // Field upstream:Ljava/util/concurrent/atomic/AtomicReference;
       4: invokestatic  #37                 // Method io/reactivex/rxjava3/internal/disposables/DisposableHelper.dispose:(Ljava/util/concurrent/atomic/AtomicReference;)Z
       7: pop
       8: aload_0
       9: getfield      #6                  // Field observers:[Lio/reactivex/rxjava3/internal/operators/observable/ObservableWithLatestFromMany$WithLatestInnerObserver;
      12: astore_1
      13: aload_1
      14: arraylength
      15: istore_2
      16: iconst_0
      17: istore_3
      18: iload_3
      19: iload_2
      20: if_icmpge     39
      23: aload_1
      24: iload_3
      25: aaload
      26: astore        4
      28: aload         4
      30: invokevirtual #38                 // Method io/reactivex/rxjava3/internal/operators/observable/ObservableWithLatestFromMany$WithLatestInnerObserver.dispose:()V
      33: iinc          3, 1
      36: goto          18
      39: return

  void innerNext(int, java.lang.Object);
    Code:
       0: aload_0
       1: getfield      #9                  // Field values:Ljava/util/concurrent/atomic/AtomicReferenceArray;
       4: iload_1
       5: aload_2
       6: invokevirtual #39                 // Method java/util/concurrent/atomic/AtomicReferenceArray.set:(ILjava/lang/Object;)V
       9: return

  void innerError(int, java.lang.Throwable);
    Code:
       0: aload_0
       1: iconst_1
       2: putfield      #19                 // Field done:Z
       5: aload_0
       6: getfield      #12                 // Field upstream:Ljava/util/concurrent/atomic/AtomicReference;
       9: invokestatic  #37                 // Method io/reactivex/rxjava3/internal/disposables/DisposableHelper.dispose:(Ljava/util/concurrent/atomic/AtomicReference;)Z
      12: pop
      13: aload_0
      14: iload_1
      15: invokevirtual #34                 // Method cancelAllBut:(I)V
      18: aload_0
      19: getfield      #2                  // Field downstream:Lio/reactivex/rxjava3/core/Observer;
      22: aload_2
      23: aload_0
      24: aload_0
      25: getfield      #15                 // Field error:Lio/reactivex/rxjava3/internal/util/AtomicThrowable;
      28: invokestatic  #35                 // Method io/reactivex/rxjava3/internal/util/HalfSerializer.onError:(Lio/reactivex/rxjava3/core/Observer;Ljava/lang/Throwable;Ljava/util/concurrent/atomic/AtomicInteger;Lio/reactivex/rxjava3/internal/util/AtomicThrowable;)V
      31: return

  void innerComplete(int, boolean);
    Code:
       0: iload_2
       1: ifne          26
       4: aload_0
       5: iconst_1
       6: putfield      #19                 // Field done:Z
       9: aload_0
      10: iload_1
      11: invokevirtual #34                 // Method cancelAllBut:(I)V
      14: aload_0
      15: getfield      #2                  // Field downstream:Lio/reactivex/rxjava3/core/Observer;
      18: aload_0
      19: aload_0
      20: getfield      #15                 // Field error:Lio/reactivex/rxjava3/internal/util/AtomicThrowable;
      23: invokestatic  #36                 // Method io/reactivex/rxjava3/internal/util/HalfSerializer.onComplete:(Lio/reactivex/rxjava3/core/Observer;Ljava/util/concurrent/atomic/AtomicInteger;Lio/reactivex/rxjava3/internal/util/AtomicThrowable;)V
      26: return

  void cancelAllBut(int);
    Code:
       0: aload_0
       1: getfield      #6                  // Field observers:[Lio/reactivex/rxjava3/internal/operators/observable/ObservableWithLatestFromMany$WithLatestInnerObserver;
       4: astore_2
       5: iconst_0
       6: istore_3
       7: iload_3
       8: aload_2
       9: arraylength
      10: if_icmpge     30
      13: iload_3
      14: iload_1
      15: if_icmpeq     24
      18: aload_2
      19: iload_3
      20: aaload
      21: invokevirtual #38                 // Method io/reactivex/rxjava3/internal/operators/observable/ObservableWithLatestFromMany$WithLatestInnerObserver.dispose:()V
      24: iinc          3, 1
      27: goto          7
      30: return
}
