Compiled from "ObservableDelaySubscriptionOther.java"
final class io.reactivex.rxjava3.internal.operators.observable.ObservableDelaySubscriptionOther$DelayObserver$OnComplete implements io.reactivex.rxjava3.core.Observer<T> {
  final io.reactivex.rxjava3.internal.operators.observable.ObservableDelaySubscriptionOther$DelayObserver this$1;

  io.reactivex.rxjava3.internal.operators.observable.ObservableDelaySubscriptionOther$DelayObserver$OnComplete(io.reactivex.rxjava3.internal.operators.observable.ObservableDelaySubscriptionOther$DelayObserver);
    Code:
       0: aload_0
       1: aload_1
       2: putfield      #1                  // Field this$1:Lio/reactivex/rxjava3/internal/operators/observable/ObservableDelaySubscriptionOther$DelayObserver;
       5: aload_0
       6: invokespecial #2                  // Method java/lang/Object."<init>":()V
       9: return

  public void onSubscribe(io.reactivex.rxjava3.disposables.Disposable);
    Code:
       0: aload_0
       1: getfield      #1                  // Field this$1:Lio/reactivex/rxjava3/internal/operators/observable/ObservableDelaySubscriptionOther$DelayObserver;
       4: getfield      #3                  // Field io/reactivex/rxjava3/internal/operators/observable/ObservableDelaySubscriptionOther$DelayObserver.serial:Lio/reactivex/rxjava3/internal/disposables/SequentialDisposable;
       7: aload_1
       8: invokevirtual #4                  // Method io/reactivex/rxjava3/internal/disposables/SequentialDisposable.update:(Lio/reactivex/rxjava3/disposables/Disposable;)Z
      11: pop
      12: return

  public void onNext(T);
    Code:
       0: aload_0
       1: getfield      #1                  // Field this$1:Lio/reactivex/rxjava3/internal/operators/observable/ObservableDelaySubscriptionOther$DelayObserver;
       4: getfield      #5                  // Field io/reactivex/rxjava3/internal/operators/observable/ObservableDelaySubscriptionOther$DelayObserver.child:Lio/reactivex/rxjava3/core/Observer;
       7: aload_1
       8: invokeinterface #6,  2            // InterfaceMethod io/reactivex/rxjava3/core/Observer.onNext:(Ljava/lang/Object;)V
      13: return

  public void onError(java.lang.Throwable);
    Code:
       0: aload_0
       1: getfield      #1                  // Field this$1:Lio/reactivex/rxjava3/internal/operators/observable/ObservableDelaySubscriptionOther$DelayObserver;
       4: getfield      #5                  // Field io/reactivex/rxjava3/internal/operators/observable/ObservableDelaySubscriptionOther$DelayObserver.child:Lio/reactivex/rxjava3/core/Observer;
       7: aload_1
       8: invokeinterface #7,  2            // InterfaceMethod io/reactivex/rxjava3/core/Observer.onError:(Ljava/lang/Throwable;)V
      13: return

  public void onComplete();
    Code:
       0: aload_0
       1: getfield      #1                  // Field this$1:Lio/reactivex/rxjava3/internal/operators/observable/ObservableDelaySubscriptionOther$DelayObserver;
       4: getfield      #5                  // Field io/reactivex/rxjava3/internal/operators/observable/ObservableDelaySubscriptionOther$DelayObserver.child:Lio/reactivex/rxjava3/core/Observer;
       7: invokeinterface #8,  1            // InterfaceMethod io/reactivex/rxjava3/core/Observer.onComplete:()V
      12: return
}
