Compiled from "ObservableUnsubscribeOn.java"
final class io.reactivex.rxjava3.internal.operators.observable.ObservableUnsubscribeOn$UnsubscribeObserver<T> extends java.util.concurrent.atomic.AtomicBoolean implements io.reactivex.rxjava3.core.Observer<T>, io.reactivex.rxjava3.disposables.Disposable {
  private static final long serialVersionUID;

  final io.reactivex.rxjava3.core.Observer<? super T> downstream;

  final io.reactivex.rxjava3.core.Scheduler scheduler;

  io.reactivex.rxjava3.disposables.Disposable upstream;

  io.reactivex.rxjava3.internal.operators.observable.ObservableUnsubscribeOn$UnsubscribeObserver(io.reactivex.rxjava3.core.Observer<? super T>, io.reactivex.rxjava3.core.Scheduler);
    Code:
       0: aload_0
       1: invokespecial #1                  // Method java/util/concurrent/atomic/AtomicBoolean."<init>":()V
       4: aload_0
       5: aload_1
       6: putfield      #2                  // Field downstream:Lio/reactivex/rxjava3/core/Observer;
       9: aload_0
      10: aload_2
      11: putfield      #3                  // Field scheduler:Lio/reactivex/rxjava3/core/Scheduler;
      14: return

  public void onSubscribe(io.reactivex.rxjava3.disposables.Disposable);
    Code:
       0: aload_0
       1: getfield      #4                  // Field upstream:Lio/reactivex/rxjava3/disposables/Disposable;
       4: aload_1
       5: invokestatic  #5                  // Method io/reactivex/rxjava3/internal/disposables/DisposableHelper.validate:(Lio/reactivex/rxjava3/disposables/Disposable;Lio/reactivex/rxjava3/disposables/Disposable;)Z
       8: ifeq          26
      11: aload_0
      12: aload_1
      13: putfield      #4                  // Field upstream:Lio/reactivex/rxjava3/disposables/Disposable;
      16: aload_0
      17: getfield      #2                  // Field downstream:Lio/reactivex/rxjava3/core/Observer;
      20: aload_0
      21: invokeinterface #6,  2            // InterfaceMethod io/reactivex/rxjava3/core/Observer.onSubscribe:(Lio/reactivex/rxjava3/disposables/Disposable;)V
      26: return

  public void onNext(T);
    Code:
       0: aload_0
       1: invokevirtual #7                  // Method get:()Z
       4: ifne          17
       7: aload_0
       8: getfield      #2                  // Field downstream:Lio/reactivex/rxjava3/core/Observer;
      11: aload_1
      12: invokeinterface #8,  2            // InterfaceMethod io/reactivex/rxjava3/core/Observer.onNext:(Ljava/lang/Object;)V
      17: return

  public void onError(java.lang.Throwable);
    Code:
       0: aload_0
       1: invokevirtual #7                  // Method get:()Z
       4: ifeq          12
       7: aload_1
       8: invokestatic  #9                  // Method io/reactivex/rxjava3/plugins/RxJavaPlugins.onError:(Ljava/lang/Throwable;)V
      11: return
      12: aload_0
      13: getfield      #2                  // Field downstream:Lio/reactivex/rxjava3/core/Observer;
      16: aload_1
      17: invokeinterface #10,  2           // InterfaceMethod io/reactivex/rxjava3/core/Observer.onError:(Ljava/lang/Throwable;)V
      22: return

  public void onComplete();
    Code:
       0: aload_0
       1: invokevirtual #7                  // Method get:()Z
       4: ifne          16
       7: aload_0
       8: getfield      #2                  // Field downstream:Lio/reactivex/rxjava3/core/Observer;
      11: invokeinterface #11,  1           // InterfaceMethod io/reactivex/rxjava3/core/Observer.onComplete:()V
      16: return

  public void dispose();
    Code:
       0: aload_0
       1: iconst_0
       2: iconst_1
       3: invokevirtual #12                 // Method compareAndSet:(ZZ)Z
       6: ifeq          25
       9: aload_0
      10: getfield      #3                  // Field scheduler:Lio/reactivex/rxjava3/core/Scheduler;
      13: new           #13                 // class io/reactivex/rxjava3/internal/operators/observable/ObservableUnsubscribeOn$UnsubscribeObserver$DisposeTask
      16: dup
      17: aload_0
      18: invokespecial #14                 // Method io/reactivex/rxjava3/internal/operators/observable/ObservableUnsubscribeOn$UnsubscribeObserver$DisposeTask."<init>":(Lio/reactivex/rxjava3/internal/operators/observable/ObservableUnsubscribeOn$UnsubscribeObserver;)V
      21: invokevirtual #15                 // Method io/reactivex/rxjava3/core/Scheduler.scheduleDirect:(Ljava/lang/Runnable;)Lio/reactivex/rxjava3/disposables/Disposable;
      24: pop
      25: return

  public boolean isDisposed();
    Code:
       0: aload_0
       1: invokevirtual #7                  // Method get:()Z
       4: ireturn
}
