Compiled from "ObservableCombineLatest.java"
final class io.reactivex.rxjava3.internal.operators.observable.ObservableCombineLatest$LatestCoordinator<T, R> extends java.util.concurrent.atomic.AtomicInteger implements io.reactivex.rxjava3.disposables.Disposable {
  private static final long serialVersionUID;

  final io.reactivex.rxjava3.core.Observer<? super R> downstream;

  final io.reactivex.rxjava3.functions.Function<? super java.lang.Object[], ? extends R> combiner;

  final io.reactivex.rxjava3.internal.operators.observable.ObservableCombineLatest$CombinerObserver<T, R>[] observers;

  java.lang.Object[] latest;

  final io.reactivex.rxjava3.operators.SpscLinkedArrayQueue<java.lang.Object[]> queue;

  final boolean delayError;

  volatile boolean cancelled;

  volatile boolean done;

  final io.reactivex.rxjava3.internal.util.AtomicThrowable errors;

  int active;

  int complete;

  io.reactivex.rxjava3.internal.operators.observable.ObservableCombineLatest$LatestCoordinator(io.reactivex.rxjava3.core.Observer<? super R>, io.reactivex.rxjava3.functions.Function<? super java.lang.Object[], ? extends R>, int, int, boolean);
    Code:
       0: aload_0
       1: invokespecial #1                  // Method java/util/concurrent/atomic/AtomicInteger."<init>":()V
       4: aload_0
       5: new           #2                  // class io/reactivex/rxjava3/internal/util/AtomicThrowable
       8: dup
       9: invokespecial #3                  // Method io/reactivex/rxjava3/internal/util/AtomicThrowable."<init>":()V
      12: putfield      #4                  // Field errors:Lio/reactivex/rxjava3/internal/util/AtomicThrowable;
      15: aload_0
      16: aload_1
      17: putfield      #5                  // Field downstream:Lio/reactivex/rxjava3/core/Observer;
      20: aload_0
      21: aload_2
      22: putfield      #6                  // Field combiner:Lio/reactivex/rxjava3/functions/Function;
      25: aload_0
      26: iload         5
      28: putfield      #7                  // Field delayError:Z
      31: aload_0
      32: iload_3
      33: anewarray     #8                  // class java/lang/Object
      36: putfield      #9                  // Field latest:[Ljava/lang/Object;
      39: iload_3
      40: anewarray     #10                 // class io/reactivex/rxjava3/internal/operators/observable/ObservableCombineLatest$CombinerObserver
      43: astore        6
      45: iconst_0
      46: istore        7
      48: iload         7
      50: iload_3
      51: if_icmpge     75
      54: aload         6
      56: iload         7
      58: new           #10                 // class io/reactivex/rxjava3/internal/operators/observable/ObservableCombineLatest$CombinerObserver
      61: dup
      62: aload_0
      63: iload         7
      65: invokespecial #11                 // Method io/reactivex/rxjava3/internal/operators/observable/ObservableCombineLatest$CombinerObserver."<init>":(Lio/reactivex/rxjava3/internal/operators/observable/ObservableCombineLatest$LatestCoordinator;I)V
      68: aastore
      69: iinc          7, 1
      72: goto          48
      75: aload_0
      76: aload         6
      78: putfield      #12                 // Field observers:[Lio/reactivex/rxjava3/internal/operators/observable/ObservableCombineLatest$CombinerObserver;
      81: aload_0
      82: new           #13                 // class io/reactivex/rxjava3/operators/SpscLinkedArrayQueue
      85: dup
      86: iload         4
      88: invokespecial #14                 // Method io/reactivex/rxjava3/operators/SpscLinkedArrayQueue."<init>":(I)V
      91: putfield      #15                 // Field queue:Lio/reactivex/rxjava3/operators/SpscLinkedArrayQueue;
      94: return

  public void subscribe(io.reactivex.rxjava3.core.ObservableSource<? extends T>[]);
    Code:
       0: aload_0
       1: getfield      #12                 // Field observers:[Lio/reactivex/rxjava3/internal/operators/observable/ObservableCombineLatest$CombinerObserver;
       4: astore_2
       5: aload_2
       6: arraylength
       7: istore_3
       8: aload_0
       9: getfield      #5                  // Field downstream:Lio/reactivex/rxjava3/core/Observer;
      12: aload_0
      13: invokeinterface #16,  2           // InterfaceMethod io/reactivex/rxjava3/core/Observer.onSubscribe:(Lio/reactivex/rxjava3/disposables/Disposable;)V
      18: iconst_0
      19: istore        4
      21: iload         4
      23: iload_3
      24: if_icmpge     61
      27: aload_0
      28: getfield      #17                 // Field done:Z
      31: ifne          41
      34: aload_0
      35: getfield      #18                 // Field cancelled:Z
      38: ifeq          42
      41: return
      42: aload_1
      43: iload         4
      45: aaload
      46: aload_2
      47: iload         4
      49: aaload
      50: invokeinterface #19,  2           // InterfaceMethod io/reactivex/rxjava3/core/ObservableSource.subscribe:(Lio/reactivex/rxjava3/core/Observer;)V
      55: iinc          4, 1
      58: goto          21
      61: return

  public void dispose();
    Code:
       0: aload_0
       1: getfield      #18                 // Field cancelled:Z
       4: ifne          20
       7: aload_0
       8: iconst_1
       9: putfield      #18                 // Field cancelled:Z
      12: aload_0
      13: invokevirtual #20                 // Method cancelSources:()V
      16: aload_0
      17: invokevirtual #21                 // Method drain:()V
      20: return

  public boolean isDisposed();
    Code:
       0: aload_0
       1: getfield      #18                 // Field cancelled:Z
       4: ireturn

  void cancelSources();
    Code:
       0: aload_0
       1: getfield      #12                 // Field observers:[Lio/reactivex/rxjava3/internal/operators/observable/ObservableCombineLatest$CombinerObserver;
       4: astore_1
       5: aload_1
       6: arraylength
       7: istore_2
       8: iconst_0
       9: istore_3
      10: iload_3
      11: iload_2
      12: if_icmpge     31
      15: aload_1
      16: iload_3
      17: aaload
      18: astore        4
      20: aload         4
      22: invokevirtual #22                 // Method io/reactivex/rxjava3/internal/operators/observable/ObservableCombineLatest$CombinerObserver.dispose:()V
      25: iinc          3, 1
      28: goto          10
      31: return

  void clear(io.reactivex.rxjava3.operators.SpscLinkedArrayQueue<?>);
    Code:
       0: aload_0
       1: dup
       2: astore_2
       3: monitorenter
       4: aload_0
       5: aconst_null
       6: putfield      #9                  // Field latest:[Ljava/lang/Object;
       9: aload_2
      10: monitorexit
      11: goto          19
      14: astore_3
      15: aload_2
      16: monitorexit
      17: aload_3
      18: athrow
      19: aload_1
      20: invokevirtual #23                 // Method io/reactivex/rxjava3/operators/SpscLinkedArrayQueue.clear:()V
      23: return
    Exception table:
       from    to  target type
           4    11    14   any
          14    17    14   any

  void drain();
    Code:
       0: aload_0
       1: invokevirtual #24                 // Method getAndIncrement:()I
       4: ifeq          8
       7: return
       8: aload_0
       9: getfield      #15                 // Field queue:Lio/reactivex/rxjava3/operators/SpscLinkedArrayQueue;
      12: astore_1
      13: aload_0
      14: getfield      #5                  // Field downstream:Lio/reactivex/rxjava3/core/Observer;
      17: astore_2
      18: aload_0
      19: getfield      #7                  // Field delayError:Z
      22: istore_3
      23: iconst_1
      24: istore        4
      26: aload_0
      27: getfield      #18                 // Field cancelled:Z
      30: ifeq          46
      33: aload_0
      34: aload_1
      35: invokevirtual #25                 // Method clear:(Lio/reactivex/rxjava3/operators/SpscLinkedArrayQueue;)V
      38: aload_0
      39: getfield      #4                  // Field errors:Lio/reactivex/rxjava3/internal/util/AtomicThrowable;
      42: invokevirtual #26                 // Method io/reactivex/rxjava3/internal/util/AtomicThrowable.tryTerminateAndReport:()V
      45: return
      46: iload_3
      47: ifne          78
      50: aload_0
      51: getfield      #4                  // Field errors:Lio/reactivex/rxjava3/internal/util/AtomicThrowable;
      54: invokevirtual #27                 // Method io/reactivex/rxjava3/internal/util/AtomicThrowable.get:()Ljava/lang/Object;
      57: ifnull        78
      60: aload_0
      61: invokevirtual #20                 // Method cancelSources:()V
      64: aload_0
      65: aload_1
      66: invokevirtual #25                 // Method clear:(Lio/reactivex/rxjava3/operators/SpscLinkedArrayQueue;)V
      69: aload_0
      70: getfield      #4                  // Field errors:Lio/reactivex/rxjava3/internal/util/AtomicThrowable;
      73: aload_2
      74: invokevirtual #28                 // Method io/reactivex/rxjava3/internal/util/AtomicThrowable.tryTerminateConsumer:(Lio/reactivex/rxjava3/core/Observer;)V
      77: return
      78: aload_0
      79: getfield      #17                 // Field done:Z
      82: istore        5
      84: aload_1
      85: invokevirtual #29                 // Method io/reactivex/rxjava3/operators/SpscLinkedArrayQueue.poll:()Ljava/lang/Object;
      88: checkcast     #30                 // class "[Ljava/lang/Object;"
      91: astore        6
      93: aload         6
      95: ifnonnull     102
      98: iconst_1
      99: goto          103
     102: iconst_0
     103: istore        7
     105: iload         5
     107: ifeq          129
     110: iload         7
     112: ifeq          129
     115: aload_0
     116: aload_1
     117: invokevirtual #25                 // Method clear:(Lio/reactivex/rxjava3/operators/SpscLinkedArrayQueue;)V
     120: aload_0
     121: getfield      #4                  // Field errors:Lio/reactivex/rxjava3/internal/util/AtomicThrowable;
     124: aload_2
     125: invokevirtual #28                 // Method io/reactivex/rxjava3/internal/util/AtomicThrowable.tryTerminateConsumer:(Lio/reactivex/rxjava3/core/Observer;)V
     128: return
     129: iload         7
     131: ifeq          137
     134: goto          204
     137: aload_0
     138: getfield      #6                  // Field combiner:Lio/reactivex/rxjava3/functions/Function;
     141: aload         6
     143: invokeinterface #31,  2           // InterfaceMethod io/reactivex/rxjava3/functions/Function.apply:(Ljava/lang/Object;)Ljava/lang/Object;
     148: ldc           #32                 // String The combiner returned a null value
     150: invokestatic  #33                 // Method java/util/Objects.requireNonNull:(Ljava/lang/Object;Ljava/lang/String;)Ljava/lang/Object;
     153: astore        8
     155: goto          193
     158: astore        9
     160: aload         9
     162: invokestatic  #35                 // Method io/reactivex/rxjava3/exceptions/Exceptions.throwIfFatal:(Ljava/lang/Throwable;)V
     165: aload_0
     166: getfield      #4                  // Field errors:Lio/reactivex/rxjava3/internal/util/AtomicThrowable;
     169: aload         9
     171: invokevirtual #36                 // Method io/reactivex/rxjava3/internal/util/AtomicThrowable.tryAddThrowableOrReport:(Ljava/lang/Throwable;)Z
     174: pop
     175: aload_0
     176: invokevirtual #20                 // Method cancelSources:()V
     179: aload_0
     180: aload_1
     181: invokevirtual #25                 // Method clear:(Lio/reactivex/rxjava3/operators/SpscLinkedArrayQueue;)V
     184: aload_0
     185: getfield      #4                  // Field errors:Lio/reactivex/rxjava3/internal/util/AtomicThrowable;
     188: aload_2
     189: invokevirtual #28                 // Method io/reactivex/rxjava3/internal/util/AtomicThrowable.tryTerminateConsumer:(Lio/reactivex/rxjava3/core/Observer;)V
     192: return
     193: aload_2
     194: aload         8
     196: invokeinterface #37,  2           // InterfaceMethod io/reactivex/rxjava3/core/Observer.onNext:(Ljava/lang/Object;)V
     201: goto          26
     204: aload_0
     205: iload         4
     207: ineg
     208: invokevirtual #38                 // Method addAndGet:(I)I
     211: istore        4
     213: iload         4
     215: ifne          26
     218: goto          221
     221: return
    Exception table:
       from    to  target type
         137   155   158   Class java/lang/Throwable

  void innerNext(int, T);
    Code:
       0: iconst_0
       1: istore_3
       2: aload_0
       3: dup
       4: astore        4
       6: monitorenter
       7: aload_0
       8: getfield      #9                  // Field latest:[Ljava/lang/Object;
      11: astore        5
      13: aload         5
      15: ifnonnull     22
      18: aload         4
      20: monitorexit
      21: return
      22: aload         5
      24: iload_1
      25: aaload
      26: astore        6
      28: aload_0
      29: getfield      #39                 // Field active:I
      32: istore        7
      34: aload         6
      36: ifnonnull     48
      39: aload_0
      40: iinc          7, 1
      43: iload         7
      45: putfield      #39                 // Field active:I
      48: aload         5
      50: iload_1
      51: aload_2
      52: aastore
      53: iload         7
      55: aload         5
      57: arraylength
      58: if_icmpne     76
      61: aload_0
      62: getfield      #15                 // Field queue:Lio/reactivex/rxjava3/operators/SpscLinkedArrayQueue;
      65: aload         5
      67: invokevirtual #40                 // Method "[Ljava/lang/Object;".clone:()Ljava/lang/Object;
      70: invokevirtual #41                 // Method io/reactivex/rxjava3/operators/SpscLinkedArrayQueue.offer:(Ljava/lang/Object;)Z
      73: pop
      74: iconst_1
      75: istore_3
      76: aload         4
      78: monitorexit
      79: goto          90
      82: astore        8
      84: aload         4
      86: monitorexit
      87: aload         8
      89: athrow
      90: iload_3
      91: ifeq          98
      94: aload_0
      95: invokevirtual #21                 // Method drain:()V
      98: return
    Exception table:
       from    to  target type
           7    21    82   any
          22    79    82   any
          82    87    82   any

  void innerError(int, java.lang.Throwable);
    Code:
       0: aload_0
       1: getfield      #4                  // Field errors:Lio/reactivex/rxjava3/internal/util/AtomicThrowable;
       4: aload_2
       5: invokevirtual #36                 // Method io/reactivex/rxjava3/internal/util/AtomicThrowable.tryAddThrowableOrReport:(Ljava/lang/Throwable;)Z
       8: ifeq          105
      11: iconst_1
      12: istore_3
      13: aload_0
      14: getfield      #7                  // Field delayError:Z
      17: ifeq          93
      20: aload_0
      21: dup
      22: astore        4
      24: monitorenter
      25: aload_0
      26: getfield      #9                  // Field latest:[Ljava/lang/Object;
      29: astore        5
      31: aload         5
      33: ifnonnull     40
      36: aload         4
      38: monitorexit
      39: return
      40: aload         5
      42: iload_1
      43: aaload
      44: ifnonnull     51
      47: iconst_1
      48: goto          52
      51: iconst_0
      52: istore_3
      53: iload_3
      54: ifne          74
      57: aload_0
      58: dup
      59: getfield      #42                 // Field complete:I
      62: iconst_1
      63: iadd
      64: dup_x1
      65: putfield      #42                 // Field complete:I
      68: aload         5
      70: arraylength
      71: if_icmpne     79
      74: aload_0
      75: iconst_1
      76: putfield      #17                 // Field done:Z
      79: aload         4
      81: monitorexit
      82: goto          93
      85: astore        6
      87: aload         4
      89: monitorexit
      90: aload         6
      92: athrow
      93: iload_3
      94: ifeq          101
      97: aload_0
      98: invokevirtual #20                 // Method cancelSources:()V
     101: aload_0
     102: invokevirtual #21                 // Method drain:()V
     105: return
    Exception table:
       from    to  target type
          25    39    85   any
          40    82    85   any
          85    90    85   any

  void innerComplete(int);
    Code:
       0: iconst_0
       1: istore_2
       2: aload_0
       3: dup
       4: astore_3
       5: monitorenter
       6: aload_0
       7: getfield      #9                  // Field latest:[Ljava/lang/Object;
      10: astore        4
      12: aload         4
      14: ifnonnull     20
      17: aload_3
      18: monitorexit
      19: return
      20: aload         4
      22: iload_1
      23: aaload
      24: ifnonnull     31
      27: iconst_1
      28: goto          32
      31: iconst_0
      32: istore_2
      33: iload_2
      34: ifne          54
      37: aload_0
      38: dup
      39: getfield      #42                 // Field complete:I
      42: iconst_1
      43: iadd
      44: dup_x1
      45: putfield      #42                 // Field complete:I
      48: aload         4
      50: arraylength
      51: if_icmpne     59
      54: aload_0
      55: iconst_1
      56: putfield      #17                 // Field done:Z
      59: aload_3
      60: monitorexit
      61: goto          71
      64: astore        5
      66: aload_3
      67: monitorexit
      68: aload         5
      70: athrow
      71: iload_2
      72: ifeq          79
      75: aload_0
      76: invokevirtual #20                 // Method cancelSources:()V
      79: aload_0
      80: invokevirtual #21                 // Method drain:()V
      83: return
    Exception table:
       from    to  target type
           6    19    64   any
          20    61    64   any
          64    68    64   any
}
