Compiled from "ObservableTakeLast.java"
final class io.reactivex.rxjava3.internal.operators.observable.ObservableTakeLast$TakeLastObserver<T> extends java.util.ArrayDeque<T> implements io.reactivex.rxjava3.core.Observer<T>, io.reactivex.rxjava3.disposables.Disposable {
  private static final long serialVersionUID;

  final io.reactivex.rxjava3.core.Observer<? super T> downstream;

  final int count;

  io.reactivex.rxjava3.disposables.Disposable upstream;

  volatile boolean cancelled;

  io.reactivex.rxjava3.internal.operators.observable.ObservableTakeLast$TakeLastObserver(io.reactivex.rxjava3.core.Observer<? super T>, int);
    Code:
       0: aload_0
       1: invokespecial #1                  // Method java/util/ArrayDeque."<init>":()V
       4: aload_0
       5: aload_1
       6: putfield      #2                  // Field downstream:Lio/reactivex/rxjava3/core/Observer;
       9: aload_0
      10: iload_2
      11: putfield      #3                  // Field count:I
      14: return

  public void onSubscribe(io.reactivex.rxjava3.disposables.Disposable);
    Code:
       0: aload_0
       1: getfield      #4                  // Field upstream:Lio/reactivex/rxjava3/disposables/Disposable;
       4: aload_1
       5: invokestatic  #5                  // Method io/reactivex/rxjava3/internal/disposables/DisposableHelper.validate:(Lio/reactivex/rxjava3/disposables/Disposable;Lio/reactivex/rxjava3/disposables/Disposable;)Z
       8: ifeq          26
      11: aload_0
      12: aload_1
      13: putfield      #4                  // Field upstream:Lio/reactivex/rxjava3/disposables/Disposable;
      16: aload_0
      17: getfield      #2                  // Field downstream:Lio/reactivex/rxjava3/core/Observer;
      20: aload_0
      21: invokeinterface #6,  2            // InterfaceMethod io/reactivex/rxjava3/core/Observer.onSubscribe:(Lio/reactivex/rxjava3/disposables/Disposable;)V
      26: return

  public void onNext(T);
    Code:
       0: aload_0
       1: getfield      #3                  // Field count:I
       4: aload_0
       5: invokevirtual #7                  // Method size:()I
       8: if_icmpne     16
      11: aload_0
      12: invokevirtual #8                  // Method poll:()Ljava/lang/Object;
      15: pop
      16: aload_0
      17: aload_1
      18: invokevirtual #9                  // Method offer:(Ljava/lang/Object;)Z
      21: pop
      22: return

  public void onError(java.lang.Throwable);
    Code:
       0: aload_0
       1: getfield      #2                  // Field downstream:Lio/reactivex/rxjava3/core/Observer;
       4: aload_1
       5: invokeinterface #10,  2           // InterfaceMethod io/reactivex/rxjava3/core/Observer.onError:(Ljava/lang/Throwable;)V
      10: return

  public void onComplete();
    Code:
       0: aload_0
       1: getfield      #2                  // Field downstream:Lio/reactivex/rxjava3/core/Observer;
       4: astore_1
       5: aload_0
       6: getfield      #11                 // Field cancelled:Z
       9: ifeq          13
      12: return
      13: aload_0
      14: invokevirtual #8                  // Method poll:()Ljava/lang/Object;
      17: astore_2
      18: aload_2
      19: ifnonnull     29
      22: aload_1
      23: invokeinterface #12,  1           // InterfaceMethod io/reactivex/rxjava3/core/Observer.onComplete:()V
      28: return
      29: aload_1
      30: aload_2
      31: invokeinterface #13,  2           // InterfaceMethod io/reactivex/rxjava3/core/Observer.onNext:(Ljava/lang/Object;)V
      36: goto          5

  public void dispose();
    Code:
       0: aload_0
       1: getfield      #11                 // Field cancelled:Z
       4: ifne          21
       7: aload_0
       8: iconst_1
       9: putfield      #11                 // Field cancelled:Z
      12: aload_0
      13: getfield      #4                  // Field upstream:Lio/reactivex/rxjava3/disposables/Disposable;
      16: invokeinterface #14,  1           // InterfaceMethod io/reactivex/rxjava3/disposables/Disposable.dispose:()V
      21: return

  public boolean isDisposed();
    Code:
       0: aload_0
       1: getfield      #11                 // Field cancelled:Z
       4: ireturn
}
