Compiled from "ObservableGroupJoin.java"
final class io.reactivex.rxjava3.internal.operators.observable.ObservableGroupJoin$LeftRightEndObserver extends java.util.concurrent.atomic.AtomicReference<io.reactivex.rxjava3.disposables.Disposable> implements io.reactivex.rxjava3.core.Observer<java.lang.Object>, io.reactivex.rxjava3.disposables.Disposable {
  private static final long serialVersionUID;

  final io.reactivex.rxjava3.internal.operators.observable.ObservableGroupJoin$JoinSupport parent;

  final boolean isLeft;

  final int index;

  io.reactivex.rxjava3.internal.operators.observable.ObservableGroupJoin$LeftRightEndObserver(io.reactivex.rxjava3.internal.operators.observable.ObservableGroupJoin$JoinSupport, boolean, int);
    Code:
       0: aload_0
       1: invokespecial #1                  // Method java/util/concurrent/atomic/AtomicReference."<init>":()V
       4: aload_0
       5: aload_1
       6: putfield      #2                  // Field parent:Lio/reactivex/rxjava3/internal/operators/observable/ObservableGroupJoin$JoinSupport;
       9: aload_0
      10: iload_2
      11: putfield      #3                  // Field isLeft:Z
      14: aload_0
      15: iload_3
      16: putfield      #4                  // Field index:I
      19: return

  public void dispose();
    Code:
       0: aload_0
       1: invokestatic  #5                  // Method io/reactivex/rxjava3/internal/disposables/DisposableHelper.dispose:(Ljava/util/concurrent/atomic/AtomicReference;)Z
       4: pop
       5: return

  public boolean isDisposed();
    Code:
       0: aload_0
       1: invokevirtual #6                  // Method get:()Ljava/lang/Object;
       4: checkcast     #7                  // class io/reactivex/rxjava3/disposables/Disposable
       7: invokestatic  #8                  // Method io/reactivex/rxjava3/internal/disposables/DisposableHelper.isDisposed:(Lio/reactivex/rxjava3/disposables/Disposable;)Z
      10: ireturn

  public void onSubscribe(io.reactivex.rxjava3.disposables.Disposable);
    Code:
       0: aload_0
       1: aload_1
       2: invokestatic  #9                  // Method io/reactivex/rxjava3/internal/disposables/DisposableHelper.setOnce:(Ljava/util/concurrent/atomic/AtomicReference;Lio/reactivex/rxjava3/disposables/Disposable;)Z
       5: pop
       6: return

  public void onNext(java.lang.Object);
    Code:
       0: aload_0
       1: invokestatic  #5                  // Method io/reactivex/rxjava3/internal/disposables/DisposableHelper.dispose:(Ljava/util/concurrent/atomic/AtomicReference;)Z
       4: ifeq          21
       7: aload_0
       8: getfield      #2                  // Field parent:Lio/reactivex/rxjava3/internal/operators/observable/ObservableGroupJoin$JoinSupport;
      11: aload_0
      12: getfield      #3                  // Field isLeft:Z
      15: aload_0
      16: invokeinterface #10,  3           // InterfaceMethod io/reactivex/rxjava3/internal/operators/observable/ObservableGroupJoin$JoinSupport.innerClose:(ZLio/reactivex/rxjava3/internal/operators/observable/ObservableGroupJoin$LeftRightEndObserver;)V
      21: return

  public void onError(java.lang.Throwable);
    Code:
       0: aload_0
       1: getfield      #2                  // Field parent:Lio/reactivex/rxjava3/internal/operators/observable/ObservableGroupJoin$JoinSupport;
       4: aload_1
       5: invokeinterface #11,  2           // InterfaceMethod io/reactivex/rxjava3/internal/operators/observable/ObservableGroupJoin$JoinSupport.innerCloseError:(Ljava/lang/Throwable;)V
      10: return

  public void onComplete();
    Code:
       0: aload_0
       1: getfield      #2                  // Field parent:Lio/reactivex/rxjava3/internal/operators/observable/ObservableGroupJoin$JoinSupport;
       4: aload_0
       5: getfield      #3                  // Field isLeft:Z
       8: aload_0
       9: invokeinterface #10,  3           // InterfaceMethod io/reactivex/rxjava3/internal/operators/observable/ObservableGroupJoin$JoinSupport.innerClose:(ZLio/reactivex/rxjava3/internal/operators/observable/ObservableGroupJoin$LeftRightEndObserver;)V
      14: return
}
