Compiled from "ObservableDelay.java"
public final class io.reactivex.rxjava3.internal.operators.observable.ObservableDelay<T> extends io.reactivex.rxjava3.internal.operators.observable.AbstractObservableWithUpstream<T, T> {
  final long delay;

  final java.util.concurrent.TimeUnit unit;

  final io.reactivex.rxjava3.core.Scheduler scheduler;

  final boolean delayError;

  public io.reactivex.rxjava3.internal.operators.observable.ObservableDelay(io.reactivex.rxjava3.core.ObservableSource<T>, long, java.util.concurrent.TimeUnit, io.reactivex.rxjava3.core.Scheduler, boolean);
    Code:
       0: aload_0
       1: aload_1
       2: invokespecial #1                  // Method io/reactivex/rxjava3/internal/operators/observable/AbstractObservableWithUpstream."<init>":(Lio/reactivex/rxjava3/core/ObservableSource;)V
       5: aload_0
       6: lload_2
       7: putfield      #2                  // Field delay:J
      10: aload_0
      11: aload         4
      13: putfield      #3                  // Field unit:Ljava/util/concurrent/TimeUnit;
      16: aload_0
      17: aload         5
      19: putfield      #4                  // Field scheduler:Lio/reactivex/rxjava3/core/Scheduler;
      22: aload_0
      23: iload         6
      25: putfield      #5                  // Field delayError:Z
      28: return

  public void subscribeActual(io.reactivex.rxjava3.core.Observer<? super T>);
    Code:
       0: aload_0
       1: getfield      #5                  // Field delayError:Z
       4: ifeq          12
       7: aload_1
       8: astore_2
       9: goto          21
      12: new           #6                  // class io/reactivex/rxjava3/observers/SerializedObserver
      15: dup
      16: aload_1
      17: invokespecial #7                  // Method io/reactivex/rxjava3/observers/SerializedObserver."<init>":(Lio/reactivex/rxjava3/core/Observer;)V
      20: astore_2
      21: aload_0
      22: getfield      #4                  // Field scheduler:Lio/reactivex/rxjava3/core/Scheduler;
      25: invokevirtual #8                  // Method io/reactivex/rxjava3/core/Scheduler.createWorker:()Lio/reactivex/rxjava3/core/Scheduler$Worker;
      28: astore_3
      29: aload_0
      30: getfield      #9                  // Field source:Lio/reactivex/rxjava3/core/ObservableSource;
      33: new           #10                 // class io/reactivex/rxjava3/internal/operators/observable/ObservableDelay$DelayObserver
      36: dup
      37: aload_2
      38: aload_0
      39: getfield      #2                  // Field delay:J
      42: aload_0
      43: getfield      #3                  // Field unit:Ljava/util/concurrent/TimeUnit;
      46: aload_3
      47: aload_0
      48: getfield      #5                  // Field delayError:Z
      51: invokespecial #11                 // Method io/reactivex/rxjava3/internal/operators/observable/ObservableDelay$DelayObserver."<init>":(Lio/reactivex/rxjava3/core/Observer;JLjava/util/concurrent/TimeUnit;Lio/reactivex/rxjava3/core/Scheduler$Worker;Z)V
      54: invokeinterface #12,  2           // InterfaceMethod io/reactivex/rxjava3/core/ObservableSource.subscribe:(Lio/reactivex/rxjava3/core/Observer;)V
      59: return
}
