Compiled from "ObservableDebounce.java"
final class io.reactivex.rxjava3.internal.operators.observable.ObservableDebounce$DebounceObserver<T, U> implements io.reactivex.rxjava3.core.Observer<T>, io.reactivex.rxjava3.disposables.Disposable {
  final io.reactivex.rxjava3.core.Observer<? super T> downstream;

  final io.reactivex.rxjava3.functions.Function<? super T, ? extends io.reactivex.rxjava3.core.ObservableSource<U>> debounceSelector;

  io.reactivex.rxjava3.disposables.Disposable upstream;

  final java.util.concurrent.atomic.AtomicReference<io.reactivex.rxjava3.disposables.Disposable> debouncer;

  volatile long index;

  boolean done;

  io.reactivex.rxjava3.internal.operators.observable.ObservableDebounce$DebounceObserver(io.reactivex.rxjava3.core.Observer<? super T>, io.reactivex.rxjava3.functions.Function<? super T, ? extends io.reactivex.rxjava3.core.ObservableSource<U>>);
    Code:
       0: aload_0
       1: invokespecial #1                  // Method java/lang/Object."<init>":()V
       4: aload_0
       5: new           #2                  // class java/util/concurrent/atomic/AtomicReference
       8: dup
       9: invokespecial #3                  // Method java/util/concurrent/atomic/AtomicReference."<init>":()V
      12: putfield      #4                  // Field debouncer:Ljava/util/concurrent/atomic/AtomicReference;
      15: aload_0
      16: aload_1
      17: putfield      #5                  // Field downstream:Lio/reactivex/rxjava3/core/Observer;
      20: aload_0
      21: aload_2
      22: putfield      #6                  // Field debounceSelector:Lio/reactivex/rxjava3/functions/Function;
      25: return

  public void onSubscribe(io.reactivex.rxjava3.disposables.Disposable);
    Code:
       0: aload_0
       1: getfield      #7                  // Field upstream:Lio/reactivex/rxjava3/disposables/Disposable;
       4: aload_1
       5: invokestatic  #8                  // Method io/reactivex/rxjava3/internal/disposables/DisposableHelper.validate:(Lio/reactivex/rxjava3/disposables/Disposable;Lio/reactivex/rxjava3/disposables/Disposable;)Z
       8: ifeq          26
      11: aload_0
      12: aload_1
      13: putfield      #7                  // Field upstream:Lio/reactivex/rxjava3/disposables/Disposable;
      16: aload_0
      17: getfield      #5                  // Field downstream:Lio/reactivex/rxjava3/core/Observer;
      20: aload_0
      21: invokeinterface #9,  2            // InterfaceMethod io/reactivex/rxjava3/core/Observer.onSubscribe:(Lio/reactivex/rxjava3/disposables/Disposable;)V
      26: return

  public void onNext(T);
    Code:
       0: aload_0
       1: getfield      #10                 // Field done:Z
       4: ifeq          8
       7: return
       8: aload_0
       9: getfield      #11                 // Field index:J
      12: lconst_1
      13: ladd
      14: lstore_2
      15: aload_0
      16: lload_2
      17: putfield      #11                 // Field index:J
      20: aload_0
      21: getfield      #4                  // Field debouncer:Ljava/util/concurrent/atomic/AtomicReference;
      24: invokevirtual #12                 // Method java/util/concurrent/atomic/AtomicReference.get:()Ljava/lang/Object;
      27: checkcast     #13                 // class io/reactivex/rxjava3/disposables/Disposable
      30: astore        4
      32: aload         4
      34: ifnull        44
      37: aload         4
      39: invokeinterface #14,  1           // InterfaceMethod io/reactivex/rxjava3/disposables/Disposable.dispose:()V
      44: aload_0
      45: getfield      #6                  // Field debounceSelector:Lio/reactivex/rxjava3/functions/Function;
      48: aload_1
      49: invokeinterface #15,  2           // InterfaceMethod io/reactivex/rxjava3/functions/Function.apply:(Ljava/lang/Object;)Ljava/lang/Object;
      54: ldc           #16                 // String The ObservableSource supplied is null
      56: invokestatic  #17                 // Method java/util/Objects.requireNonNull:(Ljava/lang/Object;Ljava/lang/String;)Ljava/lang/Object;
      59: checkcast     #18                 // class io/reactivex/rxjava3/core/ObservableSource
      62: astore        5
      64: goto          90
      67: astore        6
      69: aload         6
      71: invokestatic  #20                 // Method io/reactivex/rxjava3/exceptions/Exceptions.throwIfFatal:(Ljava/lang/Throwable;)V
      74: aload_0
      75: invokevirtual #21                 // Method dispose:()V
      78: aload_0
      79: getfield      #5                  // Field downstream:Lio/reactivex/rxjava3/core/Observer;
      82: aload         6
      84: invokeinterface #22,  2           // InterfaceMethod io/reactivex/rxjava3/core/Observer.onError:(Ljava/lang/Throwable;)V
      89: return
      90: new           #23                 // class io/reactivex/rxjava3/internal/operators/observable/ObservableDebounce$DebounceObserver$DebounceInnerObserver
      93: dup
      94: aload_0
      95: lload_2
      96: aload_1
      97: invokespecial #24                 // Method io/reactivex/rxjava3/internal/operators/observable/ObservableDebounce$DebounceObserver$DebounceInnerObserver."<init>":(Lio/reactivex/rxjava3/internal/operators/observable/ObservableDebounce$DebounceObserver;JLjava/lang/Object;)V
     100: astore        6
     102: aload_0
     103: getfield      #4                  // Field debouncer:Ljava/util/concurrent/atomic/AtomicReference;
     106: aload         4
     108: aload         6
     110: invokevirtual #25                 // Method java/util/concurrent/atomic/AtomicReference.compareAndSet:(Ljava/lang/Object;Ljava/lang/Object;)Z
     113: ifeq          125
     116: aload         5
     118: aload         6
     120: invokeinterface #26,  2           // InterfaceMethod io/reactivex/rxjava3/core/ObservableSource.subscribe:(Lio/reactivex/rxjava3/core/Observer;)V
     125: return
    Exception table:
       from    to  target type
          44    64    67   Class java/lang/Throwable

  public void onError(java.lang.Throwable);
    Code:
       0: aload_0
       1: getfield      #4                  // Field debouncer:Ljava/util/concurrent/atomic/AtomicReference;
       4: invokestatic  #27                 // Method io/reactivex/rxjava3/internal/disposables/DisposableHelper.dispose:(Ljava/util/concurrent/atomic/AtomicReference;)Z
       7: pop
       8: aload_0
       9: getfield      #5                  // Field downstream:Lio/reactivex/rxjava3/core/Observer;
      12: aload_1
      13: invokeinterface #22,  2           // InterfaceMethod io/reactivex/rxjava3/core/Observer.onError:(Ljava/lang/Throwable;)V
      18: return

  public void onComplete();
    Code:
       0: aload_0
       1: getfield      #10                 // Field done:Z
       4: ifeq          8
       7: return
       8: aload_0
       9: iconst_1
      10: putfield      #10                 // Field done:Z
      13: aload_0
      14: getfield      #4                  // Field debouncer:Ljava/util/concurrent/atomic/AtomicReference;
      17: invokevirtual #12                 // Method java/util/concurrent/atomic/AtomicReference.get:()Ljava/lang/Object;
      20: checkcast     #13                 // class io/reactivex/rxjava3/disposables/Disposable
      23: astore_1
      24: aload_1
      25: getstatic     #28                 // Field io/reactivex/rxjava3/internal/disposables/DisposableHelper.DISPOSED:Lio/reactivex/rxjava3/internal/disposables/DisposableHelper;
      28: if_acmpeq     61
      31: aload_1
      32: checkcast     #23                 // class io/reactivex/rxjava3/internal/operators/observable/ObservableDebounce$DebounceObserver$DebounceInnerObserver
      35: astore_2
      36: aload_2
      37: ifnull        44
      40: aload_2
      41: invokevirtual #29                 // Method io/reactivex/rxjava3/internal/operators/observable/ObservableDebounce$DebounceObserver$DebounceInnerObserver.emit:()V
      44: aload_0
      45: getfield      #4                  // Field debouncer:Ljava/util/concurrent/atomic/AtomicReference;
      48: invokestatic  #27                 // Method io/reactivex/rxjava3/internal/disposables/DisposableHelper.dispose:(Ljava/util/concurrent/atomic/AtomicReference;)Z
      51: pop
      52: aload_0
      53: getfield      #5                  // Field downstream:Lio/reactivex/rxjava3/core/Observer;
      56: invokeinterface #30,  1           // InterfaceMethod io/reactivex/rxjava3/core/Observer.onComplete:()V
      61: return

  public void dispose();
    Code:
       0: aload_0
       1: getfield      #7                  // Field upstream:Lio/reactivex/rxjava3/disposables/Disposable;
       4: invokeinterface #14,  1           // InterfaceMethod io/reactivex/rxjava3/disposables/Disposable.dispose:()V
       9: aload_0
      10: getfield      #4                  // Field debouncer:Ljava/util/concurrent/atomic/AtomicReference;
      13: invokestatic  #27                 // Method io/reactivex/rxjava3/internal/disposables/DisposableHelper.dispose:(Ljava/util/concurrent/atomic/AtomicReference;)Z
      16: pop
      17: return

  public boolean isDisposed();
    Code:
       0: aload_0
       1: getfield      #7                  // Field upstream:Lio/reactivex/rxjava3/disposables/Disposable;
       4: invokeinterface #31,  1           // InterfaceMethod io/reactivex/rxjava3/disposables/Disposable.isDisposed:()Z
       9: ireturn

  void emit(long, T);
    Code:
       0: lload_1
       1: aload_0
       2: getfield      #11                 // Field index:J
       5: lcmp
       6: ifne          19
       9: aload_0
      10: getfield      #5                  // Field downstream:Lio/reactivex/rxjava3/core/Observer;
      13: aload_3
      14: invokeinterface #32,  2           // InterfaceMethod io/reactivex/rxjava3/core/Observer.onNext:(Ljava/lang/Object;)V
      19: return
}
