Compiled from "ObservableTakeLastTimed.java"
final class io.reactivex.rxjava3.internal.operators.observable.ObservableTakeLastTimed$TakeLastTimedObserver<T> extends java.util.concurrent.atomic.AtomicBoolean implements io.reactivex.rxjava3.core.Observer<T>, io.reactivex.rxjava3.disposables.Disposable {
  private static final long serialVersionUID;

  final io.reactivex.rxjava3.core.Observer<? super T> downstream;

  final long count;

  final long time;

  final java.util.concurrent.TimeUnit unit;

  final io.reactivex.rxjava3.core.Scheduler scheduler;

  final io.reactivex.rxjava3.operators.SpscLinkedArrayQueue<java.lang.Object> queue;

  final boolean delayError;

  io.reactivex.rxjava3.disposables.Disposable upstream;

  volatile boolean cancelled;

  java.lang.Throwable error;

  io.reactivex.rxjava3.internal.operators.observable.ObservableTakeLastTimed$TakeLastTimedObserver(io.reactivex.rxjava3.core.Observer<? super T>, long, long, java.util.concurrent.TimeUnit, io.reactivex.rxjava3.core.Scheduler, int, boolean);
    Code:
       0: aload_0
       1: invokespecial #1                  // Method java/util/concurrent/atomic/AtomicBoolean."<init>":()V
       4: aload_0
       5: aload_1
       6: putfield      #2                  // Field downstream:Lio/reactivex/rxjava3/core/Observer;
       9: aload_0
      10: lload_2
      11: putfield      #3                  // Field count:J
      14: aload_0
      15: lload         4
      17: putfield      #4                  // Field time:J
      20: aload_0
      21: aload         6
      23: putfield      #5                  // Field unit:Ljava/util/concurrent/TimeUnit;
      26: aload_0
      27: aload         7
      29: putfield      #6                  // Field scheduler:Lio/reactivex/rxjava3/core/Scheduler;
      32: aload_0
      33: new           #7                  // class io/reactivex/rxjava3/operators/SpscLinkedArrayQueue
      36: dup
      37: iload         8
      39: invokespecial #8                  // Method io/reactivex/rxjava3/operators/SpscLinkedArrayQueue."<init>":(I)V
      42: putfield      #9                  // Field queue:Lio/reactivex/rxjava3/operators/SpscLinkedArrayQueue;
      45: aload_0
      46: iload         9
      48: putfield      #10                 // Field delayError:Z
      51: return

  public void onSubscribe(io.reactivex.rxjava3.disposables.Disposable);
    Code:
       0: aload_0
       1: getfield      #11                 // Field upstream:Lio/reactivex/rxjava3/disposables/Disposable;
       4: aload_1
       5: invokestatic  #12                 // Method io/reactivex/rxjava3/internal/disposables/DisposableHelper.validate:(Lio/reactivex/rxjava3/disposables/Disposable;Lio/reactivex/rxjava3/disposables/Disposable;)Z
       8: ifeq          26
      11: aload_0
      12: aload_1
      13: putfield      #11                 // Field upstream:Lio/reactivex/rxjava3/disposables/Disposable;
      16: aload_0
      17: getfield      #2                  // Field downstream:Lio/reactivex/rxjava3/core/Observer;
      20: aload_0
      21: invokeinterface #13,  2           // InterfaceMethod io/reactivex/rxjava3/core/Observer.onSubscribe:(Lio/reactivex/rxjava3/disposables/Disposable;)V
      26: return

  public void onNext(T);
    Code:
       0: aload_0
       1: getfield      #9                  // Field queue:Lio/reactivex/rxjava3/operators/SpscLinkedArrayQueue;
       4: astore_2
       5: aload_0
       6: getfield      #6                  // Field scheduler:Lio/reactivex/rxjava3/core/Scheduler;
       9: aload_0
      10: getfield      #5                  // Field unit:Ljava/util/concurrent/TimeUnit;
      13: invokevirtual #14                 // Method io/reactivex/rxjava3/core/Scheduler.now:(Ljava/util/concurrent/TimeUnit;)J
      16: lstore_3
      17: aload_0
      18: getfield      #4                  // Field time:J
      21: lstore        5
      23: aload_0
      24: getfield      #3                  // Field count:J
      27: lstore        7
      29: lload         7
      31: ldc2_w        #16                 // long 9223372036854775807l
      34: lcmp
      35: ifne          42
      38: iconst_1
      39: goto          43
      42: iconst_0
      43: istore        9
      45: aload_2
      46: lload_3
      47: invokestatic  #18                 // Method java/lang/Long.valueOf:(J)Ljava/lang/Long;
      50: aload_1
      51: invokevirtual #19                 // Method io/reactivex/rxjava3/operators/SpscLinkedArrayQueue.offer:(Ljava/lang/Object;Ljava/lang/Object;)Z
      54: pop
      55: aload_2
      56: invokevirtual #20                 // Method io/reactivex/rxjava3/operators/SpscLinkedArrayQueue.isEmpty:()Z
      59: ifne          115
      62: aload_2
      63: invokevirtual #21                 // Method io/reactivex/rxjava3/operators/SpscLinkedArrayQueue.peek:()Ljava/lang/Object;
      66: checkcast     #15                 // class java/lang/Long
      69: invokevirtual #22                 // Method java/lang/Long.longValue:()J
      72: lstore        10
      74: lload         10
      76: lload_3
      77: lload         5
      79: lsub
      80: lcmp
      81: ifle          102
      84: iload         9
      86: ifne          115
      89: aload_2
      90: invokevirtual #23                 // Method io/reactivex/rxjava3/operators/SpscLinkedArrayQueue.size:()I
      93: iconst_1
      94: ishr
      95: i2l
      96: lload         7
      98: lcmp
      99: ifle          115
     102: aload_2
     103: invokevirtual #24                 // Method io/reactivex/rxjava3/operators/SpscLinkedArrayQueue.poll:()Ljava/lang/Object;
     106: pop
     107: aload_2
     108: invokevirtual #24                 // Method io/reactivex/rxjava3/operators/SpscLinkedArrayQueue.poll:()Ljava/lang/Object;
     111: pop
     112: goto          55
     115: return

  public void onError(java.lang.Throwable);
    Code:
       0: aload_0
       1: aload_1
       2: putfield      #25                 // Field error:Ljava/lang/Throwable;
       5: aload_0
       6: invokevirtual #26                 // Method drain:()V
       9: return

  public void onComplete();
    Code:
       0: aload_0
       1: invokevirtual #26                 // Method drain:()V
       4: return

  public void dispose();
    Code:
       0: aload_0
       1: getfield      #27                 // Field cancelled:Z
       4: ifne          37
       7: aload_0
       8: iconst_1
       9: putfield      #27                 // Field cancelled:Z
      12: aload_0
      13: getfield      #11                 // Field upstream:Lio/reactivex/rxjava3/disposables/Disposable;
      16: invokeinterface #28,  1           // InterfaceMethod io/reactivex/rxjava3/disposables/Disposable.dispose:()V
      21: aload_0
      22: iconst_0
      23: iconst_1
      24: invokevirtual #29                 // Method compareAndSet:(ZZ)Z
      27: ifeq          37
      30: aload_0
      31: getfield      #9                  // Field queue:Lio/reactivex/rxjava3/operators/SpscLinkedArrayQueue;
      34: invokevirtual #30                 // Method io/reactivex/rxjava3/operators/SpscLinkedArrayQueue.clear:()V
      37: return

  public boolean isDisposed();
    Code:
       0: aload_0
       1: getfield      #27                 // Field cancelled:Z
       4: ireturn

  void drain();
    Code:
       0: aload_0
       1: iconst_0
       2: iconst_1
       3: invokevirtual #29                 // Method compareAndSet:(ZZ)Z
       6: ifne          10
       9: return
      10: aload_0
      11: getfield      #2                  // Field downstream:Lio/reactivex/rxjava3/core/Observer;
      14: astore_1
      15: aload_0
      16: getfield      #9                  // Field queue:Lio/reactivex/rxjava3/operators/SpscLinkedArrayQueue;
      19: astore_2
      20: aload_0
      21: getfield      #10                 // Field delayError:Z
      24: istore_3
      25: aload_0
      26: getfield      #6                  // Field scheduler:Lio/reactivex/rxjava3/core/Scheduler;
      29: aload_0
      30: getfield      #5                  // Field unit:Ljava/util/concurrent/TimeUnit;
      33: invokevirtual #14                 // Method io/reactivex/rxjava3/core/Scheduler.now:(Ljava/util/concurrent/TimeUnit;)J
      36: aload_0
      37: getfield      #4                  // Field time:J
      40: lsub
      41: lstore        4
      43: aload_0
      44: getfield      #27                 // Field cancelled:Z
      47: ifeq          55
      50: aload_2
      51: invokevirtual #30                 // Method io/reactivex/rxjava3/operators/SpscLinkedArrayQueue.clear:()V
      54: return
      55: iload_3
      56: ifne          83
      59: aload_0
      60: getfield      #25                 // Field error:Ljava/lang/Throwable;
      63: astore        6
      65: aload         6
      67: ifnull        83
      70: aload_2
      71: invokevirtual #30                 // Method io/reactivex/rxjava3/operators/SpscLinkedArrayQueue.clear:()V
      74: aload_1
      75: aload         6
      77: invokeinterface #31,  2           // InterfaceMethod io/reactivex/rxjava3/core/Observer.onError:(Ljava/lang/Throwable;)V
      82: return
      83: aload_2
      84: invokevirtual #24                 // Method io/reactivex/rxjava3/operators/SpscLinkedArrayQueue.poll:()Ljava/lang/Object;
      87: astore        6
      89: aload         6
      91: ifnonnull     98
      94: iconst_1
      95: goto          99
      98: iconst_0
      99: istore        7
     101: iload         7
     103: ifeq          135
     106: aload_0
     107: getfield      #25                 // Field error:Ljava/lang/Throwable;
     110: astore        8
     112: aload         8
     114: ifnull        128
     117: aload_1
     118: aload         8
     120: invokeinterface #31,  2           // InterfaceMethod io/reactivex/rxjava3/core/Observer.onError:(Ljava/lang/Throwable;)V
     125: goto          134
     128: aload_1
     129: invokeinterface #32,  1           // InterfaceMethod io/reactivex/rxjava3/core/Observer.onComplete:()V
     134: return
     135: aload_2
     136: invokevirtual #24                 // Method io/reactivex/rxjava3/operators/SpscLinkedArrayQueue.poll:()Ljava/lang/Object;
     139: astore        8
     141: aload         6
     143: checkcast     #15                 // class java/lang/Long
     146: invokevirtual #22                 // Method java/lang/Long.longValue:()J
     149: lload         4
     151: lcmp
     152: ifge          158
     155: goto          43
     158: aload_1
     159: aload         8
     161: invokeinterface #33,  2           // InterfaceMethod io/reactivex/rxjava3/core/Observer.onNext:(Ljava/lang/Object;)V
     166: goto          43
}
