Compiled from "ObservableReplay.java"
final class io.reactivex.rxjava3.internal.operators.observable.ObservableReplay$DisposeConsumer<R> implements io.reactivex.rxjava3.functions.Consumer<io.reactivex.rxjava3.disposables.Disposable> {
  private final io.reactivex.rxjava3.internal.operators.observable.ObserverResourceWrapper<R> srw;

  io.reactivex.rxjava3.internal.operators.observable.ObservableReplay$DisposeConsumer(io.reactivex.rxjava3.internal.operators.observable.ObserverResourceWrapper<R>);
    Code:
       0: aload_0
       1: invokespecial #1                  // Method java/lang/Object."<init>":()V
       4: aload_0
       5: aload_1
       6: putfield      #2                  // Field srw:Lio/reactivex/rxjava3/internal/operators/observable/ObserverResourceWrapper;
       9: return

  public void accept(io.reactivex.rxjava3.disposables.Disposable);
    Code:
       0: aload_0
       1: getfield      #2                  // Field srw:Lio/reactivex/rxjava3/internal/operators/observable/ObserverResourceWrapper;
       4: aload_1
       5: invokevirtual #3                  // Method io/reactivex/rxjava3/internal/operators/observable/ObserverResourceWrapper.setResource:(Lio/reactivex/rxjava3/disposables/Disposable;)V
       8: return

  public void accept(java.lang.Object) throws java.lang.Throwable;
    Code:
       0: aload_0
       1: aload_1
       2: checkcast     #4                  // class io/reactivex/rxjava3/disposables/Disposable
       5: invokevirtual #5                  // Method accept:(Lio/reactivex/rxjava3/disposables/Disposable;)V
       8: return
}
