Compiled from "ObservableGroupBy.java"
final class io.reactivex.rxjava3.internal.operators.observable.ObservableGroupBy$GroupedUnicast<K, T> extends io.reactivex.rxjava3.observables.GroupedObservable<K, T> {
  final io.reactivex.rxjava3.internal.operators.observable.ObservableGroupBy$State<T, K> state;

  public static <T, K> io.reactivex.rxjava3.internal.operators.observable.ObservableGroupBy$GroupedUnicast<K, T> createWith(K, int, io.reactivex.rxjava3.internal.operators.observable.ObservableGroupBy$GroupByObserver<?, K, T>, boolean);
    Code:
       0: new           #1                  // class io/reactivex/rxjava3/internal/operators/observable/ObservableGroupBy$State
       3: dup
       4: iload_1
       5: aload_2
       6: aload_0
       7: iload_3
       8: invokespecial #2                  // Method io/reactivex/rxjava3/internal/operators/observable/ObservableGroupBy$State."<init>":(ILio/reactivex/rxjava3/internal/operators/observable/ObservableGroupBy$GroupByObserver;Ljava/lang/Object;Z)V
      11: astore        4
      13: new           #3                  // class io/reactivex/rxjava3/internal/operators/observable/ObservableGroupBy$GroupedUnicast
      16: dup
      17: aload_0
      18: aload         4
      20: invokespecial #4                  // Method "<init>":(Ljava/lang/Object;Lio/reactivex/rxjava3/internal/operators/observable/ObservableGroupBy$State;)V
      23: areturn

  protected io.reactivex.rxjava3.internal.operators.observable.ObservableGroupBy$GroupedUnicast(K, io.reactivex.rxjava3.internal.operators.observable.ObservableGroupBy$State<T, K>);
    Code:
       0: aload_0
       1: aload_1
       2: invokespecial #5                  // Method io/reactivex/rxjava3/observables/GroupedObservable."<init>":(Ljava/lang/Object;)V
       5: aload_0
       6: aload_2
       7: putfield      #6                  // Field state:Lio/reactivex/rxjava3/internal/operators/observable/ObservableGroupBy$State;
      10: return

  protected void subscribeActual(io.reactivex.rxjava3.core.Observer<? super T>);
    Code:
       0: aload_0
       1: getfield      #6                  // Field state:Lio/reactivex/rxjava3/internal/operators/observable/ObservableGroupBy$State;
       4: aload_1
       5: invokevirtual #7                  // Method io/reactivex/rxjava3/internal/operators/observable/ObservableGroupBy$State.subscribe:(Lio/reactivex/rxjava3/core/Observer;)V
       8: return

  public void onNext(T);
    Code:
       0: aload_0
       1: getfield      #6                  // Field state:Lio/reactivex/rxjava3/internal/operators/observable/ObservableGroupBy$State;
       4: aload_1
       5: invokevirtual #8                  // Method io/reactivex/rxjava3/internal/operators/observable/ObservableGroupBy$State.onNext:(Ljava/lang/Object;)V
       8: return

  public void onError(java.lang.Throwable);
    Code:
       0: aload_0
       1: getfield      #6                  // Field state:Lio/reactivex/rxjava3/internal/operators/observable/ObservableGroupBy$State;
       4: aload_1
       5: invokevirtual #9                  // Method io/reactivex/rxjava3/internal/operators/observable/ObservableGroupBy$State.onError:(Ljava/lang/Throwable;)V
       8: return

  public void onComplete();
    Code:
       0: aload_0
       1: getfield      #6                  // Field state:Lio/reactivex/rxjava3/internal/operators/observable/ObservableGroupBy$State;
       4: invokevirtual #10                 // Method io/reactivex/rxjava3/internal/operators/observable/ObservableGroupBy$State.onComplete:()V
       7: return
}
