Compiled from "ObservableConcatMapScheduler.java"
public final class io.reactivex.rxjava3.internal.operators.observable.ObservableConcatMapScheduler<T, U> extends io.reactivex.rxjava3.internal.operators.observable.AbstractObservableWithUpstream<T, U> {
  final io.reactivex.rxjava3.functions.Function<? super T, ? extends io.reactivex.rxjava3.core.ObservableSource<? extends U>> mapper;

  final int bufferSize;

  final io.reactivex.rxjava3.internal.util.ErrorMode delayErrors;

  final io.reactivex.rxjava3.core.Scheduler scheduler;

  public io.reactivex.rxjava3.internal.operators.observable.ObservableConcatMapScheduler(io.reactivex.rxjava3.core.ObservableSource<T>, io.reactivex.rxjava3.functions.Function<? super T, ? extends io.reactivex.rxjava3.core.ObservableSource<? extends U>>, int, io.reactivex.rxjava3.internal.util.ErrorMode, io.reactivex.rxjava3.core.Scheduler);
    Code:
       0: aload_0
       1: aload_1
       2: invokespecial #1                  // Method io/reactivex/rxjava3/internal/operators/observable/AbstractObservableWithUpstream."<init>":(Lio/reactivex/rxjava3/core/ObservableSource;)V
       5: aload_0
       6: aload_2
       7: putfield      #2                  // Field mapper:Lio/reactivex/rxjava3/functions/Function;
      10: aload_0
      11: aload         4
      13: putfield      #3                  // Field delayErrors:Lio/reactivex/rxjava3/internal/util/ErrorMode;
      16: aload_0
      17: bipush        8
      19: iload_3
      20: invokestatic  #4                  // Method java/lang/Math.max:(II)I
      23: putfield      #5                  // Field bufferSize:I
      26: aload_0
      27: aload         5
      29: putfield      #6                  // Field scheduler:Lio/reactivex/rxjava3/core/Scheduler;
      32: return

  public void subscribeActual(io.reactivex.rxjava3.core.Observer<? super U>);
    Code:
       0: aload_0
       1: getfield      #3                  // Field delayErrors:Lio/reactivex/rxjava3/internal/util/ErrorMode;
       4: getstatic     #7                  // Field io/reactivex/rxjava3/internal/util/ErrorMode.IMMEDIATE:Lio/reactivex/rxjava3/internal/util/ErrorMode;
       7: if_acmpne     54
      10: new           #8                  // class io/reactivex/rxjava3/observers/SerializedObserver
      13: dup
      14: aload_1
      15: invokespecial #9                  // Method io/reactivex/rxjava3/observers/SerializedObserver."<init>":(Lio/reactivex/rxjava3/core/Observer;)V
      18: astore_2
      19: aload_0
      20: getfield      #10                 // Field source:Lio/reactivex/rxjava3/core/ObservableSource;
      23: new           #11                 // class io/reactivex/rxjava3/internal/operators/observable/ObservableConcatMapScheduler$ConcatMapObserver
      26: dup
      27: aload_2
      28: aload_0
      29: getfield      #2                  // Field mapper:Lio/reactivex/rxjava3/functions/Function;
      32: aload_0
      33: getfield      #5                  // Field bufferSize:I
      36: aload_0
      37: getfield      #6                  // Field scheduler:Lio/reactivex/rxjava3/core/Scheduler;
      40: invokevirtual #12                 // Method io/reactivex/rxjava3/core/Scheduler.createWorker:()Lio/reactivex/rxjava3/core/Scheduler$Worker;
      43: invokespecial #13                 // Method io/reactivex/rxjava3/internal/operators/observable/ObservableConcatMapScheduler$ConcatMapObserver."<init>":(Lio/reactivex/rxjava3/core/Observer;Lio/reactivex/rxjava3/functions/Function;ILio/reactivex/rxjava3/core/Scheduler$Worker;)V
      46: invokeinterface #14,  2           // InterfaceMethod io/reactivex/rxjava3/core/ObservableSource.subscribe:(Lio/reactivex/rxjava3/core/Observer;)V
      51: goto          101
      54: aload_0
      55: getfield      #10                 // Field source:Lio/reactivex/rxjava3/core/ObservableSource;
      58: new           #15                 // class io/reactivex/rxjava3/internal/operators/observable/ObservableConcatMapScheduler$ConcatMapDelayErrorObserver
      61: dup
      62: aload_1
      63: aload_0
      64: getfield      #2                  // Field mapper:Lio/reactivex/rxjava3/functions/Function;
      67: aload_0
      68: getfield      #5                  // Field bufferSize:I
      71: aload_0
      72: getfield      #3                  // Field delayErrors:Lio/reactivex/rxjava3/internal/util/ErrorMode;
      75: getstatic     #16                 // Field io/reactivex/rxjava3/internal/util/ErrorMode.END:Lio/reactivex/rxjava3/internal/util/ErrorMode;
      78: if_acmpne     85
      81: iconst_1
      82: goto          86
      85: iconst_0
      86: aload_0
      87: getfield      #6                  // Field scheduler:Lio/reactivex/rxjava3/core/Scheduler;
      90: invokevirtual #12                 // Method io/reactivex/rxjava3/core/Scheduler.createWorker:()Lio/reactivex/rxjava3/core/Scheduler$Worker;
      93: invokespecial #17                 // Method io/reactivex/rxjava3/internal/operators/observable/ObservableConcatMapScheduler$ConcatMapDelayErrorObserver."<init>":(Lio/reactivex/rxjava3/core/Observer;Lio/reactivex/rxjava3/functions/Function;IZLio/reactivex/rxjava3/core/Scheduler$Worker;)V
      96: invokeinterface #14,  2           // InterfaceMethod io/reactivex/rxjava3/core/ObservableSource.subscribe:(Lio/reactivex/rxjava3/core/Observer;)V
     101: return
}
