Compiled from "ObservableDelay.java"
final class io.reactivex.rxjava3.internal.operators.observable.ObservableDelay$DelayObserver$OnError implements java.lang.Runnable {
  private final java.lang.Throwable throwable;

  final io.reactivex.rxjava3.internal.operators.observable.ObservableDelay$DelayObserver this$0;

  io.reactivex.rxjava3.internal.operators.observable.ObservableDelay$DelayObserver$OnError(io.reactivex.rxjava3.internal.operators.observable.ObservableDelay$DelayObserver, java.lang.Throwable);
    Code:
       0: aload_0
       1: aload_1
       2: putfield      #1                  // Field this$0:Lio/reactivex/rxjava3/internal/operators/observable/ObservableDelay$DelayObserver;
       5: aload_0
       6: invokespecial #2                  // Method java/lang/Object."<init>":()V
       9: aload_0
      10: aload_2
      11: putfield      #3                  // Field throwable:Ljava/lang/Throwable;
      14: return

  public void run();
    Code:
       0: aload_0
       1: getfield      #1                  // Field this$0:Lio/reactivex/rxjava3/internal/operators/observable/ObservableDelay$DelayObserver;
       4: getfield      #4                  // Field io/reactivex/rxjava3/internal/operators/observable/ObservableDelay$DelayObserver.downstream:Lio/reactivex/rxjava3/core/Observer;
       7: aload_0
       8: getfield      #3                  // Field throwable:Ljava/lang/Throwable;
      11: invokeinterface #5,  2            // InterfaceMethod io/reactivex/rxjava3/core/Observer.onError:(Ljava/lang/Throwable;)V
      16: aload_0
      17: getfield      #1                  // Field this$0:Lio/reactivex/rxjava3/internal/operators/observable/ObservableDelay$DelayObserver;
      20: getfield      #6                  // Field io/reactivex/rxjava3/internal/operators/observable/ObservableDelay$DelayObserver.w:Lio/reactivex/rxjava3/core/Scheduler$Worker;
      23: invokevirtual #7                  // Method io/reactivex/rxjava3/core/Scheduler$Worker.dispose:()V
      26: goto          42
      29: astore_1
      30: aload_0
      31: getfield      #1                  // Field this$0:Lio/reactivex/rxjava3/internal/operators/observable/ObservableDelay$DelayObserver;
      34: getfield      #6                  // Field io/reactivex/rxjava3/internal/operators/observable/ObservableDelay$DelayObserver.w:Lio/reactivex/rxjava3/core/Scheduler$Worker;
      37: invokevirtual #7                  // Method io/reactivex/rxjava3/core/Scheduler$Worker.dispose:()V
      40: aload_1
      41: athrow
      42: return
    Exception table:
       from    to  target type
           0    16    29   any
}
