Compiled from "ObservableReplay.java"
final class io.reactivex.rxjava3.internal.operators.observable.ObservableReplay$ReplayBufferSupplier<T> implements io.reactivex.rxjava3.internal.operators.observable.ObservableReplay$BufferSupplier<T> {
  final int bufferSize;

  final boolean eagerTruncate;

  io.reactivex.rxjava3.internal.operators.observable.ObservableReplay$ReplayBufferSupplier(int, boolean);
    Code:
       0: aload_0
       1: invokespecial #1                  // Method java/lang/Object."<init>":()V
       4: aload_0
       5: iload_1
       6: putfield      #2                  // Field bufferSize:I
       9: aload_0
      10: iload_2
      11: putfield      #3                  // Field eagerTruncate:Z
      14: return

  public io.reactivex.rxjava3.internal.operators.observable.ObservableReplay$ReplayBuffer<T> call();
    Code:
       0: new           #4                  // class io/reactivex/rxjava3/internal/operators/observable/ObservableReplay$SizeBoundReplayBuffer
       3: dup
       4: aload_0
       5: getfield      #2                  // Field bufferSize:I
       8: aload_0
       9: getfield      #3                  // Field eagerTruncate:Z
      12: invokespecial #5                  // Method io/reactivex/rxjava3/internal/operators/observable/ObservableReplay$SizeBoundReplayBuffer."<init>":(IZ)V
      15: areturn
}
