Compiled from "ObservableSkipUntil.java"
final class io.reactivex.rxjava3.internal.operators.observable.ObservableSkipUntil$SkipUntil implements io.reactivex.rxjava3.core.Observer<U> {
  final io.reactivex.rxjava3.internal.disposables.ArrayCompositeDisposable frc;

  final io.reactivex.rxjava3.internal.operators.observable.ObservableSkipUntil$SkipUntilObserver<T> sus;

  final io.reactivex.rxjava3.observers.SerializedObserver<T> serial;

  io.reactivex.rxjava3.disposables.Disposable upstream;

  final io.reactivex.rxjava3.internal.operators.observable.ObservableSkipUntil this$0;

  io.reactivex.rxjava3.internal.operators.observable.ObservableSkipUntil$SkipUntil(io.reactivex.rxjava3.internal.disposables.ArrayCompositeDisposable, io.reactivex.rxjava3.internal.operators.observable.ObservableSkipUntil$SkipUntilObserver<T>, io.reactivex.rxjava3.observers.SerializedObserver<T>);
    Code:
       0: aload_0
       1: aload_1
       2: putfield      #1                  // Field this$0:Lio/reactivex/rxjava3/internal/operators/observable/ObservableSkipUntil;
       5: aload_0
       6: invokespecial #2                  // Method java/lang/Object."<init>":()V
       9: aload_0
      10: aload_2
      11: putfield      #3                  // Field frc:Lio/reactivex/rxjava3/internal/disposables/ArrayCompositeDisposable;
      14: aload_0
      15: aload_3
      16: putfield      #4                  // Field sus:Lio/reactivex/rxjava3/internal/operators/observable/ObservableSkipUntil$SkipUntilObserver;
      19: aload_0
      20: aload         4
      22: putfield      #5                  // Field serial:Lio/reactivex/rxjava3/observers/SerializedObserver;
      25: return

  public void onSubscribe(io.reactivex.rxjava3.disposables.Disposable);
    Code:
       0: aload_0
       1: getfield      #6                  // Field upstream:Lio/reactivex/rxjava3/disposables/Disposable;
       4: aload_1
       5: invokestatic  #7                  // Method io/reactivex/rxjava3/internal/disposables/DisposableHelper.validate:(Lio/reactivex/rxjava3/disposables/Disposable;Lio/reactivex/rxjava3/disposables/Disposable;)Z
       8: ifeq          26
      11: aload_0
      12: aload_1
      13: putfield      #6                  // Field upstream:Lio/reactivex/rxjava3/disposables/Disposable;
      16: aload_0
      17: getfield      #3                  // Field frc:Lio/reactivex/rxjava3/internal/disposables/ArrayCompositeDisposable;
      20: iconst_1
      21: aload_1
      22: invokevirtual #8                  // Method io/reactivex/rxjava3/internal/disposables/ArrayCompositeDisposable.setResource:(ILio/reactivex/rxjava3/disposables/Disposable;)Z
      25: pop
      26: return

  public void onNext(U);
    Code:
       0: aload_0
       1: getfield      #6                  // Field upstream:Lio/reactivex/rxjava3/disposables/Disposable;
       4: invokeinterface #9,  1            // InterfaceMethod io/reactivex/rxjava3/disposables/Disposable.dispose:()V
       9: aload_0
      10: getfield      #4                  // Field sus:Lio/reactivex/rxjava3/internal/operators/observable/ObservableSkipUntil$SkipUntilObserver;
      13: iconst_1
      14: putfield      #10                 // Field io/reactivex/rxjava3/internal/operators/observable/ObservableSkipUntil$SkipUntilObserver.notSkipping:Z
      17: return

  public void onError(java.lang.Throwable);
    Code:
       0: aload_0
       1: getfield      #3                  // Field frc:Lio/reactivex/rxjava3/internal/disposables/ArrayCompositeDisposable;
       4: invokevirtual #11                 // Method io/reactivex/rxjava3/internal/disposables/ArrayCompositeDisposable.dispose:()V
       7: aload_0
       8: getfield      #5                  // Field serial:Lio/reactivex/rxjava3/observers/SerializedObserver;
      11: aload_1
      12: invokevirtual #12                 // Method io/reactivex/rxjava3/observers/SerializedObserver.onError:(Ljava/lang/Throwable;)V
      15: return

  public void onComplete();
    Code:
       0: aload_0
       1: getfield      #4                  // Field sus:Lio/reactivex/rxjava3/internal/operators/observable/ObservableSkipUntil$SkipUntilObserver;
       4: iconst_1
       5: putfield      #10                 // Field io/reactivex/rxjava3/internal/operators/observable/ObservableSkipUntil$SkipUntilObserver.notSkipping:Z
       8: return
}
