Compiled from "ObservableGroupBy.java"
public final class io.reactivex.rxjava3.internal.operators.observable.ObservableGroupBy<T, K, V> extends io.reactivex.rxjava3.internal.operators.observable.AbstractObservableWithUpstream<T, io.reactivex.rxjava3.observables.GroupedObservable<K, V>> {
  final io.reactivex.rxjava3.functions.Function<? super T, ? extends K> keySelector;

  final io.reactivex.rxjava3.functions.Function<? super T, ? extends V> valueSelector;

  final int bufferSize;

  final boolean delayError;

  public io.reactivex.rxjava3.internal.operators.observable.ObservableGroupBy(io.reactivex.rxjava3.core.ObservableSource<T>, io.reactivex.rxjava3.functions.Function<? super T, ? extends K>, io.reactivex.rxjava3.functions.Function<? super T, ? extends V>, int, boolean);
    Code:
       0: aload_0
       1: aload_1
       2: invokespecial #1                  // Method io/reactivex/rxjava3/internal/operators/observable/AbstractObservableWithUpstream."<init>":(Lio/reactivex/rxjava3/core/ObservableSource;)V
       5: aload_0
       6: aload_2
       7: putfield      #2                  // Field keySelector:Lio/reactivex/rxjava3/functions/Function;
      10: aload_0
      11: aload_3
      12: putfield      #3                  // Field valueSelector:Lio/reactivex/rxjava3/functions/Function;
      15: aload_0
      16: iload         4
      18: putfield      #4                  // Field bufferSize:I
      21: aload_0
      22: iload         5
      24: putfield      #5                  // Field delayError:Z
      27: return

  public void subscribeActual(io.reactivex.rxjava3.core.Observer<? super io.reactivex.rxjava3.observables.GroupedObservable<K, V>>);
    Code:
       0: aload_0
       1: getfield      #6                  // Field source:Lio/reactivex/rxjava3/core/ObservableSource;
       4: new           #7                  // class io/reactivex/rxjava3/internal/operators/observable/ObservableGroupBy$GroupByObserver
       7: dup
       8: aload_1
       9: aload_0
      10: getfield      #2                  // Field keySelector:Lio/reactivex/rxjava3/functions/Function;
      13: aload_0
      14: getfield      #3                  // Field valueSelector:Lio/reactivex/rxjava3/functions/Function;
      17: aload_0
      18: getfield      #4                  // Field bufferSize:I
      21: aload_0
      22: getfield      #5                  // Field delayError:Z
      25: invokespecial #8                  // Method io/reactivex/rxjava3/internal/operators/observable/ObservableGroupBy$GroupByObserver."<init>":(Lio/reactivex/rxjava3/core/Observer;Lio/reactivex/rxjava3/functions/Function;Lio/reactivex/rxjava3/functions/Function;IZ)V
      28: invokeinterface #9,  2            // InterfaceMethod io/reactivex/rxjava3/core/ObservableSource.subscribe:(Lio/reactivex/rxjava3/core/Observer;)V
      33: return
}
