Compiled from "ObservableZipIterable.java"
final class io.reactivex.rxjava3.internal.operators.observable.ObservableZipIterable$ZipIterableObserver<T, U, V> implements io.reactivex.rxjava3.core.Observer<T>, io.reactivex.rxjava3.disposables.Disposable {
  final io.reactivex.rxjava3.core.Observer<? super V> downstream;

  final java.util.Iterator<U> iterator;

  final io.reactivex.rxjava3.functions.BiFunction<? super T, ? super U, ? extends V> zipper;

  io.reactivex.rxjava3.disposables.Disposable upstream;

  boolean done;

  io.reactivex.rxjava3.internal.operators.observable.ObservableZipIterable$ZipIterableObserver(io.reactivex.rxjava3.core.Observer<? super V>, java.util.Iterator<U>, io.reactivex.rxjava3.functions.BiFunction<? super T, ? super U, ? extends V>);
    Code:
       0: aload_0
       1: invokespecial #1                  // Method java/lang/Object."<init>":()V
       4: aload_0
       5: aload_1
       6: putfield      #2                  // Field downstream:Lio/reactivex/rxjava3/core/Observer;
       9: aload_0
      10: aload_2
      11: putfield      #3                  // Field iterator:Ljava/util/Iterator;
      14: aload_0
      15: aload_3
      16: putfield      #4                  // Field zipper:Lio/reactivex/rxjava3/functions/BiFunction;
      19: return

  public void onSubscribe(io.reactivex.rxjava3.disposables.Disposable);
    Code:
       0: aload_0
       1: getfield      #5                  // Field upstream:Lio/reactivex/rxjava3/disposables/Disposable;
       4: aload_1
       5: invokestatic  #6                  // Method io/reactivex/rxjava3/internal/disposables/DisposableHelper.validate:(Lio/reactivex/rxjava3/disposables/Disposable;Lio/reactivex/rxjava3/disposables/Disposable;)Z
       8: ifeq          26
      11: aload_0
      12: aload_1
      13: putfield      #5                  // Field upstream:Lio/reactivex/rxjava3/disposables/Disposable;
      16: aload_0
      17: getfield      #2                  // Field downstream:Lio/reactivex/rxjava3/core/Observer;
      20: aload_0
      21: invokeinterface #7,  2            // InterfaceMethod io/reactivex/rxjava3/core/Observer.onSubscribe:(Lio/reactivex/rxjava3/disposables/Disposable;)V
      26: return

  public void dispose();
    Code:
       0: aload_0
       1: getfield      #5                  // Field upstream:Lio/reactivex/rxjava3/disposables/Disposable;
       4: invokeinterface #8,  1            // InterfaceMethod io/reactivex/rxjava3/disposables/Disposable.dispose:()V
       9: return

  public boolean isDisposed();
    Code:
       0: aload_0
       1: getfield      #5                  // Field upstream:Lio/reactivex/rxjava3/disposables/Disposable;
       4: invokeinterface #9,  1            // InterfaceMethod io/reactivex/rxjava3/disposables/Disposable.isDisposed:()Z
       9: ireturn

  public void onNext(T);
    Code:
       0: aload_0
       1: getfield      #10                 // Field done:Z
       4: ifeq          8
       7: return
       8: aload_0
       9: getfield      #3                  // Field iterator:Ljava/util/Iterator;
      12: invokeinterface #11,  1           // InterfaceMethod java/util/Iterator.next:()Ljava/lang/Object;
      17: ldc           #12                 // String The iterator returned a null value
      19: invokestatic  #13                 // Method java/util/Objects.requireNonNull:(Ljava/lang/Object;Ljava/lang/String;)Ljava/lang/Object;
      22: astore_2
      23: goto          37
      26: astore_3
      27: aload_3
      28: invokestatic  #15                 // Method io/reactivex/rxjava3/exceptions/Exceptions.throwIfFatal:(Ljava/lang/Throwable;)V
      31: aload_0
      32: aload_3
      33: invokevirtual #16                 // Method fail:(Ljava/lang/Throwable;)V
      36: return
      37: aload_0
      38: getfield      #4                  // Field zipper:Lio/reactivex/rxjava3/functions/BiFunction;
      41: aload_1
      42: aload_2
      43: invokeinterface #17,  3           // InterfaceMethod io/reactivex/rxjava3/functions/BiFunction.apply:(Ljava/lang/Object;Ljava/lang/Object;)Ljava/lang/Object;
      48: ldc           #18                 // String The zipper function returned a null value
      50: invokestatic  #13                 // Method java/util/Objects.requireNonNull:(Ljava/lang/Object;Ljava/lang/String;)Ljava/lang/Object;
      53: astore_3
      54: goto          71
      57: astore        4
      59: aload         4
      61: invokestatic  #15                 // Method io/reactivex/rxjava3/exceptions/Exceptions.throwIfFatal:(Ljava/lang/Throwable;)V
      64: aload_0
      65: aload         4
      67: invokevirtual #16                 // Method fail:(Ljava/lang/Throwable;)V
      70: return
      71: aload_0
      72: getfield      #2                  // Field downstream:Lio/reactivex/rxjava3/core/Observer;
      75: aload_3
      76: invokeinterface #19,  2           // InterfaceMethod io/reactivex/rxjava3/core/Observer.onNext:(Ljava/lang/Object;)V
      81: aload_0
      82: getfield      #3                  // Field iterator:Ljava/util/Iterator;
      85: invokeinterface #20,  1           // InterfaceMethod java/util/Iterator.hasNext:()Z
      90: istore        4
      92: goto          109
      95: astore        5
      97: aload         5
      99: invokestatic  #15                 // Method io/reactivex/rxjava3/exceptions/Exceptions.throwIfFatal:(Ljava/lang/Throwable;)V
     102: aload_0
     103: aload         5
     105: invokevirtual #16                 // Method fail:(Ljava/lang/Throwable;)V
     108: return
     109: iload         4
     111: ifne          137
     114: aload_0
     115: iconst_1
     116: putfield      #10                 // Field done:Z
     119: aload_0
     120: getfield      #5                  // Field upstream:Lio/reactivex/rxjava3/disposables/Disposable;
     123: invokeinterface #8,  1            // InterfaceMethod io/reactivex/rxjava3/disposables/Disposable.dispose:()V
     128: aload_0
     129: getfield      #2                  // Field downstream:Lio/reactivex/rxjava3/core/Observer;
     132: invokeinterface #21,  1           // InterfaceMethod io/reactivex/rxjava3/core/Observer.onComplete:()V
     137: return
    Exception table:
       from    to  target type
           8    23    26   Class java/lang/Throwable
          37    54    57   Class java/lang/Throwable
          81    92    95   Class java/lang/Throwable

  void fail(java.lang.Throwable);
    Code:
       0: aload_0
       1: iconst_1
       2: putfield      #10                 // Field done:Z
       5: aload_0
       6: getfield      #5                  // Field upstream:Lio/reactivex/rxjava3/disposables/Disposable;
       9: invokeinterface #8,  1            // InterfaceMethod io/reactivex/rxjava3/disposables/Disposable.dispose:()V
      14: aload_0
      15: getfield      #2                  // Field downstream:Lio/reactivex/rxjava3/core/Observer;
      18: aload_1
      19: invokeinterface #22,  2           // InterfaceMethod io/reactivex/rxjava3/core/Observer.onError:(Ljava/lang/Throwable;)V
      24: return

  public void onError(java.lang.Throwable);
    Code:
       0: aload_0
       1: getfield      #10                 // Field done:Z
       4: ifeq          12
       7: aload_1
       8: invokestatic  #23                 // Method io/reactivex/rxjava3/plugins/RxJavaPlugins.onError:(Ljava/lang/Throwable;)V
      11: return
      12: aload_0
      13: iconst_1
      14: putfield      #10                 // Field done:Z
      17: aload_0
      18: getfield      #2                  // Field downstream:Lio/reactivex/rxjava3/core/Observer;
      21: aload_1
      22: invokeinterface #22,  2           // InterfaceMethod io/reactivex/rxjava3/core/Observer.onError:(Ljava/lang/Throwable;)V
      27: return

  public void onComplete();
    Code:
       0: aload_0
       1: getfield      #10                 // Field done:Z
       4: ifeq          8
       7: return
       8: aload_0
       9: iconst_1
      10: putfield      #10                 // Field done:Z
      13: aload_0
      14: getfield      #2                  // Field downstream:Lio/reactivex/rxjava3/core/Observer;
      17: invokeinterface #21,  1           // InterfaceMethod io/reactivex/rxjava3/core/Observer.onComplete:()V
      22: return
}
