Compiled from "ObservableRepeat.java"
public final class io.reactivex.rxjava3.internal.operators.observable.ObservableRepeat<T> extends io.reactivex.rxjava3.internal.operators.observable.AbstractObservableWithUpstream<T, T> {
  final long count;

  public io.reactivex.rxjava3.internal.operators.observable.ObservableRepeat(io.reactivex.rxjava3.core.Observable<T>, long);
    Code:
       0: aload_0
       1: aload_1
       2: invokespecial #1                  // Method io/reactivex/rxjava3/internal/operators/observable/AbstractObservableWithUpstream."<init>":(Lio/reactivex/rxjava3/core/ObservableSource;)V
       5: aload_0
       6: lload_2
       7: putfield      #2                  // Field count:J
      10: return

  public void subscribeActual(io.reactivex.rxjava3.core.Observer<? super T>);
    Code:
       0: new           #3                  // class io/reactivex/rxjava3/internal/disposables/SequentialDisposable
       3: dup
       4: invokespecial #4                  // Method io/reactivex/rxjava3/internal/disposables/SequentialDisposable."<init>":()V
       7: astore_2
       8: aload_1
       9: aload_2
      10: invokeinterface #5,  2            // InterfaceMethod io/reactivex/rxjava3/core/Observer.onSubscribe:(Lio/reactivex/rxjava3/disposables/Disposable;)V
      15: new           #6                  // class io/reactivex/rxjava3/internal/operators/observable/ObservableRepeat$RepeatObserver
      18: dup
      19: aload_1
      20: aload_0
      21: getfield      #2                  // Field count:J
      24: ldc2_w        #8                  // long 9223372036854775807l
      27: lcmp
      28: ifeq          40
      31: aload_0
      32: getfield      #2                  // Field count:J
      35: lconst_1
      36: lsub
      37: goto          43
      40: ldc2_w        #8                  // long 9223372036854775807l
      43: aload_2
      44: aload_0
      45: getfield      #10                 // Field source:Lio/reactivex/rxjava3/core/ObservableSource;
      48: invokespecial #11                 // Method io/reactivex/rxjava3/internal/operators/observable/ObservableRepeat$RepeatObserver."<init>":(Lio/reactivex/rxjava3/core/Observer;JLio/reactivex/rxjava3/internal/disposables/SequentialDisposable;Lio/reactivex/rxjava3/core/ObservableSource;)V
      51: astore_3
      52: aload_3
      53: invokevirtual #12                 // Method io/reactivex/rxjava3/internal/operators/observable/ObservableRepeat$RepeatObserver.subscribeNext:()V
      56: return
}
