Compiled from "ObservableSubscribeOn.java"
public final class io.reactivex.rxjava3.internal.operators.observable.ObservableSubscribeOn<T> extends io.reactivex.rxjava3.internal.operators.observable.AbstractObservableWithUpstream<T, T> {
  final io.reactivex.rxjava3.core.Scheduler scheduler;

  public io.reactivex.rxjava3.internal.operators.observable.ObservableSubscribeOn(io.reactivex.rxjava3.core.ObservableSource<T>, io.reactivex.rxjava3.core.Scheduler);
    Code:
       0: aload_0
       1: aload_1
       2: invokespecial #1                  // Method io/reactivex/rxjava3/internal/operators/observable/AbstractObservableWithUpstream."<init>":(Lio/reactivex/rxjava3/core/ObservableSource;)V
       5: aload_0
       6: aload_2
       7: putfield      #2                  // Field scheduler:Lio/reactivex/rxjava3/core/Scheduler;
      10: return

  public void subscribeActual(io.reactivex.rxjava3.core.Observer<? super T>);
    Code:
       0: new           #3                  // class io/reactivex/rxjava3/internal/operators/observable/ObservableSubscribeOn$SubscribeOnObserver
       3: dup
       4: aload_1
       5: invokespecial #4                  // Method io/reactivex/rxjava3/internal/operators/observable/ObservableSubscribeOn$SubscribeOnObserver."<init>":(Lio/reactivex/rxjava3/core/Observer;)V
       8: astore_2
       9: aload_1
      10: aload_2
      11: invokeinterface #5,  2            // InterfaceMethod io/reactivex/rxjava3/core/Observer.onSubscribe:(Lio/reactivex/rxjava3/disposables/Disposable;)V
      16: aload_2
      17: aload_0
      18: getfield      #2                  // Field scheduler:Lio/reactivex/rxjava3/core/Scheduler;
      21: new           #6                  // class io/reactivex/rxjava3/internal/operators/observable/ObservableSubscribeOn$SubscribeTask
      24: dup
      25: aload_0
      26: aload_2
      27: invokespecial #7                  // Method io/reactivex/rxjava3/internal/operators/observable/ObservableSubscribeOn$SubscribeTask."<init>":(Lio/reactivex/rxjava3/internal/operators/observable/ObservableSubscribeOn;Lio/reactivex/rxjava3/internal/operators/observable/ObservableSubscribeOn$SubscribeOnObserver;)V
      30: invokevirtual #8                  // Method io/reactivex/rxjava3/core/Scheduler.scheduleDirect:(Ljava/lang/Runnable;)Lio/reactivex/rxjava3/disposables/Disposable;
      33: invokevirtual #9                  // Method io/reactivex/rxjava3/internal/operators/observable/ObservableSubscribeOn$SubscribeOnObserver.setDisposable:(Lio/reactivex/rxjava3/disposables/Disposable;)V
      36: return
}
