Compiled from "ObservableSequenceEqualSingle.java"
final class io.reactivex.rxjava3.internal.operators.observable.ObservableSequenceEqualSingle$EqualObserver<T> implements io.reactivex.rxjava3.core.Observer<T> {
  final io.reactivex.rxjava3.internal.operators.observable.ObservableSequenceEqualSingle$EqualCoordinator<T> parent;

  final io.reactivex.rxjava3.operators.SpscLinkedArrayQueue<T> queue;

  final int index;

  volatile boolean done;

  java.lang.Throwable error;

  io.reactivex.rxjava3.internal.operators.observable.ObservableSequenceEqualSingle$EqualObserver(io.reactivex.rxjava3.internal.operators.observable.ObservableSequenceEqualSingle$EqualCoordinator<T>, int, int);
    Code:
       0: aload_0
       1: invokespecial #1                  // Method java/lang/Object."<init>":()V
       4: aload_0
       5: aload_1
       6: putfield      #2                  // Field parent:Lio/reactivex/rxjava3/internal/operators/observable/ObservableSequenceEqualSingle$EqualCoordinator;
       9: aload_0
      10: iload_2
      11: putfield      #3                  // Field index:I
      14: aload_0
      15: new           #4                  // class io/reactivex/rxjava3/operators/SpscLinkedArrayQueue
      18: dup
      19: iload_3
      20: invokespecial #5                  // Method io/reactivex/rxjava3/operators/SpscLinkedArrayQueue."<init>":(I)V
      23: putfield      #6                  // Field queue:Lio/reactivex/rxjava3/operators/SpscLinkedArrayQueue;
      26: return

  public void onSubscribe(io.reactivex.rxjava3.disposables.Disposable);
    Code:
       0: aload_0
       1: getfield      #2                  // Field parent:Lio/reactivex/rxjava3/internal/operators/observable/ObservableSequenceEqualSingle$EqualCoordinator;
       4: aload_1
       5: aload_0
       6: getfield      #3                  // Field index:I
       9: invokevirtual #7                  // Method io/reactivex/rxjava3/internal/operators/observable/ObservableSequenceEqualSingle$EqualCoordinator.setDisposable:(Lio/reactivex/rxjava3/disposables/Disposable;I)Z
      12: pop
      13: return

  public void onNext(T);
    Code:
       0: aload_0
       1: getfield      #6                  // Field queue:Lio/reactivex/rxjava3/operators/SpscLinkedArrayQueue;
       4: aload_1
       5: invokevirtual #8                  // Method io/reactivex/rxjava3/operators/SpscLinkedArrayQueue.offer:(Ljava/lang/Object;)Z
       8: pop
       9: aload_0
      10: getfield      #2                  // Field parent:Lio/reactivex/rxjava3/internal/operators/observable/ObservableSequenceEqualSingle$EqualCoordinator;
      13: invokevirtual #9                  // Method io/reactivex/rxjava3/internal/operators/observable/ObservableSequenceEqualSingle$EqualCoordinator.drain:()V
      16: return

  public void onError(java.lang.Throwable);
    Code:
       0: aload_0
       1: aload_1
       2: putfield      #10                 // Field error:Ljava/lang/Throwable;
       5: aload_0
       6: iconst_1
       7: putfield      #11                 // Field done:Z
      10: aload_0
      11: getfield      #2                  // Field parent:Lio/reactivex/rxjava3/internal/operators/observable/ObservableSequenceEqualSingle$EqualCoordinator;
      14: invokevirtual #9                  // Method io/reactivex/rxjava3/internal/operators/observable/ObservableSequenceEqualSingle$EqualCoordinator.drain:()V
      17: return

  public void onComplete();
    Code:
       0: aload_0
       1: iconst_1
       2: putfield      #11                 // Field done:Z
       5: aload_0
       6: getfield      #2                  // Field parent:Lio/reactivex/rxjava3/internal/operators/observable/ObservableSequenceEqualSingle$EqualCoordinator;
       9: invokevirtual #9                  // Method io/reactivex/rxjava3/internal/operators/observable/ObservableSequenceEqualSingle$EqualCoordinator.drain:()V
      12: return
}
