Compiled from "ObservableInternalHelper.java"
final class io.reactivex.rxjava3.internal.operators.observable.ObservableInternalHelper$BufferedReplaySupplier<T> implements io.reactivex.rxjava3.functions.Supplier<io.reactivex.rxjava3.observables.ConnectableObservable<T>> {
  final io.reactivex.rxjava3.core.Observable<T> parent;

  final int bufferSize;

  final boolean eagerTruncate;

  io.reactivex.rxjava3.internal.operators.observable.ObservableInternalHelper$BufferedReplaySupplier(io.reactivex.rxjava3.core.Observable<T>, int, boolean);
    Code:
       0: aload_0
       1: invokespecial #1                  // Method java/lang/Object."<init>":()V
       4: aload_0
       5: aload_1
       6: putfield      #2                  // Field parent:Lio/reactivex/rxjava3/core/Observable;
       9: aload_0
      10: iload_2
      11: putfield      #3                  // Field bufferSize:I
      14: aload_0
      15: iload_3
      16: putfield      #4                  // Field eagerTruncate:Z
      19: return

  public io.reactivex.rxjava3.observables.ConnectableObservable<T> get();
    Code:
       0: aload_0
       1: getfield      #2                  // Field parent:Lio/reactivex/rxjava3/core/Observable;
       4: aload_0
       5: getfield      #3                  // Field bufferSize:I
       8: aload_0
       9: getfield      #4                  // Field eagerTruncate:Z
      12: invokevirtual #5                  // Method io/reactivex/rxjava3/core/Observable.replay:(IZ)Lio/reactivex/rxjava3/observables/ConnectableObservable;
      15: areturn

  public java.lang.Object get() throws java.lang.Throwable;
    Code:
       0: aload_0
       1: invokevirtual #6                  // Method get:()Lio/reactivex/rxjava3/observables/ConnectableObservable;
       4: areturn
}
