Compiled from "ObservableDelaySubscriptionOther.java"
final class io.reactivex.rxjava3.internal.operators.observable.ObservableDelaySubscriptionOther$DelayObserver implements io.reactivex.rxjava3.core.Observer<U> {
  final io.reactivex.rxjava3.internal.disposables.SequentialDisposable serial;

  final io.reactivex.rxjava3.core.Observer<? super T> child;

  boolean done;

  final io.reactivex.rxjava3.internal.operators.observable.ObservableDelaySubscriptionOther this$0;

  io.reactivex.rxjava3.internal.operators.observable.ObservableDelaySubscriptionOther$DelayObserver(io.reactivex.rxjava3.internal.disposables.SequentialDisposable, io.reactivex.rxjava3.core.Observer<? super T>);
    Code:
       0: aload_0
       1: aload_1
       2: putfield      #1                  // Field this$0:Lio/reactivex/rxjava3/internal/operators/observable/ObservableDelaySubscriptionOther;
       5: aload_0
       6: invokespecial #2                  // Method java/lang/Object."<init>":()V
       9: aload_0
      10: aload_2
      11: putfield      #3                  // Field serial:Lio/reactivex/rxjava3/internal/disposables/SequentialDisposable;
      14: aload_0
      15: aload_3
      16: putfield      #4                  // Field child:Lio/reactivex/rxjava3/core/Observer;
      19: return

  public void onSubscribe(io.reactivex.rxjava3.disposables.Disposable);
    Code:
       0: aload_0
       1: getfield      #3                  // Field serial:Lio/reactivex/rxjava3/internal/disposables/SequentialDisposable;
       4: aload_1
       5: invokevirtual #5                  // Method io/reactivex/rxjava3/internal/disposables/SequentialDisposable.update:(Lio/reactivex/rxjava3/disposables/Disposable;)Z
       8: pop
       9: return

  public void onNext(U);
    Code:
       0: aload_0
       1: invokevirtual #6                  // Method onComplete:()V
       4: return

  public void onError(java.lang.Throwable);
    Code:
       0: aload_0
       1: getfield      #7                  // Field done:Z
       4: ifeq          12
       7: aload_1
       8: invokestatic  #8                  // Method io/reactivex/rxjava3/plugins/RxJavaPlugins.onError:(Ljava/lang/Throwable;)V
      11: return
      12: aload_0
      13: iconst_1
      14: putfield      #7                  // Field done:Z
      17: aload_0
      18: getfield      #4                  // Field child:Lio/reactivex/rxjava3/core/Observer;
      21: aload_1
      22: invokeinterface #9,  2            // InterfaceMethod io/reactivex/rxjava3/core/Observer.onError:(Ljava/lang/Throwable;)V
      27: return

  public void onComplete();
    Code:
       0: aload_0
       1: getfield      #7                  // Field done:Z
       4: ifeq          8
       7: return
       8: aload_0
       9: iconst_1
      10: putfield      #7                  // Field done:Z
      13: aload_0
      14: getfield      #1                  // Field this$0:Lio/reactivex/rxjava3/internal/operators/observable/ObservableDelaySubscriptionOther;
      17: getfield      #10                 // Field io/reactivex/rxjava3/internal/operators/observable/ObservableDelaySubscriptionOther.main:Lio/reactivex/rxjava3/core/ObservableSource;
      20: new           #11                 // class io/reactivex/rxjava3/internal/operators/observable/ObservableDelaySubscriptionOther$DelayObserver$OnComplete
      23: dup
      24: aload_0
      25: invokespecial #12                 // Method io/reactivex/rxjava3/internal/operators/observable/ObservableDelaySubscriptionOther$DelayObserver$OnComplete."<init>":(Lio/reactivex/rxjava3/internal/operators/observable/ObservableDelaySubscriptionOther$DelayObserver;)V
      28: invokeinterface #13,  2           // InterfaceMethod io/reactivex/rxjava3/core/ObservableSource.subscribe:(Lio/reactivex/rxjava3/core/Observer;)V
      33: return
}
