Compiled from "ObservableFromIterable.java"
public final class io.reactivex.rxjava3.internal.operators.observable.ObservableFromIterable<T> extends io.reactivex.rxjava3.core.Observable<T> {
  final java.lang.Iterable<? extends T> source;

  public io.reactivex.rxjava3.internal.operators.observable.ObservableFromIterable(java.lang.Iterable<? extends T>);
    Code:
       0: aload_0
       1: invokespecial #1                  // Method io/reactivex/rxjava3/core/Observable."<init>":()V
       4: aload_0
       5: aload_1
       6: putfield      #2                  // Field source:Ljava/lang/Iterable;
       9: return

  public void subscribeActual(io.reactivex.rxjava3.core.Observer<? super T>);
    Code:
       0: aload_0
       1: getfield      #2                  // Field source:Ljava/lang/Iterable;
       4: invokeinterface #3,  1            // InterfaceMethod java/lang/Iterable.iterator:()Ljava/util/Iterator;
       9: astore_2
      10: goto          24
      13: astore_3
      14: aload_3
      15: invokestatic  #5                  // Method io/reactivex/rxjava3/exceptions/Exceptions.throwIfFatal:(Ljava/lang/Throwable;)V
      18: aload_3
      19: aload_1
      20: invokestatic  #6                  // Method io/reactivex/rxjava3/internal/disposables/EmptyDisposable.error:(Ljava/lang/Throwable;Lio/reactivex/rxjava3/core/Observer;)V
      23: return
      24: aload_2
      25: invokeinterface #7,  1            // InterfaceMethod java/util/Iterator.hasNext:()Z
      30: istore_3
      31: goto          48
      34: astore        4
      36: aload         4
      38: invokestatic  #5                  // Method io/reactivex/rxjava3/exceptions/Exceptions.throwIfFatal:(Ljava/lang/Throwable;)V
      41: aload         4
      43: aload_1
      44: invokestatic  #6                  // Method io/reactivex/rxjava3/internal/disposables/EmptyDisposable.error:(Ljava/lang/Throwable;Lio/reactivex/rxjava3/core/Observer;)V
      47: return
      48: iload_3
      49: ifne          57
      52: aload_1
      53: invokestatic  #8                  // Method io/reactivex/rxjava3/internal/disposables/EmptyDisposable.complete:(Lio/reactivex/rxjava3/core/Observer;)V
      56: return
      57: new           #9                  // class io/reactivex/rxjava3/internal/operators/observable/ObservableFromIterable$FromIterableDisposable
      60: dup
      61: aload_1
      62: aload_2
      63: invokespecial #10                 // Method io/reactivex/rxjava3/internal/operators/observable/ObservableFromIterable$FromIterableDisposable."<init>":(Lio/reactivex/rxjava3/core/Observer;Ljava/util/Iterator;)V
      66: astore        4
      68: aload_1
      69: aload         4
      71: invokeinterface #11,  2           // InterfaceMethod io/reactivex/rxjava3/core/Observer.onSubscribe:(Lio/reactivex/rxjava3/disposables/Disposable;)V
      76: aload         4
      78: getfield      #12                 // Field io/reactivex/rxjava3/internal/operators/observable/ObservableFromIterable$FromIterableDisposable.fusionMode:Z
      81: ifne          89
      84: aload         4
      86: invokevirtual #13                 // Method io/reactivex/rxjava3/internal/operators/observable/ObservableFromIterable$FromIterableDisposable.run:()V
      89: return
    Exception table:
       from    to  target type
           0    10    13   Class java/lang/Throwable
          24    31    34   Class java/lang/Throwable
}
