Compiled from "ObservableSingleSingle.java"
public final class io.reactivex.rxjava3.internal.operators.observable.ObservableSingleSingle<T> extends io.reactivex.rxjava3.core.Single<T> {
  final io.reactivex.rxjava3.core.ObservableSource<? extends T> source;

  final T defaultValue;

  public io.reactivex.rxjava3.internal.operators.observable.ObservableSingleSingle(io.reactivex.rxjava3.core.ObservableSource<? extends T>, T);
    Code:
       0: aload_0
       1: invokespecial #1                  // Method io/reactivex/rxjava3/core/Single."<init>":()V
       4: aload_0
       5: aload_1
       6: putfield      #2                  // Field source:Lio/reactivex/rxjava3/core/ObservableSource;
       9: aload_0
      10: aload_2
      11: putfield      #3                  // Field defaultValue:Ljava/lang/Object;
      14: return

  public void subscribeActual(io.reactivex.rxjava3.core.SingleObserver<? super T>);
    Code:
       0: aload_0
       1: getfield      #2                  // Field source:Lio/reactivex/rxjava3/core/ObservableSource;
       4: new           #4                  // class io/reactivex/rxjava3/internal/operators/observable/ObservableSingleSingle$SingleElementObserver
       7: dup
       8: aload_1
       9: aload_0
      10: getfield      #3                  // Field defaultValue:Ljava/lang/Object;
      13: invokespecial #5                  // Method io/reactivex/rxjava3/internal/operators/observable/ObservableSingleSingle$SingleElementObserver."<init>":(Lio/reactivex/rxjava3/core/SingleObserver;Ljava/lang/Object;)V
      16: invokeinterface #6,  2            // InterfaceMethod io/reactivex/rxjava3/core/ObservableSource.subscribe:(Lio/reactivex/rxjava3/core/Observer;)V
      21: return
}
