Compiled from "ObservableToListSingle.java"
public final class io.reactivex.rxjava3.internal.operators.observable.ObservableToListSingle<T, U extends java.util.Collection<? super T>> extends io.reactivex.rxjava3.core.Single<U> implements io.reactivex.rxjava3.internal.fuseable.FuseToObservable<U> {
  final io.reactivex.rxjava3.core.ObservableSource<T> source;

  final io.reactivex.rxjava3.functions.Supplier<U> collectionSupplier;

  public io.reactivex.rxjava3.internal.operators.observable.ObservableToListSingle(io.reactivex.rxjava3.core.ObservableSource<T>, int);
    Code:
       0: aload_0
       1: invokespecial #1                  // Method io/reactivex/rxjava3/core/Single."<init>":()V
       4: aload_0
       5: aload_1
       6: putfield      #2                  // Field source:Lio/reactivex/rxjava3/core/ObservableSource;
       9: aload_0
      10: iload_2
      11: invokestatic  #3                  // Method io/reactivex/rxjava3/internal/functions/Functions.createArrayList:(I)Lio/reactivex/rxjava3/functions/Supplier;
      14: putfield      #4                  // Field collectionSupplier:Lio/reactivex/rxjava3/functions/Supplier;
      17: return

  public io.reactivex.rxjava3.internal.operators.observable.ObservableToListSingle(io.reactivex.rxjava3.core.ObservableSource<T>, io.reactivex.rxjava3.functions.Supplier<U>);
    Code:
       0: aload_0
       1: invokespecial #1                  // Method io/reactivex/rxjava3/core/Single."<init>":()V
       4: aload_0
       5: aload_1
       6: putfield      #2                  // Field source:Lio/reactivex/rxjava3/core/ObservableSource;
       9: aload_0
      10: aload_2
      11: putfield      #4                  // Field collectionSupplier:Lio/reactivex/rxjava3/functions/Supplier;
      14: return

  public void subscribeActual(io.reactivex.rxjava3.core.SingleObserver<? super U>);
    Code:
       0: aload_0
       1: getfield      #4                  // Field collectionSupplier:Lio/reactivex/rxjava3/functions/Supplier;
       4: invokeinterface #5,  1            // InterfaceMethod io/reactivex/rxjava3/functions/Supplier.get:()Ljava/lang/Object;
       9: ldc           #6                  // String The collectionSupplier returned a null Collection.
      11: invokestatic  #7                  // Method io/reactivex/rxjava3/internal/util/ExceptionHelper.nullCheck:(Ljava/lang/Object;Ljava/lang/String;)Ljava/lang/Object;
      14: checkcast     #8                  // class java/util/Collection
      17: astore_2
      18: goto          32
      21: astore_3
      22: aload_3
      23: invokestatic  #10                 // Method io/reactivex/rxjava3/exceptions/Exceptions.throwIfFatal:(Ljava/lang/Throwable;)V
      26: aload_3
      27: aload_1
      28: invokestatic  #11                 // Method io/reactivex/rxjava3/internal/disposables/EmptyDisposable.error:(Ljava/lang/Throwable;Lio/reactivex/rxjava3/core/SingleObserver;)V
      31: return
      32: aload_0
      33: getfield      #2                  // Field source:Lio/reactivex/rxjava3/core/ObservableSource;
      36: new           #12                 // class io/reactivex/rxjava3/internal/operators/observable/ObservableToListSingle$ToListObserver
      39: dup
      40: aload_1
      41: aload_2
      42: invokespecial #13                 // Method io/reactivex/rxjava3/internal/operators/observable/ObservableToListSingle$ToListObserver."<init>":(Lio/reactivex/rxjava3/core/SingleObserver;Ljava/util/Collection;)V
      45: invokeinterface #14,  2           // InterfaceMethod io/reactivex/rxjava3/core/ObservableSource.subscribe:(Lio/reactivex/rxjava3/core/Observer;)V
      50: return
    Exception table:
       from    to  target type
           0    18    21   Class java/lang/Throwable

  public io.reactivex.rxjava3.core.Observable<U> fuseToObservable();
    Code:
       0: new           #15                 // class io/reactivex/rxjava3/internal/operators/observable/ObservableToList
       3: dup
       4: aload_0
       5: getfield      #2                  // Field source:Lio/reactivex/rxjava3/core/ObservableSource;
       8: aload_0
       9: getfield      #4                  // Field collectionSupplier:Lio/reactivex/rxjava3/functions/Supplier;
      12: invokespecial #16                 // Method io/reactivex/rxjava3/internal/operators/observable/ObservableToList."<init>":(Lio/reactivex/rxjava3/core/ObservableSource;Lio/reactivex/rxjava3/functions/Supplier;)V
      15: invokestatic  #17                 // Method io/reactivex/rxjava3/plugins/RxJavaPlugins.onAssembly:(Lio/reactivex/rxjava3/core/Observable;)Lio/reactivex/rxjava3/core/Observable;
      18: areturn
}
