Compiled from "ObservableMapNotification.java"
public final class io.reactivex.rxjava3.internal.operators.observable.ObservableMapNotification<T, R> extends io.reactivex.rxjava3.internal.operators.observable.AbstractObservableWithUpstream<T, io.reactivex.rxjava3.core.ObservableSource<? extends R>> {
  final io.reactivex.rxjava3.functions.Function<? super T, ? extends io.reactivex.rxjava3.core.ObservableSource<? extends R>> onNextMapper;

  final io.reactivex.rxjava3.functions.Function<? super java.lang.Throwable, ? extends io.reactivex.rxjava3.core.ObservableSource<? extends R>> onErrorMapper;

  final io.reactivex.rxjava3.functions.Supplier<? extends io.reactivex.rxjava3.core.ObservableSource<? extends R>> onCompleteSupplier;

  public io.reactivex.rxjava3.internal.operators.observable.ObservableMapNotification(io.reactivex.rxjava3.core.ObservableSource<T>, io.reactivex.rxjava3.functions.Function<? super T, ? extends io.reactivex.rxjava3.core.ObservableSource<? extends R>>, io.reactivex.rxjava3.functions.Function<? super java.lang.Throwable, ? extends io.reactivex.rxjava3.core.ObservableSource<? extends R>>, io.reactivex.rxjava3.functions.Supplier<? extends io.reactivex.rxjava3.core.ObservableSource<? extends R>>);
    Code:
       0: aload_0
       1: aload_1
       2: invokespecial #1                  // Method io/reactivex/rxjava3/internal/operators/observable/AbstractObservableWithUpstream."<init>":(Lio/reactivex/rxjava3/core/ObservableSource;)V
       5: aload_0
       6: aload_2
       7: putfield      #2                  // Field onNextMapper:Lio/reactivex/rxjava3/functions/Function;
      10: aload_0
      11: aload_3
      12: putfield      #3                  // Field onErrorMapper:Lio/reactivex/rxjava3/functions/Function;
      15: aload_0
      16: aload         4
      18: putfield      #4                  // Field onCompleteSupplier:Lio/reactivex/rxjava3/functions/Supplier;
      21: return

  public void subscribeActual(io.reactivex.rxjava3.core.Observer<? super io.reactivex.rxjava3.core.ObservableSource<? extends R>>);
    Code:
       0: aload_0
       1: getfield      #5                  // Field source:Lio/reactivex/rxjava3/core/ObservableSource;
       4: new           #6                  // class io/reactivex/rxjava3/internal/operators/observable/ObservableMapNotification$MapNotificationObserver
       7: dup
       8: aload_1
       9: aload_0
      10: getfield      #2                  // Field onNextMapper:Lio/reactivex/rxjava3/functions/Function;
      13: aload_0
      14: getfield      #3                  // Field onErrorMapper:Lio/reactivex/rxjava3/functions/Function;
      17: aload_0
      18: getfield      #4                  // Field onCompleteSupplier:Lio/reactivex/rxjava3/functions/Supplier;
      21: invokespecial #7                  // Method io/reactivex/rxjava3/internal/operators/observable/ObservableMapNotification$MapNotificationObserver."<init>":(Lio/reactivex/rxjava3/core/Observer;Lio/reactivex/rxjava3/functions/Function;Lio/reactivex/rxjava3/functions/Function;Lio/reactivex/rxjava3/functions/Supplier;)V
      24: invokeinterface #8,  2            // InterfaceMethod io/reactivex/rxjava3/core/ObservableSource.subscribe:(Lio/reactivex/rxjava3/core/Observer;)V
      29: return
}
