Compiled from "ObservableDelay.java"
final class io.reactivex.rxjava3.internal.operators.observable.ObservableDelay$DelayObserver<T> implements io.reactivex.rxjava3.core.Observer<T>, io.reactivex.rxjava3.disposables.Disposable {
  final io.reactivex.rxjava3.core.Observer<? super T> downstream;

  final long delay;

  final java.util.concurrent.TimeUnit unit;

  final io.reactivex.rxjava3.core.Scheduler$Worker w;

  final boolean delayError;

  io.reactivex.rxjava3.disposables.Disposable upstream;

  io.reactivex.rxjava3.internal.operators.observable.ObservableDelay$DelayObserver(io.reactivex.rxjava3.core.Observer<? super T>, long, java.util.concurrent.TimeUnit, io.reactivex.rxjava3.core.Scheduler$Worker, boolean);
    Code:
       0: aload_0
       1: invokespecial #1                  // Method java/lang/Object."<init>":()V
       4: aload_0
       5: aload_1
       6: putfield      #2                  // Field downstream:Lio/reactivex/rxjava3/core/Observer;
       9: aload_0
      10: lload_2
      11: putfield      #3                  // Field delay:J
      14: aload_0
      15: aload         4
      17: putfield      #4                  // Field unit:Ljava/util/concurrent/TimeUnit;
      20: aload_0
      21: aload         5
      23: putfield      #5                  // Field w:Lio/reactivex/rxjava3/core/Scheduler$Worker;
      26: aload_0
      27: iload         6
      29: putfield      #6                  // Field delayError:Z
      32: return

  public void onSubscribe(io.reactivex.rxjava3.disposables.Disposable);
    Code:
       0: aload_0
       1: getfield      #7                  // Field upstream:Lio/reactivex/rxjava3/disposables/Disposable;
       4: aload_1
       5: invokestatic  #8                  // Method io/reactivex/rxjava3/internal/disposables/DisposableHelper.validate:(Lio/reactivex/rxjava3/disposables/Disposable;Lio/reactivex/rxjava3/disposables/Disposable;)Z
       8: ifeq          26
      11: aload_0
      12: aload_1
      13: putfield      #7                  // Field upstream:Lio/reactivex/rxjava3/disposables/Disposable;
      16: aload_0
      17: getfield      #2                  // Field downstream:Lio/reactivex/rxjava3/core/Observer;
      20: aload_0
      21: invokeinterface #9,  2            // InterfaceMethod io/reactivex/rxjava3/core/Observer.onSubscribe:(Lio/reactivex/rxjava3/disposables/Disposable;)V
      26: return

  public void onNext(T);
    Code:
       0: aload_0
       1: getfield      #5                  // Field w:Lio/reactivex/rxjava3/core/Scheduler$Worker;
       4: new           #10                 // class io/reactivex/rxjava3/internal/operators/observable/ObservableDelay$DelayObserver$OnNext
       7: dup
       8: aload_0
       9: aload_1
      10: invokespecial #11                 // Method io/reactivex/rxjava3/internal/operators/observable/ObservableDelay$DelayObserver$OnNext."<init>":(Lio/reactivex/rxjava3/internal/operators/observable/ObservableDelay$DelayObserver;Ljava/lang/Object;)V
      13: aload_0
      14: getfield      #3                  // Field delay:J
      17: aload_0
      18: getfield      #4                  // Field unit:Ljava/util/concurrent/TimeUnit;
      21: invokevirtual #12                 // Method io/reactivex/rxjava3/core/Scheduler$Worker.schedule:(Ljava/lang/Runnable;JLjava/util/concurrent/TimeUnit;)Lio/reactivex/rxjava3/disposables/Disposable;
      24: pop
      25: return

  public void onError(java.lang.Throwable);
    Code:
       0: aload_0
       1: getfield      #5                  // Field w:Lio/reactivex/rxjava3/core/Scheduler$Worker;
       4: new           #13                 // class io/reactivex/rxjava3/internal/operators/observable/ObservableDelay$DelayObserver$OnError
       7: dup
       8: aload_0
       9: aload_1
      10: invokespecial #14                 // Method io/reactivex/rxjava3/internal/operators/observable/ObservableDelay$DelayObserver$OnError."<init>":(Lio/reactivex/rxjava3/internal/operators/observable/ObservableDelay$DelayObserver;Ljava/lang/Throwable;)V
      13: aload_0
      14: getfield      #6                  // Field delayError:Z
      17: ifeq          27
      20: aload_0
      21: getfield      #3                  // Field delay:J
      24: goto          28
      27: lconst_0
      28: aload_0
      29: getfield      #4                  // Field unit:Ljava/util/concurrent/TimeUnit;
      32: invokevirtual #12                 // Method io/reactivex/rxjava3/core/Scheduler$Worker.schedule:(Ljava/lang/Runnable;JLjava/util/concurrent/TimeUnit;)Lio/reactivex/rxjava3/disposables/Disposable;
      35: pop
      36: return

  public void onComplete();
    Code:
       0: aload_0
       1: getfield      #5                  // Field w:Lio/reactivex/rxjava3/core/Scheduler$Worker;
       4: new           #15                 // class io/reactivex/rxjava3/internal/operators/observable/ObservableDelay$DelayObserver$OnComplete
       7: dup
       8: aload_0
       9: invokespecial #16                 // Method io/reactivex/rxjava3/internal/operators/observable/ObservableDelay$DelayObserver$OnComplete."<init>":(Lio/reactivex/rxjava3/internal/operators/observable/ObservableDelay$DelayObserver;)V
      12: aload_0
      13: getfield      #3                  // Field delay:J
      16: aload_0
      17: getfield      #4                  // Field unit:Ljava/util/concurrent/TimeUnit;
      20: invokevirtual #12                 // Method io/reactivex/rxjava3/core/Scheduler$Worker.schedule:(Ljava/lang/Runnable;JLjava/util/concurrent/TimeUnit;)Lio/reactivex/rxjava3/disposables/Disposable;
      23: pop
      24: return

  public void dispose();
    Code:
       0: aload_0
       1: getfield      #7                  // Field upstream:Lio/reactivex/rxjava3/disposables/Disposable;
       4: invokeinterface #17,  1           // InterfaceMethod io/reactivex/rxjava3/disposables/Disposable.dispose:()V
       9: aload_0
      10: getfield      #5                  // Field w:Lio/reactivex/rxjava3/core/Scheduler$Worker;
      13: invokevirtual #18                 // Method io/reactivex/rxjava3/core/Scheduler$Worker.dispose:()V
      16: return

  public boolean isDisposed();
    Code:
       0: aload_0
       1: getfield      #5                  // Field w:Lio/reactivex/rxjava3/core/Scheduler$Worker;
       4: invokevirtual #19                 // Method io/reactivex/rxjava3/core/Scheduler$Worker.isDisposed:()Z
       7: ireturn
}
