Compiled from "ErrorPageFilterConfiguration.java"
class org.springframework.boot.web.servlet.support.ErrorPageFilterConfiguration {
  org.springframework.boot.web.servlet.support.ErrorPageFilterConfiguration();
    Code:
       0: aload_0
       1: invokespecial #1                  // Method java/lang/Object."<init>":()V
       4: return

  org.springframework.boot.web.servlet.support.ErrorPageFilter errorPageFilter();
    Code:
       0: new           #7                  // class org/springframework/boot/web/servlet/support/ErrorPageFilter
       3: dup
       4: invokespecial #9                  // Method org/springframework/boot/web/servlet/support/ErrorPageFilter."<init>":()V
       7: areturn

  org.springframework.boot.web.servlet.FilterRegistrationBean<org.springframework.boot.web.servlet.support.ErrorPageFilter> errorPageFilterRegistration(org.springframework.boot.web.servlet.support.ErrorPageFilter);
    Code:
       0: new           #10                 // class org/springframework/boot/web/servlet/FilterRegistrationBean
       3: dup
       4: aload_1
       5: iconst_0
       6: anewarray     #12                 // class org/springframework/boot/web/servlet/ServletRegistrationBean
       9: invokespecial #14                 // Method org/springframework/boot/web/servlet/FilterRegistrationBean."<init>":(Ljakarta/servlet/Filter;[Lorg/springframework/boot/web/servlet/ServletRegistrationBean;)V
      12: astore_2
      13: aload_2
      14: aload_1
      15: invokevirtual #17                 // Method org/springframework/boot/web/servlet/support/ErrorPageFilter.getOrder:()I
      18: invokevirtual #21                 // Method org/springframework/boot/web/servlet/FilterRegistrationBean.setOrder:(I)V
      21: aload_2
      22: getstatic     #25                 // Field jakarta/servlet/DispatcherType.REQUEST:Ljakarta/servlet/DispatcherType;
      25: iconst_1
      26: anewarray     #26                 // class jakarta/servlet/DispatcherType
      29: dup
      30: iconst_0
      31: getstatic     #31                 // Field jakarta/servlet/DispatcherType.ASYNC:Ljakarta/servlet/DispatcherType;
      34: aastore
      35: invokevirtual #34                 // Method org/springframework/boot/web/servlet/FilterRegistrationBean.setDispatcherTypes:(Ljakarta/servlet/DispatcherType;[Ljakarta/servlet/DispatcherType;)V
      38: aload_2
      39: areturn
}
