Compiled from "ErrorPageFilter.java"
class org.springframework.boot.web.servlet.support.ErrorPageFilter$1 extends org.springframework.web.filter.OncePerRequestFilter {
  final org.springframework.boot.web.servlet.support.ErrorPageFilter this$0;

  org.springframework.boot.web.servlet.support.ErrorPageFilter$1(org.springframework.boot.web.servlet.support.ErrorPageFilter);
    Code:
       0: aload_0
       1: aload_1
       2: putfield      #1                  // Field this$0:Lorg/springframework/boot/web/servlet/support/ErrorPageFilter;
       5: aload_0
       6: invokespecial #7                  // Method org/springframework/web/filter/OncePerRequestFilter."<init>":()V
       9: return

  protected void doFilterInternal(jakarta.servlet.http.HttpServletRequest, jakarta.servlet.http.HttpServletResponse, jakarta.servlet.FilterChain) throws jakarta.servlet.ServletException, java.io.IOException;
    Code:
       0: aload_0
       1: getfield      #1                  // Field this$0:Lorg/springframework/boot/web/servlet/support/ErrorPageFilter;
       4: aload_1
       5: aload_2
       6: aload_3
       7: invokevirtual #13                 // Method org/springframework/boot/web/servlet/support/ErrorPageFilter.doFilter:(Ljakarta/servlet/http/HttpServletRequest;Ljakarta/servlet/http/HttpServletResponse;Ljakarta/servlet/FilterChain;)V
      10: return

  protected boolean shouldNotFilterAsyncDispatch();
    Code:
       0: iconst_0
       1: ireturn
}
