Compiled from "ServletContextApplicationContextInitializer.java"
public class org.springframework.boot.web.servlet.support.ServletContextApplicationContextInitializer implements org.springframework.context.ApplicationContextInitializer<org.springframework.web.context.ConfigurableWebApplicationContext>, org.springframework.core.Ordered {
  private int order;

  private final jakarta.servlet.ServletContext servletContext;

  private final boolean addApplicationContextAttribute;

  public org.springframework.boot.web.servlet.support.ServletContextApplicationContextInitializer(jakarta.servlet.ServletContext);
    Code:
       0: aload_0
       1: aload_1
       2: iconst_0
       3: invokespecial #1                  // Method "<init>":(Ljakarta/servlet/ServletContext;Z)V
       6: return

  public org.springframework.boot.web.servlet.support.ServletContextApplicationContextInitializer(jakarta.servlet.ServletContext, boolean);
    Code:
       0: aload_0
       1: invokespecial #7                  // Method java/lang/Object."<init>":()V
       4: aload_0
       5: ldc           #14                 // int -2147483648
       7: putfield      #15                 // Field order:I
      10: aload_0
      11: aload_1
      12: putfield      #19                 // Field servletContext:Ljakarta/servlet/ServletContext;
      15: aload_0
      16: iload_2
      17: putfield      #23                 // Field addApplicationContextAttribute:Z
      20: return

  public void setOrder(int);
    Code:
       0: aload_0
       1: iload_1
       2: putfield      #15                 // Field order:I
       5: return

  public int getOrder();
    Code:
       0: aload_0
       1: getfield      #15                 // Field order:I
       4: ireturn

  public void initialize(org.springframework.web.context.ConfigurableWebApplicationContext);
    Code:
       0: aload_1
       1: aload_0
       2: getfield      #19                 // Field servletContext:Ljakarta/servlet/ServletContext;
       5: invokeinterface #27,  2           // InterfaceMethod org/springframework/web/context/ConfigurableWebApplicationContext.setServletContext:(Ljakarta/servlet/ServletContext;)V
      10: aload_0
      11: getfield      #23                 // Field addApplicationContextAttribute:Z
      14: ifeq          30
      17: aload_0
      18: getfield      #19                 // Field servletContext:Ljakarta/servlet/ServletContext;
      21: getstatic     #33                 // Field org/springframework/web/context/WebApplicationContext.ROOT_WEB_APPLICATION_CONTEXT_ATTRIBUTE:Ljava/lang/String;
      24: aload_1
      25: invokeinterface #39,  3           // InterfaceMethod jakarta/servlet/ServletContext.setAttribute:(Ljava/lang/String;Ljava/lang/Object;)V
      30: return

  public void initialize(org.springframework.context.ConfigurableApplicationContext);
    Code:
       0: aload_0
       1: aload_1
       2: checkcast     #28                 // class org/springframework/web/context/ConfigurableWebApplicationContext
       5: invokevirtual #45                 // Method initialize:(Lorg/springframework/web/context/ConfigurableWebApplicationContext;)V
       8: return
}
