Compiled from "ConfigCenterEvent.java"
public class org.apache.dubbo.metrics.config.event.ConfigCenterEvent extends org.apache.dubbo.metrics.event.TimeCounterEvent {
  public static final java.lang.String NACOS_PROTOCOL;

  public static final java.lang.String APOLLO_PROTOCOL;

  public static final java.lang.String ZK_PROTOCOL;

  public org.apache.dubbo.metrics.config.event.ConfigCenterEvent(org.apache.dubbo.rpc.model.ApplicationModel, org.apache.dubbo.metrics.model.key.TypeWrapper);
    Code:
       0: aload_0
       1: aload_1
       2: aload_2
       3: invokespecial #3                  // Method org/apache/dubbo/metrics/event/TimeCounterEvent."<init>":(Lorg/apache/dubbo/rpc/model/ApplicationModel;Lorg/apache/dubbo/metrics/model/key/TypeWrapper;)V
       6: aload_1
       7: invokevirtual #4                  // Method org/apache/dubbo/rpc/model/ApplicationModel.getBeanFactory:()Lorg/apache/dubbo/common/beans/factory/ScopeBeanFactory;
      10: astore_3
      11: aload_3
      12: invokevirtual #5                  // Method org/apache/dubbo/common/beans/factory/ScopeBeanFactory.isDestroyed:()Z
      15: ifne          51
      18: aload_3
      19: ldc           #6                  // class org/apache/dubbo/metrics/config/collector/ConfigCenterMetricsCollector
      21: invokevirtual #7                  // Method org/apache/dubbo/common/beans/factory/ScopeBeanFactory.getBean:(Ljava/lang/Class;)Ljava/lang/Object;
      24: checkcast     #6                  // class org/apache/dubbo/metrics/config/collector/ConfigCenterMetricsCollector
      27: astore        4
      29: aload_0
      30: aload         4
      32: ifnull        47
      35: aload         4
      37: invokevirtual #8                  // Method org/apache/dubbo/metrics/config/collector/ConfigCenterMetricsCollector.isCollectEnabled:()Z
      40: ifeq          47
      43: iconst_1
      44: goto          48
      47: iconst_0
      48: invokespecial #9                  // Method org/apache/dubbo/metrics/event/TimeCounterEvent.setAvailable:(Z)V
      51: return

  public static org.apache.dubbo.metrics.config.event.ConfigCenterEvent toChangeEvent(org.apache.dubbo.rpc.model.ApplicationModel, java.lang.String, java.lang.String, java.lang.String, java.lang.String, int);
    Code:
       0: new           #10                 // class org/apache/dubbo/metrics/config/event/ConfigCenterEvent
       3: dup
       4: aload_0
       5: new           #11                 // class org/apache/dubbo/metrics/model/key/TypeWrapper
       8: dup
       9: getstatic     #12                 // Field org/apache/dubbo/metrics/model/key/MetricsLevel.CONFIG:Lorg/apache/dubbo/metrics/model/key/MetricsLevel;
      12: getstatic     #13                 // Field org/apache/dubbo/metrics/model/key/MetricsKey.CONFIGCENTER_METRIC_TOTAL:Lorg/apache/dubbo/metrics/model/key/MetricsKey;
      15: invokespecial #14                 // Method org/apache/dubbo/metrics/model/key/TypeWrapper."<init>":(Lorg/apache/dubbo/metrics/model/key/MetricsLevel;Lorg/apache/dubbo/metrics/model/key/MetricsKey;)V
      18: invokespecial #15                 // Method "<init>":(Lorg/apache/dubbo/rpc/model/ApplicationModel;Lorg/apache/dubbo/metrics/model/key/TypeWrapper;)V
      21: astore        6
      23: aload         6
      25: ldc           #16                 // String configFileKey
      27: aload_1
      28: invokevirtual #17                 // Method putAttachment:(Ljava/lang/String;Ljava/lang/Object;)V
      31: aload         6
      33: ldc           #18                 // String configGroup
      35: aload_2
      36: invokevirtual #17                 // Method putAttachment:(Ljava/lang/String;Ljava/lang/Object;)V
      39: aload         6
      41: ldc           #19                 // String configProtocol
      43: aload_3
      44: invokevirtual #17                 // Method putAttachment:(Ljava/lang/String;Ljava/lang/Object;)V
      47: aload         6
      49: ldc           #20                 // String configChangeType
      51: aload         4
      53: invokevirtual #17                 // Method putAttachment:(Ljava/lang/String;Ljava/lang/Object;)V
      56: aload         6
      58: ldc           #21                 // String size
      60: iload         5
      62: invokestatic  #22                 // Method java/lang/Integer.valueOf:(I)Ljava/lang/Integer;
      65: invokevirtual #17                 // Method putAttachment:(Ljava/lang/String;Ljava/lang/Object;)V
      68: aload         6
      70: areturn
}
