Compiled from "ConfigCenterSubDispatcher.java"
public final class org.apache.dubbo.metrics.config.event.ConfigCenterSubDispatcher extends org.apache.dubbo.metrics.event.SimpleMetricsEventMulticaster {
  public org.apache.dubbo.metrics.config.event.ConfigCenterSubDispatcher(org.apache.dubbo.metrics.config.collector.ConfigCenterMetricsCollector);
    Code:
       0: aload_0
       1: invokespecial #1                  // Method org/apache/dubbo/metrics/event/SimpleMetricsEventMulticaster."<init>":()V
       4: aload_0
       5: new           #2                  // class org/apache/dubbo/metrics/config/event/ConfigCenterSubDispatcher$1
       8: dup
       9: aload_0
      10: getstatic     #3                  // Field org/apache/dubbo/metrics/model/key/MetricsKey.CONFIGCENTER_METRIC_TOTAL:Lorg/apache/dubbo/metrics/model/key/MetricsKey;
      13: aload_1
      14: invokespecial #4                  // Method org/apache/dubbo/metrics/config/event/ConfigCenterSubDispatcher$1."<init>":(Lorg/apache/dubbo/metrics/config/event/ConfigCenterSubDispatcher;Lorg/apache/dubbo/metrics/model/key/MetricsKey;Lorg/apache/dubbo/metrics/config/collector/ConfigCenterMetricsCollector;)V
      17: invokespecial #5                  // Method org/apache/dubbo/metrics/event/SimpleMetricsEventMulticaster.addListener:(Lorg/apache/dubbo/metrics/listener/MetricsListener;)V
      20: return
}
