Compiled from "ConfigCenterSubDispatcher.java"
class org.apache.dubbo.metrics.config.event.ConfigCenterSubDispatcher$1 extends org.apache.dubbo.metrics.listener.AbstractMetricsKeyListener {
  final org.apache.dubbo.metrics.config.collector.ConfigCenterMetricsCollector val$collector;

  final org.apache.dubbo.metrics.config.event.ConfigCenterSubDispatcher this$0;

  org.apache.dubbo.metrics.config.event.ConfigCenterSubDispatcher$1(org.apache.dubbo.metrics.config.event.ConfigCenterSubDispatcher, org.apache.dubbo.metrics.model.key.MetricsKey, org.apache.dubbo.metrics.config.collector.ConfigCenterMetricsCollector);
    Code:
       0: aload_0
       1: aload_1
       2: putfield      #3                  // Field this$0:Lorg/apache/dubbo/metrics/config/event/ConfigCenterSubDispatcher;
       5: aload_0
       6: aload_3
       7: putfield      #4                  // Field val$collector:Lorg/apache/dubbo/metrics/config/collector/ConfigCenterMetricsCollector;
      10: aload_0
      11: aload_2
      12: invokespecial #5                  // Method org/apache/dubbo/metrics/listener/AbstractMetricsKeyListener."<init>":(Lorg/apache/dubbo/metrics/model/key/MetricsKey;)V
      15: return

  public boolean isSupport(org.apache.dubbo.metrics.event.MetricsEvent);
    Code:
       0: aload_1
       1: instanceof    #6                  // class org/apache/dubbo/metrics/config/event/ConfigCenterEvent
       4: ireturn

  public void onEvent(org.apache.dubbo.metrics.event.TimeCounterEvent);
    Code:
       0: aload_0
       1: getfield      #4                  // Field val$collector:Lorg/apache/dubbo/metrics/config/collector/ConfigCenterMetricsCollector;
       4: aload_1
       5: ldc           #7                  // String configFileKey
       7: invokevirtual #8                  // Method org/apache/dubbo/metrics/event/TimeCounterEvent.getAttachmentValue:(Ljava/lang/String;)Ljava/lang/Object;
      10: checkcast     #9                  // class java/lang/String
      13: aload_1
      14: ldc           #10                 // String configGroup
      16: invokevirtual #8                  // Method org/apache/dubbo/metrics/event/TimeCounterEvent.getAttachmentValue:(Ljava/lang/String;)Ljava/lang/Object;
      19: checkcast     #9                  // class java/lang/String
      22: aload_1
      23: ldc           #11                 // String configProtocol
      25: invokevirtual #8                  // Method org/apache/dubbo/metrics/event/TimeCounterEvent.getAttachmentValue:(Ljava/lang/String;)Ljava/lang/Object;
      28: checkcast     #9                  // class java/lang/String
      31: aload_1
      32: ldc           #12                 // String configChangeType
      34: invokevirtual #8                  // Method org/apache/dubbo/metrics/event/TimeCounterEvent.getAttachmentValue:(Ljava/lang/String;)Ljava/lang/Object;
      37: checkcast     #9                  // class java/lang/String
      40: aload_1
      41: ldc           #13                 // String size
      43: invokevirtual #8                  // Method org/apache/dubbo/metrics/event/TimeCounterEvent.getAttachmentValue:(Ljava/lang/String;)Ljava/lang/Object;
      46: checkcast     #14                 // class java/lang/Integer
      49: invokevirtual #15                 // Method java/lang/Integer.intValue:()I
      52: invokevirtual #16                 // Method org/apache/dubbo/metrics/config/collector/ConfigCenterMetricsCollector.increase:(Ljava/lang/String;Ljava/lang/String;Ljava/lang/String;Ljava/lang/String;I)V
      55: return

  public void onEvent(org.apache.dubbo.metrics.event.MetricsEvent);
    Code:
       0: aload_0
       1: aload_1
       2: checkcast     #17                 // class org/apache/dubbo/metrics/event/TimeCounterEvent
       5: invokevirtual #18                 // Method onEvent:(Lorg/apache/dubbo/metrics/event/TimeCounterEvent;)V
       8: return
}
