Compiled from "HttpProcessHandler.java"
public class org.apache.dubbo.qos.server.handler.HttpProcessHandler extends io.netty.channel.SimpleChannelInboundHandler<io.netty.handler.codec.http.HttpRequest> {
  private static final org.apache.dubbo.common.logger.ErrorTypeAwareLogger log;

  private final org.apache.dubbo.qos.command.CommandExecutor commandExecutor;

  private final org.apache.dubbo.qos.api.QosConfiguration qosConfiguration;

  public org.apache.dubbo.qos.server.handler.HttpProcessHandler(org.apache.dubbo.rpc.model.FrameworkModel, org.apache.dubbo.qos.api.QosConfiguration);
    Code:
       0: aload_0
       1: invokespecial #2                  // Method io/netty/channel/SimpleChannelInboundHandler."<init>":()V
       4: aload_0
       5: new           #3                  // class org/apache/dubbo/qos/command/DefaultCommandExecutor
       8: dup
       9: aload_1
      10: invokespecial #4                  // Method org/apache/dubbo/qos/command/DefaultCommandExecutor."<init>":(Lorg/apache/dubbo/rpc/model/FrameworkModel;)V
      13: putfield      #5                  // Field commandExecutor:Lorg/apache/dubbo/qos/command/CommandExecutor;
      16: aload_0
      17: aload_2
      18: putfield      #6                  // Field qosConfiguration:Lorg/apache/dubbo/qos/api/QosConfiguration;
      21: return

  private static io.netty.handler.codec.http.FullHttpResponse http(int, java.lang.String);
    Code:
       0: new           #7                  // class io/netty/handler/codec/http/DefaultFullHttpResponse
       3: dup
       4: getstatic     #8                  // Field io/netty/handler/codec/http/HttpVersion.HTTP_1_1:Lio/netty/handler/codec/http/HttpVersion;
       7: iload_0
       8: invokestatic  #9                  // Method io/netty/handler/codec/http/HttpResponseStatus.valueOf:(I)Lio/netty/handler/codec/http/HttpResponseStatus;
      11: aload_1
      12: invokevirtual #10                 // Method java/lang/String.getBytes:()[B
      15: invokestatic  #11                 // Method io/netty/buffer/Unpooled.wrappedBuffer:([B)Lio/netty/buffer/ByteBuf;
      18: invokespecial #12                 // Method io/netty/handler/codec/http/DefaultFullHttpResponse."<init>":(Lio/netty/handler/codec/http/HttpVersion;Lio/netty/handler/codec/http/HttpResponseStatus;Lio/netty/buffer/ByteBuf;)V
      21: astore_2
      22: aload_2
      23: invokeinterface #13,  1           // InterfaceMethod io/netty/handler/codec/http/FullHttpResponse.headers:()Lio/netty/handler/codec/http/HttpHeaders;
      28: astore_3
      29: aload_3
      30: getstatic     #14                 // Field io/netty/handler/codec/http/HttpHeaderNames.CONTENT_TYPE:Lio/netty/util/AsciiString;
      33: ldc           #15                 // String text/plain
      35: invokevirtual #16                 // Method io/netty/handler/codec/http/HttpHeaders.set:(Ljava/lang/CharSequence;Ljava/lang/Object;)Lio/netty/handler/codec/http/HttpHeaders;
      38: pop
      39: aload_3
      40: getstatic     #17                 // Field io/netty/handler/codec/http/HttpHeaderNames.CONTENT_LENGTH:Lio/netty/util/AsciiString;
      43: aload_2
      44: invokeinterface #18,  1           // InterfaceMethod io/netty/handler/codec/http/FullHttpResponse.content:()Lio/netty/buffer/ByteBuf;
      49: invokevirtual #19                 // Method io/netty/buffer/ByteBuf.readableBytes:()I
      52: invokestatic  #20                 // Method java/lang/Integer.valueOf:(I)Ljava/lang/Integer;
      55: invokevirtual #16                 // Method io/netty/handler/codec/http/HttpHeaders.set:(Ljava/lang/CharSequence;Ljava/lang/Object;)Lio/netty/handler/codec/http/HttpHeaders;
      58: pop
      59: aload_2
      60: areturn

  private static io.netty.handler.codec.http.FullHttpResponse http(int);
    Code:
       0: new           #7                  // class io/netty/handler/codec/http/DefaultFullHttpResponse
       3: dup
       4: getstatic     #8                  // Field io/netty/handler/codec/http/HttpVersion.HTTP_1_1:Lio/netty/handler/codec/http/HttpVersion;
       7: iload_0
       8: invokestatic  #9                  // Method io/netty/handler/codec/http/HttpResponseStatus.valueOf:(I)Lio/netty/handler/codec/http/HttpResponseStatus;
      11: invokespecial #21                 // Method io/netty/handler/codec/http/DefaultFullHttpResponse."<init>":(Lio/netty/handler/codec/http/HttpVersion;Lio/netty/handler/codec/http/HttpResponseStatus;)V
      14: astore_1
      15: aload_1
      16: invokeinterface #13,  1           // InterfaceMethod io/netty/handler/codec/http/FullHttpResponse.headers:()Lio/netty/handler/codec/http/HttpHeaders;
      21: astore_2
      22: aload_2
      23: getstatic     #14                 // Field io/netty/handler/codec/http/HttpHeaderNames.CONTENT_TYPE:Lio/netty/util/AsciiString;
      26: ldc           #15                 // String text/plain
      28: invokevirtual #16                 // Method io/netty/handler/codec/http/HttpHeaders.set:(Ljava/lang/CharSequence;Ljava/lang/Object;)Lio/netty/handler/codec/http/HttpHeaders;
      31: pop
      32: aload_2
      33: getstatic     #17                 // Field io/netty/handler/codec/http/HttpHeaderNames.CONTENT_LENGTH:Lio/netty/util/AsciiString;
      36: aload_1
      37: invokeinterface #18,  1           // InterfaceMethod io/netty/handler/codec/http/FullHttpResponse.content:()Lio/netty/buffer/ByteBuf;
      42: invokevirtual #19                 // Method io/netty/buffer/ByteBuf.readableBytes:()I
      45: invokestatic  #20                 // Method java/lang/Integer.valueOf:(I)Ljava/lang/Integer;
      48: invokevirtual #16                 // Method io/netty/handler/codec/http/HttpHeaders.set:(Ljava/lang/CharSequence;Ljava/lang/Object;)Lio/netty/handler/codec/http/HttpHeaders;
      51: pop
      52: aload_1
      53: areturn

  protected void channelRead0(io.netty.channel.ChannelHandlerContext, io.netty.handler.codec.http.HttpRequest) throws java.lang.Exception;
    Code:
       0: aload_2
       1: invokestatic  #22                 // Method org/apache/dubbo/qos/command/decoder/HttpCommandDecoder.decode:(Lio/netty/handler/codec/http/HttpRequest;)Lorg/apache/dubbo/qos/api/CommandContext;
       4: astore_3
       5: aload_3
       6: ifnonnull     75
       9: getstatic     #23                 // Field log:Lorg/apache/dubbo/common/logger/ErrorTypeAwareLogger;
      12: ldc           #24                 // String 7-6
      14: ldc           #25                 // String
      16: ldc           #25                 // String
      18: new           #26                 // class java/lang/StringBuilder
      21: dup
      22: invokespecial #27                 // Method java/lang/StringBuilder."<init>":()V
      25: ldc           #28                 // String can not found commandContext, url:
      27: invokevirtual #29                 // Method java/lang/StringBuilder.append:(Ljava/lang/String;)Ljava/lang/StringBuilder;
      30: aload_2
      31: invokeinterface #30,  1           // InterfaceMethod io/netty/handler/codec/http/HttpRequest.uri:()Ljava/lang/String;
      36: invokevirtual #29                 // Method java/lang/StringBuilder.append:(Ljava/lang/String;)Ljava/lang/StringBuilder;
      39: invokevirtual #31                 // Method java/lang/StringBuilder.toString:()Ljava/lang/String;
      42: invokeinterface #32,  5           // InterfaceMethod org/apache/dubbo/common/logger/ErrorTypeAwareLogger.warn:(Ljava/lang/String;Ljava/lang/String;Ljava/lang/String;Ljava/lang/String;)V
      47: sipush        404
      50: invokestatic  #33                 // Method http:(I)Lio/netty/handler/codec/http/FullHttpResponse;
      53: astore        4
      55: aload_1
      56: aload         4
      58: invokeinterface #34,  2           // InterfaceMethod io/netty/channel/ChannelHandlerContext.writeAndFlush:(Ljava/lang/Object;)Lio/netty/channel/ChannelFuture;
      63: getstatic     #35                 // Field io/netty/channel/ChannelFutureListener.CLOSE:Lio/netty/channel/ChannelFutureListener;
      66: invokeinterface #36,  2           // InterfaceMethod io/netty/channel/ChannelFuture.addListener:(Lio/netty/util/concurrent/GenericFutureListener;)Lio/netty/channel/ChannelFuture;
      71: pop
      72: goto          342
      75: aload_3
      76: aload_1
      77: invokeinterface #37,  1           // InterfaceMethod io/netty/channel/ChannelHandlerContext.channel:()Lio/netty/channel/Channel;
      82: invokevirtual #38                 // Method org/apache/dubbo/qos/api/CommandContext.setRemote:(Lio/netty/channel/Channel;)V
      85: aload_3
      86: aload_0
      87: getfield      #6                  // Field qosConfiguration:Lorg/apache/dubbo/qos/api/QosConfiguration;
      90: invokevirtual #39                 // Method org/apache/dubbo/qos/api/CommandContext.setQosConfiguration:(Lorg/apache/dubbo/qos/api/QosConfiguration;)V
      93: aload_0
      94: getfield      #5                  // Field commandExecutor:Lorg/apache/dubbo/qos/command/CommandExecutor;
      97: aload_3
      98: invokeinterface #40,  2           // InterfaceMethod org/apache/dubbo/qos/command/CommandExecutor.execute:(Lorg/apache/dubbo/qos/api/CommandContext;)Ljava/lang/String;
     103: astore        4
     105: aload_3
     106: invokevirtual #41                 // Method org/apache/dubbo/qos/api/CommandContext.getHttpCode:()I
     109: istore        5
     111: iload         5
     113: aload         4
     115: invokestatic  #42                 // Method http:(ILjava/lang/String;)Lio/netty/handler/codec/http/FullHttpResponse;
     118: astore        6
     120: aload_1
     121: aload         6
     123: invokeinterface #34,  2           // InterfaceMethod io/netty/channel/ChannelHandlerContext.writeAndFlush:(Ljava/lang/Object;)Lio/netty/channel/ChannelFuture;
     128: getstatic     #35                 // Field io/netty/channel/ChannelFutureListener.CLOSE:Lio/netty/channel/ChannelFutureListener;
     131: invokeinterface #36,  2           // InterfaceMethod io/netty/channel/ChannelFuture.addListener:(Lio/netty/util/concurrent/GenericFutureListener;)Lio/netty/channel/ChannelFuture;
     136: pop
     137: goto          342
     140: astore        4
     142: getstatic     #23                 // Field log:Lorg/apache/dubbo/common/logger/ErrorTypeAwareLogger;
     145: ldc           #44                 // String 7-5
     147: ldc           #25                 // String
     149: ldc           #25                 // String
     151: new           #26                 // class java/lang/StringBuilder
     154: dup
     155: invokespecial #27                 // Method java/lang/StringBuilder."<init>":()V
     158: ldc           #45                 // String can not find command:
     160: invokevirtual #29                 // Method java/lang/StringBuilder.append:(Ljava/lang/String;)Ljava/lang/StringBuilder;
     163: aload_3
     164: invokevirtual #46                 // Method java/lang/StringBuilder.append:(Ljava/lang/Object;)Ljava/lang/StringBuilder;
     167: invokevirtual #31                 // Method java/lang/StringBuilder.toString:()Ljava/lang/String;
     170: aload         4
     172: invokeinterface #47,  6           // InterfaceMethod org/apache/dubbo/common/logger/ErrorTypeAwareLogger.error:(Ljava/lang/String;Ljava/lang/String;Ljava/lang/String;Ljava/lang/String;Ljava/lang/Throwable;)V
     177: sipush        404
     180: invokestatic  #33                 // Method http:(I)Lio/netty/handler/codec/http/FullHttpResponse;
     183: astore        5
     185: aload_1
     186: aload         5
     188: invokeinterface #34,  2           // InterfaceMethod io/netty/channel/ChannelHandlerContext.writeAndFlush:(Ljava/lang/Object;)Lio/netty/channel/ChannelFuture;
     193: getstatic     #35                 // Field io/netty/channel/ChannelFutureListener.CLOSE:Lio/netty/channel/ChannelFutureListener;
     196: invokeinterface #36,  2           // InterfaceMethod io/netty/channel/ChannelFuture.addListener:(Lio/netty/util/concurrent/GenericFutureListener;)Lio/netty/channel/ChannelFuture;
     201: pop
     202: goto          342
     205: astore        4
     207: getstatic     #23                 // Field log:Lorg/apache/dubbo/common/logger/ErrorTypeAwareLogger;
     210: ldc           #49                 // String 7-7
     212: ldc           #25                 // String
     214: ldc           #25                 // String
     216: new           #26                 // class java/lang/StringBuilder
     219: dup
     220: invokespecial #27                 // Method java/lang/StringBuilder."<init>":()V
     223: ldc           #50                 // String permission deny to access command:
     225: invokevirtual #29                 // Method java/lang/StringBuilder.append:(Ljava/lang/String;)Ljava/lang/StringBuilder;
     228: aload_3
     229: invokevirtual #46                 // Method java/lang/StringBuilder.append:(Ljava/lang/Object;)Ljava/lang/StringBuilder;
     232: invokevirtual #31                 // Method java/lang/StringBuilder.toString:()Ljava/lang/String;
     235: aload         4
     237: invokeinterface #47,  6           // InterfaceMethod org/apache/dubbo/common/logger/ErrorTypeAwareLogger.error:(Ljava/lang/String;Ljava/lang/String;Ljava/lang/String;Ljava/lang/String;Ljava/lang/Throwable;)V
     242: sipush        403
     245: invokestatic  #33                 // Method http:(I)Lio/netty/handler/codec/http/FullHttpResponse;
     248: astore        5
     250: aload_1
     251: aload         5
     253: invokeinterface #34,  2           // InterfaceMethod io/netty/channel/ChannelHandlerContext.writeAndFlush:(Ljava/lang/Object;)Lio/netty/channel/ChannelFuture;
     258: getstatic     #35                 // Field io/netty/channel/ChannelFutureListener.CLOSE:Lio/netty/channel/ChannelFutureListener;
     261: invokeinterface #36,  2           // InterfaceMethod io/netty/channel/ChannelFuture.addListener:(Lio/netty/util/concurrent/GenericFutureListener;)Lio/netty/channel/ChannelFuture;
     266: pop
     267: goto          342
     270: astore        4
     272: getstatic     #23                 // Field log:Lorg/apache/dubbo/common/logger/ErrorTypeAwareLogger;
     275: ldc           #24                 // String 7-6
     277: ldc           #25                 // String
     279: ldc           #25                 // String
     281: new           #26                 // class java/lang/StringBuilder
     284: dup
     285: invokespecial #27                 // Method java/lang/StringBuilder."<init>":()V
     288: ldc           #52                 // String execute commandContext:
     290: invokevirtual #29                 // Method java/lang/StringBuilder.append:(Ljava/lang/String;)Ljava/lang/StringBuilder;
     293: aload_3
     294: invokevirtual #46                 // Method java/lang/StringBuilder.append:(Ljava/lang/Object;)Ljava/lang/StringBuilder;
     297: ldc           #53                 // String  got exception
     299: invokevirtual #29                 // Method java/lang/StringBuilder.append:(Ljava/lang/String;)Ljava/lang/StringBuilder;
     302: invokevirtual #31                 // Method java/lang/StringBuilder.toString:()Ljava/lang/String;
     305: aload         4
     307: invokeinterface #47,  6           // InterfaceMethod org/apache/dubbo/common/logger/ErrorTypeAwareLogger.error:(Ljava/lang/String;Ljava/lang/String;Ljava/lang/String;Ljava/lang/String;Ljava/lang/Throwable;)V
     312: sipush        500
     315: aload         4
     317: invokevirtual #54                 // Method java/lang/Exception.getMessage:()Ljava/lang/String;
     320: invokestatic  #42                 // Method http:(ILjava/lang/String;)Lio/netty/handler/codec/http/FullHttpResponse;
     323: astore        5
     325: aload_1
     326: aload         5
     328: invokeinterface #34,  2           // InterfaceMethod io/netty/channel/ChannelHandlerContext.writeAndFlush:(Ljava/lang/Object;)Lio/netty/channel/ChannelFuture;
     333: getstatic     #35                 // Field io/netty/channel/ChannelFutureListener.CLOSE:Lio/netty/channel/ChannelFutureListener;
     336: invokeinterface #36,  2           // InterfaceMethod io/netty/channel/ChannelFuture.addListener:(Lio/netty/util/concurrent/GenericFutureListener;)Lio/netty/channel/ChannelFuture;
     341: pop
     342: return
    Exception table:
       from    to  target type
          93   137   140   Class org/apache/dubbo/qos/command/exception/NoSuchCommandException
          93   137   205   Class org/apache/dubbo/qos/command/exception/PermissionDenyException
          93   137   270   Class java/lang/Exception

  protected void channelRead0(io.netty.channel.ChannelHandlerContext, java.lang.Object) throws java.lang.Exception;
    Code:
       0: aload_0
       1: aload_1
       2: aload_2
       3: checkcast     #55                 // class io/netty/handler/codec/http/HttpRequest
       6: invokevirtual #56                 // Method channelRead0:(Lio/netty/channel/ChannelHandlerContext;Lio/netty/handler/codec/http/HttpRequest;)V
       9: return

  static {};
    Code:
       0: ldc           #57                 // class org/apache/dubbo/qos/server/handler/HttpProcessHandler
       2: invokestatic  #58                 // Method org/apache/dubbo/common/logger/LoggerFactory.getErrorTypeAwareLogger:(Ljava/lang/Class;)Lorg/apache/dubbo/common/logger/ErrorTypeAwareLogger;
       5: putstatic     #23                 // Field log:Lorg/apache/dubbo/common/logger/ErrorTypeAwareLogger;
       8: return
}
