Compiled from "QosProcessHandler.java"
public class org.apache.dubbo.qos.server.handler.QosProcessHandler extends io.netty.handler.codec.ByteToMessageDecoder {
  private io.netty.util.concurrent.ScheduledFuture<?> welcomeFuture;

  private final org.apache.dubbo.rpc.model.FrameworkModel frameworkModel;

  public static final java.lang.String PROMPT;

  private final org.apache.dubbo.qos.api.QosConfiguration qosConfiguration;

  public org.apache.dubbo.qos.server.handler.QosProcessHandler(org.apache.dubbo.rpc.model.FrameworkModel, org.apache.dubbo.qos.api.QosConfiguration);
    Code:
       0: aload_0
       1: invokespecial #1                  // Method io/netty/handler/codec/ByteToMessageDecoder."<init>":()V
       4: aload_0
       5: aload_1
       6: putfield      #2                  // Field frameworkModel:Lorg/apache/dubbo/rpc/model/FrameworkModel;
       9: aload_0
      10: aload_2
      11: putfield      #3                  // Field qosConfiguration:Lorg/apache/dubbo/qos/api/QosConfiguration;
      14: return

  public void channelActive(io.netty.channel.ChannelHandlerContext) throws java.lang.Exception;
    Code:
       0: aload_0
       1: aload_1
       2: invokeinterface #4,  1            // InterfaceMethod io/netty/channel/ChannelHandlerContext.executor:()Lio/netty/util/concurrent/EventExecutor;
       7: aload_0
       8: aload_1
       9: invokedynamic #5,  0              // InvokeDynamic #0:run:(Lorg/apache/dubbo/qos/server/handler/QosProcessHandler;Lio/netty/channel/ChannelHandlerContext;)Ljava/lang/Runnable;
      14: ldc2_w        #6                  // long 500l
      17: getstatic     #8                  // Field java/util/concurrent/TimeUnit.MILLISECONDS:Ljava/util/concurrent/TimeUnit;
      20: invokeinterface #9,  5            // InterfaceMethod io/netty/util/concurrent/EventExecutor.schedule:(Ljava/lang/Runnable;JLjava/util/concurrent/TimeUnit;)Lio/netty/util/concurrent/ScheduledFuture;
      25: putfield      #10                 // Field welcomeFuture:Lio/netty/util/concurrent/ScheduledFuture;
      28: return

  protected void decode(io.netty.channel.ChannelHandlerContext, io.netty.buffer.ByteBuf, java.util.List<java.lang.Object>) throws java.lang.Exception;
    Code:
       0: aload_2
       1: invokevirtual #11                 // Method io/netty/buffer/ByteBuf.readableBytes:()I
       4: iconst_1
       5: if_icmpge     9
       8: return
       9: aload_2
      10: aload_2
      11: invokevirtual #12                 // Method io/netty/buffer/ByteBuf.readerIndex:()I
      14: invokevirtual #13                 // Method io/netty/buffer/ByteBuf.getByte:(I)B
      17: istore        4
      19: aload_1
      20: invokeinterface #14,  1           // InterfaceMethod io/netty/channel/ChannelHandlerContext.pipeline:()Lio/netty/channel/ChannelPipeline;
      25: astore        5
      27: aload         5
      29: iconst_1
      30: anewarray     #15                 // class io/netty/channel/ChannelHandler
      33: dup
      34: iconst_0
      35: new           #16                 // class org/apache/dubbo/qos/server/handler/ForeignHostPermitHandler
      38: dup
      39: aload_0
      40: getfield      #3                  // Field qosConfiguration:Lorg/apache/dubbo/qos/api/QosConfiguration;
      43: invokespecial #17                 // Method org/apache/dubbo/qos/server/handler/ForeignHostPermitHandler."<init>":(Lorg/apache/dubbo/qos/api/QosConfiguration;)V
      46: aastore
      47: invokeinterface #18,  2           // InterfaceMethod io/netty/channel/ChannelPipeline.addLast:([Lio/netty/channel/ChannelHandler;)Lio/netty/channel/ChannelPipeline;
      52: pop
      53: iload         4
      55: invokestatic  #19                 // Method isHttp:(I)Z
      58: ifeq          179
      61: aload_0
      62: getfield      #10                 // Field welcomeFuture:Lio/netty/util/concurrent/ScheduledFuture;
      65: ifnull        91
      68: aload_0
      69: getfield      #10                 // Field welcomeFuture:Lio/netty/util/concurrent/ScheduledFuture;
      72: invokeinterface #20,  1           // InterfaceMethod io/netty/util/concurrent/ScheduledFuture.isCancellable:()Z
      77: ifeq          91
      80: aload_0
      81: getfield      #10                 // Field welcomeFuture:Lio/netty/util/concurrent/ScheduledFuture;
      84: iconst_0
      85: invokeinterface #21,  2           // InterfaceMethod io/netty/util/concurrent/ScheduledFuture.cancel:(Z)Z
      90: pop
      91: aload         5
      93: iconst_1
      94: anewarray     #15                 // class io/netty/channel/ChannelHandler
      97: dup
      98: iconst_0
      99: new           #22                 // class io/netty/handler/codec/http/HttpServerCodec
     102: dup
     103: invokespecial #23                 // Method io/netty/handler/codec/http/HttpServerCodec."<init>":()V
     106: aastore
     107: invokeinterface #18,  2           // InterfaceMethod io/netty/channel/ChannelPipeline.addLast:([Lio/netty/channel/ChannelHandler;)Lio/netty/channel/ChannelPipeline;
     112: pop
     113: aload         5
     115: iconst_1
     116: anewarray     #15                 // class io/netty/channel/ChannelHandler
     119: dup
     120: iconst_0
     121: new           #24                 // class io/netty/handler/codec/http/HttpObjectAggregator
     124: dup
     125: ldc           #25                 // int 1048576
     127: invokespecial #26                 // Method io/netty/handler/codec/http/HttpObjectAggregator."<init>":(I)V
     130: aastore
     131: invokeinterface #18,  2           // InterfaceMethod io/netty/channel/ChannelPipeline.addLast:([Lio/netty/channel/ChannelHandler;)Lio/netty/channel/ChannelPipeline;
     136: pop
     137: aload         5
     139: iconst_1
     140: anewarray     #15                 // class io/netty/channel/ChannelHandler
     143: dup
     144: iconst_0
     145: new           #27                 // class org/apache/dubbo/qos/server/handler/HttpProcessHandler
     148: dup
     149: aload_0
     150: getfield      #2                  // Field frameworkModel:Lorg/apache/dubbo/rpc/model/FrameworkModel;
     153: aload_0
     154: getfield      #3                  // Field qosConfiguration:Lorg/apache/dubbo/qos/api/QosConfiguration;
     157: invokespecial #28                 // Method org/apache/dubbo/qos/server/handler/HttpProcessHandler."<init>":(Lorg/apache/dubbo/rpc/model/FrameworkModel;Lorg/apache/dubbo/qos/api/QosConfiguration;)V
     160: aastore
     161: invokeinterface #18,  2           // InterfaceMethod io/netty/channel/ChannelPipeline.addLast:([Lio/netty/channel/ChannelHandler;)Lio/netty/channel/ChannelPipeline;
     166: pop
     167: aload         5
     169: aload_0
     170: invokeinterface #29,  2           // InterfaceMethod io/netty/channel/ChannelPipeline.remove:(Lio/netty/channel/ChannelHandler;)Lio/netty/channel/ChannelPipeline;
     175: pop
     176: goto          342
     179: aload         5
     181: iconst_1
     182: anewarray     #15                 // class io/netty/channel/ChannelHandler
     185: dup
     186: iconst_0
     187: new           #30                 // class io/netty/handler/codec/LineBasedFrameDecoder
     190: dup
     191: sipush        2048
     194: invokespecial #31                 // Method io/netty/handler/codec/LineBasedFrameDecoder."<init>":(I)V
     197: aastore
     198: invokeinterface #18,  2           // InterfaceMethod io/netty/channel/ChannelPipeline.addLast:([Lio/netty/channel/ChannelHandler;)Lio/netty/channel/ChannelPipeline;
     203: pop
     204: aload         5
     206: iconst_1
     207: anewarray     #15                 // class io/netty/channel/ChannelHandler
     210: dup
     211: iconst_0
     212: new           #32                 // class io/netty/handler/codec/string/StringDecoder
     215: dup
     216: getstatic     #33                 // Field io/netty/util/CharsetUtil.UTF_8:Ljava/nio/charset/Charset;
     219: invokespecial #34                 // Method io/netty/handler/codec/string/StringDecoder."<init>":(Ljava/nio/charset/Charset;)V
     222: aastore
     223: invokeinterface #18,  2           // InterfaceMethod io/netty/channel/ChannelPipeline.addLast:([Lio/netty/channel/ChannelHandler;)Lio/netty/channel/ChannelPipeline;
     228: pop
     229: aload         5
     231: iconst_1
     232: anewarray     #15                 // class io/netty/channel/ChannelHandler
     235: dup
     236: iconst_0
     237: new           #35                 // class io/netty/handler/codec/string/StringEncoder
     240: dup
     241: getstatic     #33                 // Field io/netty/util/CharsetUtil.UTF_8:Ljava/nio/charset/Charset;
     244: invokespecial #36                 // Method io/netty/handler/codec/string/StringEncoder."<init>":(Ljava/nio/charset/Charset;)V
     247: aastore
     248: invokeinterface #18,  2           // InterfaceMethod io/netty/channel/ChannelPipeline.addLast:([Lio/netty/channel/ChannelHandler;)Lio/netty/channel/ChannelPipeline;
     253: pop
     254: aload         5
     256: iconst_1
     257: anewarray     #15                 // class io/netty/channel/ChannelHandler
     260: dup
     261: iconst_0
     262: new           #37                 // class io/netty/handler/timeout/IdleStateHandler
     265: dup
     266: iconst_0
     267: iconst_0
     268: sipush        300
     271: invokespecial #38                 // Method io/netty/handler/timeout/IdleStateHandler."<init>":(III)V
     274: aastore
     275: invokeinterface #18,  2           // InterfaceMethod io/netty/channel/ChannelPipeline.addLast:([Lio/netty/channel/ChannelHandler;)Lio/netty/channel/ChannelPipeline;
     280: pop
     281: aload         5
     283: iconst_1
     284: anewarray     #15                 // class io/netty/channel/ChannelHandler
     287: dup
     288: iconst_0
     289: new           #39                 // class org/apache/dubbo/qos/server/handler/TelnetIdleEventHandler
     292: dup
     293: invokespecial #40                 // Method org/apache/dubbo/qos/server/handler/TelnetIdleEventHandler."<init>":()V
     296: aastore
     297: invokeinterface #18,  2           // InterfaceMethod io/netty/channel/ChannelPipeline.addLast:([Lio/netty/channel/ChannelHandler;)Lio/netty/channel/ChannelPipeline;
     302: pop
     303: aload         5
     305: iconst_1
     306: anewarray     #15                 // class io/netty/channel/ChannelHandler
     309: dup
     310: iconst_0
     311: new           #41                 // class org/apache/dubbo/qos/server/handler/TelnetProcessHandler
     314: dup
     315: aload_0
     316: getfield      #2                  // Field frameworkModel:Lorg/apache/dubbo/rpc/model/FrameworkModel;
     319: aload_0
     320: getfield      #3                  // Field qosConfiguration:Lorg/apache/dubbo/qos/api/QosConfiguration;
     323: invokespecial #42                 // Method org/apache/dubbo/qos/server/handler/TelnetProcessHandler."<init>":(Lorg/apache/dubbo/rpc/model/FrameworkModel;Lorg/apache/dubbo/qos/api/QosConfiguration;)V
     326: aastore
     327: invokeinterface #18,  2           // InterfaceMethod io/netty/channel/ChannelPipeline.addLast:([Lio/netty/channel/ChannelHandler;)Lio/netty/channel/ChannelPipeline;
     332: pop
     333: aload         5
     335: aload_0
     336: invokeinterface #29,  2           // InterfaceMethod io/netty/channel/ChannelPipeline.remove:(Lio/netty/channel/ChannelHandler;)Lio/netty/channel/ChannelPipeline;
     341: pop
     342: return

  public void userEventTriggered(io.netty.channel.ChannelHandlerContext, java.lang.Object) throws java.lang.Exception;
    Code:
       0: aload_2
       1: instanceof    #43                 // class io/netty/handler/timeout/IdleStateEvent
       4: ifeq          21
       7: aload_0
       8: getfield      #10                 // Field welcomeFuture:Lio/netty/util/concurrent/ScheduledFuture;
      11: invokestatic  #44                 // Method org/apache/dubbo/common/utils/ExecutorUtil.cancelScheduledFuture:(Ljava/util/concurrent/ScheduledFuture;)V
      14: aload_1
      15: invokeinterface #45,  1           // InterfaceMethod io/netty/channel/ChannelHandlerContext.close:()Lio/netty/channel/ChannelFuture;
      20: pop
      21: return

  private static boolean isHttp(int);
    Code:
       0: iload_0
       1: bipush        71
       3: if_icmpeq     12
       6: iload_0
       7: bipush        80
       9: if_icmpne     16
      12: iconst_1
      13: goto          17
      16: iconst_0
      17: ireturn

  private void lambda$channelActive$0(io.netty.channel.ChannelHandlerContext);
    Code:
       0: aload_0
       1: getfield      #3                  // Field qosConfiguration:Lorg/apache/dubbo/qos/api/QosConfiguration;
       4: invokevirtual #46                 // Method org/apache/dubbo/qos/api/QosConfiguration.getWelcome:()Ljava/lang/String;
       7: astore_2
       8: aload_2
       9: ifnull        41
      12: aload_1
      13: aload_2
      14: invokevirtual #47                 // Method java/lang/String.getBytes:()[B
      17: invokestatic  #48                 // Method io/netty/buffer/Unpooled.wrappedBuffer:([B)Lio/netty/buffer/ByteBuf;
      20: invokeinterface #49,  2           // InterfaceMethod io/netty/channel/ChannelHandlerContext.write:(Ljava/lang/Object;)Lio/netty/channel/ChannelFuture;
      25: pop
      26: aload_1
      27: ldc           #51                 // String dubbo>
      29: invokevirtual #47                 // Method java/lang/String.getBytes:()[B
      32: invokestatic  #48                 // Method io/netty/buffer/Unpooled.wrappedBuffer:([B)Lio/netty/buffer/ByteBuf;
      35: invokeinterface #52,  2           // InterfaceMethod io/netty/channel/ChannelHandlerContext.writeAndFlush:(Ljava/lang/Object;)Lio/netty/channel/ChannelFuture;
      40: pop
      41: return
}
