Compiled from "TelnetIdleEventHandler.java"
public class org.apache.dubbo.qos.server.handler.TelnetIdleEventHandler extends io.netty.channel.ChannelDuplexHandler {
  private static final org.apache.dubbo.common.logger.Logger log;

  public org.apache.dubbo.qos.server.handler.TelnetIdleEventHandler();
    Code:
       0: aload_0
       1: invokespecial #1                  // Method io/netty/channel/ChannelDuplexHandler."<init>":()V
       4: return

  public void userEventTriggered(io.netty.channel.ChannelHandlerContext, java.lang.Object) throws java.lang.Exception;
    Code:
       0: aload_2
       1: instanceof    #2                  // class io/netty/handler/timeout/IdleStateEvent
       4: ifeq          51
       7: aload_1
       8: invokeinterface #3,  1            // InterfaceMethod io/netty/channel/ChannelHandlerContext.channel:()Lio/netty/channel/Channel;
      13: astore_3
      14: getstatic     #4                  // Field log:Lorg/apache/dubbo/common/logger/Logger;
      17: new           #5                  // class java/lang/StringBuilder
      20: dup
      21: invokespecial #6                  // Method java/lang/StringBuilder."<init>":()V
      24: ldc           #7                  // String IdleStateEvent triggered, close channel
      26: invokevirtual #8                  // Method java/lang/StringBuilder.append:(Ljava/lang/String;)Ljava/lang/StringBuilder;
      29: aload_3
      30: invokevirtual #9                  // Method java/lang/StringBuilder.append:(Ljava/lang/Object;)Ljava/lang/StringBuilder;
      33: invokevirtual #10                 // Method java/lang/StringBuilder.toString:()Ljava/lang/String;
      36: invokeinterface #11,  2           // InterfaceMethod org/apache/dubbo/common/logger/Logger.info:(Ljava/lang/String;)V
      41: aload_3
      42: invokeinterface #12,  1           // InterfaceMethod io/netty/channel/Channel.close:()Lio/netty/channel/ChannelFuture;
      47: pop
      48: goto          57
      51: aload_0
      52: aload_1
      53: aload_2
      54: invokespecial #13                 // Method io/netty/channel/ChannelDuplexHandler.userEventTriggered:(Lio/netty/channel/ChannelHandlerContext;Ljava/lang/Object;)V
      57: return

  static {};
    Code:
       0: ldc           #14                 // class org/apache/dubbo/qos/server/handler/TelnetIdleEventHandler
       2: invokestatic  #15                 // Method org/apache/dubbo/common/logger/LoggerFactory.getLogger:(Ljava/lang/Class;)Lorg/apache/dubbo/common/logger/Logger;
       5: putstatic     #4                  // Field log:Lorg/apache/dubbo/common/logger/Logger;
       8: return
}
