Compiled from "DataMask.java"
abstract class com.google.zxing.qrcode.decoder.DataMask extends java.lang.Enum<com.google.zxing.qrcode.decoder.DataMask> {
  public static final com.google.zxing.qrcode.decoder.DataMask DATA_MASK_000;

  public static final com.google.zxing.qrcode.decoder.DataMask DATA_MASK_001;

  public static final com.google.zxing.qrcode.decoder.DataMask DATA_MASK_010;

  public static final com.google.zxing.qrcode.decoder.DataMask DATA_MASK_011;

  public static final com.google.zxing.qrcode.decoder.DataMask DATA_MASK_100;

  public static final com.google.zxing.qrcode.decoder.DataMask DATA_MASK_101;

  public static final com.google.zxing.qrcode.decoder.DataMask DATA_MASK_110;

  public static final com.google.zxing.qrcode.decoder.DataMask DATA_MASK_111;

  private static final com.google.zxing.qrcode.decoder.DataMask[] $VALUES;

  public static com.google.zxing.qrcode.decoder.DataMask[] values();
    Code:
       0: getstatic     #2                  // Field $VALUES:[Lcom/google/zxing/qrcode/decoder/DataMask;
       3: invokevirtual #3                  // Method "[Lcom/google/zxing/qrcode/decoder/DataMask;".clone:()Ljava/lang/Object;
       6: checkcast     #4                  // class "[Lcom/google/zxing/qrcode/decoder/DataMask;"
       9: areturn

  public static com.google.zxing.qrcode.decoder.DataMask valueOf(java.lang.String);
    Code:
       0: ldc           #5                  // class com/google/zxing/qrcode/decoder/DataMask
       2: aload_0
       3: invokestatic  #6                  // Method java/lang/Enum.valueOf:(Ljava/lang/Class;Ljava/lang/String;)Ljava/lang/Enum;
       6: checkcast     #5                  // class com/google/zxing/qrcode/decoder/DataMask
       9: areturn

  private com.google.zxing.qrcode.decoder.DataMask();
    Code:
       0: aload_0
       1: aload_1
       2: iload_2
       3: invokespecial #7                  // Method java/lang/Enum."<init>":(Ljava/lang/String;I)V
       6: return

  final void unmaskBitMatrix(com.google.zxing.common.BitMatrix, int);
    Code:
       0: iconst_0
       1: istore_3
       2: iload_3
       3: iload_2
       4: if_icmpge     45
       7: iconst_0
       8: istore        4
      10: iload         4
      12: iload_2
      13: if_icmpge     39
      16: aload_0
      17: iload_3
      18: iload         4
      20: invokevirtual #8                  // Method isMasked:(II)Z
      23: ifeq          33
      26: aload_1
      27: iload         4
      29: iload_3
      30: invokevirtual #9                  // Method com/google/zxing/common/BitMatrix.flip:(II)V
      33: iinc          4, 1
      36: goto          10
      39: iinc          3, 1
      42: goto          2
      45: return

  abstract boolean isMasked(int, int);

  com.google.zxing.qrcode.decoder.DataMask(java.lang.String, int, com.google.zxing.qrcode.decoder.DataMask$1);
    Code:
       0: aload_0
       1: aload_1
       2: iload_2
       3: invokespecial #1                  // Method "<init>":(Ljava/lang/String;I)V
       6: return

  static {};
    Code:
       0: new           #10                 // class com/google/zxing/qrcode/decoder/DataMask$1
       3: dup
       4: ldc           #11                 // String DATA_MASK_000
       6: iconst_0
       7: invokespecial #12                 // Method com/google/zxing/qrcode/decoder/DataMask$1."<init>":(Ljava/lang/String;I)V
      10: putstatic     #13                 // Field DATA_MASK_000:Lcom/google/zxing/qrcode/decoder/DataMask;
      13: new           #14                 // class com/google/zxing/qrcode/decoder/DataMask$2
      16: dup
      17: ldc           #15                 // String DATA_MASK_001
      19: iconst_1
      20: invokespecial #16                 // Method com/google/zxing/qrcode/decoder/DataMask$2."<init>":(Ljava/lang/String;I)V
      23: putstatic     #17                 // Field DATA_MASK_001:Lcom/google/zxing/qrcode/decoder/DataMask;
      26: new           #18                 // class com/google/zxing/qrcode/decoder/DataMask$3
      29: dup
      30: ldc           #19                 // String DATA_MASK_010
      32: iconst_2
      33: invokespecial #20                 // Method com/google/zxing/qrcode/decoder/DataMask$3."<init>":(Ljava/lang/String;I)V
      36: putstatic     #21                 // Field DATA_MASK_010:Lcom/google/zxing/qrcode/decoder/DataMask;
      39: new           #22                 // class com/google/zxing/qrcode/decoder/DataMask$4
      42: dup
      43: ldc           #23                 // String DATA_MASK_011
      45: iconst_3
      46: invokespecial #24                 // Method com/google/zxing/qrcode/decoder/DataMask$4."<init>":(Ljava/lang/String;I)V
      49: putstatic     #25                 // Field DATA_MASK_011:Lcom/google/zxing/qrcode/decoder/DataMask;
      52: new           #26                 // class com/google/zxing/qrcode/decoder/DataMask$5
      55: dup
      56: ldc           #27                 // String DATA_MASK_100
      58: iconst_4
      59: invokespecial #28                 // Method com/google/zxing/qrcode/decoder/DataMask$5."<init>":(Ljava/lang/String;I)V
      62: putstatic     #29                 // Field DATA_MASK_100:Lcom/google/zxing/qrcode/decoder/DataMask;
      65: new           #30                 // class com/google/zxing/qrcode/decoder/DataMask$6
      68: dup
      69: ldc           #31                 // String DATA_MASK_101
      71: iconst_5
      72: invokespecial #32                 // Method com/google/zxing/qrcode/decoder/DataMask$6."<init>":(Ljava/lang/String;I)V
      75: putstatic     #33                 // Field DATA_MASK_101:Lcom/google/zxing/qrcode/decoder/DataMask;
      78: new           #34                 // class com/google/zxing/qrcode/decoder/DataMask$7
      81: dup
      82: ldc           #35                 // String DATA_MASK_110
      84: bipush        6
      86: invokespecial #36                 // Method com/google/zxing/qrcode/decoder/DataMask$7."<init>":(Ljava/lang/String;I)V
      89: putstatic     #37                 // Field DATA_MASK_110:Lcom/google/zxing/qrcode/decoder/DataMask;
      92: new           #38                 // class com/google/zxing/qrcode/decoder/DataMask$8
      95: dup
      96: ldc           #39                 // String DATA_MASK_111
      98: bipush        7
     100: invokespecial #40                 // Method com/google/zxing/qrcode/decoder/DataMask$8."<init>":(Ljava/lang/String;I)V
     103: putstatic     #41                 // Field DATA_MASK_111:Lcom/google/zxing/qrcode/decoder/DataMask;
     106: bipush        8
     108: anewarray     #5                  // class com/google/zxing/qrcode/decoder/DataMask
     111: dup
     112: iconst_0
     113: getstatic     #13                 // Field DATA_MASK_000:Lcom/google/zxing/qrcode/decoder/DataMask;
     116: aastore
     117: dup
     118: iconst_1
     119: getstatic     #17                 // Field DATA_MASK_001:Lcom/google/zxing/qrcode/decoder/DataMask;
     122: aastore
     123: dup
     124: iconst_2
     125: getstatic     #21                 // Field DATA_MASK_010:Lcom/google/zxing/qrcode/decoder/DataMask;
     128: aastore
     129: dup
     130: iconst_3
     131: getstatic     #25                 // Field DATA_MASK_011:Lcom/google/zxing/qrcode/decoder/DataMask;
     134: aastore
     135: dup
     136: iconst_4
     137: getstatic     #29                 // Field DATA_MASK_100:Lcom/google/zxing/qrcode/decoder/DataMask;
     140: aastore
     141: dup
     142: iconst_5
     143: getstatic     #33                 // Field DATA_MASK_101:Lcom/google/zxing/qrcode/decoder/DataMask;
     146: aastore
     147: dup
     148: bipush        6
     150: getstatic     #37                 // Field DATA_MASK_110:Lcom/google/zxing/qrcode/decoder/DataMask;
     153: aastore
     154: dup
     155: bipush        7
     157: getstatic     #41                 // Field DATA_MASK_111:Lcom/google/zxing/qrcode/decoder/DataMask;
     160: aastore
     161: putstatic     #2                  // Field $VALUES:[Lcom/google/zxing/qrcode/decoder/DataMask;
     164: return
}
