Compiled from "Decoder.java"
public final class com.google.zxing.qrcode.decoder.Decoder {
  private final com.google.zxing.common.reedsolomon.ReedSolomonDecoder rsDecoder;

  public com.google.zxing.qrcode.decoder.Decoder();
    Code:
       0: aload_0
       1: invokespecial #1                  // Method java/lang/Object."<init>":()V
       4: aload_0
       5: new           #2                  // class com/google/zxing/common/reedsolomon/ReedSolomonDecoder
       8: dup
       9: getstatic     #3                  // Field com/google/zxing/common/reedsolomon/GenericGF.QR_CODE_FIELD_256:Lcom/google/zxing/common/reedsolomon/GenericGF;
      12: invokespecial #4                  // Method com/google/zxing/common/reedsolomon/ReedSolomonDecoder."<init>":(Lcom/google/zxing/common/reedsolomon/GenericGF;)V
      15: putfield      #5                  // Field rsDecoder:Lcom/google/zxing/common/reedsolomon/ReedSolomonDecoder;
      18: return

  public com.google.zxing.common.DecoderResult decode(boolean[][]) throws com.google.zxing.ChecksumException, com.google.zxing.FormatException;
    Code:
       0: aload_0
       1: aload_1
       2: aconst_null
       3: invokevirtual #6                  // Method decode:([[ZLjava/util/Map;)Lcom/google/zxing/common/DecoderResult;
       6: areturn

  public com.google.zxing.common.DecoderResult decode(boolean[][], java.util.Map<com.google.zxing.DecodeHintType, ?>) throws com.google.zxing.ChecksumException, com.google.zxing.FormatException;
    Code:
       0: aload_0
       1: aload_1
       2: invokestatic  #7                  // Method com/google/zxing/common/BitMatrix.parse:([[Z)Lcom/google/zxing/common/BitMatrix;
       5: aload_2
       6: invokevirtual #8                  // Method decode:(Lcom/google/zxing/common/BitMatrix;Ljava/util/Map;)Lcom/google/zxing/common/DecoderResult;
       9: areturn

  public com.google.zxing.common.DecoderResult decode(com.google.zxing.common.BitMatrix) throws com.google.zxing.ChecksumException, com.google.zxing.FormatException;
    Code:
       0: aload_0
       1: aload_1
       2: aconst_null
       3: invokevirtual #8                  // Method decode:(Lcom/google/zxing/common/BitMatrix;Ljava/util/Map;)Lcom/google/zxing/common/DecoderResult;
       6: areturn

  public com.google.zxing.common.DecoderResult decode(com.google.zxing.common.BitMatrix, java.util.Map<com.google.zxing.DecodeHintType, ?>) throws com.google.zxing.FormatException, com.google.zxing.ChecksumException;
    Code:
       0: new           #9                  // class com/google/zxing/qrcode/decoder/BitMatrixParser
       3: dup
       4: aload_1
       5: invokespecial #10                 // Method com/google/zxing/qrcode/decoder/BitMatrixParser."<init>":(Lcom/google/zxing/common/BitMatrix;)V
       8: astore_3
       9: aconst_null
      10: astore        4
      12: aconst_null
      13: astore        5
      15: aload_0
      16: aload_3
      17: aload_2
      18: invokespecial #11                 // Method decode:(Lcom/google/zxing/qrcode/decoder/BitMatrixParser;Ljava/util/Map;)Lcom/google/zxing/common/DecoderResult;
      21: areturn
      22: astore        6
      24: aload         6
      26: astore        4
      28: goto          37
      31: astore        6
      33: aload         6
      35: astore        5
      37: aload_3
      38: invokevirtual #14                 // Method com/google/zxing/qrcode/decoder/BitMatrixParser.remask:()V
      41: aload_3
      42: iconst_1
      43: invokevirtual #15                 // Method com/google/zxing/qrcode/decoder/BitMatrixParser.setMirror:(Z)V
      46: aload_3
      47: invokevirtual #16                 // Method com/google/zxing/qrcode/decoder/BitMatrixParser.readVersion:()Lcom/google/zxing/qrcode/decoder/Version;
      50: pop
      51: aload_3
      52: invokevirtual #17                 // Method com/google/zxing/qrcode/decoder/BitMatrixParser.readFormatInformation:()Lcom/google/zxing/qrcode/decoder/FormatInformation;
      55: pop
      56: aload_3
      57: invokevirtual #18                 // Method com/google/zxing/qrcode/decoder/BitMatrixParser.mirror:()V
      60: aload_0
      61: aload_3
      62: aload_2
      63: invokespecial #11                 // Method decode:(Lcom/google/zxing/qrcode/decoder/BitMatrixParser;Ljava/util/Map;)Lcom/google/zxing/common/DecoderResult;
      66: astore        6
      68: aload         6
      70: new           #19                 // class com/google/zxing/qrcode/decoder/QRCodeDecoderMetaData
      73: dup
      74: iconst_1
      75: invokespecial #20                 // Method com/google/zxing/qrcode/decoder/QRCodeDecoderMetaData."<init>":(Z)V
      78: invokevirtual #21                 // Method com/google/zxing/common/DecoderResult.setOther:(Ljava/lang/Object;)V
      81: aload         6
      83: areturn
      84: astore        6
      86: aload         4
      88: ifnull        94
      91: aload         4
      93: athrow
      94: aload         5
      96: athrow
    Exception table:
       from    to  target type
          15    21    22   Class com/google/zxing/FormatException
          15    21    31   Class com/google/zxing/ChecksumException
          37    83    84   Class com/google/zxing/FormatException
          37    83    84   Class com/google/zxing/ChecksumException

  private com.google.zxing.common.DecoderResult decode(com.google.zxing.qrcode.decoder.BitMatrixParser, java.util.Map<com.google.zxing.DecodeHintType, ?>) throws com.google.zxing.FormatException, com.google.zxing.ChecksumException;
    Code:
       0: aload_1
       1: invokevirtual #16                 // Method com/google/zxing/qrcode/decoder/BitMatrixParser.readVersion:()Lcom/google/zxing/qrcode/decoder/Version;
       4: astore_3
       5: aload_1
       6: invokevirtual #17                 // Method com/google/zxing/qrcode/decoder/BitMatrixParser.readFormatInformation:()Lcom/google/zxing/qrcode/decoder/FormatInformation;
       9: invokevirtual #22                 // Method com/google/zxing/qrcode/decoder/FormatInformation.getErrorCorrectionLevel:()Lcom/google/zxing/qrcode/decoder/ErrorCorrectionLevel;
      12: astore        4
      14: aload_1
      15: invokevirtual #23                 // Method com/google/zxing/qrcode/decoder/BitMatrixParser.readCodewords:()[B
      18: astore        5
      20: aload         5
      22: aload_3
      23: aload         4
      25: invokestatic  #24                 // Method com/google/zxing/qrcode/decoder/DataBlock.getDataBlocks:([BLcom/google/zxing/qrcode/decoder/Version;Lcom/google/zxing/qrcode/decoder/ErrorCorrectionLevel;)[Lcom/google/zxing/qrcode/decoder/DataBlock;
      28: astore        6
      30: iconst_0
      31: istore        7
      33: aload         6
      35: astore        8
      37: aload         8
      39: arraylength
      40: istore        9
      42: iconst_0
      43: istore        10
      45: iload         10
      47: iload         9
      49: if_icmpge     75
      52: aload         8
      54: iload         10
      56: aaload
      57: astore        11
      59: iload         7
      61: aload         11
      63: invokevirtual #25                 // Method com/google/zxing/qrcode/decoder/DataBlock.getNumDataCodewords:()I
      66: iadd
      67: istore        7
      69: iinc          10, 1
      72: goto          45
      75: iload         7
      77: newarray       byte
      79: astore        8
      81: iconst_0
      82: istore        9
      84: aload         6
      86: astore        10
      88: aload         10
      90: arraylength
      91: istore        11
      93: iconst_0
      94: istore        12
      96: iload         12
      98: iload         11
     100: if_icmpge     167
     103: aload         10
     105: iload         12
     107: aaload
     108: astore        13
     110: aload         13
     112: invokevirtual #26                 // Method com/google/zxing/qrcode/decoder/DataBlock.getCodewords:()[B
     115: astore        14
     117: aload         13
     119: invokevirtual #25                 // Method com/google/zxing/qrcode/decoder/DataBlock.getNumDataCodewords:()I
     122: istore        15
     124: aload_0
     125: aload         14
     127: iload         15
     129: invokespecial #27                 // Method correctErrors:([BI)V
     132: iconst_0
     133: istore        16
     135: iload         16
     137: iload         15
     139: if_icmpge     161
     142: aload         8
     144: iload         9
     146: iinc          9, 1
     149: aload         14
     151: iload         16
     153: baload
     154: bastore
     155: iinc          16, 1
     158: goto          135
     161: iinc          12, 1
     164: goto          96
     167: aload         8
     169: aload_3
     170: aload         4
     172: aload_2
     173: invokestatic  #28                 // Method com/google/zxing/qrcode/decoder/DecodedBitStreamParser.decode:([BLcom/google/zxing/qrcode/decoder/Version;Lcom/google/zxing/qrcode/decoder/ErrorCorrectionLevel;Ljava/util/Map;)Lcom/google/zxing/common/DecoderResult;
     176: areturn

  private void correctErrors(byte[], int) throws com.google.zxing.ChecksumException;
    Code:
       0: aload_1
       1: arraylength
       2: istore_3
       3: iload_3
       4: newarray       int
       6: astore        4
       8: iconst_0
       9: istore        5
      11: iload         5
      13: iload_3
      14: if_icmpge     36
      17: aload         4
      19: iload         5
      21: aload_1
      22: iload         5
      24: baload
      25: sipush        255
      28: iand
      29: iastore
      30: iinc          5, 1
      33: goto          11
      36: aload_0
      37: getfield      #5                  // Field rsDecoder:Lcom/google/zxing/common/reedsolomon/ReedSolomonDecoder;
      40: aload         4
      42: aload_1
      43: arraylength
      44: iload_2
      45: isub
      46: invokevirtual #29                 // Method com/google/zxing/common/reedsolomon/ReedSolomonDecoder.decode:([II)V
      49: goto          58
      52: astore        5
      54: invokestatic  #31                 // Method com/google/zxing/ChecksumException.getChecksumInstance:()Lcom/google/zxing/ChecksumException;
      57: athrow
      58: iconst_0
      59: istore        5
      61: iload         5
      63: iload_2
      64: if_icmpge     83
      67: aload_1
      68: iload         5
      70: aload         4
      72: iload         5
      74: iaload
      75: i2b
      76: bastore
      77: iinc          5, 1
      80: goto          61
      83: return
    Exception table:
       from    to  target type
          36    49    52   Class com/google/zxing/common/reedsolomon/ReedSolomonException
}
