Compiled from "ErrorCorrectionLevel.java"
public final class com.google.zxing.qrcode.decoder.ErrorCorrectionLevel extends java.lang.Enum<com.google.zxing.qrcode.decoder.ErrorCorrectionLevel> {
  public static final com.google.zxing.qrcode.decoder.ErrorCorrectionLevel L;

  public static final com.google.zxing.qrcode.decoder.ErrorCorrectionLevel M;

  public static final com.google.zxing.qrcode.decoder.ErrorCorrectionLevel Q;

  public static final com.google.zxing.qrcode.decoder.ErrorCorrectionLevel H;

  private static final com.google.zxing.qrcode.decoder.ErrorCorrectionLevel[] FOR_BITS;

  private final int bits;

  private static final com.google.zxing.qrcode.decoder.ErrorCorrectionLevel[] $VALUES;

  public static com.google.zxing.qrcode.decoder.ErrorCorrectionLevel[] values();
    Code:
       0: getstatic     #1                  // Field $VALUES:[Lcom/google/zxing/qrcode/decoder/ErrorCorrectionLevel;
       3: invokevirtual #2                  // Method "[Lcom/google/zxing/qrcode/decoder/ErrorCorrectionLevel;".clone:()Ljava/lang/Object;
       6: checkcast     #3                  // class "[Lcom/google/zxing/qrcode/decoder/ErrorCorrectionLevel;"
       9: areturn

  public static com.google.zxing.qrcode.decoder.ErrorCorrectionLevel valueOf(java.lang.String);
    Code:
       0: ldc           #4                  // class com/google/zxing/qrcode/decoder/ErrorCorrectionLevel
       2: aload_0
       3: invokestatic  #5                  // Method java/lang/Enum.valueOf:(Ljava/lang/Class;Ljava/lang/String;)Ljava/lang/Enum;
       6: checkcast     #4                  // class com/google/zxing/qrcode/decoder/ErrorCorrectionLevel
       9: areturn

  private com.google.zxing.qrcode.decoder.ErrorCorrectionLevel(int);
    Code:
       0: aload_0
       1: aload_1
       2: iload_2
       3: invokespecial #6                  // Method java/lang/Enum."<init>":(Ljava/lang/String;I)V
       6: aload_0
       7: iload_3
       8: putfield      #7                  // Field bits:I
      11: return

  public int getBits();
    Code:
       0: aload_0
       1: getfield      #7                  // Field bits:I
       4: ireturn

  public static com.google.zxing.qrcode.decoder.ErrorCorrectionLevel forBits(int);
    Code:
       0: iload_0
       1: iflt          12
       4: iload_0
       5: getstatic     #8                  // Field FOR_BITS:[Lcom/google/zxing/qrcode/decoder/ErrorCorrectionLevel;
       8: arraylength
       9: if_icmplt     20
      12: new           #9                  // class java/lang/IllegalArgumentException
      15: dup
      16: invokespecial #10                 // Method java/lang/IllegalArgumentException."<init>":()V
      19: athrow
      20: getstatic     #8                  // Field FOR_BITS:[Lcom/google/zxing/qrcode/decoder/ErrorCorrectionLevel;
      23: iload_0
      24: aaload
      25: areturn

  static {};
    Code:
       0: new           #4                  // class com/google/zxing/qrcode/decoder/ErrorCorrectionLevel
       3: dup
       4: ldc           #11                 // String L
       6: iconst_0
       7: iconst_1
       8: invokespecial #12                 // Method "<init>":(Ljava/lang/String;II)V
      11: putstatic     #13                 // Field L:Lcom/google/zxing/qrcode/decoder/ErrorCorrectionLevel;
      14: new           #4                  // class com/google/zxing/qrcode/decoder/ErrorCorrectionLevel
      17: dup
      18: ldc           #14                 // String M
      20: iconst_1
      21: iconst_0
      22: invokespecial #12                 // Method "<init>":(Ljava/lang/String;II)V
      25: putstatic     #15                 // Field M:Lcom/google/zxing/qrcode/decoder/ErrorCorrectionLevel;
      28: new           #4                  // class com/google/zxing/qrcode/decoder/ErrorCorrectionLevel
      31: dup
      32: ldc           #16                 // String Q
      34: iconst_2
      35: iconst_3
      36: invokespecial #12                 // Method "<init>":(Ljava/lang/String;II)V
      39: putstatic     #17                 // Field Q:Lcom/google/zxing/qrcode/decoder/ErrorCorrectionLevel;
      42: new           #4                  // class com/google/zxing/qrcode/decoder/ErrorCorrectionLevel
      45: dup
      46: ldc           #18                 // String H
      48: iconst_3
      49: iconst_2
      50: invokespecial #12                 // Method "<init>":(Ljava/lang/String;II)V
      53: putstatic     #19                 // Field H:Lcom/google/zxing/qrcode/decoder/ErrorCorrectionLevel;
      56: iconst_4
      57: anewarray     #4                  // class com/google/zxing/qrcode/decoder/ErrorCorrectionLevel
      60: dup
      61: iconst_0
      62: getstatic     #13                 // Field L:Lcom/google/zxing/qrcode/decoder/ErrorCorrectionLevel;
      65: aastore
      66: dup
      67: iconst_1
      68: getstatic     #15                 // Field M:Lcom/google/zxing/qrcode/decoder/ErrorCorrectionLevel;
      71: aastore
      72: dup
      73: iconst_2
      74: getstatic     #17                 // Field Q:Lcom/google/zxing/qrcode/decoder/ErrorCorrectionLevel;
      77: aastore
      78: dup
      79: iconst_3
      80: getstatic     #19                 // Field H:Lcom/google/zxing/qrcode/decoder/ErrorCorrectionLevel;
      83: aastore
      84: putstatic     #1                  // Field $VALUES:[Lcom/google/zxing/qrcode/decoder/ErrorCorrectionLevel;
      87: iconst_4
      88: anewarray     #4                  // class com/google/zxing/qrcode/decoder/ErrorCorrectionLevel
      91: dup
      92: iconst_0
      93: getstatic     #15                 // Field M:Lcom/google/zxing/qrcode/decoder/ErrorCorrectionLevel;
      96: aastore
      97: dup
      98: iconst_1
      99: getstatic     #13                 // Field L:Lcom/google/zxing/qrcode/decoder/ErrorCorrectionLevel;
     102: aastore
     103: dup
     104: iconst_2
     105: getstatic     #19                 // Field H:Lcom/google/zxing/qrcode/decoder/ErrorCorrectionLevel;
     108: aastore
     109: dup
     110: iconst_3
     111: getstatic     #17                 // Field Q:Lcom/google/zxing/qrcode/decoder/ErrorCorrectionLevel;
     114: aastore
     115: putstatic     #8                  // Field FOR_BITS:[Lcom/google/zxing/qrcode/decoder/ErrorCorrectionLevel;
     118: return
}
