Compiled from "Mode.java"
public final class com.google.zxing.qrcode.decoder.Mode extends java.lang.Enum<com.google.zxing.qrcode.decoder.Mode> {
  public static final com.google.zxing.qrcode.decoder.Mode TERMINATOR;

  public static final com.google.zxing.qrcode.decoder.Mode NUMERIC;

  public static final com.google.zxing.qrcode.decoder.Mode ALPHANUMERIC;

  public static final com.google.zxing.qrcode.decoder.Mode STRUCTURED_APPEND;

  public static final com.google.zxing.qrcode.decoder.Mode BYTE;

  public static final com.google.zxing.qrcode.decoder.Mode ECI;

  public static final com.google.zxing.qrcode.decoder.Mode KANJI;

  public static final com.google.zxing.qrcode.decoder.Mode FNC1_FIRST_POSITION;

  public static final com.google.zxing.qrcode.decoder.Mode FNC1_SECOND_POSITION;

  public static final com.google.zxing.qrcode.decoder.Mode HANZI;

  private final int[] characterCountBitsForVersions;

  private final int bits;

  private static final com.google.zxing.qrcode.decoder.Mode[] $VALUES;

  public static com.google.zxing.qrcode.decoder.Mode[] values();
    Code:
       0: getstatic     #1                  // Field $VALUES:[Lcom/google/zxing/qrcode/decoder/Mode;
       3: invokevirtual #2                  // Method "[Lcom/google/zxing/qrcode/decoder/Mode;".clone:()Ljava/lang/Object;
       6: checkcast     #3                  // class "[Lcom/google/zxing/qrcode/decoder/Mode;"
       9: areturn

  public static com.google.zxing.qrcode.decoder.Mode valueOf(java.lang.String);
    Code:
       0: ldc           #4                  // class com/google/zxing/qrcode/decoder/Mode
       2: aload_0
       3: invokestatic  #5                  // Method java/lang/Enum.valueOf:(Ljava/lang/Class;Ljava/lang/String;)Ljava/lang/Enum;
       6: checkcast     #4                  // class com/google/zxing/qrcode/decoder/Mode
       9: areturn

  private com.google.zxing.qrcode.decoder.Mode(int[], int);
    Code:
       0: aload_0
       1: aload_1
       2: iload_2
       3: invokespecial #6                  // Method java/lang/Enum."<init>":(Ljava/lang/String;I)V
       6: aload_0
       7: aload_3
       8: putfield      #7                  // Field characterCountBitsForVersions:[I
      11: aload_0
      12: iload         4
      14: putfield      #8                  // Field bits:I
      17: return

  public static com.google.zxing.qrcode.decoder.Mode forBits(int);
    Code:
       0: iload_0
       1: tableswitch   { // 0 to 13
                     0: 72
                     1: 76
                     2: 80
                     3: 84
                     4: 88
                     5: 92
                     6: 112
                     7: 96
                     8: 100
                     9: 104
                    10: 112
                    11: 112
                    12: 112
                    13: 108
               default: 112
          }
      72: getstatic     #9                  // Field TERMINATOR:Lcom/google/zxing/qrcode/decoder/Mode;
      75: areturn
      76: getstatic     #10                 // Field NUMERIC:Lcom/google/zxing/qrcode/decoder/Mode;
      79: areturn
      80: getstatic     #11                 // Field ALPHANUMERIC:Lcom/google/zxing/qrcode/decoder/Mode;
      83: areturn
      84: getstatic     #12                 // Field STRUCTURED_APPEND:Lcom/google/zxing/qrcode/decoder/Mode;
      87: areturn
      88: getstatic     #13                 // Field BYTE:Lcom/google/zxing/qrcode/decoder/Mode;
      91: areturn
      92: getstatic     #14                 // Field FNC1_FIRST_POSITION:Lcom/google/zxing/qrcode/decoder/Mode;
      95: areturn
      96: getstatic     #15                 // Field ECI:Lcom/google/zxing/qrcode/decoder/Mode;
      99: areturn
     100: getstatic     #16                 // Field KANJI:Lcom/google/zxing/qrcode/decoder/Mode;
     103: areturn
     104: getstatic     #17                 // Field FNC1_SECOND_POSITION:Lcom/google/zxing/qrcode/decoder/Mode;
     107: areturn
     108: getstatic     #18                 // Field HANZI:Lcom/google/zxing/qrcode/decoder/Mode;
     111: areturn
     112: new           #19                 // class java/lang/IllegalArgumentException
     115: dup
     116: invokespecial #20                 // Method java/lang/IllegalArgumentException."<init>":()V
     119: athrow

  public int getCharacterCountBits(com.google.zxing.qrcode.decoder.Version);
    Code:
       0: aload_1
       1: invokevirtual #21                 // Method com/google/zxing/qrcode/decoder/Version.getVersionNumber:()I
       4: istore_2
       5: iload_2
       6: bipush        9
       8: if_icmpgt     16
      11: iconst_0
      12: istore_3
      13: goto          29
      16: iload_2
      17: bipush        26
      19: if_icmpgt     27
      22: iconst_1
      23: istore_3
      24: goto          29
      27: iconst_2
      28: istore_3
      29: aload_0
      30: getfield      #7                  // Field characterCountBitsForVersions:[I
      33: iload_3
      34: iaload
      35: ireturn

  public int getBits();
    Code:
       0: aload_0
       1: getfield      #8                  // Field bits:I
       4: ireturn

  static {};
    Code:
       0: new           #4                  // class com/google/zxing/qrcode/decoder/Mode
       3: dup
       4: ldc           #22                 // String TERMINATOR
       6: iconst_0
       7: iconst_3
       8: newarray       int
      10: dup
      11: iconst_0
      12: iconst_0
      13: iastore
      14: dup
      15: iconst_1
      16: iconst_0
      17: iastore
      18: dup
      19: iconst_2
      20: iconst_0
      21: iastore
      22: iconst_0
      23: invokespecial #23                 // Method "<init>":(Ljava/lang/String;I[II)V
      26: putstatic     #9                  // Field TERMINATOR:Lcom/google/zxing/qrcode/decoder/Mode;
      29: new           #4                  // class com/google/zxing/qrcode/decoder/Mode
      32: dup
      33: ldc           #24                 // String NUMERIC
      35: iconst_1
      36: iconst_3
      37: newarray       int
      39: dup
      40: iconst_0
      41: bipush        10
      43: iastore
      44: dup
      45: iconst_1
      46: bipush        12
      48: iastore
      49: dup
      50: iconst_2
      51: bipush        14
      53: iastore
      54: iconst_1
      55: invokespecial #23                 // Method "<init>":(Ljava/lang/String;I[II)V
      58: putstatic     #10                 // Field NUMERIC:Lcom/google/zxing/qrcode/decoder/Mode;
      61: new           #4                  // class com/google/zxing/qrcode/decoder/Mode
      64: dup
      65: ldc           #25                 // String ALPHANUMERIC
      67: iconst_2
      68: iconst_3
      69: newarray       int
      71: dup
      72: iconst_0
      73: bipush        9
      75: iastore
      76: dup
      77: iconst_1
      78: bipush        11
      80: iastore
      81: dup
      82: iconst_2
      83: bipush        13
      85: iastore
      86: iconst_2
      87: invokespecial #23                 // Method "<init>":(Ljava/lang/String;I[II)V
      90: putstatic     #11                 // Field ALPHANUMERIC:Lcom/google/zxing/qrcode/decoder/Mode;
      93: new           #4                  // class com/google/zxing/qrcode/decoder/Mode
      96: dup
      97: ldc           #26                 // String STRUCTURED_APPEND
      99: iconst_3
     100: iconst_3
     101: newarray       int
     103: dup
     104: iconst_0
     105: iconst_0
     106: iastore
     107: dup
     108: iconst_1
     109: iconst_0
     110: iastore
     111: dup
     112: iconst_2
     113: iconst_0
     114: iastore
     115: iconst_3
     116: invokespecial #23                 // Method "<init>":(Ljava/lang/String;I[II)V
     119: putstatic     #12                 // Field STRUCTURED_APPEND:Lcom/google/zxing/qrcode/decoder/Mode;
     122: new           #4                  // class com/google/zxing/qrcode/decoder/Mode
     125: dup
     126: ldc           #27                 // String BYTE
     128: iconst_4
     129: iconst_3
     130: newarray       int
     132: dup
     133: iconst_0
     134: bipush        8
     136: iastore
     137: dup
     138: iconst_1
     139: bipush        16
     141: iastore
     142: dup
     143: iconst_2
     144: bipush        16
     146: iastore
     147: iconst_4
     148: invokespecial #23                 // Method "<init>":(Ljava/lang/String;I[II)V
     151: putstatic     #13                 // Field BYTE:Lcom/google/zxing/qrcode/decoder/Mode;
     154: new           #4                  // class com/google/zxing/qrcode/decoder/Mode
     157: dup
     158: ldc           #28                 // String ECI
     160: iconst_5
     161: iconst_3
     162: newarray       int
     164: dup
     165: iconst_0
     166: iconst_0
     167: iastore
     168: dup
     169: iconst_1
     170: iconst_0
     171: iastore
     172: dup
     173: iconst_2
     174: iconst_0
     175: iastore
     176: bipush        7
     178: invokespecial #23                 // Method "<init>":(Ljava/lang/String;I[II)V
     181: putstatic     #15                 // Field ECI:Lcom/google/zxing/qrcode/decoder/Mode;
     184: new           #4                  // class com/google/zxing/qrcode/decoder/Mode
     187: dup
     188: ldc           #29                 // String KANJI
     190: bipush        6
     192: iconst_3
     193: newarray       int
     195: dup
     196: iconst_0
     197: bipush        8
     199: iastore
     200: dup
     201: iconst_1
     202: bipush        10
     204: iastore
     205: dup
     206: iconst_2
     207: bipush        12
     209: iastore
     210: bipush        8
     212: invokespecial #23                 // Method "<init>":(Ljava/lang/String;I[II)V
     215: putstatic     #16                 // Field KANJI:Lcom/google/zxing/qrcode/decoder/Mode;
     218: new           #4                  // class com/google/zxing/qrcode/decoder/Mode
     221: dup
     222: ldc           #30                 // String FNC1_FIRST_POSITION
     224: bipush        7
     226: iconst_3
     227: newarray       int
     229: dup
     230: iconst_0
     231: iconst_0
     232: iastore
     233: dup
     234: iconst_1
     235: iconst_0
     236: iastore
     237: dup
     238: iconst_2
     239: iconst_0
     240: iastore
     241: iconst_5
     242: invokespecial #23                 // Method "<init>":(Ljava/lang/String;I[II)V
     245: putstatic     #14                 // Field FNC1_FIRST_POSITION:Lcom/google/zxing/qrcode/decoder/Mode;
     248: new           #4                  // class com/google/zxing/qrcode/decoder/Mode
     251: dup
     252: ldc           #31                 // String FNC1_SECOND_POSITION
     254: bipush        8
     256: iconst_3
     257: newarray       int
     259: dup
     260: iconst_0
     261: iconst_0
     262: iastore
     263: dup
     264: iconst_1
     265: iconst_0
     266: iastore
     267: dup
     268: iconst_2
     269: iconst_0
     270: iastore
     271: bipush        9
     273: invokespecial #23                 // Method "<init>":(Ljava/lang/String;I[II)V
     276: putstatic     #17                 // Field FNC1_SECOND_POSITION:Lcom/google/zxing/qrcode/decoder/Mode;
     279: new           #4                  // class com/google/zxing/qrcode/decoder/Mode
     282: dup
     283: ldc           #32                 // String HANZI
     285: bipush        9
     287: iconst_3
     288: newarray       int
     290: dup
     291: iconst_0
     292: bipush        8
     294: iastore
     295: dup
     296: iconst_1
     297: bipush        10
     299: iastore
     300: dup
     301: iconst_2
     302: bipush        12
     304: iastore
     305: bipush        13
     307: invokespecial #23                 // Method "<init>":(Ljava/lang/String;I[II)V
     310: putstatic     #18                 // Field HANZI:Lcom/google/zxing/qrcode/decoder/Mode;
     313: bipush        10
     315: anewarray     #4                  // class com/google/zxing/qrcode/decoder/Mode
     318: dup
     319: iconst_0
     320: getstatic     #9                  // Field TERMINATOR:Lcom/google/zxing/qrcode/decoder/Mode;
     323: aastore
     324: dup
     325: iconst_1
     326: getstatic     #10                 // Field NUMERIC:Lcom/google/zxing/qrcode/decoder/Mode;
     329: aastore
     330: dup
     331: iconst_2
     332: getstatic     #11                 // Field ALPHANUMERIC:Lcom/google/zxing/qrcode/decoder/Mode;
     335: aastore
     336: dup
     337: iconst_3
     338: getstatic     #12                 // Field STRUCTURED_APPEND:Lcom/google/zxing/qrcode/decoder/Mode;
     341: aastore
     342: dup
     343: iconst_4
     344: getstatic     #13                 // Field BYTE:Lcom/google/zxing/qrcode/decoder/Mode;
     347: aastore
     348: dup
     349: iconst_5
     350: getstatic     #15                 // Field ECI:Lcom/google/zxing/qrcode/decoder/Mode;
     353: aastore
     354: dup
     355: bipush        6
     357: getstatic     #16                 // Field KANJI:Lcom/google/zxing/qrcode/decoder/Mode;
     360: aastore
     361: dup
     362: bipush        7
     364: getstatic     #14                 // Field FNC1_FIRST_POSITION:Lcom/google/zxing/qrcode/decoder/Mode;
     367: aastore
     368: dup
     369: bipush        8
     371: getstatic     #17                 // Field FNC1_SECOND_POSITION:Lcom/google/zxing/qrcode/decoder/Mode;
     374: aastore
     375: dup
     376: bipush        9
     378: getstatic     #18                 // Field HANZI:Lcom/google/zxing/qrcode/decoder/Mode;
     381: aastore
     382: putstatic     #1                  // Field $VALUES:[Lcom/google/zxing/qrcode/decoder/Mode;
     385: return
}
