Compiled from "Version.java"
public final class com.google.zxing.qrcode.decoder.Version$ECBlocks {
  private final int ecCodewordsPerBlock;

  private final com.google.zxing.qrcode.decoder.Version$ECB[] ecBlocks;

  com.google.zxing.qrcode.decoder.Version$ECBlocks(int, com.google.zxing.qrcode.decoder.Version$ECB...);
    Code:
       0: aload_0
       1: invokespecial #1                  // Method java/lang/Object."<init>":()V
       4: aload_0
       5: iload_1
       6: putfield      #2                  // Field ecCodewordsPerBlock:I
       9: aload_0
      10: aload_2
      11: putfield      #3                  // Field ecBlocks:[Lcom/google/zxing/qrcode/decoder/Version$ECB;
      14: return

  public int getECCodewordsPerBlock();
    Code:
       0: aload_0
       1: getfield      #2                  // Field ecCodewordsPerBlock:I
       4: ireturn

  public int getNumBlocks();
    Code:
       0: iconst_0
       1: istore_1
       2: aload_0
       3: getfield      #3                  // Field ecBlocks:[Lcom/google/zxing/qrcode/decoder/Version$ECB;
       6: astore_2
       7: aload_2
       8: arraylength
       9: istore_3
      10: iconst_0
      11: istore        4
      13: iload         4
      15: iload_3
      16: if_icmpge     39
      19: aload_2
      20: iload         4
      22: aaload
      23: astore        5
      25: iload_1
      26: aload         5
      28: invokevirtual #4                  // Method com/google/zxing/qrcode/decoder/Version$ECB.getCount:()I
      31: iadd
      32: istore_1
      33: iinc          4, 1
      36: goto          13
      39: iload_1
      40: ireturn

  public int getTotalECCodewords();
    Code:
       0: aload_0
       1: getfield      #2                  // Field ecCodewordsPerBlock:I
       4: aload_0
       5: invokevirtual #5                  // Method getNumBlocks:()I
       8: imul
       9: ireturn

  public com.google.zxing.qrcode.decoder.Version$ECB[] getECBlocks();
    Code:
       0: aload_0
       1: getfield      #3                  // Field ecBlocks:[Lcom/google/zxing/qrcode/decoder/Version$ECB;
       4: areturn
}
