Compiled from "Version.java"
public final class com.google.zxing.qrcode.decoder.Version$ECB {
  private final int count;

  private final int dataCodewords;

  com.google.zxing.qrcode.decoder.Version$ECB(int, int);
    Code:
       0: aload_0
       1: invokespecial #1                  // Method java/lang/Object."<init>":()V
       4: aload_0
       5: iload_1
       6: putfield      #2                  // Field count:I
       9: aload_0
      10: iload_2
      11: putfield      #3                  // Field dataCodewords:I
      14: return

  public int getCount();
    Code:
       0: aload_0
       1: getfield      #2                  // Field count:I
       4: ireturn

  public int getDataCodewords();
    Code:
       0: aload_0
       1: getfield      #3                  // Field dataCodewords:I
       4: ireturn
}
