Compiled from "Version.java"
public final class com.google.zxing.qrcode.decoder.Version {
  private static final int[] VERSION_DECODE_INFO;

  private static final com.google.zxing.qrcode.decoder.Version[] VERSIONS;

  private final int versionNumber;

  private final int[] alignmentPatternCenters;

  private final com.google.zxing.qrcode.decoder.Version$ECBlocks[] ecBlocks;

  private final int totalCodewords;

  private com.google.zxing.qrcode.decoder.Version(int, int[], com.google.zxing.qrcode.decoder.Version$ECBlocks...);
    Code:
       0: aload_0
       1: invokespecial #1                  // Method java/lang/Object."<init>":()V
       4: aload_0
       5: iload_1
       6: putfield      #2                  // Field versionNumber:I
       9: aload_0
      10: aload_2
      11: putfield      #3                  // Field alignmentPatternCenters:[I
      14: aload_0
      15: aload_3
      16: putfield      #4                  // Field ecBlocks:[Lcom/google/zxing/qrcode/decoder/Version$ECBlocks;
      19: iconst_0
      20: istore        4
      22: aload_3
      23: iconst_0
      24: aaload
      25: invokevirtual #5                  // Method com/google/zxing/qrcode/decoder/Version$ECBlocks.getECCodewordsPerBlock:()I
      28: istore        5
      30: aload_3
      31: iconst_0
      32: aaload
      33: invokevirtual #6                  // Method com/google/zxing/qrcode/decoder/Version$ECBlocks.getECBlocks:()[Lcom/google/zxing/qrcode/decoder/Version$ECB;
      36: astore        6
      38: aload         6
      40: astore        7
      42: aload         7
      44: arraylength
      45: istore        8
      47: iconst_0
      48: istore        9
      50: iload         9
      52: iload         8
      54: if_icmpge     89
      57: aload         7
      59: iload         9
      61: aaload
      62: astore        10
      64: iload         4
      66: aload         10
      68: invokevirtual #7                  // Method com/google/zxing/qrcode/decoder/Version$ECB.getCount:()I
      71: aload         10
      73: invokevirtual #8                  // Method com/google/zxing/qrcode/decoder/Version$ECB.getDataCodewords:()I
      76: iload         5
      78: iadd
      79: imul
      80: iadd
      81: istore        4
      83: iinc          9, 1
      86: goto          50
      89: aload_0
      90: iload         4
      92: putfield      #9                  // Field totalCodewords:I
      95: return

  public int getVersionNumber();
    Code:
       0: aload_0
       1: getfield      #2                  // Field versionNumber:I
       4: ireturn

  public int[] getAlignmentPatternCenters();
    Code:
       0: aload_0
       1: getfield      #3                  // Field alignmentPatternCenters:[I
       4: areturn

  public int getTotalCodewords();
    Code:
       0: aload_0
       1: getfield      #9                  // Field totalCodewords:I
       4: ireturn

  public int getDimensionForVersion();
    Code:
       0: bipush        17
       2: iconst_4
       3: aload_0
       4: getfield      #2                  // Field versionNumber:I
       7: imul
       8: iadd
       9: ireturn

  public com.google.zxing.qrcode.decoder.Version$ECBlocks getECBlocksForLevel(com.google.zxing.qrcode.decoder.ErrorCorrectionLevel);
    Code:
       0: aload_0
       1: getfield      #4                  // Field ecBlocks:[Lcom/google/zxing/qrcode/decoder/Version$ECBlocks;
       4: aload_1
       5: invokevirtual #10                 // Method com/google/zxing/qrcode/decoder/ErrorCorrectionLevel.ordinal:()I
       8: aaload
       9: areturn

  public static com.google.zxing.qrcode.decoder.Version getProvisionalVersionForDimension(int) throws com.google.zxing.FormatException;
    Code:
       0: iload_0
       1: iconst_4
       2: irem
       3: iconst_1
       4: if_icmpeq     11
       7: invokestatic  #11                 // Method com/google/zxing/FormatException.getFormatInstance:()Lcom/google/zxing/FormatException;
      10: athrow
      11: iload_0
      12: bipush        17
      14: isub
      15: iconst_4
      16: idiv
      17: invokestatic  #12                 // Method getVersionForNumber:(I)Lcom/google/zxing/qrcode/decoder/Version;
      20: areturn
      21: astore_1
      22: invokestatic  #11                 // Method com/google/zxing/FormatException.getFormatInstance:()Lcom/google/zxing/FormatException;
      25: athrow
    Exception table:
       from    to  target type
          11    20    21   Class java/lang/IllegalArgumentException

  public static com.google.zxing.qrcode.decoder.Version getVersionForNumber(int);
    Code:
       0: iload_0
       1: iconst_1
       2: if_icmplt     11
       5: iload_0
       6: bipush        40
       8: if_icmple     19
      11: new           #13                 // class java/lang/IllegalArgumentException
      14: dup
      15: invokespecial #14                 // Method java/lang/IllegalArgumentException."<init>":()V
      18: athrow
      19: getstatic     #15                 // Field VERSIONS:[Lcom/google/zxing/qrcode/decoder/Version;
      22: iload_0
      23: iconst_1
      24: isub
      25: aaload
      26: areturn

  static com.google.zxing.qrcode.decoder.Version decodeVersionInformation(int);
    Code:
       0: ldc           #17                 // int 2147483647
       2: istore_1
       3: iconst_0
       4: istore_2
       5: iconst_0
       6: istore_3
       7: iload_3
       8: getstatic     #18                 // Field VERSION_DECODE_INFO:[I
      11: arraylength
      12: if_icmpge     64
      15: getstatic     #18                 // Field VERSION_DECODE_INFO:[I
      18: iload_3
      19: iaload
      20: istore        4
      22: iload         4
      24: iload_0
      25: if_icmpne     36
      28: iload_3
      29: bipush        7
      31: iadd
      32: invokestatic  #12                 // Method getVersionForNumber:(I)Lcom/google/zxing/qrcode/decoder/Version;
      35: areturn
      36: iload_0
      37: iload         4
      39: invokestatic  #19                 // Method com/google/zxing/qrcode/decoder/FormatInformation.numBitsDiffering:(II)I
      42: istore        5
      44: iload         5
      46: iload_1
      47: if_icmpge     58
      50: iload_3
      51: bipush        7
      53: iadd
      54: istore_2
      55: iload         5
      57: istore_1
      58: iinc          3, 1
      61: goto          7
      64: iload_1
      65: iconst_3
      66: if_icmpgt     74
      69: iload_2
      70: invokestatic  #12                 // Method getVersionForNumber:(I)Lcom/google/zxing/qrcode/decoder/Version;
      73: areturn
      74: aconst_null
      75: areturn

  com.google.zxing.common.BitMatrix buildFunctionPattern();
    Code:
       0: aload_0
       1: invokevirtual #20                 // Method getDimensionForVersion:()I
       4: istore_1
       5: new           #21                 // class com/google/zxing/common/BitMatrix
       8: dup
       9: iload_1
      10: invokespecial #22                 // Method com/google/zxing/common/BitMatrix."<init>":(I)V
      13: astore_2
      14: aload_2
      15: iconst_0
      16: iconst_0
      17: bipush        9
      19: bipush        9
      21: invokevirtual #23                 // Method com/google/zxing/common/BitMatrix.setRegion:(IIII)V
      24: aload_2
      25: iload_1
      26: bipush        8
      28: isub
      29: iconst_0
      30: bipush        8
      32: bipush        9
      34: invokevirtual #23                 // Method com/google/zxing/common/BitMatrix.setRegion:(IIII)V
      37: aload_2
      38: iconst_0
      39: iload_1
      40: bipush        8
      42: isub
      43: bipush        9
      45: bipush        8
      47: invokevirtual #23                 // Method com/google/zxing/common/BitMatrix.setRegion:(IIII)V
      50: aload_0
      51: getfield      #3                  // Field alignmentPatternCenters:[I
      54: arraylength
      55: istore_3
      56: iconst_0
      57: istore        4
      59: iload         4
      61: iload_3
      62: if_icmpge     145
      65: aload_0
      66: getfield      #3                  // Field alignmentPatternCenters:[I
      69: iload         4
      71: iaload
      72: iconst_2
      73: isub
      74: istore        5
      76: iconst_0
      77: istore        6
      79: iload         6
      81: iload_3
      82: if_icmpge     139
      85: iload         4
      87: ifne          103
      90: iload         6
      92: ifeq          133
      95: iload         6
      97: iload_3
      98: iconst_1
      99: isub
     100: if_icmpeq     133
     103: iload         4
     105: iload_3
     106: iconst_1
     107: isub
     108: if_icmpne     116
     111: iload         6
     113: ifeq          133
     116: aload_2
     117: aload_0
     118: getfield      #3                  // Field alignmentPatternCenters:[I
     121: iload         6
     123: iaload
     124: iconst_2
     125: isub
     126: iload         5
     128: iconst_5
     129: iconst_5
     130: invokevirtual #23                 // Method com/google/zxing/common/BitMatrix.setRegion:(IIII)V
     133: iinc          6, 1
     136: goto          79
     139: iinc          4, 1
     142: goto          59
     145: aload_2
     146: bipush        6
     148: bipush        9
     150: iconst_1
     151: iload_1
     152: bipush        17
     154: isub
     155: invokevirtual #23                 // Method com/google/zxing/common/BitMatrix.setRegion:(IIII)V
     158: aload_2
     159: bipush        9
     161: bipush        6
     163: iload_1
     164: bipush        17
     166: isub
     167: iconst_1
     168: invokevirtual #23                 // Method com/google/zxing/common/BitMatrix.setRegion:(IIII)V
     171: aload_0
     172: getfield      #2                  // Field versionNumber:I
     175: bipush        6
     177: if_icmple     204
     180: aload_2
     181: iload_1
     182: bipush        11
     184: isub
     185: iconst_0
     186: iconst_3
     187: bipush        6
     189: invokevirtual #23                 // Method com/google/zxing/common/BitMatrix.setRegion:(IIII)V
     192: aload_2
     193: iconst_0
     194: iload_1
     195: bipush        11
     197: isub
     198: bipush        6
     200: iconst_3
     201: invokevirtual #23                 // Method com/google/zxing/common/BitMatrix.setRegion:(IIII)V
     204: aload_2
     205: areturn

  public java.lang.String toString();
    Code:
       0: aload_0
       1: getfield      #2                  // Field versionNumber:I
       4: invokestatic  #24                 // Method java/lang/String.valueOf:(I)Ljava/lang/String;
       7: areturn

  private static com.google.zxing.qrcode.decoder.Version[] buildVersions();
    Code:
       0: bipush        40
       2: anewarray     #25                 // class com/google/zxing/qrcode/decoder/Version
       5: dup
       6: iconst_0
       7: new           #25                 // class com/google/zxing/qrcode/decoder/Version
      10: dup
      11: iconst_1
      12: iconst_0
      13: newarray       int
      15: iconst_4
      16: anewarray     #26                 // class com/google/zxing/qrcode/decoder/Version$ECBlocks
      19: dup
      20: iconst_0
      21: new           #26                 // class com/google/zxing/qrcode/decoder/Version$ECBlocks
      24: dup
      25: bipush        7
      27: iconst_1
      28: anewarray     #27                 // class com/google/zxing/qrcode/decoder/Version$ECB
      31: dup
      32: iconst_0
      33: new           #27                 // class com/google/zxing/qrcode/decoder/Version$ECB
      36: dup
      37: iconst_1
      38: bipush        19
      40: invokespecial #28                 // Method com/google/zxing/qrcode/decoder/Version$ECB."<init>":(II)V
      43: aastore
      44: invokespecial #29                 // Method com/google/zxing/qrcode/decoder/Version$ECBlocks."<init>":(I[Lcom/google/zxing/qrcode/decoder/Version$ECB;)V
      47: aastore
      48: dup
      49: iconst_1
      50: new           #26                 // class com/google/zxing/qrcode/decoder/Version$ECBlocks
      53: dup
      54: bipush        10
      56: iconst_1
      57: anewarray     #27                 // class com/google/zxing/qrcode/decoder/Version$ECB
      60: dup
      61: iconst_0
      62: new           #27                 // class com/google/zxing/qrcode/decoder/Version$ECB
      65: dup
      66: iconst_1
      67: bipush        16
      69: invokespecial #28                 // Method com/google/zxing/qrcode/decoder/Version$ECB."<init>":(II)V
      72: aastore
      73: invokespecial #29                 // Method com/google/zxing/qrcode/decoder/Version$ECBlocks."<init>":(I[Lcom/google/zxing/qrcode/decoder/Version$ECB;)V
      76: aastore
      77: dup
      78: iconst_2
      79: new           #26                 // class com/google/zxing/qrcode/decoder/Version$ECBlocks
      82: dup
      83: bipush        13
      85: iconst_1
      86: anewarray     #27                 // class com/google/zxing/qrcode/decoder/Version$ECB
      89: dup
      90: iconst_0
      91: new           #27                 // class com/google/zxing/qrcode/decoder/Version$ECB
      94: dup
      95: iconst_1
      96: bipush        13
      98: invokespecial #28                 // Method com/google/zxing/qrcode/decoder/Version$ECB."<init>":(II)V
     101: aastore
     102: invokespecial #29                 // Method com/google/zxing/qrcode/decoder/Version$ECBlocks."<init>":(I[Lcom/google/zxing/qrcode/decoder/Version$ECB;)V
     105: aastore
     106: dup
     107: iconst_3
     108: new           #26                 // class com/google/zxing/qrcode/decoder/Version$ECBlocks
     111: dup
     112: bipush        17
     114: iconst_1
     115: anewarray     #27                 // class com/google/zxing/qrcode/decoder/Version$ECB
     118: dup
     119: iconst_0
     120: new           #27                 // class com/google/zxing/qrcode/decoder/Version$ECB
     123: dup
     124: iconst_1
     125: bipush        9
     127: invokespecial #28                 // Method com/google/zxing/qrcode/decoder/Version$ECB."<init>":(II)V
     130: aastore
     131: invokespecial #29                 // Method com/google/zxing/qrcode/decoder/Version$ECBlocks."<init>":(I[Lcom/google/zxing/qrcode/decoder/Version$ECB;)V
     134: aastore
     135: invokespecial #30                 // Method "<init>":(I[I[Lcom/google/zxing/qrcode/decoder/Version$ECBlocks;)V
     138: aastore
     139: dup
     140: iconst_1
     141: new           #25                 // class com/google/zxing/qrcode/decoder/Version
     144: dup
     145: iconst_2
     146: iconst_2
     147: newarray       int
     149: dup
     150: iconst_0
     151: bipush        6
     153: iastore
     154: dup
     155: iconst_1
     156: bipush        18
     158: iastore
     159: iconst_4
     160: anewarray     #26                 // class com/google/zxing/qrcode/decoder/Version$ECBlocks
     163: dup
     164: iconst_0
     165: new           #26                 // class com/google/zxing/qrcode/decoder/Version$ECBlocks
     168: dup
     169: bipush        10
     171: iconst_1
     172: anewarray     #27                 // class com/google/zxing/qrcode/decoder/Version$ECB
     175: dup
     176: iconst_0
     177: new           #27                 // class com/google/zxing/qrcode/decoder/Version$ECB
     180: dup
     181: iconst_1
     182: bipush        34
     184: invokespecial #28                 // Method com/google/zxing/qrcode/decoder/Version$ECB."<init>":(II)V
     187: aastore
     188: invokespecial #29                 // Method com/google/zxing/qrcode/decoder/Version$ECBlocks."<init>":(I[Lcom/google/zxing/qrcode/decoder/Version$ECB;)V
     191: aastore
     192: dup
     193: iconst_1
     194: new           #26                 // class com/google/zxing/qrcode/decoder/Version$ECBlocks
     197: dup
     198: bipush        16
     200: iconst_1
     201: anewarray     #27                 // class com/google/zxing/qrcode/decoder/Version$ECB
     204: dup
     205: iconst_0
     206: new           #27                 // class com/google/zxing/qrcode/decoder/Version$ECB
     209: dup
     210: iconst_1
     211: bipush        28
     213: invokespecial #28                 // Method com/google/zxing/qrcode/decoder/Version$ECB."<init>":(II)V
     216: aastore
     217: invokespecial #29                 // Method com/google/zxing/qrcode/decoder/Version$ECBlocks."<init>":(I[Lcom/google/zxing/qrcode/decoder/Version$ECB;)V
     220: aastore
     221: dup
     222: iconst_2
     223: new           #26                 // class com/google/zxing/qrcode/decoder/Version$ECBlocks
     226: dup
     227: bipush        22
     229: iconst_1
     230: anewarray     #27                 // class com/google/zxing/qrcode/decoder/Version$ECB
     233: dup
     234: iconst_0
     235: new           #27                 // class com/google/zxing/qrcode/decoder/Version$ECB
     238: dup
     239: iconst_1
     240: bipush        22
     242: invokespecial #28                 // Method com/google/zxing/qrcode/decoder/Version$ECB."<init>":(II)V
     245: aastore
     246: invokespecial #29                 // Method com/google/zxing/qrcode/decoder/Version$ECBlocks."<init>":(I[Lcom/google/zxing/qrcode/decoder/Version$ECB;)V
     249: aastore
     250: dup
     251: iconst_3
     252: new           #26                 // class com/google/zxing/qrcode/decoder/Version$ECBlocks
     255: dup
     256: bipush        28
     258: iconst_1
     259: anewarray     #27                 // class com/google/zxing/qrcode/decoder/Version$ECB
     262: dup
     263: iconst_0
     264: new           #27                 // class com/google/zxing/qrcode/decoder/Version$ECB
     267: dup
     268: iconst_1
     269: bipush        16
     271: invokespecial #28                 // Method com/google/zxing/qrcode/decoder/Version$ECB."<init>":(II)V
     274: aastore
     275: invokespecial #29                 // Method com/google/zxing/qrcode/decoder/Version$ECBlocks."<init>":(I[Lcom/google/zxing/qrcode/decoder/Version$ECB;)V
     278: aastore
     279: invokespecial #30                 // Method "<init>":(I[I[Lcom/google/zxing/qrcode/decoder/Version$ECBlocks;)V
     282: aastore
     283: dup
     284: iconst_2
     285: new           #25                 // class com/google/zxing/qrcode/decoder/Version
     288: dup
     289: iconst_3
     290: iconst_2
     291: newarray       int
     293: dup
     294: iconst_0
     295: bipush        6
     297: iastore
     298: dup
     299: iconst_1
     300: bipush        22
     302: iastore
     303: iconst_4
     304: anewarray     #26                 // class com/google/zxing/qrcode/decoder/Version$ECBlocks
     307: dup
     308: iconst_0
     309: new           #26                 // class com/google/zxing/qrcode/decoder/Version$ECBlocks
     312: dup
     313: bipush        15
     315: iconst_1
     316: anewarray     #27                 // class com/google/zxing/qrcode/decoder/Version$ECB
     319: dup
     320: iconst_0
     321: new           #27                 // class com/google/zxing/qrcode/decoder/Version$ECB
     324: dup
     325: iconst_1
     326: bipush        55
     328: invokespecial #28                 // Method com/google/zxing/qrcode/decoder/Version$ECB."<init>":(II)V
     331: aastore
     332: invokespecial #29                 // Method com/google/zxing/qrcode/decoder/Version$ECBlocks."<init>":(I[Lcom/google/zxing/qrcode/decoder/Version$ECB;)V
     335: aastore
     336: dup
     337: iconst_1
     338: new           #26                 // class com/google/zxing/qrcode/decoder/Version$ECBlocks
     341: dup
     342: bipush        26
     344: iconst_1
     345: anewarray     #27                 // class com/google/zxing/qrcode/decoder/Version$ECB
     348: dup
     349: iconst_0
     350: new           #27                 // class com/google/zxing/qrcode/decoder/Version$ECB
     353: dup
     354: iconst_1
     355: bipush        44
     357: invokespecial #28                 // Method com/google/zxing/qrcode/decoder/Version$ECB."<init>":(II)V
     360: aastore
     361: invokespecial #29                 // Method com/google/zxing/qrcode/decoder/Version$ECBlocks."<init>":(I[Lcom/google/zxing/qrcode/decoder/Version$ECB;)V
     364: aastore
     365: dup
     366: iconst_2
     367: new           #26                 // class com/google/zxing/qrcode/decoder/Version$ECBlocks
     370: dup
     371: bipush        18
     373: iconst_1
     374: anewarray     #27                 // class com/google/zxing/qrcode/decoder/Version$ECB
     377: dup
     378: iconst_0
     379: new           #27                 // class com/google/zxing/qrcode/decoder/Version$ECB
     382: dup
     383: iconst_2
     384: bipush        17
     386: invokespecial #28                 // Method com/google/zxing/qrcode/decoder/Version$ECB."<init>":(II)V
     389: aastore
     390: invokespecial #29                 // Method com/google/zxing/qrcode/decoder/Version$ECBlocks."<init>":(I[Lcom/google/zxing/qrcode/decoder/Version$ECB;)V
     393: aastore
     394: dup
     395: iconst_3
     396: new           #26                 // class com/google/zxing/qrcode/decoder/Version$ECBlocks
     399: dup
     400: bipush        22
     402: iconst_1
     403: anewarray     #27                 // class com/google/zxing/qrcode/decoder/Version$ECB
     406: dup
     407: iconst_0
     408: new           #27                 // class com/google/zxing/qrcode/decoder/Version$ECB
     411: dup
     412: iconst_2
     413: bipush        13
     415: invokespecial #28                 // Method com/google/zxing/qrcode/decoder/Version$ECB."<init>":(II)V
     418: aastore
     419: invokespecial #29                 // Method com/google/zxing/qrcode/decoder/Version$ECBlocks."<init>":(I[Lcom/google/zxing/qrcode/decoder/Version$ECB;)V
     422: aastore
     423: invokespecial #30                 // Method "<init>":(I[I[Lcom/google/zxing/qrcode/decoder/Version$ECBlocks;)V
     426: aastore
     427: dup
     428: iconst_3
     429: new           #25                 // class com/google/zxing/qrcode/decoder/Version
     432: dup
     433: iconst_4
     434: iconst_2
     435: newarray       int
     437: dup
     438: iconst_0
     439: bipush        6
     441: iastore
     442: dup
     443: iconst_1
     444: bipush        26
     446: iastore
     447: iconst_4
     448: anewarray     #26                 // class com/google/zxing/qrcode/decoder/Version$ECBlocks
     451: dup
     452: iconst_0
     453: new           #26                 // class com/google/zxing/qrcode/decoder/Version$ECBlocks
     456: dup
     457: bipush        20
     459: iconst_1
     460: anewarray     #27                 // class com/google/zxing/qrcode/decoder/Version$ECB
     463: dup
     464: iconst_0
     465: new           #27                 // class com/google/zxing/qrcode/decoder/Version$ECB
     468: dup
     469: iconst_1
     470: bipush        80
     472: invokespecial #28                 // Method com/google/zxing/qrcode/decoder/Version$ECB."<init>":(II)V
     475: aastore
     476: invokespecial #29                 // Method com/google/zxing/qrcode/decoder/Version$ECBlocks."<init>":(I[Lcom/google/zxing/qrcode/decoder/Version$ECB;)V
     479: aastore
     480: dup
     481: iconst_1
     482: new           #26                 // class com/google/zxing/qrcode/decoder/Version$ECBlocks
     485: dup
     486: bipush        18
     488: iconst_1
     489: anewarray     #27                 // class com/google/zxing/qrcode/decoder/Version$ECB
     492: dup
     493: iconst_0
     494: new           #27                 // class com/google/zxing/qrcode/decoder/Version$ECB
     497: dup
     498: iconst_2
     499: bipush        32
     501: invokespecial #28                 // Method com/google/zxing/qrcode/decoder/Version$ECB."<init>":(II)V
     504: aastore
     505: invokespecial #29                 // Method com/google/zxing/qrcode/decoder/Version$ECBlocks."<init>":(I[Lcom/google/zxing/qrcode/decoder/Version$ECB;)V
     508: aastore
     509: dup
     510: iconst_2
     511: new           #26                 // class com/google/zxing/qrcode/decoder/Version$ECBlocks
     514: dup
     515: bipush        26
     517: iconst_1
     518: anewarray     #27                 // class com/google/zxing/qrcode/decoder/Version$ECB
     521: dup
     522: iconst_0
     523: new           #27                 // class com/google/zxing/qrcode/decoder/Version$ECB
     526: dup
     527: iconst_2
     528: bipush        24
     530: invokespecial #28                 // Method com/google/zxing/qrcode/decoder/Version$ECB."<init>":(II)V
     533: aastore
     534: invokespecial #29                 // Method com/google/zxing/qrcode/decoder/Version$ECBlocks."<init>":(I[Lcom/google/zxing/qrcode/decoder/Version$ECB;)V
     537: aastore
     538: dup
     539: iconst_3
     540: new           #26                 // class com/google/zxing/qrcode/decoder/Version$ECBlocks
     543: dup
     544: bipush        16
     546: iconst_1
     547: anewarray     #27                 // class com/google/zxing/qrcode/decoder/Version$ECB
     550: dup
     551: iconst_0
     552: new           #27                 // class com/google/zxing/qrcode/decoder/Version$ECB
     555: dup
     556: iconst_4
     557: bipush        9
     559: invokespecial #28                 // Method com/google/zxing/qrcode/decoder/Version$ECB."<init>":(II)V
     562: aastore
     563: invokespecial #29                 // Method com/google/zxing/qrcode/decoder/Version$ECBlocks."<init>":(I[Lcom/google/zxing/qrcode/decoder/Version$ECB;)V
     566: aastore
     567: invokespecial #30                 // Method "<init>":(I[I[Lcom/google/zxing/qrcode/decoder/Version$ECBlocks;)V
     570: aastore
     571: dup
     572: iconst_4
     573: new           #25                 // class com/google/zxing/qrcode/decoder/Version
     576: dup
     577: iconst_5
     578: iconst_2
     579: newarray       int
     581: dup
     582: iconst_0
     583: bipush        6
     585: iastore
     586: dup
     587: iconst_1
     588: bipush        30
     590: iastore
     591: iconst_4
     592: anewarray     #26                 // class com/google/zxing/qrcode/decoder/Version$ECBlocks
     595: dup
     596: iconst_0
     597: new           #26                 // class com/google/zxing/qrcode/decoder/Version$ECBlocks
     600: dup
     601: bipush        26
     603: iconst_1
     604: anewarray     #27                 // class com/google/zxing/qrcode/decoder/Version$ECB
     607: dup
     608: iconst_0
     609: new           #27                 // class com/google/zxing/qrcode/decoder/Version$ECB
     612: dup
     613: iconst_1
     614: bipush        108
     616: invokespecial #28                 // Method com/google/zxing/qrcode/decoder/Version$ECB."<init>":(II)V
     619: aastore
     620: invokespecial #29                 // Method com/google/zxing/qrcode/decoder/Version$ECBlocks."<init>":(I[Lcom/google/zxing/qrcode/decoder/Version$ECB;)V
     623: aastore
     624: dup
     625: iconst_1
     626: new           #26                 // class com/google/zxing/qrcode/decoder/Version$ECBlocks
     629: dup
     630: bipush        24
     632: iconst_1
     633: anewarray     #27                 // class com/google/zxing/qrcode/decoder/Version$ECB
     636: dup
     637: iconst_0
     638: new           #27                 // class com/google/zxing/qrcode/decoder/Version$ECB
     641: dup
     642: iconst_2
     643: bipush        43
     645: invokespecial #28                 // Method com/google/zxing/qrcode/decoder/Version$ECB."<init>":(II)V
     648: aastore
     649: invokespecial #29                 // Method com/google/zxing/qrcode/decoder/Version$ECBlocks."<init>":(I[Lcom/google/zxing/qrcode/decoder/Version$ECB;)V
     652: aastore
     653: dup
     654: iconst_2
     655: new           #26                 // class com/google/zxing/qrcode/decoder/Version$ECBlocks
     658: dup
     659: bipush        18
     661: iconst_2
     662: anewarray     #27                 // class com/google/zxing/qrcode/decoder/Version$ECB
     665: dup
     666: iconst_0
     667: new           #27                 // class com/google/zxing/qrcode/decoder/Version$ECB
     670: dup
     671: iconst_2
     672: bipush        15
     674: invokespecial #28                 // Method com/google/zxing/qrcode/decoder/Version$ECB."<init>":(II)V
     677: aastore
     678: dup
     679: iconst_1
     680: new           #27                 // class com/google/zxing/qrcode/decoder/Version$ECB
     683: dup
     684: iconst_2
     685: bipush        16
     687: invokespecial #28                 // Method com/google/zxing/qrcode/decoder/Version$ECB."<init>":(II)V
     690: aastore
     691: invokespecial #29                 // Method com/google/zxing/qrcode/decoder/Version$ECBlocks."<init>":(I[Lcom/google/zxing/qrcode/decoder/Version$ECB;)V
     694: aastore
     695: dup
     696: iconst_3
     697: new           #26                 // class com/google/zxing/qrcode/decoder/Version$ECBlocks
     700: dup
     701: bipush        22
     703: iconst_2
     704: anewarray     #27                 // class com/google/zxing/qrcode/decoder/Version$ECB
     707: dup
     708: iconst_0
     709: new           #27                 // class com/google/zxing/qrcode/decoder/Version$ECB
     712: dup
     713: iconst_2
     714: bipush        11
     716: invokespecial #28                 // Method com/google/zxing/qrcode/decoder/Version$ECB."<init>":(II)V
     719: aastore
     720: dup
     721: iconst_1
     722: new           #27                 // class com/google/zxing/qrcode/decoder/Version$ECB
     725: dup
     726: iconst_2
     727: bipush        12
     729: invokespecial #28                 // Method com/google/zxing/qrcode/decoder/Version$ECB."<init>":(II)V
     732: aastore
     733: invokespecial #29                 // Method com/google/zxing/qrcode/decoder/Version$ECBlocks."<init>":(I[Lcom/google/zxing/qrcode/decoder/Version$ECB;)V
     736: aastore
     737: invokespecial #30                 // Method "<init>":(I[I[Lcom/google/zxing/qrcode/decoder/Version$ECBlocks;)V
     740: aastore
     741: dup
     742: iconst_5
     743: new           #25                 // class com/google/zxing/qrcode/decoder/Version
     746: dup
     747: bipush        6
     749: iconst_2
     750: newarray       int
     752: dup
     753: iconst_0
     754: bipush        6
     756: iastore
     757: dup
     758: iconst_1
     759: bipush        34
     761: iastore
     762: iconst_4
     763: anewarray     #26                 // class com/google/zxing/qrcode/decoder/Version$ECBlocks
     766: dup
     767: iconst_0
     768: new           #26                 // class com/google/zxing/qrcode/decoder/Version$ECBlocks
     771: dup
     772: bipush        18
     774: iconst_1
     775: anewarray     #27                 // class com/google/zxing/qrcode/decoder/Version$ECB
     778: dup
     779: iconst_0
     780: new           #27                 // class com/google/zxing/qrcode/decoder/Version$ECB
     783: dup
     784: iconst_2
     785: bipush        68
     787: invokespecial #28                 // Method com/google/zxing/qrcode/decoder/Version$ECB."<init>":(II)V
     790: aastore
     791: invokespecial #29                 // Method com/google/zxing/qrcode/decoder/Version$ECBlocks."<init>":(I[Lcom/google/zxing/qrcode/decoder/Version$ECB;)V
     794: aastore
     795: dup
     796: iconst_1
     797: new           #26                 // class com/google/zxing/qrcode/decoder/Version$ECBlocks
     800: dup
     801: bipush        16
     803: iconst_1
     804: anewarray     #27                 // class com/google/zxing/qrcode/decoder/Version$ECB
     807: dup
     808: iconst_0
     809: new           #27                 // class com/google/zxing/qrcode/decoder/Version$ECB
     812: dup
     813: iconst_4
     814: bipush        27
     816: invokespecial #28                 // Method com/google/zxing/qrcode/decoder/Version$ECB."<init>":(II)V
     819: aastore
     820: invokespecial #29                 // Method com/google/zxing/qrcode/decoder/Version$ECBlocks."<init>":(I[Lcom/google/zxing/qrcode/decoder/Version$ECB;)V
     823: aastore
     824: dup
     825: iconst_2
     826: new           #26                 // class com/google/zxing/qrcode/decoder/Version$ECBlocks
     829: dup
     830: bipush        24
     832: iconst_1
     833: anewarray     #27                 // class com/google/zxing/qrcode/decoder/Version$ECB
     836: dup
     837: iconst_0
     838: new           #27                 // class com/google/zxing/qrcode/decoder/Version$ECB
     841: dup
     842: iconst_4
     843: bipush        19
     845: invokespecial #28                 // Method com/google/zxing/qrcode/decoder/Version$ECB."<init>":(II)V
     848: aastore
     849: invokespecial #29                 // Method com/google/zxing/qrcode/decoder/Version$ECBlocks."<init>":(I[Lcom/google/zxing/qrcode/decoder/Version$ECB;)V
     852: aastore
     853: dup
     854: iconst_3
     855: new           #26                 // class com/google/zxing/qrcode/decoder/Version$ECBlocks
     858: dup
     859: bipush        28
     861: iconst_1
     862: anewarray     #27                 // class com/google/zxing/qrcode/decoder/Version$ECB
     865: dup
     866: iconst_0
     867: new           #27                 // class com/google/zxing/qrcode/decoder/Version$ECB
     870: dup
     871: iconst_4
     872: bipush        15
     874: invokespecial #28                 // Method com/google/zxing/qrcode/decoder/Version$ECB."<init>":(II)V
     877: aastore
     878: invokespecial #29                 // Method com/google/zxing/qrcode/decoder/Version$ECBlocks."<init>":(I[Lcom/google/zxing/qrcode/decoder/Version$ECB;)V
     881: aastore
     882: invokespecial #30                 // Method "<init>":(I[I[Lcom/google/zxing/qrcode/decoder/Version$ECBlocks;)V
     885: aastore
     886: dup
     887: bipush        6
     889: new           #25                 // class com/google/zxing/qrcode/decoder/Version
     892: dup
     893: bipush        7
     895: iconst_3
     896: newarray       int
     898: dup
     899: iconst_0
     900: bipush        6
     902: iastore
     903: dup
     904: iconst_1
     905: bipush        22
     907: iastore
     908: dup
     909: iconst_2
     910: bipush        38
     912: iastore
     913: iconst_4
     914: anewarray     #26                 // class com/google/zxing/qrcode/decoder/Version$ECBlocks
     917: dup
     918: iconst_0
     919: new           #26                 // class com/google/zxing/qrcode/decoder/Version$ECBlocks
     922: dup
     923: bipush        20
     925: iconst_1
     926: anewarray     #27                 // class com/google/zxing/qrcode/decoder/Version$ECB
     929: dup
     930: iconst_0
     931: new           #27                 // class com/google/zxing/qrcode/decoder/Version$ECB
     934: dup
     935: iconst_2
     936: bipush        78
     938: invokespecial #28                 // Method com/google/zxing/qrcode/decoder/Version$ECB."<init>":(II)V
     941: aastore
     942: invokespecial #29                 // Method com/google/zxing/qrcode/decoder/Version$ECBlocks."<init>":(I[Lcom/google/zxing/qrcode/decoder/Version$ECB;)V
     945: aastore
     946: dup
     947: iconst_1
     948: new           #26                 // class com/google/zxing/qrcode/decoder/Version$ECBlocks
     951: dup
     952: bipush        18
     954: iconst_1
     955: anewarray     #27                 // class com/google/zxing/qrcode/decoder/Version$ECB
     958: dup
     959: iconst_0
     960: new           #27                 // class com/google/zxing/qrcode/decoder/Version$ECB
     963: dup
     964: iconst_4
     965: bipush        31
     967: invokespecial #28                 // Method com/google/zxing/qrcode/decoder/Version$ECB."<init>":(II)V
     970: aastore
     971: invokespecial #29                 // Method com/google/zxing/qrcode/decoder/Version$ECBlocks."<init>":(I[Lcom/google/zxing/qrcode/decoder/Version$ECB;)V
     974: aastore
     975: dup
     976: iconst_2
     977: new           #26                 // class com/google/zxing/qrcode/decoder/Version$ECBlocks
     980: dup
     981: bipush        18
     983: iconst_2
     984: anewarray     #27                 // class com/google/zxing/qrcode/decoder/Version$ECB
     987: dup
     988: iconst_0
     989: new           #27                 // class com/google/zxing/qrcode/decoder/Version$ECB
     992: dup
     993: iconst_2
     994: bipush        14
     996: invokespecial #28                 // Method com/google/zxing/qrcode/decoder/Version$ECB."<init>":(II)V
     999: aastore
    1000: dup
    1001: iconst_1
    1002: new           #27                 // class com/google/zxing/qrcode/decoder/Version$ECB
    1005: dup
    1006: iconst_4
    1007: bipush        15
    1009: invokespecial #28                 // Method com/google/zxing/qrcode/decoder/Version$ECB."<init>":(II)V
    1012: aastore
    1013: invokespecial #29                 // Method com/google/zxing/qrcode/decoder/Version$ECBlocks."<init>":(I[Lcom/google/zxing/qrcode/decoder/Version$ECB;)V
    1016: aastore
    1017: dup
    1018: iconst_3
    1019: new           #26                 // class com/google/zxing/qrcode/decoder/Version$ECBlocks
    1022: dup
    1023: bipush        26
    1025: iconst_2
    1026: anewarray     #27                 // class com/google/zxing/qrcode/decoder/Version$ECB
    1029: dup
    1030: iconst_0
    1031: new           #27                 // class com/google/zxing/qrcode/decoder/Version$ECB
    1034: dup
    1035: iconst_4
    1036: bipush        13
    1038: invokespecial #28                 // Method com/google/zxing/qrcode/decoder/Version$ECB."<init>":(II)V
    1041: aastore
    1042: dup
    1043: iconst_1
    1044: new           #27                 // class com/google/zxing/qrcode/decoder/Version$ECB
    1047: dup
    1048: iconst_1
    1049: bipush        14
    1051: invokespecial #28                 // Method com/google/zxing/qrcode/decoder/Version$ECB."<init>":(II)V
    1054: aastore
    1055: invokespecial #29                 // Method com/google/zxing/qrcode/decoder/Version$ECBlocks."<init>":(I[Lcom/google/zxing/qrcode/decoder/Version$ECB;)V
    1058: aastore
    1059: invokespecial #30                 // Method "<init>":(I[I[Lcom/google/zxing/qrcode/decoder/Version$ECBlocks;)V
    1062: aastore
    1063: dup
    1064: bipush        7
    1066: new           #25                 // class com/google/zxing/qrcode/decoder/Version
    1069: dup
    1070: bipush        8
    1072: iconst_3
    1073: newarray       int
    1075: dup
    1076: iconst_0
    1077: bipush        6
    1079: iastore
    1080: dup
    1081: iconst_1
    1082: bipush        24
    1084: iastore
    1085: dup
    1086: iconst_2
    1087: bipush        42
    1089: iastore
    1090: iconst_4
    1091: anewarray     #26                 // class com/google/zxing/qrcode/decoder/Version$ECBlocks
    1094: dup
    1095: iconst_0
    1096: new           #26                 // class com/google/zxing/qrcode/decoder/Version$ECBlocks
    1099: dup
    1100: bipush        24
    1102: iconst_1
    1103: anewarray     #27                 // class com/google/zxing/qrcode/decoder/Version$ECB
    1106: dup
    1107: iconst_0
    1108: new           #27                 // class com/google/zxing/qrcode/decoder/Version$ECB
    1111: dup
    1112: iconst_2
    1113: bipush        97
    1115: invokespecial #28                 // Method com/google/zxing/qrcode/decoder/Version$ECB."<init>":(II)V
    1118: aastore
    1119: invokespecial #29                 // Method com/google/zxing/qrcode/decoder/Version$ECBlocks."<init>":(I[Lcom/google/zxing/qrcode/decoder/Version$ECB;)V
    1122: aastore
    1123: dup
    1124: iconst_1
    1125: new           #26                 // class com/google/zxing/qrcode/decoder/Version$ECBlocks
    1128: dup
    1129: bipush        22
    1131: iconst_2
    1132: anewarray     #27                 // class com/google/zxing/qrcode/decoder/Version$ECB
    1135: dup
    1136: iconst_0
    1137: new           #27                 // class com/google/zxing/qrcode/decoder/Version$ECB
    1140: dup
    1141: iconst_2
    1142: bipush        38
    1144: invokespecial #28                 // Method com/google/zxing/qrcode/decoder/Version$ECB."<init>":(II)V
    1147: aastore
    1148: dup
    1149: iconst_1
    1150: new           #27                 // class com/google/zxing/qrcode/decoder/Version$ECB
    1153: dup
    1154: iconst_2
    1155: bipush        39
    1157: invokespecial #28                 // Method com/google/zxing/qrcode/decoder/Version$ECB."<init>":(II)V
    1160: aastore
    1161: invokespecial #29                 // Method com/google/zxing/qrcode/decoder/Version$ECBlocks."<init>":(I[Lcom/google/zxing/qrcode/decoder/Version$ECB;)V
    1164: aastore
    1165: dup
    1166: iconst_2
    1167: new           #26                 // class com/google/zxing/qrcode/decoder/Version$ECBlocks
    1170: dup
    1171: bipush        22
    1173: iconst_2
    1174: anewarray     #27                 // class com/google/zxing/qrcode/decoder/Version$ECB
    1177: dup
    1178: iconst_0
    1179: new           #27                 // class com/google/zxing/qrcode/decoder/Version$ECB
    1182: dup
    1183: iconst_4
    1184: bipush        18
    1186: invokespecial #28                 // Method com/google/zxing/qrcode/decoder/Version$ECB."<init>":(II)V
    1189: aastore
    1190: dup
    1191: iconst_1
    1192: new           #27                 // class com/google/zxing/qrcode/decoder/Version$ECB
    1195: dup
    1196: iconst_2
    1197: bipush        19
    1199: invokespecial #28                 // Method com/google/zxing/qrcode/decoder/Version$ECB."<init>":(II)V
    1202: aastore
    1203: invokespecial #29                 // Method com/google/zxing/qrcode/decoder/Version$ECBlocks."<init>":(I[Lcom/google/zxing/qrcode/decoder/Version$ECB;)V
    1206: aastore
    1207: dup
    1208: iconst_3
    1209: new           #26                 // class com/google/zxing/qrcode/decoder/Version$ECBlocks
    1212: dup
    1213: bipush        26
    1215: iconst_2
    1216: anewarray     #27                 // class com/google/zxing/qrcode/decoder/Version$ECB
    1219: dup
    1220: iconst_0
    1221: new           #27                 // class com/google/zxing/qrcode/decoder/Version$ECB
    1224: dup
    1225: iconst_4
    1226: bipush        14
    1228: invokespecial #28                 // Method com/google/zxing/qrcode/decoder/Version$ECB."<init>":(II)V
    1231: aastore
    1232: dup
    1233: iconst_1
    1234: new           #27                 // class com/google/zxing/qrcode/decoder/Version$ECB
    1237: dup
    1238: iconst_2
    1239: bipush        15
    1241: invokespecial #28                 // Method com/google/zxing/qrcode/decoder/Version$ECB."<init>":(II)V
    1244: aastore
    1245: invokespecial #29                 // Method com/google/zxing/qrcode/decoder/Version$ECBlocks."<init>":(I[Lcom/google/zxing/qrcode/decoder/Version$ECB;)V
    1248: aastore
    1249: invokespecial #30                 // Method "<init>":(I[I[Lcom/google/zxing/qrcode/decoder/Version$ECBlocks;)V
    1252: aastore
    1253: dup
    1254: bipush        8
    1256: new           #25                 // class com/google/zxing/qrcode/decoder/Version
    1259: dup
    1260: bipush        9
    1262: iconst_3
    1263: newarray       int
    1265: dup
    1266: iconst_0
    1267: bipush        6
    1269: iastore
    1270: dup
    1271: iconst_1
    1272: bipush        26
    1274: iastore
    1275: dup
    1276: iconst_2
    1277: bipush        46
    1279: iastore
    1280: iconst_4
    1281: anewarray     #26                 // class com/google/zxing/qrcode/decoder/Version$ECBlocks
    1284: dup
    1285: iconst_0
    1286: new           #26                 // class com/google/zxing/qrcode/decoder/Version$ECBlocks
    1289: dup
    1290: bipush        30
    1292: iconst_1
    1293: anewarray     #27                 // class com/google/zxing/qrcode/decoder/Version$ECB
    1296: dup
    1297: iconst_0
    1298: new           #27                 // class com/google/zxing/qrcode/decoder/Version$ECB
    1301: dup
    1302: iconst_2
    1303: bipush        116
    1305: invokespecial #28                 // Method com/google/zxing/qrcode/decoder/Version$ECB."<init>":(II)V
    1308: aastore
    1309: invokespecial #29                 // Method com/google/zxing/qrcode/decoder/Version$ECBlocks."<init>":(I[Lcom/google/zxing/qrcode/decoder/Version$ECB;)V
    1312: aastore
    1313: dup
    1314: iconst_1
    1315: new           #26                 // class com/google/zxing/qrcode/decoder/Version$ECBlocks
    1318: dup
    1319: bipush        22
    1321: iconst_2
    1322: anewarray     #27                 // class com/google/zxing/qrcode/decoder/Version$ECB
    1325: dup
    1326: iconst_0
    1327: new           #27                 // class com/google/zxing/qrcode/decoder/Version$ECB
    1330: dup
    1331: iconst_3
    1332: bipush        36
    1334: invokespecial #28                 // Method com/google/zxing/qrcode/decoder/Version$ECB."<init>":(II)V
    1337: aastore
    1338: dup
    1339: iconst_1
    1340: new           #27                 // class com/google/zxing/qrcode/decoder/Version$ECB
    1343: dup
    1344: iconst_2
    1345: bipush        37
    1347: invokespecial #28                 // Method com/google/zxing/qrcode/decoder/Version$ECB."<init>":(II)V
    1350: aastore
    1351: invokespecial #29                 // Method com/google/zxing/qrcode/decoder/Version$ECBlocks."<init>":(I[Lcom/google/zxing/qrcode/decoder/Version$ECB;)V
    1354: aastore
    1355: dup
    1356: iconst_2
    1357: new           #26                 // class com/google/zxing/qrcode/decoder/Version$ECBlocks
    1360: dup
    1361: bipush        20
    1363: iconst_2
    1364: anewarray     #27                 // class com/google/zxing/qrcode/decoder/Version$ECB
    1367: dup
    1368: iconst_0
    1369: new           #27                 // class com/google/zxing/qrcode/decoder/Version$ECB
    1372: dup
    1373: iconst_4
    1374: bipush        16
    1376: invokespecial #28                 // Method com/google/zxing/qrcode/decoder/Version$ECB."<init>":(II)V
    1379: aastore
    1380: dup
    1381: iconst_1
    1382: new           #27                 // class com/google/zxing/qrcode/decoder/Version$ECB
    1385: dup
    1386: iconst_4
    1387: bipush        17
    1389: invokespecial #28                 // Method com/google/zxing/qrcode/decoder/Version$ECB."<init>":(II)V
    1392: aastore
    1393: invokespecial #29                 // Method com/google/zxing/qrcode/decoder/Version$ECBlocks."<init>":(I[Lcom/google/zxing/qrcode/decoder/Version$ECB;)V
    1396: aastore
    1397: dup
    1398: iconst_3
    1399: new           #26                 // class com/google/zxing/qrcode/decoder/Version$ECBlocks
    1402: dup
    1403: bipush        24
    1405: iconst_2
    1406: anewarray     #27                 // class com/google/zxing/qrcode/decoder/Version$ECB
    1409: dup
    1410: iconst_0
    1411: new           #27                 // class com/google/zxing/qrcode/decoder/Version$ECB
    1414: dup
    1415: iconst_4
    1416: bipush        12
    1418: invokespecial #28                 // Method com/google/zxing/qrcode/decoder/Version$ECB."<init>":(II)V
    1421: aastore
    1422: dup
    1423: iconst_1
    1424: new           #27                 // class com/google/zxing/qrcode/decoder/Version$ECB
    1427: dup
    1428: iconst_4
    1429: bipush        13
    1431: invokespecial #28                 // Method com/google/zxing/qrcode/decoder/Version$ECB."<init>":(II)V
    1434: aastore
    1435: invokespecial #29                 // Method com/google/zxing/qrcode/decoder/Version$ECBlocks."<init>":(I[Lcom/google/zxing/qrcode/decoder/Version$ECB;)V
    1438: aastore
    1439: invokespecial #30                 // Method "<init>":(I[I[Lcom/google/zxing/qrcode/decoder/Version$ECBlocks;)V
    1442: aastore
    1443: dup
    1444: bipush        9
    1446: new           #25                 // class com/google/zxing/qrcode/decoder/Version
    1449: dup
    1450: bipush        10
    1452: iconst_3
    1453: newarray       int
    1455: dup
    1456: iconst_0
    1457: bipush        6
    1459: iastore
    1460: dup
    1461: iconst_1
    1462: bipush        28
    1464: iastore
    1465: dup
    1466: iconst_2
    1467: bipush        50
    1469: iastore
    1470: iconst_4
    1471: anewarray     #26                 // class com/google/zxing/qrcode/decoder/Version$ECBlocks
    1474: dup
    1475: iconst_0
    1476: new           #26                 // class com/google/zxing/qrcode/decoder/Version$ECBlocks
    1479: dup
    1480: bipush        18
    1482: iconst_2
    1483: anewarray     #27                 // class com/google/zxing/qrcode/decoder/Version$ECB
    1486: dup
    1487: iconst_0
    1488: new           #27                 // class com/google/zxing/qrcode/decoder/Version$ECB
    1491: dup
    1492: iconst_2
    1493: bipush        68
    1495: invokespecial #28                 // Method com/google/zxing/qrcode/decoder/Version$ECB."<init>":(II)V
    1498: aastore
    1499: dup
    1500: iconst_1
    1501: new           #27                 // class com/google/zxing/qrcode/decoder/Version$ECB
    1504: dup
    1505: iconst_2
    1506: bipush        69
    1508: invokespecial #28                 // Method com/google/zxing/qrcode/decoder/Version$ECB."<init>":(II)V
    1511: aastore
    1512: invokespecial #29                 // Method com/google/zxing/qrcode/decoder/Version$ECBlocks."<init>":(I[Lcom/google/zxing/qrcode/decoder/Version$ECB;)V
    1515: aastore
    1516: dup
    1517: iconst_1
    1518: new           #26                 // class com/google/zxing/qrcode/decoder/Version$ECBlocks
    1521: dup
    1522: bipush        26
    1524: iconst_2
    1525: anewarray     #27                 // class com/google/zxing/qrcode/decoder/Version$ECB
    1528: dup
    1529: iconst_0
    1530: new           #27                 // class com/google/zxing/qrcode/decoder/Version$ECB
    1533: dup
    1534: iconst_4
    1535: bipush        43
    1537: invokespecial #28                 // Method com/google/zxing/qrcode/decoder/Version$ECB."<init>":(II)V
    1540: aastore
    1541: dup
    1542: iconst_1
    1543: new           #27                 // class com/google/zxing/qrcode/decoder/Version$ECB
    1546: dup
    1547: iconst_1
    1548: bipush        44
    1550: invokespecial #28                 // Method com/google/zxing/qrcode/decoder/Version$ECB."<init>":(II)V
    1553: aastore
    1554: invokespecial #29                 // Method com/google/zxing/qrcode/decoder/Version$ECBlocks."<init>":(I[Lcom/google/zxing/qrcode/decoder/Version$ECB;)V
    1557: aastore
    1558: dup
    1559: iconst_2
    1560: new           #26                 // class com/google/zxing/qrcode/decoder/Version$ECBlocks
    1563: dup
    1564: bipush        24
    1566: iconst_2
    1567: anewarray     #27                 // class com/google/zxing/qrcode/decoder/Version$ECB
    1570: dup
    1571: iconst_0
    1572: new           #27                 // class com/google/zxing/qrcode/decoder/Version$ECB
    1575: dup
    1576: bipush        6
    1578: bipush        19
    1580: invokespecial #28                 // Method com/google/zxing/qrcode/decoder/Version$ECB."<init>":(II)V
    1583: aastore
    1584: dup
    1585: iconst_1
    1586: new           #27                 // class com/google/zxing/qrcode/decoder/Version$ECB
    1589: dup
    1590: iconst_2
    1591: bipush        20
    1593: invokespecial #28                 // Method com/google/zxing/qrcode/decoder/Version$ECB."<init>":(II)V
    1596: aastore
    1597: invokespecial #29                 // Method com/google/zxing/qrcode/decoder/Version$ECBlocks."<init>":(I[Lcom/google/zxing/qrcode/decoder/Version$ECB;)V
    1600: aastore
    1601: dup
    1602: iconst_3
    1603: new           #26                 // class com/google/zxing/qrcode/decoder/Version$ECBlocks
    1606: dup
    1607: bipush        28
    1609: iconst_2
    1610: anewarray     #27                 // class com/google/zxing/qrcode/decoder/Version$ECB
    1613: dup
    1614: iconst_0
    1615: new           #27                 // class com/google/zxing/qrcode/decoder/Version$ECB
    1618: dup
    1619: bipush        6
    1621: bipush        15
    1623: invokespecial #28                 // Method com/google/zxing/qrcode/decoder/Version$ECB."<init>":(II)V
    1626: aastore
    1627: dup
    1628: iconst_1
    1629: new           #27                 // class com/google/zxing/qrcode/decoder/Version$ECB
    1632: dup
    1633: iconst_2
    1634: bipush        16
    1636: invokespecial #28                 // Method com/google/zxing/qrcode/decoder/Version$ECB."<init>":(II)V
    1639: aastore
    1640: invokespecial #29                 // Method com/google/zxing/qrcode/decoder/Version$ECBlocks."<init>":(I[Lcom/google/zxing/qrcode/decoder/Version$ECB;)V
    1643: aastore
    1644: invokespecial #30                 // Method "<init>":(I[I[Lcom/google/zxing/qrcode/decoder/Version$ECBlocks;)V
    1647: aastore
    1648: dup
    1649: bipush        10
    1651: new           #25                 // class com/google/zxing/qrcode/decoder/Version
    1654: dup
    1655: bipush        11
    1657: iconst_3
    1658: newarray       int
    1660: dup
    1661: iconst_0
    1662: bipush        6
    1664: iastore
    1665: dup
    1666: iconst_1
    1667: bipush        30
    1669: iastore
    1670: dup
    1671: iconst_2
    1672: bipush        54
    1674: iastore
    1675: iconst_4
    1676: anewarray     #26                 // class com/google/zxing/qrcode/decoder/Version$ECBlocks
    1679: dup
    1680: iconst_0
    1681: new           #26                 // class com/google/zxing/qrcode/decoder/Version$ECBlocks
    1684: dup
    1685: bipush        20
    1687: iconst_1
    1688: anewarray     #27                 // class com/google/zxing/qrcode/decoder/Version$ECB
    1691: dup
    1692: iconst_0
    1693: new           #27                 // class com/google/zxing/qrcode/decoder/Version$ECB
    1696: dup
    1697: iconst_4
    1698: bipush        81
    1700: invokespecial #28                 // Method com/google/zxing/qrcode/decoder/Version$ECB."<init>":(II)V
    1703: aastore
    1704: invokespecial #29                 // Method com/google/zxing/qrcode/decoder/Version$ECBlocks."<init>":(I[Lcom/google/zxing/qrcode/decoder/Version$ECB;)V
    1707: aastore
    1708: dup
    1709: iconst_1
    1710: new           #26                 // class com/google/zxing/qrcode/decoder/Version$ECBlocks
    1713: dup
    1714: bipush        30
    1716: iconst_2
    1717: anewarray     #27                 // class com/google/zxing/qrcode/decoder/Version$ECB
    1720: dup
    1721: iconst_0
    1722: new           #27                 // class com/google/zxing/qrcode/decoder/Version$ECB
    1725: dup
    1726: iconst_1
    1727: bipush        50
    1729: invokespecial #28                 // Method com/google/zxing/qrcode/decoder/Version$ECB."<init>":(II)V
    1732: aastore
    1733: dup
    1734: iconst_1
    1735: new           #27                 // class com/google/zxing/qrcode/decoder/Version$ECB
    1738: dup
    1739: iconst_4
    1740: bipush        51
    1742: invokespecial #28                 // Method com/google/zxing/qrcode/decoder/Version$ECB."<init>":(II)V
    1745: aastore
    1746: invokespecial #29                 // Method com/google/zxing/qrcode/decoder/Version$ECBlocks."<init>":(I[Lcom/google/zxing/qrcode/decoder/Version$ECB;)V
    1749: aastore
    1750: dup
    1751: iconst_2
    1752: new           #26                 // class com/google/zxing/qrcode/decoder/Version$ECBlocks
    1755: dup
    1756: bipush        28
    1758: iconst_2
    1759: anewarray     #27                 // class com/google/zxing/qrcode/decoder/Version$ECB
    1762: dup
    1763: iconst_0
    1764: new           #27                 // class com/google/zxing/qrcode/decoder/Version$ECB
    1767: dup
    1768: iconst_4
    1769: bipush        22
    1771: invokespecial #28                 // Method com/google/zxing/qrcode/decoder/Version$ECB."<init>":(II)V
    1774: aastore
    1775: dup
    1776: iconst_1
    1777: new           #27                 // class com/google/zxing/qrcode/decoder/Version$ECB
    1780: dup
    1781: iconst_4
    1782: bipush        23
    1784: invokespecial #28                 // Method com/google/zxing/qrcode/decoder/Version$ECB."<init>":(II)V
    1787: aastore
    1788: invokespecial #29                 // Method com/google/zxing/qrcode/decoder/Version$ECBlocks."<init>":(I[Lcom/google/zxing/qrcode/decoder/Version$ECB;)V
    1791: aastore
    1792: dup
    1793: iconst_3
    1794: new           #26                 // class com/google/zxing/qrcode/decoder/Version$ECBlocks
    1797: dup
    1798: bipush        24
    1800: iconst_2
    1801: anewarray     #27                 // class com/google/zxing/qrcode/decoder/Version$ECB
    1804: dup
    1805: iconst_0
    1806: new           #27                 // class com/google/zxing/qrcode/decoder/Version$ECB
    1809: dup
    1810: iconst_3
    1811: bipush        12
    1813: invokespecial #28                 // Method com/google/zxing/qrcode/decoder/Version$ECB."<init>":(II)V
    1816: aastore
    1817: dup
    1818: iconst_1
    1819: new           #27                 // class com/google/zxing/qrcode/decoder/Version$ECB
    1822: dup
    1823: bipush        8
    1825: bipush        13
    1827: invokespecial #28                 // Method com/google/zxing/qrcode/decoder/Version$ECB."<init>":(II)V
    1830: aastore
    1831: invokespecial #29                 // Method com/google/zxing/qrcode/decoder/Version$ECBlocks."<init>":(I[Lcom/google/zxing/qrcode/decoder/Version$ECB;)V
    1834: aastore
    1835: invokespecial #30                 // Method "<init>":(I[I[Lcom/google/zxing/qrcode/decoder/Version$ECBlocks;)V
    1838: aastore
    1839: dup
    1840: bipush        11
    1842: new           #25                 // class com/google/zxing/qrcode/decoder/Version
    1845: dup
    1846: bipush        12
    1848: iconst_3
    1849: newarray       int
    1851: dup
    1852: iconst_0
    1853: bipush        6
    1855: iastore
    1856: dup
    1857: iconst_1
    1858: bipush        32
    1860: iastore
    1861: dup
    1862: iconst_2
    1863: bipush        58
    1865: iastore
    1866: iconst_4
    1867: anewarray     #26                 // class com/google/zxing/qrcode/decoder/Version$ECBlocks
    1870: dup
    1871: iconst_0
    1872: new           #26                 // class com/google/zxing/qrcode/decoder/Version$ECBlocks
    1875: dup
    1876: bipush        24
    1878: iconst_2
    1879: anewarray     #27                 // class com/google/zxing/qrcode/decoder/Version$ECB
    1882: dup
    1883: iconst_0
    1884: new           #27                 // class com/google/zxing/qrcode/decoder/Version$ECB
    1887: dup
    1888: iconst_2
    1889: bipush        92
    1891: invokespecial #28                 // Method com/google/zxing/qrcode/decoder/Version$ECB."<init>":(II)V
    1894: aastore
    1895: dup
    1896: iconst_1
    1897: new           #27                 // class com/google/zxing/qrcode/decoder/Version$ECB
    1900: dup
    1901: iconst_2
    1902: bipush        93
    1904: invokespecial #28                 // Method com/google/zxing/qrcode/decoder/Version$ECB."<init>":(II)V
    1907: aastore
    1908: invokespecial #29                 // Method com/google/zxing/qrcode/decoder/Version$ECBlocks."<init>":(I[Lcom/google/zxing/qrcode/decoder/Version$ECB;)V
    1911: aastore
    1912: dup
    1913: iconst_1
    1914: new           #26                 // class com/google/zxing/qrcode/decoder/Version$ECBlocks
    1917: dup
    1918: bipush        22
    1920: iconst_2
    1921: anewarray     #27                 // class com/google/zxing/qrcode/decoder/Version$ECB
    1924: dup
    1925: iconst_0
    1926: new           #27                 // class com/google/zxing/qrcode/decoder/Version$ECB
    1929: dup
    1930: bipush        6
    1932: bipush        36
    1934: invokespecial #28                 // Method com/google/zxing/qrcode/decoder/Version$ECB."<init>":(II)V
    1937: aastore
    1938: dup
    1939: iconst_1
    1940: new           #27                 // class com/google/zxing/qrcode/decoder/Version$ECB
    1943: dup
    1944: iconst_2
    1945: bipush        37
    1947: invokespecial #28                 // Method com/google/zxing/qrcode/decoder/Version$ECB."<init>":(II)V
    1950: aastore
    1951: invokespecial #29                 // Method com/google/zxing/qrcode/decoder/Version$ECBlocks."<init>":(I[Lcom/google/zxing/qrcode/decoder/Version$ECB;)V
    1954: aastore
    1955: dup
    1956: iconst_2
    1957: new           #26                 // class com/google/zxing/qrcode/decoder/Version$ECBlocks
    1960: dup
    1961: bipush        26
    1963: iconst_2
    1964: anewarray     #27                 // class com/google/zxing/qrcode/decoder/Version$ECB
    1967: dup
    1968: iconst_0
    1969: new           #27                 // class com/google/zxing/qrcode/decoder/Version$ECB
    1972: dup
    1973: iconst_4
    1974: bipush        20
    1976: invokespecial #28                 // Method com/google/zxing/qrcode/decoder/Version$ECB."<init>":(II)V
    1979: aastore
    1980: dup
    1981: iconst_1
    1982: new           #27                 // class com/google/zxing/qrcode/decoder/Version$ECB
    1985: dup
    1986: bipush        6
    1988: bipush        21
    1990: invokespecial #28                 // Method com/google/zxing/qrcode/decoder/Version$ECB."<init>":(II)V
    1993: aastore
    1994: invokespecial #29                 // Method com/google/zxing/qrcode/decoder/Version$ECBlocks."<init>":(I[Lcom/google/zxing/qrcode/decoder/Version$ECB;)V
    1997: aastore
    1998: dup
    1999: iconst_3
    2000: new           #26                 // class com/google/zxing/qrcode/decoder/Version$ECBlocks
    2003: dup
    2004: bipush        28
    2006: iconst_2
    2007: anewarray     #27                 // class com/google/zxing/qrcode/decoder/Version$ECB
    2010: dup
    2011: iconst_0
    2012: new           #27                 // class com/google/zxing/qrcode/decoder/Version$ECB
    2015: dup
    2016: bipush        7
    2018: bipush        14
    2020: invokespecial #28                 // Method com/google/zxing/qrcode/decoder/Version$ECB."<init>":(II)V
    2023: aastore
    2024: dup
    2025: iconst_1
    2026: new           #27                 // class com/google/zxing/qrcode/decoder/Version$ECB
    2029: dup
    2030: iconst_4
    2031: bipush        15
    2033: invokespecial #28                 // Method com/google/zxing/qrcode/decoder/Version$ECB."<init>":(II)V
    2036: aastore
    2037: invokespecial #29                 // Method com/google/zxing/qrcode/decoder/Version$ECBlocks."<init>":(I[Lcom/google/zxing/qrcode/decoder/Version$ECB;)V
    2040: aastore
    2041: invokespecial #30                 // Method "<init>":(I[I[Lcom/google/zxing/qrcode/decoder/Version$ECBlocks;)V
    2044: aastore
    2045: dup
    2046: bipush        12
    2048: new           #25                 // class com/google/zxing/qrcode/decoder/Version
    2051: dup
    2052: bipush        13
    2054: iconst_3
    2055: newarray       int
    2057: dup
    2058: iconst_0
    2059: bipush        6
    2061: iastore
    2062: dup
    2063: iconst_1
    2064: bipush        34
    2066: iastore
    2067: dup
    2068: iconst_2
    2069: bipush        62
    2071: iastore
    2072: iconst_4
    2073: anewarray     #26                 // class com/google/zxing/qrcode/decoder/Version$ECBlocks
    2076: dup
    2077: iconst_0
    2078: new           #26                 // class com/google/zxing/qrcode/decoder/Version$ECBlocks
    2081: dup
    2082: bipush        26
    2084: iconst_1
    2085: anewarray     #27                 // class com/google/zxing/qrcode/decoder/Version$ECB
    2088: dup
    2089: iconst_0
    2090: new           #27                 // class com/google/zxing/qrcode/decoder/Version$ECB
    2093: dup
    2094: iconst_4
    2095: bipush        107
    2097: invokespecial #28                 // Method com/google/zxing/qrcode/decoder/Version$ECB."<init>":(II)V
    2100: aastore
    2101: invokespecial #29                 // Method com/google/zxing/qrcode/decoder/Version$ECBlocks."<init>":(I[Lcom/google/zxing/qrcode/decoder/Version$ECB;)V
    2104: aastore
    2105: dup
    2106: iconst_1
    2107: new           #26                 // class com/google/zxing/qrcode/decoder/Version$ECBlocks
    2110: dup
    2111: bipush        22
    2113: iconst_2
    2114: anewarray     #27                 // class com/google/zxing/qrcode/decoder/Version$ECB
    2117: dup
    2118: iconst_0
    2119: new           #27                 // class com/google/zxing/qrcode/decoder/Version$ECB
    2122: dup
    2123: bipush        8
    2125: bipush        37
    2127: invokespecial #28                 // Method com/google/zxing/qrcode/decoder/Version$ECB."<init>":(II)V
    2130: aastore
    2131: dup
    2132: iconst_1
    2133: new           #27                 // class com/google/zxing/qrcode/decoder/Version$ECB
    2136: dup
    2137: iconst_1
    2138: bipush        38
    2140: invokespecial #28                 // Method com/google/zxing/qrcode/decoder/Version$ECB."<init>":(II)V
    2143: aastore
    2144: invokespecial #29                 // Method com/google/zxing/qrcode/decoder/Version$ECBlocks."<init>":(I[Lcom/google/zxing/qrcode/decoder/Version$ECB;)V
    2147: aastore
    2148: dup
    2149: iconst_2
    2150: new           #26                 // class com/google/zxing/qrcode/decoder/Version$ECBlocks
    2153: dup
    2154: bipush        24
    2156: iconst_2
    2157: anewarray     #27                 // class com/google/zxing/qrcode/decoder/Version$ECB
    2160: dup
    2161: iconst_0
    2162: new           #27                 // class com/google/zxing/qrcode/decoder/Version$ECB
    2165: dup
    2166: bipush        8
    2168: bipush        20
    2170: invokespecial #28                 // Method com/google/zxing/qrcode/decoder/Version$ECB."<init>":(II)V
    2173: aastore
    2174: dup
    2175: iconst_1
    2176: new           #27                 // class com/google/zxing/qrcode/decoder/Version$ECB
    2179: dup
    2180: iconst_4
    2181: bipush        21
    2183: invokespecial #28                 // Method com/google/zxing/qrcode/decoder/Version$ECB."<init>":(II)V
    2186: aastore
    2187: invokespecial #29                 // Method com/google/zxing/qrcode/decoder/Version$ECBlocks."<init>":(I[Lcom/google/zxing/qrcode/decoder/Version$ECB;)V
    2190: aastore
    2191: dup
    2192: iconst_3
    2193: new           #26                 // class com/google/zxing/qrcode/decoder/Version$ECBlocks
    2196: dup
    2197: bipush        22
    2199: iconst_2
    2200: anewarray     #27                 // class com/google/zxing/qrcode/decoder/Version$ECB
    2203: dup
    2204: iconst_0
    2205: new           #27                 // class com/google/zxing/qrcode/decoder/Version$ECB
    2208: dup
    2209: bipush        12
    2211: bipush        11
    2213: invokespecial #28                 // Method com/google/zxing/qrcode/decoder/Version$ECB."<init>":(II)V
    2216: aastore
    2217: dup
    2218: iconst_1
    2219: new           #27                 // class com/google/zxing/qrcode/decoder/Version$ECB
    2222: dup
    2223: iconst_4
    2224: bipush        12
    2226: invokespecial #28                 // Method com/google/zxing/qrcode/decoder/Version$ECB."<init>":(II)V
    2229: aastore
    2230: invokespecial #29                 // Method com/google/zxing/qrcode/decoder/Version$ECBlocks."<init>":(I[Lcom/google/zxing/qrcode/decoder/Version$ECB;)V
    2233: aastore
    2234: invokespecial #30                 // Method "<init>":(I[I[Lcom/google/zxing/qrcode/decoder/Version$ECBlocks;)V
    2237: aastore
    2238: dup
    2239: bipush        13
    2241: new           #25                 // class com/google/zxing/qrcode/decoder/Version
    2244: dup
    2245: bipush        14
    2247: iconst_4
    2248: newarray       int
    2250: dup
    2251: iconst_0
    2252: bipush        6
    2254: iastore
    2255: dup
    2256: iconst_1
    2257: bipush        26
    2259: iastore
    2260: dup
    2261: iconst_2
    2262: bipush        46
    2264: iastore
    2265: dup
    2266: iconst_3
    2267: bipush        66
    2269: iastore
    2270: iconst_4
    2271: anewarray     #26                 // class com/google/zxing/qrcode/decoder/Version$ECBlocks
    2274: dup
    2275: iconst_0
    2276: new           #26                 // class com/google/zxing/qrcode/decoder/Version$ECBlocks
    2279: dup
    2280: bipush        30
    2282: iconst_2
    2283: anewarray     #27                 // class com/google/zxing/qrcode/decoder/Version$ECB
    2286: dup
    2287: iconst_0
    2288: new           #27                 // class com/google/zxing/qrcode/decoder/Version$ECB
    2291: dup
    2292: iconst_3
    2293: bipush        115
    2295: invokespecial #28                 // Method com/google/zxing/qrcode/decoder/Version$ECB."<init>":(II)V
    2298: aastore
    2299: dup
    2300: iconst_1
    2301: new           #27                 // class com/google/zxing/qrcode/decoder/Version$ECB
    2304: dup
    2305: iconst_1
    2306: bipush        116
    2308: invokespecial #28                 // Method com/google/zxing/qrcode/decoder/Version$ECB."<init>":(II)V
    2311: aastore
    2312: invokespecial #29                 // Method com/google/zxing/qrcode/decoder/Version$ECBlocks."<init>":(I[Lcom/google/zxing/qrcode/decoder/Version$ECB;)V
    2315: aastore
    2316: dup
    2317: iconst_1
    2318: new           #26                 // class com/google/zxing/qrcode/decoder/Version$ECBlocks
    2321: dup
    2322: bipush        24
    2324: iconst_2
    2325: anewarray     #27                 // class com/google/zxing/qrcode/decoder/Version$ECB
    2328: dup
    2329: iconst_0
    2330: new           #27                 // class com/google/zxing/qrcode/decoder/Version$ECB
    2333: dup
    2334: iconst_4
    2335: bipush        40
    2337: invokespecial #28                 // Method com/google/zxing/qrcode/decoder/Version$ECB."<init>":(II)V
    2340: aastore
    2341: dup
    2342: iconst_1
    2343: new           #27                 // class com/google/zxing/qrcode/decoder/Version$ECB
    2346: dup
    2347: iconst_5
    2348: bipush        41
    2350: invokespecial #28                 // Method com/google/zxing/qrcode/decoder/Version$ECB."<init>":(II)V
    2353: aastore
    2354: invokespecial #29                 // Method com/google/zxing/qrcode/decoder/Version$ECBlocks."<init>":(I[Lcom/google/zxing/qrcode/decoder/Version$ECB;)V
    2357: aastore
    2358: dup
    2359: iconst_2
    2360: new           #26                 // class com/google/zxing/qrcode/decoder/Version$ECBlocks
    2363: dup
    2364: bipush        20
    2366: iconst_2
    2367: anewarray     #27                 // class com/google/zxing/qrcode/decoder/Version$ECB
    2370: dup
    2371: iconst_0
    2372: new           #27                 // class com/google/zxing/qrcode/decoder/Version$ECB
    2375: dup
    2376: bipush        11
    2378: bipush        16
    2380: invokespecial #28                 // Method com/google/zxing/qrcode/decoder/Version$ECB."<init>":(II)V
    2383: aastore
    2384: dup
    2385: iconst_1
    2386: new           #27                 // class com/google/zxing/qrcode/decoder/Version$ECB
    2389: dup
    2390: iconst_5
    2391: bipush        17
    2393: invokespecial #28                 // Method com/google/zxing/qrcode/decoder/Version$ECB."<init>":(II)V
    2396: aastore
    2397: invokespecial #29                 // Method com/google/zxing/qrcode/decoder/Version$ECBlocks."<init>":(I[Lcom/google/zxing/qrcode/decoder/Version$ECB;)V
    2400: aastore
    2401: dup
    2402: iconst_3
    2403: new           #26                 // class com/google/zxing/qrcode/decoder/Version$ECBlocks
    2406: dup
    2407: bipush        24
    2409: iconst_2
    2410: anewarray     #27                 // class com/google/zxing/qrcode/decoder/Version$ECB
    2413: dup
    2414: iconst_0
    2415: new           #27                 // class com/google/zxing/qrcode/decoder/Version$ECB
    2418: dup
    2419: bipush        11
    2421: bipush        12
    2423: invokespecial #28                 // Method com/google/zxing/qrcode/decoder/Version$ECB."<init>":(II)V
    2426: aastore
    2427: dup
    2428: iconst_1
    2429: new           #27                 // class com/google/zxing/qrcode/decoder/Version$ECB
    2432: dup
    2433: iconst_5
    2434: bipush        13
    2436: invokespecial #28                 // Method com/google/zxing/qrcode/decoder/Version$ECB."<init>":(II)V
    2439: aastore
    2440: invokespecial #29                 // Method com/google/zxing/qrcode/decoder/Version$ECBlocks."<init>":(I[Lcom/google/zxing/qrcode/decoder/Version$ECB;)V
    2443: aastore
    2444: invokespecial #30                 // Method "<init>":(I[I[Lcom/google/zxing/qrcode/decoder/Version$ECBlocks;)V
    2447: aastore
    2448: dup
    2449: bipush        14
    2451: new           #25                 // class com/google/zxing/qrcode/decoder/Version
    2454: dup
    2455: bipush        15
    2457: iconst_4
    2458: newarray       int
    2460: dup
    2461: iconst_0
    2462: bipush        6
    2464: iastore
    2465: dup
    2466: iconst_1
    2467: bipush        26
    2469: iastore
    2470: dup
    2471: iconst_2
    2472: bipush        48
    2474: iastore
    2475: dup
    2476: iconst_3
    2477: bipush        70
    2479: iastore
    2480: iconst_4
    2481: anewarray     #26                 // class com/google/zxing/qrcode/decoder/Version$ECBlocks
    2484: dup
    2485: iconst_0
    2486: new           #26                 // class com/google/zxing/qrcode/decoder/Version$ECBlocks
    2489: dup
    2490: bipush        22
    2492: iconst_2
    2493: anewarray     #27                 // class com/google/zxing/qrcode/decoder/Version$ECB
    2496: dup
    2497: iconst_0
    2498: new           #27                 // class com/google/zxing/qrcode/decoder/Version$ECB
    2501: dup
    2502: iconst_5
    2503: bipush        87
    2505: invokespecial #28                 // Method com/google/zxing/qrcode/decoder/Version$ECB."<init>":(II)V
    2508: aastore
    2509: dup
    2510: iconst_1
    2511: new           #27                 // class com/google/zxing/qrcode/decoder/Version$ECB
    2514: dup
    2515: iconst_1
    2516: bipush        88
    2518: invokespecial #28                 // Method com/google/zxing/qrcode/decoder/Version$ECB."<init>":(II)V
    2521: aastore
    2522: invokespecial #29                 // Method com/google/zxing/qrcode/decoder/Version$ECBlocks."<init>":(I[Lcom/google/zxing/qrcode/decoder/Version$ECB;)V
    2525: aastore
    2526: dup
    2527: iconst_1
    2528: new           #26                 // class com/google/zxing/qrcode/decoder/Version$ECBlocks
    2531: dup
    2532: bipush        24
    2534: iconst_2
    2535: anewarray     #27                 // class com/google/zxing/qrcode/decoder/Version$ECB
    2538: dup
    2539: iconst_0
    2540: new           #27                 // class com/google/zxing/qrcode/decoder/Version$ECB
    2543: dup
    2544: iconst_5
    2545: bipush        41
    2547: invokespecial #28                 // Method com/google/zxing/qrcode/decoder/Version$ECB."<init>":(II)V
    2550: aastore
    2551: dup
    2552: iconst_1
    2553: new           #27                 // class com/google/zxing/qrcode/decoder/Version$ECB
    2556: dup
    2557: iconst_5
    2558: bipush        42
    2560: invokespecial #28                 // Method com/google/zxing/qrcode/decoder/Version$ECB."<init>":(II)V
    2563: aastore
    2564: invokespecial #29                 // Method com/google/zxing/qrcode/decoder/Version$ECBlocks."<init>":(I[Lcom/google/zxing/qrcode/decoder/Version$ECB;)V
    2567: aastore
    2568: dup
    2569: iconst_2
    2570: new           #26                 // class com/google/zxing/qrcode/decoder/Version$ECBlocks
    2573: dup
    2574: bipush        30
    2576: iconst_2
    2577: anewarray     #27                 // class com/google/zxing/qrcode/decoder/Version$ECB
    2580: dup
    2581: iconst_0
    2582: new           #27                 // class com/google/zxing/qrcode/decoder/Version$ECB
    2585: dup
    2586: iconst_5
    2587: bipush        24
    2589: invokespecial #28                 // Method com/google/zxing/qrcode/decoder/Version$ECB."<init>":(II)V
    2592: aastore
    2593: dup
    2594: iconst_1
    2595: new           #27                 // class com/google/zxing/qrcode/decoder/Version$ECB
    2598: dup
    2599: bipush        7
    2601: bipush        25
    2603: invokespecial #28                 // Method com/google/zxing/qrcode/decoder/Version$ECB."<init>":(II)V
    2606: aastore
    2607: invokespecial #29                 // Method com/google/zxing/qrcode/decoder/Version$ECBlocks."<init>":(I[Lcom/google/zxing/qrcode/decoder/Version$ECB;)V
    2610: aastore
    2611: dup
    2612: iconst_3
    2613: new           #26                 // class com/google/zxing/qrcode/decoder/Version$ECBlocks
    2616: dup
    2617: bipush        24
    2619: iconst_2
    2620: anewarray     #27                 // class com/google/zxing/qrcode/decoder/Version$ECB
    2623: dup
    2624: iconst_0
    2625: new           #27                 // class com/google/zxing/qrcode/decoder/Version$ECB
    2628: dup
    2629: bipush        11
    2631: bipush        12
    2633: invokespecial #28                 // Method com/google/zxing/qrcode/decoder/Version$ECB."<init>":(II)V
    2636: aastore
    2637: dup
    2638: iconst_1
    2639: new           #27                 // class com/google/zxing/qrcode/decoder/Version$ECB
    2642: dup
    2643: bipush        7
    2645: bipush        13
    2647: invokespecial #28                 // Method com/google/zxing/qrcode/decoder/Version$ECB."<init>":(II)V
    2650: aastore
    2651: invokespecial #29                 // Method com/google/zxing/qrcode/decoder/Version$ECBlocks."<init>":(I[Lcom/google/zxing/qrcode/decoder/Version$ECB;)V
    2654: aastore
    2655: invokespecial #30                 // Method "<init>":(I[I[Lcom/google/zxing/qrcode/decoder/Version$ECBlocks;)V
    2658: aastore
    2659: dup
    2660: bipush        15
    2662: new           #25                 // class com/google/zxing/qrcode/decoder/Version
    2665: dup
    2666: bipush        16
    2668: iconst_4
    2669: newarray       int
    2671: dup
    2672: iconst_0
    2673: bipush        6
    2675: iastore
    2676: dup
    2677: iconst_1
    2678: bipush        26
    2680: iastore
    2681: dup
    2682: iconst_2
    2683: bipush        50
    2685: iastore
    2686: dup
    2687: iconst_3
    2688: bipush        74
    2690: iastore
    2691: iconst_4
    2692: anewarray     #26                 // class com/google/zxing/qrcode/decoder/Version$ECBlocks
    2695: dup
    2696: iconst_0
    2697: new           #26                 // class com/google/zxing/qrcode/decoder/Version$ECBlocks
    2700: dup
    2701: bipush        24
    2703: iconst_2
    2704: anewarray     #27                 // class com/google/zxing/qrcode/decoder/Version$ECB
    2707: dup
    2708: iconst_0
    2709: new           #27                 // class com/google/zxing/qrcode/decoder/Version$ECB
    2712: dup
    2713: iconst_5
    2714: bipush        98
    2716: invokespecial #28                 // Method com/google/zxing/qrcode/decoder/Version$ECB."<init>":(II)V
    2719: aastore
    2720: dup
    2721: iconst_1
    2722: new           #27                 // class com/google/zxing/qrcode/decoder/Version$ECB
    2725: dup
    2726: iconst_1
    2727: bipush        99
    2729: invokespecial #28                 // Method com/google/zxing/qrcode/decoder/Version$ECB."<init>":(II)V
    2732: aastore
    2733: invokespecial #29                 // Method com/google/zxing/qrcode/decoder/Version$ECBlocks."<init>":(I[Lcom/google/zxing/qrcode/decoder/Version$ECB;)V
    2736: aastore
    2737: dup
    2738: iconst_1
    2739: new           #26                 // class com/google/zxing/qrcode/decoder/Version$ECBlocks
    2742: dup
    2743: bipush        28
    2745: iconst_2
    2746: anewarray     #27                 // class com/google/zxing/qrcode/decoder/Version$ECB
    2749: dup
    2750: iconst_0
    2751: new           #27                 // class com/google/zxing/qrcode/decoder/Version$ECB
    2754: dup
    2755: bipush        7
    2757: bipush        45
    2759: invokespecial #28                 // Method com/google/zxing/qrcode/decoder/Version$ECB."<init>":(II)V
    2762: aastore
    2763: dup
    2764: iconst_1
    2765: new           #27                 // class com/google/zxing/qrcode/decoder/Version$ECB
    2768: dup
    2769: iconst_3
    2770: bipush        46
    2772: invokespecial #28                 // Method com/google/zxing/qrcode/decoder/Version$ECB."<init>":(II)V
    2775: aastore
    2776: invokespecial #29                 // Method com/google/zxing/qrcode/decoder/Version$ECBlocks."<init>":(I[Lcom/google/zxing/qrcode/decoder/Version$ECB;)V
    2779: aastore
    2780: dup
    2781: iconst_2
    2782: new           #26                 // class com/google/zxing/qrcode/decoder/Version$ECBlocks
    2785: dup
    2786: bipush        24
    2788: iconst_2
    2789: anewarray     #27                 // class com/google/zxing/qrcode/decoder/Version$ECB
    2792: dup
    2793: iconst_0
    2794: new           #27                 // class com/google/zxing/qrcode/decoder/Version$ECB
    2797: dup
    2798: bipush        15
    2800: bipush        19
    2802: invokespecial #28                 // Method com/google/zxing/qrcode/decoder/Version$ECB."<init>":(II)V
    2805: aastore
    2806: dup
    2807: iconst_1
    2808: new           #27                 // class com/google/zxing/qrcode/decoder/Version$ECB
    2811: dup
    2812: iconst_2
    2813: bipush        20
    2815: invokespecial #28                 // Method com/google/zxing/qrcode/decoder/Version$ECB."<init>":(II)V
    2818: aastore
    2819: invokespecial #29                 // Method com/google/zxing/qrcode/decoder/Version$ECBlocks."<init>":(I[Lcom/google/zxing/qrcode/decoder/Version$ECB;)V
    2822: aastore
    2823: dup
    2824: iconst_3
    2825: new           #26                 // class com/google/zxing/qrcode/decoder/Version$ECBlocks
    2828: dup
    2829: bipush        30
    2831: iconst_2
    2832: anewarray     #27                 // class com/google/zxing/qrcode/decoder/Version$ECB
    2835: dup
    2836: iconst_0
    2837: new           #27                 // class com/google/zxing/qrcode/decoder/Version$ECB
    2840: dup
    2841: iconst_3
    2842: bipush        15
    2844: invokespecial #28                 // Method com/google/zxing/qrcode/decoder/Version$ECB."<init>":(II)V
    2847: aastore
    2848: dup
    2849: iconst_1
    2850: new           #27                 // class com/google/zxing/qrcode/decoder/Version$ECB
    2853: dup
    2854: bipush        13
    2856: bipush        16
    2858: invokespecial #28                 // Method com/google/zxing/qrcode/decoder/Version$ECB."<init>":(II)V
    2861: aastore
    2862: invokespecial #29                 // Method com/google/zxing/qrcode/decoder/Version$ECBlocks."<init>":(I[Lcom/google/zxing/qrcode/decoder/Version$ECB;)V
    2865: aastore
    2866: invokespecial #30                 // Method "<init>":(I[I[Lcom/google/zxing/qrcode/decoder/Version$ECBlocks;)V
    2869: aastore
    2870: dup
    2871: bipush        16
    2873: new           #25                 // class com/google/zxing/qrcode/decoder/Version
    2876: dup
    2877: bipush        17
    2879: iconst_4
    2880: newarray       int
    2882: dup
    2883: iconst_0
    2884: bipush        6
    2886: iastore
    2887: dup
    2888: iconst_1
    2889: bipush        30
    2891: iastore
    2892: dup
    2893: iconst_2
    2894: bipush        54
    2896: iastore
    2897: dup
    2898: iconst_3
    2899: bipush        78
    2901: iastore
    2902: iconst_4
    2903: anewarray     #26                 // class com/google/zxing/qrcode/decoder/Version$ECBlocks
    2906: dup
    2907: iconst_0
    2908: new           #26                 // class com/google/zxing/qrcode/decoder/Version$ECBlocks
    2911: dup
    2912: bipush        28
    2914: iconst_2
    2915: anewarray     #27                 // class com/google/zxing/qrcode/decoder/Version$ECB
    2918: dup
    2919: iconst_0
    2920: new           #27                 // class com/google/zxing/qrcode/decoder/Version$ECB
    2923: dup
    2924: iconst_1
    2925: bipush        107
    2927: invokespecial #28                 // Method com/google/zxing/qrcode/decoder/Version$ECB."<init>":(II)V
    2930: aastore
    2931: dup
    2932: iconst_1
    2933: new           #27                 // class com/google/zxing/qrcode/decoder/Version$ECB
    2936: dup
    2937: iconst_5
    2938: bipush        108
    2940: invokespecial #28                 // Method com/google/zxing/qrcode/decoder/Version$ECB."<init>":(II)V
    2943: aastore
    2944: invokespecial #29                 // Method com/google/zxing/qrcode/decoder/Version$ECBlocks."<init>":(I[Lcom/google/zxing/qrcode/decoder/Version$ECB;)V
    2947: aastore
    2948: dup
    2949: iconst_1
    2950: new           #26                 // class com/google/zxing/qrcode/decoder/Version$ECBlocks
    2953: dup
    2954: bipush        28
    2956: iconst_2
    2957: anewarray     #27                 // class com/google/zxing/qrcode/decoder/Version$ECB
    2960: dup
    2961: iconst_0
    2962: new           #27                 // class com/google/zxing/qrcode/decoder/Version$ECB
    2965: dup
    2966: bipush        10
    2968: bipush        46
    2970: invokespecial #28                 // Method com/google/zxing/qrcode/decoder/Version$ECB."<init>":(II)V
    2973: aastore
    2974: dup
    2975: iconst_1
    2976: new           #27                 // class com/google/zxing/qrcode/decoder/Version$ECB
    2979: dup
    2980: iconst_1
    2981: bipush        47
    2983: invokespecial #28                 // Method com/google/zxing/qrcode/decoder/Version$ECB."<init>":(II)V
    2986: aastore
    2987: invokespecial #29                 // Method com/google/zxing/qrcode/decoder/Version$ECBlocks."<init>":(I[Lcom/google/zxing/qrcode/decoder/Version$ECB;)V
    2990: aastore
    2991: dup
    2992: iconst_2
    2993: new           #26                 // class com/google/zxing/qrcode/decoder/Version$ECBlocks
    2996: dup
    2997: bipush        28
    2999: iconst_2
    3000: anewarray     #27                 // class com/google/zxing/qrcode/decoder/Version$ECB
    3003: dup
    3004: iconst_0
    3005: new           #27                 // class com/google/zxing/qrcode/decoder/Version$ECB
    3008: dup
    3009: iconst_1
    3010: bipush        22
    3012: invokespecial #28                 // Method com/google/zxing/qrcode/decoder/Version$ECB."<init>":(II)V
    3015: aastore
    3016: dup
    3017: iconst_1
    3018: new           #27                 // class com/google/zxing/qrcode/decoder/Version$ECB
    3021: dup
    3022: bipush        15
    3024: bipush        23
    3026: invokespecial #28                 // Method com/google/zxing/qrcode/decoder/Version$ECB."<init>":(II)V
    3029: aastore
    3030: invokespecial #29                 // Method com/google/zxing/qrcode/decoder/Version$ECBlocks."<init>":(I[Lcom/google/zxing/qrcode/decoder/Version$ECB;)V
    3033: aastore
    3034: dup
    3035: iconst_3
    3036: new           #26                 // class com/google/zxing/qrcode/decoder/Version$ECBlocks
    3039: dup
    3040: bipush        28
    3042: iconst_2
    3043: anewarray     #27                 // class com/google/zxing/qrcode/decoder/Version$ECB
    3046: dup
    3047: iconst_0
    3048: new           #27                 // class com/google/zxing/qrcode/decoder/Version$ECB
    3051: dup
    3052: iconst_2
    3053: bipush        14
    3055: invokespecial #28                 // Method com/google/zxing/qrcode/decoder/Version$ECB."<init>":(II)V
    3058: aastore
    3059: dup
    3060: iconst_1
    3061: new           #27                 // class com/google/zxing/qrcode/decoder/Version$ECB
    3064: dup
    3065: bipush        17
    3067: bipush        15
    3069: invokespecial #28                 // Method com/google/zxing/qrcode/decoder/Version$ECB."<init>":(II)V
    3072: aastore
    3073: invokespecial #29                 // Method com/google/zxing/qrcode/decoder/Version$ECBlocks."<init>":(I[Lcom/google/zxing/qrcode/decoder/Version$ECB;)V
    3076: aastore
    3077: invokespecial #30                 // Method "<init>":(I[I[Lcom/google/zxing/qrcode/decoder/Version$ECBlocks;)V
    3080: aastore
    3081: dup
    3082: bipush        17
    3084: new           #25                 // class com/google/zxing/qrcode/decoder/Version
    3087: dup
    3088: bipush        18
    3090: iconst_4
    3091: newarray       int
    3093: dup
    3094: iconst_0
    3095: bipush        6
    3097: iastore
    3098: dup
    3099: iconst_1
    3100: bipush        30
    3102: iastore
    3103: dup
    3104: iconst_2
    3105: bipush        56
    3107: iastore
    3108: dup
    3109: iconst_3
    3110: bipush        82
    3112: iastore
    3113: iconst_4
    3114: anewarray     #26                 // class com/google/zxing/qrcode/decoder/Version$ECBlocks
    3117: dup
    3118: iconst_0
    3119: new           #26                 // class com/google/zxing/qrcode/decoder/Version$ECBlocks
    3122: dup
    3123: bipush        30
    3125: iconst_2
    3126: anewarray     #27                 // class com/google/zxing/qrcode/decoder/Version$ECB
    3129: dup
    3130: iconst_0
    3131: new           #27                 // class com/google/zxing/qrcode/decoder/Version$ECB
    3134: dup
    3135: iconst_5
    3136: bipush        120
    3138: invokespecial #28                 // Method com/google/zxing/qrcode/decoder/Version$ECB."<init>":(II)V
    3141: aastore
    3142: dup
    3143: iconst_1
    3144: new           #27                 // class com/google/zxing/qrcode/decoder/Version$ECB
    3147: dup
    3148: iconst_1
    3149: bipush        121
    3151: invokespecial #28                 // Method com/google/zxing/qrcode/decoder/Version$ECB."<init>":(II)V
    3154: aastore
    3155: invokespecial #29                 // Method com/google/zxing/qrcode/decoder/Version$ECBlocks."<init>":(I[Lcom/google/zxing/qrcode/decoder/Version$ECB;)V
    3158: aastore
    3159: dup
    3160: iconst_1
    3161: new           #26                 // class com/google/zxing/qrcode/decoder/Version$ECBlocks
    3164: dup
    3165: bipush        26
    3167: iconst_2
    3168: anewarray     #27                 // class com/google/zxing/qrcode/decoder/Version$ECB
    3171: dup
    3172: iconst_0
    3173: new           #27                 // class com/google/zxing/qrcode/decoder/Version$ECB
    3176: dup
    3177: bipush        9
    3179: bipush        43
    3181: invokespecial #28                 // Method com/google/zxing/qrcode/decoder/Version$ECB."<init>":(II)V
    3184: aastore
    3185: dup
    3186: iconst_1
    3187: new           #27                 // class com/google/zxing/qrcode/decoder/Version$ECB
    3190: dup
    3191: iconst_4
    3192: bipush        44
    3194: invokespecial #28                 // Method com/google/zxing/qrcode/decoder/Version$ECB."<init>":(II)V
    3197: aastore
    3198: invokespecial #29                 // Method com/google/zxing/qrcode/decoder/Version$ECBlocks."<init>":(I[Lcom/google/zxing/qrcode/decoder/Version$ECB;)V
    3201: aastore
    3202: dup
    3203: iconst_2
    3204: new           #26                 // class com/google/zxing/qrcode/decoder/Version$ECBlocks
    3207: dup
    3208: bipush        28
    3210: iconst_2
    3211: anewarray     #27                 // class com/google/zxing/qrcode/decoder/Version$ECB
    3214: dup
    3215: iconst_0
    3216: new           #27                 // class com/google/zxing/qrcode/decoder/Version$ECB
    3219: dup
    3220: bipush        17
    3222: bipush        22
    3224: invokespecial #28                 // Method com/google/zxing/qrcode/decoder/Version$ECB."<init>":(II)V
    3227: aastore
    3228: dup
    3229: iconst_1
    3230: new           #27                 // class com/google/zxing/qrcode/decoder/Version$ECB
    3233: dup
    3234: iconst_1
    3235: bipush        23
    3237: invokespecial #28                 // Method com/google/zxing/qrcode/decoder/Version$ECB."<init>":(II)V
    3240: aastore
    3241: invokespecial #29                 // Method com/google/zxing/qrcode/decoder/Version$ECBlocks."<init>":(I[Lcom/google/zxing/qrcode/decoder/Version$ECB;)V
    3244: aastore
    3245: dup
    3246: iconst_3
    3247: new           #26                 // class com/google/zxing/qrcode/decoder/Version$ECBlocks
    3250: dup
    3251: bipush        28
    3253: iconst_2
    3254: anewarray     #27                 // class com/google/zxing/qrcode/decoder/Version$ECB
    3257: dup
    3258: iconst_0
    3259: new           #27                 // class com/google/zxing/qrcode/decoder/Version$ECB
    3262: dup
    3263: iconst_2
    3264: bipush        14
    3266: invokespecial #28                 // Method com/google/zxing/qrcode/decoder/Version$ECB."<init>":(II)V
    3269: aastore
    3270: dup
    3271: iconst_1
    3272: new           #27                 // class com/google/zxing/qrcode/decoder/Version$ECB
    3275: dup
    3276: bipush        19
    3278: bipush        15
    3280: invokespecial #28                 // Method com/google/zxing/qrcode/decoder/Version$ECB."<init>":(II)V
    3283: aastore
    3284: invokespecial #29                 // Method com/google/zxing/qrcode/decoder/Version$ECBlocks."<init>":(I[Lcom/google/zxing/qrcode/decoder/Version$ECB;)V
    3287: aastore
    3288: invokespecial #30                 // Method "<init>":(I[I[Lcom/google/zxing/qrcode/decoder/Version$ECBlocks;)V
    3291: aastore
    3292: dup
    3293: bipush        18
    3295: new           #25                 // class com/google/zxing/qrcode/decoder/Version
    3298: dup
    3299: bipush        19
    3301: iconst_4
    3302: newarray       int
    3304: dup
    3305: iconst_0
    3306: bipush        6
    3308: iastore
    3309: dup
    3310: iconst_1
    3311: bipush        30
    3313: iastore
    3314: dup
    3315: iconst_2
    3316: bipush        58
    3318: iastore
    3319: dup
    3320: iconst_3
    3321: bipush        86
    3323: iastore
    3324: iconst_4
    3325: anewarray     #26                 // class com/google/zxing/qrcode/decoder/Version$ECBlocks
    3328: dup
    3329: iconst_0
    3330: new           #26                 // class com/google/zxing/qrcode/decoder/Version$ECBlocks
    3333: dup
    3334: bipush        28
    3336: iconst_2
    3337: anewarray     #27                 // class com/google/zxing/qrcode/decoder/Version$ECB
    3340: dup
    3341: iconst_0
    3342: new           #27                 // class com/google/zxing/qrcode/decoder/Version$ECB
    3345: dup
    3346: iconst_3
    3347: bipush        113
    3349: invokespecial #28                 // Method com/google/zxing/qrcode/decoder/Version$ECB."<init>":(II)V
    3352: aastore
    3353: dup
    3354: iconst_1
    3355: new           #27                 // class com/google/zxing/qrcode/decoder/Version$ECB
    3358: dup
    3359: iconst_4
    3360: bipush        114
    3362: invokespecial #28                 // Method com/google/zxing/qrcode/decoder/Version$ECB."<init>":(II)V
    3365: aastore
    3366: invokespecial #29                 // Method com/google/zxing/qrcode/decoder/Version$ECBlocks."<init>":(I[Lcom/google/zxing/qrcode/decoder/Version$ECB;)V
    3369: aastore
    3370: dup
    3371: iconst_1
    3372: new           #26                 // class com/google/zxing/qrcode/decoder/Version$ECBlocks
    3375: dup
    3376: bipush        26
    3378: iconst_2
    3379: anewarray     #27                 // class com/google/zxing/qrcode/decoder/Version$ECB
    3382: dup
    3383: iconst_0
    3384: new           #27                 // class com/google/zxing/qrcode/decoder/Version$ECB
    3387: dup
    3388: iconst_3
    3389: bipush        44
    3391: invokespecial #28                 // Method com/google/zxing/qrcode/decoder/Version$ECB."<init>":(II)V
    3394: aastore
    3395: dup
    3396: iconst_1
    3397: new           #27                 // class com/google/zxing/qrcode/decoder/Version$ECB
    3400: dup
    3401: bipush        11
    3403: bipush        45
    3405: invokespecial #28                 // Method com/google/zxing/qrcode/decoder/Version$ECB."<init>":(II)V
    3408: aastore
    3409: invokespecial #29                 // Method com/google/zxing/qrcode/decoder/Version$ECBlocks."<init>":(I[Lcom/google/zxing/qrcode/decoder/Version$ECB;)V
    3412: aastore
    3413: dup
    3414: iconst_2
    3415: new           #26                 // class com/google/zxing/qrcode/decoder/Version$ECBlocks
    3418: dup
    3419: bipush        26
    3421: iconst_2
    3422: anewarray     #27                 // class com/google/zxing/qrcode/decoder/Version$ECB
    3425: dup
    3426: iconst_0
    3427: new           #27                 // class com/google/zxing/qrcode/decoder/Version$ECB
    3430: dup
    3431: bipush        17
    3433: bipush        21
    3435: invokespecial #28                 // Method com/google/zxing/qrcode/decoder/Version$ECB."<init>":(II)V
    3438: aastore
    3439: dup
    3440: iconst_1
    3441: new           #27                 // class com/google/zxing/qrcode/decoder/Version$ECB
    3444: dup
    3445: iconst_4
    3446: bipush        22
    3448: invokespecial #28                 // Method com/google/zxing/qrcode/decoder/Version$ECB."<init>":(II)V
    3451: aastore
    3452: invokespecial #29                 // Method com/google/zxing/qrcode/decoder/Version$ECBlocks."<init>":(I[Lcom/google/zxing/qrcode/decoder/Version$ECB;)V
    3455: aastore
    3456: dup
    3457: iconst_3
    3458: new           #26                 // class com/google/zxing/qrcode/decoder/Version$ECBlocks
    3461: dup
    3462: bipush        26
    3464: iconst_2
    3465: anewarray     #27                 // class com/google/zxing/qrcode/decoder/Version$ECB
    3468: dup
    3469: iconst_0
    3470: new           #27                 // class com/google/zxing/qrcode/decoder/Version$ECB
    3473: dup
    3474: bipush        9
    3476: bipush        13
    3478: invokespecial #28                 // Method com/google/zxing/qrcode/decoder/Version$ECB."<init>":(II)V
    3481: aastore
    3482: dup
    3483: iconst_1
    3484: new           #27                 // class com/google/zxing/qrcode/decoder/Version$ECB
    3487: dup
    3488: bipush        16
    3490: bipush        14
    3492: invokespecial #28                 // Method com/google/zxing/qrcode/decoder/Version$ECB."<init>":(II)V
    3495: aastore
    3496: invokespecial #29                 // Method com/google/zxing/qrcode/decoder/Version$ECBlocks."<init>":(I[Lcom/google/zxing/qrcode/decoder/Version$ECB;)V
    3499: aastore
    3500: invokespecial #30                 // Method "<init>":(I[I[Lcom/google/zxing/qrcode/decoder/Version$ECBlocks;)V
    3503: aastore
    3504: dup
    3505: bipush        19
    3507: new           #25                 // class com/google/zxing/qrcode/decoder/Version
    3510: dup
    3511: bipush        20
    3513: iconst_4
    3514: newarray       int
    3516: dup
    3517: iconst_0
    3518: bipush        6
    3520: iastore
    3521: dup
    3522: iconst_1
    3523: bipush        34
    3525: iastore
    3526: dup
    3527: iconst_2
    3528: bipush        62
    3530: iastore
    3531: dup
    3532: iconst_3
    3533: bipush        90
    3535: iastore
    3536: iconst_4
    3537: anewarray     #26                 // class com/google/zxing/qrcode/decoder/Version$ECBlocks
    3540: dup
    3541: iconst_0
    3542: new           #26                 // class com/google/zxing/qrcode/decoder/Version$ECBlocks
    3545: dup
    3546: bipush        28
    3548: iconst_2
    3549: anewarray     #27                 // class com/google/zxing/qrcode/decoder/Version$ECB
    3552: dup
    3553: iconst_0
    3554: new           #27                 // class com/google/zxing/qrcode/decoder/Version$ECB
    3557: dup
    3558: iconst_3
    3559: bipush        107
    3561: invokespecial #28                 // Method com/google/zxing/qrcode/decoder/Version$ECB."<init>":(II)V
    3564: aastore
    3565: dup
    3566: iconst_1
    3567: new           #27                 // class com/google/zxing/qrcode/decoder/Version$ECB
    3570: dup
    3571: iconst_5
    3572: bipush        108
    3574: invokespecial #28                 // Method com/google/zxing/qrcode/decoder/Version$ECB."<init>":(II)V
    3577: aastore
    3578: invokespecial #29                 // Method com/google/zxing/qrcode/decoder/Version$ECBlocks."<init>":(I[Lcom/google/zxing/qrcode/decoder/Version$ECB;)V
    3581: aastore
    3582: dup
    3583: iconst_1
    3584: new           #26                 // class com/google/zxing/qrcode/decoder/Version$ECBlocks
    3587: dup
    3588: bipush        26
    3590: iconst_2
    3591: anewarray     #27                 // class com/google/zxing/qrcode/decoder/Version$ECB
    3594: dup
    3595: iconst_0
    3596: new           #27                 // class com/google/zxing/qrcode/decoder/Version$ECB
    3599: dup
    3600: iconst_3
    3601: bipush        41
    3603: invokespecial #28                 // Method com/google/zxing/qrcode/decoder/Version$ECB."<init>":(II)V
    3606: aastore
    3607: dup
    3608: iconst_1
    3609: new           #27                 // class com/google/zxing/qrcode/decoder/Version$ECB
    3612: dup
    3613: bipush        13
    3615: bipush        42
    3617: invokespecial #28                 // Method com/google/zxing/qrcode/decoder/Version$ECB."<init>":(II)V
    3620: aastore
    3621: invokespecial #29                 // Method com/google/zxing/qrcode/decoder/Version$ECBlocks."<init>":(I[Lcom/google/zxing/qrcode/decoder/Version$ECB;)V
    3624: aastore
    3625: dup
    3626: iconst_2
    3627: new           #26                 // class com/google/zxing/qrcode/decoder/Version$ECBlocks
    3630: dup
    3631: bipush        30
    3633: iconst_2
    3634: anewarray     #27                 // class com/google/zxing/qrcode/decoder/Version$ECB
    3637: dup
    3638: iconst_0
    3639: new           #27                 // class com/google/zxing/qrcode/decoder/Version$ECB
    3642: dup
    3643: bipush        15
    3645: bipush        24
    3647: invokespecial #28                 // Method com/google/zxing/qrcode/decoder/Version$ECB."<init>":(II)V
    3650: aastore
    3651: dup
    3652: iconst_1
    3653: new           #27                 // class com/google/zxing/qrcode/decoder/Version$ECB
    3656: dup
    3657: iconst_5
    3658: bipush        25
    3660: invokespecial #28                 // Method com/google/zxing/qrcode/decoder/Version$ECB."<init>":(II)V
    3663: aastore
    3664: invokespecial #29                 // Method com/google/zxing/qrcode/decoder/Version$ECBlocks."<init>":(I[Lcom/google/zxing/qrcode/decoder/Version$ECB;)V
    3667: aastore
    3668: dup
    3669: iconst_3
    3670: new           #26                 // class com/google/zxing/qrcode/decoder/Version$ECBlocks
    3673: dup
    3674: bipush        28
    3676: iconst_2
    3677: anewarray     #27                 // class com/google/zxing/qrcode/decoder/Version$ECB
    3680: dup
    3681: iconst_0
    3682: new           #27                 // class com/google/zxing/qrcode/decoder/Version$ECB
    3685: dup
    3686: bipush        15
    3688: bipush        15
    3690: invokespecial #28                 // Method com/google/zxing/qrcode/decoder/Version$ECB."<init>":(II)V
    3693: aastore
    3694: dup
    3695: iconst_1
    3696: new           #27                 // class com/google/zxing/qrcode/decoder/Version$ECB
    3699: dup
    3700: bipush        10
    3702: bipush        16
    3704: invokespecial #28                 // Method com/google/zxing/qrcode/decoder/Version$ECB."<init>":(II)V
    3707: aastore
    3708: invokespecial #29                 // Method com/google/zxing/qrcode/decoder/Version$ECBlocks."<init>":(I[Lcom/google/zxing/qrcode/decoder/Version$ECB;)V
    3711: aastore
    3712: invokespecial #30                 // Method "<init>":(I[I[Lcom/google/zxing/qrcode/decoder/Version$ECBlocks;)V
    3715: aastore
    3716: dup
    3717: bipush        20
    3719: new           #25                 // class com/google/zxing/qrcode/decoder/Version
    3722: dup
    3723: bipush        21
    3725: iconst_5
    3726: newarray       int
    3728: dup
    3729: iconst_0
    3730: bipush        6
    3732: iastore
    3733: dup
    3734: iconst_1
    3735: bipush        28
    3737: iastore
    3738: dup
    3739: iconst_2
    3740: bipush        50
    3742: iastore
    3743: dup
    3744: iconst_3
    3745: bipush        72
    3747: iastore
    3748: dup
    3749: iconst_4
    3750: bipush        94
    3752: iastore
    3753: iconst_4
    3754: anewarray     #26                 // class com/google/zxing/qrcode/decoder/Version$ECBlocks
    3757: dup
    3758: iconst_0
    3759: new           #26                 // class com/google/zxing/qrcode/decoder/Version$ECBlocks
    3762: dup
    3763: bipush        28
    3765: iconst_2
    3766: anewarray     #27                 // class com/google/zxing/qrcode/decoder/Version$ECB
    3769: dup
    3770: iconst_0
    3771: new           #27                 // class com/google/zxing/qrcode/decoder/Version$ECB
    3774: dup
    3775: iconst_4
    3776: bipush        116
    3778: invokespecial #28                 // Method com/google/zxing/qrcode/decoder/Version$ECB."<init>":(II)V
    3781: aastore
    3782: dup
    3783: iconst_1
    3784: new           #27                 // class com/google/zxing/qrcode/decoder/Version$ECB
    3787: dup
    3788: iconst_4
    3789: bipush        117
    3791: invokespecial #28                 // Method com/google/zxing/qrcode/decoder/Version$ECB."<init>":(II)V
    3794: aastore
    3795: invokespecial #29                 // Method com/google/zxing/qrcode/decoder/Version$ECBlocks."<init>":(I[Lcom/google/zxing/qrcode/decoder/Version$ECB;)V
    3798: aastore
    3799: dup
    3800: iconst_1
    3801: new           #26                 // class com/google/zxing/qrcode/decoder/Version$ECBlocks
    3804: dup
    3805: bipush        26
    3807: iconst_1
    3808: anewarray     #27                 // class com/google/zxing/qrcode/decoder/Version$ECB
    3811: dup
    3812: iconst_0
    3813: new           #27                 // class com/google/zxing/qrcode/decoder/Version$ECB
    3816: dup
    3817: bipush        17
    3819: bipush        42
    3821: invokespecial #28                 // Method com/google/zxing/qrcode/decoder/Version$ECB."<init>":(II)V
    3824: aastore
    3825: invokespecial #29                 // Method com/google/zxing/qrcode/decoder/Version$ECBlocks."<init>":(I[Lcom/google/zxing/qrcode/decoder/Version$ECB;)V
    3828: aastore
    3829: dup
    3830: iconst_2
    3831: new           #26                 // class com/google/zxing/qrcode/decoder/Version$ECBlocks
    3834: dup
    3835: bipush        28
    3837: iconst_2
    3838: anewarray     #27                 // class com/google/zxing/qrcode/decoder/Version$ECB
    3841: dup
    3842: iconst_0
    3843: new           #27                 // class com/google/zxing/qrcode/decoder/Version$ECB
    3846: dup
    3847: bipush        17
    3849: bipush        22
    3851: invokespecial #28                 // Method com/google/zxing/qrcode/decoder/Version$ECB."<init>":(II)V
    3854: aastore
    3855: dup
    3856: iconst_1
    3857: new           #27                 // class com/google/zxing/qrcode/decoder/Version$ECB
    3860: dup
    3861: bipush        6
    3863: bipush        23
    3865: invokespecial #28                 // Method com/google/zxing/qrcode/decoder/Version$ECB."<init>":(II)V
    3868: aastore
    3869: invokespecial #29                 // Method com/google/zxing/qrcode/decoder/Version$ECBlocks."<init>":(I[Lcom/google/zxing/qrcode/decoder/Version$ECB;)V
    3872: aastore
    3873: dup
    3874: iconst_3
    3875: new           #26                 // class com/google/zxing/qrcode/decoder/Version$ECBlocks
    3878: dup
    3879: bipush        30
    3881: iconst_2
    3882: anewarray     #27                 // class com/google/zxing/qrcode/decoder/Version$ECB
    3885: dup
    3886: iconst_0
    3887: new           #27                 // class com/google/zxing/qrcode/decoder/Version$ECB
    3890: dup
    3891: bipush        19
    3893: bipush        16
    3895: invokespecial #28                 // Method com/google/zxing/qrcode/decoder/Version$ECB."<init>":(II)V
    3898: aastore
    3899: dup
    3900: iconst_1
    3901: new           #27                 // class com/google/zxing/qrcode/decoder/Version$ECB
    3904: dup
    3905: bipush        6
    3907: bipush        17
    3909: invokespecial #28                 // Method com/google/zxing/qrcode/decoder/Version$ECB."<init>":(II)V
    3912: aastore
    3913: invokespecial #29                 // Method com/google/zxing/qrcode/decoder/Version$ECBlocks."<init>":(I[Lcom/google/zxing/qrcode/decoder/Version$ECB;)V
    3916: aastore
    3917: invokespecial #30                 // Method "<init>":(I[I[Lcom/google/zxing/qrcode/decoder/Version$ECBlocks;)V
    3920: aastore
    3921: dup
    3922: bipush        21
    3924: new           #25                 // class com/google/zxing/qrcode/decoder/Version
    3927: dup
    3928: bipush        22
    3930: iconst_5
    3931: newarray       int
    3933: dup
    3934: iconst_0
    3935: bipush        6
    3937: iastore
    3938: dup
    3939: iconst_1
    3940: bipush        26
    3942: iastore
    3943: dup
    3944: iconst_2
    3945: bipush        50
    3947: iastore
    3948: dup
    3949: iconst_3
    3950: bipush        74
    3952: iastore
    3953: dup
    3954: iconst_4
    3955: bipush        98
    3957: iastore
    3958: iconst_4
    3959: anewarray     #26                 // class com/google/zxing/qrcode/decoder/Version$ECBlocks
    3962: dup
    3963: iconst_0
    3964: new           #26                 // class com/google/zxing/qrcode/decoder/Version$ECBlocks
    3967: dup
    3968: bipush        28
    3970: iconst_2
    3971: anewarray     #27                 // class com/google/zxing/qrcode/decoder/Version$ECB
    3974: dup
    3975: iconst_0
    3976: new           #27                 // class com/google/zxing/qrcode/decoder/Version$ECB
    3979: dup
    3980: iconst_2
    3981: bipush        111
    3983: invokespecial #28                 // Method com/google/zxing/qrcode/decoder/Version$ECB."<init>":(II)V
    3986: aastore
    3987: dup
    3988: iconst_1
    3989: new           #27                 // class com/google/zxing/qrcode/decoder/Version$ECB
    3992: dup
    3993: bipush        7
    3995: bipush        112
    3997: invokespecial #28                 // Method com/google/zxing/qrcode/decoder/Version$ECB."<init>":(II)V
    4000: aastore
    4001: invokespecial #29                 // Method com/google/zxing/qrcode/decoder/Version$ECBlocks."<init>":(I[Lcom/google/zxing/qrcode/decoder/Version$ECB;)V
    4004: aastore
    4005: dup
    4006: iconst_1
    4007: new           #26                 // class com/google/zxing/qrcode/decoder/Version$ECBlocks
    4010: dup
    4011: bipush        28
    4013: iconst_1
    4014: anewarray     #27                 // class com/google/zxing/qrcode/decoder/Version$ECB
    4017: dup
    4018: iconst_0
    4019: new           #27                 // class com/google/zxing/qrcode/decoder/Version$ECB
    4022: dup
    4023: bipush        17
    4025: bipush        46
    4027: invokespecial #28                 // Method com/google/zxing/qrcode/decoder/Version$ECB."<init>":(II)V
    4030: aastore
    4031: invokespecial #29                 // Method com/google/zxing/qrcode/decoder/Version$ECBlocks."<init>":(I[Lcom/google/zxing/qrcode/decoder/Version$ECB;)V
    4034: aastore
    4035: dup
    4036: iconst_2
    4037: new           #26                 // class com/google/zxing/qrcode/decoder/Version$ECBlocks
    4040: dup
    4041: bipush        30
    4043: iconst_2
    4044: anewarray     #27                 // class com/google/zxing/qrcode/decoder/Version$ECB
    4047: dup
    4048: iconst_0
    4049: new           #27                 // class com/google/zxing/qrcode/decoder/Version$ECB
    4052: dup
    4053: bipush        7
    4055: bipush        24
    4057: invokespecial #28                 // Method com/google/zxing/qrcode/decoder/Version$ECB."<init>":(II)V
    4060: aastore
    4061: dup
    4062: iconst_1
    4063: new           #27                 // class com/google/zxing/qrcode/decoder/Version$ECB
    4066: dup
    4067: bipush        16
    4069: bipush        25
    4071: invokespecial #28                 // Method com/google/zxing/qrcode/decoder/Version$ECB."<init>":(II)V
    4074: aastore
    4075: invokespecial #29                 // Method com/google/zxing/qrcode/decoder/Version$ECBlocks."<init>":(I[Lcom/google/zxing/qrcode/decoder/Version$ECB;)V
    4078: aastore
    4079: dup
    4080: iconst_3
    4081: new           #26                 // class com/google/zxing/qrcode/decoder/Version$ECBlocks
    4084: dup
    4085: bipush        24
    4087: iconst_1
    4088: anewarray     #27                 // class com/google/zxing/qrcode/decoder/Version$ECB
    4091: dup
    4092: iconst_0
    4093: new           #27                 // class com/google/zxing/qrcode/decoder/Version$ECB
    4096: dup
    4097: bipush        34
    4099: bipush        13
    4101: invokespecial #28                 // Method com/google/zxing/qrcode/decoder/Version$ECB."<init>":(II)V
    4104: aastore
    4105: invokespecial #29                 // Method com/google/zxing/qrcode/decoder/Version$ECBlocks."<init>":(I[Lcom/google/zxing/qrcode/decoder/Version$ECB;)V
    4108: aastore
    4109: invokespecial #30                 // Method "<init>":(I[I[Lcom/google/zxing/qrcode/decoder/Version$ECBlocks;)V
    4112: aastore
    4113: dup
    4114: bipush        22
    4116: new           #25                 // class com/google/zxing/qrcode/decoder/Version
    4119: dup
    4120: bipush        23
    4122: iconst_5
    4123: newarray       int
    4125: dup
    4126: iconst_0
    4127: bipush        6
    4129: iastore
    4130: dup
    4131: iconst_1
    4132: bipush        30
    4134: iastore
    4135: dup
    4136: iconst_2
    4137: bipush        54
    4139: iastore
    4140: dup
    4141: iconst_3
    4142: bipush        78
    4144: iastore
    4145: dup
    4146: iconst_4
    4147: bipush        102
    4149: iastore
    4150: iconst_4
    4151: anewarray     #26                 // class com/google/zxing/qrcode/decoder/Version$ECBlocks
    4154: dup
    4155: iconst_0
    4156: new           #26                 // class com/google/zxing/qrcode/decoder/Version$ECBlocks
    4159: dup
    4160: bipush        30
    4162: iconst_2
    4163: anewarray     #27                 // class com/google/zxing/qrcode/decoder/Version$ECB
    4166: dup
    4167: iconst_0
    4168: new           #27                 // class com/google/zxing/qrcode/decoder/Version$ECB
    4171: dup
    4172: iconst_4
    4173: bipush        121
    4175: invokespecial #28                 // Method com/google/zxing/qrcode/decoder/Version$ECB."<init>":(II)V
    4178: aastore
    4179: dup
    4180: iconst_1
    4181: new           #27                 // class com/google/zxing/qrcode/decoder/Version$ECB
    4184: dup
    4185: iconst_5
    4186: bipush        122
    4188: invokespecial #28                 // Method com/google/zxing/qrcode/decoder/Version$ECB."<init>":(II)V
    4191: aastore
    4192: invokespecial #29                 // Method com/google/zxing/qrcode/decoder/Version$ECBlocks."<init>":(I[Lcom/google/zxing/qrcode/decoder/Version$ECB;)V
    4195: aastore
    4196: dup
    4197: iconst_1
    4198: new           #26                 // class com/google/zxing/qrcode/decoder/Version$ECBlocks
    4201: dup
    4202: bipush        28
    4204: iconst_2
    4205: anewarray     #27                 // class com/google/zxing/qrcode/decoder/Version$ECB
    4208: dup
    4209: iconst_0
    4210: new           #27                 // class com/google/zxing/qrcode/decoder/Version$ECB
    4213: dup
    4214: iconst_4
    4215: bipush        47
    4217: invokespecial #28                 // Method com/google/zxing/qrcode/decoder/Version$ECB."<init>":(II)V
    4220: aastore
    4221: dup
    4222: iconst_1
    4223: new           #27                 // class com/google/zxing/qrcode/decoder/Version$ECB
    4226: dup
    4227: bipush        14
    4229: bipush        48
    4231: invokespecial #28                 // Method com/google/zxing/qrcode/decoder/Version$ECB."<init>":(II)V
    4234: aastore
    4235: invokespecial #29                 // Method com/google/zxing/qrcode/decoder/Version$ECBlocks."<init>":(I[Lcom/google/zxing/qrcode/decoder/Version$ECB;)V
    4238: aastore
    4239: dup
    4240: iconst_2
    4241: new           #26                 // class com/google/zxing/qrcode/decoder/Version$ECBlocks
    4244: dup
    4245: bipush        30
    4247: iconst_2
    4248: anewarray     #27                 // class com/google/zxing/qrcode/decoder/Version$ECB
    4251: dup
    4252: iconst_0
    4253: new           #27                 // class com/google/zxing/qrcode/decoder/Version$ECB
    4256: dup
    4257: bipush        11
    4259: bipush        24
    4261: invokespecial #28                 // Method com/google/zxing/qrcode/decoder/Version$ECB."<init>":(II)V
    4264: aastore
    4265: dup
    4266: iconst_1
    4267: new           #27                 // class com/google/zxing/qrcode/decoder/Version$ECB
    4270: dup
    4271: bipush        14
    4273: bipush        25
    4275: invokespecial #28                 // Method com/google/zxing/qrcode/decoder/Version$ECB."<init>":(II)V
    4278: aastore
    4279: invokespecial #29                 // Method com/google/zxing/qrcode/decoder/Version$ECBlocks."<init>":(I[Lcom/google/zxing/qrcode/decoder/Version$ECB;)V
    4282: aastore
    4283: dup
    4284: iconst_3
    4285: new           #26                 // class com/google/zxing/qrcode/decoder/Version$ECBlocks
    4288: dup
    4289: bipush        30
    4291: iconst_2
    4292: anewarray     #27                 // class com/google/zxing/qrcode/decoder/Version$ECB
    4295: dup
    4296: iconst_0
    4297: new           #27                 // class com/google/zxing/qrcode/decoder/Version$ECB
    4300: dup
    4301: bipush        16
    4303: bipush        15
    4305: invokespecial #28                 // Method com/google/zxing/qrcode/decoder/Version$ECB."<init>":(II)V
    4308: aastore
    4309: dup
    4310: iconst_1
    4311: new           #27                 // class com/google/zxing/qrcode/decoder/Version$ECB
    4314: dup
    4315: bipush        14
    4317: bipush        16
    4319: invokespecial #28                 // Method com/google/zxing/qrcode/decoder/Version$ECB."<init>":(II)V
    4322: aastore
    4323: invokespecial #29                 // Method com/google/zxing/qrcode/decoder/Version$ECBlocks."<init>":(I[Lcom/google/zxing/qrcode/decoder/Version$ECB;)V
    4326: aastore
    4327: invokespecial #30                 // Method "<init>":(I[I[Lcom/google/zxing/qrcode/decoder/Version$ECBlocks;)V
    4330: aastore
    4331: dup
    4332: bipush        23
    4334: new           #25                 // class com/google/zxing/qrcode/decoder/Version
    4337: dup
    4338: bipush        24
    4340: iconst_5
    4341: newarray       int
    4343: dup
    4344: iconst_0
    4345: bipush        6
    4347: iastore
    4348: dup
    4349: iconst_1
    4350: bipush        28
    4352: iastore
    4353: dup
    4354: iconst_2
    4355: bipush        54
    4357: iastore
    4358: dup
    4359: iconst_3
    4360: bipush        80
    4362: iastore
    4363: dup
    4364: iconst_4
    4365: bipush        106
    4367: iastore
    4368: iconst_4
    4369: anewarray     #26                 // class com/google/zxing/qrcode/decoder/Version$ECBlocks
    4372: dup
    4373: iconst_0
    4374: new           #26                 // class com/google/zxing/qrcode/decoder/Version$ECBlocks
    4377: dup
    4378: bipush        30
    4380: iconst_2
    4381: anewarray     #27                 // class com/google/zxing/qrcode/decoder/Version$ECB
    4384: dup
    4385: iconst_0
    4386: new           #27                 // class com/google/zxing/qrcode/decoder/Version$ECB
    4389: dup
    4390: bipush        6
    4392: bipush        117
    4394: invokespecial #28                 // Method com/google/zxing/qrcode/decoder/Version$ECB."<init>":(II)V
    4397: aastore
    4398: dup
    4399: iconst_1
    4400: new           #27                 // class com/google/zxing/qrcode/decoder/Version$ECB
    4403: dup
    4404: iconst_4
    4405: bipush        118
    4407: invokespecial #28                 // Method com/google/zxing/qrcode/decoder/Version$ECB."<init>":(II)V
    4410: aastore
    4411: invokespecial #29                 // Method com/google/zxing/qrcode/decoder/Version$ECBlocks."<init>":(I[Lcom/google/zxing/qrcode/decoder/Version$ECB;)V
    4414: aastore
    4415: dup
    4416: iconst_1
    4417: new           #26                 // class com/google/zxing/qrcode/decoder/Version$ECBlocks
    4420: dup
    4421: bipush        28
    4423: iconst_2
    4424: anewarray     #27                 // class com/google/zxing/qrcode/decoder/Version$ECB
    4427: dup
    4428: iconst_0
    4429: new           #27                 // class com/google/zxing/qrcode/decoder/Version$ECB
    4432: dup
    4433: bipush        6
    4435: bipush        45
    4437: invokespecial #28                 // Method com/google/zxing/qrcode/decoder/Version$ECB."<init>":(II)V
    4440: aastore
    4441: dup
    4442: iconst_1
    4443: new           #27                 // class com/google/zxing/qrcode/decoder/Version$ECB
    4446: dup
    4447: bipush        14
    4449: bipush        46
    4451: invokespecial #28                 // Method com/google/zxing/qrcode/decoder/Version$ECB."<init>":(II)V
    4454: aastore
    4455: invokespecial #29                 // Method com/google/zxing/qrcode/decoder/Version$ECBlocks."<init>":(I[Lcom/google/zxing/qrcode/decoder/Version$ECB;)V
    4458: aastore
    4459: dup
    4460: iconst_2
    4461: new           #26                 // class com/google/zxing/qrcode/decoder/Version$ECBlocks
    4464: dup
    4465: bipush        30
    4467: iconst_2
    4468: anewarray     #27                 // class com/google/zxing/qrcode/decoder/Version$ECB
    4471: dup
    4472: iconst_0
    4473: new           #27                 // class com/google/zxing/qrcode/decoder/Version$ECB
    4476: dup
    4477: bipush        11
    4479: bipush        24
    4481: invokespecial #28                 // Method com/google/zxing/qrcode/decoder/Version$ECB."<init>":(II)V
    4484: aastore
    4485: dup
    4486: iconst_1
    4487: new           #27                 // class com/google/zxing/qrcode/decoder/Version$ECB
    4490: dup
    4491: bipush        16
    4493: bipush        25
    4495: invokespecial #28                 // Method com/google/zxing/qrcode/decoder/Version$ECB."<init>":(II)V
    4498: aastore
    4499: invokespecial #29                 // Method com/google/zxing/qrcode/decoder/Version$ECBlocks."<init>":(I[Lcom/google/zxing/qrcode/decoder/Version$ECB;)V
    4502: aastore
    4503: dup
    4504: iconst_3
    4505: new           #26                 // class com/google/zxing/qrcode/decoder/Version$ECBlocks
    4508: dup
    4509: bipush        30
    4511: iconst_2
    4512: anewarray     #27                 // class com/google/zxing/qrcode/decoder/Version$ECB
    4515: dup
    4516: iconst_0
    4517: new           #27                 // class com/google/zxing/qrcode/decoder/Version$ECB
    4520: dup
    4521: bipush        30
    4523: bipush        16
    4525: invokespecial #28                 // Method com/google/zxing/qrcode/decoder/Version$ECB."<init>":(II)V
    4528: aastore
    4529: dup
    4530: iconst_1
    4531: new           #27                 // class com/google/zxing/qrcode/decoder/Version$ECB
    4534: dup
    4535: iconst_2
    4536: bipush        17
    4538: invokespecial #28                 // Method com/google/zxing/qrcode/decoder/Version$ECB."<init>":(II)V
    4541: aastore
    4542: invokespecial #29                 // Method com/google/zxing/qrcode/decoder/Version$ECBlocks."<init>":(I[Lcom/google/zxing/qrcode/decoder/Version$ECB;)V
    4545: aastore
    4546: invokespecial #30                 // Method "<init>":(I[I[Lcom/google/zxing/qrcode/decoder/Version$ECBlocks;)V
    4549: aastore
    4550: dup
    4551: bipush        24
    4553: new           #25                 // class com/google/zxing/qrcode/decoder/Version
    4556: dup
    4557: bipush        25
    4559: iconst_5
    4560: newarray       int
    4562: dup
    4563: iconst_0
    4564: bipush        6
    4566: iastore
    4567: dup
    4568: iconst_1
    4569: bipush        32
    4571: iastore
    4572: dup
    4573: iconst_2
    4574: bipush        58
    4576: iastore
    4577: dup
    4578: iconst_3
    4579: bipush        84
    4581: iastore
    4582: dup
    4583: iconst_4
    4584: bipush        110
    4586: iastore
    4587: iconst_4
    4588: anewarray     #26                 // class com/google/zxing/qrcode/decoder/Version$ECBlocks
    4591: dup
    4592: iconst_0
    4593: new           #26                 // class com/google/zxing/qrcode/decoder/Version$ECBlocks
    4596: dup
    4597: bipush        26
    4599: iconst_2
    4600: anewarray     #27                 // class com/google/zxing/qrcode/decoder/Version$ECB
    4603: dup
    4604: iconst_0
    4605: new           #27                 // class com/google/zxing/qrcode/decoder/Version$ECB
    4608: dup
    4609: bipush        8
    4611: bipush        106
    4613: invokespecial #28                 // Method com/google/zxing/qrcode/decoder/Version$ECB."<init>":(II)V
    4616: aastore
    4617: dup
    4618: iconst_1
    4619: new           #27                 // class com/google/zxing/qrcode/decoder/Version$ECB
    4622: dup
    4623: iconst_4
    4624: bipush        107
    4626: invokespecial #28                 // Method com/google/zxing/qrcode/decoder/Version$ECB."<init>":(II)V
    4629: aastore
    4630: invokespecial #29                 // Method com/google/zxing/qrcode/decoder/Version$ECBlocks."<init>":(I[Lcom/google/zxing/qrcode/decoder/Version$ECB;)V
    4633: aastore
    4634: dup
    4635: iconst_1
    4636: new           #26                 // class com/google/zxing/qrcode/decoder/Version$ECBlocks
    4639: dup
    4640: bipush        28
    4642: iconst_2
    4643: anewarray     #27                 // class com/google/zxing/qrcode/decoder/Version$ECB
    4646: dup
    4647: iconst_0
    4648: new           #27                 // class com/google/zxing/qrcode/decoder/Version$ECB
    4651: dup
    4652: bipush        8
    4654: bipush        47
    4656: invokespecial #28                 // Method com/google/zxing/qrcode/decoder/Version$ECB."<init>":(II)V
    4659: aastore
    4660: dup
    4661: iconst_1
    4662: new           #27                 // class com/google/zxing/qrcode/decoder/Version$ECB
    4665: dup
    4666: bipush        13
    4668: bipush        48
    4670: invokespecial #28                 // Method com/google/zxing/qrcode/decoder/Version$ECB."<init>":(II)V
    4673: aastore
    4674: invokespecial #29                 // Method com/google/zxing/qrcode/decoder/Version$ECBlocks."<init>":(I[Lcom/google/zxing/qrcode/decoder/Version$ECB;)V
    4677: aastore
    4678: dup
    4679: iconst_2
    4680: new           #26                 // class com/google/zxing/qrcode/decoder/Version$ECBlocks
    4683: dup
    4684: bipush        30
    4686: iconst_2
    4687: anewarray     #27                 // class com/google/zxing/qrcode/decoder/Version$ECB
    4690: dup
    4691: iconst_0
    4692: new           #27                 // class com/google/zxing/qrcode/decoder/Version$ECB
    4695: dup
    4696: bipush        7
    4698: bipush        24
    4700: invokespecial #28                 // Method com/google/zxing/qrcode/decoder/Version$ECB."<init>":(II)V
    4703: aastore
    4704: dup
    4705: iconst_1
    4706: new           #27                 // class com/google/zxing/qrcode/decoder/Version$ECB
    4709: dup
    4710: bipush        22
    4712: bipush        25
    4714: invokespecial #28                 // Method com/google/zxing/qrcode/decoder/Version$ECB."<init>":(II)V
    4717: aastore
    4718: invokespecial #29                 // Method com/google/zxing/qrcode/decoder/Version$ECBlocks."<init>":(I[Lcom/google/zxing/qrcode/decoder/Version$ECB;)V
    4721: aastore
    4722: dup
    4723: iconst_3
    4724: new           #26                 // class com/google/zxing/qrcode/decoder/Version$ECBlocks
    4727: dup
    4728: bipush        30
    4730: iconst_2
    4731: anewarray     #27                 // class com/google/zxing/qrcode/decoder/Version$ECB
    4734: dup
    4735: iconst_0
    4736: new           #27                 // class com/google/zxing/qrcode/decoder/Version$ECB
    4739: dup
    4740: bipush        22
    4742: bipush        15
    4744: invokespecial #28                 // Method com/google/zxing/qrcode/decoder/Version$ECB."<init>":(II)V
    4747: aastore
    4748: dup
    4749: iconst_1
    4750: new           #27                 // class com/google/zxing/qrcode/decoder/Version$ECB
    4753: dup
    4754: bipush        13
    4756: bipush        16
    4758: invokespecial #28                 // Method com/google/zxing/qrcode/decoder/Version$ECB."<init>":(II)V
    4761: aastore
    4762: invokespecial #29                 // Method com/google/zxing/qrcode/decoder/Version$ECBlocks."<init>":(I[Lcom/google/zxing/qrcode/decoder/Version$ECB;)V
    4765: aastore
    4766: invokespecial #30                 // Method "<init>":(I[I[Lcom/google/zxing/qrcode/decoder/Version$ECBlocks;)V
    4769: aastore
    4770: dup
    4771: bipush        25
    4773: new           #25                 // class com/google/zxing/qrcode/decoder/Version
    4776: dup
    4777: bipush        26
    4779: iconst_5
    4780: newarray       int
    4782: dup
    4783: iconst_0
    4784: bipush        6
    4786: iastore
    4787: dup
    4788: iconst_1
    4789: bipush        30
    4791: iastore
    4792: dup
    4793: iconst_2
    4794: bipush        58
    4796: iastore
    4797: dup
    4798: iconst_3
    4799: bipush        86
    4801: iastore
    4802: dup
    4803: iconst_4
    4804: bipush        114
    4806: iastore
    4807: iconst_4
    4808: anewarray     #26                 // class com/google/zxing/qrcode/decoder/Version$ECBlocks
    4811: dup
    4812: iconst_0
    4813: new           #26                 // class com/google/zxing/qrcode/decoder/Version$ECBlocks
    4816: dup
    4817: bipush        28
    4819: iconst_2
    4820: anewarray     #27                 // class com/google/zxing/qrcode/decoder/Version$ECB
    4823: dup
    4824: iconst_0
    4825: new           #27                 // class com/google/zxing/qrcode/decoder/Version$ECB
    4828: dup
    4829: bipush        10
    4831: bipush        114
    4833: invokespecial #28                 // Method com/google/zxing/qrcode/decoder/Version$ECB."<init>":(II)V
    4836: aastore
    4837: dup
    4838: iconst_1
    4839: new           #27                 // class com/google/zxing/qrcode/decoder/Version$ECB
    4842: dup
    4843: iconst_2
    4844: bipush        115
    4846: invokespecial #28                 // Method com/google/zxing/qrcode/decoder/Version$ECB."<init>":(II)V
    4849: aastore
    4850: invokespecial #29                 // Method com/google/zxing/qrcode/decoder/Version$ECBlocks."<init>":(I[Lcom/google/zxing/qrcode/decoder/Version$ECB;)V
    4853: aastore
    4854: dup
    4855: iconst_1
    4856: new           #26                 // class com/google/zxing/qrcode/decoder/Version$ECBlocks
    4859: dup
    4860: bipush        28
    4862: iconst_2
    4863: anewarray     #27                 // class com/google/zxing/qrcode/decoder/Version$ECB
    4866: dup
    4867: iconst_0
    4868: new           #27                 // class com/google/zxing/qrcode/decoder/Version$ECB
    4871: dup
    4872: bipush        19
    4874: bipush        46
    4876: invokespecial #28                 // Method com/google/zxing/qrcode/decoder/Version$ECB."<init>":(II)V
    4879: aastore
    4880: dup
    4881: iconst_1
    4882: new           #27                 // class com/google/zxing/qrcode/decoder/Version$ECB
    4885: dup
    4886: iconst_4
    4887: bipush        47
    4889: invokespecial #28                 // Method com/google/zxing/qrcode/decoder/Version$ECB."<init>":(II)V
    4892: aastore
    4893: invokespecial #29                 // Method com/google/zxing/qrcode/decoder/Version$ECBlocks."<init>":(I[Lcom/google/zxing/qrcode/decoder/Version$ECB;)V
    4896: aastore
    4897: dup
    4898: iconst_2
    4899: new           #26                 // class com/google/zxing/qrcode/decoder/Version$ECBlocks
    4902: dup
    4903: bipush        28
    4905: iconst_2
    4906: anewarray     #27                 // class com/google/zxing/qrcode/decoder/Version$ECB
    4909: dup
    4910: iconst_0
    4911: new           #27                 // class com/google/zxing/qrcode/decoder/Version$ECB
    4914: dup
    4915: bipush        28
    4917: bipush        22
    4919: invokespecial #28                 // Method com/google/zxing/qrcode/decoder/Version$ECB."<init>":(II)V
    4922: aastore
    4923: dup
    4924: iconst_1
    4925: new           #27                 // class com/google/zxing/qrcode/decoder/Version$ECB
    4928: dup
    4929: bipush        6
    4931: bipush        23
    4933: invokespecial #28                 // Method com/google/zxing/qrcode/decoder/Version$ECB."<init>":(II)V
    4936: aastore
    4937: invokespecial #29                 // Method com/google/zxing/qrcode/decoder/Version$ECBlocks."<init>":(I[Lcom/google/zxing/qrcode/decoder/Version$ECB;)V
    4940: aastore
    4941: dup
    4942: iconst_3
    4943: new           #26                 // class com/google/zxing/qrcode/decoder/Version$ECBlocks
    4946: dup
    4947: bipush        30
    4949: iconst_2
    4950: anewarray     #27                 // class com/google/zxing/qrcode/decoder/Version$ECB
    4953: dup
    4954: iconst_0
    4955: new           #27                 // class com/google/zxing/qrcode/decoder/Version$ECB
    4958: dup
    4959: bipush        33
    4961: bipush        16
    4963: invokespecial #28                 // Method com/google/zxing/qrcode/decoder/Version$ECB."<init>":(II)V
    4966: aastore
    4967: dup
    4968: iconst_1
    4969: new           #27                 // class com/google/zxing/qrcode/decoder/Version$ECB
    4972: dup
    4973: iconst_4
    4974: bipush        17
    4976: invokespecial #28                 // Method com/google/zxing/qrcode/decoder/Version$ECB."<init>":(II)V
    4979: aastore
    4980: invokespecial #29                 // Method com/google/zxing/qrcode/decoder/Version$ECBlocks."<init>":(I[Lcom/google/zxing/qrcode/decoder/Version$ECB;)V
    4983: aastore
    4984: invokespecial #30                 // Method "<init>":(I[I[Lcom/google/zxing/qrcode/decoder/Version$ECBlocks;)V
    4987: aastore
    4988: dup
    4989: bipush        26
    4991: new           #25                 // class com/google/zxing/qrcode/decoder/Version
    4994: dup
    4995: bipush        27
    4997: iconst_5
    4998: newarray       int
    5000: dup
    5001: iconst_0
    5002: bipush        6
    5004: iastore
    5005: dup
    5006: iconst_1
    5007: bipush        34
    5009: iastore
    5010: dup
    5011: iconst_2
    5012: bipush        62
    5014: iastore
    5015: dup
    5016: iconst_3
    5017: bipush        90
    5019: iastore
    5020: dup
    5021: iconst_4
    5022: bipush        118
    5024: iastore
    5025: iconst_4
    5026: anewarray     #26                 // class com/google/zxing/qrcode/decoder/Version$ECBlocks
    5029: dup
    5030: iconst_0
    5031: new           #26                 // class com/google/zxing/qrcode/decoder/Version$ECBlocks
    5034: dup
    5035: bipush        30
    5037: iconst_2
    5038: anewarray     #27                 // class com/google/zxing/qrcode/decoder/Version$ECB
    5041: dup
    5042: iconst_0
    5043: new           #27                 // class com/google/zxing/qrcode/decoder/Version$ECB
    5046: dup
    5047: bipush        8
    5049: bipush        122
    5051: invokespecial #28                 // Method com/google/zxing/qrcode/decoder/Version$ECB."<init>":(II)V
    5054: aastore
    5055: dup
    5056: iconst_1
    5057: new           #27                 // class com/google/zxing/qrcode/decoder/Version$ECB
    5060: dup
    5061: iconst_4
    5062: bipush        123
    5064: invokespecial #28                 // Method com/google/zxing/qrcode/decoder/Version$ECB."<init>":(II)V
    5067: aastore
    5068: invokespecial #29                 // Method com/google/zxing/qrcode/decoder/Version$ECBlocks."<init>":(I[Lcom/google/zxing/qrcode/decoder/Version$ECB;)V
    5071: aastore
    5072: dup
    5073: iconst_1
    5074: new           #26                 // class com/google/zxing/qrcode/decoder/Version$ECBlocks
    5077: dup
    5078: bipush        28
    5080: iconst_2
    5081: anewarray     #27                 // class com/google/zxing/qrcode/decoder/Version$ECB
    5084: dup
    5085: iconst_0
    5086: new           #27                 // class com/google/zxing/qrcode/decoder/Version$ECB
    5089: dup
    5090: bipush        22
    5092: bipush        45
    5094: invokespecial #28                 // Method com/google/zxing/qrcode/decoder/Version$ECB."<init>":(II)V
    5097: aastore
    5098: dup
    5099: iconst_1
    5100: new           #27                 // class com/google/zxing/qrcode/decoder/Version$ECB
    5103: dup
    5104: iconst_3
    5105: bipush        46
    5107: invokespecial #28                 // Method com/google/zxing/qrcode/decoder/Version$ECB."<init>":(II)V
    5110: aastore
    5111: invokespecial #29                 // Method com/google/zxing/qrcode/decoder/Version$ECBlocks."<init>":(I[Lcom/google/zxing/qrcode/decoder/Version$ECB;)V
    5114: aastore
    5115: dup
    5116: iconst_2
    5117: new           #26                 // class com/google/zxing/qrcode/decoder/Version$ECBlocks
    5120: dup
    5121: bipush        30
    5123: iconst_2
    5124: anewarray     #27                 // class com/google/zxing/qrcode/decoder/Version$ECB
    5127: dup
    5128: iconst_0
    5129: new           #27                 // class com/google/zxing/qrcode/decoder/Version$ECB
    5132: dup
    5133: bipush        8
    5135: bipush        23
    5137: invokespecial #28                 // Method com/google/zxing/qrcode/decoder/Version$ECB."<init>":(II)V
    5140: aastore
    5141: dup
    5142: iconst_1
    5143: new           #27                 // class com/google/zxing/qrcode/decoder/Version$ECB
    5146: dup
    5147: bipush        26
    5149: bipush        24
    5151: invokespecial #28                 // Method com/google/zxing/qrcode/decoder/Version$ECB."<init>":(II)V
    5154: aastore
    5155: invokespecial #29                 // Method com/google/zxing/qrcode/decoder/Version$ECBlocks."<init>":(I[Lcom/google/zxing/qrcode/decoder/Version$ECB;)V
    5158: aastore
    5159: dup
    5160: iconst_3
    5161: new           #26                 // class com/google/zxing/qrcode/decoder/Version$ECBlocks
    5164: dup
    5165: bipush        30
    5167: iconst_2
    5168: anewarray     #27                 // class com/google/zxing/qrcode/decoder/Version$ECB
    5171: dup
    5172: iconst_0
    5173: new           #27                 // class com/google/zxing/qrcode/decoder/Version$ECB
    5176: dup
    5177: bipush        12
    5179: bipush        15
    5181: invokespecial #28                 // Method com/google/zxing/qrcode/decoder/Version$ECB."<init>":(II)V
    5184: aastore
    5185: dup
    5186: iconst_1
    5187: new           #27                 // class com/google/zxing/qrcode/decoder/Version$ECB
    5190: dup
    5191: bipush        28
    5193: bipush        16
    5195: invokespecial #28                 // Method com/google/zxing/qrcode/decoder/Version$ECB."<init>":(II)V
    5198: aastore
    5199: invokespecial #29                 // Method com/google/zxing/qrcode/decoder/Version$ECBlocks."<init>":(I[Lcom/google/zxing/qrcode/decoder/Version$ECB;)V
    5202: aastore
    5203: invokespecial #30                 // Method "<init>":(I[I[Lcom/google/zxing/qrcode/decoder/Version$ECBlocks;)V
    5206: aastore
    5207: dup
    5208: bipush        27
    5210: new           #25                 // class com/google/zxing/qrcode/decoder/Version
    5213: dup
    5214: bipush        28
    5216: bipush        6
    5218: newarray       int
    5220: dup
    5221: iconst_0
    5222: bipush        6
    5224: iastore
    5225: dup
    5226: iconst_1
    5227: bipush        26
    5229: iastore
    5230: dup
    5231: iconst_2
    5232: bipush        50
    5234: iastore
    5235: dup
    5236: iconst_3
    5237: bipush        74
    5239: iastore
    5240: dup
    5241: iconst_4
    5242: bipush        98
    5244: iastore
    5245: dup
    5246: iconst_5
    5247: bipush        122
    5249: iastore
    5250: iconst_4
    5251: anewarray     #26                 // class com/google/zxing/qrcode/decoder/Version$ECBlocks
    5254: dup
    5255: iconst_0
    5256: new           #26                 // class com/google/zxing/qrcode/decoder/Version$ECBlocks
    5259: dup
    5260: bipush        30
    5262: iconst_2
    5263: anewarray     #27                 // class com/google/zxing/qrcode/decoder/Version$ECB
    5266: dup
    5267: iconst_0
    5268: new           #27                 // class com/google/zxing/qrcode/decoder/Version$ECB
    5271: dup
    5272: iconst_3
    5273: bipush        117
    5275: invokespecial #28                 // Method com/google/zxing/qrcode/decoder/Version$ECB."<init>":(II)V
    5278: aastore
    5279: dup
    5280: iconst_1
    5281: new           #27                 // class com/google/zxing/qrcode/decoder/Version$ECB
    5284: dup
    5285: bipush        10
    5287: bipush        118
    5289: invokespecial #28                 // Method com/google/zxing/qrcode/decoder/Version$ECB."<init>":(II)V
    5292: aastore
    5293: invokespecial #29                 // Method com/google/zxing/qrcode/decoder/Version$ECBlocks."<init>":(I[Lcom/google/zxing/qrcode/decoder/Version$ECB;)V
    5296: aastore
    5297: dup
    5298: iconst_1
    5299: new           #26                 // class com/google/zxing/qrcode/decoder/Version$ECBlocks
    5302: dup
    5303: bipush        28
    5305: iconst_2
    5306: anewarray     #27                 // class com/google/zxing/qrcode/decoder/Version$ECB
    5309: dup
    5310: iconst_0
    5311: new           #27                 // class com/google/zxing/qrcode/decoder/Version$ECB
    5314: dup
    5315: iconst_3
    5316: bipush        45
    5318: invokespecial #28                 // Method com/google/zxing/qrcode/decoder/Version$ECB."<init>":(II)V
    5321: aastore
    5322: dup
    5323: iconst_1
    5324: new           #27                 // class com/google/zxing/qrcode/decoder/Version$ECB
    5327: dup
    5328: bipush        23
    5330: bipush        46
    5332: invokespecial #28                 // Method com/google/zxing/qrcode/decoder/Version$ECB."<init>":(II)V
    5335: aastore
    5336: invokespecial #29                 // Method com/google/zxing/qrcode/decoder/Version$ECBlocks."<init>":(I[Lcom/google/zxing/qrcode/decoder/Version$ECB;)V
    5339: aastore
    5340: dup
    5341: iconst_2
    5342: new           #26                 // class com/google/zxing/qrcode/decoder/Version$ECBlocks
    5345: dup
    5346: bipush        30
    5348: iconst_2
    5349: anewarray     #27                 // class com/google/zxing/qrcode/decoder/Version$ECB
    5352: dup
    5353: iconst_0
    5354: new           #27                 // class com/google/zxing/qrcode/decoder/Version$ECB
    5357: dup
    5358: iconst_4
    5359: bipush        24
    5361: invokespecial #28                 // Method com/google/zxing/qrcode/decoder/Version$ECB."<init>":(II)V
    5364: aastore
    5365: dup
    5366: iconst_1
    5367: new           #27                 // class com/google/zxing/qrcode/decoder/Version$ECB
    5370: dup
    5371: bipush        31
    5373: bipush        25
    5375: invokespecial #28                 // Method com/google/zxing/qrcode/decoder/Version$ECB."<init>":(II)V
    5378: aastore
    5379: invokespecial #29                 // Method com/google/zxing/qrcode/decoder/Version$ECBlocks."<init>":(I[Lcom/google/zxing/qrcode/decoder/Version$ECB;)V
    5382: aastore
    5383: dup
    5384: iconst_3
    5385: new           #26                 // class com/google/zxing/qrcode/decoder/Version$ECBlocks
    5388: dup
    5389: bipush        30
    5391: iconst_2
    5392: anewarray     #27                 // class com/google/zxing/qrcode/decoder/Version$ECB
    5395: dup
    5396: iconst_0
    5397: new           #27                 // class com/google/zxing/qrcode/decoder/Version$ECB
    5400: dup
    5401: bipush        11
    5403: bipush        15
    5405: invokespecial #28                 // Method com/google/zxing/qrcode/decoder/Version$ECB."<init>":(II)V
    5408: aastore
    5409: dup
    5410: iconst_1
    5411: new           #27                 // class com/google/zxing/qrcode/decoder/Version$ECB
    5414: dup
    5415: bipush        31
    5417: bipush        16
    5419: invokespecial #28                 // Method com/google/zxing/qrcode/decoder/Version$ECB."<init>":(II)V
    5422: aastore
    5423: invokespecial #29                 // Method com/google/zxing/qrcode/decoder/Version$ECBlocks."<init>":(I[Lcom/google/zxing/qrcode/decoder/Version$ECB;)V
    5426: aastore
    5427: invokespecial #30                 // Method "<init>":(I[I[Lcom/google/zxing/qrcode/decoder/Version$ECBlocks;)V
    5430: aastore
    5431: dup
    5432: bipush        28
    5434: new           #25                 // class com/google/zxing/qrcode/decoder/Version
    5437: dup
    5438: bipush        29
    5440: bipush        6
    5442: newarray       int
    5444: dup
    5445: iconst_0
    5446: bipush        6
    5448: iastore
    5449: dup
    5450: iconst_1
    5451: bipush        30
    5453: iastore
    5454: dup
    5455: iconst_2
    5456: bipush        54
    5458: iastore
    5459: dup
    5460: iconst_3
    5461: bipush        78
    5463: iastore
    5464: dup
    5465: iconst_4
    5466: bipush        102
    5468: iastore
    5469: dup
    5470: iconst_5
    5471: bipush        126
    5473: iastore
    5474: iconst_4
    5475: anewarray     #26                 // class com/google/zxing/qrcode/decoder/Version$ECBlocks
    5478: dup
    5479: iconst_0
    5480: new           #26                 // class com/google/zxing/qrcode/decoder/Version$ECBlocks
    5483: dup
    5484: bipush        30
    5486: iconst_2
    5487: anewarray     #27                 // class com/google/zxing/qrcode/decoder/Version$ECB
    5490: dup
    5491: iconst_0
    5492: new           #27                 // class com/google/zxing/qrcode/decoder/Version$ECB
    5495: dup
    5496: bipush        7
    5498: bipush        116
    5500: invokespecial #28                 // Method com/google/zxing/qrcode/decoder/Version$ECB."<init>":(II)V
    5503: aastore
    5504: dup
    5505: iconst_1
    5506: new           #27                 // class com/google/zxing/qrcode/decoder/Version$ECB
    5509: dup
    5510: bipush        7
    5512: bipush        117
    5514: invokespecial #28                 // Method com/google/zxing/qrcode/decoder/Version$ECB."<init>":(II)V
    5517: aastore
    5518: invokespecial #29                 // Method com/google/zxing/qrcode/decoder/Version$ECBlocks."<init>":(I[Lcom/google/zxing/qrcode/decoder/Version$ECB;)V
    5521: aastore
    5522: dup
    5523: iconst_1
    5524: new           #26                 // class com/google/zxing/qrcode/decoder/Version$ECBlocks
    5527: dup
    5528: bipush        28
    5530: iconst_2
    5531: anewarray     #27                 // class com/google/zxing/qrcode/decoder/Version$ECB
    5534: dup
    5535: iconst_0
    5536: new           #27                 // class com/google/zxing/qrcode/decoder/Version$ECB
    5539: dup
    5540: bipush        21
    5542: bipush        45
    5544: invokespecial #28                 // Method com/google/zxing/qrcode/decoder/Version$ECB."<init>":(II)V
    5547: aastore
    5548: dup
    5549: iconst_1
    5550: new           #27                 // class com/google/zxing/qrcode/decoder/Version$ECB
    5553: dup
    5554: bipush        7
    5556: bipush        46
    5558: invokespecial #28                 // Method com/google/zxing/qrcode/decoder/Version$ECB."<init>":(II)V
    5561: aastore
    5562: invokespecial #29                 // Method com/google/zxing/qrcode/decoder/Version$ECBlocks."<init>":(I[Lcom/google/zxing/qrcode/decoder/Version$ECB;)V
    5565: aastore
    5566: dup
    5567: iconst_2
    5568: new           #26                 // class com/google/zxing/qrcode/decoder/Version$ECBlocks
    5571: dup
    5572: bipush        30
    5574: iconst_2
    5575: anewarray     #27                 // class com/google/zxing/qrcode/decoder/Version$ECB
    5578: dup
    5579: iconst_0
    5580: new           #27                 // class com/google/zxing/qrcode/decoder/Version$ECB
    5583: dup
    5584: iconst_1
    5585: bipush        23
    5587: invokespecial #28                 // Method com/google/zxing/qrcode/decoder/Version$ECB."<init>":(II)V
    5590: aastore
    5591: dup
    5592: iconst_1
    5593: new           #27                 // class com/google/zxing/qrcode/decoder/Version$ECB
    5596: dup
    5597: bipush        37
    5599: bipush        24
    5601: invokespecial #28                 // Method com/google/zxing/qrcode/decoder/Version$ECB."<init>":(II)V
    5604: aastore
    5605: invokespecial #29                 // Method com/google/zxing/qrcode/decoder/Version$ECBlocks."<init>":(I[Lcom/google/zxing/qrcode/decoder/Version$ECB;)V
    5608: aastore
    5609: dup
    5610: iconst_3
    5611: new           #26                 // class com/google/zxing/qrcode/decoder/Version$ECBlocks
    5614: dup
    5615: bipush        30
    5617: iconst_2
    5618: anewarray     #27                 // class com/google/zxing/qrcode/decoder/Version$ECB
    5621: dup
    5622: iconst_0
    5623: new           #27                 // class com/google/zxing/qrcode/decoder/Version$ECB
    5626: dup
    5627: bipush        19
    5629: bipush        15
    5631: invokespecial #28                 // Method com/google/zxing/qrcode/decoder/Version$ECB."<init>":(II)V
    5634: aastore
    5635: dup
    5636: iconst_1
    5637: new           #27                 // class com/google/zxing/qrcode/decoder/Version$ECB
    5640: dup
    5641: bipush        26
    5643: bipush        16
    5645: invokespecial #28                 // Method com/google/zxing/qrcode/decoder/Version$ECB."<init>":(II)V
    5648: aastore
    5649: invokespecial #29                 // Method com/google/zxing/qrcode/decoder/Version$ECBlocks."<init>":(I[Lcom/google/zxing/qrcode/decoder/Version$ECB;)V
    5652: aastore
    5653: invokespecial #30                 // Method "<init>":(I[I[Lcom/google/zxing/qrcode/decoder/Version$ECBlocks;)V
    5656: aastore
    5657: dup
    5658: bipush        29
    5660: new           #25                 // class com/google/zxing/qrcode/decoder/Version
    5663: dup
    5664: bipush        30
    5666: bipush        6
    5668: newarray       int
    5670: dup
    5671: iconst_0
    5672: bipush        6
    5674: iastore
    5675: dup
    5676: iconst_1
    5677: bipush        26
    5679: iastore
    5680: dup
    5681: iconst_2
    5682: bipush        52
    5684: iastore
    5685: dup
    5686: iconst_3
    5687: bipush        78
    5689: iastore
    5690: dup
    5691: iconst_4
    5692: bipush        104
    5694: iastore
    5695: dup
    5696: iconst_5
    5697: sipush        130
    5700: iastore
    5701: iconst_4
    5702: anewarray     #26                 // class com/google/zxing/qrcode/decoder/Version$ECBlocks
    5705: dup
    5706: iconst_0
    5707: new           #26                 // class com/google/zxing/qrcode/decoder/Version$ECBlocks
    5710: dup
    5711: bipush        30
    5713: iconst_2
    5714: anewarray     #27                 // class com/google/zxing/qrcode/decoder/Version$ECB
    5717: dup
    5718: iconst_0
    5719: new           #27                 // class com/google/zxing/qrcode/decoder/Version$ECB
    5722: dup
    5723: iconst_5
    5724: bipush        115
    5726: invokespecial #28                 // Method com/google/zxing/qrcode/decoder/Version$ECB."<init>":(II)V
    5729: aastore
    5730: dup
    5731: iconst_1
    5732: new           #27                 // class com/google/zxing/qrcode/decoder/Version$ECB
    5735: dup
    5736: bipush        10
    5738: bipush        116
    5740: invokespecial #28                 // Method com/google/zxing/qrcode/decoder/Version$ECB."<init>":(II)V
    5743: aastore
    5744: invokespecial #29                 // Method com/google/zxing/qrcode/decoder/Version$ECBlocks."<init>":(I[Lcom/google/zxing/qrcode/decoder/Version$ECB;)V
    5747: aastore
    5748: dup
    5749: iconst_1
    5750: new           #26                 // class com/google/zxing/qrcode/decoder/Version$ECBlocks
    5753: dup
    5754: bipush        28
    5756: iconst_2
    5757: anewarray     #27                 // class com/google/zxing/qrcode/decoder/Version$ECB
    5760: dup
    5761: iconst_0
    5762: new           #27                 // class com/google/zxing/qrcode/decoder/Version$ECB
    5765: dup
    5766: bipush        19
    5768: bipush        47
    5770: invokespecial #28                 // Method com/google/zxing/qrcode/decoder/Version$ECB."<init>":(II)V
    5773: aastore
    5774: dup
    5775: iconst_1
    5776: new           #27                 // class com/google/zxing/qrcode/decoder/Version$ECB
    5779: dup
    5780: bipush        10
    5782: bipush        48
    5784: invokespecial #28                 // Method com/google/zxing/qrcode/decoder/Version$ECB."<init>":(II)V
    5787: aastore
    5788: invokespecial #29                 // Method com/google/zxing/qrcode/decoder/Version$ECBlocks."<init>":(I[Lcom/google/zxing/qrcode/decoder/Version$ECB;)V
    5791: aastore
    5792: dup
    5793: iconst_2
    5794: new           #26                 // class com/google/zxing/qrcode/decoder/Version$ECBlocks
    5797: dup
    5798: bipush        30
    5800: iconst_2
    5801: anewarray     #27                 // class com/google/zxing/qrcode/decoder/Version$ECB
    5804: dup
    5805: iconst_0
    5806: new           #27                 // class com/google/zxing/qrcode/decoder/Version$ECB
    5809: dup
    5810: bipush        15
    5812: bipush        24
    5814: invokespecial #28                 // Method com/google/zxing/qrcode/decoder/Version$ECB."<init>":(II)V
    5817: aastore
    5818: dup
    5819: iconst_1
    5820: new           #27                 // class com/google/zxing/qrcode/decoder/Version$ECB
    5823: dup
    5824: bipush        25
    5826: bipush        25
    5828: invokespecial #28                 // Method com/google/zxing/qrcode/decoder/Version$ECB."<init>":(II)V
    5831: aastore
    5832: invokespecial #29                 // Method com/google/zxing/qrcode/decoder/Version$ECBlocks."<init>":(I[Lcom/google/zxing/qrcode/decoder/Version$ECB;)V
    5835: aastore
    5836: dup
    5837: iconst_3
    5838: new           #26                 // class com/google/zxing/qrcode/decoder/Version$ECBlocks
    5841: dup
    5842: bipush        30
    5844: iconst_2
    5845: anewarray     #27                 // class com/google/zxing/qrcode/decoder/Version$ECB
    5848: dup
    5849: iconst_0
    5850: new           #27                 // class com/google/zxing/qrcode/decoder/Version$ECB
    5853: dup
    5854: bipush        23
    5856: bipush        15
    5858: invokespecial #28                 // Method com/google/zxing/qrcode/decoder/Version$ECB."<init>":(II)V
    5861: aastore
    5862: dup
    5863: iconst_1
    5864: new           #27                 // class com/google/zxing/qrcode/decoder/Version$ECB
    5867: dup
    5868: bipush        25
    5870: bipush        16
    5872: invokespecial #28                 // Method com/google/zxing/qrcode/decoder/Version$ECB."<init>":(II)V
    5875: aastore
    5876: invokespecial #29                 // Method com/google/zxing/qrcode/decoder/Version$ECBlocks."<init>":(I[Lcom/google/zxing/qrcode/decoder/Version$ECB;)V
    5879: aastore
    5880: invokespecial #30                 // Method "<init>":(I[I[Lcom/google/zxing/qrcode/decoder/Version$ECBlocks;)V
    5883: aastore
    5884: dup
    5885: bipush        30
    5887: new           #25                 // class com/google/zxing/qrcode/decoder/Version
    5890: dup
    5891: bipush        31
    5893: bipush        6
    5895: newarray       int
    5897: dup
    5898: iconst_0
    5899: bipush        6
    5901: iastore
    5902: dup
    5903: iconst_1
    5904: bipush        30
    5906: iastore
    5907: dup
    5908: iconst_2
    5909: bipush        56
    5911: iastore
    5912: dup
    5913: iconst_3
    5914: bipush        82
    5916: iastore
    5917: dup
    5918: iconst_4
    5919: bipush        108
    5921: iastore
    5922: dup
    5923: iconst_5
    5924: sipush        134
    5927: iastore
    5928: iconst_4
    5929: anewarray     #26                 // class com/google/zxing/qrcode/decoder/Version$ECBlocks
    5932: dup
    5933: iconst_0
    5934: new           #26                 // class com/google/zxing/qrcode/decoder/Version$ECBlocks
    5937: dup
    5938: bipush        30
    5940: iconst_2
    5941: anewarray     #27                 // class com/google/zxing/qrcode/decoder/Version$ECB
    5944: dup
    5945: iconst_0
    5946: new           #27                 // class com/google/zxing/qrcode/decoder/Version$ECB
    5949: dup
    5950: bipush        13
    5952: bipush        115
    5954: invokespecial #28                 // Method com/google/zxing/qrcode/decoder/Version$ECB."<init>":(II)V
    5957: aastore
    5958: dup
    5959: iconst_1
    5960: new           #27                 // class com/google/zxing/qrcode/decoder/Version$ECB
    5963: dup
    5964: iconst_3
    5965: bipush        116
    5967: invokespecial #28                 // Method com/google/zxing/qrcode/decoder/Version$ECB."<init>":(II)V
    5970: aastore
    5971: invokespecial #29                 // Method com/google/zxing/qrcode/decoder/Version$ECBlocks."<init>":(I[Lcom/google/zxing/qrcode/decoder/Version$ECB;)V
    5974: aastore
    5975: dup
    5976: iconst_1
    5977: new           #26                 // class com/google/zxing/qrcode/decoder/Version$ECBlocks
    5980: dup
    5981: bipush        28
    5983: iconst_2
    5984: anewarray     #27                 // class com/google/zxing/qrcode/decoder/Version$ECB
    5987: dup
    5988: iconst_0
    5989: new           #27                 // class com/google/zxing/qrcode/decoder/Version$ECB
    5992: dup
    5993: iconst_2
    5994: bipush        46
    5996: invokespecial #28                 // Method com/google/zxing/qrcode/decoder/Version$ECB."<init>":(II)V
    5999: aastore
    6000: dup
    6001: iconst_1
    6002: new           #27                 // class com/google/zxing/qrcode/decoder/Version$ECB
    6005: dup
    6006: bipush        29
    6008: bipush        47
    6010: invokespecial #28                 // Method com/google/zxing/qrcode/decoder/Version$ECB."<init>":(II)V
    6013: aastore
    6014: invokespecial #29                 // Method com/google/zxing/qrcode/decoder/Version$ECBlocks."<init>":(I[Lcom/google/zxing/qrcode/decoder/Version$ECB;)V
    6017: aastore
    6018: dup
    6019: iconst_2
    6020: new           #26                 // class com/google/zxing/qrcode/decoder/Version$ECBlocks
    6023: dup
    6024: bipush        30
    6026: iconst_2
    6027: anewarray     #27                 // class com/google/zxing/qrcode/decoder/Version$ECB
    6030: dup
    6031: iconst_0
    6032: new           #27                 // class com/google/zxing/qrcode/decoder/Version$ECB
    6035: dup
    6036: bipush        42
    6038: bipush        24
    6040: invokespecial #28                 // Method com/google/zxing/qrcode/decoder/Version$ECB."<init>":(II)V
    6043: aastore
    6044: dup
    6045: iconst_1
    6046: new           #27                 // class com/google/zxing/qrcode/decoder/Version$ECB
    6049: dup
    6050: iconst_1
    6051: bipush        25
    6053: invokespecial #28                 // Method com/google/zxing/qrcode/decoder/Version$ECB."<init>":(II)V
    6056: aastore
    6057: invokespecial #29                 // Method com/google/zxing/qrcode/decoder/Version$ECBlocks."<init>":(I[Lcom/google/zxing/qrcode/decoder/Version$ECB;)V
    6060: aastore
    6061: dup
    6062: iconst_3
    6063: new           #26                 // class com/google/zxing/qrcode/decoder/Version$ECBlocks
    6066: dup
    6067: bipush        30
    6069: iconst_2
    6070: anewarray     #27                 // class com/google/zxing/qrcode/decoder/Version$ECB
    6073: dup
    6074: iconst_0
    6075: new           #27                 // class com/google/zxing/qrcode/decoder/Version$ECB
    6078: dup
    6079: bipush        23
    6081: bipush        15
    6083: invokespecial #28                 // Method com/google/zxing/qrcode/decoder/Version$ECB."<init>":(II)V
    6086: aastore
    6087: dup
    6088: iconst_1
    6089: new           #27                 // class com/google/zxing/qrcode/decoder/Version$ECB
    6092: dup
    6093: bipush        28
    6095: bipush        16
    6097: invokespecial #28                 // Method com/google/zxing/qrcode/decoder/Version$ECB."<init>":(II)V
    6100: aastore
    6101: invokespecial #29                 // Method com/google/zxing/qrcode/decoder/Version$ECBlocks."<init>":(I[Lcom/google/zxing/qrcode/decoder/Version$ECB;)V
    6104: aastore
    6105: invokespecial #30                 // Method "<init>":(I[I[Lcom/google/zxing/qrcode/decoder/Version$ECBlocks;)V
    6108: aastore
    6109: dup
    6110: bipush        31
    6112: new           #25                 // class com/google/zxing/qrcode/decoder/Version
    6115: dup
    6116: bipush        32
    6118: bipush        6
    6120: newarray       int
    6122: dup
    6123: iconst_0
    6124: bipush        6
    6126: iastore
    6127: dup
    6128: iconst_1
    6129: bipush        34
    6131: iastore
    6132: dup
    6133: iconst_2
    6134: bipush        60
    6136: iastore
    6137: dup
    6138: iconst_3
    6139: bipush        86
    6141: iastore
    6142: dup
    6143: iconst_4
    6144: bipush        112
    6146: iastore
    6147: dup
    6148: iconst_5
    6149: sipush        138
    6152: iastore
    6153: iconst_4
    6154: anewarray     #26                 // class com/google/zxing/qrcode/decoder/Version$ECBlocks
    6157: dup
    6158: iconst_0
    6159: new           #26                 // class com/google/zxing/qrcode/decoder/Version$ECBlocks
    6162: dup
    6163: bipush        30
    6165: iconst_1
    6166: anewarray     #27                 // class com/google/zxing/qrcode/decoder/Version$ECB
    6169: dup
    6170: iconst_0
    6171: new           #27                 // class com/google/zxing/qrcode/decoder/Version$ECB
    6174: dup
    6175: bipush        17
    6177: bipush        115
    6179: invokespecial #28                 // Method com/google/zxing/qrcode/decoder/Version$ECB."<init>":(II)V
    6182: aastore
    6183: invokespecial #29                 // Method com/google/zxing/qrcode/decoder/Version$ECBlocks."<init>":(I[Lcom/google/zxing/qrcode/decoder/Version$ECB;)V
    6186: aastore
    6187: dup
    6188: iconst_1
    6189: new           #26                 // class com/google/zxing/qrcode/decoder/Version$ECBlocks
    6192: dup
    6193: bipush        28
    6195: iconst_2
    6196: anewarray     #27                 // class com/google/zxing/qrcode/decoder/Version$ECB
    6199: dup
    6200: iconst_0
    6201: new           #27                 // class com/google/zxing/qrcode/decoder/Version$ECB
    6204: dup
    6205: bipush        10
    6207: bipush        46
    6209: invokespecial #28                 // Method com/google/zxing/qrcode/decoder/Version$ECB."<init>":(II)V
    6212: aastore
    6213: dup
    6214: iconst_1
    6215: new           #27                 // class com/google/zxing/qrcode/decoder/Version$ECB
    6218: dup
    6219: bipush        23
    6221: bipush        47
    6223: invokespecial #28                 // Method com/google/zxing/qrcode/decoder/Version$ECB."<init>":(II)V
    6226: aastore
    6227: invokespecial #29                 // Method com/google/zxing/qrcode/decoder/Version$ECBlocks."<init>":(I[Lcom/google/zxing/qrcode/decoder/Version$ECB;)V
    6230: aastore
    6231: dup
    6232: iconst_2
    6233: new           #26                 // class com/google/zxing/qrcode/decoder/Version$ECBlocks
    6236: dup
    6237: bipush        30
    6239: iconst_2
    6240: anewarray     #27                 // class com/google/zxing/qrcode/decoder/Version$ECB
    6243: dup
    6244: iconst_0
    6245: new           #27                 // class com/google/zxing/qrcode/decoder/Version$ECB
    6248: dup
    6249: bipush        10
    6251: bipush        24
    6253: invokespecial #28                 // Method com/google/zxing/qrcode/decoder/Version$ECB."<init>":(II)V
    6256: aastore
    6257: dup
    6258: iconst_1
    6259: new           #27                 // class com/google/zxing/qrcode/decoder/Version$ECB
    6262: dup
    6263: bipush        35
    6265: bipush        25
    6267: invokespecial #28                 // Method com/google/zxing/qrcode/decoder/Version$ECB."<init>":(II)V
    6270: aastore
    6271: invokespecial #29                 // Method com/google/zxing/qrcode/decoder/Version$ECBlocks."<init>":(I[Lcom/google/zxing/qrcode/decoder/Version$ECB;)V
    6274: aastore
    6275: dup
    6276: iconst_3
    6277: new           #26                 // class com/google/zxing/qrcode/decoder/Version$ECBlocks
    6280: dup
    6281: bipush        30
    6283: iconst_2
    6284: anewarray     #27                 // class com/google/zxing/qrcode/decoder/Version$ECB
    6287: dup
    6288: iconst_0
    6289: new           #27                 // class com/google/zxing/qrcode/decoder/Version$ECB
    6292: dup
    6293: bipush        19
    6295: bipush        15
    6297: invokespecial #28                 // Method com/google/zxing/qrcode/decoder/Version$ECB."<init>":(II)V
    6300: aastore
    6301: dup
    6302: iconst_1
    6303: new           #27                 // class com/google/zxing/qrcode/decoder/Version$ECB
    6306: dup
    6307: bipush        35
    6309: bipush        16
    6311: invokespecial #28                 // Method com/google/zxing/qrcode/decoder/Version$ECB."<init>":(II)V
    6314: aastore
    6315: invokespecial #29                 // Method com/google/zxing/qrcode/decoder/Version$ECBlocks."<init>":(I[Lcom/google/zxing/qrcode/decoder/Version$ECB;)V
    6318: aastore
    6319: invokespecial #30                 // Method "<init>":(I[I[Lcom/google/zxing/qrcode/decoder/Version$ECBlocks;)V
    6322: aastore
    6323: dup
    6324: bipush        32
    6326: new           #25                 // class com/google/zxing/qrcode/decoder/Version
    6329: dup
    6330: bipush        33
    6332: bipush        6
    6334: newarray       int
    6336: dup
    6337: iconst_0
    6338: bipush        6
    6340: iastore
    6341: dup
    6342: iconst_1
    6343: bipush        30
    6345: iastore
    6346: dup
    6347: iconst_2
    6348: bipush        58
    6350: iastore
    6351: dup
    6352: iconst_3
    6353: bipush        86
    6355: iastore
    6356: dup
    6357: iconst_4
    6358: bipush        114
    6360: iastore
    6361: dup
    6362: iconst_5
    6363: sipush        142
    6366: iastore
    6367: iconst_4
    6368: anewarray     #26                 // class com/google/zxing/qrcode/decoder/Version$ECBlocks
    6371: dup
    6372: iconst_0
    6373: new           #26                 // class com/google/zxing/qrcode/decoder/Version$ECBlocks
    6376: dup
    6377: bipush        30
    6379: iconst_2
    6380: anewarray     #27                 // class com/google/zxing/qrcode/decoder/Version$ECB
    6383: dup
    6384: iconst_0
    6385: new           #27                 // class com/google/zxing/qrcode/decoder/Version$ECB
    6388: dup
    6389: bipush        17
    6391: bipush        115
    6393: invokespecial #28                 // Method com/google/zxing/qrcode/decoder/Version$ECB."<init>":(II)V
    6396: aastore
    6397: dup
    6398: iconst_1
    6399: new           #27                 // class com/google/zxing/qrcode/decoder/Version$ECB
    6402: dup
    6403: iconst_1
    6404: bipush        116
    6406: invokespecial #28                 // Method com/google/zxing/qrcode/decoder/Version$ECB."<init>":(II)V
    6409: aastore
    6410: invokespecial #29                 // Method com/google/zxing/qrcode/decoder/Version$ECBlocks."<init>":(I[Lcom/google/zxing/qrcode/decoder/Version$ECB;)V
    6413: aastore
    6414: dup
    6415: iconst_1
    6416: new           #26                 // class com/google/zxing/qrcode/decoder/Version$ECBlocks
    6419: dup
    6420: bipush        28
    6422: iconst_2
    6423: anewarray     #27                 // class com/google/zxing/qrcode/decoder/Version$ECB
    6426: dup
    6427: iconst_0
    6428: new           #27                 // class com/google/zxing/qrcode/decoder/Version$ECB
    6431: dup
    6432: bipush        14
    6434: bipush        46
    6436: invokespecial #28                 // Method com/google/zxing/qrcode/decoder/Version$ECB."<init>":(II)V
    6439: aastore
    6440: dup
    6441: iconst_1
    6442: new           #27                 // class com/google/zxing/qrcode/decoder/Version$ECB
    6445: dup
    6446: bipush        21
    6448: bipush        47
    6450: invokespecial #28                 // Method com/google/zxing/qrcode/decoder/Version$ECB."<init>":(II)V
    6453: aastore
    6454: invokespecial #29                 // Method com/google/zxing/qrcode/decoder/Version$ECBlocks."<init>":(I[Lcom/google/zxing/qrcode/decoder/Version$ECB;)V
    6457: aastore
    6458: dup
    6459: iconst_2
    6460: new           #26                 // class com/google/zxing/qrcode/decoder/Version$ECBlocks
    6463: dup
    6464: bipush        30
    6466: iconst_2
    6467: anewarray     #27                 // class com/google/zxing/qrcode/decoder/Version$ECB
    6470: dup
    6471: iconst_0
    6472: new           #27                 // class com/google/zxing/qrcode/decoder/Version$ECB
    6475: dup
    6476: bipush        29
    6478: bipush        24
    6480: invokespecial #28                 // Method com/google/zxing/qrcode/decoder/Version$ECB."<init>":(II)V
    6483: aastore
    6484: dup
    6485: iconst_1
    6486: new           #27                 // class com/google/zxing/qrcode/decoder/Version$ECB
    6489: dup
    6490: bipush        19
    6492: bipush        25
    6494: invokespecial #28                 // Method com/google/zxing/qrcode/decoder/Version$ECB."<init>":(II)V
    6497: aastore
    6498: invokespecial #29                 // Method com/google/zxing/qrcode/decoder/Version$ECBlocks."<init>":(I[Lcom/google/zxing/qrcode/decoder/Version$ECB;)V
    6501: aastore
    6502: dup
    6503: iconst_3
    6504: new           #26                 // class com/google/zxing/qrcode/decoder/Version$ECBlocks
    6507: dup
    6508: bipush        30
    6510: iconst_2
    6511: anewarray     #27                 // class com/google/zxing/qrcode/decoder/Version$ECB
    6514: dup
    6515: iconst_0
    6516: new           #27                 // class com/google/zxing/qrcode/decoder/Version$ECB
    6519: dup
    6520: bipush        11
    6522: bipush        15
    6524: invokespecial #28                 // Method com/google/zxing/qrcode/decoder/Version$ECB."<init>":(II)V
    6527: aastore
    6528: dup
    6529: iconst_1
    6530: new           #27                 // class com/google/zxing/qrcode/decoder/Version$ECB
    6533: dup
    6534: bipush        46
    6536: bipush        16
    6538: invokespecial #28                 // Method com/google/zxing/qrcode/decoder/Version$ECB."<init>":(II)V
    6541: aastore
    6542: invokespecial #29                 // Method com/google/zxing/qrcode/decoder/Version$ECBlocks."<init>":(I[Lcom/google/zxing/qrcode/decoder/Version$ECB;)V
    6545: aastore
    6546: invokespecial #30                 // Method "<init>":(I[I[Lcom/google/zxing/qrcode/decoder/Version$ECBlocks;)V
    6549: aastore
    6550: dup
    6551: bipush        33
    6553: new           #25                 // class com/google/zxing/qrcode/decoder/Version
    6556: dup
    6557: bipush        34
    6559: bipush        6
    6561: newarray       int
    6563: dup
    6564: iconst_0
    6565: bipush        6
    6567: iastore
    6568: dup
    6569: iconst_1
    6570: bipush        34
    6572: iastore
    6573: dup
    6574: iconst_2
    6575: bipush        62
    6577: iastore
    6578: dup
    6579: iconst_3
    6580: bipush        90
    6582: iastore
    6583: dup
    6584: iconst_4
    6585: bipush        118
    6587: iastore
    6588: dup
    6589: iconst_5
    6590: sipush        146
    6593: iastore
    6594: iconst_4
    6595: anewarray     #26                 // class com/google/zxing/qrcode/decoder/Version$ECBlocks
    6598: dup
    6599: iconst_0
    6600: new           #26                 // class com/google/zxing/qrcode/decoder/Version$ECBlocks
    6603: dup
    6604: bipush        30
    6606: iconst_2
    6607: anewarray     #27                 // class com/google/zxing/qrcode/decoder/Version$ECB
    6610: dup
    6611: iconst_0
    6612: new           #27                 // class com/google/zxing/qrcode/decoder/Version$ECB
    6615: dup
    6616: bipush        13
    6618: bipush        115
    6620: invokespecial #28                 // Method com/google/zxing/qrcode/decoder/Version$ECB."<init>":(II)V
    6623: aastore
    6624: dup
    6625: iconst_1
    6626: new           #27                 // class com/google/zxing/qrcode/decoder/Version$ECB
    6629: dup
    6630: bipush        6
    6632: bipush        116
    6634: invokespecial #28                 // Method com/google/zxing/qrcode/decoder/Version$ECB."<init>":(II)V
    6637: aastore
    6638: invokespecial #29                 // Method com/google/zxing/qrcode/decoder/Version$ECBlocks."<init>":(I[Lcom/google/zxing/qrcode/decoder/Version$ECB;)V
    6641: aastore
    6642: dup
    6643: iconst_1
    6644: new           #26                 // class com/google/zxing/qrcode/decoder/Version$ECBlocks
    6647: dup
    6648: bipush        28
    6650: iconst_2
    6651: anewarray     #27                 // class com/google/zxing/qrcode/decoder/Version$ECB
    6654: dup
    6655: iconst_0
    6656: new           #27                 // class com/google/zxing/qrcode/decoder/Version$ECB
    6659: dup
    6660: bipush        14
    6662: bipush        46
    6664: invokespecial #28                 // Method com/google/zxing/qrcode/decoder/Version$ECB."<init>":(II)V
    6667: aastore
    6668: dup
    6669: iconst_1
    6670: new           #27                 // class com/google/zxing/qrcode/decoder/Version$ECB
    6673: dup
    6674: bipush        23
    6676: bipush        47
    6678: invokespecial #28                 // Method com/google/zxing/qrcode/decoder/Version$ECB."<init>":(II)V
    6681: aastore
    6682: invokespecial #29                 // Method com/google/zxing/qrcode/decoder/Version$ECBlocks."<init>":(I[Lcom/google/zxing/qrcode/decoder/Version$ECB;)V
    6685: aastore
    6686: dup
    6687: iconst_2
    6688: new           #26                 // class com/google/zxing/qrcode/decoder/Version$ECBlocks
    6691: dup
    6692: bipush        30
    6694: iconst_2
    6695: anewarray     #27                 // class com/google/zxing/qrcode/decoder/Version$ECB
    6698: dup
    6699: iconst_0
    6700: new           #27                 // class com/google/zxing/qrcode/decoder/Version$ECB
    6703: dup
    6704: bipush        44
    6706: bipush        24
    6708: invokespecial #28                 // Method com/google/zxing/qrcode/decoder/Version$ECB."<init>":(II)V
    6711: aastore
    6712: dup
    6713: iconst_1
    6714: new           #27                 // class com/google/zxing/qrcode/decoder/Version$ECB
    6717: dup
    6718: bipush        7
    6720: bipush        25
    6722: invokespecial #28                 // Method com/google/zxing/qrcode/decoder/Version$ECB."<init>":(II)V
    6725: aastore
    6726: invokespecial #29                 // Method com/google/zxing/qrcode/decoder/Version$ECBlocks."<init>":(I[Lcom/google/zxing/qrcode/decoder/Version$ECB;)V
    6729: aastore
    6730: dup
    6731: iconst_3
    6732: new           #26                 // class com/google/zxing/qrcode/decoder/Version$ECBlocks
    6735: dup
    6736: bipush        30
    6738: iconst_2
    6739: anewarray     #27                 // class com/google/zxing/qrcode/decoder/Version$ECB
    6742: dup
    6743: iconst_0
    6744: new           #27                 // class com/google/zxing/qrcode/decoder/Version$ECB
    6747: dup
    6748: bipush        59
    6750: bipush        16
    6752: invokespecial #28                 // Method com/google/zxing/qrcode/decoder/Version$ECB."<init>":(II)V
    6755: aastore
    6756: dup
    6757: iconst_1
    6758: new           #27                 // class com/google/zxing/qrcode/decoder/Version$ECB
    6761: dup
    6762: iconst_1
    6763: bipush        17
    6765: invokespecial #28                 // Method com/google/zxing/qrcode/decoder/Version$ECB."<init>":(II)V
    6768: aastore
    6769: invokespecial #29                 // Method com/google/zxing/qrcode/decoder/Version$ECBlocks."<init>":(I[Lcom/google/zxing/qrcode/decoder/Version$ECB;)V
    6772: aastore
    6773: invokespecial #30                 // Method "<init>":(I[I[Lcom/google/zxing/qrcode/decoder/Version$ECBlocks;)V
    6776: aastore
    6777: dup
    6778: bipush        34
    6780: new           #25                 // class com/google/zxing/qrcode/decoder/Version
    6783: dup
    6784: bipush        35
    6786: bipush        7
    6788: newarray       int
    6790: dup
    6791: iconst_0
    6792: bipush        6
    6794: iastore
    6795: dup
    6796: iconst_1
    6797: bipush        30
    6799: iastore
    6800: dup
    6801: iconst_2
    6802: bipush        54
    6804: iastore
    6805: dup
    6806: iconst_3
    6807: bipush        78
    6809: iastore
    6810: dup
    6811: iconst_4
    6812: bipush        102
    6814: iastore
    6815: dup
    6816: iconst_5
    6817: bipush        126
    6819: iastore
    6820: dup
    6821: bipush        6
    6823: sipush        150
    6826: iastore
    6827: iconst_4
    6828: anewarray     #26                 // class com/google/zxing/qrcode/decoder/Version$ECBlocks
    6831: dup
    6832: iconst_0
    6833: new           #26                 // class com/google/zxing/qrcode/decoder/Version$ECBlocks
    6836: dup
    6837: bipush        30
    6839: iconst_2
    6840: anewarray     #27                 // class com/google/zxing/qrcode/decoder/Version$ECB
    6843: dup
    6844: iconst_0
    6845: new           #27                 // class com/google/zxing/qrcode/decoder/Version$ECB
    6848: dup
    6849: bipush        12
    6851: bipush        121
    6853: invokespecial #28                 // Method com/google/zxing/qrcode/decoder/Version$ECB."<init>":(II)V
    6856: aastore
    6857: dup
    6858: iconst_1
    6859: new           #27                 // class com/google/zxing/qrcode/decoder/Version$ECB
    6862: dup
    6863: bipush        7
    6865: bipush        122
    6867: invokespecial #28                 // Method com/google/zxing/qrcode/decoder/Version$ECB."<init>":(II)V
    6870: aastore
    6871: invokespecial #29                 // Method com/google/zxing/qrcode/decoder/Version$ECBlocks."<init>":(I[Lcom/google/zxing/qrcode/decoder/Version$ECB;)V
    6874: aastore
    6875: dup
    6876: iconst_1
    6877: new           #26                 // class com/google/zxing/qrcode/decoder/Version$ECBlocks
    6880: dup
    6881: bipush        28
    6883: iconst_2
    6884: anewarray     #27                 // class com/google/zxing/qrcode/decoder/Version$ECB
    6887: dup
    6888: iconst_0
    6889: new           #27                 // class com/google/zxing/qrcode/decoder/Version$ECB
    6892: dup
    6893: bipush        12
    6895: bipush        47
    6897: invokespecial #28                 // Method com/google/zxing/qrcode/decoder/Version$ECB."<init>":(II)V
    6900: aastore
    6901: dup
    6902: iconst_1
    6903: new           #27                 // class com/google/zxing/qrcode/decoder/Version$ECB
    6906: dup
    6907: bipush        26
    6909: bipush        48
    6911: invokespecial #28                 // Method com/google/zxing/qrcode/decoder/Version$ECB."<init>":(II)V
    6914: aastore
    6915: invokespecial #29                 // Method com/google/zxing/qrcode/decoder/Version$ECBlocks."<init>":(I[Lcom/google/zxing/qrcode/decoder/Version$ECB;)V
    6918: aastore
    6919: dup
    6920: iconst_2
    6921: new           #26                 // class com/google/zxing/qrcode/decoder/Version$ECBlocks
    6924: dup
    6925: bipush        30
    6927: iconst_2
    6928: anewarray     #27                 // class com/google/zxing/qrcode/decoder/Version$ECB
    6931: dup
    6932: iconst_0
    6933: new           #27                 // class com/google/zxing/qrcode/decoder/Version$ECB
    6936: dup
    6937: bipush        39
    6939: bipush        24
    6941: invokespecial #28                 // Method com/google/zxing/qrcode/decoder/Version$ECB."<init>":(II)V
    6944: aastore
    6945: dup
    6946: iconst_1
    6947: new           #27                 // class com/google/zxing/qrcode/decoder/Version$ECB
    6950: dup
    6951: bipush        14
    6953: bipush        25
    6955: invokespecial #28                 // Method com/google/zxing/qrcode/decoder/Version$ECB."<init>":(II)V
    6958: aastore
    6959: invokespecial #29                 // Method com/google/zxing/qrcode/decoder/Version$ECBlocks."<init>":(I[Lcom/google/zxing/qrcode/decoder/Version$ECB;)V
    6962: aastore
    6963: dup
    6964: iconst_3
    6965: new           #26                 // class com/google/zxing/qrcode/decoder/Version$ECBlocks
    6968: dup
    6969: bipush        30
    6971: iconst_2
    6972: anewarray     #27                 // class com/google/zxing/qrcode/decoder/Version$ECB
    6975: dup
    6976: iconst_0
    6977: new           #27                 // class com/google/zxing/qrcode/decoder/Version$ECB
    6980: dup
    6981: bipush        22
    6983: bipush        15
    6985: invokespecial #28                 // Method com/google/zxing/qrcode/decoder/Version$ECB."<init>":(II)V
    6988: aastore
    6989: dup
    6990: iconst_1
    6991: new           #27                 // class com/google/zxing/qrcode/decoder/Version$ECB
    6994: dup
    6995: bipush        41
    6997: bipush        16
    6999: invokespecial #28                 // Method com/google/zxing/qrcode/decoder/Version$ECB."<init>":(II)V
    7002: aastore
    7003: invokespecial #29                 // Method com/google/zxing/qrcode/decoder/Version$ECBlocks."<init>":(I[Lcom/google/zxing/qrcode/decoder/Version$ECB;)V
    7006: aastore
    7007: invokespecial #30                 // Method "<init>":(I[I[Lcom/google/zxing/qrcode/decoder/Version$ECBlocks;)V
    7010: aastore
    7011: dup
    7012: bipush        35
    7014: new           #25                 // class com/google/zxing/qrcode/decoder/Version
    7017: dup
    7018: bipush        36
    7020: bipush        7
    7022: newarray       int
    7024: dup
    7025: iconst_0
    7026: bipush        6
    7028: iastore
    7029: dup
    7030: iconst_1
    7031: bipush        24
    7033: iastore
    7034: dup
    7035: iconst_2
    7036: bipush        50
    7038: iastore
    7039: dup
    7040: iconst_3
    7041: bipush        76
    7043: iastore
    7044: dup
    7045: iconst_4
    7046: bipush        102
    7048: iastore
    7049: dup
    7050: iconst_5
    7051: sipush        128
    7054: iastore
    7055: dup
    7056: bipush        6
    7058: sipush        154
    7061: iastore
    7062: iconst_4
    7063: anewarray     #26                 // class com/google/zxing/qrcode/decoder/Version$ECBlocks
    7066: dup
    7067: iconst_0
    7068: new           #26                 // class com/google/zxing/qrcode/decoder/Version$ECBlocks
    7071: dup
    7072: bipush        30
    7074: iconst_2
    7075: anewarray     #27                 // class com/google/zxing/qrcode/decoder/Version$ECB
    7078: dup
    7079: iconst_0
    7080: new           #27                 // class com/google/zxing/qrcode/decoder/Version$ECB
    7083: dup
    7084: bipush        6
    7086: bipush        121
    7088: invokespecial #28                 // Method com/google/zxing/qrcode/decoder/Version$ECB."<init>":(II)V
    7091: aastore
    7092: dup
    7093: iconst_1
    7094: new           #27                 // class com/google/zxing/qrcode/decoder/Version$ECB
    7097: dup
    7098: bipush        14
    7100: bipush        122
    7102: invokespecial #28                 // Method com/google/zxing/qrcode/decoder/Version$ECB."<init>":(II)V
    7105: aastore
    7106: invokespecial #29                 // Method com/google/zxing/qrcode/decoder/Version$ECBlocks."<init>":(I[Lcom/google/zxing/qrcode/decoder/Version$ECB;)V
    7109: aastore
    7110: dup
    7111: iconst_1
    7112: new           #26                 // class com/google/zxing/qrcode/decoder/Version$ECBlocks
    7115: dup
    7116: bipush        28
    7118: iconst_2
    7119: anewarray     #27                 // class com/google/zxing/qrcode/decoder/Version$ECB
    7122: dup
    7123: iconst_0
    7124: new           #27                 // class com/google/zxing/qrcode/decoder/Version$ECB
    7127: dup
    7128: bipush        6
    7130: bipush        47
    7132: invokespecial #28                 // Method com/google/zxing/qrcode/decoder/Version$ECB."<init>":(II)V
    7135: aastore
    7136: dup
    7137: iconst_1
    7138: new           #27                 // class com/google/zxing/qrcode/decoder/Version$ECB
    7141: dup
    7142: bipush        34
    7144: bipush        48
    7146: invokespecial #28                 // Method com/google/zxing/qrcode/decoder/Version$ECB."<init>":(II)V
    7149: aastore
    7150: invokespecial #29                 // Method com/google/zxing/qrcode/decoder/Version$ECBlocks."<init>":(I[Lcom/google/zxing/qrcode/decoder/Version$ECB;)V
    7153: aastore
    7154: dup
    7155: iconst_2
    7156: new           #26                 // class com/google/zxing/qrcode/decoder/Version$ECBlocks
    7159: dup
    7160: bipush        30
    7162: iconst_2
    7163: anewarray     #27                 // class com/google/zxing/qrcode/decoder/Version$ECB
    7166: dup
    7167: iconst_0
    7168: new           #27                 // class com/google/zxing/qrcode/decoder/Version$ECB
    7171: dup
    7172: bipush        46
    7174: bipush        24
    7176: invokespecial #28                 // Method com/google/zxing/qrcode/decoder/Version$ECB."<init>":(II)V
    7179: aastore
    7180: dup
    7181: iconst_1
    7182: new           #27                 // class com/google/zxing/qrcode/decoder/Version$ECB
    7185: dup
    7186: bipush        10
    7188: bipush        25
    7190: invokespecial #28                 // Method com/google/zxing/qrcode/decoder/Version$ECB."<init>":(II)V
    7193: aastore
    7194: invokespecial #29                 // Method com/google/zxing/qrcode/decoder/Version$ECBlocks."<init>":(I[Lcom/google/zxing/qrcode/decoder/Version$ECB;)V
    7197: aastore
    7198: dup
    7199: iconst_3
    7200: new           #26                 // class com/google/zxing/qrcode/decoder/Version$ECBlocks
    7203: dup
    7204: bipush        30
    7206: iconst_2
    7207: anewarray     #27                 // class com/google/zxing/qrcode/decoder/Version$ECB
    7210: dup
    7211: iconst_0
    7212: new           #27                 // class com/google/zxing/qrcode/decoder/Version$ECB
    7215: dup
    7216: iconst_2
    7217: bipush        15
    7219: invokespecial #28                 // Method com/google/zxing/qrcode/decoder/Version$ECB."<init>":(II)V
    7222: aastore
    7223: dup
    7224: iconst_1
    7225: new           #27                 // class com/google/zxing/qrcode/decoder/Version$ECB
    7228: dup
    7229: bipush        64
    7231: bipush        16
    7233: invokespecial #28                 // Method com/google/zxing/qrcode/decoder/Version$ECB."<init>":(II)V
    7236: aastore
    7237: invokespecial #29                 // Method com/google/zxing/qrcode/decoder/Version$ECBlocks."<init>":(I[Lcom/google/zxing/qrcode/decoder/Version$ECB;)V
    7240: aastore
    7241: invokespecial #30                 // Method "<init>":(I[I[Lcom/google/zxing/qrcode/decoder/Version$ECBlocks;)V
    7244: aastore
    7245: dup
    7246: bipush        36
    7248: new           #25                 // class com/google/zxing/qrcode/decoder/Version
    7251: dup
    7252: bipush        37
    7254: bipush        7
    7256: newarray       int
    7258: dup
    7259: iconst_0
    7260: bipush        6
    7262: iastore
    7263: dup
    7264: iconst_1
    7265: bipush        28
    7267: iastore
    7268: dup
    7269: iconst_2
    7270: bipush        54
    7272: iastore
    7273: dup
    7274: iconst_3
    7275: bipush        80
    7277: iastore
    7278: dup
    7279: iconst_4
    7280: bipush        106
    7282: iastore
    7283: dup
    7284: iconst_5
    7285: sipush        132
    7288: iastore
    7289: dup
    7290: bipush        6
    7292: sipush        158
    7295: iastore
    7296: iconst_4
    7297: anewarray     #26                 // class com/google/zxing/qrcode/decoder/Version$ECBlocks
    7300: dup
    7301: iconst_0
    7302: new           #26                 // class com/google/zxing/qrcode/decoder/Version$ECBlocks
    7305: dup
    7306: bipush        30
    7308: iconst_2
    7309: anewarray     #27                 // class com/google/zxing/qrcode/decoder/Version$ECB
    7312: dup
    7313: iconst_0
    7314: new           #27                 // class com/google/zxing/qrcode/decoder/Version$ECB
    7317: dup
    7318: bipush        17
    7320: bipush        122
    7322: invokespecial #28                 // Method com/google/zxing/qrcode/decoder/Version$ECB."<init>":(II)V
    7325: aastore
    7326: dup
    7327: iconst_1
    7328: new           #27                 // class com/google/zxing/qrcode/decoder/Version$ECB
    7331: dup
    7332: iconst_4
    7333: bipush        123
    7335: invokespecial #28                 // Method com/google/zxing/qrcode/decoder/Version$ECB."<init>":(II)V
    7338: aastore
    7339: invokespecial #29                 // Method com/google/zxing/qrcode/decoder/Version$ECBlocks."<init>":(I[Lcom/google/zxing/qrcode/decoder/Version$ECB;)V
    7342: aastore
    7343: dup
    7344: iconst_1
    7345: new           #26                 // class com/google/zxing/qrcode/decoder/Version$ECBlocks
    7348: dup
    7349: bipush        28
    7351: iconst_2
    7352: anewarray     #27                 // class com/google/zxing/qrcode/decoder/Version$ECB
    7355: dup
    7356: iconst_0
    7357: new           #27                 // class com/google/zxing/qrcode/decoder/Version$ECB
    7360: dup
    7361: bipush        29
    7363: bipush        46
    7365: invokespecial #28                 // Method com/google/zxing/qrcode/decoder/Version$ECB."<init>":(II)V
    7368: aastore
    7369: dup
    7370: iconst_1
    7371: new           #27                 // class com/google/zxing/qrcode/decoder/Version$ECB
    7374: dup
    7375: bipush        14
    7377: bipush        47
    7379: invokespecial #28                 // Method com/google/zxing/qrcode/decoder/Version$ECB."<init>":(II)V
    7382: aastore
    7383: invokespecial #29                 // Method com/google/zxing/qrcode/decoder/Version$ECBlocks."<init>":(I[Lcom/google/zxing/qrcode/decoder/Version$ECB;)V
    7386: aastore
    7387: dup
    7388: iconst_2
    7389: new           #26                 // class com/google/zxing/qrcode/decoder/Version$ECBlocks
    7392: dup
    7393: bipush        30
    7395: iconst_2
    7396: anewarray     #27                 // class com/google/zxing/qrcode/decoder/Version$ECB
    7399: dup
    7400: iconst_0
    7401: new           #27                 // class com/google/zxing/qrcode/decoder/Version$ECB
    7404: dup
    7405: bipush        49
    7407: bipush        24
    7409: invokespecial #28                 // Method com/google/zxing/qrcode/decoder/Version$ECB."<init>":(II)V
    7412: aastore
    7413: dup
    7414: iconst_1
    7415: new           #27                 // class com/google/zxing/qrcode/decoder/Version$ECB
    7418: dup
    7419: bipush        10
    7421: bipush        25
    7423: invokespecial #28                 // Method com/google/zxing/qrcode/decoder/Version$ECB."<init>":(II)V
    7426: aastore
    7427: invokespecial #29                 // Method com/google/zxing/qrcode/decoder/Version$ECBlocks."<init>":(I[Lcom/google/zxing/qrcode/decoder/Version$ECB;)V
    7430: aastore
    7431: dup
    7432: iconst_3
    7433: new           #26                 // class com/google/zxing/qrcode/decoder/Version$ECBlocks
    7436: dup
    7437: bipush        30
    7439: iconst_2
    7440: anewarray     #27                 // class com/google/zxing/qrcode/decoder/Version$ECB
    7443: dup
    7444: iconst_0
    7445: new           #27                 // class com/google/zxing/qrcode/decoder/Version$ECB
    7448: dup
    7449: bipush        24
    7451: bipush        15
    7453: invokespecial #28                 // Method com/google/zxing/qrcode/decoder/Version$ECB."<init>":(II)V
    7456: aastore
    7457: dup
    7458: iconst_1
    7459: new           #27                 // class com/google/zxing/qrcode/decoder/Version$ECB
    7462: dup
    7463: bipush        46
    7465: bipush        16
    7467: invokespecial #28                 // Method com/google/zxing/qrcode/decoder/Version$ECB."<init>":(II)V
    7470: aastore
    7471: invokespecial #29                 // Method com/google/zxing/qrcode/decoder/Version$ECBlocks."<init>":(I[Lcom/google/zxing/qrcode/decoder/Version$ECB;)V
    7474: aastore
    7475: invokespecial #30                 // Method "<init>":(I[I[Lcom/google/zxing/qrcode/decoder/Version$ECBlocks;)V
    7478: aastore
    7479: dup
    7480: bipush        37
    7482: new           #25                 // class com/google/zxing/qrcode/decoder/Version
    7485: dup
    7486: bipush        38
    7488: bipush        7
    7490: newarray       int
    7492: dup
    7493: iconst_0
    7494: bipush        6
    7496: iastore
    7497: dup
    7498: iconst_1
    7499: bipush        32
    7501: iastore
    7502: dup
    7503: iconst_2
    7504: bipush        58
    7506: iastore
    7507: dup
    7508: iconst_3
    7509: bipush        84
    7511: iastore
    7512: dup
    7513: iconst_4
    7514: bipush        110
    7516: iastore
    7517: dup
    7518: iconst_5
    7519: sipush        136
    7522: iastore
    7523: dup
    7524: bipush        6
    7526: sipush        162
    7529: iastore
    7530: iconst_4
    7531: anewarray     #26                 // class com/google/zxing/qrcode/decoder/Version$ECBlocks
    7534: dup
    7535: iconst_0
    7536: new           #26                 // class com/google/zxing/qrcode/decoder/Version$ECBlocks
    7539: dup
    7540: bipush        30
    7542: iconst_2
    7543: anewarray     #27                 // class com/google/zxing/qrcode/decoder/Version$ECB
    7546: dup
    7547: iconst_0
    7548: new           #27                 // class com/google/zxing/qrcode/decoder/Version$ECB
    7551: dup
    7552: iconst_4
    7553: bipush        122
    7555: invokespecial #28                 // Method com/google/zxing/qrcode/decoder/Version$ECB."<init>":(II)V
    7558: aastore
    7559: dup
    7560: iconst_1
    7561: new           #27                 // class com/google/zxing/qrcode/decoder/Version$ECB
    7564: dup
    7565: bipush        18
    7567: bipush        123
    7569: invokespecial #28                 // Method com/google/zxing/qrcode/decoder/Version$ECB."<init>":(II)V
    7572: aastore
    7573: invokespecial #29                 // Method com/google/zxing/qrcode/decoder/Version$ECBlocks."<init>":(I[Lcom/google/zxing/qrcode/decoder/Version$ECB;)V
    7576: aastore
    7577: dup
    7578: iconst_1
    7579: new           #26                 // class com/google/zxing/qrcode/decoder/Version$ECBlocks
    7582: dup
    7583: bipush        28
    7585: iconst_2
    7586: anewarray     #27                 // class com/google/zxing/qrcode/decoder/Version$ECB
    7589: dup
    7590: iconst_0
    7591: new           #27                 // class com/google/zxing/qrcode/decoder/Version$ECB
    7594: dup
    7595: bipush        13
    7597: bipush        46
    7599: invokespecial #28                 // Method com/google/zxing/qrcode/decoder/Version$ECB."<init>":(II)V
    7602: aastore
    7603: dup
    7604: iconst_1
    7605: new           #27                 // class com/google/zxing/qrcode/decoder/Version$ECB
    7608: dup
    7609: bipush        32
    7611: bipush        47
    7613: invokespecial #28                 // Method com/google/zxing/qrcode/decoder/Version$ECB."<init>":(II)V
    7616: aastore
    7617: invokespecial #29                 // Method com/google/zxing/qrcode/decoder/Version$ECBlocks."<init>":(I[Lcom/google/zxing/qrcode/decoder/Version$ECB;)V
    7620: aastore
    7621: dup
    7622: iconst_2
    7623: new           #26                 // class com/google/zxing/qrcode/decoder/Version$ECBlocks
    7626: dup
    7627: bipush        30
    7629: iconst_2
    7630: anewarray     #27                 // class com/google/zxing/qrcode/decoder/Version$ECB
    7633: dup
    7634: iconst_0
    7635: new           #27                 // class com/google/zxing/qrcode/decoder/Version$ECB
    7638: dup
    7639: bipush        48
    7641: bipush        24
    7643: invokespecial #28                 // Method com/google/zxing/qrcode/decoder/Version$ECB."<init>":(II)V
    7646: aastore
    7647: dup
    7648: iconst_1
    7649: new           #27                 // class com/google/zxing/qrcode/decoder/Version$ECB
    7652: dup
    7653: bipush        14
    7655: bipush        25
    7657: invokespecial #28                 // Method com/google/zxing/qrcode/decoder/Version$ECB."<init>":(II)V
    7660: aastore
    7661: invokespecial #29                 // Method com/google/zxing/qrcode/decoder/Version$ECBlocks."<init>":(I[Lcom/google/zxing/qrcode/decoder/Version$ECB;)V
    7664: aastore
    7665: dup
    7666: iconst_3
    7667: new           #26                 // class com/google/zxing/qrcode/decoder/Version$ECBlocks
    7670: dup
    7671: bipush        30
    7673: iconst_2
    7674: anewarray     #27                 // class com/google/zxing/qrcode/decoder/Version$ECB
    7677: dup
    7678: iconst_0
    7679: new           #27                 // class com/google/zxing/qrcode/decoder/Version$ECB
    7682: dup
    7683: bipush        42
    7685: bipush        15
    7687: invokespecial #28                 // Method com/google/zxing/qrcode/decoder/Version$ECB."<init>":(II)V
    7690: aastore
    7691: dup
    7692: iconst_1
    7693: new           #27                 // class com/google/zxing/qrcode/decoder/Version$ECB
    7696: dup
    7697: bipush        32
    7699: bipush        16
    7701: invokespecial #28                 // Method com/google/zxing/qrcode/decoder/Version$ECB."<init>":(II)V
    7704: aastore
    7705: invokespecial #29                 // Method com/google/zxing/qrcode/decoder/Version$ECBlocks."<init>":(I[Lcom/google/zxing/qrcode/decoder/Version$ECB;)V
    7708: aastore
    7709: invokespecial #30                 // Method "<init>":(I[I[Lcom/google/zxing/qrcode/decoder/Version$ECBlocks;)V
    7712: aastore
    7713: dup
    7714: bipush        38
    7716: new           #25                 // class com/google/zxing/qrcode/decoder/Version
    7719: dup
    7720: bipush        39
    7722: bipush        7
    7724: newarray       int
    7726: dup
    7727: iconst_0
    7728: bipush        6
    7730: iastore
    7731: dup
    7732: iconst_1
    7733: bipush        26
    7735: iastore
    7736: dup
    7737: iconst_2
    7738: bipush        54
    7740: iastore
    7741: dup
    7742: iconst_3
    7743: bipush        82
    7745: iastore
    7746: dup
    7747: iconst_4
    7748: bipush        110
    7750: iastore
    7751: dup
    7752: iconst_5
    7753: sipush        138
    7756: iastore
    7757: dup
    7758: bipush        6
    7760: sipush        166
    7763: iastore
    7764: iconst_4
    7765: anewarray     #26                 // class com/google/zxing/qrcode/decoder/Version$ECBlocks
    7768: dup
    7769: iconst_0
    7770: new           #26                 // class com/google/zxing/qrcode/decoder/Version$ECBlocks
    7773: dup
    7774: bipush        30
    7776: iconst_2
    7777: anewarray     #27                 // class com/google/zxing/qrcode/decoder/Version$ECB
    7780: dup
    7781: iconst_0
    7782: new           #27                 // class com/google/zxing/qrcode/decoder/Version$ECB
    7785: dup
    7786: bipush        20
    7788: bipush        117
    7790: invokespecial #28                 // Method com/google/zxing/qrcode/decoder/Version$ECB."<init>":(II)V
    7793: aastore
    7794: dup
    7795: iconst_1
    7796: new           #27                 // class com/google/zxing/qrcode/decoder/Version$ECB
    7799: dup
    7800: iconst_4
    7801: bipush        118
    7803: invokespecial #28                 // Method com/google/zxing/qrcode/decoder/Version$ECB."<init>":(II)V
    7806: aastore
    7807: invokespecial #29                 // Method com/google/zxing/qrcode/decoder/Version$ECBlocks."<init>":(I[Lcom/google/zxing/qrcode/decoder/Version$ECB;)V
    7810: aastore
    7811: dup
    7812: iconst_1
    7813: new           #26                 // class com/google/zxing/qrcode/decoder/Version$ECBlocks
    7816: dup
    7817: bipush        28
    7819: iconst_2
    7820: anewarray     #27                 // class com/google/zxing/qrcode/decoder/Version$ECB
    7823: dup
    7824: iconst_0
    7825: new           #27                 // class com/google/zxing/qrcode/decoder/Version$ECB
    7828: dup
    7829: bipush        40
    7831: bipush        47
    7833: invokespecial #28                 // Method com/google/zxing/qrcode/decoder/Version$ECB."<init>":(II)V
    7836: aastore
    7837: dup
    7838: iconst_1
    7839: new           #27                 // class com/google/zxing/qrcode/decoder/Version$ECB
    7842: dup
    7843: bipush        7
    7845: bipush        48
    7847: invokespecial #28                 // Method com/google/zxing/qrcode/decoder/Version$ECB."<init>":(II)V
    7850: aastore
    7851: invokespecial #29                 // Method com/google/zxing/qrcode/decoder/Version$ECBlocks."<init>":(I[Lcom/google/zxing/qrcode/decoder/Version$ECB;)V
    7854: aastore
    7855: dup
    7856: iconst_2
    7857: new           #26                 // class com/google/zxing/qrcode/decoder/Version$ECBlocks
    7860: dup
    7861: bipush        30
    7863: iconst_2
    7864: anewarray     #27                 // class com/google/zxing/qrcode/decoder/Version$ECB
    7867: dup
    7868: iconst_0
    7869: new           #27                 // class com/google/zxing/qrcode/decoder/Version$ECB
    7872: dup
    7873: bipush        43
    7875: bipush        24
    7877: invokespecial #28                 // Method com/google/zxing/qrcode/decoder/Version$ECB."<init>":(II)V
    7880: aastore
    7881: dup
    7882: iconst_1
    7883: new           #27                 // class com/google/zxing/qrcode/decoder/Version$ECB
    7886: dup
    7887: bipush        22
    7889: bipush        25
    7891: invokespecial #28                 // Method com/google/zxing/qrcode/decoder/Version$ECB."<init>":(II)V
    7894: aastore
    7895: invokespecial #29                 // Method com/google/zxing/qrcode/decoder/Version$ECBlocks."<init>":(I[Lcom/google/zxing/qrcode/decoder/Version$ECB;)V
    7898: aastore
    7899: dup
    7900: iconst_3
    7901: new           #26                 // class com/google/zxing/qrcode/decoder/Version$ECBlocks
    7904: dup
    7905: bipush        30
    7907: iconst_2
    7908: anewarray     #27                 // class com/google/zxing/qrcode/decoder/Version$ECB
    7911: dup
    7912: iconst_0
    7913: new           #27                 // class com/google/zxing/qrcode/decoder/Version$ECB
    7916: dup
    7917: bipush        10
    7919: bipush        15
    7921: invokespecial #28                 // Method com/google/zxing/qrcode/decoder/Version$ECB."<init>":(II)V
    7924: aastore
    7925: dup
    7926: iconst_1
    7927: new           #27                 // class com/google/zxing/qrcode/decoder/Version$ECB
    7930: dup
    7931: bipush        67
    7933: bipush        16
    7935: invokespecial #28                 // Method com/google/zxing/qrcode/decoder/Version$ECB."<init>":(II)V
    7938: aastore
    7939: invokespecial #29                 // Method com/google/zxing/qrcode/decoder/Version$ECBlocks."<init>":(I[Lcom/google/zxing/qrcode/decoder/Version$ECB;)V
    7942: aastore
    7943: invokespecial #30                 // Method "<init>":(I[I[Lcom/google/zxing/qrcode/decoder/Version$ECBlocks;)V
    7946: aastore
    7947: dup
    7948: bipush        39
    7950: new           #25                 // class com/google/zxing/qrcode/decoder/Version
    7953: dup
    7954: bipush        40
    7956: bipush        7
    7958: newarray       int
    7960: dup
    7961: iconst_0
    7962: bipush        6
    7964: iastore
    7965: dup
    7966: iconst_1
    7967: bipush        30
    7969: iastore
    7970: dup
    7971: iconst_2
    7972: bipush        58
    7974: iastore
    7975: dup
    7976: iconst_3
    7977: bipush        86
    7979: iastore
    7980: dup
    7981: iconst_4
    7982: bipush        114
    7984: iastore
    7985: dup
    7986: iconst_5
    7987: sipush        142
    7990: iastore
    7991: dup
    7992: bipush        6
    7994: sipush        170
    7997: iastore
    7998: iconst_4
    7999: anewarray     #26                 // class com/google/zxing/qrcode/decoder/Version$ECBlocks
    8002: dup
    8003: iconst_0
    8004: new           #26                 // class com/google/zxing/qrcode/decoder/Version$ECBlocks
    8007: dup
    8008: bipush        30
    8010: iconst_2
    8011: anewarray     #27                 // class com/google/zxing/qrcode/decoder/Version$ECB
    8014: dup
    8015: iconst_0
    8016: new           #27                 // class com/google/zxing/qrcode/decoder/Version$ECB
    8019: dup
    8020: bipush        19
    8022: bipush        118
    8024: invokespecial #28                 // Method com/google/zxing/qrcode/decoder/Version$ECB."<init>":(II)V
    8027: aastore
    8028: dup
    8029: iconst_1
    8030: new           #27                 // class com/google/zxing/qrcode/decoder/Version$ECB
    8033: dup
    8034: bipush        6
    8036: bipush        119
    8038: invokespecial #28                 // Method com/google/zxing/qrcode/decoder/Version$ECB."<init>":(II)V
    8041: aastore
    8042: invokespecial #29                 // Method com/google/zxing/qrcode/decoder/Version$ECBlocks."<init>":(I[Lcom/google/zxing/qrcode/decoder/Version$ECB;)V
    8045: aastore
    8046: dup
    8047: iconst_1
    8048: new           #26                 // class com/google/zxing/qrcode/decoder/Version$ECBlocks
    8051: dup
    8052: bipush        28
    8054: iconst_2
    8055: anewarray     #27                 // class com/google/zxing/qrcode/decoder/Version$ECB
    8058: dup
    8059: iconst_0
    8060: new           #27                 // class com/google/zxing/qrcode/decoder/Version$ECB
    8063: dup
    8064: bipush        18
    8066: bipush        47
    8068: invokespecial #28                 // Method com/google/zxing/qrcode/decoder/Version$ECB."<init>":(II)V
    8071: aastore
    8072: dup
    8073: iconst_1
    8074: new           #27                 // class com/google/zxing/qrcode/decoder/Version$ECB
    8077: dup
    8078: bipush        31
    8080: bipush        48
    8082: invokespecial #28                 // Method com/google/zxing/qrcode/decoder/Version$ECB."<init>":(II)V
    8085: aastore
    8086: invokespecial #29                 // Method com/google/zxing/qrcode/decoder/Version$ECBlocks."<init>":(I[Lcom/google/zxing/qrcode/decoder/Version$ECB;)V
    8089: aastore
    8090: dup
    8091: iconst_2
    8092: new           #26                 // class com/google/zxing/qrcode/decoder/Version$ECBlocks
    8095: dup
    8096: bipush        30
    8098: iconst_2
    8099: anewarray     #27                 // class com/google/zxing/qrcode/decoder/Version$ECB
    8102: dup
    8103: iconst_0
    8104: new           #27                 // class com/google/zxing/qrcode/decoder/Version$ECB
    8107: dup
    8108: bipush        34
    8110: bipush        24
    8112: invokespecial #28                 // Method com/google/zxing/qrcode/decoder/Version$ECB."<init>":(II)V
    8115: aastore
    8116: dup
    8117: iconst_1
    8118: new           #27                 // class com/google/zxing/qrcode/decoder/Version$ECB
    8121: dup
    8122: bipush        34
    8124: bipush        25
    8126: invokespecial #28                 // Method com/google/zxing/qrcode/decoder/Version$ECB."<init>":(II)V
    8129: aastore
    8130: invokespecial #29                 // Method com/google/zxing/qrcode/decoder/Version$ECBlocks."<init>":(I[Lcom/google/zxing/qrcode/decoder/Version$ECB;)V
    8133: aastore
    8134: dup
    8135: iconst_3
    8136: new           #26                 // class com/google/zxing/qrcode/decoder/Version$ECBlocks
    8139: dup
    8140: bipush        30
    8142: iconst_2
    8143: anewarray     #27                 // class com/google/zxing/qrcode/decoder/Version$ECB
    8146: dup
    8147: iconst_0
    8148: new           #27                 // class com/google/zxing/qrcode/decoder/Version$ECB
    8151: dup
    8152: bipush        20
    8154: bipush        15
    8156: invokespecial #28                 // Method com/google/zxing/qrcode/decoder/Version$ECB."<init>":(II)V
    8159: aastore
    8160: dup
    8161: iconst_1
    8162: new           #27                 // class com/google/zxing/qrcode/decoder/Version$ECB
    8165: dup
    8166: bipush        61
    8168: bipush        16
    8170: invokespecial #28                 // Method com/google/zxing/qrcode/decoder/Version$ECB."<init>":(II)V
    8173: aastore
    8174: invokespecial #29                 // Method com/google/zxing/qrcode/decoder/Version$ECBlocks."<init>":(I[Lcom/google/zxing/qrcode/decoder/Version$ECB;)V
    8177: aastore
    8178: invokespecial #30                 // Method "<init>":(I[I[Lcom/google/zxing/qrcode/decoder/Version$ECBlocks;)V
    8181: aastore
    8182: areturn

  static {};
    Code:
       0: bipush        34
       2: newarray       int
       4: dup
       5: iconst_0
       6: sipush        31892
       9: iastore
      10: dup
      11: iconst_1
      12: ldc           #31                 // int 34236
      14: iastore
      15: dup
      16: iconst_2
      17: ldc           #32                 // int 39577
      19: iastore
      20: dup
      21: iconst_3
      22: ldc           #33                 // int 42195
      24: iastore
      25: dup
      26: iconst_4
      27: ldc           #34                 // int 48118
      29: iastore
      30: dup
      31: iconst_5
      32: ldc           #35                 // int 51042
      34: iastore
      35: dup
      36: bipush        6
      38: ldc           #36                 // int 55367
      40: iastore
      41: dup
      42: bipush        7
      44: ldc           #37                 // int 58893
      46: iastore
      47: dup
      48: bipush        8
      50: ldc           #38                 // int 63784
      52: iastore
      53: dup
      54: bipush        9
      56: ldc           #39                 // int 68472
      58: iastore
      59: dup
      60: bipush        10
      62: ldc           #40                 // int 70749
      64: iastore
      65: dup
      66: bipush        11
      68: ldc           #41                 // int 76311
      70: iastore
      71: dup
      72: bipush        12
      74: ldc           #42                 // int 79154
      76: iastore
      77: dup
      78: bipush        13
      80: ldc           #43                 // int 84390
      82: iastore
      83: dup
      84: bipush        14
      86: ldc           #44                 // int 87683
      88: iastore
      89: dup
      90: bipush        15
      92: ldc           #45                 // int 92361
      94: iastore
      95: dup
      96: bipush        16
      98: ldc           #46                 // int 96236
     100: iastore
     101: dup
     102: bipush        17
     104: ldc           #47                 // int 102084
     106: iastore
     107: dup
     108: bipush        18
     110: ldc           #48                 // int 102881
     112: iastore
     113: dup
     114: bipush        19
     116: ldc           #49                 // int 110507
     118: iastore
     119: dup
     120: bipush        20
     122: ldc           #50                 // int 110734
     124: iastore
     125: dup
     126: bipush        21
     128: ldc           #51                 // int 117786
     130: iastore
     131: dup
     132: bipush        22
     134: ldc           #52                 // int 119615
     136: iastore
     137: dup
     138: bipush        23
     140: ldc           #53                 // int 126325
     142: iastore
     143: dup
     144: bipush        24
     146: ldc           #54                 // int 127568
     148: iastore
     149: dup
     150: bipush        25
     152: ldc           #55                 // int 133589
     154: iastore
     155: dup
     156: bipush        26
     158: ldc           #56                 // int 136944
     160: iastore
     161: dup
     162: bipush        27
     164: ldc           #57                 // int 141498
     166: iastore
     167: dup
     168: bipush        28
     170: ldc           #58                 // int 145311
     172: iastore
     173: dup
     174: bipush        29
     176: ldc           #59                 // int 150283
     178: iastore
     179: dup
     180: bipush        30
     182: ldc           #60                 // int 152622
     184: iastore
     185: dup
     186: bipush        31
     188: ldc           #61                 // int 158308
     190: iastore
     191: dup
     192: bipush        32
     194: ldc           #62                 // int 161089
     196: iastore
     197: dup
     198: bipush        33
     200: ldc           #63                 // int 167017
     202: iastore
     203: putstatic     #18                 // Field VERSION_DECODE_INFO:[I
     206: invokestatic  #64                 // Method buildVersions:()[Lcom/google/zxing/qrcode/decoder/Version;
     209: putstatic     #15                 // Field VERSIONS:[Lcom/google/zxing/qrcode/decoder/Version;
     212: return
}
