Compiled from "HikariDataSourcePoolMetadata.java"
public class org.springframework.boot.jdbc.metadata.HikariDataSourcePoolMetadata extends org.springframework.boot.jdbc.metadata.AbstractDataSourcePoolMetadata<com.zaxxer.hikari.HikariDataSource> {
  public org.springframework.boot.jdbc.metadata.HikariDataSourcePoolMetadata(com.zaxxer.hikari.HikariDataSource);
    Code:
       0: aload_0
       1: aload_1
       2: invokespecial #1                  // Method org/springframework/boot/jdbc/metadata/AbstractDataSourcePoolMetadata."<init>":(Ljavax/sql/DataSource;)V
       5: return

  public java.lang.Integer getActive();
    Code:
       0: aload_0
       1: invokevirtual #7                  // Method getHikariPool:()Lcom/zaxxer/hikari/pool/HikariPool;
       4: invokevirtual #13                 // Method com/zaxxer/hikari/pool/HikariPool.getActiveConnections:()I
       7: invokestatic  #19                 // Method java/lang/Integer.valueOf:(I)Ljava/lang/Integer;
      10: areturn
      11: astore_1
      12: aconst_null
      13: areturn
    Exception table:
       from    to  target type
           0    10    11   Class java/lang/Exception

  public java.lang.Integer getIdle();
    Code:
       0: aload_0
       1: invokevirtual #7                  // Method getHikariPool:()Lcom/zaxxer/hikari/pool/HikariPool;
       4: invokevirtual #27                 // Method com/zaxxer/hikari/pool/HikariPool.getIdleConnections:()I
       7: invokestatic  #19                 // Method java/lang/Integer.valueOf:(I)Ljava/lang/Integer;
      10: areturn
      11: astore_1
      12: aconst_null
      13: areturn
    Exception table:
       from    to  target type
           0    10    11   Class java/lang/Exception

  private com.zaxxer.hikari.pool.HikariPool getHikariPool();
    Code:
       0: new           #30                 // class org/springframework/beans/DirectFieldAccessor
       3: dup
       4: aload_0
       5: invokevirtual #32                 // Method getDataSource:()Ljavax/sql/DataSource;
       8: invokespecial #36                 // Method org/springframework/beans/DirectFieldAccessor."<init>":(Ljava/lang/Object;)V
      11: ldc           #39                 // String pool
      13: invokevirtual #41                 // Method org/springframework/beans/DirectFieldAccessor.getPropertyValue:(Ljava/lang/String;)Ljava/lang/Object;
      16: checkcast     #14                 // class com/zaxxer/hikari/pool/HikariPool
      19: areturn

  public java.lang.Integer getMax();
    Code:
       0: aload_0
       1: invokevirtual #32                 // Method getDataSource:()Ljavax/sql/DataSource;
       4: checkcast     #45                 // class com/zaxxer/hikari/HikariDataSource
       7: invokevirtual #47                 // Method com/zaxxer/hikari/HikariDataSource.getMaximumPoolSize:()I
      10: invokestatic  #19                 // Method java/lang/Integer.valueOf:(I)Ljava/lang/Integer;
      13: areturn

  public java.lang.Integer getMin();
    Code:
       0: aload_0
       1: invokevirtual #32                 // Method getDataSource:()Ljavax/sql/DataSource;
       4: checkcast     #45                 // class com/zaxxer/hikari/HikariDataSource
       7: invokevirtual #50                 // Method com/zaxxer/hikari/HikariDataSource.getMinimumIdle:()I
      10: invokestatic  #19                 // Method java/lang/Integer.valueOf:(I)Ljava/lang/Integer;
      13: areturn

  public java.lang.String getValidationQuery();
    Code:
       0: aload_0
       1: invokevirtual #32                 // Method getDataSource:()Ljavax/sql/DataSource;
       4: checkcast     #45                 // class com/zaxxer/hikari/HikariDataSource
       7: invokevirtual #53                 // Method com/zaxxer/hikari/HikariDataSource.getConnectionTestQuery:()Ljava/lang/String;
      10: areturn

  public java.lang.Boolean getDefaultAutoCommit();
    Code:
       0: aload_0
       1: invokevirtual #32                 // Method getDataSource:()Ljavax/sql/DataSource;
       4: checkcast     #45                 // class com/zaxxer/hikari/HikariDataSource
       7: invokevirtual #57                 // Method com/zaxxer/hikari/HikariDataSource.isAutoCommit:()Z
      10: invokestatic  #61                 // Method java/lang/Boolean.valueOf:(Z)Ljava/lang/Boolean;
      13: areturn
}
