Compiled from "OracleUcpDataSourcePoolMetadata.java"
public class org.springframework.boot.jdbc.metadata.OracleUcpDataSourcePoolMetadata extends org.springframework.boot.jdbc.metadata.AbstractDataSourcePoolMetadata<oracle.ucp.jdbc.PoolDataSource> {
  public org.springframework.boot.jdbc.metadata.OracleUcpDataSourcePoolMetadata(oracle.ucp.jdbc.PoolDataSource);
    Code:
       0: aload_0
       1: aload_1
       2: invokespecial #1                  // Method org/springframework/boot/jdbc/metadata/AbstractDataSourcePoolMetadata."<init>":(Ljavax/sql/DataSource;)V
       5: return

  public java.lang.Integer getActive();
    Code:
       0: aload_0
       1: invokevirtual #7                  // Method getDataSource:()Ljavax/sql/DataSource;
       4: checkcast     #13                 // class oracle/ucp/jdbc/PoolDataSource
       7: invokeinterface #15,  1           // InterfaceMethod oracle/ucp/jdbc/PoolDataSource.getBorrowedConnectionsCount:()I
      12: invokestatic  #19                 // Method java/lang/Integer.valueOf:(I)Ljava/lang/Integer;
      15: areturn
      16: astore_1
      17: aconst_null
      18: areturn
    Exception table:
       from    to  target type
           0    15    16   Class java/sql/SQLException

  public java.lang.Integer getIdle();
    Code:
       0: aload_0
       1: invokevirtual #7                  // Method getDataSource:()Ljavax/sql/DataSource;
       4: checkcast     #13                 // class oracle/ucp/jdbc/PoolDataSource
       7: invokeinterface #27,  1           // InterfaceMethod oracle/ucp/jdbc/PoolDataSource.getAvailableConnectionsCount:()I
      12: invokestatic  #19                 // Method java/lang/Integer.valueOf:(I)Ljava/lang/Integer;
      15: areturn
      16: astore_1
      17: aconst_null
      18: areturn
    Exception table:
       from    to  target type
           0    15    16   Class java/sql/SQLException

  public java.lang.Integer getMax();
    Code:
       0: aload_0
       1: invokevirtual #7                  // Method getDataSource:()Ljavax/sql/DataSource;
       4: checkcast     #13                 // class oracle/ucp/jdbc/PoolDataSource
       7: invokeinterface #30,  1           // InterfaceMethod oracle/ucp/jdbc/PoolDataSource.getMaxPoolSize:()I
      12: invokestatic  #19                 // Method java/lang/Integer.valueOf:(I)Ljava/lang/Integer;
      15: areturn

  public java.lang.Integer getMin();
    Code:
       0: aload_0
       1: invokevirtual #7                  // Method getDataSource:()Ljavax/sql/DataSource;
       4: checkcast     #13                 // class oracle/ucp/jdbc/PoolDataSource
       7: invokeinterface #33,  1           // InterfaceMethod oracle/ucp/jdbc/PoolDataSource.getMinPoolSize:()I
      12: invokestatic  #19                 // Method java/lang/Integer.valueOf:(I)Ljava/lang/Integer;
      15: areturn

  public java.lang.String getValidationQuery();
    Code:
       0: aload_0
       1: invokevirtual #7                  // Method getDataSource:()Ljavax/sql/DataSource;
       4: checkcast     #13                 // class oracle/ucp/jdbc/PoolDataSource
       7: invokeinterface #36,  1           // InterfaceMethod oracle/ucp/jdbc/PoolDataSource.getSQLForValidateConnection:()Ljava/lang/String;
      12: areturn

  public java.lang.Boolean getDefaultAutoCommit();
    Code:
       0: aload_0
       1: invokevirtual #7                  // Method getDataSource:()Ljavax/sql/DataSource;
       4: checkcast     #13                 // class oracle/ucp/jdbc/PoolDataSource
       7: ldc           #40                 // String autoCommit
       9: invokeinterface #42,  2           // InterfaceMethod oracle/ucp/jdbc/PoolDataSource.getConnectionProperty:(Ljava/lang/String;)Ljava/lang/String;
      14: astore_1
      15: aload_1
      16: invokestatic  #46                 // Method org/springframework/util/StringUtils.hasText:(Ljava/lang/String;)Z
      19: ifeq          29
      22: aload_1
      23: invokestatic  #52                 // Method java/lang/Boolean.valueOf:(Ljava/lang/String;)Ljava/lang/Boolean;
      26: goto          30
      29: aconst_null
      30: areturn
}
