Compiled from "TomcatDataSourcePoolMetadata.java"
public class org.springframework.boot.jdbc.metadata.TomcatDataSourcePoolMetadata extends org.springframework.boot.jdbc.metadata.AbstractDataSourcePoolMetadata<org.apache.tomcat.jdbc.pool.DataSource> {
  public org.springframework.boot.jdbc.metadata.TomcatDataSourcePoolMetadata(org.apache.tomcat.jdbc.pool.DataSource);
    Code:
       0: aload_0
       1: aload_1
       2: invokespecial #1                  // Method org/springframework/boot/jdbc/metadata/AbstractDataSourcePoolMetadata."<init>":(Ljavax/sql/DataSource;)V
       5: return

  public java.lang.Integer getActive();
    Code:
       0: aload_0
       1: invokevirtual #7                  // Method getDataSource:()Ljavax/sql/DataSource;
       4: checkcast     #13                 // class org/apache/tomcat/jdbc/pool/DataSource
       7: invokevirtual #15                 // Method org/apache/tomcat/jdbc/pool/DataSource.getPool:()Lorg/apache/tomcat/jdbc/pool/ConnectionPool;
      10: astore_1
      11: aload_1
      12: ifnull        22
      15: aload_1
      16: invokevirtual #19                 // Method org/apache/tomcat/jdbc/pool/ConnectionPool.getActive:()I
      19: goto          23
      22: iconst_0
      23: invokestatic  #25                 // Method java/lang/Integer.valueOf:(I)Ljava/lang/Integer;
      26: areturn

  public java.lang.Integer getIdle();
    Code:
       0: aload_0
       1: invokevirtual #7                  // Method getDataSource:()Ljavax/sql/DataSource;
       4: checkcast     #13                 // class org/apache/tomcat/jdbc/pool/DataSource
       7: invokevirtual #31                 // Method org/apache/tomcat/jdbc/pool/DataSource.getNumIdle:()I
      10: invokestatic  #25                 // Method java/lang/Integer.valueOf:(I)Ljava/lang/Integer;
      13: areturn

  public java.lang.Integer getMax();
    Code:
       0: aload_0
       1: invokevirtual #7                  // Method getDataSource:()Ljavax/sql/DataSource;
       4: checkcast     #13                 // class org/apache/tomcat/jdbc/pool/DataSource
       7: invokevirtual #34                 // Method org/apache/tomcat/jdbc/pool/DataSource.getMaxActive:()I
      10: invokestatic  #25                 // Method java/lang/Integer.valueOf:(I)Ljava/lang/Integer;
      13: areturn

  public java.lang.Integer getMin();
    Code:
       0: aload_0
       1: invokevirtual #7                  // Method getDataSource:()Ljavax/sql/DataSource;
       4: checkcast     #13                 // class org/apache/tomcat/jdbc/pool/DataSource
       7: invokevirtual #37                 // Method org/apache/tomcat/jdbc/pool/DataSource.getMinIdle:()I
      10: invokestatic  #25                 // Method java/lang/Integer.valueOf:(I)Ljava/lang/Integer;
      13: areturn

  public java.lang.String getValidationQuery();
    Code:
       0: aload_0
       1: invokevirtual #7                  // Method getDataSource:()Ljavax/sql/DataSource;
       4: checkcast     #13                 // class org/apache/tomcat/jdbc/pool/DataSource
       7: invokevirtual #40                 // Method org/apache/tomcat/jdbc/pool/DataSource.getValidationQuery:()Ljava/lang/String;
      10: areturn

  public java.lang.Boolean getDefaultAutoCommit();
    Code:
       0: aload_0
       1: invokevirtual #7                  // Method getDataSource:()Ljavax/sql/DataSource;
       4: checkcast     #13                 // class org/apache/tomcat/jdbc/pool/DataSource
       7: invokevirtual #44                 // Method org/apache/tomcat/jdbc/pool/DataSource.isDefaultAutoCommit:()Ljava/lang/Boolean;
      10: areturn
}
