Compiled from "BarcodeFormat.java"
public final class com.google.zxing.BarcodeFormat extends java.lang.Enum<com.google.zxing.BarcodeFormat> {
  public static final com.google.zxing.BarcodeFormat AZTEC;

  public static final com.google.zxing.BarcodeFormat CODABAR;

  public static final com.google.zxing.BarcodeFormat CODE_39;

  public static final com.google.zxing.BarcodeFormat CODE_93;

  public static final com.google.zxing.BarcodeFormat CODE_128;

  public static final com.google.zxing.BarcodeFormat DATA_MATRIX;

  public static final com.google.zxing.BarcodeFormat EAN_8;

  public static final com.google.zxing.BarcodeFormat EAN_13;

  public static final com.google.zxing.BarcodeFormat ITF;

  public static final com.google.zxing.BarcodeFormat MAXICODE;

  public static final com.google.zxing.BarcodeFormat PDF_417;

  public static final com.google.zxing.BarcodeFormat QR_CODE;

  public static final com.google.zxing.BarcodeFormat RSS_14;

  public static final com.google.zxing.BarcodeFormat RSS_EXPANDED;

  public static final com.google.zxing.BarcodeFormat UPC_A;

  public static final com.google.zxing.BarcodeFormat UPC_E;

  public static final com.google.zxing.BarcodeFormat UPC_EAN_EXTENSION;

  private static final com.google.zxing.BarcodeFormat[] $VALUES;

  public static com.google.zxing.BarcodeFormat[] values();
    Code:
       0: getstatic     #1                  // Field $VALUES:[Lcom/google/zxing/BarcodeFormat;
       3: invokevirtual #2                  // Method "[Lcom/google/zxing/BarcodeFormat;".clone:()Ljava/lang/Object;
       6: checkcast     #3                  // class "[Lcom/google/zxing/BarcodeFormat;"
       9: areturn

  public static com.google.zxing.BarcodeFormat valueOf(java.lang.String);
    Code:
       0: ldc           #4                  // class com/google/zxing/BarcodeFormat
       2: aload_0
       3: invokestatic  #5                  // Method java/lang/Enum.valueOf:(Ljava/lang/Class;Ljava/lang/String;)Ljava/lang/Enum;
       6: checkcast     #4                  // class com/google/zxing/BarcodeFormat
       9: areturn

  private com.google.zxing.BarcodeFormat();
    Code:
       0: aload_0
       1: aload_1
       2: iload_2
       3: invokespecial #6                  // Method java/lang/Enum."<init>":(Ljava/lang/String;I)V
       6: return

  static {};
    Code:
       0: new           #4                  // class com/google/zxing/BarcodeFormat
       3: dup
       4: ldc           #7                  // String AZTEC
       6: iconst_0
       7: invokespecial #8                  // Method "<init>":(Ljava/lang/String;I)V
      10: putstatic     #9                  // Field AZTEC:Lcom/google/zxing/BarcodeFormat;
      13: new           #4                  // class com/google/zxing/BarcodeFormat
      16: dup
      17: ldc           #10                 // String CODABAR
      19: iconst_1
      20: invokespecial #8                  // Method "<init>":(Ljava/lang/String;I)V
      23: putstatic     #11                 // Field CODABAR:Lcom/google/zxing/BarcodeFormat;
      26: new           #4                  // class com/google/zxing/BarcodeFormat
      29: dup
      30: ldc           #12                 // String CODE_39
      32: iconst_2
      33: invokespecial #8                  // Method "<init>":(Ljava/lang/String;I)V
      36: putstatic     #13                 // Field CODE_39:Lcom/google/zxing/BarcodeFormat;
      39: new           #4                  // class com/google/zxing/BarcodeFormat
      42: dup
      43: ldc           #14                 // String CODE_93
      45: iconst_3
      46: invokespecial #8                  // Method "<init>":(Ljava/lang/String;I)V
      49: putstatic     #15                 // Field CODE_93:Lcom/google/zxing/BarcodeFormat;
      52: new           #4                  // class com/google/zxing/BarcodeFormat
      55: dup
      56: ldc           #16                 // String CODE_128
      58: iconst_4
      59: invokespecial #8                  // Method "<init>":(Ljava/lang/String;I)V
      62: putstatic     #17                 // Field CODE_128:Lcom/google/zxing/BarcodeFormat;
      65: new           #4                  // class com/google/zxing/BarcodeFormat
      68: dup
      69: ldc           #18                 // String DATA_MATRIX
      71: iconst_5
      72: invokespecial #8                  // Method "<init>":(Ljava/lang/String;I)V
      75: putstatic     #19                 // Field DATA_MATRIX:Lcom/google/zxing/BarcodeFormat;
      78: new           #4                  // class com/google/zxing/BarcodeFormat
      81: dup
      82: ldc           #20                 // String EAN_8
      84: bipush        6
      86: invokespecial #8                  // Method "<init>":(Ljava/lang/String;I)V
      89: putstatic     #21                 // Field EAN_8:Lcom/google/zxing/BarcodeFormat;
      92: new           #4                  // class com/google/zxing/BarcodeFormat
      95: dup
      96: ldc           #22                 // String EAN_13
      98: bipush        7
     100: invokespecial #8                  // Method "<init>":(Ljava/lang/String;I)V
     103: putstatic     #23                 // Field EAN_13:Lcom/google/zxing/BarcodeFormat;
     106: new           #4                  // class com/google/zxing/BarcodeFormat
     109: dup
     110: ldc           #24                 // String ITF
     112: bipush        8
     114: invokespecial #8                  // Method "<init>":(Ljava/lang/String;I)V
     117: putstatic     #25                 // Field ITF:Lcom/google/zxing/BarcodeFormat;
     120: new           #4                  // class com/google/zxing/BarcodeFormat
     123: dup
     124: ldc           #26                 // String MAXICODE
     126: bipush        9
     128: invokespecial #8                  // Method "<init>":(Ljava/lang/String;I)V
     131: putstatic     #27                 // Field MAXICODE:Lcom/google/zxing/BarcodeFormat;
     134: new           #4                  // class com/google/zxing/BarcodeFormat
     137: dup
     138: ldc           #28                 // String PDF_417
     140: bipush        10
     142: invokespecial #8                  // Method "<init>":(Ljava/lang/String;I)V
     145: putstatic     #29                 // Field PDF_417:Lcom/google/zxing/BarcodeFormat;
     148: new           #4                  // class com/google/zxing/BarcodeFormat
     151: dup
     152: ldc           #30                 // String QR_CODE
     154: bipush        11
     156: invokespecial #8                  // Method "<init>":(Ljava/lang/String;I)V
     159: putstatic     #31                 // Field QR_CODE:Lcom/google/zxing/BarcodeFormat;
     162: new           #4                  // class com/google/zxing/BarcodeFormat
     165: dup
     166: ldc           #32                 // String RSS_14
     168: bipush        12
     170: invokespecial #8                  // Method "<init>":(Ljava/lang/String;I)V
     173: putstatic     #33                 // Field RSS_14:Lcom/google/zxing/BarcodeFormat;
     176: new           #4                  // class com/google/zxing/BarcodeFormat
     179: dup
     180: ldc           #34                 // String RSS_EXPANDED
     182: bipush        13
     184: invokespecial #8                  // Method "<init>":(Ljava/lang/String;I)V
     187: putstatic     #35                 // Field RSS_EXPANDED:Lcom/google/zxing/BarcodeFormat;
     190: new           #4                  // class com/google/zxing/BarcodeFormat
     193: dup
     194: ldc           #36                 // String UPC_A
     196: bipush        14
     198: invokespecial #8                  // Method "<init>":(Ljava/lang/String;I)V
     201: putstatic     #37                 // Field UPC_A:Lcom/google/zxing/BarcodeFormat;
     204: new           #4                  // class com/google/zxing/BarcodeFormat
     207: dup
     208: ldc           #38                 // String UPC_E
     210: bipush        15
     212: invokespecial #8                  // Method "<init>":(Ljava/lang/String;I)V
     215: putstatic     #39                 // Field UPC_E:Lcom/google/zxing/BarcodeFormat;
     218: new           #4                  // class com/google/zxing/BarcodeFormat
     221: dup
     222: ldc           #40                 // String UPC_EAN_EXTENSION
     224: bipush        16
     226: invokespecial #8                  // Method "<init>":(Ljava/lang/String;I)V
     229: putstatic     #41                 // Field UPC_EAN_EXTENSION:Lcom/google/zxing/BarcodeFormat;
     232: bipush        17
     234: anewarray     #4                  // class com/google/zxing/BarcodeFormat
     237: dup
     238: iconst_0
     239: getstatic     #9                  // Field AZTEC:Lcom/google/zxing/BarcodeFormat;
     242: aastore
     243: dup
     244: iconst_1
     245: getstatic     #11                 // Field CODABAR:Lcom/google/zxing/BarcodeFormat;
     248: aastore
     249: dup
     250: iconst_2
     251: getstatic     #13                 // Field CODE_39:Lcom/google/zxing/BarcodeFormat;
     254: aastore
     255: dup
     256: iconst_3
     257: getstatic     #15                 // Field CODE_93:Lcom/google/zxing/BarcodeFormat;
     260: aastore
     261: dup
     262: iconst_4
     263: getstatic     #17                 // Field CODE_128:Lcom/google/zxing/BarcodeFormat;
     266: aastore
     267: dup
     268: iconst_5
     269: getstatic     #19                 // Field DATA_MATRIX:Lcom/google/zxing/BarcodeFormat;
     272: aastore
     273: dup
     274: bipush        6
     276: getstatic     #21                 // Field EAN_8:Lcom/google/zxing/BarcodeFormat;
     279: aastore
     280: dup
     281: bipush        7
     283: getstatic     #23                 // Field EAN_13:Lcom/google/zxing/BarcodeFormat;
     286: aastore
     287: dup
     288: bipush        8
     290: getstatic     #25                 // Field ITF:Lcom/google/zxing/BarcodeFormat;
     293: aastore
     294: dup
     295: bipush        9
     297: getstatic     #27                 // Field MAXICODE:Lcom/google/zxing/BarcodeFormat;
     300: aastore
     301: dup
     302: bipush        10
     304: getstatic     #29                 // Field PDF_417:Lcom/google/zxing/BarcodeFormat;
     307: aastore
     308: dup
     309: bipush        11
     311: getstatic     #31                 // Field QR_CODE:Lcom/google/zxing/BarcodeFormat;
     314: aastore
     315: dup
     316: bipush        12
     318: getstatic     #33                 // Field RSS_14:Lcom/google/zxing/BarcodeFormat;
     321: aastore
     322: dup
     323: bipush        13
     325: getstatic     #35                 // Field RSS_EXPANDED:Lcom/google/zxing/BarcodeFormat;
     328: aastore
     329: dup
     330: bipush        14
     332: getstatic     #37                 // Field UPC_A:Lcom/google/zxing/BarcodeFormat;
     335: aastore
     336: dup
     337: bipush        15
     339: getstatic     #39                 // Field UPC_E:Lcom/google/zxing/BarcodeFormat;
     342: aastore
     343: dup
     344: bipush        16
     346: getstatic     #41                 // Field UPC_EAN_EXTENSION:Lcom/google/zxing/BarcodeFormat;
     349: aastore
     350: putstatic     #1                  // Field $VALUES:[Lcom/google/zxing/BarcodeFormat;
     353: return
}
