Compiled from "BinaryBitmap.java"
public final class com.google.zxing.BinaryBitmap {
  private final com.google.zxing.Binarizer binarizer;

  private com.google.zxing.common.BitMatrix matrix;

  public com.google.zxing.BinaryBitmap(com.google.zxing.Binarizer);
    Code:
       0: aload_0
       1: invokespecial #1                  // Method java/lang/Object."<init>":()V
       4: aload_1
       5: ifnonnull     18
       8: new           #2                  // class java/lang/IllegalArgumentException
      11: dup
      12: ldc           #3                  // String Binarizer must be non-null.
      14: invokespecial #4                  // Method java/lang/IllegalArgumentException."<init>":(Ljava/lang/String;)V
      17: athrow
      18: aload_0
      19: aload_1
      20: putfield      #5                  // Field binarizer:Lcom/google/zxing/Binarizer;
      23: return

  public int getWidth();
    Code:
       0: aload_0
       1: getfield      #5                  // Field binarizer:Lcom/google/zxing/Binarizer;
       4: invokevirtual #6                  // Method com/google/zxing/Binarizer.getWidth:()I
       7: ireturn

  public int getHeight();
    Code:
       0: aload_0
       1: getfield      #5                  // Field binarizer:Lcom/google/zxing/Binarizer;
       4: invokevirtual #7                  // Method com/google/zxing/Binarizer.getHeight:()I
       7: ireturn

  public com.google.zxing.common.BitArray getBlackRow(int, com.google.zxing.common.BitArray) throws com.google.zxing.NotFoundException;
    Code:
       0: aload_0
       1: getfield      #5                  // Field binarizer:Lcom/google/zxing/Binarizer;
       4: iload_1
       5: aload_2
       6: invokevirtual #8                  // Method com/google/zxing/Binarizer.getBlackRow:(ILcom/google/zxing/common/BitArray;)Lcom/google/zxing/common/BitArray;
       9: areturn

  public com.google.zxing.common.BitMatrix getBlackMatrix() throws com.google.zxing.NotFoundException;
    Code:
       0: aload_0
       1: getfield      #9                  // Field matrix:Lcom/google/zxing/common/BitMatrix;
       4: ifnonnull     18
       7: aload_0
       8: aload_0
       9: getfield      #5                  // Field binarizer:Lcom/google/zxing/Binarizer;
      12: invokevirtual #10                 // Method com/google/zxing/Binarizer.getBlackMatrix:()Lcom/google/zxing/common/BitMatrix;
      15: putfield      #9                  // Field matrix:Lcom/google/zxing/common/BitMatrix;
      18: aload_0
      19: getfield      #9                  // Field matrix:Lcom/google/zxing/common/BitMatrix;
      22: areturn

  public boolean isCropSupported();
    Code:
       0: aload_0
       1: getfield      #5                  // Field binarizer:Lcom/google/zxing/Binarizer;
       4: invokevirtual #11                 // Method com/google/zxing/Binarizer.getLuminanceSource:()Lcom/google/zxing/LuminanceSource;
       7: invokevirtual #12                 // Method com/google/zxing/LuminanceSource.isCropSupported:()Z
      10: ireturn

  public com.google.zxing.BinaryBitmap crop(int, int, int, int);
    Code:
       0: aload_0
       1: getfield      #5                  // Field binarizer:Lcom/google/zxing/Binarizer;
       4: invokevirtual #11                 // Method com/google/zxing/Binarizer.getLuminanceSource:()Lcom/google/zxing/LuminanceSource;
       7: iload_1
       8: iload_2
       9: iload_3
      10: iload         4
      12: invokevirtual #13                 // Method com/google/zxing/LuminanceSource.crop:(IIII)Lcom/google/zxing/LuminanceSource;
      15: astore        5
      17: new           #14                 // class com/google/zxing/BinaryBitmap
      20: dup
      21: aload_0
      22: getfield      #5                  // Field binarizer:Lcom/google/zxing/Binarizer;
      25: aload         5
      27: invokevirtual #15                 // Method com/google/zxing/Binarizer.createBinarizer:(Lcom/google/zxing/LuminanceSource;)Lcom/google/zxing/Binarizer;
      30: invokespecial #16                 // Method "<init>":(Lcom/google/zxing/Binarizer;)V
      33: areturn

  public boolean isRotateSupported();
    Code:
       0: aload_0
       1: getfield      #5                  // Field binarizer:Lcom/google/zxing/Binarizer;
       4: invokevirtual #11                 // Method com/google/zxing/Binarizer.getLuminanceSource:()Lcom/google/zxing/LuminanceSource;
       7: invokevirtual #17                 // Method com/google/zxing/LuminanceSource.isRotateSupported:()Z
      10: ireturn

  public com.google.zxing.BinaryBitmap rotateCounterClockwise();
    Code:
       0: aload_0
       1: getfield      #5                  // Field binarizer:Lcom/google/zxing/Binarizer;
       4: invokevirtual #11                 // Method com/google/zxing/Binarizer.getLuminanceSource:()Lcom/google/zxing/LuminanceSource;
       7: invokevirtual #18                 // Method com/google/zxing/LuminanceSource.rotateCounterClockwise:()Lcom/google/zxing/LuminanceSource;
      10: astore_1
      11: new           #14                 // class com/google/zxing/BinaryBitmap
      14: dup
      15: aload_0
      16: getfield      #5                  // Field binarizer:Lcom/google/zxing/Binarizer;
      19: aload_1
      20: invokevirtual #15                 // Method com/google/zxing/Binarizer.createBinarizer:(Lcom/google/zxing/LuminanceSource;)Lcom/google/zxing/Binarizer;
      23: invokespecial #16                 // Method "<init>":(Lcom/google/zxing/Binarizer;)V
      26: areturn

  public com.google.zxing.BinaryBitmap rotateCounterClockwise45();
    Code:
       0: aload_0
       1: getfield      #5                  // Field binarizer:Lcom/google/zxing/Binarizer;
       4: invokevirtual #11                 // Method com/google/zxing/Binarizer.getLuminanceSource:()Lcom/google/zxing/LuminanceSource;
       7: invokevirtual #19                 // Method com/google/zxing/LuminanceSource.rotateCounterClockwise45:()Lcom/google/zxing/LuminanceSource;
      10: astore_1
      11: new           #14                 // class com/google/zxing/BinaryBitmap
      14: dup
      15: aload_0
      16: getfield      #5                  // Field binarizer:Lcom/google/zxing/Binarizer;
      19: aload_1
      20: invokevirtual #15                 // Method com/google/zxing/Binarizer.createBinarizer:(Lcom/google/zxing/LuminanceSource;)Lcom/google/zxing/Binarizer;
      23: invokespecial #16                 // Method "<init>":(Lcom/google/zxing/Binarizer;)V
      26: areturn

  public java.lang.String toString();
    Code:
       0: aload_0
       1: invokevirtual #20                 // Method getBlackMatrix:()Lcom/google/zxing/common/BitMatrix;
       4: invokevirtual #21                 // Method com/google/zxing/common/BitMatrix.toString:()Ljava/lang/String;
       7: areturn
       8: astore_1
       9: ldc           #23                 // String
      11: areturn
    Exception table:
       from    to  target type
           0     7     8   Class com/google/zxing/NotFoundException
}
