Compiled from "Binarizer.java"
public abstract class com.google.zxing.Binarizer {
  private final com.google.zxing.LuminanceSource source;

  protected com.google.zxing.Binarizer(com.google.zxing.LuminanceSource);
    Code:
       0: aload_0
       1: invokespecial #1                  // Method java/lang/Object."<init>":()V
       4: aload_0
       5: aload_1
       6: putfield      #2                  // Field source:Lcom/google/zxing/LuminanceSource;
       9: return

  public final com.google.zxing.LuminanceSource getLuminanceSource();
    Code:
       0: aload_0
       1: getfield      #2                  // Field source:Lcom/google/zxing/LuminanceSource;
       4: areturn

  public abstract com.google.zxing.common.BitArray getBlackRow(int, com.google.zxing.common.BitArray) throws com.google.zxing.NotFoundException;

  public abstract com.google.zxing.common.BitMatrix getBlackMatrix() throws com.google.zxing.NotFoundException;

  public abstract com.google.zxing.Binarizer createBinarizer(com.google.zxing.LuminanceSource);

  public final int getWidth();
    Code:
       0: aload_0
       1: getfield      #2                  // Field source:Lcom/google/zxing/LuminanceSource;
       4: invokevirtual #3                  // Method com/google/zxing/LuminanceSource.getWidth:()I
       7: ireturn

  public final int getHeight();
    Code:
       0: aload_0
       1: getfield      #2                  // Field source:Lcom/google/zxing/LuminanceSource;
       4: invokevirtual #4                  // Method com/google/zxing/LuminanceSource.getHeight:()I
       7: ireturn
}
