Compiled from "ChecksumException.java"
public final class com.google.zxing.ChecksumException extends com.google.zxing.ReaderException {
  private static final com.google.zxing.ChecksumException INSTANCE;

  private com.google.zxing.ChecksumException();
    Code:
       0: aload_0
       1: invokespecial #1                  // Method com/google/zxing/ReaderException."<init>":()V
       4: return

  private com.google.zxing.ChecksumException(java.lang.Throwable);
    Code:
       0: aload_0
       1: aload_1
       2: invokespecial #2                  // Method com/google/zxing/ReaderException."<init>":(Ljava/lang/Throwable;)V
       5: return

  public static com.google.zxing.ChecksumException getChecksumInstance();
    Code:
       0: getstatic     #3                  // Field isStackTrace:Z
       3: ifeq          16
       6: new           #4                  // class com/google/zxing/ChecksumException
       9: dup
      10: invokespecial #5                  // Method "<init>":()V
      13: goto          19
      16: getstatic     #6                  // Field INSTANCE:Lcom/google/zxing/ChecksumException;
      19: areturn

  public static com.google.zxing.ChecksumException getChecksumInstance(java.lang.Throwable);
    Code:
       0: getstatic     #3                  // Field isStackTrace:Z
       3: ifeq          17
       6: new           #4                  // class com/google/zxing/ChecksumException
       9: dup
      10: aload_0
      11: invokespecial #7                  // Method "<init>":(Ljava/lang/Throwable;)V
      14: goto          20
      17: getstatic     #6                  // Field INSTANCE:Lcom/google/zxing/ChecksumException;
      20: areturn

  static {};
    Code:
       0: new           #4                  // class com/google/zxing/ChecksumException
       3: dup
       4: invokespecial #5                  // Method "<init>":()V
       7: putstatic     #6                  // Field INSTANCE:Lcom/google/zxing/ChecksumException;
      10: getstatic     #6                  // Field INSTANCE:Lcom/google/zxing/ChecksumException;
      13: getstatic     #8                  // Field NO_TRACE:[Ljava/lang/StackTraceElement;
      16: invokevirtual #9                  // Method setStackTrace:([Ljava/lang/StackTraceElement;)V
      19: return
}
