Compiled from "DecodeHintType.java"
public final class com.google.zxing.DecodeHintType extends java.lang.Enum<com.google.zxing.DecodeHintType> {
  public static final com.google.zxing.DecodeHintType OTHER;

  public static final com.google.zxing.DecodeHintType PURE_BARCODE;

  public static final com.google.zxing.DecodeHintType POSSIBLE_FORMATS;

  public static final com.google.zxing.DecodeHintType TRY_HARDER;

  public static final com.google.zxing.DecodeHintType CHARACTER_SET;

  public static final com.google.zxing.DecodeHintType ALLOWED_LENGTHS;

  public static final com.google.zxing.DecodeHintType ASSUME_CODE_39_CHECK_DIGIT;

  public static final com.google.zxing.DecodeHintType ASSUME_GS1;

  public static final com.google.zxing.DecodeHintType RETURN_CODABAR_START_END;

  public static final com.google.zxing.DecodeHintType NEED_RESULT_POINT_CALLBACK;

  public static final com.google.zxing.DecodeHintType ALLOWED_EAN_EXTENSIONS;

  public static final com.google.zxing.DecodeHintType ALSO_INVERTED;

  private final java.lang.Class<?> valueType;

  private static final com.google.zxing.DecodeHintType[] $VALUES;

  public static com.google.zxing.DecodeHintType[] values();
    Code:
       0: getstatic     #1                  // Field $VALUES:[Lcom/google/zxing/DecodeHintType;
       3: invokevirtual #2                  // Method "[Lcom/google/zxing/DecodeHintType;".clone:()Ljava/lang/Object;
       6: checkcast     #3                  // class "[Lcom/google/zxing/DecodeHintType;"
       9: areturn

  public static com.google.zxing.DecodeHintType valueOf(java.lang.String);
    Code:
       0: ldc           #4                  // class com/google/zxing/DecodeHintType
       2: aload_0
       3: invokestatic  #5                  // Method java/lang/Enum.valueOf:(Ljava/lang/Class;Ljava/lang/String;)Ljava/lang/Enum;
       6: checkcast     #4                  // class com/google/zxing/DecodeHintType
       9: areturn

  private com.google.zxing.DecodeHintType(java.lang.Class<?>);
    Code:
       0: aload_0
       1: aload_1
       2: iload_2
       3: invokespecial #6                  // Method java/lang/Enum."<init>":(Ljava/lang/String;I)V
       6: aload_0
       7: aload_3
       8: putfield      #7                  // Field valueType:Ljava/lang/Class;
      11: return

  public java.lang.Class<?> getValueType();
    Code:
       0: aload_0
       1: getfield      #7                  // Field valueType:Ljava/lang/Class;
       4: areturn

  static {};
    Code:
       0: new           #4                  // class com/google/zxing/DecodeHintType
       3: dup
       4: ldc           #8                  // String OTHER
       6: iconst_0
       7: ldc           #9                  // class java/lang/Object
       9: invokespecial #10                 // Method "<init>":(Ljava/lang/String;ILjava/lang/Class;)V
      12: putstatic     #11                 // Field OTHER:Lcom/google/zxing/DecodeHintType;
      15: new           #4                  // class com/google/zxing/DecodeHintType
      18: dup
      19: ldc           #12                 // String PURE_BARCODE
      21: iconst_1
      22: ldc           #13                 // class java/lang/Void
      24: invokespecial #10                 // Method "<init>":(Ljava/lang/String;ILjava/lang/Class;)V
      27: putstatic     #14                 // Field PURE_BARCODE:Lcom/google/zxing/DecodeHintType;
      30: new           #4                  // class com/google/zxing/DecodeHintType
      33: dup
      34: ldc           #15                 // String POSSIBLE_FORMATS
      36: iconst_2
      37: ldc           #16                 // class java/util/List
      39: invokespecial #10                 // Method "<init>":(Ljava/lang/String;ILjava/lang/Class;)V
      42: putstatic     #17                 // Field POSSIBLE_FORMATS:Lcom/google/zxing/DecodeHintType;
      45: new           #4                  // class com/google/zxing/DecodeHintType
      48: dup
      49: ldc           #18                 // String TRY_HARDER
      51: iconst_3
      52: ldc           #13                 // class java/lang/Void
      54: invokespecial #10                 // Method "<init>":(Ljava/lang/String;ILjava/lang/Class;)V
      57: putstatic     #19                 // Field TRY_HARDER:Lcom/google/zxing/DecodeHintType;
      60: new           #4                  // class com/google/zxing/DecodeHintType
      63: dup
      64: ldc           #20                 // String CHARACTER_SET
      66: iconst_4
      67: ldc           #21                 // class java/lang/String
      69: invokespecial #10                 // Method "<init>":(Ljava/lang/String;ILjava/lang/Class;)V
      72: putstatic     #22                 // Field CHARACTER_SET:Lcom/google/zxing/DecodeHintType;
      75: new           #4                  // class com/google/zxing/DecodeHintType
      78: dup
      79: ldc           #23                 // String ALLOWED_LENGTHS
      81: iconst_5
      82: ldc           #24                 // class "[I"
      84: invokespecial #10                 // Method "<init>":(Ljava/lang/String;ILjava/lang/Class;)V
      87: putstatic     #25                 // Field ALLOWED_LENGTHS:Lcom/google/zxing/DecodeHintType;
      90: new           #4                  // class com/google/zxing/DecodeHintType
      93: dup
      94: ldc           #26                 // String ASSUME_CODE_39_CHECK_DIGIT
      96: bipush        6
      98: ldc           #13                 // class java/lang/Void
     100: invokespecial #10                 // Method "<init>":(Ljava/lang/String;ILjava/lang/Class;)V
     103: putstatic     #27                 // Field ASSUME_CODE_39_CHECK_DIGIT:Lcom/google/zxing/DecodeHintType;
     106: new           #4                  // class com/google/zxing/DecodeHintType
     109: dup
     110: ldc           #28                 // String ASSUME_GS1
     112: bipush        7
     114: ldc           #13                 // class java/lang/Void
     116: invokespecial #10                 // Method "<init>":(Ljava/lang/String;ILjava/lang/Class;)V
     119: putstatic     #29                 // Field ASSUME_GS1:Lcom/google/zxing/DecodeHintType;
     122: new           #4                  // class com/google/zxing/DecodeHintType
     125: dup
     126: ldc           #30                 // String RETURN_CODABAR_START_END
     128: bipush        8
     130: ldc           #13                 // class java/lang/Void
     132: invokespecial #10                 // Method "<init>":(Ljava/lang/String;ILjava/lang/Class;)V
     135: putstatic     #31                 // Field RETURN_CODABAR_START_END:Lcom/google/zxing/DecodeHintType;
     138: new           #4                  // class com/google/zxing/DecodeHintType
     141: dup
     142: ldc           #32                 // String NEED_RESULT_POINT_CALLBACK
     144: bipush        9
     146: ldc           #33                 // class com/google/zxing/ResultPointCallback
     148: invokespecial #10                 // Method "<init>":(Ljava/lang/String;ILjava/lang/Class;)V
     151: putstatic     #34                 // Field NEED_RESULT_POINT_CALLBACK:Lcom/google/zxing/DecodeHintType;
     154: new           #4                  // class com/google/zxing/DecodeHintType
     157: dup
     158: ldc           #35                 // String ALLOWED_EAN_EXTENSIONS
     160: bipush        10
     162: ldc           #24                 // class "[I"
     164: invokespecial #10                 // Method "<init>":(Ljava/lang/String;ILjava/lang/Class;)V
     167: putstatic     #36                 // Field ALLOWED_EAN_EXTENSIONS:Lcom/google/zxing/DecodeHintType;
     170: new           #4                  // class com/google/zxing/DecodeHintType
     173: dup
     174: ldc           #37                 // String ALSO_INVERTED
     176: bipush        11
     178: ldc           #13                 // class java/lang/Void
     180: invokespecial #10                 // Method "<init>":(Ljava/lang/String;ILjava/lang/Class;)V
     183: putstatic     #38                 // Field ALSO_INVERTED:Lcom/google/zxing/DecodeHintType;
     186: bipush        12
     188: anewarray     #4                  // class com/google/zxing/DecodeHintType
     191: dup
     192: iconst_0
     193: getstatic     #11                 // Field OTHER:Lcom/google/zxing/DecodeHintType;
     196: aastore
     197: dup
     198: iconst_1
     199: getstatic     #14                 // Field PURE_BARCODE:Lcom/google/zxing/DecodeHintType;
     202: aastore
     203: dup
     204: iconst_2
     205: getstatic     #17                 // Field POSSIBLE_FORMATS:Lcom/google/zxing/DecodeHintType;
     208: aastore
     209: dup
     210: iconst_3
     211: getstatic     #19                 // Field TRY_HARDER:Lcom/google/zxing/DecodeHintType;
     214: aastore
     215: dup
     216: iconst_4
     217: getstatic     #22                 // Field CHARACTER_SET:Lcom/google/zxing/DecodeHintType;
     220: aastore
     221: dup
     222: iconst_5
     223: getstatic     #25                 // Field ALLOWED_LENGTHS:Lcom/google/zxing/DecodeHintType;
     226: aastore
     227: dup
     228: bipush        6
     230: getstatic     #27                 // Field ASSUME_CODE_39_CHECK_DIGIT:Lcom/google/zxing/DecodeHintType;
     233: aastore
     234: dup
     235: bipush        7
     237: getstatic     #29                 // Field ASSUME_GS1:Lcom/google/zxing/DecodeHintType;
     240: aastore
     241: dup
     242: bipush        8
     244: getstatic     #31                 // Field RETURN_CODABAR_START_END:Lcom/google/zxing/DecodeHintType;
     247: aastore
     248: dup
     249: bipush        9
     251: getstatic     #34                 // Field NEED_RESULT_POINT_CALLBACK:Lcom/google/zxing/DecodeHintType;
     254: aastore
     255: dup
     256: bipush        10
     258: getstatic     #36                 // Field ALLOWED_EAN_EXTENSIONS:Lcom/google/zxing/DecodeHintType;
     261: aastore
     262: dup
     263: bipush        11
     265: getstatic     #38                 // Field ALSO_INVERTED:Lcom/google/zxing/DecodeHintType;
     268: aastore
     269: putstatic     #1                  // Field $VALUES:[Lcom/google/zxing/DecodeHintType;
     272: return
}
