Compiled from "EncodeHintType.java"
public final class com.google.zxing.EncodeHintType extends java.lang.Enum<com.google.zxing.EncodeHintType> {
  public static final com.google.zxing.EncodeHintType ERROR_CORRECTION;

  public static final com.google.zxing.EncodeHintType CHARACTER_SET;

  public static final com.google.zxing.EncodeHintType DATA_MATRIX_SHAPE;

  public static final com.google.zxing.EncodeHintType DATA_MATRIX_COMPACT;

  public static final com.google.zxing.EncodeHintType MIN_SIZE;

  public static final com.google.zxing.EncodeHintType MAX_SIZE;

  public static final com.google.zxing.EncodeHintType MARGIN;

  public static final com.google.zxing.EncodeHintType PDF417_COMPACT;

  public static final com.google.zxing.EncodeHintType PDF417_COMPACTION;

  public static final com.google.zxing.EncodeHintType PDF417_DIMENSIONS;

  public static final com.google.zxing.EncodeHintType PDF417_AUTO_ECI;

  public static final com.google.zxing.EncodeHintType AZTEC_LAYERS;

  public static final com.google.zxing.EncodeHintType QR_VERSION;

  public static final com.google.zxing.EncodeHintType QR_MASK_PATTERN;

  public static final com.google.zxing.EncodeHintType QR_COMPACT;

  public static final com.google.zxing.EncodeHintType GS1_FORMAT;

  public static final com.google.zxing.EncodeHintType FORCE_CODE_SET;

  public static final com.google.zxing.EncodeHintType FORCE_C40;

  public static final com.google.zxing.EncodeHintType CODE128_COMPACT;

  private static final com.google.zxing.EncodeHintType[] $VALUES;

  public static com.google.zxing.EncodeHintType[] values();
    Code:
       0: getstatic     #1                  // Field $VALUES:[Lcom/google/zxing/EncodeHintType;
       3: invokevirtual #2                  // Method "[Lcom/google/zxing/EncodeHintType;".clone:()Ljava/lang/Object;
       6: checkcast     #3                  // class "[Lcom/google/zxing/EncodeHintType;"
       9: areturn

  public static com.google.zxing.EncodeHintType valueOf(java.lang.String);
    Code:
       0: ldc           #4                  // class com/google/zxing/EncodeHintType
       2: aload_0
       3: invokestatic  #5                  // Method java/lang/Enum.valueOf:(Ljava/lang/Class;Ljava/lang/String;)Ljava/lang/Enum;
       6: checkcast     #4                  // class com/google/zxing/EncodeHintType
       9: areturn

  private com.google.zxing.EncodeHintType();
    Code:
       0: aload_0
       1: aload_1
       2: iload_2
       3: invokespecial #6                  // Method java/lang/Enum."<init>":(Ljava/lang/String;I)V
       6: return

  static {};
    Code:
       0: new           #4                  // class com/google/zxing/EncodeHintType
       3: dup
       4: ldc           #7                  // String ERROR_CORRECTION
       6: iconst_0
       7: invokespecial #8                  // Method "<init>":(Ljava/lang/String;I)V
      10: putstatic     #9                  // Field ERROR_CORRECTION:Lcom/google/zxing/EncodeHintType;
      13: new           #4                  // class com/google/zxing/EncodeHintType
      16: dup
      17: ldc           #10                 // String CHARACTER_SET
      19: iconst_1
      20: invokespecial #8                  // Method "<init>":(Ljava/lang/String;I)V
      23: putstatic     #11                 // Field CHARACTER_SET:Lcom/google/zxing/EncodeHintType;
      26: new           #4                  // class com/google/zxing/EncodeHintType
      29: dup
      30: ldc           #12                 // String DATA_MATRIX_SHAPE
      32: iconst_2
      33: invokespecial #8                  // Method "<init>":(Ljava/lang/String;I)V
      36: putstatic     #13                 // Field DATA_MATRIX_SHAPE:Lcom/google/zxing/EncodeHintType;
      39: new           #4                  // class com/google/zxing/EncodeHintType
      42: dup
      43: ldc           #14                 // String DATA_MATRIX_COMPACT
      45: iconst_3
      46: invokespecial #8                  // Method "<init>":(Ljava/lang/String;I)V
      49: putstatic     #15                 // Field DATA_MATRIX_COMPACT:Lcom/google/zxing/EncodeHintType;
      52: new           #4                  // class com/google/zxing/EncodeHintType
      55: dup
      56: ldc           #16                 // String MIN_SIZE
      58: iconst_4
      59: invokespecial #8                  // Method "<init>":(Ljava/lang/String;I)V
      62: putstatic     #17                 // Field MIN_SIZE:Lcom/google/zxing/EncodeHintType;
      65: new           #4                  // class com/google/zxing/EncodeHintType
      68: dup
      69: ldc           #18                 // String MAX_SIZE
      71: iconst_5
      72: invokespecial #8                  // Method "<init>":(Ljava/lang/String;I)V
      75: putstatic     #19                 // Field MAX_SIZE:Lcom/google/zxing/EncodeHintType;
      78: new           #4                  // class com/google/zxing/EncodeHintType
      81: dup
      82: ldc           #20                 // String MARGIN
      84: bipush        6
      86: invokespecial #8                  // Method "<init>":(Ljava/lang/String;I)V
      89: putstatic     #21                 // Field MARGIN:Lcom/google/zxing/EncodeHintType;
      92: new           #4                  // class com/google/zxing/EncodeHintType
      95: dup
      96: ldc           #22                 // String PDF417_COMPACT
      98: bipush        7
     100: invokespecial #8                  // Method "<init>":(Ljava/lang/String;I)V
     103: putstatic     #23                 // Field PDF417_COMPACT:Lcom/google/zxing/EncodeHintType;
     106: new           #4                  // class com/google/zxing/EncodeHintType
     109: dup
     110: ldc           #24                 // String PDF417_COMPACTION
     112: bipush        8
     114: invokespecial #8                  // Method "<init>":(Ljava/lang/String;I)V
     117: putstatic     #25                 // Field PDF417_COMPACTION:Lcom/google/zxing/EncodeHintType;
     120: new           #4                  // class com/google/zxing/EncodeHintType
     123: dup
     124: ldc           #26                 // String PDF417_DIMENSIONS
     126: bipush        9
     128: invokespecial #8                  // Method "<init>":(Ljava/lang/String;I)V
     131: putstatic     #27                 // Field PDF417_DIMENSIONS:Lcom/google/zxing/EncodeHintType;
     134: new           #4                  // class com/google/zxing/EncodeHintType
     137: dup
     138: ldc           #28                 // String PDF417_AUTO_ECI
     140: bipush        10
     142: invokespecial #8                  // Method "<init>":(Ljava/lang/String;I)V
     145: putstatic     #29                 // Field PDF417_AUTO_ECI:Lcom/google/zxing/EncodeHintType;
     148: new           #4                  // class com/google/zxing/EncodeHintType
     151: dup
     152: ldc           #30                 // String AZTEC_LAYERS
     154: bipush        11
     156: invokespecial #8                  // Method "<init>":(Ljava/lang/String;I)V
     159: putstatic     #31                 // Field AZTEC_LAYERS:Lcom/google/zxing/EncodeHintType;
     162: new           #4                  // class com/google/zxing/EncodeHintType
     165: dup
     166: ldc           #32                 // String QR_VERSION
     168: bipush        12
     170: invokespecial #8                  // Method "<init>":(Ljava/lang/String;I)V
     173: putstatic     #33                 // Field QR_VERSION:Lcom/google/zxing/EncodeHintType;
     176: new           #4                  // class com/google/zxing/EncodeHintType
     179: dup
     180: ldc           #34                 // String QR_MASK_PATTERN
     182: bipush        13
     184: invokespecial #8                  // Method "<init>":(Ljava/lang/String;I)V
     187: putstatic     #35                 // Field QR_MASK_PATTERN:Lcom/google/zxing/EncodeHintType;
     190: new           #4                  // class com/google/zxing/EncodeHintType
     193: dup
     194: ldc           #36                 // String QR_COMPACT
     196: bipush        14
     198: invokespecial #8                  // Method "<init>":(Ljava/lang/String;I)V
     201: putstatic     #37                 // Field QR_COMPACT:Lcom/google/zxing/EncodeHintType;
     204: new           #4                  // class com/google/zxing/EncodeHintType
     207: dup
     208: ldc           #38                 // String GS1_FORMAT
     210: bipush        15
     212: invokespecial #8                  // Method "<init>":(Ljava/lang/String;I)V
     215: putstatic     #39                 // Field GS1_FORMAT:Lcom/google/zxing/EncodeHintType;
     218: new           #4                  // class com/google/zxing/EncodeHintType
     221: dup
     222: ldc           #40                 // String FORCE_CODE_SET
     224: bipush        16
     226: invokespecial #8                  // Method "<init>":(Ljava/lang/String;I)V
     229: putstatic     #41                 // Field FORCE_CODE_SET:Lcom/google/zxing/EncodeHintType;
     232: new           #4                  // class com/google/zxing/EncodeHintType
     235: dup
     236: ldc           #42                 // String FORCE_C40
     238: bipush        17
     240: invokespecial #8                  // Method "<init>":(Ljava/lang/String;I)V
     243: putstatic     #43                 // Field FORCE_C40:Lcom/google/zxing/EncodeHintType;
     246: new           #4                  // class com/google/zxing/EncodeHintType
     249: dup
     250: ldc           #44                 // String CODE128_COMPACT
     252: bipush        18
     254: invokespecial #8                  // Method "<init>":(Ljava/lang/String;I)V
     257: putstatic     #45                 // Field CODE128_COMPACT:Lcom/google/zxing/EncodeHintType;
     260: bipush        19
     262: anewarray     #4                  // class com/google/zxing/EncodeHintType
     265: dup
     266: iconst_0
     267: getstatic     #9                  // Field ERROR_CORRECTION:Lcom/google/zxing/EncodeHintType;
     270: aastore
     271: dup
     272: iconst_1
     273: getstatic     #11                 // Field CHARACTER_SET:Lcom/google/zxing/EncodeHintType;
     276: aastore
     277: dup
     278: iconst_2
     279: getstatic     #13                 // Field DATA_MATRIX_SHAPE:Lcom/google/zxing/EncodeHintType;
     282: aastore
     283: dup
     284: iconst_3
     285: getstatic     #15                 // Field DATA_MATRIX_COMPACT:Lcom/google/zxing/EncodeHintType;
     288: aastore
     289: dup
     290: iconst_4
     291: getstatic     #17                 // Field MIN_SIZE:Lcom/google/zxing/EncodeHintType;
     294: aastore
     295: dup
     296: iconst_5
     297: getstatic     #19                 // Field MAX_SIZE:Lcom/google/zxing/EncodeHintType;
     300: aastore
     301: dup
     302: bipush        6
     304: getstatic     #21                 // Field MARGIN:Lcom/google/zxing/EncodeHintType;
     307: aastore
     308: dup
     309: bipush        7
     311: getstatic     #23                 // Field PDF417_COMPACT:Lcom/google/zxing/EncodeHintType;
     314: aastore
     315: dup
     316: bipush        8
     318: getstatic     #25                 // Field PDF417_COMPACTION:Lcom/google/zxing/EncodeHintType;
     321: aastore
     322: dup
     323: bipush        9
     325: getstatic     #27                 // Field PDF417_DIMENSIONS:Lcom/google/zxing/EncodeHintType;
     328: aastore
     329: dup
     330: bipush        10
     332: getstatic     #29                 // Field PDF417_AUTO_ECI:Lcom/google/zxing/EncodeHintType;
     335: aastore
     336: dup
     337: bipush        11
     339: getstatic     #31                 // Field AZTEC_LAYERS:Lcom/google/zxing/EncodeHintType;
     342: aastore
     343: dup
     344: bipush        12
     346: getstatic     #33                 // Field QR_VERSION:Lcom/google/zxing/EncodeHintType;
     349: aastore
     350: dup
     351: bipush        13
     353: getstatic     #35                 // Field QR_MASK_PATTERN:Lcom/google/zxing/EncodeHintType;
     356: aastore
     357: dup
     358: bipush        14
     360: getstatic     #37                 // Field QR_COMPACT:Lcom/google/zxing/EncodeHintType;
     363: aastore
     364: dup
     365: bipush        15
     367: getstatic     #39                 // Field GS1_FORMAT:Lcom/google/zxing/EncodeHintType;
     370: aastore
     371: dup
     372: bipush        16
     374: getstatic     #41                 // Field FORCE_CODE_SET:Lcom/google/zxing/EncodeHintType;
     377: aastore
     378: dup
     379: bipush        17
     381: getstatic     #43                 // Field FORCE_C40:Lcom/google/zxing/EncodeHintType;
     384: aastore
     385: dup
     386: bipush        18
     388: getstatic     #45                 // Field CODE128_COMPACT:Lcom/google/zxing/EncodeHintType;
     391: aastore
     392: putstatic     #1                  // Field $VALUES:[Lcom/google/zxing/EncodeHintType;
     395: return
}
