Compiled from "InvertedLuminanceSource.java"
public final class com.google.zxing.InvertedLuminanceSource extends com.google.zxing.LuminanceSource {
  private final com.google.zxing.LuminanceSource delegate;

  public com.google.zxing.InvertedLuminanceSource(com.google.zxing.LuminanceSource);
    Code:
       0: aload_0
       1: aload_1
       2: invokevirtual #1                  // Method com/google/zxing/LuminanceSource.getWidth:()I
       5: aload_1
       6: invokevirtual #2                  // Method com/google/zxing/LuminanceSource.getHeight:()I
       9: invokespecial #3                  // Method com/google/zxing/LuminanceSource."<init>":(II)V
      12: aload_0
      13: aload_1
      14: putfield      #4                  // Field delegate:Lcom/google/zxing/LuminanceSource;
      17: return

  public byte[] getRow(int, byte[]);
    Code:
       0: aload_0
       1: getfield      #4                  // Field delegate:Lcom/google/zxing/LuminanceSource;
       4: iload_1
       5: aload_2
       6: invokevirtual #5                  // Method com/google/zxing/LuminanceSource.getRow:(I[B)[B
       9: astore_2
      10: aload_0
      11: invokevirtual #6                  // Method getWidth:()I
      14: istore_3
      15: iconst_0
      16: istore        4
      18: iload         4
      20: iload_3
      21: if_icmpge     47
      24: aload_2
      25: iload         4
      27: sipush        255
      30: aload_2
      31: iload         4
      33: baload
      34: sipush        255
      37: iand
      38: isub
      39: i2b
      40: bastore
      41: iinc          4, 1
      44: goto          18
      47: aload_2
      48: areturn

  public byte[] getMatrix();
    Code:
       0: aload_0
       1: getfield      #4                  // Field delegate:Lcom/google/zxing/LuminanceSource;
       4: invokevirtual #7                  // Method com/google/zxing/LuminanceSource.getMatrix:()[B
       7: astore_1
       8: aload_0
       9: invokevirtual #6                  // Method getWidth:()I
      12: aload_0
      13: invokevirtual #8                  // Method getHeight:()I
      16: imul
      17: istore_2
      18: iload_2
      19: newarray       byte
      21: astore_3
      22: iconst_0
      23: istore        4
      25: iload         4
      27: iload_2
      28: if_icmpge     54
      31: aload_3
      32: iload         4
      34: sipush        255
      37: aload_1
      38: iload         4
      40: baload
      41: sipush        255
      44: iand
      45: isub
      46: i2b
      47: bastore
      48: iinc          4, 1
      51: goto          25
      54: aload_3
      55: areturn

  public boolean isCropSupported();
    Code:
       0: aload_0
       1: getfield      #4                  // Field delegate:Lcom/google/zxing/LuminanceSource;
       4: invokevirtual #9                  // Method com/google/zxing/LuminanceSource.isCropSupported:()Z
       7: ireturn

  public com.google.zxing.LuminanceSource crop(int, int, int, int);
    Code:
       0: new           #10                 // class com/google/zxing/InvertedLuminanceSource
       3: dup
       4: aload_0
       5: getfield      #4                  // Field delegate:Lcom/google/zxing/LuminanceSource;
       8: iload_1
       9: iload_2
      10: iload_3
      11: iload         4
      13: invokevirtual #11                 // Method com/google/zxing/LuminanceSource.crop:(IIII)Lcom/google/zxing/LuminanceSource;
      16: invokespecial #12                 // Method "<init>":(Lcom/google/zxing/LuminanceSource;)V
      19: areturn

  public boolean isRotateSupported();
    Code:
       0: aload_0
       1: getfield      #4                  // Field delegate:Lcom/google/zxing/LuminanceSource;
       4: invokevirtual #13                 // Method com/google/zxing/LuminanceSource.isRotateSupported:()Z
       7: ireturn

  public com.google.zxing.LuminanceSource invert();
    Code:
       0: aload_0
       1: getfield      #4                  // Field delegate:Lcom/google/zxing/LuminanceSource;
       4: areturn

  public com.google.zxing.LuminanceSource rotateCounterClockwise();
    Code:
       0: new           #10                 // class com/google/zxing/InvertedLuminanceSource
       3: dup
       4: aload_0
       5: getfield      #4                  // Field delegate:Lcom/google/zxing/LuminanceSource;
       8: invokevirtual #14                 // Method com/google/zxing/LuminanceSource.rotateCounterClockwise:()Lcom/google/zxing/LuminanceSource;
      11: invokespecial #12                 // Method "<init>":(Lcom/google/zxing/LuminanceSource;)V
      14: areturn

  public com.google.zxing.LuminanceSource rotateCounterClockwise45();
    Code:
       0: new           #10                 // class com/google/zxing/InvertedLuminanceSource
       3: dup
       4: aload_0
       5: getfield      #4                  // Field delegate:Lcom/google/zxing/LuminanceSource;
       8: invokevirtual #15                 // Method com/google/zxing/LuminanceSource.rotateCounterClockwise45:()Lcom/google/zxing/LuminanceSource;
      11: invokespecial #12                 // Method "<init>":(Lcom/google/zxing/LuminanceSource;)V
      14: areturn
}
