Compiled from "MultiFormatReader.java"
public final class com.google.zxing.MultiFormatReader implements com.google.zxing.Reader {
  private static final com.google.zxing.Reader[] EMPTY_READER_ARRAY;

  private java.util.Map<com.google.zxing.DecodeHintType, ?> hints;

  private com.google.zxing.Reader[] readers;

  public com.google.zxing.MultiFormatReader();
    Code:
       0: aload_0
       1: invokespecial #1                  // Method java/lang/Object."<init>":()V
       4: return

  public com.google.zxing.Result decode(com.google.zxing.BinaryBitmap) throws com.google.zxing.NotFoundException;
    Code:
       0: aload_0
       1: aconst_null
       2: invokevirtual #2                  // Method setHints:(Ljava/util/Map;)V
       5: aload_0
       6: aload_1
       7: invokespecial #3                  // Method decodeInternal:(Lcom/google/zxing/BinaryBitmap;)Lcom/google/zxing/Result;
      10: areturn

  public com.google.zxing.Result decode(com.google.zxing.BinaryBitmap, java.util.Map<com.google.zxing.DecodeHintType, ?>) throws com.google.zxing.NotFoundException;
    Code:
       0: aload_0
       1: aload_2
       2: invokevirtual #2                  // Method setHints:(Ljava/util/Map;)V
       5: aload_0
       6: aload_1
       7: invokespecial #3                  // Method decodeInternal:(Lcom/google/zxing/BinaryBitmap;)Lcom/google/zxing/Result;
      10: areturn

  public com.google.zxing.Result decodeWithState(com.google.zxing.BinaryBitmap) throws com.google.zxing.NotFoundException;
    Code:
       0: aload_0
       1: getfield      #4                  // Field readers:[Lcom/google/zxing/Reader;
       4: ifnonnull     12
       7: aload_0
       8: aconst_null
       9: invokevirtual #2                  // Method setHints:(Ljava/util/Map;)V
      12: aload_0
      13: aload_1
      14: invokespecial #3                  // Method decodeInternal:(Lcom/google/zxing/BinaryBitmap;)Lcom/google/zxing/Result;
      17: areturn

  public void setHints(java.util.Map<com.google.zxing.DecodeHintType, ?>);
    Code:
       0: aload_0
       1: aload_1
       2: putfield      #5                  // Field hints:Ljava/util/Map;
       5: aload_1
       6: ifnull        25
       9: aload_1
      10: getstatic     #6                  // Field com/google/zxing/DecodeHintType.TRY_HARDER:Lcom/google/zxing/DecodeHintType;
      13: invokeinterface #7,  2            // InterfaceMethod java/util/Map.containsKey:(Ljava/lang/Object;)Z
      18: ifeq          25
      21: iconst_1
      22: goto          26
      25: iconst_0
      26: istore_2
      27: aload_1
      28: ifnonnull     35
      31: aconst_null
      32: goto          47
      35: aload_1
      36: getstatic     #8                  // Field com/google/zxing/DecodeHintType.POSSIBLE_FORMATS:Lcom/google/zxing/DecodeHintType;
      39: invokeinterface #9,  2            // InterfaceMethod java/util/Map.get:(Ljava/lang/Object;)Ljava/lang/Object;
      44: checkcast     #10                 // class java/util/Collection
      47: astore_3
      48: new           #11                 // class java/util/ArrayList
      51: dup
      52: invokespecial #12                 // Method java/util/ArrayList."<init>":()V
      55: astore        4
      57: aload_3
      58: ifnull        385
      61: aload_3
      62: getstatic     #13                 // Field com/google/zxing/BarcodeFormat.UPC_A:Lcom/google/zxing/BarcodeFormat;
      65: invokeinterface #14,  2           // InterfaceMethod java/util/Collection.contains:(Ljava/lang/Object;)Z
      70: ifne          193
      73: aload_3
      74: getstatic     #15                 // Field com/google/zxing/BarcodeFormat.UPC_E:Lcom/google/zxing/BarcodeFormat;
      77: invokeinterface #14,  2           // InterfaceMethod java/util/Collection.contains:(Ljava/lang/Object;)Z
      82: ifne          193
      85: aload_3
      86: getstatic     #16                 // Field com/google/zxing/BarcodeFormat.EAN_13:Lcom/google/zxing/BarcodeFormat;
      89: invokeinterface #14,  2           // InterfaceMethod java/util/Collection.contains:(Ljava/lang/Object;)Z
      94: ifne          193
      97: aload_3
      98: getstatic     #17                 // Field com/google/zxing/BarcodeFormat.EAN_8:Lcom/google/zxing/BarcodeFormat;
     101: invokeinterface #14,  2           // InterfaceMethod java/util/Collection.contains:(Ljava/lang/Object;)Z
     106: ifne          193
     109: aload_3
     110: getstatic     #18                 // Field com/google/zxing/BarcodeFormat.CODABAR:Lcom/google/zxing/BarcodeFormat;
     113: invokeinterface #14,  2           // InterfaceMethod java/util/Collection.contains:(Ljava/lang/Object;)Z
     118: ifne          193
     121: aload_3
     122: getstatic     #19                 // Field com/google/zxing/BarcodeFormat.CODE_39:Lcom/google/zxing/BarcodeFormat;
     125: invokeinterface #14,  2           // InterfaceMethod java/util/Collection.contains:(Ljava/lang/Object;)Z
     130: ifne          193
     133: aload_3
     134: getstatic     #20                 // Field com/google/zxing/BarcodeFormat.CODE_93:Lcom/google/zxing/BarcodeFormat;
     137: invokeinterface #14,  2           // InterfaceMethod java/util/Collection.contains:(Ljava/lang/Object;)Z
     142: ifne          193
     145: aload_3
     146: getstatic     #21                 // Field com/google/zxing/BarcodeFormat.CODE_128:Lcom/google/zxing/BarcodeFormat;
     149: invokeinterface #14,  2           // InterfaceMethod java/util/Collection.contains:(Ljava/lang/Object;)Z
     154: ifne          193
     157: aload_3
     158: getstatic     #22                 // Field com/google/zxing/BarcodeFormat.ITF:Lcom/google/zxing/BarcodeFormat;
     161: invokeinterface #14,  2           // InterfaceMethod java/util/Collection.contains:(Ljava/lang/Object;)Z
     166: ifne          193
     169: aload_3
     170: getstatic     #23                 // Field com/google/zxing/BarcodeFormat.RSS_14:Lcom/google/zxing/BarcodeFormat;
     173: invokeinterface #14,  2           // InterfaceMethod java/util/Collection.contains:(Ljava/lang/Object;)Z
     178: ifne          193
     181: aload_3
     182: getstatic     #24                 // Field com/google/zxing/BarcodeFormat.RSS_EXPANDED:Lcom/google/zxing/BarcodeFormat;
     185: invokeinterface #14,  2           // InterfaceMethod java/util/Collection.contains:(Ljava/lang/Object;)Z
     190: ifeq          197
     193: iconst_1
     194: goto          198
     197: iconst_0
     198: istore        5
     200: iload         5
     202: ifeq          225
     205: iload_2
     206: ifne          225
     209: aload         4
     211: new           #25                 // class com/google/zxing/oned/MultiFormatOneDReader
     214: dup
     215: aload_1
     216: invokespecial #26                 // Method com/google/zxing/oned/MultiFormatOneDReader."<init>":(Ljava/util/Map;)V
     219: invokeinterface #27,  2           // InterfaceMethod java/util/Collection.add:(Ljava/lang/Object;)Z
     224: pop
     225: aload_3
     226: getstatic     #28                 // Field com/google/zxing/BarcodeFormat.QR_CODE:Lcom/google/zxing/BarcodeFormat;
     229: invokeinterface #14,  2           // InterfaceMethod java/util/Collection.contains:(Ljava/lang/Object;)Z
     234: ifeq          252
     237: aload         4
     239: new           #29                 // class com/google/zxing/qrcode/QRCodeReader
     242: dup
     243: invokespecial #30                 // Method com/google/zxing/qrcode/QRCodeReader."<init>":()V
     246: invokeinterface #27,  2           // InterfaceMethod java/util/Collection.add:(Ljava/lang/Object;)Z
     251: pop
     252: aload_3
     253: getstatic     #31                 // Field com/google/zxing/BarcodeFormat.DATA_MATRIX:Lcom/google/zxing/BarcodeFormat;
     256: invokeinterface #14,  2           // InterfaceMethod java/util/Collection.contains:(Ljava/lang/Object;)Z
     261: ifeq          279
     264: aload         4
     266: new           #32                 // class com/google/zxing/datamatrix/DataMatrixReader
     269: dup
     270: invokespecial #33                 // Method com/google/zxing/datamatrix/DataMatrixReader."<init>":()V
     273: invokeinterface #27,  2           // InterfaceMethod java/util/Collection.add:(Ljava/lang/Object;)Z
     278: pop
     279: aload_3
     280: getstatic     #34                 // Field com/google/zxing/BarcodeFormat.AZTEC:Lcom/google/zxing/BarcodeFormat;
     283: invokeinterface #14,  2           // InterfaceMethod java/util/Collection.contains:(Ljava/lang/Object;)Z
     288: ifeq          306
     291: aload         4
     293: new           #35                 // class com/google/zxing/aztec/AztecReader
     296: dup
     297: invokespecial #36                 // Method com/google/zxing/aztec/AztecReader."<init>":()V
     300: invokeinterface #27,  2           // InterfaceMethod java/util/Collection.add:(Ljava/lang/Object;)Z
     305: pop
     306: aload_3
     307: getstatic     #37                 // Field com/google/zxing/BarcodeFormat.PDF_417:Lcom/google/zxing/BarcodeFormat;
     310: invokeinterface #14,  2           // InterfaceMethod java/util/Collection.contains:(Ljava/lang/Object;)Z
     315: ifeq          333
     318: aload         4
     320: new           #38                 // class com/google/zxing/pdf417/PDF417Reader
     323: dup
     324: invokespecial #39                 // Method com/google/zxing/pdf417/PDF417Reader."<init>":()V
     327: invokeinterface #27,  2           // InterfaceMethod java/util/Collection.add:(Ljava/lang/Object;)Z
     332: pop
     333: aload_3
     334: getstatic     #40                 // Field com/google/zxing/BarcodeFormat.MAXICODE:Lcom/google/zxing/BarcodeFormat;
     337: invokeinterface #14,  2           // InterfaceMethod java/util/Collection.contains:(Ljava/lang/Object;)Z
     342: ifeq          360
     345: aload         4
     347: new           #41                 // class com/google/zxing/maxicode/MaxiCodeReader
     350: dup
     351: invokespecial #42                 // Method com/google/zxing/maxicode/MaxiCodeReader."<init>":()V
     354: invokeinterface #27,  2           // InterfaceMethod java/util/Collection.add:(Ljava/lang/Object;)Z
     359: pop
     360: iload         5
     362: ifeq          385
     365: iload_2
     366: ifeq          385
     369: aload         4
     371: new           #25                 // class com/google/zxing/oned/MultiFormatOneDReader
     374: dup
     375: aload_1
     376: invokespecial #26                 // Method com/google/zxing/oned/MultiFormatOneDReader."<init>":(Ljava/util/Map;)V
     379: invokeinterface #27,  2           // InterfaceMethod java/util/Collection.add:(Ljava/lang/Object;)Z
     384: pop
     385: aload         4
     387: invokeinterface #43,  1           // InterfaceMethod java/util/Collection.isEmpty:()Z
     392: ifeq          510
     395: iload_2
     396: ifne          415
     399: aload         4
     401: new           #25                 // class com/google/zxing/oned/MultiFormatOneDReader
     404: dup
     405: aload_1
     406: invokespecial #26                 // Method com/google/zxing/oned/MultiFormatOneDReader."<init>":(Ljava/util/Map;)V
     409: invokeinterface #27,  2           // InterfaceMethod java/util/Collection.add:(Ljava/lang/Object;)Z
     414: pop
     415: aload         4
     417: new           #29                 // class com/google/zxing/qrcode/QRCodeReader
     420: dup
     421: invokespecial #30                 // Method com/google/zxing/qrcode/QRCodeReader."<init>":()V
     424: invokeinterface #27,  2           // InterfaceMethod java/util/Collection.add:(Ljava/lang/Object;)Z
     429: pop
     430: aload         4
     432: new           #32                 // class com/google/zxing/datamatrix/DataMatrixReader
     435: dup
     436: invokespecial #33                 // Method com/google/zxing/datamatrix/DataMatrixReader."<init>":()V
     439: invokeinterface #27,  2           // InterfaceMethod java/util/Collection.add:(Ljava/lang/Object;)Z
     444: pop
     445: aload         4
     447: new           #35                 // class com/google/zxing/aztec/AztecReader
     450: dup
     451: invokespecial #36                 // Method com/google/zxing/aztec/AztecReader."<init>":()V
     454: invokeinterface #27,  2           // InterfaceMethod java/util/Collection.add:(Ljava/lang/Object;)Z
     459: pop
     460: aload         4
     462: new           #38                 // class com/google/zxing/pdf417/PDF417Reader
     465: dup
     466: invokespecial #39                 // Method com/google/zxing/pdf417/PDF417Reader."<init>":()V
     469: invokeinterface #27,  2           // InterfaceMethod java/util/Collection.add:(Ljava/lang/Object;)Z
     474: pop
     475: aload         4
     477: new           #41                 // class com/google/zxing/maxicode/MaxiCodeReader
     480: dup
     481: invokespecial #42                 // Method com/google/zxing/maxicode/MaxiCodeReader."<init>":()V
     484: invokeinterface #27,  2           // InterfaceMethod java/util/Collection.add:(Ljava/lang/Object;)Z
     489: pop
     490: iload_2
     491: ifeq          510
     494: aload         4
     496: new           #25                 // class com/google/zxing/oned/MultiFormatOneDReader
     499: dup
     500: aload_1
     501: invokespecial #26                 // Method com/google/zxing/oned/MultiFormatOneDReader."<init>":(Ljava/util/Map;)V
     504: invokeinterface #27,  2           // InterfaceMethod java/util/Collection.add:(Ljava/lang/Object;)Z
     509: pop
     510: aload_0
     511: aload         4
     513: getstatic     #44                 // Field EMPTY_READER_ARRAY:[Lcom/google/zxing/Reader;
     516: invokeinterface #45,  2           // InterfaceMethod java/util/Collection.toArray:([Ljava/lang/Object;)[Ljava/lang/Object;
     521: checkcast     #46                 // class "[Lcom/google/zxing/Reader;"
     524: putfield      #4                  // Field readers:[Lcom/google/zxing/Reader;
     527: return

  public void reset();
    Code:
       0: aload_0
       1: getfield      #4                  // Field readers:[Lcom/google/zxing/Reader;
       4: ifnull        40
       7: aload_0
       8: getfield      #4                  // Field readers:[Lcom/google/zxing/Reader;
      11: astore_1
      12: aload_1
      13: arraylength
      14: istore_2
      15: iconst_0
      16: istore_3
      17: iload_3
      18: iload_2
      19: if_icmpge     40
      22: aload_1
      23: iload_3
      24: aaload
      25: astore        4
      27: aload         4
      29: invokeinterface #47,  1           // InterfaceMethod com/google/zxing/Reader.reset:()V
      34: iinc          3, 1
      37: goto          17
      40: return

  private com.google.zxing.Result decodeInternal(com.google.zxing.BinaryBitmap) throws com.google.zxing.NotFoundException;
    Code:
       0: aload_0
       1: getfield      #4                  // Field readers:[Lcom/google/zxing/Reader;
       4: ifnull        150
       7: aload_0
       8: getfield      #4                  // Field readers:[Lcom/google/zxing/Reader;
      11: astore_2
      12: aload_2
      13: arraylength
      14: istore_3
      15: iconst_0
      16: istore        4
      18: iload         4
      20: iload_3
      21: if_icmpge     64
      24: aload_2
      25: iload         4
      27: aaload
      28: astore        5
      30: invokestatic  #48                 // Method java/lang/Thread.currentThread:()Ljava/lang/Thread;
      33: invokevirtual #49                 // Method java/lang/Thread.isInterrupted:()Z
      36: ifeq          43
      39: invokestatic  #50                 // Method com/google/zxing/NotFoundException.getNotFoundInstance:()Lcom/google/zxing/NotFoundException;
      42: athrow
      43: aload         5
      45: aload_1
      46: aload_0
      47: getfield      #5                  // Field hints:Ljava/util/Map;
      50: invokeinterface #51,  3           // InterfaceMethod com/google/zxing/Reader.decode:(Lcom/google/zxing/BinaryBitmap;Ljava/util/Map;)Lcom/google/zxing/Result;
      55: areturn
      56: astore        6
      58: iinc          4, 1
      61: goto          18
      64: aload_0
      65: getfield      #5                  // Field hints:Ljava/util/Map;
      68: ifnull        150
      71: aload_0
      72: getfield      #5                  // Field hints:Ljava/util/Map;
      75: getstatic     #53                 // Field com/google/zxing/DecodeHintType.ALSO_INVERTED:Lcom/google/zxing/DecodeHintType;
      78: invokeinterface #7,  2            // InterfaceMethod java/util/Map.containsKey:(Ljava/lang/Object;)Z
      83: ifeq          150
      86: aload_1
      87: invokevirtual #54                 // Method com/google/zxing/BinaryBitmap.getBlackMatrix:()Lcom/google/zxing/common/BitMatrix;
      90: invokevirtual #55                 // Method com/google/zxing/common/BitMatrix.flip:()V
      93: aload_0
      94: getfield      #4                  // Field readers:[Lcom/google/zxing/Reader;
      97: astore_2
      98: aload_2
      99: arraylength
     100: istore_3
     101: iconst_0
     102: istore        4
     104: iload         4
     106: iload_3
     107: if_icmpge     150
     110: aload_2
     111: iload         4
     113: aaload
     114: astore        5
     116: invokestatic  #48                 // Method java/lang/Thread.currentThread:()Ljava/lang/Thread;
     119: invokevirtual #49                 // Method java/lang/Thread.isInterrupted:()Z
     122: ifeq          129
     125: invokestatic  #50                 // Method com/google/zxing/NotFoundException.getNotFoundInstance:()Lcom/google/zxing/NotFoundException;
     128: athrow
     129: aload         5
     131: aload_1
     132: aload_0
     133: getfield      #5                  // Field hints:Ljava/util/Map;
     136: invokeinterface #51,  3           // InterfaceMethod com/google/zxing/Reader.decode:(Lcom/google/zxing/BinaryBitmap;Ljava/util/Map;)Lcom/google/zxing/Result;
     141: areturn
     142: astore        6
     144: iinc          4, 1
     147: goto          104
     150: invokestatic  #50                 // Method com/google/zxing/NotFoundException.getNotFoundInstance:()Lcom/google/zxing/NotFoundException;
     153: athrow
    Exception table:
       from    to  target type
          43    55    56   Class com/google/zxing/ReaderException
         129   141   142   Class com/google/zxing/ReaderException

  static {};
    Code:
       0: iconst_0
       1: anewarray     #56                 // class com/google/zxing/Reader
       4: putstatic     #44                 // Field EMPTY_READER_ARRAY:[Lcom/google/zxing/Reader;
       7: return
}
