Compiled from "ReaderException.java"
public abstract class com.google.zxing.ReaderException extends java.lang.Exception {
  protected static boolean isStackTrace;

  protected static final java.lang.StackTraceElement[] NO_TRACE;

  com.google.zxing.ReaderException();
    Code:
       0: aload_0
       1: invokespecial #1                  // Method java/lang/Exception."<init>":()V
       4: return

  com.google.zxing.ReaderException(java.lang.Throwable);
    Code:
       0: aload_0
       1: aload_1
       2: invokespecial #2                  // Method java/lang/Exception."<init>":(Ljava/lang/Throwable;)V
       5: return

  public final synchronized java.lang.Throwable fillInStackTrace();
    Code:
       0: aconst_null
       1: areturn

  public static void setStackTrace(boolean);
    Code:
       0: iload_0
       1: putstatic     #3                  // Field isStackTrace:Z
       4: return

  static {};
    Code:
       0: ldc           #4                  // String surefire.test.class.path
       2: invokestatic  #5                  // Method java/lang/System.getProperty:(Ljava/lang/String;)Ljava/lang/String;
       5: ifnull        12
       8: iconst_1
       9: goto          13
      12: iconst_0
      13: putstatic     #3                  // Field isStackTrace:Z
      16: iconst_0
      17: anewarray     #6                  // class java/lang/StackTraceElement
      20: putstatic     #7                  // Field NO_TRACE:[Ljava/lang/StackTraceElement;
      23: return
}
