Compiled from "Result.java"
public final class com.google.zxing.Result {
  private final java.lang.String text;

  private final byte[] rawBytes;

  private final int numBits;

  private com.google.zxing.ResultPoint[] resultPoints;

  private final com.google.zxing.BarcodeFormat format;

  private java.util.Map<com.google.zxing.ResultMetadataType, java.lang.Object> resultMetadata;

  private final long timestamp;

  public com.google.zxing.Result(java.lang.String, byte[], com.google.zxing.ResultPoint[], com.google.zxing.BarcodeFormat);
    Code:
       0: aload_0
       1: aload_1
       2: aload_2
       3: aload_3
       4: aload         4
       6: invokestatic  #1                  // Method java/lang/System.currentTimeMillis:()J
       9: invokespecial #2                  // Method "<init>":(Ljava/lang/String;[B[Lcom/google/zxing/ResultPoint;Lcom/google/zxing/BarcodeFormat;J)V
      12: return

  public com.google.zxing.Result(java.lang.String, byte[], com.google.zxing.ResultPoint[], com.google.zxing.BarcodeFormat, long);
    Code:
       0: aload_0
       1: aload_1
       2: aload_2
       3: aload_2
       4: ifnonnull     11
       7: iconst_0
       8: goto          16
      11: bipush        8
      13: aload_2
      14: arraylength
      15: imul
      16: aload_3
      17: aload         4
      19: lload         5
      21: invokespecial #3                  // Method "<init>":(Ljava/lang/String;[BI[Lcom/google/zxing/ResultPoint;Lcom/google/zxing/BarcodeFormat;J)V
      24: return

  public com.google.zxing.Result(java.lang.String, byte[], int, com.google.zxing.ResultPoint[], com.google.zxing.BarcodeFormat, long);
    Code:
       0: aload_0
       1: invokespecial #4                  // Method java/lang/Object."<init>":()V
       4: aload_0
       5: aload_1
       6: putfield      #5                  // Field text:Ljava/lang/String;
       9: aload_0
      10: aload_2
      11: putfield      #6                  // Field rawBytes:[B
      14: aload_0
      15: iload_3
      16: putfield      #7                  // Field numBits:I
      19: aload_0
      20: aload         4
      22: putfield      #8                  // Field resultPoints:[Lcom/google/zxing/ResultPoint;
      25: aload_0
      26: aload         5
      28: putfield      #9                  // Field format:Lcom/google/zxing/BarcodeFormat;
      31: aload_0
      32: aconst_null
      33: putfield      #10                 // Field resultMetadata:Ljava/util/Map;
      36: aload_0
      37: lload         6
      39: putfield      #11                 // Field timestamp:J
      42: return

  public java.lang.String getText();
    Code:
       0: aload_0
       1: getfield      #5                  // Field text:Ljava/lang/String;
       4: areturn

  public byte[] getRawBytes();
    Code:
       0: aload_0
       1: getfield      #6                  // Field rawBytes:[B
       4: areturn

  public int getNumBits();
    Code:
       0: aload_0
       1: getfield      #7                  // Field numBits:I
       4: ireturn

  public com.google.zxing.ResultPoint[] getResultPoints();
    Code:
       0: aload_0
       1: getfield      #8                  // Field resultPoints:[Lcom/google/zxing/ResultPoint;
       4: areturn

  public com.google.zxing.BarcodeFormat getBarcodeFormat();
    Code:
       0: aload_0
       1: getfield      #9                  // Field format:Lcom/google/zxing/BarcodeFormat;
       4: areturn

  public java.util.Map<com.google.zxing.ResultMetadataType, java.lang.Object> getResultMetadata();
    Code:
       0: aload_0
       1: getfield      #10                 // Field resultMetadata:Ljava/util/Map;
       4: areturn

  public void putMetadata(com.google.zxing.ResultMetadataType, java.lang.Object);
    Code:
       0: aload_0
       1: getfield      #10                 // Field resultMetadata:Ljava/util/Map;
       4: ifnonnull     20
       7: aload_0
       8: new           #12                 // class java/util/EnumMap
      11: dup
      12: ldc           #13                 // class com/google/zxing/ResultMetadataType
      14: invokespecial #14                 // Method java/util/EnumMap."<init>":(Ljava/lang/Class;)V
      17: putfield      #10                 // Field resultMetadata:Ljava/util/Map;
      20: aload_0
      21: getfield      #10                 // Field resultMetadata:Ljava/util/Map;
      24: aload_1
      25: aload_2
      26: invokeinterface #15,  3           // InterfaceMethod java/util/Map.put:(Ljava/lang/Object;Ljava/lang/Object;)Ljava/lang/Object;
      31: pop
      32: return

  public void putAllMetadata(java.util.Map<com.google.zxing.ResultMetadataType, java.lang.Object>);
    Code:
       0: aload_1
       1: ifnull        29
       4: aload_0
       5: getfield      #10                 // Field resultMetadata:Ljava/util/Map;
       8: ifnonnull     19
      11: aload_0
      12: aload_1
      13: putfield      #10                 // Field resultMetadata:Ljava/util/Map;
      16: goto          29
      19: aload_0
      20: getfield      #10                 // Field resultMetadata:Ljava/util/Map;
      23: aload_1
      24: invokeinterface #16,  2           // InterfaceMethod java/util/Map.putAll:(Ljava/util/Map;)V
      29: return

  public void addResultPoints(com.google.zxing.ResultPoint[]);
    Code:
       0: aload_0
       1: getfield      #8                  // Field resultPoints:[Lcom/google/zxing/ResultPoint;
       4: astore_2
       5: aload_2
       6: ifnonnull     17
       9: aload_0
      10: aload_1
      11: putfield      #8                  // Field resultPoints:[Lcom/google/zxing/ResultPoint;
      14: goto          59
      17: aload_1
      18: ifnull        59
      21: aload_1
      22: arraylength
      23: ifle          59
      26: aload_2
      27: arraylength
      28: aload_1
      29: arraylength
      30: iadd
      31: anewarray     #17                 // class com/google/zxing/ResultPoint
      34: astore_3
      35: aload_2
      36: iconst_0
      37: aload_3
      38: iconst_0
      39: aload_2
      40: arraylength
      41: invokestatic  #18                 // Method java/lang/System.arraycopy:(Ljava/lang/Object;ILjava/lang/Object;II)V
      44: aload_1
      45: iconst_0
      46: aload_3
      47: aload_2
      48: arraylength
      49: aload_1
      50: arraylength
      51: invokestatic  #18                 // Method java/lang/System.arraycopy:(Ljava/lang/Object;ILjava/lang/Object;II)V
      54: aload_0
      55: aload_3
      56: putfield      #8                  // Field resultPoints:[Lcom/google/zxing/ResultPoint;
      59: return

  public long getTimestamp();
    Code:
       0: aload_0
       1: getfield      #11                 // Field timestamp:J
       4: lreturn

  public java.lang.String toString();
    Code:
       0: aload_0
       1: getfield      #5                  // Field text:Ljava/lang/String;
       4: areturn
}
