Compiled from "WriterException.java"
public final class com.google.zxing.WriterException extends java.lang.Exception {
  public com.google.zxing.WriterException();
    Code:
       0: aload_0
       1: invokespecial #1                  // Method java/lang/Exception."<init>":()V
       4: return

  public com.google.zxing.WriterException(java.lang.String);
    Code:
       0: aload_0
       1: aload_1
       2: invokespecial #2                  // Method java/lang/Exception."<init>":(Ljava/lang/String;)V
       5: return

  public com.google.zxing.WriterException(java.lang.Throwable);
    Code:
       0: aload_0
       1: aload_1
       2: invokespecial #3                  // Method java/lang/Exception."<init>":(Ljava/lang/Throwable;)V
       5: return
}
