Compiled from "CompositeConfiguration.java"
public class org.apache.dubbo.common.config.CompositeConfiguration implements org.apache.dubbo.common.config.Configuration {
  private final org.apache.dubbo.common.logger.ErrorTypeAwareLogger logger;

  private final java.util.List<org.apache.dubbo.common.config.Configuration> configList;

  private boolean dynamicIncluded;

  public org.apache.dubbo.common.config.CompositeConfiguration();
    Code:
       0: aload_0
       1: invokespecial #2                  // Method java/lang/Object."<init>":()V
       4: aload_0
       5: ldc           #3                  // class org/apache/dubbo/common/config/CompositeConfiguration
       7: invokestatic  #4                  // Method org/apache/dubbo/common/logger/LoggerFactory.getErrorTypeAwareLogger:(Ljava/lang/Class;)Lorg/apache/dubbo/common/logger/ErrorTypeAwareLogger;
      10: putfield      #5                  // Field logger:Lorg/apache/dubbo/common/logger/ErrorTypeAwareLogger;
      13: aload_0
      14: new           #6                  // class java/util/concurrent/CopyOnWriteArrayList
      17: dup
      18: invokespecial #7                  // Method java/util/concurrent/CopyOnWriteArrayList."<init>":()V
      21: putfield      #8                  // Field configList:Ljava/util/List;
      24: return

  public org.apache.dubbo.common.config.CompositeConfiguration(org.apache.dubbo.common.config.Configuration...);
    Code:
       0: aload_0
       1: invokespecial #2                  // Method java/lang/Object."<init>":()V
       4: aload_0
       5: ldc           #3                  // class org/apache/dubbo/common/config/CompositeConfiguration
       7: invokestatic  #4                  // Method org/apache/dubbo/common/logger/LoggerFactory.getErrorTypeAwareLogger:(Ljava/lang/Class;)Lorg/apache/dubbo/common/logger/ErrorTypeAwareLogger;
      10: putfield      #5                  // Field logger:Lorg/apache/dubbo/common/logger/ErrorTypeAwareLogger;
      13: aload_0
      14: new           #6                  // class java/util/concurrent/CopyOnWriteArrayList
      17: dup
      18: invokespecial #7                  // Method java/util/concurrent/CopyOnWriteArrayList."<init>":()V
      21: putfield      #8                  // Field configList:Ljava/util/List;
      24: aload_1
      25: invokestatic  #9                  // Method org/apache/dubbo/common/utils/ArrayUtils.isNotEmpty:([Ljava/lang/Object;)Z
      28: ifeq          65
      31: aload_1
      32: invokestatic  #10                 // Method java/util/Arrays.stream:([Ljava/lang/Object;)Ljava/util/stream/Stream;
      35: aload_0
      36: invokedynamic #11,  0             // InvokeDynamic #0:test:(Lorg/apache/dubbo/common/config/CompositeConfiguration;)Ljava/util/function/Predicate;
      41: invokeinterface #12,  2           // InterfaceMethod java/util/stream/Stream.filter:(Ljava/util/function/Predicate;)Ljava/util/stream/Stream;
      46: aload_0
      47: getfield      #8                  // Field configList:Ljava/util/List;
      50: dup
      51: invokevirtual #13                 // Method java/lang/Object.getClass:()Ljava/lang/Class;
      54: pop
      55: invokedynamic #14,  0             // InvokeDynamic #1:accept:(Ljava/util/List;)Ljava/util/function/Consumer;
      60: invokeinterface #15,  2           // InterfaceMethod java/util/stream/Stream.forEach:(Ljava/util/function/Consumer;)V
      65: return

  public boolean isDynamicIncluded();
    Code:
       0: aload_0
       1: getfield      #16                 // Field dynamicIncluded:Z
       4: ireturn

  public void setDynamicIncluded(boolean);
    Code:
       0: aload_0
       1: iload_1
       2: putfield      #16                 // Field dynamicIncluded:Z
       5: return

  public void addConfiguration(org.apache.dubbo.common.config.Configuration);
    Code:
       0: aload_0
       1: getfield      #8                  // Field configList:Ljava/util/List;
       4: aload_1
       5: invokeinterface #17,  2           // InterfaceMethod java/util/List.contains:(Ljava/lang/Object;)Z
      10: ifeq          14
      13: return
      14: aload_0
      15: getfield      #8                  // Field configList:Ljava/util/List;
      18: aload_1
      19: invokeinterface #18,  2           // InterfaceMethod java/util/List.add:(Ljava/lang/Object;)Z
      24: pop
      25: return

  public void addConfigurationFirst(org.apache.dubbo.common.config.Configuration);
    Code:
       0: aload_0
       1: iconst_0
       2: aload_1
       3: invokevirtual #19                 // Method addConfiguration:(ILorg/apache/dubbo/common/config/Configuration;)V
       6: return

  public void addConfiguration(int, org.apache.dubbo.common.config.Configuration);
    Code:
       0: aload_0
       1: getfield      #8                  // Field configList:Ljava/util/List;
       4: iload_1
       5: aload_2
       6: invokeinterface #20,  3           // InterfaceMethod java/util/List.add:(ILjava/lang/Object;)V
      11: return

  public java.lang.Object getInternalProperty(java.lang.String);
    Code:
       0: aload_0
       1: getfield      #8                  // Field configList:Ljava/util/List;
       4: invokeinterface #21,  1           // InterfaceMethod java/util/List.iterator:()Ljava/util/Iterator;
       9: astore_2
      10: aload_2
      11: invokeinterface #22,  1           // InterfaceMethod java/util/Iterator.hasNext:()Z
      16: ifeq          105
      19: aload_2
      20: invokeinterface #23,  1           // InterfaceMethod java/util/Iterator.next:()Ljava/lang/Object;
      25: checkcast     #24                 // class org/apache/dubbo/common/config/Configuration
      28: astore_3
      29: aload_3
      30: aload_1
      31: invokeinterface #25,  2           // InterfaceMethod org/apache/dubbo/common/config/Configuration.getProperty:(Ljava/lang/String;)Ljava/lang/Object;
      36: astore        4
      38: aload         4
      40: invokestatic  #26                 // Method org/apache/dubbo/common/config/ConfigurationUtils.isEmptyValue:(Ljava/lang/Object;)Z
      43: ifne          49
      46: aload         4
      48: areturn
      49: goto          102
      52: astore        4
      54: aload_0
      55: getfield      #5                  // Field logger:Lorg/apache/dubbo/common/logger/ErrorTypeAwareLogger;
      58: ldc           #28                 // String 5-5
      60: ldc           #29                 // String
      62: ldc           #29                 // String
      64: new           #30                 // class java/lang/StringBuilder
      67: dup
      68: invokespecial #31                 // Method java/lang/StringBuilder."<init>":()V
      71: ldc           #32                 // String Error when trying to get value for key
      73: invokevirtual #33                 // Method java/lang/StringBuilder.append:(Ljava/lang/String;)Ljava/lang/StringBuilder;
      76: aload_1
      77: invokevirtual #33                 // Method java/lang/StringBuilder.append:(Ljava/lang/String;)Ljava/lang/StringBuilder;
      80: ldc           #34                 // String  from
      82: invokevirtual #33                 // Method java/lang/StringBuilder.append:(Ljava/lang/String;)Ljava/lang/StringBuilder;
      85: aload_3
      86: invokevirtual #35                 // Method java/lang/StringBuilder.append:(Ljava/lang/Object;)Ljava/lang/StringBuilder;
      89: ldc           #36                 // String , will continue to try the next one.
      91: invokevirtual #33                 // Method java/lang/StringBuilder.append:(Ljava/lang/String;)Ljava/lang/StringBuilder;
      94: invokevirtual #37                 // Method java/lang/StringBuilder.toString:()Ljava/lang/String;
      97: invokeinterface #38,  5           // InterfaceMethod org/apache/dubbo/common/logger/ErrorTypeAwareLogger.error:(Ljava/lang/String;Ljava/lang/String;Ljava/lang/String;Ljava/lang/String;)V
     102: goto          10
     105: aconst_null
     106: areturn
    Exception table:
       from    to  target type
          29    48    52   Class java/lang/Exception

  private boolean lambda$new$0(org.apache.dubbo.common.config.Configuration);
    Code:
       0: aload_0
       1: getfield      #8                  // Field configList:Ljava/util/List;
       4: aload_1
       5: invokeinterface #17,  2           // InterfaceMethod java/util/List.contains:(Ljava/lang/Object;)Z
      10: ifne          17
      13: iconst_1
      14: goto          18
      17: iconst_0
      18: ireturn
}
