Compiled from "ConfigurationCache.java"
public class org.apache.dubbo.common.config.ConfigurationCache {
  private final java.util.Map<java.lang.String, java.lang.String> cache;

  public org.apache.dubbo.common.config.ConfigurationCache();
    Code:
       0: aload_0
       1: invokespecial #1                  // Method java/lang/Object."<init>":()V
       4: aload_0
       5: new           #2                  // class java/util/concurrent/ConcurrentHashMap
       8: dup
       9: invokespecial #3                  // Method java/util/concurrent/ConcurrentHashMap."<init>":()V
      12: putfield      #4                  // Field cache:Ljava/util/Map;
      15: return

  public java.lang.String computeIfAbsent(java.lang.String, java.util.function.Function<java.lang.String, java.lang.String>);
    Code:
       0: aload_0
       1: getfield      #4                  // Field cache:Ljava/util/Map;
       4: aload_1
       5: invokeinterface #5,  2            // InterfaceMethod java/util/Map.get:(Ljava/lang/Object;)Ljava/lang/Object;
      10: checkcast     #6                  // class java/lang/String
      13: astore_3
      14: aload_3
      15: ifnonnull     50
      18: aload_0
      19: getfield      #4                  // Field cache:Ljava/util/Map;
      22: aload_1
      23: aload_2
      24: aload_1
      25: invokeinterface #7,  2            // InterfaceMethod java/util/function/Function.apply:(Ljava/lang/Object;)Ljava/lang/Object;
      30: invokeinterface #8,  3            // InterfaceMethod java/util/Map.putIfAbsent:(Ljava/lang/Object;Ljava/lang/Object;)Ljava/lang/Object;
      35: pop
      36: aload_0
      37: getfield      #4                  // Field cache:Ljava/util/Map;
      40: aload_1
      41: invokeinterface #5,  2            // InterfaceMethod java/util/Map.get:(Ljava/lang/Object;)Ljava/lang/Object;
      46: checkcast     #6                  // class java/lang/String
      49: astore_3
      50: aload_3
      51: areturn
}
