Compiled from "Configuration.java"
public interface org.apache.dubbo.common.config.Configuration {
  public static final org.apache.dubbo.common.logger.ErrorTypeAwareLogger interfaceLevelLogger;

  public default java.lang.String getString(java.lang.String);
    Code:
       0: aload_0
       1: ldc           #2                  // class java/lang/String
       3: aload_1
       4: aconst_null
       5: invokeinterface #3,  4            // InterfaceMethod convert:(Ljava/lang/Class;Ljava/lang/String;Ljava/lang/Object;)Ljava/lang/Object;
      10: checkcast     #2                  // class java/lang/String
      13: areturn

  public default java.lang.String getString(java.lang.String, java.lang.String);
    Code:
       0: aload_0
       1: ldc           #2                  // class java/lang/String
       3: aload_1
       4: aload_2
       5: invokeinterface #3,  4            // InterfaceMethod convert:(Ljava/lang/Class;Ljava/lang/String;Ljava/lang/Object;)Ljava/lang/Object;
      10: checkcast     #2                  // class java/lang/String
      13: areturn

  public default int getInt(java.lang.String);
    Code:
       0: aload_0
       1: aload_1
       2: aconst_null
       3: invokeinterface #4,  3            // InterfaceMethod getInteger:(Ljava/lang/String;Ljava/lang/Integer;)Ljava/lang/Integer;
       8: astore_2
       9: aload_2
      10: ifnull        18
      13: aload_2
      14: invokevirtual #5                  // Method java/lang/Integer.intValue:()I
      17: ireturn
      18: new           #6                  // class java/util/NoSuchElementException
      21: dup
      22: new           #7                  // class java/lang/StringBuilder
      25: dup
      26: invokespecial #8                  // Method java/lang/StringBuilder."<init>":()V
      29: bipush        39
      31: invokevirtual #9                  // Method java/lang/StringBuilder.append:(C)Ljava/lang/StringBuilder;
      34: aload_1
      35: invokevirtual #10                 // Method java/lang/StringBuilder.append:(Ljava/lang/String;)Ljava/lang/StringBuilder;
      38: ldc           #11                 // String \' doesn\'t map to an existing object
      40: invokevirtual #10                 // Method java/lang/StringBuilder.append:(Ljava/lang/String;)Ljava/lang/StringBuilder;
      43: invokevirtual #12                 // Method java/lang/StringBuilder.toString:()Ljava/lang/String;
      46: invokespecial #13                 // Method java/util/NoSuchElementException."<init>":(Ljava/lang/String;)V
      49: athrow

  public default int getInt(java.lang.String, int);
    Code:
       0: aload_0
       1: aload_1
       2: aconst_null
       3: invokeinterface #4,  3            // InterfaceMethod getInteger:(Ljava/lang/String;Ljava/lang/Integer;)Ljava/lang/Integer;
       8: astore_3
       9: aload_3
      10: ifnonnull     17
      13: iload_2
      14: goto          21
      17: aload_3
      18: invokevirtual #5                  // Method java/lang/Integer.intValue:()I
      21: ireturn

  public default java.lang.Integer getInteger(java.lang.String, java.lang.Integer);
    Code:
       0: aload_0
       1: ldc           #14                 // class java/lang/Integer
       3: aload_1
       4: aload_2
       5: invokeinterface #3,  4            // InterfaceMethod convert:(Ljava/lang/Class;Ljava/lang/String;Ljava/lang/Object;)Ljava/lang/Object;
      10: checkcast     #14                 // class java/lang/Integer
      13: areturn
      14: astore_3
      15: getstatic     #16                 // Field interfaceLevelLogger:Lorg/apache/dubbo/common/logger/ErrorTypeAwareLogger;
      18: ldc           #17                 // String 0-2
      20: ldc           #18                 // String typo in property value
      22: ldc           #19                 // String This property requires an integer value.
      24: new           #7                  // class java/lang/StringBuilder
      27: dup
      28: invokespecial #8                  // Method java/lang/StringBuilder."<init>":()V
      31: ldc           #20                 // String Actual Class:
      33: invokevirtual #10                 // Method java/lang/StringBuilder.append:(Ljava/lang/String;)Ljava/lang/StringBuilder;
      36: aload_0
      37: invokevirtual #21                 // Method java/lang/Object.getClass:()Ljava/lang/Class;
      40: invokevirtual #22                 // Method java/lang/Class.getName:()Ljava/lang/String;
      43: invokevirtual #10                 // Method java/lang/StringBuilder.append:(Ljava/lang/String;)Ljava/lang/StringBuilder;
      46: invokevirtual #12                 // Method java/lang/StringBuilder.toString:()Ljava/lang/String;
      49: aload_3
      50: invokeinterface #23,  6           // InterfaceMethod org/apache/dubbo/common/logger/ErrorTypeAwareLogger.error:(Ljava/lang/String;Ljava/lang/String;Ljava/lang/String;Ljava/lang/String;Ljava/lang/Throwable;)V
      55: new           #24                 // class java/lang/IllegalStateException
      58: dup
      59: new           #7                  // class java/lang/StringBuilder
      62: dup
      63: invokespecial #8                  // Method java/lang/StringBuilder."<init>":()V
      66: bipush        39
      68: invokevirtual #9                  // Method java/lang/StringBuilder.append:(C)Ljava/lang/StringBuilder;
      71: aload_1
      72: invokevirtual #10                 // Method java/lang/StringBuilder.append:(Ljava/lang/String;)Ljava/lang/StringBuilder;
      75: ldc           #25                 // String \' doesn\'t map to a Integer object
      77: invokevirtual #10                 // Method java/lang/StringBuilder.append:(Ljava/lang/String;)Ljava/lang/StringBuilder;
      80: invokevirtual #12                 // Method java/lang/StringBuilder.toString:()Ljava/lang/String;
      83: aload_3
      84: invokespecial #26                 // Method java/lang/IllegalStateException."<init>":(Ljava/lang/String;Ljava/lang/Throwable;)V
      87: athrow
    Exception table:
       from    to  target type
           0    13    14   Class java/lang/NumberFormatException

  public default boolean getBoolean(java.lang.String);
    Code:
       0: aload_0
       1: aload_1
       2: aconst_null
       3: invokeinterface #27,  3           // InterfaceMethod getBoolean:(Ljava/lang/String;Ljava/lang/Boolean;)Ljava/lang/Boolean;
       8: astore_2
       9: aload_2
      10: ifnull        18
      13: aload_2
      14: invokevirtual #28                 // Method java/lang/Boolean.booleanValue:()Z
      17: ireturn
      18: new           #6                  // class java/util/NoSuchElementException
      21: dup
      22: new           #7                  // class java/lang/StringBuilder
      25: dup
      26: invokespecial #8                  // Method java/lang/StringBuilder."<init>":()V
      29: bipush        39
      31: invokevirtual #9                  // Method java/lang/StringBuilder.append:(C)Ljava/lang/StringBuilder;
      34: aload_1
      35: invokevirtual #10                 // Method java/lang/StringBuilder.append:(Ljava/lang/String;)Ljava/lang/StringBuilder;
      38: ldc           #11                 // String \' doesn\'t map to an existing object
      40: invokevirtual #10                 // Method java/lang/StringBuilder.append:(Ljava/lang/String;)Ljava/lang/StringBuilder;
      43: invokevirtual #12                 // Method java/lang/StringBuilder.toString:()Ljava/lang/String;
      46: invokespecial #13                 // Method java/util/NoSuchElementException."<init>":(Ljava/lang/String;)V
      49: athrow

  public default boolean getBoolean(java.lang.String, boolean);
    Code:
       0: aload_0
       1: aload_1
       2: iload_2
       3: invokestatic  #29                 // InterfaceMethod toBooleanObject:(Z)Ljava/lang/Boolean;
       6: invokeinterface #27,  3           // InterfaceMethod getBoolean:(Ljava/lang/String;Ljava/lang/Boolean;)Ljava/lang/Boolean;
      11: invokevirtual #28                 // Method java/lang/Boolean.booleanValue:()Z
      14: ireturn

  public default java.lang.Boolean getBoolean(java.lang.String, java.lang.Boolean);
    Code:
       0: aload_0
       1: ldc           #30                 // class java/lang/Boolean
       3: aload_1
       4: aload_2
       5: invokeinterface #3,  4            // InterfaceMethod convert:(Ljava/lang/Class;Ljava/lang/String;Ljava/lang/Object;)Ljava/lang/Object;
      10: checkcast     #30                 // class java/lang/Boolean
      13: areturn
      14: astore_3
      15: new           #24                 // class java/lang/IllegalStateException
      18: dup
      19: new           #7                  // class java/lang/StringBuilder
      22: dup
      23: invokespecial #8                  // Method java/lang/StringBuilder."<init>":()V
      26: ldc           #32                 // String Try to get \'
      28: invokevirtual #10                 // Method java/lang/StringBuilder.append:(Ljava/lang/String;)Ljava/lang/StringBuilder;
      31: aload_1
      32: invokevirtual #10                 // Method java/lang/StringBuilder.append:(Ljava/lang/String;)Ljava/lang/StringBuilder;
      35: ldc           #33                 // String \' failed, maybe because this key doesn\'t map to a Boolean object
      37: invokevirtual #10                 // Method java/lang/StringBuilder.append:(Ljava/lang/String;)Ljava/lang/StringBuilder;
      40: invokevirtual #12                 // Method java/lang/StringBuilder.toString:()Ljava/lang/String;
      43: aload_3
      44: invokespecial #26                 // Method java/lang/IllegalStateException."<init>":(Ljava/lang/String;Ljava/lang/Throwable;)V
      47: athrow
    Exception table:
       from    to  target type
           0    13    14   Class java/lang/Exception

  public default java.lang.Object getProperty(java.lang.String);
    Code:
       0: aload_0
       1: aload_1
       2: aconst_null
       3: invokeinterface #34,  3           // InterfaceMethod getProperty:(Ljava/lang/String;Ljava/lang/Object;)Ljava/lang/Object;
       8: areturn

  public default java.lang.Object getProperty(java.lang.String, java.lang.Object);
    Code:
       0: aload_0
       1: aload_1
       2: invokeinterface #35,  2           // InterfaceMethod getInternalProperty:(Ljava/lang/String;)Ljava/lang/Object;
       7: astore_3
       8: aload_3
       9: ifnull        16
      12: aload_3
      13: goto          17
      16: aload_2
      17: areturn

  public abstract java.lang.Object getInternalProperty(java.lang.String);

  public default boolean containsKey(java.lang.String);
    Code:
       0: aload_0
       1: aload_1
       2: invokeinterface #36,  2           // InterfaceMethod getProperty:(Ljava/lang/String;)Ljava/lang/Object;
       7: invokestatic  #37                 // Method org/apache/dubbo/common/config/ConfigurationUtils.isEmptyValue:(Ljava/lang/Object;)Z
      10: ifne          17
      13: iconst_1
      14: goto          18
      17: iconst_0
      18: ireturn

  public default <T> T convert(java.lang.Class<T>, java.lang.String, T);
    Code:
       0: aload_0
       1: aload_2
       2: invokeinterface #36,  2           // InterfaceMethod getProperty:(Ljava/lang/String;)Ljava/lang/Object;
       7: checkcast     #2                  // class java/lang/String
      10: astore        4
      12: aload         4
      14: ifnonnull     19
      17: aload_3
      18: areturn
      19: aload         4
      21: astore        5
      23: aload_1
      24: aload         4
      26: invokevirtual #38                 // Method java/lang/Class.isInstance:(Ljava/lang/Object;)Z
      29: ifeq          39
      32: aload_1
      33: aload         4
      35: invokevirtual #39                 // Method java/lang/Class.cast:(Ljava/lang/Object;)Ljava/lang/Object;
      38: areturn
      39: ldc           #30                 // class java/lang/Boolean
      41: aload_1
      42: invokevirtual #40                 // Method java/lang/Object.equals:(Ljava/lang/Object;)Z
      45: ifne          58
      48: getstatic     #41                 // Field java/lang/Boolean.TYPE:Ljava/lang/Class;
      51: aload_1
      52: invokevirtual #40                 // Method java/lang/Object.equals:(Ljava/lang/Object;)Z
      55: ifeq          68
      58: aload         4
      60: invokestatic  #42                 // Method java/lang/Boolean.valueOf:(Ljava/lang/String;)Ljava/lang/Boolean;
      63: astore        5
      65: goto          278
      68: ldc           #43                 // class java/lang/Number
      70: aload_1
      71: invokevirtual #44                 // Method java/lang/Class.isAssignableFrom:(Ljava/lang/Class;)Z
      74: ifne          84
      77: aload_1
      78: invokevirtual #45                 // Method java/lang/Class.isPrimitive:()Z
      81: ifeq          258
      84: ldc           #14                 // class java/lang/Integer
      86: aload_1
      87: invokevirtual #40                 // Method java/lang/Object.equals:(Ljava/lang/Object;)Z
      90: ifne          103
      93: getstatic     #46                 // Field java/lang/Integer.TYPE:Ljava/lang/Class;
      96: aload_1
      97: invokevirtual #40                 // Method java/lang/Object.equals:(Ljava/lang/Object;)Z
     100: ifeq          113
     103: aload         4
     105: invokestatic  #47                 // Method java/lang/Integer.valueOf:(Ljava/lang/String;)Ljava/lang/Integer;
     108: astore        5
     110: goto          278
     113: ldc           #48                 // class java/lang/Long
     115: aload_1
     116: invokevirtual #40                 // Method java/lang/Object.equals:(Ljava/lang/Object;)Z
     119: ifne          132
     122: getstatic     #49                 // Field java/lang/Long.TYPE:Ljava/lang/Class;
     125: aload_1
     126: invokevirtual #40                 // Method java/lang/Object.equals:(Ljava/lang/Object;)Z
     129: ifeq          142
     132: aload         4
     134: invokestatic  #50                 // Method java/lang/Long.valueOf:(Ljava/lang/String;)Ljava/lang/Long;
     137: astore        5
     139: goto          278
     142: ldc           #51                 // class java/lang/Byte
     144: aload_1
     145: invokevirtual #40                 // Method java/lang/Object.equals:(Ljava/lang/Object;)Z
     148: ifne          161
     151: getstatic     #52                 // Field java/lang/Byte.TYPE:Ljava/lang/Class;
     154: aload_1
     155: invokevirtual #40                 // Method java/lang/Object.equals:(Ljava/lang/Object;)Z
     158: ifeq          171
     161: aload         4
     163: invokestatic  #53                 // Method java/lang/Byte.valueOf:(Ljava/lang/String;)Ljava/lang/Byte;
     166: astore        5
     168: goto          278
     171: ldc           #54                 // class java/lang/Short
     173: aload_1
     174: invokevirtual #40                 // Method java/lang/Object.equals:(Ljava/lang/Object;)Z
     177: ifne          190
     180: getstatic     #55                 // Field java/lang/Short.TYPE:Ljava/lang/Class;
     183: aload_1
     184: invokevirtual #40                 // Method java/lang/Object.equals:(Ljava/lang/Object;)Z
     187: ifeq          200
     190: aload         4
     192: invokestatic  #56                 // Method java/lang/Short.valueOf:(Ljava/lang/String;)Ljava/lang/Short;
     195: astore        5
     197: goto          278
     200: ldc           #57                 // class java/lang/Float
     202: aload_1
     203: invokevirtual #40                 // Method java/lang/Object.equals:(Ljava/lang/Object;)Z
     206: ifne          219
     209: getstatic     #58                 // Field java/lang/Float.TYPE:Ljava/lang/Class;
     212: aload_1
     213: invokevirtual #40                 // Method java/lang/Object.equals:(Ljava/lang/Object;)Z
     216: ifeq          229
     219: aload         4
     221: invokestatic  #59                 // Method java/lang/Float.valueOf:(Ljava/lang/String;)Ljava/lang/Float;
     224: astore        5
     226: goto          278
     229: ldc           #60                 // class java/lang/Double
     231: aload_1
     232: invokevirtual #40                 // Method java/lang/Object.equals:(Ljava/lang/Object;)Z
     235: ifne          248
     238: getstatic     #61                 // Field java/lang/Double.TYPE:Ljava/lang/Class;
     241: aload_1
     242: invokevirtual #40                 // Method java/lang/Object.equals:(Ljava/lang/Object;)Z
     245: ifeq          278
     248: aload         4
     250: invokestatic  #62                 // Method java/lang/Double.valueOf:(Ljava/lang/String;)Ljava/lang/Double;
     253: astore        5
     255: goto          278
     258: aload_1
     259: invokevirtual #63                 // Method java/lang/Class.isEnum:()Z
     262: ifeq          278
     265: aload_1
     266: ldc           #64                 // class java/lang/Enum
     268: invokevirtual #65                 // Method java/lang/Class.asSubclass:(Ljava/lang/Class;)Ljava/lang/Class;
     271: aload         4
     273: invokestatic  #66                 // Method java/lang/Enum.valueOf:(Ljava/lang/Class;Ljava/lang/String;)Ljava/lang/Enum;
     276: astore        5
     278: aload_1
     279: aload         5
     281: invokevirtual #39                 // Method java/lang/Class.cast:(Ljava/lang/Object;)Ljava/lang/Object;
     284: areturn

  public static java.lang.Boolean toBooleanObject(boolean);
    Code:
       0: iload_0
       1: ifeq          10
       4: getstatic     #67                 // Field java/lang/Boolean.TRUE:Ljava/lang/Boolean;
       7: goto          13
      10: getstatic     #68                 // Field java/lang/Boolean.FALSE:Ljava/lang/Boolean;
      13: areturn

  static {};
    Code:
       0: ldc           #69                 // class org/apache/dubbo/common/config/Configuration
       2: invokestatic  #70                 // Method org/apache/dubbo/common/logger/LoggerFactory.getErrorTypeAwareLogger:(Ljava/lang/Class;)Lorg/apache/dubbo/common/logger/ErrorTypeAwareLogger;
       5: putstatic     #16                 // Field interfaceLevelLogger:Lorg/apache/dubbo/common/logger/ErrorTypeAwareLogger;
       8: return
}
