Compiled from "ConfigurationUtils.java"
public final class org.apache.dubbo.common.config.ConfigurationUtils {
  private static final org.apache.dubbo.common.logger.ErrorTypeAwareLogger logger;

  private static final java.util.List<java.lang.String> securityKey;

  private org.apache.dubbo.common.config.ConfigurationUtils();
    Code:
       0: aload_0
       1: invokespecial #3                  // Method java/lang/Object."<init>":()V
       4: new           #4                  // class java/lang/UnsupportedOperationException
       7: dup
       8: ldc           #5                  // String No instance of \'ConfigurationUtils\' for you!
      10: invokespecial #6                  // Method java/lang/UnsupportedOperationException."<init>":(Ljava/lang/String;)V
      13: athrow

  public static org.apache.dubbo.common.config.Configuration getSystemConfiguration(org.apache.dubbo.rpc.model.ScopeModel);
    Code:
       0: aload_0
       1: invokestatic  #7                  // Method getScopeModelOrDefaultApplicationModel:(Lorg/apache/dubbo/rpc/model/ScopeModel;)Lorg/apache/dubbo/rpc/model/ScopeModel;
       4: invokevirtual #8                  // Method org/apache/dubbo/rpc/model/ScopeModel.getModelEnvironment:()Lorg/apache/dubbo/common/config/Environment;
       7: invokevirtual #9                  // Method org/apache/dubbo/common/config/Environment.getSystemConfiguration:()Lorg/apache/dubbo/common/config/SystemConfiguration;
      10: areturn

  public static org.apache.dubbo.common.config.Configuration getEnvConfiguration(org.apache.dubbo.rpc.model.ScopeModel);
    Code:
       0: aload_0
       1: invokestatic  #7                  // Method getScopeModelOrDefaultApplicationModel:(Lorg/apache/dubbo/rpc/model/ScopeModel;)Lorg/apache/dubbo/rpc/model/ScopeModel;
       4: invokevirtual #8                  // Method org/apache/dubbo/rpc/model/ScopeModel.getModelEnvironment:()Lorg/apache/dubbo/common/config/Environment;
       7: invokevirtual #10                 // Method org/apache/dubbo/common/config/Environment.getEnvironmentConfiguration:()Lorg/apache/dubbo/common/config/EnvironmentConfiguration;
      10: areturn

  public static org.apache.dubbo.common.config.Configuration getGlobalConfiguration(org.apache.dubbo.rpc.model.ScopeModel);
    Code:
       0: aload_0
       1: invokestatic  #7                  // Method getScopeModelOrDefaultApplicationModel:(Lorg/apache/dubbo/rpc/model/ScopeModel;)Lorg/apache/dubbo/rpc/model/ScopeModel;
       4: invokevirtual #8                  // Method org/apache/dubbo/rpc/model/ScopeModel.getModelEnvironment:()Lorg/apache/dubbo/common/config/Environment;
       7: invokevirtual #11                 // Method org/apache/dubbo/common/config/Environment.getConfiguration:()Lorg/apache/dubbo/common/config/CompositeConfiguration;
      10: areturn

  public static org.apache.dubbo.common.config.Configuration getDynamicGlobalConfiguration(org.apache.dubbo.rpc.model.ScopeModel);
    Code:
       0: aload_0
       1: invokevirtual #8                  // Method org/apache/dubbo/rpc/model/ScopeModel.getModelEnvironment:()Lorg/apache/dubbo/common/config/Environment;
       4: invokevirtual #12                 // Method org/apache/dubbo/common/config/Environment.getDynamicGlobalConfiguration:()Lorg/apache/dubbo/common/config/Configuration;
       7: areturn

  public static int getServerShutdownTimeout(org.apache.dubbo.rpc.model.ScopeModel);
    Code:
       0: sipush        10000
       3: istore_1
       4: aload_0
       5: invokestatic  #13                 // Method getGlobalConfiguration:(Lorg/apache/dubbo/rpc/model/ScopeModel;)Lorg/apache/dubbo/common/config/Configuration;
       8: astore_2
       9: aload_2
      10: ldc           #14                 // String dubbo.service.shutdown.wait
      12: invokeinterface #15,  2           // InterfaceMethod org/apache/dubbo/common/config/Configuration.getString:(Ljava/lang/String;)Ljava/lang/String;
      17: invokestatic  #16                 // Method org/apache/dubbo/common/utils/StringUtils.trim:(Ljava/lang/String;)Ljava/lang/String;
      20: astore_3
      21: aload_3
      22: invokestatic  #17                 // Method org/apache/dubbo/common/utils/StringUtils.isNotEmpty:(Ljava/lang/String;)Z
      25: ifeq          41
      28: aload_3
      29: invokestatic  #18                 // Method java/lang/Integer.parseInt:(Ljava/lang/String;)I
      32: istore_1
      33: goto          74
      36: astore        4
      38: goto          74
      41: aload_2
      42: ldc           #20                 // String dubbo.service.shutdown.wait.seconds
      44: invokeinterface #15,  2           // InterfaceMethod org/apache/dubbo/common/config/Configuration.getString:(Ljava/lang/String;)Ljava/lang/String;
      49: invokestatic  #16                 // Method org/apache/dubbo/common/utils/StringUtils.trim:(Ljava/lang/String;)Ljava/lang/String;
      52: astore_3
      53: aload_3
      54: invokestatic  #17                 // Method org/apache/dubbo/common/utils/StringUtils.isNotEmpty:(Ljava/lang/String;)Z
      57: ifeq          74
      60: aload_3
      61: invokestatic  #18                 // Method java/lang/Integer.parseInt:(Ljava/lang/String;)I
      64: sipush        1000
      67: imul
      68: istore_1
      69: goto          74
      72: astore        4
      74: iload_1
      75: ireturn
    Exception table:
       from    to  target type
          28    33    36   Class java/lang/Exception
          60    69    72   Class java/lang/Exception

  public static java.lang.String getCachedDynamicProperty(org.apache.dubbo.rpc.model.ScopeModel, java.lang.String, java.lang.String);
    Code:
       0: aload_0
       1: invokestatic  #7                  // Method getScopeModelOrDefaultApplicationModel:(Lorg/apache/dubbo/rpc/model/ScopeModel;)Lorg/apache/dubbo/rpc/model/ScopeModel;
       4: astore_3
       5: aload_3
       6: invokevirtual #21                 // Method org/apache/dubbo/rpc/model/ScopeModel.getBeanFactory:()Lorg/apache/dubbo/common/beans/factory/ScopeBeanFactory;
       9: ldc           #22                 // class org/apache/dubbo/common/config/ConfigurationCache
      11: invokevirtual #23                 // Method org/apache/dubbo/common/beans/factory/ScopeBeanFactory.getBean:(Ljava/lang/Class;)Ljava/lang/Object;
      14: checkcast     #22                 // class org/apache/dubbo/common/config/ConfigurationCache
      17: astore        4
      19: aload         4
      21: aload_1
      22: aload_3
      23: invokedynamic #24,  0             // InvokeDynamic #0:apply:(Lorg/apache/dubbo/rpc/model/ScopeModel;)Ljava/util/function/Function;
      28: invokevirtual #25                 // Method org/apache/dubbo/common/config/ConfigurationCache.computeIfAbsent:(Ljava/lang/String;Ljava/util/function/Function;)Ljava/lang/String;
      31: astore        5
      33: aload         5
      35: invokestatic  #26                 // Method org/apache/dubbo/common/utils/StringUtils.isEmpty:(Ljava/lang/String;)Z
      38: ifeq          45
      41: aload_2
      42: goto          47
      45: aload         5
      47: areturn

  private static org.apache.dubbo.rpc.model.ScopeModel getScopeModelOrDefaultApplicationModel(org.apache.dubbo.rpc.model.ScopeModel);
    Code:
       0: aload_0
       1: ifnonnull     8
       4: invokestatic  #27                 // Method org/apache/dubbo/rpc/model/ApplicationModel.defaultModel:()Lorg/apache/dubbo/rpc/model/ApplicationModel;
       7: areturn
       8: aload_0
       9: areturn

  public static java.lang.String getDynamicProperty(org.apache.dubbo.rpc.model.ScopeModel, java.lang.String);
    Code:
       0: aload_0
       1: aload_1
       2: aconst_null
       3: invokestatic  #28                 // Method getDynamicProperty:(Lorg/apache/dubbo/rpc/model/ScopeModel;Ljava/lang/String;Ljava/lang/String;)Ljava/lang/String;
       6: areturn

  public static java.lang.String getDynamicProperty(org.apache.dubbo.rpc.model.ScopeModel, java.lang.String, java.lang.String);
    Code:
       0: aload_0
       1: invokestatic  #29                 // Method getDynamicGlobalConfiguration:(Lorg/apache/dubbo/rpc/model/ScopeModel;)Lorg/apache/dubbo/common/config/Configuration;
       4: aload_1
       5: aload_2
       6: invokeinterface #30,  3           // InterfaceMethod org/apache/dubbo/common/config/Configuration.getString:(Ljava/lang/String;Ljava/lang/String;)Ljava/lang/String;
      11: invokestatic  #16                 // Method org/apache/dubbo/common/utils/StringUtils.trim:(Ljava/lang/String;)Ljava/lang/String;
      14: areturn

  public static java.lang.String getProperty(org.apache.dubbo.rpc.model.ScopeModel, java.lang.String);
    Code:
       0: aload_0
       1: aload_1
       2: aconst_null
       3: invokestatic  #31                 // Method getProperty:(Lorg/apache/dubbo/rpc/model/ScopeModel;Ljava/lang/String;Ljava/lang/String;)Ljava/lang/String;
       6: areturn

  public static java.lang.String getProperty(org.apache.dubbo.rpc.model.ScopeModel, java.lang.String, java.lang.String);
    Code:
       0: aload_0
       1: invokestatic  #13                 // Method getGlobalConfiguration:(Lorg/apache/dubbo/rpc/model/ScopeModel;)Lorg/apache/dubbo/common/config/Configuration;
       4: aload_1
       5: aload_2
       6: invokeinterface #30,  3           // InterfaceMethod org/apache/dubbo/common/config/Configuration.getString:(Ljava/lang/String;Ljava/lang/String;)Ljava/lang/String;
      11: invokestatic  #16                 // Method org/apache/dubbo/common/utils/StringUtils.trim:(Ljava/lang/String;)Ljava/lang/String;
      14: areturn

  public static int get(org.apache.dubbo.rpc.model.ScopeModel, java.lang.String, int);
    Code:
       0: aload_0
       1: invokestatic  #13                 // Method getGlobalConfiguration:(Lorg/apache/dubbo/rpc/model/ScopeModel;)Lorg/apache/dubbo/common/config/Configuration;
       4: aload_1
       5: iload_2
       6: invokeinterface #32,  3           // InterfaceMethod org/apache/dubbo/common/config/Configuration.getInt:(Ljava/lang/String;I)I
      11: ireturn

  public static java.util.Map<java.lang.String, java.lang.String> parseProperties(java.lang.String) throws java.io.IOException;
    Code:
       0: new           #33                 // class java/util/HashMap
       3: dup
       4: invokespecial #34                 // Method java/util/HashMap."<init>":()V
       7: astore_1
       8: aload_0
       9: invokestatic  #26                 // Method org/apache/dubbo/common/utils/StringUtils.isEmpty:(Ljava/lang/String;)Z
      12: ifeq          34
      15: getstatic     #35                 // Field logger:Lorg/apache/dubbo/common/logger/ErrorTypeAwareLogger;
      18: ldc           #36                 // String 0-12
      20: ldc           #37                 // String
      22: ldc           #37                 // String
      24: ldc           #38                 // String Config center was specified, but no config item found.
      26: invokeinterface #39,  5           // InterfaceMethod org/apache/dubbo/common/logger/ErrorTypeAwareLogger.warn:(Ljava/lang/String;Ljava/lang/String;Ljava/lang/String;Ljava/lang/String;)V
      31: goto          70
      34: new           #40                 // class java/util/Properties
      37: dup
      38: invokespecial #41                 // Method java/util/Properties."<init>":()V
      41: astore_2
      42: aload_2
      43: new           #42                 // class java/io/StringReader
      46: dup
      47: aload_0
      48: invokespecial #43                 // Method java/io/StringReader."<init>":(Ljava/lang/String;)V
      51: invokevirtual #44                 // Method java/util/Properties.load:(Ljava/io/Reader;)V
      54: aload_2
      55: invokevirtual #45                 // Method java/util/Properties.stringPropertyNames:()Ljava/util/Set;
      58: aload_1
      59: aload_2
      60: invokedynamic #46,  0             // InvokeDynamic #1:accept:(Ljava/util/Map;Ljava/util/Properties;)Ljava/util/function/Consumer;
      65: invokeinterface #47,  2           // InterfaceMethod java/util/Set.forEach:(Ljava/util/function/Consumer;)V
      70: aload_1
      71: areturn

  public static boolean isEmptyValue(java.lang.Object);
    Code:
       0: aload_0
       1: ifnull        21
       4: aload_0
       5: instanceof    #48                 // class java/lang/String
       8: ifeq          25
      11: aload_0
      12: checkcast     #48                 // class java/lang/String
      15: invokestatic  #49                 // Method org/apache/dubbo/common/utils/StringUtils.isBlank:(Ljava/lang/CharSequence;)Z
      18: ifeq          25
      21: iconst_1
      22: goto          26
      25: iconst_0
      26: ireturn

  public static <V> java.util.Map<java.lang.String, V> getSubProperties(java.util.Collection<java.util.Map<java.lang.String, V>>, java.lang.String);
    Code:
       0: new           #50                 // class java/util/LinkedHashMap
       3: dup
       4: invokespecial #51                 // Method java/util/LinkedHashMap."<init>":()V
       7: astore_2
       8: aload_0
       9: invokeinterface #52,  1           // InterfaceMethod java/util/Collection.iterator:()Ljava/util/Iterator;
      14: astore_3
      15: aload_3
      16: invokeinterface #53,  1           // InterfaceMethod java/util/Iterator.hasNext:()Z
      21: ifeq          46
      24: aload_3
      25: invokeinterface #54,  1           // InterfaceMethod java/util/Iterator.next:()Ljava/lang/Object;
      30: checkcast     #55                 // class java/util/Map
      33: astore        4
      35: aload         4
      37: aload_1
      38: aload_2
      39: invokestatic  #56                 // Method getSubProperties:(Ljava/util/Map;Ljava/lang/String;Ljava/util/Map;)Ljava/util/Map;
      42: pop
      43: goto          15
      46: aload_2
      47: areturn

  public static <V> java.util.Map<java.lang.String, V> getSubProperties(java.util.Map<java.lang.String, V>, java.lang.String);
    Code:
       0: aload_0
       1: aload_1
       2: aconst_null
       3: invokestatic  #56                 // Method getSubProperties:(Ljava/util/Map;Ljava/lang/String;Ljava/util/Map;)Ljava/util/Map;
       6: areturn

  private static <V> java.util.Map<java.lang.String, V> getSubProperties(java.util.Map<java.lang.String, V>, java.lang.String, java.util.Map<java.lang.String, V>);
    Code:
       0: aload_1
       1: ldc           #57                 // String .
       3: invokevirtual #58                 // Method java/lang/String.endsWith:(Ljava/lang/String;)Z
       6: ifne          29
       9: new           #59                 // class java/lang/StringBuilder
      12: dup
      13: invokespecial #60                 // Method java/lang/StringBuilder."<init>":()V
      16: aload_1
      17: invokevirtual #61                 // Method java/lang/StringBuilder.append:(Ljava/lang/String;)Ljava/lang/StringBuilder;
      20: ldc           #57                 // String .
      22: invokevirtual #61                 // Method java/lang/StringBuilder.append:(Ljava/lang/String;)Ljava/lang/StringBuilder;
      25: invokevirtual #62                 // Method java/lang/StringBuilder.toString:()Ljava/lang/String;
      28: astore_1
      29: aconst_null
      30: aload_2
      31: if_acmpne     42
      34: new           #50                 // class java/util/LinkedHashMap
      37: dup
      38: invokespecial #51                 // Method java/util/LinkedHashMap."<init>":()V
      41: astore_2
      42: aload_0
      43: invokestatic  #63                 // Method org/apache/dubbo/common/utils/CollectionUtils.isNotEmptyMap:(Ljava/util/Map;)Z
      46: ifeq          217
      49: aload_0
      50: dup
      51: astore        4
      53: monitorenter
      54: new           #33                 // class java/util/HashMap
      57: dup
      58: aload_0
      59: invokespecial #64                 // Method java/util/HashMap."<init>":(Ljava/util/Map;)V
      62: astore_3
      63: aload         4
      65: monitorexit
      66: goto          77
      69: astore        5
      71: aload         4
      73: monitorexit
      74: aload         5
      76: athrow
      77: aload_3
      78: invokeinterface #65,  1           // InterfaceMethod java/util/Map.entrySet:()Ljava/util/Set;
      83: invokeinterface #66,  1           // InterfaceMethod java/util/Set.iterator:()Ljava/util/Iterator;
      88: astore        4
      90: aload         4
      92: invokeinterface #53,  1           // InterfaceMethod java/util/Iterator.hasNext:()Z
      97: ifeq          217
     100: aload         4
     102: invokeinterface #54,  1           // InterfaceMethod java/util/Iterator.next:()Ljava/lang/Object;
     107: checkcast     #67                 // class java/util/Map$Entry
     110: astore        5
     112: aload         5
     114: invokeinterface #68,  1           // InterfaceMethod java/util/Map$Entry.getKey:()Ljava/lang/Object;
     119: checkcast     #48                 // class java/lang/String
     122: astore        6
     124: aload         5
     126: invokeinterface #69,  1           // InterfaceMethod java/util/Map$Entry.getValue:()Ljava/lang/Object;
     131: astore        7
     133: aload         6
     135: aload_1
     136: invokestatic  #70                 // Method org/apache/dubbo/common/utils/StringUtils.startsWithIgnoreCase:(Ljava/lang/String;Ljava/lang/String;)Z
     139: ifeq          214
     142: aload         6
     144: invokevirtual #71                 // Method java/lang/String.length:()I
     147: aload_1
     148: invokevirtual #71                 // Method java/lang/String.length:()I
     151: if_icmple     214
     154: aload         7
     156: invokestatic  #72                 // Method isEmptyValue:(Ljava/lang/Object;)Z
     159: ifne          214
     162: aload         6
     164: aload_1
     165: invokevirtual #71                 // Method java/lang/String.length:()I
     168: invokevirtual #73                 // Method java/lang/String.substring:(I)Ljava/lang/String;
     171: astore        8
     173: aload         8
     175: ldc           #74                 // String -
     177: invokestatic  #75                 // Method org/apache/dubbo/common/utils/StringUtils.convertToSplitName:(Ljava/lang/String;Ljava/lang/String;)Ljava/lang/String;
     180: astore        9
     182: aload_2
     183: aload         9
     185: aload         7
     187: invokeinterface #76,  3           // InterfaceMethod java/util/Map.putIfAbsent:(Ljava/lang/Object;Ljava/lang/Object;)Ljava/lang/Object;
     192: pop
     193: aload         8
     195: aload         9
     197: invokestatic  #77                 // Method java/util/Objects.equals:(Ljava/lang/Object;Ljava/lang/Object;)Z
     200: ifne          214
     203: aload_2
     204: aload         8
     206: aload         7
     208: invokeinterface #76,  3           // InterfaceMethod java/util/Map.putIfAbsent:(Ljava/lang/Object;Ljava/lang/Object;)Ljava/lang/Object;
     213: pop
     214: goto          90
     217: aload_2
     218: areturn
    Exception table:
       from    to  target type
          54    66    69   any
          69    74    69   any

  public static <V> boolean hasSubProperties(java.util.Collection<java.util.Map<java.lang.String, V>>, java.lang.String);
    Code:
       0: aload_1
       1: ldc           #57                 // String .
       3: invokevirtual #58                 // Method java/lang/String.endsWith:(Ljava/lang/String;)Z
       6: ifne          29
       9: new           #59                 // class java/lang/StringBuilder
      12: dup
      13: invokespecial #60                 // Method java/lang/StringBuilder."<init>":()V
      16: aload_1
      17: invokevirtual #61                 // Method java/lang/StringBuilder.append:(Ljava/lang/String;)Ljava/lang/StringBuilder;
      20: ldc           #57                 // String .
      22: invokevirtual #61                 // Method java/lang/StringBuilder.append:(Ljava/lang/String;)Ljava/lang/StringBuilder;
      25: invokevirtual #62                 // Method java/lang/StringBuilder.toString:()Ljava/lang/String;
      28: astore_1
      29: aload_0
      30: invokeinterface #52,  1           // InterfaceMethod java/util/Collection.iterator:()Ljava/util/Iterator;
      35: astore_2
      36: aload_2
      37: invokeinterface #53,  1           // InterfaceMethod java/util/Iterator.hasNext:()Z
      42: ifeq          68
      45: aload_2
      46: invokeinterface #54,  1           // InterfaceMethod java/util/Iterator.next:()Ljava/lang/Object;
      51: checkcast     #55                 // class java/util/Map
      54: astore_3
      55: aload_3
      56: aload_1
      57: invokestatic  #78                 // Method hasSubProperties:(Ljava/util/Map;Ljava/lang/String;)Z
      60: ifeq          65
      63: iconst_1
      64: ireturn
      65: goto          36
      68: iconst_0
      69: ireturn

  public static <V> boolean hasSubProperties(java.util.Map<java.lang.String, V>, java.lang.String);
    Code:
       0: aload_1
       1: ldc           #57                 // String .
       3: invokevirtual #58                 // Method java/lang/String.endsWith:(Ljava/lang/String;)Z
       6: ifne          29
       9: new           #59                 // class java/lang/StringBuilder
      12: dup
      13: invokespecial #60                 // Method java/lang/StringBuilder."<init>":()V
      16: aload_1
      17: invokevirtual #61                 // Method java/lang/StringBuilder.append:(Ljava/lang/String;)Ljava/lang/StringBuilder;
      20: ldc           #57                 // String .
      22: invokevirtual #61                 // Method java/lang/StringBuilder.append:(Ljava/lang/String;)Ljava/lang/StringBuilder;
      25: invokevirtual #62                 // Method java/lang/StringBuilder.toString:()Ljava/lang/String;
      28: astore_1
      29: aload_0
      30: dup
      31: astore_3
      32: monitorenter
      33: new           #33                 // class java/util/HashMap
      36: dup
      37: aload_0
      38: invokespecial #64                 // Method java/util/HashMap."<init>":(Ljava/util/Map;)V
      41: astore_2
      42: aload_3
      43: monitorexit
      44: goto          54
      47: astore        4
      49: aload_3
      50: monitorexit
      51: aload         4
      53: athrow
      54: aload_2
      55: invokeinterface #65,  1           // InterfaceMethod java/util/Map.entrySet:()Ljava/util/Set;
      60: invokeinterface #66,  1           // InterfaceMethod java/util/Set.iterator:()Ljava/util/Iterator;
      65: astore_3
      66: aload_3
      67: invokeinterface #53,  1           // InterfaceMethod java/util/Iterator.hasNext:()Z
      72: ifeq          137
      75: aload_3
      76: invokeinterface #54,  1           // InterfaceMethod java/util/Iterator.next:()Ljava/lang/Object;
      81: checkcast     #67                 // class java/util/Map$Entry
      84: astore        4
      86: aload         4
      88: invokeinterface #68,  1           // InterfaceMethod java/util/Map$Entry.getKey:()Ljava/lang/Object;
      93: checkcast     #48                 // class java/lang/String
      96: astore        5
      98: aload         5
     100: aload_1
     101: invokestatic  #70                 // Method org/apache/dubbo/common/utils/StringUtils.startsWithIgnoreCase:(Ljava/lang/String;Ljava/lang/String;)Z
     104: ifeq          134
     107: aload         5
     109: invokevirtual #71                 // Method java/lang/String.length:()I
     112: aload_1
     113: invokevirtual #71                 // Method java/lang/String.length:()I
     116: if_icmple     134
     119: aload         4
     121: invokeinterface #69,  1           // InterfaceMethod java/util/Map$Entry.getValue:()Ljava/lang/Object;
     126: invokestatic  #72                 // Method isEmptyValue:(Ljava/lang/Object;)Z
     129: ifne          134
     132: iconst_1
     133: ireturn
     134: goto          66
     137: iconst_0
     138: ireturn
    Exception table:
       from    to  target type
          33    44    47   any
          47    51    47   any

  public static <V> java.util.Set<java.lang.String> getSubIds(java.util.Collection<java.util.Map<java.lang.String, V>>, java.lang.String);
    Code:
       0: aload_1
       1: ldc           #57                 // String .
       3: invokevirtual #58                 // Method java/lang/String.endsWith:(Ljava/lang/String;)Z
       6: ifne          29
       9: new           #59                 // class java/lang/StringBuilder
      12: dup
      13: invokespecial #60                 // Method java/lang/StringBuilder."<init>":()V
      16: aload_1
      17: invokevirtual #61                 // Method java/lang/StringBuilder.append:(Ljava/lang/String;)Ljava/lang/StringBuilder;
      20: ldc           #57                 // String .
      22: invokevirtual #61                 // Method java/lang/StringBuilder.append:(Ljava/lang/String;)Ljava/lang/StringBuilder;
      25: invokevirtual #62                 // Method java/lang/StringBuilder.toString:()Ljava/lang/String;
      28: astore_1
      29: new           #79                 // class java/util/LinkedHashSet
      32: dup
      33: invokespecial #80                 // Method java/util/LinkedHashSet."<init>":()V
      36: astore_2
      37: aload_0
      38: invokeinterface #52,  1           // InterfaceMethod java/util/Collection.iterator:()Ljava/util/Iterator;
      43: astore_3
      44: aload_3
      45: invokeinterface #53,  1           // InterfaceMethod java/util/Iterator.hasNext:()Z
      50: ifeq          231
      53: aload_3
      54: invokeinterface #54,  1           // InterfaceMethod java/util/Iterator.next:()Ljava/lang/Object;
      59: checkcast     #55                 // class java/util/Map
      62: astore        4
      64: aload         4
      66: dup
      67: astore        6
      69: monitorenter
      70: new           #33                 // class java/util/HashMap
      73: dup
      74: aload         4
      76: invokespecial #64                 // Method java/util/HashMap."<init>":(Ljava/util/Map;)V
      79: astore        5
      81: aload         6
      83: monitorexit
      84: goto          95
      87: astore        7
      89: aload         6
      91: monitorexit
      92: aload         7
      94: athrow
      95: aload         5
      97: invokeinterface #65,  1           // InterfaceMethod java/util/Map.entrySet:()Ljava/util/Set;
     102: invokeinterface #66,  1           // InterfaceMethod java/util/Set.iterator:()Ljava/util/Iterator;
     107: astore        6
     109: aload         6
     111: invokeinterface #53,  1           // InterfaceMethod java/util/Iterator.hasNext:()Z
     116: ifeq          228
     119: aload         6
     121: invokeinterface #54,  1           // InterfaceMethod java/util/Iterator.next:()Ljava/lang/Object;
     126: checkcast     #67                 // class java/util/Map$Entry
     129: astore        7
     131: aload         7
     133: invokeinterface #68,  1           // InterfaceMethod java/util/Map$Entry.getKey:()Ljava/lang/Object;
     138: checkcast     #48                 // class java/lang/String
     141: astore        8
     143: aload         7
     145: invokeinterface #69,  1           // InterfaceMethod java/util/Map$Entry.getValue:()Ljava/lang/Object;
     150: astore        9
     152: aload         8
     154: aload_1
     155: invokestatic  #70                 // Method org/apache/dubbo/common/utils/StringUtils.startsWithIgnoreCase:(Ljava/lang/String;Ljava/lang/String;)Z
     158: ifeq          225
     161: aload         8
     163: invokevirtual #71                 // Method java/lang/String.length:()I
     166: aload_1
     167: invokevirtual #71                 // Method java/lang/String.length:()I
     170: if_icmple     225
     173: aload         9
     175: invokestatic  #72                 // Method isEmptyValue:(Ljava/lang/Object;)Z
     178: ifne          225
     181: aload         8
     183: aload_1
     184: invokevirtual #71                 // Method java/lang/String.length:()I
     187: invokevirtual #73                 // Method java/lang/String.substring:(I)Ljava/lang/String;
     190: astore        10
     192: aload         10
     194: ldc           #57                 // String .
     196: invokevirtual #81                 // Method java/lang/String.indexOf:(Ljava/lang/String;)I
     199: istore        11
     201: iload         11
     203: ifle          225
     206: aload         10
     208: iconst_0
     209: iload         11
     211: invokevirtual #82                 // Method java/lang/String.substring:(II)Ljava/lang/String;
     214: astore        12
     216: aload_2
     217: aload         12
     219: invokeinterface #83,  2           // InterfaceMethod java/util/Set.add:(Ljava/lang/Object;)Z
     224: pop
     225: goto          109
     228: goto          44
     231: aload_2
     232: areturn
    Exception table:
       from    to  target type
          70    84    87   any
          87    92    87   any

  public static org.apache.dubbo.common.config.configcenter.DynamicConfigurationFactory getDynamicConfigurationFactory(org.apache.dubbo.common.extension.ExtensionAccessor, java.lang.String);
    Code:
       0: aload_0
       1: ldc           #84                 // class org/apache/dubbo/common/config/configcenter/DynamicConfigurationFactory
       3: invokeinterface #85,  2           // InterfaceMethod org/apache/dubbo/common/extension/ExtensionAccessor.getExtensionLoader:(Ljava/lang/Class;)Lorg/apache/dubbo/common/extension/ExtensionLoader;
       8: astore_2
       9: aload_2
      10: aload_1
      11: invokevirtual #86                 // Method org/apache/dubbo/common/extension/ExtensionLoader.getOrDefaultExtension:(Ljava/lang/String;)Ljava/lang/Object;
      14: checkcast     #84                 // class org/apache/dubbo/common/config/configcenter/DynamicConfigurationFactory
      17: areturn

  public static org.apache.dubbo.common.config.Configuration getSystemConfiguration();
    Code:
       0: invokestatic  #27                 // Method org/apache/dubbo/rpc/model/ApplicationModel.defaultModel:()Lorg/apache/dubbo/rpc/model/ApplicationModel;
       3: invokevirtual #87                 // Method org/apache/dubbo/rpc/model/ApplicationModel.getModelEnvironment:()Lorg/apache/dubbo/common/config/Environment;
       6: invokevirtual #9                  // Method org/apache/dubbo/common/config/Environment.getSystemConfiguration:()Lorg/apache/dubbo/common/config/SystemConfiguration;
       9: areturn

  public static org.apache.dubbo.common.config.Configuration getEnvConfiguration();
    Code:
       0: invokestatic  #27                 // Method org/apache/dubbo/rpc/model/ApplicationModel.defaultModel:()Lorg/apache/dubbo/rpc/model/ApplicationModel;
       3: invokevirtual #87                 // Method org/apache/dubbo/rpc/model/ApplicationModel.getModelEnvironment:()Lorg/apache/dubbo/common/config/Environment;
       6: invokevirtual #10                 // Method org/apache/dubbo/common/config/Environment.getEnvironmentConfiguration:()Lorg/apache/dubbo/common/config/EnvironmentConfiguration;
       9: areturn

  public static org.apache.dubbo.common.config.Configuration getGlobalConfiguration();
    Code:
       0: invokestatic  #27                 // Method org/apache/dubbo/rpc/model/ApplicationModel.defaultModel:()Lorg/apache/dubbo/rpc/model/ApplicationModel;
       3: invokevirtual #87                 // Method org/apache/dubbo/rpc/model/ApplicationModel.getModelEnvironment:()Lorg/apache/dubbo/common/config/Environment;
       6: invokevirtual #11                 // Method org/apache/dubbo/common/config/Environment.getConfiguration:()Lorg/apache/dubbo/common/config/CompositeConfiguration;
       9: areturn

  public static org.apache.dubbo.common.config.Configuration getDynamicGlobalConfiguration();
    Code:
       0: invokestatic  #27                 // Method org/apache/dubbo/rpc/model/ApplicationModel.defaultModel:()Lorg/apache/dubbo/rpc/model/ApplicationModel;
       3: invokevirtual #88                 // Method org/apache/dubbo/rpc/model/ApplicationModel.getDefaultModule:()Lorg/apache/dubbo/rpc/model/ModuleModel;
       6: invokevirtual #89                 // Method org/apache/dubbo/rpc/model/ModuleModel.getModelEnvironment:()Lorg/apache/dubbo/common/config/ModuleEnvironment;
       9: invokevirtual #90                 // Method org/apache/dubbo/common/config/ModuleEnvironment.getDynamicGlobalConfiguration:()Lorg/apache/dubbo/common/config/Configuration;
      12: areturn

  public static java.lang.String getCachedDynamicProperty(java.lang.String, java.lang.String);
    Code:
       0: invokestatic  #27                 // Method org/apache/dubbo/rpc/model/ApplicationModel.defaultModel:()Lorg/apache/dubbo/rpc/model/ApplicationModel;
       3: aload_0
       4: aload_1
       5: invokestatic  #91                 // Method getCachedDynamicProperty:(Lorg/apache/dubbo/rpc/model/ScopeModel;Ljava/lang/String;Ljava/lang/String;)Ljava/lang/String;
       8: areturn

  public static java.lang.String getDynamicProperty(java.lang.String);
    Code:
       0: invokestatic  #27                 // Method org/apache/dubbo/rpc/model/ApplicationModel.defaultModel:()Lorg/apache/dubbo/rpc/model/ApplicationModel;
       3: aload_0
       4: invokestatic  #92                 // Method getDynamicProperty:(Lorg/apache/dubbo/rpc/model/ScopeModel;Ljava/lang/String;)Ljava/lang/String;
       7: areturn

  public static java.lang.String getDynamicProperty(java.lang.String, java.lang.String);
    Code:
       0: invokestatic  #27                 // Method org/apache/dubbo/rpc/model/ApplicationModel.defaultModel:()Lorg/apache/dubbo/rpc/model/ApplicationModel;
       3: aload_0
       4: aload_1
       5: invokestatic  #28                 // Method getDynamicProperty:(Lorg/apache/dubbo/rpc/model/ScopeModel;Ljava/lang/String;Ljava/lang/String;)Ljava/lang/String;
       8: areturn

  public static java.lang.String getProperty(java.lang.String);
    Code:
       0: invokestatic  #27                 // Method org/apache/dubbo/rpc/model/ApplicationModel.defaultModel:()Lorg/apache/dubbo/rpc/model/ApplicationModel;
       3: aload_0
       4: invokestatic  #93                 // Method getProperty:(Lorg/apache/dubbo/rpc/model/ScopeModel;Ljava/lang/String;)Ljava/lang/String;
       7: areturn

  public static java.lang.String getProperty(java.lang.String, java.lang.String);
    Code:
       0: invokestatic  #27                 // Method org/apache/dubbo/rpc/model/ApplicationModel.defaultModel:()Lorg/apache/dubbo/rpc/model/ApplicationModel;
       3: aload_0
       4: aload_1
       5: invokestatic  #31                 // Method getProperty:(Lorg/apache/dubbo/rpc/model/ScopeModel;Ljava/lang/String;Ljava/lang/String;)Ljava/lang/String;
       8: areturn

  public static int get(java.lang.String, int);
    Code:
       0: invokestatic  #27                 // Method org/apache/dubbo/rpc/model/ApplicationModel.defaultModel:()Lorg/apache/dubbo/rpc/model/ApplicationModel;
       3: aload_0
       4: iload_1
       5: invokestatic  #94                 // Method get:(Lorg/apache/dubbo/rpc/model/ScopeModel;Ljava/lang/String;I)I
       8: ireturn

  private static void lambda$parseProperties$1(java.util.Map, java.util.Properties, java.lang.String);
    Code:
       0: iconst_0
       1: istore_3
       2: getstatic     #95                 // Field securityKey:Ljava/util/List;
       5: invokeinterface #96,  1           // InterfaceMethod java/util/List.iterator:()Ljava/util/Iterator;
      10: astore        4
      12: aload         4
      14: invokeinterface #53,  1           // InterfaceMethod java/util/Iterator.hasNext:()Z
      19: ifeq          51
      22: aload         4
      24: invokeinterface #54,  1           // InterfaceMethod java/util/Iterator.next:()Ljava/lang/Object;
      29: checkcast     #48                 // class java/lang/String
      32: astore        5
      34: aload_2
      35: aload         5
      37: invokevirtual #97                 // Method java/lang/String.contains:(Ljava/lang/CharSequence;)Z
      40: ifeq          48
      43: iconst_1
      44: istore_3
      45: goto          51
      48: goto          12
      51: iload_3
      52: ifne          68
      55: aload_0
      56: aload_2
      57: aload_1
      58: aload_2
      59: invokevirtual #98                 // Method java/util/Properties.getProperty:(Ljava/lang/String;)Ljava/lang/String;
      62: invokeinterface #99,  3           // InterfaceMethod java/util/Map.put:(Ljava/lang/Object;Ljava/lang/Object;)Ljava/lang/Object;
      67: pop
      68: return

  private static java.lang.String lambda$getCachedDynamicProperty$0(org.apache.dubbo.rpc.model.ScopeModel, java.lang.String);
    Code:
       0: aload_0
       1: aload_1
       2: ldc           #37                 // String
       4: invokestatic  #28                 // Method getDynamicProperty:(Lorg/apache/dubbo/rpc/model/ScopeModel;Ljava/lang/String;Ljava/lang/String;)Ljava/lang/String;
       7: areturn

  static {};
    Code:
       0: ldc           #100                // class org/apache/dubbo/common/config/ConfigurationUtils
       2: invokestatic  #101                // Method org/apache/dubbo/common/logger/LoggerFactory.getErrorTypeAwareLogger:(Ljava/lang/Class;)Lorg/apache/dubbo/common/logger/ErrorTypeAwareLogger;
       5: putstatic     #35                 // Field logger:Lorg/apache/dubbo/common/logger/ErrorTypeAwareLogger;
       8: new           #102                // class java/util/LinkedList
      11: dup
      12: invokespecial #103                // Method java/util/LinkedList."<init>":()V
      15: astore_0
      16: aload_0
      17: ldc           #104                // String accesslog
      19: invokeinterface #105,  2          // InterfaceMethod java/util/List.add:(Ljava/lang/Object;)Z
      24: pop
      25: aload_0
      26: ldc           #106                // String router
      28: invokeinterface #105,  2          // InterfaceMethod java/util/List.add:(Ljava/lang/Object;)Z
      33: pop
      34: aload_0
      35: ldc           #107                // String rule
      37: invokeinterface #105,  2          // InterfaceMethod java/util/List.add:(Ljava/lang/Object;)Z
      42: pop
      43: aload_0
      44: ldc           #108                // String runtime
      46: invokeinterface #105,  2          // InterfaceMethod java/util/List.add:(Ljava/lang/Object;)Z
      51: pop
      52: aload_0
      53: ldc           #109                // String type
      55: invokeinterface #105,  2          // InterfaceMethod java/util/List.add:(Ljava/lang/Object;)Z
      60: pop
      61: aload_0
      62: invokestatic  #110                // Method java/util/Collections.unmodifiableList:(Ljava/util/List;)Ljava/util/List;
      65: putstatic     #95                 // Field securityKey:Ljava/util/List;
      68: return
}
