Compiled from "EnvironmentConfiguration.java"
public class org.apache.dubbo.common.config.EnvironmentConfiguration implements org.apache.dubbo.common.config.Configuration {
  public org.apache.dubbo.common.config.EnvironmentConfiguration();
    Code:
       0: aload_0
       1: invokespecial #1                  // Method java/lang/Object."<init>":()V
       4: return

  public java.lang.Object getInternalProperty(java.lang.String);
    Code:
       0: aload_0
       1: aload_1
       2: invokevirtual #2                  // Method getenv:(Ljava/lang/String;)Ljava/lang/String;
       5: astore_2
       6: aload_2
       7: invokestatic  #3                  // Method org/apache/dubbo/common/utils/StringUtils.isEmpty:(Ljava/lang/String;)Z
      10: ifeq          22
      13: aload_0
      14: aload_1
      15: invokestatic  #4                  // Method org/apache/dubbo/common/utils/StringUtils.toOSStyleKey:(Ljava/lang/String;)Ljava/lang/String;
      18: invokevirtual #2                  // Method getenv:(Ljava/lang/String;)Ljava/lang/String;
      21: astore_2
      22: aload_2
      23: areturn

  public java.util.Map<java.lang.String, java.lang.String> getProperties();
    Code:
       0: aload_0
       1: invokevirtual #5                  // Method getenv:()Ljava/util/Map;
       4: areturn

  protected java.lang.String getenv(java.lang.String);
    Code:
       0: aload_1
       1: invokestatic  #6                  // Method java/lang/System.getenv:(Ljava/lang/String;)Ljava/lang/String;
       4: areturn

  protected java.util.Map<java.lang.String, java.lang.String> getenv();
    Code:
       0: invokestatic  #7                  // Method java/lang/System.getenv:()Ljava/util/Map;
       3: areturn
}
