Compiled from "InmemoryConfiguration.java"
public class org.apache.dubbo.common.config.InmemoryConfiguration implements org.apache.dubbo.common.config.Configuration {
  private java.lang.String name;

  private java.util.Map<java.lang.String, java.lang.String> store;

  public org.apache.dubbo.common.config.InmemoryConfiguration();
    Code:
       0: aload_0
       1: invokespecial #1                  // Method java/lang/Object."<init>":()V
       4: aload_0
       5: new           #2                  // class java/util/LinkedHashMap
       8: dup
       9: invokespecial #3                  // Method java/util/LinkedHashMap."<init>":()V
      12: putfield      #4                  // Field store:Ljava/util/Map;
      15: return

  public org.apache.dubbo.common.config.InmemoryConfiguration(java.lang.String);
    Code:
       0: aload_0
       1: invokespecial #1                  // Method java/lang/Object."<init>":()V
       4: aload_0
       5: new           #2                  // class java/util/LinkedHashMap
       8: dup
       9: invokespecial #3                  // Method java/util/LinkedHashMap."<init>":()V
      12: putfield      #4                  // Field store:Ljava/util/Map;
      15: aload_0
      16: aload_1
      17: putfield      #5                  // Field name:Ljava/lang/String;
      20: return

  public org.apache.dubbo.common.config.InmemoryConfiguration(java.util.Map<java.lang.String, java.lang.String>);
    Code:
       0: aload_0
       1: invokespecial #1                  // Method java/lang/Object."<init>":()V
       4: aload_0
       5: new           #2                  // class java/util/LinkedHashMap
       8: dup
       9: invokespecial #3                  // Method java/util/LinkedHashMap."<init>":()V
      12: putfield      #4                  // Field store:Ljava/util/Map;
      15: aload_0
      16: aload_1
      17: invokevirtual #6                  // Method setProperties:(Ljava/util/Map;)V
      20: return

  public java.lang.Object getInternalProperty(java.lang.String);
    Code:
       0: aload_0
       1: getfield      #4                  // Field store:Ljava/util/Map;
       4: aload_1
       5: invokeinterface #7,  2            // InterfaceMethod java/util/Map.get:(Ljava/lang/Object;)Ljava/lang/Object;
      10: areturn

  public void addProperty(java.lang.String, java.lang.String);
    Code:
       0: aload_0
       1: getfield      #4                  // Field store:Ljava/util/Map;
       4: aload_1
       5: aload_2
       6: invokeinterface #8,  3            // InterfaceMethod java/util/Map.put:(Ljava/lang/Object;Ljava/lang/Object;)Ljava/lang/Object;
      11: pop
      12: return

  public void addProperties(java.util.Map<java.lang.String, java.lang.String>);
    Code:
       0: aload_1
       1: ifnull        14
       4: aload_0
       5: getfield      #4                  // Field store:Ljava/util/Map;
       8: aload_1
       9: invokeinterface #9,  2            // InterfaceMethod java/util/Map.putAll:(Ljava/util/Map;)V
      14: return

  public void setProperties(java.util.Map<java.lang.String, java.lang.String>);
    Code:
       0: aload_1
       1: ifnull        9
       4: aload_0
       5: aload_1
       6: putfield      #4                  // Field store:Ljava/util/Map;
       9: return

  public java.util.Map<java.lang.String, java.lang.String> getProperties();
    Code:
       0: aload_0
       1: getfield      #4                  // Field store:Ljava/util/Map;
       4: areturn
}
