Compiled from "ModuleEnvironment.java"
public class org.apache.dubbo.common.config.ModuleEnvironment extends org.apache.dubbo.common.config.Environment implements org.apache.dubbo.common.context.ModuleExt {
  private static final org.apache.dubbo.common.logger.ErrorTypeAwareLogger logger;

  public static final java.lang.String NAME;

  private final java.util.concurrent.atomic.AtomicBoolean initialized;

  private final org.apache.dubbo.rpc.model.ModuleModel moduleModel;

  private final org.apache.dubbo.common.config.Environment applicationDelegate;

  private org.apache.dubbo.common.config.OrderedPropertiesConfiguration orderedPropertiesConfiguration;

  private org.apache.dubbo.common.config.CompositeConfiguration dynamicGlobalConfiguration;

  private org.apache.dubbo.common.config.configcenter.DynamicConfiguration dynamicConfiguration;

  public org.apache.dubbo.common.config.ModuleEnvironment(org.apache.dubbo.rpc.model.ModuleModel);
    Code:
       0: aload_0
       1: aload_1
       2: invokespecial #2                  // Method org/apache/dubbo/common/config/Environment."<init>":(Lorg/apache/dubbo/rpc/model/ScopeModel;)V
       5: aload_0
       6: new           #3                  // class java/util/concurrent/atomic/AtomicBoolean
       9: dup
      10: iconst_0
      11: invokespecial #4                  // Method java/util/concurrent/atomic/AtomicBoolean."<init>":(Z)V
      14: putfield      #5                  // Field initialized:Ljava/util/concurrent/atomic/AtomicBoolean;
      17: aload_0
      18: aload_1
      19: putfield      #6                  // Field moduleModel:Lorg/apache/dubbo/rpc/model/ModuleModel;
      22: aload_0
      23: aload_1
      24: invokevirtual #7                  // Method org/apache/dubbo/rpc/model/ModuleModel.getApplicationModel:()Lorg/apache/dubbo/rpc/model/ApplicationModel;
      27: invokevirtual #8                  // Method org/apache/dubbo/rpc/model/ApplicationModel.getModelEnvironment:()Lorg/apache/dubbo/common/config/Environment;
      30: putfield      #9                  // Field applicationDelegate:Lorg/apache/dubbo/common/config/Environment;
      33: return

  public void initialize() throws java.lang.IllegalStateException;
    Code:
       0: aload_0
       1: getfield      #5                  // Field initialized:Ljava/util/concurrent/atomic/AtomicBoolean;
       4: iconst_0
       5: iconst_1
       6: invokevirtual #10                 // Method java/util/concurrent/atomic/AtomicBoolean.compareAndSet:(ZZ)Z
       9: ifeq          27
      12: aload_0
      13: new           #11                 // class org/apache/dubbo/common/config/OrderedPropertiesConfiguration
      16: dup
      17: aload_0
      18: getfield      #6                  // Field moduleModel:Lorg/apache/dubbo/rpc/model/ModuleModel;
      21: invokespecial #12                 // Method org/apache/dubbo/common/config/OrderedPropertiesConfiguration."<init>":(Lorg/apache/dubbo/rpc/model/ModuleModel;)V
      24: putfield      #13                 // Field orderedPropertiesConfiguration:Lorg/apache/dubbo/common/config/OrderedPropertiesConfiguration;
      27: return

  public org.apache.dubbo.common.config.Configuration getPrefixedConfiguration(org.apache.dubbo.config.AbstractConfig, java.lang.String);
    Code:
       0: new           #14                 // class org/apache/dubbo/common/config/CompositeConfiguration
       3: dup
       4: invokespecial #15                 // Method org/apache/dubbo/common/config/CompositeConfiguration."<init>":()V
       7: astore_3
       8: aload_3
       9: aload_0
      10: getfield      #9                  // Field applicationDelegate:Lorg/apache/dubbo/common/config/Environment;
      13: aload_1
      14: aload_2
      15: invokevirtual #16                 // Method org/apache/dubbo/common/config/Environment.getPrefixedConfiguration:(Lorg/apache/dubbo/config/AbstractConfig;Ljava/lang/String;)Lorg/apache/dubbo/common/config/Configuration;
      18: invokevirtual #17                 // Method org/apache/dubbo/common/config/CompositeConfiguration.addConfiguration:(Lorg/apache/dubbo/common/config/Configuration;)V
      21: aload_3
      22: aload_0
      23: getfield      #13                 // Field orderedPropertiesConfiguration:Lorg/apache/dubbo/common/config/OrderedPropertiesConfiguration;
      26: invokevirtual #17                 // Method org/apache/dubbo/common/config/CompositeConfiguration.addConfiguration:(Lorg/apache/dubbo/common/config/Configuration;)V
      29: new           #18                 // class org/apache/dubbo/common/config/PrefixedConfiguration
      32: dup
      33: aload_3
      34: aload_2
      35: invokespecial #19                 // Method org/apache/dubbo/common/config/PrefixedConfiguration."<init>":(Lorg/apache/dubbo/common/config/Configuration;Ljava/lang/String;)V
      38: areturn

  public org.apache.dubbo.common.config.CompositeConfiguration getConfiguration();
    Code:
       0: aload_0
       1: getfield      #20                 // Field globalConfiguration:Lorg/apache/dubbo/common/config/CompositeConfiguration;
       4: ifnonnull     39
       7: new           #14                 // class org/apache/dubbo/common/config/CompositeConfiguration
      10: dup
      11: invokespecial #15                 // Method org/apache/dubbo/common/config/CompositeConfiguration."<init>":()V
      14: astore_1
      15: aload_1
      16: aload_0
      17: getfield      #9                  // Field applicationDelegate:Lorg/apache/dubbo/common/config/Environment;
      20: invokevirtual #21                 // Method org/apache/dubbo/common/config/Environment.getConfiguration:()Lorg/apache/dubbo/common/config/CompositeConfiguration;
      23: invokevirtual #17                 // Method org/apache/dubbo/common/config/CompositeConfiguration.addConfiguration:(Lorg/apache/dubbo/common/config/Configuration;)V
      26: aload_1
      27: aload_0
      28: getfield      #13                 // Field orderedPropertiesConfiguration:Lorg/apache/dubbo/common/config/OrderedPropertiesConfiguration;
      31: invokevirtual #17                 // Method org/apache/dubbo/common/config/CompositeConfiguration.addConfiguration:(Lorg/apache/dubbo/common/config/Configuration;)V
      34: aload_0
      35: aload_1
      36: putfield      #20                 // Field globalConfiguration:Lorg/apache/dubbo/common/config/CompositeConfiguration;
      39: aload_0
      40: getfield      #20                 // Field globalConfiguration:Lorg/apache/dubbo/common/config/CompositeConfiguration;
      43: areturn

  public java.util.List<java.util.Map<java.lang.String, java.lang.String>> getConfigurationMaps(org.apache.dubbo.config.AbstractConfig, java.lang.String);
    Code:
       0: aload_0
       1: getfield      #9                  // Field applicationDelegate:Lorg/apache/dubbo/common/config/Environment;
       4: aload_1
       5: aload_2
       6: invokevirtual #22                 // Method org/apache/dubbo/common/config/Environment.getConfigurationMaps:(Lorg/apache/dubbo/config/AbstractConfig;Ljava/lang/String;)Ljava/util/List;
       9: astore_3
      10: aload_3
      11: aload_0
      12: getfield      #13                 // Field orderedPropertiesConfiguration:Lorg/apache/dubbo/common/config/OrderedPropertiesConfiguration;
      15: invokevirtual #23                 // Method org/apache/dubbo/common/config/OrderedPropertiesConfiguration.getProperties:()Ljava/util/Map;
      18: invokeinterface #24,  2           // InterfaceMethod java/util/List.add:(Ljava/lang/Object;)Z
      23: pop
      24: aload_3
      25: areturn

  public org.apache.dubbo.common.config.Configuration getDynamicGlobalConfiguration();
    Code:
       0: aload_0
       1: getfield      #25                 // Field dynamicConfiguration:Lorg/apache/dubbo/common/config/configcenter/DynamicConfiguration;
       4: ifnonnull     15
       7: aload_0
       8: getfield      #9                  // Field applicationDelegate:Lorg/apache/dubbo/common/config/Environment;
      11: invokevirtual #26                 // Method org/apache/dubbo/common/config/Environment.getDynamicGlobalConfiguration:()Lorg/apache/dubbo/common/config/Configuration;
      14: areturn
      15: aload_0
      16: getfield      #27                 // Field dynamicGlobalConfiguration:Lorg/apache/dubbo/common/config/CompositeConfiguration;
      19: ifnonnull     94
      22: aload_0
      23: getfield      #25                 // Field dynamicConfiguration:Lorg/apache/dubbo/common/config/configcenter/DynamicConfiguration;
      26: ifnonnull     61
      29: getstatic     #28                 // Field logger:Lorg/apache/dubbo/common/logger/ErrorTypeAwareLogger;
      32: invokeinterface #29,  1           // InterfaceMethod org/apache/dubbo/common/logger/ErrorTypeAwareLogger.isWarnEnabled:()Z
      37: ifeq          56
      40: getstatic     #28                 // Field logger:Lorg/apache/dubbo/common/logger/ErrorTypeAwareLogger;
      43: ldc           #30                 // String 0-12
      45: ldc           #31                 // String
      47: ldc           #31                 // String
      49: ldc           #32                 // String dynamicConfiguration is null , return globalConfiguration.
      51: invokeinterface #33,  5           // InterfaceMethod org/apache/dubbo/common/logger/ErrorTypeAwareLogger.warn:(Ljava/lang/String;Ljava/lang/String;Ljava/lang/String;Ljava/lang/String;)V
      56: aload_0
      57: invokevirtual #34                 // Method getConfiguration:()Lorg/apache/dubbo/common/config/CompositeConfiguration;
      60: areturn
      61: aload_0
      62: new           #14                 // class org/apache/dubbo/common/config/CompositeConfiguration
      65: dup
      66: invokespecial #15                 // Method org/apache/dubbo/common/config/CompositeConfiguration."<init>":()V
      69: putfield      #27                 // Field dynamicGlobalConfiguration:Lorg/apache/dubbo/common/config/CompositeConfiguration;
      72: aload_0
      73: getfield      #27                 // Field dynamicGlobalConfiguration:Lorg/apache/dubbo/common/config/CompositeConfiguration;
      76: aload_0
      77: getfield      #25                 // Field dynamicConfiguration:Lorg/apache/dubbo/common/config/configcenter/DynamicConfiguration;
      80: invokevirtual #17                 // Method org/apache/dubbo/common/config/CompositeConfiguration.addConfiguration:(Lorg/apache/dubbo/common/config/Configuration;)V
      83: aload_0
      84: getfield      #27                 // Field dynamicGlobalConfiguration:Lorg/apache/dubbo/common/config/CompositeConfiguration;
      87: aload_0
      88: invokevirtual #34                 // Method getConfiguration:()Lorg/apache/dubbo/common/config/CompositeConfiguration;
      91: invokevirtual #17                 // Method org/apache/dubbo/common/config/CompositeConfiguration.addConfiguration:(Lorg/apache/dubbo/common/config/Configuration;)V
      94: aload_0
      95: getfield      #27                 // Field dynamicGlobalConfiguration:Lorg/apache/dubbo/common/config/CompositeConfiguration;
      98: areturn

  public java.util.Optional<org.apache.dubbo.common.config.configcenter.DynamicConfiguration> getDynamicConfiguration();
    Code:
       0: aload_0
       1: getfield      #25                 // Field dynamicConfiguration:Lorg/apache/dubbo/common/config/configcenter/DynamicConfiguration;
       4: ifnonnull     15
       7: aload_0
       8: getfield      #9                  // Field applicationDelegate:Lorg/apache/dubbo/common/config/Environment;
      11: invokevirtual #35                 // Method org/apache/dubbo/common/config/Environment.getDynamicConfiguration:()Ljava/util/Optional;
      14: areturn
      15: aload_0
      16: getfield      #25                 // Field dynamicConfiguration:Lorg/apache/dubbo/common/config/configcenter/DynamicConfiguration;
      19: invokestatic  #36                 // Method java/util/Optional.ofNullable:(Ljava/lang/Object;)Ljava/util/Optional;
      22: areturn

  public void setDynamicConfiguration(org.apache.dubbo.common.config.configcenter.DynamicConfiguration);
    Code:
       0: aload_0
       1: aload_1
       2: putfield      #25                 // Field dynamicConfiguration:Lorg/apache/dubbo/common/config/configcenter/DynamicConfiguration;
       5: return

  public void destroy() throws java.lang.IllegalStateException;
    Code:
       0: aload_0
       1: invokespecial #37                 // Method org/apache/dubbo/common/config/Environment.destroy:()V
       4: aload_0
       5: aconst_null
       6: putfield      #13                 // Field orderedPropertiesConfiguration:Lorg/apache/dubbo/common/config/OrderedPropertiesConfiguration;
       9: return

  public void setLocalMigrationRule(java.lang.String);
    Code:
       0: aload_0
       1: getfield      #9                  // Field applicationDelegate:Lorg/apache/dubbo/common/config/Environment;
       4: aload_1
       5: invokevirtual #38                 // Method org/apache/dubbo/common/config/Environment.setLocalMigrationRule:(Ljava/lang/String;)V
       8: return

  public void setExternalConfigMap(java.util.Map<java.lang.String, java.lang.String>);
    Code:
       0: aload_0
       1: getfield      #9                  // Field applicationDelegate:Lorg/apache/dubbo/common/config/Environment;
       4: aload_1
       5: invokevirtual #39                 // Method org/apache/dubbo/common/config/Environment.setExternalConfigMap:(Ljava/util/Map;)V
       8: return

  public void setAppExternalConfigMap(java.util.Map<java.lang.String, java.lang.String>);
    Code:
       0: aload_0
       1: getfield      #9                  // Field applicationDelegate:Lorg/apache/dubbo/common/config/Environment;
       4: aload_1
       5: invokevirtual #40                 // Method org/apache/dubbo/common/config/Environment.setAppExternalConfigMap:(Ljava/util/Map;)V
       8: return

  public void setAppConfigMap(java.util.Map<java.lang.String, java.lang.String>);
    Code:
       0: aload_0
       1: getfield      #9                  // Field applicationDelegate:Lorg/apache/dubbo/common/config/Environment;
       4: aload_1
       5: invokevirtual #41                 // Method org/apache/dubbo/common/config/Environment.setAppConfigMap:(Ljava/util/Map;)V
       8: return

  public java.util.Map<java.lang.String, java.lang.String> getExternalConfigMap();
    Code:
       0: aload_0
       1: getfield      #9                  // Field applicationDelegate:Lorg/apache/dubbo/common/config/Environment;
       4: invokevirtual #42                 // Method org/apache/dubbo/common/config/Environment.getExternalConfigMap:()Ljava/util/Map;
       7: areturn

  public java.util.Map<java.lang.String, java.lang.String> getAppExternalConfigMap();
    Code:
       0: aload_0
       1: getfield      #9                  // Field applicationDelegate:Lorg/apache/dubbo/common/config/Environment;
       4: invokevirtual #43                 // Method org/apache/dubbo/common/config/Environment.getAppExternalConfigMap:()Ljava/util/Map;
       7: areturn

  public java.util.Map<java.lang.String, java.lang.String> getAppConfigMap();
    Code:
       0: aload_0
       1: getfield      #9                  // Field applicationDelegate:Lorg/apache/dubbo/common/config/Environment;
       4: invokevirtual #44                 // Method org/apache/dubbo/common/config/Environment.getAppConfigMap:()Ljava/util/Map;
       7: areturn

  public void updateExternalConfigMap(java.util.Map<java.lang.String, java.lang.String>);
    Code:
       0: aload_0
       1: getfield      #9                  // Field applicationDelegate:Lorg/apache/dubbo/common/config/Environment;
       4: aload_1
       5: invokevirtual #45                 // Method org/apache/dubbo/common/config/Environment.updateExternalConfigMap:(Ljava/util/Map;)V
       8: return

  public void updateAppExternalConfigMap(java.util.Map<java.lang.String, java.lang.String>);
    Code:
       0: aload_0
       1: getfield      #9                  // Field applicationDelegate:Lorg/apache/dubbo/common/config/Environment;
       4: aload_1
       5: invokevirtual #46                 // Method org/apache/dubbo/common/config/Environment.updateAppExternalConfigMap:(Ljava/util/Map;)V
       8: return

  public void updateAppConfigMap(java.util.Map<java.lang.String, java.lang.String>);
    Code:
       0: aload_0
       1: getfield      #9                  // Field applicationDelegate:Lorg/apache/dubbo/common/config/Environment;
       4: aload_1
       5: invokevirtual #47                 // Method org/apache/dubbo/common/config/Environment.updateAppConfigMap:(Ljava/util/Map;)V
       8: return

  public org.apache.dubbo.common.config.PropertiesConfiguration getPropertiesConfiguration();
    Code:
       0: aload_0
       1: getfield      #9                  // Field applicationDelegate:Lorg/apache/dubbo/common/config/Environment;
       4: invokevirtual #48                 // Method org/apache/dubbo/common/config/Environment.getPropertiesConfiguration:()Lorg/apache/dubbo/common/config/PropertiesConfiguration;
       7: areturn

  public org.apache.dubbo.common.config.SystemConfiguration getSystemConfiguration();
    Code:
       0: aload_0
       1: getfield      #9                  // Field applicationDelegate:Lorg/apache/dubbo/common/config/Environment;
       4: invokevirtual #49                 // Method org/apache/dubbo/common/config/Environment.getSystemConfiguration:()Lorg/apache/dubbo/common/config/SystemConfiguration;
       7: areturn

  public org.apache.dubbo.common.config.EnvironmentConfiguration getEnvironmentConfiguration();
    Code:
       0: aload_0
       1: getfield      #9                  // Field applicationDelegate:Lorg/apache/dubbo/common/config/Environment;
       4: invokevirtual #50                 // Method org/apache/dubbo/common/config/Environment.getEnvironmentConfiguration:()Lorg/apache/dubbo/common/config/EnvironmentConfiguration;
       7: areturn

  public org.apache.dubbo.common.config.InmemoryConfiguration getExternalConfiguration();
    Code:
       0: aload_0
       1: getfield      #9                  // Field applicationDelegate:Lorg/apache/dubbo/common/config/Environment;
       4: invokevirtual #51                 // Method org/apache/dubbo/common/config/Environment.getExternalConfiguration:()Lorg/apache/dubbo/common/config/InmemoryConfiguration;
       7: areturn

  public org.apache.dubbo.common.config.InmemoryConfiguration getAppExternalConfiguration();
    Code:
       0: aload_0
       1: getfield      #9                  // Field applicationDelegate:Lorg/apache/dubbo/common/config/Environment;
       4: invokevirtual #52                 // Method org/apache/dubbo/common/config/Environment.getAppExternalConfiguration:()Lorg/apache/dubbo/common/config/InmemoryConfiguration;
       7: areturn

  public org.apache.dubbo.common.config.InmemoryConfiguration getAppConfiguration();
    Code:
       0: aload_0
       1: getfield      #9                  // Field applicationDelegate:Lorg/apache/dubbo/common/config/Environment;
       4: invokevirtual #53                 // Method org/apache/dubbo/common/config/Environment.getAppConfiguration:()Lorg/apache/dubbo/common/config/InmemoryConfiguration;
       7: areturn

  public java.lang.String getLocalMigrationRule();
    Code:
       0: aload_0
       1: getfield      #9                  // Field applicationDelegate:Lorg/apache/dubbo/common/config/Environment;
       4: invokevirtual #54                 // Method org/apache/dubbo/common/config/Environment.getLocalMigrationRule:()Ljava/lang/String;
       7: areturn

  public synchronized void refreshClassLoaders();
    Code:
       0: aload_0
       1: getfield      #13                 // Field orderedPropertiesConfiguration:Lorg/apache/dubbo/common/config/OrderedPropertiesConfiguration;
       4: invokevirtual #55                 // Method org/apache/dubbo/common/config/OrderedPropertiesConfiguration.refresh:()V
       7: aload_0
       8: getfield      #9                  // Field applicationDelegate:Lorg/apache/dubbo/common/config/Environment;
      11: invokevirtual #56                 // Method org/apache/dubbo/common/config/Environment.refreshClassLoaders:()V
      14: return

  static {};
    Code:
       0: ldc           #57                 // class org/apache/dubbo/common/config/ModuleEnvironment
       2: invokestatic  #58                 // Method org/apache/dubbo/common/logger/LoggerFactory.getErrorTypeAwareLogger:(Ljava/lang/Class;)Lorg/apache/dubbo/common/logger/ErrorTypeAwareLogger;
       5: putstatic     #28                 // Field logger:Lorg/apache/dubbo/common/logger/ErrorTypeAwareLogger;
       8: return
}
