Compiled from "OrderedPropertiesConfiguration.java"
public class org.apache.dubbo.common.config.OrderedPropertiesConfiguration implements org.apache.dubbo.common.config.Configuration {
  private java.util.Properties properties;

  private final org.apache.dubbo.rpc.model.ModuleModel moduleModel;

  public org.apache.dubbo.common.config.OrderedPropertiesConfiguration(org.apache.dubbo.rpc.model.ModuleModel);
    Code:
       0: aload_0
       1: invokespecial #1                  // Method java/lang/Object."<init>":()V
       4: aload_0
       5: aload_1
       6: putfield      #2                  // Field moduleModel:Lorg/apache/dubbo/rpc/model/ModuleModel;
       9: aload_0
      10: invokevirtual #3                  // Method refresh:()V
      13: return

  public void refresh();
    Code:
       0: aload_0
       1: new           #4                  // class java/util/Properties
       4: dup
       5: invokespecial #5                  // Method java/util/Properties."<init>":()V
       8: putfield      #6                  // Field properties:Ljava/util/Properties;
      11: aload_0
      12: getfield      #2                  // Field moduleModel:Lorg/apache/dubbo/rpc/model/ModuleModel;
      15: ldc           #7                  // class org/apache/dubbo/common/config/OrderedPropertiesProvider
      17: invokevirtual #8                  // Method org/apache/dubbo/rpc/model/ModuleModel.getExtensionLoader:(Ljava/lang/Class;)Lorg/apache/dubbo/common/extension/ExtensionLoader;
      20: astore_1
      21: aload_1
      22: invokevirtual #9                  // Method org/apache/dubbo/common/extension/ExtensionLoader.getSupportedExtensions:()Ljava/util/Set;
      25: astore_2
      26: aload_2
      27: invokestatic  #10                 // Method org/apache/dubbo/common/utils/CollectionUtils.isEmpty:(Ljava/util/Collection;)Z
      30: ifeq          34
      33: return
      34: new           #11                 // class java/util/ArrayList
      37: dup
      38: invokespecial #12                 // Method java/util/ArrayList."<init>":()V
      41: astore_3
      42: aload_2
      43: invokeinterface #13,  1           // InterfaceMethod java/util/Set.iterator:()Ljava/util/Iterator;
      48: astore        4
      50: aload         4
      52: invokeinterface #14,  1           // InterfaceMethod java/util/Iterator.hasNext:()Z
      57: ifeq          88
      60: aload         4
      62: invokeinterface #15,  1           // InterfaceMethod java/util/Iterator.next:()Ljava/lang/Object;
      67: checkcast     #16                 // class java/lang/String
      70: astore        5
      72: aload_3
      73: aload_1
      74: aload         5
      76: invokevirtual #17                 // Method org/apache/dubbo/common/extension/ExtensionLoader.getExtension:(Ljava/lang/String;)Ljava/lang/Object;
      79: invokeinterface #18,  2           // InterfaceMethod java/util/List.add:(Ljava/lang/Object;)Z
      84: pop
      85: goto          50
      88: aload_3
      89: invokedynamic #19,  0             // InvokeDynamic #0:compare:()Ljava/util/Comparator;
      94: invokeinterface #20,  2           // InterfaceMethod java/util/List.sort:(Ljava/util/Comparator;)V
      99: aload_3
     100: invokeinterface #21,  1           // InterfaceMethod java/util/List.iterator:()Ljava/util/Iterator;
     105: astore        4
     107: aload         4
     109: invokeinterface #14,  1           // InterfaceMethod java/util/Iterator.hasNext:()Z
     114: ifeq          146
     117: aload         4
     119: invokeinterface #15,  1           // InterfaceMethod java/util/Iterator.next:()Ljava/lang/Object;
     124: checkcast     #7                  // class org/apache/dubbo/common/config/OrderedPropertiesProvider
     127: astore        5
     129: aload_0
     130: getfield      #6                  // Field properties:Ljava/util/Properties;
     133: aload         5
     135: invokeinterface #22,  1           // InterfaceMethod org/apache/dubbo/common/config/OrderedPropertiesProvider.initProperties:()Ljava/util/Properties;
     140: invokevirtual #23                 // Method java/util/Properties.putAll:(Ljava/util/Map;)V
     143: goto          107
     146: return

  public java.lang.String getProperty(java.lang.String);
    Code:
       0: aload_0
       1: getfield      #6                  // Field properties:Ljava/util/Properties;
       4: aload_1
       5: invokevirtual #24                 // Method java/util/Properties.getProperty:(Ljava/lang/String;)Ljava/lang/String;
       8: areturn

  public java.lang.Object getInternalProperty(java.lang.String);
    Code:
       0: aload_0
       1: getfield      #6                  // Field properties:Ljava/util/Properties;
       4: aload_1
       5: invokevirtual #24                 // Method java/util/Properties.getProperty:(Ljava/lang/String;)Ljava/lang/String;
       8: areturn

  public void setProperty(java.lang.String, java.lang.String);
    Code:
       0: aload_0
       1: getfield      #6                  // Field properties:Ljava/util/Properties;
       4: aload_1
       5: aload_2
       6: invokevirtual #25                 // Method java/util/Properties.setProperty:(Ljava/lang/String;Ljava/lang/String;)Ljava/lang/Object;
       9: pop
      10: return

  public java.lang.String remove(java.lang.String);
    Code:
       0: aload_0
       1: getfield      #6                  // Field properties:Ljava/util/Properties;
       4: aload_1
       5: invokevirtual #26                 // Method java/util/Properties.remove:(Ljava/lang/Object;)Ljava/lang/Object;
       8: checkcast     #16                 // class java/lang/String
      11: areturn

  public void setProperties(java.util.Properties);
    Code:
       0: aload_0
       1: aload_1
       2: putfield      #6                  // Field properties:Ljava/util/Properties;
       5: return

  public java.util.Map<java.lang.String, java.lang.String> getProperties();
    Code:
       0: aload_0
       1: getfield      #6                  // Field properties:Ljava/util/Properties;
       4: areturn

  public java.lang.Object getProperty(java.lang.String);
    Code:
       0: aload_0
       1: aload_1
       2: invokevirtual #27                 // Method getProperty:(Ljava/lang/String;)Ljava/lang/String;
       5: areturn

  private static int lambda$refresh$0(org.apache.dubbo.common.config.OrderedPropertiesProvider, org.apache.dubbo.common.config.OrderedPropertiesProvider);
    Code:
       0: aload_1
       1: invokeinterface #28,  1           // InterfaceMethod org/apache/dubbo/common/config/OrderedPropertiesProvider.priority:()I
       6: aload_0
       7: invokeinterface #28,  1           // InterfaceMethod org/apache/dubbo/common/config/OrderedPropertiesProvider.priority:()I
      12: isub
      13: ireturn
}
