Compiled from "PrefixedConfiguration.java"
public class org.apache.dubbo.common.config.PrefixedConfiguration implements org.apache.dubbo.common.config.Configuration {
  private final java.lang.String prefix;

  private final org.apache.dubbo.common.config.Configuration origin;

  public org.apache.dubbo.common.config.PrefixedConfiguration(org.apache.dubbo.common.config.Configuration, java.lang.String);
    Code:
       0: aload_0
       1: invokespecial #1                  // Method java/lang/Object."<init>":()V
       4: aload_0
       5: aload_1
       6: putfield      #2                  // Field origin:Lorg/apache/dubbo/common/config/Configuration;
       9: aload_0
      10: aload_2
      11: putfield      #3                  // Field prefix:Ljava/lang/String;
      14: return

  public java.lang.Object getInternalProperty(java.lang.String);
    Code:
       0: aload_0
       1: getfield      #3                  // Field prefix:Ljava/lang/String;
       4: invokestatic  #4                  // Method org/apache/dubbo/common/utils/StringUtils.isBlank:(Ljava/lang/CharSequence;)Z
       7: ifeq          21
      10: aload_0
      11: getfield      #2                  // Field origin:Lorg/apache/dubbo/common/config/Configuration;
      14: aload_1
      15: invokeinterface #5,  2            // InterfaceMethod org/apache/dubbo/common/config/Configuration.getInternalProperty:(Ljava/lang/String;)Ljava/lang/Object;
      20: areturn
      21: aload_0
      22: getfield      #2                  // Field origin:Lorg/apache/dubbo/common/config/Configuration;
      25: new           #6                  // class java/lang/StringBuilder
      28: dup
      29: invokespecial #7                  // Method java/lang/StringBuilder."<init>":()V
      32: aload_0
      33: getfield      #3                  // Field prefix:Ljava/lang/String;
      36: invokevirtual #8                  // Method java/lang/StringBuilder.append:(Ljava/lang/String;)Ljava/lang/StringBuilder;
      39: ldc           #9                  // String .
      41: invokevirtual #8                  // Method java/lang/StringBuilder.append:(Ljava/lang/String;)Ljava/lang/StringBuilder;
      44: aload_1
      45: invokevirtual #8                  // Method java/lang/StringBuilder.append:(Ljava/lang/String;)Ljava/lang/StringBuilder;
      48: invokevirtual #10                 // Method java/lang/StringBuilder.toString:()Ljava/lang/String;
      51: invokeinterface #5,  2            // InterfaceMethod org/apache/dubbo/common/config/Configuration.getInternalProperty:(Ljava/lang/String;)Ljava/lang/Object;
      56: astore_2
      57: aload_2
      58: invokestatic  #11                 // Method org/apache/dubbo/common/config/ConfigurationUtils.isEmptyValue:(Ljava/lang/Object;)Z
      61: ifne          66
      64: aload_2
      65: areturn
      66: aconst_null
      67: areturn
}
