Compiled from "PropertiesConfiguration.java"
public class org.apache.dubbo.common.config.PropertiesConfiguration implements org.apache.dubbo.common.config.Configuration {
  private java.util.Properties properties;

  private final org.apache.dubbo.rpc.model.ScopeModel scopeModel;

  public org.apache.dubbo.common.config.PropertiesConfiguration(org.apache.dubbo.rpc.model.ScopeModel);
    Code:
       0: aload_0
       1: invokespecial #1                  // Method java/lang/Object."<init>":()V
       4: aload_0
       5: aload_1
       6: putfield      #2                  // Field scopeModel:Lorg/apache/dubbo/rpc/model/ScopeModel;
       9: aload_0
      10: invokevirtual #3                  // Method refresh:()V
      13: return

  public void refresh();
    Code:
       0: aload_0
       1: aload_0
       2: getfield      #2                  // Field scopeModel:Lorg/apache/dubbo/rpc/model/ScopeModel;
       5: invokevirtual #4                  // Method org/apache/dubbo/rpc/model/ScopeModel.getClassLoaders:()Ljava/util/Set;
       8: invokestatic  #5                  // Method org/apache/dubbo/common/utils/ConfigUtils.getProperties:(Ljava/util/Set;)Ljava/util/Properties;
      11: putfield      #6                  // Field properties:Ljava/util/Properties;
      14: return

  public java.lang.String getProperty(java.lang.String);
    Code:
       0: aload_0
       1: getfield      #6                  // Field properties:Ljava/util/Properties;
       4: aload_1
       5: invokevirtual #7                  // Method java/util/Properties.getProperty:(Ljava/lang/String;)Ljava/lang/String;
       8: areturn

  public java.lang.Object getInternalProperty(java.lang.String);
    Code:
       0: aload_0
       1: getfield      #6                  // Field properties:Ljava/util/Properties;
       4: aload_1
       5: invokevirtual #7                  // Method java/util/Properties.getProperty:(Ljava/lang/String;)Ljava/lang/String;
       8: areturn

  public void setProperty(java.lang.String, java.lang.String);
    Code:
       0: aload_0
       1: getfield      #6                  // Field properties:Ljava/util/Properties;
       4: aload_1
       5: aload_2
       6: invokevirtual #8                  // Method java/util/Properties.setProperty:(Ljava/lang/String;Ljava/lang/String;)Ljava/lang/Object;
       9: pop
      10: return

  public java.lang.String remove(java.lang.String);
    Code:
       0: aload_0
       1: getfield      #6                  // Field properties:Ljava/util/Properties;
       4: aload_1
       5: invokevirtual #9                  // Method java/util/Properties.remove:(Ljava/lang/Object;)Ljava/lang/Object;
       8: checkcast     #10                 // class java/lang/String
      11: areturn

  public void setProperties(java.util.Properties);
    Code:
       0: aload_0
       1: aload_1
       2: putfield      #6                  // Field properties:Ljava/util/Properties;
       5: return

  public java.util.Map<java.lang.String, java.lang.String> getProperties();
    Code:
       0: aload_0
       1: getfield      #6                  // Field properties:Ljava/util/Properties;
       4: areturn

  public java.lang.Object getProperty(java.lang.String);
    Code:
       0: aload_0
       1: aload_1
       2: invokevirtual #11                 // Method getProperty:(Ljava/lang/String;)Ljava/lang/String;
       5: areturn
}
