Compiled from "SystemConfiguration.java"
public class org.apache.dubbo.common.config.SystemConfiguration implements org.apache.dubbo.common.config.Configuration {
  public org.apache.dubbo.common.config.SystemConfiguration();
    Code:
       0: aload_0
       1: invokespecial #1                  // Method java/lang/Object."<init>":()V
       4: return

  public java.lang.Object getInternalProperty(java.lang.String);
    Code:
       0: aload_1
       1: invokestatic  #2                  // Method java/lang/System.getProperty:(Ljava/lang/String;)Ljava/lang/String;
       4: areturn

  public java.util.Map<java.lang.String, java.lang.String> getProperties();
    Code:
       0: invokestatic  #3                  // Method java/lang/System.getProperties:()Ljava/util/Properties;
       3: areturn
}
