Compiled from "ApplicationPidFileWriter.java"
public class org.springframework.boot.context.ApplicationPidFileWriter implements org.springframework.context.ApplicationListener<org.springframework.boot.context.event.SpringApplicationEvent>, org.springframework.core.Ordered {
  private static final org.apache.commons.logging.Log logger;

  private static final java.lang.String DEFAULT_FILE_NAME;

  private static final java.util.List<org.springframework.boot.context.ApplicationPidFileWriter$Property> FILE_PROPERTIES;

  private static final java.util.List<org.springframework.boot.context.ApplicationPidFileWriter$Property> FAIL_ON_WRITE_ERROR_PROPERTIES;

  private static final java.util.concurrent.atomic.AtomicBoolean created;

  private int order;

  private final java.io.File file;

  private java.lang.Class<? extends org.springframework.boot.context.event.SpringApplicationEvent> triggerEventType;

  public org.springframework.boot.context.ApplicationPidFileWriter();
    Code:
       0: aload_0
       1: new           #1                  // class java/io/File
       4: dup
       5: ldc           #5                  // String application.pid
       7: invokespecial #7                  // Method java/io/File."<init>":(Ljava/lang/String;)V
      10: invokespecial #11                 // Method "<init>":(Ljava/io/File;)V
      13: return

  public org.springframework.boot.context.ApplicationPidFileWriter(java.lang.String);
    Code:
       0: aload_0
       1: new           #1                  // class java/io/File
       4: dup
       5: aload_1
       6: invokespecial #7                  // Method java/io/File."<init>":(Ljava/lang/String;)V
       9: invokespecial #11                 // Method "<init>":(Ljava/io/File;)V
      12: return

  public org.springframework.boot.context.ApplicationPidFileWriter(java.io.File);
    Code:
       0: aload_0
       1: invokespecial #14                 // Method java/lang/Object."<init>":()V
       4: aload_0
       5: ldc           #21                 // int -2147483635
       7: putfield      #22                 // Field order:I
      10: aload_0
      11: ldc           #26                 // class org/springframework/boot/context/event/ApplicationPreparedEvent
      13: putfield      #28                 // Field triggerEventType:Ljava/lang/Class;
      16: aload_1
      17: ldc           #32                 // String File must not be null
      19: invokestatic  #34                 // Method org/springframework/util/Assert.notNull:(Ljava/lang/Object;Ljava/lang/String;)V
      22: aload_0
      23: aload_1
      24: putfield      #40                 // Field file:Ljava/io/File;
      27: return

  public void setTriggerEventType(java.lang.Class<? extends org.springframework.boot.context.event.SpringApplicationEvent>);
    Code:
       0: aload_1
       1: ldc           #44                 // String Trigger event type must not be null
       3: invokestatic  #34                 // Method org/springframework/util/Assert.notNull:(Ljava/lang/Object;Ljava/lang/String;)V
       6: aload_0
       7: aload_1
       8: putfield      #28                 // Field triggerEventType:Ljava/lang/Class;
      11: return

  public void onApplicationEvent(org.springframework.boot.context.event.SpringApplicationEvent);
    Code:
       0: aload_0
       1: getfield      #28                 // Field triggerEventType:Ljava/lang/Class;
       4: aload_1
       5: invokevirtual #46                 // Method java/lang/Class.isInstance:(Ljava/lang/Object;)Z
       8: ifeq          76
      11: getstatic     #52                 // Field created:Ljava/util/concurrent/atomic/AtomicBoolean;
      14: iconst_0
      15: iconst_1
      16: invokevirtual #56                 // Method java/util/concurrent/atomic/AtomicBoolean.compareAndSet:(ZZ)Z
      19: ifeq          76
      22: aload_0
      23: aload_1
      24: invokevirtual #62                 // Method writePidFile:(Lorg/springframework/boot/context/event/SpringApplicationEvent;)V
      27: goto          76
      30: astore_2
      31: ldc           #68                 // String Cannot create pid file %s
      33: iconst_1
      34: anewarray     #15                 // class java/lang/Object
      37: dup
      38: iconst_0
      39: aload_0
      40: getfield      #40                 // Field file:Ljava/io/File;
      43: aastore
      44: invokestatic  #70                 // Method java/lang/String.format:(Ljava/lang/String;[Ljava/lang/Object;)Ljava/lang/String;
      47: astore_3
      48: aload_0
      49: aload_1
      50: invokevirtual #76                 // Method failOnWriteError:(Lorg/springframework/boot/context/event/SpringApplicationEvent;)Z
      53: ifeq          66
      56: new           #80                 // class java/lang/IllegalStateException
      59: dup
      60: aload_3
      61: aload_2
      62: invokespecial #82                 // Method java/lang/IllegalStateException."<init>":(Ljava/lang/String;Ljava/lang/Throwable;)V
      65: athrow
      66: getstatic     #85                 // Field logger:Lorg/apache/commons/logging/Log;
      69: aload_3
      70: aload_2
      71: invokeinterface #89,  3           // InterfaceMethod org/apache/commons/logging/Log.warn:(Ljava/lang/Object;Ljava/lang/Throwable;)V
      76: return
    Exception table:
       from    to  target type
          22    27    30   Class java/lang/Exception

  private void writePidFile(org.springframework.boot.context.event.SpringApplicationEvent) throws java.io.IOException;
    Code:
       0: aload_0
       1: getfield      #40                 // Field file:Ljava/io/File;
       4: astore_2
       5: aload_0
       6: aload_1
       7: getstatic     #95                 // Field FILE_PROPERTIES:Ljava/util/List;
      10: invokevirtual #99                 // Method getProperty:(Lorg/springframework/boot/context/event/SpringApplicationEvent;Ljava/util/List;)Ljava/lang/String;
      13: astore_3
      14: aload_3
      15: ifnull        27
      18: new           #1                  // class java/io/File
      21: dup
      22: aload_3
      23: invokespecial #7                  // Method java/io/File."<init>":(Ljava/lang/String;)V
      26: astore_2
      27: new           #103                // class org/springframework/boot/system/ApplicationPid
      30: dup
      31: invokespecial #105                // Method org/springframework/boot/system/ApplicationPid."<init>":()V
      34: aload_2
      35: invokevirtual #106                // Method org/springframework/boot/system/ApplicationPid.write:(Ljava/io/File;)V
      38: aload_2
      39: invokevirtual #109                // Method java/io/File.deleteOnExit:()V
      42: return

  private boolean failOnWriteError(org.springframework.boot.context.event.SpringApplicationEvent);
    Code:
       0: aload_0
       1: aload_1
       2: getstatic     #112                // Field FAIL_ON_WRITE_ERROR_PROPERTIES:Ljava/util/List;
       5: invokevirtual #99                 // Method getProperty:(Lorg/springframework/boot/context/event/SpringApplicationEvent;Ljava/util/List;)Ljava/lang/String;
       8: astore_2
       9: aload_2
      10: invokestatic  #115                // Method java/lang/Boolean.parseBoolean:(Ljava/lang/String;)Z
      13: ireturn

  private java.lang.String getProperty(org.springframework.boot.context.event.SpringApplicationEvent, java.util.List<org.springframework.boot.context.ApplicationPidFileWriter$Property>);
    Code:
       0: aload_2
       1: invokeinterface #121,  1          // InterfaceMethod java/util/List.iterator:()Ljava/util/Iterator;
       6: astore_3
       7: aload_3
       8: invokeinterface #127,  1          // InterfaceMethod java/util/Iterator.hasNext:()Z
      13: ifeq          48
      16: aload_3
      17: invokeinterface #133,  1          // InterfaceMethod java/util/Iterator.next:()Ljava/lang/Object;
      22: checkcast     #137                // class org/springframework/boot/context/ApplicationPidFileWriter$Property
      25: astore        4
      27: aload         4
      29: aload_1
      30: invokeinterface #139,  2          // InterfaceMethod org/springframework/boot/context/ApplicationPidFileWriter$Property.getValue:(Lorg/springframework/boot/context/event/SpringApplicationEvent;)Ljava/lang/String;
      35: astore        5
      37: aload         5
      39: ifnull        45
      42: aload         5
      44: areturn
      45: goto          7
      48: aconst_null
      49: areturn

  public void setOrder(int);
    Code:
       0: aload_0
       1: iload_1
       2: putfield      #22                 // Field order:I
       5: return

  public int getOrder();
    Code:
       0: aload_0
       1: getfield      #22                 // Field order:I
       4: ireturn

  protected static void reset();
    Code:
       0: getstatic     #52                 // Field created:Ljava/util/concurrent/atomic/AtomicBoolean;
       3: iconst_0
       4: invokevirtual #143                // Method java/util/concurrent/atomic/AtomicBoolean.set:(Z)V
       7: return

  public void onApplicationEvent(org.springframework.context.ApplicationEvent);
    Code:
       0: aload_0
       1: aload_1
       2: checkcast     #147                // class org/springframework/boot/context/event/SpringApplicationEvent
       5: invokevirtual #149                // Method onApplicationEvent:(Lorg/springframework/boot/context/event/SpringApplicationEvent;)V
       8: return

  static {};
    Code:
       0: ldc           #3                  // class org/springframework/boot/context/ApplicationPidFileWriter
       2: invokestatic  #152                // Method org/apache/commons/logging/LogFactory.getLog:(Ljava/lang/Class;)Lorg/apache/commons/logging/Log;
       5: putstatic     #85                 // Field logger:Lorg/apache/commons/logging/Log;
       8: new           #158                // class java/util/ArrayList
      11: dup
      12: invokespecial #160                // Method java/util/ArrayList."<init>":()V
      15: astore_0
      16: aload_0
      17: new           #161                // class org/springframework/boot/context/ApplicationPidFileWriter$SpringProperty
      20: dup
      21: ldc           #163                // String spring.pid.
      23: ldc           #165                // String file
      25: invokespecial #166                // Method org/springframework/boot/context/ApplicationPidFileWriter$SpringProperty."<init>":(Ljava/lang/String;Ljava/lang/String;)V
      28: invokeinterface #169,  2          // InterfaceMethod java/util/List.add:(Ljava/lang/Object;)Z
      33: pop
      34: aload_0
      35: new           #161                // class org/springframework/boot/context/ApplicationPidFileWriter$SpringProperty
      38: dup
      39: ldc           #172                // String spring.
      41: ldc           #174                // String pidfile
      43: invokespecial #166                // Method org/springframework/boot/context/ApplicationPidFileWriter$SpringProperty."<init>":(Ljava/lang/String;Ljava/lang/String;)V
      46: invokeinterface #169,  2          // InterfaceMethod java/util/List.add:(Ljava/lang/Object;)Z
      51: pop
      52: aload_0
      53: new           #176                // class org/springframework/boot/context/ApplicationPidFileWriter$SystemProperty
      56: dup
      57: ldc           #178                // String PIDFILE
      59: invokespecial #180                // Method org/springframework/boot/context/ApplicationPidFileWriter$SystemProperty."<init>":(Ljava/lang/String;)V
      62: invokeinterface #169,  2          // InterfaceMethod java/util/List.add:(Ljava/lang/Object;)Z
      67: pop
      68: aload_0
      69: invokestatic  #181                // Method java/util/Collections.unmodifiableList:(Ljava/util/List;)Ljava/util/List;
      72: putstatic     #95                 // Field FILE_PROPERTIES:Ljava/util/List;
      75: new           #158                // class java/util/ArrayList
      78: dup
      79: invokespecial #160                // Method java/util/ArrayList."<init>":()V
      82: astore_0
      83: aload_0
      84: new           #161                // class org/springframework/boot/context/ApplicationPidFileWriter$SpringProperty
      87: dup
      88: ldc           #163                // String spring.pid.
      90: ldc           #187                // String fail-on-write-error
      92: invokespecial #166                // Method org/springframework/boot/context/ApplicationPidFileWriter$SpringProperty."<init>":(Ljava/lang/String;Ljava/lang/String;)V
      95: invokeinterface #169,  2          // InterfaceMethod java/util/List.add:(Ljava/lang/Object;)Z
     100: pop
     101: aload_0
     102: new           #176                // class org/springframework/boot/context/ApplicationPidFileWriter$SystemProperty
     105: dup
     106: ldc           #189                // String PID_FAIL_ON_WRITE_ERROR
     108: invokespecial #180                // Method org/springframework/boot/context/ApplicationPidFileWriter$SystemProperty."<init>":(Ljava/lang/String;)V
     111: invokeinterface #169,  2          // InterfaceMethod java/util/List.add:(Ljava/lang/Object;)Z
     116: pop
     117: aload_0
     118: invokestatic  #181                // Method java/util/Collections.unmodifiableList:(Ljava/util/List;)Ljava/util/List;
     121: putstatic     #112                // Field FAIL_ON_WRITE_ERROR_PROPERTIES:Ljava/util/List;
     124: new           #57                 // class java/util/concurrent/atomic/AtomicBoolean
     127: dup
     128: invokespecial #191                // Method java/util/concurrent/atomic/AtomicBoolean."<init>":()V
     131: putstatic     #52                 // Field created:Ljava/util/concurrent/atomic/AtomicBoolean;
     134: return
}
