Compiled from "AppScriptStateRouter.java"
public class org.apache.dubbo.rpc.cluster.router.script.config.AppScriptStateRouter<T> extends org.apache.dubbo.rpc.cluster.router.state.AbstractStateRouter<T> implements org.apache.dubbo.common.config.configcenter.ConfigurationListener {
  private static final org.apache.dubbo.common.logger.ErrorTypeAwareLogger logger;

  private static final java.lang.String RULE_SUFFIX;

  private org.apache.dubbo.rpc.cluster.router.script.config.model.ScriptRule scriptRule;

  private org.apache.dubbo.rpc.cluster.router.script.ScriptStateRouter<T> scriptRouter;

  private java.lang.String application;

  public org.apache.dubbo.rpc.cluster.router.script.config.AppScriptStateRouter(org.apache.dubbo.common.URL);
    Code:
       0: aload_0
       1: aload_1
       2: invokespecial #3                  // Method org/apache/dubbo/rpc/cluster/router/state/AbstractStateRouter."<init>":(Lorg/apache/dubbo/common/URL;)V
       5: return

  protected org.apache.dubbo.rpc.cluster.router.state.BitList<org.apache.dubbo.rpc.Invoker<T>> doRoute(org.apache.dubbo.rpc.cluster.router.state.BitList<org.apache.dubbo.rpc.Invoker<T>>, org.apache.dubbo.common.URL, org.apache.dubbo.rpc.Invocation, boolean, org.apache.dubbo.common.utils.Holder<org.apache.dubbo.rpc.cluster.router.RouterSnapshotNode<T>>, org.apache.dubbo.common.utils.Holder<java.lang.String>) throws org.apache.dubbo.rpc.RpcException;
    Code:
       0: aload_0
       1: getfield      #4                  // Field scriptRouter:Lorg/apache/dubbo/rpc/cluster/router/script/ScriptStateRouter;
       4: ifnull        27
       7: aload_0
       8: getfield      #5                  // Field scriptRule:Lorg/apache/dubbo/rpc/cluster/router/script/config/model/ScriptRule;
      11: invokevirtual #6                  // Method org/apache/dubbo/rpc/cluster/router/script/config/model/ScriptRule.isValid:()Z
      14: ifeq          27
      17: aload_0
      18: getfield      #5                  // Field scriptRule:Lorg/apache/dubbo/rpc/cluster/router/script/config/model/ScriptRule;
      21: invokevirtual #7                  // Method org/apache/dubbo/rpc/cluster/router/script/config/model/ScriptRule.isEnabled:()Z
      24: ifne          76
      27: iload         4
      29: ifeq          74
      32: aload         6
      34: new           #8                  // class java/lang/StringBuilder
      37: dup
      38: invokespecial #9                  // Method java/lang/StringBuilder."<init>":()V
      41: ldc           #10                 // String Directly return from script router. Reason: Invokers from previous router is empty or script is not enabled. Script rule is:
      43: invokevirtual #11                 // Method java/lang/StringBuilder.append:(Ljava/lang/String;)Ljava/lang/StringBuilder;
      46: aload_0
      47: getfield      #5                  // Field scriptRule:Lorg/apache/dubbo/rpc/cluster/router/script/config/model/ScriptRule;
      50: ifnonnull     58
      53: ldc           #12                 // String null
      55: goto          65
      58: aload_0
      59: getfield      #5                  // Field scriptRule:Lorg/apache/dubbo/rpc/cluster/router/script/config/model/ScriptRule;
      62: invokevirtual #13                 // Method org/apache/dubbo/rpc/cluster/router/script/config/model/ScriptRule.getRawRule:()Ljava/lang/String;
      65: invokevirtual #11                 // Method java/lang/StringBuilder.append:(Ljava/lang/String;)Ljava/lang/StringBuilder;
      68: invokevirtual #14                 // Method java/lang/StringBuilder.toString:()Ljava/lang/String;
      71: invokevirtual #15                 // Method org/apache/dubbo/common/utils/Holder.set:(Ljava/lang/Object;)V
      74: aload_1
      75: areturn
      76: aload_0
      77: getfield      #4                  // Field scriptRouter:Lorg/apache/dubbo/rpc/cluster/router/script/ScriptStateRouter;
      80: aload_1
      81: aload_2
      82: aload_3
      83: iload         4
      85: aload         5
      87: invokevirtual #16                 // Method org/apache/dubbo/rpc/cluster/router/script/ScriptStateRouter.route:(Lorg/apache/dubbo/rpc/cluster/router/state/BitList;Lorg/apache/dubbo/common/URL;Lorg/apache/dubbo/rpc/Invocation;ZLorg/apache/dubbo/common/utils/Holder;)Lorg/apache/dubbo/rpc/cluster/router/state/BitList;
      90: astore_1
      91: iload         4
      93: ifeq          106
      96: aload         6
      98: aload         6
     100: invokevirtual #17                 // Method org/apache/dubbo/common/utils/Holder.get:()Ljava/lang/Object;
     103: invokevirtual #15                 // Method org/apache/dubbo/common/utils/Holder.set:(Ljava/lang/Object;)V
     106: aload_1
     107: areturn

  public synchronized void process(org.apache.dubbo.common.config.configcenter.ConfigChangedEvent);
    Code:
       0: getstatic     #18                 // Field logger:Lorg/apache/dubbo/common/logger/ErrorTypeAwareLogger;
       3: invokeinterface #19,  1           // InterfaceMethod org/apache/dubbo/common/logger/ErrorTypeAwareLogger.isDebugEnabled:()Z
       8: ifeq          53
      11: getstatic     #18                 // Field logger:Lorg/apache/dubbo/common/logger/ErrorTypeAwareLogger;
      14: new           #8                  // class java/lang/StringBuilder
      17: dup
      18: invokespecial #9                  // Method java/lang/StringBuilder."<init>":()V
      21: ldc           #20                 // String Notification of script rule change, type is:
      23: invokevirtual #11                 // Method java/lang/StringBuilder.append:(Ljava/lang/String;)Ljava/lang/StringBuilder;
      26: aload_1
      27: invokevirtual #21                 // Method org/apache/dubbo/common/config/configcenter/ConfigChangedEvent.getChangeType:()Lorg/apache/dubbo/common/config/configcenter/ConfigChangeType;
      30: invokevirtual #22                 // Method java/lang/StringBuilder.append:(Ljava/lang/Object;)Ljava/lang/StringBuilder;
      33: ldc           #23                 // String , raw rule is:\n
      35: invokevirtual #11                 // Method java/lang/StringBuilder.append:(Ljava/lang/String;)Ljava/lang/StringBuilder;
      38: aload_1
      39: invokevirtual #24                 // Method org/apache/dubbo/common/config/configcenter/ConfigChangedEvent.getContent:()Ljava/lang/String;
      42: invokevirtual #11                 // Method java/lang/StringBuilder.append:(Ljava/lang/String;)Ljava/lang/StringBuilder;
      45: invokevirtual #14                 // Method java/lang/StringBuilder.toString:()Ljava/lang/String;
      48: invokeinterface #25,  2           // InterfaceMethod org/apache/dubbo/common/logger/ErrorTypeAwareLogger.debug:(Ljava/lang/String;)V
      53: aload_1
      54: invokevirtual #21                 // Method org/apache/dubbo/common/config/configcenter/ConfigChangedEvent.getChangeType:()Lorg/apache/dubbo/common/config/configcenter/ConfigChangeType;
      57: getstatic     #26                 // Field org/apache/dubbo/common/config/configcenter/ConfigChangeType.DELETED:Lorg/apache/dubbo/common/config/configcenter/ConfigChangeType;
      60: invokevirtual #27                 // Method org/apache/dubbo/common/config/configcenter/ConfigChangeType.equals:(Ljava/lang/Object;)Z
      63: ifeq          74
      66: aload_0
      67: aconst_null
      68: putfield      #5                  // Field scriptRule:Lorg/apache/dubbo/rpc/cluster/router/script/config/model/ScriptRule;
      71: goto          168
      74: aload_0
      75: aload_1
      76: invokevirtual #24                 // Method org/apache/dubbo/common/config/configcenter/ConfigChangedEvent.getContent:()Ljava/lang/String;
      79: invokestatic  #28                 // Method org/apache/dubbo/rpc/cluster/router/script/config/model/ScriptRule.parse:(Ljava/lang/String;)Lorg/apache/dubbo/rpc/cluster/router/script/config/model/ScriptRule;
      82: putfield      #5                  // Field scriptRule:Lorg/apache/dubbo/rpc/cluster/router/script/config/model/ScriptRule;
      85: aload_0
      86: invokevirtual #29                 // Method getUrl:()Lorg/apache/dubbo/common/URL;
      89: ldc           #30                 // String type
      91: aload_0
      92: getfield      #5                  // Field scriptRule:Lorg/apache/dubbo/rpc/cluster/router/script/config/model/ScriptRule;
      95: invokevirtual #31                 // Method org/apache/dubbo/rpc/cluster/router/script/config/model/ScriptRule.getType:()Ljava/lang/String;
      98: invokestatic  #32                 // Method org/apache/dubbo/common/utils/StringUtils.isEmpty:(Ljava/lang/String;)Z
     101: ifeq          109
     104: ldc           #33                 // String javascript
     106: goto          116
     109: aload_0
     110: getfield      #5                  // Field scriptRule:Lorg/apache/dubbo/rpc/cluster/router/script/config/model/ScriptRule;
     113: invokevirtual #31                 // Method org/apache/dubbo/rpc/cluster/router/script/config/model/ScriptRule.getType:()Ljava/lang/String;
     116: invokevirtual #34                 // Method org/apache/dubbo/common/URL.addParameter:(Ljava/lang/String;Ljava/lang/String;)Lorg/apache/dubbo/common/URL;
     119: ldc           #35                 // String rule
     121: aload_0
     122: getfield      #5                  // Field scriptRule:Lorg/apache/dubbo/rpc/cluster/router/script/config/model/ScriptRule;
     125: invokevirtual #36                 // Method org/apache/dubbo/rpc/cluster/router/script/config/model/ScriptRule.getScript:()Ljava/lang/String;
     128: invokevirtual #37                 // Method org/apache/dubbo/common/URL.addParameterAndEncoded:(Ljava/lang/String;Ljava/lang/String;)Lorg/apache/dubbo/common/URL;
     131: ldc           #38                 // String force
     133: aload_0
     134: getfield      #5                  // Field scriptRule:Lorg/apache/dubbo/rpc/cluster/router/script/config/model/ScriptRule;
     137: invokevirtual #39                 // Method org/apache/dubbo/rpc/cluster/router/script/config/model/ScriptRule.isForce:()Z
     140: invokevirtual #40                 // Method org/apache/dubbo/common/URL.addParameter:(Ljava/lang/String;Z)Lorg/apache/dubbo/common/URL;
     143: ldc           #41                 // String runtime
     145: aload_0
     146: getfield      #5                  // Field scriptRule:Lorg/apache/dubbo/rpc/cluster/router/script/config/model/ScriptRule;
     149: invokevirtual #42                 // Method org/apache/dubbo/rpc/cluster/router/script/config/model/ScriptRule.isRuntime:()Z
     152: invokevirtual #40                 // Method org/apache/dubbo/common/URL.addParameter:(Ljava/lang/String;Z)Lorg/apache/dubbo/common/URL;
     155: astore_2
     156: aload_0
     157: new           #43                 // class org/apache/dubbo/rpc/cluster/router/script/ScriptStateRouter
     160: dup
     161: aload_2
     162: invokespecial #44                 // Method org/apache/dubbo/rpc/cluster/router/script/ScriptStateRouter."<init>":(Lorg/apache/dubbo/common/URL;)V
     165: putfield      #4                  // Field scriptRouter:Lorg/apache/dubbo/rpc/cluster/router/script/ScriptStateRouter;
     168: goto          189
     171: astore_2
     172: getstatic     #18                 // Field logger:Lorg/apache/dubbo/common/logger/ErrorTypeAwareLogger;
     175: ldc           #46                 // String 2-11
     177: ldc           #47                 // String Failed to parse the raw tag router rule
     179: ldc           #48                 // String
     181: ldc           #49                 // String Failed to parse the raw tag router rule and it will not take effect, please check if the rule matches with the template, the raw rule is:\n
     183: aload_2
     184: invokeinterface #50,  6           // InterfaceMethod org/apache/dubbo/common/logger/ErrorTypeAwareLogger.error:(Ljava/lang/String;Ljava/lang/String;Ljava/lang/String;Ljava/lang/String;Ljava/lang/Throwable;)V
     189: return
    Exception table:
       from    to  target type
          53   168   171   Class java/lang/Exception

  public void notify(org.apache.dubbo.rpc.cluster.router.state.BitList<org.apache.dubbo.rpc.Invoker<T>>);
    Code:
       0: aload_1
       1: invokestatic  #51                 // Method org/apache/dubbo/common/utils/CollectionUtils.isEmpty:(Ljava/util/Collection;)Z
       4: ifeq          8
       7: return
       8: aload_1
       9: iconst_0
      10: invokevirtual #52                 // Method org/apache/dubbo/rpc/cluster/router/state/BitList.get:(I)Ljava/lang/Object;
      13: checkcast     #53                 // class org/apache/dubbo/rpc/Invoker
      16: astore_2
      17: aload_2
      18: invokeinterface #54,  1           // InterfaceMethod org/apache/dubbo/rpc/Invoker.getUrl:()Lorg/apache/dubbo/common/URL;
      23: astore_3
      24: aload_3
      25: invokevirtual #55                 // Method org/apache/dubbo/common/URL.getRemoteApplication:()Ljava/lang/String;
      28: astore        4
      30: aload         4
      32: invokestatic  #32                 // Method org/apache/dubbo/common/utils/StringUtils.isEmpty:(Ljava/lang/String;)Z
      35: ifeq          55
      38: getstatic     #18                 // Field logger:Lorg/apache/dubbo/common/logger/ErrorTypeAwareLogger;
      41: ldc           #56                 // String 2-12
      43: ldc           #57                 // String tag router get providerApplication is empty
      45: ldc           #48                 // String
      47: ldc           #58                 // String TagRouter must getConfig from or subscribe to a specific application, but the application in this TagRouter is not specified.
      49: invokeinterface #59,  5           // InterfaceMethod org/apache/dubbo/common/logger/ErrorTypeAwareLogger.error:(Ljava/lang/String;Ljava/lang/String;Ljava/lang/String;Ljava/lang/String;)V
      54: return
      55: aload_0
      56: dup
      57: astore        5
      59: monitorenter
      60: aload         4
      62: aload_0
      63: getfield      #60                 // Field application:Ljava/lang/String;
      66: invokevirtual #61                 // Method java/lang/String.equals:(Ljava/lang/Object;)Z
      69: ifne          194
      72: aload_0
      73: getfield      #60                 // Field application:Ljava/lang/String;
      76: invokestatic  #62                 // Method org/apache/dubbo/common/utils/StringUtils.isNotEmpty:(Ljava/lang/String;)Z
      79: ifeq          114
      82: aload_0
      83: invokevirtual #63                 // Method getRuleRepository:()Lorg/apache/dubbo/rpc/cluster/governance/GovernanceRuleRepository;
      86: new           #8                  // class java/lang/StringBuilder
      89: dup
      90: invokespecial #9                  // Method java/lang/StringBuilder."<init>":()V
      93: aload_0
      94: getfield      #60                 // Field application:Ljava/lang/String;
      97: invokevirtual #11                 // Method java/lang/StringBuilder.append:(Ljava/lang/String;)Ljava/lang/StringBuilder;
     100: ldc           #65                 // String .script-router
     102: invokevirtual #11                 // Method java/lang/StringBuilder.append:(Ljava/lang/String;)Ljava/lang/StringBuilder;
     105: invokevirtual #14                 // Method java/lang/StringBuilder.toString:()Ljava/lang/String;
     108: aload_0
     109: invokeinterface #66,  3           // InterfaceMethod org/apache/dubbo/rpc/cluster/governance/GovernanceRuleRepository.removeListener:(Ljava/lang/String;Lorg/apache/dubbo/common/config/configcenter/ConfigurationListener;)V
     114: new           #8                  // class java/lang/StringBuilder
     117: dup
     118: invokespecial #9                  // Method java/lang/StringBuilder."<init>":()V
     121: aload         4
     123: invokevirtual #11                 // Method java/lang/StringBuilder.append:(Ljava/lang/String;)Ljava/lang/StringBuilder;
     126: ldc           #65                 // String .script-router
     128: invokevirtual #11                 // Method java/lang/StringBuilder.append:(Ljava/lang/String;)Ljava/lang/StringBuilder;
     131: invokevirtual #14                 // Method java/lang/StringBuilder.toString:()Ljava/lang/String;
     134: astore        6
     136: aload_0
     137: invokevirtual #63                 // Method getRuleRepository:()Lorg/apache/dubbo/rpc/cluster/governance/GovernanceRuleRepository;
     140: aload         6
     142: aload_0
     143: invokeinterface #67,  3           // InterfaceMethod org/apache/dubbo/rpc/cluster/governance/GovernanceRuleRepository.addListener:(Ljava/lang/String;Lorg/apache/dubbo/common/config/configcenter/ConfigurationListener;)V
     148: aload_0
     149: aload         4
     151: putfield      #60                 // Field application:Ljava/lang/String;
     154: aload_0
     155: invokevirtual #63                 // Method getRuleRepository:()Lorg/apache/dubbo/rpc/cluster/governance/GovernanceRuleRepository;
     158: aload         6
     160: ldc           #69                 // String dubbo
     162: invokeinterface #70,  3           // InterfaceMethod org/apache/dubbo/rpc/cluster/governance/GovernanceRuleRepository.getRule:(Ljava/lang/String;Ljava/lang/String;)Ljava/lang/String;
     167: astore        7
     169: aload         7
     171: invokestatic  #62                 // Method org/apache/dubbo/common/utils/StringUtils.isNotEmpty:(Ljava/lang/String;)Z
     174: ifeq          194
     177: aload_0
     178: new           #71                 // class org/apache/dubbo/common/config/configcenter/ConfigChangedEvent
     181: dup
     182: aload         6
     184: ldc           #69                 // String dubbo
     186: aload         7
     188: invokespecial #72                 // Method org/apache/dubbo/common/config/configcenter/ConfigChangedEvent."<init>":(Ljava/lang/String;Ljava/lang/String;Ljava/lang/String;)V
     191: invokevirtual #73                 // Method process:(Lorg/apache/dubbo/common/config/configcenter/ConfigChangedEvent;)V
     194: aload         5
     196: monitorexit
     197: goto          208
     200: astore        8
     202: aload         5
     204: monitorexit
     205: aload         8
     207: athrow
     208: return
    Exception table:
       from    to  target type
          60   197   200   any
         200   205   200   any

  public void stop();
    Code:
       0: aload_0
       1: getfield      #60                 // Field application:Ljava/lang/String;
       4: invokestatic  #62                 // Method org/apache/dubbo/common/utils/StringUtils.isNotEmpty:(Ljava/lang/String;)Z
       7: ifeq          42
      10: aload_0
      11: invokevirtual #63                 // Method getRuleRepository:()Lorg/apache/dubbo/rpc/cluster/governance/GovernanceRuleRepository;
      14: new           #8                  // class java/lang/StringBuilder
      17: dup
      18: invokespecial #9                  // Method java/lang/StringBuilder."<init>":()V
      21: aload_0
      22: getfield      #60                 // Field application:Ljava/lang/String;
      25: invokevirtual #11                 // Method java/lang/StringBuilder.append:(Ljava/lang/String;)Ljava/lang/StringBuilder;
      28: ldc           #65                 // String .script-router
      30: invokevirtual #11                 // Method java/lang/StringBuilder.append:(Ljava/lang/String;)Ljava/lang/StringBuilder;
      33: invokevirtual #14                 // Method java/lang/StringBuilder.toString:()Ljava/lang/String;
      36: aload_0
      37: invokeinterface #66,  3           // InterfaceMethod org/apache/dubbo/rpc/cluster/governance/GovernanceRuleRepository.removeListener:(Ljava/lang/String;Lorg/apache/dubbo/common/config/configcenter/ConfigurationListener;)V
      42: return

  public void setScriptRule(org.apache.dubbo.rpc.cluster.router.script.config.model.ScriptRule);
    Code:
       0: aload_0
       1: aload_1
       2: putfield      #5                  // Field scriptRule:Lorg/apache/dubbo/rpc/cluster/router/script/config/model/ScriptRule;
       5: return

  static {};
    Code:
       0: ldc           #64                 // class org/apache/dubbo/rpc/cluster/router/script/config/AppScriptStateRouter
       2: invokestatic  #74                 // Method org/apache/dubbo/common/logger/LoggerFactory.getErrorTypeAwareLogger:(Ljava/lang/Class;)Lorg/apache/dubbo/common/logger/ErrorTypeAwareLogger;
       5: putstatic     #18                 // Field logger:Lorg/apache/dubbo/common/logger/ErrorTypeAwareLogger;
       8: return
}
