Compiled from "MessageOnlyDispatcher.java"
public class org.apache.dubbo.remoting.transport.dispatcher.message.MessageOnlyDispatcher implements org.apache.dubbo.remoting.Dispatcher {
  public static final java.lang.String NAME;

  public org.apache.dubbo.remoting.transport.dispatcher.message.MessageOnlyDispatcher();
    Code:
       0: aload_0
       1: invokespecial #1                  // Method java/lang/Object."<init>":()V
       4: return

  public org.apache.dubbo.remoting.ChannelHandler dispatch(org.apache.dubbo.remoting.ChannelHandler, org.apache.dubbo.common.URL);
    Code:
       0: new           #2                  // class org/apache/dubbo/remoting/transport/dispatcher/message/MessageOnlyChannelHandler
       3: dup
       4: aload_1
       5: aload_2
       6: invokespecial #3                  // Method org/apache/dubbo/remoting/transport/dispatcher/message/MessageOnlyChannelHandler."<init>":(Lorg/apache/dubbo/remoting/ChannelHandler;Lorg/apache/dubbo/common/URL;)V
       9: areturn
}
