Compiled from "BoundConfigurationProperties.java"
public class org.springframework.boot.context.properties.BoundConfigurationProperties {
  private final java.util.Map<org.springframework.boot.context.properties.source.ConfigurationPropertyName, org.springframework.boot.context.properties.source.ConfigurationProperty> properties;

  private static final java.lang.String BEAN_NAME;

  public org.springframework.boot.context.properties.BoundConfigurationProperties();
    Code:
       0: aload_0
       1: invokespecial #1                  // Method java/lang/Object."<init>":()V
       4: aload_0
       5: new           #7                  // class java/util/LinkedHashMap
       8: dup
       9: invokespecial #9                  // Method java/util/LinkedHashMap."<init>":()V
      12: putfield      #10                 // Field properties:Ljava/util/Map;
      15: return

  void add(org.springframework.boot.context.properties.source.ConfigurationProperty);
    Code:
       0: aload_0
       1: getfield      #10                 // Field properties:Ljava/util/Map;
       4: aload_1
       5: invokevirtual #16                 // Method org/springframework/boot/context/properties/source/ConfigurationProperty.getName:()Lorg/springframework/boot/context/properties/source/ConfigurationPropertyName;
       8: aload_1
       9: invokeinterface #22,  3           // InterfaceMethod java/util/Map.put:(Ljava/lang/Object;Ljava/lang/Object;)Ljava/lang/Object;
      14: pop
      15: return

  public org.springframework.boot.context.properties.source.ConfigurationProperty get(org.springframework.boot.context.properties.source.ConfigurationPropertyName);
    Code:
       0: aload_0
       1: getfield      #10                 // Field properties:Ljava/util/Map;
       4: aload_1
       5: invokeinterface #28,  2           // InterfaceMethod java/util/Map.get:(Ljava/lang/Object;)Ljava/lang/Object;
      10: checkcast     #17                 // class org/springframework/boot/context/properties/source/ConfigurationProperty
      13: areturn

  public java.util.Map<org.springframework.boot.context.properties.source.ConfigurationPropertyName, org.springframework.boot.context.properties.source.ConfigurationProperty> getAll();
    Code:
       0: aload_0
       1: getfield      #10                 // Field properties:Ljava/util/Map;
       4: invokestatic  #32                 // Method java/util/Collections.unmodifiableMap:(Ljava/util/Map;)Ljava/util/Map;
       7: areturn

  public static org.springframework.boot.context.properties.BoundConfigurationProperties get(org.springframework.context.ApplicationContext);
    Code:
       0: aload_0
       1: getstatic     #38                 // Field BEAN_NAME:Ljava/lang/String;
       4: invokeinterface #42,  2           // InterfaceMethod org/springframework/context/ApplicationContext.containsBeanDefinition:(Ljava/lang/String;)Z
       9: ifne          14
      12: aconst_null
      13: areturn
      14: aload_0
      15: getstatic     #38                 // Field BEAN_NAME:Ljava/lang/String;
      18: ldc           #11                 // class org/springframework/boot/context/properties/BoundConfigurationProperties
      20: invokeinterface #48,  3           // InterfaceMethod org/springframework/context/ApplicationContext.getBean:(Ljava/lang/String;Ljava/lang/Class;)Ljava/lang/Object;
      25: checkcast     #11                 // class org/springframework/boot/context/properties/BoundConfigurationProperties
      28: areturn

  static void register(org.springframework.beans.factory.support.BeanDefinitionRegistry);
    Code:
       0: aload_0
       1: ldc           #52                 // String Registry must not be null
       3: invokestatic  #54                 // Method org/springframework/util/Assert.notNull:(Ljava/lang/Object;Ljava/lang/String;)V
       6: aload_0
       7: getstatic     #38                 // Field BEAN_NAME:Ljava/lang/String;
      10: invokeinterface #60,  2           // InterfaceMethod org/springframework/beans/factory/support/BeanDefinitionRegistry.containsBeanDefinition:(Ljava/lang/String;)Z
      15: ifne          44
      18: ldc           #11                 // class org/springframework/boot/context/properties/BoundConfigurationProperties
      20: invokestatic  #63                 // Method org/springframework/beans/factory/support/BeanDefinitionBuilder.genericBeanDefinition:(Ljava/lang/Class;)Lorg/springframework/beans/factory/support/BeanDefinitionBuilder;
      23: invokevirtual #69                 // Method org/springframework/beans/factory/support/BeanDefinitionBuilder.getBeanDefinition:()Lorg/springframework/beans/factory/support/AbstractBeanDefinition;
      26: astore_1
      27: aload_1
      28: iconst_2
      29: invokeinterface #75,  2           // InterfaceMethod org/springframework/beans/factory/config/BeanDefinition.setRole:(I)V
      34: aload_0
      35: getstatic     #38                 // Field BEAN_NAME:Ljava/lang/String;
      38: aload_1
      39: invokeinterface #79,  3           // InterfaceMethod org/springframework/beans/factory/support/BeanDefinitionRegistry.registerBeanDefinition:(Ljava/lang/String;Lorg/springframework/beans/factory/config/BeanDefinition;)V
      44: return

  static {};
    Code:
       0: ldc           #11                 // class org/springframework/boot/context/properties/BoundConfigurationProperties
       2: invokevirtual #83                 // Method java/lang/Class.getName:()Ljava/lang/String;
       5: putstatic     #38                 // Field BEAN_NAME:Ljava/lang/String;
       8: return
}
