Compiled from "ConfigurationPropertiesBeanRegistrationAotProcessor.java"
class org.springframework.boot.context.properties.ConfigurationPropertiesBeanRegistrationAotProcessor implements org.springframework.beans.factory.aot.BeanRegistrationAotProcessor {
  org.springframework.boot.context.properties.ConfigurationPropertiesBeanRegistrationAotProcessor();
    Code:
       0: aload_0
       1: invokespecial #1                  // Method java/lang/Object."<init>":()V
       4: return

  public org.springframework.beans.factory.aot.BeanRegistrationAotContribution processAheadOfTime(org.springframework.beans.factory.support.RegisteredBean);
    Code:
       0: aload_0
       1: aload_1
       2: invokevirtual #7                  // Method org/springframework/beans/factory/support/RegisteredBean.getMergedBeanDefinition:()Lorg/springframework/beans/factory/support/RootBeanDefinition;
       5: invokevirtual #13                 // Method isImmutableConfigurationPropertiesBeanDefinition:(Lorg/springframework/beans/factory/config/BeanDefinition;)Z
       8: ifne          13
      11: aconst_null
      12: areturn
      13: aload_1
      14: invokedynamic #19,  0             // InvokeDynamic #0:apply:(Lorg/springframework/beans/factory/support/RegisteredBean;)Ljava/util/function/UnaryOperator;
      19: invokestatic  #23                 // InterfaceMethod org/springframework/beans/factory/aot/BeanRegistrationAotContribution.withCustomCodeFragments:(Ljava/util/function/UnaryOperator;)Lorg/springframework/beans/factory/aot/BeanRegistrationAotContribution;
      22: areturn

  private boolean isImmutableConfigurationPropertiesBeanDefinition(org.springframework.beans.factory.config.BeanDefinition);
    Code:
       0: aload_1
       1: ldc           #29                 // class org/springframework/boot/context/properties/ConfigurationPropertiesBean$BindMethod
       3: invokevirtual #31                 // Method java/lang/Class.getName:()Ljava/lang/String;
       6: invokeinterface #37,  2           // InterfaceMethod org/springframework/beans/factory/config/BeanDefinition.hasAttribute:(Ljava/lang/String;)Z
      11: ifeq          38
      14: getstatic     #43                 // Field org/springframework/boot/context/properties/ConfigurationPropertiesBean$BindMethod.VALUE_OBJECT:Lorg/springframework/boot/context/properties/ConfigurationPropertiesBean$BindMethod;
      17: aload_1
      18: ldc           #29                 // class org/springframework/boot/context/properties/ConfigurationPropertiesBean$BindMethod
      20: invokevirtual #31                 // Method java/lang/Class.getName:()Ljava/lang/String;
      23: invokeinterface #47,  2           // InterfaceMethod org/springframework/beans/factory/config/BeanDefinition.getAttribute:(Ljava/lang/String;)Ljava/lang/Object;
      28: invokevirtual #51                 // Method org/springframework/boot/context/properties/ConfigurationPropertiesBean$BindMethod.equals:(Ljava/lang/Object;)Z
      31: ifeq          38
      34: iconst_1
      35: goto          39
      38: iconst_0
      39: ireturn

  private static org.springframework.beans.factory.aot.BeanRegistrationCodeFragments lambda$processAheadOfTime$0(org.springframework.beans.factory.support.RegisteredBean, org.springframework.beans.factory.aot.BeanRegistrationCodeFragments);
    Code:
       0: new           #55                 // class org/springframework/boot/context/properties/ConfigurationPropertiesBeanRegistrationAotProcessor$ConfigurationPropertiesBeanRegistrationCodeFragments
       3: dup
       4: aload_1
       5: aload_0
       6: invokespecial #57                 // Method org/springframework/boot/context/properties/ConfigurationPropertiesBeanRegistrationAotProcessor$ConfigurationPropertiesBeanRegistrationCodeFragments."<init>":(Lorg/springframework/beans/factory/aot/BeanRegistrationCodeFragments;Lorg/springframework/beans/factory/support/RegisteredBean;)V
       9: areturn
}
