Compiled from "ConfigurationPropertiesBeanFactoryInitializationAotProcessor.java"
final class org.springframework.boot.context.properties.ConfigurationPropertiesBeanFactoryInitializationAotProcessor$ConfigurationPropertiesReflectionHintsContribution implements org.springframework.beans.factory.aot.BeanFactoryInitializationAotContribution {
  private final java.lang.Iterable<java.lang.Class<?>> types;

  private org.springframework.boot.context.properties.ConfigurationPropertiesBeanFactoryInitializationAotProcessor$ConfigurationPropertiesReflectionHintsContribution(java.lang.Iterable<java.lang.Class<?>>);
    Code:
       0: aload_0
       1: invokespecial #1                  // Method java/lang/Object."<init>":()V
       4: aload_0
       5: aload_1
       6: putfield      #7                  // Field types:Ljava/lang/Iterable;
       9: return

  public void applyTo(org.springframework.aot.generate.GenerationContext, org.springframework.beans.factory.aot.BeanFactoryInitializationCode);
    Code:
       0: aload_0
       1: getfield      #7                  // Field types:Ljava/lang/Iterable;
       4: invokestatic  #13                 // Method org/springframework/boot/context/properties/bind/BindableRuntimeHintsRegistrar.forTypes:(Ljava/lang/Iterable;)Lorg/springframework/boot/context/properties/bind/BindableRuntimeHintsRegistrar;
       7: aload_1
       8: invokeinterface #19,  1           // InterfaceMethod org/springframework/aot/generate/GenerationContext.getRuntimeHints:()Lorg/springframework/aot/hint/RuntimeHints;
      13: invokevirtual #25                 // Method org/springframework/boot/context/properties/bind/BindableRuntimeHintsRegistrar.registerHints:(Lorg/springframework/aot/hint/RuntimeHints;)V
      16: return
}
