Compiled from "ConfigurationPropertiesJsr303Validator.java"
class org.springframework.boot.context.properties.ConfigurationPropertiesJsr303Validator$Delegate extends org.springframework.validation.beanvalidation.LocalValidatorFactoryBean {
  org.springframework.boot.context.properties.ConfigurationPropertiesJsr303Validator$Delegate(org.springframework.context.ApplicationContext);
    Code:
       0: aload_0
       1: invokespecial #1                  // Method org/springframework/validation/beanvalidation/LocalValidatorFactoryBean."<init>":()V
       4: aload_0
       5: aload_1
       6: invokevirtual #7                  // Method setApplicationContext:(Lorg/springframework/context/ApplicationContext;)V
       9: aload_0
      10: new           #13                 // class org/springframework/boot/validation/MessageInterpolatorFactory
      13: dup
      14: aload_1
      15: invokespecial #15                 // Method org/springframework/boot/validation/MessageInterpolatorFactory."<init>":(Lorg/springframework/context/MessageSource;)V
      18: invokevirtual #18                 // Method org/springframework/boot/validation/MessageInterpolatorFactory.getObject:()Ljakarta/validation/MessageInterpolator;
      21: invokevirtual #22                 // Method setMessageInterpolator:(Ljakarta/validation/MessageInterpolator;)V
      24: aload_0
      25: invokevirtual #26                 // Method afterPropertiesSet:()V
      28: return
}
