Compiled from "ConfigurationPropertiesBeanRegistrationAotProcessor.java"
class org.springframework.boot.context.properties.ConfigurationPropertiesBeanRegistrationAotProcessor$ConfigurationPropertiesBeanRegistrationCodeFragments extends org.springframework.beans.factory.aot.BeanRegistrationCodeFragmentsDecorator {
  private static final java.util.function.Predicate<java.lang.String> INCLUDE_BIND_METHOD_ATTRIBUTE_FILTER;

  private static final java.lang.String REGISTERED_BEAN_PARAMETER_NAME;

  private final org.springframework.beans.factory.support.RegisteredBean registeredBean;

  org.springframework.boot.context.properties.ConfigurationPropertiesBeanRegistrationAotProcessor$ConfigurationPropertiesBeanRegistrationCodeFragments(org.springframework.beans.factory.aot.BeanRegistrationCodeFragments, org.springframework.beans.factory.support.RegisteredBean);
    Code:
       0: aload_0
       1: aload_1
       2: invokespecial #1                  // Method org/springframework/beans/factory/aot/BeanRegistrationCodeFragmentsDecorator."<init>":(Lorg/springframework/beans/factory/aot/BeanRegistrationCodeFragments;)V
       5: aload_0
       6: aload_2
       7: putfield      #7                  // Field registeredBean:Lorg/springframework/beans/factory/support/RegisteredBean;
      10: return

  public org.springframework.javapoet.CodeBlock generateSetBeanDefinitionPropertiesCode(org.springframework.aot.generate.GenerationContext, org.springframework.beans.factory.aot.BeanRegistrationCode, org.springframework.beans.factory.support.RootBeanDefinition, java.util.function.Predicate<java.lang.String>);
    Code:
       0: aload_0
       1: aload_1
       2: aload_2
       3: aload_3
       4: getstatic     #13                 // Field INCLUDE_BIND_METHOD_ATTRIBUTE_FILTER:Ljava/util/function/Predicate;
       7: aload         4
       9: invokeinterface #17,  2           // InterfaceMethod java/util/function/Predicate.or:(Ljava/util/function/Predicate;)Ljava/util/function/Predicate;
      14: invokespecial #23                 // Method org/springframework/beans/factory/aot/BeanRegistrationCodeFragmentsDecorator.generateSetBeanDefinitionPropertiesCode:(Lorg/springframework/aot/generate/GenerationContext;Lorg/springframework/beans/factory/aot/BeanRegistrationCode;Lorg/springframework/beans/factory/support/RootBeanDefinition;Ljava/util/function/Predicate;)Lorg/springframework/javapoet/CodeBlock;
      17: areturn

  public org.springframework.javapoet.CodeBlock generateInstanceSupplierCode(org.springframework.aot.generate.GenerationContext, org.springframework.beans.factory.aot.BeanRegistrationCode, java.lang.reflect.Executable, boolean);
    Code:
       0: aload_2
       1: invokeinterface #27,  1           // InterfaceMethod org/springframework/beans/factory/aot/BeanRegistrationCode.getMethods:()Lorg/springframework/aot/generate/GeneratedMethods;
       6: ldc           #33                 // String getInstance
       8: aload_0
       9: invokedynamic #35,  0             // InvokeDynamic #0:accept:(Lorg/springframework/boot/context/properties/ConfigurationPropertiesBeanRegistrationAotProcessor$ConfigurationPropertiesBeanRegistrationCodeFragments;)Ljava/util/function/Consumer;
      14: invokevirtual #39                 // Method org/springframework/aot/generate/GeneratedMethods.add:(Ljava/lang/String;Ljava/util/function/Consumer;)Lorg/springframework/aot/generate/GeneratedMethod;
      17: astore        5
      19: ldc           #45                 // String $T.of($T::$L)
      21: iconst_3
      22: anewarray     #47                 // class java/lang/Object
      25: dup
      26: iconst_0
      27: ldc           #49                 // class org/springframework/beans/factory/support/InstanceSupplier
      29: aastore
      30: dup
      31: iconst_1
      32: aload_2
      33: invokeinterface #51,  1           // InterfaceMethod org/springframework/beans/factory/aot/BeanRegistrationCode.getClassName:()Lorg/springframework/javapoet/ClassName;
      38: aastore
      39: dup
      40: iconst_2
      41: aload         5
      43: invokevirtual #55                 // Method org/springframework/aot/generate/GeneratedMethod.getName:()Ljava/lang/String;
      46: aastore
      47: invokestatic  #61                 // Method org/springframework/javapoet/CodeBlock.of:(Ljava/lang/String;[Ljava/lang/Object;)Lorg/springframework/javapoet/CodeBlock;
      50: areturn

  private void lambda$generateInstanceSupplierCode$1(org.springframework.javapoet.MethodSpec$Builder);
    Code:
       0: aload_0
       1: getfield      #7                  // Field registeredBean:Lorg/springframework/beans/factory/support/RegisteredBean;
       4: invokevirtual #67                 // Method org/springframework/beans/factory/support/RegisteredBean.getBeanClass:()Ljava/lang/Class;
       7: astore_2
       8: aload_1
       9: ldc           #73                 // String Get the bean instance for \'$L\'.
      11: iconst_1
      12: anewarray     #47                 // class java/lang/Object
      15: dup
      16: iconst_0
      17: aload_0
      18: getfield      #7                  // Field registeredBean:Lorg/springframework/beans/factory/support/RegisteredBean;
      21: invokevirtual #75                 // Method org/springframework/beans/factory/support/RegisteredBean.getBeanName:()Ljava/lang/String;
      24: aastore
      25: invokevirtual #78                 // Method org/springframework/javapoet/MethodSpec$Builder.addJavadoc:(Ljava/lang/String;[Ljava/lang/Object;)Lorg/springframework/javapoet/MethodSpec$Builder;
      28: iconst_2
      29: anewarray     #84                 // class javax/lang/model/element/Modifier
      32: dup
      33: iconst_0
      34: getstatic     #86                 // Field javax/lang/model/element/Modifier.PRIVATE:Ljavax/lang/model/element/Modifier;
      37: aastore
      38: dup
      39: iconst_1
      40: getstatic     #90                 // Field javax/lang/model/element/Modifier.STATIC:Ljavax/lang/model/element/Modifier;
      43: aastore
      44: invokevirtual #93                 // Method org/springframework/javapoet/MethodSpec$Builder.addModifiers:([Ljavax/lang/model/element/Modifier;)Lorg/springframework/javapoet/MethodSpec$Builder;
      47: aload_2
      48: invokevirtual #97                 // Method org/springframework/javapoet/MethodSpec$Builder.returns:(Ljava/lang/reflect/Type;)Lorg/springframework/javapoet/MethodSpec$Builder;
      51: ldc           #68                 // class org/springframework/beans/factory/support/RegisteredBean
      53: ldc           #101                // String registeredBean
      55: iconst_0
      56: anewarray     #84                 // class javax/lang/model/element/Modifier
      59: invokevirtual #102                // Method org/springframework/javapoet/MethodSpec$Builder.addParameter:(Ljava/lang/reflect/Type;Ljava/lang/String;[Ljavax/lang/model/element/Modifier;)Lorg/springframework/javapoet/MethodSpec$Builder;
      62: ldc           #106                // String $T beanFactory = registeredBean.getBeanFactory()
      64: iconst_1
      65: anewarray     #47                 // class java/lang/Object
      68: dup
      69: iconst_0
      70: ldc           #108                // class org/springframework/beans/factory/BeanFactory
      72: aastore
      73: invokevirtual #110                // Method org/springframework/javapoet/MethodSpec$Builder.addStatement:(Ljava/lang/String;[Ljava/lang/Object;)Lorg/springframework/javapoet/MethodSpec$Builder;
      76: ldc           #113                // String $T beanName = registeredBean.getBeanName()
      78: iconst_1
      79: anewarray     #47                 // class java/lang/Object
      82: dup
      83: iconst_0
      84: ldc           #115                // class java/lang/String
      86: aastore
      87: invokevirtual #110                // Method org/springframework/javapoet/MethodSpec$Builder.addStatement:(Ljava/lang/String;[Ljava/lang/Object;)Lorg/springframework/javapoet/MethodSpec$Builder;
      90: ldc           #117                // String $T<?> beanClass = registeredBean.getBeanClass()
      92: iconst_1
      93: anewarray     #47                 // class java/lang/Object
      96: dup
      97: iconst_0
      98: ldc           #119                // class java/lang/Class
     100: aastore
     101: invokevirtual #110                // Method org/springframework/javapoet/MethodSpec$Builder.addStatement:(Ljava/lang/String;[Ljava/lang/Object;)Lorg/springframework/javapoet/MethodSpec$Builder;
     104: ldc           #121                // String return ($T) $T.from(beanFactory, beanName, beanClass)
     106: iconst_2
     107: anewarray     #47                 // class java/lang/Object
     110: dup
     111: iconst_0
     112: aload_2
     113: aastore
     114: dup
     115: iconst_1
     116: ldc           #123                // class org/springframework/boot/context/properties/ConstructorBound
     118: aastore
     119: invokevirtual #110                // Method org/springframework/javapoet/MethodSpec$Builder.addStatement:(Ljava/lang/String;[Ljava/lang/Object;)Lorg/springframework/javapoet/MethodSpec$Builder;
     122: pop
     123: return

  private static boolean lambda$static$0(java.lang.String);
    Code:
       0: aload_0
       1: ldc           #125                // class org/springframework/boot/context/properties/ConfigurationPropertiesBean$BindMethod
       3: invokevirtual #127                // Method java/lang/Class.getName:()Ljava/lang/String;
       6: invokevirtual #128                // Method java/lang/String.equals:(Ljava/lang/Object;)Z
       9: ireturn

  static {};
    Code:
       0: invokedynamic #132,  0            // InvokeDynamic #1:test:()Ljava/util/function/Predicate;
       5: putstatic     #13                 // Field INCLUDE_BIND_METHOD_ATTRIBUTE_FILTER:Ljava/util/function/Predicate;
       8: return
}
