Compiled from "ConfigurationPropertiesBinder.java"
class org.springframework.boot.context.properties.ConfigurationPropertiesBinder {
  private static final java.lang.String BEAN_NAME;

  private static final java.lang.String VALIDATOR_BEAN_NAME;

  private final org.springframework.context.ApplicationContext applicationContext;

  private final org.springframework.core.env.PropertySources propertySources;

  private final org.springframework.validation.Validator configurationPropertiesValidator;

  private final boolean jsr303Present;

  private volatile org.springframework.validation.Validator jsr303Validator;

  private volatile org.springframework.boot.context.properties.bind.Binder binder;

  org.springframework.boot.context.properties.ConfigurationPropertiesBinder(org.springframework.context.ApplicationContext);
    Code:
       0: aload_0
       1: invokespecial #3                  // Method java/lang/Object."<init>":()V
       4: aload_0
       5: aload_1
       6: putfield      #9                  // Field applicationContext:Lorg/springframework/context/ApplicationContext;
       9: aload_0
      10: new           #15                 // class org/springframework/boot/context/properties/PropertySourcesDeducer
      13: dup
      14: aload_1
      15: invokespecial #17                 // Method org/springframework/boot/context/properties/PropertySourcesDeducer."<init>":(Lorg/springframework/context/ApplicationContext;)V
      18: invokevirtual #20                 // Method org/springframework/boot/context/properties/PropertySourcesDeducer.getPropertySources:()Lorg/springframework/core/env/PropertySources;
      21: putfield      #24                 // Field propertySources:Lorg/springframework/core/env/PropertySources;
      24: aload_0
      25: aload_0
      26: aload_1
      27: invokevirtual #28                 // Method getConfigurationPropertiesValidator:(Lorg/springframework/context/ApplicationContext;)Lorg/springframework/validation/Validator;
      30: putfield      #32                 // Field configurationPropertiesValidator:Lorg/springframework/validation/Validator;
      33: aload_0
      34: aload_1
      35: invokestatic  #36                 // Method org/springframework/boot/context/properties/ConfigurationPropertiesJsr303Validator.isJsr303Present:(Lorg/springframework/context/ApplicationContext;)Z
      38: putfield      #42                 // Field jsr303Present:Z
      41: return

  org.springframework.boot.context.properties.bind.BindResult<?> bind(org.springframework.boot.context.properties.ConfigurationPropertiesBean);
    Code:
       0: aload_1
       1: invokevirtual #46                 // Method org/springframework/boot/context/properties/ConfigurationPropertiesBean.asBindTarget:()Lorg/springframework/boot/context/properties/bind/Bindable;
       4: astore_2
       5: aload_1
       6: invokevirtual #52                 // Method org/springframework/boot/context/properties/ConfigurationPropertiesBean.getAnnotation:()Lorg/springframework/boot/context/properties/ConfigurationProperties;
       9: astore_3
      10: aload_0
      11: aload_2
      12: aload_3
      13: invokevirtual #56                 // Method getBindHandler:(Lorg/springframework/boot/context/properties/bind/Bindable;Lorg/springframework/boot/context/properties/ConfigurationProperties;)Lorg/springframework/boot/context/properties/bind/BindHandler;
      16: astore        4
      18: aload_0
      19: invokevirtual #60                 // Method getBinder:()Lorg/springframework/boot/context/properties/bind/Binder;
      22: aload_3
      23: invokeinterface #64,  1           // InterfaceMethod org/springframework/boot/context/properties/ConfigurationProperties.prefix:()Ljava/lang/String;
      28: aload_2
      29: aload         4
      31: invokevirtual #70                 // Method org/springframework/boot/context/properties/bind/Binder.bind:(Ljava/lang/String;Lorg/springframework/boot/context/properties/bind/Bindable;Lorg/springframework/boot/context/properties/bind/BindHandler;)Lorg/springframework/boot/context/properties/bind/BindResult;
      34: areturn

  java.lang.Object bindOrCreate(org.springframework.boot.context.properties.ConfigurationPropertiesBean);
    Code:
       0: aload_1
       1: invokevirtual #46                 // Method org/springframework/boot/context/properties/ConfigurationPropertiesBean.asBindTarget:()Lorg/springframework/boot/context/properties/bind/Bindable;
       4: astore_2
       5: aload_1
       6: invokevirtual #52                 // Method org/springframework/boot/context/properties/ConfigurationPropertiesBean.getAnnotation:()Lorg/springframework/boot/context/properties/ConfigurationProperties;
       9: astore_3
      10: aload_0
      11: aload_2
      12: aload_3
      13: invokevirtual #56                 // Method getBindHandler:(Lorg/springframework/boot/context/properties/bind/Bindable;Lorg/springframework/boot/context/properties/ConfigurationProperties;)Lorg/springframework/boot/context/properties/bind/BindHandler;
      16: astore        4
      18: aload_0
      19: invokevirtual #60                 // Method getBinder:()Lorg/springframework/boot/context/properties/bind/Binder;
      22: aload_3
      23: invokeinterface #64,  1           // InterfaceMethod org/springframework/boot/context/properties/ConfigurationProperties.prefix:()Ljava/lang/String;
      28: aload_2
      29: aload         4
      31: invokevirtual #76                 // Method org/springframework/boot/context/properties/bind/Binder.bindOrCreate:(Ljava/lang/String;Lorg/springframework/boot/context/properties/bind/Bindable;Lorg/springframework/boot/context/properties/bind/BindHandler;)Ljava/lang/Object;
      34: areturn

  private org.springframework.validation.Validator getConfigurationPropertiesValidator(org.springframework.context.ApplicationContext);
    Code:
       0: aload_1
       1: ldc           #80                 // String configurationPropertiesValidator
       3: invokeinterface #81,  2           // InterfaceMethod org/springframework/context/ApplicationContext.containsBean:(Ljava/lang/String;)Z
       8: ifeq          25
      11: aload_1
      12: ldc           #80                 // String configurationPropertiesValidator
      14: ldc           #87                 // class org/springframework/validation/Validator
      16: invokeinterface #89,  3           // InterfaceMethod org/springframework/context/ApplicationContext.getBean:(Ljava/lang/String;Ljava/lang/Class;)Ljava/lang/Object;
      21: checkcast     #87                 // class org/springframework/validation/Validator
      24: areturn
      25: aconst_null
      26: areturn

  private <T> org.springframework.boot.context.properties.bind.BindHandler getBindHandler(org.springframework.boot.context.properties.bind.Bindable<T>, org.springframework.boot.context.properties.ConfigurationProperties);
    Code:
       0: aload_0
       1: aload_1
       2: invokevirtual #93                 // Method getValidators:(Lorg/springframework/boot/context/properties/bind/Bindable;)Ljava/util/List;
       5: astore_3
       6: aload_0
       7: invokevirtual #97                 // Method getHandler:()Lorg/springframework/boot/context/properties/bind/handler/IgnoreTopLevelConverterNotFoundBindHandler;
      10: astore        4
      12: new           #101                // class org/springframework/boot/context/properties/ConfigurationPropertiesBinder$ConfigurationPropertiesBindHandler
      15: dup
      16: aload         4
      18: invokespecial #103                // Method org/springframework/boot/context/properties/ConfigurationPropertiesBinder$ConfigurationPropertiesBindHandler."<init>":(Lorg/springframework/boot/context/properties/bind/BindHandler;)V
      21: astore        4
      23: aload_2
      24: invokeinterface #106,  1          // InterfaceMethod org/springframework/boot/context/properties/ConfigurationProperties.ignoreInvalidFields:()Z
      29: ifeq          43
      32: new           #110                // class org/springframework/boot/context/properties/bind/handler/IgnoreErrorsBindHandler
      35: dup
      36: aload         4
      38: invokespecial #112                // Method org/springframework/boot/context/properties/bind/handler/IgnoreErrorsBindHandler."<init>":(Lorg/springframework/boot/context/properties/bind/BindHandler;)V
      41: astore        4
      43: aload_2
      44: invokeinterface #113,  1          // InterfaceMethod org/springframework/boot/context/properties/ConfigurationProperties.ignoreUnknownFields:()Z
      49: ifne          74
      52: new           #116                // class org/springframework/boot/context/properties/source/UnboundElementsSourceFilter
      55: dup
      56: invokespecial #118                // Method org/springframework/boot/context/properties/source/UnboundElementsSourceFilter."<init>":()V
      59: astore        5
      61: new           #119                // class org/springframework/boot/context/properties/bind/handler/NoUnboundElementsBindHandler
      64: dup
      65: aload         4
      67: aload         5
      69: invokespecial #121                // Method org/springframework/boot/context/properties/bind/handler/NoUnboundElementsBindHandler."<init>":(Lorg/springframework/boot/context/properties/bind/BindHandler;Ljava/util/function/Function;)V
      72: astore        4
      74: aload_3
      75: invokeinterface #124,  1          // InterfaceMethod java/util/List.isEmpty:()Z
      80: ifne          107
      83: new           #129                // class org/springframework/boot/context/properties/bind/validation/ValidationBindHandler
      86: dup
      87: aload         4
      89: aload_3
      90: iconst_0
      91: anewarray     #87                 // class org/springframework/validation/Validator
      94: invokeinterface #131,  2          // InterfaceMethod java/util/List.toArray:([Ljava/lang/Object;)[Ljava/lang/Object;
      99: checkcast     #135                // class "[Lorg/springframework/validation/Validator;"
     102: invokespecial #137                // Method org/springframework/boot/context/properties/bind/validation/ValidationBindHandler."<init>":(Lorg/springframework/boot/context/properties/bind/BindHandler;[Lorg/springframework/validation/Validator;)V
     105: astore        4
     107: aload_0
     108: invokevirtual #140                // Method getBindHandlerAdvisors:()Ljava/util/List;
     111: invokeinterface #144,  1          // InterfaceMethod java/util/List.iterator:()Ljava/util/Iterator;
     116: astore        5
     118: aload         5
     120: invokeinterface #148,  1          // InterfaceMethod java/util/Iterator.hasNext:()Z
     125: ifeq          154
     128: aload         5
     130: invokeinterface #153,  1          // InterfaceMethod java/util/Iterator.next:()Ljava/lang/Object;
     135: checkcast     #157                // class org/springframework/boot/context/properties/ConfigurationPropertiesBindHandlerAdvisor
     138: astore        6
     140: aload         6
     142: aload         4
     144: invokeinterface #159,  2          // InterfaceMethod org/springframework/boot/context/properties/ConfigurationPropertiesBindHandlerAdvisor.apply:(Lorg/springframework/boot/context/properties/bind/BindHandler;)Lorg/springframework/boot/context/properties/bind/BindHandler;
     149: astore        4
     151: goto          118
     154: aload         4
     156: areturn

  private org.springframework.boot.context.properties.bind.handler.IgnoreTopLevelConverterNotFoundBindHandler getHandler();
    Code:
       0: aload_0
       1: getfield      #9                  // Field applicationContext:Lorg/springframework/context/ApplicationContext;
       4: invokestatic  #163                // Method org/springframework/boot/context/properties/BoundConfigurationProperties.get:(Lorg/springframework/context/ApplicationContext;)Lorg/springframework/boot/context/properties/BoundConfigurationProperties;
       7: astore_1
       8: aload_1
       9: ifnull        40
      12: new           #169                // class org/springframework/boot/context/properties/bind/handler/IgnoreTopLevelConverterNotFoundBindHandler
      15: dup
      16: new           #171                // class org/springframework/boot/context/properties/bind/BoundPropertiesTrackingBindHandler
      19: dup
      20: aload_1
      21: dup
      22: invokestatic  #173                // Method java/util/Objects.requireNonNull:(Ljava/lang/Object;)Ljava/lang/Object;
      25: pop
      26: invokedynamic #179,  0            // InvokeDynamic #0:accept:(Lorg/springframework/boot/context/properties/BoundConfigurationProperties;)Ljava/util/function/Consumer;
      31: invokespecial #183                // Method org/springframework/boot/context/properties/bind/BoundPropertiesTrackingBindHandler."<init>":(Ljava/util/function/Consumer;)V
      34: invokespecial #186                // Method org/springframework/boot/context/properties/bind/handler/IgnoreTopLevelConverterNotFoundBindHandler."<init>":(Lorg/springframework/boot/context/properties/bind/BindHandler;)V
      37: goto          47
      40: new           #169                // class org/springframework/boot/context/properties/bind/handler/IgnoreTopLevelConverterNotFoundBindHandler
      43: dup
      44: invokespecial #187                // Method org/springframework/boot/context/properties/bind/handler/IgnoreTopLevelConverterNotFoundBindHandler."<init>":()V
      47: areturn

  private java.util.List<org.springframework.validation.Validator> getValidators(org.springframework.boot.context.properties.bind.Bindable<?>);
    Code:
       0: new           #188                // class java/util/ArrayList
       3: dup
       4: iconst_3
       5: invokespecial #190                // Method java/util/ArrayList."<init>":(I)V
       8: astore_2
       9: aload_0
      10: getfield      #32                 // Field configurationPropertiesValidator:Lorg/springframework/validation/Validator;
      13: ifnull        27
      16: aload_2
      17: aload_0
      18: getfield      #32                 // Field configurationPropertiesValidator:Lorg/springframework/validation/Validator;
      21: invokeinterface #193,  2          // InterfaceMethod java/util/List.add:(Ljava/lang/Object;)Z
      26: pop
      27: aload_0
      28: getfield      #42                 // Field jsr303Present:Z
      31: ifeq          54
      34: aload_1
      35: ldc           #197                // class org/springframework/validation/annotation/Validated
      37: invokevirtual #199                // Method org/springframework/boot/context/properties/bind/Bindable.getAnnotation:(Ljava/lang/Class;)Ljava/lang/annotation/Annotation;
      40: ifnull        54
      43: aload_2
      44: aload_0
      45: invokevirtual #204                // Method getJsr303Validator:()Lorg/springframework/validation/Validator;
      48: invokeinterface #193,  2          // InterfaceMethod java/util/List.add:(Ljava/lang/Object;)Z
      53: pop
      54: aload_1
      55: invokevirtual #208                // Method org/springframework/boot/context/properties/bind/Bindable.getValue:()Ljava/util/function/Supplier;
      58: ifnull        94
      61: aload_1
      62: invokevirtual #208                // Method org/springframework/boot/context/properties/bind/Bindable.getValue:()Ljava/util/function/Supplier;
      65: invokeinterface #212,  1          // InterfaceMethod java/util/function/Supplier.get:()Ljava/lang/Object;
      70: astore        4
      72: aload         4
      74: instanceof    #87                 // class org/springframework/validation/Validator
      77: ifeq          94
      80: aload         4
      82: checkcast     #87                 // class org/springframework/validation/Validator
      85: astore_3
      86: aload_2
      87: aload_3
      88: invokeinterface #193,  2          // InterfaceMethod java/util/List.add:(Ljava/lang/Object;)Z
      93: pop
      94: aload_2
      95: areturn

  private org.springframework.validation.Validator getJsr303Validator();
    Code:
       0: aload_0
       1: getfield      #216                // Field jsr303Validator:Lorg/springframework/validation/Validator;
       4: ifnonnull     22
       7: aload_0
       8: new           #37                 // class org/springframework/boot/context/properties/ConfigurationPropertiesJsr303Validator
      11: dup
      12: aload_0
      13: getfield      #9                  // Field applicationContext:Lorg/springframework/context/ApplicationContext;
      16: invokespecial #219                // Method org/springframework/boot/context/properties/ConfigurationPropertiesJsr303Validator."<init>":(Lorg/springframework/context/ApplicationContext;)V
      19: putfield      #216                // Field jsr303Validator:Lorg/springframework/validation/Validator;
      22: aload_0
      23: getfield      #216                // Field jsr303Validator:Lorg/springframework/validation/Validator;
      26: areturn

  private java.util.List<org.springframework.boot.context.properties.ConfigurationPropertiesBindHandlerAdvisor> getBindHandlerAdvisors();
    Code:
       0: aload_0
       1: getfield      #9                  // Field applicationContext:Lorg/springframework/context/ApplicationContext;
       4: ldc           #157                // class org/springframework/boot/context/properties/ConfigurationPropertiesBindHandlerAdvisor
       6: invokeinterface #220,  2          // InterfaceMethod org/springframework/context/ApplicationContext.getBeanProvider:(Ljava/lang/Class;)Lorg/springframework/beans/factory/ObjectProvider;
      11: invokeinterface #224,  1          // InterfaceMethod org/springframework/beans/factory/ObjectProvider.orderedStream:()Ljava/util/stream/Stream;
      16: invokeinterface #230,  1          // InterfaceMethod java/util/stream/Stream.toList:()Ljava/util/List;
      21: areturn

  private org.springframework.boot.context.properties.bind.Binder getBinder();
    Code:
       0: aload_0
       1: getfield      #235                // Field binder:Lorg/springframework/boot/context/properties/bind/Binder;
       4: ifnonnull     36
       7: aload_0
       8: new           #71                 // class org/springframework/boot/context/properties/bind/Binder
      11: dup
      12: aload_0
      13: invokevirtual #239                // Method getConfigurationPropertySources:()Ljava/lang/Iterable;
      16: aload_0
      17: invokevirtual #243                // Method getPropertySourcesPlaceholdersResolver:()Lorg/springframework/boot/context/properties/bind/PropertySourcesPlaceholdersResolver;
      20: aload_0
      21: invokevirtual #247                // Method getConversionServices:()Ljava/util/List;
      24: aload_0
      25: invokevirtual #250                // Method getPropertyEditorInitializer:()Ljava/util/function/Consumer;
      28: aconst_null
      29: aconst_null
      30: invokespecial #254                // Method org/springframework/boot/context/properties/bind/Binder."<init>":(Ljava/lang/Iterable;Lorg/springframework/boot/context/properties/bind/PlaceholdersResolver;Ljava/util/List;Ljava/util/function/Consumer;Lorg/springframework/boot/context/properties/bind/BindHandler;Lorg/springframework/boot/context/properties/bind/BindConstructorProvider;)V
      33: putfield      #235                // Field binder:Lorg/springframework/boot/context/properties/bind/Binder;
      36: aload_0
      37: getfield      #235                // Field binder:Lorg/springframework/boot/context/properties/bind/Binder;
      40: areturn

  private java.lang.Iterable<org.springframework.boot.context.properties.source.ConfigurationPropertySource> getConfigurationPropertySources();
    Code:
       0: aload_0
       1: getfield      #24                 // Field propertySources:Lorg/springframework/core/env/PropertySources;
       4: invokestatic  #257                // Method org/springframework/boot/context/properties/source/ConfigurationPropertySources.from:(Ljava/lang/Iterable;)Ljava/lang/Iterable;
       7: areturn

  private org.springframework.boot.context.properties.bind.PropertySourcesPlaceholdersResolver getPropertySourcesPlaceholdersResolver();
    Code:
       0: new           #263                // class org/springframework/boot/context/properties/bind/PropertySourcesPlaceholdersResolver
       3: dup
       4: aload_0
       5: getfield      #24                 // Field propertySources:Lorg/springframework/core/env/PropertySources;
       8: invokespecial #265                // Method org/springframework/boot/context/properties/bind/PropertySourcesPlaceholdersResolver."<init>":(Ljava/lang/Iterable;)V
      11: areturn

  private java.util.List<org.springframework.core.convert.ConversionService> getConversionServices();
    Code:
       0: new           #268                // class org/springframework/boot/context/properties/ConversionServiceDeducer
       3: dup
       4: aload_0
       5: getfield      #9                  // Field applicationContext:Lorg/springframework/context/ApplicationContext;
       8: invokespecial #270                // Method org/springframework/boot/context/properties/ConversionServiceDeducer."<init>":(Lorg/springframework/context/ApplicationContext;)V
      11: invokevirtual #271                // Method org/springframework/boot/context/properties/ConversionServiceDeducer.getConversionServices:()Ljava/util/List;
      14: areturn

  private java.util.function.Consumer<org.springframework.beans.PropertyEditorRegistry> getPropertyEditorInitializer();
    Code:
       0: aload_0
       1: getfield      #9                  // Field applicationContext:Lorg/springframework/context/ApplicationContext;
       4: astore_2
       5: aload_2
       6: instanceof    #272                // class org/springframework/context/ConfigurableApplicationContext
       9: ifeq          34
      12: aload_2
      13: checkcast     #272                // class org/springframework/context/ConfigurableApplicationContext
      16: astore_1
      17: aload_1
      18: invokeinterface #274,  1          // InterfaceMethod org/springframework/context/ConfigurableApplicationContext.getBeanFactory:()Lorg/springframework/beans/factory/config/ConfigurableListableBeanFactory;
      23: dup
      24: invokestatic  #173                // Method java/util/Objects.requireNonNull:(Ljava/lang/Object;)Ljava/lang/Object;
      27: pop
      28: invokedynamic #278,  0            // InvokeDynamic #1:accept:(Lorg/springframework/beans/factory/config/ConfigurableListableBeanFactory;)Ljava/util/function/Consumer;
      33: areturn
      34: aconst_null
      35: areturn

  static void register(org.springframework.beans.factory.support.BeanDefinitionRegistry);
    Code:
       0: aload_0
       1: ldc_w         #281                // String org.springframework.boot.context.internalConfigurationPropertiesBinder
       4: invokeinterface #283,  2          // InterfaceMethod org/springframework/beans/factory/support/BeanDefinitionRegistry.containsBeanDefinition:(Ljava/lang/String;)Z
       9: ifne          39
      12: ldc_w         #288                // class org/springframework/boot/context/properties/ConfigurationPropertiesBinder$ConfigurationPropertiesBinderFactory
      15: invokestatic  #290                // Method org/springframework/beans/factory/support/BeanDefinitionBuilder.rootBeanDefinition:(Ljava/lang/Class;)Lorg/springframework/beans/factory/support/BeanDefinitionBuilder;
      18: invokevirtual #296                // Method org/springframework/beans/factory/support/BeanDefinitionBuilder.getBeanDefinition:()Lorg/springframework/beans/factory/support/AbstractBeanDefinition;
      21: astore_1
      22: aload_1
      23: iconst_2
      24: invokeinterface #302,  2          // InterfaceMethod org/springframework/beans/factory/config/BeanDefinition.setRole:(I)V
      29: aload_0
      30: ldc_w         #281                // String org.springframework.boot.context.internalConfigurationPropertiesBinder
      33: aload_1
      34: invokeinterface #305,  3          // InterfaceMethod org/springframework/beans/factory/support/BeanDefinitionRegistry.registerBeanDefinition:(Ljava/lang/String;Lorg/springframework/beans/factory/config/BeanDefinition;)V
      39: return

  static org.springframework.boot.context.properties.ConfigurationPropertiesBinder get(org.springframework.beans.factory.BeanFactory);
    Code:
       0: aload_0
       1: ldc_w         #281                // String org.springframework.boot.context.internalConfigurationPropertiesBinder
       4: ldc           #10                 // class org/springframework/boot/context/properties/ConfigurationPropertiesBinder
       6: invokeinterface #309,  3          // InterfaceMethod org/springframework/beans/factory/BeanFactory.getBean:(Ljava/lang/String;Ljava/lang/Class;)Ljava/lang/Object;
      11: checkcast     #10                 // class org/springframework/boot/context/properties/ConfigurationPropertiesBinder
      14: areturn
}
