Compiled from "ConfigurationPropertiesBean.java"
public final class org.springframework.boot.context.properties.ConfigurationPropertiesBean$BindMethod extends java.lang.Enum<org.springframework.boot.context.properties.ConfigurationPropertiesBean$BindMethod> {
  public static final org.springframework.boot.context.properties.ConfigurationPropertiesBean$BindMethod JAVA_BEAN;

  public static final org.springframework.boot.context.properties.ConfigurationPropertiesBean$BindMethod VALUE_OBJECT;

  private static final org.springframework.boot.context.properties.ConfigurationPropertiesBean$BindMethod[] $VALUES;

  public static org.springframework.boot.context.properties.ConfigurationPropertiesBean$BindMethod[] values();
    Code:
       0: getstatic     #10                 // Field $VALUES:[Lorg/springframework/boot/context/properties/ConfigurationPropertiesBean$BindMethod;
       3: invokevirtual #14                 // Method "[Lorg/springframework/boot/context/properties/ConfigurationPropertiesBean$BindMethod;".clone:()Ljava/lang/Object;
       6: checkcast     #15                 // class "[Lorg/springframework/boot/context/properties/ConfigurationPropertiesBean$BindMethod;"
       9: areturn

  public static org.springframework.boot.context.properties.ConfigurationPropertiesBean$BindMethod valueOf(java.lang.String);
    Code:
       0: ldc           #1                  // class org/springframework/boot/context/properties/ConfigurationPropertiesBean$BindMethod
       2: aload_0
       3: invokestatic  #19                 // Method java/lang/Enum.valueOf:(Ljava/lang/Class;Ljava/lang/String;)Ljava/lang/Enum;
       6: checkcast     #1                  // class org/springframework/boot/context/properties/ConfigurationPropertiesBean$BindMethod
       9: areturn

  private org.springframework.boot.context.properties.ConfigurationPropertiesBean$BindMethod();
    Code:
       0: aload_0
       1: aload_1
       2: iload_2
       3: invokespecial #25                 // Method java/lang/Enum."<init>":(Ljava/lang/String;I)V
       6: return

  static org.springframework.boot.context.properties.ConfigurationPropertiesBean$BindMethod get(java.lang.Class<?>);
    Code:
       0: getstatic     #29                 // Field org/springframework/boot/context/properties/bind/BindConstructorProvider.DEFAULT:Lorg/springframework/boot/context/properties/bind/BindConstructorProvider;
       3: aload_0
       4: iconst_0
       5: invokeinterface #35,  3           // InterfaceMethod org/springframework/boot/context/properties/bind/BindConstructorProvider.getBindConstructor:(Ljava/lang/Class;Z)Ljava/lang/reflect/Constructor;
      10: invokestatic  #39                 // Method get:(Ljava/lang/reflect/Constructor;)Lorg/springframework/boot/context/properties/ConfigurationPropertiesBean$BindMethod;
      13: areturn

  static org.springframework.boot.context.properties.ConfigurationPropertiesBean$BindMethod get(org.springframework.boot.context.properties.bind.Bindable<?>);
    Code:
       0: getstatic     #29                 // Field org/springframework/boot/context/properties/bind/BindConstructorProvider.DEFAULT:Lorg/springframework/boot/context/properties/bind/BindConstructorProvider;
       3: aload_0
       4: iconst_0
       5: invokeinterface #43,  3           // InterfaceMethod org/springframework/boot/context/properties/bind/BindConstructorProvider.getBindConstructor:(Lorg/springframework/boot/context/properties/bind/Bindable;Z)Ljava/lang/reflect/Constructor;
      10: invokestatic  #39                 // Method get:(Ljava/lang/reflect/Constructor;)Lorg/springframework/boot/context/properties/ConfigurationPropertiesBean$BindMethod;
      13: areturn

  private static org.springframework.boot.context.properties.ConfigurationPropertiesBean$BindMethod get(java.lang.reflect.Constructor<?>);
    Code:
       0: aload_0
       1: ifnull        10
       4: getstatic     #7                  // Field VALUE_OBJECT:Lorg/springframework/boot/context/properties/ConfigurationPropertiesBean$BindMethod;
       7: goto          13
      10: getstatic     #3                  // Field JAVA_BEAN:Lorg/springframework/boot/context/properties/ConfigurationPropertiesBean$BindMethod;
      13: areturn

  private static org.springframework.boot.context.properties.ConfigurationPropertiesBean$BindMethod[] $values();
    Code:
       0: iconst_2
       1: anewarray     #1                  // class org/springframework/boot/context/properties/ConfigurationPropertiesBean$BindMethod
       4: dup
       5: iconst_0
       6: getstatic     #3                  // Field JAVA_BEAN:Lorg/springframework/boot/context/properties/ConfigurationPropertiesBean$BindMethod;
       9: aastore
      10: dup
      11: iconst_1
      12: getstatic     #7                  // Field VALUE_OBJECT:Lorg/springframework/boot/context/properties/ConfigurationPropertiesBean$BindMethod;
      15: aastore
      16: areturn

  static {};
    Code:
       0: new           #1                  // class org/springframework/boot/context/properties/ConfigurationPropertiesBean$BindMethod
       3: dup
       4: ldc           #46                 // String JAVA_BEAN
       6: iconst_0
       7: invokespecial #47                 // Method "<init>":(Ljava/lang/String;I)V
      10: putstatic     #3                  // Field JAVA_BEAN:Lorg/springframework/boot/context/properties/ConfigurationPropertiesBean$BindMethod;
      13: new           #1                  // class org/springframework/boot/context/properties/ConfigurationPropertiesBean$BindMethod
      16: dup
      17: ldc           #48                 // String VALUE_OBJECT
      19: iconst_1
      20: invokespecial #47                 // Method "<init>":(Ljava/lang/String;I)V
      23: putstatic     #7                  // Field VALUE_OBJECT:Lorg/springframework/boot/context/properties/ConfigurationPropertiesBean$BindMethod;
      26: invokestatic  #49                 // Method $values:()[Lorg/springframework/boot/context/properties/ConfigurationPropertiesBean$BindMethod;
      29: putstatic     #10                 // Field $VALUES:[Lorg/springframework/boot/context/properties/ConfigurationPropertiesBean$BindMethod;
      32: return
}
