Compiled from "ConfigurationPropertiesBinder.java"
class org.springframework.boot.context.properties.ConfigurationPropertiesBinder$ConfigurationPropertiesBindHandler extends org.springframework.boot.context.properties.bind.AbstractBindHandler {
  org.springframework.boot.context.properties.ConfigurationPropertiesBinder$ConfigurationPropertiesBindHandler(org.springframework.boot.context.properties.bind.BindHandler);
    Code:
       0: aload_0
       1: aload_1
       2: invokespecial #1                  // Method org/springframework/boot/context/properties/bind/AbstractBindHandler."<init>":(Lorg/springframework/boot/context/properties/bind/BindHandler;)V
       5: return

  public <T> org.springframework.boot.context.properties.bind.Bindable<T> onStart(org.springframework.boot.context.properties.source.ConfigurationPropertyName, org.springframework.boot.context.properties.bind.Bindable<T>, org.springframework.boot.context.properties.bind.BindContext);
    Code:
       0: aload_0
       1: aload_2
       2: invokevirtual #7                  // Method org/springframework/boot/context/properties/bind/Bindable.getType:()Lorg/springframework/core/ResolvableType;
       5: invokevirtual #13                 // Method org/springframework/core/ResolvableType.resolve:()Ljava/lang/Class;
       8: invokevirtual #19                 // Method isConfigurationProperties:(Ljava/lang/Class;)Z
      11: ifeq          31
      14: aload_2
      15: iconst_1
      16: anewarray     #25                 // class org/springframework/boot/context/properties/bind/Bindable$BindRestriction
      19: dup
      20: iconst_0
      21: getstatic     #27                 // Field org/springframework/boot/context/properties/bind/Bindable$BindRestriction.NO_DIRECT_PROPERTY:Lorg/springframework/boot/context/properties/bind/Bindable$BindRestriction;
      24: aastore
      25: invokevirtual #31                 // Method org/springframework/boot/context/properties/bind/Bindable.withBindRestrictions:([Lorg/springframework/boot/context/properties/bind/Bindable$BindRestriction;)Lorg/springframework/boot/context/properties/bind/Bindable;
      28: goto          32
      31: aload_2
      32: areturn

  private boolean isConfigurationProperties(java.lang.Class<?>);
    Code:
       0: aload_1
       1: ifnull        22
       4: aload_1
       5: invokestatic  #35                 // InterfaceMethod org/springframework/core/annotation/MergedAnnotations.from:(Ljava/lang/reflect/AnnotatedElement;)Lorg/springframework/core/annotation/MergedAnnotations;
       8: ldc           #41                 // class org/springframework/boot/context/properties/ConfigurationProperties
      10: invokeinterface #43,  2           // InterfaceMethod org/springframework/core/annotation/MergedAnnotations.isPresent:(Ljava/lang/Class;)Z
      15: ifeq          22
      18: iconst_1
      19: goto          23
      22: iconst_0
      23: ireturn
}
