Compiled from "ConfigurationPropertiesBean.java"
public final class org.springframework.boot.context.properties.ConfigurationPropertiesBean {
  private final java.lang.String name;

  private final java.lang.Object instance;

  private final org.springframework.boot.context.properties.ConfigurationProperties annotation;

  private final org.springframework.boot.context.properties.bind.Bindable<?> bindTarget;

  private final org.springframework.boot.context.properties.ConfigurationPropertiesBean$BindMethod bindMethod;

  private org.springframework.boot.context.properties.ConfigurationPropertiesBean(java.lang.String, java.lang.Object, org.springframework.boot.context.properties.ConfigurationProperties, org.springframework.boot.context.properties.bind.Bindable<?>, org.springframework.boot.context.properties.ConfigurationPropertiesBean$BindMethod);
    Code:
       0: aload_0
       1: invokespecial #1                  // Method java/lang/Object."<init>":()V
       4: aload_0
       5: aload_1
       6: putfield      #7                  // Field name:Ljava/lang/String;
       9: aload_0
      10: aload_2
      11: putfield      #13                 // Field instance:Ljava/lang/Object;
      14: aload_0
      15: aload_3
      16: putfield      #17                 // Field annotation:Lorg/springframework/boot/context/properties/ConfigurationProperties;
      19: aload_0
      20: aload         4
      22: putfield      #21                 // Field bindTarget:Lorg/springframework/boot/context/properties/bind/Bindable;
      25: aload_0
      26: aload         5
      28: ifnull        36
      31: aload         5
      33: goto          41
      36: aload         4
      38: invokestatic  #25                 // Method org/springframework/boot/context/properties/ConfigurationPropertiesBean$BindMethod.get:(Lorg/springframework/boot/context/properties/bind/Bindable;)Lorg/springframework/boot/context/properties/ConfigurationPropertiesBean$BindMethod;
      41: putfield      #31                 // Field bindMethod:Lorg/springframework/boot/context/properties/ConfigurationPropertiesBean$BindMethod;
      44: return

  public java.lang.String getName();
    Code:
       0: aload_0
       1: getfield      #7                  // Field name:Ljava/lang/String;
       4: areturn

  public java.lang.Object getInstance();
    Code:
       0: aload_0
       1: getfield      #13                 // Field instance:Ljava/lang/Object;
       4: areturn

  java.lang.Class<?> getType();
    Code:
       0: aload_0
       1: getfield      #21                 // Field bindTarget:Lorg/springframework/boot/context/properties/bind/Bindable;
       4: invokevirtual #35                 // Method org/springframework/boot/context/properties/bind/Bindable.getType:()Lorg/springframework/core/ResolvableType;
       7: invokevirtual #41                 // Method org/springframework/core/ResolvableType.resolve:()Ljava/lang/Class;
      10: areturn

  public org.springframework.boot.context.properties.ConfigurationPropertiesBean$BindMethod getBindMethod();
    Code:
       0: aload_0
       1: getfield      #31                 // Field bindMethod:Lorg/springframework/boot/context/properties/ConfigurationPropertiesBean$BindMethod;
       4: areturn

  public org.springframework.boot.context.properties.ConfigurationProperties getAnnotation();
    Code:
       0: aload_0
       1: getfield      #17                 // Field annotation:Lorg/springframework/boot/context/properties/ConfigurationProperties;
       4: areturn

  public org.springframework.boot.context.properties.bind.Bindable<?> asBindTarget();
    Code:
       0: aload_0
       1: getfield      #21                 // Field bindTarget:Lorg/springframework/boot/context/properties/bind/Bindable;
       4: areturn

  public static java.util.Map<java.lang.String, org.springframework.boot.context.properties.ConfigurationPropertiesBean> getAll(org.springframework.context.ApplicationContext);
    Code:
       0: aload_0
       1: ldc           #47                 // String ApplicationContext must not be null
       3: invokestatic  #49                 // Method org/springframework/util/Assert.notNull:(Ljava/lang/Object;Ljava/lang/String;)V
       6: aload_0
       7: instanceof    #55                 // class org/springframework/context/ConfigurableApplicationContext
      10: ifeq          23
      13: aload_0
      14: checkcast     #55                 // class org/springframework/context/ConfigurableApplicationContext
      17: astore_1
      18: aload_1
      19: invokestatic  #57                 // Method getAll:(Lorg/springframework/context/ConfigurableApplicationContext;)Ljava/util/Map;
      22: areturn
      23: new           #61                 // class java/util/LinkedHashMap
      26: dup
      27: invokespecial #63                 // Method java/util/LinkedHashMap."<init>":()V
      30: astore_1
      31: aload_0
      32: ldc           #64                 // class org/springframework/boot/context/properties/ConfigurationProperties
      34: invokeinterface #66,  2           // InterfaceMethod org/springframework/context/ApplicationContext.getBeansWithAnnotation:(Ljava/lang/Class;)Ljava/util/Map;
      39: aload_0
      40: aload_1
      41: invokedynamic #72,  0             // InvokeDynamic #0:accept:(Lorg/springframework/context/ApplicationContext;Ljava/util/Map;)Ljava/util/function/BiConsumer;
      46: invokeinterface #76,  2           // InterfaceMethod java/util/Map.forEach:(Ljava/util/function/BiConsumer;)V
      51: aload_1
      52: areturn

  private static java.util.Map<java.lang.String, org.springframework.boot.context.properties.ConfigurationPropertiesBean> getAll(org.springframework.context.ConfigurableApplicationContext);
    Code:
       0: new           #61                 // class java/util/LinkedHashMap
       3: dup
       4: invokespecial #63                 // Method java/util/LinkedHashMap."<init>":()V
       7: astore_1
       8: aload_0
       9: invokeinterface #82,  1           // InterfaceMethod org/springframework/context/ConfigurableApplicationContext.getBeanFactory:()Lorg/springframework/beans/factory/config/ConfigurableListableBeanFactory;
      14: astore_2
      15: aload_2
      16: invokeinterface #86,  1           // InterfaceMethod org/springframework/beans/factory/config/ConfigurableListableBeanFactory.getBeanNamesIterator:()Ljava/util/Iterator;
      21: astore_3
      22: aload_3
      23: invokeinterface #92,  1           // InterfaceMethod java/util/Iterator.hasNext:()Z
      28: ifeq          105
      31: aload_3
      32: invokeinterface #98,  1           // InterfaceMethod java/util/Iterator.next:()Ljava/lang/Object;
      37: checkcast     #102                // class java/lang/String
      40: astore        4
      42: aload_2
      43: aload         4
      45: invokestatic  #104                // Method isConfigurationPropertiesBean:(Lorg/springframework/beans/factory/config/ConfigurableListableBeanFactory;Ljava/lang/String;)Z
      48: ifeq          102
      51: aload_2
      52: aload         4
      54: invokeinterface #108,  2          // InterfaceMethod org/springframework/beans/factory/config/ConfigurableListableBeanFactory.getBean:(Ljava/lang/String;)Ljava/lang/Object;
      59: astore        5
      61: aload_2
      62: aload         4
      64: invokestatic  #112                // Method getBindMethod:(Lorg/springframework/beans/factory/config/ConfigurableListableBeanFactory;Ljava/lang/String;)Lorg/springframework/boot/context/properties/ConfigurationPropertiesBean$BindMethod;
      67: astore        6
      69: aload_0
      70: aload         5
      72: aload         4
      74: aload         6
      76: invokestatic  #116                // Method get:(Lorg/springframework/context/ApplicationContext;Ljava/lang/Object;Ljava/lang/String;Lorg/springframework/boot/context/properties/ConfigurationPropertiesBean$BindMethod;)Lorg/springframework/boot/context/properties/ConfigurationPropertiesBean;
      79: astore        7
      81: aload         7
      83: ifnull        97
      86: aload_1
      87: aload         4
      89: aload         7
      91: invokeinterface #119,  3          // InterfaceMethod java/util/Map.put:(Ljava/lang/Object;Ljava/lang/Object;)Ljava/lang/Object;
      96: pop
      97: goto          102
     100: astore        5
     102: goto          22
     105: aload_1
     106: areturn
    Exception table:
       from    to  target type
          51    97   100   Class java/lang/Exception

  private static org.springframework.boot.context.properties.ConfigurationPropertiesBean$BindMethod getBindMethod(org.springframework.beans.factory.config.ConfigurableListableBeanFactory, java.lang.String);
    Code:
       0: aload_0
       1: aload_1
       2: invokeinterface #125,  2          // InterfaceMethod org/springframework/beans/factory/config/ConfigurableListableBeanFactory.getBeanDefinition:(Ljava/lang/String;)Lorg/springframework/beans/factory/config/BeanDefinition;
       7: astore_2
       8: aload_2
       9: ldc           #26                 // class org/springframework/boot/context/properties/ConfigurationPropertiesBean$BindMethod
      11: invokevirtual #129                // Method java/lang/Class.getName:()Ljava/lang/String;
      14: invokeinterface #135,  2          // InterfaceMethod org/springframework/beans/factory/config/BeanDefinition.getAttribute:(Ljava/lang/String;)Ljava/lang/Object;
      19: checkcast     #26                 // class org/springframework/boot/context/properties/ConfigurationPropertiesBean$BindMethod
      22: areturn
      23: astore_2
      24: aconst_null
      25: areturn
    Exception table:
       from    to  target type
           0    22    23   Class org/springframework/beans/factory/NoSuchBeanDefinitionException

  private static boolean isConfigurationPropertiesBean(org.springframework.beans.factory.config.ConfigurableListableBeanFactory, java.lang.String);
    Code:
       0: aload_0
       1: aload_1
       2: invokeinterface #125,  2          // InterfaceMethod org/springframework/beans/factory/config/ConfigurableListableBeanFactory.getBeanDefinition:(Ljava/lang/String;)Lorg/springframework/beans/factory/config/BeanDefinition;
       7: invokeinterface #142,  1          // InterfaceMethod org/springframework/beans/factory/config/BeanDefinition.isAbstract:()Z
      12: ifeq          17
      15: iconst_0
      16: ireturn
      17: aload_0
      18: aload_1
      19: ldc           #64                 // class org/springframework/boot/context/properties/ConfigurationProperties
      21: invokeinterface #145,  3          // InterfaceMethod org/springframework/beans/factory/config/ConfigurableListableBeanFactory.findAnnotationOnBean:(Ljava/lang/String;Ljava/lang/Class;)Ljava/lang/annotation/Annotation;
      26: ifnull        31
      29: iconst_1
      30: ireturn
      31: aload_0
      32: aload_1
      33: invokestatic  #149                // Method findFactoryMethod:(Lorg/springframework/beans/factory/config/ConfigurableListableBeanFactory;Ljava/lang/String;)Ljava/lang/reflect/Method;
      36: astore_2
      37: aload_2
      38: ldc           #64                 // class org/springframework/boot/context/properties/ConfigurationProperties
      40: invokestatic  #153                // Method findMergedAnnotation:(Ljava/lang/reflect/AnnotatedElement;Ljava/lang/Class;)Lorg/springframework/core/annotation/MergedAnnotation;
      43: invokeinterface #157,  1          // InterfaceMethod org/springframework/core/annotation/MergedAnnotation.isPresent:()Z
      48: ireturn
      49: astore_2
      50: iconst_0
      51: ireturn
    Exception table:
       from    to  target type
           0    16    49   Class org/springframework/beans/factory/NoSuchBeanDefinitionException
          17    30    49   Class org/springframework/beans/factory/NoSuchBeanDefinitionException
          31    48    49   Class org/springframework/beans/factory/NoSuchBeanDefinitionException

  public static org.springframework.boot.context.properties.ConfigurationPropertiesBean get(org.springframework.context.ApplicationContext, java.lang.Object, java.lang.String);
    Code:
       0: aload_0
       1: aload_1
       2: aload_2
       3: aconst_null
       4: invokestatic  #116                // Method get:(Lorg/springframework/context/ApplicationContext;Ljava/lang/Object;Ljava/lang/String;Lorg/springframework/boot/context/properties/ConfigurationPropertiesBean$BindMethod;)Lorg/springframework/boot/context/properties/ConfigurationPropertiesBean;
       7: areturn

  private static org.springframework.boot.context.properties.ConfigurationPropertiesBean get(org.springframework.context.ApplicationContext, java.lang.Object, java.lang.String, org.springframework.boot.context.properties.ConfigurationPropertiesBean$BindMethod);
    Code:
       0: aload_0
       1: aload_2
       2: invokestatic  #162                // Method findFactoryMethod:(Lorg/springframework/context/ApplicationContext;Ljava/lang/String;)Ljava/lang/reflect/Method;
       5: astore        4
       7: aload_2
       8: aload_1
       9: aload_1
      10: invokevirtual #165                // Method java/lang/Object.getClass:()Ljava/lang/Class;
      13: aload         4
      15: aload_3
      16: invokestatic  #168                // Method create:(Ljava/lang/String;Ljava/lang/Object;Ljava/lang/Class;Ljava/lang/reflect/Method;Lorg/springframework/boot/context/properties/ConfigurationPropertiesBean$BindMethod;)Lorg/springframework/boot/context/properties/ConfigurationPropertiesBean;
      19: areturn

  private static java.lang.reflect.Method findFactoryMethod(org.springframework.context.ApplicationContext, java.lang.String);
    Code:
       0: aload_0
       1: instanceof    #55                 // class org/springframework/context/ConfigurableApplicationContext
       4: ifeq          18
       7: aload_0
       8: checkcast     #55                 // class org/springframework/context/ConfigurableApplicationContext
      11: astore_2
      12: aload_2
      13: aload_1
      14: invokestatic  #172                // Method findFactoryMethod:(Lorg/springframework/context/ConfigurableApplicationContext;Ljava/lang/String;)Ljava/lang/reflect/Method;
      17: areturn
      18: aconst_null
      19: areturn

  private static java.lang.reflect.Method findFactoryMethod(org.springframework.context.ConfigurableApplicationContext, java.lang.String);
    Code:
       0: aload_0
       1: invokeinterface #82,  1           // InterfaceMethod org/springframework/context/ConfigurableApplicationContext.getBeanFactory:()Lorg/springframework/beans/factory/config/ConfigurableListableBeanFactory;
       6: aload_1
       7: invokestatic  #149                // Method findFactoryMethod:(Lorg/springframework/beans/factory/config/ConfigurableListableBeanFactory;Ljava/lang/String;)Ljava/lang/reflect/Method;
      10: areturn

  private static java.lang.reflect.Method findFactoryMethod(org.springframework.beans.factory.config.ConfigurableListableBeanFactory, java.lang.String);
    Code:
       0: aload_0
       1: aload_1
       2: invokeinterface #175,  2          // InterfaceMethod org/springframework/beans/factory/config/ConfigurableListableBeanFactory.containsBeanDefinition:(Ljava/lang/String;)Z
       7: ifeq          50
      10: aload_0
      11: aload_1
      12: invokeinterface #179,  2          // InterfaceMethod org/springframework/beans/factory/config/ConfigurableListableBeanFactory.getMergedBeanDefinition:(Ljava/lang/String;)Lorg/springframework/beans/factory/config/BeanDefinition;
      17: astore_2
      18: aload_2
      19: instanceof    #182                // class org/springframework/beans/factory/support/RootBeanDefinition
      22: ifeq          44
      25: aload_2
      26: checkcast     #182                // class org/springframework/beans/factory/support/RootBeanDefinition
      29: astore_3
      30: aload_3
      31: invokevirtual #184                // Method org/springframework/beans/factory/support/RootBeanDefinition.getResolvedFactoryMethod:()Ljava/lang/reflect/Method;
      34: astore        4
      36: aload         4
      38: ifnull        44
      41: aload         4
      43: areturn
      44: aload_0
      45: aload_2
      46: invokestatic  #188                // Method findFactoryMethodUsingReflection:(Lorg/springframework/beans/factory/config/ConfigurableListableBeanFactory;Lorg/springframework/beans/factory/config/BeanDefinition;)Ljava/lang/reflect/Method;
      49: areturn
      50: aconst_null
      51: areturn

  private static java.lang.reflect.Method findFactoryMethodUsingReflection(org.springframework.beans.factory.config.ConfigurableListableBeanFactory, org.springframework.beans.factory.config.BeanDefinition);
    Code:
       0: aload_1
       1: invokeinterface #192,  1          // InterfaceMethod org/springframework/beans/factory/config/BeanDefinition.getFactoryMethodName:()Ljava/lang/String;
       6: astore_2
       7: aload_1
       8: invokeinterface #195,  1          // InterfaceMethod org/springframework/beans/factory/config/BeanDefinition.getFactoryBeanName:()Ljava/lang/String;
      13: astore_3
      14: aload_2
      15: ifnull        22
      18: aload_3
      19: ifnonnull     24
      22: aconst_null
      23: areturn
      24: aload_0
      25: aload_3
      26: invokeinterface #198,  2          // InterfaceMethod org/springframework/beans/factory/config/ConfigurableListableBeanFactory.getType:(Ljava/lang/String;)Ljava/lang/Class;
      31: astore        4
      33: aload         4
      35: invokevirtual #129                // Method java/lang/Class.getName:()Ljava/lang/String;
      38: ldc           #203                // String $$
      40: invokevirtual #205                // Method java/lang/String.contains:(Ljava/lang/CharSequence;)Z
      43: ifeq          53
      46: aload         4
      48: invokevirtual #209                // Method java/lang/Class.getSuperclass:()Ljava/lang/Class;
      51: astore        4
      53: new           #212                // class java/util/concurrent/atomic/AtomicReference
      56: dup
      57: invokespecial #214                // Method java/util/concurrent/atomic/AtomicReference."<init>":()V
      60: astore        5
      62: aload         4
      64: aload_2
      65: aload         5
      67: invokedynamic #215,  0            // InvokeDynamic #1:doWith:(Ljava/lang/String;Ljava/util/concurrent/atomic/AtomicReference;)Lorg/springframework/util/ReflectionUtils$MethodCallback;
      72: invokestatic  #219                // Method org/springframework/util/ReflectionUtils.doWithMethods:(Ljava/lang/Class;Lorg/springframework/util/ReflectionUtils$MethodCallback;)V
      75: aload         5
      77: invokevirtual #225                // Method java/util/concurrent/atomic/AtomicReference.get:()Ljava/lang/Object;
      80: checkcast     #227                // class java/lang/reflect/Method
      83: areturn

  static org.springframework.boot.context.properties.ConfigurationPropertiesBean forValueObject(java.lang.Class<?>, java.lang.String);
    Code:
       0: aload_1
       1: aconst_null
       2: aload_0
       3: aconst_null
       4: aconst_null
       5: invokestatic  #168                // Method create:(Ljava/lang/String;Ljava/lang/Object;Ljava/lang/Class;Ljava/lang/reflect/Method;Lorg/springframework/boot/context/properties/ConfigurationPropertiesBean$BindMethod;)Lorg/springframework/boot/context/properties/ConfigurationPropertiesBean;
       8: astore_2
       9: aload_2
      10: ifnull        27
      13: aload_2
      14: invokevirtual #229                // Method getBindMethod:()Lorg/springframework/boot/context/properties/ConfigurationPropertiesBean$BindMethod;
      17: getstatic     #232                // Field org/springframework/boot/context/properties/ConfigurationPropertiesBean$BindMethod.VALUE_OBJECT:Lorg/springframework/boot/context/properties/ConfigurationPropertiesBean$BindMethod;
      20: if_acmpne     27
      23: iconst_1
      24: goto          28
      27: iconst_0
      28: aload_1
      29: invokedynamic #235,  0            // InvokeDynamic #2:get:(Ljava/lang/String;)Ljava/util/function/Supplier;
      34: invokestatic  #238                // Method org/springframework/util/Assert.state:(ZLjava/util/function/Supplier;)V
      37: aload_2
      38: areturn

  private static org.springframework.boot.context.properties.ConfigurationPropertiesBean create(java.lang.String, java.lang.Object, java.lang.Class<?>, java.lang.reflect.Method, org.springframework.boot.context.properties.ConfigurationPropertiesBean$BindMethod);
    Code:
       0: aload_1
       1: aload_2
       2: aload_3
       3: ldc           #64                 // class org/springframework/boot/context/properties/ConfigurationProperties
       5: invokestatic  #242                // Method findAnnotation:(Ljava/lang/Object;Ljava/lang/Class;Ljava/lang/reflect/Method;Ljava/lang/Class;)Ljava/lang/annotation/Annotation;
       8: checkcast     #64                 // class org/springframework/boot/context/properties/ConfigurationProperties
      11: astore        5
      13: aload         5
      15: ifnonnull     20
      18: aconst_null
      19: areturn
      20: aload_1
      21: aload_2
      22: aload_3
      23: ldc           #246                // class org/springframework/validation/annotation/Validated
      25: invokestatic  #242                // Method findAnnotation:(Ljava/lang/Object;Ljava/lang/Class;Ljava/lang/reflect/Method;Ljava/lang/Class;)Ljava/lang/annotation/Annotation;
      28: checkcast     #246                // class org/springframework/validation/annotation/Validated
      31: astore        6
      33: aload         6
      35: ifnull        55
      38: iconst_2
      39: anewarray     #248                // class java/lang/annotation/Annotation
      42: dup
      43: iconst_0
      44: aload         5
      46: aastore
      47: dup
      48: iconst_1
      49: aload         6
      51: aastore
      52: goto          64
      55: iconst_1
      56: anewarray     #248                // class java/lang/annotation/Annotation
      59: dup
      60: iconst_0
      61: aload         5
      63: aastore
      64: astore        7
      66: aload_3
      67: ifnull        77
      70: aload_3
      71: invokestatic  #250                // Method org/springframework/core/ResolvableType.forMethodReturnType:(Ljava/lang/reflect/Method;)Lorg/springframework/core/ResolvableType;
      74: goto          81
      77: aload_2
      78: invokestatic  #254                // Method org/springframework/core/ResolvableType.forClass:(Ljava/lang/Class;)Lorg/springframework/core/ResolvableType;
      81: astore        8
      83: aload         8
      85: invokestatic  #258                // Method org/springframework/boot/context/properties/bind/Bindable.of:(Lorg/springframework/core/ResolvableType;)Lorg/springframework/boot/context/properties/bind/Bindable;
      88: aload         7
      90: invokevirtual #262                // Method org/springframework/boot/context/properties/bind/Bindable.withAnnotations:([Ljava/lang/annotation/Annotation;)Lorg/springframework/boot/context/properties/bind/Bindable;
      93: astore        9
      95: aload_3
      96: ifnull        105
      99: getstatic     #266                // Field org/springframework/boot/context/properties/ConfigurationPropertiesBean$BindMethod.JAVA_BEAN:Lorg/springframework/boot/context/properties/ConfigurationPropertiesBean$BindMethod;
     102: goto          107
     105: aload         4
     107: astore        4
     109: aload_1
     110: ifnull        129
     113: aload         4
     115: getstatic     #232                // Field org/springframework/boot/context/properties/ConfigurationPropertiesBean$BindMethod.VALUE_OBJECT:Lorg/springframework/boot/context/properties/ConfigurationPropertiesBean$BindMethod;
     118: if_acmpeq     129
     121: aload         9
     123: aload_1
     124: invokevirtual #269                // Method org/springframework/boot/context/properties/bind/Bindable.withExistingValue:(Ljava/lang/Object;)Lorg/springframework/boot/context/properties/bind/Bindable;
     127: astore        9
     129: new           #8                  // class org/springframework/boot/context/properties/ConfigurationPropertiesBean
     132: dup
     133: aload_0
     134: aload_1
     135: aload         5
     137: aload         9
     139: aload         4
     141: invokespecial #273                // Method "<init>":(Ljava/lang/String;Ljava/lang/Object;Lorg/springframework/boot/context/properties/ConfigurationProperties;Lorg/springframework/boot/context/properties/bind/Bindable;Lorg/springframework/boot/context/properties/ConfigurationPropertiesBean$BindMethod;)V
     144: areturn

  private static <A extends java.lang.annotation.Annotation> A findAnnotation(java.lang.Object, java.lang.Class<?>, java.lang.reflect.Method, java.lang.Class<A>);
    Code:
       0: invokestatic  #276                // InterfaceMethod org/springframework/core/annotation/MergedAnnotation.missing:()Lorg/springframework/core/annotation/MergedAnnotation;
       3: astore        4
       5: aload_2
       6: ifnull        16
       9: aload_2
      10: aload_3
      11: invokestatic  #153                // Method findMergedAnnotation:(Ljava/lang/reflect/AnnotatedElement;Ljava/lang/Class;)Lorg/springframework/core/annotation/MergedAnnotation;
      14: astore        4
      16: aload         4
      18: invokeinterface #157,  1          // InterfaceMethod org/springframework/core/annotation/MergedAnnotation.isPresent:()Z
      23: ifne          33
      26: aload_1
      27: aload_3
      28: invokestatic  #153                // Method findMergedAnnotation:(Ljava/lang/reflect/AnnotatedElement;Ljava/lang/Class;)Lorg/springframework/core/annotation/MergedAnnotation;
      31: astore        4
      33: aload         4
      35: invokeinterface #157,  1          // InterfaceMethod org/springframework/core/annotation/MergedAnnotation.isPresent:()Z
      40: ifne          68
      43: aload_0
      44: invokestatic  #280                // Method org/springframework/aop/support/AopUtils.isAopProxy:(Ljava/lang/Object;)Z
      47: ifeq          68
      50: aload_0
      51: invokestatic  #286                // Method org/springframework/aop/support/AopUtils.getTargetClass:(Ljava/lang/Object;)Ljava/lang/Class;
      54: getstatic     #290                // Field org/springframework/core/annotation/MergedAnnotations$SearchStrategy.TYPE_HIERARCHY:Lorg/springframework/core/annotation/MergedAnnotations$SearchStrategy;
      57: invokestatic  #296                // InterfaceMethod org/springframework/core/annotation/MergedAnnotations.from:(Ljava/lang/reflect/AnnotatedElement;Lorg/springframework/core/annotation/MergedAnnotations$SearchStrategy;)Lorg/springframework/core/annotation/MergedAnnotations;
      60: aload_3
      61: invokeinterface #302,  2          // InterfaceMethod org/springframework/core/annotation/MergedAnnotations.get:(Ljava/lang/Class;)Lorg/springframework/core/annotation/MergedAnnotation;
      66: astore        4
      68: aload         4
      70: invokeinterface #157,  1          // InterfaceMethod org/springframework/core/annotation/MergedAnnotation.isPresent:()Z
      75: ifeq          88
      78: aload         4
      80: invokeinterface #305,  1          // InterfaceMethod org/springframework/core/annotation/MergedAnnotation.synthesize:()Ljava/lang/annotation/Annotation;
      85: goto          89
      88: aconst_null
      89: areturn

  private static <A extends java.lang.annotation.Annotation> org.springframework.core.annotation.MergedAnnotation<A> findMergedAnnotation(java.lang.reflect.AnnotatedElement, java.lang.Class<A>);
    Code:
       0: aload_0
       1: ifnull        20
       4: aload_0
       5: getstatic     #290                // Field org/springframework/core/annotation/MergedAnnotations$SearchStrategy.TYPE_HIERARCHY:Lorg/springframework/core/annotation/MergedAnnotations$SearchStrategy;
       8: invokestatic  #296                // InterfaceMethod org/springframework/core/annotation/MergedAnnotations.from:(Ljava/lang/reflect/AnnotatedElement;Lorg/springframework/core/annotation/MergedAnnotations$SearchStrategy;)Lorg/springframework/core/annotation/MergedAnnotations;
      11: aload_1
      12: invokeinterface #302,  2          // InterfaceMethod org/springframework/core/annotation/MergedAnnotations.get:(Ljava/lang/Class;)Lorg/springframework/core/annotation/MergedAnnotation;
      17: goto          23
      20: invokestatic  #276                // InterfaceMethod org/springframework/core/annotation/MergedAnnotation.missing:()Lorg/springframework/core/annotation/MergedAnnotation;
      23: areturn

  private static java.lang.String lambda$forValueObject$2(java.lang.String);
    Code:
       0: aload_0
       1: invokedynamic #309,  0            // InvokeDynamic #3:makeConcatWithConstants:(Ljava/lang/String;)Ljava/lang/String;
       6: areturn

  private static void lambda$findFactoryMethodUsingReflection$1(java.lang.String, java.util.concurrent.atomic.AtomicReference, java.lang.reflect.Method) throws java.lang.IllegalArgumentException, java.lang.IllegalAccessException;
    Code:
       0: aload_2
       1: invokevirtual #313                // Method java/lang/reflect/Method.getName:()Ljava/lang/String;
       4: aload_0
       5: invokevirtual #314                // Method java/lang/String.equals:(Ljava/lang/Object;)Z
       8: ifeq          16
      11: aload_1
      12: aload_2
      13: invokevirtual #317                // Method java/util/concurrent/atomic/AtomicReference.set:(Ljava/lang/Object;)V
      16: return

  private static void lambda$getAll$0(org.springframework.context.ApplicationContext, java.util.Map, java.lang.String, java.lang.Object);
    Code:
       0: aload_0
       1: aload_3
       2: aload_2
       3: invokestatic  #321                // Method get:(Lorg/springframework/context/ApplicationContext;Ljava/lang/Object;Ljava/lang/String;)Lorg/springframework/boot/context/properties/ConfigurationPropertiesBean;
       6: astore        4
       8: aload         4
      10: ifnull        23
      13: aload_1
      14: aload_2
      15: aload         4
      17: invokeinterface #119,  3          // InterfaceMethod java/util/Map.put:(Ljava/lang/Object;Ljava/lang/Object;)Ljava/lang/Object;
      22: pop
      23: return
}
