Compiled from "ConfigurationPropertiesBinder.java"
class org.springframework.boot.context.properties.ConfigurationPropertiesBinder$ConfigurationPropertiesBinderFactory implements org.springframework.beans.factory.FactoryBean<org.springframework.boot.context.properties.ConfigurationPropertiesBinder>, org.springframework.context.ApplicationContextAware {
  private org.springframework.boot.context.properties.ConfigurationPropertiesBinder binder;

  org.springframework.boot.context.properties.ConfigurationPropertiesBinder$ConfigurationPropertiesBinderFactory();
    Code:
       0: aload_0
       1: invokespecial #1                  // Method java/lang/Object."<init>":()V
       4: return

  public void setApplicationContext(org.springframework.context.ApplicationContext) throws org.springframework.beans.BeansException;
    Code:
       0: aload_0
       1: aload_0
       2: getfield      #7                  // Field binder:Lorg/springframework/boot/context/properties/ConfigurationPropertiesBinder;
       5: ifnull        15
       8: aload_0
       9: getfield      #7                  // Field binder:Lorg/springframework/boot/context/properties/ConfigurationPropertiesBinder;
      12: goto          23
      15: new           #13                 // class org/springframework/boot/context/properties/ConfigurationPropertiesBinder
      18: dup
      19: aload_1
      20: invokespecial #15                 // Method org/springframework/boot/context/properties/ConfigurationPropertiesBinder."<init>":(Lorg/springframework/context/ApplicationContext;)V
      23: putfield      #7                  // Field binder:Lorg/springframework/boot/context/properties/ConfigurationPropertiesBinder;
      26: return

  public java.lang.Class<?> getObjectType();
    Code:
       0: ldc           #13                 // class org/springframework/boot/context/properties/ConfigurationPropertiesBinder
       2: areturn

  public org.springframework.boot.context.properties.ConfigurationPropertiesBinder getObject() throws java.lang.Exception;
    Code:
       0: aload_0
       1: getfield      #7                  // Field binder:Lorg/springframework/boot/context/properties/ConfigurationPropertiesBinder;
       4: ifnull        11
       7: iconst_1
       8: goto          12
      11: iconst_0
      12: ldc           #18                 // String Binder was not created due to missing setApplicationContext call
      14: invokestatic  #20                 // Method org/springframework/util/Assert.state:(ZLjava/lang/String;)V
      17: aload_0
      18: getfield      #7                  // Field binder:Lorg/springframework/boot/context/properties/ConfigurationPropertiesBinder;
      21: areturn

  public java.lang.Object getObject() throws java.lang.Exception;
    Code:
       0: aload_0
       1: invokevirtual #26                 // Method getObject:()Lorg/springframework/boot/context/properties/ConfigurationPropertiesBinder;
       4: areturn
}
