Compiled from "ConfigurationPropertiesScanRegistrar.java"
class org.springframework.boot.context.properties.ConfigurationPropertiesScanRegistrar implements org.springframework.context.annotation.ImportBeanDefinitionRegistrar {
  private final org.springframework.core.env.Environment environment;

  private final org.springframework.core.io.ResourceLoader resourceLoader;

  org.springframework.boot.context.properties.ConfigurationPropertiesScanRegistrar(org.springframework.core.env.Environment, org.springframework.core.io.ResourceLoader);
    Code:
       0: aload_0
       1: invokespecial #1                  // Method java/lang/Object."<init>":()V
       4: aload_0
       5: aload_1
       6: putfield      #7                  // Field environment:Lorg/springframework/core/env/Environment;
       9: aload_0
      10: aload_2
      11: putfield      #13                 // Field resourceLoader:Lorg/springframework/core/io/ResourceLoader;
      14: return

  public void registerBeanDefinitions(org.springframework.core.type.AnnotationMetadata, org.springframework.beans.factory.support.BeanDefinitionRegistry);
    Code:
       0: aload_0
       1: aload_1
       2: invokevirtual #17                 // Method getPackagesToScan:(Lorg/springframework/core/type/AnnotationMetadata;)Ljava/util/Set;
       5: astore_3
       6: aload_0
       7: aload_2
       8: aload_3
       9: invokevirtual #21                 // Method scan:(Lorg/springframework/beans/factory/support/BeanDefinitionRegistry;Ljava/util/Set;)V
      12: return

  private java.util.Set<java.lang.String> getPackagesToScan(org.springframework.core.type.AnnotationMetadata);
    Code:
       0: aload_1
       1: ldc           #25                 // class org/springframework/boot/context/properties/ConfigurationPropertiesScan
       3: invokevirtual #27                 // Method java/lang/Class.getName:()Ljava/lang/String;
       6: invokeinterface #33,  2           // InterfaceMethod org/springframework/core/type/AnnotationMetadata.getAnnotationAttributes:(Ljava/lang/String;)Ljava/util/Map;
      11: invokestatic  #39                 // Method org/springframework/core/annotation/AnnotationAttributes.fromMap:(Ljava/util/Map;)Lorg/springframework/core/annotation/AnnotationAttributes;
      14: astore_2
      15: aload_2
      16: ldc           #45                 // String basePackages
      18: invokevirtual #47                 // Method org/springframework/core/annotation/AnnotationAttributes.getStringArray:(Ljava/lang/String;)[Ljava/lang/String;
      21: astore_3
      22: aload_2
      23: ldc           #51                 // String basePackageClasses
      25: invokevirtual #53                 // Method org/springframework/core/annotation/AnnotationAttributes.getClassArray:(Ljava/lang/String;)[Ljava/lang/Class;
      28: astore        4
      30: new           #57                 // class java/util/LinkedHashSet
      33: dup
      34: aload_3
      35: invokestatic  #59                 // Method java/util/Arrays.asList:([Ljava/lang/Object;)Ljava/util/List;
      38: invokespecial #65                 // Method java/util/LinkedHashSet."<init>":(Ljava/util/Collection;)V
      41: astore        5
      43: aload         4
      45: astore        6
      47: aload         6
      49: arraylength
      50: istore        7
      52: iconst_0
      53: istore        8
      55: iload         8
      57: iload         7
      59: if_icmpge     88
      62: aload         6
      64: iload         8
      66: aaload
      67: astore        9
      69: aload         5
      71: aload         9
      73: invokestatic  #68                 // Method org/springframework/util/ClassUtils.getPackageName:(Ljava/lang/Class;)Ljava/lang/String;
      76: invokeinterface #74,  2           // InterfaceMethod java/util/Set.add:(Ljava/lang/Object;)Z
      81: pop
      82: iinc          8, 1
      85: goto          55
      88: aload         5
      90: invokeinterface #80,  1           // InterfaceMethod java/util/Set.isEmpty:()Z
      95: ifeq          115
      98: aload         5
     100: aload_1
     101: invokeinterface #84,  1           // InterfaceMethod org/springframework/core/type/AnnotationMetadata.getClassName:()Ljava/lang/String;
     106: invokestatic  #87                 // Method org/springframework/util/ClassUtils.getPackageName:(Ljava/lang/String;)Ljava/lang/String;
     109: invokeinterface #74,  2           // InterfaceMethod java/util/Set.add:(Ljava/lang/Object;)Z
     114: pop
     115: aload         5
     117: invokedynamic #90,  0             // InvokeDynamic #0:test:()Ljava/util/function/Predicate;
     122: invokeinterface #94,  2           // InterfaceMethod java/util/Set.removeIf:(Ljava/util/function/Predicate;)Z
     127: pop
     128: aload         5
     130: areturn

  private void scan(org.springframework.beans.factory.support.BeanDefinitionRegistry, java.util.Set<java.lang.String>);
    Code:
       0: new           #98                 // class org/springframework/boot/context/properties/ConfigurationPropertiesBeanRegistrar
       3: dup
       4: aload_1
       5: invokespecial #100                // Method org/springframework/boot/context/properties/ConfigurationPropertiesBeanRegistrar."<init>":(Lorg/springframework/beans/factory/support/BeanDefinitionRegistry;)V
       8: astore_3
       9: aload_0
      10: aload_1
      11: invokevirtual #103                // Method getScanner:(Lorg/springframework/beans/factory/support/BeanDefinitionRegistry;)Lorg/springframework/context/annotation/ClassPathScanningCandidateComponentProvider;
      14: astore        4
      16: aload_2
      17: invokeinterface #107,  1          // InterfaceMethod java/util/Set.iterator:()Ljava/util/Iterator;
      22: astore        5
      24: aload         5
      26: invokeinterface #111,  1          // InterfaceMethod java/util/Iterator.hasNext:()Z
      31: ifeq          100
      34: aload         5
      36: invokeinterface #116,  1          // InterfaceMethod java/util/Iterator.next:()Ljava/lang/Object;
      41: checkcast     #120                // class java/lang/String
      44: astore        6
      46: aload         4
      48: aload         6
      50: invokevirtual #122                // Method org/springframework/context/annotation/ClassPathScanningCandidateComponentProvider.findCandidateComponents:(Ljava/lang/String;)Ljava/util/Set;
      53: invokeinterface #107,  1          // InterfaceMethod java/util/Set.iterator:()Ljava/util/Iterator;
      58: astore        7
      60: aload         7
      62: invokeinterface #111,  1          // InterfaceMethod java/util/Iterator.hasNext:()Z
      67: ifeq          97
      70: aload         7
      72: invokeinterface #116,  1          // InterfaceMethod java/util/Iterator.next:()Ljava/lang/Object;
      77: checkcast     #128                // class org/springframework/beans/factory/config/BeanDefinition
      80: astore        8
      82: aload_0
      83: aload_3
      84: aload         8
      86: invokeinterface #130,  1          // InterfaceMethod org/springframework/beans/factory/config/BeanDefinition.getBeanClassName:()Ljava/lang/String;
      91: invokevirtual #133                // Method register:(Lorg/springframework/boot/context/properties/ConfigurationPropertiesBeanRegistrar;Ljava/lang/String;)V
      94: goto          60
      97: goto          24
     100: return

  private org.springframework.context.annotation.ClassPathScanningCandidateComponentProvider getScanner(org.springframework.beans.factory.support.BeanDefinitionRegistry);
    Code:
       0: new           #123                // class org/springframework/context/annotation/ClassPathScanningCandidateComponentProvider
       3: dup
       4: iconst_0
       5: invokespecial #137                // Method org/springframework/context/annotation/ClassPathScanningCandidateComponentProvider."<init>":(Z)V
       8: astore_2
       9: aload_2
      10: aload_0
      11: getfield      #7                  // Field environment:Lorg/springframework/core/env/Environment;
      14: invokevirtual #140                // Method org/springframework/context/annotation/ClassPathScanningCandidateComponentProvider.setEnvironment:(Lorg/springframework/core/env/Environment;)V
      17: aload_2
      18: aload_0
      19: getfield      #13                 // Field resourceLoader:Lorg/springframework/core/io/ResourceLoader;
      22: invokevirtual #144                // Method org/springframework/context/annotation/ClassPathScanningCandidateComponentProvider.setResourceLoader:(Lorg/springframework/core/io/ResourceLoader;)V
      25: aload_2
      26: new           #148                // class org/springframework/core/type/filter/AnnotationTypeFilter
      29: dup
      30: ldc           #150                // class org/springframework/boot/context/properties/ConfigurationProperties
      32: invokespecial #152                // Method org/springframework/core/type/filter/AnnotationTypeFilter."<init>":(Ljava/lang/Class;)V
      35: invokevirtual #155                // Method org/springframework/context/annotation/ClassPathScanningCandidateComponentProvider.addIncludeFilter:(Lorg/springframework/core/type/filter/TypeFilter;)V
      38: new           #159                // class org/springframework/boot/context/TypeExcludeFilter
      41: dup
      42: invokespecial #161                // Method org/springframework/boot/context/TypeExcludeFilter."<init>":()V
      45: astore_3
      46: aload_3
      47: aload_1
      48: checkcast     #162                // class org/springframework/beans/factory/BeanFactory
      51: invokevirtual #164                // Method org/springframework/boot/context/TypeExcludeFilter.setBeanFactory:(Lorg/springframework/beans/factory/BeanFactory;)V
      54: aload_2
      55: aload_3
      56: invokevirtual #168                // Method org/springframework/context/annotation/ClassPathScanningCandidateComponentProvider.addExcludeFilter:(Lorg/springframework/core/type/filter/TypeFilter;)V
      59: aload_2
      60: areturn

  private void register(org.springframework.boot.context.properties.ConfigurationPropertiesBeanRegistrar, java.lang.String) throws java.lang.LinkageError;
    Code:
       0: aload_0
       1: aload_1
       2: aload_2
       3: aconst_null
       4: invokestatic  #171                // Method org/springframework/util/ClassUtils.forName:(Ljava/lang/String;Ljava/lang/ClassLoader;)Ljava/lang/Class;
       7: invokevirtual #175                // Method register:(Lorg/springframework/boot/context/properties/ConfigurationPropertiesBeanRegistrar;Ljava/lang/Class;)V
      10: goto          14
      13: astore_3
      14: return
    Exception table:
       from    to  target type
           0    10    13   Class java/lang/ClassNotFoundException

  private void register(org.springframework.boot.context.properties.ConfigurationPropertiesBeanRegistrar, java.lang.Class<?>);
    Code:
       0: aload_0
       1: aload_2
       2: invokevirtual #180                // Method isComponent:(Ljava/lang/Class;)Z
       5: ifne          13
       8: aload_1
       9: aload_2
      10: invokevirtual #184                // Method org/springframework/boot/context/properties/ConfigurationPropertiesBeanRegistrar.register:(Ljava/lang/Class;)V
      13: return

  private boolean isComponent(java.lang.Class<?>);
    Code:
       0: aload_1
       1: getstatic     #186                // Field org/springframework/core/annotation/MergedAnnotations$SearchStrategy.TYPE_HIERARCHY:Lorg/springframework/core/annotation/MergedAnnotations$SearchStrategy;
       4: invokestatic  #192                // InterfaceMethod org/springframework/core/annotation/MergedAnnotations.from:(Ljava/lang/reflect/AnnotatedElement;Lorg/springframework/core/annotation/MergedAnnotations$SearchStrategy;)Lorg/springframework/core/annotation/MergedAnnotations;
       7: ldc           #198                // class org/springframework/stereotype/Component
       9: invokeinterface #200,  2          // InterfaceMethod org/springframework/core/annotation/MergedAnnotations.isPresent:(Ljava/lang/Class;)Z
      14: ireturn

  private static boolean lambda$getPackagesToScan$0(java.lang.String);
    Code:
       0: aload_0
       1: invokestatic  #203                // Method org/springframework/util/StringUtils.hasText:(Ljava/lang/String;)Z
       4: ifne          11
       7: iconst_1
       8: goto          12
      11: iconst_0
      12: ireturn
}
