Compiled from "ConfigurationPropertiesBeanFactoryInitializationAotProcessor.java"
class org.springframework.boot.context.properties.ConfigurationPropertiesBeanFactoryInitializationAotProcessor implements org.springframework.beans.factory.aot.BeanFactoryInitializationAotProcessor {
  org.springframework.boot.context.properties.ConfigurationPropertiesBeanFactoryInitializationAotProcessor();
    Code:
       0: aload_0
       1: invokespecial #1                  // Method java/lang/Object."<init>":()V
       4: return

  public org.springframework.beans.factory.aot.BeanFactoryInitializationAotContribution processAheadOfTime(org.springframework.beans.factory.config.ConfigurableListableBeanFactory);
    Code:
       0: aload_1
       1: ldc           #7                  // class org/springframework/boot/context/properties/ConfigurationProperties
       3: invokeinterface #9,  2            // InterfaceMethod org/springframework/beans/factory/config/ConfigurableListableBeanFactory.getBeanNamesForAnnotation:(Ljava/lang/Class;)[Ljava/lang/String;
       8: astore_2
       9: new           #15                 // class java/util/ArrayList
      12: dup
      13: invokespecial #17                 // Method java/util/ArrayList."<init>":()V
      16: astore_3
      17: aload_2
      18: astore        4
      20: aload         4
      22: arraylength
      23: istore        5
      25: iconst_0
      26: istore        6
      28: iload         6
      30: iload         5
      32: if_icmpge     76
      35: aload         4
      37: iload         6
      39: aaload
      40: astore        7
      42: aload_1
      43: aload         7
      45: iconst_0
      46: invokeinterface #18,  3           // InterfaceMethod org/springframework/beans/factory/config/ConfigurableListableBeanFactory.getType:(Ljava/lang/String;Z)Ljava/lang/Class;
      51: astore        8
      53: aload         8
      55: ifnull        70
      58: aload_3
      59: aload         8
      61: invokestatic  #22                 // Method org/springframework/util/ClassUtils.getUserClass:(Ljava/lang/Class;)Ljava/lang/Class;
      64: invokeinterface #28,  2           // InterfaceMethod java/util/List.add:(Ljava/lang/Object;)Z
      69: pop
      70: iinc          6, 1
      73: goto          28
      76: aload_3
      77: invokestatic  #34                 // Method org/springframework/util/CollectionUtils.isEmpty:(Ljava/util/Collection;)Z
      80: ifne          92
      83: new           #40                 // class org/springframework/boot/context/properties/ConfigurationPropertiesBeanFactoryInitializationAotProcessor$ConfigurationPropertiesReflectionHintsContribution
      86: dup
      87: aload_3
      88: invokespecial #42                 // Method org/springframework/boot/context/properties/ConfigurationPropertiesBeanFactoryInitializationAotProcessor$ConfigurationPropertiesReflectionHintsContribution."<init>":(Ljava/lang/Iterable;)V
      91: areturn
      92: aconst_null
      93: areturn
}
