Compiled from "ConfigurationPropertiesBindException.java"
public class org.springframework.boot.context.properties.ConfigurationPropertiesBindException extends org.springframework.beans.factory.BeanCreationException {
  private final org.springframework.boot.context.properties.ConfigurationPropertiesBean bean;

  org.springframework.boot.context.properties.ConfigurationPropertiesBindException(org.springframework.boot.context.properties.ConfigurationPropertiesBean, java.lang.Exception);
    Code:
       0: aload_0
       1: aload_1
       2: invokevirtual #1                  // Method org/springframework/boot/context/properties/ConfigurationPropertiesBean.getName:()Ljava/lang/String;
       5: aload_1
       6: invokestatic  #7                  // Method getMessage:(Lorg/springframework/boot/context/properties/ConfigurationPropertiesBean;)Ljava/lang/String;
       9: aload_2
      10: invokespecial #13                 // Method org/springframework/beans/factory/BeanCreationException."<init>":(Ljava/lang/String;Ljava/lang/String;Ljava/lang/Throwable;)V
      13: aload_0
      14: aload_1
      15: putfield      #19                 // Field bean:Lorg/springframework/boot/context/properties/ConfigurationPropertiesBean;
      18: return

  public java.lang.Class<?> getBeanType();
    Code:
       0: aload_0
       1: getfield      #19                 // Field bean:Lorg/springframework/boot/context/properties/ConfigurationPropertiesBean;
       4: invokevirtual #23                 // Method org/springframework/boot/context/properties/ConfigurationPropertiesBean.getType:()Ljava/lang/Class;
       7: areturn

  public org.springframework.boot.context.properties.ConfigurationProperties getAnnotation();
    Code:
       0: aload_0
       1: getfield      #19                 // Field bean:Lorg/springframework/boot/context/properties/ConfigurationPropertiesBean;
       4: invokevirtual #27                 // Method org/springframework/boot/context/properties/ConfigurationPropertiesBean.getAnnotation:()Lorg/springframework/boot/context/properties/ConfigurationProperties;
       7: areturn

  private static java.lang.String getMessage(org.springframework.boot.context.properties.ConfigurationPropertiesBean);
    Code:
       0: aload_0
       1: invokevirtual #27                 // Method org/springframework/boot/context/properties/ConfigurationPropertiesBean.getAnnotation:()Lorg/springframework/boot/context/properties/ConfigurationProperties;
       4: astore_1
       5: new           #31                 // class java/lang/StringBuilder
       8: dup
       9: invokespecial #33                 // Method java/lang/StringBuilder."<init>":()V
      12: astore_2
      13: aload_2
      14: ldc           #36                 // String Could not bind properties to \'
      16: invokevirtual #38                 // Method java/lang/StringBuilder.append:(Ljava/lang/String;)Ljava/lang/StringBuilder;
      19: pop
      20: aload_2
      21: aload_0
      22: invokevirtual #23                 // Method org/springframework/boot/context/properties/ConfigurationPropertiesBean.getType:()Ljava/lang/Class;
      25: invokestatic  #42                 // Method org/springframework/util/ClassUtils.getShortName:(Ljava/lang/Class;)Ljava/lang/String;
      28: invokevirtual #38                 // Method java/lang/StringBuilder.append:(Ljava/lang/String;)Ljava/lang/StringBuilder;
      31: ldc           #48                 // String \' :
      33: invokevirtual #38                 // Method java/lang/StringBuilder.append:(Ljava/lang/String;)Ljava/lang/StringBuilder;
      36: pop
      37: aload_2
      38: ldc           #50                 // String prefix=
      40: invokevirtual #38                 // Method java/lang/StringBuilder.append:(Ljava/lang/String;)Ljava/lang/StringBuilder;
      43: aload_1
      44: invokeinterface #52,  1           // InterfaceMethod org/springframework/boot/context/properties/ConfigurationProperties.prefix:()Ljava/lang/String;
      49: invokevirtual #38                 // Method java/lang/StringBuilder.append:(Ljava/lang/String;)Ljava/lang/StringBuilder;
      52: pop
      53: aload_2
      54: ldc           #57                 // String , ignoreInvalidFields=
      56: invokevirtual #38                 // Method java/lang/StringBuilder.append:(Ljava/lang/String;)Ljava/lang/StringBuilder;
      59: aload_1
      60: invokeinterface #59,  1           // InterfaceMethod org/springframework/boot/context/properties/ConfigurationProperties.ignoreInvalidFields:()Z
      65: invokevirtual #63                 // Method java/lang/StringBuilder.append:(Z)Ljava/lang/StringBuilder;
      68: pop
      69: aload_2
      70: ldc           #66                 // String , ignoreUnknownFields=
      72: invokevirtual #38                 // Method java/lang/StringBuilder.append:(Ljava/lang/String;)Ljava/lang/StringBuilder;
      75: aload_1
      76: invokeinterface #68,  1           // InterfaceMethod org/springframework/boot/context/properties/ConfigurationProperties.ignoreUnknownFields:()Z
      81: invokevirtual #63                 // Method java/lang/StringBuilder.append:(Z)Ljava/lang/StringBuilder;
      84: pop
      85: aload_2
      86: invokevirtual #71                 // Method java/lang/StringBuilder.toString:()Ljava/lang/String;
      89: areturn
}
