Compiled from "ConstructorBound.java"
public abstract class org.springframework.boot.context.properties.ConstructorBound {
  public org.springframework.boot.context.properties.ConstructorBound();
    Code:
       0: aload_0
       1: invokespecial #1                  // Method java/lang/Object."<init>":()V
       4: return

  public static java.lang.Object from(org.springframework.beans.factory.BeanFactory, java.lang.String, java.lang.Class<?>);
    Code:
       0: aload_2
       1: aload_1
       2: invokestatic  #7                  // Method org/springframework/boot/context/properties/ConfigurationPropertiesBean.forValueObject:(Ljava/lang/Class;Ljava/lang/String;)Lorg/springframework/boot/context/properties/ConfigurationPropertiesBean;
       5: astore_3
       6: aload_0
       7: invokestatic  #13                 // Method org/springframework/boot/context/properties/ConfigurationPropertiesBinder.get:(Lorg/springframework/beans/factory/BeanFactory;)Lorg/springframework/boot/context/properties/ConfigurationPropertiesBinder;
      10: astore        4
      12: aload         4
      14: aload_3
      15: invokevirtual #19                 // Method org/springframework/boot/context/properties/ConfigurationPropertiesBinder.bindOrCreate:(Lorg/springframework/boot/context/properties/ConfigurationPropertiesBean;)Ljava/lang/Object;
      18: areturn
      19: astore        5
      21: new           #25                 // class org/springframework/boot/context/properties/ConfigurationPropertiesBindException
      24: dup
      25: aload_3
      26: aload         5
      28: invokespecial #27                 // Method org/springframework/boot/context/properties/ConfigurationPropertiesBindException."<init>":(Lorg/springframework/boot/context/properties/ConfigurationPropertiesBean;Ljava/lang/Exception;)V
      31: athrow
    Exception table:
       from    to  target type
          12    18    19   Class java/lang/Exception
}
