Compiled from "ConversionServiceDeducer.java"
class org.springframework.boot.context.properties.ConversionServiceDeducer {
  private final org.springframework.context.ApplicationContext applicationContext;

  org.springframework.boot.context.properties.ConversionServiceDeducer(org.springframework.context.ApplicationContext);
    Code:
       0: aload_0
       1: invokespecial #1                  // Method java/lang/Object."<init>":()V
       4: aload_0
       5: aload_1
       6: putfield      #7                  // Field applicationContext:Lorg/springframework/context/ApplicationContext;
       9: return

  java.util.List<org.springframework.core.convert.ConversionService> getConversionServices();
    Code:
       0: aload_0
       1: invokevirtual #13                 // Method hasUserDefinedConfigurationServiceBean:()Z
       4: ifeq          27
       7: aload_0
       8: getfield      #7                  // Field applicationContext:Lorg/springframework/context/ApplicationContext;
      11: ldc           #19                 // String conversionService
      13: ldc           #21                 // class org/springframework/core/convert/ConversionService
      15: invokeinterface #23,  3           // InterfaceMethod org/springframework/context/ApplicationContext.getBean:(Ljava/lang/String;Ljava/lang/Class;)Ljava/lang/Object;
      20: checkcast     #21                 // class org/springframework/core/convert/ConversionService
      23: invokestatic  #29                 // Method java/util/Collections.singletonList:(Ljava/lang/Object;)Ljava/util/List;
      26: areturn
      27: aload_0
      28: getfield      #7                  // Field applicationContext:Lorg/springframework/context/ApplicationContext;
      31: astore_2
      32: aload_2
      33: instanceof    #17                 // class org/springframework/context/ConfigurableApplicationContext
      36: ifeq          50
      39: aload_2
      40: checkcast     #17                 // class org/springframework/context/ConfigurableApplicationContext
      43: astore_1
      44: aload_0
      45: aload_1
      46: invokevirtual #35                 // Method getConversionServices:(Lorg/springframework/context/ConfigurableApplicationContext;)Ljava/util/List;
      49: areturn
      50: aconst_null
      51: areturn

  private java.util.List<org.springframework.core.convert.ConversionService> getConversionServices(org.springframework.context.ConfigurableApplicationContext);
    Code:
       0: new           #39                 // class java/util/ArrayList
       3: dup
       4: invokespecial #41                 // Method java/util/ArrayList."<init>":()V
       7: astore_2
       8: aload_1
       9: invokeinterface #42,  1           // InterfaceMethod org/springframework/context/ConfigurableApplicationContext.getBeanFactory:()Lorg/springframework/beans/factory/config/ConfigurableListableBeanFactory;
      14: invokeinterface #46,  1           // InterfaceMethod org/springframework/beans/factory/config/ConfigurableListableBeanFactory.getConversionService:()Lorg/springframework/core/convert/ConversionService;
      19: ifnull        40
      22: aload_2
      23: aload_1
      24: invokeinterface #42,  1           // InterfaceMethod org/springframework/context/ConfigurableApplicationContext.getBeanFactory:()Lorg/springframework/beans/factory/config/ConfigurableListableBeanFactory;
      29: invokeinterface #46,  1           // InterfaceMethod org/springframework/beans/factory/config/ConfigurableListableBeanFactory.getConversionService:()Lorg/springframework/core/convert/ConversionService;
      34: invokeinterface #52,  2           // InterfaceMethod java/util/List.add:(Ljava/lang/Object;)Z
      39: pop
      40: new           #58                 // class org/springframework/boot/context/properties/ConversionServiceDeducer$ConverterBeans
      43: dup
      44: aload_1
      45: invokespecial #60                 // Method org/springframework/boot/context/properties/ConversionServiceDeducer$ConverterBeans."<init>":(Lorg/springframework/context/ConfigurableApplicationContext;)V
      48: astore_3
      49: aload_3
      50: invokevirtual #63                 // Method org/springframework/boot/context/properties/ConversionServiceDeducer$ConverterBeans.isEmpty:()Z
      53: ifne          80
      56: new           #66                 // class org/springframework/boot/convert/ApplicationConversionService
      59: dup
      60: invokespecial #68                 // Method org/springframework/boot/convert/ApplicationConversionService."<init>":()V
      63: astore        4
      65: aload_3
      66: aload         4
      68: invokevirtual #69                 // Method org/springframework/boot/context/properties/ConversionServiceDeducer$ConverterBeans.addTo:(Lorg/springframework/format/FormatterRegistry;)V
      71: aload_2
      72: aload         4
      74: invokeinterface #52,  2           // InterfaceMethod java/util/List.add:(Ljava/lang/Object;)Z
      79: pop
      80: aload_2
      81: areturn

  private boolean hasUserDefinedConfigurationServiceBean();
    Code:
       0: ldc           #19                 // String conversionService
       2: astore_1
       3: aload_0
       4: getfield      #7                  // Field applicationContext:Lorg/springframework/context/ApplicationContext;
       7: aload_1
       8: invokeinterface #73,  2           // InterfaceMethod org/springframework/context/ApplicationContext.containsBean:(Ljava/lang/String;)Z
      13: ifeq          40
      16: aload_0
      17: getfield      #7                  // Field applicationContext:Lorg/springframework/context/ApplicationContext;
      20: invokeinterface #77,  1           // InterfaceMethod org/springframework/context/ApplicationContext.getAutowireCapableBeanFactory:()Lorg/springframework/beans/factory/config/AutowireCapableBeanFactory;
      25: aload_1
      26: ldc           #21                 // class org/springframework/core/convert/ConversionService
      28: invokeinterface #81,  3           // InterfaceMethod org/springframework/beans/factory/config/AutowireCapableBeanFactory.isTypeMatch:(Ljava/lang/String;Ljava/lang/Class;)Z
      33: ifeq          40
      36: iconst_1
      37: goto          41
      40: iconst_0
      41: ireturn
}
