Compiled from "ConversionServiceDeducer.java"
class org.springframework.boot.context.properties.ConversionServiceDeducer$ConverterBeans {
  private final java.util.List<org.springframework.core.convert.converter.Converter> converters;

  private final java.util.List<org.springframework.core.convert.converter.GenericConverter> genericConverters;

  private final java.util.List<org.springframework.format.Formatter> formatters;

  org.springframework.boot.context.properties.ConversionServiceDeducer$ConverterBeans(org.springframework.context.ConfigurableApplicationContext);
    Code:
       0: aload_0
       1: invokespecial #1                  // Method java/lang/Object."<init>":()V
       4: aload_1
       5: invokeinterface #7,  1            // InterfaceMethod org/springframework/context/ConfigurableApplicationContext.getBeanFactory:()Lorg/springframework/beans/factory/config/ConfigurableListableBeanFactory;
      10: astore_2
      11: aload_0
      12: aload_0
      13: ldc           #13                 // class org/springframework/core/convert/converter/Converter
      15: ldc           #17                 // String org.springframework.boot.context.properties.ConfigurationPropertiesBinding
      17: aload_2
      18: invokevirtual #19                 // Method beans:(Ljava/lang/Class;Ljava/lang/String;Lorg/springframework/beans/factory/ListableBeanFactory;)Ljava/util/List;
      21: putfield      #25                 // Field converters:Ljava/util/List;
      24: aload_0
      25: aload_0
      26: ldc           #29                 // class org/springframework/core/convert/converter/GenericConverter
      28: ldc           #17                 // String org.springframework.boot.context.properties.ConfigurationPropertiesBinding
      30: aload_2
      31: invokevirtual #19                 // Method beans:(Ljava/lang/Class;Ljava/lang/String;Lorg/springframework/beans/factory/ListableBeanFactory;)Ljava/util/List;
      34: putfield      #31                 // Field genericConverters:Ljava/util/List;
      37: aload_0
      38: aload_0
      39: ldc           #34                 // class org/springframework/format/Formatter
      41: ldc           #17                 // String org.springframework.boot.context.properties.ConfigurationPropertiesBinding
      43: aload_2
      44: invokevirtual #19                 // Method beans:(Ljava/lang/Class;Ljava/lang/String;Lorg/springframework/beans/factory/ListableBeanFactory;)Ljava/util/List;
      47: putfield      #36                 // Field formatters:Ljava/util/List;
      50: return

  private <T> java.util.List<T> beans(java.lang.Class<T>, java.lang.String, org.springframework.beans.factory.ListableBeanFactory);
    Code:
       0: new           #39                 // class java/util/ArrayList
       3: dup
       4: aload_3
       5: aload_1
       6: aload_2
       7: invokestatic  #41                 // Method org/springframework/beans/factory/annotation/BeanFactoryAnnotationUtils.qualifiedBeansOfType:(Lorg/springframework/beans/factory/ListableBeanFactory;Ljava/lang/Class;Ljava/lang/String;)Ljava/util/Map;
      10: invokeinterface #47,  1           // InterfaceMethod java/util/Map.values:()Ljava/util/Collection;
      15: invokespecial #53                 // Method java/util/ArrayList."<init>":(Ljava/util/Collection;)V
      18: areturn

  boolean isEmpty();
    Code:
       0: aload_0
       1: getfield      #25                 // Field converters:Ljava/util/List;
       4: invokeinterface #56,  1           // InterfaceMethod java/util/List.isEmpty:()Z
       9: ifeq          40
      12: aload_0
      13: getfield      #31                 // Field genericConverters:Ljava/util/List;
      16: invokeinterface #56,  1           // InterfaceMethod java/util/List.isEmpty:()Z
      21: ifeq          40
      24: aload_0
      25: getfield      #36                 // Field formatters:Ljava/util/List;
      28: invokeinterface #56,  1           // InterfaceMethod java/util/List.isEmpty:()Z
      33: ifeq          40
      36: iconst_1
      37: goto          41
      40: iconst_0
      41: ireturn

  void addTo(org.springframework.format.FormatterRegistry);
    Code:
       0: aload_0
       1: getfield      #25                 // Field converters:Ljava/util/List;
       4: invokeinterface #62,  1           // InterfaceMethod java/util/List.iterator:()Ljava/util/Iterator;
       9: astore_2
      10: aload_2
      11: invokeinterface #66,  1           // InterfaceMethod java/util/Iterator.hasNext:()Z
      16: ifeq          39
      19: aload_2
      20: invokeinterface #71,  1           // InterfaceMethod java/util/Iterator.next:()Ljava/lang/Object;
      25: checkcast     #13                 // class org/springframework/core/convert/converter/Converter
      28: astore_3
      29: aload_1
      30: aload_3
      31: invokeinterface #75,  2           // InterfaceMethod org/springframework/format/FormatterRegistry.addConverter:(Lorg/springframework/core/convert/converter/Converter;)V
      36: goto          10
      39: aload_0
      40: getfield      #31                 // Field genericConverters:Ljava/util/List;
      43: invokeinterface #62,  1           // InterfaceMethod java/util/List.iterator:()Ljava/util/Iterator;
      48: astore_2
      49: aload_2
      50: invokeinterface #66,  1           // InterfaceMethod java/util/Iterator.hasNext:()Z
      55: ifeq          78
      58: aload_2
      59: invokeinterface #71,  1           // InterfaceMethod java/util/Iterator.next:()Ljava/lang/Object;
      64: checkcast     #29                 // class org/springframework/core/convert/converter/GenericConverter
      67: astore_3
      68: aload_1
      69: aload_3
      70: invokeinterface #81,  2           // InterfaceMethod org/springframework/format/FormatterRegistry.addConverter:(Lorg/springframework/core/convert/converter/GenericConverter;)V
      75: goto          49
      78: aload_0
      79: getfield      #36                 // Field formatters:Ljava/util/List;
      82: invokeinterface #62,  1           // InterfaceMethod java/util/List.iterator:()Ljava/util/Iterator;
      87: astore_2
      88: aload_2
      89: invokeinterface #66,  1           // InterfaceMethod java/util/Iterator.hasNext:()Z
      94: ifeq          117
      97: aload_2
      98: invokeinterface #71,  1           // InterfaceMethod java/util/Iterator.next:()Ljava/lang/Object;
     103: checkcast     #34                 // class org/springframework/format/Formatter
     106: astore_3
     107: aload_1
     108: aload_3
     109: invokeinterface #84,  2           // InterfaceMethod org/springframework/format/FormatterRegistry.addFormatter:(Lorg/springframework/format/Formatter;)V
     114: goto          88
     117: return
}
