Compiled from "EnableConfigurationPropertiesRegistrar.java"
class org.springframework.boot.context.properties.EnableConfigurationPropertiesRegistrar implements org.springframework.context.annotation.ImportBeanDefinitionRegistrar {
  private static final java.lang.String METHOD_VALIDATION_EXCLUDE_FILTER_BEAN_NAME;

  org.springframework.boot.context.properties.EnableConfigurationPropertiesRegistrar();
    Code:
       0: aload_0
       1: invokespecial #1                  // Method java/lang/Object."<init>":()V
       4: return

  public void registerBeanDefinitions(org.springframework.core.type.AnnotationMetadata, org.springframework.beans.factory.support.BeanDefinitionRegistry);
    Code:
       0: aload_2
       1: invokestatic  #7                  // Method registerInfrastructureBeans:(Lorg/springframework/beans/factory/support/BeanDefinitionRegistry;)V
       4: aload_2
       5: invokestatic  #13                 // Method registerMethodValidationExcludeFilter:(Lorg/springframework/beans/factory/support/BeanDefinitionRegistry;)V
       8: new           #16                 // class org/springframework/boot/context/properties/ConfigurationPropertiesBeanRegistrar
      11: dup
      12: aload_2
      13: invokespecial #18                 // Method org/springframework/boot/context/properties/ConfigurationPropertiesBeanRegistrar."<init>":(Lorg/springframework/beans/factory/support/BeanDefinitionRegistry;)V
      16: astore_3
      17: aload_0
      18: aload_1
      19: invokevirtual #20                 // Method getTypes:(Lorg/springframework/core/type/AnnotationMetadata;)Ljava/util/Set;
      22: aload_3
      23: dup
      24: invokestatic  #24                 // Method java/util/Objects.requireNonNull:(Ljava/lang/Object;)Ljava/lang/Object;
      27: pop
      28: invokedynamic #30,  0             // InvokeDynamic #0:accept:(Lorg/springframework/boot/context/properties/ConfigurationPropertiesBeanRegistrar;)Ljava/util/function/Consumer;
      33: invokeinterface #34,  2           // InterfaceMethod java/util/Set.forEach:(Ljava/util/function/Consumer;)V
      38: return

  private java.util.Set<java.lang.Class<?>> getTypes(org.springframework.core.type.AnnotationMetadata);
    Code:
       0: aload_1
       1: invokeinterface #40,  1           // InterfaceMethod org/springframework/core/type/AnnotationMetadata.getAnnotations:()Lorg/springframework/core/annotation/MergedAnnotations;
       6: ldc           #46                 // class org/springframework/boot/context/properties/EnableConfigurationProperties
       8: invokeinterface #48,  2           // InterfaceMethod org/springframework/core/annotation/MergedAnnotations.stream:(Ljava/lang/Class;)Ljava/util/stream/Stream;
      13: invokedynamic #54,  0             // InvokeDynamic #1:apply:()Ljava/util/function/Function;
      18: invokeinterface #58,  2           // InterfaceMethod java/util/stream/Stream.flatMap:(Ljava/util/function/Function;)Ljava/util/stream/Stream;
      23: invokedynamic #64,  0             // InvokeDynamic #2:test:()Ljava/util/function/Predicate;
      28: invokeinterface #68,  2           // InterfaceMethod java/util/stream/Stream.filter:(Ljava/util/function/Predicate;)Ljava/util/stream/Stream;
      33: invokestatic  #72                 // Method java/util/stream/Collectors.toSet:()Ljava/util/stream/Collector;
      36: invokeinterface #78,  2           // InterfaceMethod java/util/stream/Stream.collect:(Ljava/util/stream/Collector;)Ljava/lang/Object;
      41: checkcast     #35                 // class java/util/Set
      44: areturn

  static void registerInfrastructureBeans(org.springframework.beans.factory.support.BeanDefinitionRegistry);
    Code:
       0: aload_0
       1: invokestatic  #82                 // Method org/springframework/boot/context/properties/ConfigurationPropertiesBindingPostProcessor.register:(Lorg/springframework/beans/factory/support/BeanDefinitionRegistry;)V
       4: aload_0
       5: invokestatic  #87                 // Method org/springframework/boot/context/properties/BoundConfigurationProperties.register:(Lorg/springframework/beans/factory/support/BeanDefinitionRegistry;)V
       8: return

  static void registerMethodValidationExcludeFilter(org.springframework.beans.factory.support.BeanDefinitionRegistry);
    Code:
       0: aload_0
       1: getstatic     #90                 // Field METHOD_VALIDATION_EXCLUDE_FILTER_BEAN_NAME:Ljava/lang/String;
       4: invokeinterface #94,  2           // InterfaceMethod org/springframework/beans/factory/support/BeanDefinitionRegistry.containsBeanDefinition:(Ljava/lang/String;)Z
       9: ifne          42
      12: ldc           #100                // class org/springframework/boot/validation/beanvalidation/MethodValidationExcludeFilter
      14: ldc           #102                // String byAnnotation
      16: invokestatic  #104                // Method org/springframework/beans/factory/support/BeanDefinitionBuilder.rootBeanDefinition:(Ljava/lang/Class;Ljava/lang/String;)Lorg/springframework/beans/factory/support/BeanDefinitionBuilder;
      19: ldc           #110                // class org/springframework/boot/context/properties/ConfigurationProperties
      21: invokevirtual #112                // Method org/springframework/beans/factory/support/BeanDefinitionBuilder.addConstructorArgValue:(Ljava/lang/Object;)Lorg/springframework/beans/factory/support/BeanDefinitionBuilder;
      24: iconst_2
      25: invokevirtual #118                // Method org/springframework/beans/factory/support/BeanDefinitionBuilder.setRole:(I)Lorg/springframework/beans/factory/support/BeanDefinitionBuilder;
      28: invokevirtual #122                // Method org/springframework/beans/factory/support/BeanDefinitionBuilder.getBeanDefinition:()Lorg/springframework/beans/factory/support/AbstractBeanDefinition;
      31: astore_1
      32: aload_0
      33: getstatic     #90                 // Field METHOD_VALIDATION_EXCLUDE_FILTER_BEAN_NAME:Ljava/lang/String;
      36: aload_1
      37: invokeinterface #126,  3          // InterfaceMethod org/springframework/beans/factory/support/BeanDefinitionRegistry.registerBeanDefinition:(Ljava/lang/String;Lorg/springframework/beans/factory/config/BeanDefinition;)V
      42: return

  private static boolean lambda$getTypes$1(java.lang.Class);
    Code:
       0: getstatic     #130                // Field java/lang/Void.TYPE:Ljava/lang/Class;
       3: aload_0
       4: if_acmpeq     11
       7: iconst_1
       8: goto          12
      11: iconst_0
      12: ireturn

  private static java.util.stream.Stream lambda$getTypes$0(org.springframework.core.annotation.MergedAnnotation);
    Code:
       0: aload_0
       1: ldc           #138                // String value
       3: invokeinterface #140,  2          // InterfaceMethod org/springframework/core/annotation/MergedAnnotation.getClassArray:(Ljava/lang/String;)[Ljava/lang/Class;
       8: invokestatic  #144                // Method java/util/Arrays.stream:([Ljava/lang/Object;)Ljava/util/stream/Stream;
      11: areturn

  static {};
    Code:
       0: ldc           #8                  // class org/springframework/boot/context/properties/EnableConfigurationPropertiesRegistrar
       2: ldc           #149                // String methodValidationExcludeFilter
       4: invokestatic  #151                // Method org/springframework/core/Conventions.getQualifiedAttributeName:(Ljava/lang/Class;Ljava/lang/String;)Ljava/lang/String;
       7: putstatic     #90                 // Field METHOD_VALIDATION_EXCLUDE_FILTER_BEAN_NAME:Ljava/lang/String;
      10: return
}
