Compiled from "IncompatibleConfigurationFailureAnalyzer.java"
class org.springframework.boot.context.properties.IncompatibleConfigurationFailureAnalyzer extends org.springframework.boot.diagnostics.AbstractFailureAnalyzer<org.springframework.boot.context.properties.IncompatibleConfigurationException> {
  org.springframework.boot.context.properties.IncompatibleConfigurationFailureAnalyzer();
    Code:
       0: aload_0
       1: invokespecial #1                  // Method org/springframework/boot/diagnostics/AbstractFailureAnalyzer."<init>":()V
       4: return

  protected org.springframework.boot.diagnostics.FailureAnalysis analyze(java.lang.Throwable, org.springframework.boot.context.properties.IncompatibleConfigurationException);
    Code:
       0: ldc           #7                  // String Review the docs for %s and change the configured values.
       2: iconst_1
       3: anewarray     #9                  // class java/lang/Object
       6: dup
       7: iconst_0
       8: aload_2
       9: invokevirtual #11                 // Method org/springframework/boot/context/properties/IncompatibleConfigurationException.getIncompatibleKeys:()Ljava/util/Collection;
      12: invokeinterface #17,  1           // InterfaceMethod java/util/Collection.stream:()Ljava/util/stream/Stream;
      17: ldc           #23                 // String ,
      19: invokestatic  #25                 // Method java/util/stream/Collectors.joining:(Ljava/lang/CharSequence;)Ljava/util/stream/Collector;
      22: invokeinterface #31,  2           // InterfaceMethod java/util/stream/Stream.collect:(Ljava/util/stream/Collector;)Ljava/lang/Object;
      27: aastore
      28: invokestatic  #37                 // Method java/lang/String.format:(Ljava/lang/String;[Ljava/lang/Object;)Ljava/lang/String;
      31: astore_3
      32: new           #43                 // class org/springframework/boot/diagnostics/FailureAnalysis
      35: dup
      36: aload_2
      37: invokevirtual #45                 // Method org/springframework/boot/context/properties/IncompatibleConfigurationException.getMessage:()Ljava/lang/String;
      40: aload_3
      41: aload_2
      42: invokespecial #49                 // Method org/springframework/boot/diagnostics/FailureAnalysis."<init>":(Ljava/lang/String;Ljava/lang/String;Ljava/lang/Throwable;)V
      45: areturn

  protected org.springframework.boot.diagnostics.FailureAnalysis analyze(java.lang.Throwable, java.lang.Throwable);
    Code:
       0: aload_0
       1: aload_1
       2: aload_2
       3: checkcast     #12                 // class org/springframework/boot/context/properties/IncompatibleConfigurationException
       6: invokevirtual #52                 // Method analyze:(Ljava/lang/Throwable;Lorg/springframework/boot/context/properties/IncompatibleConfigurationException;)Lorg/springframework/boot/diagnostics/FailureAnalysis;
       9: areturn
}
