Compiled from "IncompatibleConfigurationException.java"
public class org.springframework.boot.context.properties.IncompatibleConfigurationException extends java.lang.RuntimeException {
  private final java.util.List<java.lang.String> incompatibleKeys;

  public org.springframework.boot.context.properties.IncompatibleConfigurationException(java.lang.String...);
    Code:
       0: aload_0
       1: aload_1
       2: invokestatic  #1                  // Method java/util/Arrays.toString:([Ljava/lang/Object;)Ljava/lang/String;
       5: invokedynamic #7,  0              // InvokeDynamic #0:makeConcatWithConstants:(Ljava/lang/String;)Ljava/lang/String;
      10: invokespecial #11                 // Method java/lang/RuntimeException."<init>":(Ljava/lang/String;)V
      13: aload_0
      14: aload_1
      15: invokestatic  #17                 // Method java/util/Arrays.asList:([Ljava/lang/Object;)Ljava/util/List;
      18: putfield      #21                 // Field incompatibleKeys:Ljava/util/List;
      21: return

  public java.util.Collection<java.lang.String> getIncompatibleKeys();
    Code:
       0: aload_0
       1: getfield      #21                 // Field incompatibleKeys:Ljava/util/List;
       4: areturn
}
