Compiled from "NotConstructorBoundInjectionFailureAnalyzer.java"
class org.springframework.boot.context.properties.NotConstructorBoundInjectionFailureAnalyzer extends org.springframework.boot.diagnostics.analyzer.AbstractInjectionFailureAnalyzer<org.springframework.beans.factory.NoSuchBeanDefinitionException> implements org.springframework.core.Ordered {
  org.springframework.boot.context.properties.NotConstructorBoundInjectionFailureAnalyzer();
    Code:
       0: aload_0
       1: invokespecial #1                  // Method org/springframework/boot/diagnostics/analyzer/AbstractInjectionFailureAnalyzer."<init>":()V
       4: return

  public int getOrder();
    Code:
       0: iconst_0
       1: ireturn

  protected org.springframework.boot.diagnostics.FailureAnalysis analyze(java.lang.Throwable, org.springframework.beans.factory.NoSuchBeanDefinitionException, java.lang.String);
    Code:
       0: aload_0
       1: aload_1
       2: invokevirtual #7                  // Method findInjectionPoint:(Ljava/lang/Throwable;)Lorg/springframework/beans/factory/InjectionPoint;
       5: astore        4
       7: aload_0
       8: aload         4
      10: invokevirtual #13                 // Method isConstructorBindingConfigurationProperties:(Lorg/springframework/beans/factory/InjectionPoint;)Z
      13: ifeq          85
      16: aload         4
      18: invokevirtual #17                 // Method org/springframework/beans/factory/InjectionPoint.getMember:()Ljava/lang/reflect/Member;
      21: invokeinterface #23,  1           // InterfaceMethod java/lang/reflect/Member.getDeclaringClass:()Ljava/lang/Class;
      26: invokevirtual #29                 // Method java/lang/Class.getSimpleName:()Ljava/lang/String;
      29: astore        5
      31: aload         5
      33: ldc           #35                 // class org/springframework/boot/context/properties/ConfigurationPropertiesScan
      35: invokevirtual #29                 // Method java/lang/Class.getSimpleName:()Ljava/lang/String;
      38: ldc           #37                 // class org/springframework/boot/context/properties/EnableConfigurationProperties
      40: invokevirtual #29                 // Method java/lang/Class.getSimpleName:()Ljava/lang/String;
      43: invokedynamic #39,  0             // InvokeDynamic #0:makeConcatWithConstants:(Ljava/lang/String;Ljava/lang/String;Ljava/lang/String;)Ljava/lang/String;
      48: iconst_1
      49: anewarray     #43                 // class java/lang/Object
      52: dup
      53: iconst_0
      54: aload         5
      56: aastore
      57: invokestatic  #45                 // Method java/lang/String.format:(Ljava/lang/String;[Ljava/lang/Object;)Ljava/lang/String;
      60: astore        6
      62: new           #51                 // class org/springframework/boot/diagnostics/FailureAnalysis
      65: dup
      66: aload         5
      68: ldc           #53                 // class org/springframework/boot/context/properties/bind/ConstructorBinding
      70: invokevirtual #29                 // Method java/lang/Class.getSimpleName:()Ljava/lang/String;
      73: invokedynamic #55,  0             // InvokeDynamic #1:makeConcatWithConstants:(Ljava/lang/String;Ljava/lang/String;)Ljava/lang/String;
      78: aload         6
      80: aload_2
      81: invokespecial #58                 // Method org/springframework/boot/diagnostics/FailureAnalysis."<init>":(Ljava/lang/String;Ljava/lang/String;Ljava/lang/Throwable;)V
      84: areturn
      85: aconst_null
      86: areturn

  private boolean isConstructorBindingConfigurationProperties(org.springframework.beans.factory.InjectionPoint);
    Code:
       0: aload_1
       1: ifnull        68
       4: aload_1
       5: invokevirtual #17                 // Method org/springframework/beans/factory/InjectionPoint.getMember:()Ljava/lang/reflect/Member;
       8: astore_3
       9: aload_3
      10: instanceof    #61                 // class java/lang/reflect/Constructor
      13: ifeq          68
      16: aload_3
      17: checkcast     #61                 // class java/lang/reflect/Constructor
      20: astore_2
      21: aload_2
      22: invokevirtual #63                 // Method java/lang/reflect/Constructor.getDeclaringClass:()Ljava/lang/Class;
      25: astore_3
      26: aload_3
      27: invokestatic  #64                 // InterfaceMethod org/springframework/core/annotation/MergedAnnotations.from:(Ljava/lang/reflect/AnnotatedElement;)Lorg/springframework/core/annotation/MergedAnnotations;
      30: ldc           #70                 // class org/springframework/boot/context/properties/ConfigurationProperties
      32: invokeinterface #72,  2           // InterfaceMethod org/springframework/core/annotation/MergedAnnotations.get:(Ljava/lang/Class;)Lorg/springframework/core/annotation/MergedAnnotation;
      37: astore        4
      39: aload         4
      41: invokeinterface #76,  1           // InterfaceMethod org/springframework/core/annotation/MergedAnnotation.isPresent:()Z
      46: ifeq          66
      49: aload_2
      50: invokevirtual #63                 // Method java/lang/reflect/Constructor.getDeclaringClass:()Ljava/lang/Class;
      53: invokestatic  #82                 // Method org/springframework/boot/context/properties/ConfigurationPropertiesBean$BindMethod.get:(Ljava/lang/Class;)Lorg/springframework/boot/context/properties/ConfigurationPropertiesBean$BindMethod;
      56: getstatic     #87                 // Field org/springframework/boot/context/properties/ConfigurationPropertiesBean$BindMethod.VALUE_OBJECT:Lorg/springframework/boot/context/properties/ConfigurationPropertiesBean$BindMethod;
      59: if_acmpne     66
      62: iconst_1
      63: goto          67
      66: iconst_0
      67: ireturn
      68: iconst_0
      69: ireturn

  private org.springframework.beans.factory.InjectionPoint findInjectionPoint(java.lang.Throwable);
    Code:
       0: aload_0
       1: aload_1
       2: ldc           #91                 // class org/springframework/beans/factory/UnsatisfiedDependencyException
       4: invokevirtual #93                 // Method findCause:(Ljava/lang/Throwable;Ljava/lang/Class;)Ljava/lang/Throwable;
       7: checkcast     #91                 // class org/springframework/beans/factory/UnsatisfiedDependencyException
      10: astore_2
      11: aload_2
      12: ifnonnull     17
      15: aconst_null
      16: areturn
      17: aload_2
      18: invokevirtual #97                 // Method org/springframework/beans/factory/UnsatisfiedDependencyException.getInjectionPoint:()Lorg/springframework/beans/factory/InjectionPoint;
      21: areturn

  protected org.springframework.boot.diagnostics.FailureAnalysis analyze(java.lang.Throwable, java.lang.Throwable, java.lang.String);
    Code:
       0: aload_0
       1: aload_1
       2: aload_2
       3: checkcast     #101                // class org/springframework/beans/factory/NoSuchBeanDefinitionException
       6: aload_3
       7: invokevirtual #103                // Method analyze:(Ljava/lang/Throwable;Lorg/springframework/beans/factory/NoSuchBeanDefinitionException;Ljava/lang/String;)Lorg/springframework/boot/diagnostics/FailureAnalysis;
      10: areturn
}
