Compiled from "PropertyMapper.java"
public final class org.springframework.boot.context.properties.PropertyMapper$Source<T> {
  private final java.util.function.Supplier<T> supplier;

  private final java.util.function.Predicate<T> predicate;

  private org.springframework.boot.context.properties.PropertyMapper$Source(java.util.function.Supplier<T>, java.util.function.Predicate<T>);
    Code:
       0: aload_0
       1: invokespecial #1                  // Method java/lang/Object."<init>":()V
       4: aload_2
       5: ldc           #7                  // String Predicate must not be null
       7: invokestatic  #9                  // Method org/springframework/util/Assert.notNull:(Ljava/lang/Object;Ljava/lang/String;)V
      10: aload_0
      11: aload_1
      12: putfield      #15                 // Field supplier:Ljava/util/function/Supplier;
      15: aload_0
      16: aload_2
      17: putfield      #21                 // Field predicate:Ljava/util/function/Predicate;
      20: return

  public <R extends java.lang.Number> org.springframework.boot.context.properties.PropertyMapper$Source<java.lang.Integer> asInt(java.util.function.Function<T, R>);
    Code:
       0: aload_0
       1: aload_1
       2: invokevirtual #25                 // Method as:(Ljava/util/function/Function;)Lorg/springframework/boot/context/properties/PropertyMapper$Source;
       5: invokedynamic #29,  0             // InvokeDynamic #0:apply:()Ljava/util/function/Function;
      10: invokevirtual #25                 // Method as:(Ljava/util/function/Function;)Lorg/springframework/boot/context/properties/PropertyMapper$Source;
      13: areturn

  public <R> org.springframework.boot.context.properties.PropertyMapper$Source<R> as(java.util.function.Function<T, R>);
    Code:
       0: aload_1
       1: ldc           #33                 // String Adapter must not be null
       3: invokestatic  #9                  // Method org/springframework/util/Assert.notNull:(Ljava/lang/Object;Ljava/lang/String;)V
       6: aload_0
       7: invokedynamic #35,  0             // InvokeDynamic #1:get:(Lorg/springframework/boot/context/properties/PropertyMapper$Source;)Ljava/util/function/Supplier;
      12: astore_2
      13: aload_2
      14: invokedynamic #39,  0             // InvokeDynamic #2:test:(Ljava/util/function/Supplier;)Ljava/util/function/Predicate;
      19: astore_3
      20: aload_0
      21: aload_2
      22: aload_1
      23: invokedynamic #43,  0             // InvokeDynamic #3:get:(Lorg/springframework/boot/context/properties/PropertyMapper$Source;Ljava/util/function/Supplier;Ljava/util/function/Function;)Ljava/util/function/Supplier;
      28: astore        4
      30: new           #16                 // class org/springframework/boot/context/properties/PropertyMapper$Source
      33: dup
      34: aload         4
      36: aload_3
      37: invokespecial #46                 // Method "<init>":(Ljava/util/function/Supplier;Ljava/util/function/Predicate;)V
      40: areturn

  public org.springframework.boot.context.properties.PropertyMapper$Source<T> whenNonNull();
    Code:
       0: new           #16                 // class org/springframework/boot/context/properties/PropertyMapper$Source
       3: dup
       4: new           #49                 // class org/springframework/boot/context/properties/PropertyMapper$NullPointerExceptionSafeSupplier
       7: dup
       8: aload_0
       9: getfield      #15                 // Field supplier:Ljava/util/function/Supplier;
      12: invokespecial #51                 // Method org/springframework/boot/context/properties/PropertyMapper$NullPointerExceptionSafeSupplier."<init>":(Ljava/util/function/Supplier;)V
      15: invokedynamic #54,  0             // InvokeDynamic #4:test:()Ljava/util/function/Predicate;
      20: invokespecial #46                 // Method "<init>":(Ljava/util/function/Supplier;Ljava/util/function/Predicate;)V
      23: areturn

  public org.springframework.boot.context.properties.PropertyMapper$Source<T> whenTrue();
    Code:
       0: aload_0
       1: getstatic     #57                 // Field java/lang/Boolean.TRUE:Ljava/lang/Boolean;
       4: dup
       5: invokestatic  #63                 // Method java/util/Objects.requireNonNull:(Ljava/lang/Object;)Ljava/lang/Object;
       8: pop
       9: invokedynamic #69,  0             // InvokeDynamic #5:test:(Ljava/lang/Boolean;)Ljava/util/function/Predicate;
      14: invokevirtual #72                 // Method when:(Ljava/util/function/Predicate;)Lorg/springframework/boot/context/properties/PropertyMapper$Source;
      17: areturn

  public org.springframework.boot.context.properties.PropertyMapper$Source<T> whenFalse();
    Code:
       0: aload_0
       1: getstatic     #76                 // Field java/lang/Boolean.FALSE:Ljava/lang/Boolean;
       4: dup
       5: invokestatic  #63                 // Method java/util/Objects.requireNonNull:(Ljava/lang/Object;)Ljava/lang/Object;
       8: pop
       9: invokedynamic #69,  0             // InvokeDynamic #5:test:(Ljava/lang/Boolean;)Ljava/util/function/Predicate;
      14: invokevirtual #72                 // Method when:(Ljava/util/function/Predicate;)Lorg/springframework/boot/context/properties/PropertyMapper$Source;
      17: areturn

  public org.springframework.boot.context.properties.PropertyMapper$Source<T> whenHasText();
    Code:
       0: aload_0
       1: invokedynamic #79,  0             // InvokeDynamic #6:test:()Ljava/util/function/Predicate;
       6: invokevirtual #72                 // Method when:(Ljava/util/function/Predicate;)Lorg/springframework/boot/context/properties/PropertyMapper$Source;
       9: areturn

  public org.springframework.boot.context.properties.PropertyMapper$Source<T> whenEqualTo(java.lang.Object);
    Code:
       0: aload_0
       1: aload_1
       2: dup
       3: invokestatic  #63                 // Method java/util/Objects.requireNonNull:(Ljava/lang/Object;)Ljava/lang/Object;
       6: pop
       7: invokedynamic #80,  0             // InvokeDynamic #7:test:(Ljava/lang/Object;)Ljava/util/function/Predicate;
      12: invokevirtual #72                 // Method when:(Ljava/util/function/Predicate;)Lorg/springframework/boot/context/properties/PropertyMapper$Source;
      15: areturn

  public <R extends T> org.springframework.boot.context.properties.PropertyMapper$Source<R> whenInstanceOf(java.lang.Class<R>);
    Code:
       0: aload_0
       1: aload_1
       2: dup
       3: invokestatic  #63                 // Method java/util/Objects.requireNonNull:(Ljava/lang/Object;)Ljava/lang/Object;
       6: pop
       7: invokedynamic #83,  0             // InvokeDynamic #8:test:(Ljava/lang/Class;)Ljava/util/function/Predicate;
      12: invokevirtual #72                 // Method when:(Ljava/util/function/Predicate;)Lorg/springframework/boot/context/properties/PropertyMapper$Source;
      15: aload_1
      16: dup
      17: invokestatic  #63                 // Method java/util/Objects.requireNonNull:(Ljava/lang/Object;)Ljava/lang/Object;
      20: pop
      21: invokedynamic #86,  0             // InvokeDynamic #9:apply:(Ljava/lang/Class;)Ljava/util/function/Function;
      26: invokevirtual #25                 // Method as:(Ljava/util/function/Function;)Lorg/springframework/boot/context/properties/PropertyMapper$Source;
      29: areturn

  public org.springframework.boot.context.properties.PropertyMapper$Source<T> whenNot(java.util.function.Predicate<T>);
    Code:
       0: aload_1
       1: ldc           #7                  // String Predicate must not be null
       3: invokestatic  #9                  // Method org/springframework/util/Assert.notNull:(Ljava/lang/Object;Ljava/lang/String;)V
       6: aload_0
       7: aload_1
       8: invokeinterface #89,  1           // InterfaceMethod java/util/function/Predicate.negate:()Ljava/util/function/Predicate;
      13: invokevirtual #72                 // Method when:(Ljava/util/function/Predicate;)Lorg/springframework/boot/context/properties/PropertyMapper$Source;
      16: areturn

  public org.springframework.boot.context.properties.PropertyMapper$Source<T> when(java.util.function.Predicate<T>);
    Code:
       0: aload_1
       1: ldc           #7                  // String Predicate must not be null
       3: invokestatic  #9                  // Method org/springframework/util/Assert.notNull:(Ljava/lang/Object;Ljava/lang/String;)V
       6: new           #16                 // class org/springframework/boot/context/properties/PropertyMapper$Source
       9: dup
      10: aload_0
      11: getfield      #15                 // Field supplier:Ljava/util/function/Supplier;
      14: aload_0
      15: getfield      #21                 // Field predicate:Ljava/util/function/Predicate;
      18: ifnull        34
      21: aload_0
      22: getfield      #21                 // Field predicate:Ljava/util/function/Predicate;
      25: aload_1
      26: invokeinterface #94,  2           // InterfaceMethod java/util/function/Predicate.and:(Ljava/util/function/Predicate;)Ljava/util/function/Predicate;
      31: goto          35
      34: aload_1
      35: invokespecial #46                 // Method "<init>":(Ljava/util/function/Supplier;Ljava/util/function/Predicate;)V
      38: areturn

  public void to(java.util.function.Consumer<T>);
    Code:
       0: aload_1
       1: ldc           #98                 // String Consumer must not be null
       3: invokestatic  #9                  // Method org/springframework/util/Assert.notNull:(Ljava/lang/Object;Ljava/lang/String;)V
       6: aload_0
       7: getfield      #15                 // Field supplier:Ljava/util/function/Supplier;
      10: invokeinterface #100,  1          // InterfaceMethod java/util/function/Supplier.get:()Ljava/lang/Object;
      15: astore_2
      16: aload_0
      17: getfield      #21                 // Field predicate:Ljava/util/function/Predicate;
      20: aload_2
      21: invokeinterface #105,  2          // InterfaceMethod java/util/function/Predicate.test:(Ljava/lang/Object;)Z
      26: ifeq          36
      29: aload_1
      30: aload_2
      31: invokeinterface #108,  2          // InterfaceMethod java/util/function/Consumer.accept:(Ljava/lang/Object;)V
      36: return

  public <R> R to(R, java.util.function.BiFunction<R, T, R>);
    Code:
       0: aload_1
       1: ldc           #114                // String Instance must not be null
       3: invokestatic  #9                  // Method org/springframework/util/Assert.notNull:(Ljava/lang/Object;Ljava/lang/String;)V
       6: aload_2
       7: ldc           #116                // String Mapper must not be null
       9: invokestatic  #9                  // Method org/springframework/util/Assert.notNull:(Ljava/lang/Object;Ljava/lang/String;)V
      12: aload_0
      13: getfield      #15                 // Field supplier:Ljava/util/function/Supplier;
      16: invokeinterface #100,  1          // InterfaceMethod java/util/function/Supplier.get:()Ljava/lang/Object;
      21: astore_3
      22: aload_0
      23: getfield      #21                 // Field predicate:Ljava/util/function/Predicate;
      26: aload_3
      27: invokeinterface #105,  2          // InterfaceMethod java/util/function/Predicate.test:(Ljava/lang/Object;)Z
      32: ifne          39
      35: aload_1
      36: goto          47
      39: aload_2
      40: aload_1
      41: aload_3
      42: invokeinterface #118,  3          // InterfaceMethod java/util/function/BiFunction.apply:(Ljava/lang/Object;Ljava/lang/Object;)Ljava/lang/Object;
      47: areturn

  public <R> R toInstance(java.util.function.Function<T, R>);
    Code:
       0: aload_1
       1: ldc           #123                // String Factory must not be null
       3: invokestatic  #9                  // Method org/springframework/util/Assert.notNull:(Ljava/lang/Object;Ljava/lang/String;)V
       6: aload_0
       7: getfield      #15                 // Field supplier:Ljava/util/function/Supplier;
      10: invokeinterface #100,  1          // InterfaceMethod java/util/function/Supplier.get:()Ljava/lang/Object;
      15: astore_2
      16: aload_0
      17: getfield      #21                 // Field predicate:Ljava/util/function/Predicate;
      20: aload_2
      21: invokeinterface #105,  2          // InterfaceMethod java/util/function/Predicate.test:(Ljava/lang/Object;)Z
      26: ifne          39
      29: new           #125                // class java/util/NoSuchElementException
      32: dup
      33: ldc           #127                // String No value present
      35: invokespecial #129                // Method java/util/NoSuchElementException."<init>":(Ljava/lang/String;)V
      38: athrow
      39: aload_1
      40: aload_2
      41: invokeinterface #132,  2          // InterfaceMethod java/util/function/Function.apply:(Ljava/lang/Object;)Ljava/lang/Object;
      46: areturn

  public void toCall(java.lang.Runnable);
    Code:
       0: aload_1
       1: ldc           #136                // String Runnable must not be null
       3: invokestatic  #9                  // Method org/springframework/util/Assert.notNull:(Ljava/lang/Object;Ljava/lang/String;)V
       6: aload_0
       7: getfield      #15                 // Field supplier:Ljava/util/function/Supplier;
      10: invokeinterface #100,  1          // InterfaceMethod java/util/function/Supplier.get:()Ljava/lang/Object;
      15: astore_2
      16: aload_0
      17: getfield      #21                 // Field predicate:Ljava/util/function/Predicate;
      20: aload_2
      21: invokeinterface #105,  2          // InterfaceMethod java/util/function/Predicate.test:(Ljava/lang/Object;)Z
      26: ifeq          35
      29: aload_1
      30: invokeinterface #138,  1          // InterfaceMethod java/lang/Runnable.run:()V
      35: return

  private static boolean lambda$whenHasText$3(java.lang.Object);
    Code:
       0: aload_0
       1: aconst_null
       2: invokestatic  #143                // Method java/util/Objects.toString:(Ljava/lang/Object;Ljava/lang/String;)Ljava/lang/String;
       5: invokestatic  #147                // Method org/springframework/util/StringUtils.hasText:(Ljava/lang/String;)Z
       8: ireturn

  private java.lang.Object lambda$as$2(java.util.function.Supplier, java.util.function.Function);
    Code:
       0: aload_1
       1: invokeinterface #100,  1          // InterfaceMethod java/util/function/Supplier.get:()Ljava/lang/Object;
       6: checkcast     #58                 // class java/lang/Boolean
       9: invokevirtual #153                // Method java/lang/Boolean.booleanValue:()Z
      12: ifeq          31
      15: aload_2
      16: aload_0
      17: getfield      #15                 // Field supplier:Ljava/util/function/Supplier;
      20: invokeinterface #100,  1          // InterfaceMethod java/util/function/Supplier.get:()Ljava/lang/Object;
      25: invokeinterface #132,  2          // InterfaceMethod java/util/function/Function.apply:(Ljava/lang/Object;)Ljava/lang/Object;
      30: areturn
      31: aconst_null
      32: areturn

  private static boolean lambda$as$1(java.util.function.Supplier, java.lang.Object);
    Code:
       0: aload_0
       1: invokeinterface #100,  1          // InterfaceMethod java/util/function/Supplier.get:()Ljava/lang/Object;
       6: checkcast     #58                 // class java/lang/Boolean
       9: invokevirtual #153                // Method java/lang/Boolean.booleanValue:()Z
      12: ireturn

  private java.lang.Boolean lambda$as$0();
    Code:
       0: aload_0
       1: getfield      #21                 // Field predicate:Ljava/util/function/Predicate;
       4: aload_0
       5: getfield      #15                 // Field supplier:Ljava/util/function/Supplier;
       8: invokeinterface #100,  1          // InterfaceMethod java/util/function/Supplier.get:()Ljava/lang/Object;
      13: invokeinterface #105,  2          // InterfaceMethod java/util/function/Predicate.test:(Ljava/lang/Object;)Z
      18: invokestatic  #157                // Method java/lang/Boolean.valueOf:(Z)Ljava/lang/Boolean;
      21: areturn
}
