Compiled from "CuratorZookeeperClient.java"
class org.apache.dubbo.remoting.zookeeper.curator.CuratorZookeeperClient$CuratorConnectionStateListener implements org.apache.curator.framework.state.ConnectionStateListener {
  private final long UNKNOWN_SESSION_ID;

  private long lastSessionId;

  private int timeout;

  private int sessionExpireMs;

  final org.apache.dubbo.remoting.zookeeper.curator.CuratorZookeeperClient this$0;

  public org.apache.dubbo.remoting.zookeeper.curator.CuratorZookeeperClient$CuratorConnectionStateListener(org.apache.dubbo.remoting.zookeeper.curator.CuratorZookeeperClient, org.apache.dubbo.common.URL);
    Code:
       0: aload_0
       1: aload_1
       2: putfield      #3                  // Field this$0:Lorg/apache/dubbo/remoting/zookeeper/curator/CuratorZookeeperClient;
       5: aload_0
       6: invokespecial #4                  // Method java/lang/Object."<init>":()V
       9: aload_0
      10: ldc2_w        #5                  // long -1l
      13: putfield      #7                  // Field UNKNOWN_SESSION_ID:J
      16: aload_0
      17: aload_2
      18: ldc           #8                  // String timeout
      20: aload_1
      21: invokestatic  #9                  // Method org/apache/dubbo/remoting/zookeeper/curator/CuratorZookeeperClient.access$500:(Lorg/apache/dubbo/remoting/zookeeper/curator/CuratorZookeeperClient;)I
      24: invokevirtual #10                 // Method org/apache/dubbo/common/URL.getParameter:(Ljava/lang/String;I)I
      27: putfield      #11                 // Field timeout:I
      30: aload_0
      31: aload_2
      32: ldc           #12                 // String session
      34: aload_1
      35: invokestatic  #13                 // Method org/apache/dubbo/remoting/zookeeper/curator/CuratorZookeeperClient.access$600:(Lorg/apache/dubbo/remoting/zookeeper/curator/CuratorZookeeperClient;)I
      38: invokevirtual #10                 // Method org/apache/dubbo/common/URL.getParameter:(Ljava/lang/String;I)I
      41: putfield      #14                 // Field sessionExpireMs:I
      44: return

  public void stateChanged(org.apache.curator.framework.CuratorFramework, org.apache.curator.framework.state.ConnectionState);
    Code:
       0: ldc2_w        #5                  // long -1l
       3: lstore_3
       4: aload_1
       5: invokeinterface #16,  1           // InterfaceMethod org/apache/curator/framework/CuratorFramework.getZookeeperClient:()Lorg/apache/curator/CuratorZookeeperClient;
      10: invokevirtual #17                 // Method org/apache/curator/CuratorZookeeperClient.getZooKeeper:()Lorg/apache/zookeeper/ZooKeeper;
      13: invokevirtual #18                 // Method org/apache/zookeeper/ZooKeeper.getSessionId:()J
      16: lstore_3
      17: goto          38
      20: astore        5
      22: getstatic     #20                 // Field org/apache/dubbo/remoting/zookeeper/curator/CuratorZookeeperClient.logger:Lorg/apache/dubbo/common/logger/ErrorTypeAwareLogger;
      25: ldc           #21                 // String 1-35
      27: ldc           #22                 // String
      29: ldc           #22                 // String
      31: ldc           #23                 // String Curator client state changed, but failed to get the related zk session instance.
      33: invokeinterface #24,  5           // InterfaceMethod org/apache/dubbo/common/logger/ErrorTypeAwareLogger.warn:(Ljava/lang/String;Ljava/lang/String;Ljava/lang/String;Ljava/lang/String;)V
      38: aload_2
      39: getstatic     #25                 // Field org/apache/curator/framework/state/ConnectionState.LOST:Lorg/apache/curator/framework/state/ConnectionState;
      42: if_acmpne     100
      45: getstatic     #20                 // Field org/apache/dubbo/remoting/zookeeper/curator/CuratorZookeeperClient.logger:Lorg/apache/dubbo/common/logger/ErrorTypeAwareLogger;
      48: ldc           #21                 // String 1-35
      50: ldc           #22                 // String
      52: ldc           #22                 // String
      54: new           #26                 // class java/lang/StringBuilder
      57: dup
      58: invokespecial #27                 // Method java/lang/StringBuilder."<init>":()V
      61: ldc           #28                 // String Curator zookeeper session
      63: invokevirtual #29                 // Method java/lang/StringBuilder.append:(Ljava/lang/String;)Ljava/lang/StringBuilder;
      66: aload_0
      67: getfield      #30                 // Field lastSessionId:J
      70: invokestatic  #31                 // Method java/lang/Long.toHexString:(J)Ljava/lang/String;
      73: invokevirtual #29                 // Method java/lang/StringBuilder.append:(Ljava/lang/String;)Ljava/lang/StringBuilder;
      76: ldc           #32                 // String  expired.
      78: invokevirtual #29                 // Method java/lang/StringBuilder.append:(Ljava/lang/String;)Ljava/lang/StringBuilder;
      81: invokevirtual #33                 // Method java/lang/StringBuilder.toString:()Ljava/lang/String;
      84: invokeinterface #24,  5           // InterfaceMethod org/apache/dubbo/common/logger/ErrorTypeAwareLogger.warn:(Ljava/lang/String;Ljava/lang/String;Ljava/lang/String;Ljava/lang/String;)V
      89: aload_0
      90: getfield      #3                  // Field this$0:Lorg/apache/dubbo/remoting/zookeeper/curator/CuratorZookeeperClient;
      93: iconst_0
      94: invokestatic  #35                 // Method org/apache/dubbo/remoting/zookeeper/curator/CuratorZookeeperClient.access$700:(Lorg/apache/dubbo/remoting/zookeeper/curator/CuratorZookeeperClient;I)V
      97: goto          366
     100: aload_2
     101: getstatic     #36                 // Field org/apache/curator/framework/state/ConnectionState.SUSPENDED:Lorg/apache/curator/framework/state/ConnectionState;
     104: if_acmpne     178
     107: getstatic     #20                 // Field org/apache/dubbo/remoting/zookeeper/curator/CuratorZookeeperClient.logger:Lorg/apache/dubbo/common/logger/ErrorTypeAwareLogger;
     110: ldc           #21                 // String 1-35
     112: ldc           #22                 // String
     114: ldc           #22                 // String
     116: new           #26                 // class java/lang/StringBuilder
     119: dup
     120: invokespecial #27                 // Method java/lang/StringBuilder."<init>":()V
     123: ldc           #37                 // String Curator zookeeper connection of session
     125: invokevirtual #29                 // Method java/lang/StringBuilder.append:(Ljava/lang/String;)Ljava/lang/StringBuilder;
     128: lload_3
     129: invokestatic  #31                 // Method java/lang/Long.toHexString:(J)Ljava/lang/String;
     132: invokevirtual #29                 // Method java/lang/StringBuilder.append:(Ljava/lang/String;)Ljava/lang/StringBuilder;
     135: ldc           #38                 // String  timed out. connection timeout value is
     137: invokevirtual #29                 // Method java/lang/StringBuilder.append:(Ljava/lang/String;)Ljava/lang/StringBuilder;
     140: aload_0
     141: getfield      #11                 // Field timeout:I
     144: invokevirtual #39                 // Method java/lang/StringBuilder.append:(I)Ljava/lang/StringBuilder;
     147: ldc           #40                 // String , session expire timeout value is
     149: invokevirtual #29                 // Method java/lang/StringBuilder.append:(Ljava/lang/String;)Ljava/lang/StringBuilder;
     152: aload_0
     153: getfield      #14                 // Field sessionExpireMs:I
     156: invokevirtual #39                 // Method java/lang/StringBuilder.append:(I)Ljava/lang/StringBuilder;
     159: invokevirtual #33                 // Method java/lang/StringBuilder.toString:()Ljava/lang/String;
     162: invokeinterface #24,  5           // InterfaceMethod org/apache/dubbo/common/logger/ErrorTypeAwareLogger.warn:(Ljava/lang/String;Ljava/lang/String;Ljava/lang/String;Ljava/lang/String;)V
     167: aload_0
     168: getfield      #3                  // Field this$0:Lorg/apache/dubbo/remoting/zookeeper/curator/CuratorZookeeperClient;
     171: iconst_3
     172: invokestatic  #41                 // Method org/apache/dubbo/remoting/zookeeper/curator/CuratorZookeeperClient.access$800:(Lorg/apache/dubbo/remoting/zookeeper/curator/CuratorZookeeperClient;I)V
     175: goto          366
     178: aload_2
     179: getstatic     #42                 // Field org/apache/curator/framework/state/ConnectionState.CONNECTED:Lorg/apache/curator/framework/state/ConnectionState;
     182: if_acmpne     231
     185: aload_0
     186: lload_3
     187: putfield      #30                 // Field lastSessionId:J
     190: getstatic     #20                 // Field org/apache/dubbo/remoting/zookeeper/curator/CuratorZookeeperClient.logger:Lorg/apache/dubbo/common/logger/ErrorTypeAwareLogger;
     193: new           #26                 // class java/lang/StringBuilder
     196: dup
     197: invokespecial #27                 // Method java/lang/StringBuilder."<init>":()V
     200: ldc           #43                 // String Curator zookeeper client instance initiated successfully, session id is
     202: invokevirtual #29                 // Method java/lang/StringBuilder.append:(Ljava/lang/String;)Ljava/lang/StringBuilder;
     205: lload_3
     206: invokestatic  #31                 // Method java/lang/Long.toHexString:(J)Ljava/lang/String;
     209: invokevirtual #29                 // Method java/lang/StringBuilder.append:(Ljava/lang/String;)Ljava/lang/StringBuilder;
     212: invokevirtual #33                 // Method java/lang/StringBuilder.toString:()Ljava/lang/String;
     215: invokeinterface #44,  2           // InterfaceMethod org/apache/dubbo/common/logger/ErrorTypeAwareLogger.info:(Ljava/lang/String;)V
     220: aload_0
     221: getfield      #3                  // Field this$0:Lorg/apache/dubbo/remoting/zookeeper/curator/CuratorZookeeperClient;
     224: iconst_1
     225: invokestatic  #45                 // Method org/apache/dubbo/remoting/zookeeper/curator/CuratorZookeeperClient.access$900:(Lorg/apache/dubbo/remoting/zookeeper/curator/CuratorZookeeperClient;I)V
     228: goto          366
     231: aload_2
     232: getstatic     #46                 // Field org/apache/curator/framework/state/ConnectionState.RECONNECTED:Lorg/apache/curator/framework/state/ConnectionState;
     235: if_acmpne     366
     238: aload_0
     239: getfield      #30                 // Field lastSessionId:J
     242: lload_3
     243: lcmp
     244: ifne          302
     247: lload_3
     248: ldc2_w        #5                  // long -1l
     251: lcmp
     252: ifeq          302
     255: getstatic     #20                 // Field org/apache/dubbo/remoting/zookeeper/curator/CuratorZookeeperClient.logger:Lorg/apache/dubbo/common/logger/ErrorTypeAwareLogger;
     258: ldc           #21                 // String 1-35
     260: ldc           #22                 // String
     262: ldc           #22                 // String
     264: new           #26                 // class java/lang/StringBuilder
     267: dup
     268: invokespecial #27                 // Method java/lang/StringBuilder."<init>":()V
     271: ldc           #47                 // String Curator zookeeper connection recovered from connection lose, reuse the old session
     273: invokevirtual #29                 // Method java/lang/StringBuilder.append:(Ljava/lang/String;)Ljava/lang/StringBuilder;
     276: lload_3
     277: invokestatic  #31                 // Method java/lang/Long.toHexString:(J)Ljava/lang/String;
     280: invokevirtual #29                 // Method java/lang/StringBuilder.append:(Ljava/lang/String;)Ljava/lang/StringBuilder;
     283: invokevirtual #33                 // Method java/lang/StringBuilder.toString:()Ljava/lang/String;
     286: invokeinterface #24,  5           // InterfaceMethod org/apache/dubbo/common/logger/ErrorTypeAwareLogger.warn:(Ljava/lang/String;Ljava/lang/String;Ljava/lang/String;Ljava/lang/String;)V
     291: aload_0
     292: getfield      #3                  // Field this$0:Lorg/apache/dubbo/remoting/zookeeper/curator/CuratorZookeeperClient;
     295: iconst_2
     296: invokestatic  #48                 // Method org/apache/dubbo/remoting/zookeeper/curator/CuratorZookeeperClient.access$1000:(Lorg/apache/dubbo/remoting/zookeeper/curator/CuratorZookeeperClient;I)V
     299: goto          366
     302: getstatic     #20                 // Field org/apache/dubbo/remoting/zookeeper/curator/CuratorZookeeperClient.logger:Lorg/apache/dubbo/common/logger/ErrorTypeAwareLogger;
     305: ldc           #21                 // String 1-35
     307: ldc           #22                 // String
     309: ldc           #22                 // String
     311: new           #26                 // class java/lang/StringBuilder
     314: dup
     315: invokespecial #27                 // Method java/lang/StringBuilder."<init>":()V
     318: ldc           #49                 // String New session created after old session lost, old session
     320: invokevirtual #29                 // Method java/lang/StringBuilder.append:(Ljava/lang/String;)Ljava/lang/StringBuilder;
     323: aload_0
     324: getfield      #30                 // Field lastSessionId:J
     327: invokestatic  #31                 // Method java/lang/Long.toHexString:(J)Ljava/lang/String;
     330: invokevirtual #29                 // Method java/lang/StringBuilder.append:(Ljava/lang/String;)Ljava/lang/StringBuilder;
     333: ldc           #50                 // String , new session
     335: invokevirtual #29                 // Method java/lang/StringBuilder.append:(Ljava/lang/String;)Ljava/lang/StringBuilder;
     338: lload_3
     339: invokestatic  #31                 // Method java/lang/Long.toHexString:(J)Ljava/lang/String;
     342: invokevirtual #29                 // Method java/lang/StringBuilder.append:(Ljava/lang/String;)Ljava/lang/StringBuilder;
     345: invokevirtual #33                 // Method java/lang/StringBuilder.toString:()Ljava/lang/String;
     348: invokeinterface #24,  5           // InterfaceMethod org/apache/dubbo/common/logger/ErrorTypeAwareLogger.warn:(Ljava/lang/String;Ljava/lang/String;Ljava/lang/String;Ljava/lang/String;)V
     353: aload_0
     354: lload_3
     355: putfield      #30                 // Field lastSessionId:J
     358: aload_0
     359: getfield      #3                  // Field this$0:Lorg/apache/dubbo/remoting/zookeeper/curator/CuratorZookeeperClient;
     362: iconst_4
     363: invokestatic  #51                 // Method org/apache/dubbo/remoting/zookeeper/curator/CuratorZookeeperClient.access$1100:(Lorg/apache/dubbo/remoting/zookeeper/curator/CuratorZookeeperClient;I)V
     366: return
    Exception table:
       from    to  target type
           4    17    20   Class java/lang/Exception
}
