Compiled from "SwitchPayload.java"
public class jadx.api.plugins.input.insns.custom.impl.SwitchPayload implements jadx.api.plugins.input.insns.custom.ISwitchPayload {
  private final int size;

  private final int[] keys;

  private final int[] targets;

  public jadx.api.plugins.input.insns.custom.impl.SwitchPayload(int, int[], int[]);
    Code:
       0: aload_0
       1: invokespecial #1                  // Method java/lang/Object."<init>":()V
       4: aload_0
       5: iload_1
       6: putfield      #2                  // Field size:I
       9: aload_0
      10: aload_2
      11: putfield      #3                  // Field keys:[I
      14: aload_0
      15: aload_3
      16: putfield      #4                  // Field targets:[I
      19: return

  public int getSize();
    Code:
       0: aload_0
       1: getfield      #2                  // Field size:I
       4: ireturn

  public int[] getKeys();
    Code:
       0: aload_0
       1: getfield      #3                  // Field keys:[I
       4: areturn

  public int[] getTargets();
    Code:
       0: aload_0
       1: getfield      #4                  // Field targets:[I
       4: areturn
}
