Compiled from "MultipleServiceDiscovery.java"
public class org.apache.dubbo.registry.multiple.MultipleServiceDiscovery$SingleServiceInstancesChangedListener extends org.apache.dubbo.registry.client.event.listener.ServiceInstancesChangedListener {
  private final org.apache.dubbo.registry.multiple.MultipleServiceDiscovery$MultiServiceInstancesChangedListener multiListener;

  volatile org.apache.dubbo.registry.client.event.ServiceInstancesChangedEvent event;

  public org.apache.dubbo.registry.multiple.MultipleServiceDiscovery$SingleServiceInstancesChangedListener(java.util.Set<java.lang.String>, org.apache.dubbo.registry.client.ServiceDiscovery, org.apache.dubbo.registry.multiple.MultipleServiceDiscovery$MultiServiceInstancesChangedListener);
    Code:
       0: aload_0
       1: aload_1
       2: aload_2
       3: invokespecial #1                  // Method org/apache/dubbo/registry/client/event/listener/ServiceInstancesChangedListener."<init>":(Ljava/util/Set;Lorg/apache/dubbo/registry/client/ServiceDiscovery;)V
       6: aload_0
       7: aload_3
       8: putfield      #2                  // Field multiListener:Lorg/apache/dubbo/registry/multiple/MultipleServiceDiscovery$MultiServiceInstancesChangedListener;
      11: return

  public void onEvent(org.apache.dubbo.registry.client.event.ServiceInstancesChangedEvent);
    Code:
       0: aload_0
       1: aload_1
       2: putfield      #3                  // Field event:Lorg/apache/dubbo/registry/client/event/ServiceInstancesChangedEvent;
       5: aload_0
       6: getfield      #2                  // Field multiListener:Lorg/apache/dubbo/registry/multiple/MultipleServiceDiscovery$MultiServiceInstancesChangedListener;
       9: ifnull        20
      12: aload_0
      13: getfield      #2                  // Field multiListener:Lorg/apache/dubbo/registry/multiple/MultipleServiceDiscovery$MultiServiceInstancesChangedListener;
      16: aload_1
      17: invokevirtual #4                  // Method org/apache/dubbo/registry/multiple/MultipleServiceDiscovery$MultiServiceInstancesChangedListener.onEvent:(Lorg/apache/dubbo/registry/client/event/ServiceInstancesChangedEvent;)V
      20: return
}
