Compiled from "MultipleRegistryFactory.java"
public class org.apache.dubbo.registry.multiple.MultipleRegistryFactory extends org.apache.dubbo.registry.support.AbstractRegistryFactory {
  public org.apache.dubbo.registry.multiple.MultipleRegistryFactory();
    Code:
       0: aload_0
       1: invokespecial #1                  // Method org/apache/dubbo/registry/support/AbstractRegistryFactory."<init>":()V
       4: return

  protected org.apache.dubbo.registry.Registry createRegistry(org.apache.dubbo.common.URL);
    Code:
       0: new           #2                  // class org/apache/dubbo/registry/multiple/MultipleRegistry
       3: dup
       4: aload_1
       5: invokespecial #3                  // Method org/apache/dubbo/registry/multiple/MultipleRegistry."<init>":(Lorg/apache/dubbo/common/URL;)V
       8: areturn
}
