Compiled from "MultipleRegistry.java"
public class org.apache.dubbo.registry.multiple.MultipleRegistry$SingleNotifyListener implements org.apache.dubbo.registry.NotifyListener {
  org.apache.dubbo.registry.multiple.MultipleRegistry$MultipleNotifyListenerWrapper multipleNotifyListenerWrapper;

  org.apache.dubbo.registry.Registry registry;

  volatile java.util.List<org.apache.dubbo.common.URL> urlList;

  public org.apache.dubbo.registry.multiple.MultipleRegistry$SingleNotifyListener(org.apache.dubbo.registry.multiple.MultipleRegistry$MultipleNotifyListenerWrapper, org.apache.dubbo.registry.Registry);
    Code:
       0: aload_0
       1: invokespecial #1                  // Method java/lang/Object."<init>":()V
       4: aload_0
       5: aload_2
       6: putfield      #2                  // Field registry:Lorg/apache/dubbo/registry/Registry;
       9: aload_0
      10: aload_1
      11: putfield      #3                  // Field multipleNotifyListenerWrapper:Lorg/apache/dubbo/registry/multiple/MultipleRegistry$MultipleNotifyListenerWrapper;
      14: return

  public synchronized void notify(java.util.List<org.apache.dubbo.common.URL>);
    Code:
       0: aload_0
       1: aload_1
       2: putfield      #4                  // Field urlList:Ljava/util/List;
       5: aload_0
       6: getfield      #3                  // Field multipleNotifyListenerWrapper:Lorg/apache/dubbo/registry/multiple/MultipleRegistry$MultipleNotifyListenerWrapper;
       9: ifnull        19
      12: aload_0
      13: getfield      #3                  // Field multipleNotifyListenerWrapper:Lorg/apache/dubbo/registry/multiple/MultipleRegistry$MultipleNotifyListenerWrapper;
      16: invokevirtual #5                  // Method org/apache/dubbo/registry/multiple/MultipleRegistry$MultipleNotifyListenerWrapper.notifySourceListener:()V
      19: return

  public void destroy();
    Code:
       0: aload_0
       1: aconst_null
       2: putfield      #3                  // Field multipleNotifyListenerWrapper:Lorg/apache/dubbo/registry/multiple/MultipleRegistry$MultipleNotifyListenerWrapper;
       5: aload_0
       6: aconst_null
       7: putfield      #2                  // Field registry:Lorg/apache/dubbo/registry/Registry;
      10: return

  public java.util.List<org.apache.dubbo.common.URL> getUrlList();
    Code:
       0: aload_0
       1: getfield      #4                  // Field urlList:Ljava/util/List;
       4: areturn

  public org.apache.dubbo.registry.Registry getRegistry();
    Code:
       0: aload_0
       1: getfield      #2                  // Field registry:Lorg/apache/dubbo/registry/Registry;
       4: areturn
}
