Compiled from "MultipleServiceDiscoveryFactory.java"
public class org.apache.dubbo.registry.multiple.MultipleServiceDiscoveryFactory extends org.apache.dubbo.registry.client.AbstractServiceDiscoveryFactory {
  public org.apache.dubbo.registry.multiple.MultipleServiceDiscoveryFactory();
    Code:
       0: aload_0
       1: invokespecial #1                  // Method org/apache/dubbo/registry/client/AbstractServiceDiscoveryFactory."<init>":()V
       4: return

  protected org.apache.dubbo.registry.client.ServiceDiscovery createDiscovery(org.apache.dubbo.common.URL);
    Code:
       0: new           #2                  // class org/apache/dubbo/registry/multiple/MultipleServiceDiscovery
       3: dup
       4: aload_1
       5: invokespecial #3                  // Method org/apache/dubbo/registry/multiple/MultipleServiceDiscovery."<init>":(Lorg/apache/dubbo/common/URL;)V
       8: areturn
}
