Compiled from "MultipleRegistry.java"
public class org.apache.dubbo.registry.multiple.MultipleRegistry$MultipleNotifyListenerWrapper implements org.apache.dubbo.registry.NotifyListener {
  java.util.Map<org.apache.dubbo.common.URL, org.apache.dubbo.registry.multiple.MultipleRegistry$SingleNotifyListener> registryMap;

  org.apache.dubbo.registry.NotifyListener sourceNotifyListener;

  public org.apache.dubbo.registry.multiple.MultipleRegistry$MultipleNotifyListenerWrapper(org.apache.dubbo.registry.NotifyListener);
    Code:
       0: aload_0
       1: invokespecial #3                  // Method java/lang/Object."<init>":()V
       4: aload_0
       5: new           #4                  // class java/util/concurrent/ConcurrentHashMap
       8: dup
       9: iconst_4
      10: invokespecial #5                  // Method java/util/concurrent/ConcurrentHashMap."<init>":(I)V
      13: putfield      #6                  // Field registryMap:Ljava/util/Map;
      16: aload_0
      17: aload_1
      18: putfield      #7                  // Field sourceNotifyListener:Lorg/apache/dubbo/registry/NotifyListener;
      21: return

  public void putRegistryMap(org.apache.dubbo.common.URL, org.apache.dubbo.registry.multiple.MultipleRegistry$SingleNotifyListener);
    Code:
       0: aload_0
       1: getfield      #6                  // Field registryMap:Ljava/util/Map;
       4: aload_1
       5: aload_2
       6: invokeinterface #8,  3            // InterfaceMethod java/util/Map.put:(Ljava/lang/Object;Ljava/lang/Object;)Ljava/lang/Object;
      11: pop
      12: return

  public void destroy();
    Code:
       0: aload_0
       1: getfield      #6                  // Field registryMap:Ljava/util/Map;
       4: invokeinterface #9,  1            // InterfaceMethod java/util/Map.values:()Ljava/util/Collection;
       9: invokeinterface #10,  1           // InterfaceMethod java/util/Collection.iterator:()Ljava/util/Iterator;
      14: astore_1
      15: aload_1
      16: invokeinterface #11,  1           // InterfaceMethod java/util/Iterator.hasNext:()Z
      21: ifeq          45
      24: aload_1
      25: invokeinterface #12,  1           // InterfaceMethod java/util/Iterator.next:()Ljava/lang/Object;
      30: checkcast     #13                 // class org/apache/dubbo/registry/multiple/MultipleRegistry$SingleNotifyListener
      33: astore_2
      34: aload_2
      35: ifnull        42
      38: aload_2
      39: invokevirtual #14                 // Method org/apache/dubbo/registry/multiple/MultipleRegistry$SingleNotifyListener.destroy:()V
      42: goto          15
      45: aload_0
      46: getfield      #6                  // Field registryMap:Ljava/util/Map;
      49: invokeinterface #15,  1           // InterfaceMethod java/util/Map.clear:()V
      54: aload_0
      55: aconst_null
      56: putfield      #7                  // Field sourceNotifyListener:Lorg/apache/dubbo/registry/NotifyListener;
      59: return

  public synchronized void notifySourceListener();
    Code:
       0: new           #16                 // class java/util/ArrayList
       3: dup
       4: invokespecial #17                 // Method java/util/ArrayList."<init>":()V
       7: astore_1
       8: aconst_null
       9: astore_2
      10: aload_0
      11: getfield      #6                  // Field registryMap:Ljava/util/Map;
      14: invokeinterface #9,  1            // InterfaceMethod java/util/Map.values:()Ljava/util/Collection;
      19: invokeinterface #10,  1           // InterfaceMethod java/util/Collection.iterator:()Ljava/util/Iterator;
      24: astore_3
      25: aload_3
      26: invokeinterface #11,  1           // InterfaceMethod java/util/Iterator.hasNext:()Z
      31: ifeq          149
      34: aload_3
      35: invokeinterface #12,  1           // InterfaceMethod java/util/Iterator.next:()Ljava/lang/Object;
      40: checkcast     #13                 // class org/apache/dubbo/registry/multiple/MultipleRegistry$SingleNotifyListener
      43: astore        4
      45: aload         4
      47: invokevirtual #18                 // Method org/apache/dubbo/registry/multiple/MultipleRegistry$SingleNotifyListener.getUrlList:()Ljava/util/List;
      50: astore        5
      52: aload         5
      54: invokestatic  #19                 // Method org/apache/dubbo/common/utils/CollectionUtils.isEmpty:(Ljava/util/Collection;)Z
      57: ifeq          63
      60: goto          25
      63: aload         5
      65: invokeinterface #20,  1           // InterfaceMethod java/util/List.size:()I
      70: iconst_1
      71: if_icmpne     126
      74: aload         5
      76: iconst_0
      77: invokeinterface #21,  2           // InterfaceMethod java/util/List.get:(I)Ljava/lang/Object;
      82: ifnull        126
      85: ldc           #22                 // String empty
      87: aload         5
      89: iconst_0
      90: invokeinterface #21,  2           // InterfaceMethod java/util/List.get:(I)Ljava/lang/Object;
      95: checkcast     #23                 // class org/apache/dubbo/common/URL
      98: invokevirtual #24                 // Method org/apache/dubbo/common/URL.getProtocol:()Ljava/lang/String;
     101: invokevirtual #25                 // Method java/lang/String.equals:(Ljava/lang/Object;)Z
     104: ifeq          126
     107: aload_2
     108: ifnonnull     25
     111: aload         5
     113: iconst_0
     114: invokeinterface #21,  2           // InterfaceMethod java/util/List.get:(I)Ljava/lang/Object;
     119: checkcast     #23                 // class org/apache/dubbo/common/URL
     122: astore_2
     123: goto          25
     126: aload         4
     128: invokevirtual #26                 // Method org/apache/dubbo/registry/multiple/MultipleRegistry$SingleNotifyListener.getRegistry:()Lorg/apache/dubbo/registry/Registry;
     131: invokeinterface #27,  1           // InterfaceMethod org/apache/dubbo/registry/Registry.getUrl:()Lorg/apache/dubbo/common/URL;
     136: astore        6
     138: aload_1
     139: aload         5
     141: aload         6
     143: invokestatic  #28                 // Method aggregateRegistryUrls:(Ljava/util/List;Ljava/util/List;Lorg/apache/dubbo/common/URL;)V
     146: goto          25
     149: aload_2
     150: ifnull        183
     153: aload_1
     154: invokeinterface #29,  1           // InterfaceMethod java/util/List.isEmpty:()Z
     159: ifeq          183
     162: aload_1
     163: aload_2
     164: invokeinterface #30,  2           // InterfaceMethod java/util/List.add:(Ljava/lang/Object;)Z
     169: pop
     170: getstatic     #31                 // Field org/apache/dubbo/registry/multiple/MultipleRegistry.LOGGER:Lorg/apache/dubbo/common/logger/Logger;
     173: ldc           #32                 // String No provider after aggregation, notify url with EMPTY protocol.
     175: invokeinterface #33,  2           // InterfaceMethod org/apache/dubbo/common/logger/Logger.info:(Ljava/lang/String;)V
     180: goto          215
     183: getstatic     #31                 // Field org/apache/dubbo/registry/multiple/MultipleRegistry.LOGGER:Lorg/apache/dubbo/common/logger/Logger;
     186: new           #34                 // class java/lang/StringBuilder
     189: dup
     190: invokespecial #35                 // Method java/lang/StringBuilder."<init>":()V
     193: ldc           #36                 // String Aggregated provider url size
     195: invokevirtual #37                 // Method java/lang/StringBuilder.append:(Ljava/lang/String;)Ljava/lang/StringBuilder;
     198: aload_1
     199: invokeinterface #20,  1           // InterfaceMethod java/util/List.size:()I
     204: invokevirtual #38                 // Method java/lang/StringBuilder.append:(I)Ljava/lang/StringBuilder;
     207: invokevirtual #39                 // Method java/lang/StringBuilder.toString:()Ljava/lang/String;
     210: invokeinterface #33,  2           // InterfaceMethod org/apache/dubbo/common/logger/Logger.info:(Ljava/lang/String;)V
     215: aload_0
     216: aload_1
     217: invokevirtual #40                 // Method notify:(Ljava/util/List;)V
     220: return

  public static void aggregateRegistryUrls(java.util.List<org.apache.dubbo.common.URL>, java.util.List<org.apache.dubbo.common.URL>, org.apache.dubbo.common.URL);
    Code:
       0: aload_2
       1: ldc           #41                 // String attachments
       3: invokevirtual #42                 // Method org/apache/dubbo/common/URL.getParameter:(Ljava/lang/String;)Ljava/lang/String;
       6: astore_3
       7: aload_3
       8: invokestatic  #43                 // Method org/apache/dubbo/common/utils/StringUtils.isNotBlank:(Ljava/lang/CharSequence;)Z
      11: ifeq          258
      14: getstatic     #31                 // Field org/apache/dubbo/registry/multiple/MultipleRegistry.LOGGER:Lorg/apache/dubbo/common/logger/Logger;
      17: new           #34                 // class java/lang/StringBuilder
      20: dup
      21: invokespecial #35                 // Method java/lang/StringBuilder."<init>":()V
      24: ldc           #44                 // String Registry attachments
      26: invokevirtual #37                 // Method java/lang/StringBuilder.append:(Ljava/lang/String;)Ljava/lang/StringBuilder;
      29: aload_3
      30: invokevirtual #37                 // Method java/lang/StringBuilder.append:(Ljava/lang/String;)Ljava/lang/StringBuilder;
      33: ldc           #45                 // String  found, will append to provider urls, urls size
      35: invokevirtual #37                 // Method java/lang/StringBuilder.append:(Ljava/lang/String;)Ljava/lang/StringBuilder;
      38: aload_1
      39: invokeinterface #20,  1           // InterfaceMethod java/util/List.size:()I
      44: invokevirtual #38                 // Method java/lang/StringBuilder.append:(I)Ljava/lang/StringBuilder;
      47: invokevirtual #39                 // Method java/lang/StringBuilder.toString:()Ljava/lang/String;
      50: invokeinterface #33,  2           // InterfaceMethod org/apache/dubbo/common/logger/Logger.info:(Ljava/lang/String;)V
      55: aload_3
      56: ldc           #46                 // String ,
      58: invokevirtual #47                 // Method java/lang/String.split:(Ljava/lang/String;)[Ljava/lang/String;
      61: astore        4
      63: new           #48                 // class java/util/HashMap
      66: dup
      67: aload         4
      69: arraylength
      70: invokespecial #49                 // Method java/util/HashMap."<init>":(I)V
      73: astore        5
      75: aload         4
      77: astore        6
      79: aload         6
      81: arraylength
      82: istore        7
      84: iconst_0
      85: istore        8
      87: iload         8
      89: iload         7
      91: if_icmpge     147
      94: aload         6
      96: iload         8
      98: aaload
      99: astore        9
     101: aload         9
     103: ldc           #50                 // String =
     105: invokevirtual #47                 // Method java/lang/String.split:(Ljava/lang/String;)[Ljava/lang/String;
     108: astore        10
     110: aload         10
     112: arraylength
     113: iconst_2
     114: if_icmpne     141
     117: aload         10
     119: iconst_0
     120: aaload
     121: astore        11
     123: aload         10
     125: iconst_1
     126: aaload
     127: astore        12
     129: aload         5
     131: aload         11
     133: aload         12
     135: invokeinterface #8,  3            // InterfaceMethod java/util/Map.put:(Ljava/lang/Object;Ljava/lang/Object;)Ljava/lang/Object;
     140: pop
     141: iinc          8, 1
     144: goto          87
     147: aload_1
     148: invokeinterface #51,  1           // InterfaceMethod java/util/List.iterator:()Ljava/util/Iterator;
     153: astore        6
     155: aload         6
     157: invokeinterface #11,  1           // InterfaceMethod java/util/Iterator.hasNext:()Z
     162: ifeq          255
     165: aload         6
     167: invokeinterface #12,  1           // InterfaceMethod java/util/Iterator.next:()Ljava/lang/Object;
     172: checkcast     #23                 // class org/apache/dubbo/common/URL
     175: astore        7
     177: aload         5
     179: invokeinterface #52,  1           // InterfaceMethod java/util/Map.entrySet:()Ljava/util/Set;
     184: invokeinterface #53,  1           // InterfaceMethod java/util/Set.iterator:()Ljava/util/Iterator;
     189: astore        8
     191: aload         8
     193: invokeinterface #11,  1           // InterfaceMethod java/util/Iterator.hasNext:()Z
     198: ifeq          243
     201: aload         8
     203: invokeinterface #12,  1           // InterfaceMethod java/util/Iterator.next:()Ljava/lang/Object;
     208: checkcast     #54                 // class java/util/Map$Entry
     211: astore        9
     213: aload         7
     215: aload         9
     217: invokeinterface #55,  1           // InterfaceMethod java/util/Map$Entry.getKey:()Ljava/lang/Object;
     222: checkcast     #56                 // class java/lang/String
     225: aload         9
     227: invokeinterface #57,  1           // InterfaceMethod java/util/Map$Entry.getValue:()Ljava/lang/Object;
     232: checkcast     #56                 // class java/lang/String
     235: invokevirtual #58                 // Method org/apache/dubbo/common/URL.addParameterIfAbsent:(Ljava/lang/String;Ljava/lang/String;)Lorg/apache/dubbo/common/URL;
     238: astore        7
     240: goto          191
     243: aload_0
     244: aload         7
     246: invokeinterface #30,  2           // InterfaceMethod java/util/List.add:(Ljava/lang/Object;)Z
     251: pop
     252: goto          155
     255: goto          307
     258: getstatic     #31                 // Field org/apache/dubbo/registry/multiple/MultipleRegistry.LOGGER:Lorg/apache/dubbo/common/logger/Logger;
     261: new           #34                 // class java/lang/StringBuilder
     264: dup
     265: invokespecial #35                 // Method java/lang/StringBuilder."<init>":()V
     268: ldc           #59                 // String Single registry
     270: invokevirtual #37                 // Method java/lang/StringBuilder.append:(Ljava/lang/String;)Ljava/lang/StringBuilder;
     273: aload_2
     274: invokevirtual #60                 // Method java/lang/StringBuilder.append:(Ljava/lang/Object;)Ljava/lang/StringBuilder;
     277: ldc           #61                 // String  has url size
     279: invokevirtual #37                 // Method java/lang/StringBuilder.append:(Ljava/lang/String;)Ljava/lang/StringBuilder;
     282: aload_1
     283: invokeinterface #20,  1           // InterfaceMethod java/util/List.size:()I
     288: invokevirtual #38                 // Method java/lang/StringBuilder.append:(I)Ljava/lang/StringBuilder;
     291: invokevirtual #39                 // Method java/lang/StringBuilder.toString:()Ljava/lang/String;
     294: invokeinterface #33,  2           // InterfaceMethod org/apache/dubbo/common/logger/Logger.info:(Ljava/lang/String;)V
     299: aload_0
     300: aload_1
     301: invokeinterface #62,  2           // InterfaceMethod java/util/List.addAll:(Ljava/util/Collection;)Z
     306: pop
     307: return

  public void notify(java.util.List<org.apache.dubbo.common.URL>);
    Code:
       0: aload_0
       1: getfield      #7                  // Field sourceNotifyListener:Lorg/apache/dubbo/registry/NotifyListener;
       4: aload_1
       5: invokeinterface #63,  2           // InterfaceMethod org/apache/dubbo/registry/NotifyListener.notify:(Ljava/util/List;)V
      10: return

  public java.util.Map<org.apache.dubbo.common.URL, org.apache.dubbo.registry.multiple.MultipleRegistry$SingleNotifyListener> getRegistryMap();
    Code:
       0: aload_0
       1: getfield      #6                  // Field registryMap:Ljava/util/Map;
       4: areturn
}
