Compiled from "ProtobufTypeBuilder.java"
public class org.apache.dubbo.metadata.definition.protobuf.ProtobufTypeBuilder implements org.apache.dubbo.metadata.definition.builder.TypeBuilder,org.apache.dubbo.common.lang.Prioritized {
  private final org.apache.dubbo.common.logger.Logger logger;

  private static final java.util.regex.Pattern MAP_PATTERN;

  private static final java.util.regex.Pattern LIST_PATTERN;

  private static final java.util.List<java.lang.String> LIST;

  private static java.lang.reflect.Type STRING_LIST_TYPE;

  public org.apache.dubbo.metadata.definition.protobuf.ProtobufTypeBuilder();
    Code:
       0: aload_0
       1: invokespecial #1                  // Method java/lang/Object."<init>":()V
       4: aload_0
       5: aload_0
       6: invokevirtual #2                  // Method java/lang/Object.getClass:()Ljava/lang/Class;
       9: invokestatic  #3                  // Method org/apache/dubbo/common/logger/LoggerFactory.getLogger:(Ljava/lang/Class;)Lorg/apache/dubbo/common/logger/Logger;
      12: putfield      #4                  // Field logger:Lorg/apache/dubbo/common/logger/Logger;
      15: return

  public int getPriority();
    Code:
       0: iconst_m1
       1: ireturn

  public boolean accept(java.lang.Class<?>);
    Code:
       0: aload_1
       1: ifnonnull     6
       4: iconst_0
       5: ireturn
       6: ldc           #5                  // class com/google/protobuf/GeneratedMessageV3
       8: aload_1
       9: invokevirtual #6                  // Method java/lang/Class.isAssignableFrom:(Ljava/lang/Class;)Z
      12: ireturn

  public org.apache.dubbo.metadata.definition.model.TypeDefinition build(java.lang.reflect.Type, java.lang.Class<?>, java.util.Map<java.lang.String, org.apache.dubbo.metadata.definition.model.TypeDefinition>);
    Code:
       0: aload_2
       1: invokevirtual #7                  // Method java/lang/Class.getCanonicalName:()Ljava/lang/String;
       4: astore        4
       6: aload_3
       7: aload         4
       9: invokeinterface #8,  2            // InterfaceMethod java/util/Map.get:(Ljava/lang/Object;)Ljava/lang/Object;
      14: checkcast     #9                  // class org/apache/dubbo/metadata/definition/model/TypeDefinition
      17: astore        5
      19: aload         5
      21: ifnull        27
      24: aload         5
      26: areturn
      27: aload_0
      28: aload_2
      29: invokespecial #10                 // Method getMessageBuilder:(Ljava/lang/Class;)Lcom/google/protobuf/GeneratedMessageV3$Builder;
      32: astore        6
      34: aload_0
      35: aload_2
      36: aload         6
      38: aload_3
      39: invokespecial #11                 // Method buildProtobufTypeDefinition:(Ljava/lang/Class;Lcom/google/protobuf/GeneratedMessageV3$Builder;Ljava/util/Map;)Lorg/apache/dubbo/metadata/definition/model/TypeDefinition;
      42: astore        5
      44: aload_3
      45: aload         4
      47: aload         5
      49: invokeinterface #12,  3           // InterfaceMethod java/util/Map.put:(Ljava/lang/Object;Ljava/lang/Object;)Ljava/lang/Object;
      54: pop
      55: goto          73
      58: astore        6
      60: aload_0
      61: getfield      #4                  // Field logger:Lorg/apache/dubbo/common/logger/Logger;
      64: ldc           #14                 // String TypeDefinition build failed.
      66: aload         6
      68: invokeinterface #15,  3           // InterfaceMethod org/apache/dubbo/common/logger/Logger.info:(Ljava/lang/String;Ljava/lang/Throwable;)V
      73: aload         5
      75: areturn
    Exception table:
       from    to  target type
          27    55    58   Class java/lang/Exception

  private com.google.protobuf.GeneratedMessageV3$Builder getMessageBuilder(java.lang.Class<?>) throws java.lang.Exception;
    Code:
       0: aload_1
       1: ldc           #16                 // String newBuilder
       3: iconst_0
       4: anewarray     #17                 // class java/lang/Class
       7: invokevirtual #18                 // Method java/lang/Class.getMethod:(Ljava/lang/String;[Ljava/lang/Class;)Ljava/lang/reflect/Method;
      10: astore_2
      11: aload_2
      12: aconst_null
      13: aconst_null
      14: invokevirtual #19                 // Method java/lang/reflect/Method.invoke:(Ljava/lang/Object;[Ljava/lang/Object;)Ljava/lang/Object;
      17: checkcast     #20                 // class com/google/protobuf/GeneratedMessageV3$Builder
      20: areturn

  private org.apache.dubbo.metadata.definition.model.TypeDefinition buildProtobufTypeDefinition(java.lang.Class<?>, com.google.protobuf.GeneratedMessageV3$Builder, java.util.Map<java.lang.String, org.apache.dubbo.metadata.definition.model.TypeDefinition>);
    Code:
       0: aload_1
       1: invokevirtual #7                  // Method java/lang/Class.getCanonicalName:()Ljava/lang/String;
       4: astore        4
       6: new           #9                  // class org/apache/dubbo/metadata/definition/model/TypeDefinition
       9: dup
      10: aload         4
      12: invokespecial #21                 // Method org/apache/dubbo/metadata/definition/model/TypeDefinition."<init>":(Ljava/lang/String;)V
      15: astore        5
      17: aload_2
      18: ifnonnull     24
      21: aload         5
      23: areturn
      24: new           #22                 // class java/util/HashMap
      27: dup
      28: invokespecial #23                 // Method java/util/HashMap."<init>":()V
      31: astore        6
      33: aload_2
      34: invokevirtual #2                  // Method java/lang/Object.getClass:()Ljava/lang/Class;
      37: invokevirtual #24                 // Method java/lang/Class.getDeclaredMethods:()[Ljava/lang/reflect/Method;
      40: astore        7
      42: aload         7
      44: astore        8
      46: aload         8
      48: arraylength
      49: istore        9
      51: iconst_0
      52: istore        10
      54: iload         10
      56: iload         9
      58: if_icmpge     301
      61: aload         8
      63: iload         10
      65: aaload
      66: astore        11
      68: aload         11
      70: invokevirtual #25                 // Method java/lang/reflect/Method.getName:()Ljava/lang/String;
      73: astore        12
      75: aload_0
      76: aload         11
      78: invokespecial #26                 // Method isSimplePropertySettingMethod:(Ljava/lang/reflect/Method;)Z
      81: ifeq          126
      84: aload         11
      86: invokevirtual #27                 // Method java/lang/reflect/Method.getGenericParameterTypes:()[Ljava/lang/reflect/Type;
      89: iconst_0
      90: aaload
      91: aload         11
      93: invokevirtual #28                 // Method java/lang/reflect/Method.getParameterTypes:()[Ljava/lang/Class;
      96: iconst_0
      97: aaload
      98: aload_3
      99: invokestatic  #29                 // Method org/apache/dubbo/metadata/definition/TypeDefinitionBuilder.build:(Ljava/lang/reflect/Type;Ljava/lang/Class;Ljava/util/Map;)Lorg/apache/dubbo/metadata/definition/model/TypeDefinition;
     102: astore        13
     104: aload         6
     106: aload_0
     107: aload         12
     109: invokespecial #30                 // Method generateSimpleFiledName:(Ljava/lang/String;)Ljava/lang/String;
     112: aload         13
     114: invokevirtual #31                 // Method org/apache/dubbo/metadata/definition/model/TypeDefinition.getType:()Ljava/lang/String;
     117: invokeinterface #12,  3           // InterfaceMethod java/util/Map.put:(Ljava/lang/Object;Ljava/lang/Object;)Ljava/lang/Object;
     122: pop
     123: goto          295
     126: aload_0
     127: aload         11
     129: invokespecial #32                 // Method isMapPropertySettingMethod:(Ljava/lang/reflect/Method;)Z
     132: ifeq          196
     135: aload         11
     137: invokevirtual #27                 // Method java/lang/reflect/Method.getGenericParameterTypes:()[Ljava/lang/reflect/Type;
     140: iconst_0
     141: aaload
     142: astore        13
     144: aload_0
     145: aload         12
     147: invokespecial #33                 // Method generateMapFieldName:(Ljava/lang/String;)Ljava/lang/String;
     150: astore        14
     152: aload_0
     153: aload         14
     155: aload         13
     157: invokevirtual #34                 // Method java/lang/Object.toString:()Ljava/lang/String;
     160: invokespecial #35                 // Method validateMapType:(Ljava/lang/String;Ljava/lang/String;)V
     163: aload         13
     165: aload         11
     167: invokevirtual #28                 // Method java/lang/reflect/Method.getParameterTypes:()[Ljava/lang/Class;
     170: iconst_0
     171: aaload
     172: aload_3
     173: invokestatic  #29                 // Method org/apache/dubbo/metadata/definition/TypeDefinitionBuilder.build:(Ljava/lang/reflect/Type;Ljava/lang/Class;Ljava/util/Map;)Lorg/apache/dubbo/metadata/definition/model/TypeDefinition;
     176: astore        15
     178: aload         6
     180: aload         14
     182: aload         15
     184: invokevirtual #31                 // Method org/apache/dubbo/metadata/definition/model/TypeDefinition.getType:()Ljava/lang/String;
     187: invokeinterface #12,  3           // InterfaceMethod java/util/Map.put:(Ljava/lang/Object;Ljava/lang/Object;)Ljava/lang/Object;
     192: pop
     193: goto          295
     196: aload_0
     197: aload         11
     199: invokevirtual #36                 // Method isListPropertyGettingMethod:(Ljava/lang/reflect/Method;)Z
     202: ifeq          295
     205: aload         11
     207: invokevirtual #37                 // Method java/lang/reflect/Method.getGenericReturnType:()Ljava/lang/reflect/Type;
     210: astore        13
     212: aload_0
     213: aload         12
     215: invokespecial #38                 // Method generateListFieldName:(Ljava/lang/String;)Ljava/lang/String;
     218: astore        14
     220: ldc           #39                 // class com/google/protobuf/ProtocolStringList
     222: aload         11
     224: invokevirtual #40                 // Method java/lang/reflect/Method.getReturnType:()Ljava/lang/Class;
     227: invokevirtual #6                  // Method java/lang/Class.isAssignableFrom:(Ljava/lang/Class;)Z
     230: ifeq          247
     233: getstatic     #41                 // Field STRING_LIST_TYPE:Ljava/lang/reflect/Type;
     236: ldc           #42                 // class java/util/List
     238: aload_3
     239: invokestatic  #29                 // Method org/apache/dubbo/metadata/definition/TypeDefinitionBuilder.build:(Ljava/lang/reflect/Type;Ljava/lang/Class;Ljava/util/Map;)Lorg/apache/dubbo/metadata/definition/model/TypeDefinition;
     242: astore        15
     244: goto          280
     247: getstatic     #43                 // Field LIST_PATTERN:Ljava/util/regex/Pattern;
     250: aload         13
     252: invokevirtual #34                 // Method java/lang/Object.toString:()Ljava/lang/String;
     255: invokevirtual #44                 // Method java/util/regex/Pattern.matcher:(Ljava/lang/CharSequence;)Ljava/util/regex/Matcher;
     258: invokevirtual #45                 // Method java/util/regex/Matcher.matches:()Z
     261: ifne          267
     264: goto          295
     267: aload         13
     269: aload         11
     271: invokevirtual #40                 // Method java/lang/reflect/Method.getReturnType:()Ljava/lang/Class;
     274: aload_3
     275: invokestatic  #29                 // Method org/apache/dubbo/metadata/definition/TypeDefinitionBuilder.build:(Ljava/lang/reflect/Type;Ljava/lang/Class;Ljava/util/Map;)Lorg/apache/dubbo/metadata/definition/model/TypeDefinition;
     278: astore        15
     280: aload         6
     282: aload         14
     284: aload         15
     286: invokevirtual #31                 // Method org/apache/dubbo/metadata/definition/model/TypeDefinition.getType:()Ljava/lang/String;
     289: invokeinterface #12,  3           // InterfaceMethod java/util/Map.put:(Ljava/lang/Object;Ljava/lang/Object;)Ljava/lang/Object;
     294: pop
     295: iinc          10, 1
     298: goto          54
     301: aload         5
     303: aload         6
     305: invokevirtual #46                 // Method org/apache/dubbo/metadata/definition/model/TypeDefinition.setProperties:(Ljava/util/Map;)V
     308: aload         5
     310: areturn

  private void validateMapType(java.lang.String, java.lang.String);
    Code:
       0: getstatic     #47                 // Field MAP_PATTERN:Ljava/util/regex/Pattern;
       3: aload_2
       4: invokevirtual #44                 // Method java/util/regex/Pattern.matcher:(Ljava/lang/CharSequence;)Ljava/util/regex/Matcher;
       7: astore_3
       8: aload_3
       9: invokevirtual #45                 // Method java/util/regex/Matcher.matches:()Z
      12: ifne          70
      15: new           #48                 // class java/lang/IllegalArgumentException
      18: dup
      19: new           #49                 // class java/lang/StringBuilder
      22: dup
      23: invokespecial #50                 // Method java/lang/StringBuilder."<init>":()V
      26: ldc           #51                 // String Map protobuf property
      28: invokevirtual #52                 // Method java/lang/StringBuilder.append:(Ljava/lang/String;)Ljava/lang/StringBuilder;
      31: aload_1
      32: invokevirtual #52                 // Method java/lang/StringBuilder.append:(Ljava/lang/String;)Ljava/lang/StringBuilder;
      35: ldc           #53                 // String of Type
      37: invokevirtual #52                 // Method java/lang/StringBuilder.append:(Ljava/lang/String;)Ljava/lang/StringBuilder;
      40: aload_2
      41: invokevirtual #52                 // Method java/lang/StringBuilder.append:(Ljava/lang/String;)Ljava/lang/StringBuilder;
      44: ldc           #54                 // String  can\'t be parsed.The type name should mathch[
      46: invokevirtual #52                 // Method java/lang/StringBuilder.append:(Ljava/lang/String;)Ljava/lang/StringBuilder;
      49: getstatic     #47                 // Field MAP_PATTERN:Ljava/util/regex/Pattern;
      52: invokevirtual #55                 // Method java/util/regex/Pattern.toString:()Ljava/lang/String;
      55: invokevirtual #52                 // Method java/lang/StringBuilder.append:(Ljava/lang/String;)Ljava/lang/StringBuilder;
      58: ldc           #56                 // String ].
      60: invokevirtual #52                 // Method java/lang/StringBuilder.append:(Ljava/lang/String;)Ljava/lang/StringBuilder;
      63: invokevirtual #57                 // Method java/lang/StringBuilder.toString:()Ljava/lang/String;
      66: invokespecial #58                 // Method java/lang/IllegalArgumentException."<init>":(Ljava/lang/String;)V
      69: athrow
      70: return

  private java.lang.String generateSimpleFiledName(java.lang.String);
    Code:
       0: aload_0
       1: aload_1
       2: iconst_3
       3: invokevirtual #59                 // Method java/lang/String.substring:(I)Ljava/lang/String;
       6: invokespecial #60                 // Method toCamelCase:(Ljava/lang/String;)Ljava/lang/String;
       9: areturn

  private java.lang.String generateMapFieldName(java.lang.String);
    Code:
       0: aload_0
       1: aload_1
       2: bipush        6
       4: invokevirtual #59                 // Method java/lang/String.substring:(I)Ljava/lang/String;
       7: invokespecial #60                 // Method toCamelCase:(Ljava/lang/String;)Ljava/lang/String;
      10: areturn

  private java.lang.String generateListFieldName(java.lang.String);
    Code:
       0: aload_0
       1: aload_1
       2: iconst_3
       3: aload_1
       4: invokevirtual #61                 // Method java/lang/String.length:()I
       7: iconst_4
       8: isub
       9: invokevirtual #62                 // Method java/lang/String.substring:(II)Ljava/lang/String;
      12: invokespecial #60                 // Method toCamelCase:(Ljava/lang/String;)Ljava/lang/String;
      15: areturn

  private java.lang.String toCamelCase(java.lang.String);
    Code:
       0: aload_1
       1: invokevirtual #63                 // Method java/lang/String.toCharArray:()[C
       4: astore_2
       5: aload_2
       6: iconst_0
       7: aload_2
       8: iconst_0
       9: caload
      10: invokestatic  #64                 // Method java/lang/Character.toLowerCase:(C)C
      13: castore
      14: new           #65                 // class java/lang/String
      17: dup
      18: aload_2
      19: invokespecial #66                 // Method java/lang/String."<init>":([C)V
      22: areturn

  private boolean isSimplePropertySettingMethod(java.lang.reflect.Method);
    Code:
       0: aload_1
       1: invokevirtual #25                 // Method java/lang/reflect/Method.getName:()Ljava/lang/String;
       4: astore_2
       5: aload_1
       6: invokevirtual #28                 // Method java/lang/reflect/Method.getParameterTypes:()[Ljava/lang/Class;
       9: astore_3
      10: aload_2
      11: ldc           #67                 // String set
      13: invokevirtual #68                 // Method java/lang/String.startsWith:(Ljava/lang/String;)Z
      16: ifeq          25
      19: aload_3
      20: arraylength
      21: iconst_1
      22: if_icmpeq     27
      25: iconst_0
      26: ireturn
      27: ldc           #69                 // String setField
      29: aload_2
      30: invokevirtual #70                 // Method java/lang/String.equals:(Ljava/lang/Object;)Z
      33: ifeq          47
      36: aload_3
      37: iconst_0
      38: aaload
      39: ldc           #71                 // class com/google/protobuf/Descriptors$FieldDescriptor
      41: invokevirtual #72                 // Method java/lang/Object.equals:(Ljava/lang/Object;)Z
      44: ifne          87
      47: ldc           #73                 // String setUnknownFields
      49: aload_2
      50: invokevirtual #70                 // Method java/lang/String.equals:(Ljava/lang/Object;)Z
      53: ifeq          67
      56: aload_3
      57: iconst_0
      58: aaload
      59: ldc           #74                 // class com/google/protobuf/UnknownFieldSet
      61: invokevirtual #72                 // Method java/lang/Object.equals:(Ljava/lang/Object;)Z
      64: ifne          87
      67: ldc           #75                 // String setRepeatedField
      69: aload_2
      70: invokevirtual #70                 // Method java/lang/String.equals:(Ljava/lang/Object;)Z
      73: ifeq          89
      76: aload_3
      77: iconst_0
      78: aaload
      79: ldc           #71                 // class com/google/protobuf/Descriptors$FieldDescriptor
      81: invokevirtual #72                 // Method java/lang/Object.equals:(Ljava/lang/Object;)Z
      84: ifeq          89
      87: iconst_0
      88: ireturn
      89: aload_2
      90: ldc           #76                 // String Bytes
      92: invokevirtual #77                 // Method java/lang/String.endsWith:(Ljava/lang/String;)Z
      95: ifeq          111
      98: aload_3
      99: iconst_0
     100: aaload
     101: ldc           #78                 // class com/google/protobuf/ByteString
     103: invokevirtual #72                 // Method java/lang/Object.equals:(Ljava/lang/Object;)Z
     106: ifeq          111
     109: iconst_0
     110: ireturn
     111: ldc           #20                 // class com/google/protobuf/GeneratedMessageV3$Builder
     113: aload_3
     114: iconst_0
     115: aaload
     116: invokevirtual #6                  // Method java/lang/Class.isAssignableFrom:(Ljava/lang/Class;)Z
     119: ifeq          124
     122: iconst_0
     123: ireturn
     124: aload_2
     125: ldc           #79                 // String Value
     127: invokevirtual #77                 // Method java/lang/String.endsWith:(Ljava/lang/String;)Z
     130: ifeq          144
     133: aload_3
     134: iconst_0
     135: aaload
     136: getstatic     #80                 // Field java/lang/Integer.TYPE:Ljava/lang/Class;
     139: if_acmpne     144
     142: iconst_0
     143: ireturn
     144: iconst_1
     145: ireturn

  boolean isListPropertyGettingMethod(java.lang.reflect.Method);
    Code:
       0: aload_1
       1: invokevirtual #25                 // Method java/lang/reflect/Method.getName:()Ljava/lang/String;
       4: astore_2
       5: aload_1
       6: invokevirtual #40                 // Method java/lang/reflect/Method.getReturnType:()Ljava/lang/Class;
       9: astore_3
      10: aload_2
      11: ldc           #81                 // String get
      13: invokevirtual #68                 // Method java/lang/String.startsWith:(Ljava/lang/String;)Z
      16: ifeq          28
      19: aload_2
      20: ldc           #82                 // String List
      22: invokevirtual #77                 // Method java/lang/String.endsWith:(Ljava/lang/String;)Z
      25: ifne          30
      28: iconst_0
      29: ireturn
      30: aload_2
      31: ldc           #83                 // String BuilderList
      33: invokevirtual #77                 // Method java/lang/String.endsWith:(Ljava/lang/String;)Z
      36: ifeq          41
      39: iconst_0
      40: ireturn
      41: ldc           #42                 // class java/util/List
      43: aload_3
      44: invokevirtual #6                  // Method java/lang/Class.isAssignableFrom:(Ljava/lang/Class;)Z
      47: ifne          52
      50: iconst_0
      51: ireturn
      52: iconst_1
      53: ireturn

  private boolean isMapPropertySettingMethod(java.lang.reflect.Method);
    Code:
       0: aload_1
       1: invokevirtual #25                 // Method java/lang/reflect/Method.getName:()Ljava/lang/String;
       4: astore_2
       5: aload_1
       6: invokevirtual #28                 // Method java/lang/reflect/Method.getParameterTypes:()[Ljava/lang/Class;
       9: astore_3
      10: aload_2
      11: ldc           #84                 // String putAll
      13: invokevirtual #68                 // Method java/lang/String.startsWith:(Ljava/lang/String;)Z
      16: ifeq          38
      19: aload_3
      20: arraylength
      21: iconst_1
      22: if_icmpne     38
      25: ldc           #85                 // class java/util/Map
      27: aload_3
      28: iconst_0
      29: aaload
      30: invokevirtual #6                  // Method java/lang/Class.isAssignableFrom:(Ljava/lang/Class;)Z
      33: ifeq          38
      36: iconst_1
      37: ireturn
      38: iconst_0
      39: ireturn

  static {};
    Code:
       0: ldc           #86                 // String ^java\\.util\\.Map<(\\S+), (\\S+)>$
       2: invokestatic  #87                 // Method java/util/regex/Pattern.compile:(Ljava/lang/String;)Ljava/util/regex/Pattern;
       5: putstatic     #47                 // Field MAP_PATTERN:Ljava/util/regex/Pattern;
       8: ldc           #88                 // String ^java\\.util\\.List<(\\S+)>$
      10: invokestatic  #87                 // Method java/util/regex/Pattern.compile:(Ljava/lang/String;)Ljava/util/regex/Pattern;
      13: putstatic     #43                 // Field LIST_PATTERN:Ljava/util/regex/Pattern;
      16: aconst_null
      17: putstatic     #89                 // Field LIST:Ljava/util/List;
      20: ldc           #90                 // class org/apache/dubbo/metadata/definition/protobuf/ProtobufTypeBuilder
      22: ldc           #91                 // String LIST
      24: invokevirtual #92                 // Method java/lang/Class.getDeclaredField:(Ljava/lang/String;)Ljava/lang/reflect/Field;
      27: invokevirtual #93                 // Method java/lang/reflect/Field.getGenericType:()Ljava/lang/reflect/Type;
      30: putstatic     #41                 // Field STRING_LIST_TYPE:Ljava/lang/reflect/Type;
      33: goto          37
      36: astore_0
      37: return
    Exception table:
       from    to  target type
          20    33    36   Class java/lang/NoSuchFieldException
}
