Compiled from "AddMustAttachmentIntercept.java"
public class org.apache.dubbo.rpc.protocol.rest.annotation.consumer.inercept.AddMustAttachmentIntercept implements org.apache.dubbo.rpc.protocol.rest.annotation.consumer.HttpConnectionPreBuildIntercept {
  public org.apache.dubbo.rpc.protocol.rest.annotation.consumer.inercept.AddMustAttachmentIntercept();
    Code:
       0: aload_0
       1: invokespecial #1                  // Method java/lang/Object."<init>":()V
       4: return

  public void intercept(org.apache.dubbo.rpc.protocol.rest.annotation.consumer.HttpConnectionCreateContext);
    Code:
       0: aload_1
       1: invokevirtual #2                  // Method org/apache/dubbo/rpc/protocol/rest/annotation/consumer/HttpConnectionCreateContext.getRequestTemplate:()Lorg/apache/dubbo/remoting/http/RequestTemplate;
       4: astore_2
       5: aload_1
       6: invokevirtual #3                  // Method org/apache/dubbo/rpc/protocol/rest/annotation/consumer/HttpConnectionCreateContext.getServiceRestMetadata:()Lorg/apache/dubbo/metadata/rest/ServiceRestMetadata;
       9: astore_3
      10: aload_2
      11: getstatic     #4                  // Field org/apache/dubbo/rpc/protocol/rest/RestHeaderEnum.GROUP:Lorg/apache/dubbo/rpc/protocol/rest/RestHeaderEnum;
      14: invokevirtual #5                  // Method org/apache/dubbo/rpc/protocol/rest/RestHeaderEnum.getHeader:()Ljava/lang/String;
      17: aload_3
      18: invokevirtual #6                  // Method org/apache/dubbo/metadata/rest/ServiceRestMetadata.getGroup:()Ljava/lang/String;
      21: invokevirtual #7                  // Method org/apache/dubbo/remoting/http/RequestTemplate.addHeader:(Ljava/lang/String;Ljava/lang/String;)V
      24: aload_2
      25: getstatic     #8                  // Field org/apache/dubbo/rpc/protocol/rest/RestHeaderEnum.VERSION:Lorg/apache/dubbo/rpc/protocol/rest/RestHeaderEnum;
      28: invokevirtual #5                  // Method org/apache/dubbo/rpc/protocol/rest/RestHeaderEnum.getHeader:()Ljava/lang/String;
      31: aload_3
      32: invokevirtual #9                  // Method org/apache/dubbo/metadata/rest/ServiceRestMetadata.getVersion:()Ljava/lang/String;
      35: invokevirtual #7                  // Method org/apache/dubbo/remoting/http/RequestTemplate.addHeader:(Ljava/lang/String;Ljava/lang/String;)V
      38: aload_2
      39: getstatic     #10                 // Field org/apache/dubbo/rpc/protocol/rest/RestHeaderEnum.PATH:Lorg/apache/dubbo/rpc/protocol/rest/RestHeaderEnum;
      42: invokevirtual #5                  // Method org/apache/dubbo/rpc/protocol/rest/RestHeaderEnum.getHeader:()Ljava/lang/String;
      45: aload_3
      46: invokevirtual #11                 // Method org/apache/dubbo/metadata/rest/ServiceRestMetadata.getServiceInterface:()Ljava/lang/String;
      49: invokevirtual #7                  // Method org/apache/dubbo/remoting/http/RequestTemplate.addHeader:(Ljava/lang/String;Ljava/lang/String;)V
      52: aload_2
      53: getstatic     #12                 // Field org/apache/dubbo/rpc/protocol/rest/RestHeaderEnum.TOKEN_KEY:Lorg/apache/dubbo/rpc/protocol/rest/RestHeaderEnum;
      56: invokevirtual #5                  // Method org/apache/dubbo/rpc/protocol/rest/RestHeaderEnum.getHeader:()Ljava/lang/String;
      59: aload_1
      60: invokevirtual #13                 // Method org/apache/dubbo/rpc/protocol/rest/annotation/consumer/HttpConnectionCreateContext.getUrl:()Lorg/apache/dubbo/common/URL;
      63: ldc           #15                 // String token
      65: invokevirtual #16                 // Method org/apache/dubbo/common/URL.getParameter:(Ljava/lang/String;)Ljava/lang/String;
      68: invokevirtual #7                  // Method org/apache/dubbo/remoting/http/RequestTemplate.addHeader:(Ljava/lang/String;Ljava/lang/String;)V
      71: return
}
