Compiled from "AttachmentIntercept.java"
public class org.apache.dubbo.rpc.protocol.rest.annotation.consumer.inercept.AttachmentIntercept implements org.apache.dubbo.rpc.protocol.rest.annotation.consumer.HttpConnectionPreBuildIntercept {
  public org.apache.dubbo.rpc.protocol.rest.annotation.consumer.inercept.AttachmentIntercept();
    Code:
       0: aload_0
       1: invokespecial #1                  // Method java/lang/Object."<init>":()V
       4: return

  public void intercept(org.apache.dubbo.rpc.protocol.rest.annotation.consumer.HttpConnectionCreateContext);
    Code:
       0: aload_1
       1: invokevirtual #2                  // Method org/apache/dubbo/rpc/protocol/rest/annotation/consumer/HttpConnectionCreateContext.getRequestTemplate:()Lorg/apache/dubbo/remoting/http/RequestTemplate;
       4: astore_2
       5: aload_2
       6: aload_1
       7: invokevirtual #3                  // Method org/apache/dubbo/rpc/protocol/rest/annotation/consumer/HttpConnectionCreateContext.getInvocation:()Lorg/apache/dubbo/rpc/Invocation;
      10: invokeinterface #4,  1            // InterfaceMethod org/apache/dubbo/rpc/Invocation.getObjectAttachments:()Ljava/util/Map;
      15: invokestatic  #5                  // Method org/apache/dubbo/rpc/protocol/rest/util/HttpHeaderUtil.addRequestAttachments:(Lorg/apache/dubbo/remoting/http/RequestTemplate;Ljava/util/Map;)V
      18: return
}
