Compiled from "ParamParseIntercept.java"
public class org.apache.dubbo.rpc.protocol.rest.annotation.consumer.inercept.ParamParseIntercept implements org.apache.dubbo.rpc.protocol.rest.annotation.consumer.HttpConnectionPreBuildIntercept {
  public org.apache.dubbo.rpc.protocol.rest.annotation.consumer.inercept.ParamParseIntercept();
    Code:
       0: aload_0
       1: invokespecial #1                  // Method java/lang/Object."<init>":()V
       4: return

  public void intercept(org.apache.dubbo.rpc.protocol.rest.annotation.consumer.HttpConnectionCreateContext);
    Code:
       0: new           #2                  // class org/apache/dubbo/rpc/protocol/rest/annotation/param/parse/consumer/ConsumerParseContext
       3: dup
       4: aload_1
       5: invokevirtual #3                  // Method org/apache/dubbo/rpc/protocol/rest/annotation/consumer/HttpConnectionCreateContext.getRequestTemplate:()Lorg/apache/dubbo/remoting/http/RequestTemplate;
       8: invokespecial #4                  // Method org/apache/dubbo/rpc/protocol/rest/annotation/param/parse/consumer/ConsumerParseContext."<init>":(Lorg/apache/dubbo/remoting/http/RequestTemplate;)V
      11: astore_2
      12: aload_2
      13: aload_1
      14: invokevirtual #5                  // Method org/apache/dubbo/rpc/protocol/rest/annotation/consumer/HttpConnectionCreateContext.getRestMethodMetadata:()Lorg/apache/dubbo/metadata/rest/RestMethodMetadata;
      17: invokevirtual #6                  // Method org/apache/dubbo/metadata/rest/RestMethodMetadata.getArgInfos:()Ljava/util/List;
      20: invokevirtual #7                  // Method org/apache/dubbo/rpc/protocol/rest/annotation/param/parse/consumer/ConsumerParseContext.setArgInfos:(Ljava/util/List;)V
      23: aload_2
      24: aload_1
      25: invokevirtual #8                  // Method org/apache/dubbo/rpc/protocol/rest/annotation/consumer/HttpConnectionCreateContext.getInvocation:()Lorg/apache/dubbo/rpc/Invocation;
      28: invokeinterface #9,  1            // InterfaceMethod org/apache/dubbo/rpc/Invocation.getArguments:()[Ljava/lang/Object;
      33: invokestatic  #10                 // Method java/util/Arrays.asList:([Ljava/lang/Object;)Ljava/util/List;
      36: invokevirtual #11                 // Method org/apache/dubbo/rpc/protocol/rest/annotation/param/parse/consumer/ConsumerParseContext.setArgs:(Ljava/util/List;)V
      39: aload_2
      40: invokestatic  #12                 // Method org/apache/dubbo/rpc/protocol/rest/annotation/ParamParserManager.consumerParamParse:(Lorg/apache/dubbo/rpc/protocol/rest/annotation/param/parse/consumer/ConsumerParseContext;)V
      43: return
}
