Compiled from "PathVariableIntercept.java"
public class org.apache.dubbo.rpc.protocol.rest.annotation.consumer.inercept.PathVariableIntercept implements org.apache.dubbo.rpc.protocol.rest.annotation.consumer.HttpConnectionPreBuildIntercept {
  public org.apache.dubbo.rpc.protocol.rest.annotation.consumer.inercept.PathVariableIntercept();
    Code:
       0: aload_0
       1: invokespecial #1                  // Method java/lang/Object."<init>":()V
       4: return

  public void intercept(org.apache.dubbo.rpc.protocol.rest.annotation.consumer.HttpConnectionCreateContext);
    Code:
       0: aload_1
       1: invokevirtual #2                  // Method org/apache/dubbo/rpc/protocol/rest/annotation/consumer/HttpConnectionCreateContext.getRestMethodMetadata:()Lorg/apache/dubbo/metadata/rest/RestMethodMetadata;
       4: astore_2
       5: aload_1
       6: invokevirtual #3                  // Method org/apache/dubbo/rpc/protocol/rest/annotation/consumer/HttpConnectionCreateContext.getRequestTemplate:()Lorg/apache/dubbo/remoting/http/RequestTemplate;
       9: astore_3
      10: aload_2
      11: invokevirtual #4                  // Method org/apache/dubbo/metadata/rest/RestMethodMetadata.getArgInfos:()Ljava/util/List;
      14: astore        4
      16: aload_2
      17: invokevirtual #5                  // Method org/apache/dubbo/metadata/rest/RestMethodMetadata.getRequest:()Lorg/apache/dubbo/metadata/rest/RequestMetadata;
      20: invokevirtual #6                  // Method org/apache/dubbo/metadata/rest/RequestMetadata.getPath:()Ljava/lang/String;
      23: aload         4
      25: aload_1
      26: invokevirtual #7                  // Method org/apache/dubbo/rpc/protocol/rest/annotation/consumer/HttpConnectionCreateContext.getInvocation:()Lorg/apache/dubbo/rpc/Invocation;
      29: invokeinterface #8,  1            // InterfaceMethod org/apache/dubbo/rpc/Invocation.getArguments:()[Ljava/lang/Object;
      34: invokestatic  #9                  // Method java/util/Arrays.asList:([Ljava/lang/Object;)Ljava/util/List;
      37: invokestatic  #10                 // Method org/apache/dubbo/metadata/rest/PathUtil.resolvePathVariable:(Ljava/lang/String;Ljava/util/List;Ljava/util/List;)Ljava/lang/String;
      40: astore        5
      42: aload_3
      43: aload         5
      45: invokevirtual #11                 // Method org/apache/dubbo/remoting/http/RequestTemplate.path:(Ljava/lang/String;)Lorg/apache/dubbo/remoting/http/RequestTemplate;
      48: pop
      49: return
}
