Compiled from "RequestHeaderIntercept.java"
public class org.apache.dubbo.rpc.protocol.rest.annotation.consumer.inercept.RequestHeaderIntercept implements org.apache.dubbo.rpc.protocol.rest.annotation.consumer.HttpConnectionPreBuildIntercept {
  public org.apache.dubbo.rpc.protocol.rest.annotation.consumer.inercept.RequestHeaderIntercept();
    Code:
       0: aload_0
       1: invokespecial #1                  // Method java/lang/Object."<init>":()V
       4: return

  public void intercept(org.apache.dubbo.rpc.protocol.rest.annotation.consumer.HttpConnectionCreateContext);
    Code:
       0: aload_1
       1: invokevirtual #2                  // Method org/apache/dubbo/rpc/protocol/rest/annotation/consumer/HttpConnectionCreateContext.getRestMethodMetadata:()Lorg/apache/dubbo/metadata/rest/RestMethodMetadata;
       4: astore_2
       5: aload_1
       6: invokevirtual #3                  // Method org/apache/dubbo/rpc/protocol/rest/annotation/consumer/HttpConnectionCreateContext.getRequestTemplate:()Lorg/apache/dubbo/remoting/http/RequestTemplate;
       9: astore_3
      10: aload_2
      11: invokevirtual #4                  // Method org/apache/dubbo/metadata/rest/RestMethodMetadata.getRequest:()Lorg/apache/dubbo/metadata/rest/RequestMetadata;
      14: invokevirtual #5                  // Method org/apache/dubbo/metadata/rest/RequestMetadata.getConsumes:()Ljava/util/Set;
      17: astore        4
      19: aload_3
      20: getstatic     #6                  // Field org/apache/dubbo/rpc/protocol/rest/RestHeaderEnum.CONTENT_TYPE:Lorg/apache/dubbo/rpc/protocol/rest/RestHeaderEnum;
      23: invokevirtual #7                  // Method org/apache/dubbo/rpc/protocol/rest/RestHeaderEnum.getHeader:()Ljava/lang/String;
      26: aload         4
      28: invokevirtual #8                  // Method org/apache/dubbo/remoting/http/RequestTemplate.addHeaders:(Ljava/lang/String;Ljava/util/Collection;)V
      31: aload_2
      32: invokevirtual #4                  // Method org/apache/dubbo/metadata/rest/RestMethodMetadata.getRequest:()Lorg/apache/dubbo/metadata/rest/RequestMetadata;
      35: invokevirtual #9                  // Method org/apache/dubbo/metadata/rest/RequestMetadata.getProduces:()Ljava/util/Set;
      38: astore        5
      40: aload         5
      42: ifnull        55
      45: aload         5
      47: invokeinterface #10,  1           // InterfaceMethod java/util/Collection.isEmpty:()Z
      52: ifeq          70
      55: aload_3
      56: getstatic     #11                 // Field org/apache/dubbo/rpc/protocol/rest/RestHeaderEnum.ACCEPT:Lorg/apache/dubbo/rpc/protocol/rest/RestHeaderEnum;
      59: invokevirtual #7                  // Method org/apache/dubbo/rpc/protocol/rest/RestHeaderEnum.getHeader:()Ljava/lang/String;
      62: ldc           #13                 // String */*
      64: invokevirtual #14                 // Method org/apache/dubbo/remoting/http/RequestTemplate.addHeader:(Ljava/lang/String;Ljava/lang/String;)V
      67: goto          82
      70: aload_3
      71: getstatic     #11                 // Field org/apache/dubbo/rpc/protocol/rest/RestHeaderEnum.ACCEPT:Lorg/apache/dubbo/rpc/protocol/rest/RestHeaderEnum;
      74: invokevirtual #7                  // Method org/apache/dubbo/rpc/protocol/rest/RestHeaderEnum.getHeader:()Ljava/lang/String;
      77: aload         5
      79: invokevirtual #15                 // Method org/apache/dubbo/remoting/http/RequestTemplate.addHeader:(Ljava/lang/String;Ljava/lang/Object;)V
      82: return
}
