Compiled from "SerializeBodyIntercept.java"
public class org.apache.dubbo.rpc.protocol.rest.annotation.consumer.inercept.SerializeBodyIntercept implements org.apache.dubbo.rpc.protocol.rest.annotation.consumer.HttpConnectionPreBuildIntercept {
  private static final org.apache.dubbo.common.logger.ErrorTypeAwareLogger logger;

  public org.apache.dubbo.rpc.protocol.rest.annotation.consumer.inercept.SerializeBodyIntercept();
    Code:
       0: aload_0
       1: invokespecial #1                  // Method java/lang/Object."<init>":()V
       4: return

  public void intercept(org.apache.dubbo.rpc.protocol.rest.annotation.consumer.HttpConnectionCreateContext);
    Code:
       0: aload_1
       1: invokevirtual #2                  // Method org/apache/dubbo/rpc/protocol/rest/annotation/consumer/HttpConnectionCreateContext.getRequestTemplate:()Lorg/apache/dubbo/remoting/http/RequestTemplate;
       4: astore_2
       5: aload_2
       6: invokevirtual #3                  // Method org/apache/dubbo/remoting/http/RequestTemplate.isBodyEmpty:()Z
       9: ifeq          13
      12: return
      13: aload_2
      14: invokevirtual #4                  // Method org/apache/dubbo/remoting/http/RequestTemplate.getUnSerializedBody:()Ljava/lang/Object;
      17: astore_3
      18: aload_1
      19: invokevirtual #5                  // Method org/apache/dubbo/rpc/protocol/rest/annotation/consumer/HttpConnectionCreateContext.getUrl:()Lorg/apache/dubbo/common/URL;
      22: astore        4
      24: new           #6                  // class java/io/ByteArrayOutputStream
      27: dup
      28: invokespecial #7                  // Method java/io/ByteArrayOutputStream."<init>":()V
      31: astore        5
      33: aload_2
      34: ldc           #9                  // String Content-Type
      36: invokevirtual #10                 // Method org/apache/dubbo/remoting/http/RequestTemplate.getHeaders:(Ljava/lang/String;)Ljava/util/Collection;
      39: astore        6
      41: aload_2
      42: invokevirtual #11                 // Method org/apache/dubbo/remoting/http/RequestTemplate.getBodyType:()Ljava/lang/Class;
      45: aload         6
      47: iconst_0
      48: anewarray     #12                 // class java/lang/String
      51: invokeinterface #13,  2           // InterfaceMethod java/util/Collection.toArray:([Ljava/lang/Object;)[Ljava/lang/Object;
      56: checkcast     #14                 // class "[Ljava/lang/String;"
      59: invokestatic  #15                 // Method org/apache/dubbo/rpc/protocol/rest/util/MediaTypeUtil.convertMediaType:(Ljava/lang/Class;[Ljava/lang/String;)Lorg/apache/dubbo/metadata/rest/media/MediaType;
      62: astore        7
      64: aload         6
      66: invokeinterface #16,  1           // InterfaceMethod java/util/Collection.isEmpty:()Z
      71: ifeq          103
      74: aload         7
      76: ifnull        103
      79: aload         7
      81: getstatic     #17                 // Field org/apache/dubbo/metadata/rest/media/MediaType.ALL_VALUE:Lorg/apache/dubbo/metadata/rest/media/MediaType;
      84: invokevirtual #18                 // Method org/apache/dubbo/metadata/rest/media/MediaType.equals:(Ljava/lang/Object;)Z
      87: ifne          103
      90: aload         6
      92: aload         7
      94: getfield      #19                 // Field org/apache/dubbo/metadata/rest/media/MediaType.value:Ljava/lang/String;
      97: invokeinterface #20,  2           // InterfaceMethod java/util/Collection.add:(Ljava/lang/Object;)Z
     102: pop
     103: aload         5
     105: aload_3
     106: aload         4
     108: aload         7
     110: aload_2
     111: invokevirtual #11                 // Method org/apache/dubbo/remoting/http/RequestTemplate.getBodyType:()Ljava/lang/Class;
     114: invokestatic  #21                 // Method org/apache/dubbo/rpc/protocol/rest/message/HttpMessageCodecManager.httpMessageEncode:(Ljava/io/OutputStream;Ljava/lang/Object;Lorg/apache/dubbo/common/URL;Lorg/apache/dubbo/metadata/rest/media/MediaType;Ljava/lang/Class;)Lorg/apache/dubbo/rpc/protocol/rest/pair/MessageCodecResultPair;
     117: pop
     118: aload_2
     119: aload         5
     121: invokevirtual #22                 // Method java/io/ByteArrayOutputStream.toByteArray:()[B
     124: invokevirtual #23                 // Method org/apache/dubbo/remoting/http/RequestTemplate.serializeBody:([B)V
     127: aload         5
     129: invokevirtual #24                 // Method java/io/ByteArrayOutputStream.close:()V
     132: goto          162
     135: astore_3
     136: getstatic     #26                 // Field logger:Lorg/apache/dubbo/common/logger/ErrorTypeAwareLogger;
     139: ldc           #28                 // String 4-6
     141: ldc           #29                 // String
     143: ldc           #29                 // String
     145: ldc           #30                 // String Rest SerializeBodyIntercept serialize error: {}
     147: aload_3
     148: invokeinterface #31,  6           // InterfaceMethod org/apache/dubbo/common/logger/ErrorTypeAwareLogger.error:(Ljava/lang/String;Ljava/lang/String;Ljava/lang/String;Ljava/lang/String;Ljava/lang/Throwable;)V
     153: new           #32                 // class org/apache/dubbo/rpc/RpcException
     156: dup
     157: aload_3
     158: invokespecial #33                 // Method org/apache/dubbo/rpc/RpcException."<init>":(Ljava/lang/Throwable;)V
     161: athrow
     162: return
    Exception table:
       from    to  target type
          13   132   135   Class java/lang/Exception

  static {};
    Code:
       0: ldc           #34                 // class org/apache/dubbo/rpc/protocol/rest/annotation/consumer/inercept/SerializeBodyIntercept
       2: invokestatic  #35                 // Method org/apache/dubbo/common/logger/LoggerFactory.getErrorTypeAwareLogger:(Ljava/lang/Class;)Lorg/apache/dubbo/common/logger/ErrorTypeAwareLogger;
       5: putstatic     #26                 // Field logger:Lorg/apache/dubbo/common/logger/ErrorTypeAwareLogger;
       8: return
}
