Compiled from "RpcUtils.java"
public class com.alibaba.dubbo.rpc.support.RpcUtils extends org.apache.dubbo.rpc.support.RpcUtils {
  public com.alibaba.dubbo.rpc.support.RpcUtils();
    Code:
       0: aload_0
       1: invokespecial #1                  // Method org/apache/dubbo/rpc/support/RpcUtils."<init>":()V
       4: return

  public static java.lang.Class<?> getReturnType(com.alibaba.dubbo.rpc.Invocation);
    Code:
       0: aload_0
       1: invokestatic  #2                  // Method org/apache/dubbo/rpc/support/RpcUtils.getReturnType:(Lorg/apache/dubbo/rpc/Invocation;)Ljava/lang/Class;
       4: areturn

  public static java.lang.reflect.Type[] getReturnTypes(com.alibaba.dubbo.rpc.Invocation);
    Code:
       0: aload_0
       1: invokestatic  #3                  // Method org/apache/dubbo/rpc/support/RpcUtils.getReturnTypes:(Lorg/apache/dubbo/rpc/Invocation;)[Ljava/lang/reflect/Type;
       4: areturn

  public static java.lang.Long getInvocationId(com.alibaba.dubbo.rpc.Invocation);
    Code:
       0: aload_0
       1: invokestatic  #4                  // Method org/apache/dubbo/rpc/support/RpcUtils.getInvocationId:(Lorg/apache/dubbo/rpc/Invocation;)Ljava/lang/Long;
       4: areturn

  public static void attachInvocationIdIfAsync(com.alibaba.dubbo.common.URL, com.alibaba.dubbo.rpc.Invocation);
    Code:
       0: aload_0
       1: invokevirtual #5                  // Method com/alibaba/dubbo/common/URL.getOriginalURL:()Lorg/apache/dubbo/common/URL;
       4: aload_1
       5: invokestatic  #6                  // Method org/apache/dubbo/rpc/support/RpcUtils.attachInvocationIdIfAsync:(Lorg/apache/dubbo/common/URL;Lorg/apache/dubbo/rpc/Invocation;)V
       8: return

  public static java.lang.String getMethodName(com.alibaba.dubbo.rpc.Invocation);
    Code:
       0: aload_0
       1: invokestatic  #7                  // Method org/apache/dubbo/rpc/support/RpcUtils.getMethodName:(Lorg/apache/dubbo/rpc/Invocation;)Ljava/lang/String;
       4: areturn

  public static java.lang.Object[] getArguments(com.alibaba.dubbo.rpc.Invocation);
    Code:
       0: aload_0
       1: invokestatic  #8                  // Method org/apache/dubbo/rpc/support/RpcUtils.getArguments:(Lorg/apache/dubbo/rpc/Invocation;)[Ljava/lang/Object;
       4: areturn

  public static java.lang.Class<?>[] getParameterTypes(com.alibaba.dubbo.rpc.Invocation);
    Code:
       0: aload_0
       1: invokestatic  #9                  // Method org/apache/dubbo/rpc/support/RpcUtils.getParameterTypes:(Lorg/apache/dubbo/rpc/Invocation;)[Ljava/lang/Class;
       4: areturn

  public static boolean isAsync(com.alibaba.dubbo.common.URL, com.alibaba.dubbo.rpc.Invocation);
    Code:
       0: aload_0
       1: invokevirtual #5                  // Method com/alibaba/dubbo/common/URL.getOriginalURL:()Lorg/apache/dubbo/common/URL;
       4: aload_1
       5: invokestatic  #10                 // Method org/apache/dubbo/rpc/support/RpcUtils.isAsync:(Lorg/apache/dubbo/common/URL;Lorg/apache/dubbo/rpc/Invocation;)Z
       8: ireturn

  public static boolean isReturnTypeFuture(com.alibaba.dubbo.rpc.Invocation);
    Code:
       0: aload_0
       1: invokestatic  #11                 // Method org/apache/dubbo/rpc/support/RpcUtils.isReturnTypeFuture:(Lorg/apache/dubbo/rpc/Invocation;)Z
       4: ireturn

  public static boolean isOneway(com.alibaba.dubbo.common.URL, com.alibaba.dubbo.rpc.Invocation);
    Code:
       0: aload_0
       1: invokevirtual #5                  // Method com/alibaba/dubbo/common/URL.getOriginalURL:()Lorg/apache/dubbo/common/URL;
       4: aload_1
       5: invokestatic  #12                 // Method org/apache/dubbo/rpc/support/RpcUtils.isOneway:(Lorg/apache/dubbo/common/URL;Lorg/apache/dubbo/rpc/Invocation;)Z
       8: ireturn
}
