Compiled from "Endpoint.java"
public class org.apache.dubbo.registry.xds.util.protocol.message.Endpoint {
  private java.lang.String clusterName;

  private java.lang.String address;

  private int portValue;

  private boolean healthy;

  private int weight;

  public org.apache.dubbo.registry.xds.util.protocol.message.Endpoint();
    Code:
       0: aload_0
       1: invokespecial #1                  // Method java/lang/Object."<init>":()V
       4: return

  public java.lang.String getClusterName();
    Code:
       0: aload_0
       1: getfield      #2                  // Field clusterName:Ljava/lang/String;
       4: areturn

  public void setClusterName(java.lang.String);
    Code:
       0: aload_0
       1: aload_1
       2: putfield      #2                  // Field clusterName:Ljava/lang/String;
       5: return

  public java.lang.String getAddress();
    Code:
       0: aload_0
       1: getfield      #3                  // Field address:Ljava/lang/String;
       4: areturn

  public void setAddress(java.lang.String);
    Code:
       0: aload_0
       1: aload_1
       2: putfield      #3                  // Field address:Ljava/lang/String;
       5: return

  public int getPortValue();
    Code:
       0: aload_0
       1: getfield      #4                  // Field portValue:I
       4: ireturn

  public void setPortValue(int);
    Code:
       0: aload_0
       1: iload_1
       2: putfield      #4                  // Field portValue:I
       5: return

  public boolean isHealthy();
    Code:
       0: aload_0
       1: getfield      #5                  // Field healthy:Z
       4: ireturn

  public void setHealthy(boolean);
    Code:
       0: aload_0
       1: iload_1
       2: putfield      #5                  // Field healthy:Z
       5: return

  public int getWeight();
    Code:
       0: aload_0
       1: getfield      #6                  // Field weight:I
       4: ireturn

  public void setWeight(int);
    Code:
       0: aload_0
       1: iload_1
       2: putfield      #6                  // Field weight:I
       5: return

  public java.lang.String toString();
    Code:
       0: new           #7                  // class java/lang/StringBuilder
       3: dup
       4: invokespecial #8                  // Method java/lang/StringBuilder."<init>":()V
       7: ldc           #9                  // String Endpoint{address=\'
       9: invokevirtual #10                 // Method java/lang/StringBuilder.append:(Ljava/lang/String;)Ljava/lang/StringBuilder;
      12: aload_0
      13: getfield      #3                  // Field address:Ljava/lang/String;
      16: invokevirtual #10                 // Method java/lang/StringBuilder.append:(Ljava/lang/String;)Ljava/lang/StringBuilder;
      19: bipush        39
      21: invokevirtual #11                 // Method java/lang/StringBuilder.append:(C)Ljava/lang/StringBuilder;
      24: ldc           #12                 // String , portValue=\'
      26: invokevirtual #10                 // Method java/lang/StringBuilder.append:(Ljava/lang/String;)Ljava/lang/StringBuilder;
      29: aload_0
      30: getfield      #4                  // Field portValue:I
      33: invokevirtual #13                 // Method java/lang/StringBuilder.append:(I)Ljava/lang/StringBuilder;
      36: bipush        39
      38: invokevirtual #11                 // Method java/lang/StringBuilder.append:(C)Ljava/lang/StringBuilder;
      41: ldc           #14                 // String , healthy=
      43: invokevirtual #10                 // Method java/lang/StringBuilder.append:(Ljava/lang/String;)Ljava/lang/StringBuilder;
      46: aload_0
      47: getfield      #5                  // Field healthy:Z
      50: invokevirtual #15                 // Method java/lang/StringBuilder.append:(Z)Ljava/lang/StringBuilder;
      53: ldc           #16                 // String , weight=
      55: invokevirtual #10                 // Method java/lang/StringBuilder.append:(Ljava/lang/String;)Ljava/lang/StringBuilder;
      58: aload_0
      59: getfield      #6                  // Field weight:I
      62: invokevirtual #13                 // Method java/lang/StringBuilder.append:(I)Ljava/lang/StringBuilder;
      65: bipush        125
      67: invokevirtual #11                 // Method java/lang/StringBuilder.append:(C)Ljava/lang/StringBuilder;
      70: invokevirtual #17                 // Method java/lang/StringBuilder.toString:()Ljava/lang/String;
      73: areturn

  public boolean equals(java.lang.Object);
    Code:
       0: aload_0
       1: aload_1
       2: if_acmpne     7
       5: iconst_1
       6: ireturn
       7: aload_1
       8: ifnull        22
      11: aload_0
      12: invokevirtual #18                 // Method java/lang/Object.getClass:()Ljava/lang/Class;
      15: aload_1
      16: invokevirtual #18                 // Method java/lang/Object.getClass:()Ljava/lang/Class;
      19: if_acmpeq     24
      22: iconst_0
      23: ireturn
      24: aload_1
      25: checkcast     #19                 // class org/apache/dubbo/registry/xds/util/protocol/message/Endpoint
      28: astore_2
      29: aload_0
      30: getfield      #5                  // Field healthy:Z
      33: aload_2
      34: getfield      #5                  // Field healthy:Z
      37: if_icmpne     89
      40: aload_0
      41: getfield      #6                  // Field weight:I
      44: aload_2
      45: getfield      #6                  // Field weight:I
      48: if_icmpne     89
      51: aload_0
      52: getfield      #3                  // Field address:Ljava/lang/String;
      55: aload_2
      56: getfield      #3                  // Field address:Ljava/lang/String;
      59: invokestatic  #20                 // Method java/util/Objects.equals:(Ljava/lang/Object;Ljava/lang/Object;)Z
      62: ifeq          89
      65: aload_0
      66: getfield      #4                  // Field portValue:I
      69: invokestatic  #21                 // Method java/lang/Integer.valueOf:(I)Ljava/lang/Integer;
      72: aload_2
      73: getfield      #4                  // Field portValue:I
      76: invokestatic  #21                 // Method java/lang/Integer.valueOf:(I)Ljava/lang/Integer;
      79: invokestatic  #20                 // Method java/util/Objects.equals:(Ljava/lang/Object;Ljava/lang/Object;)Z
      82: ifeq          89
      85: iconst_1
      86: goto          90
      89: iconst_0
      90: ireturn

  public int hashCode();
    Code:
       0: iconst_4
       1: anewarray     #22                 // class java/lang/Object
       4: dup
       5: iconst_0
       6: aload_0
       7: getfield      #3                  // Field address:Ljava/lang/String;
      10: aastore
      11: dup
      12: iconst_1
      13: aload_0
      14: getfield      #4                  // Field portValue:I
      17: invokestatic  #21                 // Method java/lang/Integer.valueOf:(I)Ljava/lang/Integer;
      20: aastore
      21: dup
      22: iconst_2
      23: aload_0
      24: getfield      #5                  // Field healthy:Z
      27: invokestatic  #23                 // Method java/lang/Boolean.valueOf:(Z)Ljava/lang/Boolean;
      30: aastore
      31: dup
      32: iconst_3
      33: aload_0
      34: getfield      #6                  // Field weight:I
      37: invokestatic  #21                 // Method java/lang/Integer.valueOf:(I)Ljava/lang/Integer;
      40: aastore
      41: invokestatic  #24                 // Method java/util/Objects.hash:([Ljava/lang/Object;)I
      44: ireturn
}
