Compiled from "ListenerResult.java"
public class org.apache.dubbo.registry.xds.util.protocol.message.ListenerResult {
  private java.util.Set<java.lang.String> routeConfigNames;

  public org.apache.dubbo.registry.xds.util.protocol.message.ListenerResult();
    Code:
       0: aload_0
       1: invokespecial #1                  // Method java/lang/Object."<init>":()V
       4: aload_0
       5: new           #2                  // class org/apache/dubbo/common/utils/ConcurrentHashSet
       8: dup
       9: invokespecial #3                  // Method org/apache/dubbo/common/utils/ConcurrentHashSet."<init>":()V
      12: putfield      #4                  // Field routeConfigNames:Ljava/util/Set;
      15: return

  public org.apache.dubbo.registry.xds.util.protocol.message.ListenerResult(java.util.Set<java.lang.String>);
    Code:
       0: aload_0
       1: invokespecial #1                  // Method java/lang/Object."<init>":()V
       4: aload_0
       5: aload_1
       6: putfield      #4                  // Field routeConfigNames:Ljava/util/Set;
       9: return

  public java.util.Set<java.lang.String> getRouteConfigNames();
    Code:
       0: aload_0
       1: getfield      #4                  // Field routeConfigNames:Ljava/util/Set;
       4: areturn

  public void setRouteConfigNames(java.util.Set<java.lang.String>);
    Code:
       0: aload_0
       1: aload_1
       2: putfield      #4                  // Field routeConfigNames:Ljava/util/Set;
       5: return

  public void mergeRouteConfigNames(java.util.Set<java.lang.String>);
    Code:
       0: aload_0
       1: getfield      #4                  // Field routeConfigNames:Ljava/util/Set;
       4: aload_1
       5: invokeinterface #5,  2            // InterfaceMethod java/util/Set.addAll:(Ljava/util/Collection;)Z
      10: pop
      11: return

  public boolean equals(java.lang.Object);
    Code:
       0: aload_0
       1: aload_1
       2: if_acmpne     7
       5: iconst_1
       6: ireturn
       7: aload_1
       8: ifnull        22
      11: aload_0
      12: invokevirtual #6                  // Method java/lang/Object.getClass:()Ljava/lang/Class;
      15: aload_1
      16: invokevirtual #6                  // Method java/lang/Object.getClass:()Ljava/lang/Class;
      19: if_acmpeq     24
      22: iconst_0
      23: ireturn
      24: aload_1
      25: checkcast     #7                  // class org/apache/dubbo/registry/xds/util/protocol/message/ListenerResult
      28: astore_2
      29: aload_0
      30: getfield      #4                  // Field routeConfigNames:Ljava/util/Set;
      33: aload_2
      34: getfield      #4                  // Field routeConfigNames:Ljava/util/Set;
      37: invokestatic  #8                  // Method java/util/Objects.equals:(Ljava/lang/Object;Ljava/lang/Object;)Z
      40: ireturn

  public int hashCode();
    Code:
       0: iconst_1
       1: anewarray     #9                  // class java/lang/Object
       4: dup
       5: iconst_0
       6: aload_0
       7: getfield      #4                  // Field routeConfigNames:Ljava/util/Set;
      10: aastore
      11: invokestatic  #10                 // Method java/util/Objects.hash:([Ljava/lang/Object;)I
      14: ireturn

  public java.lang.String toString();
    Code:
       0: new           #11                 // class java/lang/StringBuilder
       3: dup
       4: invokespecial #12                 // Method java/lang/StringBuilder."<init>":()V
       7: ldc           #13                 // String ListenerResult{routeConfigNames=
       9: invokevirtual #14                 // Method java/lang/StringBuilder.append:(Ljava/lang/String;)Ljava/lang/StringBuilder;
      12: aload_0
      13: getfield      #4                  // Field routeConfigNames:Ljava/util/Set;
      16: invokevirtual #15                 // Method java/lang/StringBuilder.append:(Ljava/lang/Object;)Ljava/lang/StringBuilder;
      19: bipush        125
      21: invokevirtual #16                 // Method java/lang/StringBuilder.append:(C)Ljava/lang/StringBuilder;
      24: invokevirtual #17                 // Method java/lang/StringBuilder.toString:()Ljava/lang/String;
      27: areturn
}
