Compiled from "ExpandedRow.java"
final class com.google.zxing.oned.rss.expanded.ExpandedRow {
  private final java.util.List<com.google.zxing.oned.rss.expanded.ExpandedPair> pairs;

  private final int rowNumber;

  com.google.zxing.oned.rss.expanded.ExpandedRow(java.util.List<com.google.zxing.oned.rss.expanded.ExpandedPair>, int);
    Code:
       0: aload_0
       1: invokespecial #1                  // Method java/lang/Object."<init>":()V
       4: aload_0
       5: new           #2                  // class java/util/ArrayList
       8: dup
       9: aload_1
      10: invokespecial #3                  // Method java/util/ArrayList."<init>":(Ljava/util/Collection;)V
      13: putfield      #4                  // Field pairs:Ljava/util/List;
      16: aload_0
      17: iload_2
      18: putfield      #5                  // Field rowNumber:I
      21: return

  java.util.List<com.google.zxing.oned.rss.expanded.ExpandedPair> getPairs();
    Code:
       0: aload_0
       1: getfield      #4                  // Field pairs:Ljava/util/List;
       4: areturn

  int getRowNumber();
    Code:
       0: aload_0
       1: getfield      #5                  // Field rowNumber:I
       4: ireturn

  boolean isEquivalent(java.util.List<com.google.zxing.oned.rss.expanded.ExpandedPair>);
    Code:
       0: aload_0
       1: getfield      #4                  // Field pairs:Ljava/util/List;
       4: aload_1
       5: invokeinterface #6,  2            // InterfaceMethod java/util/List.equals:(Ljava/lang/Object;)Z
      10: ireturn

  public java.lang.String toString();
    Code:
       0: new           #7                  // class java/lang/StringBuilder
       3: dup
       4: invokespecial #8                  // Method java/lang/StringBuilder."<init>":()V
       7: ldc           #9                  // String {
       9: invokevirtual #10                 // Method java/lang/StringBuilder.append:(Ljava/lang/String;)Ljava/lang/StringBuilder;
      12: aload_0
      13: getfield      #4                  // Field pairs:Ljava/util/List;
      16: invokevirtual #11                 // Method java/lang/StringBuilder.append:(Ljava/lang/Object;)Ljava/lang/StringBuilder;
      19: ldc           #12                 // String  }
      21: invokevirtual #10                 // Method java/lang/StringBuilder.append:(Ljava/lang/String;)Ljava/lang/StringBuilder;
      24: invokevirtual #13                 // Method java/lang/StringBuilder.toString:()Ljava/lang/String;
      27: areturn

  public boolean equals(java.lang.Object);
    Code:
       0: aload_1
       1: instanceof    #14                 // class com/google/zxing/oned/rss/expanded/ExpandedRow
       4: ifne          9
       7: iconst_0
       8: ireturn
       9: aload_1
      10: checkcast     #14                 // class com/google/zxing/oned/rss/expanded/ExpandedRow
      13: astore_2
      14: aload_0
      15: getfield      #4                  // Field pairs:Ljava/util/List;
      18: aload_2
      19: getfield      #4                  // Field pairs:Ljava/util/List;
      22: invokeinterface #6,  2            // InterfaceMethod java/util/List.equals:(Ljava/lang/Object;)Z
      27: ireturn

  public int hashCode();
    Code:
       0: aload_0
       1: getfield      #4                  // Field pairs:Ljava/util/List;
       4: invokeinterface #15,  1           // InterfaceMethod java/util/List.hashCode:()I
       9: ireturn
}
