Compiled from "ExpandedPair.java"
final class com.google.zxing.oned.rss.expanded.ExpandedPair {
  private final com.google.zxing.oned.rss.DataCharacter leftChar;

  private final com.google.zxing.oned.rss.DataCharacter rightChar;

  private final com.google.zxing.oned.rss.FinderPattern finderPattern;

  com.google.zxing.oned.rss.expanded.ExpandedPair(com.google.zxing.oned.rss.DataCharacter, com.google.zxing.oned.rss.DataCharacter, com.google.zxing.oned.rss.FinderPattern);
    Code:
       0: aload_0
       1: invokespecial #1                  // Method java/lang/Object."<init>":()V
       4: aload_0
       5: aload_1
       6: putfield      #2                  // Field leftChar:Lcom/google/zxing/oned/rss/DataCharacter;
       9: aload_0
      10: aload_2
      11: putfield      #3                  // Field rightChar:Lcom/google/zxing/oned/rss/DataCharacter;
      14: aload_0
      15: aload_3
      16: putfield      #4                  // Field finderPattern:Lcom/google/zxing/oned/rss/FinderPattern;
      19: return

  com.google.zxing.oned.rss.DataCharacter getLeftChar();
    Code:
       0: aload_0
       1: getfield      #2                  // Field leftChar:Lcom/google/zxing/oned/rss/DataCharacter;
       4: areturn

  com.google.zxing.oned.rss.DataCharacter getRightChar();
    Code:
       0: aload_0
       1: getfield      #3                  // Field rightChar:Lcom/google/zxing/oned/rss/DataCharacter;
       4: areturn

  com.google.zxing.oned.rss.FinderPattern getFinderPattern();
    Code:
       0: aload_0
       1: getfield      #4                  // Field finderPattern:Lcom/google/zxing/oned/rss/FinderPattern;
       4: areturn

  boolean mustBeLast();
    Code:
       0: aload_0
       1: getfield      #3                  // Field rightChar:Lcom/google/zxing/oned/rss/DataCharacter;
       4: ifnonnull     11
       7: iconst_1
       8: goto          12
      11: iconst_0
      12: ireturn

  public java.lang.String toString();
    Code:
       0: new           #5                  // class java/lang/StringBuilder
       3: dup
       4: invokespecial #6                  // Method java/lang/StringBuilder."<init>":()V
       7: ldc           #7                  // String [
       9: invokevirtual #8                  // Method java/lang/StringBuilder.append:(Ljava/lang/String;)Ljava/lang/StringBuilder;
      12: aload_0
      13: getfield      #2                  // Field leftChar:Lcom/google/zxing/oned/rss/DataCharacter;
      16: invokevirtual #9                  // Method java/lang/StringBuilder.append:(Ljava/lang/Object;)Ljava/lang/StringBuilder;
      19: ldc           #10                 // String  ,
      21: invokevirtual #8                  // Method java/lang/StringBuilder.append:(Ljava/lang/String;)Ljava/lang/StringBuilder;
      24: aload_0
      25: getfield      #3                  // Field rightChar:Lcom/google/zxing/oned/rss/DataCharacter;
      28: invokevirtual #9                  // Method java/lang/StringBuilder.append:(Ljava/lang/Object;)Ljava/lang/StringBuilder;
      31: ldc           #11                 // String  :
      33: invokevirtual #8                  // Method java/lang/StringBuilder.append:(Ljava/lang/String;)Ljava/lang/StringBuilder;
      36: aload_0
      37: getfield      #4                  // Field finderPattern:Lcom/google/zxing/oned/rss/FinderPattern;
      40: ifnonnull     48
      43: ldc           #12                 // String null
      45: goto          58
      48: aload_0
      49: getfield      #4                  // Field finderPattern:Lcom/google/zxing/oned/rss/FinderPattern;
      52: invokevirtual #13                 // Method com/google/zxing/oned/rss/FinderPattern.getValue:()I
      55: invokestatic  #14                 // Method java/lang/Integer.valueOf:(I)Ljava/lang/Integer;
      58: invokevirtual #9                  // Method java/lang/StringBuilder.append:(Ljava/lang/Object;)Ljava/lang/StringBuilder;
      61: ldc           #15                 // String  ]
      63: invokevirtual #8                  // Method java/lang/StringBuilder.append:(Ljava/lang/String;)Ljava/lang/StringBuilder;
      66: invokevirtual #16                 // Method java/lang/StringBuilder.toString:()Ljava/lang/String;
      69: areturn

  public boolean equals(java.lang.Object);
    Code:
       0: aload_1
       1: instanceof    #17                 // class com/google/zxing/oned/rss/expanded/ExpandedPair
       4: ifne          9
       7: iconst_0
       8: ireturn
       9: aload_1
      10: checkcast     #17                 // class com/google/zxing/oned/rss/expanded/ExpandedPair
      13: astore_2
      14: aload_0
      15: getfield      #2                  // Field leftChar:Lcom/google/zxing/oned/rss/DataCharacter;
      18: aload_2
      19: getfield      #2                  // Field leftChar:Lcom/google/zxing/oned/rss/DataCharacter;
      22: invokestatic  #18                 // Method java/util/Objects.equals:(Ljava/lang/Object;Ljava/lang/Object;)Z
      25: ifeq          60
      28: aload_0
      29: getfield      #3                  // Field rightChar:Lcom/google/zxing/oned/rss/DataCharacter;
      32: aload_2
      33: getfield      #3                  // Field rightChar:Lcom/google/zxing/oned/rss/DataCharacter;
      36: invokestatic  #18                 // Method java/util/Objects.equals:(Ljava/lang/Object;Ljava/lang/Object;)Z
      39: ifeq          60
      42: aload_0
      43: getfield      #4                  // Field finderPattern:Lcom/google/zxing/oned/rss/FinderPattern;
      46: aload_2
      47: getfield      #4                  // Field finderPattern:Lcom/google/zxing/oned/rss/FinderPattern;
      50: invokestatic  #18                 // Method java/util/Objects.equals:(Ljava/lang/Object;Ljava/lang/Object;)Z
      53: ifeq          60
      56: iconst_1
      57: goto          61
      60: iconst_0
      61: ireturn

  public int hashCode();
    Code:
       0: aload_0
       1: getfield      #2                  // Field leftChar:Lcom/google/zxing/oned/rss/DataCharacter;
       4: invokestatic  #19                 // Method java/util/Objects.hashCode:(Ljava/lang/Object;)I
       7: aload_0
       8: getfield      #3                  // Field rightChar:Lcom/google/zxing/oned/rss/DataCharacter;
      11: invokestatic  #19                 // Method java/util/Objects.hashCode:(Ljava/lang/Object;)I
      14: ixor
      15: aload_0
      16: getfield      #4                  // Field finderPattern:Lcom/google/zxing/oned/rss/FinderPattern;
      19: invokestatic  #19                 // Method java/util/Objects.hashCode:(Ljava/lang/Object;)I
      22: ixor
      23: ireturn
}
