Compiled from "MigrationRule.java"
public class org.apache.dubbo.registry.client.migration.model.MigrationRule {
  private java.lang.String key;

  private org.apache.dubbo.registry.client.migration.model.MigrationStep step;

  private java.lang.Float threshold;

  private java.lang.Integer proportion;

  private java.lang.Integer delay;

  private java.lang.Boolean force;

  private java.util.List<org.apache.dubbo.registry.client.migration.model.SubMigrationRule> interfaces;

  private java.util.List<org.apache.dubbo.registry.client.migration.model.SubMigrationRule> applications;

  private transient java.util.Map<java.lang.String, org.apache.dubbo.registry.client.migration.model.SubMigrationRule> interfaceRules;

  private transient java.util.Map<java.lang.String, org.apache.dubbo.registry.client.migration.model.SubMigrationRule> applicationRules;

  public static org.apache.dubbo.registry.client.migration.model.MigrationRule getInitRule();
    Code:
       0: new           #3                  // class org/apache/dubbo/registry/client/migration/model/MigrationRule
       3: dup
       4: invokespecial #4                  // Method "<init>":()V
       7: areturn

  private static org.apache.dubbo.registry.client.migration.model.MigrationRule parseFromMap(java.util.Map<java.lang.String, java.lang.Object>);
    Code:
       0: new           #3                  // class org/apache/dubbo/registry/client/migration/model/MigrationRule
       3: dup
       4: invokespecial #4                  // Method "<init>":()V
       7: astore_1
       8: aload_1
       9: aload_0
      10: ldc           #5                  // String key
      12: invokeinterface #6,  2            // InterfaceMethod java/util/Map.get:(Ljava/lang/Object;)Ljava/lang/Object;
      17: checkcast     #7                  // class java/lang/String
      20: invokevirtual #8                  // Method setKey:(Ljava/lang/String;)V
      23: aload_0
      24: ldc           #9                  // String step
      26: invokeinterface #6,  2            // InterfaceMethod java/util/Map.get:(Ljava/lang/Object;)Ljava/lang/Object;
      31: astore_2
      32: aload_2
      33: ifnull        47
      36: aload_1
      37: aload_2
      38: invokevirtual #10                 // Method java/lang/Object.toString:()Ljava/lang/String;
      41: invokestatic  #11                 // Method org/apache/dubbo/registry/client/migration/model/MigrationStep.valueOf:(Ljava/lang/String;)Lorg/apache/dubbo/registry/client/migration/model/MigrationStep;
      44: invokevirtual #12                 // Method setStep:(Lorg/apache/dubbo/registry/client/migration/model/MigrationStep;)V
      47: aload_0
      48: ldc           #13                 // String threshold
      50: invokeinterface #6,  2            // InterfaceMethod java/util/Map.get:(Ljava/lang/Object;)Ljava/lang/Object;
      55: astore_3
      56: aload_3
      57: ifnull        71
      60: aload_1
      61: aload_3
      62: invokevirtual #10                 // Method java/lang/Object.toString:()Ljava/lang/String;
      65: invokestatic  #14                 // Method java/lang/Float.valueOf:(Ljava/lang/String;)Ljava/lang/Float;
      68: invokevirtual #15                 // Method setThreshold:(Ljava/lang/Float;)V
      71: aload_0
      72: ldc           #16                 // String proportion
      74: invokeinterface #6,  2            // InterfaceMethod java/util/Map.get:(Ljava/lang/Object;)Ljava/lang/Object;
      79: astore        4
      81: aload         4
      83: ifnull        98
      86: aload_1
      87: aload         4
      89: invokevirtual #10                 // Method java/lang/Object.toString:()Ljava/lang/String;
      92: invokestatic  #17                 // Method java/lang/Integer.valueOf:(Ljava/lang/String;)Ljava/lang/Integer;
      95: invokevirtual #18                 // Method setProportion:(Ljava/lang/Integer;)V
      98: aload_0
      99: ldc           #19                 // String delay
     101: invokeinterface #6,  2            // InterfaceMethod java/util/Map.get:(Ljava/lang/Object;)Ljava/lang/Object;
     106: astore        5
     108: aload         5
     110: ifnull        125
     113: aload_1
     114: aload         5
     116: invokevirtual #10                 // Method java/lang/Object.toString:()Ljava/lang/String;
     119: invokestatic  #17                 // Method java/lang/Integer.valueOf:(Ljava/lang/String;)Ljava/lang/Integer;
     122: invokevirtual #20                 // Method setDelay:(Ljava/lang/Integer;)V
     125: aload_0
     126: ldc           #21                 // String force
     128: invokeinterface #6,  2            // InterfaceMethod java/util/Map.get:(Ljava/lang/Object;)Ljava/lang/Object;
     133: astore        6
     135: aload         6
     137: ifnull        152
     140: aload_1
     141: aload         6
     143: invokevirtual #10                 // Method java/lang/Object.toString:()Ljava/lang/String;
     146: invokestatic  #22                 // Method java/lang/Boolean.valueOf:(Ljava/lang/String;)Ljava/lang/Boolean;
     149: invokevirtual #23                 // Method setForce:(Ljava/lang/Boolean;)V
     152: aload_0
     153: ldc           #24                 // String interfaces
     155: invokeinterface #6,  2            // InterfaceMethod java/util/Map.get:(Ljava/lang/Object;)Ljava/lang/Object;
     160: astore        7
     162: aload         7
     164: ifnull        215
     167: ldc           #25                 // class java/util/List
     169: aload         7
     171: invokevirtual #26                 // Method java/lang/Object.getClass:()Ljava/lang/Class;
     174: invokevirtual #27                 // Method java/lang/Class.isAssignableFrom:(Ljava/lang/Class;)Z
     177: ifeq          215
     180: aload_1
     181: aload         7
     183: checkcast     #25                 // class java/util/List
     186: invokeinterface #28,  1           // InterfaceMethod java/util/List.stream:()Ljava/util/stream/Stream;
     191: invokedynamic #29,  0             // InvokeDynamic #0:apply:()Ljava/util/function/Function;
     196: invokeinterface #30,  2           // InterfaceMethod java/util/stream/Stream.map:(Ljava/util/function/Function;)Ljava/util/stream/Stream;
     201: invokestatic  #31                 // Method java/util/stream/Collectors.toList:()Ljava/util/stream/Collector;
     204: invokeinterface #32,  2           // InterfaceMethod java/util/stream/Stream.collect:(Ljava/util/stream/Collector;)Ljava/lang/Object;
     209: checkcast     #25                 // class java/util/List
     212: invokevirtual #33                 // Method setInterfaces:(Ljava/util/List;)V
     215: aload_0
     216: ldc           #34                 // String applications
     218: invokeinterface #6,  2            // InterfaceMethod java/util/Map.get:(Ljava/lang/Object;)Ljava/lang/Object;
     223: astore        8
     225: aload         8
     227: ifnull        278
     230: ldc           #25                 // class java/util/List
     232: aload         8
     234: invokevirtual #26                 // Method java/lang/Object.getClass:()Ljava/lang/Class;
     237: invokevirtual #27                 // Method java/lang/Class.isAssignableFrom:(Ljava/lang/Class;)Z
     240: ifeq          278
     243: aload_1
     244: aload         8
     246: checkcast     #25                 // class java/util/List
     249: invokeinterface #28,  1           // InterfaceMethod java/util/List.stream:()Ljava/util/stream/Stream;
     254: invokedynamic #29,  0             // InvokeDynamic #0:apply:()Ljava/util/function/Function;
     259: invokeinterface #30,  2           // InterfaceMethod java/util/stream/Stream.map:(Ljava/util/function/Function;)Ljava/util/stream/Stream;
     264: invokestatic  #31                 // Method java/util/stream/Collectors.toList:()Ljava/util/stream/Collector;
     267: invokeinterface #32,  2           // InterfaceMethod java/util/stream/Stream.collect:(Ljava/util/stream/Collector;)Ljava/lang/Object;
     272: checkcast     #25                 // class java/util/List
     275: invokevirtual #35                 // Method setApplications:(Ljava/util/List;)V
     278: aload_1
     279: areturn

  public org.apache.dubbo.registry.client.migration.model.MigrationRule();
    Code:
       0: aload_0
       1: invokespecial #36                 // Method java/lang/Object."<init>":()V
       4: return

  public org.apache.dubbo.registry.client.migration.model.MigrationRule(java.lang.String);
    Code:
       0: aload_0
       1: invokespecial #36                 // Method java/lang/Object."<init>":()V
       4: aload_0
       5: aload_1
       6: putfield      #37                 // Field key:Ljava/lang/String;
       9: return

  public java.lang.String getKey();
    Code:
       0: aload_0
       1: getfield      #37                 // Field key:Ljava/lang/String;
       4: areturn

  public void setKey(java.lang.String);
    Code:
       0: aload_0
       1: aload_1
       2: putfield      #37                 // Field key:Ljava/lang/String;
       5: return

  public org.apache.dubbo.registry.client.migration.model.MigrationStep getStep(org.apache.dubbo.common.URL);
    Code:
       0: aload_0
       1: aload_1
       2: invokedynamic #38,  0             // InvokeDynamic #1:apply:()Ljava/util/function/Function;
       7: invokevirtual #39                 // Method getValue:(Lorg/apache/dubbo/common/URL;Ljava/util/function/Function;)Ljava/lang/Object;
      10: checkcast     #40                 // class org/apache/dubbo/registry/client/migration/model/MigrationStep
      13: astore_2
      14: aload_2
      15: ifnull        20
      18: aload_2
      19: areturn
      20: aload_0
      21: getfield      #41                 // Field step:Lorg/apache/dubbo/registry/client/migration/model/MigrationStep;
      24: ifnonnull     64
      27: aload_0
      28: getstatic     #42                 // Field org/apache/dubbo/registry/client/migration/model/MigrationStep.APPLICATION_FIRST:Lorg/apache/dubbo/registry/client/migration/model/MigrationStep;
      31: putfield      #41                 // Field step:Lorg/apache/dubbo/registry/client/migration/model/MigrationStep;
      34: aload_0
      35: ldc           #40                 // class org/apache/dubbo/registry/client/migration/model/MigrationStep
      37: aload_1
      38: ldc           #43                 // String migration.step
      40: aload_0
      41: aload_1
      42: aload_0
      43: getfield      #41                 // Field step:Lorg/apache/dubbo/registry/client/migration/model/MigrationStep;
      46: invokevirtual #44                 // Method org/apache/dubbo/registry/client/migration/model/MigrationStep.name:()Ljava/lang/String;
      49: invokespecial #45                 // Method getDefaultStep:(Lorg/apache/dubbo/common/URL;Ljava/lang/String;)Ljava/lang/String;
      52: invokevirtual #46                 // Method org/apache/dubbo/common/URL.getParameter:(Ljava/lang/String;Ljava/lang/String;)Ljava/lang/String;
      55: invokestatic  #47                 // Method java/lang/Enum.valueOf:(Ljava/lang/Class;Ljava/lang/String;)Ljava/lang/Enum;
      58: checkcast     #40                 // class org/apache/dubbo/registry/client/migration/model/MigrationStep
      61: putfield      #41                 // Field step:Lorg/apache/dubbo/registry/client/migration/model/MigrationStep;
      64: aload_0
      65: getfield      #41                 // Field step:Lorg/apache/dubbo/registry/client/migration/model/MigrationStep;
      68: areturn

  private java.lang.String getDefaultStep(org.apache.dubbo.common.URL, java.lang.String);
    Code:
       0: aload_1
       1: invokevirtual #48                 // Method org/apache/dubbo/common/URL.getScopeModel:()Lorg/apache/dubbo/rpc/model/ScopeModel;
       4: ldc           #49                 // String dubbo.application.migration.step
       6: aconst_null
       7: invokestatic  #50                 // Method org/apache/dubbo/common/config/ConfigurationUtils.getCachedDynamicProperty:(Lorg/apache/dubbo/rpc/model/ScopeModel;Ljava/lang/String;Ljava/lang/String;)Ljava/lang/String;
      10: astore_3
      11: aload_3
      12: invokestatic  #51                 // Method org/apache/dubbo/common/utils/StringUtils.isEmpty:(Ljava/lang/String;)Z
      15: ifeq          29
      18: aload_1
      19: invokevirtual #48                 // Method org/apache/dubbo/common/URL.getScopeModel:()Lorg/apache/dubbo/rpc/model/ScopeModel;
      22: ldc           #52                 // String dubbo.application.service-discovery.migration
      24: aload_2
      25: invokestatic  #50                 // Method org/apache/dubbo/common/config/ConfigurationUtils.getCachedDynamicProperty:(Lorg/apache/dubbo/rpc/model/ScopeModel;Ljava/lang/String;Ljava/lang/String;)Ljava/lang/String;
      28: astore_3
      29: aload_3
      30: areturn

  public org.apache.dubbo.registry.client.migration.model.MigrationStep getStep();
    Code:
       0: aload_0
       1: getfield      #41                 // Field step:Lorg/apache/dubbo/registry/client/migration/model/MigrationStep;
       4: areturn

  public float getThreshold(org.apache.dubbo.common.URL);
    Code:
       0: aload_0
       1: aload_1
       2: invokedynamic #53,  0             // InvokeDynamic #2:apply:()Ljava/util/function/Function;
       7: invokevirtual #39                 // Method getValue:(Lorg/apache/dubbo/common/URL;Ljava/util/function/Function;)Ljava/lang/Object;
      10: checkcast     #54                 // class java/lang/Float
      13: astore_2
      14: aload_2
      15: ifnull        23
      18: aload_2
      19: invokevirtual #55                 // Method java/lang/Float.floatValue:()F
      22: freturn
      23: aload_0
      24: getfield      #56                 // Field threshold:Ljava/lang/Float;
      27: ifnonnull     41
      30: aload_1
      31: ldc           #57                 // String migration.threshold
      33: ldc           #58                 // float -1.0f
      35: invokevirtual #59                 // Method org/apache/dubbo/common/URL.getParameter:(Ljava/lang/String;F)F
      38: goto          48
      41: aload_0
      42: getfield      #56                 // Field threshold:Ljava/lang/Float;
      45: invokevirtual #55                 // Method java/lang/Float.floatValue:()F
      48: freturn

  public java.lang.Float getThreshold();
    Code:
       0: aload_0
       1: getfield      #56                 // Field threshold:Ljava/lang/Float;
       4: areturn

  public void setThreshold(java.lang.Float);
    Code:
       0: aload_0
       1: aload_1
       2: putfield      #56                 // Field threshold:Ljava/lang/Float;
       5: return

  public java.lang.Integer getProportion();
    Code:
       0: aload_0
       1: getfield      #60                 // Field proportion:Ljava/lang/Integer;
       4: areturn

  public int getProportion(org.apache.dubbo.common.URL);
    Code:
       0: aload_0
       1: aload_1
       2: invokedynamic #61,  0             // InvokeDynamic #3:apply:()Ljava/util/function/Function;
       7: invokevirtual #39                 // Method getValue:(Lorg/apache/dubbo/common/URL;Ljava/util/function/Function;)Ljava/lang/Object;
      10: checkcast     #62                 // class java/lang/Integer
      13: astore_2
      14: aload_2
      15: ifnull        23
      18: aload_2
      19: invokevirtual #63                 // Method java/lang/Integer.intValue:()I
      22: ireturn
      23: aload_0
      24: getfield      #60                 // Field proportion:Ljava/lang/Integer;
      27: ifnonnull     41
      30: aload_1
      31: ldc           #64                 // String migration.promotion
      33: bipush        100
      35: invokevirtual #65                 // Method org/apache/dubbo/common/URL.getParameter:(Ljava/lang/String;I)I
      38: goto          48
      41: aload_0
      42: getfield      #60                 // Field proportion:Ljava/lang/Integer;
      45: invokevirtual #63                 // Method java/lang/Integer.intValue:()I
      48: ireturn

  public void setProportion(java.lang.Integer);
    Code:
       0: aload_0
       1: aload_1
       2: putfield      #60                 // Field proportion:Ljava/lang/Integer;
       5: return

  public java.lang.Integer getDelay();
    Code:
       0: aload_0
       1: getfield      #66                 // Field delay:Ljava/lang/Integer;
       4: areturn

  public int getDelay(org.apache.dubbo.common.URL);
    Code:
       0: aload_0
       1: aload_1
       2: invokedynamic #67,  0             // InvokeDynamic #4:apply:()Ljava/util/function/Function;
       7: invokevirtual #39                 // Method getValue:(Lorg/apache/dubbo/common/URL;Ljava/util/function/Function;)Ljava/lang/Object;
      10: checkcast     #62                 // class java/lang/Integer
      13: astore_2
      14: aload_2
      15: ifnull        23
      18: aload_2
      19: invokevirtual #63                 // Method java/lang/Integer.intValue:()I
      22: ireturn
      23: aload_0
      24: getfield      #66                 // Field delay:Ljava/lang/Integer;
      27: ifnonnull     40
      30: aload_1
      31: ldc           #68                 // String migration.delay
      33: iconst_0
      34: invokevirtual #65                 // Method org/apache/dubbo/common/URL.getParameter:(Ljava/lang/String;I)I
      37: goto          47
      40: aload_0
      41: getfield      #66                 // Field delay:Ljava/lang/Integer;
      44: invokevirtual #63                 // Method java/lang/Integer.intValue:()I
      47: ireturn

  public void setDelay(java.lang.Integer);
    Code:
       0: aload_0
       1: aload_1
       2: putfield      #66                 // Field delay:Ljava/lang/Integer;
       5: return

  public void setStep(org.apache.dubbo.registry.client.migration.model.MigrationStep);
    Code:
       0: aload_0
       1: aload_1
       2: putfield      #41                 // Field step:Lorg/apache/dubbo/registry/client/migration/model/MigrationStep;
       5: return

  public java.lang.Boolean getForce();
    Code:
       0: aload_0
       1: getfield      #69                 // Field force:Ljava/lang/Boolean;
       4: areturn

  public boolean getForce(org.apache.dubbo.common.URL);
    Code:
       0: aload_0
       1: aload_1
       2: invokedynamic #70,  0             // InvokeDynamic #5:apply:()Ljava/util/function/Function;
       7: invokevirtual #39                 // Method getValue:(Lorg/apache/dubbo/common/URL;Ljava/util/function/Function;)Ljava/lang/Object;
      10: checkcast     #71                 // class java/lang/Boolean
      13: astore_2
      14: aload_2
      15: ifnull        23
      18: aload_2
      19: invokevirtual #72                 // Method java/lang/Boolean.booleanValue:()Z
      22: ireturn
      23: aload_0
      24: getfield      #69                 // Field force:Ljava/lang/Boolean;
      27: ifnonnull     40
      30: aload_1
      31: ldc           #73                 // String migration.force
      33: iconst_0
      34: invokevirtual #74                 // Method org/apache/dubbo/common/URL.getParameter:(Ljava/lang/String;Z)Z
      37: goto          47
      40: aload_0
      41: getfield      #69                 // Field force:Ljava/lang/Boolean;
      44: invokevirtual #72                 // Method java/lang/Boolean.booleanValue:()Z
      47: ireturn

  public <T> T getValue(org.apache.dubbo.common.URL, java.util.function.Function<org.apache.dubbo.registry.client.migration.model.SubMigrationRule, T>);
    Code:
       0: aload_0
       1: getfield      #75                 // Field interfaceRules:Ljava/util/Map;
       4: ifnull        45
       7: aload_0
       8: getfield      #75                 // Field interfaceRules:Ljava/util/Map;
      11: aload_1
      12: invokevirtual #76                 // Method org/apache/dubbo/common/URL.getDisplayServiceKey:()Ljava/lang/String;
      15: invokeinterface #6,  2            // InterfaceMethod java/util/Map.get:(Ljava/lang/Object;)Ljava/lang/Object;
      20: checkcast     #77                 // class org/apache/dubbo/registry/client/migration/model/SubMigrationRule
      23: astore_3
      24: aload_3
      25: ifnull        45
      28: aload_2
      29: aload_3
      30: invokeinterface #78,  2           // InterfaceMethod java/util/function/Function.apply:(Ljava/lang/Object;)Ljava/lang/Object;
      35: astore        4
      37: aload         4
      39: ifnull        45
      42: aload         4
      44: areturn
      45: aload_0
      46: getfield      #79                 // Field applications:Ljava/util/List;
      49: ifnull        150
      52: aload_1
      53: invokevirtual #48                 // Method org/apache/dubbo/common/URL.getScopeModel:()Lorg/apache/dubbo/rpc/model/ScopeModel;
      56: invokestatic  #80                 // InterfaceMethod org/apache/dubbo/metadata/ServiceNameMapping.getDefaultExtension:(Lorg/apache/dubbo/rpc/model/ScopeModel;)Lorg/apache/dubbo/metadata/ServiceNameMapping;
      59: astore_3
      60: aload_3
      61: aload_1
      62: invokeinterface #81,  2           // InterfaceMethod org/apache/dubbo/metadata/ServiceNameMapping.getRemoteMapping:(Lorg/apache/dubbo/common/URL;)Ljava/util/Set;
      67: astore        4
      69: aload         4
      71: invokestatic  #82                 // Method org/apache/dubbo/common/utils/CollectionUtils.isNotEmpty:(Ljava/util/Collection;)Z
      74: ifeq          150
      77: aload         4
      79: invokeinterface #83,  1           // InterfaceMethod java/util/Set.iterator:()Ljava/util/Iterator;
      84: astore        5
      86: aload         5
      88: invokeinterface #84,  1           // InterfaceMethod java/util/Iterator.hasNext:()Z
      93: ifeq          150
      96: aload         5
      98: invokeinterface #85,  1           // InterfaceMethod java/util/Iterator.next:()Ljava/lang/Object;
     103: checkcast     #7                  // class java/lang/String
     106: astore        6
     108: aload_0
     109: getfield      #86                 // Field applicationRules:Ljava/util/Map;
     112: aload         6
     114: invokeinterface #6,  2            // InterfaceMethod java/util/Map.get:(Ljava/lang/Object;)Ljava/lang/Object;
     119: checkcast     #77                 // class org/apache/dubbo/registry/client/migration/model/SubMigrationRule
     122: astore        7
     124: aload         7
     126: ifnull        147
     129: aload_2
     130: aload         7
     132: invokeinterface #78,  2           // InterfaceMethod java/util/function/Function.apply:(Ljava/lang/Object;)Ljava/lang/Object;
     137: astore        8
     139: aload         8
     141: ifnull        147
     144: aload         8
     146: areturn
     147: goto          86
     150: aconst_null
     151: areturn

  public void setForce(java.lang.Boolean);
    Code:
       0: aload_0
       1: aload_1
       2: putfield      #69                 // Field force:Ljava/lang/Boolean;
       5: return

  public java.util.List<org.apache.dubbo.registry.client.migration.model.SubMigrationRule> getInterfaces();
    Code:
       0: aload_0
       1: getfield      #87                 // Field interfaces:Ljava/util/List;
       4: areturn

  public void setInterfaces(java.util.List<org.apache.dubbo.registry.client.migration.model.SubMigrationRule>);
    Code:
       0: aload_0
       1: aload_1
       2: putfield      #87                 // Field interfaces:Ljava/util/List;
       5: aload_1
       6: ifnull        32
       9: aload_0
      10: new           #88                 // class java/util/HashMap
      13: dup
      14: invokespecial #89                 // Method java/util/HashMap."<init>":()V
      17: putfield      #75                 // Field interfaceRules:Ljava/util/Map;
      20: aload_1
      21: aload_0
      22: invokedynamic #90,  0             // InvokeDynamic #6:accept:(Lorg/apache/dubbo/registry/client/migration/model/MigrationRule;)Ljava/util/function/Consumer;
      27: invokeinterface #91,  2           // InterfaceMethod java/util/List.forEach:(Ljava/util/function/Consumer;)V
      32: return

  public java.util.List<org.apache.dubbo.registry.client.migration.model.SubMigrationRule> getApplications();
    Code:
       0: aload_0
       1: getfield      #79                 // Field applications:Ljava/util/List;
       4: areturn

  public void setApplications(java.util.List<org.apache.dubbo.registry.client.migration.model.SubMigrationRule>);
    Code:
       0: aload_0
       1: aload_1
       2: putfield      #79                 // Field applications:Ljava/util/List;
       5: aload_1
       6: ifnull        32
       9: aload_0
      10: new           #88                 // class java/util/HashMap
      13: dup
      14: invokespecial #89                 // Method java/util/HashMap."<init>":()V
      17: putfield      #86                 // Field applicationRules:Ljava/util/Map;
      20: aload_1
      21: aload_0
      22: invokedynamic #92,  0             // InvokeDynamic #7:accept:(Lorg/apache/dubbo/registry/client/migration/model/MigrationRule;)Ljava/util/function/Consumer;
      27: invokeinterface #91,  2           // InterfaceMethod java/util/List.forEach:(Ljava/util/function/Consumer;)V
      32: return

  public static org.apache.dubbo.registry.client.migration.model.MigrationRule parse(java.lang.String);
    Code:
       0: new           #93                 // class org/yaml/snakeyaml/Yaml
       3: dup
       4: new           #94                 // class org/yaml/snakeyaml/constructor/SafeConstructor
       7: dup
       8: new           #95                 // class org/yaml/snakeyaml/LoaderOptions
      11: dup
      12: invokespecial #96                 // Method org/yaml/snakeyaml/LoaderOptions."<init>":()V
      15: invokespecial #97                 // Method org/yaml/snakeyaml/constructor/SafeConstructor."<init>":(Lorg/yaml/snakeyaml/LoaderOptions;)V
      18: invokespecial #98                 // Method org/yaml/snakeyaml/Yaml."<init>":(Lorg/yaml/snakeyaml/constructor/BaseConstructor;)V
      21: astore_1
      22: aload_1
      23: aload_0
      24: invokevirtual #99                 // Method org/yaml/snakeyaml/Yaml.load:(Ljava/lang/String;)Ljava/lang/Object;
      27: checkcast     #100                // class java/util/Map
      30: astore_2
      31: aload_2
      32: invokestatic  #101                // Method parseFromMap:(Ljava/util/Map;)Lorg/apache/dubbo/registry/client/migration/model/MigrationRule;
      35: areturn

  public static java.lang.String toYaml(org.apache.dubbo.registry.client.migration.model.MigrationRule);
    Code:
       0: new           #102                // class org/yaml/snakeyaml/constructor/Constructor
       3: dup
       4: ldc           #3                  // class org/apache/dubbo/registry/client/migration/model/MigrationRule
       6: new           #95                 // class org/yaml/snakeyaml/LoaderOptions
       9: dup
      10: invokespecial #96                 // Method org/yaml/snakeyaml/LoaderOptions."<init>":()V
      13: invokespecial #103                // Method org/yaml/snakeyaml/constructor/Constructor."<init>":(Ljava/lang/Class;Lorg/yaml/snakeyaml/LoaderOptions;)V
      16: astore_1
      17: new           #93                 // class org/yaml/snakeyaml/Yaml
      20: dup
      21: aload_1
      22: invokespecial #98                 // Method org/yaml/snakeyaml/Yaml."<init>":(Lorg/yaml/snakeyaml/constructor/BaseConstructor;)V
      25: astore_2
      26: aload_2
      27: aload_0
      28: invokevirtual #104                // Method org/yaml/snakeyaml/Yaml.dump:(Ljava/lang/Object;)Ljava/lang/String;
      31: areturn

  public boolean equals(java.lang.Object);
    Code:
       0: aload_0
       1: aload_1
       2: if_acmpne     7
       5: iconst_1
       6: ireturn
       7: aload_1
       8: ifnull        22
      11: aload_0
      12: invokevirtual #26                 // Method java/lang/Object.getClass:()Ljava/lang/Class;
      15: aload_1
      16: invokevirtual #26                 // Method java/lang/Object.getClass:()Ljava/lang/Class;
      19: if_acmpeq     24
      22: iconst_0
      23: ireturn
      24: aload_1
      25: checkcast     #3                  // class org/apache/dubbo/registry/client/migration/model/MigrationRule
      28: astore_2
      29: aload_0
      30: getfield      #37                 // Field key:Ljava/lang/String;
      33: aload_2
      34: getfield      #37                 // Field key:Ljava/lang/String;
      37: invokestatic  #105                // Method java/util/Objects.equals:(Ljava/lang/Object;Ljava/lang/Object;)Z
      40: ifeq          170
      43: aload_0
      44: getfield      #41                 // Field step:Lorg/apache/dubbo/registry/client/migration/model/MigrationStep;
      47: aload_2
      48: getfield      #41                 // Field step:Lorg/apache/dubbo/registry/client/migration/model/MigrationStep;
      51: if_acmpne     170
      54: aload_0
      55: getfield      #56                 // Field threshold:Ljava/lang/Float;
      58: aload_2
      59: getfield      #56                 // Field threshold:Ljava/lang/Float;
      62: invokestatic  #105                // Method java/util/Objects.equals:(Ljava/lang/Object;Ljava/lang/Object;)Z
      65: ifeq          170
      68: aload_0
      69: getfield      #60                 // Field proportion:Ljava/lang/Integer;
      72: aload_2
      73: getfield      #60                 // Field proportion:Ljava/lang/Integer;
      76: invokestatic  #105                // Method java/util/Objects.equals:(Ljava/lang/Object;Ljava/lang/Object;)Z
      79: ifeq          170
      82: aload_0
      83: getfield      #66                 // Field delay:Ljava/lang/Integer;
      86: aload_2
      87: getfield      #66                 // Field delay:Ljava/lang/Integer;
      90: invokestatic  #105                // Method java/util/Objects.equals:(Ljava/lang/Object;Ljava/lang/Object;)Z
      93: ifeq          170
      96: aload_0
      97: getfield      #69                 // Field force:Ljava/lang/Boolean;
     100: aload_2
     101: getfield      #69                 // Field force:Ljava/lang/Boolean;
     104: invokestatic  #105                // Method java/util/Objects.equals:(Ljava/lang/Object;Ljava/lang/Object;)Z
     107: ifeq          170
     110: aload_0
     111: getfield      #87                 // Field interfaces:Ljava/util/List;
     114: aload_2
     115: getfield      #87                 // Field interfaces:Ljava/util/List;
     118: invokestatic  #105                // Method java/util/Objects.equals:(Ljava/lang/Object;Ljava/lang/Object;)Z
     121: ifeq          170
     124: aload_0
     125: getfield      #79                 // Field applications:Ljava/util/List;
     128: aload_2
     129: getfield      #79                 // Field applications:Ljava/util/List;
     132: invokestatic  #105                // Method java/util/Objects.equals:(Ljava/lang/Object;Ljava/lang/Object;)Z
     135: ifeq          170
     138: aload_0
     139: getfield      #75                 // Field interfaceRules:Ljava/util/Map;
     142: aload_2
     143: getfield      #75                 // Field interfaceRules:Ljava/util/Map;
     146: invokestatic  #105                // Method java/util/Objects.equals:(Ljava/lang/Object;Ljava/lang/Object;)Z
     149: ifeq          170
     152: aload_0
     153: getfield      #86                 // Field applicationRules:Ljava/util/Map;
     156: aload_2
     157: getfield      #86                 // Field applicationRules:Ljava/util/Map;
     160: invokestatic  #105                // Method java/util/Objects.equals:(Ljava/lang/Object;Ljava/lang/Object;)Z
     163: ifeq          170
     166: iconst_1
     167: goto          171
     170: iconst_0
     171: ireturn

  public int hashCode();
    Code:
       0: bipush        10
       2: anewarray     #106                // class java/lang/Object
       5: dup
       6: iconst_0
       7: aload_0
       8: getfield      #37                 // Field key:Ljava/lang/String;
      11: aastore
      12: dup
      13: iconst_1
      14: aload_0
      15: getfield      #41                 // Field step:Lorg/apache/dubbo/registry/client/migration/model/MigrationStep;
      18: aastore
      19: dup
      20: iconst_2
      21: aload_0
      22: getfield      #56                 // Field threshold:Ljava/lang/Float;
      25: aastore
      26: dup
      27: iconst_3
      28: aload_0
      29: getfield      #60                 // Field proportion:Ljava/lang/Integer;
      32: aastore
      33: dup
      34: iconst_4
      35: aload_0
      36: getfield      #66                 // Field delay:Ljava/lang/Integer;
      39: aastore
      40: dup
      41: iconst_5
      42: aload_0
      43: getfield      #69                 // Field force:Ljava/lang/Boolean;
      46: aastore
      47: dup
      48: bipush        6
      50: aload_0
      51: getfield      #87                 // Field interfaces:Ljava/util/List;
      54: aastore
      55: dup
      56: bipush        7
      58: aload_0
      59: getfield      #79                 // Field applications:Ljava/util/List;
      62: aastore
      63: dup
      64: bipush        8
      66: aload_0
      67: getfield      #75                 // Field interfaceRules:Ljava/util/Map;
      70: aastore
      71: dup
      72: bipush        9
      74: aload_0
      75: getfield      #86                 // Field applicationRules:Ljava/util/Map;
      78: aastore
      79: invokestatic  #107                // Method java/util/Objects.hash:([Ljava/lang/Object;)I
      82: ireturn

  private void lambda$setApplications$1(org.apache.dubbo.registry.client.migration.model.SubMigrationRule);
    Code:
       0: aload_0
       1: getfield      #86                 // Field applicationRules:Ljava/util/Map;
       4: aload_1
       5: invokevirtual #108                // Method org/apache/dubbo/registry/client/migration/model/SubMigrationRule.getServiceKey:()Ljava/lang/String;
       8: aload_1
       9: invokeinterface #109,  3          // InterfaceMethod java/util/Map.put:(Ljava/lang/Object;Ljava/lang/Object;)Ljava/lang/Object;
      14: pop
      15: return

  private void lambda$setInterfaces$0(org.apache.dubbo.registry.client.migration.model.SubMigrationRule);
    Code:
       0: aload_0
       1: getfield      #75                 // Field interfaceRules:Ljava/util/Map;
       4: aload_1
       5: invokevirtual #108                // Method org/apache/dubbo/registry/client/migration/model/SubMigrationRule.getServiceKey:()Ljava/lang/String;
       8: aload_1
       9: invokeinterface #109,  3          // InterfaceMethod java/util/Map.put:(Ljava/lang/Object;Ljava/lang/Object;)Ljava/lang/Object;
      14: pop
      15: return
}
