Compiled from "MigrationStep.java"
public final class org.apache.dubbo.registry.client.migration.model.MigrationStep extends java.lang.Enum<org.apache.dubbo.registry.client.migration.model.MigrationStep> {
  public static final org.apache.dubbo.registry.client.migration.model.MigrationStep FORCE_INTERFACE;

  public static final org.apache.dubbo.registry.client.migration.model.MigrationStep APPLICATION_FIRST;

  public static final org.apache.dubbo.registry.client.migration.model.MigrationStep FORCE_APPLICATION;

  private static final org.apache.dubbo.registry.client.migration.model.MigrationStep[] $VALUES;

  public static org.apache.dubbo.registry.client.migration.model.MigrationStep[] values();
    Code:
       0: getstatic     #1                  // Field $VALUES:[Lorg/apache/dubbo/registry/client/migration/model/MigrationStep;
       3: invokevirtual #2                  // Method "[Lorg/apache/dubbo/registry/client/migration/model/MigrationStep;".clone:()Ljava/lang/Object;
       6: checkcast     #3                  // class "[Lorg/apache/dubbo/registry/client/migration/model/MigrationStep;"
       9: areturn

  public static org.apache.dubbo.registry.client.migration.model.MigrationStep valueOf(java.lang.String);
    Code:
       0: ldc           #4                  // class org/apache/dubbo/registry/client/migration/model/MigrationStep
       2: aload_0
       3: invokestatic  #5                  // Method java/lang/Enum.valueOf:(Ljava/lang/Class;Ljava/lang/String;)Ljava/lang/Enum;
       6: checkcast     #4                  // class org/apache/dubbo/registry/client/migration/model/MigrationStep
       9: areturn

  private org.apache.dubbo.registry.client.migration.model.MigrationStep();
    Code:
       0: aload_0
       1: aload_1
       2: iload_2
       3: invokespecial #6                  // Method java/lang/Enum."<init>":(Ljava/lang/String;I)V
       6: return

  static {};
    Code:
       0: new           #4                  // class org/apache/dubbo/registry/client/migration/model/MigrationStep
       3: dup
       4: ldc           #7                  // String FORCE_INTERFACE
       6: iconst_0
       7: invokespecial #8                  // Method "<init>":(Ljava/lang/String;I)V
      10: putstatic     #9                  // Field FORCE_INTERFACE:Lorg/apache/dubbo/registry/client/migration/model/MigrationStep;
      13: new           #4                  // class org/apache/dubbo/registry/client/migration/model/MigrationStep
      16: dup
      17: ldc           #10                 // String APPLICATION_FIRST
      19: iconst_1
      20: invokespecial #8                  // Method "<init>":(Ljava/lang/String;I)V
      23: putstatic     #11                 // Field APPLICATION_FIRST:Lorg/apache/dubbo/registry/client/migration/model/MigrationStep;
      26: new           #4                  // class org/apache/dubbo/registry/client/migration/model/MigrationStep
      29: dup
      30: ldc           #12                 // String FORCE_APPLICATION
      32: iconst_2
      33: invokespecial #8                  // Method "<init>":(Ljava/lang/String;I)V
      36: putstatic     #13                 // Field FORCE_APPLICATION:Lorg/apache/dubbo/registry/client/migration/model/MigrationStep;
      39: iconst_3
      40: anewarray     #4                  // class org/apache/dubbo/registry/client/migration/model/MigrationStep
      43: dup
      44: iconst_0
      45: getstatic     #9                  // Field FORCE_INTERFACE:Lorg/apache/dubbo/registry/client/migration/model/MigrationStep;
      48: aastore
      49: dup
      50: iconst_1
      51: getstatic     #11                 // Field APPLICATION_FIRST:Lorg/apache/dubbo/registry/client/migration/model/MigrationStep;
      54: aastore
      55: dup
      56: iconst_2
      57: getstatic     #13                 // Field FORCE_APPLICATION:Lorg/apache/dubbo/registry/client/migration/model/MigrationStep;
      60: aastore
      61: putstatic     #1                  // Field $VALUES:[Lorg/apache/dubbo/registry/client/migration/model/MigrationStep;
      64: return
}
