Compiled from "SubMigrationRule.java"
public class org.apache.dubbo.registry.client.migration.model.SubMigrationRule {
  private java.lang.String serviceKey;

  private org.apache.dubbo.registry.client.migration.model.MigrationStep step;

  private java.lang.Float threshold;

  private java.lang.Integer proportion;

  private java.lang.Integer delay;

  private java.lang.Boolean force;

  public static org.apache.dubbo.registry.client.migration.model.SubMigrationRule parseFromMap(java.util.Map<java.lang.String, java.lang.Object>);
    Code:
       0: new           #2                  // class org/apache/dubbo/registry/client/migration/model/SubMigrationRule
       3: dup
       4: invokespecial #3                  // Method "<init>":()V
       7: astore_1
       8: aload_1
       9: aload_0
      10: ldc           #4                  // String serviceKey
      12: invokeinterface #5,  2            // InterfaceMethod java/util/Map.get:(Ljava/lang/Object;)Ljava/lang/Object;
      17: checkcast     #6                  // class java/lang/String
      20: invokevirtual #7                  // Method setServiceKey:(Ljava/lang/String;)V
      23: aload_0
      24: ldc           #8                  // String step
      26: invokeinterface #5,  2            // InterfaceMethod java/util/Map.get:(Ljava/lang/Object;)Ljava/lang/Object;
      31: astore_2
      32: aload_2
      33: ifnull        47
      36: aload_1
      37: aload_2
      38: invokevirtual #9                  // Method java/lang/Object.toString:()Ljava/lang/String;
      41: invokestatic  #10                 // Method org/apache/dubbo/registry/client/migration/model/MigrationStep.valueOf:(Ljava/lang/String;)Lorg/apache/dubbo/registry/client/migration/model/MigrationStep;
      44: invokevirtual #11                 // Method setStep:(Lorg/apache/dubbo/registry/client/migration/model/MigrationStep;)V
      47: aload_0
      48: ldc           #12                 // String threshold
      50: invokeinterface #5,  2            // InterfaceMethod java/util/Map.get:(Ljava/lang/Object;)Ljava/lang/Object;
      55: astore_3
      56: aload_3
      57: ifnull        71
      60: aload_1
      61: aload_3
      62: invokevirtual #9                  // Method java/lang/Object.toString:()Ljava/lang/String;
      65: invokestatic  #13                 // Method java/lang/Float.valueOf:(Ljava/lang/String;)Ljava/lang/Float;
      68: invokevirtual #14                 // Method setThreshold:(Ljava/lang/Float;)V
      71: aload_0
      72: ldc           #15                 // String proportion
      74: invokeinterface #5,  2            // InterfaceMethod java/util/Map.get:(Ljava/lang/Object;)Ljava/lang/Object;
      79: astore        4
      81: aload         4
      83: ifnull        98
      86: aload_1
      87: aload         4
      89: invokevirtual #9                  // Method java/lang/Object.toString:()Ljava/lang/String;
      92: invokestatic  #16                 // Method java/lang/Integer.valueOf:(Ljava/lang/String;)Ljava/lang/Integer;
      95: invokevirtual #17                 // Method setProportion:(Ljava/lang/Integer;)V
      98: aload_0
      99: ldc           #18                 // String delay
     101: invokeinterface #5,  2            // InterfaceMethod java/util/Map.get:(Ljava/lang/Object;)Ljava/lang/Object;
     106: astore        5
     108: aload         5
     110: ifnull        125
     113: aload_1
     114: aload         5
     116: invokevirtual #9                  // Method java/lang/Object.toString:()Ljava/lang/String;
     119: invokestatic  #16                 // Method java/lang/Integer.valueOf:(Ljava/lang/String;)Ljava/lang/Integer;
     122: invokevirtual #19                 // Method setDelay:(Ljava/lang/Integer;)V
     125: aload_0
     126: ldc           #20                 // String force
     128: invokeinterface #5,  2            // InterfaceMethod java/util/Map.get:(Ljava/lang/Object;)Ljava/lang/Object;
     133: astore        6
     135: aload         6
     137: ifnull        152
     140: aload_1
     141: aload         6
     143: invokevirtual #9                  // Method java/lang/Object.toString:()Ljava/lang/String;
     146: invokestatic  #21                 // Method java/lang/Boolean.valueOf:(Ljava/lang/String;)Ljava/lang/Boolean;
     149: invokevirtual #22                 // Method setForce:(Ljava/lang/Boolean;)V
     152: aload_1
     153: areturn

  public org.apache.dubbo.registry.client.migration.model.SubMigrationRule();
    Code:
       0: aload_0
       1: invokespecial #23                 // Method java/lang/Object."<init>":()V
       4: return

  public org.apache.dubbo.registry.client.migration.model.SubMigrationRule(java.lang.String, org.apache.dubbo.registry.client.migration.model.MigrationStep, java.lang.Float, java.lang.Integer);
    Code:
       0: aload_0
       1: invokespecial #23                 // Method java/lang/Object."<init>":()V
       4: aload_0
       5: aload_1
       6: putfield      #24                 // Field serviceKey:Ljava/lang/String;
       9: aload_0
      10: aload_2
      11: putfield      #25                 // Field step:Lorg/apache/dubbo/registry/client/migration/model/MigrationStep;
      14: aload_0
      15: aload_3
      16: putfield      #26                 // Field threshold:Ljava/lang/Float;
      19: aload_0
      20: aload         4
      22: putfield      #27                 // Field proportion:Ljava/lang/Integer;
      25: return

  public java.lang.String getServiceKey();
    Code:
       0: aload_0
       1: getfield      #24                 // Field serviceKey:Ljava/lang/String;
       4: areturn

  public void setServiceKey(java.lang.String);
    Code:
       0: aload_0
       1: aload_1
       2: putfield      #24                 // Field serviceKey:Ljava/lang/String;
       5: return

  public org.apache.dubbo.registry.client.migration.model.MigrationStep getStep();
    Code:
       0: aload_0
       1: getfield      #25                 // Field step:Lorg/apache/dubbo/registry/client/migration/model/MigrationStep;
       4: areturn

  public void setStep(org.apache.dubbo.registry.client.migration.model.MigrationStep);
    Code:
       0: aload_0
       1: aload_1
       2: putfield      #25                 // Field step:Lorg/apache/dubbo/registry/client/migration/model/MigrationStep;
       5: return

  public java.lang.Float getThreshold();
    Code:
       0: aload_0
       1: getfield      #26                 // Field threshold:Ljava/lang/Float;
       4: areturn

  public void setThreshold(java.lang.Float);
    Code:
       0: aload_0
       1: aload_1
       2: putfield      #26                 // Field threshold:Ljava/lang/Float;
       5: return

  public java.lang.Integer getProportion();
    Code:
       0: aload_0
       1: getfield      #27                 // Field proportion:Ljava/lang/Integer;
       4: areturn

  public void setProportion(java.lang.Integer);
    Code:
       0: aload_0
       1: aload_1
       2: putfield      #27                 // Field proportion:Ljava/lang/Integer;
       5: return

  public java.lang.Integer getDelay();
    Code:
       0: aload_0
       1: getfield      #28                 // Field delay:Ljava/lang/Integer;
       4: areturn

  public void setDelay(java.lang.Integer);
    Code:
       0: aload_0
       1: aload_1
       2: putfield      #28                 // Field delay:Ljava/lang/Integer;
       5: return

  public java.lang.Boolean getForce();
    Code:
       0: aload_0
       1: getfield      #29                 // Field force:Ljava/lang/Boolean;
       4: areturn

  public void setForce(java.lang.Boolean);
    Code:
       0: aload_0
       1: aload_1
       2: putfield      #29                 // Field force:Ljava/lang/Boolean;
       5: return
}
