Compiled from "Detector.java"
final class com.google.zxing.aztec.detector.Detector$Point {
  private final int x;

  private final int y;

  com.google.zxing.ResultPoint toResultPoint();
    Code:
       0: new           #1                  // class com/google/zxing/ResultPoint
       3: dup
       4: aload_0
       5: getfield      #2                  // Field x:I
       8: i2f
       9: aload_0
      10: getfield      #3                  // Field y:I
      13: i2f
      14: invokespecial #4                  // Method com/google/zxing/ResultPoint."<init>":(FF)V
      17: areturn

  com.google.zxing.aztec.detector.Detector$Point(int, int);
    Code:
       0: aload_0
       1: invokespecial #5                  // Method java/lang/Object."<init>":()V
       4: aload_0
       5: iload_1
       6: putfield      #2                  // Field x:I
       9: aload_0
      10: iload_2
      11: putfield      #3                  // Field y:I
      14: return

  int getX();
    Code:
       0: aload_0
       1: getfield      #2                  // Field x:I
       4: ireturn

  int getY();
    Code:
       0: aload_0
       1: getfield      #3                  // Field y:I
       4: ireturn

  public java.lang.String toString();
    Code:
       0: new           #6                  // class java/lang/StringBuilder
       3: dup
       4: invokespecial #7                  // Method java/lang/StringBuilder."<init>":()V
       7: ldc           #8                  // String <
       9: invokevirtual #9                  // Method java/lang/StringBuilder.append:(Ljava/lang/String;)Ljava/lang/StringBuilder;
      12: aload_0
      13: getfield      #2                  // Field x:I
      16: invokevirtual #10                 // Method java/lang/StringBuilder.append:(I)Ljava/lang/StringBuilder;
      19: bipush        32
      21: invokevirtual #11                 // Method java/lang/StringBuilder.append:(C)Ljava/lang/StringBuilder;
      24: aload_0
      25: getfield      #3                  // Field y:I
      28: invokevirtual #10                 // Method java/lang/StringBuilder.append:(I)Ljava/lang/StringBuilder;
      31: bipush        62
      33: invokevirtual #11                 // Method java/lang/StringBuilder.append:(C)Ljava/lang/StringBuilder;
      36: invokevirtual #12                 // Method java/lang/StringBuilder.toString:()Ljava/lang/String;
      39: areturn
}
