Compiled from "HealthStatusManager.java"
public class org.apache.dubbo.rpc.protocol.tri.service.HealthStatusManager {
  public static final java.lang.String SERVICE_NAME_ALL_SERVICES;

  private final org.apache.dubbo.rpc.protocol.tri.service.TriHealthImpl healthService;

  public org.apache.dubbo.rpc.protocol.tri.service.HealthStatusManager(org.apache.dubbo.rpc.protocol.tri.service.TriHealthImpl);
    Code:
       0: aload_0
       1: invokespecial #1                  // Method java/lang/Object."<init>":()V
       4: aload_0
       5: aload_1
       6: putfield      #2                  // Field healthService:Lorg/apache/dubbo/rpc/protocol/tri/service/TriHealthImpl;
       9: return

  public io.grpc.health.v1.Health getHealthService();
    Code:
       0: aload_0
       1: getfield      #2                  // Field healthService:Lorg/apache/dubbo/rpc/protocol/tri/service/TriHealthImpl;
       4: areturn

  public void setStatus(java.lang.String, io.grpc.health.v1.HealthCheckResponse$ServingStatus);
    Code:
       0: aload_0
       1: getfield      #2                  // Field healthService:Lorg/apache/dubbo/rpc/protocol/tri/service/TriHealthImpl;
       4: aload_1
       5: aload_2
       6: invokevirtual #3                  // Method org/apache/dubbo/rpc/protocol/tri/service/TriHealthImpl.setStatus:(Ljava/lang/String;Lio/grpc/health/v1/HealthCheckResponse$ServingStatus;)V
       9: return

  public void clearStatus(java.lang.String);
    Code:
       0: aload_0
       1: getfield      #2                  // Field healthService:Lorg/apache/dubbo/rpc/protocol/tri/service/TriHealthImpl;
       4: aload_1
       5: invokevirtual #4                  // Method org/apache/dubbo/rpc/protocol/tri/service/TriHealthImpl.clearStatus:(Ljava/lang/String;)V
       8: return

  public void enterTerminalState();
    Code:
       0: aload_0
       1: getfield      #2                  // Field healthService:Lorg/apache/dubbo/rpc/protocol/tri/service/TriHealthImpl;
       4: invokevirtual #5                  // Method org/apache/dubbo/rpc/protocol/tri/service/TriHealthImpl.enterTerminalState:()V
       7: return
}
