Compiled from "ReflectionV1AlphaService.java"
public class org.apache.dubbo.rpc.protocol.tri.service.ReflectionV1AlphaService extends io.grpc.reflection.v1alpha.DubboServerReflectionTriple$ServerReflectionImplBase {
  public org.apache.dubbo.rpc.protocol.tri.service.ReflectionV1AlphaService();
    Code:
       0: aload_0
       1: invokespecial #7                  // Method io/grpc/reflection/v1alpha/DubboServerReflectionTriple$ServerReflectionImplBase."<init>":()V
       4: return

  public org.apache.dubbo.common.stream.StreamObserver<io.grpc.reflection.v1alpha.ServerReflectionRequest> serverReflectionInfo(org.apache.dubbo.common.stream.StreamObserver<io.grpc.reflection.v1alpha.ServerReflectionResponse>);
    Code:
       0: new           #8                  // class org/apache/dubbo/rpc/protocol/tri/service/ReflectionV1AlphaService$1
       3: dup
       4: aload_0
       5: aload_1
       6: invokespecial #9                  // Method org/apache/dubbo/rpc/protocol/tri/service/ReflectionV1AlphaService$1."<init>":(Lorg/apache/dubbo/rpc/protocol/tri/service/ReflectionV1AlphaService;Lorg/apache/dubbo/common/stream/StreamObserver;)V
       9: areturn

  private void getFileByName(io.grpc.reflection.v1alpha.ServerReflectionRequest, org.apache.dubbo.common.stream.StreamObserver<io.grpc.reflection.v1alpha.ServerReflectionResponse>);
    Code:
       0: aload_1
       1: invokevirtual #10                 // Method io/grpc/reflection/v1alpha/ServerReflectionRequest.getFileByFilename:()Ljava/lang/String;
       4: astore_3
       5: aload_3
       6: invokestatic  #11                 // Method org/apache/dubbo/rpc/protocol/tri/service/SchemaDescriptorRegistry.getSchemaDescriptor:(Ljava/lang/String;)Lcom/google/protobuf/Descriptors$FileDescriptor;
       9: astore        4
      11: aload         4
      13: ifnull        32
      16: aload_2
      17: aload_0
      18: aload_1
      19: aload         4
      21: invokespecial #12                 // Method createServerReflectionResponse:(Lio/grpc/reflection/v1alpha/ServerReflectionRequest;Lcom/google/protobuf/Descriptors$FileDescriptor;)Lio/grpc/reflection/v1alpha/ServerReflectionResponse;
      24: invokeinterface #13,  2           // InterfaceMethod org/apache/dubbo/common/stream/StreamObserver.onNext:(Ljava/lang/Object;)V
      29: goto          43
      32: aload_0
      33: aload_1
      34: getstatic     #14                 // Field org/apache/dubbo/rpc/TriRpcStatus$Code.NOT_FOUND:Lorg/apache/dubbo/rpc/TriRpcStatus$Code;
      37: ldc           #15                 // String File not found.
      39: aload_2
      40: invokespecial #1                  // Method sendErrorResponse:(Lio/grpc/reflection/v1alpha/ServerReflectionRequest;Lorg/apache/dubbo/rpc/TriRpcStatus$Code;Ljava/lang/String;Lorg/apache/dubbo/common/stream/StreamObserver;)V
      43: return

  private void getFileContainingSymbol(io.grpc.reflection.v1alpha.ServerReflectionRequest, org.apache.dubbo.common.stream.StreamObserver<io.grpc.reflection.v1alpha.ServerReflectionResponse>);
    Code:
       0: aload_1
       1: invokevirtual #16                 // Method io/grpc/reflection/v1alpha/ServerReflectionRequest.getFileContainingSymbol:()Ljava/lang/String;
       4: astore_3
       5: aload_3
       6: invokestatic  #11                 // Method org/apache/dubbo/rpc/protocol/tri/service/SchemaDescriptorRegistry.getSchemaDescriptor:(Ljava/lang/String;)Lcom/google/protobuf/Descriptors$FileDescriptor;
       9: astore        4
      11: aload         4
      13: ifnull        32
      16: aload_2
      17: aload_0
      18: aload_1
      19: aload         4
      21: invokespecial #12                 // Method createServerReflectionResponse:(Lio/grpc/reflection/v1alpha/ServerReflectionRequest;Lcom/google/protobuf/Descriptors$FileDescriptor;)Lio/grpc/reflection/v1alpha/ServerReflectionResponse;
      24: invokeinterface #13,  2           // InterfaceMethod org/apache/dubbo/common/stream/StreamObserver.onNext:(Ljava/lang/Object;)V
      29: goto          43
      32: aload_0
      33: aload_1
      34: getstatic     #14                 // Field org/apache/dubbo/rpc/TriRpcStatus$Code.NOT_FOUND:Lorg/apache/dubbo/rpc/TriRpcStatus$Code;
      37: ldc           #17                 // String Symbol not found.
      39: aload_2
      40: invokespecial #1                  // Method sendErrorResponse:(Lio/grpc/reflection/v1alpha/ServerReflectionRequest;Lorg/apache/dubbo/rpc/TriRpcStatus$Code;Ljava/lang/String;Lorg/apache/dubbo/common/stream/StreamObserver;)V
      43: return

  private void getFileByExtension(io.grpc.reflection.v1alpha.ServerReflectionRequest, org.apache.dubbo.common.stream.StreamObserver<io.grpc.reflection.v1alpha.ServerReflectionResponse>);
    Code:
       0: aload_1
       1: invokevirtual #18                 // Method io/grpc/reflection/v1alpha/ServerReflectionRequest.getFileContainingExtension:()Lio/grpc/reflection/v1alpha/ExtensionRequest;
       4: astore_3
       5: aload_3
       6: invokevirtual #19                 // Method io/grpc/reflection/v1alpha/ExtensionRequest.getContainingType:()Ljava/lang/String;
       9: astore        4
      11: aload_3
      12: invokevirtual #20                 // Method io/grpc/reflection/v1alpha/ExtensionRequest.getExtensionNumber:()I
      15: istore        5
      17: aload         4
      19: iload         5
      21: invokestatic  #21                 // Method org/apache/dubbo/rpc/protocol/tri/service/SchemaDescriptorRegistry.getFileDescriptorByExtensionAndNumber:(Ljava/lang/String;I)Lcom/google/protobuf/Descriptors$FileDescriptor;
      24: astore        6
      26: aload         6
      28: ifnull        47
      31: aload_2
      32: aload_0
      33: aload_1
      34: aload         6
      36: invokespecial #12                 // Method createServerReflectionResponse:(Lio/grpc/reflection/v1alpha/ServerReflectionRequest;Lcom/google/protobuf/Descriptors$FileDescriptor;)Lio/grpc/reflection/v1alpha/ServerReflectionResponse;
      39: invokeinterface #13,  2           // InterfaceMethod org/apache/dubbo/common/stream/StreamObserver.onNext:(Ljava/lang/Object;)V
      44: goto          58
      47: aload_0
      48: aload_1
      49: getstatic     #14                 // Field org/apache/dubbo/rpc/TriRpcStatus$Code.NOT_FOUND:Lorg/apache/dubbo/rpc/TriRpcStatus$Code;
      52: ldc           #22                 // String Extension not found.
      54: aload_2
      55: invokespecial #1                  // Method sendErrorResponse:(Lio/grpc/reflection/v1alpha/ServerReflectionRequest;Lorg/apache/dubbo/rpc/TriRpcStatus$Code;Ljava/lang/String;Lorg/apache/dubbo/common/stream/StreamObserver;)V
      58: return

  private void getAllExtensions(io.grpc.reflection.v1alpha.ServerReflectionRequest, org.apache.dubbo.common.stream.StreamObserver<io.grpc.reflection.v1alpha.ServerReflectionResponse>);
    Code:
       0: aload_1
       1: invokevirtual #23                 // Method io/grpc/reflection/v1alpha/ServerReflectionRequest.getAllExtensionNumbersOfType:()Ljava/lang/String;
       4: astore_3
       5: aload_3
       6: invokestatic  #24                 // Method org/apache/dubbo/rpc/protocol/tri/service/SchemaDescriptorRegistry.getExtensionNumbers:(Ljava/lang/String;)Ljava/util/Set;
       9: astore        4
      11: aload         4
      13: ifnull        61
      16: invokestatic  #25                 // Method io/grpc/reflection/v1alpha/ExtensionNumberResponse.newBuilder:()Lio/grpc/reflection/v1alpha/ExtensionNumberResponse$Builder;
      19: aload_3
      20: invokevirtual #26                 // Method io/grpc/reflection/v1alpha/ExtensionNumberResponse$Builder.setBaseTypeName:(Ljava/lang/String;)Lio/grpc/reflection/v1alpha/ExtensionNumberResponse$Builder;
      23: aload         4
      25: invokevirtual #27                 // Method io/grpc/reflection/v1alpha/ExtensionNumberResponse$Builder.addAllExtensionNumber:(Ljava/lang/Iterable;)Lio/grpc/reflection/v1alpha/ExtensionNumberResponse$Builder;
      28: astore        5
      30: aload_2
      31: invokestatic  #28                 // Method io/grpc/reflection/v1alpha/ServerReflectionResponse.newBuilder:()Lio/grpc/reflection/v1alpha/ServerReflectionResponse$Builder;
      34: aload_1
      35: invokevirtual #29                 // Method io/grpc/reflection/v1alpha/ServerReflectionRequest.getHost:()Ljava/lang/String;
      38: invokevirtual #30                 // Method io/grpc/reflection/v1alpha/ServerReflectionResponse$Builder.setValidHost:(Ljava/lang/String;)Lio/grpc/reflection/v1alpha/ServerReflectionResponse$Builder;
      41: aload_1
      42: invokevirtual #31                 // Method io/grpc/reflection/v1alpha/ServerReflectionResponse$Builder.setOriginalRequest:(Lio/grpc/reflection/v1alpha/ServerReflectionRequest;)Lio/grpc/reflection/v1alpha/ServerReflectionResponse$Builder;
      45: aload         5
      47: invokevirtual #32                 // Method io/grpc/reflection/v1alpha/ServerReflectionResponse$Builder.setAllExtensionNumbersResponse:(Lio/grpc/reflection/v1alpha/ExtensionNumberResponse$Builder;)Lio/grpc/reflection/v1alpha/ServerReflectionResponse$Builder;
      50: invokevirtual #33                 // Method io/grpc/reflection/v1alpha/ServerReflectionResponse$Builder.build:()Lio/grpc/reflection/v1alpha/ServerReflectionResponse;
      53: invokeinterface #13,  2           // InterfaceMethod org/apache/dubbo/common/stream/StreamObserver.onNext:(Ljava/lang/Object;)V
      58: goto          72
      61: aload_0
      62: aload_1
      63: getstatic     #14                 // Field org/apache/dubbo/rpc/TriRpcStatus$Code.NOT_FOUND:Lorg/apache/dubbo/rpc/TriRpcStatus$Code;
      66: ldc           #34                 // String Type not found.
      68: aload_2
      69: invokespecial #1                  // Method sendErrorResponse:(Lio/grpc/reflection/v1alpha/ServerReflectionRequest;Lorg/apache/dubbo/rpc/TriRpcStatus$Code;Ljava/lang/String;Lorg/apache/dubbo/common/stream/StreamObserver;)V
      72: return

  private void listServices(io.grpc.reflection.v1alpha.ServerReflectionRequest, org.apache.dubbo.common.stream.StreamObserver<io.grpc.reflection.v1alpha.ServerReflectionResponse>);
    Code:
       0: invokestatic  #35                 // Method io/grpc/reflection/v1alpha/ListServiceResponse.newBuilder:()Lio/grpc/reflection/v1alpha/ListServiceResponse$Builder;
       3: astore_3
       4: invokestatic  #36                 // Method org/apache/dubbo/rpc/protocol/tri/service/SchemaDescriptorRegistry.listServiceNames:()Ljava/util/List;
       7: invokeinterface #37,  1           // InterfaceMethod java/util/List.iterator:()Ljava/util/Iterator;
      12: astore        4
      14: aload         4
      16: invokeinterface #38,  1           // InterfaceMethod java/util/Iterator.hasNext:()Z
      21: ifeq          52
      24: aload         4
      26: invokeinterface #39,  1           // InterfaceMethod java/util/Iterator.next:()Ljava/lang/Object;
      31: checkcast     #40                 // class java/lang/String
      34: astore        5
      36: aload_3
      37: invokestatic  #41                 // Method io/grpc/reflection/v1alpha/ServiceResponse.newBuilder:()Lio/grpc/reflection/v1alpha/ServiceResponse$Builder;
      40: aload         5
      42: invokevirtual #42                 // Method io/grpc/reflection/v1alpha/ServiceResponse$Builder.setName:(Ljava/lang/String;)Lio/grpc/reflection/v1alpha/ServiceResponse$Builder;
      45: invokevirtual #43                 // Method io/grpc/reflection/v1alpha/ListServiceResponse$Builder.addService:(Lio/grpc/reflection/v1alpha/ServiceResponse$Builder;)Lio/grpc/reflection/v1alpha/ListServiceResponse$Builder;
      48: pop
      49: goto          14
      52: aload_2
      53: invokestatic  #28                 // Method io/grpc/reflection/v1alpha/ServerReflectionResponse.newBuilder:()Lio/grpc/reflection/v1alpha/ServerReflectionResponse$Builder;
      56: aload_1
      57: invokevirtual #29                 // Method io/grpc/reflection/v1alpha/ServerReflectionRequest.getHost:()Ljava/lang/String;
      60: invokevirtual #30                 // Method io/grpc/reflection/v1alpha/ServerReflectionResponse$Builder.setValidHost:(Ljava/lang/String;)Lio/grpc/reflection/v1alpha/ServerReflectionResponse$Builder;
      63: aload_1
      64: invokevirtual #31                 // Method io/grpc/reflection/v1alpha/ServerReflectionResponse$Builder.setOriginalRequest:(Lio/grpc/reflection/v1alpha/ServerReflectionRequest;)Lio/grpc/reflection/v1alpha/ServerReflectionResponse$Builder;
      67: aload_3
      68: invokevirtual #44                 // Method io/grpc/reflection/v1alpha/ServerReflectionResponse$Builder.setListServicesResponse:(Lio/grpc/reflection/v1alpha/ListServiceResponse$Builder;)Lio/grpc/reflection/v1alpha/ServerReflectionResponse$Builder;
      71: invokevirtual #33                 // Method io/grpc/reflection/v1alpha/ServerReflectionResponse$Builder.build:()Lio/grpc/reflection/v1alpha/ServerReflectionResponse;
      74: invokeinterface #13,  2           // InterfaceMethod org/apache/dubbo/common/stream/StreamObserver.onNext:(Ljava/lang/Object;)V
      79: return

  private void sendErrorResponse(io.grpc.reflection.v1alpha.ServerReflectionRequest, org.apache.dubbo.rpc.TriRpcStatus$Code, java.lang.String, org.apache.dubbo.common.stream.StreamObserver<io.grpc.reflection.v1alpha.ServerReflectionResponse>);
    Code:
       0: invokestatic  #28                 // Method io/grpc/reflection/v1alpha/ServerReflectionResponse.newBuilder:()Lio/grpc/reflection/v1alpha/ServerReflectionResponse$Builder;
       3: aload_1
       4: invokevirtual #29                 // Method io/grpc/reflection/v1alpha/ServerReflectionRequest.getHost:()Ljava/lang/String;
       7: invokevirtual #30                 // Method io/grpc/reflection/v1alpha/ServerReflectionResponse$Builder.setValidHost:(Ljava/lang/String;)Lio/grpc/reflection/v1alpha/ServerReflectionResponse$Builder;
      10: aload_1
      11: invokevirtual #31                 // Method io/grpc/reflection/v1alpha/ServerReflectionResponse$Builder.setOriginalRequest:(Lio/grpc/reflection/v1alpha/ServerReflectionRequest;)Lio/grpc/reflection/v1alpha/ServerReflectionResponse$Builder;
      14: invokestatic  #45                 // Method io/grpc/reflection/v1alpha/ErrorResponse.newBuilder:()Lio/grpc/reflection/v1alpha/ErrorResponse$Builder;
      17: aload_2
      18: getfield      #46                 // Field org/apache/dubbo/rpc/TriRpcStatus$Code.code:I
      21: invokevirtual #47                 // Method io/grpc/reflection/v1alpha/ErrorResponse$Builder.setErrorCode:(I)Lio/grpc/reflection/v1alpha/ErrorResponse$Builder;
      24: aload_3
      25: invokevirtual #48                 // Method io/grpc/reflection/v1alpha/ErrorResponse$Builder.setErrorMessage:(Ljava/lang/String;)Lio/grpc/reflection/v1alpha/ErrorResponse$Builder;
      28: invokevirtual #49                 // Method io/grpc/reflection/v1alpha/ServerReflectionResponse$Builder.setErrorResponse:(Lio/grpc/reflection/v1alpha/ErrorResponse$Builder;)Lio/grpc/reflection/v1alpha/ServerReflectionResponse$Builder;
      31: invokevirtual #33                 // Method io/grpc/reflection/v1alpha/ServerReflectionResponse$Builder.build:()Lio/grpc/reflection/v1alpha/ServerReflectionResponse;
      34: astore        5
      36: aload         4
      38: aload         5
      40: invokeinterface #13,  2           // InterfaceMethod org/apache/dubbo/common/stream/StreamObserver.onNext:(Ljava/lang/Object;)V
      45: return

  private io.grpc.reflection.v1alpha.ServerReflectionResponse createServerReflectionResponse(io.grpc.reflection.v1alpha.ServerReflectionRequest, com.google.protobuf.Descriptors$FileDescriptor);
    Code:
       0: invokestatic  #50                 // Method io/grpc/reflection/v1alpha/FileDescriptorResponse.newBuilder:()Lio/grpc/reflection/v1alpha/FileDescriptorResponse$Builder;
       3: astore_3
       4: new           #51                 // class java/util/HashSet
       7: dup
       8: invokespecial #52                 // Method java/util/HashSet."<init>":()V
      11: astore        4
      13: new           #53                 // class java/util/ArrayDeque
      16: dup
      17: invokespecial #54                 // Method java/util/ArrayDeque."<init>":()V
      20: astore        5
      22: aload         4
      24: aload_2
      25: invokevirtual #55                 // Method com/google/protobuf/Descriptors$FileDescriptor.getName:()Ljava/lang/String;
      28: invokeinterface #56,  2           // InterfaceMethod java/util/Set.add:(Ljava/lang/Object;)Z
      33: pop
      34: aload         5
      36: aload_2
      37: invokeinterface #57,  2           // InterfaceMethod java/util/Queue.add:(Ljava/lang/Object;)Z
      42: pop
      43: aload         5
      45: invokeinterface #58,  1           // InterfaceMethod java/util/Queue.isEmpty:()Z
      50: ifne          156
      53: aload         5
      55: invokeinterface #59,  1           // InterfaceMethod java/util/Queue.remove:()Ljava/lang/Object;
      60: checkcast     #60                 // class com/google/protobuf/Descriptors$FileDescriptor
      63: astore        6
      65: aload_3
      66: aload         6
      68: invokevirtual #61                 // Method com/google/protobuf/Descriptors$FileDescriptor.toProto:()Lcom/google/protobuf/DescriptorProtos$FileDescriptorProto;
      71: invokevirtual #62                 // Method com/google/protobuf/DescriptorProtos$FileDescriptorProto.toByteString:()Lcom/google/protobuf/ByteString;
      74: invokevirtual #63                 // Method io/grpc/reflection/v1alpha/FileDescriptorResponse$Builder.addFileDescriptorProto:(Lcom/google/protobuf/ByteString;)Lio/grpc/reflection/v1alpha/FileDescriptorResponse$Builder;
      77: pop
      78: aload         6
      80: invokevirtual #64                 // Method com/google/protobuf/Descriptors$FileDescriptor.getDependencies:()Ljava/util/List;
      83: invokeinterface #37,  1           // InterfaceMethod java/util/List.iterator:()Ljava/util/Iterator;
      88: astore        7
      90: aload         7
      92: invokeinterface #38,  1           // InterfaceMethod java/util/Iterator.hasNext:()Z
      97: ifeq          153
     100: aload         7
     102: invokeinterface #39,  1           // InterfaceMethod java/util/Iterator.next:()Ljava/lang/Object;
     107: checkcast     #60                 // class com/google/protobuf/Descriptors$FileDescriptor
     110: astore        8
     112: aload         4
     114: aload         8
     116: invokevirtual #55                 // Method com/google/protobuf/Descriptors$FileDescriptor.getName:()Ljava/lang/String;
     119: invokeinterface #65,  2           // InterfaceMethod java/util/Set.contains:(Ljava/lang/Object;)Z
     124: ifne          150
     127: aload         4
     129: aload         8
     131: invokevirtual #55                 // Method com/google/protobuf/Descriptors$FileDescriptor.getName:()Ljava/lang/String;
     134: invokeinterface #56,  2           // InterfaceMethod java/util/Set.add:(Ljava/lang/Object;)Z
     139: pop
     140: aload         5
     142: aload         8
     144: invokeinterface #57,  2           // InterfaceMethod java/util/Queue.add:(Ljava/lang/Object;)Z
     149: pop
     150: goto          90
     153: goto          43
     156: invokestatic  #28                 // Method io/grpc/reflection/v1alpha/ServerReflectionResponse.newBuilder:()Lio/grpc/reflection/v1alpha/ServerReflectionResponse$Builder;
     159: aload_1
     160: invokevirtual #29                 // Method io/grpc/reflection/v1alpha/ServerReflectionRequest.getHost:()Ljava/lang/String;
     163: invokevirtual #30                 // Method io/grpc/reflection/v1alpha/ServerReflectionResponse$Builder.setValidHost:(Ljava/lang/String;)Lio/grpc/reflection/v1alpha/ServerReflectionResponse$Builder;
     166: aload_1
     167: invokevirtual #31                 // Method io/grpc/reflection/v1alpha/ServerReflectionResponse$Builder.setOriginalRequest:(Lio/grpc/reflection/v1alpha/ServerReflectionRequest;)Lio/grpc/reflection/v1alpha/ServerReflectionResponse$Builder;
     170: aload_3
     171: invokevirtual #66                 // Method io/grpc/reflection/v1alpha/ServerReflectionResponse$Builder.setFileDescriptorResponse:(Lio/grpc/reflection/v1alpha/FileDescriptorResponse$Builder;)Lio/grpc/reflection/v1alpha/ServerReflectionResponse$Builder;
     174: invokevirtual #33                 // Method io/grpc/reflection/v1alpha/ServerReflectionResponse$Builder.build:()Lio/grpc/reflection/v1alpha/ServerReflectionResponse;
     177: areturn

  static void access$000(org.apache.dubbo.rpc.protocol.tri.service.ReflectionV1AlphaService, io.grpc.reflection.v1alpha.ServerReflectionRequest, org.apache.dubbo.common.stream.StreamObserver);
    Code:
       0: aload_0
       1: aload_1
       2: aload_2
       3: invokespecial #6                  // Method getFileByName:(Lio/grpc/reflection/v1alpha/ServerReflectionRequest;Lorg/apache/dubbo/common/stream/StreamObserver;)V
       6: return

  static void access$100(org.apache.dubbo.rpc.protocol.tri.service.ReflectionV1AlphaService, io.grpc.reflection.v1alpha.ServerReflectionRequest, org.apache.dubbo.common.stream.StreamObserver);
    Code:
       0: aload_0
       1: aload_1
       2: aload_2
       3: invokespecial #5                  // Method getFileContainingSymbol:(Lio/grpc/reflection/v1alpha/ServerReflectionRequest;Lorg/apache/dubbo/common/stream/StreamObserver;)V
       6: return

  static void access$200(org.apache.dubbo.rpc.protocol.tri.service.ReflectionV1AlphaService, io.grpc.reflection.v1alpha.ServerReflectionRequest, org.apache.dubbo.common.stream.StreamObserver);
    Code:
       0: aload_0
       1: aload_1
       2: aload_2
       3: invokespecial #4                  // Method getFileByExtension:(Lio/grpc/reflection/v1alpha/ServerReflectionRequest;Lorg/apache/dubbo/common/stream/StreamObserver;)V
       6: return

  static void access$300(org.apache.dubbo.rpc.protocol.tri.service.ReflectionV1AlphaService, io.grpc.reflection.v1alpha.ServerReflectionRequest, org.apache.dubbo.common.stream.StreamObserver);
    Code:
       0: aload_0
       1: aload_1
       2: aload_2
       3: invokespecial #3                  // Method getAllExtensions:(Lio/grpc/reflection/v1alpha/ServerReflectionRequest;Lorg/apache/dubbo/common/stream/StreamObserver;)V
       6: return

  static void access$400(org.apache.dubbo.rpc.protocol.tri.service.ReflectionV1AlphaService, io.grpc.reflection.v1alpha.ServerReflectionRequest, org.apache.dubbo.common.stream.StreamObserver);
    Code:
       0: aload_0
       1: aload_1
       2: aload_2
       3: invokespecial #2                  // Method listServices:(Lio/grpc/reflection/v1alpha/ServerReflectionRequest;Lorg/apache/dubbo/common/stream/StreamObserver;)V
       6: return

  static void access$500(org.apache.dubbo.rpc.protocol.tri.service.ReflectionV1AlphaService, io.grpc.reflection.v1alpha.ServerReflectionRequest, org.apache.dubbo.rpc.TriRpcStatus$Code, java.lang.String, org.apache.dubbo.common.stream.StreamObserver);
    Code:
       0: aload_0
       1: aload_1
       2: aload_2
       3: aload_3
       4: aload         4
       6: invokespecial #1                  // Method sendErrorResponse:(Lio/grpc/reflection/v1alpha/ServerReflectionRequest;Lorg/apache/dubbo/rpc/TriRpcStatus$Code;Ljava/lang/String;Lorg/apache/dubbo/common/stream/StreamObserver;)V
       9: return
}
