Compiled from "ReflectionV1AlphaService.java"
class org.apache.dubbo.rpc.protocol.tri.service.ReflectionV1AlphaService$1 implements org.apache.dubbo.common.stream.StreamObserver<io.grpc.reflection.v1alpha.ServerReflectionRequest> {
  final org.apache.dubbo.common.stream.StreamObserver val$responseObserver;

  final org.apache.dubbo.rpc.protocol.tri.service.ReflectionV1AlphaService this$0;

  org.apache.dubbo.rpc.protocol.tri.service.ReflectionV1AlphaService$1(org.apache.dubbo.rpc.protocol.tri.service.ReflectionV1AlphaService, org.apache.dubbo.common.stream.StreamObserver);
    Code:
       0: aload_0
       1: aload_1
       2: putfield      #1                  // Field this$0:Lorg/apache/dubbo/rpc/protocol/tri/service/ReflectionV1AlphaService;
       5: aload_0
       6: aload_2
       7: putfield      #2                  // Field val$responseObserver:Lorg/apache/dubbo/common/stream/StreamObserver;
      10: aload_0
      11: invokespecial #3                  // Method java/lang/Object."<init>":()V
      14: return

  public void onNext(io.grpc.reflection.v1alpha.ServerReflectionRequest);
    Code:
       0: getstatic     #4                  // Field org/apache/dubbo/rpc/protocol/tri/service/ReflectionV1AlphaService$2.$SwitchMap$io$grpc$reflection$v1alpha$ServerReflectionRequest$MessageRequestCase:[I
       3: aload_1
       4: invokevirtual #5                  // Method io/grpc/reflection/v1alpha/ServerReflectionRequest.getMessageRequestCase:()Lio/grpc/reflection/v1alpha/ServerReflectionRequest$MessageRequestCase;
       7: invokevirtual #6                  // Method io/grpc/reflection/v1alpha/ServerReflectionRequest$MessageRequestCase.ordinal:()I
      10: iaload
      11: tableswitch   { // 1 to 5
                     1: 44
                     2: 59
                     3: 74
                     4: 89
                     5: 104
               default: 119
          }
      44: aload_0
      45: getfield      #1                  // Field this$0:Lorg/apache/dubbo/rpc/protocol/tri/service/ReflectionV1AlphaService;
      48: aload_1
      49: aload_0
      50: getfield      #2                  // Field val$responseObserver:Lorg/apache/dubbo/common/stream/StreamObserver;
      53: invokestatic  #7                  // Method org/apache/dubbo/rpc/protocol/tri/service/ReflectionV1AlphaService.access$000:(Lorg/apache/dubbo/rpc/protocol/tri/service/ReflectionV1AlphaService;Lio/grpc/reflection/v1alpha/ServerReflectionRequest;Lorg/apache/dubbo/common/stream/StreamObserver;)V
      56: goto          156
      59: aload_0
      60: getfield      #1                  // Field this$0:Lorg/apache/dubbo/rpc/protocol/tri/service/ReflectionV1AlphaService;
      63: aload_1
      64: aload_0
      65: getfield      #2                  // Field val$responseObserver:Lorg/apache/dubbo/common/stream/StreamObserver;
      68: invokestatic  #8                  // Method org/apache/dubbo/rpc/protocol/tri/service/ReflectionV1AlphaService.access$100:(Lorg/apache/dubbo/rpc/protocol/tri/service/ReflectionV1AlphaService;Lio/grpc/reflection/v1alpha/ServerReflectionRequest;Lorg/apache/dubbo/common/stream/StreamObserver;)V
      71: goto          156
      74: aload_0
      75: getfield      #1                  // Field this$0:Lorg/apache/dubbo/rpc/protocol/tri/service/ReflectionV1AlphaService;
      78: aload_1
      79: aload_0
      80: getfield      #2                  // Field val$responseObserver:Lorg/apache/dubbo/common/stream/StreamObserver;
      83: invokestatic  #9                  // Method org/apache/dubbo/rpc/protocol/tri/service/ReflectionV1AlphaService.access$200:(Lorg/apache/dubbo/rpc/protocol/tri/service/ReflectionV1AlphaService;Lio/grpc/reflection/v1alpha/ServerReflectionRequest;Lorg/apache/dubbo/common/stream/StreamObserver;)V
      86: goto          156
      89: aload_0
      90: getfield      #1                  // Field this$0:Lorg/apache/dubbo/rpc/protocol/tri/service/ReflectionV1AlphaService;
      93: aload_1
      94: aload_0
      95: getfield      #2                  // Field val$responseObserver:Lorg/apache/dubbo/common/stream/StreamObserver;
      98: invokestatic  #10                 // Method org/apache/dubbo/rpc/protocol/tri/service/ReflectionV1AlphaService.access$300:(Lorg/apache/dubbo/rpc/protocol/tri/service/ReflectionV1AlphaService;Lio/grpc/reflection/v1alpha/ServerReflectionRequest;Lorg/apache/dubbo/common/stream/StreamObserver;)V
     101: goto          156
     104: aload_0
     105: getfield      #1                  // Field this$0:Lorg/apache/dubbo/rpc/protocol/tri/service/ReflectionV1AlphaService;
     108: aload_1
     109: aload_0
     110: getfield      #2                  // Field val$responseObserver:Lorg/apache/dubbo/common/stream/StreamObserver;
     113: invokestatic  #11                 // Method org/apache/dubbo/rpc/protocol/tri/service/ReflectionV1AlphaService.access$400:(Lorg/apache/dubbo/rpc/protocol/tri/service/ReflectionV1AlphaService;Lio/grpc/reflection/v1alpha/ServerReflectionRequest;Lorg/apache/dubbo/common/stream/StreamObserver;)V
     116: goto          156
     119: aload_0
     120: getfield      #1                  // Field this$0:Lorg/apache/dubbo/rpc/protocol/tri/service/ReflectionV1AlphaService;
     123: aload_1
     124: getstatic     #12                 // Field org/apache/dubbo/rpc/TriRpcStatus$Code.UNIMPLEMENTED:Lorg/apache/dubbo/rpc/TriRpcStatus$Code;
     127: new           #13                 // class java/lang/StringBuilder
     130: dup
     131: invokespecial #14                 // Method java/lang/StringBuilder."<init>":()V
     134: ldc           #15                 // String not implemented
     136: invokevirtual #16                 // Method java/lang/StringBuilder.append:(Ljava/lang/String;)Ljava/lang/StringBuilder;
     139: aload_1
     140: invokevirtual #5                  // Method io/grpc/reflection/v1alpha/ServerReflectionRequest.getMessageRequestCase:()Lio/grpc/reflection/v1alpha/ServerReflectionRequest$MessageRequestCase;
     143: invokevirtual #17                 // Method java/lang/StringBuilder.append:(Ljava/lang/Object;)Ljava/lang/StringBuilder;
     146: invokevirtual #18                 // Method java/lang/StringBuilder.toString:()Ljava/lang/String;
     149: aload_0
     150: getfield      #2                  // Field val$responseObserver:Lorg/apache/dubbo/common/stream/StreamObserver;
     153: invokestatic  #19                 // Method org/apache/dubbo/rpc/protocol/tri/service/ReflectionV1AlphaService.access$500:(Lorg/apache/dubbo/rpc/protocol/tri/service/ReflectionV1AlphaService;Lio/grpc/reflection/v1alpha/ServerReflectionRequest;Lorg/apache/dubbo/rpc/TriRpcStatus$Code;Ljava/lang/String;Lorg/apache/dubbo/common/stream/StreamObserver;)V
     156: return

  public void onError(java.lang.Throwable);
    Code:
       0: aload_0
       1: getfield      #2                  // Field val$responseObserver:Lorg/apache/dubbo/common/stream/StreamObserver;
       4: aload_1
       5: invokeinterface #20,  2           // InterfaceMethod org/apache/dubbo/common/stream/StreamObserver.onError:(Ljava/lang/Throwable;)V
      10: return

  public void onCompleted();
    Code:
       0: aload_0
       1: getfield      #2                  // Field val$responseObserver:Lorg/apache/dubbo/common/stream/StreamObserver;
       4: invokeinterface #21,  1           // InterfaceMethod org/apache/dubbo/common/stream/StreamObserver.onCompleted:()V
       9: return

  public void onNext(java.lang.Object);
    Code:
       0: aload_0
       1: aload_1
       2: checkcast     #22                 // class io/grpc/reflection/v1alpha/ServerReflectionRequest
       5: invokevirtual #23                 // Method onNext:(Lio/grpc/reflection/v1alpha/ServerReflectionRequest;)V
       8: return
}
