Compiled from "SchemaDescriptorRegistry.java"
public class org.apache.dubbo.rpc.protocol.tri.service.SchemaDescriptorRegistry {
  private static final java.util.Map<java.lang.String, com.google.protobuf.Descriptors$FileDescriptor> DESCRIPTORS_BY_SYMBOL;

  private static final java.util.Map<java.lang.String, java.util.Map<java.lang.Integer, com.google.protobuf.Descriptors$FileDescriptor>> EXTENSIONS;

  private static final java.util.Set<java.lang.String> SERVICES;

  public org.apache.dubbo.rpc.protocol.tri.service.SchemaDescriptorRegistry();
    Code:
       0: aload_0
       1: invokespecial #1                  // Method java/lang/Object."<init>":()V
       4: return

  public static void addSchemaDescriptor(java.lang.String, com.google.protobuf.Descriptors$FileDescriptor);
    Code:
       0: getstatic     #2                  // Field SERVICES:Ljava/util/Set;
       3: aload_0
       4: invokeinterface #3,  2            // InterfaceMethod java/util/Set.add:(Ljava/lang/Object;)Z
       9: pop
      10: getstatic     #4                  // Field DESCRIPTORS_BY_SYMBOL:Ljava/util/Map;
      13: aload_0
      14: aload_1
      15: invokeinterface #5,  3            // InterfaceMethod java/util/Map.put:(Ljava/lang/Object;Ljava/lang/Object;)Ljava/lang/Object;
      20: pop
      21: aload_1
      22: invokevirtual #6                  // Method com/google/protobuf/Descriptors$FileDescriptor.getMessageTypes:()Ljava/util/List;
      25: invokeinterface #7,  1            // InterfaceMethod java/util/List.iterator:()Ljava/util/Iterator;
      30: astore_2
      31: aload_2
      32: invokeinterface #8,  1            // InterfaceMethod java/util/Iterator.hasNext:()Z
      37: ifeq          57
      40: aload_2
      41: invokeinterface #9,  1            // InterfaceMethod java/util/Iterator.next:()Ljava/lang/Object;
      46: checkcast     #10                 // class com/google/protobuf/Descriptors$Descriptor
      49: astore_3
      50: aload_3
      51: invokestatic  #11                 // Method addType:(Lcom/google/protobuf/Descriptors$Descriptor;)V
      54: goto          31
      57: aload_1
      58: invokevirtual #12                 // Method com/google/protobuf/Descriptors$FileDescriptor.getExtensions:()Ljava/util/List;
      61: invokeinterface #7,  1            // InterfaceMethod java/util/List.iterator:()Ljava/util/Iterator;
      66: astore_2
      67: aload_2
      68: invokeinterface #8,  1            // InterfaceMethod java/util/Iterator.hasNext:()Z
      73: ifeq          94
      76: aload_2
      77: invokeinterface #9,  1            // InterfaceMethod java/util/Iterator.next:()Ljava/lang/Object;
      82: checkcast     #13                 // class com/google/protobuf/Descriptors$FieldDescriptor
      85: astore_3
      86: aload_3
      87: aload_1
      88: invokestatic  #14                 // Method addExtension:(Lcom/google/protobuf/Descriptors$FieldDescriptor;Lcom/google/protobuf/Descriptors$FileDescriptor;)V
      91: goto          67
      94: return

  private static void addType(com.google.protobuf.Descriptors$Descriptor);
    Code:
       0: getstatic     #4                  // Field DESCRIPTORS_BY_SYMBOL:Ljava/util/Map;
       3: aload_0
       4: invokevirtual #15                 // Method com/google/protobuf/Descriptors$Descriptor.getFullName:()Ljava/lang/String;
       7: aload_0
       8: invokevirtual #16                 // Method com/google/protobuf/Descriptors$Descriptor.getFile:()Lcom/google/protobuf/Descriptors$FileDescriptor;
      11: invokeinterface #5,  3            // InterfaceMethod java/util/Map.put:(Ljava/lang/Object;Ljava/lang/Object;)Ljava/lang/Object;
      16: pop
      17: aload_0
      18: invokevirtual #17                 // Method com/google/protobuf/Descriptors$Descriptor.getNestedTypes:()Ljava/util/List;
      21: invokeinterface #7,  1            // InterfaceMethod java/util/List.iterator:()Ljava/util/Iterator;
      26: astore_1
      27: aload_1
      28: invokeinterface #8,  1            // InterfaceMethod java/util/Iterator.hasNext:()Z
      33: ifeq          53
      36: aload_1
      37: invokeinterface #9,  1            // InterfaceMethod java/util/Iterator.next:()Ljava/lang/Object;
      42: checkcast     #10                 // class com/google/protobuf/Descriptors$Descriptor
      45: astore_2
      46: aload_2
      47: invokestatic  #11                 // Method addType:(Lcom/google/protobuf/Descriptors$Descriptor;)V
      50: goto          27
      53: return

  private static void addExtension(com.google.protobuf.Descriptors$FieldDescriptor, com.google.protobuf.Descriptors$FileDescriptor);
    Code:
       0: aload_0
       1: invokevirtual #18                 // Method com/google/protobuf/Descriptors$FieldDescriptor.getContainingType:()Lcom/google/protobuf/Descriptors$Descriptor;
       4: invokevirtual #15                 // Method com/google/protobuf/Descriptors$Descriptor.getFullName:()Ljava/lang/String;
       7: astore_2
       8: aload_0
       9: invokevirtual #19                 // Method com/google/protobuf/Descriptors$FieldDescriptor.getNumber:()I
      12: istore_3
      13: getstatic     #20                 // Field EXTENSIONS:Ljava/util/Map;
      16: aload_2
      17: invokeinterface #21,  2           // InterfaceMethod java/util/Map.containsKey:(Ljava/lang/Object;)Z
      22: ifne          42
      25: getstatic     #20                 // Field EXTENSIONS:Ljava/util/Map;
      28: aload_2
      29: new           #22                 // class java/util/HashMap
      32: dup
      33: invokespecial #23                 // Method java/util/HashMap."<init>":()V
      36: invokeinterface #5,  3            // InterfaceMethod java/util/Map.put:(Ljava/lang/Object;Ljava/lang/Object;)Ljava/lang/Object;
      41: pop
      42: getstatic     #20                 // Field EXTENSIONS:Ljava/util/Map;
      45: aload_2
      46: invokeinterface #24,  2           // InterfaceMethod java/util/Map.get:(Ljava/lang/Object;)Ljava/lang/Object;
      51: checkcast     #25                 // class java/util/Map
      54: astore        4
      56: aload         4
      58: iload_3
      59: invokestatic  #26                 // Method java/lang/Integer.valueOf:(I)Ljava/lang/Integer;
      62: aload_1
      63: invokeinterface #5,  3            // InterfaceMethod java/util/Map.put:(Ljava/lang/Object;Ljava/lang/Object;)Ljava/lang/Object;
      68: pop
      69: return

  public static com.google.protobuf.Descriptors$FileDescriptor getFileDescriptorByExtensionAndNumber(java.lang.String, int);
    Code:
       0: getstatic     #20                 // Field EXTENSIONS:Ljava/util/Map;
       3: aload_0
       4: invokestatic  #27                 // Method java/util/Collections.emptyMap:()Ljava/util/Map;
       7: invokeinterface #28,  3           // InterfaceMethod java/util/Map.getOrDefault:(Ljava/lang/Object;Ljava/lang/Object;)Ljava/lang/Object;
      12: checkcast     #25                 // class java/util/Map
      15: iload_1
      16: invokestatic  #26                 // Method java/lang/Integer.valueOf:(I)Ljava/lang/Integer;
      19: invokeinterface #24,  2           // InterfaceMethod java/util/Map.get:(Ljava/lang/Object;)Ljava/lang/Object;
      24: checkcast     #29                 // class com/google/protobuf/Descriptors$FileDescriptor
      27: areturn

  public static java.util.Set<java.lang.Integer> getExtensionNumbers(java.lang.String);
    Code:
       0: getstatic     #20                 // Field EXTENSIONS:Ljava/util/Map;
       3: aload_0
       4: invokeinterface #24,  2           // InterfaceMethod java/util/Map.get:(Ljava/lang/Object;)Ljava/lang/Object;
       9: checkcast     #25                 // class java/util/Map
      12: astore_1
      13: aload_1
      14: ifnonnull     19
      17: aconst_null
      18: areturn
      19: aload_1
      20: invokeinterface #30,  1           // InterfaceMethod java/util/Map.keySet:()Ljava/util/Set;
      25: areturn

  public static com.google.protobuf.Descriptors$FileDescriptor getSchemaDescriptor(java.lang.String);
    Code:
       0: getstatic     #4                  // Field DESCRIPTORS_BY_SYMBOL:Ljava/util/Map;
       3: aload_0
       4: invokeinterface #24,  2           // InterfaceMethod java/util/Map.get:(Ljava/lang/Object;)Ljava/lang/Object;
       9: checkcast     #29                 // class com/google/protobuf/Descriptors$FileDescriptor
      12: areturn

  public static java.util.List<java.lang.String> listServiceNames();
    Code:
       0: new           #31                 // class java/util/ArrayList
       3: dup
       4: getstatic     #2                  // Field SERVICES:Ljava/util/Set;
       7: invokespecial #32                 // Method java/util/ArrayList."<init>":(Ljava/util/Collection;)V
      10: areturn

  static {};
    Code:
       0: new           #33                 // class java/util/concurrent/ConcurrentHashMap
       3: dup
       4: invokespecial #34                 // Method java/util/concurrent/ConcurrentHashMap."<init>":()V
       7: putstatic     #4                  // Field DESCRIPTORS_BY_SYMBOL:Ljava/util/Map;
      10: new           #33                 // class java/util/concurrent/ConcurrentHashMap
      13: dup
      14: invokespecial #34                 // Method java/util/concurrent/ConcurrentHashMap."<init>":()V
      17: putstatic     #20                 // Field EXTENSIONS:Ljava/util/Map;
      20: new           #35                 // class java/util/HashSet
      23: dup
      24: invokespecial #36                 // Method java/util/HashSet."<init>":()V
      27: putstatic     #2                  // Field SERVICES:Ljava/util/Set;
      30: return
}
