Compiled from "TriBuiltinService.java"
public class org.apache.dubbo.rpc.protocol.tri.service.TriBuiltinService {
  private org.apache.dubbo.rpc.ProxyFactory proxyFactory;

  private org.apache.dubbo.rpc.PathResolver pathResolver;

  private io.grpc.health.v1.Health healthService;

  private org.apache.dubbo.rpc.model.FrameworkModel frameworkModel;

  private org.apache.dubbo.rpc.protocol.tri.service.ReflectionV1AlphaService reflectionServiceV1Alpha;

  private org.apache.dubbo.rpc.protocol.tri.service.HealthStatusManager healthStatusManager;

  private org.apache.dubbo.common.config.Configuration config;

  private final java.util.concurrent.atomic.AtomicBoolean init;

  public org.apache.dubbo.rpc.protocol.tri.service.TriBuiltinService(org.apache.dubbo.rpc.model.FrameworkModel);
    Code:
       0: aload_0
       1: invokespecial #3                  // Method java/lang/Object."<init>":()V
       4: aload_0
       5: invokestatic  #4                  // Method org/apache/dubbo/rpc/model/ApplicationModel.defaultModel:()Lorg/apache/dubbo/rpc/model/ApplicationModel;
       8: invokestatic  #5                  // Method org/apache/dubbo/common/config/ConfigurationUtils.getGlobalConfiguration:(Lorg/apache/dubbo/rpc/model/ScopeModel;)Lorg/apache/dubbo/common/config/Configuration;
      11: putfield      #6                  // Field config:Lorg/apache/dubbo/common/config/Configuration;
      14: aload_0
      15: new           #7                  // class java/util/concurrent/atomic/AtomicBoolean
      18: dup
      19: invokespecial #8                  // Method java/util/concurrent/atomic/AtomicBoolean."<init>":()V
      22: putfield      #9                  // Field init:Ljava/util/concurrent/atomic/AtomicBoolean;
      25: aload_0
      26: aload_1
      27: putfield      #10                 // Field frameworkModel:Lorg/apache/dubbo/rpc/model/FrameworkModel;
      30: aload_0
      31: invokevirtual #11                 // Method enable:()Z
      34: ifeq          41
      37: aload_0
      38: invokevirtual #12                 // Method init:()V
      41: return

  public void init();
    Code:
       0: aload_0
       1: getfield      #9                  // Field init:Ljava/util/concurrent/atomic/AtomicBoolean;
       4: iconst_0
       5: iconst_1
       6: invokevirtual #13                 // Method java/util/concurrent/atomic/AtomicBoolean.compareAndSet:(ZZ)Z
       9: ifeq          114
      12: aload_0
      13: new           #14                 // class org/apache/dubbo/rpc/protocol/tri/service/HealthStatusManager
      16: dup
      17: new           #15                 // class org/apache/dubbo/rpc/protocol/tri/service/TriHealthImpl
      20: dup
      21: invokespecial #16                 // Method org/apache/dubbo/rpc/protocol/tri/service/TriHealthImpl."<init>":()V
      24: invokespecial #17                 // Method org/apache/dubbo/rpc/protocol/tri/service/HealthStatusManager."<init>":(Lorg/apache/dubbo/rpc/protocol/tri/service/TriHealthImpl;)V
      27: putfield      #18                 // Field healthStatusManager:Lorg/apache/dubbo/rpc/protocol/tri/service/HealthStatusManager;
      30: aload_0
      31: aload_0
      32: getfield      #18                 // Field healthStatusManager:Lorg/apache/dubbo/rpc/protocol/tri/service/HealthStatusManager;
      35: invokevirtual #19                 // Method org/apache/dubbo/rpc/protocol/tri/service/HealthStatusManager.getHealthService:()Lio/grpc/health/v1/Health;
      38: putfield      #20                 // Field healthService:Lio/grpc/health/v1/Health;
      41: aload_0
      42: new           #21                 // class org/apache/dubbo/rpc/protocol/tri/service/ReflectionV1AlphaService
      45: dup
      46: invokespecial #22                 // Method org/apache/dubbo/rpc/protocol/tri/service/ReflectionV1AlphaService."<init>":()V
      49: putfield      #23                 // Field reflectionServiceV1Alpha:Lorg/apache/dubbo/rpc/protocol/tri/service/ReflectionV1AlphaService;
      52: aload_0
      53: aload_0
      54: getfield      #10                 // Field frameworkModel:Lorg/apache/dubbo/rpc/model/FrameworkModel;
      57: ldc           #24                 // class org/apache/dubbo/rpc/ProxyFactory
      59: invokevirtual #25                 // Method org/apache/dubbo/rpc/model/FrameworkModel.getExtensionLoader:(Ljava/lang/Class;)Lorg/apache/dubbo/common/extension/ExtensionLoader;
      62: invokevirtual #26                 // Method org/apache/dubbo/common/extension/ExtensionLoader.getAdaptiveExtension:()Ljava/lang/Object;
      65: checkcast     #24                 // class org/apache/dubbo/rpc/ProxyFactory
      68: putfield      #27                 // Field proxyFactory:Lorg/apache/dubbo/rpc/ProxyFactory;
      71: aload_0
      72: aload_0
      73: getfield      #10                 // Field frameworkModel:Lorg/apache/dubbo/rpc/model/FrameworkModel;
      76: ldc           #28                 // class org/apache/dubbo/rpc/PathResolver
      78: invokevirtual #25                 // Method org/apache/dubbo/rpc/model/FrameworkModel.getExtensionLoader:(Ljava/lang/Class;)Lorg/apache/dubbo/common/extension/ExtensionLoader;
      81: invokevirtual #29                 // Method org/apache/dubbo/common/extension/ExtensionLoader.getDefaultExtension:()Ljava/lang/Object;
      84: checkcast     #28                 // class org/apache/dubbo/rpc/PathResolver
      87: putfield      #30                 // Field pathResolver:Lorg/apache/dubbo/rpc/PathResolver;
      90: aload_0
      91: ldc           #32                 // String grpc.health.v1.Health
      93: aload_0
      94: getfield      #20                 // Field healthService:Lio/grpc/health/v1/Health;
      97: ldc           #33                 // class io/grpc/health/v1/Health
      99: invokespecial #34                 // Method addSingleBuiltinService:(Ljava/lang/String;Ljava/lang/Object;Ljava/lang/Class;)V
     102: aload_0
     103: ldc           #35                 // String grpc.reflection.v1alpha.ServerReflection
     105: aload_0
     106: getfield      #23                 // Field reflectionServiceV1Alpha:Lorg/apache/dubbo/rpc/protocol/tri/service/ReflectionV1AlphaService;
     109: ldc           #21                 // class org/apache/dubbo/rpc/protocol/tri/service/ReflectionV1AlphaService
     111: invokespecial #34                 // Method addSingleBuiltinService:(Ljava/lang/String;Ljava/lang/Object;Ljava/lang/Class;)V
     114: return

  public boolean enable();
    Code:
       0: aload_0
       1: getfield      #6                  // Field config:Lorg/apache/dubbo/common/config/Configuration;
       4: ldc           #36                 // String dubbo.tri.builtin.service.init
       6: iconst_0
       7: invokeinterface #37,  3           // InterfaceMethod org/apache/dubbo/common/config/Configuration.getBoolean:(Ljava/lang/String;Z)Z
      12: ireturn

  private <T> void addSingleBuiltinService(java.lang.String, T, java.lang.Class<T>);
    Code:
       0: invokestatic  #4                  // Method org/apache/dubbo/rpc/model/ApplicationModel.defaultModel:()Lorg/apache/dubbo/rpc/model/ApplicationModel;
       3: invokevirtual #38                 // Method org/apache/dubbo/rpc/model/ApplicationModel.getInternalModule:()Lorg/apache/dubbo/rpc/model/ModuleModel;
       6: astore        4
       8: new           #39                 // class org/apache/dubbo/common/url/component/ServiceConfigURL
      11: dup
      12: ldc           #40                 // String tri
      14: aconst_null
      15: aconst_null
      16: ldc           #41                 // String 0.0.0.0
      18: iconst_0
      19: aload_1
      20: invokespecial #42                 // Method org/apache/dubbo/common/url/component/ServiceConfigURL."<init>":(Ljava/lang/String;Ljava/lang/String;Ljava/lang/String;Ljava/lang/String;ILjava/lang/String;)V
      23: ldc           #43                 // String proxy
      25: ldc           #44                 // String nativestub
      27: invokevirtual #45                 // Method org/apache/dubbo/common/url/component/ServiceConfigURL.addParameter:(Ljava/lang/String;Ljava/lang/String;)Lorg/apache/dubbo/common/URL;
      30: aload         4
      32: invokevirtual #46                 // Method org/apache/dubbo/common/URL.setScopeModel:(Lorg/apache/dubbo/rpc/model/ScopeModel;)Lorg/apache/dubbo/common/URL;
      35: astore        5
      37: aload_0
      38: getfield      #27                 // Field proxyFactory:Lorg/apache/dubbo/rpc/ProxyFactory;
      41: aload_2
      42: aload_3
      43: aload         5
      45: invokeinterface #47,  4           // InterfaceMethod org/apache/dubbo/rpc/ProxyFactory.getInvoker:(Ljava/lang/Object;Ljava/lang/Class;Lorg/apache/dubbo/common/URL;)Lorg/apache/dubbo/rpc/Invoker;
      50: astore        6
      52: aload_0
      53: getfield      #30                 // Field pathResolver:Lorg/apache/dubbo/rpc/PathResolver;
      56: aload_1
      57: aload         6
      59: invokeinterface #48,  3           // InterfaceMethod org/apache/dubbo/rpc/PathResolver.add:(Ljava/lang/String;Lorg/apache/dubbo/rpc/Invoker;)V
      64: aload         4
      66: aload_0
      67: aload_1
      68: invokedynamic #49,  0             // InvokeDynamic #0:onDestroy:(Lorg/apache/dubbo/rpc/protocol/tri/service/TriBuiltinService;Ljava/lang/String;)Lorg/apache/dubbo/rpc/model/ScopeModelDestroyListener;
      73: invokevirtual #50                 // Method org/apache/dubbo/rpc/model/ModuleModel.addDestroyListener:(Lorg/apache/dubbo/rpc/model/ScopeModelDestroyListener;)V
      76: return

  public org.apache.dubbo.rpc.protocol.tri.service.HealthStatusManager getHealthStatusManager();
    Code:
       0: aload_0
       1: getfield      #18                 // Field healthStatusManager:Lorg/apache/dubbo/rpc/protocol/tri/service/HealthStatusManager;
       4: areturn

  private void lambda$addSingleBuiltinService$0(java.lang.String, org.apache.dubbo.rpc.model.ScopeModel);
    Code:
       0: aload_0
       1: getfield      #30                 // Field pathResolver:Lorg/apache/dubbo/rpc/PathResolver;
       4: aload_1
       5: invokeinterface #51,  2           // InterfaceMethod org/apache/dubbo/rpc/PathResolver.remove:(Ljava/lang/String;)V
      10: return
}
