Compiled from "ScriptStateRouter.java"
public class org.apache.dubbo.rpc.cluster.router.script.ScriptStateRouter<T> extends org.apache.dubbo.rpc.cluster.router.state.AbstractStateRouter<T> {
  public static final java.lang.String NAME;

  private static final int SCRIPT_ROUTER_DEFAULT_PRIORITY;

  private static final org.apache.dubbo.common.logger.ErrorTypeAwareLogger logger;

  private static final java.util.concurrent.ConcurrentMap<java.lang.String, javax.script.ScriptEngine> ENGINES;

  private final javax.script.ScriptEngine engine;

  private final java.lang.String rule;

  private javax.script.CompiledScript function;

  private java.security.AccessControlContext accessControlContext;

  public org.apache.dubbo.rpc.cluster.router.script.ScriptStateRouter(org.apache.dubbo.common.URL);
    Code:
       0: aload_0
       1: aload_1
       2: invokespecial #3                  // Method org/apache/dubbo/rpc/cluster/router/state/AbstractStateRouter."<init>":(Lorg/apache/dubbo/common/URL;)V
       5: new           #4                  // class java/security/Permissions
       8: dup
       9: invokespecial #5                  // Method java/security/Permissions."<init>":()V
      12: astore_2
      13: aload_2
      14: new           #6                  // class java/lang/RuntimePermission
      17: dup
      18: ldc           #7                  // String accessDeclaredMembers
      20: invokespecial #8                  // Method java/lang/RuntimePermission."<init>":(Ljava/lang/String;)V
      23: invokevirtual #9                  // Method java/security/Permissions.add:(Ljava/security/Permission;)V
      26: new           #10                 // class java/security/ProtectionDomain
      29: dup
      30: new           #11                 // class java/security/CodeSource
      33: dup
      34: aconst_null
      35: aconst_null
      36: checkcast     #12                 // class "[Ljava/security/cert/Certificate;"
      39: invokespecial #13                 // Method java/security/CodeSource."<init>":(Ljava/net/URL;[Ljava/security/cert/Certificate;)V
      42: aload_2
      43: invokespecial #14                 // Method java/security/ProtectionDomain."<init>":(Ljava/security/CodeSource;Ljava/security/PermissionCollection;)V
      46: astore_3
      47: aload_0
      48: new           #15                 // class java/security/AccessControlContext
      51: dup
      52: iconst_1
      53: anewarray     #10                 // class java/security/ProtectionDomain
      56: dup
      57: iconst_0
      58: aload_3
      59: aastore
      60: invokespecial #16                 // Method java/security/AccessControlContext."<init>":([Ljava/security/ProtectionDomain;)V
      63: putfield      #17                 // Field accessControlContext:Ljava/security/AccessControlContext;
      66: aload_0
      67: aload_1
      68: invokevirtual #18                 // Method setUrl:(Lorg/apache/dubbo/common/URL;)V
      71: aload_0
      72: aload_0
      73: aload_1
      74: invokespecial #19                 // Method getEngine:(Lorg/apache/dubbo/common/URL;)Ljavax/script/ScriptEngine;
      77: putfield      #20                 // Field engine:Ljavax/script/ScriptEngine;
      80: aload_0
      81: aload_0
      82: aload_1
      83: invokespecial #21                 // Method getRule:(Lorg/apache/dubbo/common/URL;)Ljava/lang/String;
      86: putfield      #22                 // Field rule:Ljava/lang/String;
      89: aload_0
      90: getfield      #20                 // Field engine:Ljavax/script/ScriptEngine;
      93: checkcast     #23                 // class javax/script/Compilable
      96: astore_2
      97: aload_0
      98: aload_2
      99: aload_0
     100: getfield      #22                 // Field rule:Ljava/lang/String;
     103: invokeinterface #24,  2           // InterfaceMethod javax/script/Compilable.compile:(Ljava/lang/String;)Ljavax/script/CompiledScript;
     108: putfield      #25                 // Field function:Ljavax/script/CompiledScript;
     111: goto          166
     114: astore_2
     115: getstatic     #27                 // Field logger:Lorg/apache/dubbo/common/logger/ErrorTypeAwareLogger;
     118: ldc           #28                 // String 2-14
     120: ldc           #29                 // String script route rule invalid
     122: ldc           #30                 // String
     124: new           #31                 // class java/lang/StringBuilder
     127: dup
     128: invokespecial #32                 // Method java/lang/StringBuilder."<init>":()V
     131: ldc           #33                 // String script route error, rule has been ignored. rule:
     133: invokevirtual #34                 // Method java/lang/StringBuilder.append:(Ljava/lang/String;)Ljava/lang/StringBuilder;
     136: aload_0
     137: getfield      #22                 // Field rule:Ljava/lang/String;
     140: invokevirtual #34                 // Method java/lang/StringBuilder.append:(Ljava/lang/String;)Ljava/lang/StringBuilder;
     143: ldc           #35                 // String , url:
     145: invokevirtual #34                 // Method java/lang/StringBuilder.append:(Ljava/lang/String;)Ljava/lang/StringBuilder;
     148: invokestatic  #36                 // Method org/apache/dubbo/rpc/RpcContext.getServiceContext:()Lorg/apache/dubbo/rpc/RpcServiceContext;
     151: invokevirtual #37                 // Method org/apache/dubbo/rpc/RpcServiceContext.getUrl:()Lorg/apache/dubbo/common/URL;
     154: invokevirtual #38                 // Method java/lang/StringBuilder.append:(Ljava/lang/Object;)Ljava/lang/StringBuilder;
     157: invokevirtual #39                 // Method java/lang/StringBuilder.toString:()Ljava/lang/String;
     160: aload_2
     161: invokeinterface #40,  6           // InterfaceMethod org/apache/dubbo/common/logger/ErrorTypeAwareLogger.error:(Ljava/lang/String;Ljava/lang/String;Ljava/lang/String;Ljava/lang/String;Ljava/lang/Throwable;)V
     166: return
    Exception table:
       from    to  target type
          89   111   114   Class javax/script/ScriptException

  private java.lang.String getRule(org.apache.dubbo.common.URL);
    Code:
       0: aload_1
       1: ldc           #41                 // String rule
       3: invokevirtual #42                 // Method org/apache/dubbo/common/URL.getParameterAndDecoded:(Ljava/lang/String;)Ljava/lang/String;
       6: astore_2
       7: aload_2
       8: invokestatic  #43                 // Method org/apache/dubbo/common/utils/StringUtils.isEmpty:(Ljava/lang/String;)Z
      11: ifeq          24
      14: new           #44                 // class java/lang/IllegalStateException
      17: dup
      18: ldc           #45                 // String route rule can not be empty.
      20: invokespecial #46                 // Method java/lang/IllegalStateException."<init>":(Ljava/lang/String;)V
      23: athrow
      24: aload_2
      25: areturn

  private javax.script.ScriptEngine getEngine(org.apache.dubbo.common.URL);
    Code:
       0: aload_1
       1: ldc           #47                 // String type
       3: ldc           #48                 // String javascript
       5: invokevirtual #49                 // Method org/apache/dubbo/common/URL.getParameter:(Ljava/lang/String;Ljava/lang/String;)Ljava/lang/String;
       8: astore_2
       9: getstatic     #50                 // Field ENGINES:Ljava/util/concurrent/ConcurrentMap;
      12: aload_2
      13: aload_2
      14: invokedynamic #51,  0             // InvokeDynamic #0:apply:(Ljava/lang/String;)Ljava/util/function/Function;
      19: invokestatic  #52                 // Method org/apache/dubbo/common/utils/ConcurrentHashMapUtils.computeIfAbsent:(Ljava/util/concurrent/ConcurrentMap;Ljava/lang/Object;Ljava/util/function/Function;)Ljava/lang/Object;
      22: checkcast     #53                 // class javax/script/ScriptEngine
      25: areturn

  protected org.apache.dubbo.rpc.cluster.router.state.BitList<org.apache.dubbo.rpc.Invoker<T>> doRoute(org.apache.dubbo.rpc.cluster.router.state.BitList<org.apache.dubbo.rpc.Invoker<T>>, org.apache.dubbo.common.URL, org.apache.dubbo.rpc.Invocation, boolean, org.apache.dubbo.common.utils.Holder<org.apache.dubbo.rpc.cluster.router.RouterSnapshotNode<T>>, org.apache.dubbo.common.utils.Holder<java.lang.String>) throws org.apache.dubbo.rpc.RpcException;
    Code:
       0: aload_0
       1: getfield      #20                 // Field engine:Ljavax/script/ScriptEngine;
       4: ifnull        14
       7: aload_0
       8: getfield      #25                 // Field function:Ljavax/script/CompiledScript;
      11: ifnonnull     28
      14: iload         4
      16: ifeq          26
      19: aload         6
      21: ldc           #54                 // String Directly Return. Reason: engine or function is null
      23: invokevirtual #55                 // Method org/apache/dubbo/common/utils/Holder.set:(Ljava/lang/Object;)V
      26: aload_1
      27: areturn
      28: aload_0
      29: aload_1
      30: aload_3
      31: invokespecial #56                 // Method createBindings:(Ljava/util/List;Lorg/apache/dubbo/rpc/Invocation;)Ljavax/script/Bindings;
      34: astore        7
      36: aload_0
      37: aload_1
      38: aload_0
      39: aload         7
      41: aload_3
      42: aload_1
      43: invokedynamic #57,  0             // InvokeDynamic #1:run:(Lorg/apache/dubbo/rpc/cluster/router/script/ScriptStateRouter;Ljavax/script/Bindings;Lorg/apache/dubbo/rpc/Invocation;Lorg/apache/dubbo/rpc/cluster/router/state/BitList;)Ljava/security/PrivilegedAction;
      48: aload_0
      49: getfield      #17                 // Field accessControlContext:Ljava/security/AccessControlContext;
      52: invokestatic  #58                 // Method java/security/AccessController.doPrivileged:(Ljava/security/PrivilegedAction;Ljava/security/AccessControlContext;)Ljava/lang/Object;
      55: invokevirtual #59                 // Method getRoutedInvokers:(Lorg/apache/dubbo/rpc/cluster/router/state/BitList;Ljava/lang/Object;)Lorg/apache/dubbo/rpc/cluster/router/state/BitList;
      58: areturn

  protected org.apache.dubbo.rpc.cluster.router.state.BitList<org.apache.dubbo.rpc.Invoker<T>> getRoutedInvokers(org.apache.dubbo.rpc.cluster.router.state.BitList<org.apache.dubbo.rpc.Invoker<T>>, java.lang.Object);
    Code:
       0: aload_1
       1: invokevirtual #60                 // Method org/apache/dubbo/rpc/cluster/router/state/BitList.clone:()Lorg/apache/dubbo/rpc/cluster/router/state/BitList;
       4: astore_3
       5: aload_2
       6: instanceof    #61                 // class "[Lorg/apache/dubbo/rpc/Invoker;"
       9: ifeq          30
      12: aload_3
      13: aload_2
      14: checkcast     #61                 // class "[Lorg/apache/dubbo/rpc/Invoker;"
      17: checkcast     #61                 // class "[Lorg/apache/dubbo/rpc/Invoker;"
      20: invokestatic  #62                 // Method java/util/Arrays.asList:([Ljava/lang/Object;)Ljava/util/List;
      23: invokevirtual #63                 // Method org/apache/dubbo/rpc/cluster/router/state/BitList.retainAll:(Ljava/util/Collection;)Z
      26: pop
      27: goto          85
      30: aload_2
      31: instanceof    #64                 // class "[Ljava/lang/Object;"
      34: ifeq          76
      37: aload_3
      38: aload_2
      39: checkcast     #64                 // class "[Ljava/lang/Object;"
      42: checkcast     #64                 // class "[Ljava/lang/Object;"
      45: invokestatic  #65                 // Method java/util/Arrays.stream:([Ljava/lang/Object;)Ljava/util/stream/Stream;
      48: invokedynamic #66,  0             // InvokeDynamic #2:apply:()Ljava/util/function/Function;
      53: invokeinterface #67,  2           // InterfaceMethod java/util/stream/Stream.map:(Ljava/util/function/Function;)Ljava/util/stream/Stream;
      58: invokestatic  #68                 // Method java/util/stream/Collectors.toList:()Ljava/util/stream/Collector;
      61: invokeinterface #69,  2           // InterfaceMethod java/util/stream/Stream.collect:(Ljava/util/stream/Collector;)Ljava/lang/Object;
      66: checkcast     #70                 // class java/util/Collection
      69: invokevirtual #63                 // Method org/apache/dubbo/rpc/cluster/router/state/BitList.retainAll:(Ljava/util/Collection;)Z
      72: pop
      73: goto          85
      76: aload_3
      77: aload_2
      78: checkcast     #71                 // class java/util/List
      81: invokevirtual #63                 // Method org/apache/dubbo/rpc/cluster/router/state/BitList.retainAll:(Ljava/util/Collection;)Z
      84: pop
      85: aload_3
      86: areturn

  private javax.script.Bindings createBindings(java.util.List<org.apache.dubbo.rpc.Invoker<T>>, org.apache.dubbo.rpc.Invocation);
    Code:
       0: aload_0
       1: getfield      #20                 // Field engine:Ljavax/script/ScriptEngine;
       4: invokeinterface #72,  1           // InterfaceMethod javax/script/ScriptEngine.createBindings:()Ljavax/script/Bindings;
       9: astore_3
      10: aload_3
      11: ldc           #73                 // String invokers
      13: new           #74                 // class java/util/ArrayList
      16: dup
      17: aload_1
      18: invokespecial #75                 // Method java/util/ArrayList."<init>":(Ljava/util/Collection;)V
      21: invokeinterface #76,  3           // InterfaceMethod javax/script/Bindings.put:(Ljava/lang/String;Ljava/lang/Object;)Ljava/lang/Object;
      26: pop
      27: aload_3
      28: ldc           #77                 // String invocation
      30: aload_2
      31: invokeinterface #76,  3           // InterfaceMethod javax/script/Bindings.put:(Ljava/lang/String;Ljava/lang/Object;)Ljava/lang/Object;
      36: pop
      37: aload_3
      38: ldc           #78                 // String context
      40: invokestatic  #79                 // Method org/apache/dubbo/rpc/RpcContext.getClientAttachment:()Lorg/apache/dubbo/rpc/RpcContextAttachment;
      43: invokeinterface #76,  3           // InterfaceMethod javax/script/Bindings.put:(Ljava/lang/String;Ljava/lang/Object;)Ljava/lang/Object;
      48: pop
      49: aload_3
      50: areturn

  public boolean isRuntime();
    Code:
       0: aload_0
       1: invokevirtual #80                 // Method getUrl:()Lorg/apache/dubbo/common/URL;
       4: ldc           #81                 // String runtime
       6: iconst_0
       7: invokevirtual #82                 // Method org/apache/dubbo/common/URL.getParameter:(Ljava/lang/String;Z)Z
      10: ireturn

  public boolean isForce();
    Code:
       0: aload_0
       1: invokevirtual #80                 // Method getUrl:()Lorg/apache/dubbo/common/URL;
       4: ldc           #83                 // String force
       6: iconst_0
       7: invokevirtual #82                 // Method org/apache/dubbo/common/URL.getParameter:(Ljava/lang/String;Z)Z
      10: ireturn

  private static org.apache.dubbo.rpc.Invoker lambda$getRoutedInvokers$2(java.lang.Object);
    Code:
       0: aload_0
       1: checkcast     #84                 // class org/apache/dubbo/rpc/Invoker
       4: areturn

  private java.lang.Object lambda$doRoute$1(javax.script.Bindings, org.apache.dubbo.rpc.Invocation, org.apache.dubbo.rpc.cluster.router.state.BitList);
    Code:
       0: aload_0
       1: getfield      #25                 // Field function:Ljavax/script/CompiledScript;
       4: aload_1
       5: invokevirtual #85                 // Method javax/script/CompiledScript.eval:(Ljavax/script/Bindings;)Ljava/lang/Object;
       8: areturn
       9: astore        4
      11: getstatic     #27                 // Field logger:Lorg/apache/dubbo/common/logger/ErrorTypeAwareLogger;
      14: ldc           #28                 // String 2-14
      16: ldc           #86                 // String Scriptrouter exec script error
      18: ldc           #30                 // String
      20: new           #31                 // class java/lang/StringBuilder
      23: dup
      24: invokespecial #32                 // Method java/lang/StringBuilder."<init>":()V
      27: ldc           #87                 // String Script route error, rule has been ignored. rule:
      29: invokevirtual #34                 // Method java/lang/StringBuilder.append:(Ljava/lang/String;)Ljava/lang/StringBuilder;
      32: aload_0
      33: getfield      #22                 // Field rule:Ljava/lang/String;
      36: invokevirtual #34                 // Method java/lang/StringBuilder.append:(Ljava/lang/String;)Ljava/lang/StringBuilder;
      39: ldc           #88                 // String , method:
      41: invokevirtual #34                 // Method java/lang/StringBuilder.append:(Ljava/lang/String;)Ljava/lang/StringBuilder;
      44: aload_2
      45: invokeinterface #89,  1           // InterfaceMethod org/apache/dubbo/rpc/Invocation.getMethodName:()Ljava/lang/String;
      50: invokevirtual #34                 // Method java/lang/StringBuilder.append:(Ljava/lang/String;)Ljava/lang/StringBuilder;
      53: ldc           #35                 // String , url:
      55: invokevirtual #34                 // Method java/lang/StringBuilder.append:(Ljava/lang/String;)Ljava/lang/StringBuilder;
      58: invokestatic  #90                 // Method org/apache/dubbo/rpc/RpcContext.getContext:()Lorg/apache/dubbo/rpc/RpcContext;
      61: invokevirtual #91                 // Method org/apache/dubbo/rpc/RpcContext.getUrl:()Lorg/apache/dubbo/common/URL;
      64: invokevirtual #38                 // Method java/lang/StringBuilder.append:(Ljava/lang/Object;)Ljava/lang/StringBuilder;
      67: invokevirtual #39                 // Method java/lang/StringBuilder.toString:()Ljava/lang/String;
      70: aload         4
      72: invokeinterface #40,  6           // InterfaceMethod org/apache/dubbo/common/logger/ErrorTypeAwareLogger.error:(Ljava/lang/String;Ljava/lang/String;Ljava/lang/String;Ljava/lang/String;Ljava/lang/Throwable;)V
      77: aload_3
      78: areturn
    Exception table:
       from    to  target type
           0     8     9   Class javax/script/ScriptException

  private static javax.script.ScriptEngine lambda$getEngine$0(java.lang.String, java.lang.String);
    Code:
       0: new           #92                 // class javax/script/ScriptEngineManager
       3: dup
       4: invokespecial #93                 // Method javax/script/ScriptEngineManager."<init>":()V
       7: aload_0
       8: invokevirtual #94                 // Method javax/script/ScriptEngineManager.getEngineByName:(Ljava/lang/String;)Ljavax/script/ScriptEngine;
      11: astore_2
      12: aload_2
      13: ifnonnull     43
      16: new           #44                 // class java/lang/IllegalStateException
      19: dup
      20: new           #31                 // class java/lang/StringBuilder
      23: dup
      24: invokespecial #32                 // Method java/lang/StringBuilder."<init>":()V
      27: ldc           #95                 // String unsupported route engine type:
      29: invokevirtual #34                 // Method java/lang/StringBuilder.append:(Ljava/lang/String;)Ljava/lang/StringBuilder;
      32: aload_0
      33: invokevirtual #34                 // Method java/lang/StringBuilder.append:(Ljava/lang/String;)Ljava/lang/StringBuilder;
      36: invokevirtual #39                 // Method java/lang/StringBuilder.toString:()Ljava/lang/String;
      39: invokespecial #46                 // Method java/lang/IllegalStateException."<init>":(Ljava/lang/String;)V
      42: athrow
      43: aload_2
      44: areturn

  static {};
    Code:
       0: ldc           #96                 // class org/apache/dubbo/rpc/cluster/router/script/ScriptStateRouter
       2: invokestatic  #97                 // Method org/apache/dubbo/common/logger/LoggerFactory.getErrorTypeAwareLogger:(Ljava/lang/Class;)Lorg/apache/dubbo/common/logger/ErrorTypeAwareLogger;
       5: putstatic     #27                 // Field logger:Lorg/apache/dubbo/common/logger/ErrorTypeAwareLogger;
       8: new           #98                 // class java/util/concurrent/ConcurrentHashMap
      11: dup
      12: invokespecial #99                 // Method java/util/concurrent/ConcurrentHashMap."<init>":()V
      15: putstatic     #50                 // Field ENGINES:Ljava/util/concurrent/ConcurrentMap;
      18: return
}
