Compiled from "DataSourceStatusChecker.java"
public class org.apache.dubbo.config.spring.status.DataSourceStatusChecker implements org.apache.dubbo.common.status.StatusChecker {
  private static final org.apache.dubbo.common.logger.ErrorTypeAwareLogger logger;

  private org.apache.dubbo.rpc.model.ApplicationModel applicationModel;

  private org.springframework.context.ApplicationContext applicationContext;

  public org.apache.dubbo.config.spring.status.DataSourceStatusChecker(org.apache.dubbo.rpc.model.ApplicationModel);
    Code:
       0: aload_0
       1: invokespecial #2                  // Method java/lang/Object."<init>":()V
       4: aload_0
       5: aload_1
       6: putfield      #3                  // Field applicationModel:Lorg/apache/dubbo/rpc/model/ApplicationModel;
       9: return

  public org.apache.dubbo.config.spring.status.DataSourceStatusChecker(org.springframework.context.ApplicationContext);
    Code:
       0: aload_0
       1: invokespecial #2                  // Method java/lang/Object."<init>":()V
       4: aload_0
       5: aload_1
       6: putfield      #4                  // Field applicationContext:Lorg/springframework/context/ApplicationContext;
       9: return

  public org.apache.dubbo.common.status.Status check();
    Code:
       0: aload_0
       1: getfield      #4                  // Field applicationContext:Lorg/springframework/context/ApplicationContext;
       4: ifnonnull     23
       7: aload_0
       8: getfield      #3                  // Field applicationModel:Lorg/apache/dubbo/rpc/model/ApplicationModel;
      11: invokestatic  #5                  // Method org/apache/dubbo/config/spring/extension/SpringExtensionInjector.get:(Lorg/apache/dubbo/common/extension/ExtensionAccessor;)Lorg/apache/dubbo/config/spring/extension/SpringExtensionInjector;
      14: astore_1
      15: aload_0
      16: aload_1
      17: invokevirtual #6                  // Method org/apache/dubbo/config/spring/extension/SpringExtensionInjector.getContext:()Lorg/springframework/context/ApplicationContext;
      20: putfield      #4                  // Field applicationContext:Lorg/springframework/context/ApplicationContext;
      23: aload_0
      24: getfield      #4                  // Field applicationContext:Lorg/springframework/context/ApplicationContext;
      27: ifnonnull     41
      30: new           #7                  // class org/apache/dubbo/common/status/Status
      33: dup
      34: getstatic     #8                  // Field org/apache/dubbo/common/status/Status$Level.UNKNOWN:Lorg/apache/dubbo/common/status/Status$Level;
      37: invokespecial #9                  // Method org/apache/dubbo/common/status/Status."<init>":(Lorg/apache/dubbo/common/status/Status$Level;)V
      40: areturn
      41: aload_0
      42: getfield      #4                  // Field applicationContext:Lorg/springframework/context/ApplicationContext;
      45: ldc           #10                 // class javax/sql/DataSource
      47: iconst_0
      48: iconst_0
      49: invokeinterface #11,  4           // InterfaceMethod org/springframework/context/ApplicationContext.getBeansOfType:(Ljava/lang/Class;ZZ)Ljava/util/Map;
      54: astore_1
      55: aload_1
      56: invokestatic  #12                 // Method org/apache/dubbo/common/utils/CollectionUtils.isEmptyMap:(Ljava/util/Map;)Z
      59: ifeq          73
      62: new           #7                  // class org/apache/dubbo/common/status/Status
      65: dup
      66: getstatic     #8                  // Field org/apache/dubbo/common/status/Status$Level.UNKNOWN:Lorg/apache/dubbo/common/status/Status$Level;
      69: invokespecial #9                  // Method org/apache/dubbo/common/status/Status."<init>":(Lorg/apache/dubbo/common/status/Status$Level;)V
      72: areturn
      73: getstatic     #13                 // Field org/apache/dubbo/common/status/Status$Level.OK:Lorg/apache/dubbo/common/status/Status$Level;
      76: astore_2
      77: new           #14                 // class java/lang/StringBuilder
      80: dup
      81: invokespecial #15                 // Method java/lang/StringBuilder."<init>":()V
      84: astore_3
      85: aload_1
      86: invokeinterface #16,  1           // InterfaceMethod java/util/Map.entrySet:()Ljava/util/Set;
      91: invokeinterface #17,  1           // InterfaceMethod java/util/Set.iterator:()Ljava/util/Iterator;
      96: astore        4
      98: aload         4
     100: invokeinterface #18,  1           // InterfaceMethod java/util/Iterator.hasNext:()Z
     105: ifeq          498
     108: aload         4
     110: invokeinterface #19,  1           // InterfaceMethod java/util/Iterator.next:()Ljava/lang/Object;
     115: checkcast     #20                 // class java/util/Map$Entry
     118: astore        5
     120: aload         5
     122: invokeinterface #21,  1           // InterfaceMethod java/util/Map$Entry.getValue:()Ljava/lang/Object;
     127: checkcast     #10                 // class javax/sql/DataSource
     130: astore        6
     132: aload_3
     133: invokevirtual #22                 // Method java/lang/StringBuilder.length:()I
     136: ifle          146
     139: aload_3
     140: ldc           #23                 // String ,
     142: invokevirtual #24                 // Method java/lang/StringBuilder.append:(Ljava/lang/String;)Ljava/lang/StringBuilder;
     145: pop
     146: aload_3
     147: aload         5
     149: invokeinterface #25,  1           // InterfaceMethod java/util/Map$Entry.getKey:()Ljava/lang/Object;
     154: checkcast     #26                 // class java/lang/String
     157: invokevirtual #24                 // Method java/lang/StringBuilder.append:(Ljava/lang/String;)Ljava/lang/StringBuilder;
     160: pop
     161: aload         6
     163: invokeinterface #27,  1           // InterfaceMethod javax/sql/DataSource.getConnection:()Ljava/sql/Connection;
     168: astore        7
     170: aconst_null
     171: astore        8
     173: aload         7
     175: invokeinterface #28,  1           // InterfaceMethod java/sql/Connection.getMetaData:()Ljava/sql/DatabaseMetaData;
     180: astore        9
     182: aload         9
     184: invokeinterface #29,  1           // InterfaceMethod java/sql/DatabaseMetaData.getTypeInfo:()Ljava/sql/ResultSet;
     189: astore        10
     191: aconst_null
     192: astore        11
     194: aload         10
     196: invokeinterface #30,  1           // InterfaceMethod java/sql/ResultSet.next:()Z
     201: ifne          208
     204: getstatic     #31                 // Field org/apache/dubbo/common/status/Status$Level.ERROR:Lorg/apache/dubbo/common/status/Status$Level;
     207: astore_2
     208: aload         10
     210: ifnull        303
     213: aload         11
     215: ifnull        240
     218: aload         10
     220: invokeinterface #32,  1           // InterfaceMethod java/sql/ResultSet.close:()V
     225: goto          303
     228: astore        12
     230: aload         11
     232: aload         12
     234: invokevirtual #34                 // Method java/lang/Throwable.addSuppressed:(Ljava/lang/Throwable;)V
     237: goto          303
     240: aload         10
     242: invokeinterface #32,  1           // InterfaceMethod java/sql/ResultSet.close:()V
     247: goto          303
     250: astore        12
     252: aload         12
     254: astore        11
     256: aload         12
     258: athrow
     259: astore        13
     261: aload         10
     263: ifnull        300
     266: aload         11
     268: ifnull        293
     271: aload         10
     273: invokeinterface #32,  1           // InterfaceMethod java/sql/ResultSet.close:()V
     278: goto          300
     281: astore        14
     283: aload         11
     285: aload         14
     287: invokevirtual #34                 // Method java/lang/Throwable.addSuppressed:(Ljava/lang/Throwable;)V
     290: goto          300
     293: aload         10
     295: invokeinterface #32,  1           // InterfaceMethod java/sql/ResultSet.close:()V
     300: aload         13
     302: athrow
     303: aload_3
     304: aload         9
     306: invokeinterface #35,  1           // InterfaceMethod java/sql/DatabaseMetaData.getURL:()Ljava/lang/String;
     311: invokevirtual #24                 // Method java/lang/StringBuilder.append:(Ljava/lang/String;)Ljava/lang/StringBuilder;
     314: pop
     315: aload_3
     316: bipush        40
     318: invokevirtual #36                 // Method java/lang/StringBuilder.append:(C)Ljava/lang/StringBuilder;
     321: pop
     322: aload_3
     323: aload         9
     325: invokeinterface #37,  1           // InterfaceMethod java/sql/DatabaseMetaData.getDatabaseProductName:()Ljava/lang/String;
     330: invokevirtual #24                 // Method java/lang/StringBuilder.append:(Ljava/lang/String;)Ljava/lang/StringBuilder;
     333: pop
     334: aload_3
     335: bipush        45
     337: invokevirtual #36                 // Method java/lang/StringBuilder.append:(C)Ljava/lang/StringBuilder;
     340: pop
     341: aload_3
     342: aload         9
     344: invokeinterface #38,  1           // InterfaceMethod java/sql/DatabaseMetaData.getDatabaseProductVersion:()Ljava/lang/String;
     349: invokevirtual #24                 // Method java/lang/StringBuilder.append:(Ljava/lang/String;)Ljava/lang/StringBuilder;
     352: pop
     353: aload_3
     354: bipush        41
     356: invokevirtual #36                 // Method java/lang/StringBuilder.append:(C)Ljava/lang/StringBuilder;
     359: pop
     360: aload         7
     362: ifnull        455
     365: aload         8
     367: ifnull        392
     370: aload         7
     372: invokeinterface #39,  1           // InterfaceMethod java/sql/Connection.close:()V
     377: goto          455
     380: astore        9
     382: aload         8
     384: aload         9
     386: invokevirtual #34                 // Method java/lang/Throwable.addSuppressed:(Ljava/lang/Throwable;)V
     389: goto          455
     392: aload         7
     394: invokeinterface #39,  1           // InterfaceMethod java/sql/Connection.close:()V
     399: goto          455
     402: astore        9
     404: aload         9
     406: astore        8
     408: aload         9
     410: athrow
     411: astore        15
     413: aload         7
     415: ifnull        452
     418: aload         8
     420: ifnull        445
     423: aload         7
     425: invokeinterface #39,  1           // InterfaceMethod java/sql/Connection.close:()V
     430: goto          452
     433: astore        16
     435: aload         8
     437: aload         16
     439: invokevirtual #34                 // Method java/lang/Throwable.addSuppressed:(Ljava/lang/Throwable;)V
     442: goto          452
     445: aload         7
     447: invokeinterface #39,  1           // InterfaceMethod java/sql/Connection.close:()V
     452: aload         15
     454: athrow
     455: goto          495
     458: astore        7
     460: getstatic     #40                 // Field logger:Lorg/apache/dubbo/common/logger/ErrorTypeAwareLogger;
     463: ldc           #41                 // String 5-31
     465: ldc           #42                 // String
     467: ldc           #42                 // String
     469: aload         7
     471: invokevirtual #43                 // Method java/lang/Throwable.getMessage:()Ljava/lang/String;
     474: aload         7
     476: invokeinterface #44,  6           // InterfaceMethod org/apache/dubbo/common/logger/ErrorTypeAwareLogger.warn:(Ljava/lang/String;Ljava/lang/String;Ljava/lang/String;Ljava/lang/String;Ljava/lang/Throwable;)V
     481: new           #7                  // class org/apache/dubbo/common/status/Status
     484: dup
     485: aload_2
     486: aload         7
     488: invokevirtual #43                 // Method java/lang/Throwable.getMessage:()Ljava/lang/String;
     491: invokespecial #45                 // Method org/apache/dubbo/common/status/Status."<init>":(Lorg/apache/dubbo/common/status/Status$Level;Ljava/lang/String;)V
     494: areturn
     495: goto          98
     498: new           #7                  // class org/apache/dubbo/common/status/Status
     501: dup
     502: aload_2
     503: aload_3
     504: invokevirtual #46                 // Method java/lang/StringBuilder.toString:()Ljava/lang/String;
     507: invokespecial #45                 // Method org/apache/dubbo/common/status/Status."<init>":(Lorg/apache/dubbo/common/status/Status$Level;Ljava/lang/String;)V
     510: areturn
    Exception table:
       from    to  target type
         218   225   228   Class java/lang/Throwable
         194   208   250   Class java/lang/Throwable
         194   208   259   any
         271   278   281   Class java/lang/Throwable
         250   261   259   any
         370   377   380   Class java/lang/Throwable
         173   360   402   Class java/lang/Throwable
         173   360   411   any
         423   430   433   Class java/lang/Throwable
         402   413   411   any
         161   455   458   Class java/lang/Throwable

  static {};
    Code:
       0: ldc           #47                 // class org/apache/dubbo/config/spring/status/DataSourceStatusChecker
       2: invokestatic  #48                 // Method org/apache/dubbo/common/logger/LoggerFactory.getErrorTypeAwareLogger:(Ljava/lang/Class;)Lorg/apache/dubbo/common/logger/ErrorTypeAwareLogger;
       5: putstatic     #40                 // Field logger:Lorg/apache/dubbo/common/logger/ErrorTypeAwareLogger;
       8: return
}
