Compiled from "EntityManagerFactoryBuilder.java"
public class org.springframework.boot.orm.jpa.EntityManagerFactoryBuilder {
  private final org.springframework.orm.jpa.JpaVendorAdapter jpaVendorAdapter;

  private final org.springframework.orm.jpa.persistenceunit.PersistenceUnitManager persistenceUnitManager;

  private final java.util.Map<java.lang.String, java.lang.Object> jpaProperties;

  private final java.net.URL persistenceUnitRootLocation;

  private org.springframework.core.task.AsyncTaskExecutor bootstrapExecutor;

  private org.springframework.orm.jpa.persistenceunit.PersistenceUnitPostProcessor[] persistenceUnitPostProcessors;

  public org.springframework.boot.orm.jpa.EntityManagerFactoryBuilder(org.springframework.orm.jpa.JpaVendorAdapter, java.util.Map<java.lang.String, ?>, org.springframework.orm.jpa.persistenceunit.PersistenceUnitManager);
    Code:
       0: aload_0
       1: aload_1
       2: aload_2
       3: aload_3
       4: aconst_null
       5: invokespecial #1                  // Method "<init>":(Lorg/springframework/orm/jpa/JpaVendorAdapter;Ljava/util/Map;Lorg/springframework/orm/jpa/persistenceunit/PersistenceUnitManager;Ljava/net/URL;)V
       8: return

  public org.springframework.boot.orm.jpa.EntityManagerFactoryBuilder(org.springframework.orm.jpa.JpaVendorAdapter, java.util.Map<java.lang.String, ?>, org.springframework.orm.jpa.persistenceunit.PersistenceUnitManager, java.net.URL);
    Code:
       0: aload_0
       1: invokespecial #7                  // Method java/lang/Object."<init>":()V
       4: aload_0
       5: aload_1
       6: putfield      #12                 // Field jpaVendorAdapter:Lorg/springframework/orm/jpa/JpaVendorAdapter;
       9: aload_0
      10: aload_3
      11: putfield      #16                 // Field persistenceUnitManager:Lorg/springframework/orm/jpa/persistenceunit/PersistenceUnitManager;
      14: aload_0
      15: new           #20                 // class java/util/LinkedHashMap
      18: dup
      19: aload_2
      20: invokespecial #22                 // Method java/util/LinkedHashMap."<init>":(Ljava/util/Map;)V
      23: putfield      #25                 // Field jpaProperties:Ljava/util/Map;
      26: aload_0
      27: aload         4
      29: putfield      #29                 // Field persistenceUnitRootLocation:Ljava/net/URL;
      32: return

  public org.springframework.boot.orm.jpa.EntityManagerFactoryBuilder$Builder dataSource(javax.sql.DataSource);
    Code:
       0: new           #33                 // class org/springframework/boot/orm/jpa/EntityManagerFactoryBuilder$Builder
       3: dup
       4: aload_0
       5: aload_1
       6: invokespecial #35                 // Method org/springframework/boot/orm/jpa/EntityManagerFactoryBuilder$Builder."<init>":(Lorg/springframework/boot/orm/jpa/EntityManagerFactoryBuilder;Ljavax/sql/DataSource;)V
       9: areturn

  public void setBootstrapExecutor(org.springframework.core.task.AsyncTaskExecutor);
    Code:
       0: aload_0
       1: aload_1
       2: putfield      #38                 // Field bootstrapExecutor:Lorg/springframework/core/task/AsyncTaskExecutor;
       5: return

  public void setPersistenceUnitPostProcessors(org.springframework.orm.jpa.persistenceunit.PersistenceUnitPostProcessor...);
    Code:
       0: aload_0
       1: aload_1
       2: putfield      #42                 // Field persistenceUnitPostProcessors:[Lorg/springframework/orm/jpa/persistenceunit/PersistenceUnitPostProcessor;
       5: return
}
