Compiled from "EntityManagerFactoryBuilder.java"
public final class org.springframework.boot.orm.jpa.EntityManagerFactoryBuilder$Builder {
  private final javax.sql.DataSource dataSource;

  private org.springframework.orm.jpa.persistenceunit.PersistenceManagedTypes managedTypes;

  private java.lang.String[] packagesToScan;

  private java.lang.String persistenceUnit;

  private final java.util.Map<java.lang.String, java.lang.Object> properties;

  private java.lang.String[] mappingResources;

  private boolean jta;

  final org.springframework.boot.orm.jpa.EntityManagerFactoryBuilder this$0;

  private org.springframework.boot.orm.jpa.EntityManagerFactoryBuilder$Builder(org.springframework.boot.orm.jpa.EntityManagerFactoryBuilder, javax.sql.DataSource);
    Code:
       0: aload_0
       1: aload_1
       2: putfield      #1                  // Field this$0:Lorg/springframework/boot/orm/jpa/EntityManagerFactoryBuilder;
       5: aload_0
       6: invokespecial #7                  // Method java/lang/Object."<init>":()V
       9: aload_0
      10: new           #13                 // class java/util/HashMap
      13: dup
      14: invokespecial #15                 // Method java/util/HashMap."<init>":()V
      17: putfield      #16                 // Field properties:Ljava/util/Map;
      20: aload_0
      21: aload_2
      22: putfield      #20                 // Field dataSource:Ljavax/sql/DataSource;
      25: return

  public org.springframework.boot.orm.jpa.EntityManagerFactoryBuilder$Builder managedTypes(org.springframework.orm.jpa.persistenceunit.PersistenceManagedTypes);
    Code:
       0: aload_0
       1: aload_1
       2: putfield      #24                 // Field managedTypes:Lorg/springframework/orm/jpa/persistenceunit/PersistenceManagedTypes;
       5: aload_0
       6: areturn

  public org.springframework.boot.orm.jpa.EntityManagerFactoryBuilder$Builder packages(java.lang.String...);
    Code:
       0: aload_0
       1: aload_1
       2: putfield      #28                 // Field packagesToScan:[Ljava/lang/String;
       5: aload_0
       6: areturn

  public org.springframework.boot.orm.jpa.EntityManagerFactoryBuilder$Builder packages(java.lang.Class<?>...);
    Code:
       0: new           #32                 // class java/util/HashSet
       3: dup
       4: invokespecial #34                 // Method java/util/HashSet."<init>":()V
       7: astore_2
       8: aload_1
       9: astore_3
      10: aload_3
      11: arraylength
      12: istore        4
      14: iconst_0
      15: istore        5
      17: iload         5
      19: iload         4
      21: if_icmpge     48
      24: aload_3
      25: iload         5
      27: aaload
      28: astore        6
      30: aload_2
      31: aload         6
      33: invokestatic  #35                 // Method org/springframework/util/ClassUtils.getPackageName:(Ljava/lang/Class;)Ljava/lang/String;
      36: invokeinterface #41,  2           // InterfaceMethod java/util/Set.add:(Ljava/lang/Object;)Z
      41: pop
      42: iinc          5, 1
      45: goto          17
      48: aload_0
      49: aload_2
      50: invokestatic  #47                 // Method org/springframework/util/StringUtils.toStringArray:(Ljava/util/Collection;)[Ljava/lang/String;
      53: putfield      #28                 // Field packagesToScan:[Ljava/lang/String;
      56: aload_0
      57: areturn

  public org.springframework.boot.orm.jpa.EntityManagerFactoryBuilder$Builder persistenceUnit(java.lang.String);
    Code:
       0: aload_0
       1: aload_1
       2: putfield      #53                 // Field persistenceUnit:Ljava/lang/String;
       5: aload_0
       6: areturn

  public org.springframework.boot.orm.jpa.EntityManagerFactoryBuilder$Builder properties(java.util.Map<java.lang.String, ?>);
    Code:
       0: aload_0
       1: getfield      #16                 // Field properties:Ljava/util/Map;
       4: aload_1
       5: invokeinterface #57,  2           // InterfaceMethod java/util/Map.putAll:(Ljava/util/Map;)V
      10: aload_0
      11: areturn

  public org.springframework.boot.orm.jpa.EntityManagerFactoryBuilder$Builder mappingResources(java.lang.String...);
    Code:
       0: aload_0
       1: aload_1
       2: putfield      #63                 // Field mappingResources:[Ljava/lang/String;
       5: aload_0
       6: areturn

  public org.springframework.boot.orm.jpa.EntityManagerFactoryBuilder$Builder jta(boolean);
    Code:
       0: aload_0
       1: iload_1
       2: putfield      #66                 // Field jta:Z
       5: aload_0
       6: areturn

  public org.springframework.orm.jpa.LocalContainerEntityManagerFactoryBean build();
    Code:
       0: new           #70                 // class org/springframework/orm/jpa/LocalContainerEntityManagerFactoryBean
       3: dup
       4: invokespecial #72                 // Method org/springframework/orm/jpa/LocalContainerEntityManagerFactoryBean."<init>":()V
       7: astore_1
       8: aload_0
       9: getfield      #1                  // Field this$0:Lorg/springframework/boot/orm/jpa/EntityManagerFactoryBuilder;
      12: getfield      #73                 // Field org/springframework/boot/orm/jpa/EntityManagerFactoryBuilder.persistenceUnitManager:Lorg/springframework/orm/jpa/persistenceunit/PersistenceUnitManager;
      15: ifnull        29
      18: aload_1
      19: aload_0
      20: getfield      #1                  // Field this$0:Lorg/springframework/boot/orm/jpa/EntityManagerFactoryBuilder;
      23: getfield      #73                 // Field org/springframework/boot/orm/jpa/EntityManagerFactoryBuilder.persistenceUnitManager:Lorg/springframework/orm/jpa/persistenceunit/PersistenceUnitManager;
      26: invokevirtual #79                 // Method org/springframework/orm/jpa/LocalContainerEntityManagerFactoryBean.setPersistenceUnitManager:(Lorg/springframework/orm/jpa/persistenceunit/PersistenceUnitManager;)V
      29: aload_0
      30: getfield      #53                 // Field persistenceUnit:Ljava/lang/String;
      33: ifnull        44
      36: aload_1
      37: aload_0
      38: getfield      #53                 // Field persistenceUnit:Ljava/lang/String;
      41: invokevirtual #83                 // Method org/springframework/orm/jpa/LocalContainerEntityManagerFactoryBean.setPersistenceUnitName:(Ljava/lang/String;)V
      44: aload_1
      45: aload_0
      46: getfield      #1                  // Field this$0:Lorg/springframework/boot/orm/jpa/EntityManagerFactoryBuilder;
      49: getfield      #87                 // Field org/springframework/boot/orm/jpa/EntityManagerFactoryBuilder.jpaVendorAdapter:Lorg/springframework/orm/jpa/JpaVendorAdapter;
      52: invokevirtual #91                 // Method org/springframework/orm/jpa/LocalContainerEntityManagerFactoryBean.setJpaVendorAdapter:(Lorg/springframework/orm/jpa/JpaVendorAdapter;)V
      55: aload_0
      56: getfield      #66                 // Field jta:Z
      59: ifeq          73
      62: aload_1
      63: aload_0
      64: getfield      #20                 // Field dataSource:Ljavax/sql/DataSource;
      67: invokevirtual #95                 // Method org/springframework/orm/jpa/LocalContainerEntityManagerFactoryBean.setJtaDataSource:(Ljavax/sql/DataSource;)V
      70: goto          81
      73: aload_1
      74: aload_0
      75: getfield      #20                 // Field dataSource:Ljavax/sql/DataSource;
      78: invokevirtual #99                 // Method org/springframework/orm/jpa/LocalContainerEntityManagerFactoryBean.setDataSource:(Ljavax/sql/DataSource;)V
      81: aload_0
      82: getfield      #24                 // Field managedTypes:Lorg/springframework/orm/jpa/persistenceunit/PersistenceManagedTypes;
      85: ifnull        99
      88: aload_1
      89: aload_0
      90: getfield      #24                 // Field managedTypes:Lorg/springframework/orm/jpa/persistenceunit/PersistenceManagedTypes;
      93: invokevirtual #102                // Method org/springframework/orm/jpa/LocalContainerEntityManagerFactoryBean.setManagedTypes:(Lorg/springframework/orm/jpa/persistenceunit/PersistenceManagedTypes;)V
      96: goto          107
      99: aload_1
     100: aload_0
     101: getfield      #28                 // Field packagesToScan:[Ljava/lang/String;
     104: invokevirtual #106                // Method org/springframework/orm/jpa/LocalContainerEntityManagerFactoryBean.setPackagesToScan:([Ljava/lang/String;)V
     107: aload_1
     108: invokevirtual #110                // Method org/springframework/orm/jpa/LocalContainerEntityManagerFactoryBean.getJpaPropertyMap:()Ljava/util/Map;
     111: aload_0
     112: getfield      #1                  // Field this$0:Lorg/springframework/boot/orm/jpa/EntityManagerFactoryBuilder;
     115: getfield      #114                // Field org/springframework/boot/orm/jpa/EntityManagerFactoryBuilder.jpaProperties:Ljava/util/Map;
     118: invokeinterface #57,  2           // InterfaceMethod java/util/Map.putAll:(Ljava/util/Map;)V
     123: aload_1
     124: invokevirtual #110                // Method org/springframework/orm/jpa/LocalContainerEntityManagerFactoryBean.getJpaPropertyMap:()Ljava/util/Map;
     127: aload_0
     128: getfield      #16                 // Field properties:Ljava/util/Map;
     131: invokeinterface #57,  2           // InterfaceMethod java/util/Map.putAll:(Ljava/util/Map;)V
     136: aload_0
     137: getfield      #63                 // Field mappingResources:[Ljava/lang/String;
     140: invokestatic  #117                // Method org/springframework/util/ObjectUtils.isEmpty:([Ljava/lang/Object;)Z
     143: ifne          154
     146: aload_1
     147: aload_0
     148: getfield      #63                 // Field mappingResources:[Ljava/lang/String;
     151: invokevirtual #123                // Method org/springframework/orm/jpa/LocalContainerEntityManagerFactoryBean.setMappingResources:([Ljava/lang/String;)V
     154: aload_0
     155: getfield      #1                  // Field this$0:Lorg/springframework/boot/orm/jpa/EntityManagerFactoryBuilder;
     158: getfield      #126                // Field org/springframework/boot/orm/jpa/EntityManagerFactoryBuilder.persistenceUnitRootLocation:Ljava/net/URL;
     161: astore_2
     162: aload_2
     163: ifnull        174
     166: aload_1
     167: aload_2
     168: invokevirtual #130                // Method java/net/URL.toString:()Ljava/lang/String;
     171: invokevirtual #136                // Method org/springframework/orm/jpa/LocalContainerEntityManagerFactoryBean.setPersistenceUnitRootLocation:(Ljava/lang/String;)V
     174: aload_0
     175: getfield      #1                  // Field this$0:Lorg/springframework/boot/orm/jpa/EntityManagerFactoryBuilder;
     178: getfield      #139                // Field org/springframework/boot/orm/jpa/EntityManagerFactoryBuilder.bootstrapExecutor:Lorg/springframework/core/task/AsyncTaskExecutor;
     181: ifnull        195
     184: aload_1
     185: aload_0
     186: getfield      #1                  // Field this$0:Lorg/springframework/boot/orm/jpa/EntityManagerFactoryBuilder;
     189: getfield      #139                // Field org/springframework/boot/orm/jpa/EntityManagerFactoryBuilder.bootstrapExecutor:Lorg/springframework/core/task/AsyncTaskExecutor;
     192: invokevirtual #143                // Method org/springframework/orm/jpa/LocalContainerEntityManagerFactoryBean.setBootstrapExecutor:(Lorg/springframework/core/task/AsyncTaskExecutor;)V
     195: aload_0
     196: getfield      #1                  // Field this$0:Lorg/springframework/boot/orm/jpa/EntityManagerFactoryBuilder;
     199: getfield      #147                // Field org/springframework/boot/orm/jpa/EntityManagerFactoryBuilder.persistenceUnitPostProcessors:[Lorg/springframework/orm/jpa/persistenceunit/PersistenceUnitPostProcessor;
     202: ifnull        216
     205: aload_1
     206: aload_0
     207: getfield      #1                  // Field this$0:Lorg/springframework/boot/orm/jpa/EntityManagerFactoryBuilder;
     210: getfield      #147                // Field org/springframework/boot/orm/jpa/EntityManagerFactoryBuilder.persistenceUnitPostProcessors:[Lorg/springframework/orm/jpa/persistenceunit/PersistenceUnitPostProcessor;
     213: invokevirtual #151                // Method org/springframework/orm/jpa/LocalContainerEntityManagerFactoryBean.setPersistenceUnitPostProcessors:([Lorg/springframework/orm/jpa/persistenceunit/PersistenceUnitPostProcessor;)V
     216: aload_1
     217: areturn
}
