Compiled from "JpaDatabaseInitializerDetector.java"
class org.springframework.boot.orm.jpa.JpaDatabaseInitializerDetector extends org.springframework.boot.sql.init.dependency.AbstractBeansOfTypeDatabaseInitializerDetector {
  private final org.springframework.core.env.Environment environment;

  org.springframework.boot.orm.jpa.JpaDatabaseInitializerDetector(org.springframework.core.env.Environment);
    Code:
       0: aload_0
       1: invokespecial #1                  // Method org/springframework/boot/sql/init/dependency/AbstractBeansOfTypeDatabaseInitializerDetector."<init>":()V
       4: aload_0
       5: aload_1
       6: putfield      #7                  // Field environment:Lorg/springframework/core/env/Environment;
       9: return

  protected java.util.Set<java.lang.Class<?>> getDatabaseInitializerBeanTypes();
    Code:
       0: aload_0
       1: getfield      #7                  // Field environment:Lorg/springframework/core/env/Environment;
       4: ldc           #13                 // String spring.jpa.defer-datasource-initialization
       6: getstatic     #15                 // Field java/lang/Boolean.TYPE:Ljava/lang/Class;
       9: iconst_0
      10: invokestatic  #21                 // Method java/lang/Boolean.valueOf:(Z)Ljava/lang/Boolean;
      13: invokeinterface #25,  4           // InterfaceMethod org/springframework/core/env/Environment.getProperty:(Ljava/lang/String;Ljava/lang/Class;Ljava/lang/Object;)Ljava/lang/Object;
      18: checkcast     #16                 // class java/lang/Boolean
      21: invokevirtual #31                 // Method java/lang/Boolean.booleanValue:()Z
      24: istore_1
      25: iload_1
      26: ifeq          37
      29: ldc           #35                 // class jakarta/persistence/EntityManagerFactory
      31: invokestatic  #37                 // Method java/util/Collections.singleton:(Ljava/lang/Object;)Ljava/util/Set;
      34: goto          40
      37: invokestatic  #43                 // Method java/util/Collections.emptySet:()Ljava/util/Set;
      40: areturn

  public void detectionComplete(org.springframework.beans.factory.config.ConfigurableListableBeanFactory, java.util.Set<java.lang.String>);
    Code:
       0: aload_0
       1: aload_1
       2: aload_2
       3: invokevirtual #47                 // Method configureOtherInitializersToDependOnJpaInitializers:(Lorg/springframework/beans/factory/config/ConfigurableListableBeanFactory;Ljava/util/Set;)V
       6: return

  private void configureOtherInitializersToDependOnJpaInitializers(org.springframework.beans.factory.config.ConfigurableListableBeanFactory, java.util.Set<java.lang.String>);
    Code:
       0: new           #51                 // class java/util/HashSet
       3: dup
       4: invokespecial #53                 // Method java/util/HashSet."<init>":()V
       7: astore_3
       8: new           #51                 // class java/util/HashSet
      11: dup
      12: aload_2
      13: invokespecial #54                 // Method java/util/HashSet."<init>":(Ljava/util/Collection;)V
      16: astore        4
      18: aload         4
      20: invokeinterface #57,  1           // InterfaceMethod java/util/Set.iterator:()Ljava/util/Iterator;
      25: astore        5
      27: aload         5
      29: invokeinterface #63,  1           // InterfaceMethod java/util/Iterator.hasNext:()Z
      34: ifeq          101
      37: aload         5
      39: invokeinterface #68,  1           // InterfaceMethod java/util/Iterator.next:()Ljava/lang/Object;
      44: checkcast     #72                 // class java/lang/String
      47: astore        6
      49: aload_1
      50: aload         6
      52: invokeinterface #74,  2           // InterfaceMethod org/springframework/beans/factory/config/ConfigurableListableBeanFactory.getBeanDefinition:(Ljava/lang/String;)Lorg/springframework/beans/factory/config/BeanDefinition;
      57: astore        7
      59: ldc           #8                  // class org/springframework/boot/orm/jpa/JpaDatabaseInitializerDetector
      61: invokevirtual #80                 // Method java/lang/Class.getName:()Ljava/lang/String;
      64: aload         7
      66: ldc           #86                 // class org/springframework/boot/sql/init/dependency/DatabaseInitializerDetector
      68: invokevirtual #80                 // Method java/lang/Class.getName:()Ljava/lang/String;
      71: invokeinterface #88,  2           // InterfaceMethod org/springframework/beans/factory/config/BeanDefinition.getAttribute:(Ljava/lang/String;)Ljava/lang/Object;
      76: invokevirtual #94                 // Method java/lang/String.equals:(Ljava/lang/Object;)Z
      79: ifeq          98
      82: aload         5
      84: invokeinterface #98,  1           // InterfaceMethod java/util/Iterator.remove:()V
      89: aload_3
      90: aload         6
      92: invokeinterface #101,  2          // InterfaceMethod java/util/Set.add:(Ljava/lang/Object;)Z
      97: pop
      98: goto          27
     101: aload         4
     103: invokeinterface #57,  1           // InterfaceMethod java/util/Set.iterator:()Ljava/util/Iterator;
     108: astore        6
     110: aload         6
     112: invokeinterface #63,  1           // InterfaceMethod java/util/Iterator.hasNext:()Z
     117: ifeq          205
     120: aload         6
     122: invokeinterface #68,  1           // InterfaceMethod java/util/Iterator.next:()Ljava/lang/Object;
     127: checkcast     #72                 // class java/lang/String
     130: astore        7
     132: aload_1
     133: aload         7
     135: invokeinterface #74,  2           // InterfaceMethod org/springframework/beans/factory/config/ConfigurableListableBeanFactory.getBeanDefinition:(Ljava/lang/String;)Lorg/springframework/beans/factory/config/BeanDefinition;
     140: astore        8
     142: aload         8
     144: invokeinterface #104,  1          // InterfaceMethod org/springframework/beans/factory/config/BeanDefinition.getDependsOn:()[Ljava/lang/String;
     149: astore        9
     151: aload_3
     152: invokeinterface #57,  1           // InterfaceMethod java/util/Set.iterator:()Ljava/util/Iterator;
     157: astore        10
     159: aload         10
     161: invokeinterface #63,  1           // InterfaceMethod java/util/Iterator.hasNext:()Z
     166: ifeq          193
     169: aload         10
     171: invokeinterface #68,  1           // InterfaceMethod java/util/Iterator.next:()Ljava/lang/Object;
     176: checkcast     #72                 // class java/lang/String
     179: astore        11
     181: aload         9
     183: aload         11
     185: invokestatic  #108                // Method org/springframework/util/StringUtils.addStringToArray:([Ljava/lang/String;Ljava/lang/String;)[Ljava/lang/String;
     188: astore        9
     190: goto          159
     193: aload         8
     195: aload         9
     197: invokeinterface #114,  2          // InterfaceMethod org/springframework/beans/factory/config/BeanDefinition.setDependsOn:([Ljava/lang/String;)V
     202: goto          110
     205: return
}
