Compiled from "JpaDependsOnDatabaseInitializationDetector.java"
class org.springframework.boot.orm.jpa.JpaDependsOnDatabaseInitializationDetector extends org.springframework.boot.sql.init.dependency.AbstractBeansOfTypeDependsOnDatabaseInitializationDetector {
  private final org.springframework.core.env.Environment environment;

  org.springframework.boot.orm.jpa.JpaDependsOnDatabaseInitializationDetector(org.springframework.core.env.Environment);
    Code:
       0: aload_0
       1: invokespecial #1                  // Method org/springframework/boot/sql/init/dependency/AbstractBeansOfTypeDependsOnDatabaseInitializationDetector."<init>":()V
       4: aload_0
       5: aload_1
       6: putfield      #7                  // Field environment:Lorg/springframework/core/env/Environment;
       9: return

  protected java.util.Set<java.lang.Class<?>> getDependsOnDatabaseInitializationBeanTypes();
    Code:
       0: aload_0
       1: getfield      #7                  // Field environment:Lorg/springframework/core/env/Environment;
       4: ldc           #13                 // String spring.jpa.defer-datasource-initialization
       6: getstatic     #15                 // Field java/lang/Boolean.TYPE:Ljava/lang/Class;
       9: iconst_0
      10: invokestatic  #21                 // Method java/lang/Boolean.valueOf:(Z)Ljava/lang/Boolean;
      13: invokeinterface #25,  4           // InterfaceMethod org/springframework/core/env/Environment.getProperty:(Ljava/lang/String;Ljava/lang/Class;Ljava/lang/Object;)Ljava/lang/Object;
      18: checkcast     #16                 // class java/lang/Boolean
      21: invokevirtual #31                 // Method java/lang/Boolean.booleanValue:()Z
      24: istore_1
      25: iload_1
      26: ifeq          35
      29: invokestatic  #35                 // Method java/util/Collections.emptySet:()Ljava/util/Set;
      32: goto          59
      35: new           #41                 // class java/util/HashSet
      38: dup
      39: iconst_2
      40: anewarray     #43                 // class java/lang/Class
      43: dup
      44: iconst_0
      45: ldc           #45                 // class jakarta/persistence/EntityManagerFactory
      47: aastore
      48: dup
      49: iconst_1
      50: ldc           #47                 // class org/springframework/orm/jpa/AbstractEntityManagerFactoryBean
      52: aastore
      53: invokestatic  #49                 // Method java/util/Arrays.asList:([Ljava/lang/Object;)Ljava/util/List;
      56: invokespecial #55                 // Method java/util/HashSet."<init>":(Ljava/util/Collection;)V
      59: areturn
}
