Compiled from "MetaCacheManager.java"
public class org.apache.dubbo.registry.client.metadata.store.MetaCacheManager extends org.apache.dubbo.metadata.AbstractCacheManager<org.apache.dubbo.metadata.MetadataInfo> {
  private static final java.lang.String DEFAULT_FILE_NAME;

  private static final int DEFAULT_ENTRY_SIZE;

  public static org.apache.dubbo.registry.client.metadata.store.MetaCacheManager getInstance(org.apache.dubbo.rpc.model.ScopeModel);
    Code:
       0: aload_0
       1: invokevirtual #1                  // Method org/apache/dubbo/rpc/model/ScopeModel.getBeanFactory:()Lorg/apache/dubbo/common/beans/factory/ScopeBeanFactory;
       4: ldc           #2                  // class org/apache/dubbo/registry/client/metadata/store/MetaCacheManager
       6: invokevirtual #3                  // Method org/apache/dubbo/common/beans/factory/ScopeBeanFactory.getOrRegisterBean:(Ljava/lang/Class;)Ljava/lang/Object;
       9: checkcast     #2                  // class org/apache/dubbo/registry/client/metadata/store/MetaCacheManager
      12: areturn

  public org.apache.dubbo.registry.client.metadata.store.MetaCacheManager(boolean, java.lang.String, java.util.concurrent.ScheduledExecutorService);
    Code:
       0: aload_0
       1: invokespecial #4                  // Method org/apache/dubbo/metadata/AbstractCacheManager."<init>":()V
       4: ldc           #5                  // String dubbo.meta.cache.filePath
       6: invokestatic  #6                  // Method java/lang/System.getProperty:(Ljava/lang/String;)Ljava/lang/String;
       9: astore        4
      11: ldc           #7                  // String dubbo.meta.cache.fileName
      13: invokestatic  #6                  // Method java/lang/System.getProperty:(Ljava/lang/String;)Ljava/lang/String;
      16: astore        5
      18: aload         5
      20: invokestatic  #8                  // Method org/apache/dubbo/common/utils/StringUtils.isEmpty:(Ljava/lang/String;)Z
      23: ifeq          30
      26: ldc           #9                  // String .metadata
      28: astore        5
      30: aload_2
      31: invokestatic  #10                 // Method org/apache/dubbo/common/utils/StringUtils.isNotEmpty:(Ljava/lang/String;)Z
      34: ifeq          63
      37: new           #11                 // class java/lang/StringBuilder
      40: dup
      41: invokespecial #12                 // Method java/lang/StringBuilder."<init>":()V
      44: aload         5
      46: invokevirtual #13                 // Method java/lang/StringBuilder.append:(Ljava/lang/String;)Ljava/lang/StringBuilder;
      49: ldc           #14                 // String .
      51: invokevirtual #13                 // Method java/lang/StringBuilder.append:(Ljava/lang/String;)Ljava/lang/StringBuilder;
      54: aload_2
      55: invokevirtual #13                 // Method java/lang/StringBuilder.append:(Ljava/lang/String;)Ljava/lang/StringBuilder;
      58: invokevirtual #15                 // Method java/lang/StringBuilder.toString:()Ljava/lang/String;
      61: astore        5
      63: ldc           #16                 // String dubbo.meta.cache.entrySize
      65: invokestatic  #6                  // Method java/lang/System.getProperty:(Ljava/lang/String;)Ljava/lang/String;
      68: astore        6
      70: aload         6
      72: invokestatic  #17                 // Method org/apache/dubbo/common/utils/StringUtils.parseInteger:(Ljava/lang/String;)I
      75: istore        7
      77: iload         7
      79: ifne          87
      82: bipush        100
      84: goto          89
      87: iload         7
      89: istore        7
      91: ldc           #18                 // String dubbo.meta.cache.maxFileSize
      93: invokestatic  #6                  // Method java/lang/System.getProperty:(Ljava/lang/String;)Ljava/lang/String;
      96: astore        8
      98: aload         8
     100: invokestatic  #19                 // Method org/apache/dubbo/common/utils/StringUtils.parseLong:(Ljava/lang/String;)J
     103: lstore        9
     105: aload_0
     106: iload_1
     107: aload         4
     109: aload         5
     111: iload         7
     113: lload         9
     115: bipush        60
     117: aload_3
     118: invokevirtual #20                 // Method init:(ZLjava/lang/String;Ljava/lang/String;IJILjava/util/concurrent/ScheduledExecutorService;)V
     121: return

  public org.apache.dubbo.registry.client.metadata.store.MetaCacheManager();
    Code:
       0: aload_0
       1: iconst_1
       2: ldc           #21                 // String
       4: aconst_null
       5: invokespecial #22                 // Method "<init>":(ZLjava/lang/String;Ljava/util/concurrent/ScheduledExecutorService;)V
       8: return

  protected org.apache.dubbo.metadata.MetadataInfo toValueType(java.lang.String);
    Code:
       0: aload_1
       1: ldc           #23                 // class org/apache/dubbo/metadata/MetadataInfo
       3: invokestatic  #24                 // Method org/apache/dubbo/common/utils/JsonUtils.toJavaObject:(Ljava/lang/String;Ljava/lang/reflect/Type;)Ljava/lang/Object;
       6: checkcast     #23                 // class org/apache/dubbo/metadata/MetadataInfo
       9: areturn

  protected java.lang.String getName();
    Code:
       0: ldc           #25                 // String meta
       2: areturn

  protected java.lang.Object toValueType(java.lang.String);
    Code:
       0: aload_0
       1: aload_1
       2: invokevirtual #26                 // Method toValueType:(Ljava/lang/String;)Lorg/apache/dubbo/metadata/MetadataInfo;
       5: areturn
}
