Compiled from "InfoProperties.java"
final class org.springframework.boot.info.InfoProperties$PropertiesIterator implements java.util.Iterator<org.springframework.boot.info.InfoProperties$Entry> {
  private final java.util.Iterator<java.util.Map$Entry<java.lang.Object, java.lang.Object>> iterator;

  private org.springframework.boot.info.InfoProperties$PropertiesIterator(java.util.Properties);
    Code:
       0: aload_0
       1: invokespecial #1                  // Method java/lang/Object."<init>":()V
       4: aload_0
       5: aload_1
       6: invokevirtual #7                  // Method java/util/Properties.entrySet:()Ljava/util/Set;
       9: invokeinterface #13,  1           // InterfaceMethod java/util/Set.iterator:()Ljava/util/Iterator;
      14: putfield      #19                 // Field iterator:Ljava/util/Iterator;
      17: return

  public boolean hasNext();
    Code:
       0: aload_0
       1: getfield      #19                 // Field iterator:Ljava/util/Iterator;
       4: invokeinterface #24,  1           // InterfaceMethod java/util/Iterator.hasNext:()Z
       9: ireturn

  public org.springframework.boot.info.InfoProperties$Entry next();
    Code:
       0: aload_0
       1: getfield      #19                 // Field iterator:Ljava/util/Iterator;
       4: invokeinterface #30,  1           // InterfaceMethod java/util/Iterator.next:()Ljava/lang/Object;
       9: checkcast     #34                 // class java/util/Map$Entry
      12: astore_1
      13: new           #36                 // class org/springframework/boot/info/InfoProperties$Entry
      16: dup
      17: aload_1
      18: invokeinterface #38,  1           // InterfaceMethod java/util/Map$Entry.getKey:()Ljava/lang/Object;
      23: checkcast     #41                 // class java/lang/String
      26: aload_1
      27: invokeinterface #43,  1           // InterfaceMethod java/util/Map$Entry.getValue:()Ljava/lang/Object;
      32: checkcast     #41                 // class java/lang/String
      35: invokespecial #46                 // Method org/springframework/boot/info/InfoProperties$Entry."<init>":(Ljava/lang/String;Ljava/lang/String;)V
      38: areturn

  public void remove();
    Code:
       0: new           #49                 // class java/lang/UnsupportedOperationException
       3: dup
       4: ldc           #51                 // String InfoProperties are immutable.
       6: invokespecial #53                 // Method java/lang/UnsupportedOperationException."<init>":(Ljava/lang/String;)V
       9: athrow

  public java.lang.Object next();
    Code:
       0: aload_0
       1: invokevirtual #56                 // Method next:()Lorg/springframework/boot/info/InfoProperties$Entry;
       4: areturn
}
