Compiled from "JavaInfo.java"
public class org.springframework.boot.info.JavaInfo {
  private final java.lang.String version;

  private final org.springframework.boot.info.JavaInfo$JavaVendorInfo vendor;

  private final org.springframework.boot.info.JavaInfo$JavaRuntimeEnvironmentInfo runtime;

  private final org.springframework.boot.info.JavaInfo$JavaVirtualMachineInfo jvm;

  public org.springframework.boot.info.JavaInfo();
    Code:
       0: aload_0
       1: invokespecial #1                  // Method java/lang/Object."<init>":()V
       4: aload_0
       5: ldc           #7                  // String java.version
       7: invokestatic  #9                  // Method java/lang/System.getProperty:(Ljava/lang/String;)Ljava/lang/String;
      10: putfield      #15                 // Field version:Ljava/lang/String;
      13: aload_0
      14: new           #21                 // class org/springframework/boot/info/JavaInfo$JavaVendorInfo
      17: dup
      18: invokespecial #23                 // Method org/springframework/boot/info/JavaInfo$JavaVendorInfo."<init>":()V
      21: putfield      #24                 // Field vendor:Lorg/springframework/boot/info/JavaInfo$JavaVendorInfo;
      24: aload_0
      25: new           #28                 // class org/springframework/boot/info/JavaInfo$JavaRuntimeEnvironmentInfo
      28: dup
      29: invokespecial #30                 // Method org/springframework/boot/info/JavaInfo$JavaRuntimeEnvironmentInfo."<init>":()V
      32: putfield      #31                 // Field runtime:Lorg/springframework/boot/info/JavaInfo$JavaRuntimeEnvironmentInfo;
      35: aload_0
      36: new           #35                 // class org/springframework/boot/info/JavaInfo$JavaVirtualMachineInfo
      39: dup
      40: invokespecial #37                 // Method org/springframework/boot/info/JavaInfo$JavaVirtualMachineInfo."<init>":()V
      43: putfield      #38                 // Field jvm:Lorg/springframework/boot/info/JavaInfo$JavaVirtualMachineInfo;
      46: return

  public java.lang.String getVersion();
    Code:
       0: aload_0
       1: getfield      #15                 // Field version:Ljava/lang/String;
       4: areturn

  public org.springframework.boot.info.JavaInfo$JavaVendorInfo getVendor();
    Code:
       0: aload_0
       1: getfield      #24                 // Field vendor:Lorg/springframework/boot/info/JavaInfo$JavaVendorInfo;
       4: areturn

  public org.springframework.boot.info.JavaInfo$JavaRuntimeEnvironmentInfo getRuntime();
    Code:
       0: aload_0
       1: getfield      #31                 // Field runtime:Lorg/springframework/boot/info/JavaInfo$JavaRuntimeEnvironmentInfo;
       4: areturn

  public org.springframework.boot.info.JavaInfo$JavaVirtualMachineInfo getJvm();
    Code:
       0: aload_0
       1: getfield      #38                 // Field jvm:Lorg/springframework/boot/info/JavaInfo$JavaVirtualMachineInfo;
       4: areturn
}
