Compiled from "JavaInfo.java"
public class org.springframework.boot.info.JavaInfo$JavaVirtualMachineInfo {
  private final java.lang.String name;

  private final java.lang.String vendor;

  private final java.lang.String version;

  public org.springframework.boot.info.JavaInfo$JavaVirtualMachineInfo();
    Code:
       0: aload_0
       1: invokespecial #1                  // Method java/lang/Object."<init>":()V
       4: aload_0
       5: ldc           #7                  // String java.vm.name
       7: invokestatic  #9                  // Method java/lang/System.getProperty:(Ljava/lang/String;)Ljava/lang/String;
      10: putfield      #15                 // Field name:Ljava/lang/String;
      13: aload_0
      14: ldc           #21                 // String java.vm.vendor
      16: invokestatic  #9                  // Method java/lang/System.getProperty:(Ljava/lang/String;)Ljava/lang/String;
      19: putfield      #23                 // Field vendor:Ljava/lang/String;
      22: aload_0
      23: ldc           #26                 // String java.vm.version
      25: invokestatic  #9                  // Method java/lang/System.getProperty:(Ljava/lang/String;)Ljava/lang/String;
      28: putfield      #28                 // Field version:Ljava/lang/String;
      31: return

  public java.lang.String getName();
    Code:
       0: aload_0
       1: getfield      #15                 // Field name:Ljava/lang/String;
       4: areturn

  public java.lang.String getVendor();
    Code:
       0: aload_0
       1: getfield      #23                 // Field vendor:Ljava/lang/String;
       4: areturn

  public java.lang.String getVersion();
    Code:
       0: aload_0
       1: getfield      #28                 // Field version:Ljava/lang/String;
       4: areturn
}
