Compiled from "JadxPluginManager.java"
final class jadx.api.plugins.JadxPluginManager$PluginData implements java.lang.Comparable<jadx.api.plugins.JadxPluginManager$PluginData> {
  private final jadx.api.plugins.JadxPlugin plugin;

  private final jadx.api.plugins.JadxPluginInfo info;

  private jadx.api.plugins.JadxPluginManager$PluginData(jadx.api.plugins.JadxPlugin, jadx.api.plugins.JadxPluginInfo);
    Code:
       0: aload_0
       1: invokespecial #2                  // Method java/lang/Object."<init>":()V
       4: aload_0
       5: aload_1
       6: putfield      #3                  // Field plugin:Ljadx/api/plugins/JadxPlugin;
       9: aload_0
      10: aload_2
      11: putfield      #4                  // Field info:Ljadx/api/plugins/JadxPluginInfo;
      14: return

  public jadx.api.plugins.JadxPlugin getPlugin();
    Code:
       0: aload_0
       1: getfield      #3                  // Field plugin:Ljadx/api/plugins/JadxPlugin;
       4: areturn

  public jadx.api.plugins.JadxPluginInfo getInfo();
    Code:
       0: aload_0
       1: getfield      #4                  // Field info:Ljadx/api/plugins/JadxPluginInfo;
       4: areturn

  public java.lang.String getPluginId();
    Code:
       0: aload_0
       1: getfield      #4                  // Field info:Ljadx/api/plugins/JadxPluginInfo;
       4: invokevirtual #5                  // Method jadx/api/plugins/JadxPluginInfo.getPluginId:()Ljava/lang/String;
       7: areturn

  public int compareTo(jadx.api.plugins.JadxPluginManager$PluginData);
    Code:
       0: aload_0
       1: getfield      #4                  // Field info:Ljadx/api/plugins/JadxPluginInfo;
       4: invokevirtual #5                  // Method jadx/api/plugins/JadxPluginInfo.getPluginId:()Ljava/lang/String;
       7: aload_1
       8: getfield      #4                  // Field info:Ljadx/api/plugins/JadxPluginInfo;
      11: invokevirtual #5                  // Method jadx/api/plugins/JadxPluginInfo.getPluginId:()Ljava/lang/String;
      14: invokevirtual #6                  // Method java/lang/String.compareTo:(Ljava/lang/String;)I
      17: ireturn

  public boolean equals(java.lang.Object);
    Code:
       0: aload_0
       1: aload_1
       2: if_acmpne     7
       5: iconst_1
       6: ireturn
       7: aload_1
       8: instanceof    #7                  // class jadx/api/plugins/JadxPluginManager$PluginData
      11: ifne          16
      14: iconst_0
      15: ireturn
      16: aload_1
      17: checkcast     #7                  // class jadx/api/plugins/JadxPluginManager$PluginData
      20: astore_2
      21: aload_0
      22: invokevirtual #8                  // Method getInfo:()Ljadx/api/plugins/JadxPluginInfo;
      25: invokevirtual #5                  // Method jadx/api/plugins/JadxPluginInfo.getPluginId:()Ljava/lang/String;
      28: aload_2
      29: invokevirtual #8                  // Method getInfo:()Ljadx/api/plugins/JadxPluginInfo;
      32: invokevirtual #5                  // Method jadx/api/plugins/JadxPluginInfo.getPluginId:()Ljava/lang/String;
      35: invokevirtual #9                  // Method java/lang/String.equals:(Ljava/lang/Object;)Z
      38: ireturn

  public int hashCode();
    Code:
       0: aload_0
       1: getfield      #4                  // Field info:Ljadx/api/plugins/JadxPluginInfo;
       4: invokevirtual #5                  // Method jadx/api/plugins/JadxPluginInfo.getPluginId:()Ljava/lang/String;
       7: invokevirtual #10                 // Method java/lang/String.hashCode:()I
      10: ireturn

  public java.lang.String toString();
    Code:
       0: aload_0
       1: getfield      #4                  // Field info:Ljadx/api/plugins/JadxPluginInfo;
       4: invokevirtual #5                  // Method jadx/api/plugins/JadxPluginInfo.getPluginId:()Ljava/lang/String;
       7: areturn

  public int compareTo(java.lang.Object);
    Code:
       0: aload_0
       1: aload_1
       2: checkcast     #7                  // class jadx/api/plugins/JadxPluginManager$PluginData
       5: invokevirtual #11                 // Method compareTo:(Ljadx/api/plugins/JadxPluginManager$PluginData;)I
       8: ireturn

  jadx.api.plugins.JadxPluginManager$PluginData(jadx.api.plugins.JadxPlugin, jadx.api.plugins.JadxPluginInfo, jadx.api.plugins.JadxPluginManager$1);
    Code:
       0: aload_0
       1: aload_1
       2: aload_2
       3: invokespecial #1                  // Method "<init>":(Ljadx/api/plugins/JadxPlugin;Ljadx/api/plugins/JadxPluginInfo;)V
       6: return
}
