Compiled from "JadxPluginInfo.java"
public class jadx.api.plugins.JadxPluginInfo {
  private final java.lang.String pluginId;

  private final java.lang.String name;

  private final java.lang.String description;

  private final java.lang.String provides;

  public jadx.api.plugins.JadxPluginInfo(java.lang.String, java.lang.String, java.lang.String);
    Code:
       0: aload_0
       1: aload_1
       2: aload_2
       3: aload_3
       4: aload_1
       5: invokespecial #1                  // Method "<init>":(Ljava/lang/String;Ljava/lang/String;Ljava/lang/String;Ljava/lang/String;)V
       8: return

  public jadx.api.plugins.JadxPluginInfo(java.lang.String, java.lang.String, java.lang.String, java.lang.String);
    Code:
       0: aload_0
       1: invokespecial #2                  // Method java/lang/Object."<init>":()V
       4: aload_0
       5: aload_1
       6: putfield      #3                  // Field pluginId:Ljava/lang/String;
       9: aload_0
      10: aload_2
      11: putfield      #4                  // Field name:Ljava/lang/String;
      14: aload_0
      15: aload_3
      16: putfield      #5                  // Field description:Ljava/lang/String;
      19: aload_0
      20: aload         4
      22: putfield      #6                  // Field provides:Ljava/lang/String;
      25: return

  public java.lang.String getPluginId();
    Code:
       0: aload_0
       1: getfield      #3                  // Field pluginId:Ljava/lang/String;
       4: areturn

  public java.lang.String getName();
    Code:
       0: aload_0
       1: getfield      #4                  // Field name:Ljava/lang/String;
       4: areturn

  public java.lang.String getDescription();
    Code:
       0: aload_0
       1: getfield      #5                  // Field description:Ljava/lang/String;
       4: areturn

  public java.lang.String getProvides();
    Code:
       0: aload_0
       1: getfield      #6                  // Field provides:Ljava/lang/String;
       4: areturn

  public java.lang.String toString();
    Code:
       0: new           #7                  // class java/lang/StringBuilder
       3: dup
       4: invokespecial #8                  // Method java/lang/StringBuilder."<init>":()V
       7: aload_0
       8: getfield      #3                  // Field pluginId:Ljava/lang/String;
      11: invokevirtual #9                  // Method java/lang/StringBuilder.append:(Ljava/lang/String;)Ljava/lang/StringBuilder;
      14: ldc           #10                 // String :
      16: invokevirtual #9                  // Method java/lang/StringBuilder.append:(Ljava/lang/String;)Ljava/lang/StringBuilder;
      19: aload_0
      20: getfield      #4                  // Field name:Ljava/lang/String;
      23: invokevirtual #9                  // Method java/lang/StringBuilder.append:(Ljava/lang/String;)Ljava/lang/StringBuilder;
      26: ldc           #11                 // String  - \'
      28: invokevirtual #9                  // Method java/lang/StringBuilder.append:(Ljava/lang/String;)Ljava/lang/StringBuilder;
      31: aload_0
      32: getfield      #5                  // Field description:Ljava/lang/String;
      35: invokevirtual #9                  // Method java/lang/StringBuilder.append:(Ljava/lang/String;)Ljava/lang/StringBuilder;
      38: bipush        39
      40: invokevirtual #12                 // Method java/lang/StringBuilder.append:(C)Ljava/lang/StringBuilder;
      43: invokevirtual #13                 // Method java/lang/StringBuilder.toString:()Ljava/lang/String;
      46: areturn
}
