Compiled from "NettyHttpHandler.java"
public class org.apache.dubbo.rpc.protocol.rest.handler.NettyHttpHandler implements org.apache.dubbo.remoting.http.HttpHandler<org.apache.dubbo.rpc.protocol.rest.request.NettyRequestFacade, org.apache.dubbo.rpc.protocol.rest.netty.NettyHttpResponse> {
  private final org.apache.dubbo.common.logger.ErrorTypeAwareLogger logger;

  private final org.apache.dubbo.rpc.protocol.rest.PathAndInvokerMapper pathAndInvokerMapper;

  private final org.apache.dubbo.rpc.protocol.rest.exception.mapper.ExceptionMapper exceptionMapper;

  public org.apache.dubbo.rpc.protocol.rest.handler.NettyHttpHandler(org.apache.dubbo.rpc.protocol.rest.PathAndInvokerMapper, org.apache.dubbo.rpc.protocol.rest.exception.mapper.ExceptionMapper);
    Code:
       0: aload_0
       1: invokespecial #1                  // Method java/lang/Object."<init>":()V
       4: aload_0
       5: aload_0
       6: invokevirtual #2                  // Method java/lang/Object.getClass:()Ljava/lang/Class;
       9: invokestatic  #3                  // Method org/apache/dubbo/common/logger/LoggerFactory.getErrorTypeAwareLogger:(Ljava/lang/Class;)Lorg/apache/dubbo/common/logger/ErrorTypeAwareLogger;
      12: putfield      #4                  // Field logger:Lorg/apache/dubbo/common/logger/ErrorTypeAwareLogger;
      15: aload_0
      16: aload_1
      17: putfield      #5                  // Field pathAndInvokerMapper:Lorg/apache/dubbo/rpc/protocol/rest/PathAndInvokerMapper;
      20: aload_0
      21: aload_2
      22: putfield      #6                  // Field exceptionMapper:Lorg/apache/dubbo/rpc/protocol/rest/exception/mapper/ExceptionMapper;
      25: return

  public void handle(org.apache.dubbo.rpc.protocol.rest.request.NettyRequestFacade, org.apache.dubbo.rpc.protocol.rest.netty.NettyHttpResponse) throws java.io.IOException;
    Code:
       0: invokestatic  #7                  // Method org/apache/dubbo/rpc/RpcContext.getServiceContext:()Lorg/apache/dubbo/rpc/RpcServiceContext;
       3: aload_1
       4: invokevirtual #8                  // Method org/apache/dubbo/rpc/protocol/rest/request/NettyRequestFacade.getRemoteAddr:()Ljava/lang/String;
       7: aload_1
       8: invokevirtual #9                  // Method org/apache/dubbo/rpc/protocol/rest/request/NettyRequestFacade.getRemotePort:()I
      11: invokevirtual #10                 // Method org/apache/dubbo/rpc/RpcServiceContext.setRemoteAddress:(Ljava/lang/String;I)Lorg/apache/dubbo/rpc/RpcServiceContext;
      14: pop
      15: invokestatic  #7                  // Method org/apache/dubbo/rpc/RpcContext.getServiceContext:()Lorg/apache/dubbo/rpc/RpcServiceContext;
      18: aload_1
      19: invokevirtual #11                 // Method org/apache/dubbo/rpc/protocol/rest/request/NettyRequestFacade.getLocalAddr:()Ljava/lang/String;
      22: aload_1
      23: invokevirtual #12                 // Method org/apache/dubbo/rpc/protocol/rest/request/NettyRequestFacade.getLocalPort:()I
      26: invokevirtual #13                 // Method org/apache/dubbo/rpc/RpcServiceContext.setLocalAddress:(Ljava/lang/String;I)Lorg/apache/dubbo/rpc/RpcServiceContext;
      29: pop
      30: invokestatic  #7                  // Method org/apache/dubbo/rpc/RpcContext.getServiceContext:()Lorg/apache/dubbo/rpc/RpcServiceContext;
      33: aload_1
      34: invokevirtual #14                 // Method org/apache/dubbo/rpc/RpcServiceContext.setRequest:(Ljava/lang/Object;)V
      37: invokestatic  #7                  // Method org/apache/dubbo/rpc/RpcContext.getServiceContext:()Lorg/apache/dubbo/rpc/RpcServiceContext;
      40: aload_2
      41: invokevirtual #15                 // Method org/apache/dubbo/rpc/RpcServiceContext.setResponse:(Ljava/lang/Object;)V
      44: aload_1
      45: invokevirtual #16                 // Method org/apache/dubbo/rpc/protocol/rest/request/NettyRequestFacade.getRequest:()Ljava/lang/Object;
      48: checkcast     #17                 // class io/netty/handler/codec/http/FullHttpRequest
      51: astore_3
      52: aload_0
      53: aload_3
      54: aload_2
      55: aload_1
      56: invokespecial #18                 // Method doHandler:(Lio/netty/handler/codec/http/FullHttpRequest;Lorg/apache/dubbo/rpc/protocol/rest/netty/NettyHttpResponse;Lorg/apache/dubbo/rpc/protocol/rest/request/RequestFacade;)V
      59: goto          314
      62: astore        4
      64: aload_0
      65: getfield      #4                  // Field logger:Lorg/apache/dubbo/common/logger/ErrorTypeAwareLogger;
      68: ldc           #20                 // String
      70: aload         4
      72: invokevirtual #21                 // Method org/apache/dubbo/rpc/protocol/rest/exception/PathNoFoundException.getMessage:()Ljava/lang/String;
      75: ldc           #20                 // String
      77: new           #22                 // class java/lang/StringBuilder
      80: dup
      81: invokespecial #23                 // Method java/lang/StringBuilder."<init>":()V
      84: ldc           #24                 // String dubbo rest protocol provider path   no found ,raw request is :
      86: invokevirtual #25                 // Method java/lang/StringBuilder.append:(Ljava/lang/String;)Ljava/lang/StringBuilder;
      89: aload_3
      90: invokevirtual #26                 // Method java/lang/StringBuilder.append:(Ljava/lang/Object;)Ljava/lang/StringBuilder;
      93: invokevirtual #27                 // Method java/lang/StringBuilder.toString:()Ljava/lang/String;
      96: aload         4
      98: invokeinterface #28,  6           // InterfaceMethod org/apache/dubbo/common/logger/ErrorTypeAwareLogger.error:(Ljava/lang/String;Ljava/lang/String;Ljava/lang/String;Ljava/lang/String;Ljava/lang/Throwable;)V
     103: aload_2
     104: sipush        404
     107: aload         4
     109: invokevirtual #21                 // Method org/apache/dubbo/rpc/protocol/rest/exception/PathNoFoundException.getMessage:()Ljava/lang/String;
     112: invokevirtual #29                 // Method org/apache/dubbo/rpc/protocol/rest/netty/NettyHttpResponse.sendError:(ILjava/lang/String;)V
     115: goto          314
     118: astore        4
     120: aload_0
     121: getfield      #4                  // Field logger:Lorg/apache/dubbo/common/logger/ErrorTypeAwareLogger;
     124: ldc           #20                 // String
     126: aload         4
     128: invokevirtual #31                 // Method org/apache/dubbo/rpc/protocol/rest/exception/ParamParseException.getMessage:()Ljava/lang/String;
     131: ldc           #20                 // String
     133: new           #22                 // class java/lang/StringBuilder
     136: dup
     137: invokespecial #23                 // Method java/lang/StringBuilder."<init>":()V
     140: ldc           #32                 // String dubbo rest protocol provider param parse error ,and raw request is :
     142: invokevirtual #25                 // Method java/lang/StringBuilder.append:(Ljava/lang/String;)Ljava/lang/StringBuilder;
     145: aload_3
     146: invokevirtual #26                 // Method java/lang/StringBuilder.append:(Ljava/lang/Object;)Ljava/lang/StringBuilder;
     149: invokevirtual #27                 // Method java/lang/StringBuilder.toString:()Ljava/lang/String;
     152: aload         4
     154: invokeinterface #28,  6           // InterfaceMethod org/apache/dubbo/common/logger/ErrorTypeAwareLogger.error:(Ljava/lang/String;Ljava/lang/String;Ljava/lang/String;Ljava/lang/String;Ljava/lang/Throwable;)V
     159: aload_2
     160: sipush        400
     163: aload         4
     165: invokevirtual #31                 // Method org/apache/dubbo/rpc/protocol/rest/exception/ParamParseException.getMessage:()Ljava/lang/String;
     168: invokevirtual #29                 // Method org/apache/dubbo/rpc/protocol/rest/netty/NettyHttpResponse.sendError:(ILjava/lang/String;)V
     171: goto          314
     174: astore        4
     176: aload_0
     177: getfield      #4                  // Field logger:Lorg/apache/dubbo/common/logger/ErrorTypeAwareLogger;
     180: ldc           #20                 // String
     182: aload         4
     184: invokevirtual #34                 // Method org/apache/dubbo/rpc/protocol/rest/exception/MediaTypeUnSupportException.getMessage:()Ljava/lang/String;
     187: ldc           #20                 // String
     189: new           #22                 // class java/lang/StringBuilder
     192: dup
     193: invokespecial #23                 // Method java/lang/StringBuilder."<init>":()V
     196: ldc           #35                 // String dubbo rest protocol provider content-type un support
     198: invokevirtual #25                 // Method java/lang/StringBuilder.append:(Ljava/lang/String;)Ljava/lang/StringBuilder;
     201: aload_3
     202: invokevirtual #26                 // Method java/lang/StringBuilder.append:(Ljava/lang/Object;)Ljava/lang/StringBuilder;
     205: invokevirtual #27                 // Method java/lang/StringBuilder.toString:()Ljava/lang/String;
     208: aload         4
     210: invokeinterface #28,  6           // InterfaceMethod org/apache/dubbo/common/logger/ErrorTypeAwareLogger.error:(Ljava/lang/String;Ljava/lang/String;Ljava/lang/String;Ljava/lang/String;Ljava/lang/Throwable;)V
     215: aload_2
     216: sipush        415
     219: aload         4
     221: invokevirtual #34                 // Method org/apache/dubbo/rpc/protocol/rest/exception/MediaTypeUnSupportException.getMessage:()Ljava/lang/String;
     224: invokevirtual #29                 // Method org/apache/dubbo/rpc/protocol/rest/netty/NettyHttpResponse.sendError:(ILjava/lang/String;)V
     227: goto          314
     230: astore        4
     232: aload_0
     233: getfield      #4                  // Field logger:Lorg/apache/dubbo/common/logger/ErrorTypeAwareLogger;
     236: ldc           #20                 // String
     238: aload         4
     240: invokevirtual #37                 // Method java/lang/Throwable.getMessage:()Ljava/lang/String;
     243: ldc           #20                 // String
     245: new           #22                 // class java/lang/StringBuilder
     248: dup
     249: invokespecial #23                 // Method java/lang/StringBuilder."<init>":()V
     252: ldc           #38                 // String dubbo rest protocol provider error ,and raw request is
     254: invokevirtual #25                 // Method java/lang/StringBuilder.append:(Ljava/lang/String;)Ljava/lang/StringBuilder;
     257: aload_3
     258: invokevirtual #26                 // Method java/lang/StringBuilder.append:(Ljava/lang/Object;)Ljava/lang/StringBuilder;
     261: invokevirtual #27                 // Method java/lang/StringBuilder.toString:()Ljava/lang/String;
     264: aload         4
     266: invokeinterface #28,  6           // InterfaceMethod org/apache/dubbo/common/logger/ErrorTypeAwareLogger.error:(Ljava/lang/String;Ljava/lang/String;Ljava/lang/String;Ljava/lang/String;Ljava/lang/Throwable;)V
     271: aload_2
     272: sipush        500
     275: new           #22                 // class java/lang/StringBuilder
     278: dup
     279: invokespecial #23                 // Method java/lang/StringBuilder."<init>":()V
     282: ldc           #39                 // String dubbo rest invoke Internal error, message is
     284: invokevirtual #25                 // Method java/lang/StringBuilder.append:(Ljava/lang/String;)Ljava/lang/StringBuilder;
     287: aload         4
     289: invokevirtual #37                 // Method java/lang/Throwable.getMessage:()Ljava/lang/String;
     292: invokevirtual #25                 // Method java/lang/StringBuilder.append:(Ljava/lang/String;)Ljava/lang/StringBuilder;
     295: ldc           #40                 // String  , stacktrace is:
     297: invokevirtual #25                 // Method java/lang/StringBuilder.append:(Ljava/lang/String;)Ljava/lang/StringBuilder;
     300: aload         4
     302: invokestatic  #41                 // Method stackTraceToString:(Ljava/lang/Throwable;)Ljava/lang/String;
     305: invokevirtual #25                 // Method java/lang/StringBuilder.append:(Ljava/lang/String;)Ljava/lang/StringBuilder;
     308: invokevirtual #27                 // Method java/lang/StringBuilder.toString:()Ljava/lang/String;
     311: invokevirtual #29                 // Method org/apache/dubbo/rpc/protocol/rest/netty/NettyHttpResponse.sendError:(ILjava/lang/String;)V
     314: return
    Exception table:
       from    to  target type
          52    59    62   Class org/apache/dubbo/rpc/protocol/rest/exception/PathNoFoundException
          52    59   118   Class org/apache/dubbo/rpc/protocol/rest/exception/ParamParseException
          52    59   174   Class org/apache/dubbo/rpc/protocol/rest/exception/MediaTypeUnSupportException
          52    59   230   Class java/lang/Throwable

  private void doHandler(io.netty.handler.codec.http.FullHttpRequest, org.apache.dubbo.rpc.protocol.rest.netty.NettyHttpResponse, org.apache.dubbo.rpc.protocol.rest.request.RequestFacade) throws java.lang.Exception;
    Code:
       0: aload_3
       1: aload_0
       2: getfield      #5                  // Field pathAndInvokerMapper:Lorg/apache/dubbo/rpc/protocol/rest/PathAndInvokerMapper;
       5: invokestatic  #42                 // Method org/apache/dubbo/rpc/protocol/rest/RestRPCInvocationUtil.getRestMethodMetadata:(Lorg/apache/dubbo/rpc/protocol/rest/request/RequestFacade;Lorg/apache/dubbo/rpc/protocol/rest/PathAndInvokerMapper;)Lorg/apache/dubbo/rpc/protocol/rest/pair/InvokerAndRestMethodMetadataPair;
       8: astore        4
      10: aload         4
      12: invokevirtual #43                 // Method org/apache/dubbo/rpc/protocol/rest/pair/InvokerAndRestMethodMetadataPair.getInvoker:()Lorg/apache/dubbo/rpc/Invoker;
      15: astore        5
      17: aload         4
      19: invokevirtual #44                 // Method org/apache/dubbo/rpc/protocol/rest/pair/InvokerAndRestMethodMetadataPair.getRestMethodMetadata:()Lorg/apache/dubbo/metadata/rest/RestMethodMetadata;
      22: astore        6
      24: aload         6
      26: invokevirtual #45                 // Method org/apache/dubbo/metadata/rest/RestMethodMetadata.getRequest:()Lorg/apache/dubbo/metadata/rest/RequestMetadata;
      29: aload_3
      30: invokevirtual #46                 // Method org/apache/dubbo/rpc/protocol/rest/request/RequestFacade.getMethod:()Ljava/lang/String;
      33: invokevirtual #47                 // Method org/apache/dubbo/metadata/rest/RequestMetadata.methodAllowed:(Ljava/lang/String;)Z
      36: ifne          85
      39: aload_2
      40: sipush        405
      43: new           #22                 // class java/lang/StringBuilder
      46: dup
      47: invokespecial #23                 // Method java/lang/StringBuilder."<init>":()V
      50: ldc           #48                 // String service require request method is :
      52: invokevirtual #25                 // Method java/lang/StringBuilder.append:(Ljava/lang/String;)Ljava/lang/StringBuilder;
      55: aload         6
      57: invokevirtual #45                 // Method org/apache/dubbo/metadata/rest/RestMethodMetadata.getRequest:()Lorg/apache/dubbo/metadata/rest/RequestMetadata;
      60: invokevirtual #49                 // Method org/apache/dubbo/metadata/rest/RequestMetadata.getMethod:()Ljava/lang/String;
      63: invokevirtual #25                 // Method java/lang/StringBuilder.append:(Ljava/lang/String;)Ljava/lang/StringBuilder;
      66: ldc           #50                 // String , but current request method is:
      68: invokevirtual #25                 // Method java/lang/StringBuilder.append:(Ljava/lang/String;)Ljava/lang/StringBuilder;
      71: aload_3
      72: invokevirtual #46                 // Method org/apache/dubbo/rpc/protocol/rest/request/RequestFacade.getMethod:()Ljava/lang/String;
      75: invokevirtual #25                 // Method java/lang/StringBuilder.append:(Ljava/lang/String;)Ljava/lang/StringBuilder;
      78: invokevirtual #27                 // Method java/lang/StringBuilder.toString:()Ljava/lang/String;
      81: invokevirtual #29                 // Method org/apache/dubbo/rpc/protocol/rest/netty/NettyHttpResponse.sendError:(ILjava/lang/String;)V
      84: return
      85: aload_0
      86: aload_3
      87: aload         6
      89: invokevirtual #51                 // Method org/apache/dubbo/metadata/rest/RestMethodMetadata.getReflectMethod:()Ljava/lang/reflect/Method;
      92: invokevirtual #52                 // Method java/lang/reflect/Method.getReturnType:()Ljava/lang/Class;
      95: invokespecial #53                 // Method acceptSupportJudge:(Lorg/apache/dubbo/rpc/protocol/rest/request/RequestFacade;Ljava/lang/Class;)V
      98: aload_3
      99: aload         6
     101: invokestatic  #54                 // Method org/apache/dubbo/rpc/protocol/rest/RestRPCInvocationUtil.createBaseRpcInvocation:(Lorg/apache/dubbo/rpc/protocol/rest/request/RequestFacade;Lorg/apache/dubbo/metadata/rest/RestMethodMetadata;)Lorg/apache/dubbo/rpc/RpcInvocation;
     104: astore        7
     106: aload         7
     108: aload_3
     109: aload_1
     110: aload_2
     111: aload         6
     113: invokestatic  #55                 // Method org/apache/dubbo/rpc/protocol/rest/RestRPCInvocationUtil.parseMethodArgs:(Lorg/apache/dubbo/rpc/RpcInvocation;Lorg/apache/dubbo/rpc/protocol/rest/request/RequestFacade;Ljava/lang/Object;Ljava/lang/Object;Lorg/apache/dubbo/metadata/rest/RestMethodMetadata;)V
     116: aload         5
     118: aload         7
     120: invokeinterface #56,  2           // InterfaceMethod org/apache/dubbo/rpc/Invoker.invoke:(Lorg/apache/dubbo/rpc/Invocation;)Lorg/apache/dubbo/rpc/Result;
     125: astore        8
     127: aload         8
     129: invokeinterface #57,  1           // InterfaceMethod org/apache/dubbo/rpc/Result.hasException:()Z
     134: ifeq          286
     137: aload         8
     139: invokeinterface #58,  1           // InterfaceMethod org/apache/dubbo/rpc/Result.getException:()Ljava/lang/Throwable;
     144: astore        9
     146: aload_0
     147: getfield      #4                  // Field logger:Lorg/apache/dubbo/common/logger/ErrorTypeAwareLogger;
     150: ldc           #20                 // String
     152: aload         9
     154: invokevirtual #37                 // Method java/lang/Throwable.getMessage:()Ljava/lang/String;
     157: ldc           #20                 // String
     159: ldc           #59                 // String dubbo rest protocol provider Invoker invoke error
     161: aload         9
     163: invokeinterface #28,  6           // InterfaceMethod org/apache/dubbo/common/logger/ErrorTypeAwareLogger.error:(Ljava/lang/String;Ljava/lang/String;Ljava/lang/String;Ljava/lang/String;Ljava/lang/Throwable;)V
     168: aload_0
     169: getfield      #6                  // Field exceptionMapper:Lorg/apache/dubbo/rpc/protocol/rest/exception/mapper/ExceptionMapper;
     172: aload         9
     174: invokevirtual #60                 // Method org/apache/dubbo/rpc/protocol/rest/exception/mapper/ExceptionMapper.hasExceptionMapper:(Ljava/lang/Object;)Z
     177: ifeq          217
     180: aload_0
     181: aload_2
     182: aload_3
     183: aload         5
     185: aload_0
     186: getfield      #6                  // Field exceptionMapper:Lorg/apache/dubbo/rpc/protocol/rest/exception/mapper/ExceptionMapper;
     189: aload         8
     191: invokeinterface #58,  1           // InterfaceMethod org/apache/dubbo/rpc/Result.getException:()Ljava/lang/Throwable;
     196: invokevirtual #61                 // Method org/apache/dubbo/rpc/protocol/rest/exception/mapper/ExceptionMapper.exceptionToResult:(Ljava/lang/Object;)Ljava/lang/Object;
     199: aload         7
     201: invokevirtual #62                 // Method org/apache/dubbo/rpc/RpcInvocation.getReturnType:()Ljava/lang/Class;
     204: invokespecial #63                 // Method writeResult:(Lorg/apache/dubbo/rpc/protocol/rest/netty/NettyHttpResponse;Lorg/apache/dubbo/rpc/protocol/rest/request/RequestFacade;Lorg/apache/dubbo/rpc/Invoker;Ljava/lang/Object;Ljava/lang/Class;)V
     207: aload_2
     208: sipush        200
     211: invokevirtual #64                 // Method org/apache/dubbo/rpc/protocol/rest/netty/NettyHttpResponse.setStatus:(I)V
     214: goto          283
     217: aload_2
     218: sipush        500
     221: new           #22                 // class java/lang/StringBuilder
     224: dup
     225: invokespecial #23                 // Method java/lang/StringBuilder."<init>":()V
     228: ldc           #65                 // String \n dubbo rest business exception, error cause is:
     230: invokevirtual #25                 // Method java/lang/StringBuilder.append:(Ljava/lang/String;)Ljava/lang/StringBuilder;
     233: aload         8
     235: invokeinterface #58,  1           // InterfaceMethod org/apache/dubbo/rpc/Result.getException:()Ljava/lang/Throwable;
     240: invokevirtual #66                 // Method java/lang/Throwable.getCause:()Ljava/lang/Throwable;
     243: invokevirtual #26                 // Method java/lang/StringBuilder.append:(Ljava/lang/Object;)Ljava/lang/StringBuilder;
     246: ldc           #67                 // String \n message is:
     248: invokevirtual #25                 // Method java/lang/StringBuilder.append:(Ljava/lang/String;)Ljava/lang/StringBuilder;
     251: aload         8
     253: invokeinterface #58,  1           // InterfaceMethod org/apache/dubbo/rpc/Result.getException:()Ljava/lang/Throwable;
     258: invokevirtual #37                 // Method java/lang/Throwable.getMessage:()Ljava/lang/String;
     261: invokevirtual #25                 // Method java/lang/StringBuilder.append:(Ljava/lang/String;)Ljava/lang/StringBuilder;
     264: ldc           #68                 // String \n stacktrace is:
     266: invokevirtual #25                 // Method java/lang/StringBuilder.append:(Ljava/lang/String;)Ljava/lang/StringBuilder;
     269: aload         9
     271: invokestatic  #41                 // Method stackTraceToString:(Ljava/lang/Throwable;)Ljava/lang/String;
     274: invokevirtual #25                 // Method java/lang/StringBuilder.append:(Ljava/lang/String;)Ljava/lang/StringBuilder;
     277: invokevirtual #27                 // Method java/lang/StringBuilder.toString:()Ljava/lang/String;
     280: invokevirtual #29                 // Method org/apache/dubbo/rpc/protocol/rest/netty/NettyHttpResponse.sendError:(ILjava/lang/String;)V
     283: goto          317
     286: aload         8
     288: invokeinterface #69,  1           // InterfaceMethod org/apache/dubbo/rpc/Result.getValue:()Ljava/lang/Object;
     293: astore        9
     295: aload_0
     296: aload_2
     297: aload_3
     298: aload         5
     300: aload         9
     302: aload         7
     304: invokevirtual #62                 // Method org/apache/dubbo/rpc/RpcInvocation.getReturnType:()Ljava/lang/Class;
     307: invokespecial #63                 // Method writeResult:(Lorg/apache/dubbo/rpc/protocol/rest/netty/NettyHttpResponse;Lorg/apache/dubbo/rpc/protocol/rest/request/RequestFacade;Lorg/apache/dubbo/rpc/Invoker;Ljava/lang/Object;Ljava/lang/Class;)V
     310: aload_2
     311: sipush        200
     314: invokevirtual #64                 // Method org/apache/dubbo/rpc/protocol/rest/netty/NettyHttpResponse.setStatus:(I)V
     317: return

  private void writeResult(org.apache.dubbo.rpc.protocol.rest.netty.NettyHttpResponse, org.apache.dubbo.rpc.protocol.rest.request.RequestFacade, org.apache.dubbo.rpc.Invoker, java.lang.Object, java.lang.Class) throws java.lang.Exception;
    Code:
       0: aload_0
       1: aload_2
       2: aload         5
       4: invokespecial #70                 // Method getAcceptMediaType:(Lorg/apache/dubbo/rpc/protocol/rest/request/RequestFacade;Ljava/lang/Class;)Lorg/apache/dubbo/metadata/rest/media/MediaType;
       7: astore        6
       9: aload_1
      10: invokevirtual #71                 // Method org/apache/dubbo/rpc/protocol/rest/netty/NettyHttpResponse.getOutputStream:()Ljava/io/OutputStream;
      13: aload         4
      15: aload_3
      16: invokeinterface #72,  1           // InterfaceMethod org/apache/dubbo/rpc/Invoker.getUrl:()Lorg/apache/dubbo/common/URL;
      21: aload         6
      23: aload         5
      25: invokestatic  #73                 // Method org/apache/dubbo/rpc/protocol/rest/message/HttpMessageCodecManager.httpMessageEncode:(Ljava/io/OutputStream;Ljava/lang/Object;Lorg/apache/dubbo/common/URL;Lorg/apache/dubbo/metadata/rest/media/MediaType;Ljava/lang/Class;)Lorg/apache/dubbo/rpc/protocol/rest/pair/MessageCodecResultPair;
      28: astore        7
      30: aload_1
      31: getstatic     #74                 // Field org/apache/dubbo/rpc/protocol/rest/RestHeaderEnum.CONTENT_TYPE:Lorg/apache/dubbo/rpc/protocol/rest/RestHeaderEnum;
      34: invokevirtual #75                 // Method org/apache/dubbo/rpc/protocol/rest/RestHeaderEnum.getHeader:()Ljava/lang/String;
      37: aload         7
      39: invokevirtual #76                 // Method org/apache/dubbo/rpc/protocol/rest/pair/MessageCodecResultPair.getMediaType:()Lorg/apache/dubbo/metadata/rest/media/MediaType;
      42: getfield      #77                 // Field org/apache/dubbo/metadata/rest/media/MediaType.value:Ljava/lang/String;
      45: invokevirtual #78                 // Method org/apache/dubbo/rpc/protocol/rest/netty/NettyHttpResponse.addOutputHeaders:(Ljava/lang/String;Ljava/lang/String;)V
      48: return

  private org.apache.dubbo.metadata.rest.media.MediaType getAcceptMediaType(org.apache.dubbo.rpc.protocol.rest.request.RequestFacade, java.lang.Class<?>);
    Code:
       0: aload_1
       1: getstatic     #79                 // Field org/apache/dubbo/rpc/protocol/rest/RestHeaderEnum.ACCEPT:Lorg/apache/dubbo/rpc/protocol/rest/RestHeaderEnum;
       4: invokevirtual #75                 // Method org/apache/dubbo/rpc/protocol/rest/RestHeaderEnum.getHeader:()Ljava/lang/String;
       7: invokevirtual #80                 // Method org/apache/dubbo/rpc/protocol/rest/request/RequestFacade.getHeader:(Ljava/lang/String;)Ljava/lang/String;
      10: astore_3
      11: aload_2
      12: iconst_1
      13: anewarray     #81                 // class java/lang/String
      16: dup
      17: iconst_0
      18: aload_3
      19: aastore
      20: invokestatic  #82                 // Method org/apache/dubbo/rpc/protocol/rest/util/MediaTypeUtil.convertMediaType:(Ljava/lang/Class;[Ljava/lang/String;)Lorg/apache/dubbo/metadata/rest/media/MediaType;
      23: astore        4
      25: aload         4
      27: areturn

  private void acceptSupportJudge(org.apache.dubbo.rpc.protocol.rest.request.RequestFacade, java.lang.Class<?>);
    Code:
       0: aload_0
       1: aload_1
       2: aload_2
       3: invokespecial #70                 // Method getAcceptMediaType:(Lorg/apache/dubbo/rpc/protocol/rest/request/RequestFacade;Ljava/lang/Class;)Lorg/apache/dubbo/metadata/rest/media/MediaType;
       6: pop
       7: goto          56
      10: astore_3
      11: aload_2
      12: invokestatic  #84                 // Method org/apache/dubbo/rpc/protocol/rest/message/HttpMessageCodecManager.typeSupport:(Ljava/lang/Class;)Lorg/apache/dubbo/metadata/rest/media/MediaType;
      15: astore        4
      17: aload_1
      18: getstatic     #79                 // Field org/apache/dubbo/rpc/protocol/rest/RestHeaderEnum.ACCEPT:Lorg/apache/dubbo/rpc/protocol/rest/RestHeaderEnum;
      21: invokevirtual #75                 // Method org/apache/dubbo/rpc/protocol/rest/RestHeaderEnum.getHeader:()Ljava/lang/String;
      24: invokevirtual #80                 // Method org/apache/dubbo/rpc/protocol/rest/request/RequestFacade.getHeader:(Ljava/lang/String;)Ljava/lang/String;
      27: astore        5
      29: aload         4
      31: ifnull        39
      34: aload         5
      36: ifnonnull     41
      39: aload_3
      40: athrow
      41: aload         5
      43: aload         4
      45: getfield      #77                 // Field org/apache/dubbo/metadata/rest/media/MediaType.value:Ljava/lang/String;
      48: invokevirtual #85                 // Method java/lang/String.contains:(Ljava/lang/CharSequence;)Z
      51: ifne          56
      54: aload_3
      55: athrow
      56: return
    Exception table:
       from    to  target type
           0     7    10   Class org/apache/dubbo/rpc/protocol/rest/exception/UnSupportContentTypeException

  public static java.lang.String stackTraceToString(java.lang.Throwable);
    Code:
       0: aload_0
       1: invokevirtual #86                 // Method java/lang/Throwable.getStackTrace:()[Ljava/lang/StackTraceElement;
       4: astore_1
       5: new           #22                 // class java/lang/StringBuilder
       8: dup
       9: ldc           #87                 // String \n
      11: invokespecial #88                 // Method java/lang/StringBuilder."<init>":(Ljava/lang/String;)V
      14: astore_2
      15: aload_1
      16: astore_3
      17: aload_3
      18: arraylength
      19: istore        4
      21: iconst_0
      22: istore        5
      24: iload         5
      26: iload         4
      28: if_icmpge     73
      31: aload_3
      32: iload         5
      34: aaload
      35: astore        6
      37: aload_2
      38: new           #22                 // class java/lang/StringBuilder
      41: dup
      42: invokespecial #23                 // Method java/lang/StringBuilder."<init>":()V
      45: ldc           #89                 // String \tat
      47: invokevirtual #25                 // Method java/lang/StringBuilder.append:(Ljava/lang/String;)Ljava/lang/StringBuilder;
      50: aload         6
      52: invokevirtual #26                 // Method java/lang/StringBuilder.append:(Ljava/lang/Object;)Ljava/lang/StringBuilder;
      55: invokevirtual #27                 // Method java/lang/StringBuilder.toString:()Ljava/lang/String;
      58: invokevirtual #25                 // Method java/lang/StringBuilder.append:(Ljava/lang/String;)Ljava/lang/StringBuilder;
      61: ldc           #87                 // String \n
      63: invokevirtual #25                 // Method java/lang/StringBuilder.append:(Ljava/lang/String;)Ljava/lang/StringBuilder;
      66: pop
      67: iinc          5, 1
      70: goto          24
      73: aload_2
      74: invokevirtual #27                 // Method java/lang/StringBuilder.toString:()Ljava/lang/String;
      77: areturn

  public void handle(java.lang.Object, java.lang.Object) throws java.io.IOException;
    Code:
       0: aload_0
       1: aload_1
       2: checkcast     #90                 // class org/apache/dubbo/rpc/protocol/rest/request/NettyRequestFacade
       5: aload_2
       6: checkcast     #91                 // class org/apache/dubbo/rpc/protocol/rest/netty/NettyHttpResponse
       9: invokevirtual #92                 // Method handle:(Lorg/apache/dubbo/rpc/protocol/rest/request/NettyRequestFacade;Lorg/apache/dubbo/rpc/protocol/rest/netty/NettyHttpResponse;)V
      12: return
}
