Compiled from "StatusUtils.java"
public class org.apache.dubbo.common.status.support.StatusUtils {
  public org.apache.dubbo.common.status.support.StatusUtils();
    Code:
       0: aload_0
       1: invokespecial #1                  // Method java/lang/Object."<init>":()V
       4: return

  public static org.apache.dubbo.common.status.Status getSummaryStatus(java.util.Map<java.lang.String, org.apache.dubbo.common.status.Status>);
    Code:
       0: getstatic     #2                  // Field org/apache/dubbo/common/status/Status$Level.OK:Lorg/apache/dubbo/common/status/Status$Level;
       3: astore_1
       4: new           #3                  // class java/lang/StringBuilder
       7: dup
       8: invokespecial #4                  // Method java/lang/StringBuilder."<init>":()V
      11: astore_2
      12: aload_0
      13: invokeinterface #5,  1            // InterfaceMethod java/util/Map.entrySet:()Ljava/util/Set;
      18: invokeinterface #6,  1            // InterfaceMethod java/util/Set.iterator:()Ljava/util/Iterator;
      23: astore_3
      24: aload_3
      25: invokeinterface #7,  1            // InterfaceMethod java/util/Iterator.hasNext:()Z
      30: ifeq          163
      33: aload_3
      34: invokeinterface #8,  1            // InterfaceMethod java/util/Iterator.next:()Ljava/lang/Object;
      39: checkcast     #9                  // class java/util/Map$Entry
      42: astore        4
      44: aload         4
      46: invokeinterface #10,  1           // InterfaceMethod java/util/Map$Entry.getKey:()Ljava/lang/Object;
      51: checkcast     #11                 // class java/lang/String
      54: astore        5
      56: aload         4
      58: invokeinterface #12,  1           // InterfaceMethod java/util/Map$Entry.getValue:()Ljava/lang/Object;
      63: checkcast     #13                 // class org/apache/dubbo/common/status/Status
      66: astore        6
      68: aload         6
      70: invokevirtual #14                 // Method org/apache/dubbo/common/status/Status.getLevel:()Lorg/apache/dubbo/common/status/Status$Level;
      73: astore        7
      75: getstatic     #15                 // Field org/apache/dubbo/common/status/Status$Level.ERROR:Lorg/apache/dubbo/common/status/Status$Level;
      78: aload         7
      80: invokevirtual #16                 // Method org/apache/dubbo/common/status/Status$Level.equals:(Ljava/lang/Object;)Z
      83: ifeq          114
      86: getstatic     #15                 // Field org/apache/dubbo/common/status/Status$Level.ERROR:Lorg/apache/dubbo/common/status/Status$Level;
      89: astore_1
      90: aload_2
      91: invokevirtual #17                 // Method java/lang/StringBuilder.length:()I
      94: ifle          104
      97: aload_2
      98: bipush        44
     100: invokevirtual #18                 // Method java/lang/StringBuilder.append:(C)Ljava/lang/StringBuilder;
     103: pop
     104: aload_2
     105: aload         5
     107: invokevirtual #19                 // Method java/lang/StringBuilder.append:(Ljava/lang/String;)Ljava/lang/StringBuilder;
     110: pop
     111: goto          160
     114: getstatic     #20                 // Field org/apache/dubbo/common/status/Status$Level.WARN:Lorg/apache/dubbo/common/status/Status$Level;
     117: aload         7
     119: invokevirtual #16                 // Method org/apache/dubbo/common/status/Status$Level.equals:(Ljava/lang/Object;)Z
     122: ifeq          160
     125: getstatic     #15                 // Field org/apache/dubbo/common/status/Status$Level.ERROR:Lorg/apache/dubbo/common/status/Status$Level;
     128: aload_1
     129: invokevirtual #16                 // Method org/apache/dubbo/common/status/Status$Level.equals:(Ljava/lang/Object;)Z
     132: ifne          139
     135: getstatic     #20                 // Field org/apache/dubbo/common/status/Status$Level.WARN:Lorg/apache/dubbo/common/status/Status$Level;
     138: astore_1
     139: aload_2
     140: invokevirtual #17                 // Method java/lang/StringBuilder.length:()I
     143: ifle          153
     146: aload_2
     147: bipush        44
     149: invokevirtual #18                 // Method java/lang/StringBuilder.append:(C)Ljava/lang/StringBuilder;
     152: pop
     153: aload_2
     154: aload         5
     156: invokevirtual #19                 // Method java/lang/StringBuilder.append:(Ljava/lang/String;)Ljava/lang/StringBuilder;
     159: pop
     160: goto          24
     163: new           #13                 // class org/apache/dubbo/common/status/Status
     166: dup
     167: aload_1
     168: aload_2
     169: invokevirtual #21                 // Method java/lang/StringBuilder.toString:()Ljava/lang/String;
     172: invokespecial #22                 // Method org/apache/dubbo/common/status/Status."<init>":(Lorg/apache/dubbo/common/status/Status$Level;Ljava/lang/String;)V
     175: areturn
}
