Compiled from "HomePageHandler.java"
public class com.alibaba.dubbo.container.page.pages.HomePageHandler implements com.alibaba.dubbo.container.page.PageHandler {
  public com.alibaba.dubbo.container.page.pages.HomePageHandler();
    Code:
       0: aload_0
       1: invokespecial #1                  // Method java/lang/Object."<init>":()V
       4: return

  public com.alibaba.dubbo.container.page.Page handle(com.alibaba.dubbo.common.URL);
    Code:
       0: new           #2                  // class java/util/ArrayList
       3: dup
       4: invokespecial #3                  // Method java/util/ArrayList."<init>":()V
       7: astore_2
       8: invokestatic  #4                  // Method com/alibaba/dubbo/container/page/PageServlet.getInstance:()Lcom/alibaba/dubbo/container/page/PageServlet;
      11: invokevirtual #5                  // Method com/alibaba/dubbo/container/page/PageServlet.getMenus:()Ljava/util/List;
      14: invokeinterface #6,  1            // InterfaceMethod java/util/List.iterator:()Ljava/util/Iterator;
      19: astore_3
      20: aload_3
      21: invokeinterface #7,  1            // InterfaceMethod java/util/Iterator.hasNext:()Z
      26: ifeq          151
      29: aload_3
      30: invokeinterface #8,  1            // InterfaceMethod java/util/Iterator.next:()Ljava/lang/Object;
      35: checkcast     #9                  // class com/alibaba/dubbo/container/page/PageHandler
      38: astore        4
      40: ldc           #9                  // class com/alibaba/dubbo/container/page/PageHandler
      42: invokestatic  #10                 // Method org/apache/dubbo/common/extension/ExtensionLoader.getExtensionLoader:(Ljava/lang/Class;)Lorg/apache/dubbo/common/extension/ExtensionLoader;
      45: aload         4
      47: invokevirtual #11                 // Method org/apache/dubbo/common/extension/ExtensionLoader.getExtensionName:(Ljava/lang/Object;)Ljava/lang/String;
      50: astore        5
      52: aload         4
      54: invokevirtual #12                 // Method java/lang/Object.getClass:()Ljava/lang/Class;
      57: ldc           #13                 // class com/alibaba/dubbo/container/page/Menu
      59: invokevirtual #14                 // Method java/lang/Class.getAnnotation:(Ljava/lang/Class;)Ljava/lang/annotation/Annotation;
      62: checkcast     #13                 // class com/alibaba/dubbo/container/page/Menu
      65: astore        6
      67: new           #2                  // class java/util/ArrayList
      70: dup
      71: invokespecial #3                  // Method java/util/ArrayList."<init>":()V
      74: astore        7
      76: aload         7
      78: new           #15                 // class java/lang/StringBuilder
      81: dup
      82: invokespecial #16                 // Method java/lang/StringBuilder."<init>":()V
      85: ldc           #17                 // String <a href=\"
      87: invokevirtual #18                 // Method java/lang/StringBuilder.append:(Ljava/lang/String;)Ljava/lang/StringBuilder;
      90: aload         5
      92: invokevirtual #18                 // Method java/lang/StringBuilder.append:(Ljava/lang/String;)Ljava/lang/StringBuilder;
      95: ldc           #19                 // String .html\">
      97: invokevirtual #18                 // Method java/lang/StringBuilder.append:(Ljava/lang/String;)Ljava/lang/StringBuilder;
     100: aload         6
     102: invokeinterface #20,  1           // InterfaceMethod com/alibaba/dubbo/container/page/Menu.name:()Ljava/lang/String;
     107: invokevirtual #18                 // Method java/lang/StringBuilder.append:(Ljava/lang/String;)Ljava/lang/StringBuilder;
     110: ldc           #21                 // String </a>
     112: invokevirtual #18                 // Method java/lang/StringBuilder.append:(Ljava/lang/String;)Ljava/lang/StringBuilder;
     115: invokevirtual #22                 // Method java/lang/StringBuilder.toString:()Ljava/lang/String;
     118: invokeinterface #23,  2           // InterfaceMethod java/util/List.add:(Ljava/lang/Object;)Z
     123: pop
     124: aload         7
     126: aload         6
     128: invokeinterface #24,  1           // InterfaceMethod com/alibaba/dubbo/container/page/Menu.desc:()Ljava/lang/String;
     133: invokeinterface #23,  2           // InterfaceMethod java/util/List.add:(Ljava/lang/Object;)Z
     138: pop
     139: aload_2
     140: aload         7
     142: invokeinterface #23,  2           // InterfaceMethod java/util/List.add:(Ljava/lang/Object;)Z
     147: pop
     148: goto          20
     151: new           #25                 // class com/alibaba/dubbo/container/page/Page
     154: dup
     155: ldc           #26                 // String Home
     157: ldc           #27                 // String Menus
     159: iconst_2
     160: anewarray     #28                 // class java/lang/String
     163: dup
     164: iconst_0
     165: ldc           #29                 // String Menu Name
     167: aastore
     168: dup
     169: iconst_1
     170: ldc           #30                 // String Menu Desc
     172: aastore
     173: aload_2
     174: invokespecial #31                 // Method com/alibaba/dubbo/container/page/Page."<init>":(Ljava/lang/String;Ljava/lang/String;[Ljava/lang/String;Ljava/util/List;)V
     177: areturn
}
