Compiled from "StatusPageHandler.java"
public class com.alibaba.dubbo.container.page.pages.StatusPageHandler implements com.alibaba.dubbo.container.page.PageHandler {
  public com.alibaba.dubbo.container.page.pages.StatusPageHandler();
    Code:
       0: aload_0
       1: invokespecial #1                  // Method java/lang/Object."<init>":()V
       4: return

  public com.alibaba.dubbo.container.page.Page handle(com.alibaba.dubbo.common.URL);
    Code:
       0: new           #2                  // class java/util/ArrayList
       3: dup
       4: invokespecial #3                  // Method java/util/ArrayList."<init>":()V
       7: astore_2
       8: ldc           #4                  // class com/alibaba/dubbo/common/status/StatusChecker
      10: invokestatic  #5                  // Method org/apache/dubbo/common/extension/ExtensionLoader.getExtensionLoader:(Ljava/lang/Class;)Lorg/apache/dubbo/common/extension/ExtensionLoader;
      13: invokevirtual #6                  // Method org/apache/dubbo/common/extension/ExtensionLoader.getSupportedExtensions:()Ljava/util/Set;
      16: astore_3
      17: new           #7                  // class java/util/HashMap
      20: dup
      21: invokespecial #8                  // Method java/util/HashMap."<init>":()V
      24: astore        4
      26: aload_3
      27: invokeinterface #9,  1            // InterfaceMethod java/util/Set.iterator:()Ljava/util/Iterator;
      32: astore        5
      34: aload         5
      36: invokeinterface #10,  1           // InterfaceMethod java/util/Iterator.hasNext:()Z
      41: ifeq          172
      44: aload         5
      46: invokeinterface #11,  1           // InterfaceMethod java/util/Iterator.next:()Ljava/lang/Object;
      51: checkcast     #12                 // class java/lang/String
      54: astore        6
      56: ldc           #4                  // class com/alibaba/dubbo/common/status/StatusChecker
      58: invokestatic  #5                  // Method org/apache/dubbo/common/extension/ExtensionLoader.getExtensionLoader:(Ljava/lang/Class;)Lorg/apache/dubbo/common/extension/ExtensionLoader;
      61: aload         6
      63: invokevirtual #13                 // Method org/apache/dubbo/common/extension/ExtensionLoader.getExtension:(Ljava/lang/String;)Ljava/lang/Object;
      66: checkcast     #4                  // class com/alibaba/dubbo/common/status/StatusChecker
      69: astore        7
      71: new           #2                  // class java/util/ArrayList
      74: dup
      75: invokespecial #3                  // Method java/util/ArrayList."<init>":()V
      78: astore        8
      80: aload         8
      82: aload         6
      84: invokeinterface #14,  2           // InterfaceMethod java/util/List.add:(Ljava/lang/Object;)Z
      89: pop
      90: aload         7
      92: invokeinterface #15,  1           // InterfaceMethod com/alibaba/dubbo/common/status/StatusChecker.check:()Lcom/alibaba/dubbo/common/status/Status;
      97: astore        9
      99: aload         9
     101: ifnull        169
     104: getstatic     #16                 // Field org/apache/dubbo/common/status/Status$Level.UNKNOWN:Lorg/apache/dubbo/common/status/Status$Level;
     107: aload         9
     109: invokevirtual #17                 // Method org/apache/dubbo/common/status/Status.getLevel:()Lorg/apache/dubbo/common/status/Status$Level;
     112: invokevirtual #18                 // Method org/apache/dubbo/common/status/Status$Level.equals:(Ljava/lang/Object;)Z
     115: ifne          169
     118: aload         4
     120: aload         6
     122: aload         9
     124: invokeinterface #19,  3           // InterfaceMethod java/util/Map.put:(Ljava/lang/Object;Ljava/lang/Object;)Ljava/lang/Object;
     129: pop
     130: aload         8
     132: aload_0
     133: aload         9
     135: invokevirtual #17                 // Method org/apache/dubbo/common/status/Status.getLevel:()Lorg/apache/dubbo/common/status/Status$Level;
     138: invokespecial #20                 // Method getLevelHtml:(Lorg/apache/dubbo/common/status/Status$Level;)Ljava/lang/String;
     141: invokeinterface #14,  2           // InterfaceMethod java/util/List.add:(Ljava/lang/Object;)Z
     146: pop
     147: aload         8
     149: aload         9
     151: invokevirtual #21                 // Method org/apache/dubbo/common/status/Status.getMessage:()Ljava/lang/String;
     154: invokeinterface #14,  2           // InterfaceMethod java/util/List.add:(Ljava/lang/Object;)Z
     159: pop
     160: aload_2
     161: aload         8
     163: invokeinterface #14,  2           // InterfaceMethod java/util/List.add:(Ljava/lang/Object;)Z
     168: pop
     169: goto          34
     172: aload         4
     174: invokestatic  #22                 // Method org/apache/dubbo/common/status/support/StatusUtils.getSummaryStatus:(Ljava/util/Map;)Lorg/apache/dubbo/common/status/Status;
     177: astore        5
     179: ldc           #23                 // String status
     181: aload_1
     182: invokevirtual #24                 // Method com/alibaba/dubbo/common/URL.getPath:()Ljava/lang/String;
     185: invokevirtual #25                 // Method java/lang/String.equals:(Ljava/lang/Object;)Z
     188: ifeq          213
     191: new           #26                 // class com/alibaba/dubbo/container/page/Page
     194: dup
     195: ldc           #27                 // String
     197: ldc           #27                 // String
     199: ldc           #27                 // String
     201: aload         5
     203: invokevirtual #17                 // Method org/apache/dubbo/common/status/Status.getLevel:()Lorg/apache/dubbo/common/status/Status$Level;
     206: invokevirtual #28                 // Method org/apache/dubbo/common/status/Status$Level.toString:()Ljava/lang/String;
     209: invokespecial #29                 // Method com/alibaba/dubbo/container/page/Page."<init>":(Ljava/lang/String;Ljava/lang/String;Ljava/lang/String;Ljava/lang/String;)V
     212: areturn
     213: new           #2                  // class java/util/ArrayList
     216: dup
     217: invokespecial #3                  // Method java/util/ArrayList."<init>":()V
     220: astore        6
     222: aload         6
     224: ldc           #30                 // String summary
     226: invokeinterface #14,  2           // InterfaceMethod java/util/List.add:(Ljava/lang/Object;)Z
     231: pop
     232: aload         6
     234: aload_0
     235: aload         5
     237: invokevirtual #17                 // Method org/apache/dubbo/common/status/Status.getLevel:()Lorg/apache/dubbo/common/status/Status$Level;
     240: invokespecial #20                 // Method getLevelHtml:(Lorg/apache/dubbo/common/status/Status$Level;)Ljava/lang/String;
     243: invokeinterface #14,  2           // InterfaceMethod java/util/List.add:(Ljava/lang/Object;)Z
     248: pop
     249: aload         6
     251: ldc           #31                 // String <a href=\"/status\" target=\"_blank\">summary</a>
     253: invokeinterface #14,  2           // InterfaceMethod java/util/List.add:(Ljava/lang/Object;)Z
     258: pop
     259: aload_2
     260: aload         6
     262: invokeinterface #14,  2           // InterfaceMethod java/util/List.add:(Ljava/lang/Object;)Z
     267: pop
     268: new           #26                 // class com/alibaba/dubbo/container/page/Page
     271: dup
     272: ldc           #32                 // String Status (<a href=\"/status\" target=\"_blank\">summary</a>)
     274: ldc           #33                 // String Status
     276: iconst_3
     277: anewarray     #12                 // class java/lang/String
     280: dup
     281: iconst_0
     282: ldc           #34                 // String Name
     284: aastore
     285: dup
     286: iconst_1
     287: ldc           #33                 // String Status
     289: aastore
     290: dup
     291: iconst_2
     292: ldc           #35                 // String Description
     294: aastore
     295: aload_2
     296: invokespecial #36                 // Method com/alibaba/dubbo/container/page/Page."<init>":(Ljava/lang/String;Ljava/lang/String;[Ljava/lang/String;Ljava/util/List;)V
     299: areturn

  private java.lang.String getLevelHtml(org.apache.dubbo.common.status.Status$Level);
    Code:
       0: new           #37                 // class java/lang/StringBuilder
       3: dup
       4: invokespecial #38                 // Method java/lang/StringBuilder."<init>":()V
       7: ldc           #39                 // String <font color=\"
       9: invokevirtual #40                 // Method java/lang/StringBuilder.append:(Ljava/lang/String;)Ljava/lang/StringBuilder;
      12: aload_0
      13: aload_1
      14: invokespecial #41                 // Method getLevelColor:(Lorg/apache/dubbo/common/status/Status$Level;)Ljava/lang/String;
      17: invokevirtual #40                 // Method java/lang/StringBuilder.append:(Ljava/lang/String;)Ljava/lang/StringBuilder;
      20: ldc           #42                 // String \">
      22: invokevirtual #40                 // Method java/lang/StringBuilder.append:(Ljava/lang/String;)Ljava/lang/StringBuilder;
      25: aload_1
      26: invokevirtual #43                 // Method org/apache/dubbo/common/status/Status$Level.name:()Ljava/lang/String;
      29: invokevirtual #40                 // Method java/lang/StringBuilder.append:(Ljava/lang/String;)Ljava/lang/StringBuilder;
      32: ldc           #44                 // String </font>
      34: invokevirtual #40                 // Method java/lang/StringBuilder.append:(Ljava/lang/String;)Ljava/lang/StringBuilder;
      37: invokevirtual #45                 // Method java/lang/StringBuilder.toString:()Ljava/lang/String;
      40: areturn

  private java.lang.String getLevelColor(org.apache.dubbo.common.status.Status$Level);
    Code:
       0: aload_1
       1: getstatic     #46                 // Field org/apache/dubbo/common/status/Status$Level.OK:Lorg/apache/dubbo/common/status/Status$Level;
       4: if_acmpne     10
       7: ldc           #47                 // String green
       9: areturn
      10: aload_1
      11: getstatic     #48                 // Field org/apache/dubbo/common/status/Status$Level.ERROR:Lorg/apache/dubbo/common/status/Status$Level;
      14: if_acmpne     20
      17: ldc           #49                 // String red
      19: areturn
      20: aload_1
      21: getstatic     #50                 // Field org/apache/dubbo/common/status/Status$Level.WARN:Lorg/apache/dubbo/common/status/Status$Level;
      24: if_acmpne     30
      27: ldc           #51                 // String yellow
      29: areturn
      30: ldc           #52                 // String gray
      32: areturn
}
