Compiled from "AnnotationUtils.java"
public interface org.apache.dubbo.common.utils.AnnotationUtils {
  public static <A extends java.lang.annotation.Annotation> java.lang.Class<A> resolveAnnotationType(java.lang.reflect.AnnotatedElement, java.lang.String);
    Code:
       0: aload_0
       1: invokevirtual #1                  // Method java/lang/Object.getClass:()Ljava/lang/Class;
       4: invokevirtual #2                  // Method java/lang/Class.getClassLoader:()Ljava/lang/ClassLoader;
       7: astore_2
       8: aload_1
       9: aload_2
      10: invokestatic  #3                  // Method org/apache/dubbo/common/utils/ClassUtils.resolveClass:(Ljava/lang/String;Ljava/lang/ClassLoader;)Ljava/lang/Class;
      13: astore_3
      14: aload_3
      15: ifnull        27
      18: ldc           #4                  // class java/lang/annotation/Annotation
      20: aload_3
      21: invokevirtual #5                  // Method java/lang/Class.isAssignableFrom:(Ljava/lang/Class;)Z
      24: ifne          29
      27: aconst_null
      28: areturn
      29: aload_3
      30: areturn

  public static boolean isType(java.lang.reflect.AnnotatedElement);
    Code:
       0: aload_0
       1: instanceof    #6                  // class java/lang/Class
       4: ireturn

  public static boolean isSameType(java.lang.annotation.Annotation, java.lang.Class<? extends java.lang.annotation.Annotation>);
    Code:
       0: aload_0
       1: ifnull        8
       4: aload_1
       5: ifnonnull     10
       8: iconst_0
       9: ireturn
      10: aload_0
      11: invokeinterface #7,  1            // InterfaceMethod java/lang/annotation/Annotation.annotationType:()Ljava/lang/Class;
      16: aload_1
      17: invokestatic  #8                  // Method java/util/Objects.equals:(Ljava/lang/Object;Ljava/lang/Object;)Z
      20: ireturn

  public static java.util.function.Predicate<java.lang.annotation.Annotation> excludedType(java.lang.Class<? extends java.lang.annotation.Annotation>);
    Code:
       0: aload_0
       1: invokedynamic #9,  0              // InvokeDynamic #0:test:(Ljava/lang/Class;)Ljava/util/function/Predicate;
       6: areturn

  public static <T> T getAttribute(java.lang.annotation.Annotation, java.lang.String) throws java.lang.IllegalArgumentException;
    Code:
       0: aload_0
       1: ifnonnull     8
       4: aconst_null
       5: goto          17
       8: aload_0
       9: aload_1
      10: iconst_0
      11: anewarray     #10                 // class java/lang/Object
      14: invokestatic  #11                 // InterfaceMethod org/apache/dubbo/common/utils/MethodUtils.invokeMethod:(Ljava/lang/Object;Ljava/lang/String;[Ljava/lang/Object;)Ljava/lang/Object;
      17: areturn

  public static <T> T getValue(java.lang.annotation.Annotation) throws java.lang.IllegalArgumentException;
    Code:
       0: aload_0
       1: ldc           #12                 // String value
       3: invokestatic  #13                 // InterfaceMethod getAttribute:(Ljava/lang/annotation/Annotation;Ljava/lang/String;)Ljava/lang/Object;
       6: areturn

  public static <A extends java.lang.annotation.Annotation> A getAnnotation(java.lang.reflect.AnnotatedElement, java.lang.String) throws java.lang.ClassCastException;
    Code:
       0: aload_0
       1: aload_1
       2: invokestatic  #14                 // InterfaceMethod resolveAnnotationType:(Ljava/lang/reflect/AnnotatedElement;Ljava/lang/String;)Ljava/lang/Class;
       5: astore_2
       6: aload_2
       7: ifnonnull     12
      10: aconst_null
      11: areturn
      12: aload_0
      13: aload_2
      14: invokeinterface #15,  2           // InterfaceMethod java/lang/reflect/AnnotatedElement.getAnnotation:(Ljava/lang/Class;)Ljava/lang/annotation/Annotation;
      19: areturn

  public static java.util.List<java.lang.annotation.Annotation> getDeclaredAnnotations(java.lang.reflect.AnnotatedElement, java.util.function.Predicate<java.lang.annotation.Annotation>...);
    Code:
       0: aload_0
       1: ifnonnull     8
       4: invokestatic  #16                 // Method java/util/Collections.emptyList:()Ljava/util/List;
       7: areturn
       8: aload_0
       9: invokeinterface #17,  1           // InterfaceMethod java/lang/reflect/AnnotatedElement.getDeclaredAnnotations:()[Ljava/lang/annotation/Annotation;
      14: invokestatic  #18                 // Method java/util/Arrays.asList:([Ljava/lang/Object;)Ljava/util/List;
      17: aload_1
      18: invokestatic  #19                 // InterfaceMethod org/apache/dubbo/common/function/Streams.filterAll:(Ljava/lang/Iterable;[Ljava/util/function/Predicate;)Ljava/lang/Iterable;
      21: checkcast     #20                 // class java/util/List
      24: invokestatic  #21                 // Method java/util/Collections.unmodifiableList:(Ljava/util/List;)Ljava/util/List;
      27: areturn

  public static java.util.List<java.lang.annotation.Annotation> getAllDeclaredAnnotations(java.lang.reflect.AnnotatedElement, java.util.function.Predicate<java.lang.annotation.Annotation>...);
    Code:
       0: aload_0
       1: invokestatic  #22                 // InterfaceMethod isType:(Ljava/lang/reflect/AnnotatedElement;)Z
       4: ifeq          16
       7: aload_0
       8: checkcast     #6                  // class java/lang/Class
      11: aload_1
      12: invokestatic  #23                 // InterfaceMethod getAllDeclaredAnnotations:(Ljava/lang/Class;[Ljava/util/function/Predicate;)Ljava/util/List;
      15: areturn
      16: aload_0
      17: aload_1
      18: invokestatic  #24                 // InterfaceMethod getDeclaredAnnotations:(Ljava/lang/reflect/AnnotatedElement;[Ljava/util/function/Predicate;)Ljava/util/List;
      21: areturn

  public static java.util.List<java.lang.annotation.Annotation> getAllDeclaredAnnotations(java.lang.Class<?>, java.util.function.Predicate<java.lang.annotation.Annotation>...);
    Code:
       0: aload_0
       1: ifnonnull     8
       4: invokestatic  #16                 // Method java/util/Collections.emptyList:()Ljava/util/List;
       7: areturn
       8: new           #25                 // class java/util/LinkedList
      11: dup
      12: invokespecial #26                 // Method java/util/LinkedList."<init>":()V
      15: astore_2
      16: new           #27                 // class java/util/LinkedHashSet
      19: dup
      20: invokespecial #28                 // Method java/util/LinkedHashSet."<init>":()V
      23: astore_3
      24: aload_3
      25: aload_0
      26: invokeinterface #29,  2           // InterfaceMethod java/util/Set.add:(Ljava/lang/Object;)Z
      31: pop
      32: aload_3
      33: aload_0
      34: iconst_1
      35: anewarray     #30                 // class java/util/function/Predicate
      38: dup
      39: iconst_0
      40: invokedynamic #31,  0             // InvokeDynamic #1:test:()Ljava/util/function/Predicate;
      45: aastore
      46: invokestatic  #32                 // Method org/apache/dubbo/common/utils/ClassUtils.getAllInheritedTypes:(Ljava/lang/Class;[Ljava/util/function/Predicate;)Ljava/util/Set;
      49: invokeinterface #33,  2           // InterfaceMethod java/util/Set.addAll:(Ljava/util/Collection;)Z
      54: pop
      55: aload_3
      56: invokeinterface #34,  1           // InterfaceMethod java/util/Set.iterator:()Ljava/util/Iterator;
      61: astore        4
      63: aload         4
      65: invokeinterface #35,  1           // InterfaceMethod java/util/Iterator.hasNext:()Z
      70: ifeq          101
      73: aload         4
      75: invokeinterface #36,  1           // InterfaceMethod java/util/Iterator.next:()Ljava/lang/Object;
      80: checkcast     #6                  // class java/lang/Class
      83: astore        5
      85: aload_2
      86: aload         5
      88: aload_1
      89: invokestatic  #24                 // InterfaceMethod getDeclaredAnnotations:(Ljava/lang/reflect/AnnotatedElement;[Ljava/util/function/Predicate;)Ljava/util/List;
      92: invokeinterface #37,  2           // InterfaceMethod java/util/List.addAll:(Ljava/util/Collection;)Z
      97: pop
      98: goto          63
     101: aload_2
     102: invokestatic  #21                 // Method java/util/Collections.unmodifiableList:(Ljava/util/List;)Ljava/util/List;
     105: areturn

  public static java.util.List<java.lang.annotation.Annotation> getMetaAnnotations(java.lang.Class<? extends java.lang.annotation.Annotation>, java.util.function.Predicate<java.lang.annotation.Annotation>...);
    Code:
       0: aload_0
       1: iconst_4
       2: anewarray     #30                 // class java/util/function/Predicate
       5: dup
       6: iconst_0
       7: ldc           #38                 // class java/lang/annotation/Target
       9: invokestatic  #39                 // InterfaceMethod excludedType:(Ljava/lang/Class;)Ljava/util/function/Predicate;
      12: aastore
      13: dup
      14: iconst_1
      15: ldc           #40                 // class java/lang/annotation/Retention
      17: invokestatic  #39                 // InterfaceMethod excludedType:(Ljava/lang/Class;)Ljava/util/function/Predicate;
      20: aastore
      21: dup
      22: iconst_2
      23: ldc           #41                 // class java/lang/annotation/Documented
      25: invokestatic  #39                 // InterfaceMethod excludedType:(Ljava/lang/Class;)Ljava/util/function/Predicate;
      28: aastore
      29: dup
      30: iconst_3
      31: aload_1
      32: invokestatic  #42                 // InterfaceMethod org/apache/dubbo/common/function/Predicates.and:([Ljava/util/function/Predicate;)Ljava/util/function/Predicate;
      35: aastore
      36: invokestatic  #24                 // InterfaceMethod getDeclaredAnnotations:(Ljava/lang/reflect/AnnotatedElement;[Ljava/util/function/Predicate;)Ljava/util/List;
      39: areturn

  public static java.util.List<java.lang.annotation.Annotation> getAllMetaAnnotations(java.lang.Class<? extends java.lang.annotation.Annotation>, java.util.function.Predicate<java.lang.annotation.Annotation>...);
    Code:
       0: new           #25                 // class java/util/LinkedList
       3: dup
       4: invokespecial #26                 // Method java/util/LinkedList."<init>":()V
       7: astore_2
       8: aload_0
       9: iconst_0
      10: anewarray     #30                 // class java/util/function/Predicate
      13: invokestatic  #43                 // InterfaceMethod getMetaAnnotations:(Ljava/lang/Class;[Ljava/util/function/Predicate;)Ljava/util/List;
      16: astore_3
      17: aload_2
      18: aload_3
      19: invokeinterface #37,  2           // InterfaceMethod java/util/List.addAll:(Ljava/util/Collection;)Z
      24: pop
      25: aload_3
      26: invokeinterface #44,  1           // InterfaceMethod java/util/List.iterator:()Ljava/util/Iterator;
      31: astore        4
      33: aload         4
      35: invokeinterface #35,  1           // InterfaceMethod java/util/Iterator.hasNext:()Z
      40: ifeq          79
      43: aload         4
      45: invokeinterface #36,  1           // InterfaceMethod java/util/Iterator.next:()Ljava/lang/Object;
      50: checkcast     #4                  // class java/lang/annotation/Annotation
      53: astore        5
      55: aload_2
      56: aload         5
      58: invokeinterface #7,  1            // InterfaceMethod java/lang/annotation/Annotation.annotationType:()Ljava/lang/Class;
      63: iconst_0
      64: anewarray     #30                 // class java/util/function/Predicate
      67: invokestatic  #45                 // InterfaceMethod getAllMetaAnnotations:(Ljava/lang/Class;[Ljava/util/function/Predicate;)Ljava/util/List;
      70: invokeinterface #37,  2           // InterfaceMethod java/util/List.addAll:(Ljava/util/Collection;)Z
      75: pop
      76: goto          33
      79: aload_2
      80: aload_1
      81: invokestatic  #19                 // InterfaceMethod org/apache/dubbo/common/function/Streams.filterAll:(Ljava/lang/Iterable;[Ljava/util/function/Predicate;)Ljava/lang/Iterable;
      84: checkcast     #20                 // class java/util/List
      87: invokestatic  #21                 // Method java/util/Collections.unmodifiableList:(Ljava/util/List;)Ljava/util/List;
      90: areturn

  public static <A extends java.lang.annotation.Annotation> A findAnnotation(java.lang.reflect.AnnotatedElement, java.lang.String);
    Code:
       0: aload_0
       1: aload_0
       2: aload_1
       3: invokestatic  #14                 // InterfaceMethod resolveAnnotationType:(Ljava/lang/reflect/AnnotatedElement;Ljava/lang/String;)Ljava/lang/Class;
       6: invokestatic  #46                 // InterfaceMethod findAnnotation:(Ljava/lang/reflect/AnnotatedElement;Ljava/lang/Class;)Ljava/lang/annotation/Annotation;
       9: areturn

  public static <A extends java.lang.annotation.Annotation> A findAnnotation(java.lang.reflect.AnnotatedElement, java.lang.Class<A>);
    Code:
       0: aload_0
       1: iconst_0
       2: anewarray     #30                 // class java/util/function/Predicate
       5: invokestatic  #47                 // InterfaceMethod getAllDeclaredAnnotations:(Ljava/lang/reflect/AnnotatedElement;[Ljava/util/function/Predicate;)Ljava/util/List;
       8: iconst_1
       9: anewarray     #30                 // class java/util/function/Predicate
      12: dup
      13: iconst_0
      14: aload_1
      15: invokedynamic #48,  0             // InvokeDynamic #2:test:(Ljava/lang/Class;)Ljava/util/function/Predicate;
      20: aastore
      21: invokestatic  #49                 // InterfaceMethod org/apache/dubbo/common/function/Streams.filterFirst:(Ljava/lang/Iterable;[Ljava/util/function/Predicate;)Ljava/lang/Object;
      24: checkcast     #4                  // class java/lang/annotation/Annotation
      27: areturn

  public static <A extends java.lang.annotation.Annotation> java.util.List<A> findMetaAnnotations(java.lang.Class<? extends java.lang.annotation.Annotation>, java.lang.Class<A>);
    Code:
       0: aload_0
       1: iconst_1
       2: anewarray     #30                 // class java/util/function/Predicate
       5: dup
       6: iconst_0
       7: aload_1
       8: invokedynamic #50,  0             // InvokeDynamic #3:test:(Ljava/lang/Class;)Ljava/util/function/Predicate;
      13: aastore
      14: invokestatic  #45                 // InterfaceMethod getAllMetaAnnotations:(Ljava/lang/Class;[Ljava/util/function/Predicate;)Ljava/util/List;
      17: areturn

  public static <A extends java.lang.annotation.Annotation> java.util.List<A> findMetaAnnotations(java.lang.reflect.AnnotatedElement, java.lang.Class<A>);
    Code:
       0: new           #25                 // class java/util/LinkedList
       3: dup
       4: invokespecial #26                 // Method java/util/LinkedList."<init>":()V
       7: astore_2
       8: aload_0
       9: iconst_0
      10: anewarray     #30                 // class java/util/function/Predicate
      13: invokestatic  #47                 // InterfaceMethod getAllDeclaredAnnotations:(Ljava/lang/reflect/AnnotatedElement;[Ljava/util/function/Predicate;)Ljava/util/List;
      16: invokeinterface #44,  1           // InterfaceMethod java/util/List.iterator:()Ljava/util/Iterator;
      21: astore_3
      22: aload_3
      23: invokeinterface #35,  1           // InterfaceMethod java/util/Iterator.hasNext:()Z
      28: ifeq          63
      31: aload_3
      32: invokeinterface #36,  1           // InterfaceMethod java/util/Iterator.next:()Ljava/lang/Object;
      37: checkcast     #4                  // class java/lang/annotation/Annotation
      40: astore        4
      42: aload_2
      43: aload         4
      45: invokeinterface #7,  1            // InterfaceMethod java/lang/annotation/Annotation.annotationType:()Ljava/lang/Class;
      50: aload_1
      51: invokestatic  #51                 // InterfaceMethod findMetaAnnotations:(Ljava/lang/Class;Ljava/lang/Class;)Ljava/util/List;
      54: invokeinterface #37,  2           // InterfaceMethod java/util/List.addAll:(Ljava/util/Collection;)Z
      59: pop
      60: goto          22
      63: aload_2
      64: invokestatic  #21                 // Method java/util/Collections.unmodifiableList:(Ljava/util/List;)Ljava/util/List;
      67: areturn

  public static <A extends java.lang.annotation.Annotation> A findMetaAnnotation(java.lang.reflect.AnnotatedElement, java.lang.String);
    Code:
       0: aload_0
       1: aload_0
       2: aload_1
       3: invokestatic  #14                 // InterfaceMethod resolveAnnotationType:(Ljava/lang/reflect/AnnotatedElement;Ljava/lang/String;)Ljava/lang/Class;
       6: invokestatic  #52                 // InterfaceMethod findMetaAnnotation:(Ljava/lang/reflect/AnnotatedElement;Ljava/lang/Class;)Ljava/lang/annotation/Annotation;
       9: areturn

  public static <A extends java.lang.annotation.Annotation> A findMetaAnnotation(java.lang.Class<? extends java.lang.annotation.Annotation>, java.lang.Class<A>);
    Code:
       0: aload_0
       1: aload_1
       2: invokestatic  #51                 // InterfaceMethod findMetaAnnotations:(Ljava/lang/Class;Ljava/lang/Class;)Ljava/util/List;
       5: invokestatic  #53                 // Method org/apache/dubbo/common/utils/CollectionUtils.first:(Ljava/util/Collection;)Ljava/lang/Object;
       8: checkcast     #4                  // class java/lang/annotation/Annotation
      11: areturn

  public static <A extends java.lang.annotation.Annotation> A findMetaAnnotation(java.lang.reflect.AnnotatedElement, java.lang.Class<A>);
    Code:
       0: aload_0
       1: aload_1
       2: invokestatic  #54                 // InterfaceMethod findMetaAnnotations:(Ljava/lang/reflect/AnnotatedElement;Ljava/lang/Class;)Ljava/util/List;
       5: invokestatic  #53                 // Method org/apache/dubbo/common/utils/CollectionUtils.first:(Ljava/util/Collection;)Ljava/lang/Object;
       8: checkcast     #4                  // class java/lang/annotation/Annotation
      11: areturn

  public static boolean isAnnotationPresent(java.lang.Class<?>, boolean, java.lang.Class<? extends java.lang.annotation.Annotation>...);
    Code:
       0: aload_2
       1: ifnonnull     8
       4: iconst_0
       5: goto          10
       8: aload_2
       9: arraylength
      10: istore_3
      11: iload_3
      12: iconst_1
      13: if_icmpge     18
      16: iconst_0
      17: ireturn
      18: iconst_0
      19: istore        4
      21: iconst_0
      22: istore        5
      24: iload         5
      26: iload_3
      27: if_icmpge     63
      30: aload_2
      31: iload         5
      33: aaload
      34: astore        6
      36: aload_0
      37: aload         6
      39: invokestatic  #46                 // InterfaceMethod findAnnotation:(Ljava/lang/reflect/AnnotatedElement;Ljava/lang/Class;)Ljava/lang/annotation/Annotation;
      42: ifnonnull     54
      45: aload_0
      46: aload         6
      48: invokestatic  #52                 // InterfaceMethod findMetaAnnotation:(Ljava/lang/reflect/AnnotatedElement;Ljava/lang/Class;)Ljava/lang/annotation/Annotation;
      51: ifnull        57
      54: iinc          4, 1
      57: iinc          5, 1
      60: goto          24
      63: iload_1
      64: ifeq          81
      67: iload         4
      69: iload_3
      70: if_icmpne     77
      73: iconst_1
      74: goto          91
      77: iconst_0
      78: goto          91
      81: iload         4
      83: ifle          90
      86: iconst_1
      87: goto          91
      90: iconst_0
      91: ireturn

  public static boolean isAnnotationPresent(java.lang.Class<?>, java.lang.Class<? extends java.lang.annotation.Annotation>);
    Code:
       0: aload_0
       1: iconst_1
       2: iconst_1
       3: anewarray     #6                  // class java/lang/Class
       6: dup
       7: iconst_0
       8: aload_1
       9: aastore
      10: invokestatic  #55                 // InterfaceMethod isAnnotationPresent:(Ljava/lang/Class;Z[Ljava/lang/Class;)Z
      13: ireturn

  public static boolean isAnnotationPresent(java.lang.reflect.AnnotatedElement, java.lang.String);
    Code:
       0: aload_0
       1: invokevirtual #1                  // Method java/lang/Object.getClass:()Ljava/lang/Class;
       4: invokevirtual #2                  // Method java/lang/Class.getClassLoader:()Ljava/lang/ClassLoader;
       7: astore_2
       8: aload_1
       9: aload_2
      10: invokestatic  #3                  // Method org/apache/dubbo/common/utils/ClassUtils.resolveClass:(Ljava/lang/String;Ljava/lang/ClassLoader;)Ljava/lang/Class;
      13: astore_3
      14: aload_3
      15: ifnull        27
      18: ldc           #4                  // class java/lang/annotation/Annotation
      20: aload_3
      21: invokevirtual #5                  // Method java/lang/Class.isAssignableFrom:(Ljava/lang/Class;)Z
      24: ifne          29
      27: iconst_0
      28: ireturn
      29: aload_0
      30: aload_3
      31: invokestatic  #56                 // InterfaceMethod isAnnotationPresent:(Ljava/lang/reflect/AnnotatedElement;Ljava/lang/Class;)Z
      34: ireturn

  public static boolean isAnnotationPresent(java.lang.reflect.AnnotatedElement, java.lang.Class<? extends java.lang.annotation.Annotation>);
    Code:
       0: aload_0
       1: invokestatic  #22                 // InterfaceMethod isType:(Ljava/lang/reflect/AnnotatedElement;)Z
       4: ifeq          16
       7: aload_0
       8: checkcast     #6                  // class java/lang/Class
      11: aload_1
      12: invokestatic  #57                 // InterfaceMethod isAnnotationPresent:(Ljava/lang/Class;Ljava/lang/Class;)Z
      15: ireturn
      16: aload_0
      17: aload_1
      18: invokeinterface #58,  2           // InterfaceMethod java/lang/reflect/AnnotatedElement.isAnnotationPresent:(Ljava/lang/Class;)Z
      23: ifne          34
      26: aload_0
      27: aload_1
      28: invokestatic  #52                 // InterfaceMethod findMetaAnnotation:(Ljava/lang/reflect/AnnotatedElement;Ljava/lang/Class;)Ljava/lang/annotation/Annotation;
      31: ifnull        38
      34: iconst_1
      35: goto          39
      38: iconst_0
      39: ireturn

  public static boolean isAllAnnotationPresent(java.lang.Class<?>, java.lang.Class<? extends java.lang.annotation.Annotation>...);
    Code:
       0: aload_0
       1: iconst_1
       2: aload_1
       3: invokestatic  #55                 // InterfaceMethod isAnnotationPresent:(Ljava/lang/Class;Z[Ljava/lang/Class;)Z
       6: ireturn

  public static boolean isAnyAnnotationPresent(java.lang.Class<?>, java.lang.Class<? extends java.lang.annotation.Annotation>...);
    Code:
       0: aload_0
       1: iconst_0
       2: aload_1
       3: invokestatic  #55                 // InterfaceMethod isAnnotationPresent:(Ljava/lang/Class;Z[Ljava/lang/Class;)Z
       6: ireturn

  public static <T> T getDefaultValue(java.lang.annotation.Annotation, java.lang.String);
    Code:
       0: aload_0
       1: invokeinterface #7,  1            // InterfaceMethod java/lang/annotation/Annotation.annotationType:()Ljava/lang/Class;
       6: aload_1
       7: invokestatic  #59                 // InterfaceMethod getDefaultValue:(Ljava/lang/Class;Ljava/lang/String;)Ljava/lang/Object;
      10: areturn

  public static <T> T getDefaultValue(java.lang.Class<? extends java.lang.annotation.Annotation>, java.lang.String);
    Code:
       0: aload_0
       1: aload_1
       2: invokestatic  #60                 // InterfaceMethod org/apache/dubbo/common/utils/MethodUtils.findMethod:(Ljava/lang/Class;Ljava/lang/String;)Ljava/lang/reflect/Method;
       5: astore_2
       6: aload_2
       7: ifnonnull     14
      10: aconst_null
      11: goto          18
      14: aload_2
      15: invokevirtual #61                 // Method java/lang/reflect/Method.getDefaultValue:()Ljava/lang/Object;
      18: areturn

  public static java.util.Map<java.lang.String, java.lang.Object> filterDefaultValues(java.lang.Class<? extends java.lang.annotation.Annotation>, java.util.Map<java.lang.String, java.lang.Object>);
    Code:
       0: new           #62                 // class java/util/LinkedHashMap
       3: dup
       4: aload_1
       5: invokeinterface #63,  1           // InterfaceMethod java/util/Map.size:()I
      10: invokespecial #64                 // Method java/util/LinkedHashMap."<init>":(I)V
      13: astore_2
      14: aload_1
      15: aload_0
      16: aload_2
      17: invokedynamic #65,  0             // InvokeDynamic #4:accept:(Ljava/lang/Class;Ljava/util/Map;)Ljava/util/function/BiConsumer;
      22: invokeinterface #66,  2           // InterfaceMethod java/util/Map.forEach:(Ljava/util/function/BiConsumer;)V
      27: aload_2
      28: ldc           #67                 // String interfaceClass
      30: invokeinterface #68,  2           // InterfaceMethod java/util/Map.get:(Ljava/lang/Object;)Ljava/lang/Object;
      35: astore_3
      36: aload_3
      37: instanceof    #69                 // class java/lang/String
      40: ifeq          64
      43: aload_3
      44: checkcast     #69                 // class java/lang/String
      47: ldc           #70                 // String void
      49: invokestatic  #71                 // Method org/apache/dubbo/common/utils/StringUtils.isEquals:(Ljava/lang/String;Ljava/lang/String;)Z
      52: ifeq          64
      55: aload_2
      56: ldc           #67                 // String interfaceClass
      58: invokeinterface #72,  2           // InterfaceMethod java/util/Map.remove:(Ljava/lang/Object;)Ljava/lang/Object;
      63: pop
      64: aload_2
      65: areturn

  public static java.util.Map<java.lang.String, java.lang.Object> filterDefaultValues(java.lang.annotation.Annotation, java.util.Map<java.lang.String, java.lang.Object>);
    Code:
       0: aload_0
       1: invokeinterface #7,  1            // InterfaceMethod java/lang/annotation/Annotation.annotationType:()Ljava/lang/Class;
       6: aload_1
       7: invokestatic  #73                 // InterfaceMethod filterDefaultValues:(Ljava/lang/Class;Ljava/util/Map;)Ljava/util/Map;
      10: areturn

  public static java.util.Map<java.lang.String, java.lang.Object> getAttributes(java.lang.annotation.Annotation, boolean);
    Code:
       0: aload_0
       1: invokeinterface #7,  1            // InterfaceMethod java/lang/annotation/Annotation.annotationType:()Ljava/lang/Class;
       6: astore_2
       7: aload_2
       8: invokevirtual #74                 // Method java/lang/Class.getMethods:()[Ljava/lang/reflect/Method;
      11: astore_3
      12: new           #62                 // class java/util/LinkedHashMap
      15: dup
      16: aload_3
      17: arraylength
      18: invokespecial #64                 // Method java/util/LinkedHashMap."<init>":(I)V
      21: astore        4
      23: aload_3
      24: astore        5
      26: aload         5
      28: arraylength
      29: istore        6
      31: iconst_0
      32: istore        7
      34: iload         7
      36: iload         6
      38: if_icmpge     150
      41: aload         5
      43: iload         7
      45: aaload
      46: astore        8
      48: aload         8
      50: invokevirtual #75                 // Method java/lang/reflect/Method.getDeclaringClass:()Ljava/lang/Class;
      53: ldc           #4                  // class java/lang/annotation/Annotation
      55: if_acmpne     61
      58: goto          144
      61: aload         8
      63: invokevirtual #76                 // Method java/lang/reflect/Method.getName:()Ljava/lang/String;
      66: astore        9
      68: aload         8
      70: aload_0
      71: iconst_0
      72: anewarray     #10                 // class java/lang/Object
      75: invokevirtual #77                 // Method java/lang/reflect/Method.invoke:(Ljava/lang/Object;[Ljava/lang/Object;)Ljava/lang/Object;
      78: astore        10
      80: iload_1
      81: ifeq          97
      84: aload         10
      86: aload         8
      88: invokevirtual #61                 // Method java/lang/reflect/Method.getDefaultValue:()Ljava/lang/Object;
      91: invokestatic  #78                 // Method java/util/Objects.deepEquals:(Ljava/lang/Object;Ljava/lang/Object;)Z
      94: ifne          109
      97: aload         4
      99: aload         9
     101: aload         10
     103: invokeinterface #79,  3           // InterfaceMethod java/util/Map.put:(Ljava/lang/Object;Ljava/lang/Object;)Ljava/lang/Object;
     108: pop
     109: goto          144
     112: astore        9
     114: new           #81                 // class java/lang/IllegalStateException
     117: dup
     118: new           #82                 // class java/lang/StringBuilder
     121: dup
     122: invokespecial #83                 // Method java/lang/StringBuilder."<init>":()V
     125: ldc           #84                 // String get attribute value of annotation failed:
     127: invokevirtual #85                 // Method java/lang/StringBuilder.append:(Ljava/lang/String;)Ljava/lang/StringBuilder;
     130: aload         8
     132: invokevirtual #86                 // Method java/lang/StringBuilder.append:(Ljava/lang/Object;)Ljava/lang/StringBuilder;
     135: invokevirtual #87                 // Method java/lang/StringBuilder.toString:()Ljava/lang/String;
     138: aload         9
     140: invokespecial #88                 // Method java/lang/IllegalStateException."<init>":(Ljava/lang/String;Ljava/lang/Throwable;)V
     143: athrow
     144: iinc          7, 1
     147: goto          34
     150: aload         4
     152: areturn
    Exception table:
       from    to  target type
          48    58   112   Class java/lang/Exception
          61   109   112   Class java/lang/Exception

  private static void lambda$filterDefaultValues$4(java.lang.Class, java.util.Map, java.lang.String, java.lang.Object);
    Code:
       0: aload_3
       1: aload_0
       2: aload_2
       3: invokestatic  #59                 // InterfaceMethod getDefaultValue:(Ljava/lang/Class;Ljava/lang/String;)Ljava/lang/Object;
       6: invokestatic  #78                 // Method java/util/Objects.deepEquals:(Ljava/lang/Object;Ljava/lang/Object;)Z
       9: ifne          21
      12: aload_1
      13: aload_2
      14: aload_3
      15: invokeinterface #79,  3           // InterfaceMethod java/util/Map.put:(Ljava/lang/Object;Ljava/lang/Object;)Ljava/lang/Object;
      20: pop
      21: return

  private static boolean lambda$findMetaAnnotations$3(java.lang.Class, java.lang.annotation.Annotation);
    Code:
       0: aload_1
       1: aload_0
       2: invokestatic  #89                 // InterfaceMethod isSameType:(Ljava/lang/annotation/Annotation;Ljava/lang/Class;)Z
       5: ireturn

  private static boolean lambda$findAnnotation$2(java.lang.Class, java.lang.annotation.Annotation);
    Code:
       0: aload_1
       1: aload_0
       2: invokestatic  #89                 // InterfaceMethod isSameType:(Ljava/lang/annotation/Annotation;Ljava/lang/Class;)Z
       5: ireturn

  private static boolean lambda$getAllDeclaredAnnotations$1(java.lang.Class);
    Code:
       0: ldc           #10                 // class java/lang/Object
       2: aload_0
       3: invokevirtual #90                 // Method java/lang/Object.equals:(Ljava/lang/Object;)Z
       6: ifne          13
       9: iconst_1
      10: goto          14
      13: iconst_0
      14: ireturn

  private static boolean lambda$excludedType$0(java.lang.Class, java.lang.annotation.Annotation);
    Code:
       0: aload_1
       1: aload_0
       2: invokestatic  #89                 // InterfaceMethod isSameType:(Ljava/lang/annotation/Annotation;Ljava/lang/Class;)Z
       5: ifne          12
       8: iconst_1
       9: goto          13
      12: iconst_0
      13: ireturn
}
