Compiled from "Assert.java"
public abstract class org.apache.dubbo.common.utils.Assert {
  protected org.apache.dubbo.common.utils.Assert();
    Code:
       0: aload_0
       1: invokespecial #1                  // Method java/lang/Object."<init>":()V
       4: return

  public static void notNull(java.lang.Object, java.lang.String);
    Code:
       0: aload_0
       1: ifnonnull     13
       4: new           #2                  // class java/lang/IllegalArgumentException
       7: dup
       8: aload_1
       9: invokespecial #3                  // Method java/lang/IllegalArgumentException."<init>":(Ljava/lang/String;)V
      12: athrow
      13: return

  public static void notEmptyString(java.lang.String, java.lang.String);
    Code:
       0: aload_0
       1: invokestatic  #4                  // Method org/apache/dubbo/common/utils/StringUtils.isEmpty:(Ljava/lang/String;)Z
       4: ifeq          16
       7: new           #2                  // class java/lang/IllegalArgumentException
      10: dup
      11: aload_1
      12: invokespecial #3                  // Method java/lang/IllegalArgumentException."<init>":(Ljava/lang/String;)V
      15: athrow
      16: return

  public static void notNull(java.lang.Object, java.lang.RuntimeException);
    Code:
       0: aload_0
       1: ifnonnull     6
       4: aload_1
       5: athrow
       6: return

  public static void assertTrue(boolean, java.lang.String);
    Code:
       0: iload_0
       1: ifne          13
       4: new           #2                  // class java/lang/IllegalArgumentException
       7: dup
       8: aload_1
       9: invokespecial #3                  // Method java/lang/IllegalArgumentException."<init>":(Ljava/lang/String;)V
      12: athrow
      13: return

  public static void assertTrue(boolean, java.util.function.Supplier<java.lang.String>);
    Code:
       0: iload_0
       1: ifne          16
       4: new           #5                  // class java/lang/IllegalStateException
       7: dup
       8: aload_1
       9: invokestatic  #6                  // Method nullSafeGet:(Ljava/util/function/Supplier;)Ljava/lang/String;
      12: invokespecial #7                  // Method java/lang/IllegalStateException."<init>":(Ljava/lang/String;)V
      15: athrow
      16: return

  private static java.lang.String nullSafeGet(java.util.function.Supplier<java.lang.String>);
    Code:
       0: aload_0
       1: ifnull        16
       4: aload_0
       5: invokeinterface #8,  1            // InterfaceMethod java/util/function/Supplier.get:()Ljava/lang/Object;
      10: checkcast     #9                  // class java/lang/String
      13: goto          17
      16: aconst_null
      17: areturn
}
