Compiled from "CharSequenceComparator.java"
public class org.apache.dubbo.common.utils.CharSequenceComparator implements java.util.Comparator<java.lang.CharSequence> {
  public static final org.apache.dubbo.common.utils.CharSequenceComparator INSTANCE;

  private org.apache.dubbo.common.utils.CharSequenceComparator();
    Code:
       0: aload_0
       1: invokespecial #1                  // Method java/lang/Object."<init>":()V
       4: return

  public int compare(java.lang.CharSequence, java.lang.CharSequence);
    Code:
       0: aload_1
       1: invokeinterface #2,  1            // InterfaceMethod java/lang/CharSequence.toString:()Ljava/lang/String;
       6: aload_2
       7: invokeinterface #2,  1            // InterfaceMethod java/lang/CharSequence.toString:()Ljava/lang/String;
      12: invokevirtual #3                  // Method java/lang/String.compareTo:(Ljava/lang/String;)I
      15: ireturn

  public int compare(java.lang.Object, java.lang.Object);
    Code:
       0: aload_0
       1: aload_1
       2: checkcast     #4                  // class java/lang/CharSequence
       5: aload_2
       6: checkcast     #4                  // class java/lang/CharSequence
       9: invokevirtual #5                  // Method compare:(Ljava/lang/CharSequence;Ljava/lang/CharSequence;)I
      12: ireturn

  static {};
    Code:
       0: new           #6                  // class org/apache/dubbo/common/utils/CharSequenceComparator
       3: dup
       4: invokespecial #7                  // Method "<init>":()V
       7: putstatic     #8                  // Field INSTANCE:Lorg/apache/dubbo/common/utils/CharSequenceComparator;
      10: return
}
