Compiled from "ClassUtils.java"
public class org.apache.dubbo.common.utils.ClassUtils {
  public static final java.lang.String ARRAY_SUFFIX;

  public static final java.util.Set<java.lang.Class<?>> SIMPLE_TYPES;

  private static final java.lang.String INTERNAL_ARRAY_PREFIX;

  private static final java.util.Map<java.lang.String, java.lang.Class<?>> PRIMITIVE_TYPE_NAME_MAP;

  private static final java.util.Map<java.lang.Class<?>, java.lang.Class<?>> PRIMITIVE_WRAPPER_TYPE_MAP;

  private static final java.util.Map<java.lang.Class<?>, java.lang.Class<?>> WRAPPER_PRIMITIVE_TYPE_MAP;

  private static final char PACKAGE_SEPARATOR_CHAR;

  private static final java.lang.String[] OBJECT_METHODS;

  public org.apache.dubbo.common.utils.ClassUtils();
    Code:
       0: aload_0
       1: invokespecial #1                  // Method java/lang/Object."<init>":()V
       4: return

  public static java.lang.Class<?> forNameWithThreadContextClassLoader(java.lang.String) throws java.lang.ClassNotFoundException;
    Code:
       0: aload_0
       1: invokestatic  #2                  // Method java/lang/Thread.currentThread:()Ljava/lang/Thread;
       4: invokevirtual #3                  // Method java/lang/Thread.getContextClassLoader:()Ljava/lang/ClassLoader;
       7: invokestatic  #4                  // Method forName:(Ljava/lang/String;Ljava/lang/ClassLoader;)Ljava/lang/Class;
      10: areturn

  public static java.lang.Class<?> forNameWithCallerClassLoader(java.lang.String, java.lang.Class<?>) throws java.lang.ClassNotFoundException;
    Code:
       0: aload_0
       1: aload_1
       2: invokevirtual #5                  // Method java/lang/Class.getClassLoader:()Ljava/lang/ClassLoader;
       5: invokestatic  #4                  // Method forName:(Ljava/lang/String;Ljava/lang/ClassLoader;)Ljava/lang/Class;
       8: areturn

  public static java.lang.ClassLoader getCallerClassLoader(java.lang.Class<?>);
    Code:
       0: aload_0
       1: invokevirtual #5                  // Method java/lang/Class.getClassLoader:()Ljava/lang/ClassLoader;
       4: areturn

  public static java.lang.ClassLoader getClassLoader(java.lang.Class<?>);
    Code:
       0: aconst_null
       1: astore_1
       2: aload_0
       3: invokevirtual #6                  // Method java/lang/Class.getName:()Ljava/lang/String;
       6: ldc           #7                  // String org.apache.dubbo
       8: invokevirtual #8                  // Method java/lang/String.startsWith:(Ljava/lang/String;)Z
      11: ifne          19
      14: aload_0
      15: invokevirtual #5                  // Method java/lang/Class.getClassLoader:()Ljava/lang/ClassLoader;
      18: astore_1
      19: aload_1
      20: ifnonnull     55
      23: invokestatic  #2                  // Method java/lang/Thread.currentThread:()Ljava/lang/Thread;
      26: invokevirtual #3                  // Method java/lang/Thread.getContextClassLoader:()Ljava/lang/ClassLoader;
      29: astore_1
      30: goto          34
      33: astore_2
      34: aload_1
      35: ifnonnull     55
      38: aload_0
      39: invokevirtual #5                  // Method java/lang/Class.getClassLoader:()Ljava/lang/ClassLoader;
      42: astore_1
      43: aload_1
      44: ifnonnull     55
      47: invokestatic  #10                 // Method java/lang/ClassLoader.getSystemClassLoader:()Ljava/lang/ClassLoader;
      50: astore_1
      51: goto          55
      54: astore_2
      55: aload_1
      56: areturn
    Exception table:
       from    to  target type
          23    30    33   Class java/lang/Exception
          47    51    54   Class java/lang/Exception

  public static java.lang.ClassLoader getClassLoader();
    Code:
       0: ldc           #11                 // class org/apache/dubbo/common/utils/ClassUtils
       2: invokestatic  #12                 // Method getClassLoader:(Ljava/lang/Class;)Ljava/lang/ClassLoader;
       5: areturn

  public static java.lang.Class<?> forName(java.lang.String) throws java.lang.ClassNotFoundException;
    Code:
       0: aload_0
       1: invokestatic  #13                 // Method getClassLoader:()Ljava/lang/ClassLoader;
       4: invokestatic  #4                  // Method forName:(Ljava/lang/String;Ljava/lang/ClassLoader;)Ljava/lang/Class;
       7: areturn

  public static java.lang.Class<?> forName(java.lang.String, java.lang.ClassLoader) throws java.lang.ClassNotFoundException, java.lang.LinkageError;
    Code:
       0: aload_0
       1: invokestatic  #14                 // Method resolvePrimitiveClassName:(Ljava/lang/String;)Ljava/lang/Class;
       4: astore_2
       5: aload_2
       6: ifnull        11
       9: aload_2
      10: areturn
      11: aload_0
      12: ldc           #15                 // String []
      14: invokevirtual #16                 // Method java/lang/String.endsWith:(Ljava/lang/String;)Z
      17: ifeq          53
      20: aload_0
      21: iconst_0
      22: aload_0
      23: invokevirtual #17                 // Method java/lang/String.length:()I
      26: ldc           #15                 // String []
      28: invokevirtual #17                 // Method java/lang/String.length:()I
      31: isub
      32: invokevirtual #18                 // Method java/lang/String.substring:(II)Ljava/lang/String;
      35: astore_3
      36: aload_3
      37: aload_1
      38: invokestatic  #4                  // Method forName:(Ljava/lang/String;Ljava/lang/ClassLoader;)Ljava/lang/Class;
      41: astore        4
      43: aload         4
      45: iconst_0
      46: invokestatic  #19                 // Method java/lang/reflect/Array.newInstance:(Ljava/lang/Class;I)Ljava/lang/Object;
      49: invokevirtual #20                 // Method java/lang/Object.getClass:()Ljava/lang/Class;
      52: areturn
      53: aload_0
      54: ldc           #21                 // String [L
      56: invokevirtual #22                 // Method java/lang/String.indexOf:(Ljava/lang/String;)I
      59: istore_3
      60: iload_3
      61: iconst_m1
      62: if_icmpeq     135
      65: aload_0
      66: ldc           #23                 // String ;
      68: invokevirtual #16                 // Method java/lang/String.endsWith:(Ljava/lang/String;)Z
      71: ifeq          135
      74: aconst_null
      75: astore        4
      77: iload_3
      78: ifne          101
      81: aload_0
      82: ldc           #21                 // String [L
      84: invokevirtual #17                 // Method java/lang/String.length:()I
      87: aload_0
      88: invokevirtual #17                 // Method java/lang/String.length:()I
      91: iconst_1
      92: isub
      93: invokevirtual #18                 // Method java/lang/String.substring:(II)Ljava/lang/String;
      96: astore        4
      98: goto          117
     101: aload_0
     102: ldc           #24                 // String [
     104: invokevirtual #8                  // Method java/lang/String.startsWith:(Ljava/lang/String;)Z
     107: ifeq          117
     110: aload_0
     111: iconst_1
     112: invokevirtual #25                 // Method java/lang/String.substring:(I)Ljava/lang/String;
     115: astore        4
     117: aload         4
     119: aload_1
     120: invokestatic  #4                  // Method forName:(Ljava/lang/String;Ljava/lang/ClassLoader;)Ljava/lang/Class;
     123: astore        5
     125: aload         5
     127: iconst_0
     128: invokestatic  #19                 // Method java/lang/reflect/Array.newInstance:(Ljava/lang/Class;I)Ljava/lang/Object;
     131: invokevirtual #20                 // Method java/lang/Object.getClass:()Ljava/lang/Class;
     134: areturn
     135: aload_1
     136: astore        4
     138: aload         4
     140: ifnonnull     148
     143: invokestatic  #13                 // Method getClassLoader:()Ljava/lang/ClassLoader;
     146: astore        4
     148: aload         4
     150: aload_0
     151: invokevirtual #26                 // Method java/lang/ClassLoader.loadClass:(Ljava/lang/String;)Ljava/lang/Class;
     154: areturn

  public static java.lang.Class<?> resolvePrimitiveClassName(java.lang.String);
    Code:
       0: aconst_null
       1: astore_1
       2: aload_0
       3: ifnull        28
       6: aload_0
       7: invokevirtual #17                 // Method java/lang/String.length:()I
      10: bipush        8
      12: if_icmpgt     28
      15: getstatic     #27                 // Field PRIMITIVE_TYPE_NAME_MAP:Ljava/util/Map;
      18: aload_0
      19: invokeinterface #28,  2           // InterfaceMethod java/util/Map.get:(Ljava/lang/Object;)Ljava/lang/Object;
      24: checkcast     #29                 // class java/lang/Class
      27: astore_1
      28: aload_1
      29: areturn

  public static java.lang.String toShortString(java.lang.Object);
    Code:
       0: aload_0
       1: ifnonnull     7
       4: ldc           #30                 // String null
       6: areturn
       7: new           #31                 // class java/lang/StringBuilder
      10: dup
      11: invokespecial #32                 // Method java/lang/StringBuilder."<init>":()V
      14: aload_0
      15: invokevirtual #20                 // Method java/lang/Object.getClass:()Ljava/lang/Class;
      18: invokevirtual #33                 // Method java/lang/Class.getSimpleName:()Ljava/lang/String;
      21: invokevirtual #34                 // Method java/lang/StringBuilder.append:(Ljava/lang/String;)Ljava/lang/StringBuilder;
      24: ldc           #35                 // String @
      26: invokevirtual #34                 // Method java/lang/StringBuilder.append:(Ljava/lang/String;)Ljava/lang/StringBuilder;
      29: aload_0
      30: invokestatic  #36                 // Method java/lang/System.identityHashCode:(Ljava/lang/Object;)I
      33: invokevirtual #37                 // Method java/lang/StringBuilder.append:(I)Ljava/lang/StringBuilder;
      36: invokevirtual #38                 // Method java/lang/StringBuilder.toString:()Ljava/lang/String;
      39: areturn

  public static java.lang.String simpleClassName(java.lang.Class<?>);
    Code:
       0: aload_0
       1: ifnonnull     14
       4: new           #39                 // class java/lang/NullPointerException
       7: dup
       8: ldc           #40                 // String clazz
      10: invokespecial #41                 // Method java/lang/NullPointerException."<init>":(Ljava/lang/String;)V
      13: athrow
      14: aload_0
      15: invokevirtual #6                  // Method java/lang/Class.getName:()Ljava/lang/String;
      18: astore_1
      19: aload_1
      20: bipush        46
      22: invokevirtual #42                 // Method java/lang/String.lastIndexOf:(I)I
      25: istore_2
      26: iload_2
      27: iconst_m1
      28: if_icmple     39
      31: aload_1
      32: iload_2
      33: iconst_1
      34: iadd
      35: invokevirtual #25                 // Method java/lang/String.substring:(I)Ljava/lang/String;
      38: areturn
      39: aload_1
      40: areturn

  public static boolean isPrimitive(java.lang.Class<?>);
    Code:
       0: aload_0
       1: ifnull        22
       4: aload_0
       5: invokevirtual #43                 // Method java/lang/Class.isPrimitive:()Z
       8: ifne          18
      11: aload_0
      12: invokestatic  #44                 // Method isSimpleType:(Ljava/lang/Class;)Z
      15: ifeq          22
      18: iconst_1
      19: goto          23
      22: iconst_0
      23: ireturn

  public static boolean isSimpleType(java.lang.Class<?>);
    Code:
       0: getstatic     #45                 // Field SIMPLE_TYPES:Ljava/util/Set;
       3: aload_0
       4: invokeinterface #46,  2           // InterfaceMethod java/util/Set.contains:(Ljava/lang/Object;)Z
       9: ireturn

  public static java.lang.Object convertPrimitive(java.lang.Class<?>, java.lang.String);
    Code:
       0: invokestatic  #47                 // Method org/apache/dubbo/rpc/model/FrameworkModel.defaultModel:()Lorg/apache/dubbo/rpc/model/FrameworkModel;
       3: aload_0
       4: aload_1
       5: invokestatic  #48                 // Method convertPrimitive:(Lorg/apache/dubbo/rpc/model/FrameworkModel;Ljava/lang/Class;Ljava/lang/String;)Ljava/lang/Object;
       8: areturn

  public static java.lang.Object convertPrimitive(org.apache.dubbo.rpc.model.FrameworkModel, java.lang.Class<?>, java.lang.String);
    Code:
       0: aload_2
       1: invokestatic  #49                 // Method org/apache/dubbo/common/utils/StringUtils.isEmpty:(Ljava/lang/String;)Z
       4: ifeq          9
       7: aconst_null
       8: areturn
       9: getstatic     #50                 // Field WRAPPER_PRIMITIVE_TYPE_MAP:Ljava/util/Map;
      12: aload_1
      13: aload_1
      14: invokeinterface #51,  3           // InterfaceMethod java/util/Map.getOrDefault:(Ljava/lang/Object;Ljava/lang/Object;)Ljava/lang/Object;
      19: checkcast     #29                 // class java/lang/Class
      22: astore_3
      23: aconst_null
      24: astore        4
      26: aload_0
      27: invokevirtual #52                 // Method org/apache/dubbo/rpc/model/FrameworkModel.getBeanFactory:()Lorg/apache/dubbo/common/beans/factory/ScopeBeanFactory;
      30: ldc           #53                 // class org/apache/dubbo/common/convert/ConverterUtil
      32: invokevirtual #54                 // Method org/apache/dubbo/common/beans/factory/ScopeBeanFactory.getBean:(Ljava/lang/Class;)Ljava/lang/Object;
      35: checkcast     #53                 // class org/apache/dubbo/common/convert/ConverterUtil
      38: aload_2
      39: aload_3
      40: invokevirtual #55                 // Method org/apache/dubbo/common/convert/ConverterUtil.convertIfPossible:(Ljava/lang/Object;Ljava/lang/Class;)Ljava/lang/Object;
      43: astore        4
      45: goto          50
      48: astore        5
      50: aload         4
      52: areturn
    Exception table:
       from    to  target type
          26    45    48   Class java/lang/Exception

  public static boolean isTypeMatch(java.lang.Class<?>, java.lang.String);
    Code:
       0: aload_0
       1: getstatic     #56                 // Field java/lang/Boolean.TYPE:Ljava/lang/Class;
       4: if_acmpeq     13
       7: aload_0
       8: ldc           #57                 // class java/lang/Boolean
      10: if_acmpne     33
      13: ldc           #58                 // String true
      15: aload_1
      16: invokevirtual #59                 // Method java/lang/String.equals:(Ljava/lang/Object;)Z
      19: ifne          33
      22: ldc           #60                 // String false
      24: aload_1
      25: invokevirtual #59                 // Method java/lang/String.equals:(Ljava/lang/Object;)Z
      28: ifne          33
      31: iconst_0
      32: ireturn
      33: iconst_1
      34: ireturn

  public static java.util.Set<java.lang.Class<?>> getAllSuperClasses(java.lang.Class<?>, java.util.function.Predicate<java.lang.Class<?>>...);
    Code:
       0: new           #61                 // class java/util/LinkedHashSet
       3: dup
       4: invokespecial #62                 // Method java/util/LinkedHashSet."<init>":()V
       7: astore_2
       8: aload_0
       9: invokevirtual #63                 // Method java/lang/Class.getSuperclass:()Ljava/lang/Class;
      12: astore_3
      13: aload_3
      14: ifnull        33
      17: aload_2
      18: aload_3
      19: invokeinterface #64,  2           // InterfaceMethod java/util/Set.add:(Ljava/lang/Object;)Z
      24: pop
      25: aload_3
      26: invokevirtual #63                 // Method java/lang/Class.getSuperclass:()Ljava/lang/Class;
      29: astore_3
      30: goto          13
      33: aload_2
      34: aload_1
      35: invokestatic  #65                 // InterfaceMethod org/apache/dubbo/common/function/Streams.filterAll:(Ljava/lang/Iterable;[Ljava/util/function/Predicate;)Ljava/lang/Iterable;
      38: checkcast     #66                 // class java/util/Set
      41: invokestatic  #67                 // Method java/util/Collections.unmodifiableSet:(Ljava/util/Set;)Ljava/util/Set;
      44: areturn

  public static java.util.Set<java.lang.Class<?>> getAllInterfaces(java.lang.Class<?>, java.util.function.Predicate<java.lang.Class<?>>...);
    Code:
       0: aload_0
       1: ifnull        11
       4: aload_0
       5: invokevirtual #43                 // Method java/lang/Class.isPrimitive:()Z
       8: ifeq          15
      11: invokestatic  #68                 // Method java/util/Collections.emptySet:()Ljava/util/Set;
      14: areturn
      15: new           #61                 // class java/util/LinkedHashSet
      18: dup
      19: invokespecial #62                 // Method java/util/LinkedHashSet."<init>":()V
      22: astore_2
      23: new           #61                 // class java/util/LinkedHashSet
      26: dup
      27: invokespecial #62                 // Method java/util/LinkedHashSet."<init>":()V
      30: astore_3
      31: new           #69                 // class java/util/LinkedList
      34: dup
      35: invokespecial #70                 // Method java/util/LinkedList."<init>":()V
      38: astore        4
      40: aload_3
      41: aload_0
      42: invokeinterface #64,  2           // InterfaceMethod java/util/Set.add:(Ljava/lang/Object;)Z
      47: pop
      48: aload_0
      49: astore        5
      51: aload         5
      53: ifnull        167
      56: aload         5
      58: invokevirtual #71                 // Method java/lang/Class.getInterfaces:()[Ljava/lang/Class;
      61: astore        6
      63: aload         6
      65: invokestatic  #72                 // Method org/apache/dubbo/common/utils/ArrayUtils.isNotEmpty:([Ljava/lang/Object;)Z
      68: ifeq          105
      71: aload         6
      73: invokestatic  #73                 // Method java/util/Arrays.stream:([Ljava/lang/Object;)Ljava/util/stream/Stream;
      76: aload_3
      77: dup
      78: invokevirtual #20                 // Method java/lang/Object.getClass:()Ljava/lang/Class;
      81: pop
      82: invokedynamic #74,  0             // InvokeDynamic #0:test:(Ljava/util/Set;)Ljava/util/function/Predicate;
      87: invokeinterface #75,  2           // InterfaceMethod java/util/stream/Stream.filter:(Ljava/util/function/Predicate;)Ljava/util/stream/Stream;
      92: aload_2
      93: aload         4
      95: invokedynamic #76,  0             // InvokeDynamic #1:accept:(Ljava/util/Set;Ljava/util/Queue;)Ljava/util/function/Consumer;
     100: invokeinterface #77,  2           // InterfaceMethod java/util/stream/Stream.forEach:(Ljava/util/function/Consumer;)V
     105: aload         5
     107: iconst_0
     108: anewarray     #78                 // class java/util/function/Predicate
     111: invokestatic  #79                 // Method getAllSuperClasses:(Ljava/lang/Class;[Ljava/util/function/Predicate;)Ljava/util/Set;
     114: invokeinterface #80,  1           // InterfaceMethod java/util/Set.stream:()Ljava/util/stream/Stream;
     119: aload_3
     120: dup
     121: invokevirtual #20                 // Method java/lang/Object.getClass:()Ljava/lang/Class;
     124: pop
     125: invokedynamic #74,  0             // InvokeDynamic #0:test:(Ljava/util/Set;)Ljava/util/function/Predicate;
     130: invokeinterface #75,  2           // InterfaceMethod java/util/stream/Stream.filter:(Ljava/util/function/Predicate;)Ljava/util/stream/Stream;
     135: aload         4
     137: dup
     138: invokevirtual #20                 // Method java/lang/Object.getClass:()Ljava/lang/Class;
     141: pop
     142: invokedynamic #81,  0             // InvokeDynamic #2:accept:(Ljava/util/Queue;)Ljava/util/function/Consumer;
     147: invokeinterface #77,  2           // InterfaceMethod java/util/stream/Stream.forEach:(Ljava/util/function/Consumer;)V
     152: aload         4
     154: invokeinterface #82,  1           // InterfaceMethod java/util/Queue.poll:()Ljava/lang/Object;
     159: checkcast     #29                 // class java/lang/Class
     162: astore        5
     164: goto          51
     167: aload_2
     168: aload_1
     169: invokestatic  #65                 // InterfaceMethod org/apache/dubbo/common/function/Streams.filterAll:(Ljava/lang/Iterable;[Ljava/util/function/Predicate;)Ljava/lang/Iterable;
     172: checkcast     #66                 // class java/util/Set
     175: areturn

  public static java.util.Set<java.lang.Class<?>> getAllInheritedTypes(java.lang.Class<?>, java.util.function.Predicate<java.lang.Class<?>>...);
    Code:
       0: new           #61                 // class java/util/LinkedHashSet
       3: dup
       4: aload_0
       5: aload_1
       6: invokestatic  #79                 // Method getAllSuperClasses:(Ljava/lang/Class;[Ljava/util/function/Predicate;)Ljava/util/Set;
       9: invokespecial #83                 // Method java/util/LinkedHashSet."<init>":(Ljava/util/Collection;)V
      12: astore_2
      13: aload_2
      14: aload_0
      15: aload_1
      16: invokestatic  #84                 // Method getAllInterfaces:(Ljava/lang/Class;[Ljava/util/function/Predicate;)Ljava/util/Set;
      19: invokeinterface #85,  2           // InterfaceMethod java/util/Set.addAll:(Ljava/util/Collection;)Z
      24: pop
      25: aload_2
      26: invokestatic  #67                 // Method java/util/Collections.unmodifiableSet:(Ljava/util/Set;)Ljava/util/Set;
      29: areturn

  public static boolean isAssignableFrom(java.lang.Class<?>, java.lang.Class<?>);
    Code:
       0: aload_0
       1: ifnull        8
       4: aload_1
       5: ifnonnull     10
       8: iconst_0
       9: ireturn
      10: aload_0
      11: aload_1
      12: invokestatic  #86                 // Method java/util/Objects.equals:(Ljava/lang/Object;Ljava/lang/Object;)Z
      15: ifeq          20
      18: iconst_1
      19: ireturn
      20: aload_0
      21: aload_1
      22: invokevirtual #87                 // Method java/lang/Class.isAssignableFrom:(Ljava/lang/Class;)Z
      25: ireturn

  public static boolean isPresent(java.lang.String, java.lang.ClassLoader);
    Code:
       0: aload_0
       1: aload_1
       2: invokestatic  #4                  // Method forName:(Ljava/lang/String;Ljava/lang/ClassLoader;)Ljava/lang/Class;
       5: pop
       6: goto          12
       9: astore_2
      10: iconst_0
      11: ireturn
      12: iconst_1
      13: ireturn
    Exception table:
       from    to  target type
           0     6     9   Class java/lang/Exception

  public static java.lang.Class<?> resolveClass(java.lang.String, java.lang.ClassLoader);
    Code:
       0: aconst_null
       1: astore_2
       2: aload_0
       3: aload_1
       4: invokestatic  #4                  // Method forName:(Ljava/lang/String;Ljava/lang/ClassLoader;)Ljava/lang/Class;
       7: astore_2
       8: goto          12
      11: astore_3
      12: aload_2
      13: areturn
    Exception table:
       from    to  target type
           2     8    11   Class java/lang/Exception

  public static boolean isGenericClass(java.lang.Class<?>);
    Code:
       0: aload_0
       1: ifnull        27
       4: getstatic     #88                 // Field java/lang/Void.TYPE:Ljava/lang/Class;
       7: aload_0
       8: invokevirtual #89                 // Method java/lang/Object.equals:(Ljava/lang/Object;)Z
      11: ifne          27
      14: ldc           #90                 // class java/lang/Void
      16: aload_0
      17: invokevirtual #89                 // Method java/lang/Object.equals:(Ljava/lang/Object;)Z
      20: ifne          27
      23: iconst_1
      24: goto          28
      27: iconst_0
      28: ireturn

  public static boolean hasMethods(java.lang.reflect.Method[]);
    Code:
       0: aload_0
       1: ifnull        9
       4: aload_0
       5: arraylength
       6: ifne          11
       9: iconst_0
      10: ireturn
      11: aload_0
      12: astore_1
      13: aload_1
      14: arraylength
      15: istore_2
      16: iconst_0
      17: istore_3
      18: iload_3
      19: iload_2
      20: if_icmpge     46
      23: aload_1
      24: iload_3
      25: aaload
      26: astore        4
      28: aload         4
      30: invokevirtual #91                 // Method java/lang/reflect/Method.getDeclaringClass:()Ljava/lang/Class;
      33: ldc           #92                 // class java/lang/Object
      35: if_acmpeq     40
      38: iconst_1
      39: ireturn
      40: iinc          3, 1
      43: goto          18
      46: iconst_0
      47: ireturn

  public static java.lang.String[] getMethodNames(java.lang.Class<?>);
    Code:
       0: aload_0
       1: ldc           #92                 // class java/lang/Object
       3: if_acmpne     10
       6: getstatic     #93                 // Field OBJECT_METHODS:[Ljava/lang/String;
       9: areturn
      10: aload_0
      11: invokevirtual #94                 // Method java/lang/Class.getMethods:()[Ljava/lang/reflect/Method;
      14: invokestatic  #73                 // Method java/util/Arrays.stream:([Ljava/lang/Object;)Ljava/util/stream/Stream;
      17: invokestatic  #95                 // Method java/util/stream/Collectors.toList:()Ljava/util/stream/Collector;
      20: invokeinterface #96,  2           // InterfaceMethod java/util/stream/Stream.collect:(Ljava/util/stream/Collector;)Ljava/lang/Object;
      25: checkcast     #97                 // class java/util/List
      28: iconst_0
      29: anewarray     #98                 // class java/lang/reflect/Method
      32: invokeinterface #99,  2           // InterfaceMethod java/util/List.toArray:([Ljava/lang/Object;)[Ljava/lang/Object;
      37: checkcast     #100                // class "[Ljava/lang/reflect/Method;"
      40: astore_1
      41: new           #101                // class java/util/ArrayList
      44: dup
      45: invokespecial #102                // Method java/util/ArrayList."<init>":()V
      48: astore_2
      49: aload_1
      50: invokestatic  #103                // Method hasMethods:([Ljava/lang/reflect/Method;)Z
      53: istore_3
      54: iload_3
      55: ifeq          118
      58: aload_1
      59: astore        4
      61: aload         4
      63: arraylength
      64: istore        5
      66: iconst_0
      67: istore        6
      69: iload         6
      71: iload         5
      73: if_icmpge     118
      76: aload         4
      78: iload         6
      80: aaload
      81: astore        7
      83: aload         7
      85: invokevirtual #91                 // Method java/lang/reflect/Method.getDeclaringClass:()Ljava/lang/Class;
      88: ldc           #92                 // class java/lang/Object
      90: if_acmpne     96
      93: goto          112
      96: aload         7
      98: invokevirtual #104                // Method java/lang/reflect/Method.getName:()Ljava/lang/String;
     101: astore        8
     103: aload_2
     104: aload         8
     106: invokeinterface #105,  2          // InterfaceMethod java/util/List.add:(Ljava/lang/Object;)Z
     111: pop
     112: iinc          6, 1
     115: goto          69
     118: aload_2
     119: iconst_0
     120: anewarray     #106                // class java/lang/String
     123: invokeinterface #99,  2           // InterfaceMethod java/util/List.toArray:([Ljava/lang/Object;)[Ljava/lang/Object;
     128: checkcast     #107                // class "[Ljava/lang/String;"
     131: areturn

  public static boolean isMatch(java.lang.Class<?>, java.lang.Class<?>);
    Code:
       0: aload_0
       1: aload_1
       2: if_acmpne     7
       5: iconst_1
       6: ireturn
       7: aload_0
       8: invokevirtual #43                 // Method java/lang/Class.isPrimitive:()Z
      11: ifeq          23
      14: aload_0
      15: aload_1
      16: invokestatic  #108                // Method matchPrimitive:(Ljava/lang/Class;Ljava/lang/Class;)Z
      19: istore_2
      20: goto          45
      23: aload_1
      24: invokevirtual #43                 // Method java/lang/Class.isPrimitive:()Z
      27: ifeq          39
      30: aload_1
      31: aload_0
      32: invokestatic  #108                // Method matchPrimitive:(Ljava/lang/Class;Ljava/lang/Class;)Z
      35: istore_2
      36: goto          45
      39: aload_1
      40: aload_0
      41: invokevirtual #87                 // Method java/lang/Class.isAssignableFrom:(Ljava/lang/Class;)Z
      44: istore_2
      45: iload_2
      46: ireturn

  private static boolean matchPrimitive(java.lang.Class<?>, java.lang.Class<?>);
    Code:
       0: aload_0
       1: getstatic     #56                 // Field java/lang/Boolean.TYPE:Ljava/lang/Class;
       4: if_acmpne     19
       7: aload_1
       8: ldc           #57                 // class java/lang/Boolean
      10: if_acmpne     17
      13: iconst_1
      14: goto          18
      17: iconst_0
      18: ireturn
      19: aload_0
      20: getstatic     #109                // Field java/lang/Byte.TYPE:Ljava/lang/Class;
      23: if_acmpne     38
      26: aload_1
      27: ldc           #110                // class java/lang/Byte
      29: if_acmpne     36
      32: iconst_1
      33: goto          37
      36: iconst_0
      37: ireturn
      38: aload_0
      39: getstatic     #111                // Field java/lang/Character.TYPE:Ljava/lang/Class;
      42: if_acmpne     57
      45: aload_1
      46: ldc           #112                // class java/lang/Character
      48: if_acmpne     55
      51: iconst_1
      52: goto          56
      55: iconst_0
      56: ireturn
      57: aload_0
      58: getstatic     #113                // Field java/lang/Short.TYPE:Ljava/lang/Class;
      61: if_acmpne     76
      64: aload_1
      65: ldc           #114                // class java/lang/Short
      67: if_acmpne     74
      70: iconst_1
      71: goto          75
      74: iconst_0
      75: ireturn
      76: aload_0
      77: getstatic     #115                // Field java/lang/Integer.TYPE:Ljava/lang/Class;
      80: if_acmpne     95
      83: aload_1
      84: ldc           #116                // class java/lang/Integer
      86: if_acmpne     93
      89: iconst_1
      90: goto          94
      93: iconst_0
      94: ireturn
      95: aload_0
      96: getstatic     #117                // Field java/lang/Long.TYPE:Ljava/lang/Class;
      99: if_acmpne     114
     102: aload_1
     103: ldc           #118                // class java/lang/Long
     105: if_acmpne     112
     108: iconst_1
     109: goto          113
     112: iconst_0
     113: ireturn
     114: aload_0
     115: getstatic     #119                // Field java/lang/Float.TYPE:Ljava/lang/Class;
     118: if_acmpne     133
     121: aload_1
     122: ldc           #120                // class java/lang/Float
     124: if_acmpne     131
     127: iconst_1
     128: goto          132
     131: iconst_0
     132: ireturn
     133: aload_0
     134: getstatic     #121                // Field java/lang/Double.TYPE:Ljava/lang/Class;
     137: if_acmpne     152
     140: aload_1
     141: ldc           #122                // class java/lang/Double
     143: if_acmpne     150
     146: iconst_1
     147: goto          151
     150: iconst_0
     151: ireturn
     152: aload_0
     153: getstatic     #88                 // Field java/lang/Void.TYPE:Ljava/lang/Class;
     156: if_acmpne     171
     159: aload_1
     160: ldc           #90                 // class java/lang/Void
     162: if_acmpne     169
     165: iconst_1
     166: goto          170
     169: iconst_0
     170: ireturn
     171: iconst_0
     172: ireturn

  public static java.lang.String[] getDeclaredMethodNames(java.lang.Class<?>);
    Code:
       0: aload_0
       1: ldc           #92                 // class java/lang/Object
       3: if_acmpne     10
       6: getstatic     #93                 // Field OBJECT_METHODS:[Ljava/lang/String;
       9: areturn
      10: aload_0
      11: invokevirtual #94                 // Method java/lang/Class.getMethods:()[Ljava/lang/reflect/Method;
      14: invokestatic  #73                 // Method java/util/Arrays.stream:([Ljava/lang/Object;)Ljava/util/stream/Stream;
      17: invokestatic  #95                 // Method java/util/stream/Collectors.toList:()Ljava/util/stream/Collector;
      20: invokeinterface #96,  2           // InterfaceMethod java/util/stream/Stream.collect:(Ljava/util/stream/Collector;)Ljava/lang/Object;
      25: checkcast     #97                 // class java/util/List
      28: iconst_0
      29: anewarray     #98                 // class java/lang/reflect/Method
      32: invokeinterface #99,  2           // InterfaceMethod java/util/List.toArray:([Ljava/lang/Object;)[Ljava/lang/Object;
      37: checkcast     #100                // class "[Ljava/lang/reflect/Method;"
      40: astore_1
      41: new           #101                // class java/util/ArrayList
      44: dup
      45: invokespecial #102                // Method java/util/ArrayList."<init>":()V
      48: astore_2
      49: aload_1
      50: invokestatic  #103                // Method hasMethods:([Ljava/lang/reflect/Method;)Z
      53: istore_3
      54: iload_3
      55: ifeq          127
      58: aload_1
      59: astore        4
      61: aload         4
      63: arraylength
      64: istore        5
      66: iconst_0
      67: istore        6
      69: iload         6
      71: iload         5
      73: if_icmpge     127
      76: aload         4
      78: iload         6
      80: aaload
      81: astore        7
      83: aload         7
      85: invokevirtual #91                 // Method java/lang/reflect/Method.getDeclaringClass:()Ljava/lang/Class;
      88: ldc           #92                 // class java/lang/Object
      90: if_acmpne     96
      93: goto          121
      96: aload         7
      98: invokevirtual #104                // Method java/lang/reflect/Method.getName:()Ljava/lang/String;
     101: astore        8
     103: aload         7
     105: invokevirtual #91                 // Method java/lang/reflect/Method.getDeclaringClass:()Ljava/lang/Class;
     108: aload_0
     109: if_acmpne     121
     112: aload_2
     113: aload         8
     115: invokeinterface #105,  2          // InterfaceMethod java/util/List.add:(Ljava/lang/Object;)Z
     120: pop
     121: iinc          6, 1
     124: goto          69
     127: aload_2
     128: invokestatic  #123                // InterfaceMethod java/util/Comparator.naturalOrder:()Ljava/util/Comparator;
     131: invokeinterface #124,  2          // InterfaceMethod java/util/List.sort:(Ljava/util/Comparator;)V
     136: aload_2
     137: iconst_0
     138: anewarray     #106                // class java/lang/String
     141: invokeinterface #99,  2           // InterfaceMethod java/util/List.toArray:([Ljava/lang/Object;)[Ljava/lang/Object;
     146: checkcast     #107                // class "[Ljava/lang/String;"
     149: areturn

  private static void lambda$getAllInterfaces$0(java.util.Set, java.util.Queue, java.lang.Class);
    Code:
       0: aload_0
       1: aload_2
       2: invokeinterface #64,  2           // InterfaceMethod java/util/Set.add:(Ljava/lang/Object;)Z
       7: pop
       8: aload_1
       9: aload_2
      10: invokeinterface #125,  2          // InterfaceMethod java/util/Queue.add:(Ljava/lang/Object;)Z
      15: pop
      16: return

  static {};
    Code:
       0: bipush        14
       2: anewarray     #29                 // class java/lang/Class
       5: dup
       6: iconst_0
       7: ldc           #90                 // class java/lang/Void
       9: aastore
      10: dup
      11: iconst_1
      12: ldc           #57                 // class java/lang/Boolean
      14: aastore
      15: dup
      16: iconst_2
      17: ldc           #112                // class java/lang/Character
      19: aastore
      20: dup
      21: iconst_3
      22: ldc           #110                // class java/lang/Byte
      24: aastore
      25: dup
      26: iconst_4
      27: ldc           #114                // class java/lang/Short
      29: aastore
      30: dup
      31: iconst_5
      32: ldc           #116                // class java/lang/Integer
      34: aastore
      35: dup
      36: bipush        6
      38: ldc           #118                // class java/lang/Long
      40: aastore
      41: dup
      42: bipush        7
      44: ldc           #120                // class java/lang/Float
      46: aastore
      47: dup
      48: bipush        8
      50: ldc           #122                // class java/lang/Double
      52: aastore
      53: dup
      54: bipush        9
      56: ldc           #106                // class java/lang/String
      58: aastore
      59: dup
      60: bipush        10
      62: ldc           #126                // class java/math/BigDecimal
      64: aastore
      65: dup
      66: bipush        11
      68: ldc           #127                // class java/math/BigInteger
      70: aastore
      71: dup
      72: bipush        12
      74: ldc           #128                // class java/util/Date
      76: aastore
      77: dup
      78: bipush        13
      80: ldc           #92                 // class java/lang/Object
      82: aastore
      83: invokestatic  #129                // Method org/apache/dubbo/common/utils/CollectionUtils.ofSet:([Ljava/lang/Object;)Ljava/util/Set;
      86: putstatic     #45                 // Field SIMPLE_TYPES:Ljava/util/Set;
      89: new           #130                // class java/util/HashMap
      92: dup
      93: bipush        32
      95: invokespecial #131                // Method java/util/HashMap."<init>":(I)V
      98: putstatic     #27                 // Field PRIMITIVE_TYPE_NAME_MAP:Ljava/util/Map;
     101: new           #130                // class java/util/HashMap
     104: dup
     105: bipush        16
     107: invokespecial #131                // Method java/util/HashMap."<init>":(I)V
     110: putstatic     #132                // Field PRIMITIVE_WRAPPER_TYPE_MAP:Ljava/util/Map;
     113: getstatic     #132                // Field PRIMITIVE_WRAPPER_TYPE_MAP:Ljava/util/Map;
     116: ldc           #57                 // class java/lang/Boolean
     118: getstatic     #56                 // Field java/lang/Boolean.TYPE:Ljava/lang/Class;
     121: invokeinterface #133,  3          // InterfaceMethod java/util/Map.put:(Ljava/lang/Object;Ljava/lang/Object;)Ljava/lang/Object;
     126: pop
     127: getstatic     #132                // Field PRIMITIVE_WRAPPER_TYPE_MAP:Ljava/util/Map;
     130: ldc           #110                // class java/lang/Byte
     132: getstatic     #109                // Field java/lang/Byte.TYPE:Ljava/lang/Class;
     135: invokeinterface #133,  3          // InterfaceMethod java/util/Map.put:(Ljava/lang/Object;Ljava/lang/Object;)Ljava/lang/Object;
     140: pop
     141: getstatic     #132                // Field PRIMITIVE_WRAPPER_TYPE_MAP:Ljava/util/Map;
     144: ldc           #112                // class java/lang/Character
     146: getstatic     #111                // Field java/lang/Character.TYPE:Ljava/lang/Class;
     149: invokeinterface #133,  3          // InterfaceMethod java/util/Map.put:(Ljava/lang/Object;Ljava/lang/Object;)Ljava/lang/Object;
     154: pop
     155: getstatic     #132                // Field PRIMITIVE_WRAPPER_TYPE_MAP:Ljava/util/Map;
     158: ldc           #122                // class java/lang/Double
     160: getstatic     #121                // Field java/lang/Double.TYPE:Ljava/lang/Class;
     163: invokeinterface #133,  3          // InterfaceMethod java/util/Map.put:(Ljava/lang/Object;Ljava/lang/Object;)Ljava/lang/Object;
     168: pop
     169: getstatic     #132                // Field PRIMITIVE_WRAPPER_TYPE_MAP:Ljava/util/Map;
     172: ldc           #120                // class java/lang/Float
     174: getstatic     #119                // Field java/lang/Float.TYPE:Ljava/lang/Class;
     177: invokeinterface #133,  3          // InterfaceMethod java/util/Map.put:(Ljava/lang/Object;Ljava/lang/Object;)Ljava/lang/Object;
     182: pop
     183: getstatic     #132                // Field PRIMITIVE_WRAPPER_TYPE_MAP:Ljava/util/Map;
     186: ldc           #116                // class java/lang/Integer
     188: getstatic     #115                // Field java/lang/Integer.TYPE:Ljava/lang/Class;
     191: invokeinterface #133,  3          // InterfaceMethod java/util/Map.put:(Ljava/lang/Object;Ljava/lang/Object;)Ljava/lang/Object;
     196: pop
     197: getstatic     #132                // Field PRIMITIVE_WRAPPER_TYPE_MAP:Ljava/util/Map;
     200: ldc           #118                // class java/lang/Long
     202: getstatic     #117                // Field java/lang/Long.TYPE:Ljava/lang/Class;
     205: invokeinterface #133,  3          // InterfaceMethod java/util/Map.put:(Ljava/lang/Object;Ljava/lang/Object;)Ljava/lang/Object;
     210: pop
     211: getstatic     #132                // Field PRIMITIVE_WRAPPER_TYPE_MAP:Ljava/util/Map;
     214: ldc           #114                // class java/lang/Short
     216: getstatic     #113                // Field java/lang/Short.TYPE:Ljava/lang/Class;
     219: invokeinterface #133,  3          // InterfaceMethod java/util/Map.put:(Ljava/lang/Object;Ljava/lang/Object;)Ljava/lang/Object;
     224: pop
     225: getstatic     #132                // Field PRIMITIVE_WRAPPER_TYPE_MAP:Ljava/util/Map;
     228: ldc           #90                 // class java/lang/Void
     230: getstatic     #88                 // Field java/lang/Void.TYPE:Ljava/lang/Class;
     233: invokeinterface #133,  3          // InterfaceMethod java/util/Map.put:(Ljava/lang/Object;Ljava/lang/Object;)Ljava/lang/Object;
     238: pop
     239: new           #134                // class java/util/HashSet
     242: dup
     243: bipush        32
     245: invokespecial #135                // Method java/util/HashSet."<init>":(I)V
     248: astore_0
     249: aload_0
     250: getstatic     #132                // Field PRIMITIVE_WRAPPER_TYPE_MAP:Ljava/util/Map;
     253: invokeinterface #136,  1          // InterfaceMethod java/util/Map.values:()Ljava/util/Collection;
     258: invokeinterface #85,  2           // InterfaceMethod java/util/Set.addAll:(Ljava/util/Collection;)Z
     263: pop
     264: aload_0
     265: bipush        8
     267: anewarray     #29                 // class java/lang/Class
     270: dup
     271: iconst_0
     272: ldc           #137                // class "[Z"
     274: aastore
     275: dup
     276: iconst_1
     277: ldc           #138                // class "[B"
     279: aastore
     280: dup
     281: iconst_2
     282: ldc           #139                // class "[C"
     284: aastore
     285: dup
     286: iconst_3
     287: ldc           #140                // class "[D"
     289: aastore
     290: dup
     291: iconst_4
     292: ldc           #141                // class "[F"
     294: aastore
     295: dup
     296: iconst_5
     297: ldc           #142                // class "[I"
     299: aastore
     300: dup
     301: bipush        6
     303: ldc           #143                // class "[J"
     305: aastore
     306: dup
     307: bipush        7
     309: ldc           #144                // class "[S"
     311: aastore
     312: invokestatic  #145                // Method java/util/Arrays.asList:([Ljava/lang/Object;)Ljava/util/List;
     315: invokeinterface #85,  2           // InterfaceMethod java/util/Set.addAll:(Ljava/util/Collection;)Z
     320: pop
     321: aload_0
     322: invokeinterface #146,  1          // InterfaceMethod java/util/Set.iterator:()Ljava/util/Iterator;
     327: astore_1
     328: aload_1
     329: invokeinterface #147,  1          // InterfaceMethod java/util/Iterator.hasNext:()Z
     334: ifeq          364
     337: aload_1
     338: invokeinterface #148,  1          // InterfaceMethod java/util/Iterator.next:()Ljava/lang/Object;
     343: checkcast     #29                 // class java/lang/Class
     346: astore_2
     347: getstatic     #27                 // Field PRIMITIVE_TYPE_NAME_MAP:Ljava/util/Map;
     350: aload_2
     351: invokevirtual #6                  // Method java/lang/Class.getName:()Ljava/lang/String;
     354: aload_2
     355: invokeinterface #133,  3          // InterfaceMethod java/util/Map.put:(Ljava/lang/Object;Ljava/lang/Object;)Ljava/lang/Object;
     360: pop
     361: goto          328
     364: getstatic     #132                // Field PRIMITIVE_WRAPPER_TYPE_MAP:Ljava/util/Map;
     367: invokestatic  #149                // Method org/apache/dubbo/common/utils/CollectionUtils.flip:(Ljava/util/Map;)Ljava/util/Map;
     370: putstatic     #50                 // Field WRAPPER_PRIMITIVE_TYPE_MAP:Ljava/util/Map;
     373: iconst_4
     374: anewarray     #106                // class java/lang/String
     377: dup
     378: iconst_0
     379: ldc           #150                // String getClass
     381: aastore
     382: dup
     383: iconst_1
     384: ldc           #151                // String hashCode
     386: aastore
     387: dup
     388: iconst_2
     389: ldc           #152                // String toString
     391: aastore
     392: dup
     393: iconst_3
     394: ldc           #153                // String equals
     396: aastore
     397: putstatic     #93                 // Field OBJECT_METHODS:[Ljava/lang/String;
     400: return
}
