Compiled from "ClassHelper.java"
public class org.apache.dubbo.common.utils.ClassHelper {
  public org.apache.dubbo.common.utils.ClassHelper();
    Code:
       0: aload_0
       1: invokespecial #1                  // Method java/lang/Object."<init>":()V
       4: return

  public static java.lang.Class<?> forNameWithThreadContextClassLoader(java.lang.String) throws java.lang.ClassNotFoundException;
    Code:
       0: aload_0
       1: invokestatic  #2                  // Method java/lang/Thread.currentThread:()Ljava/lang/Thread;
       4: invokevirtual #3                  // Method java/lang/Thread.getContextClassLoader:()Ljava/lang/ClassLoader;
       7: invokestatic  #4                  // Method org/apache/dubbo/common/utils/ClassUtils.forName:(Ljava/lang/String;Ljava/lang/ClassLoader;)Ljava/lang/Class;
      10: areturn

  public static java.lang.Class<?> forNameWithCallerClassLoader(java.lang.String, java.lang.Class<?>) throws java.lang.ClassNotFoundException;
    Code:
       0: aload_0
       1: aload_1
       2: invokevirtual #5                  // Method java/lang/Class.getClassLoader:()Ljava/lang/ClassLoader;
       5: invokestatic  #4                  // Method org/apache/dubbo/common/utils/ClassUtils.forName:(Ljava/lang/String;Ljava/lang/ClassLoader;)Ljava/lang/Class;
       8: areturn

  public static java.lang.ClassLoader getCallerClassLoader(java.lang.Class<?>);
    Code:
       0: aload_0
       1: invokevirtual #5                  // Method java/lang/Class.getClassLoader:()Ljava/lang/ClassLoader;
       4: areturn

  public static java.lang.ClassLoader getClassLoader(java.lang.Class<?>);
    Code:
       0: aload_0
       1: invokestatic  #6                  // Method org/apache/dubbo/common/utils/ClassUtils.getClassLoader:(Ljava/lang/Class;)Ljava/lang/ClassLoader;
       4: areturn

  public static java.lang.ClassLoader getClassLoader();
    Code:
       0: ldc           #7                  // class org/apache/dubbo/common/utils/ClassHelper
       2: invokestatic  #8                  // Method getClassLoader:(Ljava/lang/Class;)Ljava/lang/ClassLoader;
       5: areturn

  public static java.lang.Class<?> forName(java.lang.String) throws java.lang.ClassNotFoundException;
    Code:
       0: aload_0
       1: invokestatic  #9                  // Method getClassLoader:()Ljava/lang/ClassLoader;
       4: invokestatic  #10                 // Method forName:(Ljava/lang/String;Ljava/lang/ClassLoader;)Ljava/lang/Class;
       7: areturn

  public static java.lang.Class<?> forName(java.lang.String, java.lang.ClassLoader) throws java.lang.ClassNotFoundException, java.lang.LinkageError;
    Code:
       0: aload_0
       1: aload_1
       2: invokestatic  #4                  // Method org/apache/dubbo/common/utils/ClassUtils.forName:(Ljava/lang/String;Ljava/lang/ClassLoader;)Ljava/lang/Class;
       5: areturn

  public static java.lang.Class<?> resolvePrimitiveClassName(java.lang.String);
    Code:
       0: aload_0
       1: invokestatic  #11                 // Method org/apache/dubbo/common/utils/ClassUtils.resolvePrimitiveClassName:(Ljava/lang/String;)Ljava/lang/Class;
       4: areturn

  public static java.lang.String toShortString(java.lang.Object);
    Code:
       0: aload_0
       1: invokestatic  #12                 // Method org/apache/dubbo/common/utils/ClassUtils.toShortString:(Ljava/lang/Object;)Ljava/lang/String;
       4: areturn

  public static java.lang.String simpleClassName(java.lang.Class<?>);
    Code:
       0: aload_0
       1: invokestatic  #13                 // Method org/apache/dubbo/common/utils/ClassUtils.simpleClassName:(Ljava/lang/Class;)Ljava/lang/String;
       4: areturn

  public static boolean isSetter(java.lang.reflect.Method);
    Code:
       0: aload_0
       1: invokestatic  #14                 // InterfaceMethod org/apache/dubbo/common/utils/MethodUtils.isSetter:(Ljava/lang/reflect/Method;)Z
       4: ireturn

  public static boolean isGetter(java.lang.reflect.Method);
    Code:
       0: aload_0
       1: invokestatic  #15                 // InterfaceMethod org/apache/dubbo/common/utils/MethodUtils.isGetter:(Ljava/lang/reflect/Method;)Z
       4: ireturn

  public static boolean isPrimitive(java.lang.Class<?>);
    Code:
       0: aload_0
       1: invokestatic  #16                 // Method org/apache/dubbo/common/utils/ClassUtils.isPrimitive:(Ljava/lang/Class;)Z
       4: ireturn

  public static java.lang.Object convertPrimitive(java.lang.Class<?>, java.lang.String);
    Code:
       0: aload_0
       1: aload_1
       2: invokestatic  #17                 // Method org/apache/dubbo/common/utils/ClassUtils.convertPrimitive:(Ljava/lang/Class;Ljava/lang/String;)Ljava/lang/Object;
       5: areturn

  public static boolean isTypeMatch(java.lang.Class<?>, java.lang.String);
    Code:
       0: aload_0
       1: aload_1
       2: invokestatic  #18                 // Method org/apache/dubbo/common/utils/ClassUtils.isTypeMatch:(Ljava/lang/Class;Ljava/lang/String;)Z
       5: ireturn
}
