Compiled from "ConcurrentHashMapUtils.java"
public class org.apache.dubbo.common.utils.ConcurrentHashMapUtils {
  public org.apache.dubbo.common.utils.ConcurrentHashMapUtils();
    Code:
       0: aload_0
       1: invokespecial #1                  // Method java/lang/Object."<init>":()V
       4: return

  public static <K, V> V computeIfAbsent(java.util.concurrent.ConcurrentMap<K, V>, K, java.util.function.Function<? super K, ? extends V>);
    Code:
       0: aload_2
       1: invokestatic  #2                  // Method java/util/Objects.requireNonNull:(Ljava/lang/Object;)Ljava/lang/Object;
       4: pop
       5: getstatic     #3                  // Field org/apache/dubbo/common/utils/JRE.JAVA_8:Lorg/apache/dubbo/common/utils/JRE;
       8: invokevirtual #4                  // Method org/apache/dubbo/common/utils/JRE.isCurrentVersion:()Z
      11: ifeq          63
      14: aload_0
      15: aload_1
      16: invokeinterface #5,  2            // InterfaceMethod java/util/concurrent/ConcurrentMap.get:(Ljava/lang/Object;)Ljava/lang/Object;
      21: astore_3
      22: aconst_null
      23: aload_3
      24: if_acmpne     61
      27: aload_2
      28: aload_1
      29: invokeinterface #6,  2            // InterfaceMethod java/util/function/Function.apply:(Ljava/lang/Object;)Ljava/lang/Object;
      34: astore_3
      35: aconst_null
      36: aload_3
      37: if_acmpne     42
      40: aconst_null
      41: areturn
      42: aload_0
      43: aload_1
      44: aload_3
      45: invokeinterface #7,  3            // InterfaceMethod java/util/concurrent/ConcurrentMap.putIfAbsent:(Ljava/lang/Object;Ljava/lang/Object;)Ljava/lang/Object;
      50: astore        4
      52: aconst_null
      53: aload         4
      55: if_acmpeq     61
      58: aload         4
      60: areturn
      61: aload_3
      62: areturn
      63: aload_0
      64: aload_1
      65: aload_2
      66: invokeinterface #8,  3            // InterfaceMethod java/util/concurrent/ConcurrentMap.computeIfAbsent:(Ljava/lang/Object;Ljava/util/function/Function;)Ljava/lang/Object;
      71: areturn
}
