Compiled from "JRE.java"
public final class org.apache.dubbo.common.utils.JRE extends java.lang.Enum<org.apache.dubbo.common.utils.JRE> {
  public static final org.apache.dubbo.common.utils.JRE JAVA_8;

  public static final org.apache.dubbo.common.utils.JRE JAVA_9;

  public static final org.apache.dubbo.common.utils.JRE JAVA_10;

  public static final org.apache.dubbo.common.utils.JRE JAVA_11;

  public static final org.apache.dubbo.common.utils.JRE JAVA_12;

  public static final org.apache.dubbo.common.utils.JRE JAVA_13;

  public static final org.apache.dubbo.common.utils.JRE JAVA_14;

  public static final org.apache.dubbo.common.utils.JRE JAVA_15;

  public static final org.apache.dubbo.common.utils.JRE JAVA_16;

  public static final org.apache.dubbo.common.utils.JRE JAVA_17;

  public static final org.apache.dubbo.common.utils.JRE JAVA_18;

  public static final org.apache.dubbo.common.utils.JRE JAVA_19;

  public static final org.apache.dubbo.common.utils.JRE OTHER;

  private static final org.apache.dubbo.common.logger.ErrorTypeAwareLogger logger;

  private static final org.apache.dubbo.common.utils.JRE VERSION;

  private static final org.apache.dubbo.common.utils.JRE[] $VALUES;

  public static org.apache.dubbo.common.utils.JRE[] values();
    Code:
       0: getstatic     #1                  // Field $VALUES:[Lorg/apache/dubbo/common/utils/JRE;
       3: invokevirtual #2                  // Method "[Lorg/apache/dubbo/common/utils/JRE;".clone:()Ljava/lang/Object;
       6: checkcast     #3                  // class "[Lorg/apache/dubbo/common/utils/JRE;"
       9: areturn

  public static org.apache.dubbo.common.utils.JRE valueOf(java.lang.String);
    Code:
       0: ldc           #4                  // class org/apache/dubbo/common/utils/JRE
       2: aload_0
       3: invokestatic  #5                  // Method java/lang/Enum.valueOf:(Ljava/lang/Class;Ljava/lang/String;)Ljava/lang/Enum;
       6: checkcast     #4                  // class org/apache/dubbo/common/utils/JRE
       9: areturn

  private org.apache.dubbo.common.utils.JRE();
    Code:
       0: aload_0
       1: aload_1
       2: iload_2
       3: invokespecial #6                  // Method java/lang/Enum."<init>":(Ljava/lang/String;I)V
       6: return

  public static org.apache.dubbo.common.utils.JRE currentVersion();
    Code:
       0: getstatic     #7                  // Field VERSION:Lorg/apache/dubbo/common/utils/JRE;
       3: areturn

  public boolean isCurrentVersion();
    Code:
       0: aload_0
       1: getstatic     #7                  // Field VERSION:Lorg/apache/dubbo/common/utils/JRE;
       4: if_acmpne     11
       7: iconst_1
       8: goto          12
      11: iconst_0
      12: ireturn

  private static org.apache.dubbo.common.utils.JRE getJre();
    Code:
       0: ldc           #8                  // String java.version
       2: invokestatic  #9                  // Method java/lang/System.getProperty:(Ljava/lang/String;)Ljava/lang/String;
       5: astore_0
       6: aload_0
       7: invokestatic  #10                 // Method org/apache/dubbo/common/utils/StringUtils.isBlank:(Ljava/lang/CharSequence;)Z
      10: istore_1
      11: iload_1
      12: ifeq          25
      15: getstatic     #11                 // Field logger:Lorg/apache/dubbo/common/logger/ErrorTypeAwareLogger;
      18: ldc           #12                 // String java.version is blank
      20: invokeinterface #13,  2           // InterfaceMethod org/apache/dubbo/common/logger/ErrorTypeAwareLogger.debug:(Ljava/lang/String;)V
      25: iload_1
      26: ifne          42
      29: aload_0
      30: ldc           #14                 // String 1.8
      32: invokevirtual #15                 // Method java/lang/String.startsWith:(Ljava/lang/String;)Z
      35: ifeq          42
      38: getstatic     #16                 // Field JAVA_8:Lorg/apache/dubbo/common/utils/JRE;
      41: areturn
      42: invokestatic  #17                 // Method java/lang/Runtime.getRuntime:()Ljava/lang/Runtime;
      45: ldc           #18                 // String version
      47: iconst_0
      48: anewarray     #19                 // class java/lang/Object
      51: invokestatic  #20                 // InterfaceMethod org/apache/dubbo/common/utils/MethodUtils.invokeMethod:(Ljava/lang/Object;Ljava/lang/String;[Ljava/lang/Object;)Ljava/lang/Object;
      54: astore_2
      55: aload_2
      56: ldc           #21                 // String major
      58: iconst_0
      59: anewarray     #19                 // class java/lang/Object
      62: invokestatic  #20                 // InterfaceMethod org/apache/dubbo/common/utils/MethodUtils.invokeMethod:(Ljava/lang/Object;Ljava/lang/String;[Ljava/lang/Object;)Ljava/lang/Object;
      65: checkcast     #22                 // class java/lang/Integer
      68: invokevirtual #23                 // Method java/lang/Integer.intValue:()I
      71: istore_3
      72: iload_3
      73: tableswitch   { // 9 to 19
                     9: 132
                    10: 136
                    11: 140
                    12: 144
                    13: 148
                    14: 152
                    15: 156
                    16: 160
                    17: 164
                    18: 168
                    19: 172
               default: 176
          }
     132: getstatic     #24                 // Field JAVA_9:Lorg/apache/dubbo/common/utils/JRE;
     135: areturn
     136: getstatic     #25                 // Field JAVA_10:Lorg/apache/dubbo/common/utils/JRE;
     139: areturn
     140: getstatic     #26                 // Field JAVA_11:Lorg/apache/dubbo/common/utils/JRE;
     143: areturn
     144: getstatic     #27                 // Field JAVA_12:Lorg/apache/dubbo/common/utils/JRE;
     147: areturn
     148: getstatic     #28                 // Field JAVA_13:Lorg/apache/dubbo/common/utils/JRE;
     151: areturn
     152: getstatic     #29                 // Field JAVA_14:Lorg/apache/dubbo/common/utils/JRE;
     155: areturn
     156: getstatic     #30                 // Field JAVA_15:Lorg/apache/dubbo/common/utils/JRE;
     159: areturn
     160: getstatic     #31                 // Field JAVA_16:Lorg/apache/dubbo/common/utils/JRE;
     163: areturn
     164: getstatic     #32                 // Field JAVA_17:Lorg/apache/dubbo/common/utils/JRE;
     167: areturn
     168: getstatic     #33                 // Field JAVA_18:Lorg/apache/dubbo/common/utils/JRE;
     171: areturn
     172: getstatic     #34                 // Field JAVA_19:Lorg/apache/dubbo/common/utils/JRE;
     175: areturn
     176: getstatic     #35                 // Field OTHER:Lorg/apache/dubbo/common/utils/JRE;
     179: areturn
     180: astore_2
     181: getstatic     #11                 // Field logger:Lorg/apache/dubbo/common/logger/ErrorTypeAwareLogger;
     184: ldc           #37                 // String Can\'t determine current JRE version (maybe java.version is null), assuming that JRE version is 8.
     186: aload_2
     187: invokeinterface #38,  3           // InterfaceMethod org/apache/dubbo/common/logger/ErrorTypeAwareLogger.debug:(Ljava/lang/String;Ljava/lang/Throwable;)V
     192: getstatic     #16                 // Field JAVA_8:Lorg/apache/dubbo/common/utils/JRE;
     195: areturn
    Exception table:
       from    to  target type
          42   135   180   Class java/lang/Exception
         136   139   180   Class java/lang/Exception
         140   143   180   Class java/lang/Exception
         144   147   180   Class java/lang/Exception
         148   151   180   Class java/lang/Exception
         152   155   180   Class java/lang/Exception
         156   159   180   Class java/lang/Exception
         160   163   180   Class java/lang/Exception
         164   167   180   Class java/lang/Exception
         168   171   180   Class java/lang/Exception
         172   175   180   Class java/lang/Exception
         176   179   180   Class java/lang/Exception

  static {};
    Code:
       0: new           #4                  // class org/apache/dubbo/common/utils/JRE
       3: dup
       4: ldc           #39                 // String JAVA_8
       6: iconst_0
       7: invokespecial #40                 // Method "<init>":(Ljava/lang/String;I)V
      10: putstatic     #16                 // Field JAVA_8:Lorg/apache/dubbo/common/utils/JRE;
      13: new           #4                  // class org/apache/dubbo/common/utils/JRE
      16: dup
      17: ldc           #41                 // String JAVA_9
      19: iconst_1
      20: invokespecial #40                 // Method "<init>":(Ljava/lang/String;I)V
      23: putstatic     #24                 // Field JAVA_9:Lorg/apache/dubbo/common/utils/JRE;
      26: new           #4                  // class org/apache/dubbo/common/utils/JRE
      29: dup
      30: ldc           #42                 // String JAVA_10
      32: iconst_2
      33: invokespecial #40                 // Method "<init>":(Ljava/lang/String;I)V
      36: putstatic     #25                 // Field JAVA_10:Lorg/apache/dubbo/common/utils/JRE;
      39: new           #4                  // class org/apache/dubbo/common/utils/JRE
      42: dup
      43: ldc           #43                 // String JAVA_11
      45: iconst_3
      46: invokespecial #40                 // Method "<init>":(Ljava/lang/String;I)V
      49: putstatic     #26                 // Field JAVA_11:Lorg/apache/dubbo/common/utils/JRE;
      52: new           #4                  // class org/apache/dubbo/common/utils/JRE
      55: dup
      56: ldc           #44                 // String JAVA_12
      58: iconst_4
      59: invokespecial #40                 // Method "<init>":(Ljava/lang/String;I)V
      62: putstatic     #27                 // Field JAVA_12:Lorg/apache/dubbo/common/utils/JRE;
      65: new           #4                  // class org/apache/dubbo/common/utils/JRE
      68: dup
      69: ldc           #45                 // String JAVA_13
      71: iconst_5
      72: invokespecial #40                 // Method "<init>":(Ljava/lang/String;I)V
      75: putstatic     #28                 // Field JAVA_13:Lorg/apache/dubbo/common/utils/JRE;
      78: new           #4                  // class org/apache/dubbo/common/utils/JRE
      81: dup
      82: ldc           #46                 // String JAVA_14
      84: bipush        6
      86: invokespecial #40                 // Method "<init>":(Ljava/lang/String;I)V
      89: putstatic     #29                 // Field JAVA_14:Lorg/apache/dubbo/common/utils/JRE;
      92: new           #4                  // class org/apache/dubbo/common/utils/JRE
      95: dup
      96: ldc           #47                 // String JAVA_15
      98: bipush        7
     100: invokespecial #40                 // Method "<init>":(Ljava/lang/String;I)V
     103: putstatic     #30                 // Field JAVA_15:Lorg/apache/dubbo/common/utils/JRE;
     106: new           #4                  // class org/apache/dubbo/common/utils/JRE
     109: dup
     110: ldc           #48                 // String JAVA_16
     112: bipush        8
     114: invokespecial #40                 // Method "<init>":(Ljava/lang/String;I)V
     117: putstatic     #31                 // Field JAVA_16:Lorg/apache/dubbo/common/utils/JRE;
     120: new           #4                  // class org/apache/dubbo/common/utils/JRE
     123: dup
     124: ldc           #49                 // String JAVA_17
     126: bipush        9
     128: invokespecial #40                 // Method "<init>":(Ljava/lang/String;I)V
     131: putstatic     #32                 // Field JAVA_17:Lorg/apache/dubbo/common/utils/JRE;
     134: new           #4                  // class org/apache/dubbo/common/utils/JRE
     137: dup
     138: ldc           #50                 // String JAVA_18
     140: bipush        10
     142: invokespecial #40                 // Method "<init>":(Ljava/lang/String;I)V
     145: putstatic     #33                 // Field JAVA_18:Lorg/apache/dubbo/common/utils/JRE;
     148: new           #4                  // class org/apache/dubbo/common/utils/JRE
     151: dup
     152: ldc           #51                 // String JAVA_19
     154: bipush        11
     156: invokespecial #40                 // Method "<init>":(Ljava/lang/String;I)V
     159: putstatic     #34                 // Field JAVA_19:Lorg/apache/dubbo/common/utils/JRE;
     162: new           #4                  // class org/apache/dubbo/common/utils/JRE
     165: dup
     166: ldc           #52                 // String OTHER
     168: bipush        12
     170: invokespecial #40                 // Method "<init>":(Ljava/lang/String;I)V
     173: putstatic     #35                 // Field OTHER:Lorg/apache/dubbo/common/utils/JRE;
     176: bipush        13
     178: anewarray     #4                  // class org/apache/dubbo/common/utils/JRE
     181: dup
     182: iconst_0
     183: getstatic     #16                 // Field JAVA_8:Lorg/apache/dubbo/common/utils/JRE;
     186: aastore
     187: dup
     188: iconst_1
     189: getstatic     #24                 // Field JAVA_9:Lorg/apache/dubbo/common/utils/JRE;
     192: aastore
     193: dup
     194: iconst_2
     195: getstatic     #25                 // Field JAVA_10:Lorg/apache/dubbo/common/utils/JRE;
     198: aastore
     199: dup
     200: iconst_3
     201: getstatic     #26                 // Field JAVA_11:Lorg/apache/dubbo/common/utils/JRE;
     204: aastore
     205: dup
     206: iconst_4
     207: getstatic     #27                 // Field JAVA_12:Lorg/apache/dubbo/common/utils/JRE;
     210: aastore
     211: dup
     212: iconst_5
     213: getstatic     #28                 // Field JAVA_13:Lorg/apache/dubbo/common/utils/JRE;
     216: aastore
     217: dup
     218: bipush        6
     220: getstatic     #29                 // Field JAVA_14:Lorg/apache/dubbo/common/utils/JRE;
     223: aastore
     224: dup
     225: bipush        7
     227: getstatic     #30                 // Field JAVA_15:Lorg/apache/dubbo/common/utils/JRE;
     230: aastore
     231: dup
     232: bipush        8
     234: getstatic     #31                 // Field JAVA_16:Lorg/apache/dubbo/common/utils/JRE;
     237: aastore
     238: dup
     239: bipush        9
     241: getstatic     #32                 // Field JAVA_17:Lorg/apache/dubbo/common/utils/JRE;
     244: aastore
     245: dup
     246: bipush        10
     248: getstatic     #33                 // Field JAVA_18:Lorg/apache/dubbo/common/utils/JRE;
     251: aastore
     252: dup
     253: bipush        11
     255: getstatic     #34                 // Field JAVA_19:Lorg/apache/dubbo/common/utils/JRE;
     258: aastore
     259: dup
     260: bipush        12
     262: getstatic     #35                 // Field OTHER:Lorg/apache/dubbo/common/utils/JRE;
     265: aastore
     266: putstatic     #1                  // Field $VALUES:[Lorg/apache/dubbo/common/utils/JRE;
     269: ldc           #4                  // class org/apache/dubbo/common/utils/JRE
     271: invokestatic  #53                 // Method org/apache/dubbo/common/logger/LoggerFactory.getErrorTypeAwareLogger:(Ljava/lang/Class;)Lorg/apache/dubbo/common/logger/ErrorTypeAwareLogger;
     274: putstatic     #11                 // Field logger:Lorg/apache/dubbo/common/logger/ErrorTypeAwareLogger;
     277: invokestatic  #54                 // Method getJre:()Lorg/apache/dubbo/common/utils/JRE;
     280: putstatic     #7                  // Field VERSION:Lorg/apache/dubbo/common/utils/JRE;
     283: return
}
