Compiled from "LFUCache.java"
class org.apache.dubbo.common.utils.LFUCache$CacheNode<K, V> {
  org.apache.dubbo.common.utils.LFUCache$CacheNode<K, V> prev;

  org.apache.dubbo.common.utils.LFUCache$CacheNode<K, V> next;

  K key;

  V value;

  org.apache.dubbo.common.utils.LFUCache$CacheDeque<K, V> owner;

  org.apache.dubbo.common.utils.LFUCache$CacheNode();
    Code:
       0: aload_0
       1: invokespecial #1                  // Method java/lang/Object."<init>":()V
       4: return

  org.apache.dubbo.common.utils.LFUCache$CacheNode(K, V);
    Code:
       0: aload_0
       1: invokespecial #1                  // Method java/lang/Object."<init>":()V
       4: aload_0
       5: aload_1
       6: putfield      #2                  // Field key:Ljava/lang/Object;
       9: aload_0
      10: aload_2
      11: putfield      #3                  // Field value:Ljava/lang/Object;
      14: return

  static <K, V> org.apache.dubbo.common.utils.LFUCache$CacheNode<K, V> withdrawNode(org.apache.dubbo.common.utils.LFUCache$CacheNode<K, V>);
    Code:
       0: aload_0
       1: ifnull        40
       4: aload_0
       5: getfield      #4                  // Field prev:Lorg/apache/dubbo/common/utils/LFUCache$CacheNode;
       8: ifnull        40
      11: aload_0
      12: getfield      #4                  // Field prev:Lorg/apache/dubbo/common/utils/LFUCache$CacheNode;
      15: aload_0
      16: getfield      #5                  // Field next:Lorg/apache/dubbo/common/utils/LFUCache$CacheNode;
      19: putfield      #5                  // Field next:Lorg/apache/dubbo/common/utils/LFUCache$CacheNode;
      22: aload_0
      23: getfield      #5                  // Field next:Lorg/apache/dubbo/common/utils/LFUCache$CacheNode;
      26: ifnull        40
      29: aload_0
      30: getfield      #5                  // Field next:Lorg/apache/dubbo/common/utils/LFUCache$CacheNode;
      33: aload_0
      34: getfield      #4                  // Field prev:Lorg/apache/dubbo/common/utils/LFUCache$CacheNode;
      37: putfield      #4                  // Field prev:Lorg/apache/dubbo/common/utils/LFUCache$CacheNode;
      40: aload_0
      41: areturn
}
