Compiled from "LFUCache.java"
class org.apache.dubbo.common.utils.LFUCache$CacheDeque<K, V> {
  org.apache.dubbo.common.utils.LFUCache$CacheNode<K, V> last;

  org.apache.dubbo.common.utils.LFUCache$CacheNode<K, V> first;

  org.apache.dubbo.common.utils.LFUCache$CacheDeque<K, V> nextDeque;

  org.apache.dubbo.common.utils.LFUCache$CacheDeque();
    Code:
       0: aload_0
       1: invokespecial #1                  // Method java/lang/Object."<init>":()V
       4: aload_0
       5: new           #2                  // class org/apache/dubbo/common/utils/LFUCache$CacheNode
       8: dup
       9: invokespecial #3                  // Method org/apache/dubbo/common/utils/LFUCache$CacheNode."<init>":()V
      12: putfield      #4                  // Field last:Lorg/apache/dubbo/common/utils/LFUCache$CacheNode;
      15: aload_0
      16: new           #2                  // class org/apache/dubbo/common/utils/LFUCache$CacheNode
      19: dup
      20: invokespecial #3                  // Method org/apache/dubbo/common/utils/LFUCache$CacheNode."<init>":()V
      23: putfield      #5                  // Field first:Lorg/apache/dubbo/common/utils/LFUCache$CacheNode;
      26: aload_0
      27: getfield      #4                  // Field last:Lorg/apache/dubbo/common/utils/LFUCache$CacheNode;
      30: aload_0
      31: getfield      #5                  // Field first:Lorg/apache/dubbo/common/utils/LFUCache$CacheNode;
      34: putfield      #6                  // Field org/apache/dubbo/common/utils/LFUCache$CacheNode.next:Lorg/apache/dubbo/common/utils/LFUCache$CacheNode;
      37: aload_0
      38: getfield      #5                  // Field first:Lorg/apache/dubbo/common/utils/LFUCache$CacheNode;
      41: aload_0
      42: getfield      #4                  // Field last:Lorg/apache/dubbo/common/utils/LFUCache$CacheNode;
      45: putfield      #7                  // Field org/apache/dubbo/common/utils/LFUCache$CacheNode.prev:Lorg/apache/dubbo/common/utils/LFUCache$CacheNode;
      48: return

  org.apache.dubbo.common.utils.LFUCache$CacheNode<K, V> addLast(K, V);
    Code:
       0: new           #2                  // class org/apache/dubbo/common/utils/LFUCache$CacheNode
       3: dup
       4: aload_1
       5: aload_2
       6: invokespecial #8                  // Method org/apache/dubbo/common/utils/LFUCache$CacheNode."<init>":(Ljava/lang/Object;Ljava/lang/Object;)V
       9: astore_3
      10: aload_3
      11: aload_0
      12: putfield      #9                  // Field org/apache/dubbo/common/utils/LFUCache$CacheNode.owner:Lorg/apache/dubbo/common/utils/LFUCache$CacheDeque;
      15: aload_3
      16: aload_0
      17: getfield      #4                  // Field last:Lorg/apache/dubbo/common/utils/LFUCache$CacheNode;
      20: getfield      #6                  // Field org/apache/dubbo/common/utils/LFUCache$CacheNode.next:Lorg/apache/dubbo/common/utils/LFUCache$CacheNode;
      23: putfield      #6                  // Field org/apache/dubbo/common/utils/LFUCache$CacheNode.next:Lorg/apache/dubbo/common/utils/LFUCache$CacheNode;
      26: aload_3
      27: aload_0
      28: getfield      #4                  // Field last:Lorg/apache/dubbo/common/utils/LFUCache$CacheNode;
      31: putfield      #7                  // Field org/apache/dubbo/common/utils/LFUCache$CacheNode.prev:Lorg/apache/dubbo/common/utils/LFUCache$CacheNode;
      34: aload_3
      35: getfield      #6                  // Field org/apache/dubbo/common/utils/LFUCache$CacheNode.next:Lorg/apache/dubbo/common/utils/LFUCache$CacheNode;
      38: aload_3
      39: putfield      #7                  // Field org/apache/dubbo/common/utils/LFUCache$CacheNode.prev:Lorg/apache/dubbo/common/utils/LFUCache$CacheNode;
      42: aload_0
      43: getfield      #4                  // Field last:Lorg/apache/dubbo/common/utils/LFUCache$CacheNode;
      46: aload_3
      47: putfield      #6                  // Field org/apache/dubbo/common/utils/LFUCache$CacheNode.next:Lorg/apache/dubbo/common/utils/LFUCache$CacheNode;
      50: aload_3
      51: areturn

  org.apache.dubbo.common.utils.LFUCache$CacheNode<K, V> addLastNode(org.apache.dubbo.common.utils.LFUCache$CacheNode<K, V>);
    Code:
       0: aload_1
       1: aload_0
       2: putfield      #9                  // Field org/apache/dubbo/common/utils/LFUCache$CacheNode.owner:Lorg/apache/dubbo/common/utils/LFUCache$CacheDeque;
       5: aload_1
       6: aload_0
       7: getfield      #4                  // Field last:Lorg/apache/dubbo/common/utils/LFUCache$CacheNode;
      10: getfield      #6                  // Field org/apache/dubbo/common/utils/LFUCache$CacheNode.next:Lorg/apache/dubbo/common/utils/LFUCache$CacheNode;
      13: putfield      #6                  // Field org/apache/dubbo/common/utils/LFUCache$CacheNode.next:Lorg/apache/dubbo/common/utils/LFUCache$CacheNode;
      16: aload_1
      17: aload_0
      18: getfield      #4                  // Field last:Lorg/apache/dubbo/common/utils/LFUCache$CacheNode;
      21: putfield      #7                  // Field org/apache/dubbo/common/utils/LFUCache$CacheNode.prev:Lorg/apache/dubbo/common/utils/LFUCache$CacheNode;
      24: aload_1
      25: getfield      #6                  // Field org/apache/dubbo/common/utils/LFUCache$CacheNode.next:Lorg/apache/dubbo/common/utils/LFUCache$CacheNode;
      28: aload_1
      29: putfield      #7                  // Field org/apache/dubbo/common/utils/LFUCache$CacheNode.prev:Lorg/apache/dubbo/common/utils/LFUCache$CacheNode;
      32: aload_0
      33: getfield      #4                  // Field last:Lorg/apache/dubbo/common/utils/LFUCache$CacheNode;
      36: aload_1
      37: putfield      #6                  // Field org/apache/dubbo/common/utils/LFUCache$CacheNode.next:Lorg/apache/dubbo/common/utils/LFUCache$CacheNode;
      40: aload_1
      41: areturn

  org.apache.dubbo.common.utils.LFUCache$CacheNode<K, V> pollFirst();
    Code:
       0: aconst_null
       1: astore_1
       2: aload_0
       3: getfield      #5                  // Field first:Lorg/apache/dubbo/common/utils/LFUCache$CacheNode;
       6: getfield      #7                  // Field org/apache/dubbo/common/utils/LFUCache$CacheNode.prev:Lorg/apache/dubbo/common/utils/LFUCache$CacheNode;
       9: aload_0
      10: getfield      #4                  // Field last:Lorg/apache/dubbo/common/utils/LFUCache$CacheNode;
      13: if_acmpeq     59
      16: aload_0
      17: getfield      #5                  // Field first:Lorg/apache/dubbo/common/utils/LFUCache$CacheNode;
      20: getfield      #7                  // Field org/apache/dubbo/common/utils/LFUCache$CacheNode.prev:Lorg/apache/dubbo/common/utils/LFUCache$CacheNode;
      23: astore_1
      24: aload_0
      25: getfield      #5                  // Field first:Lorg/apache/dubbo/common/utils/LFUCache$CacheNode;
      28: aload_1
      29: getfield      #7                  // Field org/apache/dubbo/common/utils/LFUCache$CacheNode.prev:Lorg/apache/dubbo/common/utils/LFUCache$CacheNode;
      32: putfield      #7                  // Field org/apache/dubbo/common/utils/LFUCache$CacheNode.prev:Lorg/apache/dubbo/common/utils/LFUCache$CacheNode;
      35: aload_0
      36: getfield      #5                  // Field first:Lorg/apache/dubbo/common/utils/LFUCache$CacheNode;
      39: getfield      #7                  // Field org/apache/dubbo/common/utils/LFUCache$CacheNode.prev:Lorg/apache/dubbo/common/utils/LFUCache$CacheNode;
      42: aload_0
      43: getfield      #5                  // Field first:Lorg/apache/dubbo/common/utils/LFUCache$CacheNode;
      46: putfield      #6                  // Field org/apache/dubbo/common/utils/LFUCache$CacheNode.next:Lorg/apache/dubbo/common/utils/LFUCache$CacheNode;
      49: aload_1
      50: aconst_null
      51: putfield      #7                  // Field org/apache/dubbo/common/utils/LFUCache$CacheNode.prev:Lorg/apache/dubbo/common/utils/LFUCache$CacheNode;
      54: aload_1
      55: aconst_null
      56: putfield      #6                  // Field org/apache/dubbo/common/utils/LFUCache$CacheNode.next:Lorg/apache/dubbo/common/utils/LFUCache$CacheNode;
      59: aload_1
      60: areturn

  boolean isEmpty();
    Code:
       0: aload_0
       1: getfield      #4                  // Field last:Lorg/apache/dubbo/common/utils/LFUCache$CacheNode;
       4: getfield      #6                  // Field org/apache/dubbo/common/utils/LFUCache$CacheNode.next:Lorg/apache/dubbo/common/utils/LFUCache$CacheNode;
       7: aload_0
       8: getfield      #5                  // Field first:Lorg/apache/dubbo/common/utils/LFUCache$CacheNode;
      11: if_acmpne     18
      14: iconst_1
      15: goto          19
      18: iconst_0
      19: ireturn
}
