Compiled from "Log.java"
public class org.apache.dubbo.common.utils.Log implements java.io.Serializable {
  private static final long serialVersionUID;

  private java.lang.String logName;

  private org.apache.log4j.Level logLevel;

  private java.lang.String logMessage;

  private java.lang.String logThread;

  public org.apache.dubbo.common.utils.Log();
    Code:
       0: aload_0
       1: invokespecial #1                  // Method java/lang/Object."<init>":()V
       4: return

  public java.lang.String getLogName();
    Code:
       0: aload_0
       1: getfield      #2                  // Field logName:Ljava/lang/String;
       4: areturn

  public void setLogName(java.lang.String);
    Code:
       0: aload_0
       1: aload_1
       2: putfield      #2                  // Field logName:Ljava/lang/String;
       5: return

  public org.apache.log4j.Level getLogLevel();
    Code:
       0: aload_0
       1: getfield      #3                  // Field logLevel:Lorg/apache/log4j/Level;
       4: areturn

  public void setLogLevel(org.apache.log4j.Level);
    Code:
       0: aload_0
       1: aload_1
       2: putfield      #3                  // Field logLevel:Lorg/apache/log4j/Level;
       5: return

  public java.lang.String getLogMessage();
    Code:
       0: aload_0
       1: getfield      #4                  // Field logMessage:Ljava/lang/String;
       4: areturn

  public void setLogMessage(java.lang.String);
    Code:
       0: aload_0
       1: aload_1
       2: putfield      #4                  // Field logMessage:Ljava/lang/String;
       5: return

  public java.lang.String getLogThread();
    Code:
       0: aload_0
       1: getfield      #5                  // Field logThread:Ljava/lang/String;
       4: areturn

  public void setLogThread(java.lang.String);
    Code:
       0: aload_0
       1: aload_1
       2: putfield      #5                  // Field logThread:Ljava/lang/String;
       5: return

  public int hashCode();
    Code:
       0: bipush        31
       2: istore_1
       3: iconst_1
       4: istore_2
       5: bipush        31
       7: iload_2
       8: imul
       9: aload_0
      10: getfield      #3                  // Field logLevel:Lorg/apache/log4j/Level;
      13: ifnonnull     20
      16: iconst_0
      17: goto          27
      20: aload_0
      21: getfield      #3                  // Field logLevel:Lorg/apache/log4j/Level;
      24: invokevirtual #6                  // Method java/lang/Object.hashCode:()I
      27: iadd
      28: istore_2
      29: bipush        31
      31: iload_2
      32: imul
      33: aload_0
      34: getfield      #4                  // Field logMessage:Ljava/lang/String;
      37: ifnonnull     44
      40: iconst_0
      41: goto          51
      44: aload_0
      45: getfield      #4                  // Field logMessage:Ljava/lang/String;
      48: invokevirtual #7                  // Method java/lang/String.hashCode:()I
      51: iadd
      52: istore_2
      53: bipush        31
      55: iload_2
      56: imul
      57: aload_0
      58: getfield      #2                  // Field logName:Ljava/lang/String;
      61: ifnonnull     68
      64: iconst_0
      65: goto          75
      68: aload_0
      69: getfield      #2                  // Field logName:Ljava/lang/String;
      72: invokevirtual #7                  // Method java/lang/String.hashCode:()I
      75: iadd
      76: istore_2
      77: bipush        31
      79: iload_2
      80: imul
      81: aload_0
      82: getfield      #5                  // Field logThread:Ljava/lang/String;
      85: ifnonnull     92
      88: iconst_0
      89: goto          99
      92: aload_0
      93: getfield      #5                  // Field logThread:Ljava/lang/String;
      96: invokevirtual #7                  // Method java/lang/String.hashCode:()I
      99: iadd
     100: istore_2
     101: iload_2
     102: ireturn

  public boolean equals(java.lang.Object);
    Code:
       0: aload_0
       1: aload_1
       2: if_acmpne     7
       5: iconst_1
       6: ireturn
       7: aload_1
       8: ifnonnull     13
      11: iconst_0
      12: ireturn
      13: aload_0
      14: invokevirtual #8                  // Method java/lang/Object.getClass:()Ljava/lang/Class;
      17: aload_1
      18: invokevirtual #8                  // Method java/lang/Object.getClass:()Ljava/lang/Class;
      21: if_acmpeq     26
      24: iconst_0
      25: ireturn
      26: aload_1
      27: checkcast     #9                  // class org/apache/dubbo/common/utils/Log
      30: astore_2
      31: aload_0
      32: getfield      #3                  // Field logLevel:Lorg/apache/log4j/Level;
      35: ifnonnull     47
      38: aload_2
      39: getfield      #3                  // Field logLevel:Lorg/apache/log4j/Level;
      42: ifnull        63
      45: iconst_0
      46: ireturn
      47: aload_0
      48: getfield      #3                  // Field logLevel:Lorg/apache/log4j/Level;
      51: aload_2
      52: getfield      #3                  // Field logLevel:Lorg/apache/log4j/Level;
      55: invokevirtual #10                 // Method org/apache/log4j/Level.equals:(Ljava/lang/Object;)Z
      58: ifne          63
      61: iconst_0
      62: ireturn
      63: aload_0
      64: getfield      #4                  // Field logMessage:Ljava/lang/String;
      67: ifnonnull     79
      70: aload_2
      71: getfield      #4                  // Field logMessage:Ljava/lang/String;
      74: ifnull        95
      77: iconst_0
      78: ireturn
      79: aload_0
      80: getfield      #4                  // Field logMessage:Ljava/lang/String;
      83: aload_2
      84: getfield      #4                  // Field logMessage:Ljava/lang/String;
      87: invokevirtual #11                 // Method java/lang/String.equals:(Ljava/lang/Object;)Z
      90: ifne          95
      93: iconst_0
      94: ireturn
      95: aload_0
      96: getfield      #2                  // Field logName:Ljava/lang/String;
      99: ifnonnull     111
     102: aload_2
     103: getfield      #2                  // Field logName:Ljava/lang/String;
     106: ifnull        127
     109: iconst_0
     110: ireturn
     111: aload_0
     112: getfield      #2                  // Field logName:Ljava/lang/String;
     115: aload_2
     116: getfield      #2                  // Field logName:Ljava/lang/String;
     119: invokevirtual #11                 // Method java/lang/String.equals:(Ljava/lang/Object;)Z
     122: ifne          127
     125: iconst_0
     126: ireturn
     127: aload_0
     128: getfield      #5                  // Field logThread:Ljava/lang/String;
     131: ifnonnull     143
     134: aload_2
     135: getfield      #5                  // Field logThread:Ljava/lang/String;
     138: ifnull        159
     141: iconst_0
     142: ireturn
     143: aload_0
     144: getfield      #5                  // Field logThread:Ljava/lang/String;
     147: aload_2
     148: getfield      #5                  // Field logThread:Ljava/lang/String;
     151: invokevirtual #11                 // Method java/lang/String.equals:(Ljava/lang/Object;)Z
     154: ifne          159
     157: iconst_0
     158: ireturn
     159: iconst_1
     160: ireturn
}
