Compiled from "LogHelper.java"
public class org.apache.dubbo.common.utils.LogHelper {
  private org.apache.dubbo.common.utils.LogHelper();
    Code:
       0: aload_0
       1: invokespecial #1                  // Method java/lang/Object."<init>":()V
       4: return

  public static void trace(org.apache.dubbo.common.logger.Logger, java.lang.String);
    Code:
       0: aload_0
       1: ifnonnull     5
       4: return
       5: aload_0
       6: invokeinterface #2,  1            // InterfaceMethod org/apache/dubbo/common/logger/Logger.isTraceEnabled:()Z
      11: ifeq          21
      14: aload_0
      15: aload_1
      16: invokeinterface #3,  2            // InterfaceMethod org/apache/dubbo/common/logger/Logger.trace:(Ljava/lang/String;)V
      21: return

  public static void trace(org.apache.dubbo.common.logger.Logger, java.lang.Throwable);
    Code:
       0: aload_0
       1: ifnonnull     5
       4: return
       5: aload_0
       6: invokeinterface #2,  1            // InterfaceMethod org/apache/dubbo/common/logger/Logger.isTraceEnabled:()Z
      11: ifeq          21
      14: aload_0
      15: aload_1
      16: invokeinterface #4,  2            // InterfaceMethod org/apache/dubbo/common/logger/Logger.trace:(Ljava/lang/Throwable;)V
      21: return

  public static void trace(org.apache.dubbo.common.logger.Logger, java.lang.String, java.lang.Throwable);
    Code:
       0: aload_0
       1: ifnonnull     5
       4: return
       5: aload_0
       6: invokeinterface #2,  1            // InterfaceMethod org/apache/dubbo/common/logger/Logger.isTraceEnabled:()Z
      11: ifeq          22
      14: aload_0
      15: aload_1
      16: aload_2
      17: invokeinterface #5,  3            // InterfaceMethod org/apache/dubbo/common/logger/Logger.trace:(Ljava/lang/String;Ljava/lang/Throwable;)V
      22: return

  public static void debug(org.apache.dubbo.common.logger.Logger, java.lang.String);
    Code:
       0: aload_0
       1: ifnonnull     5
       4: return
       5: aload_0
       6: invokeinterface #6,  1            // InterfaceMethod org/apache/dubbo/common/logger/Logger.isDebugEnabled:()Z
      11: ifeq          21
      14: aload_0
      15: aload_1
      16: invokeinterface #7,  2            // InterfaceMethod org/apache/dubbo/common/logger/Logger.debug:(Ljava/lang/String;)V
      21: return

  public static void debug(org.apache.dubbo.common.logger.Logger, java.lang.Throwable);
    Code:
       0: aload_0
       1: ifnonnull     5
       4: return
       5: aload_0
       6: invokeinterface #6,  1            // InterfaceMethod org/apache/dubbo/common/logger/Logger.isDebugEnabled:()Z
      11: ifeq          21
      14: aload_0
      15: aload_1
      16: invokeinterface #8,  2            // InterfaceMethod org/apache/dubbo/common/logger/Logger.debug:(Ljava/lang/Throwable;)V
      21: return

  public static void debug(org.apache.dubbo.common.logger.Logger, java.lang.String, java.lang.Throwable);
    Code:
       0: aload_0
       1: ifnonnull     5
       4: return
       5: aload_0
       6: invokeinterface #6,  1            // InterfaceMethod org/apache/dubbo/common/logger/Logger.isDebugEnabled:()Z
      11: ifeq          22
      14: aload_0
      15: aload_1
      16: aload_2
      17: invokeinterface #9,  3            // InterfaceMethod org/apache/dubbo/common/logger/Logger.debug:(Ljava/lang/String;Ljava/lang/Throwable;)V
      22: return

  public static void info(org.apache.dubbo.common.logger.Logger, java.lang.String);
    Code:
       0: aload_0
       1: ifnonnull     5
       4: return
       5: aload_0
       6: invokeinterface #10,  1           // InterfaceMethod org/apache/dubbo/common/logger/Logger.isInfoEnabled:()Z
      11: ifeq          21
      14: aload_0
      15: aload_1
      16: invokeinterface #11,  2           // InterfaceMethod org/apache/dubbo/common/logger/Logger.info:(Ljava/lang/String;)V
      21: return

  public static void info(org.apache.dubbo.common.logger.Logger, java.lang.Throwable);
    Code:
       0: aload_0
       1: ifnonnull     5
       4: return
       5: aload_0
       6: invokeinterface #10,  1           // InterfaceMethod org/apache/dubbo/common/logger/Logger.isInfoEnabled:()Z
      11: ifeq          21
      14: aload_0
      15: aload_1
      16: invokeinterface #12,  2           // InterfaceMethod org/apache/dubbo/common/logger/Logger.info:(Ljava/lang/Throwable;)V
      21: return

  public static void info(org.apache.dubbo.common.logger.Logger, java.lang.String, java.lang.Throwable);
    Code:
       0: aload_0
       1: ifnonnull     5
       4: return
       5: aload_0
       6: invokeinterface #10,  1           // InterfaceMethod org/apache/dubbo/common/logger/Logger.isInfoEnabled:()Z
      11: ifeq          22
      14: aload_0
      15: aload_1
      16: aload_2
      17: invokeinterface #13,  3           // InterfaceMethod org/apache/dubbo/common/logger/Logger.info:(Ljava/lang/String;Ljava/lang/Throwable;)V
      22: return

  public static void warn(org.apache.dubbo.common.logger.Logger, java.lang.String, java.lang.Throwable);
    Code:
       0: aload_0
       1: ifnonnull     5
       4: return
       5: aload_0
       6: invokeinterface #14,  1           // InterfaceMethod org/apache/dubbo/common/logger/Logger.isWarnEnabled:()Z
      11: ifeq          22
      14: aload_0
      15: aload_1
      16: aload_2
      17: invokeinterface #15,  3           // InterfaceMethod org/apache/dubbo/common/logger/Logger.warn:(Ljava/lang/String;Ljava/lang/Throwable;)V
      22: return

  public static void warn(org.apache.dubbo.common.logger.Logger, java.lang.String);
    Code:
       0: aload_0
       1: ifnonnull     5
       4: return
       5: aload_0
       6: invokeinterface #14,  1           // InterfaceMethod org/apache/dubbo/common/logger/Logger.isWarnEnabled:()Z
      11: ifeq          21
      14: aload_0
      15: aload_1
      16: invokeinterface #16,  2           // InterfaceMethod org/apache/dubbo/common/logger/Logger.warn:(Ljava/lang/String;)V
      21: return

  public static void warn(org.apache.dubbo.common.logger.Logger, java.lang.Throwable);
    Code:
       0: aload_0
       1: ifnonnull     5
       4: return
       5: aload_0
       6: invokeinterface #14,  1           // InterfaceMethod org/apache/dubbo/common/logger/Logger.isWarnEnabled:()Z
      11: ifeq          21
      14: aload_0
      15: aload_1
      16: invokeinterface #17,  2           // InterfaceMethod org/apache/dubbo/common/logger/Logger.warn:(Ljava/lang/Throwable;)V
      21: return

  public static void error(org.apache.dubbo.common.logger.Logger, java.lang.Throwable);
    Code:
       0: aload_0
       1: ifnonnull     5
       4: return
       5: aload_0
       6: invokeinterface #18,  1           // InterfaceMethod org/apache/dubbo/common/logger/Logger.isErrorEnabled:()Z
      11: ifeq          21
      14: aload_0
      15: aload_1
      16: invokeinterface #19,  2           // InterfaceMethod org/apache/dubbo/common/logger/Logger.error:(Ljava/lang/Throwable;)V
      21: return

  public static void error(org.apache.dubbo.common.logger.Logger, java.lang.String);
    Code:
       0: aload_0
       1: ifnonnull     5
       4: return
       5: aload_0
       6: invokeinterface #18,  1           // InterfaceMethod org/apache/dubbo/common/logger/Logger.isErrorEnabled:()Z
      11: ifeq          21
      14: aload_0
      15: aload_1
      16: invokeinterface #20,  2           // InterfaceMethod org/apache/dubbo/common/logger/Logger.error:(Ljava/lang/String;)V
      21: return

  public static void error(org.apache.dubbo.common.logger.Logger, java.lang.String, java.lang.Throwable);
    Code:
       0: aload_0
       1: ifnonnull     5
       4: return
       5: aload_0
       6: invokeinterface #18,  1           // InterfaceMethod org/apache/dubbo/common/logger/Logger.isErrorEnabled:()Z
      11: ifeq          22
      14: aload_0
      15: aload_1
      16: aload_2
      17: invokeinterface #21,  3           // InterfaceMethod org/apache/dubbo/common/logger/Logger.error:(Ljava/lang/String;Ljava/lang/Throwable;)V
      22: return
}
