Compiled from "LRU2Cache.java"
public class org.apache.dubbo.common.utils.LRU2Cache<K, V> extends java.util.LinkedHashMap<K, V> {
  private static final long serialVersionUID;

  private static final float DEFAULT_LOAD_FACTOR;

  private static final int DEFAULT_MAX_CAPACITY;

  private final java.util.concurrent.locks.Lock lock;

  private volatile int maxCapacity;

  private final org.apache.dubbo.common.utils.LRU2Cache$PreCache<K, java.lang.Boolean> preCache;

  public org.apache.dubbo.common.utils.LRU2Cache();
    Code:
       0: aload_0
       1: sipush        1000
       4: invokespecial #2                  // Method "<init>":(I)V
       7: return

  public org.apache.dubbo.common.utils.LRU2Cache(int);
    Code:
       0: aload_0
       1: bipush        16
       3: ldc           #3                  // float 0.75f
       5: iconst_1
       6: invokespecial #4                  // Method java/util/LinkedHashMap."<init>":(IFZ)V
       9: aload_0
      10: new           #5                  // class java/util/concurrent/locks/ReentrantLock
      13: dup
      14: invokespecial #6                  // Method java/util/concurrent/locks/ReentrantLock."<init>":()V
      17: putfield      #7                  // Field lock:Ljava/util/concurrent/locks/Lock;
      20: aload_0
      21: iload_1
      22: putfield      #8                  // Field maxCapacity:I
      25: aload_0
      26: new           #9                  // class org/apache/dubbo/common/utils/LRU2Cache$PreCache
      29: dup
      30: iload_1
      31: invokespecial #10                 // Method org/apache/dubbo/common/utils/LRU2Cache$PreCache."<init>":(I)V
      34: putfield      #11                 // Field preCache:Lorg/apache/dubbo/common/utils/LRU2Cache$PreCache;
      37: return

  protected boolean removeEldestEntry(java.util.Map$Entry<K, V>);
    Code:
       0: aload_0
       1: invokevirtual #12                 // Method size:()I
       4: aload_0
       5: getfield      #8                  // Field maxCapacity:I
       8: if_icmple     15
      11: iconst_1
      12: goto          16
      15: iconst_0
      16: ireturn

  public boolean containsKey(java.lang.Object);
    Code:
       0: aload_0
       1: getfield      #7                  // Field lock:Ljava/util/concurrent/locks/Lock;
       4: invokeinterface #13,  1           // InterfaceMethod java/util/concurrent/locks/Lock.lock:()V
       9: aload_0
      10: aload_1
      11: invokespecial #14                 // Method java/util/LinkedHashMap.containsKey:(Ljava/lang/Object;)Z
      14: istore_2
      15: aload_0
      16: getfield      #7                  // Field lock:Ljava/util/concurrent/locks/Lock;
      19: invokeinterface #15,  1           // InterfaceMethod java/util/concurrent/locks/Lock.unlock:()V
      24: iload_2
      25: ireturn
      26: astore_3
      27: aload_0
      28: getfield      #7                  // Field lock:Ljava/util/concurrent/locks/Lock;
      31: invokeinterface #15,  1           // InterfaceMethod java/util/concurrent/locks/Lock.unlock:()V
      36: aload_3
      37: athrow
    Exception table:
       from    to  target type
           9    15    26   any

  public V get(java.lang.Object);
    Code:
       0: aload_0
       1: getfield      #7                  // Field lock:Ljava/util/concurrent/locks/Lock;
       4: invokeinterface #13,  1           // InterfaceMethod java/util/concurrent/locks/Lock.lock:()V
       9: aload_0
      10: aload_1
      11: invokespecial #16                 // Method java/util/LinkedHashMap.get:(Ljava/lang/Object;)Ljava/lang/Object;
      14: astore_2
      15: aload_0
      16: getfield      #7                  // Field lock:Ljava/util/concurrent/locks/Lock;
      19: invokeinterface #15,  1           // InterfaceMethod java/util/concurrent/locks/Lock.unlock:()V
      24: aload_2
      25: areturn
      26: astore_3
      27: aload_0
      28: getfield      #7                  // Field lock:Ljava/util/concurrent/locks/Lock;
      31: invokeinterface #15,  1           // InterfaceMethod java/util/concurrent/locks/Lock.unlock:()V
      36: aload_3
      37: athrow
    Exception table:
       from    to  target type
           9    15    26   any

  public V put(K, V);
    Code:
       0: aload_0
       1: getfield      #7                  // Field lock:Ljava/util/concurrent/locks/Lock;
       4: invokeinterface #13,  1           // InterfaceMethod java/util/concurrent/locks/Lock.lock:()V
       9: aload_0
      10: getfield      #11                 // Field preCache:Lorg/apache/dubbo/common/utils/LRU2Cache$PreCache;
      13: aload_1
      14: invokevirtual #17                 // Method org/apache/dubbo/common/utils/LRU2Cache$PreCache.containsKey:(Ljava/lang/Object;)Z
      17: ifeq          47
      20: aload_0
      21: getfield      #11                 // Field preCache:Lorg/apache/dubbo/common/utils/LRU2Cache$PreCache;
      24: aload_1
      25: invokevirtual #18                 // Method org/apache/dubbo/common/utils/LRU2Cache$PreCache.remove:(Ljava/lang/Object;)Ljava/lang/Object;
      28: pop
      29: aload_0
      30: aload_1
      31: aload_2
      32: invokespecial #19                 // Method java/util/LinkedHashMap.put:(Ljava/lang/Object;Ljava/lang/Object;)Ljava/lang/Object;
      35: astore_3
      36: aload_0
      37: getfield      #7                  // Field lock:Ljava/util/concurrent/locks/Lock;
      40: invokeinterface #15,  1           // InterfaceMethod java/util/concurrent/locks/Lock.unlock:()V
      45: aload_3
      46: areturn
      47: aload_0
      48: getfield      #11                 // Field preCache:Lorg/apache/dubbo/common/utils/LRU2Cache$PreCache;
      51: aload_1
      52: iconst_1
      53: invokestatic  #20                 // Method java/lang/Boolean.valueOf:(Z)Ljava/lang/Boolean;
      56: invokevirtual #21                 // Method org/apache/dubbo/common/utils/LRU2Cache$PreCache.put:(Ljava/lang/Object;Ljava/lang/Object;)Ljava/lang/Object;
      59: pop
      60: aload_2
      61: astore_3
      62: aload_0
      63: getfield      #7                  // Field lock:Ljava/util/concurrent/locks/Lock;
      66: invokeinterface #15,  1           // InterfaceMethod java/util/concurrent/locks/Lock.unlock:()V
      71: aload_3
      72: areturn
      73: astore        4
      75: aload_0
      76: getfield      #7                  // Field lock:Ljava/util/concurrent/locks/Lock;
      79: invokeinterface #15,  1           // InterfaceMethod java/util/concurrent/locks/Lock.unlock:()V
      84: aload         4
      86: athrow
    Exception table:
       from    to  target type
           9    36    73   any
          47    62    73   any
          73    75    73   any

  public V remove(java.lang.Object);
    Code:
       0: aload_0
       1: getfield      #7                  // Field lock:Ljava/util/concurrent/locks/Lock;
       4: invokeinterface #13,  1           // InterfaceMethod java/util/concurrent/locks/Lock.lock:()V
       9: aload_0
      10: getfield      #11                 // Field preCache:Lorg/apache/dubbo/common/utils/LRU2Cache$PreCache;
      13: aload_1
      14: invokevirtual #18                 // Method org/apache/dubbo/common/utils/LRU2Cache$PreCache.remove:(Ljava/lang/Object;)Ljava/lang/Object;
      17: pop
      18: aload_0
      19: aload_1
      20: invokespecial #22                 // Method java/util/LinkedHashMap.remove:(Ljava/lang/Object;)Ljava/lang/Object;
      23: astore_2
      24: aload_0
      25: getfield      #7                  // Field lock:Ljava/util/concurrent/locks/Lock;
      28: invokeinterface #15,  1           // InterfaceMethod java/util/concurrent/locks/Lock.unlock:()V
      33: aload_2
      34: areturn
      35: astore_3
      36: aload_0
      37: getfield      #7                  // Field lock:Ljava/util/concurrent/locks/Lock;
      40: invokeinterface #15,  1           // InterfaceMethod java/util/concurrent/locks/Lock.unlock:()V
      45: aload_3
      46: athrow
    Exception table:
       from    to  target type
           9    24    35   any

  public int size();
    Code:
       0: aload_0
       1: getfield      #7                  // Field lock:Ljava/util/concurrent/locks/Lock;
       4: invokeinterface #13,  1           // InterfaceMethod java/util/concurrent/locks/Lock.lock:()V
       9: aload_0
      10: invokespecial #23                 // Method java/util/LinkedHashMap.size:()I
      13: istore_1
      14: aload_0
      15: getfield      #7                  // Field lock:Ljava/util/concurrent/locks/Lock;
      18: invokeinterface #15,  1           // InterfaceMethod java/util/concurrent/locks/Lock.unlock:()V
      23: iload_1
      24: ireturn
      25: astore_2
      26: aload_0
      27: getfield      #7                  // Field lock:Ljava/util/concurrent/locks/Lock;
      30: invokeinterface #15,  1           // InterfaceMethod java/util/concurrent/locks/Lock.unlock:()V
      35: aload_2
      36: athrow
    Exception table:
       from    to  target type
           9    14    25   any

  public void clear();
    Code:
       0: aload_0
       1: getfield      #7                  // Field lock:Ljava/util/concurrent/locks/Lock;
       4: invokeinterface #13,  1           // InterfaceMethod java/util/concurrent/locks/Lock.lock:()V
       9: aload_0
      10: getfield      #11                 // Field preCache:Lorg/apache/dubbo/common/utils/LRU2Cache$PreCache;
      13: invokevirtual #24                 // Method org/apache/dubbo/common/utils/LRU2Cache$PreCache.clear:()V
      16: aload_0
      17: invokespecial #25                 // Method java/util/LinkedHashMap.clear:()V
      20: aload_0
      21: getfield      #7                  // Field lock:Ljava/util/concurrent/locks/Lock;
      24: invokeinterface #15,  1           // InterfaceMethod java/util/concurrent/locks/Lock.unlock:()V
      29: goto          44
      32: astore_1
      33: aload_0
      34: getfield      #7                  // Field lock:Ljava/util/concurrent/locks/Lock;
      37: invokeinterface #15,  1           // InterfaceMethod java/util/concurrent/locks/Lock.unlock:()V
      42: aload_1
      43: athrow
      44: return
    Exception table:
       from    to  target type
           9    20    32   any

  public int getMaxCapacity();
    Code:
       0: aload_0
       1: getfield      #8                  // Field maxCapacity:I
       4: ireturn

  public void setMaxCapacity(int);
    Code:
       0: aload_0
       1: getfield      #11                 // Field preCache:Lorg/apache/dubbo/common/utils/LRU2Cache$PreCache;
       4: iload_1
       5: invokevirtual #26                 // Method org/apache/dubbo/common/utils/LRU2Cache$PreCache.setMaxCapacity:(I)V
       8: aload_0
       9: iload_1
      10: putfield      #8                  // Field maxCapacity:I
      13: return
}
