Compiled from "MemberUtils.java"
public interface org.apache.dubbo.common.utils.MemberUtils {
  public static boolean isStatic(java.lang.reflect.Member);
    Code:
       0: aload_0
       1: ifnull        20
       4: aload_0
       5: invokeinterface #1,  1            // InterfaceMethod java/lang/reflect/Member.getModifiers:()I
      10: invokestatic  #2                  // Method java/lang/reflect/Modifier.isStatic:(I)Z
      13: ifeq          20
      16: iconst_1
      17: goto          21
      20: iconst_0
      21: ireturn

  public static boolean isPrivate(java.lang.reflect.Member);
    Code:
       0: aload_0
       1: ifnull        20
       4: aload_0
       5: invokeinterface #1,  1            // InterfaceMethod java/lang/reflect/Member.getModifiers:()I
      10: invokestatic  #3                  // Method java/lang/reflect/Modifier.isPrivate:(I)Z
      13: ifeq          20
      16: iconst_1
      17: goto          21
      20: iconst_0
      21: ireturn

  public static boolean isPublic(java.lang.reflect.Member);
    Code:
       0: aload_0
       1: ifnull        20
       4: aload_0
       5: invokeinterface #1,  1            // InterfaceMethod java/lang/reflect/Member.getModifiers:()I
      10: invokestatic  #4                  // Method java/lang/reflect/Modifier.isPublic:(I)Z
      13: ifeq          20
      16: iconst_1
      17: goto          21
      20: iconst_0
      21: ireturn
}
