Compiled from "NativeUtils.java"
public abstract class org.apache.dubbo.common.utils.NativeUtils {
  public org.apache.dubbo.common.utils.NativeUtils();
    Code:
       0: aload_0
       1: invokespecial #2                  // Method java/lang/Object."<init>":()V
       4: return

  public static boolean isNative();
    Code:
       0: ldc           #3                  // String native
       2: ldc           #4                  // String false
       4: invokestatic  #5                  // Method java/lang/System.getProperty:(Ljava/lang/String;Ljava/lang/String;)Ljava/lang/String;
       7: invokestatic  #6                  // Method java/lang/Boolean.parseBoolean:(Ljava/lang/String;)Z
      10: ireturn
}
