Compiled from "NetUtils.java"
public final class org.apache.dubbo.common.utils.NetUtils {
  private static org.apache.dubbo.common.logger.Logger logger;

  private static final int RND_PORT_START;

  private static final int RND_PORT_RANGE;

  private static final int MIN_PORT;

  private static final int MAX_PORT;

  private static final java.util.regex.Pattern ADDRESS_PATTERN;

  private static final java.util.regex.Pattern LOCAL_IP_PATTERN;

  private static final java.util.regex.Pattern IP_PATTERN;

  private static final java.util.Map<java.lang.String, java.lang.String> HOST_NAME_CACHE;

  private static volatile java.net.InetAddress LOCAL_ADDRESS;

  private static volatile java.net.Inet6Address LOCAL_ADDRESS_V6;

  private static final java.lang.String SPLIT_IPV4_CHARACTER;

  private static final java.lang.String SPLIT_IPV6_CHARACTER;

  private static java.util.BitSet USED_PORT;

  private static volatile java.lang.String HOST_ADDRESS;

  private static volatile java.lang.String HOST_NAME;

  private static volatile java.lang.String HOST_ADDRESS_V6;

  private org.apache.dubbo.common.utils.NetUtils();
    Code:
       0: aload_0
       1: invokespecial #2                  // Method java/lang/Object."<init>":()V
       4: new           #3                  // class java/lang/UnsupportedOperationException
       7: dup
       8: ldc           #4                  // String No instance of \'NetUtils\' for you!
      10: invokespecial #5                  // Method java/lang/UnsupportedOperationException."<init>":(Ljava/lang/String;)V
      13: athrow

  public static int getRandomPort();
    Code:
       0: sipush        30000
       3: invokestatic  #7                  // Method java/util/concurrent/ThreadLocalRandom.current:()Ljava/util/concurrent/ThreadLocalRandom;
       6: sipush        10000
       9: invokevirtual #8                  // Method java/util/concurrent/ThreadLocalRandom.nextInt:(I)I
      12: iadd
      13: ireturn

  public static synchronized int getAvailablePort();
    Code:
       0: invokestatic  #9                  // Method getRandomPort:()I
       3: istore_0
       4: iload_0
       5: invokestatic  #10                 // Method getAvailablePort:(I)I
       8: ireturn

  public static synchronized int getAvailablePort(int);
    Code:
       0: iload_0
       1: iconst_1
       2: if_icmpge     7
       5: iconst_1
       6: ireturn
       7: iload_0
       8: istore_1
       9: iload_1
      10: ldc           #11                 // int 65535
      12: if_icmpge     131
      15: getstatic     #12                 // Field USED_PORT:Ljava/util/BitSet;
      18: iload_1
      19: invokevirtual #13                 // Method java/util/BitSet.get:(I)Z
      22: ifeq          28
      25: goto          125
      28: new           #14                 // class java/net/ServerSocket
      31: dup
      32: iload_1
      33: invokespecial #15                 // Method java/net/ServerSocket."<init>":(I)V
      36: astore_2
      37: aconst_null
      38: astore_3
      39: getstatic     #12                 // Field USED_PORT:Ljava/util/BitSet;
      42: iload_1
      43: invokevirtual #16                 // Method java/util/BitSet.set:(I)V
      46: iload_1
      47: istore_0
      48: aload_2
      49: ifnull        78
      52: aload_3
      53: ifnull        74
      56: aload_2
      57: invokevirtual #17                 // Method java/net/ServerSocket.close:()V
      60: goto          78
      63: astore        4
      65: aload_3
      66: aload         4
      68: invokevirtual #19                 // Method java/lang/Throwable.addSuppressed:(Ljava/lang/Throwable;)V
      71: goto          78
      74: aload_2
      75: invokevirtual #17                 // Method java/net/ServerSocket.close:()V
      78: goto          131
      81: astore        4
      83: aload         4
      85: astore_3
      86: aload         4
      88: athrow
      89: astore        5
      91: aload_2
      92: ifnull        121
      95: aload_3
      96: ifnull        117
      99: aload_2
     100: invokevirtual #17                 // Method java/net/ServerSocket.close:()V
     103: goto          121
     106: astore        6
     108: aload_3
     109: aload         6
     111: invokevirtual #19                 // Method java/lang/Throwable.addSuppressed:(Ljava/lang/Throwable;)V
     114: goto          121
     117: aload_2
     118: invokevirtual #17                 // Method java/net/ServerSocket.close:()V
     121: aload         5
     123: athrow
     124: astore_2
     125: iinc          1, 1
     128: goto          9
     131: iload_0
     132: ireturn
    Exception table:
       from    to  target type
          56    60    63   Class java/lang/Throwable
          39    48    81   Class java/lang/Throwable
          39    48    89   any
          99   103   106   Class java/lang/Throwable
          81    91    89   any
          28    78   124   Class java/io/IOException
          81   124   124   Class java/io/IOException

  public static boolean isPortInUsed(int);
    Code:
       0: new           #14                 // class java/net/ServerSocket
       3: dup
       4: iload_0
       5: invokespecial #15                 // Method java/net/ServerSocket."<init>":(I)V
       8: astore_1
       9: aconst_null
      10: astore_2
      11: iconst_0
      12: istore_3
      13: aload_1
      14: ifnull        43
      17: aload_2
      18: ifnull        39
      21: aload_1
      22: invokevirtual #17                 // Method java/net/ServerSocket.close:()V
      25: goto          43
      28: astore        4
      30: aload_2
      31: aload         4
      33: invokevirtual #19                 // Method java/lang/Throwable.addSuppressed:(Ljava/lang/Throwable;)V
      36: goto          43
      39: aload_1
      40: invokevirtual #17                 // Method java/net/ServerSocket.close:()V
      43: iload_3
      44: ireturn
      45: astore_3
      46: aload_3
      47: astore_2
      48: aload_3
      49: athrow
      50: astore        5
      52: aload_1
      53: ifnull        82
      56: aload_2
      57: ifnull        78
      60: aload_1
      61: invokevirtual #17                 // Method java/net/ServerSocket.close:()V
      64: goto          82
      67: astore        6
      69: aload_2
      70: aload         6
      72: invokevirtual #19                 // Method java/lang/Throwable.addSuppressed:(Ljava/lang/Throwable;)V
      75: goto          82
      78: aload_1
      79: invokevirtual #17                 // Method java/net/ServerSocket.close:()V
      82: aload         5
      84: athrow
      85: astore_1
      86: iconst_1
      87: ireturn
    Exception table:
       from    to  target type
          21    25    28   Class java/lang/Throwable
          11    13    45   Class java/lang/Throwable
          11    13    50   any
          60    64    67   Class java/lang/Throwable
          45    52    50   any
           0    43    85   Class java/io/IOException
          45    85    85   Class java/io/IOException

  public static boolean isInvalidPort(int);
    Code:
       0: iload_0
       1: iconst_1
       2: if_icmplt     11
       5: iload_0
       6: ldc           #11                 // int 65535
       8: if_icmple     15
      11: iconst_1
      12: goto          16
      15: iconst_0
      16: ireturn

  public static boolean isValidAddress(java.lang.String);
    Code:
       0: getstatic     #21                 // Field ADDRESS_PATTERN:Ljava/util/regex/Pattern;
       3: aload_0
       4: invokevirtual #22                 // Method java/util/regex/Pattern.matcher:(Ljava/lang/CharSequence;)Ljava/util/regex/Matcher;
       7: invokevirtual #23                 // Method java/util/regex/Matcher.matches:()Z
      10: ireturn

  public static boolean isLocalHost(java.lang.String);
    Code:
       0: aload_0
       1: ifnull        30
       4: getstatic     #24                 // Field LOCAL_IP_PATTERN:Ljava/util/regex/Pattern;
       7: aload_0
       8: invokevirtual #22                 // Method java/util/regex/Pattern.matcher:(Ljava/lang/CharSequence;)Ljava/util/regex/Matcher;
      11: invokevirtual #23                 // Method java/util/regex/Matcher.matches:()Z
      14: ifne          26
      17: aload_0
      18: ldc           #25                 // String localhost
      20: invokevirtual #26                 // Method java/lang/String.equalsIgnoreCase:(Ljava/lang/String;)Z
      23: ifeq          30
      26: iconst_1
      27: goto          31
      30: iconst_0
      31: ireturn

  public static boolean isAnyHost(java.lang.String);
    Code:
       0: ldc           #27                 // String 0.0.0.0
       2: aload_0
       3: invokevirtual #28                 // Method java/lang/String.equals:(Ljava/lang/Object;)Z
       6: ireturn

  public static boolean isInvalidLocalHost(java.lang.String);
    Code:
       0: aload_0
       1: ifnull        38
       4: aload_0
       5: invokevirtual #29                 // Method java/lang/String.length:()I
       8: ifeq          38
      11: aload_0
      12: ldc           #25                 // String localhost
      14: invokevirtual #26                 // Method java/lang/String.equalsIgnoreCase:(Ljava/lang/String;)Z
      17: ifne          38
      20: aload_0
      21: ldc           #27                 // String 0.0.0.0
      23: invokevirtual #28                 // Method java/lang/String.equals:(Ljava/lang/Object;)Z
      26: ifne          38
      29: aload_0
      30: ldc           #30                 // String 127.
      32: invokevirtual #31                 // Method java/lang/String.startsWith:(Ljava/lang/String;)Z
      35: ifeq          42
      38: iconst_1
      39: goto          43
      42: iconst_0
      43: ireturn

  public static boolean isValidLocalHost(java.lang.String);
    Code:
       0: aload_0
       1: invokestatic  #32                 // Method isInvalidLocalHost:(Ljava/lang/String;)Z
       4: ifne          11
       7: iconst_1
       8: goto          12
      11: iconst_0
      12: ireturn

  public static java.net.InetSocketAddress getLocalSocketAddress(java.lang.String, int);
    Code:
       0: aload_0
       1: invokestatic  #32                 // Method isInvalidLocalHost:(Ljava/lang/String;)Z
       4: ifeq          18
       7: new           #33                 // class java/net/InetSocketAddress
      10: dup
      11: iload_1
      12: invokespecial #34                 // Method java/net/InetSocketAddress."<init>":(I)V
      15: goto          27
      18: new           #33                 // class java/net/InetSocketAddress
      21: dup
      22: aload_0
      23: iload_1
      24: invokespecial #35                 // Method java/net/InetSocketAddress."<init>":(Ljava/lang/String;I)V
      27: areturn

  static boolean isValidV4Address(java.net.InetAddress);
    Code:
       0: aload_0
       1: ifnull        11
       4: aload_0
       5: invokevirtual #36                 // Method java/net/InetAddress.isLoopbackAddress:()Z
       8: ifeq          13
      11: iconst_0
      12: ireturn
      13: aload_0
      14: invokevirtual #37                 // Method java/net/InetAddress.getHostAddress:()Ljava/lang/String;
      17: astore_1
      18: aload_1
      19: ifnull        57
      22: getstatic     #38                 // Field IP_PATTERN:Ljava/util/regex/Pattern;
      25: aload_1
      26: invokevirtual #22                 // Method java/util/regex/Pattern.matcher:(Ljava/lang/CharSequence;)Ljava/util/regex/Matcher;
      29: invokevirtual #23                 // Method java/util/regex/Matcher.matches:()Z
      32: ifeq          57
      35: ldc           #27                 // String 0.0.0.0
      37: aload_1
      38: invokevirtual #28                 // Method java/lang/String.equals:(Ljava/lang/Object;)Z
      41: ifne          57
      44: ldc           #39                 // String 127.0.0.1
      46: aload_1
      47: invokevirtual #28                 // Method java/lang/String.equals:(Ljava/lang/Object;)Z
      50: ifne          57
      53: iconst_1
      54: goto          58
      57: iconst_0
      58: ireturn

  static boolean isPreferIPV6Address();
    Code:
       0: ldc           #40                 // String java.net.preferIPv6Addresses
       2: invokestatic  #41                 // Method java/lang/Boolean.getBoolean:(Ljava/lang/String;)Z
       5: ireturn

  static java.net.InetAddress normalizeV6Address(java.net.Inet6Address);
    Code:
       0: aload_0
       1: invokevirtual #42                 // Method java/net/Inet6Address.getHostAddress:()Ljava/lang/String;
       4: astore_1
       5: aload_1
       6: bipush        37
       8: invokevirtual #43                 // Method java/lang/String.lastIndexOf:(I)I
      11: istore_2
      12: iload_2
      13: ifle          63
      16: new           #44                 // class java/lang/StringBuilder
      19: dup
      20: invokespecial #45                 // Method java/lang/StringBuilder."<init>":()V
      23: aload_1
      24: iconst_0
      25: iload_2
      26: invokevirtual #46                 // Method java/lang/String.substring:(II)Ljava/lang/String;
      29: invokevirtual #47                 // Method java/lang/StringBuilder.append:(Ljava/lang/String;)Ljava/lang/StringBuilder;
      32: bipush        37
      34: invokevirtual #48                 // Method java/lang/StringBuilder.append:(C)Ljava/lang/StringBuilder;
      37: aload_0
      38: invokevirtual #49                 // Method java/net/Inet6Address.getScopeId:()I
      41: invokevirtual #50                 // Method java/lang/StringBuilder.append:(I)Ljava/lang/StringBuilder;
      44: invokevirtual #51                 // Method java/lang/StringBuilder.toString:()Ljava/lang/String;
      47: invokestatic  #52                 // Method java/net/InetAddress.getByName:(Ljava/lang/String;)Ljava/net/InetAddress;
      50: areturn
      51: astore_3
      52: getstatic     #54                 // Field logger:Lorg/apache/dubbo/common/logger/Logger;
      55: ldc           #55                 // String Unknown IPV6 address:
      57: aload_3
      58: invokeinterface #56,  3           // InterfaceMethod org/apache/dubbo/common/logger/Logger.debug:(Ljava/lang/String;Ljava/lang/Throwable;)V
      63: aload_0
      64: areturn
    Exception table:
       from    to  target type
          16    50    51   Class java/net/UnknownHostException

  public static java.lang.String getLocalHost();
    Code:
       0: getstatic     #57                 // Field HOST_ADDRESS:Ljava/lang/String;
       3: ifnull        10
       6: getstatic     #57                 // Field HOST_ADDRESS:Ljava/lang/String;
       9: areturn
      10: invokestatic  #58                 // Method getLocalAddress:()Ljava/net/InetAddress;
      13: astore_0
      14: aload_0
      15: ifnull        70
      18: aload_0
      19: instanceof    #59                 // class java/net/Inet6Address
      22: ifeq          59
      25: aload_0
      26: invokevirtual #37                 // Method java/net/InetAddress.getHostAddress:()Ljava/lang/String;
      29: astore_1
      30: aload_1
      31: ldc           #60                 // String %
      33: invokevirtual #61                 // Method java/lang/String.contains:(Ljava/lang/CharSequence;)Z
      36: ifeq          51
      39: aload_1
      40: iconst_0
      41: aload_1
      42: ldc           #60                 // String %
      44: invokevirtual #62                 // Method java/lang/String.indexOf:(Ljava/lang/String;)I
      47: invokevirtual #46                 // Method java/lang/String.substring:(II)Ljava/lang/String;
      50: astore_1
      51: aload_1
      52: putstatic     #57                 // Field HOST_ADDRESS:Ljava/lang/String;
      55: getstatic     #57                 // Field HOST_ADDRESS:Ljava/lang/String;
      58: areturn
      59: aload_0
      60: invokevirtual #37                 // Method java/net/InetAddress.getHostAddress:()Ljava/lang/String;
      63: putstatic     #57                 // Field HOST_ADDRESS:Ljava/lang/String;
      66: getstatic     #57                 // Field HOST_ADDRESS:Ljava/lang/String;
      69: areturn
      70: ldc           #39                 // String 127.0.0.1
      72: areturn

  public static java.lang.String getLocalHostV6();
    Code:
       0: getstatic     #63                 // Field HOST_ADDRESS_V6:Ljava/lang/String;
       3: invokestatic  #64                 // Method org/apache/dubbo/common/utils/StringUtils.isNotEmpty:(Ljava/lang/String;)Z
       6: ifeq          13
       9: getstatic     #63                 // Field HOST_ADDRESS_V6:Ljava/lang/String;
      12: areturn
      13: ldc           #65                 // String
      15: getstatic     #63                 // Field HOST_ADDRESS_V6:Ljava/lang/String;
      18: invokevirtual #28                 // Method java/lang/String.equals:(Ljava/lang/Object;)Z
      21: ifeq          26
      24: aconst_null
      25: areturn
      26: invokestatic  #66                 // Method getLocalAddressV6:()Ljava/net/Inet6Address;
      29: astore_0
      30: aload_0
      31: ifnull        68
      34: aload_0
      35: invokevirtual #42                 // Method java/net/Inet6Address.getHostAddress:()Ljava/lang/String;
      38: astore_1
      39: aload_1
      40: ldc           #60                 // String %
      42: invokevirtual #61                 // Method java/lang/String.contains:(Ljava/lang/CharSequence;)Z
      45: ifeq          60
      48: aload_1
      49: iconst_0
      50: aload_1
      51: ldc           #60                 // String %
      53: invokevirtual #62                 // Method java/lang/String.indexOf:(Ljava/lang/String;)I
      56: invokevirtual #46                 // Method java/lang/String.substring:(II)Ljava/lang/String;
      59: astore_1
      60: aload_1
      61: putstatic     #63                 // Field HOST_ADDRESS_V6:Ljava/lang/String;
      64: getstatic     #63                 // Field HOST_ADDRESS_V6:Ljava/lang/String;
      67: areturn
      68: ldc           #65                 // String
      70: putstatic     #63                 // Field HOST_ADDRESS_V6:Ljava/lang/String;
      73: aconst_null
      74: areturn

  public static java.lang.String filterLocalHost(java.lang.String);
    Code:
       0: aload_0
       1: ifnull        11
       4: aload_0
       5: invokevirtual #29                 // Method java/lang/String.length:()I
       8: ifne          13
      11: aload_0
      12: areturn
      13: aload_0
      14: ldc           #67                 // String ://
      16: invokevirtual #61                 // Method java/lang/String.contains:(Ljava/lang/CharSequence;)Z
      19: ifeq          51
      22: aload_0
      23: invokestatic  #68                 // Method org/apache/dubbo/common/URL.valueOf:(Ljava/lang/String;)Lorg/apache/dubbo/common/URL;
      26: astore_1
      27: aload_1
      28: invokevirtual #69                 // Method org/apache/dubbo/common/URL.getHost:()Ljava/lang/String;
      31: invokestatic  #32                 // Method isInvalidLocalHost:(Ljava/lang/String;)Z
      34: ifeq          48
      37: aload_1
      38: invokestatic  #70                 // Method getLocalHost:()Ljava/lang/String;
      41: invokevirtual #71                 // Method org/apache/dubbo/common/URL.setHost:(Ljava/lang/String;)Lorg/apache/dubbo/common/URL;
      44: invokevirtual #72                 // Method org/apache/dubbo/common/URL.toFullString:()Ljava/lang/String;
      47: areturn
      48: goto          118
      51: aload_0
      52: ldc           #73                 // String :
      54: invokevirtual #61                 // Method java/lang/String.contains:(Ljava/lang/CharSequence;)Z
      57: ifeq          107
      60: aload_0
      61: bipush        58
      63: invokevirtual #43                 // Method java/lang/String.lastIndexOf:(I)I
      66: istore_1
      67: aload_0
      68: iconst_0
      69: iload_1
      70: invokevirtual #46                 // Method java/lang/String.substring:(II)Ljava/lang/String;
      73: invokestatic  #32                 // Method isInvalidLocalHost:(Ljava/lang/String;)Z
      76: ifeq          104
      79: new           #44                 // class java/lang/StringBuilder
      82: dup
      83: invokespecial #45                 // Method java/lang/StringBuilder."<init>":()V
      86: invokestatic  #70                 // Method getLocalHost:()Ljava/lang/String;
      89: invokevirtual #47                 // Method java/lang/StringBuilder.append:(Ljava/lang/String;)Ljava/lang/StringBuilder;
      92: aload_0
      93: iload_1
      94: invokevirtual #74                 // Method java/lang/String.substring:(I)Ljava/lang/String;
      97: invokevirtual #47                 // Method java/lang/StringBuilder.append:(Ljava/lang/String;)Ljava/lang/StringBuilder;
     100: invokevirtual #51                 // Method java/lang/StringBuilder.toString:()Ljava/lang/String;
     103: areturn
     104: goto          118
     107: aload_0
     108: invokestatic  #32                 // Method isInvalidLocalHost:(Ljava/lang/String;)Z
     111: ifeq          118
     114: invokestatic  #70                 // Method getLocalHost:()Ljava/lang/String;
     117: areturn
     118: aload_0
     119: areturn

  public static java.lang.String getIpByConfig(org.apache.dubbo.rpc.model.ScopeModel);
    Code:
       0: aload_0
       1: ldc           #75                 // String DUBBO_IP_TO_BIND
       3: invokestatic  #76                 // Method org/apache/dubbo/common/config/ConfigurationUtils.getProperty:(Lorg/apache/dubbo/rpc/model/ScopeModel;Ljava/lang/String;)Ljava/lang/String;
       6: astore_1
       7: aload_1
       8: ifnull        13
      11: aload_1
      12: areturn
      13: invokestatic  #70                 // Method getLocalHost:()Ljava/lang/String;
      16: areturn

  public static java.net.InetAddress getLocalAddress();
    Code:
       0: getstatic     #77                 // Field LOCAL_ADDRESS:Ljava/net/InetAddress;
       3: ifnull        10
       6: getstatic     #77                 // Field LOCAL_ADDRESS:Ljava/net/InetAddress;
       9: areturn
      10: invokestatic  #78                 // Method getLocalAddress0:()Ljava/net/InetAddress;
      13: astore_0
      14: aload_0
      15: putstatic     #77                 // Field LOCAL_ADDRESS:Ljava/net/InetAddress;
      18: aload_0
      19: areturn

  public static java.net.Inet6Address getLocalAddressV6();
    Code:
       0: getstatic     #79                 // Field LOCAL_ADDRESS_V6:Ljava/net/Inet6Address;
       3: ifnull        10
       6: getstatic     #79                 // Field LOCAL_ADDRESS_V6:Ljava/net/Inet6Address;
       9: areturn
      10: invokestatic  #80                 // Method getLocalAddress0V6:()Ljava/net/Inet6Address;
      13: astore_0
      14: aload_0
      15: putstatic     #79                 // Field LOCAL_ADDRESS_V6:Ljava/net/Inet6Address;
      18: aload_0
      19: areturn

  private static java.util.Optional<java.net.InetAddress> toValidAddress(java.net.InetAddress);
    Code:
       0: aload_0
       1: instanceof    #59                 // class java/net/Inet6Address
       4: ifeq          26
       7: aload_0
       8: checkcast     #59                 // class java/net/Inet6Address
      11: astore_1
      12: invokestatic  #81                 // Method isPreferIPV6Address:()Z
      15: ifeq          26
      18: aload_1
      19: invokestatic  #82                 // Method normalizeV6Address:(Ljava/net/Inet6Address;)Ljava/net/InetAddress;
      22: invokestatic  #83                 // Method java/util/Optional.ofNullable:(Ljava/lang/Object;)Ljava/util/Optional;
      25: areturn
      26: aload_0
      27: invokestatic  #84                 // Method isValidV4Address:(Ljava/net/InetAddress;)Z
      30: ifeq          38
      33: aload_0
      34: invokestatic  #85                 // Method java/util/Optional.of:(Ljava/lang/Object;)Ljava/util/Optional;
      37: areturn
      38: invokestatic  #86                 // Method java/util/Optional.empty:()Ljava/util/Optional;
      41: areturn

  private static java.net.InetAddress getLocalAddress0();
    Code:
       0: aconst_null
       1: astore_0
       2: invokestatic  #87                 // Method findNetworkInterface:()Ljava/net/NetworkInterface;
       5: astore_1
       6: aload_1
       7: invokevirtual #88                 // Method java/net/NetworkInterface.getInetAddresses:()Ljava/util/Enumeration;
      10: astore_2
      11: aload_2
      12: invokeinterface #89,  1           // InterfaceMethod java/util/Enumeration.hasMoreElements:()Z
      17: ifeq          71
      20: aload_2
      21: invokeinterface #90,  1           // InterfaceMethod java/util/Enumeration.nextElement:()Ljava/lang/Object;
      26: checkcast     #91                 // class java/net/InetAddress
      29: invokestatic  #92                 // Method toValidAddress:(Ljava/net/InetAddress;)Ljava/util/Optional;
      32: astore_3
      33: aload_3
      34: invokevirtual #93                 // Method java/util/Optional.isPresent:()Z
      37: ifeq          68
      40: aload_3
      41: invokevirtual #94                 // Method java/util/Optional.get:()Ljava/lang/Object;
      44: checkcast     #91                 // class java/net/InetAddress
      47: bipush        100
      49: invokevirtual #95                 // Method java/net/InetAddress.isReachable:(I)Z
      52: ifeq          63
      55: aload_3
      56: invokevirtual #94                 // Method java/util/Optional.get:()Ljava/lang/Object;
      59: checkcast     #91                 // class java/net/InetAddress
      62: areturn
      63: goto          68
      66: astore        4
      68: goto          11
      71: goto          84
      74: astore_1
      75: getstatic     #54                 // Field logger:Lorg/apache/dubbo/common/logger/Logger;
      78: aload_1
      79: invokeinterface #96,  2           // InterfaceMethod org/apache/dubbo/common/logger/Logger.warn:(Ljava/lang/Throwable;)V
      84: invokestatic  #97                 // Method java/net/InetAddress.getLocalHost:()Ljava/net/InetAddress;
      87: astore_0
      88: aload_0
      89: invokestatic  #92                 // Method toValidAddress:(Ljava/net/InetAddress;)Ljava/util/Optional;
      92: astore_1
      93: aload_1
      94: invokevirtual #93                 // Method java/util/Optional.isPresent:()Z
      97: ifeq          108
     100: aload_1
     101: invokevirtual #94                 // Method java/util/Optional.get:()Ljava/lang/Object;
     104: checkcast     #91                 // class java/net/InetAddress
     107: areturn
     108: goto          121
     111: astore_1
     112: getstatic     #54                 // Field logger:Lorg/apache/dubbo/common/logger/Logger;
     115: aload_1
     116: invokeinterface #96,  2           // InterfaceMethod org/apache/dubbo/common/logger/Logger.warn:(Ljava/lang/Throwable;)V
     121: invokestatic  #66                 // Method getLocalAddressV6:()Ljava/net/Inet6Address;
     124: astore_0
     125: aload_0
     126: areturn
    Exception table:
       from    to  target type
          40    62    66   Class java/io/IOException
           2    62    74   Class java/lang/Throwable
          63    71    74   Class java/lang/Throwable
          84   107   111   Class java/lang/Throwable

  private static java.net.Inet6Address getLocalAddress0V6();
    Code:
       0: invokestatic  #87                 // Method findNetworkInterface:()Ljava/net/NetworkInterface;
       3: astore_0
       4: aload_0
       5: invokevirtual #88                 // Method java/net/NetworkInterface.getInetAddresses:()Ljava/util/Enumeration;
       8: astore_1
       9: aload_1
      10: invokeinterface #89,  1           // InterfaceMethod java/util/Enumeration.hasMoreElements:()Z
      15: ifeq          90
      18: aload_1
      19: invokeinterface #90,  1           // InterfaceMethod java/util/Enumeration.nextElement:()Ljava/lang/Object;
      24: checkcast     #91                 // class java/net/InetAddress
      27: astore_2
      28: aload_2
      29: instanceof    #59                 // class java/net/Inet6Address
      32: ifeq          87
      35: aload_2
      36: invokevirtual #36                 // Method java/net/InetAddress.isLoopbackAddress:()Z
      39: ifne          87
      42: aload_2
      43: invokevirtual #98                 // Method java/net/InetAddress.isAnyLocalAddress:()Z
      46: ifne          87
      49: aload_2
      50: invokevirtual #99                 // Method java/net/InetAddress.isLinkLocalAddress:()Z
      53: ifne          87
      56: aload_2
      57: invokevirtual #100                // Method java/net/InetAddress.isSiteLocalAddress:()Z
      60: ifne          87
      63: aload_2
      64: invokestatic  #101                // Method isUniqueLocalAddress:(Ljava/net/InetAddress;)Z
      67: ifne          87
      70: aload_2
      71: invokevirtual #37                 // Method java/net/InetAddress.getHostAddress:()Ljava/lang/String;
      74: ldc           #73                 // String :
      76: invokevirtual #61                 // Method java/lang/String.contains:(Ljava/lang/CharSequence;)Z
      79: ifeq          87
      82: aload_2
      83: checkcast     #59                 // class java/net/Inet6Address
      86: areturn
      87: goto          9
      90: goto          103
      93: astore_0
      94: getstatic     #54                 // Field logger:Lorg/apache/dubbo/common/logger/Logger;
      97: aload_0
      98: invokeinterface #96,  2           // InterfaceMethod org/apache/dubbo/common/logger/Logger.warn:(Ljava/lang/Throwable;)V
     103: aconst_null
     104: areturn
    Exception table:
       from    to  target type
           0    86    93   Class java/lang/Throwable
          87    90    93   Class java/lang/Throwable

  private static boolean isUniqueLocalAddress(java.net.InetAddress);
    Code:
       0: aload_0
       1: invokevirtual #102                // Method java/net/InetAddress.getAddress:()[B
       4: astore_1
       5: aload_1
       6: iconst_0
       7: baload
       8: sipush        255
      11: iand
      12: sipush        253
      15: if_icmpne     22
      18: iconst_1
      19: goto          23
      22: iconst_0
      23: ireturn

  private static boolean ignoreNetworkInterface(java.net.NetworkInterface) throws java.net.SocketException;
    Code:
       0: aload_0
       1: ifnull        25
       4: aload_0
       5: invokevirtual #103                // Method java/net/NetworkInterface.isLoopback:()Z
       8: ifne          25
      11: aload_0
      12: invokevirtual #104                // Method java/net/NetworkInterface.isVirtual:()Z
      15: ifne          25
      18: aload_0
      19: invokevirtual #105                // Method java/net/NetworkInterface.isUp:()Z
      22: ifne          27
      25: iconst_1
      26: ireturn
      27: ldc           #106                // String dubbo.network.interface.ignored
      29: invokestatic  #107                // Method java/lang/System.getProperty:(Ljava/lang/String;)Ljava/lang/String;
      32: astore_1
      33: aload_1
      34: invokestatic  #64                 // Method org/apache/dubbo/common/utils/StringUtils.isNotEmpty:(Ljava/lang/String;)Z
      37: ifeq          203
      40: aload_0
      41: invokevirtual #108                // Method java/net/NetworkInterface.getDisplayName:()Ljava/lang/String;
      44: dup
      45: astore_2
      46: invokestatic  #64                 // Method org/apache/dubbo/common/utils/StringUtils.isNotEmpty:(Ljava/lang/String;)Z
      49: ifeq          203
      52: aload_1
      53: ldc           #109                // String ,
      55: invokevirtual #110                // Method java/lang/String.split:(Ljava/lang/String;)[Ljava/lang/String;
      58: astore_3
      59: aload_3
      60: arraylength
      61: istore        4
      63: iconst_0
      64: istore        5
      66: iload         5
      68: iload         4
      70: if_icmpge     203
      73: aload_3
      74: iload         5
      76: aaload
      77: astore        6
      79: aload         6
      81: invokevirtual #111                // Method java/lang/String.trim:()Ljava/lang/String;
      84: astore        7
      86: iconst_0
      87: istore        8
      89: aload_2
      90: aload         7
      92: invokevirtual #112                // Method java/lang/String.matches:(Ljava/lang/String;)Z
      95: istore        8
      97: iload         8
      99: ifeq          104
     102: iconst_1
     103: ireturn
     104: aload_2
     105: aload         7
     107: invokevirtual #28                 // Method java/lang/String.equals:(Ljava/lang/Object;)Z
     110: ifeq          197
     113: iconst_1
     114: ireturn
     115: astore        9
     117: getstatic     #54                 // Field logger:Lorg/apache/dubbo/common/logger/Logger;
     120: new           #44                 // class java/lang/StringBuilder
     123: dup
     124: invokespecial #45                 // Method java/lang/StringBuilder."<init>":()V
     127: ldc           #114                // String exception occurred:
     129: invokevirtual #47                 // Method java/lang/StringBuilder.append:(Ljava/lang/String;)Ljava/lang/StringBuilder;
     132: aload_2
     133: invokevirtual #47                 // Method java/lang/StringBuilder.append:(Ljava/lang/String;)Ljava/lang/StringBuilder;
     136: ldc           #115                // String  matches
     138: invokevirtual #47                 // Method java/lang/StringBuilder.append:(Ljava/lang/String;)Ljava/lang/StringBuilder;
     141: aload         7
     143: invokevirtual #47                 // Method java/lang/StringBuilder.append:(Ljava/lang/String;)Ljava/lang/StringBuilder;
     146: invokevirtual #51                 // Method java/lang/StringBuilder.toString:()Ljava/lang/String;
     149: aload         9
     151: invokeinterface #116,  3          // InterfaceMethod org/apache/dubbo/common/logger/Logger.warn:(Ljava/lang/String;Ljava/lang/Throwable;)V
     156: iload         8
     158: ifeq          163
     161: iconst_1
     162: ireturn
     163: aload_2
     164: aload         7
     166: invokevirtual #28                 // Method java/lang/String.equals:(Ljava/lang/Object;)Z
     169: ifeq          197
     172: iconst_1
     173: ireturn
     174: astore        10
     176: iload         8
     178: ifeq          183
     181: iconst_1
     182: ireturn
     183: aload_2
     184: aload         7
     186: invokevirtual #28                 // Method java/lang/String.equals:(Ljava/lang/Object;)Z
     189: ifeq          194
     192: iconst_1
     193: ireturn
     194: aload         10
     196: athrow
     197: iinc          5, 1
     200: goto          66
     203: iconst_0
     204: ireturn
    Exception table:
       from    to  target type
          89    97   115   Class java/util/regex/PatternSyntaxException
          89    97   174   any
         115   156   174   any
         174   176   174   any

  private static java.util.List<java.net.NetworkInterface> getValidNetworkInterfaces() throws java.net.SocketException;
    Code:
       0: new           #117                // class java/util/LinkedList
       3: dup
       4: invokespecial #118                // Method java/util/LinkedList."<init>":()V
       7: astore_0
       8: invokestatic  #119                // Method java/net/NetworkInterface.getNetworkInterfaces:()Ljava/util/Enumeration;
      11: astore_1
      12: aload_1
      13: invokeinterface #89,  1           // InterfaceMethod java/util/Enumeration.hasMoreElements:()Z
      18: ifeq          52
      21: aload_1
      22: invokeinterface #90,  1           // InterfaceMethod java/util/Enumeration.nextElement:()Ljava/lang/Object;
      27: checkcast     #120                // class java/net/NetworkInterface
      30: astore_2
      31: aload_2
      32: invokestatic  #121                // Method ignoreNetworkInterface:(Ljava/net/NetworkInterface;)Z
      35: ifeq          41
      38: goto          12
      41: aload_0
      42: aload_2
      43: invokeinterface #122,  2          // InterfaceMethod java/util/List.add:(Ljava/lang/Object;)Z
      48: pop
      49: goto          12
      52: aload_0
      53: areturn

  public static boolean isPreferredNetworkInterface(java.net.NetworkInterface);
    Code:
       0: ldc           #123                // String dubbo.network.interface.preferred
       2: invokestatic  #107                // Method java/lang/System.getProperty:(Ljava/lang/String;)Ljava/lang/String;
       5: astore_1
       6: aload_0
       7: invokevirtual #108                // Method java/net/NetworkInterface.getDisplayName:()Ljava/lang/String;
      10: aload_1
      11: invokestatic  #124                // Method java/util/Objects.equals:(Ljava/lang/Object;Ljava/lang/Object;)Z
      14: ireturn

  public static java.net.NetworkInterface findNetworkInterface();
    Code:
       0: invokestatic  #125                // Method java/util/Collections.emptyList:()Ljava/util/List;
       3: astore_0
       4: invokestatic  #126                // Method getValidNetworkInterfaces:()Ljava/util/List;
       7: astore_0
       8: goto          21
      11: astore_1
      12: getstatic     #54                 // Field logger:Lorg/apache/dubbo/common/logger/Logger;
      15: aload_1
      16: invokeinterface #96,  2           // InterfaceMethod org/apache/dubbo/common/logger/Logger.warn:(Ljava/lang/Throwable;)V
      21: aconst_null
      22: astore_1
      23: aload_0
      24: invokeinterface #127,  1          // InterfaceMethod java/util/List.iterator:()Ljava/util/Iterator;
      29: astore_2
      30: aload_2
      31: invokeinterface #128,  1          // InterfaceMethod java/util/Iterator.hasNext:()Z
      36: ifeq          64
      39: aload_2
      40: invokeinterface #129,  1          // InterfaceMethod java/util/Iterator.next:()Ljava/lang/Object;
      45: checkcast     #120                // class java/net/NetworkInterface
      48: astore_3
      49: aload_3
      50: invokestatic  #130                // Method isPreferredNetworkInterface:(Ljava/net/NetworkInterface;)Z
      53: ifeq          61
      56: aload_3
      57: astore_1
      58: goto          64
      61: goto          30
      64: aload_1
      65: ifnonnull     162
      68: aload_0
      69: invokeinterface #127,  1          // InterfaceMethod java/util/List.iterator:()Ljava/util/Iterator;
      74: astore_2
      75: aload_2
      76: invokeinterface #128,  1          // InterfaceMethod java/util/Iterator.hasNext:()Z
      81: ifeq          162
      84: aload_2
      85: invokeinterface #129,  1          // InterfaceMethod java/util/Iterator.next:()Ljava/lang/Object;
      90: checkcast     #120                // class java/net/NetworkInterface
      93: astore_3
      94: aload_3
      95: invokevirtual #88                 // Method java/net/NetworkInterface.getInetAddresses:()Ljava/util/Enumeration;
      98: astore        4
     100: aload         4
     102: invokeinterface #89,  1           // InterfaceMethod java/util/Enumeration.hasMoreElements:()Z
     107: ifeq          159
     110: aload         4
     112: invokeinterface #90,  1           // InterfaceMethod java/util/Enumeration.nextElement:()Ljava/lang/Object;
     117: checkcast     #91                 // class java/net/InetAddress
     120: invokestatic  #92                 // Method toValidAddress:(Ljava/net/InetAddress;)Ljava/util/Optional;
     123: astore        5
     125: aload         5
     127: invokevirtual #93                 // Method java/util/Optional.isPresent:()Z
     130: ifeq          156
     133: aload         5
     135: invokevirtual #94                 // Method java/util/Optional.get:()Ljava/lang/Object;
     138: checkcast     #91                 // class java/net/InetAddress
     141: bipush        100
     143: invokevirtual #95                 // Method java/net/InetAddress.isReachable:(I)Z
     146: ifeq          151
     149: aload_3
     150: areturn
     151: goto          156
     154: astore        6
     156: goto          100
     159: goto          75
     162: aload_1
     163: ifnonnull     174
     166: aload_0
     167: invokestatic  #131                // Method org/apache/dubbo/common/utils/CollectionUtils.first:(Ljava/util/Collection;)Ljava/lang/Object;
     170: checkcast     #120                // class java/net/NetworkInterface
     173: astore_1
     174: aload_1
     175: areturn
    Exception table:
       from    to  target type
           4     8    11   Class java/lang/Throwable
         133   150   154   Class java/io/IOException

  public static java.lang.String getHostName(java.lang.String);
    Code:
       0: aload_0
       1: bipush        58
       3: invokevirtual #132                // Method java/lang/String.indexOf:(I)I
       6: istore_1
       7: iload_1
       8: iconst_m1
       9: if_icmple     19
      12: aload_0
      13: iconst_0
      14: iload_1
      15: invokevirtual #46                 // Method java/lang/String.substring:(II)Ljava/lang/String;
      18: astore_0
      19: getstatic     #133                // Field HOST_NAME_CACHE:Ljava/util/Map;
      22: aload_0
      23: invokeinterface #134,  2          // InterfaceMethod java/util/Map.get:(Ljava/lang/Object;)Ljava/lang/Object;
      28: checkcast     #135                // class java/lang/String
      31: astore_2
      32: aload_2
      33: ifnull        45
      36: aload_2
      37: invokevirtual #29                 // Method java/lang/String.length:()I
      40: ifle          45
      43: aload_2
      44: areturn
      45: aload_0
      46: invokestatic  #52                 // Method java/net/InetAddress.getByName:(Ljava/lang/String;)Ljava/net/InetAddress;
      49: astore_3
      50: aload_3
      51: ifnull        72
      54: aload_3
      55: invokevirtual #136                // Method java/net/InetAddress.getHostName:()Ljava/lang/String;
      58: astore_2
      59: getstatic     #133                // Field HOST_NAME_CACHE:Ljava/util/Map;
      62: aload_0
      63: aload_2
      64: invokeinterface #137,  3          // InterfaceMethod java/util/Map.put:(Ljava/lang/Object;Ljava/lang/Object;)Ljava/lang/Object;
      69: pop
      70: aload_2
      71: areturn
      72: goto          76
      75: astore_1
      76: aload_0
      77: areturn
    Exception table:
       from    to  target type
           0    44    75   Class java/lang/Throwable
          45    71    75   Class java/lang/Throwable

  public static java.lang.String getLocalHostName();
    Code:
       0: getstatic     #138                // Field HOST_NAME:Ljava/lang/String;
       3: ifnull        10
       6: getstatic     #138                // Field HOST_NAME:Ljava/lang/String;
       9: areturn
      10: invokestatic  #97                 // Method java/net/InetAddress.getLocalHost:()Ljava/net/InetAddress;
      13: invokevirtual #136                // Method java/net/InetAddress.getHostName:()Ljava/lang/String;
      16: putstatic     #138                // Field HOST_NAME:Ljava/lang/String;
      19: goto          47
      22: astore_0
      23: invokestatic  #58                 // Method getLocalAddress:()Ljava/net/InetAddress;
      26: invokestatic  #83                 // Method java/util/Optional.ofNullable:(Ljava/lang/Object;)Ljava/util/Optional;
      29: invokedynamic #139,  0            // InvokeDynamic #0:apply:()Ljava/util/function/Function;
      34: invokevirtual #140                // Method java/util/Optional.map:(Ljava/util/function/Function;)Ljava/util/Optional;
      37: aconst_null
      38: invokevirtual #141                // Method java/util/Optional.orElse:(Ljava/lang/Object;)Ljava/lang/Object;
      41: checkcast     #135                // class java/lang/String
      44: putstatic     #138                // Field HOST_NAME:Ljava/lang/String;
      47: getstatic     #138                // Field HOST_NAME:Ljava/lang/String;
      50: areturn
    Exception table:
       from    to  target type
          10    19    22   Class java/net/UnknownHostException

  public static java.lang.String getIpByHost(java.lang.String);
    Code:
       0: aload_0
       1: invokestatic  #52                 // Method java/net/InetAddress.getByName:(Ljava/lang/String;)Ljava/net/InetAddress;
       4: invokevirtual #37                 // Method java/net/InetAddress.getHostAddress:()Ljava/lang/String;
       7: areturn
       8: astore_1
       9: aload_0
      10: areturn
    Exception table:
       from    to  target type
           0     7     8   Class java/net/UnknownHostException

  public static java.lang.String toAddressString(java.net.InetSocketAddress);
    Code:
       0: new           #44                 // class java/lang/StringBuilder
       3: dup
       4: invokespecial #45                 // Method java/lang/StringBuilder."<init>":()V
       7: aload_0
       8: invokevirtual #142                // Method java/net/InetSocketAddress.getAddress:()Ljava/net/InetAddress;
      11: invokevirtual #37                 // Method java/net/InetAddress.getHostAddress:()Ljava/lang/String;
      14: invokevirtual #47                 // Method java/lang/StringBuilder.append:(Ljava/lang/String;)Ljava/lang/StringBuilder;
      17: ldc           #73                 // String :
      19: invokevirtual #47                 // Method java/lang/StringBuilder.append:(Ljava/lang/String;)Ljava/lang/StringBuilder;
      22: aload_0
      23: invokevirtual #143                // Method java/net/InetSocketAddress.getPort:()I
      26: invokevirtual #50                 // Method java/lang/StringBuilder.append:(I)Ljava/lang/StringBuilder;
      29: invokevirtual #51                 // Method java/lang/StringBuilder.toString:()Ljava/lang/String;
      32: areturn

  public static java.net.InetSocketAddress toAddress(java.lang.String);
    Code:
       0: aload_0
       1: bipush        58
       3: invokevirtual #132                // Method java/lang/String.indexOf:(I)I
       6: istore_1
       7: iload_1
       8: iconst_m1
       9: if_icmple     33
      12: aload_0
      13: iconst_0
      14: iload_1
      15: invokevirtual #46                 // Method java/lang/String.substring:(II)Ljava/lang/String;
      18: astore_2
      19: aload_0
      20: iload_1
      21: iconst_1
      22: iadd
      23: invokevirtual #74                 // Method java/lang/String.substring:(I)Ljava/lang/String;
      26: invokestatic  #144                // Method java/lang/Integer.parseInt:(Ljava/lang/String;)I
      29: istore_3
      30: goto          37
      33: aload_0
      34: astore_2
      35: iconst_0
      36: istore_3
      37: new           #33                 // class java/net/InetSocketAddress
      40: dup
      41: aload_2
      42: iload_3
      43: invokespecial #35                 // Method java/net/InetSocketAddress."<init>":(Ljava/lang/String;I)V
      46: areturn

  public static java.lang.String toURL(java.lang.String, java.lang.String, int, java.lang.String);
    Code:
       0: new           #44                 // class java/lang/StringBuilder
       3: dup
       4: invokespecial #45                 // Method java/lang/StringBuilder."<init>":()V
       7: astore        4
       9: aload         4
      11: aload_0
      12: invokevirtual #47                 // Method java/lang/StringBuilder.append:(Ljava/lang/String;)Ljava/lang/StringBuilder;
      15: ldc           #67                 // String ://
      17: invokevirtual #47                 // Method java/lang/StringBuilder.append:(Ljava/lang/String;)Ljava/lang/StringBuilder;
      20: pop
      21: aload         4
      23: aload_1
      24: invokevirtual #47                 // Method java/lang/StringBuilder.append:(Ljava/lang/String;)Ljava/lang/StringBuilder;
      27: bipush        58
      29: invokevirtual #48                 // Method java/lang/StringBuilder.append:(C)Ljava/lang/StringBuilder;
      32: iload_2
      33: invokevirtual #50                 // Method java/lang/StringBuilder.append:(I)Ljava/lang/StringBuilder;
      36: pop
      37: aload_3
      38: iconst_0
      39: invokevirtual #145                // Method java/lang/String.charAt:(I)C
      42: bipush        47
      44: if_icmpeq     55
      47: aload         4
      49: bipush        47
      51: invokevirtual #48                 // Method java/lang/StringBuilder.append:(C)Ljava/lang/StringBuilder;
      54: pop
      55: aload         4
      57: aload_3
      58: invokevirtual #47                 // Method java/lang/StringBuilder.append:(Ljava/lang/String;)Ljava/lang/StringBuilder;
      61: pop
      62: aload         4
      64: invokevirtual #51                 // Method java/lang/StringBuilder.toString:()Ljava/lang/String;
      67: areturn

  public static void joinMulticastGroup(java.net.MulticastSocket, java.net.InetAddress) throws java.io.IOException;
    Code:
       0: aload_0
       1: aload_1
       2: instanceof    #59                 // class java/net/Inet6Address
       5: invokestatic  #146                // Method setInterface:(Ljava/net/MulticastSocket;Z)V
       8: aload_0
       9: iconst_0
      10: invokevirtual #147                // Method java/net/MulticastSocket.setLoopbackMode:(Z)V
      13: aload_0
      14: aload_1
      15: invokevirtual #148                // Method java/net/MulticastSocket.joinGroup:(Ljava/net/InetAddress;)V
      18: return

  public static void setInterface(java.net.MulticastSocket, boolean) throws java.io.IOException;
    Code:
       0: iconst_0
       1: istore_2
       2: invokestatic  #126                // Method getValidNetworkInterfaces:()Ljava/util/List;
       5: invokeinterface #127,  1          // InterfaceMethod java/util/List.iterator:()Ljava/util/Iterator;
      10: astore_3
      11: aload_3
      12: invokeinterface #128,  1          // InterfaceMethod java/util/Iterator.hasNext:()Z
      17: ifeq          152
      20: aload_3
      21: invokeinterface #129,  1          // InterfaceMethod java/util/Iterator.next:()Ljava/lang/Object;
      26: checkcast     #120                // class java/net/NetworkInterface
      29: astore        4
      31: aload         4
      33: invokevirtual #88                 // Method java/net/NetworkInterface.getInetAddresses:()Ljava/util/Enumeration;
      36: astore        5
      38: aload         5
      40: invokeinterface #89,  1           // InterfaceMethod java/util/Enumeration.hasMoreElements:()Z
      45: ifeq          142
      48: aload         5
      50: invokeinterface #90,  1           // InterfaceMethod java/util/Enumeration.nextElement:()Ljava/lang/Object;
      55: checkcast     #91                 // class java/net/InetAddress
      58: astore        6
      60: iload_1
      61: ifeq          101
      64: aload         6
      66: instanceof    #59                 // class java/net/Inet6Address
      69: ifeq          101
      72: aload         6
      74: bipush        100
      76: invokevirtual #95                 // Method java/net/InetAddress.isReachable:(I)Z
      79: ifeq          93
      82: aload_0
      83: aload         6
      85: invokevirtual #149                // Method java/net/MulticastSocket.setInterface:(Ljava/net/InetAddress;)V
      88: iconst_1
      89: istore_2
      90: goto          142
      93: goto          139
      96: astore        7
      98: goto          139
     101: iload_1
     102: ifne          139
     105: aload         6
     107: instanceof    #150                // class java/net/Inet4Address
     110: ifeq          139
     113: aload         6
     115: bipush        100
     117: invokevirtual #95                 // Method java/net/InetAddress.isReachable:(I)Z
     120: ifeq          134
     123: aload_0
     124: aload         6
     126: invokevirtual #149                // Method java/net/MulticastSocket.setInterface:(Ljava/net/InetAddress;)V
     129: iconst_1
     130: istore_2
     131: goto          142
     134: goto          139
     137: astore        7
     139: goto          38
     142: iload_2
     143: ifeq          149
     146: goto          152
     149: goto          11
     152: return
    Exception table:
       from    to  target type
          72    90    96   Class java/io/IOException
         113   131   137   Class java/io/IOException

  public static boolean matchIpExpression(java.lang.String, java.lang.String) throws java.net.UnknownHostException;
    Code:
       0: aload_1
       1: ifnonnull     6
       4: iconst_0
       5: ireturn
       6: aload_1
       7: astore_2
       8: iconst_0
       9: istore_3
      10: aload_1
      11: ldc           #73                 // String :
      13: invokevirtual #151                // Method java/lang/String.endsWith:(Ljava/lang/String;)Z
      16: ifeq          40
      19: aload_1
      20: ldc           #73                 // String :
      22: invokevirtual #110                // Method java/lang/String.split:(Ljava/lang/String;)[Ljava/lang/String;
      25: astore        4
      27: aload         4
      29: iconst_0
      30: aaload
      31: astore_2
      32: aload         4
      34: iconst_1
      35: aaload
      36: invokestatic  #152                // Method org/apache/dubbo/common/utils/StringUtils.parseInteger:(Ljava/lang/String;)I
      39: istore_3
      40: aload_0
      41: ldc           #153                // String /
      43: invokevirtual #61                 // Method java/lang/String.contains:(Ljava/lang/CharSequence;)Z
      46: ifeq          66
      49: new           #154                // class org/apache/dubbo/common/utils/CIDRUtils
      52: dup
      53: aload_0
      54: invokespecial #155                // Method org/apache/dubbo/common/utils/CIDRUtils."<init>":(Ljava/lang/String;)V
      57: astore        4
      59: aload         4
      61: aload_2
      62: invokevirtual #156                // Method org/apache/dubbo/common/utils/CIDRUtils.isInRange:(Ljava/lang/String;)Z
      65: ireturn
      66: aload_0
      67: aload_2
      68: iload_3
      69: invokestatic  #157                // Method matchIpRange:(Ljava/lang/String;Ljava/lang/String;I)Z
      72: ireturn

  public static boolean matchIpExpression(java.lang.String, java.lang.String, int) throws java.net.UnknownHostException;
    Code:
       0: aload_0
       1: ldc           #153                // String /
       3: invokevirtual #61                 // Method java/lang/String.contains:(Ljava/lang/CharSequence;)Z
       6: ifeq          24
       9: new           #154                // class org/apache/dubbo/common/utils/CIDRUtils
      12: dup
      13: aload_0
      14: invokespecial #155                // Method org/apache/dubbo/common/utils/CIDRUtils."<init>":(Ljava/lang/String;)V
      17: astore_3
      18: aload_3
      19: aload_1
      20: invokevirtual #156                // Method org/apache/dubbo/common/utils/CIDRUtils.isInRange:(Ljava/lang/String;)Z
      23: ireturn
      24: aload_0
      25: aload_1
      26: iload_2
      27: invokestatic  #157                // Method matchIpRange:(Ljava/lang/String;Ljava/lang/String;I)Z
      30: ireturn

  public static boolean matchIpRange(java.lang.String, java.lang.String, int) throws java.net.UnknownHostException;
    Code:
       0: aload_0
       1: ifnull        8
       4: aload_1
       5: ifnonnull     44
       8: new           #158                // class java/lang/IllegalArgumentException
      11: dup
      12: new           #44                 // class java/lang/StringBuilder
      15: dup
      16: invokespecial #45                 // Method java/lang/StringBuilder."<init>":()V
      19: ldc           #159                // String Illegal Argument pattern or hostName. Pattern:
      21: invokevirtual #47                 // Method java/lang/StringBuilder.append:(Ljava/lang/String;)Ljava/lang/StringBuilder;
      24: aload_0
      25: invokevirtual #47                 // Method java/lang/StringBuilder.append:(Ljava/lang/String;)Ljava/lang/StringBuilder;
      28: ldc           #160                // String , Host:
      30: invokevirtual #47                 // Method java/lang/StringBuilder.append:(Ljava/lang/String;)Ljava/lang/StringBuilder;
      33: aload_1
      34: invokevirtual #47                 // Method java/lang/StringBuilder.append:(Ljava/lang/String;)Ljava/lang/StringBuilder;
      37: invokevirtual #51                 // Method java/lang/StringBuilder.toString:()Ljava/lang/String;
      40: invokespecial #161                // Method java/lang/IllegalArgumentException."<init>":(Ljava/lang/String;)V
      43: athrow
      44: aload_0
      45: invokevirtual #111                // Method java/lang/String.trim:()Ljava/lang/String;
      48: astore_0
      49: ldc           #162                // String *.*.*.*
      51: aload_0
      52: invokevirtual #28                 // Method java/lang/String.equals:(Ljava/lang/Object;)Z
      55: ifne          67
      58: ldc           #163                // String *
      60: aload_0
      61: invokevirtual #28                 // Method java/lang/String.equals:(Ljava/lang/Object;)Z
      64: ifeq          69
      67: iconst_1
      68: ireturn
      69: aload_1
      70: invokestatic  #52                 // Method java/net/InetAddress.getByName:(Ljava/lang/String;)Ljava/net/InetAddress;
      73: astore_3
      74: aload_3
      75: invokestatic  #84                 // Method isValidV4Address:(Ljava/net/InetAddress;)Z
      78: istore        4
      80: aload_0
      81: iload         4
      83: invokestatic  #164                // Method getPatternHostAndPort:(Ljava/lang/String;Z)[Ljava/lang/String;
      86: astore        5
      88: aload         5
      90: iconst_1
      91: aaload
      92: ifnull        111
      95: aload         5
      97: iconst_1
      98: aaload
      99: iload_2
     100: invokestatic  #165                // Method java/lang/String.valueOf:(I)Ljava/lang/String;
     103: invokevirtual #28                 // Method java/lang/String.equals:(Ljava/lang/Object;)Z
     106: ifne          111
     109: iconst_0
     110: ireturn
     111: aload         5
     113: iconst_0
     114: aaload
     115: astore_0
     116: ldc           #166                // String \\.
     118: astore        6
     120: iload         4
     122: ifne          129
     125: ldc           #73                 // String :
     127: astore        6
     129: aload_0
     130: aload         6
     132: invokevirtual #110                // Method java/lang/String.split:(Ljava/lang/String;)[Ljava/lang/String;
     135: astore        7
     137: aload_0
     138: aload         7
     140: iload         4
     142: invokestatic  #167                // Method checkHostPattern:(Ljava/lang/String;[Ljava/lang/String;Z)V
     145: aload_3
     146: invokevirtual #37                 // Method java/net/InetAddress.getHostAddress:()Ljava/lang/String;
     149: astore_1
     150: aload_0
     151: aload_1
     152: invokevirtual #28                 // Method java/lang/String.equals:(Ljava/lang/Object;)Z
     155: ifeq          160
     158: iconst_1
     159: ireturn
     160: aload_0
     161: invokestatic  #168                // Method ipPatternContainExpression:(Ljava/lang/String;)Z
     164: ifne          183
     167: aload_0
     168: invokestatic  #52                 // Method java/net/InetAddress.getByName:(Ljava/lang/String;)Ljava/net/InetAddress;
     171: astore        8
     173: aload         8
     175: invokevirtual #37                 // Method java/net/InetAddress.getHostAddress:()Ljava/lang/String;
     178: aload_1
     179: invokevirtual #28                 // Method java/lang/String.equals:(Ljava/lang/Object;)Z
     182: ireturn
     183: aload_1
     184: aload         6
     186: invokevirtual #110                // Method java/lang/String.split:(Ljava/lang/String;)[Ljava/lang/String;
     189: astore        8
     191: iconst_0
     192: istore        9
     194: iload         9
     196: aload         7
     198: arraylength
     199: if_icmpge     454
     202: ldc           #163                // String *
     204: aload         7
     206: iload         9
     208: aaload
     209: invokevirtual #28                 // Method java/lang/String.equals:(Ljava/lang/Object;)Z
     212: ifne          448
     215: aload         7
     217: iload         9
     219: aaload
     220: aload         8
     222: iload         9
     224: aaload
     225: invokevirtual #28                 // Method java/lang/String.equals:(Ljava/lang/Object;)Z
     228: ifeq          234
     231: goto          448
     234: aload         7
     236: iload         9
     238: aaload
     239: ldc           #169                // String -
     241: invokevirtual #61                 // Method java/lang/String.contains:(Ljava/lang/CharSequence;)Z
     244: ifeq          362
     247: aload         7
     249: iload         9
     251: aaload
     252: bipush        45
     254: invokestatic  #170                // Method org/apache/dubbo/common/utils/StringUtils.split:(Ljava/lang/String;C)[Ljava/lang/String;
     257: astore        10
     259: aload         10
     261: arraylength
     262: iconst_2
     263: if_icmpeq     297
     266: new           #158                // class java/lang/IllegalArgumentException
     269: dup
     270: new           #44                 // class java/lang/StringBuilder
     273: dup
     274: invokespecial #45                 // Method java/lang/StringBuilder."<init>":()V
     277: ldc           #171                // String There is wrong format of ip Address:
     279: invokevirtual #47                 // Method java/lang/StringBuilder.append:(Ljava/lang/String;)Ljava/lang/StringBuilder;
     282: aload         7
     284: iload         9
     286: aaload
     287: invokevirtual #47                 // Method java/lang/StringBuilder.append:(Ljava/lang/String;)Ljava/lang/StringBuilder;
     290: invokevirtual #51                 // Method java/lang/StringBuilder.toString:()Ljava/lang/String;
     293: invokespecial #161                // Method java/lang/IllegalArgumentException."<init>":(Ljava/lang/String;)V
     296: athrow
     297: aload         10
     299: iconst_0
     300: aaload
     301: iload         4
     303: invokestatic  #172                // Method getNumOfIpSegment:(Ljava/lang/String;Z)Ljava/lang/Integer;
     306: astore        11
     308: aload         10
     310: iconst_1
     311: aaload
     312: iload         4
     314: invokestatic  #172                // Method getNumOfIpSegment:(Ljava/lang/String;Z)Ljava/lang/Integer;
     317: astore        12
     319: aload         8
     321: iload         9
     323: aaload
     324: iload         4
     326: invokestatic  #172                // Method getNumOfIpSegment:(Ljava/lang/String;Z)Ljava/lang/Integer;
     329: astore        13
     331: aload         13
     333: invokevirtual #173                // Method java/lang/Integer.intValue:()I
     336: aload         11
     338: invokevirtual #173                // Method java/lang/Integer.intValue:()I
     341: if_icmplt     357
     344: aload         13
     346: invokevirtual #173                // Method java/lang/Integer.intValue:()I
     349: aload         12
     351: invokevirtual #173                // Method java/lang/Integer.intValue:()I
     354: if_icmple     359
     357: iconst_0
     358: ireturn
     359: goto          448
     362: ldc           #174                // String 0
     364: aload         8
     366: iload         9
     368: aaload
     369: invokevirtual #28                 // Method java/lang/String.equals:(Ljava/lang/Object;)Z
     372: ifeq          430
     375: ldc           #174                // String 0
     377: aload         7
     379: iload         9
     381: aaload
     382: invokevirtual #28                 // Method java/lang/String.equals:(Ljava/lang/Object;)Z
     385: ifne          448
     388: ldc           #175                // String 00
     390: aload         7
     392: iload         9
     394: aaload
     395: invokevirtual #28                 // Method java/lang/String.equals:(Ljava/lang/Object;)Z
     398: ifne          448
     401: ldc           #176                // String 000
     403: aload         7
     405: iload         9
     407: aaload
     408: invokevirtual #28                 // Method java/lang/String.equals:(Ljava/lang/Object;)Z
     411: ifne          448
     414: ldc           #177                // String 0000
     416: aload         7
     418: iload         9
     420: aaload
     421: invokevirtual #28                 // Method java/lang/String.equals:(Ljava/lang/Object;)Z
     424: ifeq          430
     427: goto          448
     430: aload         7
     432: iload         9
     434: aaload
     435: aload         8
     437: iload         9
     439: aaload
     440: invokevirtual #28                 // Method java/lang/String.equals:(Ljava/lang/Object;)Z
     443: ifne          448
     446: iconst_0
     447: ireturn
     448: iinc          9, 1
     451: goto          194
     454: iconst_1
     455: ireturn

  public static boolean isMulticastAddress(java.lang.String);
    Code:
       0: aload_0
       1: bipush        46
       3: invokevirtual #132                // Method java/lang/String.indexOf:(I)I
       6: istore_1
       7: iload_1
       8: ifle          50
      11: aload_0
      12: iconst_0
      13: iload_1
      14: invokevirtual #46                 // Method java/lang/String.substring:(II)Ljava/lang/String;
      17: astore_2
      18: aload_2
      19: invokestatic  #178                // Method org/apache/dubbo/common/utils/StringUtils.isNumber:(Ljava/lang/String;)Z
      22: ifeq          50
      25: aload_2
      26: invokestatic  #144                // Method java/lang/Integer.parseInt:(Ljava/lang/String;)I
      29: istore_3
      30: iload_3
      31: sipush        224
      34: if_icmplt     48
      37: iload_3
      38: sipush        239
      41: if_icmpgt     48
      44: iconst_1
      45: goto          49
      48: iconst_0
      49: ireturn
      50: iconst_0
      51: ireturn

  private static boolean ipPatternContainExpression(java.lang.String);
    Code:
       0: aload_0
       1: ldc           #163                // String *
       3: invokevirtual #61                 // Method java/lang/String.contains:(Ljava/lang/CharSequence;)Z
       6: ifne          18
       9: aload_0
      10: ldc           #169                // String -
      12: invokevirtual #61                 // Method java/lang/String.contains:(Ljava/lang/CharSequence;)Z
      15: ifeq          22
      18: iconst_1
      19: goto          23
      22: iconst_0
      23: ireturn

  private static void checkHostPattern(java.lang.String, java.lang.String[], boolean);
    Code:
       0: iload_2
       1: ifne          71
       4: aload_1
       5: arraylength
       6: bipush        8
       8: if_icmpeq     28
      11: aload_0
      12: invokestatic  #168                // Method ipPatternContainExpression:(Ljava/lang/String;)Z
      15: ifeq          28
      18: new           #158                // class java/lang/IllegalArgumentException
      21: dup
      22: ldc           #179                // String If you config ip expression that contains \'*\' or \'-\', please fill qualified ip pattern like 234e:0:4567:0:0:0:3d:*.
      24: invokespecial #161                // Method java/lang/IllegalArgumentException."<init>":(Ljava/lang/String;)V
      27: athrow
      28: aload_1
      29: arraylength
      30: bipush        8
      32: if_icmpeq     104
      35: aload_0
      36: ldc           #180                // String ::
      38: invokevirtual #61                 // Method java/lang/String.contains:(Ljava/lang/CharSequence;)Z
      41: ifne          104
      44: new           #158                // class java/lang/IllegalArgumentException
      47: dup
      48: new           #44                 // class java/lang/StringBuilder
      51: dup
      52: invokespecial #45                 // Method java/lang/StringBuilder."<init>":()V
      55: ldc           #181                // String The host is ipv6, but the pattern is not ipv6 pattern :
      57: invokevirtual #47                 // Method java/lang/StringBuilder.append:(Ljava/lang/String;)Ljava/lang/StringBuilder;
      60: aload_0
      61: invokevirtual #47                 // Method java/lang/StringBuilder.append:(Ljava/lang/String;)Ljava/lang/StringBuilder;
      64: invokevirtual #51                 // Method java/lang/StringBuilder.toString:()Ljava/lang/String;
      67: invokespecial #161                // Method java/lang/IllegalArgumentException."<init>":(Ljava/lang/String;)V
      70: athrow
      71: aload_1
      72: arraylength
      73: iconst_4
      74: if_icmpeq     104
      77: new           #158                // class java/lang/IllegalArgumentException
      80: dup
      81: new           #44                 // class java/lang/StringBuilder
      84: dup
      85: invokespecial #45                 // Method java/lang/StringBuilder."<init>":()V
      88: ldc           #182                // String The host is ipv4, but the pattern is not ipv4 pattern :
      90: invokevirtual #47                 // Method java/lang/StringBuilder.append:(Ljava/lang/String;)Ljava/lang/StringBuilder;
      93: aload_0
      94: invokevirtual #47                 // Method java/lang/StringBuilder.append:(Ljava/lang/String;)Ljava/lang/StringBuilder;
      97: invokevirtual #51                 // Method java/lang/StringBuilder.toString:()Ljava/lang/String;
     100: invokespecial #161                // Method java/lang/IllegalArgumentException."<init>":(Ljava/lang/String;)V
     103: athrow
     104: return

  private static java.lang.String[] getPatternHostAndPort(java.lang.String, boolean);
    Code:
       0: iconst_2
       1: anewarray     #135                // class java/lang/String
       4: astore_2
       5: aload_0
       6: ldc           #183                // String [
       8: invokevirtual #31                 // Method java/lang/String.startsWith:(Ljava/lang/String;)Z
      11: ifeq          51
      14: aload_0
      15: ldc           #184                // String ]:
      17: invokevirtual #61                 // Method java/lang/String.contains:(Ljava/lang/CharSequence;)Z
      20: ifeq          51
      23: aload_0
      24: ldc           #184                // String ]:
      26: invokevirtual #62                 // Method java/lang/String.indexOf:(Ljava/lang/String;)I
      29: istore_3
      30: aload_2
      31: iconst_0
      32: aload_0
      33: iconst_1
      34: iload_3
      35: invokevirtual #46                 // Method java/lang/String.substring:(II)Ljava/lang/String;
      38: aastore
      39: aload_2
      40: iconst_1
      41: aload_0
      42: iload_3
      43: iconst_2
      44: iadd
      45: invokevirtual #74                 // Method java/lang/String.substring:(I)Ljava/lang/String;
      48: aastore
      49: aload_2
      50: areturn
      51: aload_0
      52: ldc           #183                // String [
      54: invokevirtual #31                 // Method java/lang/String.startsWith:(Ljava/lang/String;)Z
      57: ifeq          89
      60: aload_0
      61: ldc           #185                // String ]
      63: invokevirtual #151                // Method java/lang/String.endsWith:(Ljava/lang/String;)Z
      66: ifeq          89
      69: aload_2
      70: iconst_0
      71: aload_0
      72: iconst_1
      73: aload_0
      74: invokevirtual #29                 // Method java/lang/String.length:()I
      77: iconst_1
      78: isub
      79: invokevirtual #46                 // Method java/lang/String.substring:(II)Ljava/lang/String;
      82: aastore
      83: aload_2
      84: iconst_1
      85: aconst_null
      86: aastore
      87: aload_2
      88: areturn
      89: iload_1
      90: ifeq          130
      93: aload_0
      94: ldc           #73                 // String :
      96: invokevirtual #61                 // Method java/lang/String.contains:(Ljava/lang/CharSequence;)Z
      99: ifeq          130
     102: aload_0
     103: ldc           #73                 // String :
     105: invokevirtual #62                 // Method java/lang/String.indexOf:(Ljava/lang/String;)I
     108: istore_3
     109: aload_2
     110: iconst_0
     111: aload_0
     112: iconst_0
     113: iload_3
     114: invokevirtual #46                 // Method java/lang/String.substring:(II)Ljava/lang/String;
     117: aastore
     118: aload_2
     119: iconst_1
     120: aload_0
     121: iload_3
     122: iconst_1
     123: iadd
     124: invokevirtual #74                 // Method java/lang/String.substring:(I)Ljava/lang/String;
     127: aastore
     128: aload_2
     129: areturn
     130: aload_2
     131: iconst_0
     132: aload_0
     133: aastore
     134: aload_2
     135: areturn

  private static java.lang.Integer getNumOfIpSegment(java.lang.String, boolean);
    Code:
       0: iload_1
       1: ifeq          12
       4: aload_0
       5: invokestatic  #144                // Method java/lang/Integer.parseInt:(Ljava/lang/String;)I
       8: invokestatic  #186                // Method java/lang/Integer.valueOf:(I)Ljava/lang/Integer;
      11: areturn
      12: aload_0
      13: bipush        16
      15: invokestatic  #187                // Method java/lang/Integer.parseInt:(Ljava/lang/String;I)I
      18: invokestatic  #186                // Method java/lang/Integer.valueOf:(I)Ljava/lang/Integer;
      21: areturn

  public static boolean isIPV6URLStdFormat(java.lang.String);
    Code:
       0: aload_0
       1: iconst_0
       2: invokevirtual #145                // Method java/lang/String.charAt:(I)C
       5: bipush        91
       7: if_icmpne     22
      10: aload_0
      11: bipush        93
      13: invokevirtual #132                // Method java/lang/String.indexOf:(I)I
      16: iconst_2
      17: if_icmple     22
      20: iconst_1
      21: ireturn
      22: aload_0
      23: ldc           #73                 // String :
      25: invokevirtual #62                 // Method java/lang/String.indexOf:(Ljava/lang/String;)I
      28: aload_0
      29: ldc           #73                 // String :
      31: invokevirtual #188                // Method java/lang/String.lastIndexOf:(Ljava/lang/String;)I
      34: if_icmpeq     39
      37: iconst_1
      38: ireturn
      39: iconst_0
      40: ireturn

  public static java.lang.String getLegalIP(java.lang.String);
    Code:
       0: aload_0
       1: iconst_0
       2: invokevirtual #145                // Method java/lang/String.charAt:(I)C
       5: bipush        91
       7: if_icmpne     42
      10: aload_0
      11: bipush        93
      13: invokevirtual #132                // Method java/lang/String.indexOf:(I)I
      16: dup
      17: istore_1
      18: iconst_2
      19: if_icmple     42
      22: aload_0
      23: astore_2
      24: aload_2
      25: iconst_0
      26: iload_1
      27: iconst_1
      28: iadd
      29: invokevirtual #46                 // Method java/lang/String.substring:(II)Ljava/lang/String;
      32: astore_0
      33: aload_0
      34: iconst_1
      35: iload_1
      36: invokevirtual #46                 // Method java/lang/String.substring:(II)Ljava/lang/String;
      39: astore_0
      40: aload_0
      41: areturn
      42: aload_0
      43: areturn

  private static java.lang.String lambda$getLocalHostName$0(java.net.InetAddress);
    Code:
       0: aload_0
       1: invokevirtual #136                // Method java/net/InetAddress.getHostName:()Ljava/lang/String;
       4: areturn

  static {};
    Code:
       0: ldc           #6                  // class org/apache/dubbo/common/utils/NetUtils
       2: invokestatic  #189                // Method org/apache/dubbo/common/logger/LoggerFactory.getLogger:(Ljava/lang/Class;)Lorg/apache/dubbo/common/logger/Logger;
       5: putstatic     #54                 // Field logger:Lorg/apache/dubbo/common/logger/Logger;
       8: getstatic     #54                 // Field logger:Lorg/apache/dubbo/common/logger/Logger;
      11: instanceof    #190                // class org/apache/dubbo/common/logger/support/FailsafeLogger
      14: ifeq          29
      17: getstatic     #54                 // Field logger:Lorg/apache/dubbo/common/logger/Logger;
      20: checkcast     #190                // class org/apache/dubbo/common/logger/support/FailsafeLogger
      23: invokevirtual #191                // Method org/apache/dubbo/common/logger/support/FailsafeLogger.getLogger:()Lorg/apache/dubbo/common/logger/Logger;
      26: putstatic     #54                 // Field logger:Lorg/apache/dubbo/common/logger/Logger;
      29: ldc           #192                // String ^\\d{1,3}(\\.\\d{1,3}){3}\\:\\d{1,5}$
      31: invokestatic  #193                // Method java/util/regex/Pattern.compile:(Ljava/lang/String;)Ljava/util/regex/Pattern;
      34: putstatic     #21                 // Field ADDRESS_PATTERN:Ljava/util/regex/Pattern;
      37: ldc           #194                // String 127(\\.\\d{1,3}){3}$
      39: invokestatic  #193                // Method java/util/regex/Pattern.compile:(Ljava/lang/String;)Ljava/util/regex/Pattern;
      42: putstatic     #24                 // Field LOCAL_IP_PATTERN:Ljava/util/regex/Pattern;
      45: ldc           #195                // String \\d{1,3}(\\.\\d{1,3}){3,5}$
      47: invokestatic  #193                // Method java/util/regex/Pattern.compile:(Ljava/lang/String;)Ljava/util/regex/Pattern;
      50: putstatic     #38                 // Field IP_PATTERN:Ljava/util/regex/Pattern;
      53: new           #196                // class org/apache/dubbo/common/utils/LRUCache
      56: dup
      57: sipush        1000
      60: invokespecial #197                // Method org/apache/dubbo/common/utils/LRUCache."<init>":(I)V
      63: putstatic     #133                // Field HOST_NAME_CACHE:Ljava/util/Map;
      66: aconst_null
      67: putstatic     #77                 // Field LOCAL_ADDRESS:Ljava/net/InetAddress;
      70: aconst_null
      71: putstatic     #79                 // Field LOCAL_ADDRESS_V6:Ljava/net/Inet6Address;
      74: new           #198                // class java/util/BitSet
      77: dup
      78: ldc           #199                // int 65536
      80: invokespecial #200                // Method java/util/BitSet."<init>":(I)V
      83: putstatic     #12                 // Field USED_PORT:Ljava/util/BitSet;
      86: return
}
