Compiled from "Page.java"
public interface org.apache.dubbo.common.utils.Page<T> {
  public abstract int getOffset();

  public abstract int getPageSize();

  public abstract int getTotalSize();

  public abstract int getTotalPages();

  public abstract java.util.List<T> getData();

  public default int getDataSize();
    Code:
       0: aload_0
       1: invokeinterface #1,  1            // InterfaceMethod getData:()Ljava/util/List;
       6: invokeinterface #2,  1            // InterfaceMethod java/util/List.size:()I
      11: ireturn

  public abstract boolean hasNext();

  public default boolean hasData();
    Code:
       0: aload_0
       1: invokeinterface #3,  1            // InterfaceMethod getDataSize:()I
       6: ifle          13
       9: iconst_1
      10: goto          14
      13: iconst_0
      14: ireturn
}
