Compiled from "PathUtils.java"
public interface org.apache.dubbo.common.utils.PathUtils {
  public static java.lang.String buildPath(java.lang.String, java.lang.String...);
    Code:
       0: new           #1                  // class java/util/LinkedHashSet
       3: dup
       4: invokespecial #2                  // Method java/util/LinkedHashSet."<init>":()V
       7: astore_2
       8: aload_2
       9: aload_0
      10: invokeinterface #3,  2            // InterfaceMethod java/util/Set.add:(Ljava/lang/Object;)Z
      15: pop
      16: aload_2
      17: aload_1
      18: invokestatic  #4                  // Method java/util/Arrays.asList:([Ljava/lang/Object;)Ljava/util/List;
      21: invokeinterface #5,  2            // InterfaceMethod java/util/Set.addAll:(Ljava/util/Collection;)Z
      26: pop
      27: aload_2
      28: invokeinterface #6,  1            // InterfaceMethod java/util/Set.stream:()Ljava/util/stream/Stream;
      33: invokedynamic #7,  0              // InvokeDynamic #0:test:()Ljava/util/function/Predicate;
      38: invokeinterface #8,  2            // InterfaceMethod java/util/stream/Stream.filter:(Ljava/util/function/Predicate;)Ljava/util/stream/Stream;
      43: getstatic     #9                  // Field org/apache/dubbo/common/utils/StringUtils.SLASH:Ljava/lang/String;
      46: invokestatic  #10                 // Method java/util/stream/Collectors.joining:(Ljava/lang/CharSequence;)Ljava/util/stream/Collector;
      49: invokeinterface #11,  2           // InterfaceMethod java/util/stream/Stream.collect:(Ljava/util/stream/Collector;)Ljava/lang/Object;
      54: checkcast     #12                 // class java/lang/String
      57: invokestatic  #13                 // InterfaceMethod normalize:(Ljava/lang/String;)Ljava/lang/String;
      60: areturn

  public static java.lang.String normalize(java.lang.String);
    Code:
       0: aload_0
       1: invokestatic  #14                 // Method org/apache/dubbo/common/utils/StringUtils.isEmpty:(Ljava/lang/String;)Z
       4: ifeq          11
       7: getstatic     #9                  // Field org/apache/dubbo/common/utils/StringUtils.SLASH:Ljava/lang/String;
      10: areturn
      11: aload_0
      12: astore_1
      13: aload_1
      14: getstatic     #15                 // Field org/apache/dubbo/common/utils/StringUtils.QUESTION_MASK:Ljava/lang/String;
      17: invokevirtual #16                 // Method java/lang/String.indexOf:(Ljava/lang/String;)I
      20: istore_2
      21: iload_2
      22: iconst_m1
      23: if_icmple     33
      26: aload_1
      27: iconst_0
      28: iload_2
      29: invokevirtual #17                 // Method java/lang/String.substring:(II)Ljava/lang/String;
      32: astore_1
      33: aload_1
      34: ldc           #18                 // String //
      36: invokevirtual #19                 // Method java/lang/String.contains:(Ljava/lang/CharSequence;)Z
      39: ifeq          54
      42: aload_1
      43: ldc           #18                 // String //
      45: ldc           #20                 // String /
      47: invokestatic  #21                 // Method org/apache/dubbo/common/utils/StringUtils.replace:(Ljava/lang/String;Ljava/lang/String;Ljava/lang/String;)Ljava/lang/String;
      50: astore_1
      51: goto          33
      54: aload_1
      55: areturn
}
