Compiled from "PojoUtils.java"
public class org.apache.dubbo.common.utils.PojoUtils {
  private static final org.apache.dubbo.common.logger.ErrorTypeAwareLogger logger;

  private static final java.util.concurrent.ConcurrentMap<java.lang.String, java.lang.reflect.Method> NAME_METHODS_CACHE;

  private static final java.util.concurrent.ConcurrentMap<java.lang.Class<?>, java.util.concurrent.ConcurrentMap<java.lang.String, java.lang.reflect.Field>> CLASS_FIELD_CACHE;

  private static final java.util.concurrent.ConcurrentMap<java.lang.String, java.lang.Object> CLASS_NOT_FOUND_CACHE;

  private static final java.lang.Object NOT_FOUND_VALUE;

  private static final boolean GENERIC_WITH_CLZ;

  private static final java.util.List<java.lang.Class<?>> CLASS_CAN_BE_STRING;

  public org.apache.dubbo.common.utils.PojoUtils();
    Code:
       0: aload_0
       1: invokespecial #3                  // Method java/lang/Object."<init>":()V
       4: return

  public static java.lang.Object[] generalize(java.lang.Object[]);
    Code:
       0: aload_0
       1: arraylength
       2: anewarray     #4                  // class java/lang/Object
       5: astore_1
       6: iconst_0
       7: istore_2
       8: iload_2
       9: aload_0
      10: arraylength
      11: if_icmpge     29
      14: aload_1
      15: iload_2
      16: aload_0
      17: iload_2
      18: aaload
      19: invokestatic  #5                  // Method generalize:(Ljava/lang/Object;)Ljava/lang/Object;
      22: aastore
      23: iinc          2, 1
      26: goto          8
      29: aload_1
      30: areturn

  public static java.lang.Object[] realize(java.lang.Object[], java.lang.Class<?>[]);
    Code:
       0: aload_0
       1: arraylength
       2: aload_1
       3: arraylength
       4: if_icmpeq     17
       7: new           #6                  // class java/lang/IllegalArgumentException
      10: dup
      11: ldc           #7                  // String args.length != types.length
      13: invokespecial #8                  // Method java/lang/IllegalArgumentException."<init>":(Ljava/lang/String;)V
      16: athrow
      17: aload_0
      18: arraylength
      19: anewarray     #4                  // class java/lang/Object
      22: astore_2
      23: iconst_0
      24: istore_3
      25: iload_3
      26: aload_0
      27: arraylength
      28: if_icmpge     49
      31: aload_2
      32: iload_3
      33: aload_0
      34: iload_3
      35: aaload
      36: aload_1
      37: iload_3
      38: aaload
      39: invokestatic  #9                  // Method realize:(Ljava/lang/Object;Ljava/lang/Class;)Ljava/lang/Object;
      42: aastore
      43: iinc          3, 1
      46: goto          25
      49: aload_2
      50: areturn

  public static java.lang.Object[] realize(java.lang.Object[], java.lang.Class<?>[], java.lang.reflect.Type[]);
    Code:
       0: aload_0
       1: arraylength
       2: aload_1
       3: arraylength
       4: if_icmpne     14
       7: aload_0
       8: arraylength
       9: aload_2
      10: arraylength
      11: if_icmpeq     24
      14: new           #6                  // class java/lang/IllegalArgumentException
      17: dup
      18: ldc           #7                  // String args.length != types.length
      20: invokespecial #8                  // Method java/lang/IllegalArgumentException."<init>":(Ljava/lang/String;)V
      23: athrow
      24: aload_0
      25: arraylength
      26: anewarray     #4                  // class java/lang/Object
      29: astore_3
      30: iconst_0
      31: istore        4
      33: iload         4
      35: aload_0
      36: arraylength
      37: if_icmpge     65
      40: aload_3
      41: iload         4
      43: aload_0
      44: iload         4
      46: aaload
      47: aload_1
      48: iload         4
      50: aaload
      51: aload_2
      52: iload         4
      54: aaload
      55: invokestatic  #10                 // Method realize:(Ljava/lang/Object;Ljava/lang/Class;Ljava/lang/reflect/Type;)Ljava/lang/Object;
      58: aastore
      59: iinc          4, 1
      62: goto          33
      65: aload_3
      66: areturn

  public static java.lang.Object generalize(java.lang.Object);
    Code:
       0: aload_0
       1: new           #11                 // class java/util/IdentityHashMap
       4: dup
       5: invokespecial #12                 // Method java/util/IdentityHashMap."<init>":()V
       8: invokestatic  #13                 // Method generalize:(Ljava/lang/Object;Ljava/util/Map;)Ljava/lang/Object;
      11: areturn

  private static java.lang.Object generalize(java.lang.Object, java.util.Map<java.lang.Object, java.lang.Object>);
    Code:
       0: aload_0
       1: ifnonnull     6
       4: aconst_null
       5: areturn
       6: aload_0
       7: instanceof    #14                 // class java/lang/Enum
      10: ifeq          21
      13: aload_0
      14: checkcast     #14                 // class java/lang/Enum
      17: invokevirtual #15                 // Method java/lang/Enum.name:()Ljava/lang/String;
      20: areturn
      21: aload_0
      22: invokevirtual #16                 // Method java/lang/Object.getClass:()Ljava/lang/Class;
      25: invokevirtual #17                 // Method java/lang/Class.isArray:()Z
      28: ifeq          89
      31: ldc           #14                 // class java/lang/Enum
      33: aload_0
      34: invokevirtual #16                 // Method java/lang/Object.getClass:()Ljava/lang/Class;
      37: invokevirtual #18                 // Method java/lang/Class.getComponentType:()Ljava/lang/Class;
      40: invokevirtual #19                 // Method java/lang/Class.isAssignableFrom:(Ljava/lang/Class;)Z
      43: ifeq          89
      46: aload_0
      47: invokestatic  #20                 // Method java/lang/reflect/Array.getLength:(Ljava/lang/Object;)I
      50: istore_2
      51: iload_2
      52: anewarray     #21                 // class java/lang/String
      55: astore_3
      56: iconst_0
      57: istore        4
      59: iload         4
      61: iload_2
      62: if_icmpge     87
      65: aload_3
      66: iload         4
      68: aload_0
      69: iload         4
      71: invokestatic  #22                 // Method java/lang/reflect/Array.get:(Ljava/lang/Object;I)Ljava/lang/Object;
      74: checkcast     #14                 // class java/lang/Enum
      77: invokevirtual #15                 // Method java/lang/Enum.name:()Ljava/lang/String;
      80: aastore
      81: iinc          4, 1
      84: goto          59
      87: aload_3
      88: areturn
      89: aload_0
      90: invokevirtual #16                 // Method java/lang/Object.getClass:()Ljava/lang/Class;
      93: invokestatic  #23                 // Method org/apache/dubbo/common/utils/ReflectUtils.isPrimitives:(Ljava/lang/Class;)Z
      96: ifeq          101
      99: aload_0
     100: areturn
     101: aload_0
     102: instanceof    #24                 // class java/time/LocalDate
     105: ifne          122
     108: aload_0
     109: instanceof    #25                 // class java/time/LocalDateTime
     112: ifne          122
     115: aload_0
     116: instanceof    #26                 // class java/time/LocalTime
     119: ifeq          127
     122: aload_0
     123: invokevirtual #27                 // Method java/lang/Object.toString:()Ljava/lang/String;
     126: areturn
     127: aload_0
     128: instanceof    #28                 // class java/lang/Class
     131: ifeq          142
     134: aload_0
     135: checkcast     #28                 // class java/lang/Class
     138: invokevirtual #29                 // Method java/lang/Class.getName:()Ljava/lang/String;
     141: areturn
     142: aload_1
     143: aload_0
     144: invokeinterface #30,  2           // InterfaceMethod java/util/Map.get:(Ljava/lang/Object;)Ljava/lang/Object;
     149: astore_2
     150: aload_2
     151: ifnull        156
     154: aload_2
     155: areturn
     156: aload_1
     157: aload_0
     158: aload_0
     159: invokeinterface #31,  3           // InterfaceMethod java/util/Map.put:(Ljava/lang/Object;Ljava/lang/Object;)Ljava/lang/Object;
     164: pop
     165: aload_0
     166: invokevirtual #16                 // Method java/lang/Object.getClass:()Ljava/lang/Class;
     169: invokevirtual #17                 // Method java/lang/Class.isArray:()Z
     172: ifeq          233
     175: aload_0
     176: invokestatic  #20                 // Method java/lang/reflect/Array.getLength:(Ljava/lang/Object;)I
     179: istore_3
     180: iload_3
     181: anewarray     #4                  // class java/lang/Object
     184: astore        4
     186: aload_1
     187: aload_0
     188: aload         4
     190: invokeinterface #31,  3           // InterfaceMethod java/util/Map.put:(Ljava/lang/Object;Ljava/lang/Object;)Ljava/lang/Object;
     195: pop
     196: iconst_0
     197: istore        5
     199: iload         5
     201: iload_3
     202: if_icmpge     230
     205: aload_0
     206: iload         5
     208: invokestatic  #22                 // Method java/lang/reflect/Array.get:(Ljava/lang/Object;I)Ljava/lang/Object;
     211: astore        6
     213: aload         4
     215: iload         5
     217: aload         6
     219: aload_1
     220: invokestatic  #13                 // Method generalize:(Ljava/lang/Object;Ljava/util/Map;)Ljava/lang/Object;
     223: aastore
     224: iinc          5, 1
     227: goto          199
     230: aload         4
     232: areturn
     233: aload_0
     234: instanceof    #32                 // class java/util/Collection
     237: ifeq          340
     240: aload_0
     241: checkcast     #32                 // class java/util/Collection
     244: astore_3
     245: aload_3
     246: invokeinterface #33,  1           // InterfaceMethod java/util/Collection.size:()I
     251: istore        4
     253: aload_0
     254: instanceof    #34                 // class java/util/List
     257: ifeq          272
     260: new           #35                 // class java/util/ArrayList
     263: dup
     264: iload         4
     266: invokespecial #36                 // Method java/util/ArrayList."<init>":(I)V
     269: goto          281
     272: new           #37                 // class java/util/HashSet
     275: dup
     276: iload         4
     278: invokespecial #38                 // Method java/util/HashSet."<init>":(I)V
     281: astore        5
     283: aload_1
     284: aload_0
     285: aload         5
     287: invokeinterface #31,  3           // InterfaceMethod java/util/Map.put:(Ljava/lang/Object;Ljava/lang/Object;)Ljava/lang/Object;
     292: pop
     293: aload_3
     294: invokeinterface #39,  1           // InterfaceMethod java/util/Collection.iterator:()Ljava/util/Iterator;
     299: astore        6
     301: aload         6
     303: invokeinterface #40,  1           // InterfaceMethod java/util/Iterator.hasNext:()Z
     308: ifeq          337
     311: aload         6
     313: invokeinterface #41,  1           // InterfaceMethod java/util/Iterator.next:()Ljava/lang/Object;
     318: astore        7
     320: aload         5
     322: aload         7
     324: aload_1
     325: invokestatic  #13                 // Method generalize:(Ljava/lang/Object;Ljava/util/Map;)Ljava/lang/Object;
     328: invokeinterface #42,  2           // InterfaceMethod java/util/Collection.add:(Ljava/lang/Object;)Z
     333: pop
     334: goto          301
     337: aload         5
     339: areturn
     340: aload_0
     341: instanceof    #43                 // class java/util/Map
     344: ifeq          439
     347: aload_0
     348: checkcast     #43                 // class java/util/Map
     351: astore_3
     352: aload_3
     353: invokestatic  #44                 // Method createMap:(Ljava/util/Map;)Ljava/util/Map;
     356: astore        4
     358: aload_1
     359: aload_0
     360: aload         4
     362: invokeinterface #31,  3           // InterfaceMethod java/util/Map.put:(Ljava/lang/Object;Ljava/lang/Object;)Ljava/lang/Object;
     367: pop
     368: aload_3
     369: invokeinterface #45,  1           // InterfaceMethod java/util/Map.entrySet:()Ljava/util/Set;
     374: invokeinterface #46,  1           // InterfaceMethod java/util/Set.iterator:()Ljava/util/Iterator;
     379: astore        5
     381: aload         5
     383: invokeinterface #40,  1           // InterfaceMethod java/util/Iterator.hasNext:()Z
     388: ifeq          436
     391: aload         5
     393: invokeinterface #41,  1           // InterfaceMethod java/util/Iterator.next:()Ljava/lang/Object;
     398: checkcast     #47                 // class java/util/Map$Entry
     401: astore        6
     403: aload         4
     405: aload         6
     407: invokeinterface #48,  1           // InterfaceMethod java/util/Map$Entry.getKey:()Ljava/lang/Object;
     412: aload_1
     413: invokestatic  #13                 // Method generalize:(Ljava/lang/Object;Ljava/util/Map;)Ljava/lang/Object;
     416: aload         6
     418: invokeinterface #49,  1           // InterfaceMethod java/util/Map$Entry.getValue:()Ljava/lang/Object;
     423: aload_1
     424: invokestatic  #13                 // Method generalize:(Ljava/lang/Object;Ljava/util/Map;)Ljava/lang/Object;
     427: invokeinterface #31,  3           // InterfaceMethod java/util/Map.put:(Ljava/lang/Object;Ljava/lang/Object;)Ljava/lang/Object;
     432: pop
     433: goto          381
     436: aload         4
     438: areturn
     439: new           #50                 // class java/util/HashMap
     442: dup
     443: invokespecial #51                 // Method java/util/HashMap."<init>":()V
     446: astore_3
     447: aload_1
     448: aload_0
     449: aload_3
     450: invokeinterface #31,  3           // InterfaceMethod java/util/Map.put:(Ljava/lang/Object;Ljava/lang/Object;)Ljava/lang/Object;
     455: pop
     456: getstatic     #52                 // Field GENERIC_WITH_CLZ:Z
     459: ifeq          478
     462: aload_3
     463: ldc           #53                 // String class
     465: aload_0
     466: invokevirtual #16                 // Method java/lang/Object.getClass:()Ljava/lang/Class;
     469: invokevirtual #29                 // Method java/lang/Class.getName:()Ljava/lang/String;
     472: invokeinterface #31,  3           // InterfaceMethod java/util/Map.put:(Ljava/lang/Object;Ljava/lang/Object;)Ljava/lang/Object;
     477: pop
     478: aload_0
     479: invokevirtual #16                 // Method java/lang/Object.getClass:()Ljava/lang/Class;
     482: invokevirtual #54                 // Method java/lang/Class.getMethods:()[Ljava/lang/reflect/Method;
     485: astore        4
     487: aload         4
     489: arraylength
     490: istore        5
     492: iconst_0
     493: istore        6
     495: iload         6
     497: iload         5
     499: if_icmpge     574
     502: aload         4
     504: iload         6
     506: aaload
     507: astore        7
     509: aload         7
     511: invokestatic  #55                 // Method org/apache/dubbo/common/utils/ReflectUtils.isBeanPropertyReadMethod:(Ljava/lang/reflect/Method;)Z
     514: ifeq          568
     517: aload         7
     519: invokestatic  #56                 // Method org/apache/dubbo/common/utils/ReflectUtils.makeAccessible:(Ljava/lang/reflect/Method;)V
     522: aload_3
     523: aload         7
     525: invokestatic  #57                 // Method org/apache/dubbo/common/utils/ReflectUtils.getPropertyNameFromBeanReadMethod:(Ljava/lang/reflect/Method;)Ljava/lang/String;
     528: aload         7
     530: aload_0
     531: iconst_0
     532: anewarray     #4                  // class java/lang/Object
     535: invokevirtual #58                 // Method java/lang/reflect/Method.invoke:(Ljava/lang/Object;[Ljava/lang/Object;)Ljava/lang/Object;
     538: aload_1
     539: invokestatic  #13                 // Method generalize:(Ljava/lang/Object;Ljava/util/Map;)Ljava/lang/Object;
     542: invokeinterface #31,  3           // InterfaceMethod java/util/Map.put:(Ljava/lang/Object;Ljava/lang/Object;)Ljava/lang/Object;
     547: pop
     548: goto          568
     551: astore        8
     553: new           #60                 // class java/lang/RuntimeException
     556: dup
     557: aload         8
     559: invokevirtual #61                 // Method java/lang/Exception.getMessage:()Ljava/lang/String;
     562: aload         8
     564: invokespecial #62                 // Method java/lang/RuntimeException."<init>":(Ljava/lang/String;Ljava/lang/Throwable;)V
     567: athrow
     568: iinc          6, 1
     571: goto          495
     574: aload_0
     575: invokevirtual #16                 // Method java/lang/Object.getClass:()Ljava/lang/Class;
     578: invokevirtual #63                 // Method java/lang/Class.getFields:()[Ljava/lang/reflect/Field;
     581: astore        4
     583: aload         4
     585: arraylength
     586: istore        5
     588: iconst_0
     589: istore        6
     591: iload         6
     593: iload         5
     595: if_icmpge     718
     598: aload         4
     600: iload         6
     602: aaload
     603: astore        7
     605: aload         7
     607: invokestatic  #64                 // Method org/apache/dubbo/common/utils/ReflectUtils.isPublicInstanceField:(Ljava/lang/reflect/Field;)Z
     610: ifeq          712
     613: aload         7
     615: aload_0
     616: invokevirtual #65                 // Method java/lang/reflect/Field.get:(Ljava/lang/Object;)Ljava/lang/Object;
     619: astore        8
     621: aload_1
     622: aload_0
     623: invokeinterface #66,  2           // InterfaceMethod java/util/Map.containsKey:(Ljava/lang/Object;)Z
     628: ifeq          669
     631: aload_1
     632: aload_0
     633: invokeinterface #30,  2           // InterfaceMethod java/util/Map.get:(Ljava/lang/Object;)Ljava/lang/Object;
     638: astore        9
     640: aload         9
     642: instanceof    #43                 // class java/util/Map
     645: ifeq          669
     648: aload         9
     650: checkcast     #43                 // class java/util/Map
     653: aload         7
     655: invokevirtual #67                 // Method java/lang/reflect/Field.getName:()Ljava/lang/String;
     658: invokeinterface #66,  2           // InterfaceMethod java/util/Map.containsKey:(Ljava/lang/Object;)Z
     663: ifeq          669
     666: goto          712
     669: aload         8
     671: ifnull        692
     674: aload_3
     675: aload         7
     677: invokevirtual #67                 // Method java/lang/reflect/Field.getName:()Ljava/lang/String;
     680: aload         8
     682: aload_1
     683: invokestatic  #13                 // Method generalize:(Ljava/lang/Object;Ljava/util/Map;)Ljava/lang/Object;
     686: invokeinterface #31,  3           // InterfaceMethod java/util/Map.put:(Ljava/lang/Object;Ljava/lang/Object;)Ljava/lang/Object;
     691: pop
     692: goto          712
     695: astore        8
     697: new           #60                 // class java/lang/RuntimeException
     700: dup
     701: aload         8
     703: invokevirtual #61                 // Method java/lang/Exception.getMessage:()Ljava/lang/String;
     706: aload         8
     708: invokespecial #62                 // Method java/lang/RuntimeException."<init>":(Ljava/lang/String;Ljava/lang/Throwable;)V
     711: athrow
     712: iinc          6, 1
     715: goto          591
     718: aload_3
     719: areturn
    Exception table:
       from    to  target type
         522   548   551   Class java/lang/Exception
         613   666   695   Class java/lang/Exception
         669   692   695   Class java/lang/Exception

  public static java.lang.Object realize(java.lang.Object, java.lang.Class<?>);
    Code:
       0: aload_0
       1: aload_1
       2: aconst_null
       3: new           #11                 // class java/util/IdentityHashMap
       6: dup
       7: invokespecial #12                 // Method java/util/IdentityHashMap."<init>":()V
      10: invokestatic  #2                  // Method realize0:(Ljava/lang/Object;Ljava/lang/Class;Ljava/lang/reflect/Type;Ljava/util/Map;)Ljava/lang/Object;
      13: areturn

  public static java.lang.Object realize(java.lang.Object, java.lang.Class<?>, java.lang.reflect.Type);
    Code:
       0: aload_0
       1: aload_1
       2: aload_2
       3: new           #11                 // class java/util/IdentityHashMap
       6: dup
       7: invokespecial #12                 // Method java/util/IdentityHashMap."<init>":()V
      10: invokestatic  #2                  // Method realize0:(Ljava/lang/Object;Ljava/lang/Class;Ljava/lang/reflect/Type;Ljava/util/Map;)Ljava/lang/Object;
      13: areturn

  private static java.util.Collection<java.lang.Object> createCollection(java.lang.Class<?>, int);
    Code:
       0: aload_0
       1: ldc           #35                 // class java/util/ArrayList
       3: invokevirtual #19                 // Method java/lang/Class.isAssignableFrom:(Ljava/lang/Class;)Z
       6: ifeq          18
       9: new           #35                 // class java/util/ArrayList
      12: dup
      13: iload_1
      14: invokespecial #36                 // Method java/util/ArrayList."<init>":(I)V
      17: areturn
      18: aload_0
      19: ldc           #37                 // class java/util/HashSet
      21: invokevirtual #19                 // Method java/lang/Class.isAssignableFrom:(Ljava/lang/Class;)Z
      24: ifeq          36
      27: new           #37                 // class java/util/HashSet
      30: dup
      31: iload_1
      32: invokespecial #38                 // Method java/util/HashSet."<init>":(I)V
      35: areturn
      36: aload_0
      37: invokevirtual #68                 // Method java/lang/Class.isInterface:()Z
      40: ifne          73
      43: aload_0
      44: invokevirtual #69                 // Method java/lang/Class.getModifiers:()I
      47: invokestatic  #70                 // Method java/lang/reflect/Modifier.isAbstract:(I)Z
      50: ifne          73
      53: aload_0
      54: iconst_0
      55: anewarray     #28                 // class java/lang/Class
      58: invokevirtual #71                 // Method java/lang/Class.getDeclaredConstructor:([Ljava/lang/Class;)Ljava/lang/reflect/Constructor;
      61: iconst_0
      62: anewarray     #4                  // class java/lang/Object
      65: invokevirtual #72                 // Method java/lang/reflect/Constructor.newInstance:([Ljava/lang/Object;)Ljava/lang/Object;
      68: checkcast     #32                 // class java/util/Collection
      71: areturn
      72: astore_2
      73: new           #35                 // class java/util/ArrayList
      76: dup
      77: invokespecial #73                 // Method java/util/ArrayList."<init>":()V
      80: areturn
    Exception table:
       from    to  target type
          53    71    72   Class java/lang/Exception

  private static java.util.Map createMap(java.util.Map);
    Code:
       0: aload_0
       1: invokevirtual #16                 // Method java/lang/Object.getClass:()Ljava/lang/Class;
       4: astore_1
       5: aconst_null
       6: astore_2
       7: ldc           #50                 // class java/util/HashMap
       9: aload_1
      10: if_acmpne     24
      13: new           #50                 // class java/util/HashMap
      16: dup
      17: invokespecial #51                 // Method java/util/HashMap."<init>":()V
      20: astore_2
      21: goto          220
      24: ldc           #74                 // class java/util/Hashtable
      26: aload_1
      27: if_acmpne     41
      30: new           #74                 // class java/util/Hashtable
      33: dup
      34: invokespecial #75                 // Method java/util/Hashtable."<init>":()V
      37: astore_2
      38: goto          220
      41: ldc           #11                 // class java/util/IdentityHashMap
      43: aload_1
      44: if_acmpne     58
      47: new           #11                 // class java/util/IdentityHashMap
      50: dup
      51: invokespecial #12                 // Method java/util/IdentityHashMap."<init>":()V
      54: astore_2
      55: goto          220
      58: ldc           #76                 // class java/util/LinkedHashMap
      60: aload_1
      61: if_acmpne     75
      64: new           #76                 // class java/util/LinkedHashMap
      67: dup
      68: invokespecial #77                 // Method java/util/LinkedHashMap."<init>":()V
      71: astore_2
      72: goto          220
      75: ldc           #78                 // class java/util/Properties
      77: aload_1
      78: if_acmpne     92
      81: new           #78                 // class java/util/Properties
      84: dup
      85: invokespecial #79                 // Method java/util/Properties."<init>":()V
      88: astore_2
      89: goto          220
      92: ldc           #80                 // class java/util/TreeMap
      94: aload_1
      95: if_acmpne     109
      98: new           #80                 // class java/util/TreeMap
     101: dup
     102: invokespecial #81                 // Method java/util/TreeMap."<init>":()V
     105: astore_2
     106: goto          220
     109: ldc           #82                 // class java/util/WeakHashMap
     111: aload_1
     112: if_acmpne     123
     115: new           #82                 // class java/util/WeakHashMap
     118: dup
     119: invokespecial #83                 // Method java/util/WeakHashMap."<init>":()V
     122: areturn
     123: ldc           #84                 // class java/util/concurrent/ConcurrentHashMap
     125: aload_1
     126: if_acmpne     140
     129: new           #84                 // class java/util/concurrent/ConcurrentHashMap
     132: dup
     133: invokespecial #85                 // Method java/util/concurrent/ConcurrentHashMap."<init>":()V
     136: astore_2
     137: goto          220
     140: ldc           #86                 // class java/util/concurrent/ConcurrentSkipListMap
     142: aload_1
     143: if_acmpne     157
     146: new           #86                 // class java/util/concurrent/ConcurrentSkipListMap
     149: dup
     150: invokespecial #87                 // Method java/util/concurrent/ConcurrentSkipListMap."<init>":()V
     153: astore_2
     154: goto          220
     157: aload_1
     158: iconst_0
     159: anewarray     #28                 // class java/lang/Class
     162: invokevirtual #71                 // Method java/lang/Class.getDeclaredConstructor:([Ljava/lang/Class;)Ljava/lang/reflect/Constructor;
     165: iconst_0
     166: anewarray     #4                  // class java/lang/Object
     169: invokevirtual #72                 // Method java/lang/reflect/Constructor.newInstance:([Ljava/lang/Object;)Ljava/lang/Object;
     172: checkcast     #43                 // class java/util/Map
     175: astore_2
     176: goto          180
     179: astore_3
     180: aload_2
     181: ifnonnull     220
     184: aload_1
     185: iconst_1
     186: anewarray     #28                 // class java/lang/Class
     189: dup
     190: iconst_0
     191: ldc           #43                 // class java/util/Map
     193: aastore
     194: invokevirtual #88                 // Method java/lang/Class.getConstructor:([Ljava/lang/Class;)Ljava/lang/reflect/Constructor;
     197: astore_3
     198: aload_3
     199: iconst_1
     200: anewarray     #4                  // class java/lang/Object
     203: dup
     204: iconst_0
     205: getstatic     #89                 // Field java/util/Collections.EMPTY_MAP:Ljava/util/Map;
     208: aastore
     209: invokevirtual #72                 // Method java/lang/reflect/Constructor.newInstance:([Ljava/lang/Object;)Ljava/lang/Object;
     212: checkcast     #43                 // class java/util/Map
     215: astore_2
     216: goto          220
     219: astore_3
     220: aload_2
     221: ifnonnull     232
     224: new           #50                 // class java/util/HashMap
     227: dup
     228: invokespecial #51                 // Method java/util/HashMap."<init>":()V
     231: astore_2
     232: aload_2
     233: areturn
    Exception table:
       from    to  target type
         157   176   179   Class java/lang/Exception
         184   216   219   Class java/lang/Exception

  private static java.lang.Object realize0(java.lang.Object, java.lang.Class<?>, java.lang.reflect.Type, java.util.Map<java.lang.Object, java.lang.Object>);
    Code:
       0: aload_0
       1: aload_1
       2: aload_2
       3: new           #50                 // class java/util/HashMap
       6: dup
       7: bipush        8
       9: invokespecial #90                 // Method java/util/HashMap."<init>":(I)V
      12: aload_3
      13: invokestatic  #91                 // Method realize1:(Ljava/lang/Object;Ljava/lang/Class;Ljava/lang/reflect/Type;Ljava/util/Map;Ljava/util/Map;)Ljava/lang/Object;
      16: areturn

  private static java.lang.Object realize1(java.lang.Object, java.lang.Class<?>, java.lang.reflect.Type, java.util.Map<java.lang.String, java.lang.reflect.Type>, java.util.Map<java.lang.Object, java.lang.Object>);
    Code:
       0: aload_0
       1: ifnonnull     6
       4: aconst_null
       5: areturn
       6: aload_1
       7: ifnull        35
      10: aload_1
      11: invokevirtual #92                 // Method java/lang/Class.isEnum:()Z
      14: ifeq          35
      17: aload_0
      18: invokevirtual #16                 // Method java/lang/Object.getClass:()Ljava/lang/Class;
      21: ldc           #21                 // class java/lang/String
      23: if_acmpne     35
      26: aload_1
      27: aload_0
      28: checkcast     #21                 // class java/lang/String
      31: invokestatic  #93                 // Method java/lang/Enum.valueOf:(Ljava/lang/Class;Ljava/lang/String;)Ljava/lang/Enum;
      34: areturn
      35: aload_0
      36: invokevirtual #16                 // Method java/lang/Object.getClass:()Ljava/lang/Class;
      39: invokestatic  #23                 // Method org/apache/dubbo/common/utils/ReflectUtils.isPrimitives:(Ljava/lang/Class;)Z
      42: ifeq          81
      45: aload_1
      46: ifnull        75
      49: aload_1
      50: invokevirtual #17                 // Method java/lang/Class.isArray:()Z
      53: ifeq          75
      56: aload_1
      57: invokevirtual #18                 // Method java/lang/Class.getComponentType:()Ljava/lang/Class;
      60: invokevirtual #92                 // Method java/lang/Class.isEnum:()Z
      63: ifeq          75
      66: aload_0
      67: invokevirtual #16                 // Method java/lang/Object.getClass:()Ljava/lang/Class;
      70: ldc           #94                 // class "[Ljava/lang/String;"
      72: if_acmpeq     81
      75: aload_0
      76: aload_1
      77: invokestatic  #95                 // Method org/apache/dubbo/common/utils/CompatibleTypeUtils.compatibleTypeConvert:(Ljava/lang/Object;Ljava/lang/Class;)Ljava/lang/Object;
      80: areturn
      81: aload         4
      83: aload_0
      84: invokeinterface #30,  2           // InterfaceMethod java/util/Map.get:(Ljava/lang/Object;)Ljava/lang/Object;
      89: astore        5
      91: aload         5
      93: ifnull        99
      96: aload         5
      98: areturn
      99: aload         4
     101: aload_0
     102: aload_0
     103: invokeinterface #31,  3           // InterfaceMethod java/util/Map.put:(Ljava/lang/Object;Ljava/lang/Object;)Ljava/lang/Object;
     108: pop
     109: new           #50                 // class java/util/HashMap
     112: dup
     113: bipush        8
     115: invokespecial #90                 // Method java/util/HashMap."<init>":(I)V
     118: astore        6
     120: aload         6
     122: aload_3
     123: invokeinterface #96,  2           // InterfaceMethod java/util/Map.putAll:(Ljava/util/Map;)V
     128: aload_1
     129: invokevirtual #97                 // Method java/lang/Class.getTypeParameters:()[Ljava/lang/reflect/TypeVariable;
     132: astore        7
     134: aload_2
     135: instanceof    #98                 // class java/lang/reflect/ParameterizedType
     138: ifeq          213
     141: aload         7
     143: arraylength
     144: ifle          213
     147: aload_2
     148: checkcast     #98                 // class java/lang/reflect/ParameterizedType
     151: astore        8
     153: aload         8
     155: invokeinterface #99,  1           // InterfaceMethod java/lang/reflect/ParameterizedType.getActualTypeArguments:()[Ljava/lang/reflect/Type;
     160: astore        9
     162: iconst_0
     163: istore        10
     165: iload         10
     167: aload         7
     169: arraylength
     170: if_icmpge     213
     173: aload         9
     175: iload         10
     177: aaload
     178: instanceof    #100                // class java/lang/reflect/TypeVariable
     181: ifne          207
     184: aload         6
     186: aload         7
     188: iload         10
     190: aaload
     191: invokeinterface #101,  1          // InterfaceMethod java/lang/reflect/TypeVariable.getTypeName:()Ljava/lang/String;
     196: aload         9
     198: iload         10
     200: aaload
     201: invokeinterface #31,  3           // InterfaceMethod java/util/Map.put:(Ljava/lang/Object;Ljava/lang/Object;)Ljava/lang/Object;
     206: pop
     207: iinc          10, 1
     210: goto          165
     213: aload_0
     214: invokevirtual #16                 // Method java/lang/Object.getClass:()Ljava/lang/Class;
     217: invokevirtual #17                 // Method java/lang/Class.isArray:()Z
     220: ifeq          420
     223: ldc           #32                 // class java/util/Collection
     225: aload_1
     226: invokevirtual #19                 // Method java/lang/Class.isAssignableFrom:(Ljava/lang/Class;)Z
     229: ifeq          317
     232: aload_0
     233: invokevirtual #16                 // Method java/lang/Object.getClass:()Ljava/lang/Class;
     236: invokevirtual #18                 // Method java/lang/Class.getComponentType:()Ljava/lang/Class;
     239: astore        8
     241: aload_0
     242: invokestatic  #20                 // Method java/lang/reflect/Array.getLength:(Ljava/lang/Object;)I
     245: istore        9
     247: aload_1
     248: iload         9
     250: invokestatic  #102                // Method createCollection:(Ljava/lang/Class;I)Ljava/util/Collection;
     253: astore        10
     255: aload         4
     257: aload_0
     258: aload         10
     260: invokeinterface #31,  3           // InterfaceMethod java/util/Map.put:(Ljava/lang/Object;Ljava/lang/Object;)Ljava/lang/Object;
     265: pop
     266: iconst_0
     267: istore        11
     269: iload         11
     271: iload         9
     273: if_icmpge     314
     276: aload_0
     277: iload         11
     279: invokestatic  #22                 // Method java/lang/reflect/Array.get:(Ljava/lang/Object;I)Ljava/lang/Object;
     282: astore        12
     284: aload         12
     286: aload         8
     288: aconst_null
     289: aload         6
     291: aload         4
     293: invokestatic  #91                 // Method realize1:(Ljava/lang/Object;Ljava/lang/Class;Ljava/lang/reflect/Type;Ljava/util/Map;Ljava/util/Map;)Ljava/lang/Object;
     296: astore        13
     298: aload         10
     300: aload         13
     302: invokeinterface #42,  2           // InterfaceMethod java/util/Collection.add:(Ljava/lang/Object;)Z
     307: pop
     308: iinc          11, 1
     311: goto          269
     314: aload         10
     316: areturn
     317: aload_1
     318: ifnull        335
     321: aload_1
     322: invokevirtual #17                 // Method java/lang/Class.isArray:()Z
     325: ifeq          335
     328: aload_1
     329: invokevirtual #18                 // Method java/lang/Class.getComponentType:()Ljava/lang/Class;
     332: goto          342
     335: aload_0
     336: invokevirtual #16                 // Method java/lang/Object.getClass:()Ljava/lang/Class;
     339: invokevirtual #18                 // Method java/lang/Class.getComponentType:()Ljava/lang/Class;
     342: astore        8
     344: aload_0
     345: invokestatic  #20                 // Method java/lang/reflect/Array.getLength:(Ljava/lang/Object;)I
     348: istore        9
     350: aload         8
     352: iload         9
     354: invokestatic  #103                // Method java/lang/reflect/Array.newInstance:(Ljava/lang/Class;I)Ljava/lang/Object;
     357: astore        10
     359: aload         4
     361: aload_0
     362: aload         10
     364: invokeinterface #31,  3           // InterfaceMethod java/util/Map.put:(Ljava/lang/Object;Ljava/lang/Object;)Ljava/lang/Object;
     369: pop
     370: iconst_0
     371: istore        11
     373: iload         11
     375: iload         9
     377: if_icmpge     417
     380: aload_0
     381: iload         11
     383: invokestatic  #22                 // Method java/lang/reflect/Array.get:(Ljava/lang/Object;I)Ljava/lang/Object;
     386: astore        12
     388: aload         12
     390: aload         8
     392: aconst_null
     393: aload         6
     395: aload         4
     397: invokestatic  #91                 // Method realize1:(Ljava/lang/Object;Ljava/lang/Class;Ljava/lang/reflect/Type;Ljava/util/Map;Ljava/util/Map;)Ljava/lang/Object;
     400: astore        13
     402: aload         10
     404: iload         11
     406: aload         13
     408: invokestatic  #104                // Method java/lang/reflect/Array.set:(Ljava/lang/Object;ILjava/lang/Object;)V
     411: iinc          11, 1
     414: goto          373
     417: aload         10
     419: areturn
     420: aload_0
     421: instanceof    #32                 // class java/util/Collection
     424: ifeq          669
     427: aload_1
     428: invokevirtual #17                 // Method java/lang/Class.isArray:()Z
     431: ifeq          538
     434: aload_1
     435: invokevirtual #18                 // Method java/lang/Class.getComponentType:()Ljava/lang/Class;
     438: astore        8
     440: aload_0
     441: checkcast     #32                 // class java/util/Collection
     444: astore        9
     446: aload         9
     448: invokeinterface #33,  1           // InterfaceMethod java/util/Collection.size:()I
     453: istore        10
     455: aload         8
     457: iload         10
     459: invokestatic  #103                // Method java/lang/reflect/Array.newInstance:(Ljava/lang/Class;I)Ljava/lang/Object;
     462: astore        11
     464: aload         4
     466: aload_0
     467: aload         11
     469: invokeinterface #31,  3           // InterfaceMethod java/util/Map.put:(Ljava/lang/Object;Ljava/lang/Object;)Ljava/lang/Object;
     474: pop
     475: iconst_0
     476: istore        12
     478: aload         9
     480: invokeinterface #39,  1           // InterfaceMethod java/util/Collection.iterator:()Ljava/util/Iterator;
     485: astore        13
     487: aload         13
     489: invokeinterface #40,  1           // InterfaceMethod java/util/Iterator.hasNext:()Z
     494: ifeq          535
     497: aload         13
     499: invokeinterface #41,  1           // InterfaceMethod java/util/Iterator.next:()Ljava/lang/Object;
     504: astore        14
     506: aload         14
     508: aload         8
     510: aconst_null
     511: aload         6
     513: aload         4
     515: invokestatic  #91                 // Method realize1:(Ljava/lang/Object;Ljava/lang/Class;Ljava/lang/reflect/Type;Ljava/util/Map;Ljava/util/Map;)Ljava/lang/Object;
     518: astore        15
     520: aload         11
     522: iload         12
     524: aload         15
     526: invokestatic  #104                // Method java/lang/reflect/Array.set:(Ljava/lang/Object;ILjava/lang/Object;)V
     529: iinc          12, 1
     532: goto          487
     535: aload         11
     537: areturn
     538: aload_0
     539: checkcast     #32                 // class java/util/Collection
     542: astore        8
     544: aload         8
     546: invokeinterface #33,  1           // InterfaceMethod java/util/Collection.size:()I
     551: istore        9
     553: aload_1
     554: iload         9
     556: invokestatic  #102                // Method createCollection:(Ljava/lang/Class;I)Ljava/util/Collection;
     559: astore        10
     561: aload         4
     563: aload_0
     564: aload         10
     566: invokeinterface #31,  3           // InterfaceMethod java/util/Map.put:(Ljava/lang/Object;Ljava/lang/Object;)Ljava/lang/Object;
     571: pop
     572: aload         8
     574: invokeinterface #39,  1           // InterfaceMethod java/util/Collection.iterator:()Ljava/util/Iterator;
     579: astore        11
     581: aload         11
     583: invokeinterface #40,  1           // InterfaceMethod java/util/Iterator.hasNext:()Z
     588: ifeq          666
     591: aload         11
     593: invokeinterface #41,  1           // InterfaceMethod java/util/Iterator.next:()Ljava/lang/Object;
     598: astore        12
     600: aload_2
     601: iconst_0
     602: invokestatic  #105                // Method getGenericClassByIndex:(Ljava/lang/reflect/Type;I)Ljava/lang/reflect/Type;
     605: astore        13
     607: aload         12
     609: ifnonnull     616
     612: aconst_null
     613: goto          621
     616: aload         12
     618: invokevirtual #16                 // Method java/lang/Object.getClass:()Ljava/lang/Class;
     621: astore        14
     623: aload         13
     625: instanceof    #28                 // class java/lang/Class
     628: ifeq          638
     631: aload         13
     633: checkcast     #28                 // class java/lang/Class
     636: astore        14
     638: aload         12
     640: aload         14
     642: aload         13
     644: aload         6
     646: aload         4
     648: invokestatic  #91                 // Method realize1:(Ljava/lang/Object;Ljava/lang/Class;Ljava/lang/reflect/Type;Ljava/util/Map;Ljava/util/Map;)Ljava/lang/Object;
     651: astore        15
     653: aload         10
     655: aload         15
     657: invokeinterface #42,  2           // InterfaceMethod java/util/Collection.add:(Ljava/lang/Object;)Z
     662: pop
     663: goto          581
     666: aload         10
     668: areturn
     669: aload_0
     670: instanceof    #43                 // class java/util/Map
     673: ifeq          1902
     676: aload_1
     677: ifnull        1902
     680: aload_0
     681: checkcast     #43                 // class java/util/Map
     684: ldc           #53                 // String class
     686: invokeinterface #30,  2           // InterfaceMethod java/util/Map.get:(Ljava/lang/Object;)Ljava/lang/Object;
     691: astore        8
     693: aload         8
     695: instanceof    #21                 // class java/lang/String
     698: ifeq          751
     701: getstatic     #106                // Field CLASS_NOT_FOUND_CACHE:Ljava/util/concurrent/ConcurrentMap;
     704: aload         8
     706: invokeinterface #107,  2          // InterfaceMethod java/util/concurrent/ConcurrentMap.containsKey:(Ljava/lang/Object;)Z
     711: ifne          751
     714: invokestatic  #108                // Method org/apache/dubbo/common/utils/DefaultSerializeClassChecker.getInstance:()Lorg/apache/dubbo/common/utils/DefaultSerializeClassChecker;
     717: invokestatic  #109                // Method org/apache/dubbo/common/utils/ClassUtils.getClassLoader:()Ljava/lang/ClassLoader;
     720: aload         8
     722: checkcast     #21                 // class java/lang/String
     725: invokevirtual #110                // Method org/apache/dubbo/common/utils/DefaultSerializeClassChecker.loadClass:(Ljava/lang/ClassLoader;Ljava/lang/String;)Ljava/lang/Class;
     728: astore_1
     729: goto          751
     732: astore        9
     734: getstatic     #106                // Field CLASS_NOT_FOUND_CACHE:Ljava/util/concurrent/ConcurrentMap;
     737: aload         8
     739: checkcast     #21                 // class java/lang/String
     742: getstatic     #112                // Field NOT_FOUND_VALUE:Ljava/lang/Object;
     745: invokeinterface #113,  3          // InterfaceMethod java/util/concurrent/ConcurrentMap.put:(Ljava/lang/Object;Ljava/lang/Object;)Ljava/lang/Object;
     750: pop
     751: aload_1
     752: invokevirtual #92                 // Method java/lang/Class.isEnum:()Z
     755: ifeq          804
     758: aload_0
     759: checkcast     #43                 // class java/util/Map
     762: ldc           #114                // String name
     764: invokeinterface #30,  2           // InterfaceMethod java/util/Map.get:(Ljava/lang/Object;)Ljava/lang/Object;
     769: astore        9
     771: aload         9
     773: ifnull        804
     776: aload         9
     778: instanceof    #21                 // class java/lang/String
     781: ifne          794
     784: new           #6                  // class java/lang/IllegalArgumentException
     787: dup
     788: ldc           #115                // String `name` filed should be string!
     790: invokespecial #8                  // Method java/lang/IllegalArgumentException."<init>":(Ljava/lang/String;)V
     793: athrow
     794: aload_1
     795: aload         9
     797: checkcast     #21                 // class java/lang/String
     800: invokestatic  #93                 // Method java/lang/Enum.valueOf:(Ljava/lang/Class;Ljava/lang/String;)Ljava/lang/Enum;
     803: areturn
     804: aload_1
     805: invokevirtual #68                 // Method java/lang/Class.isInterface:()Z
     808: ifne          887
     811: aload_1
     812: aload_0
     813: invokevirtual #16                 // Method java/lang/Object.getClass:()Ljava/lang/Class;
     816: invokevirtual #19                 // Method java/lang/Class.isAssignableFrom:(Ljava/lang/Class;)Z
     819: ifne          887
     822: aload_1
     823: iconst_0
     824: anewarray     #28                 // class java/lang/Class
     827: invokevirtual #71                 // Method java/lang/Class.getDeclaredConstructor:([Ljava/lang/Class;)Ljava/lang/reflect/Constructor;
     830: iconst_0
     831: anewarray     #4                  // class java/lang/Object
     834: invokevirtual #72                 // Method java/lang/reflect/Constructor.newInstance:([Ljava/lang/Object;)Ljava/lang/Object;
     837: checkcast     #43                 // class java/util/Map
     840: astore        9
     842: aload_0
     843: checkcast     #43                 // class java/util/Map
     846: astore        10
     848: aload         9
     850: aload         10
     852: invokeinterface #96,  2           // InterfaceMethod java/util/Map.putAll:(Ljava/util/Map;)V
     857: getstatic     #52                 // Field GENERIC_WITH_CLZ:Z
     860: ifeq          873
     863: aload         9
     865: ldc           #53                 // String class
     867: invokeinterface #116,  2          // InterfaceMethod java/util/Map.remove:(Ljava/lang/Object;)Ljava/lang/Object;
     872: pop
     873: goto          893
     876: astore        10
     878: aload_0
     879: checkcast     #43                 // class java/util/Map
     882: astore        9
     884: goto          893
     887: aload_0
     888: checkcast     #43                 // class java/util/Map
     891: astore        9
     893: ldc           #43                 // class java/util/Map
     895: aload_1
     896: invokevirtual #19                 // Method java/lang/Class.isAssignableFrom:(Ljava/lang/Class;)Z
     899: ifne          908
     902: aload_1
     903: ldc           #4                  // class java/lang/Object
     905: if_acmpne     1285
     908: aload         9
     910: invokevirtual #16                 // Method java/lang/Object.getClass:()Ljava/lang/Class;
     913: invokestatic  #117                // Method getKeyTypeForMap:(Ljava/lang/Class;)Ljava/lang/reflect/Type;
     916: astore        11
     918: aload_2
     919: iconst_0
     920: invokestatic  #105                // Method getGenericClassByIndex:(Ljava/lang/reflect/Type;I)Ljava/lang/reflect/Type;
     923: astore        12
     925: aload         11
     927: instanceof    #28                 // class java/lang/Class
     930: ifeq          965
     933: aload         12
     935: instanceof    #28                 // class java/lang/Class
     938: ifeq          965
     941: aload         12
     943: invokeinterface #118,  1          // InterfaceMethod java/lang/reflect/Type.getTypeName:()Ljava/lang/String;
     948: aload         11
     950: invokeinterface #118,  1          // InterfaceMethod java/lang/reflect/Type.getTypeName:()Ljava/lang/String;
     955: invokevirtual #119                // Method java/lang/String.equals:(Ljava/lang/Object;)Z
     958: ifne          965
     961: iconst_1
     962: goto          966
     965: iconst_0
     966: istore        13
     968: iload         13
     970: ifeq          989
     973: new           #50                 // class java/util/HashMap
     976: dup
     977: iconst_0
     978: invokespecial #90                 // Method java/util/HashMap."<init>":(I)V
     981: invokestatic  #44                 // Method createMap:(Ljava/util/Map;)Ljava/util/Map;
     984: astore        10
     986: goto          996
     989: aload         9
     991: invokestatic  #44                 // Method createMap:(Ljava/util/Map;)Ljava/util/Map;
     994: astore        10
     996: aload         4
     998: aload_0
     999: aload         10
    1001: invokeinterface #31,  3           // InterfaceMethod java/util/Map.put:(Ljava/lang/Object;Ljava/lang/Object;)Ljava/lang/Object;
    1006: pop
    1007: aload         9
    1009: invokeinterface #45,  1           // InterfaceMethod java/util/Map.entrySet:()Ljava/util/Set;
    1014: invokeinterface #46,  1           // InterfaceMethod java/util/Set.iterator:()Ljava/util/Iterator;
    1019: astore        14
    1021: aload         14
    1023: invokeinterface #40,  1           // InterfaceMethod java/util/Iterator.hasNext:()Z
    1028: ifeq          1282
    1031: aload         14
    1033: invokeinterface #41,  1           // InterfaceMethod java/util/Iterator.next:()Ljava/lang/Object;
    1038: checkcast     #47                 // class java/util/Map$Entry
    1041: astore        15
    1043: aload_2
    1044: iconst_0
    1045: invokestatic  #105                // Method getGenericClassByIndex:(Ljava/lang/reflect/Type;I)Ljava/lang/reflect/Type;
    1048: astore        16
    1050: aload_2
    1051: iconst_1
    1052: invokestatic  #105                // Method getGenericClassByIndex:(Ljava/lang/reflect/Type;I)Ljava/lang/reflect/Type;
    1055: astore        17
    1057: aload         16
    1059: instanceof    #28                 // class java/lang/Class
    1062: ifeq          1075
    1065: aload         16
    1067: checkcast     #28                 // class java/lang/Class
    1070: astore        18
    1072: goto          1127
    1075: aload         16
    1077: instanceof    #98                 // class java/lang/reflect/ParameterizedType
    1080: ifeq          1101
    1083: aload         16
    1085: checkcast     #98                 // class java/lang/reflect/ParameterizedType
    1088: invokeinterface #120,  1          // InterfaceMethod java/lang/reflect/ParameterizedType.getRawType:()Ljava/lang/reflect/Type;
    1093: checkcast     #28                 // class java/lang/Class
    1096: astore        18
    1098: goto          1127
    1101: aload         15
    1103: invokeinterface #48,  1           // InterfaceMethod java/util/Map$Entry.getKey:()Ljava/lang/Object;
    1108: ifnonnull     1115
    1111: aconst_null
    1112: goto          1125
    1115: aload         15
    1117: invokeinterface #48,  1           // InterfaceMethod java/util/Map$Entry.getKey:()Ljava/lang/Object;
    1122: invokevirtual #16                 // Method java/lang/Object.getClass:()Ljava/lang/Class;
    1125: astore        18
    1127: aload         17
    1129: instanceof    #28                 // class java/lang/Class
    1132: ifeq          1145
    1135: aload         17
    1137: checkcast     #28                 // class java/lang/Class
    1140: astore        19
    1142: goto          1197
    1145: aload         17
    1147: instanceof    #98                 // class java/lang/reflect/ParameterizedType
    1150: ifeq          1171
    1153: aload         17
    1155: checkcast     #98                 // class java/lang/reflect/ParameterizedType
    1158: invokeinterface #120,  1          // InterfaceMethod java/lang/reflect/ParameterizedType.getRawType:()Ljava/lang/reflect/Type;
    1163: checkcast     #28                 // class java/lang/Class
    1166: astore        19
    1168: goto          1197
    1171: aload         15
    1173: invokeinterface #49,  1           // InterfaceMethod java/util/Map$Entry.getValue:()Ljava/lang/Object;
    1178: ifnonnull     1185
    1181: aconst_null
    1182: goto          1195
    1185: aload         15
    1187: invokeinterface #49,  1           // InterfaceMethod java/util/Map$Entry.getValue:()Ljava/lang/Object;
    1192: invokevirtual #16                 // Method java/lang/Object.getClass:()Ljava/lang/Class;
    1195: astore        19
    1197: aload         18
    1199: ifnonnull     1212
    1202: aload         15
    1204: invokeinterface #48,  1           // InterfaceMethod java/util/Map$Entry.getKey:()Ljava/lang/Object;
    1209: goto          1230
    1212: aload         15
    1214: invokeinterface #48,  1           // InterfaceMethod java/util/Map$Entry.getKey:()Ljava/lang/Object;
    1219: aload         18
    1221: aload         16
    1223: aload         6
    1225: aload         4
    1227: invokestatic  #91                 // Method realize1:(Ljava/lang/Object;Ljava/lang/Class;Ljava/lang/reflect/Type;Ljava/util/Map;Ljava/util/Map;)Ljava/lang/Object;
    1230: astore        20
    1232: aload         19
    1234: ifnonnull     1247
    1237: aload         15
    1239: invokeinterface #49,  1           // InterfaceMethod java/util/Map$Entry.getValue:()Ljava/lang/Object;
    1244: goto          1265
    1247: aload         15
    1249: invokeinterface #49,  1           // InterfaceMethod java/util/Map$Entry.getValue:()Ljava/lang/Object;
    1254: aload         19
    1256: aload         17
    1258: aload         6
    1260: aload         4
    1262: invokestatic  #91                 // Method realize1:(Ljava/lang/Object;Ljava/lang/Class;Ljava/lang/reflect/Type;Ljava/util/Map;Ljava/util/Map;)Ljava/lang/Object;
    1265: astore        21
    1267: aload         10
    1269: aload         20
    1271: aload         21
    1273: invokeinterface #31,  3           // InterfaceMethod java/util/Map.put:(Ljava/lang/Object;Ljava/lang/Object;)Ljava/lang/Object;
    1278: pop
    1279: goto          1021
    1282: aload         10
    1284: areturn
    1285: aload_1
    1286: invokevirtual #68                 // Method java/lang/Class.isInterface:()Z
    1289: ifeq          1334
    1292: invokestatic  #121                // Method java/lang/Thread.currentThread:()Ljava/lang/Thread;
    1295: invokevirtual #122                // Method java/lang/Thread.getContextClassLoader:()Ljava/lang/ClassLoader;
    1298: iconst_1
    1299: anewarray     #28                 // class java/lang/Class
    1302: dup
    1303: iconst_0
    1304: aload_1
    1305: aastore
    1306: new           #123                // class org/apache/dubbo/common/utils/PojoUtils$PojoInvocationHandler
    1309: dup
    1310: aload         9
    1312: invokespecial #124                // Method org/apache/dubbo/common/utils/PojoUtils$PojoInvocationHandler."<init>":(Ljava/util/Map;)V
    1315: invokestatic  #125                // Method java/lang/reflect/Proxy.newProxyInstance:(Ljava/lang/ClassLoader;[Ljava/lang/Class;Ljava/lang/reflect/InvocationHandler;)Ljava/lang/Object;
    1318: astore        10
    1320: aload         4
    1322: aload_0
    1323: aload         10
    1325: invokeinterface #31,  3           // InterfaceMethod java/util/Map.put:(Ljava/lang/Object;Ljava/lang/Object;)Ljava/lang/Object;
    1330: pop
    1331: aload         10
    1333: areturn
    1334: ldc           #126                // class java/lang/Throwable
    1336: aload_1
    1337: invokevirtual #19                 // Method java/lang/Class.isAssignableFrom:(Ljava/lang/Class;)Z
    1340: ifeq          1385
    1343: aload         9
    1345: ldc           #127                // String message
    1347: invokeinterface #30,  2           // InterfaceMethod java/util/Map.get:(Ljava/lang/Object;)Ljava/lang/Object;
    1352: astore        11
    1354: aload         11
    1356: instanceof    #21                 // class java/lang/String
    1359: ifeq          1376
    1362: aload_1
    1363: aload         11
    1365: checkcast     #21                 // class java/lang/String
    1368: invokestatic  #128                // Method newThrowableInstance:(Ljava/lang/Class;Ljava/lang/String;)Ljava/lang/Object;
    1371: astore        10
    1373: goto          1382
    1376: aload_1
    1377: invokestatic  #129                // Method newInstance:(Ljava/lang/Class;)Ljava/lang/Object;
    1380: astore        10
    1382: goto          1391
    1385: aload_1
    1386: invokestatic  #129                // Method newInstance:(Ljava/lang/Class;)Ljava/lang/Object;
    1389: astore        10
    1391: aload         4
    1393: aload_0
    1394: aload         10
    1396: invokeinterface #31,  3           // InterfaceMethod java/util/Map.put:(Ljava/lang/Object;Ljava/lang/Object;)Ljava/lang/Object;
    1401: pop
    1402: aload         9
    1404: invokeinterface #45,  1           // InterfaceMethod java/util/Map.entrySet:()Ljava/util/Set;
    1409: invokeinterface #46,  1           // InterfaceMethod java/util/Set.iterator:()Ljava/util/Iterator;
    1414: astore        11
    1416: aload         11
    1418: invokeinterface #40,  1           // InterfaceMethod java/util/Iterator.hasNext:()Z
    1423: ifeq          1899
    1426: aload         11
    1428: invokeinterface #41,  1           // InterfaceMethod java/util/Iterator.next:()Ljava/lang/Object;
    1433: checkcast     #47                 // class java/util/Map$Entry
    1436: astore        12
    1438: aload         12
    1440: invokeinterface #48,  1           // InterfaceMethod java/util/Map$Entry.getKey:()Ljava/lang/Object;
    1445: astore        13
    1447: aload         13
    1449: instanceof    #21                 // class java/lang/String
    1452: ifeq          1896
    1455: aload         13
    1457: checkcast     #21                 // class java/lang/String
    1460: astore        14
    1462: aload         12
    1464: invokeinterface #49,  1           // InterfaceMethod java/util/Map$Entry.getValue:()Ljava/lang/Object;
    1469: astore        15
    1471: aload         15
    1473: ifnull        1896
    1476: aload         10
    1478: invokevirtual #16                 // Method java/lang/Object.getClass:()Ljava/lang/Class;
    1481: aload         14
    1483: aload         15
    1485: invokevirtual #16                 // Method java/lang/Object.getClass:()Ljava/lang/Class;
    1488: invokestatic  #130                // Method getSetterMethod:(Ljava/lang/Class;Ljava/lang/String;Ljava/lang/Class;)Ljava/lang/reflect/Method;
    1491: astore        16
    1493: aload         10
    1495: invokevirtual #16                 // Method java/lang/Object.getClass:()Ljava/lang/Class;
    1498: aload         14
    1500: invokestatic  #131                // Method getField:(Ljava/lang/Class;Ljava/lang/String;)Ljava/lang/reflect/Field;
    1503: astore        17
    1505: aload         16
    1507: ifnull        1797
    1510: aload         16
    1512: invokevirtual #132                // Method java/lang/reflect/Method.isAccessible:()Z
    1515: ifne          1524
    1518: aload         16
    1520: iconst_1
    1521: invokevirtual #133                // Method java/lang/reflect/Method.setAccessible:(Z)V
    1524: aload         6
    1526: aload         17
    1528: invokevirtual #134                // Method java/lang/reflect/Field.getGenericType:()Ljava/lang/reflect/Type;
    1531: invokeinterface #118,  1          // InterfaceMethod java/lang/reflect/Type.getTypeName:()Ljava/lang/String;
    1536: invokeinterface #30,  2           // InterfaceMethod java/util/Map.get:(Ljava/lang/Object;)Ljava/lang/Object;
    1541: checkcast     #135                // class java/lang/reflect/Type
    1544: astore        18
    1546: aload         18
    1548: ifnull        1649
    1551: aload         18
    1553: instanceof    #98                 // class java/lang/reflect/ParameterizedType
    1556: ifeq          1588
    1559: aload         15
    1561: aload         18
    1563: checkcast     #98                 // class java/lang/reflect/ParameterizedType
    1566: invokeinterface #120,  1          // InterfaceMethod java/lang/reflect/ParameterizedType.getRawType:()Ljava/lang/reflect/Type;
    1571: checkcast     #28                 // class java/lang/Class
    1574: aload         18
    1576: aload         6
    1578: aload         4
    1580: invokestatic  #91                 // Method realize1:(Ljava/lang/Object;Ljava/lang/Class;Ljava/lang/reflect/Type;Ljava/util/Map;Ljava/util/Map;)Ljava/lang/Object;
    1583: astore        15
    1585: goto          1678
    1588: aload         18
    1590: instanceof    #28                 // class java/lang/Class
    1593: ifeq          1617
    1596: aload         15
    1598: aload         18
    1600: checkcast     #28                 // class java/lang/Class
    1603: aload         18
    1605: aload         6
    1607: aload         4
    1609: invokestatic  #91                 // Method realize1:(Ljava/lang/Object;Ljava/lang/Class;Ljava/lang/reflect/Type;Ljava/util/Map;Ljava/util/Map;)Ljava/lang/Object;
    1612: astore        15
    1614: goto          1678
    1617: aload         16
    1619: invokevirtual #136                // Method java/lang/reflect/Method.getGenericParameterTypes:()[Ljava/lang/reflect/Type;
    1622: iconst_0
    1623: aaload
    1624: astore        19
    1626: aload         15
    1628: aload         16
    1630: invokevirtual #137                // Method java/lang/reflect/Method.getParameterTypes:()[Ljava/lang/Class;
    1633: iconst_0
    1634: aaload
    1635: aload         19
    1637: aload         6
    1639: aload         4
    1641: invokestatic  #91                 // Method realize1:(Ljava/lang/Object;Ljava/lang/Class;Ljava/lang/reflect/Type;Ljava/util/Map;Ljava/util/Map;)Ljava/lang/Object;
    1644: astore        15
    1646: goto          1678
    1649: aload         16
    1651: invokevirtual #136                // Method java/lang/reflect/Method.getGenericParameterTypes:()[Ljava/lang/reflect/Type;
    1654: iconst_0
    1655: aaload
    1656: astore        19
    1658: aload         15
    1660: aload         16
    1662: invokevirtual #137                // Method java/lang/reflect/Method.getParameterTypes:()[Ljava/lang/Class;
    1665: iconst_0
    1666: aaload
    1667: aload         19
    1669: aload         6
    1671: aload         4
    1673: invokestatic  #91                 // Method realize1:(Ljava/lang/Object;Ljava/lang/Class;Ljava/lang/reflect/Type;Ljava/util/Map;Ljava/util/Map;)Ljava/lang/Object;
    1676: astore        15
    1678: aload         16
    1680: aload         10
    1682: iconst_1
    1683: anewarray     #4                  // class java/lang/Object
    1686: dup
    1687: iconst_0
    1688: aload         15
    1690: aastore
    1691: invokevirtual #58                 // Method java/lang/reflect/Method.invoke:(Ljava/lang/Object;[Ljava/lang/Object;)Ljava/lang/Object;
    1694: pop
    1695: goto          1794
    1698: astore        19
    1700: new           #138                // class java/lang/StringBuilder
    1703: dup
    1704: invokespecial #139                // Method java/lang/StringBuilder."<init>":()V
    1707: ldc           #140                // String Failed to set pojo
    1709: invokevirtual #141                // Method java/lang/StringBuilder.append:(Ljava/lang/String;)Ljava/lang/StringBuilder;
    1712: aload         10
    1714: invokevirtual #16                 // Method java/lang/Object.getClass:()Ljava/lang/Class;
    1717: invokevirtual #142                // Method java/lang/Class.getSimpleName:()Ljava/lang/String;
    1720: invokevirtual #141                // Method java/lang/StringBuilder.append:(Ljava/lang/String;)Ljava/lang/StringBuilder;
    1723: ldc           #143                // String  property
    1725: invokevirtual #141                // Method java/lang/StringBuilder.append:(Ljava/lang/String;)Ljava/lang/StringBuilder;
    1728: aload         14
    1730: invokevirtual #141                // Method java/lang/StringBuilder.append:(Ljava/lang/String;)Ljava/lang/StringBuilder;
    1733: ldc           #144                // String  value
    1735: invokevirtual #141                // Method java/lang/StringBuilder.append:(Ljava/lang/String;)Ljava/lang/StringBuilder;
    1738: aload         15
    1740: invokevirtual #16                 // Method java/lang/Object.getClass:()Ljava/lang/Class;
    1743: invokevirtual #145                // Method java/lang/StringBuilder.append:(Ljava/lang/Object;)Ljava/lang/StringBuilder;
    1746: ldc           #146                // String , cause:
    1748: invokevirtual #141                // Method java/lang/StringBuilder.append:(Ljava/lang/String;)Ljava/lang/StringBuilder;
    1751: aload         19
    1753: invokevirtual #61                 // Method java/lang/Exception.getMessage:()Ljava/lang/String;
    1756: invokevirtual #141                // Method java/lang/StringBuilder.append:(Ljava/lang/String;)Ljava/lang/StringBuilder;
    1759: invokevirtual #147                // Method java/lang/StringBuilder.toString:()Ljava/lang/String;
    1762: astore        20
    1764: getstatic     #148                // Field logger:Lorg/apache/dubbo/common/logger/ErrorTypeAwareLogger;
    1767: ldc           #149                // String 0-8
    1769: ldc           #150                // String
    1771: ldc           #150                // String
    1773: aload         20
    1775: aload         19
    1777: invokeinterface #151,  6          // InterfaceMethod org/apache/dubbo/common/logger/ErrorTypeAwareLogger.error:(Ljava/lang/String;Ljava/lang/String;Ljava/lang/String;Ljava/lang/String;Ljava/lang/Throwable;)V
    1782: new           #60                 // class java/lang/RuntimeException
    1785: dup
    1786: aload         20
    1788: aload         19
    1790: invokespecial #62                 // Method java/lang/RuntimeException."<init>":(Ljava/lang/String;Ljava/lang/Throwable;)V
    1793: athrow
    1794: goto          1896
    1797: aload         17
    1799: ifnull        1896
    1802: aload         15
    1804: aload         17
    1806: invokevirtual #152                // Method java/lang/reflect/Field.getType:()Ljava/lang/Class;
    1809: aload         17
    1811: invokevirtual #134                // Method java/lang/reflect/Field.getGenericType:()Ljava/lang/reflect/Type;
    1814: aload         6
    1816: aload         4
    1818: invokestatic  #91                 // Method realize1:(Ljava/lang/Object;Ljava/lang/Class;Ljava/lang/reflect/Type;Ljava/util/Map;Ljava/util/Map;)Ljava/lang/Object;
    1821: astore        15
    1823: aload         17
    1825: aload         10
    1827: aload         15
    1829: invokevirtual #153                // Method java/lang/reflect/Field.set:(Ljava/lang/Object;Ljava/lang/Object;)V
    1832: goto          1896
    1835: astore        18
    1837: new           #60                 // class java/lang/RuntimeException
    1840: dup
    1841: new           #138                // class java/lang/StringBuilder
    1844: dup
    1845: invokespecial #139                // Method java/lang/StringBuilder."<init>":()V
    1848: ldc           #155                // String Failed to set field
    1850: invokevirtual #141                // Method java/lang/StringBuilder.append:(Ljava/lang/String;)Ljava/lang/StringBuilder;
    1853: aload         14
    1855: invokevirtual #141                // Method java/lang/StringBuilder.append:(Ljava/lang/String;)Ljava/lang/StringBuilder;
    1858: ldc           #156                // String  of pojo
    1860: invokevirtual #141                // Method java/lang/StringBuilder.append:(Ljava/lang/String;)Ljava/lang/StringBuilder;
    1863: aload         10
    1865: invokevirtual #16                 // Method java/lang/Object.getClass:()Ljava/lang/Class;
    1868: invokevirtual #29                 // Method java/lang/Class.getName:()Ljava/lang/String;
    1871: invokevirtual #141                // Method java/lang/StringBuilder.append:(Ljava/lang/String;)Ljava/lang/StringBuilder;
    1874: ldc           #157                // String  :
    1876: invokevirtual #141                // Method java/lang/StringBuilder.append:(Ljava/lang/String;)Ljava/lang/StringBuilder;
    1879: aload         18
    1881: invokevirtual #158                // Method java/lang/IllegalAccessException.getMessage:()Ljava/lang/String;
    1884: invokevirtual #141                // Method java/lang/StringBuilder.append:(Ljava/lang/String;)Ljava/lang/StringBuilder;
    1887: invokevirtual #147                // Method java/lang/StringBuilder.toString:()Ljava/lang/String;
    1890: aload         18
    1892: invokespecial #62                 // Method java/lang/RuntimeException."<init>":(Ljava/lang/String;Ljava/lang/Throwable;)V
    1895: athrow
    1896: goto          1416
    1899: aload         10
    1901: areturn
    1902: aload_0
    1903: areturn
    Exception table:
       from    to  target type
         714   729   732   Class java/lang/ClassNotFoundException
         822   873   876   Class java/lang/Exception
        1678  1695  1698   Class java/lang/Exception
        1823  1832  1835   Class java/lang/IllegalAccessException

  private static java.lang.reflect.Type getKeyTypeForMap(java.lang.Class<?>);
    Code:
       0: aload_0
       1: invokevirtual #159                // Method java/lang/Class.getGenericInterfaces:()[Ljava/lang/reflect/Type;
       4: astore_1
       5: aload_1
       6: invokestatic  #160                // Method org/apache/dubbo/common/utils/ArrayUtils.isEmpty:([Ljava/lang/Object;)Z
       9: ifne          83
      12: aload_1
      13: astore_2
      14: aload_2
      15: arraylength
      16: istore_3
      17: iconst_0
      18: istore        4
      20: iload         4
      22: iload_3
      23: if_icmpge     83
      26: aload_2
      27: iload         4
      29: aaload
      30: astore        5
      32: aload         5
      34: instanceof    #98                 // class java/lang/reflect/ParameterizedType
      37: ifeq          77
      40: aload         5
      42: checkcast     #98                 // class java/lang/reflect/ParameterizedType
      45: astore        6
      47: ldc           #161                // String java.util.Map
      49: aload         6
      51: invokeinterface #120,  1          // InterfaceMethod java/lang/reflect/ParameterizedType.getRawType:()Ljava/lang/reflect/Type;
      56: invokeinterface #118,  1          // InterfaceMethod java/lang/reflect/Type.getTypeName:()Ljava/lang/String;
      61: invokevirtual #119                // Method java/lang/String.equals:(Ljava/lang/Object;)Z
      64: ifeq          77
      67: aload         6
      69: invokeinterface #99,  1           // InterfaceMethod java/lang/reflect/ParameterizedType.getActualTypeArguments:()[Ljava/lang/reflect/Type;
      74: iconst_0
      75: aaload
      76: areturn
      77: iinc          4, 1
      80: goto          20
      83: aconst_null
      84: areturn

  private static java.lang.reflect.Type getGenericClassByIndex(java.lang.reflect.Type, int);
    Code:
       0: aconst_null
       1: astore_2
       2: aload_0
       3: instanceof    #98                 // class java/lang/reflect/ParameterizedType
       6: ifeq          27
       9: aload_0
      10: checkcast     #98                 // class java/lang/reflect/ParameterizedType
      13: astore_3
      14: aload_3
      15: invokeinterface #99,  1           // InterfaceMethod java/lang/reflect/ParameterizedType.getActualTypeArguments:()[Ljava/lang/reflect/Type;
      20: astore        4
      22: aload         4
      24: iload_1
      25: aaload
      26: astore_2
      27: aload_2
      28: areturn

  private static java.lang.Object newThrowableInstance(java.lang.Class<?>, java.lang.String);
    Code:
       0: aload_0
       1: iconst_1
       2: anewarray     #28                 // class java/lang/Class
       5: dup
       6: iconst_0
       7: ldc           #21                 // class java/lang/String
       9: aastore
      10: invokevirtual #71                 // Method java/lang/Class.getDeclaredConstructor:([Ljava/lang/Class;)Ljava/lang/reflect/Constructor;
      13: astore_2
      14: aload_2
      15: iconst_1
      16: anewarray     #4                  // class java/lang/Object
      19: dup
      20: iconst_0
      21: aload_1
      22: aastore
      23: invokevirtual #72                 // Method java/lang/reflect/Constructor.newInstance:([Ljava/lang/Object;)Ljava/lang/Object;
      26: areturn
      27: astore_2
      28: aload_0
      29: invokestatic  #129                // Method newInstance:(Ljava/lang/Class;)Ljava/lang/Object;
      32: areturn
    Exception table:
       from    to  target type
           0    26    27   Class java/lang/Throwable

  private static java.lang.Object newInstance(java.lang.Class<?>);
    Code:
       0: aload_0
       1: iconst_0
       2: anewarray     #28                 // class java/lang/Class
       5: invokevirtual #71                 // Method java/lang/Class.getDeclaredConstructor:([Ljava/lang/Class;)Ljava/lang/reflect/Constructor;
       8: iconst_0
       9: anewarray     #4                  // class java/lang/Object
      12: invokevirtual #72                 // Method java/lang/reflect/Constructor.newInstance:([Ljava/lang/Object;)Ljava/lang/Object;
      15: areturn
      16: astore_1
      17: aload_0
      18: invokevirtual #162                // Method java/lang/Class.getDeclaredConstructors:()[Ljava/lang/reflect/Constructor;
      21: astore_2
      22: aload_2
      23: arraylength
      24: ifne          57
      27: new           #60                 // class java/lang/RuntimeException
      30: dup
      31: new           #138                // class java/lang/StringBuilder
      34: dup
      35: invokespecial #139                // Method java/lang/StringBuilder."<init>":()V
      38: ldc           #163                // String Illegal constructor:
      40: invokevirtual #141                // Method java/lang/StringBuilder.append:(Ljava/lang/String;)Ljava/lang/StringBuilder;
      43: aload_0
      44: invokevirtual #29                 // Method java/lang/Class.getName:()Ljava/lang/String;
      47: invokevirtual #141                // Method java/lang/StringBuilder.append:(Ljava/lang/String;)Ljava/lang/StringBuilder;
      50: invokevirtual #147                // Method java/lang/StringBuilder.toString:()Ljava/lang/String;
      53: invokespecial #164                // Method java/lang/RuntimeException."<init>":(Ljava/lang/String;)V
      56: athrow
      57: aconst_null
      58: astore_3
      59: aload_2
      60: invokedynamic #165,  0            // InvokeDynamic #0:applyAsInt:()Ljava/util/function/ToIntFunction;
      65: invokestatic  #166                // InterfaceMethod java/util/Comparator.comparingInt:(Ljava/util/function/ToIntFunction;)Ljava/util/Comparator;
      68: invokestatic  #167                // Method java/util/Arrays.sort:([Ljava/lang/Object;Ljava/util/Comparator;)V
      71: aload_2
      72: astore        4
      74: aload         4
      76: arraylength
      77: istore        5
      79: iconst_0
      80: istore        6
      82: iload         6
      84: iload         5
      86: if_icmpge     146
      89: aload         4
      91: iload         6
      93: aaload
      94: astore        7
      96: aload         7
      98: iconst_1
      99: invokevirtual #168                // Method java/lang/reflect/Constructor.setAccessible:(Z)V
     102: aload         7
     104: invokevirtual #169                // Method java/lang/reflect/Constructor.getParameterTypes:()[Ljava/lang/Class;
     107: invokestatic  #170                // Method java/util/Arrays.stream:([Ljava/lang/Object;)Ljava/util/stream/Stream;
     110: invokedynamic #171,  0            // InvokeDynamic #1:apply:()Ljava/util/function/Function;
     115: invokeinterface #172,  2          // InterfaceMethod java/util/stream/Stream.map:(Ljava/util/function/Function;)Ljava/util/stream/Stream;
     120: invokeinterface #173,  1          // InterfaceMethod java/util/stream/Stream.toArray:()[Ljava/lang/Object;
     125: astore        8
     127: aload         7
     129: aload         8
     131: invokevirtual #72                 // Method java/lang/reflect/Constructor.newInstance:([Ljava/lang/Object;)Ljava/lang/Object;
     134: areturn
     135: astore        8
     137: aload         8
     139: astore_3
     140: iinc          6, 1
     143: goto          82
     146: new           #60                 // class java/lang/RuntimeException
     149: dup
     150: aload_3
     151: invokevirtual #174                // Method java/lang/Throwable.getMessage:()Ljava/lang/String;
     154: aload_3
     155: invokespecial #62                 // Method java/lang/RuntimeException."<init>":(Ljava/lang/String;Ljava/lang/Throwable;)V
     158: athrow
    Exception table:
       from    to  target type
           0    15    16   Class java/lang/Throwable
          96   134   135   Class java/lang/Throwable

  private static java.lang.Object getDefaultValue(java.lang.Class<?>);
    Code:
       0: ldc           #175                // String char
       2: aload_0
       3: invokevirtual #29                 // Method java/lang/Class.getName:()Ljava/lang/String;
       6: invokevirtual #119                // Method java/lang/String.equals:(Ljava/lang/Object;)Z
       9: ifeq          17
      12: iconst_0
      13: invokestatic  #177                // Method java/lang/Character.valueOf:(C)Ljava/lang/Character;
      16: areturn
      17: ldc           #178                // String boolean
      19: aload_0
      20: invokevirtual #29                 // Method java/lang/Class.getName:()Ljava/lang/String;
      23: invokevirtual #119                // Method java/lang/String.equals:(Ljava/lang/Object;)Z
      26: ifeq          34
      29: iconst_0
      30: invokestatic  #179                // Method java/lang/Boolean.valueOf:(Z)Ljava/lang/Boolean;
      33: areturn
      34: ldc           #180                // String byte
      36: aload_0
      37: invokevirtual #29                 // Method java/lang/Class.getName:()Ljava/lang/String;
      40: invokevirtual #119                // Method java/lang/String.equals:(Ljava/lang/Object;)Z
      43: ifeq          51
      46: iconst_0
      47: invokestatic  #181                // Method java/lang/Byte.valueOf:(B)Ljava/lang/Byte;
      50: areturn
      51: ldc           #182                // String short
      53: aload_0
      54: invokevirtual #29                 // Method java/lang/Class.getName:()Ljava/lang/String;
      57: invokevirtual #119                // Method java/lang/String.equals:(Ljava/lang/Object;)Z
      60: ifeq          68
      63: iconst_0
      64: invokestatic  #183                // Method java/lang/Short.valueOf:(S)Ljava/lang/Short;
      67: areturn
      68: aload_0
      69: invokevirtual #184                // Method java/lang/Class.isPrimitive:()Z
      72: ifeq          82
      75: iconst_0
      76: invokestatic  #185                // Method java/lang/Integer.valueOf:(I)Ljava/lang/Integer;
      79: goto          83
      82: aconst_null
      83: areturn

  private static java.lang.reflect.Method getSetterMethod(java.lang.Class<?>, java.lang.String, java.lang.Class<?>);
    Code:
       0: new           #138                // class java/lang/StringBuilder
       3: dup
       4: invokespecial #139                // Method java/lang/StringBuilder."<init>":()V
       7: ldc           #186                // String set
       9: invokevirtual #141                // Method java/lang/StringBuilder.append:(Ljava/lang/String;)Ljava/lang/StringBuilder;
      12: aload_1
      13: iconst_0
      14: iconst_1
      15: invokevirtual #187                // Method java/lang/String.substring:(II)Ljava/lang/String;
      18: invokevirtual #188                // Method java/lang/String.toUpperCase:()Ljava/lang/String;
      21: invokevirtual #141                // Method java/lang/StringBuilder.append:(Ljava/lang/String;)Ljava/lang/StringBuilder;
      24: aload_1
      25: iconst_1
      26: invokevirtual #189                // Method java/lang/String.substring:(I)Ljava/lang/String;
      29: invokevirtual #141                // Method java/lang/StringBuilder.append:(Ljava/lang/String;)Ljava/lang/StringBuilder;
      32: invokevirtual #147                // Method java/lang/StringBuilder.toString:()Ljava/lang/String;
      35: astore_3
      36: getstatic     #190                // Field NAME_METHODS_CACHE:Ljava/util/concurrent/ConcurrentMap;
      39: new           #138                // class java/lang/StringBuilder
      42: dup
      43: invokespecial #139                // Method java/lang/StringBuilder."<init>":()V
      46: aload_0
      47: invokevirtual #29                 // Method java/lang/Class.getName:()Ljava/lang/String;
      50: invokevirtual #141                // Method java/lang/StringBuilder.append:(Ljava/lang/String;)Ljava/lang/StringBuilder;
      53: ldc           #191                // String .
      55: invokevirtual #141                // Method java/lang/StringBuilder.append:(Ljava/lang/String;)Ljava/lang/StringBuilder;
      58: aload_3
      59: invokevirtual #141                // Method java/lang/StringBuilder.append:(Ljava/lang/String;)Ljava/lang/StringBuilder;
      62: ldc           #192                // String (
      64: invokevirtual #141                // Method java/lang/StringBuilder.append:(Ljava/lang/String;)Ljava/lang/StringBuilder;
      67: aload_2
      68: invokevirtual #29                 // Method java/lang/Class.getName:()Ljava/lang/String;
      71: invokevirtual #141                // Method java/lang/StringBuilder.append:(Ljava/lang/String;)Ljava/lang/StringBuilder;
      74: ldc           #193                // String )
      76: invokevirtual #141                // Method java/lang/StringBuilder.append:(Ljava/lang/String;)Ljava/lang/StringBuilder;
      79: invokevirtual #147                // Method java/lang/StringBuilder.toString:()Ljava/lang/String;
      82: invokeinterface #194,  2          // InterfaceMethod java/util/concurrent/ConcurrentMap.get:(Ljava/lang/Object;)Ljava/lang/Object;
      87: checkcast     #195                // class java/lang/reflect/Method
      90: astore        4
      92: aload         4
      94: ifnonnull     237
      97: aload_0
      98: aload_3
      99: iconst_1
     100: anewarray     #28                 // class java/lang/Class
     103: dup
     104: iconst_0
     105: aload_2
     106: aastore
     107: invokevirtual #196                // Method java/lang/Class.getMethod:(Ljava/lang/String;[Ljava/lang/Class;)Ljava/lang/reflect/Method;
     110: astore        4
     112: goto          178
     115: astore        5
     117: aload_0
     118: invokevirtual #54                 // Method java/lang/Class.getMethods:()[Ljava/lang/reflect/Method;
     121: astore        6
     123: aload         6
     125: arraylength
     126: istore        7
     128: iconst_0
     129: istore        8
     131: iload         8
     133: iload         7
     135: if_icmpge     178
     138: aload         6
     140: iload         8
     142: aaload
     143: astore        9
     145: aload         9
     147: invokestatic  #198                // Method org/apache/dubbo/common/utils/ReflectUtils.isBeanPropertyWriteMethod:(Ljava/lang/reflect/Method;)Z
     150: ifeq          172
     153: aload         9
     155: invokevirtual #199                // Method java/lang/reflect/Method.getName:()Ljava/lang/String;
     158: aload_3
     159: invokevirtual #119                // Method java/lang/String.equals:(Ljava/lang/Object;)Z
     162: ifeq          172
     165: aload         9
     167: astore        4
     169: goto          178
     172: iinc          8, 1
     175: goto          131
     178: aload         4
     180: ifnull        237
     183: getstatic     #190                // Field NAME_METHODS_CACHE:Ljava/util/concurrent/ConcurrentMap;
     186: new           #138                // class java/lang/StringBuilder
     189: dup
     190: invokespecial #139                // Method java/lang/StringBuilder."<init>":()V
     193: aload_0
     194: invokevirtual #29                 // Method java/lang/Class.getName:()Ljava/lang/String;
     197: invokevirtual #141                // Method java/lang/StringBuilder.append:(Ljava/lang/String;)Ljava/lang/StringBuilder;
     200: ldc           #191                // String .
     202: invokevirtual #141                // Method java/lang/StringBuilder.append:(Ljava/lang/String;)Ljava/lang/StringBuilder;
     205: aload_3
     206: invokevirtual #141                // Method java/lang/StringBuilder.append:(Ljava/lang/String;)Ljava/lang/StringBuilder;
     209: ldc           #192                // String (
     211: invokevirtual #141                // Method java/lang/StringBuilder.append:(Ljava/lang/String;)Ljava/lang/StringBuilder;
     214: aload_2
     215: invokevirtual #29                 // Method java/lang/Class.getName:()Ljava/lang/String;
     218: invokevirtual #141                // Method java/lang/StringBuilder.append:(Ljava/lang/String;)Ljava/lang/StringBuilder;
     221: ldc           #193                // String )
     223: invokevirtual #141                // Method java/lang/StringBuilder.append:(Ljava/lang/String;)Ljava/lang/StringBuilder;
     226: invokevirtual #147                // Method java/lang/StringBuilder.toString:()Ljava/lang/String;
     229: aload         4
     231: invokeinterface #113,  3          // InterfaceMethod java/util/concurrent/ConcurrentMap.put:(Ljava/lang/Object;Ljava/lang/Object;)Ljava/lang/Object;
     236: pop
     237: aload         4
     239: areturn
    Exception table:
       from    to  target type
          97   112   115   Class java/lang/NoSuchMethodException

  private static java.lang.reflect.Field getField(java.lang.Class<?>, java.lang.String);
    Code:
       0: aconst_null
       1: astore_2
       2: getstatic     #200                // Field CLASS_FIELD_CACHE:Ljava/util/concurrent/ConcurrentMap;
       5: aload_0
       6: invokeinterface #107,  2          // InterfaceMethod java/util/concurrent/ConcurrentMap.containsKey:(Ljava/lang/Object;)Z
      11: ifeq          57
      14: getstatic     #200                // Field CLASS_FIELD_CACHE:Ljava/util/concurrent/ConcurrentMap;
      17: aload_0
      18: invokeinterface #194,  2          // InterfaceMethod java/util/concurrent/ConcurrentMap.get:(Ljava/lang/Object;)Ljava/lang/Object;
      23: checkcast     #201                // class java/util/concurrent/ConcurrentMap
      26: aload_1
      27: invokeinterface #107,  2          // InterfaceMethod java/util/concurrent/ConcurrentMap.containsKey:(Ljava/lang/Object;)Z
      32: ifeq          57
      35: getstatic     #200                // Field CLASS_FIELD_CACHE:Ljava/util/concurrent/ConcurrentMap;
      38: aload_0
      39: invokeinterface #194,  2          // InterfaceMethod java/util/concurrent/ConcurrentMap.get:(Ljava/lang/Object;)Ljava/lang/Object;
      44: checkcast     #201                // class java/util/concurrent/ConcurrentMap
      47: aload_1
      48: invokeinterface #194,  2          // InterfaceMethod java/util/concurrent/ConcurrentMap.get:(Ljava/lang/Object;)Ljava/lang/Object;
      53: checkcast     #202                // class java/lang/reflect/Field
      56: areturn
      57: aload_0
      58: astore_3
      59: aload_3
      60: ifnull        97
      63: aload_3
      64: aload_1
      65: invokevirtual #203                // Method java/lang/Class.getDeclaredField:(Ljava/lang/String;)Ljava/lang/reflect/Field;
      68: astore_2
      69: aload_2
      70: invokevirtual #204                // Method java/lang/reflect/Field.getModifiers:()I
      73: invokestatic  #205                // Method java/lang/reflect/Modifier.isPublic:(I)Z
      76: ifne          84
      79: aload_2
      80: iconst_1
      81: invokevirtual #206                // Method java/lang/reflect/Field.setAccessible:(Z)V
      84: goto          89
      87: astore        4
      89: aload_3
      90: invokevirtual #208                // Method java/lang/Class.getSuperclass:()Ljava/lang/Class;
      93: astore_3
      94: goto          59
      97: aload_2
      98: ifnonnull     158
     101: aload_0
     102: invokevirtual #63                 // Method java/lang/Class.getFields:()[Ljava/lang/reflect/Field;
     105: astore_3
     106: aload_3
     107: arraylength
     108: istore        4
     110: iconst_0
     111: istore        5
     113: iload         5
     115: iload         4
     117: if_icmpge     158
     120: aload_3
     121: iload         5
     123: aaload
     124: astore        6
     126: aload_1
     127: aload         6
     129: invokevirtual #67                 // Method java/lang/reflect/Field.getName:()Ljava/lang/String;
     132: invokevirtual #119                // Method java/lang/String.equals:(Ljava/lang/Object;)Z
     135: ifeq          152
     138: aload         6
     140: invokestatic  #64                 // Method org/apache/dubbo/common/utils/ReflectUtils.isPublicInstanceField:(Ljava/lang/reflect/Field;)Z
     143: ifeq          152
     146: aload         6
     148: astore_2
     149: goto          158
     152: iinc          5, 1
     155: goto          113
     158: aload_2
     159: ifnull        189
     162: getstatic     #200                // Field CLASS_FIELD_CACHE:Ljava/util/concurrent/ConcurrentMap;
     165: aload_0
     166: invokedynamic #209,  0            // InvokeDynamic #2:apply:()Ljava/util/function/Function;
     171: invokeinterface #210,  3          // InterfaceMethod java/util/concurrent/ConcurrentMap.computeIfAbsent:(Ljava/lang/Object;Ljava/util/function/Function;)Ljava/lang/Object;
     176: checkcast     #201                // class java/util/concurrent/ConcurrentMap
     179: astore_3
     180: aload_3
     181: aload_1
     182: aload_2
     183: invokeinterface #211,  3          // InterfaceMethod java/util/concurrent/ConcurrentMap.putIfAbsent:(Ljava/lang/Object;Ljava/lang/Object;)Ljava/lang/Object;
     188: pop
     189: aload_2
     190: areturn
    Exception table:
       from    to  target type
          63    84    87   Class java/lang/NoSuchFieldException

  public static boolean isPojo(java.lang.Class<?>);
    Code:
       0: aload_0
       1: invokestatic  #23                 // Method org/apache/dubbo/common/utils/ReflectUtils.isPrimitives:(Ljava/lang/Class;)Z
       4: ifne          29
       7: ldc           #32                 // class java/util/Collection
       9: aload_0
      10: invokevirtual #19                 // Method java/lang/Class.isAssignableFrom:(Ljava/lang/Class;)Z
      13: ifne          29
      16: ldc           #43                 // class java/util/Map
      18: aload_0
      19: invokevirtual #19                 // Method java/lang/Class.isAssignableFrom:(Ljava/lang/Class;)Z
      22: ifne          29
      25: iconst_1
      26: goto          30
      29: iconst_0
      30: ireturn

  public static <T> void updatePropertyIfAbsent(java.util.function.Supplier<T>, java.util.function.Consumer<T>, T);
    Code:
       0: aload_2
       1: ifnull        20
       4: aload_0
       5: invokeinterface #212,  1          // InterfaceMethod java/util/function/Supplier.get:()Ljava/lang/Object;
      10: ifnonnull     20
      13: aload_1
      14: aload_2
      15: invokeinterface #213,  2          // InterfaceMethod java/util/function/Consumer.accept:(Ljava/lang/Object;)V
      20: return

  public static <T> T mapToPojo(java.util.Map<java.lang.String, java.lang.Object>, java.lang.Class<T>) throws java.lang.ReflectiveOperationException;
    Code:
       0: aload_1
       1: iconst_0
       2: anewarray     #28                 // class java/lang/Class
       5: invokevirtual #71                 // Method java/lang/Class.getDeclaredConstructor:([Ljava/lang/Class;)Ljava/lang/reflect/Constructor;
       8: iconst_0
       9: anewarray     #4                  // class java/lang/Object
      12: invokevirtual #72                 // Method java/lang/reflect/Constructor.newInstance:([Ljava/lang/Object;)Ljava/lang/Object;
      15: astore_2
      16: aload_1
      17: invokestatic  #214                // Method org/apache/dubbo/common/utils/ReflectUtils.getBeanPropertyFields:(Ljava/lang/Class;)Ljava/util/Map;
      20: astore_3
      21: aload_3
      22: invokeinterface #45,  1           // InterfaceMethod java/util/Map.entrySet:()Ljava/util/Set;
      27: invokeinterface #46,  1           // InterfaceMethod java/util/Set.iterator:()Ljava/util/Iterator;
      32: astore        4
      34: aload         4
      36: invokeinterface #40,  1           // InterfaceMethod java/util/Iterator.hasNext:()Z
      41: ifeq          125
      44: aload         4
      46: invokeinterface #41,  1           // InterfaceMethod java/util/Iterator.next:()Ljava/lang/Object;
      51: checkcast     #47                 // class java/util/Map$Entry
      54: astore        5
      56: aload         5
      58: invokeinterface #48,  1           // InterfaceMethod java/util/Map$Entry.getKey:()Ljava/lang/Object;
      63: checkcast     #21                 // class java/lang/String
      66: astore        6
      68: aload         5
      70: invokeinterface #49,  1           // InterfaceMethod java/util/Map$Entry.getValue:()Ljava/lang/Object;
      75: checkcast     #202                // class java/lang/reflect/Field
      78: astore        7
      80: aload_0
      81: aload         6
      83: invokeinterface #30,  2           // InterfaceMethod java/util/Map.get:(Ljava/lang/Object;)Ljava/lang/Object;
      88: astore        8
      90: aload         8
      92: ifnonnull     98
      95: goto          34
      98: aload         7
     100: invokevirtual #134                // Method java/lang/reflect/Field.getGenericType:()Ljava/lang/reflect/Type;
     103: astore        9
     105: aload         8
     107: aload         9
     109: invokestatic  #215                // Method getFieldObject:(Ljava/lang/Object;Ljava/lang/reflect/Type;)Ljava/lang/Object;
     112: astore        10
     114: aload         7
     116: aload_2
     117: aload         10
     119: invokevirtual #153                // Method java/lang/reflect/Field.set:(Ljava/lang/Object;Ljava/lang/Object;)V
     122: goto          34
     125: aload_2
     126: areturn

  private static java.lang.Object getFieldObject(java.lang.Object, java.lang.reflect.Type) throws java.lang.ReflectiveOperationException;
    Code:
       0: aload_1
       1: instanceof    #28                 // class java/lang/Class
       4: ifeq          16
       7: aload_0
       8: aload_1
       9: checkcast     #28                 // class java/lang/Class
      12: invokestatic  #216                // Method convertClassType:(Ljava/lang/Object;Ljava/lang/Class;)Ljava/lang/Object;
      15: areturn
      16: aload_1
      17: instanceof    #98                 // class java/lang/reflect/ParameterizedType
      20: ifeq          32
      23: aload_0
      24: aload_1
      25: checkcast     #98                 // class java/lang/reflect/ParameterizedType
      28: invokestatic  #217                // Method convertParameterizedType:(Ljava/lang/Object;Ljava/lang/reflect/ParameterizedType;)Ljava/lang/Object;
      31: areturn
      32: aload_1
      33: instanceof    #218                // class java/lang/reflect/GenericArrayType
      36: ifne          53
      39: aload_1
      40: instanceof    #100                // class java/lang/reflect/TypeVariable
      43: ifne          53
      46: aload_1
      47: instanceof    #219                // class java/lang/reflect/WildcardType
      50: ifeq          55
      53: aconst_null
      54: areturn
      55: new           #6                  // class java/lang/IllegalArgumentException
      58: dup
      59: new           #138                // class java/lang/StringBuilder
      62: dup
      63: invokespecial #139                // Method java/lang/StringBuilder."<init>":()V
      66: ldc           #220                // String Unrecognized Type:
      68: invokevirtual #141                // Method java/lang/StringBuilder.append:(Ljava/lang/String;)Ljava/lang/StringBuilder;
      71: aload_1
      72: invokevirtual #27                 // Method java/lang/Object.toString:()Ljava/lang/String;
      75: invokevirtual #141                // Method java/lang/StringBuilder.append:(Ljava/lang/String;)Ljava/lang/StringBuilder;
      78: invokevirtual #147                // Method java/lang/StringBuilder.toString:()Ljava/lang/String;
      81: invokespecial #8                  // Method java/lang/IllegalArgumentException."<init>":(Ljava/lang/String;)V
      84: athrow

  private static java.lang.Object convertClassType(java.lang.Object, java.lang.Class<?>) throws java.lang.ReflectiveOperationException;
    Code:
       0: aload_1
       1: invokevirtual #184                // Method java/lang/Class.isPrimitive:()Z
       4: ifne          18
       7: aload_1
       8: aload_0
       9: invokevirtual #16                 // Method java/lang/Object.getClass:()Ljava/lang/Class;
      12: invokestatic  #221                // Method org/apache/dubbo/common/utils/ClassUtils.isAssignableFrom:(Ljava/lang/Class;Ljava/lang/Class;)Z
      15: ifeq          20
      18: aload_0
      19: areturn
      20: aload_1
      21: ldc           #21                 // class java/lang/String
      23: invokestatic  #222                // Method java/util/Objects.equals:(Ljava/lang/Object;Ljava/lang/Object;)Z
      26: ifeq          49
      29: getstatic     #223                // Field CLASS_CAN_BE_STRING:Ljava/util/List;
      32: aload_0
      33: invokevirtual #16                 // Method java/lang/Object.getClass:()Ljava/lang/Class;
      36: invokeinterface #224,  2          // InterfaceMethod java/util/List.contains:(Ljava/lang/Object;)Z
      41: ifeq          49
      44: aload_0
      45: invokevirtual #27                 // Method java/lang/Object.toString:()Ljava/lang/String;
      48: areturn
      49: aload_0
      50: instanceof    #43                 // class java/util/Map
      53: ifeq          65
      56: aload_0
      57: checkcast     #43                 // class java/util/Map
      60: aload_1
      61: invokestatic  #225                // Method mapToPojo:(Ljava/util/Map;Ljava/lang/Class;)Ljava/lang/Object;
      64: areturn
      65: aconst_null
      66: areturn

  private static java.lang.Object convertParameterizedType(java.lang.Object, java.lang.reflect.ParameterizedType) throws java.lang.ReflectiveOperationException;
    Code:
       0: aload_1
       1: invokeinterface #120,  1          // InterfaceMethod java/lang/reflect/ParameterizedType.getRawType:()Ljava/lang/reflect/Type;
       6: astore_2
       7: aload_2
       8: checkcast     #28                 // class java/lang/Class
      11: aload_0
      12: invokevirtual #16                 // Method java/lang/Object.getClass:()Ljava/lang/Class;
      15: invokestatic  #221                // Method org/apache/dubbo/common/utils/ClassUtils.isAssignableFrom:(Ljava/lang/Class;Ljava/lang/Class;)Z
      18: ifne          23
      21: aconst_null
      22: areturn
      23: aload_1
      24: invokeinterface #99,  1           // InterfaceMethod java/lang/reflect/ParameterizedType.getActualTypeArguments:()[Ljava/lang/reflect/Type;
      29: astore_3
      30: ldc           #43                 // class java/util/Map
      32: aload_2
      33: checkcast     #28                 // class java/lang/Class
      36: invokestatic  #221                // Method org/apache/dubbo/common/utils/ClassUtils.isAssignableFrom:(Ljava/lang/Class;Ljava/lang/Class;)Z
      39: ifeq          151
      42: aload_0
      43: invokevirtual #16                 // Method java/lang/Object.getClass:()Ljava/lang/Class;
      46: iconst_0
      47: anewarray     #28                 // class java/lang/Class
      50: invokevirtual #71                 // Method java/lang/Class.getDeclaredConstructor:([Ljava/lang/Class;)Ljava/lang/reflect/Constructor;
      53: iconst_0
      54: anewarray     #4                  // class java/lang/Object
      57: invokevirtual #72                 // Method java/lang/reflect/Constructor.newInstance:([Ljava/lang/Object;)Ljava/lang/Object;
      60: checkcast     #43                 // class java/util/Map
      63: astore        4
      65: aload_0
      66: checkcast     #43                 // class java/util/Map
      69: invokeinterface #45,  1           // InterfaceMethod java/util/Map.entrySet:()Ljava/util/Set;
      74: invokeinterface #46,  1           // InterfaceMethod java/util/Set.iterator:()Ljava/util/Iterator;
      79: astore        5
      81: aload         5
      83: invokeinterface #40,  1           // InterfaceMethod java/util/Iterator.hasNext:()Z
      88: ifeq          148
      91: aload         5
      93: invokeinterface #41,  1           // InterfaceMethod java/util/Iterator.next:()Ljava/lang/Object;
      98: checkcast     #47                 // class java/util/Map$Entry
     101: astore        6
     103: aload         6
     105: invokeinterface #48,  1           // InterfaceMethod java/util/Map$Entry.getKey:()Ljava/lang/Object;
     110: aload_3
     111: iconst_0
     112: aaload
     113: invokestatic  #215                // Method getFieldObject:(Ljava/lang/Object;Ljava/lang/reflect/Type;)Ljava/lang/Object;
     116: astore        7
     118: aload         6
     120: invokeinterface #49,  1           // InterfaceMethod java/util/Map$Entry.getValue:()Ljava/lang/Object;
     125: aload_3
     126: iconst_1
     127: aaload
     128: invokestatic  #215                // Method getFieldObject:(Ljava/lang/Object;Ljava/lang/reflect/Type;)Ljava/lang/Object;
     131: astore        8
     133: aload         4
     135: aload         7
     137: aload         8
     139: invokeinterface #31,  3           // InterfaceMethod java/util/Map.put:(Ljava/lang/Object;Ljava/lang/Object;)Ljava/lang/Object;
     144: pop
     145: goto          81
     148: aload         4
     150: areturn
     151: ldc           #32                 // class java/util/Collection
     153: aload_2
     154: checkcast     #28                 // class java/lang/Class
     157: invokestatic  #221                // Method org/apache/dubbo/common/utils/ClassUtils.isAssignableFrom:(Ljava/lang/Class;Ljava/lang/Class;)Z
     160: ifeq          242
     163: aload_0
     164: invokevirtual #16                 // Method java/lang/Object.getClass:()Ljava/lang/Class;
     167: iconst_0
     168: anewarray     #28                 // class java/lang/Class
     171: invokevirtual #71                 // Method java/lang/Class.getDeclaredConstructor:([Ljava/lang/Class;)Ljava/lang/reflect/Constructor;
     174: iconst_0
     175: anewarray     #4                  // class java/lang/Object
     178: invokevirtual #72                 // Method java/lang/reflect/Constructor.newInstance:([Ljava/lang/Object;)Ljava/lang/Object;
     181: checkcast     #32                 // class java/util/Collection
     184: astore        4
     186: aload_0
     187: checkcast     #226                // class java/lang/Iterable
     190: invokeinterface #227,  1          // InterfaceMethod java/lang/Iterable.iterator:()Ljava/util/Iterator;
     195: astore        5
     197: aload         5
     199: invokeinterface #40,  1           // InterfaceMethod java/util/Iterator.hasNext:()Z
     204: ifeq          239
     207: aload         5
     209: invokeinterface #41,  1           // InterfaceMethod java/util/Iterator.next:()Ljava/lang/Object;
     214: astore        6
     216: aload         6
     218: aload_3
     219: iconst_0
     220: aaload
     221: invokestatic  #215                // Method getFieldObject:(Ljava/lang/Object;Ljava/lang/reflect/Type;)Ljava/lang/Object;
     224: astore        7
     226: aload         4
     228: aload         7
     230: invokeinterface #42,  2           // InterfaceMethod java/util/Collection.add:(Ljava/lang/Object;)Z
     235: pop
     236: goto          197
     239: aload         4
     241: areturn
     242: aconst_null
     243: areturn

  private static java.util.concurrent.ConcurrentMap lambda$getField$1(java.lang.Class);
    Code:
       0: new           #84                 // class java/util/concurrent/ConcurrentHashMap
       3: dup
       4: invokespecial #85                 // Method java/util/concurrent/ConcurrentHashMap."<init>":()V
       7: areturn

  private static int lambda$newInstance$0(java.lang.reflect.Constructor);
    Code:
       0: aload_0
       1: invokevirtual #169                // Method java/lang/reflect/Constructor.getParameterTypes:()[Ljava/lang/Class;
       4: arraylength
       5: ireturn

  static java.lang.Object access$000(java.lang.Object, java.lang.Class, java.lang.reflect.Type, java.util.Map);
    Code:
       0: aload_0
       1: aload_1
       2: aload_2
       3: aload_3
       4: invokestatic  #2                  // Method realize0:(Ljava/lang/Object;Ljava/lang/Class;Ljava/lang/reflect/Type;Ljava/util/Map;)Ljava/lang/Object;
       7: areturn

  static {};
    Code:
       0: ldc           #228                // class org/apache/dubbo/common/utils/PojoUtils
       2: invokestatic  #229                // Method org/apache/dubbo/common/logger/LoggerFactory.getErrorTypeAwareLogger:(Ljava/lang/Class;)Lorg/apache/dubbo/common/logger/ErrorTypeAwareLogger;
       5: putstatic     #148                // Field logger:Lorg/apache/dubbo/common/logger/ErrorTypeAwareLogger;
       8: new           #84                 // class java/util/concurrent/ConcurrentHashMap
      11: dup
      12: invokespecial #85                 // Method java/util/concurrent/ConcurrentHashMap."<init>":()V
      15: putstatic     #190                // Field NAME_METHODS_CACHE:Ljava/util/concurrent/ConcurrentMap;
      18: new           #84                 // class java/util/concurrent/ConcurrentHashMap
      21: dup
      22: invokespecial #85                 // Method java/util/concurrent/ConcurrentHashMap."<init>":()V
      25: putstatic     #200                // Field CLASS_FIELD_CACHE:Ljava/util/concurrent/ConcurrentMap;
      28: new           #84                 // class java/util/concurrent/ConcurrentHashMap
      31: dup
      32: invokespecial #85                 // Method java/util/concurrent/ConcurrentHashMap."<init>":()V
      35: putstatic     #106                // Field CLASS_NOT_FOUND_CACHE:Ljava/util/concurrent/ConcurrentMap;
      38: new           #4                  // class java/lang/Object
      41: dup
      42: invokespecial #3                  // Method java/lang/Object."<init>":()V
      45: putstatic     #112                // Field NOT_FOUND_VALUE:Ljava/lang/Object;
      48: invokestatic  #230                // Method org/apache/dubbo/rpc/model/ApplicationModel.defaultModel:()Lorg/apache/dubbo/rpc/model/ApplicationModel;
      51: ldc           #232                // String generic.include.class
      53: ldc           #233                // String true
      55: invokestatic  #234                // Method org/apache/dubbo/common/config/ConfigurationUtils.getProperty:(Lorg/apache/dubbo/rpc/model/ScopeModel;Ljava/lang/String;Ljava/lang/String;)Ljava/lang/String;
      58: invokestatic  #235                // Method java/lang/Boolean.parseBoolean:(Ljava/lang/String;)Z
      61: putstatic     #52                 // Field GENERIC_WITH_CLZ:Z
      64: bipush        8
      66: anewarray     #28                 // class java/lang/Class
      69: dup
      70: iconst_0
      71: ldc           #236                // class java/lang/Byte
      73: aastore
      74: dup
      75: iconst_1
      76: ldc           #237                // class java/lang/Short
      78: aastore
      79: dup
      80: iconst_2
      81: ldc           #238                // class java/lang/Integer
      83: aastore
      84: dup
      85: iconst_3
      86: ldc           #239                // class java/lang/Long
      88: aastore
      89: dup
      90: iconst_4
      91: ldc           #240                // class java/lang/Float
      93: aastore
      94: dup
      95: iconst_5
      96: ldc           #241                // class java/lang/Double
      98: aastore
      99: dup
     100: bipush        6
     102: ldc           #242                // class java/lang/Boolean
     104: aastore
     105: dup
     106: bipush        7
     108: ldc           #176                // class java/lang/Character
     110: aastore
     111: invokestatic  #243                // Method java/util/Arrays.asList:([Ljava/lang/Object;)Ljava/util/List;
     114: putstatic     #223                // Field CLASS_CAN_BE_STRING:Ljava/util/List;
     117: return
}
