Compiled from "ReflectUtils.java"
public final class org.apache.dubbo.common.utils.ReflectUtils {
  public static final char JVM_VOID;

  public static final char JVM_BOOLEAN;

  public static final char JVM_BYTE;

  public static final char JVM_CHAR;

  public static final char JVM_DOUBLE;

  public static final char JVM_FLOAT;

  public static final char JVM_INT;

  public static final char JVM_LONG;

  public static final char JVM_SHORT;

  public static final java.lang.Class<?>[] EMPTY_CLASS_ARRAY;

  public static final java.lang.String JAVA_IDENT_REGEX;

  public static final java.lang.String JAVA_NAME_REGEX;

  public static final java.lang.String CLASS_DESC;

  public static final java.lang.String ARRAY_DESC;

  public static final java.lang.String DESC_REGEX;

  public static final java.util.regex.Pattern DESC_PATTERN;

  public static final java.lang.String METHOD_DESC_REGEX;

  public static final java.util.regex.Pattern METHOD_DESC_PATTERN;

  public static final java.util.regex.Pattern GETTER_METHOD_DESC_PATTERN;

  public static final java.util.regex.Pattern SETTER_METHOD_DESC_PATTERN;

  public static final java.util.regex.Pattern IS_HAS_CAN_METHOD_DESC_PATTERN;

  private static java.util.Map<java.lang.Class<?>, java.lang.Object> primitiveDefaults;

  private org.apache.dubbo.common.utils.ReflectUtils();
    Code:
       0: aload_0
       1: invokespecial #2                  // Method java/lang/Object."<init>":()V
       4: return

  public static boolean isPrimitives(java.lang.Class<?>);
    Code:
       0: aload_0
       1: invokevirtual #3                  // Method java/lang/Class.isArray:()Z
       4: ifeq          15
       7: aload_0
       8: invokevirtual #4                  // Method java/lang/Class.getComponentType:()Ljava/lang/Class;
      11: astore_0
      12: goto          0
      15: aload_0
      16: invokestatic  #5                  // Method isPrimitive:(Ljava/lang/Class;)Z
      19: ireturn

  public static boolean isPrimitive(java.lang.Class<?>);
    Code:
       0: aload_0
       1: invokevirtual #6                  // Method java/lang/Class.isPrimitive:()Z
       4: ifne          43
       7: aload_0
       8: ldc           #7                  // class java/lang/String
      10: if_acmpeq     43
      13: aload_0
      14: ldc           #8                  // class java/lang/Boolean
      16: if_acmpeq     43
      19: aload_0
      20: ldc           #9                  // class java/lang/Character
      22: if_acmpeq     43
      25: ldc           #10                 // class java/lang/Number
      27: aload_0
      28: invokevirtual #11                 // Method java/lang/Class.isAssignableFrom:(Ljava/lang/Class;)Z
      31: ifne          43
      34: ldc           #12                 // class java/util/Date
      36: aload_0
      37: invokevirtual #11                 // Method java/lang/Class.isAssignableFrom:(Ljava/lang/Class;)Z
      40: ifeq          47
      43: iconst_1
      44: goto          48
      47: iconst_0
      48: ireturn

  public static java.lang.Class<?> getBoxedClass(java.lang.Class<?>);
    Code:
       0: aload_0
       1: getstatic     #13                 // Field java/lang/Integer.TYPE:Ljava/lang/Class;
       4: if_acmpne     13
       7: ldc           #14                 // class java/lang/Integer
       9: astore_0
      10: goto          101
      13: aload_0
      14: getstatic     #15                 // Field java/lang/Boolean.TYPE:Ljava/lang/Class;
      17: if_acmpne     26
      20: ldc           #8                  // class java/lang/Boolean
      22: astore_0
      23: goto          101
      26: aload_0
      27: getstatic     #16                 // Field java/lang/Long.TYPE:Ljava/lang/Class;
      30: if_acmpne     39
      33: ldc           #17                 // class java/lang/Long
      35: astore_0
      36: goto          101
      39: aload_0
      40: getstatic     #18                 // Field java/lang/Float.TYPE:Ljava/lang/Class;
      43: if_acmpne     52
      46: ldc           #19                 // class java/lang/Float
      48: astore_0
      49: goto          101
      52: aload_0
      53: getstatic     #20                 // Field java/lang/Double.TYPE:Ljava/lang/Class;
      56: if_acmpne     65
      59: ldc           #21                 // class java/lang/Double
      61: astore_0
      62: goto          101
      65: aload_0
      66: getstatic     #22                 // Field java/lang/Character.TYPE:Ljava/lang/Class;
      69: if_acmpne     78
      72: ldc           #9                  // class java/lang/Character
      74: astore_0
      75: goto          101
      78: aload_0
      79: getstatic     #23                 // Field java/lang/Byte.TYPE:Ljava/lang/Class;
      82: if_acmpne     91
      85: ldc           #24                 // class java/lang/Byte
      87: astore_0
      88: goto          101
      91: aload_0
      92: getstatic     #25                 // Field java/lang/Short.TYPE:Ljava/lang/Class;
      95: if_acmpne     101
      98: ldc           #26                 // class java/lang/Short
     100: astore_0
     101: aload_0
     102: areturn

  public static boolean isCompatible(java.lang.Class<?>, java.lang.Object);
    Code:
       0: aload_0
       1: invokevirtual #6                  // Method java/lang/Class.isPrimitive:()Z
       4: istore_2
       5: aload_1
       6: ifnonnull     19
       9: iload_2
      10: ifne          17
      13: iconst_1
      14: goto          18
      17: iconst_0
      18: ireturn
      19: iload_2
      20: ifeq          28
      23: aload_0
      24: invokestatic  #27                 // Method getBoxedClass:(Ljava/lang/Class;)Ljava/lang/Class;
      27: astore_0
      28: aload_0
      29: aload_1
      30: invokevirtual #28                 // Method java/lang/Object.getClass:()Ljava/lang/Class;
      33: if_acmpeq     44
      36: aload_0
      37: aload_1
      38: invokevirtual #29                 // Method java/lang/Class.isInstance:(Ljava/lang/Object;)Z
      41: ifeq          48
      44: iconst_1
      45: goto          49
      48: iconst_0
      49: ireturn

  public static boolean isCompatible(java.lang.Class<?>[], java.lang.Object[]);
    Code:
       0: aload_0
       1: arraylength
       2: istore_2
       3: iload_2
       4: aload_1
       5: arraylength
       6: if_icmpeq     11
       9: iconst_0
      10: ireturn
      11: iload_2
      12: ifne          17
      15: iconst_1
      16: ireturn
      17: iconst_0
      18: istore_3
      19: iload_3
      20: iload_2
      21: if_icmpge     44
      24: aload_0
      25: iload_3
      26: aaload
      27: aload_1
      28: iload_3
      29: aaload
      30: invokestatic  #30                 // Method isCompatible:(Ljava/lang/Class;Ljava/lang/Object;)Z
      33: ifne          38
      36: iconst_0
      37: ireturn
      38: iinc          3, 1
      41: goto          19
      44: iconst_1
      45: ireturn

  public static java.lang.String getCodeBase(java.lang.Class<?>);
    Code:
       0: aload_0
       1: ifnonnull     6
       4: aconst_null
       5: areturn
       6: aload_0
       7: invokevirtual #31                 // Method java/lang/Class.getProtectionDomain:()Ljava/security/ProtectionDomain;
      10: astore_1
      11: aload_1
      12: ifnonnull     17
      15: aconst_null
      16: areturn
      17: aload_1
      18: invokevirtual #32                 // Method java/security/ProtectionDomain.getCodeSource:()Ljava/security/CodeSource;
      21: astore_2
      22: aload_2
      23: ifnonnull     28
      26: aconst_null
      27: areturn
      28: aload_2
      29: invokevirtual #33                 // Method java/security/CodeSource.getLocation:()Ljava/net/URL;
      32: astore_3
      33: aload_3
      34: ifnonnull     39
      37: aconst_null
      38: areturn
      39: aload_3
      40: invokevirtual #34                 // Method java/net/URL.getFile:()Ljava/lang/String;
      43: areturn

  public static java.lang.String getName(java.lang.Class<?>);
    Code:
       0: aload_0
       1: invokevirtual #3                  // Method java/lang/Class.isArray:()Z
       4: ifeq          59
       7: new           #35                 // class java/lang/StringBuilder
      10: dup
      11: invokespecial #36                 // Method java/lang/StringBuilder."<init>":()V
      14: astore_1
      15: aload_1
      16: ldc           #37                 // String []
      18: invokevirtual #38                 // Method java/lang/StringBuilder.append:(Ljava/lang/String;)Ljava/lang/StringBuilder;
      21: pop
      22: aload_0
      23: invokevirtual #4                  // Method java/lang/Class.getComponentType:()Ljava/lang/Class;
      26: astore_0
      27: aload_0
      28: invokevirtual #3                  // Method java/lang/Class.isArray:()Z
      31: ifne          15
      34: new           #35                 // class java/lang/StringBuilder
      37: dup
      38: invokespecial #36                 // Method java/lang/StringBuilder."<init>":()V
      41: aload_0
      42: invokevirtual #39                 // Method java/lang/Class.getName:()Ljava/lang/String;
      45: invokevirtual #38                 // Method java/lang/StringBuilder.append:(Ljava/lang/String;)Ljava/lang/StringBuilder;
      48: aload_1
      49: invokevirtual #40                 // Method java/lang/StringBuilder.toString:()Ljava/lang/String;
      52: invokevirtual #38                 // Method java/lang/StringBuilder.append:(Ljava/lang/String;)Ljava/lang/StringBuilder;
      55: invokevirtual #40                 // Method java/lang/StringBuilder.toString:()Ljava/lang/String;
      58: areturn
      59: aload_0
      60: invokevirtual #39                 // Method java/lang/Class.getName:()Ljava/lang/String;
      63: areturn

  public static java.lang.Class<?> getGenericClass(java.lang.Class<?>);
    Code:
       0: aload_0
       1: iconst_0
       2: invokestatic  #41                 // Method getGenericClass:(Ljava/lang/Class;I)Ljava/lang/Class;
       5: areturn

  public static java.lang.Class<?> getGenericClass(java.lang.Class<?>, int);
    Code:
       0: aload_0
       1: invokevirtual #42                 // Method java/lang/Class.getGenericInterfaces:()[Ljava/lang/reflect/Type;
       4: iconst_0
       5: aaload
       6: checkcast     #43                 // class java/lang/reflect/ParameterizedType
       9: astore_2
      10: aload_2
      11: invokeinterface #44,  1           // InterfaceMethod java/lang/reflect/ParameterizedType.getActualTypeArguments:()[Ljava/lang/reflect/Type;
      16: iload_1
      17: aaload
      18: astore_3
      19: aload_3
      20: instanceof    #43                 // class java/lang/reflect/ParameterizedType
      23: ifeq          39
      26: aload_3
      27: checkcast     #43                 // class java/lang/reflect/ParameterizedType
      30: invokeinterface #45,  1           // InterfaceMethod java/lang/reflect/ParameterizedType.getRawType:()Ljava/lang/reflect/Type;
      35: checkcast     #46                 // class java/lang/Class
      38: areturn
      39: aload_3
      40: instanceof    #47                 // class java/lang/reflect/GenericArrayType
      43: ifeq          59
      46: aload_3
      47: checkcast     #47                 // class java/lang/reflect/GenericArrayType
      50: invokeinterface #48,  1           // InterfaceMethod java/lang/reflect/GenericArrayType.getGenericComponentType:()Ljava/lang/reflect/Type;
      55: checkcast     #46                 // class java/lang/Class
      58: areturn
      59: aload_3
      60: checkcast     #46                 // class java/lang/Class
      63: invokevirtual #3                  // Method java/lang/Class.isArray:()Z
      66: ifeq          77
      69: aload_3
      70: checkcast     #46                 // class java/lang/Class
      73: invokevirtual #4                  // Method java/lang/Class.getComponentType:()Ljava/lang/Class;
      76: areturn
      77: aload_3
      78: checkcast     #46                 // class java/lang/Class
      81: areturn
      82: astore_2
      83: new           #50                 // class java/lang/IllegalArgumentException
      86: dup
      87: new           #35                 // class java/lang/StringBuilder
      90: dup
      91: invokespecial #36                 // Method java/lang/StringBuilder."<init>":()V
      94: aload_0
      95: invokevirtual #39                 // Method java/lang/Class.getName:()Ljava/lang/String;
      98: invokevirtual #38                 // Method java/lang/StringBuilder.append:(Ljava/lang/String;)Ljava/lang/StringBuilder;
     101: ldc           #51                 // String  generic type undefined!
     103: invokevirtual #38                 // Method java/lang/StringBuilder.append:(Ljava/lang/String;)Ljava/lang/StringBuilder;
     106: invokevirtual #40                 // Method java/lang/StringBuilder.toString:()Ljava/lang/String;
     109: aload_2
     110: invokespecial #52                 // Method java/lang/IllegalArgumentException."<init>":(Ljava/lang/String;Ljava/lang/Throwable;)V
     113: athrow
    Exception table:
       from    to  target type
           0    38    82   Class java/lang/Throwable
          39    58    82   Class java/lang/Throwable
          59    76    82   Class java/lang/Throwable
          77    81    82   Class java/lang/Throwable

  public static java.lang.String getName(java.lang.reflect.Method);
    Code:
       0: new           #35                 // class java/lang/StringBuilder
       3: dup
       4: invokespecial #36                 // Method java/lang/StringBuilder."<init>":()V
       7: astore_1
       8: aload_1
       9: aload_0
      10: invokevirtual #53                 // Method java/lang/reflect/Method.getReturnType:()Ljava/lang/Class;
      13: invokestatic  #54                 // Method getName:(Ljava/lang/Class;)Ljava/lang/String;
      16: invokevirtual #38                 // Method java/lang/StringBuilder.append:(Ljava/lang/String;)Ljava/lang/StringBuilder;
      19: bipush        32
      21: invokevirtual #55                 // Method java/lang/StringBuilder.append:(C)Ljava/lang/StringBuilder;
      24: pop
      25: aload_1
      26: aload_0
      27: invokevirtual #56                 // Method java/lang/reflect/Method.getName:()Ljava/lang/String;
      30: invokevirtual #38                 // Method java/lang/StringBuilder.append:(Ljava/lang/String;)Ljava/lang/StringBuilder;
      33: bipush        40
      35: invokevirtual #55                 // Method java/lang/StringBuilder.append:(C)Ljava/lang/StringBuilder;
      38: pop
      39: aload_0
      40: invokevirtual #57                 // Method java/lang/reflect/Method.getParameterTypes:()[Ljava/lang/Class;
      43: astore_2
      44: iconst_0
      45: istore_3
      46: iload_3
      47: aload_2
      48: arraylength
      49: if_icmpge     80
      52: iload_3
      53: ifle          63
      56: aload_1
      57: bipush        44
      59: invokevirtual #55                 // Method java/lang/StringBuilder.append:(C)Ljava/lang/StringBuilder;
      62: pop
      63: aload_1
      64: aload_2
      65: iload_3
      66: aaload
      67: invokestatic  #54                 // Method getName:(Ljava/lang/Class;)Ljava/lang/String;
      70: invokevirtual #38                 // Method java/lang/StringBuilder.append:(Ljava/lang/String;)Ljava/lang/StringBuilder;
      73: pop
      74: iinc          3, 1
      77: goto          46
      80: aload_1
      81: bipush        41
      83: invokevirtual #55                 // Method java/lang/StringBuilder.append:(C)Ljava/lang/StringBuilder;
      86: pop
      87: aload_1
      88: invokevirtual #40                 // Method java/lang/StringBuilder.toString:()Ljava/lang/String;
      91: areturn

  public static java.lang.String getSignature(java.lang.String, java.lang.Class<?>[]);
    Code:
       0: new           #35                 // class java/lang/StringBuilder
       3: dup
       4: aload_0
       5: invokespecial #58                 // Method java/lang/StringBuilder."<init>":(Ljava/lang/String;)V
       8: astore_2
       9: aload_2
      10: bipush        40
      12: invokevirtual #55                 // Method java/lang/StringBuilder.append:(C)Ljava/lang/StringBuilder;
      15: pop
      16: aload_1
      17: ifnull        84
      20: aload_1
      21: arraylength
      22: ifle          84
      25: iconst_1
      26: istore_3
      27: aload_1
      28: astore        4
      30: aload         4
      32: arraylength
      33: istore        5
      35: iconst_0
      36: istore        6
      38: iload         6
      40: iload         5
      42: if_icmpge     84
      45: aload         4
      47: iload         6
      49: aaload
      50: astore        7
      52: iload_3
      53: ifeq          61
      56: iconst_0
      57: istore_3
      58: goto          68
      61: aload_2
      62: bipush        44
      64: invokevirtual #55                 // Method java/lang/StringBuilder.append:(C)Ljava/lang/StringBuilder;
      67: pop
      68: aload_2
      69: aload         7
      71: invokevirtual #39                 // Method java/lang/Class.getName:()Ljava/lang/String;
      74: invokevirtual #38                 // Method java/lang/StringBuilder.append:(Ljava/lang/String;)Ljava/lang/StringBuilder;
      77: pop
      78: iinc          6, 1
      81: goto          38
      84: aload_2
      85: bipush        41
      87: invokevirtual #55                 // Method java/lang/StringBuilder.append:(C)Ljava/lang/StringBuilder;
      90: pop
      91: aload_2
      92: invokevirtual #40                 // Method java/lang/StringBuilder.toString:()Ljava/lang/String;
      95: areturn

  public static java.lang.String getName(java.lang.reflect.Constructor<?>);
    Code:
       0: new           #35                 // class java/lang/StringBuilder
       3: dup
       4: ldc           #59                 // String (
       6: invokespecial #58                 // Method java/lang/StringBuilder."<init>":(Ljava/lang/String;)V
       9: astore_1
      10: aload_0
      11: invokevirtual #60                 // Method java/lang/reflect/Constructor.getParameterTypes:()[Ljava/lang/Class;
      14: astore_2
      15: iconst_0
      16: istore_3
      17: iload_3
      18: aload_2
      19: arraylength
      20: if_icmpge     51
      23: iload_3
      24: ifle          34
      27: aload_1
      28: bipush        44
      30: invokevirtual #55                 // Method java/lang/StringBuilder.append:(C)Ljava/lang/StringBuilder;
      33: pop
      34: aload_1
      35: aload_2
      36: iload_3
      37: aaload
      38: invokestatic  #54                 // Method getName:(Ljava/lang/Class;)Ljava/lang/String;
      41: invokevirtual #38                 // Method java/lang/StringBuilder.append:(Ljava/lang/String;)Ljava/lang/StringBuilder;
      44: pop
      45: iinc          3, 1
      48: goto          17
      51: aload_1
      52: bipush        41
      54: invokevirtual #55                 // Method java/lang/StringBuilder.append:(C)Ljava/lang/StringBuilder;
      57: pop
      58: aload_1
      59: invokevirtual #40                 // Method java/lang/StringBuilder.toString:()Ljava/lang/String;
      62: areturn

  public static java.lang.String getDesc(java.lang.Class<?>);
    Code:
       0: new           #35                 // class java/lang/StringBuilder
       3: dup
       4: invokespecial #36                 // Method java/lang/StringBuilder."<init>":()V
       7: astore_1
       8: aload_0
       9: invokevirtual #3                  // Method java/lang/Class.isArray:()Z
      12: ifeq          30
      15: aload_1
      16: bipush        91
      18: invokevirtual #55                 // Method java/lang/StringBuilder.append:(C)Ljava/lang/StringBuilder;
      21: pop
      22: aload_0
      23: invokevirtual #4                  // Method java/lang/Class.getComponentType:()Ljava/lang/Class;
      26: astore_0
      27: goto          8
      30: aload_0
      31: invokevirtual #6                  // Method java/lang/Class.isPrimitive:()Z
      34: ifeq          213
      37: aload_0
      38: invokevirtual #39                 // Method java/lang/Class.getName:()Ljava/lang/String;
      41: astore_2
      42: ldc           #61                 // String void
      44: aload_2
      45: invokevirtual #62                 // Method java/lang/String.equals:(Ljava/lang/Object;)Z
      48: ifeq          61
      51: aload_1
      52: bipush        86
      54: invokevirtual #55                 // Method java/lang/StringBuilder.append:(C)Ljava/lang/StringBuilder;
      57: pop
      58: goto          210
      61: ldc           #63                 // String boolean
      63: aload_2
      64: invokevirtual #62                 // Method java/lang/String.equals:(Ljava/lang/Object;)Z
      67: ifeq          80
      70: aload_1
      71: bipush        90
      73: invokevirtual #55                 // Method java/lang/StringBuilder.append:(C)Ljava/lang/StringBuilder;
      76: pop
      77: goto          210
      80: ldc           #64                 // String byte
      82: aload_2
      83: invokevirtual #62                 // Method java/lang/String.equals:(Ljava/lang/Object;)Z
      86: ifeq          99
      89: aload_1
      90: bipush        66
      92: invokevirtual #55                 // Method java/lang/StringBuilder.append:(C)Ljava/lang/StringBuilder;
      95: pop
      96: goto          210
      99: ldc           #65                 // String char
     101: aload_2
     102: invokevirtual #62                 // Method java/lang/String.equals:(Ljava/lang/Object;)Z
     105: ifeq          118
     108: aload_1
     109: bipush        67
     111: invokevirtual #55                 // Method java/lang/StringBuilder.append:(C)Ljava/lang/StringBuilder;
     114: pop
     115: goto          210
     118: ldc           #66                 // String double
     120: aload_2
     121: invokevirtual #62                 // Method java/lang/String.equals:(Ljava/lang/Object;)Z
     124: ifeq          137
     127: aload_1
     128: bipush        68
     130: invokevirtual #55                 // Method java/lang/StringBuilder.append:(C)Ljava/lang/StringBuilder;
     133: pop
     134: goto          210
     137: ldc           #67                 // String float
     139: aload_2
     140: invokevirtual #62                 // Method java/lang/String.equals:(Ljava/lang/Object;)Z
     143: ifeq          156
     146: aload_1
     147: bipush        70
     149: invokevirtual #55                 // Method java/lang/StringBuilder.append:(C)Ljava/lang/StringBuilder;
     152: pop
     153: goto          210
     156: ldc           #68                 // String int
     158: aload_2
     159: invokevirtual #62                 // Method java/lang/String.equals:(Ljava/lang/Object;)Z
     162: ifeq          175
     165: aload_1
     166: bipush        73
     168: invokevirtual #55                 // Method java/lang/StringBuilder.append:(C)Ljava/lang/StringBuilder;
     171: pop
     172: goto          210
     175: ldc           #69                 // String long
     177: aload_2
     178: invokevirtual #62                 // Method java/lang/String.equals:(Ljava/lang/Object;)Z
     181: ifeq          194
     184: aload_1
     185: bipush        74
     187: invokevirtual #55                 // Method java/lang/StringBuilder.append:(C)Ljava/lang/StringBuilder;
     190: pop
     191: goto          210
     194: ldc           #70                 // String short
     196: aload_2
     197: invokevirtual #62                 // Method java/lang/String.equals:(Ljava/lang/Object;)Z
     200: ifeq          210
     203: aload_1
     204: bipush        83
     206: invokevirtual #55                 // Method java/lang/StringBuilder.append:(C)Ljava/lang/StringBuilder;
     209: pop
     210: goto          243
     213: aload_1
     214: bipush        76
     216: invokevirtual #55                 // Method java/lang/StringBuilder.append:(C)Ljava/lang/StringBuilder;
     219: pop
     220: aload_1
     221: aload_0
     222: invokevirtual #39                 // Method java/lang/Class.getName:()Ljava/lang/String;
     225: bipush        46
     227: bipush        47
     229: invokevirtual #71                 // Method java/lang/String.replace:(CC)Ljava/lang/String;
     232: invokevirtual #38                 // Method java/lang/StringBuilder.append:(Ljava/lang/String;)Ljava/lang/StringBuilder;
     235: pop
     236: aload_1
     237: bipush        59
     239: invokevirtual #55                 // Method java/lang/StringBuilder.append:(C)Ljava/lang/StringBuilder;
     242: pop
     243: aload_1
     244: invokevirtual #40                 // Method java/lang/StringBuilder.toString:()Ljava/lang/String;
     247: areturn

  public static java.lang.String getDesc(java.lang.Class<?>[]);
    Code:
       0: aload_0
       1: arraylength
       2: ifne          8
       5: ldc           #72                 // String
       7: areturn
       8: new           #35                 // class java/lang/StringBuilder
      11: dup
      12: bipush        64
      14: invokespecial #73                 // Method java/lang/StringBuilder."<init>":(I)V
      17: astore_1
      18: aload_0
      19: astore_2
      20: aload_2
      21: arraylength
      22: istore_3
      23: iconst_0
      24: istore        4
      26: iload         4
      28: iload_3
      29: if_icmpge     54
      32: aload_2
      33: iload         4
      35: aaload
      36: astore        5
      38: aload_1
      39: aload         5
      41: invokestatic  #74                 // Method getDesc:(Ljava/lang/Class;)Ljava/lang/String;
      44: invokevirtual #38                 // Method java/lang/StringBuilder.append:(Ljava/lang/String;)Ljava/lang/StringBuilder;
      47: pop
      48: iinc          4, 1
      51: goto          26
      54: aload_1
      55: invokevirtual #40                 // Method java/lang/StringBuilder.toString:()Ljava/lang/String;
      58: areturn

  public static java.lang.String getDesc(java.lang.reflect.Method);
    Code:
       0: new           #35                 // class java/lang/StringBuilder
       3: dup
       4: aload_0
       5: invokevirtual #56                 // Method java/lang/reflect/Method.getName:()Ljava/lang/String;
       8: invokespecial #58                 // Method java/lang/StringBuilder."<init>":(Ljava/lang/String;)V
      11: bipush        40
      13: invokevirtual #55                 // Method java/lang/StringBuilder.append:(C)Ljava/lang/StringBuilder;
      16: astore_1
      17: aload_0
      18: invokevirtual #57                 // Method java/lang/reflect/Method.getParameterTypes:()[Ljava/lang/Class;
      21: astore_2
      22: iconst_0
      23: istore_3
      24: iload_3
      25: aload_2
      26: arraylength
      27: if_icmpge     47
      30: aload_1
      31: aload_2
      32: iload_3
      33: aaload
      34: invokestatic  #74                 // Method getDesc:(Ljava/lang/Class;)Ljava/lang/String;
      37: invokevirtual #38                 // Method java/lang/StringBuilder.append:(Ljava/lang/String;)Ljava/lang/StringBuilder;
      40: pop
      41: iinc          3, 1
      44: goto          24
      47: aload_1
      48: bipush        41
      50: invokevirtual #55                 // Method java/lang/StringBuilder.append:(C)Ljava/lang/StringBuilder;
      53: aload_0
      54: invokevirtual #53                 // Method java/lang/reflect/Method.getReturnType:()Ljava/lang/Class;
      57: invokestatic  #74                 // Method getDesc:(Ljava/lang/Class;)Ljava/lang/String;
      60: invokevirtual #38                 // Method java/lang/StringBuilder.append:(Ljava/lang/String;)Ljava/lang/StringBuilder;
      63: pop
      64: aload_1
      65: invokevirtual #40                 // Method java/lang/StringBuilder.toString:()Ljava/lang/String;
      68: areturn

  public static java.lang.String[] getDescArray(java.lang.reflect.Method);
    Code:
       0: aload_0
       1: invokevirtual #57                 // Method java/lang/reflect/Method.getParameterTypes:()[Ljava/lang/Class;
       4: astore_1
       5: aload_1
       6: arraylength
       7: anewarray     #7                  // class java/lang/String
      10: astore_2
      11: iconst_0
      12: istore_3
      13: iload_3
      14: aload_1
      15: arraylength
      16: if_icmpge     34
      19: aload_2
      20: iload_3
      21: aload_1
      22: iload_3
      23: aaload
      24: invokestatic  #74                 // Method getDesc:(Ljava/lang/Class;)Ljava/lang/String;
      27: aastore
      28: iinc          3, 1
      31: goto          13
      34: aload_2
      35: areturn

  public static java.lang.String getDesc(java.lang.reflect.Constructor<?>);
    Code:
       0: new           #35                 // class java/lang/StringBuilder
       3: dup
       4: ldc           #59                 // String (
       6: invokespecial #58                 // Method java/lang/StringBuilder."<init>":(Ljava/lang/String;)V
       9: astore_1
      10: aload_0
      11: invokevirtual #60                 // Method java/lang/reflect/Constructor.getParameterTypes:()[Ljava/lang/Class;
      14: astore_2
      15: iconst_0
      16: istore_3
      17: iload_3
      18: aload_2
      19: arraylength
      20: if_icmpge     40
      23: aload_1
      24: aload_2
      25: iload_3
      26: aaload
      27: invokestatic  #74                 // Method getDesc:(Ljava/lang/Class;)Ljava/lang/String;
      30: invokevirtual #38                 // Method java/lang/StringBuilder.append:(Ljava/lang/String;)Ljava/lang/StringBuilder;
      33: pop
      34: iinc          3, 1
      37: goto          17
      40: aload_1
      41: bipush        41
      43: invokevirtual #55                 // Method java/lang/StringBuilder.append:(C)Ljava/lang/StringBuilder;
      46: bipush        86
      48: invokevirtual #55                 // Method java/lang/StringBuilder.append:(C)Ljava/lang/StringBuilder;
      51: pop
      52: aload_1
      53: invokevirtual #40                 // Method java/lang/StringBuilder.toString:()Ljava/lang/String;
      56: areturn

  public static java.lang.String getDescWithoutMethodName(java.lang.reflect.Method);
    Code:
       0: new           #35                 // class java/lang/StringBuilder
       3: dup
       4: invokespecial #36                 // Method java/lang/StringBuilder."<init>":()V
       7: astore_1
       8: aload_1
       9: bipush        40
      11: invokevirtual #55                 // Method java/lang/StringBuilder.append:(C)Ljava/lang/StringBuilder;
      14: pop
      15: aload_0
      16: invokevirtual #57                 // Method java/lang/reflect/Method.getParameterTypes:()[Ljava/lang/Class;
      19: astore_2
      20: iconst_0
      21: istore_3
      22: iload_3
      23: aload_2
      24: arraylength
      25: if_icmpge     45
      28: aload_1
      29: aload_2
      30: iload_3
      31: aaload
      32: invokestatic  #74                 // Method getDesc:(Ljava/lang/Class;)Ljava/lang/String;
      35: invokevirtual #38                 // Method java/lang/StringBuilder.append:(Ljava/lang/String;)Ljava/lang/StringBuilder;
      38: pop
      39: iinc          3, 1
      42: goto          22
      45: aload_1
      46: bipush        41
      48: invokevirtual #55                 // Method java/lang/StringBuilder.append:(C)Ljava/lang/StringBuilder;
      51: aload_0
      52: invokevirtual #53                 // Method java/lang/reflect/Method.getReturnType:()Ljava/lang/Class;
      55: invokestatic  #74                 // Method getDesc:(Ljava/lang/Class;)Ljava/lang/String;
      58: invokevirtual #38                 // Method java/lang/StringBuilder.append:(Ljava/lang/String;)Ljava/lang/StringBuilder;
      61: pop
      62: aload_1
      63: invokevirtual #40                 // Method java/lang/StringBuilder.toString:()Ljava/lang/String;
      66: areturn

  public static java.lang.String getDesc(javassist.CtClass) throws javassist.NotFoundException;
    Code:
       0: new           #35                 // class java/lang/StringBuilder
       3: dup
       4: invokespecial #36                 // Method java/lang/StringBuilder."<init>":()V
       7: astore_1
       8: aload_0
       9: invokevirtual #75                 // Method javassist/CtClass.isArray:()Z
      12: ifeq          37
      15: aload_1
      16: bipush        91
      18: invokevirtual #55                 // Method java/lang/StringBuilder.append:(C)Ljava/lang/StringBuilder;
      21: pop
      22: aload_1
      23: aload_0
      24: invokevirtual #76                 // Method javassist/CtClass.getComponentType:()Ljavassist/CtClass;
      27: invokestatic  #77                 // Method getDesc:(Ljavassist/CtClass;)Ljava/lang/String;
      30: invokevirtual #38                 // Method java/lang/StringBuilder.append:(Ljava/lang/String;)Ljava/lang/StringBuilder;
      33: pop
      34: goto          250
      37: aload_0
      38: invokevirtual #78                 // Method javassist/CtClass.isPrimitive:()Z
      41: ifeq          220
      44: aload_0
      45: invokevirtual #79                 // Method javassist/CtClass.getName:()Ljava/lang/String;
      48: astore_2
      49: ldc           #61                 // String void
      51: aload_2
      52: invokevirtual #62                 // Method java/lang/String.equals:(Ljava/lang/Object;)Z
      55: ifeq          68
      58: aload_1
      59: bipush        86
      61: invokevirtual #55                 // Method java/lang/StringBuilder.append:(C)Ljava/lang/StringBuilder;
      64: pop
      65: goto          217
      68: ldc           #63                 // String boolean
      70: aload_2
      71: invokevirtual #62                 // Method java/lang/String.equals:(Ljava/lang/Object;)Z
      74: ifeq          87
      77: aload_1
      78: bipush        90
      80: invokevirtual #55                 // Method java/lang/StringBuilder.append:(C)Ljava/lang/StringBuilder;
      83: pop
      84: goto          217
      87: ldc           #64                 // String byte
      89: aload_2
      90: invokevirtual #62                 // Method java/lang/String.equals:(Ljava/lang/Object;)Z
      93: ifeq          106
      96: aload_1
      97: bipush        66
      99: invokevirtual #55                 // Method java/lang/StringBuilder.append:(C)Ljava/lang/StringBuilder;
     102: pop
     103: goto          217
     106: ldc           #65                 // String char
     108: aload_2
     109: invokevirtual #62                 // Method java/lang/String.equals:(Ljava/lang/Object;)Z
     112: ifeq          125
     115: aload_1
     116: bipush        67
     118: invokevirtual #55                 // Method java/lang/StringBuilder.append:(C)Ljava/lang/StringBuilder;
     121: pop
     122: goto          217
     125: ldc           #66                 // String double
     127: aload_2
     128: invokevirtual #62                 // Method java/lang/String.equals:(Ljava/lang/Object;)Z
     131: ifeq          144
     134: aload_1
     135: bipush        68
     137: invokevirtual #55                 // Method java/lang/StringBuilder.append:(C)Ljava/lang/StringBuilder;
     140: pop
     141: goto          217
     144: ldc           #67                 // String float
     146: aload_2
     147: invokevirtual #62                 // Method java/lang/String.equals:(Ljava/lang/Object;)Z
     150: ifeq          163
     153: aload_1
     154: bipush        70
     156: invokevirtual #55                 // Method java/lang/StringBuilder.append:(C)Ljava/lang/StringBuilder;
     159: pop
     160: goto          217
     163: ldc           #68                 // String int
     165: aload_2
     166: invokevirtual #62                 // Method java/lang/String.equals:(Ljava/lang/Object;)Z
     169: ifeq          182
     172: aload_1
     173: bipush        73
     175: invokevirtual #55                 // Method java/lang/StringBuilder.append:(C)Ljava/lang/StringBuilder;
     178: pop
     179: goto          217
     182: ldc           #69                 // String long
     184: aload_2
     185: invokevirtual #62                 // Method java/lang/String.equals:(Ljava/lang/Object;)Z
     188: ifeq          201
     191: aload_1
     192: bipush        74
     194: invokevirtual #55                 // Method java/lang/StringBuilder.append:(C)Ljava/lang/StringBuilder;
     197: pop
     198: goto          217
     201: ldc           #70                 // String short
     203: aload_2
     204: invokevirtual #62                 // Method java/lang/String.equals:(Ljava/lang/Object;)Z
     207: ifeq          217
     210: aload_1
     211: bipush        83
     213: invokevirtual #55                 // Method java/lang/StringBuilder.append:(C)Ljava/lang/StringBuilder;
     216: pop
     217: goto          250
     220: aload_1
     221: bipush        76
     223: invokevirtual #55                 // Method java/lang/StringBuilder.append:(C)Ljava/lang/StringBuilder;
     226: pop
     227: aload_1
     228: aload_0
     229: invokevirtual #79                 // Method javassist/CtClass.getName:()Ljava/lang/String;
     232: bipush        46
     234: bipush        47
     236: invokevirtual #71                 // Method java/lang/String.replace:(CC)Ljava/lang/String;
     239: invokevirtual #38                 // Method java/lang/StringBuilder.append:(Ljava/lang/String;)Ljava/lang/StringBuilder;
     242: pop
     243: aload_1
     244: bipush        59
     246: invokevirtual #55                 // Method java/lang/StringBuilder.append:(C)Ljava/lang/StringBuilder;
     249: pop
     250: aload_1
     251: invokevirtual #40                 // Method java/lang/StringBuilder.toString:()Ljava/lang/String;
     254: areturn

  public static java.lang.String getDesc(javassist.CtMethod) throws javassist.NotFoundException;
    Code:
       0: new           #35                 // class java/lang/StringBuilder
       3: dup
       4: aload_0
       5: invokevirtual #80                 // Method javassist/CtMethod.getName:()Ljava/lang/String;
       8: invokespecial #58                 // Method java/lang/StringBuilder."<init>":(Ljava/lang/String;)V
      11: bipush        40
      13: invokevirtual #55                 // Method java/lang/StringBuilder.append:(C)Ljava/lang/StringBuilder;
      16: astore_1
      17: aload_0
      18: invokevirtual #81                 // Method javassist/CtMethod.getParameterTypes:()[Ljavassist/CtClass;
      21: astore_2
      22: aload_2
      23: astore_3
      24: aload_3
      25: arraylength
      26: istore        4
      28: iconst_0
      29: istore        5
      31: iload         5
      33: iload         4
      35: if_icmpge     60
      38: aload_3
      39: iload         5
      41: aaload
      42: astore        6
      44: aload_1
      45: aload         6
      47: invokestatic  #77                 // Method getDesc:(Ljavassist/CtClass;)Ljava/lang/String;
      50: invokevirtual #38                 // Method java/lang/StringBuilder.append:(Ljava/lang/String;)Ljava/lang/StringBuilder;
      53: pop
      54: iinc          5, 1
      57: goto          31
      60: aload_1
      61: bipush        41
      63: invokevirtual #55                 // Method java/lang/StringBuilder.append:(C)Ljava/lang/StringBuilder;
      66: aload_0
      67: invokevirtual #82                 // Method javassist/CtMethod.getReturnType:()Ljavassist/CtClass;
      70: invokestatic  #77                 // Method getDesc:(Ljavassist/CtClass;)Ljava/lang/String;
      73: invokevirtual #38                 // Method java/lang/StringBuilder.append:(Ljava/lang/String;)Ljava/lang/StringBuilder;
      76: pop
      77: aload_1
      78: invokevirtual #40                 // Method java/lang/StringBuilder.toString:()Ljava/lang/String;
      81: areturn

  public static java.lang.String getDesc(javassist.CtConstructor) throws javassist.NotFoundException;
    Code:
       0: new           #35                 // class java/lang/StringBuilder
       3: dup
       4: ldc           #59                 // String (
       6: invokespecial #58                 // Method java/lang/StringBuilder."<init>":(Ljava/lang/String;)V
       9: astore_1
      10: aload_0
      11: invokevirtual #83                 // Method javassist/CtConstructor.getParameterTypes:()[Ljavassist/CtClass;
      14: astore_2
      15: iconst_0
      16: istore_3
      17: iload_3
      18: aload_2
      19: arraylength
      20: if_icmpge     40
      23: aload_1
      24: aload_2
      25: iload_3
      26: aaload
      27: invokestatic  #77                 // Method getDesc:(Ljavassist/CtClass;)Ljava/lang/String;
      30: invokevirtual #38                 // Method java/lang/StringBuilder.append:(Ljava/lang/String;)Ljava/lang/StringBuilder;
      33: pop
      34: iinc          3, 1
      37: goto          17
      40: aload_1
      41: bipush        41
      43: invokevirtual #55                 // Method java/lang/StringBuilder.append:(C)Ljava/lang/StringBuilder;
      46: bipush        86
      48: invokevirtual #55                 // Method java/lang/StringBuilder.append:(C)Ljava/lang/StringBuilder;
      51: pop
      52: aload_1
      53: invokevirtual #40                 // Method java/lang/StringBuilder.toString:()Ljava/lang/String;
      56: areturn

  public static java.lang.String getDescWithoutMethodName(javassist.CtMethod) throws javassist.NotFoundException;
    Code:
       0: new           #35                 // class java/lang/StringBuilder
       3: dup
       4: invokespecial #36                 // Method java/lang/StringBuilder."<init>":()V
       7: astore_1
       8: aload_1
       9: bipush        40
      11: invokevirtual #55                 // Method java/lang/StringBuilder.append:(C)Ljava/lang/StringBuilder;
      14: pop
      15: aload_0
      16: invokevirtual #81                 // Method javassist/CtMethod.getParameterTypes:()[Ljavassist/CtClass;
      19: astore_2
      20: iconst_0
      21: istore_3
      22: iload_3
      23: aload_2
      24: arraylength
      25: if_icmpge     45
      28: aload_1
      29: aload_2
      30: iload_3
      31: aaload
      32: invokestatic  #77                 // Method getDesc:(Ljavassist/CtClass;)Ljava/lang/String;
      35: invokevirtual #38                 // Method java/lang/StringBuilder.append:(Ljava/lang/String;)Ljava/lang/StringBuilder;
      38: pop
      39: iinc          3, 1
      42: goto          22
      45: aload_1
      46: bipush        41
      48: invokevirtual #55                 // Method java/lang/StringBuilder.append:(C)Ljava/lang/StringBuilder;
      51: aload_0
      52: invokevirtual #82                 // Method javassist/CtMethod.getReturnType:()Ljavassist/CtClass;
      55: invokestatic  #77                 // Method getDesc:(Ljavassist/CtClass;)Ljava/lang/String;
      58: invokevirtual #38                 // Method java/lang/StringBuilder.append:(Ljava/lang/String;)Ljava/lang/StringBuilder;
      61: pop
      62: aload_1
      63: invokevirtual #40                 // Method java/lang/StringBuilder.toString:()Ljava/lang/String;
      66: areturn

  public static java.lang.String name2desc(java.lang.String);
    Code:
       0: new           #35                 // class java/lang/StringBuilder
       3: dup
       4: invokespecial #36                 // Method java/lang/StringBuilder."<init>":()V
       7: astore_1
       8: iconst_0
       9: istore_2
      10: aload_0
      11: bipush        91
      13: invokevirtual #84                 // Method java/lang/String.indexOf:(I)I
      16: istore_3
      17: iload_3
      18: ifle          37
      21: aload_0
      22: invokevirtual #85                 // Method java/lang/String.length:()I
      25: iload_3
      26: isub
      27: iconst_2
      28: idiv
      29: istore_2
      30: aload_0
      31: iconst_0
      32: iload_3
      33: invokevirtual #86                 // Method java/lang/String.substring:(II)Ljava/lang/String;
      36: astore_0
      37: iload_2
      38: iinc          2, -1
      41: ifle          54
      44: aload_1
      45: bipush        91
      47: invokevirtual #55                 // Method java/lang/StringBuilder.append:(C)Ljava/lang/StringBuilder;
      50: pop
      51: goto          37
      54: ldc           #61                 // String void
      56: aload_0
      57: invokevirtual #62                 // Method java/lang/String.equals:(Ljava/lang/Object;)Z
      60: ifeq          73
      63: aload_1
      64: bipush        86
      66: invokevirtual #55                 // Method java/lang/StringBuilder.append:(C)Ljava/lang/StringBuilder;
      69: pop
      70: goto          248
      73: ldc           #63                 // String boolean
      75: aload_0
      76: invokevirtual #62                 // Method java/lang/String.equals:(Ljava/lang/Object;)Z
      79: ifeq          92
      82: aload_1
      83: bipush        90
      85: invokevirtual #55                 // Method java/lang/StringBuilder.append:(C)Ljava/lang/StringBuilder;
      88: pop
      89: goto          248
      92: ldc           #64                 // String byte
      94: aload_0
      95: invokevirtual #62                 // Method java/lang/String.equals:(Ljava/lang/Object;)Z
      98: ifeq          111
     101: aload_1
     102: bipush        66
     104: invokevirtual #55                 // Method java/lang/StringBuilder.append:(C)Ljava/lang/StringBuilder;
     107: pop
     108: goto          248
     111: ldc           #65                 // String char
     113: aload_0
     114: invokevirtual #62                 // Method java/lang/String.equals:(Ljava/lang/Object;)Z
     117: ifeq          130
     120: aload_1
     121: bipush        67
     123: invokevirtual #55                 // Method java/lang/StringBuilder.append:(C)Ljava/lang/StringBuilder;
     126: pop
     127: goto          248
     130: ldc           #66                 // String double
     132: aload_0
     133: invokevirtual #62                 // Method java/lang/String.equals:(Ljava/lang/Object;)Z
     136: ifeq          149
     139: aload_1
     140: bipush        68
     142: invokevirtual #55                 // Method java/lang/StringBuilder.append:(C)Ljava/lang/StringBuilder;
     145: pop
     146: goto          248
     149: ldc           #67                 // String float
     151: aload_0
     152: invokevirtual #62                 // Method java/lang/String.equals:(Ljava/lang/Object;)Z
     155: ifeq          168
     158: aload_1
     159: bipush        70
     161: invokevirtual #55                 // Method java/lang/StringBuilder.append:(C)Ljava/lang/StringBuilder;
     164: pop
     165: goto          248
     168: ldc           #68                 // String int
     170: aload_0
     171: invokevirtual #62                 // Method java/lang/String.equals:(Ljava/lang/Object;)Z
     174: ifeq          187
     177: aload_1
     178: bipush        73
     180: invokevirtual #55                 // Method java/lang/StringBuilder.append:(C)Ljava/lang/StringBuilder;
     183: pop
     184: goto          248
     187: ldc           #69                 // String long
     189: aload_0
     190: invokevirtual #62                 // Method java/lang/String.equals:(Ljava/lang/Object;)Z
     193: ifeq          206
     196: aload_1
     197: bipush        74
     199: invokevirtual #55                 // Method java/lang/StringBuilder.append:(C)Ljava/lang/StringBuilder;
     202: pop
     203: goto          248
     206: ldc           #70                 // String short
     208: aload_0
     209: invokevirtual #62                 // Method java/lang/String.equals:(Ljava/lang/Object;)Z
     212: ifeq          225
     215: aload_1
     216: bipush        83
     218: invokevirtual #55                 // Method java/lang/StringBuilder.append:(C)Ljava/lang/StringBuilder;
     221: pop
     222: goto          248
     225: aload_1
     226: bipush        76
     228: invokevirtual #55                 // Method java/lang/StringBuilder.append:(C)Ljava/lang/StringBuilder;
     231: aload_0
     232: bipush        46
     234: bipush        47
     236: invokevirtual #71                 // Method java/lang/String.replace:(CC)Ljava/lang/String;
     239: invokevirtual #38                 // Method java/lang/StringBuilder.append:(Ljava/lang/String;)Ljava/lang/StringBuilder;
     242: bipush        59
     244: invokevirtual #55                 // Method java/lang/StringBuilder.append:(C)Ljava/lang/StringBuilder;
     247: pop
     248: aload_1
     249: invokevirtual #40                 // Method java/lang/StringBuilder.toString:()Ljava/lang/String;
     252: areturn

  public static java.lang.String desc2name(java.lang.String);
    Code:
       0: new           #35                 // class java/lang/StringBuilder
       3: dup
       4: invokespecial #36                 // Method java/lang/StringBuilder."<init>":()V
       7: astore_1
       8: aload_0
       9: bipush        91
      11: invokevirtual #87                 // Method java/lang/String.lastIndexOf:(I)I
      14: iconst_1
      15: iadd
      16: istore_2
      17: aload_0
      18: invokevirtual #85                 // Method java/lang/String.length:()I
      21: iload_2
      22: iconst_1
      23: iadd
      24: if_icmpne     246
      27: aload_0
      28: iload_2
      29: invokevirtual #88                 // Method java/lang/String.charAt:(I)C
      32: tableswitch   { // 66 to 90
                    66: 168
                    67: 178
                    68: 188
                    69: 238
                    70: 198
                    71: 238
                    72: 238
                    73: 208
                    74: 218
                    75: 238
                    76: 238
                    77: 238
                    78: 238
                    79: 238
                    80: 238
                    81: 238
                    82: 238
                    83: 228
                    84: 238
                    85: 238
                    86: 148
                    87: 238
                    88: 238
                    89: 238
                    90: 158
               default: 238
          }
     148: aload_1
     149: ldc           #61                 // String void
     151: invokevirtual #38                 // Method java/lang/StringBuilder.append:(Ljava/lang/String;)Ljava/lang/StringBuilder;
     154: pop
     155: goto          271
     158: aload_1
     159: ldc           #63                 // String boolean
     161: invokevirtual #38                 // Method java/lang/StringBuilder.append:(Ljava/lang/String;)Ljava/lang/StringBuilder;
     164: pop
     165: goto          271
     168: aload_1
     169: ldc           #64                 // String byte
     171: invokevirtual #38                 // Method java/lang/StringBuilder.append:(Ljava/lang/String;)Ljava/lang/StringBuilder;
     174: pop
     175: goto          271
     178: aload_1
     179: ldc           #65                 // String char
     181: invokevirtual #38                 // Method java/lang/StringBuilder.append:(Ljava/lang/String;)Ljava/lang/StringBuilder;
     184: pop
     185: goto          271
     188: aload_1
     189: ldc           #66                 // String double
     191: invokevirtual #38                 // Method java/lang/StringBuilder.append:(Ljava/lang/String;)Ljava/lang/StringBuilder;
     194: pop
     195: goto          271
     198: aload_1
     199: ldc           #67                 // String float
     201: invokevirtual #38                 // Method java/lang/StringBuilder.append:(Ljava/lang/String;)Ljava/lang/StringBuilder;
     204: pop
     205: goto          271
     208: aload_1
     209: ldc           #68                 // String int
     211: invokevirtual #38                 // Method java/lang/StringBuilder.append:(Ljava/lang/String;)Ljava/lang/StringBuilder;
     214: pop
     215: goto          271
     218: aload_1
     219: ldc           #69                 // String long
     221: invokevirtual #38                 // Method java/lang/StringBuilder.append:(Ljava/lang/String;)Ljava/lang/StringBuilder;
     224: pop
     225: goto          271
     228: aload_1
     229: ldc           #70                 // String short
     231: invokevirtual #38                 // Method java/lang/StringBuilder.append:(Ljava/lang/String;)Ljava/lang/StringBuilder;
     234: pop
     235: goto          271
     238: new           #89                 // class java/lang/RuntimeException
     241: dup
     242: invokespecial #90                 // Method java/lang/RuntimeException."<init>":()V
     245: athrow
     246: aload_1
     247: aload_0
     248: iload_2
     249: iconst_1
     250: iadd
     251: aload_0
     252: invokevirtual #85                 // Method java/lang/String.length:()I
     255: iconst_1
     256: isub
     257: invokevirtual #86                 // Method java/lang/String.substring:(II)Ljava/lang/String;
     260: bipush        47
     262: bipush        46
     264: invokevirtual #71                 // Method java/lang/String.replace:(CC)Ljava/lang/String;
     267: invokevirtual #38                 // Method java/lang/StringBuilder.append:(Ljava/lang/String;)Ljava/lang/StringBuilder;
     270: pop
     271: iload_2
     272: iinc          2, -1
     275: ifle          288
     278: aload_1
     279: ldc           #37                 // String []
     281: invokevirtual #38                 // Method java/lang/StringBuilder.append:(Ljava/lang/String;)Ljava/lang/StringBuilder;
     284: pop
     285: goto          271
     288: aload_1
     289: invokevirtual #40                 // Method java/lang/StringBuilder.toString:()Ljava/lang/String;
     292: areturn

  public static java.lang.Class<?> forName(java.lang.String);
    Code:
       0: aload_0
       1: invokestatic  #91                 // Method name2class:(Ljava/lang/String;)Ljava/lang/Class;
       4: areturn
       5: astore_1
       6: new           #93                 // class java/lang/IllegalStateException
       9: dup
      10: new           #35                 // class java/lang/StringBuilder
      13: dup
      14: invokespecial #36                 // Method java/lang/StringBuilder."<init>":()V
      17: ldc           #94                 // String Not found class
      19: invokevirtual #38                 // Method java/lang/StringBuilder.append:(Ljava/lang/String;)Ljava/lang/StringBuilder;
      22: aload_0
      23: invokevirtual #38                 // Method java/lang/StringBuilder.append:(Ljava/lang/String;)Ljava/lang/StringBuilder;
      26: ldc           #95                 // String , cause:
      28: invokevirtual #38                 // Method java/lang/StringBuilder.append:(Ljava/lang/String;)Ljava/lang/StringBuilder;
      31: aload_1
      32: invokevirtual #96                 // Method java/lang/ClassNotFoundException.getMessage:()Ljava/lang/String;
      35: invokevirtual #38                 // Method java/lang/StringBuilder.append:(Ljava/lang/String;)Ljava/lang/StringBuilder;
      38: invokevirtual #40                 // Method java/lang/StringBuilder.toString:()Ljava/lang/String;
      41: aload_1
      42: invokespecial #97                 // Method java/lang/IllegalStateException."<init>":(Ljava/lang/String;Ljava/lang/Throwable;)V
      45: athrow
    Exception table:
       from    to  target type
           0     4     5   Class java/lang/ClassNotFoundException

  public static java.lang.Class<?> forName(java.lang.ClassLoader, java.lang.String);
    Code:
       0: aload_0
       1: aload_1
       2: invokestatic  #98                 // Method name2class:(Ljava/lang/ClassLoader;Ljava/lang/String;)Ljava/lang/Class;
       5: areturn
       6: astore_2
       7: new           #93                 // class java/lang/IllegalStateException
      10: dup
      11: new           #35                 // class java/lang/StringBuilder
      14: dup
      15: invokespecial #36                 // Method java/lang/StringBuilder."<init>":()V
      18: ldc           #94                 // String Not found class
      20: invokevirtual #38                 // Method java/lang/StringBuilder.append:(Ljava/lang/String;)Ljava/lang/StringBuilder;
      23: aload_1
      24: invokevirtual #38                 // Method java/lang/StringBuilder.append:(Ljava/lang/String;)Ljava/lang/StringBuilder;
      27: ldc           #95                 // String , cause:
      29: invokevirtual #38                 // Method java/lang/StringBuilder.append:(Ljava/lang/String;)Ljava/lang/StringBuilder;
      32: aload_2
      33: invokevirtual #96                 // Method java/lang/ClassNotFoundException.getMessage:()Ljava/lang/String;
      36: invokevirtual #38                 // Method java/lang/StringBuilder.append:(Ljava/lang/String;)Ljava/lang/StringBuilder;
      39: invokevirtual #40                 // Method java/lang/StringBuilder.toString:()Ljava/lang/String;
      42: aload_2
      43: invokespecial #97                 // Method java/lang/IllegalStateException."<init>":(Ljava/lang/String;Ljava/lang/Throwable;)V
      46: athrow
    Exception table:
       from    to  target type
           0     5     6   Class java/lang/ClassNotFoundException

  public static java.lang.Class<?> name2class(java.lang.String) throws java.lang.ClassNotFoundException;
    Code:
       0: invokestatic  #99                 // Method org/apache/dubbo/common/utils/ClassUtils.getClassLoader:()Ljava/lang/ClassLoader;
       3: aload_0
       4: invokestatic  #98                 // Method name2class:(Ljava/lang/ClassLoader;Ljava/lang/String;)Ljava/lang/Class;
       7: areturn

  private static java.lang.Class<?> name2class(java.lang.ClassLoader, java.lang.String) throws java.lang.ClassNotFoundException;
    Code:
       0: iconst_0
       1: istore_2
       2: aload_1
       3: bipush        91
       5: invokevirtual #84                 // Method java/lang/String.indexOf:(I)I
       8: istore_3
       9: iload_3
      10: ifle          29
      13: aload_1
      14: invokevirtual #85                 // Method java/lang/String.length:()I
      17: iload_3
      18: isub
      19: iconst_2
      20: idiv
      21: istore_2
      22: aload_1
      23: iconst_0
      24: iload_3
      25: invokevirtual #86                 // Method java/lang/String.substring:(II)Ljava/lang/String;
      28: astore_1
      29: iload_2
      30: ifle          266
      33: new           #35                 // class java/lang/StringBuilder
      36: dup
      37: invokespecial #36                 // Method java/lang/StringBuilder."<init>":()V
      40: astore        4
      42: iload_2
      43: iinc          2, -1
      46: ifle          60
      49: aload         4
      51: bipush        91
      53: invokevirtual #55                 // Method java/lang/StringBuilder.append:(C)Ljava/lang/StringBuilder;
      56: pop
      57: goto          42
      60: ldc           #61                 // String void
      62: aload_1
      63: invokevirtual #62                 // Method java/lang/String.equals:(Ljava/lang/Object;)Z
      66: ifeq          80
      69: aload         4
      71: bipush        86
      73: invokevirtual #55                 // Method java/lang/StringBuilder.append:(C)Ljava/lang/StringBuilder;
      76: pop
      77: goto          257
      80: ldc           #63                 // String boolean
      82: aload_1
      83: invokevirtual #62                 // Method java/lang/String.equals:(Ljava/lang/Object;)Z
      86: ifeq          100
      89: aload         4
      91: bipush        90
      93: invokevirtual #55                 // Method java/lang/StringBuilder.append:(C)Ljava/lang/StringBuilder;
      96: pop
      97: goto          257
     100: ldc           #64                 // String byte
     102: aload_1
     103: invokevirtual #62                 // Method java/lang/String.equals:(Ljava/lang/Object;)Z
     106: ifeq          120
     109: aload         4
     111: bipush        66
     113: invokevirtual #55                 // Method java/lang/StringBuilder.append:(C)Ljava/lang/StringBuilder;
     116: pop
     117: goto          257
     120: ldc           #65                 // String char
     122: aload_1
     123: invokevirtual #62                 // Method java/lang/String.equals:(Ljava/lang/Object;)Z
     126: ifeq          140
     129: aload         4
     131: bipush        67
     133: invokevirtual #55                 // Method java/lang/StringBuilder.append:(C)Ljava/lang/StringBuilder;
     136: pop
     137: goto          257
     140: ldc           #66                 // String double
     142: aload_1
     143: invokevirtual #62                 // Method java/lang/String.equals:(Ljava/lang/Object;)Z
     146: ifeq          160
     149: aload         4
     151: bipush        68
     153: invokevirtual #55                 // Method java/lang/StringBuilder.append:(C)Ljava/lang/StringBuilder;
     156: pop
     157: goto          257
     160: ldc           #67                 // String float
     162: aload_1
     163: invokevirtual #62                 // Method java/lang/String.equals:(Ljava/lang/Object;)Z
     166: ifeq          180
     169: aload         4
     171: bipush        70
     173: invokevirtual #55                 // Method java/lang/StringBuilder.append:(C)Ljava/lang/StringBuilder;
     176: pop
     177: goto          257
     180: ldc           #68                 // String int
     182: aload_1
     183: invokevirtual #62                 // Method java/lang/String.equals:(Ljava/lang/Object;)Z
     186: ifeq          200
     189: aload         4
     191: bipush        73
     193: invokevirtual #55                 // Method java/lang/StringBuilder.append:(C)Ljava/lang/StringBuilder;
     196: pop
     197: goto          257
     200: ldc           #69                 // String long
     202: aload_1
     203: invokevirtual #62                 // Method java/lang/String.equals:(Ljava/lang/Object;)Z
     206: ifeq          220
     209: aload         4
     211: bipush        74
     213: invokevirtual #55                 // Method java/lang/StringBuilder.append:(C)Ljava/lang/StringBuilder;
     216: pop
     217: goto          257
     220: ldc           #70                 // String short
     222: aload_1
     223: invokevirtual #62                 // Method java/lang/String.equals:(Ljava/lang/Object;)Z
     226: ifeq          240
     229: aload         4
     231: bipush        83
     233: invokevirtual #55                 // Method java/lang/StringBuilder.append:(C)Ljava/lang/StringBuilder;
     236: pop
     237: goto          257
     240: aload         4
     242: bipush        76
     244: invokevirtual #55                 // Method java/lang/StringBuilder.append:(C)Ljava/lang/StringBuilder;
     247: aload_1
     248: invokevirtual #38                 // Method java/lang/StringBuilder.append:(Ljava/lang/String;)Ljava/lang/StringBuilder;
     251: bipush        59
     253: invokevirtual #55                 // Method java/lang/StringBuilder.append:(C)Ljava/lang/StringBuilder;
     256: pop
     257: aload         4
     259: invokevirtual #40                 // Method java/lang/StringBuilder.toString:()Ljava/lang/String;
     262: astore_1
     263: goto          383
     266: ldc           #61                 // String void
     268: aload_1
     269: invokevirtual #62                 // Method java/lang/String.equals:(Ljava/lang/Object;)Z
     272: ifeq          279
     275: getstatic     #100                // Field java/lang/Void.TYPE:Ljava/lang/Class;
     278: areturn
     279: ldc           #63                 // String boolean
     281: aload_1
     282: invokevirtual #62                 // Method java/lang/String.equals:(Ljava/lang/Object;)Z
     285: ifeq          292
     288: getstatic     #15                 // Field java/lang/Boolean.TYPE:Ljava/lang/Class;
     291: areturn
     292: ldc           #64                 // String byte
     294: aload_1
     295: invokevirtual #62                 // Method java/lang/String.equals:(Ljava/lang/Object;)Z
     298: ifeq          305
     301: getstatic     #23                 // Field java/lang/Byte.TYPE:Ljava/lang/Class;
     304: areturn
     305: ldc           #65                 // String char
     307: aload_1
     308: invokevirtual #62                 // Method java/lang/String.equals:(Ljava/lang/Object;)Z
     311: ifeq          318
     314: getstatic     #22                 // Field java/lang/Character.TYPE:Ljava/lang/Class;
     317: areturn
     318: ldc           #66                 // String double
     320: aload_1
     321: invokevirtual #62                 // Method java/lang/String.equals:(Ljava/lang/Object;)Z
     324: ifeq          331
     327: getstatic     #20                 // Field java/lang/Double.TYPE:Ljava/lang/Class;
     330: areturn
     331: ldc           #67                 // String float
     333: aload_1
     334: invokevirtual #62                 // Method java/lang/String.equals:(Ljava/lang/Object;)Z
     337: ifeq          344
     340: getstatic     #18                 // Field java/lang/Float.TYPE:Ljava/lang/Class;
     343: areturn
     344: ldc           #68                 // String int
     346: aload_1
     347: invokevirtual #62                 // Method java/lang/String.equals:(Ljava/lang/Object;)Z
     350: ifeq          357
     353: getstatic     #13                 // Field java/lang/Integer.TYPE:Ljava/lang/Class;
     356: areturn
     357: ldc           #69                 // String long
     359: aload_1
     360: invokevirtual #62                 // Method java/lang/String.equals:(Ljava/lang/Object;)Z
     363: ifeq          370
     366: getstatic     #16                 // Field java/lang/Long.TYPE:Ljava/lang/Class;
     369: areturn
     370: ldc           #70                 // String short
     372: aload_1
     373: invokevirtual #62                 // Method java/lang/String.equals:(Ljava/lang/Object;)Z
     376: ifeq          383
     379: getstatic     #25                 // Field java/lang/Short.TYPE:Ljava/lang/Class;
     382: areturn
     383: aload_0
     384: ifnonnull     391
     387: invokestatic  #99                 // Method org/apache/dubbo/common/utils/ClassUtils.getClassLoader:()Ljava/lang/ClassLoader;
     390: astore_0
     391: aload_1
     392: iconst_1
     393: aload_0
     394: invokestatic  #101                // Method java/lang/Class.forName:(Ljava/lang/String;ZLjava/lang/ClassLoader;)Ljava/lang/Class;
     397: areturn

  public static java.lang.Class<?> desc2class(java.lang.String) throws java.lang.ClassNotFoundException;
    Code:
       0: invokestatic  #99                 // Method org/apache/dubbo/common/utils/ClassUtils.getClassLoader:()Ljava/lang/ClassLoader;
       3: aload_0
       4: invokestatic  #102                // Method desc2class:(Ljava/lang/ClassLoader;Ljava/lang/String;)Ljava/lang/Class;
       7: areturn

  private static java.lang.Class<?> desc2class(java.lang.ClassLoader, java.lang.String) throws java.lang.ClassNotFoundException;
    Code:
       0: aload_1
       1: iconst_0
       2: invokevirtual #88                 // Method java/lang/String.charAt:(I)C
       5: tableswitch   { // 66 to 91
                    66: 132
                    67: 136
                    68: 140
                    69: 194
                    70: 144
                    71: 194
                    72: 194
                    73: 148
                    74: 152
                    75: 194
                    76: 160
                    77: 194
                    78: 194
                    79: 194
                    80: 194
                    81: 194
                    82: 194
                    83: 156
                    84: 194
                    85: 194
                    86: 124
                    87: 194
                    88: 194
                    89: 194
                    90: 128
                    91: 182
               default: 194
          }
     124: getstatic     #100                // Field java/lang/Void.TYPE:Ljava/lang/Class;
     127: areturn
     128: getstatic     #15                 // Field java/lang/Boolean.TYPE:Ljava/lang/Class;
     131: areturn
     132: getstatic     #23                 // Field java/lang/Byte.TYPE:Ljava/lang/Class;
     135: areturn
     136: getstatic     #22                 // Field java/lang/Character.TYPE:Ljava/lang/Class;
     139: areturn
     140: getstatic     #20                 // Field java/lang/Double.TYPE:Ljava/lang/Class;
     143: areturn
     144: getstatic     #18                 // Field java/lang/Float.TYPE:Ljava/lang/Class;
     147: areturn
     148: getstatic     #13                 // Field java/lang/Integer.TYPE:Ljava/lang/Class;
     151: areturn
     152: getstatic     #16                 // Field java/lang/Long.TYPE:Ljava/lang/Class;
     155: areturn
     156: getstatic     #25                 // Field java/lang/Short.TYPE:Ljava/lang/Class;
     159: areturn
     160: aload_1
     161: iconst_1
     162: aload_1
     163: invokevirtual #85                 // Method java/lang/String.length:()I
     166: iconst_1
     167: isub
     168: invokevirtual #86                 // Method java/lang/String.substring:(II)Ljava/lang/String;
     171: bipush        47
     173: bipush        46
     175: invokevirtual #71                 // Method java/lang/String.replace:(CC)Ljava/lang/String;
     178: astore_1
     179: goto          221
     182: aload_1
     183: bipush        47
     185: bipush        46
     187: invokevirtual #71                 // Method java/lang/String.replace:(CC)Ljava/lang/String;
     190: astore_1
     191: goto          221
     194: new           #92                 // class java/lang/ClassNotFoundException
     197: dup
     198: new           #35                 // class java/lang/StringBuilder
     201: dup
     202: invokespecial #36                 // Method java/lang/StringBuilder."<init>":()V
     205: ldc           #103                // String Class not found:
     207: invokevirtual #38                 // Method java/lang/StringBuilder.append:(Ljava/lang/String;)Ljava/lang/StringBuilder;
     210: aload_1
     211: invokevirtual #38                 // Method java/lang/StringBuilder.append:(Ljava/lang/String;)Ljava/lang/StringBuilder;
     214: invokevirtual #40                 // Method java/lang/StringBuilder.toString:()Ljava/lang/String;
     217: invokespecial #104                // Method java/lang/ClassNotFoundException."<init>":(Ljava/lang/String;)V
     220: athrow
     221: aload_0
     222: ifnonnull     229
     225: invokestatic  #99                 // Method org/apache/dubbo/common/utils/ClassUtils.getClassLoader:()Ljava/lang/ClassLoader;
     228: astore_0
     229: aload_1
     230: iconst_1
     231: aload_0
     232: invokestatic  #101                // Method java/lang/Class.forName:(Ljava/lang/String;ZLjava/lang/ClassLoader;)Ljava/lang/Class;
     235: areturn

  public static java.lang.Class<?>[] desc2classArray(java.lang.String) throws java.lang.ClassNotFoundException;
    Code:
       0: invokestatic  #99                 // Method org/apache/dubbo/common/utils/ClassUtils.getClassLoader:()Ljava/lang/ClassLoader;
       3: aload_0
       4: invokestatic  #105                // Method desc2classArray:(Ljava/lang/ClassLoader;Ljava/lang/String;)[Ljava/lang/Class;
       7: astore_1
       8: aload_1
       9: areturn

  private static java.lang.Class<?>[] desc2classArray(java.lang.ClassLoader, java.lang.String) throws java.lang.ClassNotFoundException;
    Code:
       0: aload_1
       1: invokevirtual #85                 // Method java/lang/String.length:()I
       4: ifne          11
       7: getstatic     #106                // Field EMPTY_CLASS_ARRAY:[Ljava/lang/Class;
      10: areturn
      11: new           #107                // class java/util/ArrayList
      14: dup
      15: invokespecial #108                // Method java/util/ArrayList."<init>":()V
      18: astore_2
      19: getstatic     #109                // Field DESC_PATTERN:Ljava/util/regex/Pattern;
      22: aload_1
      23: invokevirtual #110                // Method java/util/regex/Pattern.matcher:(Ljava/lang/CharSequence;)Ljava/util/regex/Matcher;
      26: astore_3
      27: aload_3
      28: invokevirtual #111                // Method java/util/regex/Matcher.find:()Z
      31: ifeq          52
      34: aload_2
      35: aload_0
      36: aload_3
      37: invokevirtual #112                // Method java/util/regex/Matcher.group:()Ljava/lang/String;
      40: invokestatic  #102                // Method desc2class:(Ljava/lang/ClassLoader;Ljava/lang/String;)Ljava/lang/Class;
      43: invokeinterface #113,  2          // InterfaceMethod java/util/List.add:(Ljava/lang/Object;)Z
      48: pop
      49: goto          27
      52: aload_2
      53: getstatic     #106                // Field EMPTY_CLASS_ARRAY:[Ljava/lang/Class;
      56: invokeinterface #114,  2          // InterfaceMethod java/util/List.toArray:([Ljava/lang/Object;)[Ljava/lang/Object;
      61: checkcast     #115                // class "[Ljava/lang/Class;"
      64: areturn

  public static java.lang.reflect.Method findMethodByMethodSignature(java.lang.Class<?>, java.lang.String, java.lang.String[]) throws java.lang.NoSuchMethodException, java.lang.ClassNotFoundException;
    Code:
       0: new           #35                 // class java/lang/StringBuilder
       3: dup
       4: invokespecial #36                 // Method java/lang/StringBuilder."<init>":()V
       7: aload_0
       8: invokevirtual #39                 // Method java/lang/Class.getName:()Ljava/lang/String;
      11: invokevirtual #38                 // Method java/lang/StringBuilder.append:(Ljava/lang/String;)Ljava/lang/StringBuilder;
      14: ldc           #116                // String .
      16: invokevirtual #38                 // Method java/lang/StringBuilder.append:(Ljava/lang/String;)Ljava/lang/StringBuilder;
      19: aload_1
      20: invokevirtual #38                 // Method java/lang/StringBuilder.append:(Ljava/lang/String;)Ljava/lang/StringBuilder;
      23: invokevirtual #40                 // Method java/lang/StringBuilder.toString:()Ljava/lang/String;
      26: astore_3
      27: aload_2
      28: ifnull        58
      31: aload_2
      32: arraylength
      33: ifle          58
      36: new           #35                 // class java/lang/StringBuilder
      39: dup
      40: invokespecial #36                 // Method java/lang/StringBuilder."<init>":()V
      43: aload_3
      44: invokevirtual #38                 // Method java/lang/StringBuilder.append:(Ljava/lang/String;)Ljava/lang/StringBuilder;
      47: aload_2
      48: invokestatic  #117                // Method org/apache/dubbo/common/utils/StringUtils.join:([Ljava/lang/String;)Ljava/lang/String;
      51: invokevirtual #38                 // Method java/lang/StringBuilder.append:(Ljava/lang/String;)Ljava/lang/StringBuilder;
      54: invokevirtual #40                 // Method java/lang/StringBuilder.toString:()Ljava/lang/String;
      57: astore_3
      58: aload_2
      59: ifnonnull     245
      62: new           #107                // class java/util/ArrayList
      65: dup
      66: invokespecial #108                // Method java/util/ArrayList."<init>":()V
      69: astore        5
      71: aload_0
      72: invokevirtual #118                // Method java/lang/Class.getMethods:()[Ljava/lang/reflect/Method;
      75: astore        6
      77: aload         6
      79: arraylength
      80: istore        7
      82: iconst_0
      83: istore        8
      85: iload         8
      87: iload         7
      89: if_icmpge     127
      92: aload         6
      94: iload         8
      96: aaload
      97: astore        9
      99: aload         9
     101: invokevirtual #56                 // Method java/lang/reflect/Method.getName:()Ljava/lang/String;
     104: aload_1
     105: invokevirtual #62                 // Method java/lang/String.equals:(Ljava/lang/Object;)Z
     108: ifeq          121
     111: aload         5
     113: aload         9
     115: invokeinterface #113,  2          // InterfaceMethod java/util/List.add:(Ljava/lang/Object;)Z
     120: pop
     121: iinc          8, 1
     124: goto          85
     127: aload         5
     129: invokeinterface #119,  1          // InterfaceMethod java/util/List.isEmpty:()Z
     134: ifeq          173
     137: new           #120                // class java/lang/NoSuchMethodException
     140: dup
     141: new           #35                 // class java/lang/StringBuilder
     144: dup
     145: invokespecial #36                 // Method java/lang/StringBuilder."<init>":()V
     148: ldc           #121                // String No such method
     150: invokevirtual #38                 // Method java/lang/StringBuilder.append:(Ljava/lang/String;)Ljava/lang/StringBuilder;
     153: aload_1
     154: invokevirtual #38                 // Method java/lang/StringBuilder.append:(Ljava/lang/String;)Ljava/lang/StringBuilder;
     157: ldc           #122                // String  in class
     159: invokevirtual #38                 // Method java/lang/StringBuilder.append:(Ljava/lang/String;)Ljava/lang/StringBuilder;
     162: aload_0
     163: invokevirtual #123                // Method java/lang/StringBuilder.append:(Ljava/lang/Object;)Ljava/lang/StringBuilder;
     166: invokevirtual #40                 // Method java/lang/StringBuilder.toString:()Ljava/lang/String;
     169: invokespecial #124                // Method java/lang/NoSuchMethodException."<init>":(Ljava/lang/String;)V
     172: athrow
     173: aload         5
     175: invokeinterface #125,  1          // InterfaceMethod java/util/List.size:()I
     180: iconst_1
     181: if_icmple     229
     184: ldc           #126                // String Not unique method for method name(%s) in class(%s), find %d methods.
     186: iconst_3
     187: anewarray     #127                // class java/lang/Object
     190: dup
     191: iconst_0
     192: aload_1
     193: aastore
     194: dup
     195: iconst_1
     196: aload_0
     197: invokevirtual #39                 // Method java/lang/Class.getName:()Ljava/lang/String;
     200: aastore
     201: dup
     202: iconst_2
     203: aload         5
     205: invokeinterface #125,  1          // InterfaceMethod java/util/List.size:()I
     210: invokestatic  #128                // Method java/lang/Integer.valueOf:(I)Ljava/lang/Integer;
     213: aastore
     214: invokestatic  #129                // Method java/lang/String.format:(Ljava/lang/String;[Ljava/lang/Object;)Ljava/lang/String;
     217: astore        6
     219: new           #93                 // class java/lang/IllegalStateException
     222: dup
     223: aload         6
     225: invokespecial #130                // Method java/lang/IllegalStateException."<init>":(Ljava/lang/String;)V
     228: athrow
     229: aload         5
     231: iconst_0
     232: invokeinterface #131,  2          // InterfaceMethod java/util/List.get:(I)Ljava/lang/Object;
     237: checkcast     #132                // class java/lang/reflect/Method
     240: astore        4
     242: goto          289
     245: aload_2
     246: arraylength
     247: anewarray     #46                 // class java/lang/Class
     250: astore        5
     252: iconst_0
     253: istore        6
     255: iload         6
     257: aload_2
     258: arraylength
     259: if_icmpge     280
     262: aload         5
     264: iload         6
     266: aload_2
     267: iload         6
     269: aaload
     270: invokestatic  #91                 // Method name2class:(Ljava/lang/String;)Ljava/lang/Class;
     273: aastore
     274: iinc          6, 1
     277: goto          255
     280: aload_0
     281: aload_1
     282: aload         5
     284: invokevirtual #133                // Method java/lang/Class.getMethod:(Ljava/lang/String;[Ljava/lang/Class;)Ljava/lang/reflect/Method;
     287: astore        4
     289: aload         4
     291: areturn

  public static java.lang.reflect.Method findMethodByMethodName(java.lang.Class<?>, java.lang.String) throws java.lang.NoSuchMethodException, java.lang.ClassNotFoundException;
    Code:
       0: aload_0
       1: aload_1
       2: aconst_null
       3: invokestatic  #134                // Method findMethodByMethodSignature:(Ljava/lang/Class;Ljava/lang/String;[Ljava/lang/String;)Ljava/lang/reflect/Method;
       6: areturn

  public static java.lang.reflect.Constructor<?> findConstructor(java.lang.Class<?>, java.lang.Class<?>) throws java.lang.NoSuchMethodException;
    Code:
       0: aload_0
       1: iconst_1
       2: anewarray     #46                 // class java/lang/Class
       5: dup
       6: iconst_0
       7: aload_1
       8: aastore
       9: invokevirtual #135                // Method java/lang/Class.getConstructor:([Ljava/lang/Class;)Ljava/lang/reflect/Constructor;
      12: astore_2
      13: goto          104
      16: astore_3
      17: aconst_null
      18: astore_2
      19: aload_0
      20: invokevirtual #136                // Method java/lang/Class.getConstructors:()[Ljava/lang/reflect/Constructor;
      23: astore        4
      25: aload         4
      27: astore        5
      29: aload         5
      31: arraylength
      32: istore        6
      34: iconst_0
      35: istore        7
      37: iload         7
      39: iload         6
      41: if_icmpge     98
      44: aload         5
      46: iload         7
      48: aaload
      49: astore        8
      51: aload         8
      53: invokevirtual #137                // Method java/lang/reflect/Constructor.getModifiers:()I
      56: invokestatic  #138                // Method java/lang/reflect/Modifier.isPublic:(I)Z
      59: ifeq          92
      62: aload         8
      64: invokevirtual #60                 // Method java/lang/reflect/Constructor.getParameterTypes:()[Ljava/lang/Class;
      67: arraylength
      68: iconst_1
      69: if_icmpne     92
      72: aload         8
      74: invokevirtual #60                 // Method java/lang/reflect/Constructor.getParameterTypes:()[Ljava/lang/Class;
      77: iconst_0
      78: aaload
      79: aload_1
      80: invokevirtual #11                 // Method java/lang/Class.isAssignableFrom:(Ljava/lang/Class;)Z
      83: ifeq          92
      86: aload         8
      88: astore_2
      89: goto          98
      92: iinc          7, 1
      95: goto          37
      98: aload_2
      99: ifnonnull     104
     102: aload_3
     103: athrow
     104: aload_2
     105: areturn
    Exception table:
       from    to  target type
           0    13    16   Class java/lang/NoSuchMethodException

  public static boolean isInstance(java.lang.Object, java.lang.String);
    Code:
       0: aload_0
       1: invokevirtual #28                 // Method java/lang/Object.getClass:()Ljava/lang/Class;
       4: astore_2
       5: aload_2
       6: ifnull        76
       9: aload_2
      10: ldc           #127                // class java/lang/Object
      12: invokevirtual #139                // Method java/lang/Object.equals:(Ljava/lang/Object;)Z
      15: ifne          76
      18: aload_2
      19: invokevirtual #140                // Method java/lang/Class.getInterfaces:()[Ljava/lang/Class;
      22: astore_3
      23: aload_3
      24: astore        4
      26: aload         4
      28: arraylength
      29: istore        5
      31: iconst_0
      32: istore        6
      34: iload         6
      36: iload         5
      38: if_icmpge     68
      41: aload         4
      43: iload         6
      45: aaload
      46: astore        7
      48: aload         7
      50: invokevirtual #39                 // Method java/lang/Class.getName:()Ljava/lang/String;
      53: aload_1
      54: invokevirtual #62                 // Method java/lang/String.equals:(Ljava/lang/Object;)Z
      57: ifeq          62
      60: iconst_1
      61: ireturn
      62: iinc          6, 1
      65: goto          34
      68: aload_2
      69: invokevirtual #141                // Method java/lang/Class.getSuperclass:()Ljava/lang/Class;
      72: astore_2
      73: goto          5
      76: iconst_0
      77: ireturn

  public static java.lang.Object getEmptyObject(java.lang.Class<?>);
    Code:
       0: aload_0
       1: new           #142                // class java/util/HashMap
       4: dup
       5: invokespecial #143                // Method java/util/HashMap."<init>":()V
       8: iconst_0
       9: invokestatic  #144                // Method getEmptyObject:(Ljava/lang/Class;Ljava/util/Map;I)Ljava/lang/Object;
      12: areturn

  private static java.lang.Object getEmptyObject(java.lang.Class<?>, java.util.Map<java.lang.Class<?>, java.lang.Object>, int);
    Code:
       0: iload_2
       1: iconst_2
       2: if_icmple     7
       5: aconst_null
       6: areturn
       7: aload_0
       8: ifnonnull     13
      11: aconst_null
      12: areturn
      13: aload_0
      14: getstatic     #15                 // Field java/lang/Boolean.TYPE:Ljava/lang/Class;
      17: if_acmpeq     26
      20: aload_0
      21: ldc           #8                  // class java/lang/Boolean
      23: if_acmpne     31
      26: iconst_0
      27: invokestatic  #145                // Method java/lang/Boolean.valueOf:(Z)Ljava/lang/Boolean;
      30: areturn
      31: aload_0
      32: getstatic     #22                 // Field java/lang/Character.TYPE:Ljava/lang/Class;
      35: if_acmpeq     44
      38: aload_0
      39: ldc           #9                  // class java/lang/Character
      41: if_acmpne     49
      44: iconst_0
      45: invokestatic  #146                // Method java/lang/Character.valueOf:(C)Ljava/lang/Character;
      48: areturn
      49: aload_0
      50: getstatic     #23                 // Field java/lang/Byte.TYPE:Ljava/lang/Class;
      53: if_acmpeq     62
      56: aload_0
      57: ldc           #24                 // class java/lang/Byte
      59: if_acmpne     67
      62: iconst_0
      63: invokestatic  #147                // Method java/lang/Byte.valueOf:(B)Ljava/lang/Byte;
      66: areturn
      67: aload_0
      68: getstatic     #25                 // Field java/lang/Short.TYPE:Ljava/lang/Class;
      71: if_acmpeq     80
      74: aload_0
      75: ldc           #26                 // class java/lang/Short
      77: if_acmpne     85
      80: iconst_0
      81: invokestatic  #148                // Method java/lang/Short.valueOf:(S)Ljava/lang/Short;
      84: areturn
      85: aload_0
      86: getstatic     #13                 // Field java/lang/Integer.TYPE:Ljava/lang/Class;
      89: if_acmpeq     98
      92: aload_0
      93: ldc           #14                 // class java/lang/Integer
      95: if_acmpne     103
      98: iconst_0
      99: invokestatic  #128                // Method java/lang/Integer.valueOf:(I)Ljava/lang/Integer;
     102: areturn
     103: aload_0
     104: getstatic     #16                 // Field java/lang/Long.TYPE:Ljava/lang/Class;
     107: if_acmpeq     116
     110: aload_0
     111: ldc           #17                 // class java/lang/Long
     113: if_acmpne     121
     116: lconst_0
     117: invokestatic  #149                // Method java/lang/Long.valueOf:(J)Ljava/lang/Long;
     120: areturn
     121: aload_0
     122: getstatic     #18                 // Field java/lang/Float.TYPE:Ljava/lang/Class;
     125: if_acmpeq     134
     128: aload_0
     129: ldc           #19                 // class java/lang/Float
     131: if_acmpne     139
     134: fconst_0
     135: invokestatic  #150                // Method java/lang/Float.valueOf:(F)Ljava/lang/Float;
     138: areturn
     139: aload_0
     140: getstatic     #20                 // Field java/lang/Double.TYPE:Ljava/lang/Class;
     143: if_acmpeq     152
     146: aload_0
     147: ldc           #21                 // class java/lang/Double
     149: if_acmpne     157
     152: dconst_0
     153: invokestatic  #151                // Method java/lang/Double.valueOf:(D)Ljava/lang/Double;
     156: areturn
     157: aload_0
     158: invokevirtual #3                  // Method java/lang/Class.isArray:()Z
     161: ifeq          173
     164: aload_0
     165: invokevirtual #4                  // Method java/lang/Class.getComponentType:()Ljava/lang/Class;
     168: iconst_0
     169: invokestatic  #152                // Method java/lang/reflect/Array.newInstance:(Ljava/lang/Class;I)Ljava/lang/Object;
     172: areturn
     173: aload_0
     174: ldc           #107                // class java/util/ArrayList
     176: invokevirtual #11                 // Method java/lang/Class.isAssignableFrom:(Ljava/lang/Class;)Z
     179: ifeq          191
     182: new           #107                // class java/util/ArrayList
     185: dup
     186: iconst_0
     187: invokespecial #153                // Method java/util/ArrayList."<init>":(I)V
     190: areturn
     191: aload_0
     192: ldc           #154                // class java/util/HashSet
     194: invokevirtual #11                 // Method java/lang/Class.isAssignableFrom:(Ljava/lang/Class;)Z
     197: ifeq          209
     200: new           #154                // class java/util/HashSet
     203: dup
     204: iconst_0
     205: invokespecial #155                // Method java/util/HashSet."<init>":(I)V
     208: areturn
     209: aload_0
     210: ldc           #142                // class java/util/HashMap
     212: invokevirtual #11                 // Method java/lang/Class.isAssignableFrom:(Ljava/lang/Class;)Z
     215: ifeq          227
     218: new           #142                // class java/util/HashMap
     221: dup
     222: iconst_0
     223: invokespecial #156                // Method java/util/HashMap."<init>":(I)V
     226: areturn
     227: ldc           #7                  // class java/lang/String
     229: aload_0
     230: invokevirtual #139                // Method java/lang/Object.equals:(Ljava/lang/Object;)Z
     233: ifeq          239
     236: ldc           #72                 // String
     238: areturn
     239: aload_0
     240: invokevirtual #157                // Method java/lang/Class.isInterface:()Z
     243: ifeq          248
     246: aconst_null
     247: areturn
     248: aload_1
     249: aload_0
     250: invokeinterface #158,  2          // InterfaceMethod java/util/Map.get:(Ljava/lang/Object;)Ljava/lang/Object;
     255: astore_3
     256: aload_3
     257: ifnonnull     285
     260: aload_0
     261: iconst_0
     262: anewarray     #46                 // class java/lang/Class
     265: invokevirtual #159                // Method java/lang/Class.getDeclaredConstructor:([Ljava/lang/Class;)Ljava/lang/reflect/Constructor;
     268: iconst_0
     269: anewarray     #127                // class java/lang/Object
     272: invokevirtual #160                // Method java/lang/reflect/Constructor.newInstance:([Ljava/lang/Object;)Ljava/lang/Object;
     275: astore_3
     276: aload_1
     277: aload_0
     278: aload_3
     279: invokeinterface #161,  3          // InterfaceMethod java/util/Map.put:(Ljava/lang/Object;Ljava/lang/Object;)Ljava/lang/Object;
     284: pop
     285: aload_3
     286: invokevirtual #28                 // Method java/lang/Object.getClass:()Ljava/lang/Class;
     289: astore        4
     291: aload         4
     293: ifnull        409
     296: aload         4
     298: ldc           #127                // class java/lang/Object
     300: if_acmpeq     409
     303: aload         4
     305: invokevirtual #162                // Method java/lang/Class.getDeclaredFields:()[Ljava/lang/reflect/Field;
     308: astore        5
     310: aload         5
     312: astore        6
     314: aload         6
     316: arraylength
     317: istore        7
     319: iconst_0
     320: istore        8
     322: iload         8
     324: iload         7
     326: if_icmpge     399
     329: aload         6
     331: iload         8
     333: aaload
     334: astore        9
     336: aload         9
     338: invokevirtual #163                // Method java/lang/reflect/Field.isSynthetic:()Z
     341: ifeq          347
     344: goto          393
     347: aload         9
     349: invokevirtual #164                // Method java/lang/reflect/Field.getType:()Ljava/lang/Class;
     352: aload_1
     353: iload_2
     354: iconst_1
     355: iadd
     356: invokestatic  #144                // Method getEmptyObject:(Ljava/lang/Class;Ljava/util/Map;I)Ljava/lang/Object;
     359: astore        10
     361: aload         10
     363: ifnull        393
     366: aload         9
     368: invokevirtual #165                // Method java/lang/reflect/Field.isAccessible:()Z
     371: ifne          380
     374: aload         9
     376: iconst_1
     377: invokevirtual #166                // Method java/lang/reflect/Field.setAccessible:(Z)V
     380: aload         9
     382: aload_3
     383: aload         10
     385: invokevirtual #167                // Method java/lang/reflect/Field.set:(Ljava/lang/Object;Ljava/lang/Object;)V
     388: goto          393
     391: astore        11
     393: iinc          8, 1
     396: goto          322
     399: aload         4
     401: invokevirtual #141                // Method java/lang/Class.getSuperclass:()Ljava/lang/Class;
     404: astore        4
     406: goto          291
     409: aload_3
     410: areturn
     411: astore_3
     412: aconst_null
     413: areturn
    Exception table:
       from    to  target type
         366   388   391   Class java/lang/Throwable
         248   410   411   Class java/lang/Throwable

  public static java.lang.Object defaultReturn(java.lang.reflect.Method);
    Code:
       0: aload_0
       1: invokevirtual #53                 // Method java/lang/reflect/Method.getReturnType:()Ljava/lang/Class;
       4: invokevirtual #6                  // Method java/lang/Class.isPrimitive:()Z
       7: ifeq          23
      10: getstatic     #168                // Field primitiveDefaults:Ljava/util/Map;
      13: aload_0
      14: invokevirtual #53                 // Method java/lang/reflect/Method.getReturnType:()Ljava/lang/Class;
      17: invokeinterface #158,  2          // InterfaceMethod java/util/Map.get:(Ljava/lang/Object;)Ljava/lang/Object;
      22: areturn
      23: aconst_null
      24: areturn

  public static java.lang.Object defaultReturn(java.lang.Class<?>);
    Code:
       0: aload_0
       1: ifnull        21
       4: aload_0
       5: invokevirtual #6                  // Method java/lang/Class.isPrimitive:()Z
       8: ifeq          21
      11: getstatic     #168                // Field primitiveDefaults:Ljava/util/Map;
      14: aload_0
      15: invokeinterface #158,  2          // InterfaceMethod java/util/Map.get:(Ljava/lang/Object;)Ljava/lang/Object;
      20: areturn
      21: aconst_null
      22: areturn

  public static boolean isBeanPropertyReadMethod(java.lang.reflect.Method);
    Code:
       0: aload_0
       1: ifnull        101
       4: aload_0
       5: invokevirtual #169                // Method java/lang/reflect/Method.getModifiers:()I
       8: invokestatic  #138                // Method java/lang/reflect/Modifier.isPublic:(I)Z
      11: ifeq          101
      14: aload_0
      15: invokevirtual #169                // Method java/lang/reflect/Method.getModifiers:()I
      18: invokestatic  #170                // Method java/lang/reflect/Modifier.isStatic:(I)Z
      21: ifne          101
      24: aload_0
      25: invokevirtual #53                 // Method java/lang/reflect/Method.getReturnType:()Ljava/lang/Class;
      28: getstatic     #100                // Field java/lang/Void.TYPE:Ljava/lang/Class;
      31: if_acmpeq     101
      34: aload_0
      35: invokevirtual #171                // Method java/lang/reflect/Method.getDeclaringClass:()Ljava/lang/Class;
      38: ldc           #127                // class java/lang/Object
      40: if_acmpeq     101
      43: aload_0
      44: invokevirtual #57                 // Method java/lang/reflect/Method.getParameterTypes:()[Ljava/lang/Class;
      47: arraylength
      48: ifne          101
      51: aload_0
      52: invokevirtual #56                 // Method java/lang/reflect/Method.getName:()Ljava/lang/String;
      55: ldc           #172                // String get
      57: invokevirtual #173                // Method java/lang/String.startsWith:(Ljava/lang/String;)Z
      60: ifeq          74
      63: aload_0
      64: invokevirtual #56                 // Method java/lang/reflect/Method.getName:()Ljava/lang/String;
      67: invokevirtual #85                 // Method java/lang/String.length:()I
      70: iconst_3
      71: if_icmpgt     97
      74: aload_0
      75: invokevirtual #56                 // Method java/lang/reflect/Method.getName:()Ljava/lang/String;
      78: ldc           #174                // String is
      80: invokevirtual #173                // Method java/lang/String.startsWith:(Ljava/lang/String;)Z
      83: ifeq          101
      86: aload_0
      87: invokevirtual #56                 // Method java/lang/reflect/Method.getName:()Ljava/lang/String;
      90: invokevirtual #85                 // Method java/lang/String.length:()I
      93: iconst_2
      94: if_icmple     101
      97: iconst_1
      98: goto          102
     101: iconst_0
     102: ireturn

  public static java.lang.String getPropertyNameFromBeanReadMethod(java.lang.reflect.Method);
    Code:
       0: aload_0
       1: invokestatic  #175                // Method isBeanPropertyReadMethod:(Ljava/lang/reflect/Method;)Z
       4: ifeq          105
       7: aload_0
       8: invokevirtual #56                 // Method java/lang/reflect/Method.getName:()Ljava/lang/String;
      11: ldc           #172                // String get
      13: invokevirtual #173                // Method java/lang/String.startsWith:(Ljava/lang/String;)Z
      16: ifeq          56
      19: new           #35                 // class java/lang/StringBuilder
      22: dup
      23: invokespecial #36                 // Method java/lang/StringBuilder."<init>":()V
      26: aload_0
      27: invokevirtual #56                 // Method java/lang/reflect/Method.getName:()Ljava/lang/String;
      30: iconst_3
      31: iconst_4
      32: invokevirtual #86                 // Method java/lang/String.substring:(II)Ljava/lang/String;
      35: invokevirtual #176                // Method java/lang/String.toLowerCase:()Ljava/lang/String;
      38: invokevirtual #38                 // Method java/lang/StringBuilder.append:(Ljava/lang/String;)Ljava/lang/StringBuilder;
      41: aload_0
      42: invokevirtual #56                 // Method java/lang/reflect/Method.getName:()Ljava/lang/String;
      45: iconst_4
      46: invokevirtual #177                // Method java/lang/String.substring:(I)Ljava/lang/String;
      49: invokevirtual #38                 // Method java/lang/StringBuilder.append:(Ljava/lang/String;)Ljava/lang/StringBuilder;
      52: invokevirtual #40                 // Method java/lang/StringBuilder.toString:()Ljava/lang/String;
      55: areturn
      56: aload_0
      57: invokevirtual #56                 // Method java/lang/reflect/Method.getName:()Ljava/lang/String;
      60: ldc           #174                // String is
      62: invokevirtual #173                // Method java/lang/String.startsWith:(Ljava/lang/String;)Z
      65: ifeq          105
      68: new           #35                 // class java/lang/StringBuilder
      71: dup
      72: invokespecial #36                 // Method java/lang/StringBuilder."<init>":()V
      75: aload_0
      76: invokevirtual #56                 // Method java/lang/reflect/Method.getName:()Ljava/lang/String;
      79: iconst_2
      80: iconst_3
      81: invokevirtual #86                 // Method java/lang/String.substring:(II)Ljava/lang/String;
      84: invokevirtual #176                // Method java/lang/String.toLowerCase:()Ljava/lang/String;
      87: invokevirtual #38                 // Method java/lang/StringBuilder.append:(Ljava/lang/String;)Ljava/lang/StringBuilder;
      90: aload_0
      91: invokevirtual #56                 // Method java/lang/reflect/Method.getName:()Ljava/lang/String;
      94: iconst_3
      95: invokevirtual #177                // Method java/lang/String.substring:(I)Ljava/lang/String;
      98: invokevirtual #38                 // Method java/lang/StringBuilder.append:(Ljava/lang/String;)Ljava/lang/StringBuilder;
     101: invokevirtual #40                 // Method java/lang/StringBuilder.toString:()Ljava/lang/String;
     104: areturn
     105: aconst_null
     106: areturn

  public static boolean isBeanPropertyWriteMethod(java.lang.reflect.Method);
    Code:
       0: aload_0
       1: ifnull        69
       4: aload_0
       5: invokevirtual #169                // Method java/lang/reflect/Method.getModifiers:()I
       8: invokestatic  #138                // Method java/lang/reflect/Modifier.isPublic:(I)Z
      11: ifeq          69
      14: aload_0
      15: invokevirtual #169                // Method java/lang/reflect/Method.getModifiers:()I
      18: invokestatic  #170                // Method java/lang/reflect/Modifier.isStatic:(I)Z
      21: ifne          69
      24: aload_0
      25: invokevirtual #171                // Method java/lang/reflect/Method.getDeclaringClass:()Ljava/lang/Class;
      28: ldc           #127                // class java/lang/Object
      30: if_acmpeq     69
      33: aload_0
      34: invokevirtual #57                 // Method java/lang/reflect/Method.getParameterTypes:()[Ljava/lang/Class;
      37: arraylength
      38: iconst_1
      39: if_icmpne     69
      42: aload_0
      43: invokevirtual #56                 // Method java/lang/reflect/Method.getName:()Ljava/lang/String;
      46: ldc           #178                // String set
      48: invokevirtual #173                // Method java/lang/String.startsWith:(Ljava/lang/String;)Z
      51: ifeq          69
      54: aload_0
      55: invokevirtual #56                 // Method java/lang/reflect/Method.getName:()Ljava/lang/String;
      58: invokevirtual #85                 // Method java/lang/String.length:()I
      61: iconst_3
      62: if_icmple     69
      65: iconst_1
      66: goto          70
      69: iconst_0
      70: ireturn

  public static java.lang.String getPropertyNameFromBeanWriteMethod(java.lang.reflect.Method);
    Code:
       0: aload_0
       1: invokestatic  #179                // Method isBeanPropertyWriteMethod:(Ljava/lang/reflect/Method;)Z
       4: ifeq          44
       7: new           #35                 // class java/lang/StringBuilder
      10: dup
      11: invokespecial #36                 // Method java/lang/StringBuilder."<init>":()V
      14: aload_0
      15: invokevirtual #56                 // Method java/lang/reflect/Method.getName:()Ljava/lang/String;
      18: iconst_3
      19: iconst_4
      20: invokevirtual #86                 // Method java/lang/String.substring:(II)Ljava/lang/String;
      23: invokevirtual #176                // Method java/lang/String.toLowerCase:()Ljava/lang/String;
      26: invokevirtual #38                 // Method java/lang/StringBuilder.append:(Ljava/lang/String;)Ljava/lang/StringBuilder;
      29: aload_0
      30: invokevirtual #56                 // Method java/lang/reflect/Method.getName:()Ljava/lang/String;
      33: iconst_4
      34: invokevirtual #177                // Method java/lang/String.substring:(I)Ljava/lang/String;
      37: invokevirtual #38                 // Method java/lang/StringBuilder.append:(Ljava/lang/String;)Ljava/lang/StringBuilder;
      40: invokevirtual #40                 // Method java/lang/StringBuilder.toString:()Ljava/lang/String;
      43: areturn
      44: aconst_null
      45: areturn

  public static boolean isPublicInstanceField(java.lang.reflect.Field);
    Code:
       0: aload_0
       1: invokevirtual #180                // Method java/lang/reflect/Field.getModifiers:()I
       4: invokestatic  #138                // Method java/lang/reflect/Modifier.isPublic:(I)Z
       7: ifeq          41
      10: aload_0
      11: invokevirtual #180                // Method java/lang/reflect/Field.getModifiers:()I
      14: invokestatic  #170                // Method java/lang/reflect/Modifier.isStatic:(I)Z
      17: ifne          41
      20: aload_0
      21: invokevirtual #180                // Method java/lang/reflect/Field.getModifiers:()I
      24: invokestatic  #181                // Method java/lang/reflect/Modifier.isFinal:(I)Z
      27: ifne          41
      30: aload_0
      31: invokevirtual #163                // Method java/lang/reflect/Field.isSynthetic:()Z
      34: ifne          41
      37: iconst_1
      38: goto          42
      41: iconst_0
      42: ireturn

  public static java.util.Map<java.lang.String, java.lang.reflect.Field> getBeanPropertyFields(java.lang.Class);
    Code:
       0: new           #142                // class java/util/HashMap
       3: dup
       4: invokespecial #143                // Method java/util/HashMap."<init>":()V
       7: astore_1
       8: aload_0
       9: ifnull        98
      12: aload_0
      13: invokevirtual #162                // Method java/lang/Class.getDeclaredFields:()[Ljava/lang/reflect/Field;
      16: astore_2
      17: aload_2
      18: astore_3
      19: aload_3
      20: arraylength
      21: istore        4
      23: iconst_0
      24: istore        5
      26: iload         5
      28: iload         4
      30: if_icmpge     90
      33: aload_3
      34: iload         5
      36: aaload
      37: astore        6
      39: aload         6
      41: invokevirtual #180                // Method java/lang/reflect/Field.getModifiers:()I
      44: invokestatic  #182                // Method java/lang/reflect/Modifier.isTransient:(I)Z
      47: ifne          84
      50: aload         6
      52: invokevirtual #180                // Method java/lang/reflect/Field.getModifiers:()I
      55: invokestatic  #170                // Method java/lang/reflect/Modifier.isStatic:(I)Z
      58: ifeq          64
      61: goto          84
      64: aload         6
      66: iconst_1
      67: invokevirtual #166                // Method java/lang/reflect/Field.setAccessible:(Z)V
      70: aload_1
      71: aload         6
      73: invokevirtual #183                // Method java/lang/reflect/Field.getName:()Ljava/lang/String;
      76: aload         6
      78: invokeinterface #161,  3          // InterfaceMethod java/util/Map.put:(Ljava/lang/Object;Ljava/lang/Object;)Ljava/lang/Object;
      83: pop
      84: iinc          5, 1
      87: goto          26
      90: aload_0
      91: invokevirtual #141                // Method java/lang/Class.getSuperclass:()Ljava/lang/Class;
      94: astore_0
      95: goto          8
      98: aload_1
      99: areturn

  public static java.util.Map<java.lang.String, java.lang.reflect.Method> getBeanPropertyReadMethods(java.lang.Class);
    Code:
       0: new           #142                // class java/util/HashMap
       3: dup
       4: invokespecial #143                // Method java/util/HashMap."<init>":()V
       7: astore_1
       8: aload_0
       9: ifnull        85
      12: aload_0
      13: invokevirtual #184                // Method java/lang/Class.getDeclaredMethods:()[Ljava/lang/reflect/Method;
      16: astore_2
      17: aload_2
      18: astore_3
      19: aload_3
      20: arraylength
      21: istore        4
      23: iconst_0
      24: istore        5
      26: iload         5
      28: iload         4
      30: if_icmpge     77
      33: aload_3
      34: iload         5
      36: aaload
      37: astore        6
      39: aload         6
      41: invokestatic  #175                // Method isBeanPropertyReadMethod:(Ljava/lang/reflect/Method;)Z
      44: ifeq          71
      47: aload         6
      49: iconst_1
      50: invokevirtual #185                // Method java/lang/reflect/Method.setAccessible:(Z)V
      53: aload         6
      55: invokestatic  #186                // Method getPropertyNameFromBeanReadMethod:(Ljava/lang/reflect/Method;)Ljava/lang/String;
      58: astore        7
      60: aload_1
      61: aload         7
      63: aload         6
      65: invokeinterface #161,  3          // InterfaceMethod java/util/Map.put:(Ljava/lang/Object;Ljava/lang/Object;)Ljava/lang/Object;
      70: pop
      71: iinc          5, 1
      74: goto          26
      77: aload_0
      78: invokevirtual #141                // Method java/lang/Class.getSuperclass:()Ljava/lang/Class;
      81: astore_0
      82: goto          8
      85: aload_1
      86: areturn

  public static java.lang.reflect.Type[] getReturnTypes(java.lang.reflect.Method);
    Code:
       0: aload_0
       1: invokevirtual #53                 // Method java/lang/reflect/Method.getReturnType:()Ljava/lang/Class;
       4: astore_1
       5: aload_0
       6: invokevirtual #187                // Method java/lang/reflect/Method.getGenericReturnType:()Ljava/lang/reflect/Type;
       9: astore_2
      10: ldc           #188                // class java/util/concurrent/Future
      12: aload_1
      13: invokevirtual #11                 // Method java/lang/Class.isAssignableFrom:(Ljava/lang/Class;)Z
      16: ifeq          104
      19: aload_2
      20: instanceof    #43                 // class java/lang/reflect/ParameterizedType
      23: ifeq          100
      26: aload_2
      27: checkcast     #43                 // class java/lang/reflect/ParameterizedType
      30: invokeinterface #44,  1           // InterfaceMethod java/lang/reflect/ParameterizedType.getActualTypeArguments:()[Ljava/lang/reflect/Type;
      35: iconst_0
      36: aaload
      37: astore_3
      38: aload_3
      39: instanceof    #43                 // class java/lang/reflect/ParameterizedType
      42: ifeq          63
      45: aload_3
      46: checkcast     #43                 // class java/lang/reflect/ParameterizedType
      49: invokeinterface #45,  1           // InterfaceMethod java/lang/reflect/ParameterizedType.getRawType:()Ljava/lang/reflect/Type;
      54: checkcast     #46                 // class java/lang/Class
      57: astore_1
      58: aload_3
      59: astore_2
      60: goto          97
      63: aload_3
      64: instanceof    #189                // class java/lang/reflect/TypeVariable
      67: ifeq          90
      70: aload_3
      71: checkcast     #189                // class java/lang/reflect/TypeVariable
      74: invokeinterface #190,  1          // InterfaceMethod java/lang/reflect/TypeVariable.getBounds:()[Ljava/lang/reflect/Type;
      79: iconst_0
      80: aaload
      81: checkcast     #46                 // class java/lang/Class
      84: astore_1
      85: aload_3
      86: astore_2
      87: goto          97
      90: aload_3
      91: checkcast     #46                 // class java/lang/Class
      94: astore_1
      95: aload_1
      96: astore_2
      97: goto          104
     100: aconst_null
     101: astore_1
     102: aconst_null
     103: astore_2
     104: iconst_2
     105: anewarray     #191                // class java/lang/reflect/Type
     108: dup
     109: iconst_0
     110: aload_1
     111: aastore
     112: dup
     113: iconst_1
     114: aload_2
     115: aastore
     116: areturn

  public static java.util.Set<java.lang.reflect.ParameterizedType> findParameterizedTypes(java.lang.Class<?>);
    Code:
       0: new           #192                // class java/util/LinkedList
       3: dup
       4: aload_0
       5: invokevirtual #42                 // Method java/lang/Class.getGenericInterfaces:()[Ljava/lang/reflect/Type;
       8: invokestatic  #193                // Method java/util/Arrays.asList:([Ljava/lang/Object;)Ljava/util/List;
      11: invokespecial #194                // Method java/util/LinkedList."<init>":(Ljava/util/Collection;)V
      14: astore_1
      15: aload_1
      16: aload_0
      17: invokevirtual #195                // Method java/lang/Class.getGenericSuperclass:()Ljava/lang/reflect/Type;
      20: invokeinterface #113,  2          // InterfaceMethod java/util/List.add:(Ljava/lang/Object;)Z
      25: pop
      26: aload_1
      27: invokeinterface #196,  1          // InterfaceMethod java/util/List.stream:()Ljava/util/stream/Stream;
      32: invokedynamic #197,  0            // InvokeDynamic #0:test:()Ljava/util/function/Predicate;
      37: invokeinterface #198,  2          // InterfaceMethod java/util/stream/Stream.filter:(Ljava/util/function/Predicate;)Ljava/util/stream/Stream;
      42: ldc           #43                 // class java/lang/reflect/ParameterizedType
      44: dup
      45: invokevirtual #28                 // Method java/lang/Object.getClass:()Ljava/lang/Class;
      48: pop
      49: invokedynamic #199,  0            // InvokeDynamic #1:apply:(Ljava/lang/Class;)Ljava/util/function/Function;
      54: invokeinterface #200,  2          // InterfaceMethod java/util/stream/Stream.map:(Ljava/util/function/Function;)Ljava/util/stream/Stream;
      59: invokestatic  #201                // Method java/util/stream/Collectors.toSet:()Ljava/util/stream/Collector;
      62: invokeinterface #202,  2          // InterfaceMethod java/util/stream/Stream.collect:(Ljava/util/stream/Collector;)Ljava/lang/Object;
      67: checkcast     #203                // class java/util/Set
      70: astore_2
      71: aload_2
      72: invokeinterface #204,  1          // InterfaceMethod java/util/Set.isEmpty:()Z
      77: ifeq          124
      80: aload_1
      81: invokeinterface #196,  1          // InterfaceMethod java/util/List.stream:()Ljava/util/stream/Stream;
      86: invokedynamic #205,  0            // InvokeDynamic #2:test:()Ljava/util/function/Predicate;
      91: invokeinterface #198,  2          // InterfaceMethod java/util/stream/Stream.filter:(Ljava/util/function/Predicate;)Ljava/util/stream/Stream;
      96: ldc           #46                 // class java/lang/Class
      98: dup
      99: invokevirtual #28                 // Method java/lang/Object.getClass:()Ljava/lang/Class;
     102: pop
     103: invokedynamic #206,  0            // InvokeDynamic #3:apply:(Ljava/lang/Class;)Ljava/util/function/Function;
     108: invokeinterface #200,  2          // InterfaceMethod java/util/stream/Stream.map:(Ljava/util/function/Function;)Ljava/util/stream/Stream;
     113: aload_2
     114: invokedynamic #207,  0            // InvokeDynamic #4:accept:(Ljava/util/Set;)Ljava/util/function/Consumer;
     119: invokeinterface #208,  2          // InterfaceMethod java/util/stream/Stream.forEach:(Ljava/util/function/Consumer;)V
     124: aload_2
     125: invokestatic  #209                // Method java/util/Collections.unmodifiableSet:(Ljava/util/Set;)Ljava/util/Set;
     128: areturn

  public static <T> java.util.Set<java.lang.Class<T>> findHierarchicalTypes(java.lang.Class<?>, java.lang.Class<T>);
    Code:
       0: aload_0
       1: ifnonnull     8
       4: invokestatic  #210                // Method java/util/Collections.emptySet:()Ljava/util/Set;
       7: areturn
       8: new           #211                // class java/util/LinkedHashSet
      11: dup
      12: invokespecial #212                // Method java/util/LinkedHashSet."<init>":()V
      15: astore_2
      16: aload_1
      17: aload_0
      18: invokevirtual #11                 // Method java/lang/Class.isAssignableFrom:(Ljava/lang/Class;)Z
      21: ifeq          32
      24: aload_2
      25: aload_0
      26: invokeinterface #213,  2          // InterfaceMethod java/util/Set.add:(Ljava/lang/Object;)Z
      31: pop
      32: aload_2
      33: aload_0
      34: invokevirtual #141                // Method java/lang/Class.getSuperclass:()Ljava/lang/Class;
      37: aload_1
      38: invokestatic  #214                // Method findHierarchicalTypes:(Ljava/lang/Class;Ljava/lang/Class;)Ljava/util/Set;
      41: invokeinterface #215,  2          // InterfaceMethod java/util/Set.addAll:(Ljava/util/Collection;)Z
      46: pop
      47: aload_2
      48: invokestatic  #209                // Method java/util/Collections.unmodifiableSet:(Ljava/util/Set;)Ljava/util/Set;
      51: areturn

  public static <T> T getProperty(java.lang.Object, java.lang.String);
    Code:
       0: aload_0
       1: invokevirtual #28                 // Method java/lang/Object.getClass:()Ljava/lang/Class;
       4: astore_2
       5: aconst_null
       6: astore_3
       7: aconst_null
       8: astore        4
      10: aload_2
      11: invokestatic  #216                // Method java/beans/Introspector.getBeanInfo:(Ljava/lang/Class;)Ljava/beans/BeanInfo;
      14: astore_3
      15: aload_3
      16: invokeinterface #217,  1          // InterfaceMethod java/beans/BeanInfo.getMethodDescriptors:()[Ljava/beans/MethodDescriptor;
      21: invokestatic  #218                // InterfaceMethod java/util/stream/Stream.of:([Ljava/lang/Object;)Ljava/util/stream/Stream;
      24: aload_1
      25: invokedynamic #219,  0            // InvokeDynamic #5:test:(Ljava/lang/String;)Ljava/util/function/Predicate;
      30: invokeinterface #198,  2          // InterfaceMethod java/util/stream/Stream.filter:(Ljava/util/function/Predicate;)Ljava/util/stream/Stream;
      35: invokeinterface #220,  1          // InterfaceMethod java/util/stream/Stream.findFirst:()Ljava/util/Optional;
      40: aload_0
      41: invokedynamic #221,  0            // InvokeDynamic #6:apply:(Ljava/lang/Object;)Ljava/util/function/Function;
      46: invokevirtual #222                // Method java/util/Optional.map:(Ljava/util/function/Function;)Ljava/util/Optional;
      49: invokevirtual #223                // Method java/util/Optional.get:()Ljava/lang/Object;
      52: astore        4
      54: goto          59
      57: astore        5
      59: aload         4
      61: areturn
    Exception table:
       from    to  target type
          10    54    57   Class java/lang/Exception

  public static boolean hasMethod(java.lang.Class<?>, java.lang.String);
    Code:
       0: aload_0
       1: invokestatic  #216                // Method java/beans/Introspector.getBeanInfo:(Ljava/lang/Class;)Ljava/beans/BeanInfo;
       4: astore_2
       5: aload_2
       6: invokeinterface #217,  1          // InterfaceMethod java/beans/BeanInfo.getMethodDescriptors:()[Ljava/beans/MethodDescriptor;
      11: invokestatic  #218                // InterfaceMethod java/util/stream/Stream.of:([Ljava/lang/Object;)Ljava/util/stream/Stream;
      14: aload_1
      15: invokedynamic #225,  0            // InvokeDynamic #7:test:(Ljava/lang/String;)Ljava/util/function/Predicate;
      20: invokeinterface #198,  2          // InterfaceMethod java/util/stream/Stream.filter:(Ljava/util/function/Predicate;)Ljava/util/stream/Stream;
      25: invokeinterface #220,  1          // InterfaceMethod java/util/stream/Stream.findFirst:()Ljava/util/Optional;
      30: astore_3
      31: aload_3
      32: invokevirtual #226                // Method java/util/Optional.isPresent:()Z
      35: ireturn
      36: astore_2
      37: iconst_0
      38: ireturn
    Exception table:
       from    to  target type
           0    35    36   Class java/lang/Exception

  public static java.lang.Class[] resolveTypes(java.lang.Object...);
    Code:
       0: aload_0
       1: invokestatic  #227                // Method org/apache/dubbo/common/utils/ArrayUtils.isEmpty:([Ljava/lang/Object;)Z
       4: ifeq          11
       7: getstatic     #106                // Field EMPTY_CLASS_ARRAY:[Ljava/lang/Class;
      10: areturn
      11: aload_0
      12: arraylength
      13: istore_1
      14: iload_1
      15: anewarray     #46                 // class java/lang/Class
      18: astore_2
      19: iconst_0
      20: istore_3
      21: iload_3
      22: iload_1
      23: if_icmpge     54
      26: aload_0
      27: iload_3
      28: aaload
      29: astore        4
      31: aload_2
      32: iload_3
      33: aload         4
      35: ifnonnull     42
      38: aconst_null
      39: goto          47
      42: aload         4
      44: invokevirtual #28                 // Method java/lang/Object.getClass:()Ljava/lang/Class;
      47: aastore
      48: iinc          3, 1
      51: goto          21
      54: aload_2
      55: areturn

  public static boolean checkZeroArgConstructor(java.lang.Class);
    Code:
       0: aload_0
       1: iconst_0
       2: anewarray     #46                 // class java/lang/Class
       5: invokevirtual #159                // Method java/lang/Class.getDeclaredConstructor:([Ljava/lang/Class;)Ljava/lang/reflect/Constructor;
       8: pop
       9: iconst_1
      10: ireturn
      11: astore_1
      12: iconst_0
      13: ireturn
    Exception table:
       from    to  target type
           0    10    11   Class java/lang/NoSuchMethodException

  public static boolean isJdk(java.lang.Class);
    Code:
       0: aload_0
       1: invokevirtual #39                 // Method java/lang/Class.getName:()Ljava/lang/String;
       4: ldc           #228                // String java.
       6: invokevirtual #173                // Method java/lang/String.startsWith:(Ljava/lang/String;)Z
       9: ifne          24
      12: aload_0
      13: invokevirtual #39                 // Method java/lang/Class.getName:()Ljava/lang/String;
      16: ldc           #229                // String javax.
      18: invokevirtual #173                // Method java/lang/String.startsWith:(Ljava/lang/String;)Z
      21: ifeq          28
      24: iconst_1
      25: goto          29
      28: iconst_0
      29: ireturn

  public static void makeAccessible(java.lang.reflect.Method);
    Code:
       0: aload_0
       1: invokevirtual #169                // Method java/lang/reflect/Method.getModifiers:()I
       4: invokestatic  #138                // Method java/lang/reflect/Modifier.isPublic:(I)Z
       7: ifeq          23
      10: aload_0
      11: invokevirtual #171                // Method java/lang/reflect/Method.getDeclaringClass:()Ljava/lang/Class;
      14: invokevirtual #230                // Method java/lang/Class.getModifiers:()I
      17: invokestatic  #138                // Method java/lang/reflect/Modifier.isPublic:(I)Z
      20: ifne          35
      23: aload_0
      24: invokevirtual #231                // Method java/lang/reflect/Method.isAccessible:()Z
      27: ifne          35
      30: aload_0
      31: iconst_1
      32: invokevirtual #185                // Method java/lang/reflect/Method.setAccessible:(Z)V
      35: return

  public static java.util.Set<java.lang.String> getAllFieldNames(java.lang.Class<?>);
    Code:
       0: new           #154                // class java/util/HashSet
       3: dup
       4: invokespecial #232                // Method java/util/HashSet."<init>":()V
       7: astore_1
       8: aload_0
       9: invokevirtual #162                // Method java/lang/Class.getDeclaredFields:()[Ljava/lang/reflect/Field;
      12: astore_2
      13: aload_2
      14: arraylength
      15: istore_3
      16: iconst_0
      17: istore        4
      19: iload         4
      21: iload_3
      22: if_icmpge     49
      25: aload_2
      26: iload         4
      28: aaload
      29: astore        5
      31: aload_1
      32: aload         5
      34: invokevirtual #183                // Method java/lang/reflect/Field.getName:()Ljava/lang/String;
      37: invokeinterface #213,  2          // InterfaceMethod java/util/Set.add:(Ljava/lang/Object;)Z
      42: pop
      43: iinc          4, 1
      46: goto          19
      49: aload_0
      50: iconst_0
      51: anewarray     #233                // class java/util/function/Predicate
      54: invokestatic  #234                // Method org/apache/dubbo/common/utils/ClassUtils.getAllSuperClasses:(Ljava/lang/Class;[Ljava/util/function/Predicate;)Ljava/util/Set;
      57: astore_2
      58: aload_2
      59: invokeinterface #235,  1          // InterfaceMethod java/util/Set.iterator:()Ljava/util/Iterator;
      64: astore_3
      65: aload_3
      66: invokeinterface #236,  1          // InterfaceMethod java/util/Iterator.hasNext:()Z
      71: ifeq          135
      74: aload_3
      75: invokeinterface #237,  1          // InterfaceMethod java/util/Iterator.next:()Ljava/lang/Object;
      80: checkcast     #46                 // class java/lang/Class
      83: astore        4
      85: aload         4
      87: invokevirtual #162                // Method java/lang/Class.getDeclaredFields:()[Ljava/lang/reflect/Field;
      90: astore        5
      92: aload         5
      94: arraylength
      95: istore        6
      97: iconst_0
      98: istore        7
     100: iload         7
     102: iload         6
     104: if_icmpge     132
     107: aload         5
     109: iload         7
     111: aaload
     112: astore        8
     114: aload_1
     115: aload         8
     117: invokevirtual #183                // Method java/lang/reflect/Field.getName:()Ljava/lang/String;
     120: invokeinterface #213,  2          // InterfaceMethod java/util/Set.add:(Ljava/lang/Object;)Z
     125: pop
     126: iinc          7, 1
     129: goto          100
     132: goto          65
     135: aload_1
     136: areturn

  public static <T> T getFieldValue(java.lang.Object, java.lang.String) throws java.lang.RuntimeException;
    Code:
       0: aload_0
       1: ifnonnull     14
       4: new           #50                 // class java/lang/IllegalArgumentException
       7: dup
       8: ldc           #238                // String object is null
      10: invokespecial #239                // Method java/lang/IllegalArgumentException."<init>":(Ljava/lang/String;)V
      13: athrow
      14: aload_0
      15: invokevirtual #28                 // Method java/lang/Object.getClass:()Ljava/lang/Class;
      18: aload_1
      19: invokevirtual #240                // Method java/lang/Class.getDeclaredField:(Ljava/lang/String;)Ljava/lang/reflect/Field;
      22: astore_2
      23: aload_2
      24: iconst_1
      25: invokevirtual #166                // Method java/lang/reflect/Field.setAccessible:(Z)V
      28: aload_2
      29: aload_0
      30: invokevirtual #241                // Method java/lang/reflect/Field.get:(Ljava/lang/Object;)Ljava/lang/Object;
      33: areturn
      34: astore_2
      35: new           #89                 // class java/lang/RuntimeException
      38: dup
      39: aload_2
      40: invokevirtual #242                // Method java/lang/Exception.getMessage:()Ljava/lang/String;
      43: aload_2
      44: invokespecial #243                // Method java/lang/RuntimeException."<init>":(Ljava/lang/String;Ljava/lang/Throwable;)V
      47: athrow
    Exception table:
       from    to  target type
          14    33    34   Class java/lang/Exception

  private static boolean lambda$hasMethod$5(java.lang.String, java.beans.MethodDescriptor);
    Code:
       0: aload_0
       1: aload_1
       2: invokevirtual #244                // Method java/beans/MethodDescriptor.getName:()Ljava/lang/String;
       5: invokevirtual #62                 // Method java/lang/String.equals:(Ljava/lang/Object;)Z
       8: ireturn

  private static java.lang.Object lambda$getProperty$4(java.lang.Object, java.beans.MethodDescriptor);
    Code:
       0: aload_1
       1: invokevirtual #245                // Method java/beans/MethodDescriptor.getMethod:()Ljava/lang/reflect/Method;
       4: aload_0
       5: iconst_0
       6: anewarray     #127                // class java/lang/Object
       9: invokevirtual #246                // Method java/lang/reflect/Method.invoke:(Ljava/lang/Object;[Ljava/lang/Object;)Ljava/lang/Object;
      12: areturn
      13: astore_2
      14: aconst_null
      15: areturn
    Exception table:
       from    to  target type
           0    12    13   Class java/lang/Exception

  private static boolean lambda$getProperty$3(java.lang.String, java.beans.MethodDescriptor);
    Code:
       0: aload_0
       1: aload_1
       2: invokevirtual #244                // Method java/beans/MethodDescriptor.getName:()Ljava/lang/String;
       5: invokevirtual #62                 // Method java/lang/String.equals:(Ljava/lang/Object;)Z
       8: ireturn

  private static void lambda$findParameterizedTypes$2(java.util.Set, java.lang.Class);
    Code:
       0: aload_0
       1: aload_1
       2: invokestatic  #247                // Method findParameterizedTypes:(Ljava/lang/Class;)Ljava/util/Set;
       5: invokeinterface #215,  2          // InterfaceMethod java/util/Set.addAll:(Ljava/util/Collection;)Z
      10: pop
      11: return

  private static boolean lambda$findParameterizedTypes$1(java.lang.reflect.Type);
    Code:
       0: aload_0
       1: instanceof    #46                 // class java/lang/Class
       4: ireturn

  private static boolean lambda$findParameterizedTypes$0(java.lang.reflect.Type);
    Code:
       0: aload_0
       1: instanceof    #43                 // class java/lang/reflect/ParameterizedType
       4: ireturn

  static {};
    Code:
       0: iconst_0
       1: anewarray     #46                 // class java/lang/Class
       4: putstatic     #106                // Field EMPTY_CLASS_ARRAY:[Ljava/lang/Class;
       7: ldc           #248                // String (?:(?:[VZBCDFIJS])|(?:L(?:[_$a-zA-Z][_$a-zA-Z0-9]*)(?:\\/(?:[_$a-zA-Z][_$a-zA-Z0-9]*))*;)|(?:\\[+(?:(?:[VZBCDFIJS])|(?:L(?:[_$a-zA-Z][_$a-zA-Z0-9]*)(?:\\/(?:[_$a-zA-Z][_$a-zA-Z0-9]*))*;))))
       9: invokestatic  #249                // Method java/util/regex/Pattern.compile:(Ljava/lang/String;)Ljava/util/regex/Pattern;
      12: putstatic     #109                // Field DESC_PATTERN:Ljava/util/regex/Pattern;
      15: ldc           #250                // String (?:((?:[_$a-zA-Z][_$a-zA-Z0-9]*))?\\(((?:(?:[VZBCDFIJS])|(?:L(?:[_$a-zA-Z][_$a-zA-Z0-9]*)(?:\\/(?:[_$a-zA-Z][_$a-zA-Z0-9]*))*;)|(?:\\[+(?:(?:[VZBCDFIJS])|(?:L(?:[_$a-zA-Z][_$a-zA-Z0-9]*)(?:\\/(?:[_$a-zA-Z][_$a-zA-Z0-9]*))*;))))*)\\)((?:(?:[VZBCDFIJS])|(?:L(?:[_$a-zA-Z][_$a-zA-Z0-9]*)(?:\\/(?:[_$a-zA-Z][_$a-zA-Z0-9]*))*;)|(?:\\[+(?:(?:[VZBCDFIJS])|(?:L(?:[_$a-zA-Z][_$a-zA-Z0-9]*)(?:\\/(?:[_$a-zA-Z][_$a-zA-Z0-9]*))*;)))))?)
      17: invokestatic  #249                // Method java/util/regex/Pattern.compile:(Ljava/lang/String;)Ljava/util/regex/Pattern;
      20: putstatic     #251                // Field METHOD_DESC_PATTERN:Ljava/util/regex/Pattern;
      23: ldc           #252                // String get([A-Z][_a-zA-Z0-9]*)\\(\\)((?:(?:[VZBCDFIJS])|(?:L(?:[_$a-zA-Z][_$a-zA-Z0-9]*)(?:\\/(?:[_$a-zA-Z][_$a-zA-Z0-9]*))*;)|(?:\\[+(?:(?:[VZBCDFIJS])|(?:L(?:[_$a-zA-Z][_$a-zA-Z0-9]*)(?:\\/(?:[_$a-zA-Z][_$a-zA-Z0-9]*))*;)))))
      25: invokestatic  #249                // Method java/util/regex/Pattern.compile:(Ljava/lang/String;)Ljava/util/regex/Pattern;
      28: putstatic     #253                // Field GETTER_METHOD_DESC_PATTERN:Ljava/util/regex/Pattern;
      31: ldc           #254                // String set([A-Z][_a-zA-Z0-9]*)\\(((?:(?:[VZBCDFIJS])|(?:L(?:[_$a-zA-Z][_$a-zA-Z0-9]*)(?:\\/(?:[_$a-zA-Z][_$a-zA-Z0-9]*))*;)|(?:\\[+(?:(?:[VZBCDFIJS])|(?:L(?:[_$a-zA-Z][_$a-zA-Z0-9]*)(?:\\/(?:[_$a-zA-Z][_$a-zA-Z0-9]*))*;)))))\\)V
      33: invokestatic  #249                // Method java/util/regex/Pattern.compile:(Ljava/lang/String;)Ljava/util/regex/Pattern;
      36: putstatic     #255                // Field SETTER_METHOD_DESC_PATTERN:Ljava/util/regex/Pattern;
      39: ldc_w         #256                // String (?:is|has|can)([A-Z][_a-zA-Z0-9]*)\\(\\)Z
      42: invokestatic  #249                // Method java/util/regex/Pattern.compile:(Ljava/lang/String;)Ljava/util/regex/Pattern;
      45: putstatic     #257                // Field IS_HAS_CAN_METHOD_DESC_PATTERN:Ljava/util/regex/Pattern;
      48: new           #142                // class java/util/HashMap
      51: dup
      52: invokespecial #143                // Method java/util/HashMap."<init>":()V
      55: putstatic     #168                // Field primitiveDefaults:Ljava/util/Map;
      58: getstatic     #168                // Field primitiveDefaults:Ljava/util/Map;
      61: getstatic     #13                 // Field java/lang/Integer.TYPE:Ljava/lang/Class;
      64: iconst_0
      65: invokestatic  #128                // Method java/lang/Integer.valueOf:(I)Ljava/lang/Integer;
      68: invokeinterface #161,  3          // InterfaceMethod java/util/Map.put:(Ljava/lang/Object;Ljava/lang/Object;)Ljava/lang/Object;
      73: pop
      74: getstatic     #168                // Field primitiveDefaults:Ljava/util/Map;
      77: getstatic     #16                 // Field java/lang/Long.TYPE:Ljava/lang/Class;
      80: lconst_0
      81: invokestatic  #149                // Method java/lang/Long.valueOf:(J)Ljava/lang/Long;
      84: invokeinterface #161,  3          // InterfaceMethod java/util/Map.put:(Ljava/lang/Object;Ljava/lang/Object;)Ljava/lang/Object;
      89: pop
      90: getstatic     #168                // Field primitiveDefaults:Ljava/util/Map;
      93: getstatic     #23                 // Field java/lang/Byte.TYPE:Ljava/lang/Class;
      96: iconst_0
      97: invokestatic  #147                // Method java/lang/Byte.valueOf:(B)Ljava/lang/Byte;
     100: invokeinterface #161,  3          // InterfaceMethod java/util/Map.put:(Ljava/lang/Object;Ljava/lang/Object;)Ljava/lang/Object;
     105: pop
     106: getstatic     #168                // Field primitiveDefaults:Ljava/util/Map;
     109: getstatic     #22                 // Field java/lang/Character.TYPE:Ljava/lang/Class;
     112: iconst_0
     113: invokestatic  #146                // Method java/lang/Character.valueOf:(C)Ljava/lang/Character;
     116: invokeinterface #161,  3          // InterfaceMethod java/util/Map.put:(Ljava/lang/Object;Ljava/lang/Object;)Ljava/lang/Object;
     121: pop
     122: getstatic     #168                // Field primitiveDefaults:Ljava/util/Map;
     125: getstatic     #25                 // Field java/lang/Short.TYPE:Ljava/lang/Class;
     128: iconst_0
     129: invokestatic  #148                // Method java/lang/Short.valueOf:(S)Ljava/lang/Short;
     132: invokeinterface #161,  3          // InterfaceMethod java/util/Map.put:(Ljava/lang/Object;Ljava/lang/Object;)Ljava/lang/Object;
     137: pop
     138: getstatic     #168                // Field primitiveDefaults:Ljava/util/Map;
     141: getstatic     #18                 // Field java/lang/Float.TYPE:Ljava/lang/Class;
     144: fconst_0
     145: invokestatic  #150                // Method java/lang/Float.valueOf:(F)Ljava/lang/Float;
     148: invokeinterface #161,  3          // InterfaceMethod java/util/Map.put:(Ljava/lang/Object;Ljava/lang/Object;)Ljava/lang/Object;
     153: pop
     154: getstatic     #168                // Field primitiveDefaults:Ljava/util/Map;
     157: getstatic     #20                 // Field java/lang/Double.TYPE:Ljava/lang/Class;
     160: dconst_0
     161: invokestatic  #151                // Method java/lang/Double.valueOf:(D)Ljava/lang/Double;
     164: invokeinterface #161,  3          // InterfaceMethod java/util/Map.put:(Ljava/lang/Object;Ljava/lang/Object;)Ljava/lang/Object;
     169: pop
     170: getstatic     #168                // Field primitiveDefaults:Ljava/util/Map;
     173: getstatic     #15                 // Field java/lang/Boolean.TYPE:Ljava/lang/Class;
     176: iconst_0
     177: invokestatic  #145                // Method java/lang/Boolean.valueOf:(Z)Ljava/lang/Boolean;
     180: invokeinterface #161,  3          // InterfaceMethod java/util/Map.put:(Ljava/lang/Object;Ljava/lang/Object;)Ljava/lang/Object;
     185: pop
     186: getstatic     #168                // Field primitiveDefaults:Ljava/util/Map;
     189: getstatic     #100                // Field java/lang/Void.TYPE:Ljava/lang/Class;
     192: aconst_null
     193: invokeinterface #161,  3          // InterfaceMethod java/util/Map.put:(Ljava/lang/Object;Ljava/lang/Object;)Ljava/lang/Object;
     198: pop
     199: return
}
