Compiled from "RegexProperties.java"
public class org.apache.dubbo.common.utils.RegexProperties extends java.util.Properties {
  public org.apache.dubbo.common.utils.RegexProperties();
    Code:
       0: aload_0
       1: invokespecial #1                  // Method java/util/Properties."<init>":()V
       4: return

  public java.lang.String getProperty(java.lang.String);
    Code:
       0: aload_0
       1: aload_1
       2: invokespecial #2                  // Method java/util/Properties.getProperty:(Ljava/lang/String;)Ljava/lang/String;
       5: astore_2
       6: aload_2
       7: ifnull        12
      10: aload_2
      11: areturn
      12: aload_0
      13: invokevirtual #3                  // Method keySet:()Ljava/util/Set;
      16: invokeinterface #4,  1            // InterfaceMethod java/util/Set.stream:()Ljava/util/stream/Stream;
      21: invokedynamic #5,  0              // InvokeDynamic #0:apply:()Ljava/util/function/Function;
      26: invokeinterface #6,  2            // InterfaceMethod java/util/stream/Stream.map:(Ljava/util/function/Function;)Ljava/util/stream/Stream;
      31: invokestatic  #7                  // InterfaceMethod java/util/Comparator.reverseOrder:()Ljava/util/Comparator;
      34: invokeinterface #8,  2            // InterfaceMethod java/util/stream/Stream.sorted:(Ljava/util/Comparator;)Ljava/util/stream/Stream;
      39: invokestatic  #9                  // Method java/util/stream/Collectors.toList:()Ljava/util/stream/Collector;
      42: invokeinterface #10,  2           // InterfaceMethod java/util/stream/Stream.collect:(Ljava/util/stream/Collector;)Ljava/lang/Object;
      47: checkcast     #11                 // class java/util/List
      50: astore_3
      51: aload_3
      52: invokeinterface #12,  1           // InterfaceMethod java/util/List.stream:()Ljava/util/stream/Stream;
      57: aload_1
      58: invokedynamic #13,  0             // InvokeDynamic #1:test:(Ljava/lang/String;)Ljava/util/function/Predicate;
      63: invokeinterface #14,  2           // InterfaceMethod java/util/stream/Stream.filter:(Ljava/util/function/Predicate;)Ljava/util/stream/Stream;
      68: invokeinterface #15,  1           // InterfaceMethod java/util/stream/Stream.findFirst:()Ljava/util/Optional;
      73: aconst_null
      74: invokevirtual #16                 // Method java/util/Optional.orElse:(Ljava/lang/Object;)Ljava/lang/Object;
      77: checkcast     #17                 // class java/lang/String
      80: astore        4
      82: aload         4
      84: ifnonnull     91
      87: aconst_null
      88: goto          97
      91: aload_0
      92: aload         4
      94: invokespecial #2                  // Method java/util/Properties.getProperty:(Ljava/lang/String;)Ljava/lang/String;
      97: areturn

  private static boolean lambda$getProperty$1(java.lang.String, java.lang.String);
    Code:
       0: aload_1
       1: astore_2
       2: aload_2
       3: ldc           #19                 // String *
       5: invokevirtual #20                 // Method java/lang/String.startsWith:(Ljava/lang/String;)Z
       8: ifeq          31
      11: new           #21                 // class java/lang/StringBuilder
      14: dup
      15: invokespecial #22                 // Method java/lang/StringBuilder."<init>":()V
      18: ldc           #23                 // String .
      20: invokevirtual #24                 // Method java/lang/StringBuilder.append:(Ljava/lang/String;)Ljava/lang/StringBuilder;
      23: aload_2
      24: invokevirtual #24                 // Method java/lang/StringBuilder.append:(Ljava/lang/String;)Ljava/lang/StringBuilder;
      27: invokevirtual #25                 // Method java/lang/StringBuilder.toString:()Ljava/lang/String;
      30: astore_2
      31: aload_2
      32: aload_0
      33: invokestatic  #26                 // Method java/util/regex/Pattern.matches:(Ljava/lang/String;Ljava/lang/CharSequence;)Z
      36: ireturn

  private static java.lang.String lambda$getProperty$0(java.lang.Object);
    Code:
       0: aload_0
       1: checkcast     #17                 // class java/lang/String
       4: areturn
}
