Compiled from "SerializeCheckStatus.java"
public final class org.apache.dubbo.common.utils.SerializeCheckStatus extends java.lang.Enum<org.apache.dubbo.common.utils.SerializeCheckStatus> {
  public static final org.apache.dubbo.common.utils.SerializeCheckStatus DISABLE;

  public static final org.apache.dubbo.common.utils.SerializeCheckStatus WARN;

  public static final org.apache.dubbo.common.utils.SerializeCheckStatus STRICT;

  private final int level;

  private static final org.apache.dubbo.common.utils.SerializeCheckStatus[] $VALUES;

  public static org.apache.dubbo.common.utils.SerializeCheckStatus[] values();
    Code:
       0: getstatic     #1                  // Field $VALUES:[Lorg/apache/dubbo/common/utils/SerializeCheckStatus;
       3: invokevirtual #2                  // Method "[Lorg/apache/dubbo/common/utils/SerializeCheckStatus;".clone:()Ljava/lang/Object;
       6: checkcast     #3                  // class "[Lorg/apache/dubbo/common/utils/SerializeCheckStatus;"
       9: areturn

  public static org.apache.dubbo.common.utils.SerializeCheckStatus valueOf(java.lang.String);
    Code:
       0: ldc           #4                  // class org/apache/dubbo/common/utils/SerializeCheckStatus
       2: aload_0
       3: invokestatic  #5                  // Method java/lang/Enum.valueOf:(Ljava/lang/Class;Ljava/lang/String;)Ljava/lang/Enum;
       6: checkcast     #4                  // class org/apache/dubbo/common/utils/SerializeCheckStatus
       9: areturn

  private org.apache.dubbo.common.utils.SerializeCheckStatus(int);
    Code:
       0: aload_0
       1: aload_1
       2: iload_2
       3: invokespecial #6                  // Method java/lang/Enum."<init>":(Ljava/lang/String;I)V
       6: aload_0
       7: iload_3
       8: putfield      #7                  // Field level:I
      11: return

  public int level();
    Code:
       0: aload_0
       1: getfield      #7                  // Field level:I
       4: ireturn

  static {};
    Code:
       0: new           #4                  // class org/apache/dubbo/common/utils/SerializeCheckStatus
       3: dup
       4: ldc           #8                  // String DISABLE
       6: iconst_0
       7: iconst_0
       8: invokespecial #9                  // Method "<init>":(Ljava/lang/String;II)V
      11: putstatic     #10                 // Field DISABLE:Lorg/apache/dubbo/common/utils/SerializeCheckStatus;
      14: new           #4                  // class org/apache/dubbo/common/utils/SerializeCheckStatus
      17: dup
      18: ldc           #11                 // String WARN
      20: iconst_1
      21: iconst_1
      22: invokespecial #9                  // Method "<init>":(Ljava/lang/String;II)V
      25: putstatic     #12                 // Field WARN:Lorg/apache/dubbo/common/utils/SerializeCheckStatus;
      28: new           #4                  // class org/apache/dubbo/common/utils/SerializeCheckStatus
      31: dup
      32: ldc           #13                 // String STRICT
      34: iconst_2
      35: iconst_2
      36: invokespecial #9                  // Method "<init>":(Ljava/lang/String;II)V
      39: putstatic     #14                 // Field STRICT:Lorg/apache/dubbo/common/utils/SerializeCheckStatus;
      42: iconst_3
      43: anewarray     #4                  // class org/apache/dubbo/common/utils/SerializeCheckStatus
      46: dup
      47: iconst_0
      48: getstatic     #10                 // Field DISABLE:Lorg/apache/dubbo/common/utils/SerializeCheckStatus;
      51: aastore
      52: dup
      53: iconst_1
      54: getstatic     #12                 // Field WARN:Lorg/apache/dubbo/common/utils/SerializeCheckStatus;
      57: aastore
      58: dup
      59: iconst_2
      60: getstatic     #14                 // Field STRICT:Lorg/apache/dubbo/common/utils/SerializeCheckStatus;
      63: aastore
      64: putstatic     #1                  // Field $VALUES:[Lorg/apache/dubbo/common/utils/SerializeCheckStatus;
      67: return
}
