Compiled from "SerializeSecurityConfigurator.java"
public class org.apache.dubbo.common.utils.SerializeSecurityConfigurator implements org.apache.dubbo.rpc.model.ScopeClassLoaderListener<org.apache.dubbo.rpc.model.ModuleModel> {
  private final org.apache.dubbo.common.utils.SerializeSecurityManager serializeSecurityManager;

  private static final org.apache.dubbo.common.logger.ErrorTypeAwareLogger logger;

  private final org.apache.dubbo.rpc.model.ModuleModel moduleModel;

  private volatile boolean autoTrustSerializeClass;

  private volatile int trustSerializeClassLevel;

  public org.apache.dubbo.common.utils.SerializeSecurityConfigurator(org.apache.dubbo.rpc.model.ModuleModel);
    Code:
       0: aload_0
       1: invokespecial #3                  // Method java/lang/Object."<init>":()V
       4: aload_0
       5: iconst_1
       6: putfield      #4                  // Field autoTrustSerializeClass:Z
       9: aload_0
      10: ldc           #6                  // int 2147483647
      12: putfield      #7                  // Field trustSerializeClassLevel:I
      15: aload_0
      16: aload_1
      17: putfield      #8                  // Field moduleModel:Lorg/apache/dubbo/rpc/model/ModuleModel;
      20: aload_1
      21: aload_0
      22: invokevirtual #9                  // Method org/apache/dubbo/rpc/model/ModuleModel.addClassLoaderListener:(Lorg/apache/dubbo/rpc/model/ScopeClassLoaderListener;)V
      25: aload_1
      26: invokevirtual #10                 // Method org/apache/dubbo/rpc/model/ModuleModel.getApplicationModel:()Lorg/apache/dubbo/rpc/model/ApplicationModel;
      29: invokevirtual #11                 // Method org/apache/dubbo/rpc/model/ApplicationModel.getFrameworkModel:()Lorg/apache/dubbo/rpc/model/FrameworkModel;
      32: astore_2
      33: aload_0
      34: aload_2
      35: invokevirtual #12                 // Method org/apache/dubbo/rpc/model/FrameworkModel.getBeanFactory:()Lorg/apache/dubbo/common/beans/factory/ScopeBeanFactory;
      38: ldc           #13                 // class org/apache/dubbo/common/utils/SerializeSecurityManager
      40: invokevirtual #14                 // Method org/apache/dubbo/common/beans/factory/ScopeBeanFactory.getBean:(Ljava/lang/Class;)Ljava/lang/Object;
      43: checkcast     #13                 // class org/apache/dubbo/common/utils/SerializeSecurityManager
      46: putfield      #15                 // Field serializeSecurityManager:Lorg/apache/dubbo/common/utils/SerializeSecurityManager;
      49: aload_0
      50: invokevirtual #16                 // Method refreshStatus:()V
      53: aload_0
      54: invokevirtual #17                 // Method refreshCheck:()V
      57: aload_0
      58: invokespecial #18                 // Method refreshConfig:()V
      61: aload_0
      62: aload_1
      63: invokestatic  #19                 // Method java/lang/Thread.currentThread:()Ljava/lang/Thread;
      66: invokevirtual #20                 // Method java/lang/Thread.getContextClassLoader:()Ljava/lang/ClassLoader;
      69: invokevirtual #21                 // Method onAddClassLoader:(Lorg/apache/dubbo/rpc/model/ModuleModel;Ljava/lang/ClassLoader;)V
      72: return

  public void refreshCheck();
    Code:
       0: aload_0
       1: getfield      #8                  // Field moduleModel:Lorg/apache/dubbo/rpc/model/ModuleModel;
       4: invokevirtual #10                 // Method org/apache/dubbo/rpc/model/ModuleModel.getApplicationModel:()Lorg/apache/dubbo/rpc/model/ApplicationModel;
       7: invokevirtual #22                 // Method org/apache/dubbo/rpc/model/ApplicationModel.getApplicationConfigManager:()Lorg/apache/dubbo/config/context/ConfigManager;
      10: invokevirtual #23                 // Method org/apache/dubbo/config/context/ConfigManager.getApplication:()Ljava/util/Optional;
      13: astore_1
      14: aload_0
      15: aload_1
      16: invokedynamic #24,  0             // InvokeDynamic #0:apply:()Ljava/util/function/Function;
      21: invokevirtual #25                 // Method java/util/Optional.map:(Ljava/util/function/Function;)Ljava/util/Optional;
      24: iconst_1
      25: invokestatic  #26                 // Method java/lang/Boolean.valueOf:(Z)Ljava/lang/Boolean;
      28: invokevirtual #27                 // Method java/util/Optional.orElse:(Ljava/lang/Object;)Ljava/lang/Object;
      31: checkcast     #28                 // class java/lang/Boolean
      34: invokevirtual #29                 // Method java/lang/Boolean.booleanValue:()Z
      37: putfield      #4                  // Field autoTrustSerializeClass:Z
      40: aload_0
      41: aload_1
      42: invokedynamic #30,  0             // InvokeDynamic #1:apply:()Ljava/util/function/Function;
      47: invokevirtual #25                 // Method java/util/Optional.map:(Ljava/util/function/Function;)Ljava/util/Optional;
      50: ldc           #6                  // int 2147483647
      52: invokestatic  #31                 // Method java/lang/Integer.valueOf:(I)Ljava/lang/Integer;
      55: invokevirtual #27                 // Method java/util/Optional.orElse:(Ljava/lang/Object;)Ljava/lang/Object;
      58: checkcast     #5                  // class java/lang/Integer
      61: invokevirtual #32                 // Method java/lang/Integer.intValue:()I
      64: putfield      #7                  // Field trustSerializeClassLevel:I
      67: aload_0
      68: getfield      #15                 // Field serializeSecurityManager:Lorg/apache/dubbo/common/utils/SerializeSecurityManager;
      71: aload_1
      72: invokedynamic #33,  0             // InvokeDynamic #2:apply:()Ljava/util/function/Function;
      77: invokevirtual #25                 // Method java/util/Optional.map:(Ljava/util/function/Function;)Ljava/util/Optional;
      80: iconst_1
      81: invokestatic  #26                 // Method java/lang/Boolean.valueOf:(Z)Ljava/lang/Boolean;
      84: invokevirtual #27                 // Method java/util/Optional.orElse:(Ljava/lang/Object;)Ljava/lang/Object;
      87: checkcast     #28                 // class java/lang/Boolean
      90: invokevirtual #29                 // Method java/lang/Boolean.booleanValue:()Z
      93: invokevirtual #34                 // Method org/apache/dubbo/common/utils/SerializeSecurityManager.setCheckSerializable:(Z)V
      96: return

  public void onAddClassLoader(org.apache.dubbo.rpc.model.ModuleModel, java.lang.ClassLoader);
    Code:
       0: aload_0
       1: aload_2
       2: invokespecial #35                 // Method refreshClassLoader:(Ljava/lang/ClassLoader;)V
       5: return

  public void onRemoveClassLoader(org.apache.dubbo.rpc.model.ModuleModel, java.lang.ClassLoader);
    Code:
       0: return

  private void refreshClassLoader(java.lang.ClassLoader);
    Code:
       0: aload_0
       1: aload_1
       2: invokespecial #36                 // Method loadAllow:(Ljava/lang/ClassLoader;)V
       5: aload_0
       6: aload_1
       7: invokespecial #37                 // Method loadBlocked:(Ljava/lang/ClassLoader;)V
      10: return

  private void refreshConfig();
    Code:
       0: ldc           #38                 // String dubbo.security.serialize.allowedClassList
       2: ldc           #39                 // String
       4: invokestatic  #40                 // Method java/lang/System.getProperty:(Ljava/lang/String;Ljava/lang/String;)Ljava/lang/String;
       7: invokevirtual #41                 // Method java/lang/String.trim:()Ljava/lang/String;
      10: astore_1
      11: ldc           #42                 // String dubbo.security.serialize.blockedClassList
      13: ldc           #39                 // String
      15: invokestatic  #40                 // Method java/lang/System.getProperty:(Ljava/lang/String;Ljava/lang/String;)Ljava/lang/String;
      18: invokevirtual #41                 // Method java/lang/String.trim:()Ljava/lang/String;
      21: astore_2
      22: aload_1
      23: invokestatic  #43                 // Method org/apache/dubbo/common/utils/StringUtils.isNotEmpty:(Ljava/lang/String;)Z
      26: ifeq          94
      29: aload_1
      30: invokevirtual #41                 // Method java/lang/String.trim:()Ljava/lang/String;
      33: ldc           #44                 // String ,
      35: invokevirtual #45                 // Method java/lang/String.split:(Ljava/lang/String;)[Ljava/lang/String;
      38: astore_3
      39: aload_3
      40: astore        4
      42: aload         4
      44: arraylength
      45: istore        5
      47: iconst_0
      48: istore        6
      50: iload         6
      52: iload         5
      54: if_icmpge     94
      57: aload         4
      59: iload         6
      61: aaload
      62: astore        7
      64: aload         7
      66: invokevirtual #41                 // Method java/lang/String.trim:()Ljava/lang/String;
      69: astore        7
      71: aload         7
      73: invokestatic  #43                 // Method org/apache/dubbo/common/utils/StringUtils.isNotEmpty:(Ljava/lang/String;)Z
      76: ifeq          88
      79: aload_0
      80: getfield      #15                 // Field serializeSecurityManager:Lorg/apache/dubbo/common/utils/SerializeSecurityManager;
      83: aload         7
      85: invokevirtual #46                 // Method org/apache/dubbo/common/utils/SerializeSecurityManager.addToAlwaysAllowed:(Ljava/lang/String;)V
      88: iinc          6, 1
      91: goto          50
      94: aload_2
      95: invokestatic  #43                 // Method org/apache/dubbo/common/utils/StringUtils.isNotEmpty:(Ljava/lang/String;)Z
      98: ifeq          166
     101: aload_2
     102: invokevirtual #41                 // Method java/lang/String.trim:()Ljava/lang/String;
     105: ldc           #44                 // String ,
     107: invokevirtual #45                 // Method java/lang/String.split:(Ljava/lang/String;)[Ljava/lang/String;
     110: astore_3
     111: aload_3
     112: astore        4
     114: aload         4
     116: arraylength
     117: istore        5
     119: iconst_0
     120: istore        6
     122: iload         6
     124: iload         5
     126: if_icmpge     166
     129: aload         4
     131: iload         6
     133: aaload
     134: astore        7
     136: aload         7
     138: invokevirtual #41                 // Method java/lang/String.trim:()Ljava/lang/String;
     141: astore        7
     143: aload         7
     145: invokestatic  #43                 // Method org/apache/dubbo/common/utils/StringUtils.isNotEmpty:(Ljava/lang/String;)Z
     148: ifeq          160
     151: aload_0
     152: getfield      #15                 // Field serializeSecurityManager:Lorg/apache/dubbo/common/utils/SerializeSecurityManager;
     155: aload         7
     157: invokevirtual #47                 // Method org/apache/dubbo/common/utils/SerializeSecurityManager.addToDisAllowed:(Ljava/lang/String;)V
     160: iinc          6, 1
     163: goto          122
     166: return

  private void loadAllow(java.lang.ClassLoader);
    Code:
       0: ldc           #48                 // String security/serialize.allowlist
       2: aload_1
       3: invokestatic  #49                 // Method org/apache/dubbo/common/utils/ClassLoaderResourceLoader.loadResources:(Ljava/lang/String;Ljava/lang/ClassLoader;)Ljava/util/Set;
       6: astore_2
       7: aload_2
       8: invokeinterface #50,  1           // InterfaceMethod java/util/Set.iterator:()Ljava/util/Iterator;
      13: astore_3
      14: aload_3
      15: invokeinterface #51,  1           // InterfaceMethod java/util/Iterator.hasNext:()Z
      20: ifeq          185
      23: aload_3
      24: invokeinterface #52,  1           // InterfaceMethod java/util/Iterator.next:()Ljava/lang/Object;
      29: checkcast     #53                 // class java/net/URL
      32: astore        4
      34: getstatic     #54                 // Field logger:Lorg/apache/dubbo/common/logger/ErrorTypeAwareLogger;
      37: new           #55                 // class java/lang/StringBuilder
      40: dup
      41: invokespecial #56                 // Method java/lang/StringBuilder."<init>":()V
      44: ldc           #57                 // String Read serialize allow list from
      46: invokevirtual #58                 // Method java/lang/StringBuilder.append:(Ljava/lang/String;)Ljava/lang/StringBuilder;
      49: aload         4
      51: invokevirtual #59                 // Method java/lang/StringBuilder.append:(Ljava/lang/Object;)Ljava/lang/StringBuilder;
      54: invokevirtual #60                 // Method java/lang/StringBuilder.toString:()Ljava/lang/String;
      57: invokeinterface #61,  2           // InterfaceMethod org/apache/dubbo/common/logger/ErrorTypeAwareLogger.info:(Ljava/lang/String;)V
      62: aload         4
      64: invokevirtual #62                 // Method java/net/URL.openStream:()Ljava/io/InputStream;
      67: invokestatic  #63                 // Method org/apache/dubbo/common/utils/IOUtils.readLines:(Ljava/io/InputStream;)[Ljava/lang/String;
      70: astore        5
      72: aload         5
      74: astore        6
      76: aload         6
      78: arraylength
      79: istore        7
      81: iconst_0
      82: istore        8
      84: iload         8
      86: iload         7
      88: if_icmpge     141
      91: aload         6
      93: iload         8
      95: aaload
      96: astore        9
      98: aload         9
     100: invokevirtual #41                 // Method java/lang/String.trim:()Ljava/lang/String;
     103: astore        9
     105: aload         9
     107: invokestatic  #64                 // Method org/apache/dubbo/common/utils/StringUtils.isEmpty:(Ljava/lang/String;)Z
     110: ifne          135
     113: aload         9
     115: ldc           #65                 // String #
     117: invokevirtual #66                 // Method java/lang/String.startsWith:(Ljava/lang/String;)Z
     120: ifeq          126
     123: goto          135
     126: aload_0
     127: getfield      #15                 // Field serializeSecurityManager:Lorg/apache/dubbo/common/utils/SerializeSecurityManager;
     130: aload         9
     132: invokevirtual #46                 // Method org/apache/dubbo/common/utils/SerializeSecurityManager.addToAlwaysAllowed:(Ljava/lang/String;)V
     135: iinc          8, 1
     138: goto          84
     141: goto          182
     144: astore        5
     146: getstatic     #54                 // Field logger:Lorg/apache/dubbo/common/logger/ErrorTypeAwareLogger;
     149: ldc           #68                 // String 0-22
     151: ldc           #39                 // String
     153: ldc           #39                 // String
     155: new           #55                 // class java/lang/StringBuilder
     158: dup
     159: invokespecial #56                 // Method java/lang/StringBuilder."<init>":()V
     162: ldc           #69                 // String Failed to load allow class list! Will ignore allow lis from
     164: invokevirtual #58                 // Method java/lang/StringBuilder.append:(Ljava/lang/String;)Ljava/lang/StringBuilder;
     167: aload         4
     169: invokevirtual #59                 // Method java/lang/StringBuilder.append:(Ljava/lang/Object;)Ljava/lang/StringBuilder;
     172: invokevirtual #60                 // Method java/lang/StringBuilder.toString:()Ljava/lang/String;
     175: aload         5
     177: invokeinterface #70,  6           // InterfaceMethod org/apache/dubbo/common/logger/ErrorTypeAwareLogger.error:(Ljava/lang/String;Ljava/lang/String;Ljava/lang/String;Ljava/lang/String;Ljava/lang/Throwable;)V
     182: goto          14
     185: return
    Exception table:
       from    to  target type
          34   141   144   Class java/io/IOException

  private void loadBlocked(java.lang.ClassLoader);
    Code:
       0: ldc           #71                 // String security/serialize.blockedlist
       2: aload_1
       3: invokestatic  #49                 // Method org/apache/dubbo/common/utils/ClassLoaderResourceLoader.loadResources:(Ljava/lang/String;Ljava/lang/ClassLoader;)Ljava/util/Set;
       6: astore_2
       7: aload_2
       8: invokeinterface #50,  1           // InterfaceMethod java/util/Set.iterator:()Ljava/util/Iterator;
      13: astore_3
      14: aload_3
      15: invokeinterface #51,  1           // InterfaceMethod java/util/Iterator.hasNext:()Z
      20: ifeq          185
      23: aload_3
      24: invokeinterface #52,  1           // InterfaceMethod java/util/Iterator.next:()Ljava/lang/Object;
      29: checkcast     #53                 // class java/net/URL
      32: astore        4
      34: getstatic     #54                 // Field logger:Lorg/apache/dubbo/common/logger/ErrorTypeAwareLogger;
      37: new           #55                 // class java/lang/StringBuilder
      40: dup
      41: invokespecial #56                 // Method java/lang/StringBuilder."<init>":()V
      44: ldc           #72                 // String Read serialize blocked list from
      46: invokevirtual #58                 // Method java/lang/StringBuilder.append:(Ljava/lang/String;)Ljava/lang/StringBuilder;
      49: aload         4
      51: invokevirtual #59                 // Method java/lang/StringBuilder.append:(Ljava/lang/Object;)Ljava/lang/StringBuilder;
      54: invokevirtual #60                 // Method java/lang/StringBuilder.toString:()Ljava/lang/String;
      57: invokeinterface #61,  2           // InterfaceMethod org/apache/dubbo/common/logger/ErrorTypeAwareLogger.info:(Ljava/lang/String;)V
      62: aload         4
      64: invokevirtual #62                 // Method java/net/URL.openStream:()Ljava/io/InputStream;
      67: invokestatic  #63                 // Method org/apache/dubbo/common/utils/IOUtils.readLines:(Ljava/io/InputStream;)[Ljava/lang/String;
      70: astore        5
      72: aload         5
      74: astore        6
      76: aload         6
      78: arraylength
      79: istore        7
      81: iconst_0
      82: istore        8
      84: iload         8
      86: iload         7
      88: if_icmpge     141
      91: aload         6
      93: iload         8
      95: aaload
      96: astore        9
      98: aload         9
     100: invokevirtual #41                 // Method java/lang/String.trim:()Ljava/lang/String;
     103: astore        9
     105: aload         9
     107: invokestatic  #64                 // Method org/apache/dubbo/common/utils/StringUtils.isEmpty:(Ljava/lang/String;)Z
     110: ifne          135
     113: aload         9
     115: ldc           #65                 // String #
     117: invokevirtual #66                 // Method java/lang/String.startsWith:(Ljava/lang/String;)Z
     120: ifeq          126
     123: goto          135
     126: aload_0
     127: getfield      #15                 // Field serializeSecurityManager:Lorg/apache/dubbo/common/utils/SerializeSecurityManager;
     130: aload         9
     132: invokevirtual #47                 // Method org/apache/dubbo/common/utils/SerializeSecurityManager.addToDisAllowed:(Ljava/lang/String;)V
     135: iinc          8, 1
     138: goto          84
     141: goto          182
     144: astore        5
     146: getstatic     #54                 // Field logger:Lorg/apache/dubbo/common/logger/ErrorTypeAwareLogger;
     149: ldc           #68                 // String 0-22
     151: ldc           #39                 // String
     153: ldc           #39                 // String
     155: new           #55                 // class java/lang/StringBuilder
     158: dup
     159: invokespecial #56                 // Method java/lang/StringBuilder."<init>":()V
     162: ldc           #73                 // String Failed to load blocked class list! Will ignore blocked lis from
     164: invokevirtual #58                 // Method java/lang/StringBuilder.append:(Ljava/lang/String;)Ljava/lang/StringBuilder;
     167: aload         4
     169: invokevirtual #59                 // Method java/lang/StringBuilder.append:(Ljava/lang/Object;)Ljava/lang/StringBuilder;
     172: invokevirtual #60                 // Method java/lang/StringBuilder.toString:()Ljava/lang/String;
     175: aload         5
     177: invokeinterface #70,  6           // InterfaceMethod org/apache/dubbo/common/logger/ErrorTypeAwareLogger.error:(Ljava/lang/String;Ljava/lang/String;Ljava/lang/String;Ljava/lang/String;Ljava/lang/Throwable;)V
     182: goto          14
     185: return
    Exception table:
       from    to  target type
          34   141   144   Class java/io/IOException

  public void refreshStatus();
    Code:
       0: aload_0
       1: getfield      #8                  // Field moduleModel:Lorg/apache/dubbo/rpc/model/ModuleModel;
       4: invokevirtual #10                 // Method org/apache/dubbo/rpc/model/ModuleModel.getApplicationModel:()Lorg/apache/dubbo/rpc/model/ApplicationModel;
       7: invokevirtual #22                 // Method org/apache/dubbo/rpc/model/ApplicationModel.getApplicationConfigManager:()Lorg/apache/dubbo/config/context/ConfigManager;
      10: invokevirtual #23                 // Method org/apache/dubbo/config/context/ConfigManager.getApplication:()Ljava/util/Optional;
      13: astore_1
      14: aload_1
      15: invokedynamic #74,  0             // InvokeDynamic #3:apply:()Ljava/util/function/Function;
      20: invokevirtual #25                 // Method java/util/Optional.map:(Ljava/util/function/Function;)Ljava/util/Optional;
      23: aconst_null
      24: invokevirtual #27                 // Method java/util/Optional.orElse:(Ljava/lang/Object;)Ljava/lang/Object;
      27: checkcast     #75                 // class java/lang/String
      30: astore_2
      31: aconst_null
      32: astore_3
      33: aload_2
      34: invokestatic  #64                 // Method org/apache/dubbo/common/utils/StringUtils.isEmpty:(Ljava/lang/String;)Z
      37: ifeq          85
      40: ldc           #76                 // String dubbo.security.serialize.openCheckClass
      42: ldc           #77                 // String true
      44: invokestatic  #40                 // Method java/lang/System.getProperty:(Ljava/lang/String;Ljava/lang/String;)Ljava/lang/String;
      47: astore        4
      49: aload         4
      51: invokestatic  #78                 // Method java/lang/Boolean.parseBoolean:(Ljava/lang/String;)Z
      54: ifne          61
      57: getstatic     #79                 // Field org/apache/dubbo/common/utils/SerializeCheckStatus.DISABLE:Lorg/apache/dubbo/common/utils/SerializeCheckStatus;
      60: astore_3
      61: ldc           #80                 // String dubbo.security.serialize.blockAllClassExceptAllow
      63: ldc           #81                 // String false
      65: invokestatic  #40                 // Method java/lang/System.getProperty:(Ljava/lang/String;Ljava/lang/String;)Ljava/lang/String;
      68: astore        5
      70: aload         5
      72: invokestatic  #78                 // Method java/lang/Boolean.parseBoolean:(Ljava/lang/String;)Z
      75: ifeq          82
      78: getstatic     #82                 // Field org/apache/dubbo/common/utils/SerializeCheckStatus.STRICT:Lorg/apache/dubbo/common/utils/SerializeCheckStatus;
      81: astore_3
      82: goto          90
      85: aload_2
      86: invokestatic  #83                 // Method org/apache/dubbo/common/utils/SerializeCheckStatus.valueOf:(Ljava/lang/String;)Lorg/apache/dubbo/common/utils/SerializeCheckStatus;
      89: astore_3
      90: aload_3
      91: ifnull        102
      94: aload_0
      95: getfield      #15                 // Field serializeSecurityManager:Lorg/apache/dubbo/common/utils/SerializeSecurityManager;
      98: aload_3
      99: invokevirtual #84                 // Method org/apache/dubbo/common/utils/SerializeSecurityManager.setCheckStatus:(Lorg/apache/dubbo/common/utils/SerializeCheckStatus;)V
     102: return

  public synchronized void registerInterface(java.lang.Class<?>);
    Code:
       0: aload_0
       1: getfield      #4                  // Field autoTrustSerializeClass:Z
       4: ifne          8
       7: return
       8: new           #85                 // class java/util/HashSet
      11: dup
      12: invokespecial #86                 // Method java/util/HashSet."<init>":()V
      15: astore_2
      16: aload_0
      17: aload_2
      18: aload_1
      19: invokespecial #87                 // Method checkClass:(Ljava/util/Set;Ljava/lang/Class;)V
      22: aload_0
      23: aload_1
      24: invokevirtual #88                 // Method java/lang/Class.getName:()Ljava/lang/String;
      27: invokespecial #89                 // Method addToAllow:(Ljava/lang/String;)V
      30: aload_1
      31: invokevirtual #90                 // Method java/lang/Class.getMethods:()[Ljava/lang/reflect/Method;
      34: astore_3
      35: aload_3
      36: astore        4
      38: aload         4
      40: arraylength
      41: istore        5
      43: iconst_0
      44: istore        6
      46: iload         6
      48: iload         5
      50: if_icmpge     278
      53: aload         4
      55: iload         6
      57: aaload
      58: astore        7
      60: aload         7
      62: invokevirtual #91                 // Method java/lang/reflect/Method.getParameterTypes:()[Ljava/lang/Class;
      65: astore        8
      67: aload         8
      69: astore        9
      71: aload         9
      73: arraylength
      74: istore        10
      76: iconst_0
      77: istore        11
      79: iload         11
      81: iload         10
      83: if_icmpge     106
      86: aload         9
      88: iload         11
      90: aaload
      91: astore        12
      93: aload_0
      94: aload_2
      95: aload         12
      97: invokespecial #87                 // Method checkClass:(Ljava/util/Set;Ljava/lang/Class;)V
     100: iinc          11, 1
     103: goto          79
     106: aload         7
     108: invokevirtual #92                 // Method java/lang/reflect/Method.getGenericParameterTypes:()[Ljava/lang/reflect/Type;
     111: astore        9
     113: aload         9
     115: astore        10
     117: aload         10
     119: arraylength
     120: istore        11
     122: iconst_0
     123: istore        12
     125: iload         12
     127: iload         11
     129: if_icmpge     152
     132: aload         10
     134: iload         12
     136: aaload
     137: astore        13
     139: aload_0
     140: aload_2
     141: aload         13
     143: invokespecial #93                 // Method checkType:(Ljava/util/Set;Ljava/lang/reflect/Type;)V
     146: iinc          12, 1
     149: goto          125
     152: aload         7
     154: invokevirtual #94                 // Method java/lang/reflect/Method.getReturnType:()Ljava/lang/Class;
     157: astore        10
     159: aload_0
     160: aload_2
     161: aload         10
     163: invokespecial #87                 // Method checkClass:(Ljava/util/Set;Ljava/lang/Class;)V
     166: aload         7
     168: invokevirtual #95                 // Method java/lang/reflect/Method.getGenericReturnType:()Ljava/lang/reflect/Type;
     171: astore        11
     173: aload_0
     174: aload_2
     175: aload         11
     177: invokespecial #93                 // Method checkType:(Ljava/util/Set;Ljava/lang/reflect/Type;)V
     180: aload         7
     182: invokevirtual #96                 // Method java/lang/reflect/Method.getExceptionTypes:()[Ljava/lang/Class;
     185: astore        12
     187: aload         12
     189: astore        13
     191: aload         13
     193: arraylength
     194: istore        14
     196: iconst_0
     197: istore        15
     199: iload         15
     201: iload         14
     203: if_icmpge     226
     206: aload         13
     208: iload         15
     210: aaload
     211: astore        16
     213: aload_0
     214: aload_2
     215: aload         16
     217: invokespecial #87                 // Method checkClass:(Ljava/util/Set;Ljava/lang/Class;)V
     220: iinc          15, 1
     223: goto          199
     226: aload         7
     228: invokevirtual #97                 // Method java/lang/reflect/Method.getGenericExceptionTypes:()[Ljava/lang/reflect/Type;
     231: astore        13
     233: aload         13
     235: astore        14
     237: aload         14
     239: arraylength
     240: istore        15
     242: iconst_0
     243: istore        16
     245: iload         16
     247: iload         15
     249: if_icmpge     272
     252: aload         14
     254: iload         16
     256: aaload
     257: astore        17
     259: aload_0
     260: aload_2
     261: aload         17
     263: invokespecial #93                 // Method checkType:(Ljava/util/Set;Ljava/lang/reflect/Type;)V
     266: iinc          16, 1
     269: goto          245
     272: iinc          6, 1
     275: goto          46
     278: return

  private void checkType(java.util.Set<java.lang.reflect.Type>, java.lang.reflect.Type);
    Code:
       0: aload_2
       1: ifnonnull     5
       4: return
       5: aload_2
       6: instanceof    #98                 // class java/lang/Class
       9: ifeq          22
      12: aload_0
      13: aload_1
      14: aload_2
      15: checkcast     #98                 // class java/lang/Class
      18: invokespecial #87                 // Method checkClass:(Ljava/util/Set;Ljava/lang/Class;)V
      21: return
      22: aload_1
      23: aload_2
      24: invokeinterface #99,  2           // InterfaceMethod java/util/Set.add:(Ljava/lang/Object;)Z
      29: ifne          33
      32: return
      33: aload_2
      34: instanceof    #100                // class java/lang/reflect/ParameterizedType
      37: ifeq          105
      40: aload_2
      41: checkcast     #100                // class java/lang/reflect/ParameterizedType
      44: astore_3
      45: aload_0
      46: aload_1
      47: aload_3
      48: invokeinterface #101,  1          // InterfaceMethod java/lang/reflect/ParameterizedType.getRawType:()Ljava/lang/reflect/Type;
      53: checkcast     #98                 // class java/lang/Class
      56: invokespecial #87                 // Method checkClass:(Ljava/util/Set;Ljava/lang/Class;)V
      59: aload_3
      60: invokeinterface #102,  1          // InterfaceMethod java/lang/reflect/ParameterizedType.getActualTypeArguments:()[Ljava/lang/reflect/Type;
      65: astore        4
      67: aload         4
      69: arraylength
      70: istore        5
      72: iconst_0
      73: istore        6
      75: iload         6
      77: iload         5
      79: if_icmpge     102
      82: aload         4
      84: iload         6
      86: aaload
      87: astore        7
      89: aload_0
      90: aload_1
      91: aload         7
      93: invokespecial #93                 // Method checkType:(Ljava/util/Set;Ljava/lang/reflect/Type;)V
      96: iinc          6, 1
      99: goto          75
     102: goto          287
     105: aload_2
     106: instanceof    #103                // class java/lang/reflect/GenericArrayType
     109: ifeq          131
     112: aload_2
     113: checkcast     #103                // class java/lang/reflect/GenericArrayType
     116: astore_3
     117: aload_0
     118: aload_1
     119: aload_3
     120: invokeinterface #104,  1          // InterfaceMethod java/lang/reflect/GenericArrayType.getGenericComponentType:()Ljava/lang/reflect/Type;
     125: invokespecial #93                 // Method checkType:(Ljava/util/Set;Ljava/lang/reflect/Type;)V
     128: goto          287
     131: aload_2
     132: instanceof    #105                // class java/lang/reflect/TypeVariable
     135: ifeq          189
     138: aload_2
     139: checkcast     #105                // class java/lang/reflect/TypeVariable
     142: astore_3
     143: aload_3
     144: invokeinterface #106,  1          // InterfaceMethod java/lang/reflect/TypeVariable.getBounds:()[Ljava/lang/reflect/Type;
     149: astore        4
     151: aload         4
     153: arraylength
     154: istore        5
     156: iconst_0
     157: istore        6
     159: iload         6
     161: iload         5
     163: if_icmpge     186
     166: aload         4
     168: iload         6
     170: aaload
     171: astore        7
     173: aload_0
     174: aload_1
     175: aload         7
     177: invokespecial #93                 // Method checkType:(Ljava/util/Set;Ljava/lang/reflect/Type;)V
     180: iinc          6, 1
     183: goto          159
     186: goto          287
     189: aload_2
     190: instanceof    #107                // class java/lang/reflect/WildcardType
     193: ifeq          287
     196: aload_2
     197: checkcast     #107                // class java/lang/reflect/WildcardType
     200: astore_3
     201: aload_3
     202: invokeinterface #108,  1          // InterfaceMethod java/lang/reflect/WildcardType.getUpperBounds:()[Ljava/lang/reflect/Type;
     207: astore        4
     209: aload         4
     211: arraylength
     212: istore        5
     214: iconst_0
     215: istore        6
     217: iload         6
     219: iload         5
     221: if_icmpge     244
     224: aload         4
     226: iload         6
     228: aaload
     229: astore        7
     231: aload_0
     232: aload_1
     233: aload         7
     235: invokespecial #93                 // Method checkType:(Ljava/util/Set;Ljava/lang/reflect/Type;)V
     238: iinc          6, 1
     241: goto          217
     244: aload_3
     245: invokeinterface #109,  1          // InterfaceMethod java/lang/reflect/WildcardType.getLowerBounds:()[Ljava/lang/reflect/Type;
     250: astore        4
     252: aload         4
     254: arraylength
     255: istore        5
     257: iconst_0
     258: istore        6
     260: iload         6
     262: iload         5
     264: if_icmpge     287
     267: aload         4
     269: iload         6
     271: aaload
     272: astore        7
     274: aload_0
     275: aload_1
     276: aload         7
     278: invokespecial #93                 // Method checkType:(Ljava/util/Set;Ljava/lang/reflect/Type;)V
     281: iinc          6, 1
     284: goto          260
     287: return

  private void checkClass(java.util.Set<java.lang.reflect.Type>, java.lang.Class<?>);
    Code:
       0: aload_2
       1: ifnonnull     5
       4: return
       5: aload_1
       6: aload_2
       7: invokeinterface #99,  2           // InterfaceMethod java/util/Set.add:(Ljava/lang/Object;)Z
      12: ifne          16
      15: return
      16: aload_0
      17: aload_2
      18: invokevirtual #88                 // Method java/lang/Class.getName:()Ljava/lang/String;
      21: invokespecial #89                 // Method addToAllow:(Ljava/lang/String;)V
      24: aload_2
      25: invokevirtual #110                // Method java/lang/Class.getInterfaces:()[Ljava/lang/Class;
      28: astore_3
      29: aload_3
      30: astore        4
      32: aload         4
      34: arraylength
      35: istore        5
      37: iconst_0
      38: istore        6
      40: iload         6
      42: iload         5
      44: if_icmpge     67
      47: aload         4
      49: iload         6
      51: aaload
      52: astore        7
      54: aload_0
      55: aload_1
      56: aload         7
      58: invokespecial #87                 // Method checkClass:(Ljava/util/Set;Ljava/lang/Class;)V
      61: iinc          6, 1
      64: goto          40
      67: aload_2
      68: invokevirtual #111                // Method java/lang/Class.getGenericInterfaces:()[Ljava/lang/reflect/Type;
      71: astore        4
      73: aload         4
      75: arraylength
      76: istore        5
      78: iconst_0
      79: istore        6
      81: iload         6
      83: iload         5
      85: if_icmpge     108
      88: aload         4
      90: iload         6
      92: aaload
      93: astore        7
      95: aload_0
      96: aload_1
      97: aload         7
      99: invokespecial #93                 // Method checkType:(Ljava/util/Set;Ljava/lang/reflect/Type;)V
     102: iinc          6, 1
     105: goto          81
     108: aload_2
     109: invokevirtual #112                // Method java/lang/Class.getSuperclass:()Ljava/lang/Class;
     112: astore        4
     114: aload         4
     116: ifnull        126
     119: aload_0
     120: aload_1
     121: aload         4
     123: invokespecial #87                 // Method checkClass:(Ljava/util/Set;Ljava/lang/Class;)V
     126: aload_2
     127: invokevirtual #113                // Method java/lang/Class.getGenericSuperclass:()Ljava/lang/reflect/Type;
     130: astore        5
     132: aload         5
     134: ifnull        144
     137: aload_0
     138: aload_1
     139: aload         5
     141: invokespecial #93                 // Method checkType:(Ljava/util/Set;Ljava/lang/reflect/Type;)V
     144: aload_2
     145: invokevirtual #114                // Method java/lang/Class.getDeclaredFields:()[Ljava/lang/reflect/Field;
     148: astore        6
     150: aload         6
     152: astore        7
     154: aload         7
     156: arraylength
     157: istore        8
     159: iconst_0
     160: istore        9
     162: iload         9
     164: iload         8
     166: if_icmpge     220
     169: aload         7
     171: iload         9
     173: aaload
     174: astore        10
     176: aload         10
     178: invokevirtual #115                // Method java/lang/reflect/Field.getModifiers:()I
     181: invokestatic  #116                // Method java/lang/reflect/Modifier.isTransient:(I)Z
     184: ifeq          190
     187: goto          214
     190: aload         10
     192: invokevirtual #117                // Method java/lang/reflect/Field.getType:()Ljava/lang/Class;
     195: astore        11
     197: aload_0
     198: aload_1
     199: aload         11
     201: invokespecial #87                 // Method checkClass:(Ljava/util/Set;Ljava/lang/Class;)V
     204: aload_0
     205: aload_1
     206: aload         10
     208: invokevirtual #118                // Method java/lang/reflect/Field.getGenericType:()Ljava/lang/reflect/Type;
     211: invokespecial #93                 // Method checkType:(Ljava/util/Set;Ljava/lang/reflect/Type;)V
     214: iinc          9, 1
     217: goto          162
     220: return

  private void addToAllow(java.lang.String);
    Code:
       0: aload_1
       1: ldc           #119                // String java.
       3: invokevirtual #66                 // Method java/lang/String.startsWith:(Ljava/lang/String;)Z
       6: ifne          45
       9: aload_1
      10: ldc           #120                // String javax.
      12: invokevirtual #66                 // Method java/lang/String.startsWith:(Ljava/lang/String;)Z
      15: ifne          45
      18: aload_1
      19: ldc           #121                // String com.sun.
      21: invokevirtual #66                 // Method java/lang/String.startsWith:(Ljava/lang/String;)Z
      24: ifne          45
      27: aload_1
      28: ldc           #122                // String sun.
      30: invokevirtual #66                 // Method java/lang/String.startsWith:(Ljava/lang/String;)Z
      33: ifne          45
      36: aload_1
      37: ldc           #123                // String jdk.
      39: invokevirtual #66                 // Method java/lang/String.startsWith:(Ljava/lang/String;)Z
      42: ifeq          54
      45: aload_0
      46: getfield      #15                 // Field serializeSecurityManager:Lorg/apache/dubbo/common/utils/SerializeSecurityManager;
      49: aload_1
      50: invokevirtual #124                // Method org/apache/dubbo/common/utils/SerializeSecurityManager.addToAllowed:(Ljava/lang/String;)V
      53: return
      54: aload_1
      55: ldc           #125                // String \\.
      57: invokevirtual #45                 // Method java/lang/String.split:(Ljava/lang/String;)[Ljava/lang/String;
      60: astore_2
      61: aload_2
      62: arraylength
      63: aload_0
      64: getfield      #7                  // Field trustSerializeClassLevel:I
      67: if_icmple     125
      70: aload_0
      71: getfield      #15                 // Field serializeSecurityManager:Lorg/apache/dubbo/common/utils/SerializeSecurityManager;
      74: new           #55                 // class java/lang/StringBuilder
      77: dup
      78: invokespecial #56                 // Method java/lang/StringBuilder."<init>":()V
      81: aload_2
      82: invokestatic  #126                // Method java/util/Arrays.stream:([Ljava/lang/Object;)Ljava/util/stream/Stream;
      85: aload_0
      86: getfield      #7                  // Field trustSerializeClassLevel:I
      89: i2l
      90: invokeinterface #127,  3          // InterfaceMethod java/util/stream/Stream.limit:(J)Ljava/util/stream/Stream;
      95: ldc           #128                // String .
      97: invokestatic  #129                // Method java/util/stream/Collectors.joining:(Ljava/lang/CharSequence;)Ljava/util/stream/Collector;
     100: invokeinterface #130,  2          // InterfaceMethod java/util/stream/Stream.collect:(Ljava/util/stream/Collector;)Ljava/lang/Object;
     105: checkcast     #75                 // class java/lang/String
     108: invokevirtual #58                 // Method java/lang/StringBuilder.append:(Ljava/lang/String;)Ljava/lang/StringBuilder;
     111: ldc           #128                // String .
     113: invokevirtual #58                 // Method java/lang/StringBuilder.append:(Ljava/lang/String;)Ljava/lang/StringBuilder;
     116: invokevirtual #60                 // Method java/lang/StringBuilder.toString:()Ljava/lang/String;
     119: invokevirtual #124                // Method org/apache/dubbo/common/utils/SerializeSecurityManager.addToAllowed:(Ljava/lang/String;)V
     122: goto          133
     125: aload_0
     126: getfield      #15                 // Field serializeSecurityManager:Lorg/apache/dubbo/common/utils/SerializeSecurityManager;
     129: aload_1
     130: invokevirtual #124                // Method org/apache/dubbo/common/utils/SerializeSecurityManager.addToAllowed:(Ljava/lang/String;)V
     133: return

  public void onRemoveClassLoader(org.apache.dubbo.rpc.model.ScopeModel, java.lang.ClassLoader);
    Code:
       0: aload_0
       1: aload_1
       2: checkcast     #131                // class org/apache/dubbo/rpc/model/ModuleModel
       5: aload_2
       6: invokevirtual #132                // Method onRemoveClassLoader:(Lorg/apache/dubbo/rpc/model/ModuleModel;Ljava/lang/ClassLoader;)V
       9: return

  public void onAddClassLoader(org.apache.dubbo.rpc.model.ScopeModel, java.lang.ClassLoader);
    Code:
       0: aload_0
       1: aload_1
       2: checkcast     #131                // class org/apache/dubbo/rpc/model/ModuleModel
       5: aload_2
       6: invokevirtual #21                 // Method onAddClassLoader:(Lorg/apache/dubbo/rpc/model/ModuleModel;Ljava/lang/ClassLoader;)V
       9: return

  static {};
    Code:
       0: ldc           #133                // class org/apache/dubbo/common/utils/SerializeSecurityConfigurator
       2: invokestatic  #134                // Method org/apache/dubbo/common/logger/LoggerFactory.getErrorTypeAwareLogger:(Ljava/lang/Class;)Lorg/apache/dubbo/common/logger/ErrorTypeAwareLogger;
       5: putstatic     #54                 // Field logger:Lorg/apache/dubbo/common/logger/ErrorTypeAwareLogger;
       8: return
}
