Compiled from "ServiceAnnotationResolver.java"
public class org.apache.dubbo.common.utils.ServiceAnnotationResolver {
  public static java.util.List<java.lang.Class<? extends java.lang.annotation.Annotation>> SERVICE_ANNOTATION_CLASSES;

  private final java.lang.annotation.Annotation serviceAnnotation;

  private final java.lang.Class<?> serviceType;

  public org.apache.dubbo.common.utils.ServiceAnnotationResolver(java.lang.Class<?>) throws java.lang.IllegalArgumentException;
    Code:
       0: aload_0
       1: invokespecial #1                  // Method java/lang/Object."<init>":()V
       4: aload_0
       5: aload_1
       6: putfield      #2                  // Field serviceType:Ljava/lang/Class;
       9: aload_0
      10: aload_0
      11: aload_1
      12: invokespecial #3                  // Method getServiceAnnotation:(Ljava/lang/Class;)Ljava/lang/annotation/Annotation;
      15: putfield      #4                  // Field serviceAnnotation:Ljava/lang/annotation/Annotation;
      18: return

  private java.lang.annotation.Annotation getServiceAnnotation(java.lang.Class<?>);
    Code:
       0: aconst_null
       1: astore_2
       2: getstatic     #5                  // Field SERVICE_ANNOTATION_CLASSES:Ljava/util/List;
       5: invokeinterface #6,  1            // InterfaceMethod java/util/List.iterator:()Ljava/util/Iterator;
      10: astore_3
      11: aload_3
      12: invokeinterface #7,  1            // InterfaceMethod java/util/Iterator.hasNext:()Z
      17: ifeq          48
      20: aload_3
      21: invokeinterface #8,  1            // InterfaceMethod java/util/Iterator.next:()Ljava/lang/Object;
      26: checkcast     #9                  // class java/lang/Class
      29: astore        4
      31: aload_1
      32: aload         4
      34: invokevirtual #10                 // Method java/lang/Class.getAnnotation:(Ljava/lang/Class;)Ljava/lang/annotation/Annotation;
      37: astore_2
      38: aload_2
      39: ifnull        45
      42: goto          48
      45: goto          11
      48: aload_2
      49: ifnonnull     82
      52: new           #11                 // class java/lang/IllegalArgumentException
      55: dup
      56: ldc           #12                 // String Any annotation of [%s] can\'t be annotated in the service type[%s].
      58: iconst_2
      59: anewarray     #13                 // class java/lang/Object
      62: dup
      63: iconst_0
      64: getstatic     #5                  // Field SERVICE_ANNOTATION_CLASSES:Ljava/util/List;
      67: aastore
      68: dup
      69: iconst_1
      70: aload_1
      71: invokevirtual #14                 // Method java/lang/Class.getName:()Ljava/lang/String;
      74: aastore
      75: invokestatic  #15                 // Method java/lang/String.format:(Ljava/lang/String;[Ljava/lang/Object;)Ljava/lang/String;
      78: invokespecial #16                 // Method java/lang/IllegalArgumentException."<init>":(Ljava/lang/String;)V
      81: athrow
      82: aload_2
      83: areturn

  public java.lang.String resolveInterfaceClassName();
    Code:
       0: aload_0
       1: ldc           #17                 // String interfaceName
       3: invokespecial #18                 // Method resolveAttribute:(Ljava/lang/String;)Ljava/lang/Object;
       6: checkcast     #19                 // class java/lang/String
       9: astore_2
      10: aload_2
      11: invokestatic  #20                 // Method org/apache/dubbo/common/utils/StringUtils.isEmpty:(Ljava/lang/String;)Z
      14: ifeq          30
      17: aload_0
      18: ldc           #21                 // String interfaceClass
      20: invokespecial #18                 // Method resolveAttribute:(Ljava/lang/String;)Ljava/lang/Object;
      23: checkcast     #9                  // class java/lang/Class
      26: astore_1
      27: goto          42
      30: aload_2
      31: aload_0
      32: invokevirtual #22                 // Method java/lang/Object.getClass:()Ljava/lang/Class;
      35: invokevirtual #23                 // Method java/lang/Class.getClassLoader:()Ljava/lang/ClassLoader;
      38: invokestatic  #24                 // Method org/apache/dubbo/common/utils/ClassUtils.resolveClass:(Ljava/lang/String;Ljava/lang/ClassLoader;)Ljava/lang/Class;
      41: astore_1
      42: aload_1
      43: invokestatic  #25                 // Method org/apache/dubbo/common/utils/ClassUtils.isGenericClass:(Ljava/lang/Class;)Z
      46: ifeq          57
      49: aload_1
      50: invokevirtual #14                 // Method java/lang/Class.getName:()Ljava/lang/String;
      53: astore_2
      54: goto          59
      57: aconst_null
      58: astore_2
      59: aload_2
      60: invokestatic  #20                 // Method org/apache/dubbo/common/utils/StringUtils.isEmpty:(Ljava/lang/String;)Z
      63: ifeq          88
      66: aload_0
      67: getfield      #2                  // Field serviceType:Ljava/lang/Class;
      70: invokevirtual #26                 // Method java/lang/Class.getInterfaces:()[Ljava/lang/Class;
      73: astore_3
      74: aload_3
      75: invokestatic  #27                 // Method org/apache/dubbo/common/utils/ArrayUtils.isNotEmpty:([Ljava/lang/Object;)Z
      78: ifeq          88
      81: aload_3
      82: iconst_0
      83: aaload
      84: invokevirtual #14                 // Method java/lang/Class.getName:()Ljava/lang/String;
      87: astore_2
      88: aload_2
      89: areturn

  public java.lang.String resolveVersion();
    Code:
       0: aload_0
       1: ldc           #28                 // String version
       3: invokespecial #18                 // Method resolveAttribute:(Ljava/lang/String;)Ljava/lang/Object;
       6: checkcast     #19                 // class java/lang/String
       9: areturn

  public java.lang.String resolveGroup();
    Code:
       0: aload_0
       1: ldc           #29                 // String group
       3: invokespecial #18                 // Method resolveAttribute:(Ljava/lang/String;)Ljava/lang/Object;
       6: checkcast     #19                 // class java/lang/String
       9: areturn

  private <T> T resolveAttribute(java.lang.String);
    Code:
       0: aload_0
       1: getfield      #4                  // Field serviceAnnotation:Ljava/lang/annotation/Annotation;
       4: aload_1
       5: invokestatic  #30                 // InterfaceMethod org/apache/dubbo/common/utils/AnnotationUtils.getAttribute:(Ljava/lang/annotation/Annotation;Ljava/lang/String;)Ljava/lang/Object;
       8: areturn

  public java.lang.annotation.Annotation getServiceAnnotation();
    Code:
       0: aload_0
       1: getfield      #4                  // Field serviceAnnotation:Ljava/lang/annotation/Annotation;
       4: areturn

  public java.lang.Class<?> getServiceType();
    Code:
       0: aload_0
       1: getfield      #2                  // Field serviceType:Ljava/lang/Class;
       4: areturn

  static {};
    Code:
       0: iconst_3
       1: anewarray     #9                  // class java/lang/Class
       4: dup
       5: iconst_0
       6: ldc           #31                 // class org/apache/dubbo/config/annotation/DubboService
       8: aastore
       9: dup
      10: iconst_1
      11: ldc           #32                 // class org/apache/dubbo/config/annotation/Service
      13: aastore
      14: dup
      15: iconst_2
      16: ldc           #33                 // class com/alibaba/dubbo/config/annotation/Service
      18: aastore
      19: invokestatic  #34                 // Method java/util/Arrays.asList:([Ljava/lang/Object;)Ljava/util/List;
      22: invokestatic  #35                 // Method java/util/Collections.unmodifiableList:(Ljava/util/List;)Ljava/util/List;
      25: putstatic     #5                  // Field SERVICE_ANNOTATION_CLASSES:Ljava/util/List;
      28: return
}
