Compiled from "StringConstantFieldValuePredicate.java"
public class org.apache.dubbo.common.utils.StringConstantFieldValuePredicate implements java.util.function.Predicate<java.lang.String> {
  private final java.util.Set<java.lang.String> constantFieldValues;

  public org.apache.dubbo.common.utils.StringConstantFieldValuePredicate(java.lang.Class<?>);
    Code:
       0: aload_0
       1: invokespecial #1                  // Method java/lang/Object."<init>":()V
       4: aload_0
       5: aload_0
       6: aload_1
       7: invokespecial #2                  // Method getConstantFieldValues:(Ljava/lang/Class;)Ljava/util/Set;
      10: putfield      #3                  // Field constantFieldValues:Ljava/util/Set;
      13: return

  public static java.util.function.Predicate<java.lang.String> of(java.lang.Class<?>);
    Code:
       0: new           #4                  // class org/apache/dubbo/common/utils/StringConstantFieldValuePredicate
       3: dup
       4: aload_0
       5: invokespecial #5                  // Method "<init>":(Ljava/lang/Class;)V
       8: areturn

  private java.util.Set<java.lang.String> getConstantFieldValues(java.lang.Class<?>);
    Code:
       0: aload_1
       1: invokevirtual #6                  // Method java/lang/Class.getFields:()[Ljava/lang/reflect/Field;
       4: invokestatic  #7                  // InterfaceMethod java/util/stream/Stream.of:([Ljava/lang/Object;)Ljava/util/stream/Stream;
       7: invokedynamic #8,  0              // InvokeDynamic #0:test:()Ljava/util/function/Predicate;
      12: invokeinterface #9,  2            // InterfaceMethod java/util/stream/Stream.filter:(Ljava/util/function/Predicate;)Ljava/util/stream/Stream;
      17: invokedynamic #10,  0             // InvokeDynamic #1:test:()Ljava/util/function/Predicate;
      22: invokeinterface #9,  2            // InterfaceMethod java/util/stream/Stream.filter:(Ljava/util/function/Predicate;)Ljava/util/stream/Stream;
      27: invokedynamic #11,  0             // InvokeDynamic #2:test:()Ljava/util/function/Predicate;
      32: invokeinterface #9,  2            // InterfaceMethod java/util/stream/Stream.filter:(Ljava/util/function/Predicate;)Ljava/util/stream/Stream;
      37: aload_0
      38: invokedynamic #12,  0             // InvokeDynamic #3:apply:(Lorg/apache/dubbo/common/utils/StringConstantFieldValuePredicate;)Ljava/util/function/Function;
      43: invokeinterface #13,  2           // InterfaceMethod java/util/stream/Stream.map:(Ljava/util/function/Function;)Ljava/util/stream/Stream;
      48: invokedynamic #14,  0             // InvokeDynamic #4:test:()Ljava/util/function/Predicate;
      53: invokeinterface #9,  2            // InterfaceMethod java/util/stream/Stream.filter:(Ljava/util/function/Predicate;)Ljava/util/stream/Stream;
      58: ldc           #15                 // class java/lang/String
      60: dup
      61: invokevirtual #16                 // Method java/lang/Object.getClass:()Ljava/lang/Class;
      64: pop
      65: invokedynamic #17,  0             // InvokeDynamic #5:apply:(Ljava/lang/Class;)Ljava/util/function/Function;
      70: invokeinterface #13,  2           // InterfaceMethod java/util/stream/Stream.map:(Ljava/util/function/Function;)Ljava/util/stream/Stream;
      75: invokestatic  #18                 // Method java/util/stream/Collectors.toSet:()Ljava/util/stream/Collector;
      78: invokeinterface #19,  2           // InterfaceMethod java/util/stream/Stream.collect:(Ljava/util/stream/Collector;)Ljava/lang/Object;
      83: checkcast     #20                 // class java/util/Set
      86: areturn

  public boolean test(java.lang.String);
    Code:
       0: aload_0
       1: getfield      #3                  // Field constantFieldValues:Ljava/util/Set;
       4: aload_1
       5: invokeinterface #21,  2           // InterfaceMethod java/util/Set.contains:(Ljava/lang/Object;)Z
      10: ireturn

  private java.lang.Object getConstantValue(java.lang.reflect.Field);
    Code:
       0: aconst_null
       1: aload_1
       2: invokestatic  #22                 // InterfaceMethod org/apache/dubbo/common/utils/FieldUtils.getFieldValue:(Ljava/lang/Object;Ljava/lang/reflect/Field;)Ljava/lang/Object;
       5: areturn

  public boolean test(java.lang.Object);
    Code:
       0: aload_0
       1: aload_1
       2: checkcast     #15                 // class java/lang/String
       5: invokevirtual #23                 // Method test:(Ljava/lang/String;)Z
       8: ireturn

  private static boolean lambda$getConstantFieldValues$3(java.lang.Object);
    Code:
       0: aload_0
       1: instanceof    #15                 // class java/lang/String
       4: ireturn

  private static boolean lambda$getConstantFieldValues$2(java.lang.reflect.Field);
    Code:
       0: aload_0
       1: invokevirtual #24                 // Method java/lang/reflect/Field.getModifiers:()I
       4: invokestatic  #25                 // Method java/lang/reflect/Modifier.isFinal:(I)Z
       7: ireturn

  private static boolean lambda$getConstantFieldValues$1(java.lang.reflect.Field);
    Code:
       0: aload_0
       1: invokevirtual #24                 // Method java/lang/reflect/Field.getModifiers:()I
       4: invokestatic  #26                 // Method java/lang/reflect/Modifier.isPublic:(I)Z
       7: ireturn

  private static boolean lambda$getConstantFieldValues$0(java.lang.reflect.Field);
    Code:
       0: aload_0
       1: invokevirtual #24                 // Method java/lang/reflect/Field.getModifiers:()I
       4: invokestatic  #27                 // Method java/lang/reflect/Modifier.isStatic:(I)Z
       7: ireturn
}
