Compiled from "R2dbcScriptDatabaseInitializer.java"
public class org.springframework.boot.r2dbc.init.R2dbcScriptDatabaseInitializer extends org.springframework.boot.sql.init.AbstractScriptDatabaseInitializer {
  private final io.r2dbc.spi.ConnectionFactory connectionFactory;

  public org.springframework.boot.r2dbc.init.R2dbcScriptDatabaseInitializer(io.r2dbc.spi.ConnectionFactory, org.springframework.boot.sql.init.DatabaseInitializationSettings);
    Code:
       0: aload_0
       1: aload_2
       2: invokespecial #1                  // Method org/springframework/boot/sql/init/AbstractScriptDatabaseInitializer."<init>":(Lorg/springframework/boot/sql/init/DatabaseInitializationSettings;)V
       5: aload_0
       6: aload_1
       7: putfield      #7                  // Field connectionFactory:Lio/r2dbc/spi/ConnectionFactory;
      10: return

  protected boolean isEmbeddedDatabase();
    Code:
       0: aload_0
       1: getfield      #7                  // Field connectionFactory:Lio/r2dbc/spi/ConnectionFactory;
       4: invokestatic  #13                 // Method org/springframework/boot/r2dbc/EmbeddedDatabaseConnection.isEmbedded:(Lio/r2dbc/spi/ConnectionFactory;)Z
       7: ireturn

  protected void runScripts(org.springframework.boot.sql.init.AbstractScriptDatabaseInitializer$Scripts);
    Code:
       0: new           #19                 // class org/springframework/r2dbc/connection/init/ResourceDatabasePopulator
       3: dup
       4: invokespecial #21                 // Method org/springframework/r2dbc/connection/init/ResourceDatabasePopulator."<init>":()V
       7: astore_2
       8: aload_2
       9: aload_1
      10: invokevirtual #24                 // Method org/springframework/boot/sql/init/AbstractScriptDatabaseInitializer$Scripts.isContinueOnError:()Z
      13: invokevirtual #30                 // Method org/springframework/r2dbc/connection/init/ResourceDatabasePopulator.setContinueOnError:(Z)V
      16: aload_2
      17: aload_1
      18: invokevirtual #34                 // Method org/springframework/boot/sql/init/AbstractScriptDatabaseInitializer$Scripts.getSeparator:()Ljava/lang/String;
      21: invokevirtual #38                 // Method org/springframework/r2dbc/connection/init/ResourceDatabasePopulator.setSeparator:(Ljava/lang/String;)V
      24: aload_1
      25: invokevirtual #42                 // Method org/springframework/boot/sql/init/AbstractScriptDatabaseInitializer$Scripts.getEncoding:()Ljava/nio/charset/Charset;
      28: ifnull        42
      31: aload_2
      32: aload_1
      33: invokevirtual #42                 // Method org/springframework/boot/sql/init/AbstractScriptDatabaseInitializer$Scripts.getEncoding:()Ljava/nio/charset/Charset;
      36: invokevirtual #46                 // Method java/nio/charset/Charset.name:()Ljava/lang/String;
      39: invokevirtual #51                 // Method org/springframework/r2dbc/connection/init/ResourceDatabasePopulator.setSqlScriptEncoding:(Ljava/lang/String;)V
      42: aload_1
      43: invokevirtual #54                 // Method org/springframework/boot/sql/init/AbstractScriptDatabaseInitializer$Scripts.iterator:()Ljava/util/Iterator;
      46: astore_3
      47: aload_3
      48: invokeinterface #58,  1           // InterfaceMethod java/util/Iterator.hasNext:()Z
      53: ifeq          76
      56: aload_3
      57: invokeinterface #63,  1           // InterfaceMethod java/util/Iterator.next:()Ljava/lang/Object;
      62: checkcast     #67                 // class org/springframework/core/io/Resource
      65: astore        4
      67: aload_2
      68: aload         4
      70: invokevirtual #69                 // Method org/springframework/r2dbc/connection/init/ResourceDatabasePopulator.addScript:(Lorg/springframework/core/io/Resource;)V
      73: goto          47
      76: aload_2
      77: aload_0
      78: getfield      #7                  // Field connectionFactory:Lio/r2dbc/spi/ConnectionFactory;
      81: invokevirtual #73                 // Method org/springframework/r2dbc/connection/init/ResourceDatabasePopulator.populate:(Lio/r2dbc/spi/ConnectionFactory;)Lreactor/core/publisher/Mono;
      84: invokevirtual #77                 // Method reactor/core/publisher/Mono.block:()Ljava/lang/Object;
      87: pop
      88: return
}
