Compiled from "ThreadLocalCache.java"
public class org.apache.dubbo.cache.support.threadlocal.ThreadLocalCache implements org.apache.dubbo.cache.Cache {
  private final java.lang.ThreadLocal<java.util.Map<java.lang.Object, java.lang.Object>> store;

  public org.apache.dubbo.cache.support.threadlocal.ThreadLocalCache(org.apache.dubbo.common.URL);
    Code:
       0: aload_0
       1: invokespecial #1                  // Method java/lang/Object."<init>":()V
       4: aload_0
       5: invokedynamic #2,  0              // InvokeDynamic #0:get:()Ljava/util/function/Supplier;
      10: invokestatic  #3                  // Method java/lang/ThreadLocal.withInitial:(Ljava/util/function/Supplier;)Ljava/lang/ThreadLocal;
      13: putfield      #4                  // Field store:Ljava/lang/ThreadLocal;
      16: return

  public void put(java.lang.Object, java.lang.Object);
    Code:
       0: aload_0
       1: getfield      #4                  // Field store:Ljava/lang/ThreadLocal;
       4: invokevirtual #5                  // Method java/lang/ThreadLocal.get:()Ljava/lang/Object;
       7: checkcast     #6                  // class java/util/Map
      10: aload_1
      11: aload_2
      12: invokeinterface #7,  3            // InterfaceMethod java/util/Map.put:(Ljava/lang/Object;Ljava/lang/Object;)Ljava/lang/Object;
      17: pop
      18: return

  public java.lang.Object get(java.lang.Object);
    Code:
       0: aload_0
       1: getfield      #4                  // Field store:Ljava/lang/ThreadLocal;
       4: invokevirtual #5                  // Method java/lang/ThreadLocal.get:()Ljava/lang/Object;
       7: checkcast     #6                  // class java/util/Map
      10: aload_1
      11: invokeinterface #8,  2            // InterfaceMethod java/util/Map.get:(Ljava/lang/Object;)Ljava/lang/Object;
      16: areturn
}
