Compiled from "BuiltInConverters.java"
final class retrofit2.BuiltInConverters$VoidResponseBodyConverter implements retrofit2.Converter<okhttp3.ResponseBody, java.lang.Void> {
  static final retrofit2.BuiltInConverters$VoidResponseBodyConverter INSTANCE;

  retrofit2.BuiltInConverters$VoidResponseBodyConverter();
    Code:
       0: aload_0
       1: invokespecial #1                  // Method java/lang/Object."<init>":()V
       4: return

  public java.lang.Void convert(okhttp3.ResponseBody);
    Code:
       0: aload_1
       1: invokevirtual #7                  // Method okhttp3/ResponseBody.close:()V
       4: aconst_null
       5: areturn

  public java.lang.Object convert(java.lang.Object) throws java.io.IOException;
    Code:
       0: aload_0
       1: aload_1
       2: checkcast     #8                  // class okhttp3/ResponseBody
       5: invokevirtual #12                 // Method convert:(Lokhttp3/ResponseBody;)Ljava/lang/Void;
       8: areturn

  static {};
    Code:
       0: new           #13                 // class retrofit2/BuiltInConverters$VoidResponseBodyConverter
       3: dup
       4: invokespecial #18                 // Method "<init>":()V
       7: putstatic     #19                 // Field INSTANCE:Lretrofit2/BuiltInConverters$VoidResponseBodyConverter;
      10: return
}
