Compiled from "BuiltInConverters.java"
final class retrofit2.BuiltInConverters$RequestBodyConverter implements retrofit2.Converter<okhttp3.RequestBody, okhttp3.RequestBody> {
  static final retrofit2.BuiltInConverters$RequestBodyConverter INSTANCE;

  retrofit2.BuiltInConverters$RequestBodyConverter();
    Code:
       0: aload_0
       1: invokespecial #1                  // Method java/lang/Object."<init>":()V
       4: return

  public okhttp3.RequestBody convert(okhttp3.RequestBody);
    Code:
       0: aload_1
       1: areturn

  public java.lang.Object convert(java.lang.Object) throws java.io.IOException;
    Code:
       0: aload_0
       1: aload_1
       2: checkcast     #7                  // class okhttp3/RequestBody
       5: invokevirtual #9                  // Method convert:(Lokhttp3/RequestBody;)Lokhttp3/RequestBody;
       8: areturn

  static {};
    Code:
       0: new           #10                 // class retrofit2/BuiltInConverters$RequestBodyConverter
       3: dup
       4: invokespecial #15                 // Method "<init>":()V
       7: putstatic     #16                 // Field INSTANCE:Lretrofit2/BuiltInConverters$RequestBodyConverter;
      10: return
}
