Compiled from "BuiltInConverters.java"
final class retrofit2.BuiltInConverters$UnitResponseBodyConverter implements retrofit2.Converter<okhttp3.ResponseBody, kotlin.Unit> {
  static final retrofit2.BuiltInConverters$UnitResponseBodyConverter INSTANCE;

  retrofit2.BuiltInConverters$UnitResponseBodyConverter();
    Code:
       0: aload_0
       1: invokespecial #1                  // Method java/lang/Object."<init>":()V
       4: return

  public kotlin.Unit convert(okhttp3.ResponseBody);
    Code:
       0: aload_1
       1: invokevirtual #7                  // Method okhttp3/ResponseBody.close:()V
       4: getstatic     #12                 // Field kotlin/Unit.INSTANCE:Lkotlin/Unit;
       7: areturn

  public java.lang.Object convert(java.lang.Object) throws java.io.IOException;
    Code:
       0: aload_0
       1: aload_1
       2: checkcast     #8                  // class okhttp3/ResponseBody
       5: invokevirtual #18                 // Method convert:(Lokhttp3/ResponseBody;)Lkotlin/Unit;
       8: areturn

  static {};
    Code:
       0: new           #19                 // class retrofit2/BuiltInConverters$UnitResponseBodyConverter
       3: dup
       4: invokespecial #24                 // Method "<init>":()V
       7: putstatic     #25                 // Field INSTANCE:Lretrofit2/BuiltInConverters$UnitResponseBodyConverter;
      10: return
}
