Compiled from "BuiltInConverters.java"
final class retrofit2.BuiltInConverters$ToStringConverter implements retrofit2.Converter<java.lang.Object, java.lang.String> {
  static final retrofit2.BuiltInConverters$ToStringConverter INSTANCE;

  retrofit2.BuiltInConverters$ToStringConverter();
    Code:
       0: aload_0
       1: invokespecial #1                  // Method java/lang/Object."<init>":()V
       4: return

  public java.lang.String convert(java.lang.Object);
    Code:
       0: aload_1
       1: invokevirtual #7                  // Method java/lang/Object.toString:()Ljava/lang/String;
       4: areturn

  public java.lang.Object convert(java.lang.Object) throws java.io.IOException;
    Code:
       0: aload_0
       1: aload_1
       2: invokevirtual #11                 // Method convert:(Ljava/lang/Object;)Ljava/lang/String;
       5: areturn

  static {};
    Code:
       0: new           #12                 // class retrofit2/BuiltInConverters$ToStringConverter
       3: dup
       4: invokespecial #17                 // Method "<init>":()V
       7: putstatic     #18                 // Field INSTANCE:Lretrofit2/BuiltInConverters$ToStringConverter;
      10: return
}
