Compiled from "BuiltInConverters.java"
final class retrofit2.BuiltInConverters extends retrofit2.Converter$Factory {
  private boolean checkForKotlinUnit;

  retrofit2.BuiltInConverters();
    Code:
       0: aload_0
       1: invokespecial #1                  // Method retrofit2/Converter$Factory."<init>":()V
       4: aload_0
       5: iconst_1
       6: putfield      #7                  // Field checkForKotlinUnit:Z
       9: return

  public retrofit2.Converter<okhttp3.ResponseBody, ?> responseBodyConverter(java.lang.reflect.Type, java.lang.annotation.Annotation[], retrofit2.Retrofit);
    Code:
       0: aload_1
       1: ldc           #13                 // class okhttp3/ResponseBody
       3: if_acmpne     25
       6: aload_2
       7: ldc           #15                 // class retrofit2/http/Streaming
       9: invokestatic  #17                 // Method retrofit2/Utils.isAnnotationPresent:([Ljava/lang/annotation/Annotation;Ljava/lang/Class;)Z
      12: ifeq          21
      15: getstatic     #23                 // Field retrofit2/BuiltInConverters$StreamingResponseBodyConverter.INSTANCE:Lretrofit2/BuiltInConverters$StreamingResponseBodyConverter;
      18: goto          24
      21: getstatic     #29                 // Field retrofit2/BuiltInConverters$BufferingResponseBodyConverter.INSTANCE:Lretrofit2/BuiltInConverters$BufferingResponseBodyConverter;
      24: areturn
      25: aload_1
      26: ldc           #34                 // class java/lang/Void
      28: if_acmpne     35
      31: getstatic     #36                 // Field retrofit2/BuiltInConverters$VoidResponseBodyConverter.INSTANCE:Lretrofit2/BuiltInConverters$VoidResponseBodyConverter;
      34: areturn
      35: aload_0
      36: getfield      #7                  // Field checkForKotlinUnit:Z
      39: ifeq          62
      42: aload_1
      43: ldc           #41                 // class kotlin/Unit
      45: if_acmpne     52
      48: getstatic     #43                 // Field retrofit2/BuiltInConverters$UnitResponseBodyConverter.INSTANCE:Lretrofit2/BuiltInConverters$UnitResponseBodyConverter;
      51: areturn
      52: goto          62
      55: astore        4
      57: aload_0
      58: iconst_0
      59: putfield      #7                  // Field checkForKotlinUnit:Z
      62: aconst_null
      63: areturn
    Exception table:
       from    to  target type
          42    51    55   Class java/lang/NoClassDefFoundError

  public retrofit2.Converter<?, okhttp3.RequestBody> requestBodyConverter(java.lang.reflect.Type, java.lang.annotation.Annotation[], java.lang.annotation.Annotation[], retrofit2.Retrofit);
    Code:
       0: ldc           #50                 // class okhttp3/RequestBody
       2: aload_1
       3: invokestatic  #52                 // Method retrofit2/Utils.getRawType:(Ljava/lang/reflect/Type;)Ljava/lang/Class;
       6: invokevirtual #56                 // Method java/lang/Class.isAssignableFrom:(Ljava/lang/Class;)Z
       9: ifeq          16
      12: getstatic     #62                 // Field retrofit2/BuiltInConverters$RequestBodyConverter.INSTANCE:Lretrofit2/BuiltInConverters$RequestBodyConverter;
      15: areturn
      16: aconst_null
      17: areturn
}
