Compiled from "BuiltInConverters.java"
final class retrofit2.BuiltInConverters$StreamingResponseBodyConverter implements retrofit2.Converter<okhttp3.ResponseBody, okhttp3.ResponseBody> {
  static final retrofit2.BuiltInConverters$StreamingResponseBodyConverter INSTANCE;

  retrofit2.BuiltInConverters$StreamingResponseBodyConverter();
    Code:
       0: aload_0
       1: invokespecial #1                  // Method java/lang/Object."<init>":()V
       4: return

  public okhttp3.ResponseBody convert(okhttp3.ResponseBody);
    Code:
       0: aload_1
       1: areturn

  public java.lang.Object convert(java.lang.Object) throws java.io.IOException;
    Code:
       0: aload_0
       1: aload_1
       2: checkcast     #7                  // class okhttp3/ResponseBody
       5: invokevirtual #9                  // Method convert:(Lokhttp3/ResponseBody;)Lokhttp3/ResponseBody;
       8: areturn

  static {};
    Code:
       0: new           #10                 // class retrofit2/BuiltInConverters$StreamingResponseBodyConverter
       3: dup
       4: invokespecial #15                 // Method "<init>":()V
       7: putstatic     #16                 // Field INSTANCE:Lretrofit2/BuiltInConverters$StreamingResponseBodyConverter;
      10: return
}
