Compiled from "BuiltInConverters.java"
final class retrofit2.BuiltInConverters$BufferingResponseBodyConverter implements retrofit2.Converter<okhttp3.ResponseBody, okhttp3.ResponseBody> {
  static final retrofit2.BuiltInConverters$BufferingResponseBodyConverter INSTANCE;

  retrofit2.BuiltInConverters$BufferingResponseBodyConverter();
    Code:
       0: aload_0
       1: invokespecial #1                  // Method java/lang/Object."<init>":()V
       4: return

  public okhttp3.ResponseBody convert(okhttp3.ResponseBody) throws java.io.IOException;
    Code:
       0: aload_1
       1: invokestatic  #7                  // Method retrofit2/Utils.buffer:(Lokhttp3/ResponseBody;)Lokhttp3/ResponseBody;
       4: astore_2
       5: aload_1
       6: invokevirtual #13                 // Method okhttp3/ResponseBody.close:()V
       9: aload_2
      10: areturn
      11: astore_3
      12: aload_1
      13: invokevirtual #13                 // Method okhttp3/ResponseBody.close:()V
      16: aload_3
      17: athrow
    Exception table:
       from    to  target type
           0     5    11   any

  public java.lang.Object convert(java.lang.Object) throws java.io.IOException;
    Code:
       0: aload_0
       1: aload_1
       2: checkcast     #14                 // class okhttp3/ResponseBody
       5: invokevirtual #18                 // Method convert:(Lokhttp3/ResponseBody;)Lokhttp3/ResponseBody;
       8: areturn

  static {};
    Code:
       0: new           #19                 // class retrofit2/BuiltInConverters$BufferingResponseBodyConverter
       3: dup
       4: invokespecial #23                 // Method "<init>":()V
       7: putstatic     #24                 // Field INSTANCE:Lretrofit2/BuiltInConverters$BufferingResponseBodyConverter;
      10: return
}
