Compiled from "CompletableFutureCallAdapterFactory.java"
final class retrofit2.CompletableFutureCallAdapterFactory extends retrofit2.CallAdapter$Factory {
  static final retrofit2.CallAdapter$Factory INSTANCE;

  retrofit2.CompletableFutureCallAdapterFactory();
    Code:
       0: aload_0
       1: invokespecial #1                  // Method retrofit2/CallAdapter$Factory."<init>":()V
       4: return

  public retrofit2.CallAdapter<?, ?> get(java.lang.reflect.Type, java.lang.annotation.Annotation[], retrofit2.Retrofit);
    Code:
       0: aload_1
       1: invokestatic  #7                  // Method getRawType:(Ljava/lang/reflect/Type;)Ljava/lang/Class;
       4: ldc           #13                 // class java/util/concurrent/CompletableFuture
       6: if_acmpeq     11
       9: aconst_null
      10: areturn
      11: aload_1
      12: instanceof    #15                 // class java/lang/reflect/ParameterizedType
      15: ifne          28
      18: new           #17                 // class java/lang/IllegalStateException
      21: dup
      22: ldc           #19                 // String CompletableFuture return type must be parameterized as CompletableFuture<Foo> or CompletableFuture<? extends Foo>
      24: invokespecial #21                 // Method java/lang/IllegalStateException."<init>":(Ljava/lang/String;)V
      27: athrow
      28: iconst_0
      29: aload_1
      30: checkcast     #15                 // class java/lang/reflect/ParameterizedType
      33: invokestatic  #24                 // Method getParameterUpperBound:(ILjava/lang/reflect/ParameterizedType;)Ljava/lang/reflect/Type;
      36: astore        4
      38: aload         4
      40: invokestatic  #7                  // Method getRawType:(Ljava/lang/reflect/Type;)Ljava/lang/Class;
      43: ldc           #28                 // class retrofit2/Response
      45: if_acmpeq     58
      48: new           #30                 // class retrofit2/CompletableFutureCallAdapterFactory$BodyCallAdapter
      51: dup
      52: aload         4
      54: invokespecial #32                 // Method retrofit2/CompletableFutureCallAdapterFactory$BodyCallAdapter."<init>":(Ljava/lang/reflect/Type;)V
      57: areturn
      58: aload         4
      60: instanceof    #15                 // class java/lang/reflect/ParameterizedType
      63: ifne          76
      66: new           #17                 // class java/lang/IllegalStateException
      69: dup
      70: ldc           #35                 // String Response must be parameterized as Response<Foo> or Response<? extends Foo>
      72: invokespecial #21                 // Method java/lang/IllegalStateException."<init>":(Ljava/lang/String;)V
      75: athrow
      76: iconst_0
      77: aload         4
      79: checkcast     #15                 // class java/lang/reflect/ParameterizedType
      82: invokestatic  #24                 // Method getParameterUpperBound:(ILjava/lang/reflect/ParameterizedType;)Ljava/lang/reflect/Type;
      85: astore        5
      87: new           #37                 // class retrofit2/CompletableFutureCallAdapterFactory$ResponseCallAdapter
      90: dup
      91: aload         5
      93: invokespecial #39                 // Method retrofit2/CompletableFutureCallAdapterFactory$ResponseCallAdapter."<init>":(Ljava/lang/reflect/Type;)V
      96: areturn

  static {};
    Code:
       0: new           #8                  // class retrofit2/CompletableFutureCallAdapterFactory
       3: dup
       4: invokespecial #40                 // Method "<init>":()V
       7: putstatic     #41                 // Field INSTANCE:Lretrofit2/CallAdapter$Factory;
      10: return
}
