Compiled from "CompletableFutureCallAdapterFactory.java"
final class retrofit2.CompletableFutureCallAdapterFactory$CallCancelCompletableFuture<T> extends java.util.concurrent.CompletableFuture<T> {
  private final retrofit2.Call<?> call;

  retrofit2.CompletableFutureCallAdapterFactory$CallCancelCompletableFuture(retrofit2.Call<?>);
    Code:
       0: aload_0
       1: invokespecial #1                  // Method java/util/concurrent/CompletableFuture."<init>":()V
       4: aload_0
       5: aload_1
       6: putfield      #7                  // Field call:Lretrofit2/Call;
       9: return

  public boolean cancel(boolean);
    Code:
       0: iload_1
       1: ifeq          13
       4: aload_0
       5: getfield      #7                  // Field call:Lretrofit2/Call;
       8: invokeinterface #13,  1           // InterfaceMethod retrofit2/Call.cancel:()V
      13: aload_0
      14: iload_1
      15: invokespecial #18                 // Method java/util/concurrent/CompletableFuture.cancel:(Z)Z
      18: ireturn
}
