Compiled from "CompletableFutureCallAdapterFactory.java"
class retrofit2.CompletableFutureCallAdapterFactory$BodyCallAdapter$BodyCallback implements retrofit2.Callback<R> {
  private final java.util.concurrent.CompletableFuture<R> future;

  final retrofit2.CompletableFutureCallAdapterFactory$BodyCallAdapter this$0;

  public retrofit2.CompletableFutureCallAdapterFactory$BodyCallAdapter$BodyCallback(java.util.concurrent.CompletableFuture<R>);
    Code:
       0: aload_0
       1: aload_1
       2: putfield      #1                  // Field this$0:Lretrofit2/CompletableFutureCallAdapterFactory$BodyCallAdapter;
       5: aload_0
       6: invokespecial #7                  // Method java/lang/Object."<init>":()V
       9: aload_0
      10: aload_2
      11: putfield      #13                 // Field future:Ljava/util/concurrent/CompletableFuture;
      14: return

  public void onResponse(retrofit2.Call<R>, retrofit2.Response<R>);
    Code:
       0: aload_2
       1: invokevirtual #17                 // Method retrofit2/Response.isSuccessful:()Z
       4: ifeq          22
       7: aload_0
       8: getfield      #13                 // Field future:Ljava/util/concurrent/CompletableFuture;
      11: aload_2
      12: invokevirtual #23                 // Method retrofit2/Response.body:()Ljava/lang/Object;
      15: invokevirtual #27                 // Method java/util/concurrent/CompletableFuture.complete:(Ljava/lang/Object;)Z
      18: pop
      19: goto          38
      22: aload_0
      23: getfield      #13                 // Field future:Ljava/util/concurrent/CompletableFuture;
      26: new           #33                 // class retrofit2/HttpException
      29: dup
      30: aload_2
      31: invokespecial #35                 // Method retrofit2/HttpException."<init>":(Lretrofit2/Response;)V
      34: invokevirtual #38                 // Method java/util/concurrent/CompletableFuture.completeExceptionally:(Ljava/lang/Throwable;)Z
      37: pop
      38: return

  public void onFailure(retrofit2.Call<R>, java.lang.Throwable);
    Code:
       0: aload_0
       1: getfield      #13                 // Field future:Ljava/util/concurrent/CompletableFuture;
       4: aload_2
       5: invokevirtual #38                 // Method java/util/concurrent/CompletableFuture.completeExceptionally:(Ljava/lang/Throwable;)Z
       8: pop
       9: return
}
