Compiled from "CompletableFutureCallAdapterFactory.java"
final class retrofit2.CompletableFutureCallAdapterFactory$BodyCallAdapter<R> implements retrofit2.CallAdapter<R, java.util.concurrent.CompletableFuture<R>> {
  private final java.lang.reflect.Type responseType;

  retrofit2.CompletableFutureCallAdapterFactory$BodyCallAdapter(java.lang.reflect.Type);
    Code:
       0: aload_0
       1: invokespecial #1                  // Method java/lang/Object."<init>":()V
       4: aload_0
       5: aload_1
       6: putfield      #7                  // Field responseType:Ljava/lang/reflect/Type;
       9: return

  public java.lang.reflect.Type responseType();
    Code:
       0: aload_0
       1: getfield      #7                  // Field responseType:Ljava/lang/reflect/Type;
       4: areturn

  public java.util.concurrent.CompletableFuture<R> adapt(retrofit2.Call<R>);
    Code:
       0: new           #13                 // class retrofit2/CompletableFutureCallAdapterFactory$CallCancelCompletableFuture
       3: dup
       4: aload_1
       5: invokespecial #15                 // Method retrofit2/CompletableFutureCallAdapterFactory$CallCancelCompletableFuture."<init>":(Lretrofit2/Call;)V
       8: astore_2
       9: aload_1
      10: new           #18                 // class retrofit2/CompletableFutureCallAdapterFactory$BodyCallAdapter$BodyCallback
      13: dup
      14: aload_0
      15: aload_2
      16: invokespecial #20                 // Method retrofit2/CompletableFutureCallAdapterFactory$BodyCallAdapter$BodyCallback."<init>":(Lretrofit2/CompletableFutureCallAdapterFactory$BodyCallAdapter;Ljava/util/concurrent/CompletableFuture;)V
      19: invokeinterface #23,  2           // InterfaceMethod retrofit2/Call.enqueue:(Lretrofit2/Callback;)V
      24: aload_2
      25: areturn

  public java.lang.Object adapt(retrofit2.Call);
    Code:
       0: aload_0
       1: aload_1
       2: invokevirtual #29                 // Method adapt:(Lretrofit2/Call;)Ljava/util/concurrent/CompletableFuture;
       5: areturn
}
