Compiled from "CompletableFutureCallAdapterFactory.java"
class retrofit2.CompletableFutureCallAdapterFactory$ResponseCallAdapter$ResponseCallback implements retrofit2.Callback<R> {
  private final java.util.concurrent.CompletableFuture<retrofit2.Response<R>> future;

  final retrofit2.CompletableFutureCallAdapterFactory$ResponseCallAdapter this$0;

  public retrofit2.CompletableFutureCallAdapterFactory$ResponseCallAdapter$ResponseCallback(java.util.concurrent.CompletableFuture<retrofit2.Response<R>>);
    Code:
       0: aload_0
       1: aload_1
       2: putfield      #1                  // Field this$0:Lretrofit2/CompletableFutureCallAdapterFactory$ResponseCallAdapter;
       5: aload_0
       6: invokespecial #7                  // Method java/lang/Object."<init>":()V
       9: aload_0
      10: aload_2
      11: putfield      #13                 // Field future:Ljava/util/concurrent/CompletableFuture;
      14: return

  public void onResponse(retrofit2.Call<R>, retrofit2.Response<R>);
    Code:
       0: aload_0
       1: getfield      #13                 // Field future:Ljava/util/concurrent/CompletableFuture;
       4: aload_2
       5: invokevirtual #17                 // Method java/util/concurrent/CompletableFuture.complete:(Ljava/lang/Object;)Z
       8: pop
       9: return

  public void onFailure(retrofit2.Call<R>, java.lang.Throwable);
    Code:
       0: aload_0
       1: getfield      #13                 // Field future:Ljava/util/concurrent/CompletableFuture;
       4: aload_2
       5: invokevirtual #23                 // Method java/util/concurrent/CompletableFuture.completeExceptionally:(Ljava/lang/Throwable;)Z
       8: pop
       9: return
}
