Compiled from "Converter.java"
public abstract class retrofit2.Converter$Factory {
  public retrofit2.Converter$Factory();
    Code:
       0: aload_0
       1: invokespecial #1                  // Method java/lang/Object."<init>":()V
       4: return

  public retrofit2.Converter<okhttp3.ResponseBody, ?> responseBodyConverter(java.lang.reflect.Type, java.lang.annotation.Annotation[], retrofit2.Retrofit);
    Code:
       0: aconst_null
       1: areturn

  public retrofit2.Converter<?, okhttp3.RequestBody> requestBodyConverter(java.lang.reflect.Type, java.lang.annotation.Annotation[], java.lang.annotation.Annotation[], retrofit2.Retrofit);
    Code:
       0: aconst_null
       1: areturn

  public retrofit2.Converter<?, java.lang.String> stringConverter(java.lang.reflect.Type, java.lang.annotation.Annotation[], retrofit2.Retrofit);
    Code:
       0: aconst_null
       1: areturn

  protected static java.lang.reflect.Type getParameterUpperBound(int, java.lang.reflect.ParameterizedType);
    Code:
       0: iload_0
       1: aload_1
       2: invokestatic  #7                  // Method retrofit2/Utils.getParameterUpperBound:(ILjava/lang/reflect/ParameterizedType;)Ljava/lang/reflect/Type;
       5: areturn

  protected static java.lang.Class<?> getRawType(java.lang.reflect.Type);
    Code:
       0: aload_0
       1: invokestatic  #13                 // Method retrofit2/Utils.getRawType:(Ljava/lang/reflect/Type;)Ljava/lang/Class;
       4: areturn
}
