Compiled from "DefaultCallAdapterFactory.java"
class retrofit2.DefaultCallAdapterFactory$1 implements retrofit2.CallAdapter<java.lang.Object, retrofit2.Call<?>> {
  final java.lang.reflect.Type val$responseType;

  final java.util.concurrent.Executor val$executor;

  final retrofit2.DefaultCallAdapterFactory this$0;

  retrofit2.DefaultCallAdapterFactory$1();
    Code:
       0: aload_0
       1: aload_1
       2: putfield      #1                  // Field this$0:Lretrofit2/DefaultCallAdapterFactory;
       5: aload_0
       6: aload_2
       7: putfield      #7                  // Field val$responseType:Ljava/lang/reflect/Type;
      10: aload_0
      11: aload_3
      12: putfield      #11                 // Field val$executor:Ljava/util/concurrent/Executor;
      15: aload_0
      16: invokespecial #15                 // Method java/lang/Object."<init>":()V
      19: return

  public java.lang.reflect.Type responseType();
    Code:
       0: aload_0
       1: getfield      #7                  // Field val$responseType:Ljava/lang/reflect/Type;
       4: areturn

  public retrofit2.Call<java.lang.Object> adapt(retrofit2.Call<java.lang.Object>);
    Code:
       0: aload_0
       1: getfield      #11                 // Field val$executor:Ljava/util/concurrent/Executor;
       4: ifnonnull     11
       7: aload_1
       8: goto          23
      11: new           #21                 // class retrofit2/DefaultCallAdapterFactory$ExecutorCallbackCall
      14: dup
      15: aload_0
      16: getfield      #11                 // Field val$executor:Ljava/util/concurrent/Executor;
      19: aload_1
      20: invokespecial #23                 // Method retrofit2/DefaultCallAdapterFactory$ExecutorCallbackCall."<init>":(Ljava/util/concurrent/Executor;Lretrofit2/Call;)V
      23: areturn

  public java.lang.Object adapt(retrofit2.Call);
    Code:
       0: aload_0
       1: aload_1
       2: invokevirtual #26                 // Method adapt:(Lretrofit2/Call;)Lretrofit2/Call;
       5: areturn
}
