Compiled from "DefaultCallAdapterFactory.java"
class retrofit2.DefaultCallAdapterFactory$ExecutorCallbackCall$1 implements retrofit2.Callback<T> {
  final retrofit2.Callback val$callback;

  final retrofit2.DefaultCallAdapterFactory$ExecutorCallbackCall this$0;

  retrofit2.DefaultCallAdapterFactory$ExecutorCallbackCall$1();
    Code:
       0: aload_0
       1: aload_1
       2: putfield      #1                  // Field this$0:Lretrofit2/DefaultCallAdapterFactory$ExecutorCallbackCall;
       5: aload_0
       6: aload_2
       7: putfield      #7                  // Field val$callback:Lretrofit2/Callback;
      10: aload_0
      11: invokespecial #11                 // Method java/lang/Object."<init>":()V
      14: return

  public void onResponse(retrofit2.Call<T>, retrofit2.Response<T>);
    Code:
       0: aload_0
       1: getfield      #1                  // Field this$0:Lretrofit2/DefaultCallAdapterFactory$ExecutorCallbackCall;
       4: getfield      #17                 // Field retrofit2/DefaultCallAdapterFactory$ExecutorCallbackCall.callbackExecutor:Ljava/util/concurrent/Executor;
       7: aload_0
       8: aload_0
       9: getfield      #7                  // Field val$callback:Lretrofit2/Callback;
      12: aload_2
      13: invokedynamic #23,  0             // InvokeDynamic #0:run:(Lretrofit2/DefaultCallAdapterFactory$ExecutorCallbackCall$1;Lretrofit2/Callback;Lretrofit2/Response;)Ljava/lang/Runnable;
      18: invokeinterface #27,  2           // InterfaceMethod java/util/concurrent/Executor.execute:(Ljava/lang/Runnable;)V
      23: return

  public void onFailure(retrofit2.Call<T>, java.lang.Throwable);
    Code:
       0: aload_0
       1: getfield      #1                  // Field this$0:Lretrofit2/DefaultCallAdapterFactory$ExecutorCallbackCall;
       4: getfield      #17                 // Field retrofit2/DefaultCallAdapterFactory$ExecutorCallbackCall.callbackExecutor:Ljava/util/concurrent/Executor;
       7: aload_0
       8: aload_0
       9: getfield      #7                  // Field val$callback:Lretrofit2/Callback;
      12: aload_2
      13: invokedynamic #33,  0             // InvokeDynamic #1:run:(Lretrofit2/DefaultCallAdapterFactory$ExecutorCallbackCall$1;Lretrofit2/Callback;Ljava/lang/Throwable;)Ljava/lang/Runnable;
      18: invokeinterface #27,  2           // InterfaceMethod java/util/concurrent/Executor.execute:(Ljava/lang/Runnable;)V
      23: return

  private void lambda$onFailure$1(retrofit2.Callback, java.lang.Throwable);
    Code:
       0: aload_1
       1: aload_0
       2: getfield      #1                  // Field this$0:Lretrofit2/DefaultCallAdapterFactory$ExecutorCallbackCall;
       5: aload_2
       6: invokeinterface #36,  3           // InterfaceMethod retrofit2/Callback.onFailure:(Lretrofit2/Call;Ljava/lang/Throwable;)V
      11: return

  private void lambda$onResponse$0(retrofit2.Callback, retrofit2.Response);
    Code:
       0: aload_0
       1: getfield      #1                  // Field this$0:Lretrofit2/DefaultCallAdapterFactory$ExecutorCallbackCall;
       4: getfield      #42                 // Field retrofit2/DefaultCallAdapterFactory$ExecutorCallbackCall.delegate:Lretrofit2/Call;
       7: invokeinterface #46,  1           // InterfaceMethod retrofit2/Call.isCanceled:()Z
      12: ifeq          37
      15: aload_1
      16: aload_0
      17: getfield      #1                  // Field this$0:Lretrofit2/DefaultCallAdapterFactory$ExecutorCallbackCall;
      20: new           #52                 // class java/io/IOException
      23: dup
      24: ldc           #54                 // String Canceled
      26: invokespecial #56                 // Method java/io/IOException."<init>":(Ljava/lang/String;)V
      29: invokeinterface #36,  3           // InterfaceMethod retrofit2/Callback.onFailure:(Lretrofit2/Call;Ljava/lang/Throwable;)V
      34: goto          48
      37: aload_1
      38: aload_0
      39: getfield      #1                  // Field this$0:Lretrofit2/DefaultCallAdapterFactory$ExecutorCallbackCall;
      42: aload_2
      43: invokeinterface #59,  3           // InterfaceMethod retrofit2/Callback.onResponse:(Lretrofit2/Call;Lretrofit2/Response;)V
      48: return
}
