Compiled from "DefaultCallAdapterFactory.java"
final class retrofit2.DefaultCallAdapterFactory extends retrofit2.CallAdapter$Factory {
  private final java.util.concurrent.Executor callbackExecutor;

  retrofit2.DefaultCallAdapterFactory(java.util.concurrent.Executor);
    Code:
       0: aload_0
       1: invokespecial #1                  // Method retrofit2/CallAdapter$Factory."<init>":()V
       4: aload_0
       5: aload_1
       6: putfield      #7                  // Field callbackExecutor:Ljava/util/concurrent/Executor;
       9: return

  public retrofit2.CallAdapter<?, ?> get(java.lang.reflect.Type, java.lang.annotation.Annotation[], retrofit2.Retrofit);
    Code:
       0: aload_1
       1: invokestatic  #13                 // Method getRawType:(Ljava/lang/reflect/Type;)Ljava/lang/Class;
       4: ldc           #17                 // class retrofit2/Call
       6: if_acmpeq     11
       9: aconst_null
      10: areturn
      11: aload_1
      12: instanceof    #19                 // class java/lang/reflect/ParameterizedType
      15: ifne          28
      18: new           #21                 // class java/lang/IllegalArgumentException
      21: dup
      22: ldc           #23                 // String Call return type must be parameterized as Call<Foo> or Call<? extends Foo>
      24: invokespecial #25                 // Method java/lang/IllegalArgumentException."<init>":(Ljava/lang/String;)V
      27: athrow
      28: iconst_0
      29: aload_1
      30: checkcast     #19                 // class java/lang/reflect/ParameterizedType
      33: invokestatic  #28                 // Method retrofit2/Utils.getParameterUpperBound:(ILjava/lang/reflect/ParameterizedType;)Ljava/lang/reflect/Type;
      36: astore        4
      38: aload_2
      39: ldc           #34                 // class retrofit2/SkipCallbackExecutor
      41: invokestatic  #36                 // Method retrofit2/Utils.isAnnotationPresent:([Ljava/lang/annotation/Annotation;Ljava/lang/Class;)Z
      44: ifeq          51
      47: aconst_null
      48: goto          55
      51: aload_0
      52: getfield      #7                  // Field callbackExecutor:Ljava/util/concurrent/Executor;
      55: astore        5
      57: new           #40                 // class retrofit2/DefaultCallAdapterFactory$1
      60: dup
      61: aload_0
      62: aload         4
      64: aload         5
      66: invokespecial #42                 // Method retrofit2/DefaultCallAdapterFactory$1."<init>":(Lretrofit2/DefaultCallAdapterFactory;Ljava/lang/reflect/Type;Ljava/util/concurrent/Executor;)V
      69: areturn
}
