Compiled from "HttpServiceMethod.java"
abstract class retrofit2.HttpServiceMethod<ResponseT, ReturnT> extends retrofit2.ServiceMethod<ReturnT> {
  private final retrofit2.RequestFactory requestFactory;

  private final okhttp3.Call$Factory callFactory;

  private final retrofit2.Converter<okhttp3.ResponseBody, ResponseT> responseConverter;

  static <ResponseT, ReturnT> retrofit2.HttpServiceMethod<ResponseT, ReturnT> parseAnnotations(retrofit2.Retrofit, java.lang.reflect.Method, retrofit2.RequestFactory);
    Code:
       0: aload_2
       1: getfield      #1                  // Field retrofit2/RequestFactory.isKotlinSuspendFunction:Z
       4: istore_3
       5: iconst_0
       6: istore        4
       8: iconst_0
       9: istore        5
      11: aload_1
      12: invokevirtual #7                  // Method java/lang/reflect/Method.getAnnotations:()[Ljava/lang/annotation/Annotation;
      15: astore        6
      17: iload_3
      18: ifeq          107
      21: aload_1
      22: invokevirtual #13                 // Method java/lang/reflect/Method.getGenericParameterTypes:()[Ljava/lang/reflect/Type;
      25: astore        8
      27: iconst_0
      28: aload         8
      30: aload         8
      32: arraylength
      33: iconst_1
      34: isub
      35: aaload
      36: checkcast     #17                 // class java/lang/reflect/ParameterizedType
      39: invokestatic  #19                 // Method retrofit2/Utils.getParameterLowerBound:(ILjava/lang/reflect/ParameterizedType;)Ljava/lang/reflect/Type;
      42: astore        9
      44: aload         9
      46: invokestatic  #25                 // Method retrofit2/Utils.getRawType:(Ljava/lang/reflect/Type;)Ljava/lang/Class;
      49: ldc           #29                 // class retrofit2/Response
      51: if_acmpne     76
      54: aload         9
      56: instanceof    #17                 // class java/lang/reflect/ParameterizedType
      59: ifeq          76
      62: iconst_0
      63: aload         9
      65: checkcast     #17                 // class java/lang/reflect/ParameterizedType
      68: invokestatic  #31                 // Method retrofit2/Utils.getParameterUpperBound:(ILjava/lang/reflect/ParameterizedType;)Ljava/lang/reflect/Type;
      71: astore        9
      73: iconst_1
      74: istore        4
      76: new           #34                 // class retrofit2/Utils$ParameterizedTypeImpl
      79: dup
      80: aconst_null
      81: ldc           #36                 // class retrofit2/Call
      83: iconst_1
      84: anewarray     #38                 // class java/lang/reflect/Type
      87: dup
      88: iconst_0
      89: aload         9
      91: aastore
      92: invokespecial #40                 // Method retrofit2/Utils$ParameterizedTypeImpl."<init>":(Ljava/lang/reflect/Type;Ljava/lang/reflect/Type;[Ljava/lang/reflect/Type;)V
      95: astore        7
      97: aload         6
      99: invokestatic  #44                 // Method retrofit2/SkipCallbackExecutorImpl.ensurePresent:([Ljava/lang/annotation/Annotation;)[Ljava/lang/annotation/Annotation;
     102: astore        6
     104: goto          113
     107: aload_1
     108: invokevirtual #50                 // Method java/lang/reflect/Method.getGenericReturnType:()Ljava/lang/reflect/Type;
     111: astore        7
     113: aload_0
     114: aload_1
     115: aload         7
     117: aload         6
     119: invokestatic  #54                 // Method createCallAdapter:(Lretrofit2/Retrofit;Ljava/lang/reflect/Method;Ljava/lang/reflect/Type;[Ljava/lang/annotation/Annotation;)Lretrofit2/CallAdapter;
     122: astore        8
     124: aload         8
     126: invokeinterface #60,  1           // InterfaceMethod retrofit2/CallAdapter.responseType:()Ljava/lang/reflect/Type;
     131: astore        9
     133: aload         9
     135: ldc           #65                 // class okhttp3/Response
     137: if_acmpne     180
     140: aload_1
     141: new           #67                 // class java/lang/StringBuilder
     144: dup
     145: invokespecial #69                 // Method java/lang/StringBuilder."<init>":()V
     148: ldc           #72                 // String \'
     150: invokevirtual #74                 // Method java/lang/StringBuilder.append:(Ljava/lang/String;)Ljava/lang/StringBuilder;
     153: aload         9
     155: invokestatic  #25                 // Method retrofit2/Utils.getRawType:(Ljava/lang/reflect/Type;)Ljava/lang/Class;
     158: invokevirtual #78                 // Method java/lang/Class.getName:()Ljava/lang/String;
     161: invokevirtual #74                 // Method java/lang/StringBuilder.append:(Ljava/lang/String;)Ljava/lang/StringBuilder;
     164: ldc           #84                 // String \' is not a valid response body type. Did you mean ResponseBody?
     166: invokevirtual #74                 // Method java/lang/StringBuilder.append:(Ljava/lang/String;)Ljava/lang/StringBuilder;
     169: invokevirtual #86                 // Method java/lang/StringBuilder.toString:()Ljava/lang/String;
     172: iconst_0
     173: anewarray     #89                 // class java/lang/Object
     176: invokestatic  #91                 // Method retrofit2/Utils.methodError:(Ljava/lang/reflect/Method;Ljava/lang/String;[Ljava/lang/Object;)Ljava/lang/RuntimeException;
     179: athrow
     180: aload         9
     182: ldc           #29                 // class retrofit2/Response
     184: if_acmpne     198
     187: aload_1
     188: ldc           #95                 // String Response must include generic type (e.g., Response<String>)
     190: iconst_0
     191: anewarray     #89                 // class java/lang/Object
     194: invokestatic  #91                 // Method retrofit2/Utils.methodError:(Ljava/lang/reflect/Method;Ljava/lang/String;[Ljava/lang/Object;)Ljava/lang/RuntimeException;
     197: athrow
     198: aload_2
     199: getfield      #97                 // Field retrofit2/RequestFactory.httpMethod:Ljava/lang/String;
     202: ldc           #101                // String HEAD
     204: invokevirtual #103                // Method java/lang/String.equals:(Ljava/lang/Object;)Z
     207: ifeq          231
     210: ldc           #109                // class java/lang/Void
     212: aload         9
     214: invokevirtual #111                // Method java/lang/Object.equals:(Ljava/lang/Object;)Z
     217: ifne          231
     220: aload_1
     221: ldc           #112                // String HEAD method must use Void as response type.
     223: iconst_0
     224: anewarray     #89                 // class java/lang/Object
     227: invokestatic  #91                 // Method retrofit2/Utils.methodError:(Ljava/lang/reflect/Method;Ljava/lang/String;[Ljava/lang/Object;)Ljava/lang/RuntimeException;
     230: athrow
     231: aload_0
     232: aload_1
     233: aload         9
     235: invokestatic  #114                // Method createResponseConverter:(Lretrofit2/Retrofit;Ljava/lang/reflect/Method;Ljava/lang/reflect/Type;)Lretrofit2/Converter;
     238: astore        10
     240: aload_0
     241: getfield      #118                // Field retrofit2/Retrofit.callFactory:Lokhttp3/Call$Factory;
     244: astore        11
     246: iload_3
     247: ifne          265
     250: new           #124                // class retrofit2/HttpServiceMethod$CallAdapted
     253: dup
     254: aload_2
     255: aload         11
     257: aload         10
     259: aload         8
     261: invokespecial #126                // Method retrofit2/HttpServiceMethod$CallAdapted."<init>":(Lretrofit2/RequestFactory;Lokhttp3/Call$Factory;Lretrofit2/Converter;Lretrofit2/CallAdapter;)V
     264: areturn
     265: iload         4
     267: ifeq          285
     270: new           #129                // class retrofit2/HttpServiceMethod$SuspendForResponse
     273: dup
     274: aload_2
     275: aload         11
     277: aload         10
     279: aload         8
     281: invokespecial #131                // Method retrofit2/HttpServiceMethod$SuspendForResponse."<init>":(Lretrofit2/RequestFactory;Lokhttp3/Call$Factory;Lretrofit2/Converter;Lretrofit2/CallAdapter;)V
     284: areturn
     285: new           #132                // class retrofit2/HttpServiceMethod$SuspendForBody
     288: dup
     289: aload_2
     290: aload         11
     292: aload         10
     294: aload         8
     296: iload         5
     298: invokespecial #134                // Method retrofit2/HttpServiceMethod$SuspendForBody."<init>":(Lretrofit2/RequestFactory;Lokhttp3/Call$Factory;Lretrofit2/Converter;Lretrofit2/CallAdapter;Z)V
     301: areturn

  private static <ResponseT, ReturnT> retrofit2.CallAdapter<ResponseT, ReturnT> createCallAdapter(retrofit2.Retrofit, java.lang.reflect.Method, java.lang.reflect.Type, java.lang.annotation.Annotation[]);
    Code:
       0: aload_0
       1: aload_2
       2: aload_3
       3: invokevirtual #137                // Method retrofit2/Retrofit.callAdapter:(Ljava/lang/reflect/Type;[Ljava/lang/annotation/Annotation;)Lretrofit2/CallAdapter;
       6: areturn
       7: astore        4
       9: aload_1
      10: aload         4
      12: ldc           #143                // String Unable to create call adapter for %s
      14: iconst_1
      15: anewarray     #89                 // class java/lang/Object
      18: dup
      19: iconst_0
      20: aload_2
      21: aastore
      22: invokestatic  #145                // Method retrofit2/Utils.methodError:(Ljava/lang/reflect/Method;Ljava/lang/Throwable;Ljava/lang/String;[Ljava/lang/Object;)Ljava/lang/RuntimeException;
      25: athrow
    Exception table:
       from    to  target type
           0     6     7   Class java/lang/RuntimeException

  private static <ResponseT> retrofit2.Converter<okhttp3.ResponseBody, ResponseT> createResponseConverter(retrofit2.Retrofit, java.lang.reflect.Method, java.lang.reflect.Type);
    Code:
       0: aload_1
       1: invokevirtual #7                  // Method java/lang/reflect/Method.getAnnotations:()[Ljava/lang/annotation/Annotation;
       4: astore_3
       5: aload_0
       6: aload_2
       7: aload_3
       8: invokevirtual #148                // Method retrofit2/Retrofit.responseBodyConverter:(Ljava/lang/reflect/Type;[Ljava/lang/annotation/Annotation;)Lretrofit2/Converter;
      11: areturn
      12: astore        4
      14: aload_1
      15: aload         4
      17: ldc           #152                // String Unable to create converter for %s
      19: iconst_1
      20: anewarray     #89                 // class java/lang/Object
      23: dup
      24: iconst_0
      25: aload_2
      26: aastore
      27: invokestatic  #145                // Method retrofit2/Utils.methodError:(Ljava/lang/reflect/Method;Ljava/lang/Throwable;Ljava/lang/String;[Ljava/lang/Object;)Ljava/lang/RuntimeException;
      30: athrow
    Exception table:
       from    to  target type
           5    11    12   Class java/lang/RuntimeException

  retrofit2.HttpServiceMethod(retrofit2.RequestFactory, okhttp3.Call$Factory, retrofit2.Converter<okhttp3.ResponseBody, ResponseT>);
    Code:
       0: aload_0
       1: invokespecial #154                // Method retrofit2/ServiceMethod."<init>":()V
       4: aload_0
       5: aload_1
       6: putfield      #157                // Field requestFactory:Lretrofit2/RequestFactory;
       9: aload_0
      10: aload_2
      11: putfield      #161                // Field callFactory:Lokhttp3/Call$Factory;
      14: aload_0
      15: aload_3
      16: putfield      #162                // Field responseConverter:Lretrofit2/Converter;
      19: return

  final ReturnT invoke(java.lang.Object[]);
    Code:
       0: new           #166                // class retrofit2/OkHttpCall
       3: dup
       4: aload_0
       5: getfield      #157                // Field requestFactory:Lretrofit2/RequestFactory;
       8: aload_1
       9: aload_0
      10: getfield      #161                // Field callFactory:Lokhttp3/Call$Factory;
      13: aload_0
      14: getfield      #162                // Field responseConverter:Lretrofit2/Converter;
      17: invokespecial #168                // Method retrofit2/OkHttpCall."<init>":(Lretrofit2/RequestFactory;[Ljava/lang/Object;Lokhttp3/Call$Factory;Lretrofit2/Converter;)V
      20: astore_2
      21: aload_0
      22: aload_2
      23: aload_1
      24: invokevirtual #171                // Method adapt:(Lretrofit2/Call;[Ljava/lang/Object;)Ljava/lang/Object;
      27: areturn

  protected abstract ReturnT adapt(retrofit2.Call<ResponseT>, java.lang.Object[]);
}
