Compiled from "HttpServiceMethod.java"
final class retrofit2.HttpServiceMethod$SuspendForBody<ResponseT> extends retrofit2.HttpServiceMethod<ResponseT, java.lang.Object> {
  private final retrofit2.CallAdapter<ResponseT, retrofit2.Call<ResponseT>> callAdapter;

  private final boolean isNullable;

  retrofit2.HttpServiceMethod$SuspendForBody(retrofit2.RequestFactory, okhttp3.Call$Factory, retrofit2.Converter<okhttp3.ResponseBody, ResponseT>, retrofit2.CallAdapter<ResponseT, retrofit2.Call<ResponseT>>, boolean);
    Code:
       0: aload_0
       1: aload_1
       2: aload_2
       3: aload_3
       4: invokespecial #1                  // Method retrofit2/HttpServiceMethod."<init>":(Lretrofit2/RequestFactory;Lokhttp3/Call$Factory;Lretrofit2/Converter;)V
       7: aload_0
       8: aload         4
      10: putfield      #7                  // Field callAdapter:Lretrofit2/CallAdapter;
      13: aload_0
      14: iload         5
      16: putfield      #13                 // Field isNullable:Z
      19: return

  protected java.lang.Object adapt(retrofit2.Call<ResponseT>, java.lang.Object[]);
    Code:
       0: aload_0
       1: getfield      #7                  // Field callAdapter:Lretrofit2/CallAdapter;
       4: aload_1
       5: invokeinterface #17,  2           // InterfaceMethod retrofit2/CallAdapter.adapt:(Lretrofit2/Call;)Ljava/lang/Object;
      10: checkcast     #23                 // class retrofit2/Call
      13: astore_1
      14: aload_2
      15: aload_2
      16: arraylength
      17: iconst_1
      18: isub
      19: aaload
      20: checkcast     #25                 // class kotlin/coroutines/Continuation
      23: astore_3
      24: aload_0
      25: getfield      #13                 // Field isNullable:Z
      28: ifeq          39
      31: aload_1
      32: aload_3
      33: invokestatic  #27                 // Method retrofit2/KotlinExtensions.awaitNullable:(Lretrofit2/Call;Lkotlin/coroutines/Continuation;)Ljava/lang/Object;
      36: goto          44
      39: aload_1
      40: aload_3
      41: invokestatic  #33                 // Method retrofit2/KotlinExtensions.await:(Lretrofit2/Call;Lkotlin/coroutines/Continuation;)Ljava/lang/Object;
      44: areturn
      45: astore        4
      47: aload         4
      49: aload_3
      50: invokestatic  #38                 // Method retrofit2/KotlinExtensions.suspendAndThrow:(Ljava/lang/Exception;Lkotlin/coroutines/Continuation;)Ljava/lang/Object;
      53: areturn
    Exception table:
       from    to  target type
          24    44    45   Class java/lang/Exception
}
