Compiled from "HttpServiceMethod.java"
final class retrofit2.HttpServiceMethod$CallAdapted<ResponseT, ReturnT> extends retrofit2.HttpServiceMethod<ResponseT, ReturnT> {
  private final retrofit2.CallAdapter<ResponseT, ReturnT> callAdapter;

  retrofit2.HttpServiceMethod$CallAdapted(retrofit2.RequestFactory, okhttp3.Call$Factory, retrofit2.Converter<okhttp3.ResponseBody, ResponseT>, retrofit2.CallAdapter<ResponseT, ReturnT>);
    Code:
       0: aload_0
       1: aload_1
       2: aload_2
       3: aload_3
       4: invokespecial #1                  // Method retrofit2/HttpServiceMethod."<init>":(Lretrofit2/RequestFactory;Lokhttp3/Call$Factory;Lretrofit2/Converter;)V
       7: aload_0
       8: aload         4
      10: putfield      #7                  // Field callAdapter:Lretrofit2/CallAdapter;
      13: return

  protected ReturnT adapt(retrofit2.Call<ResponseT>, java.lang.Object[]);
    Code:
       0: aload_0
       1: getfield      #7                  // Field callAdapter:Lretrofit2/CallAdapter;
       4: aload_1
       5: invokeinterface #13,  2           // InterfaceMethod retrofit2/CallAdapter.adapt:(Lretrofit2/Call;)Ljava/lang/Object;
      10: areturn
}
