Compiled from "HttpException.java"
public class retrofit2.HttpException extends java.lang.RuntimeException {
  private final int code;

  private final java.lang.String message;

  private final transient retrofit2.Response<?> response;

  private static java.lang.String getMessage(retrofit2.Response<?>);
    Code:
       0: aload_0
       1: ldc           #1                  // String response == null
       3: invokestatic  #3                  // Method java/util/Objects.requireNonNull:(Ljava/lang/Object;Ljava/lang/String;)Ljava/lang/Object;
       6: pop
       7: new           #9                  // class java/lang/StringBuilder
      10: dup
      11: invokespecial #11                 // Method java/lang/StringBuilder."<init>":()V
      14: ldc           #15                 // String HTTP
      16: invokevirtual #17                 // Method java/lang/StringBuilder.append:(Ljava/lang/String;)Ljava/lang/StringBuilder;
      19: aload_0
      20: invokevirtual #21                 // Method retrofit2/Response.code:()I
      23: invokevirtual #27                 // Method java/lang/StringBuilder.append:(I)Ljava/lang/StringBuilder;
      26: ldc           #30                 // String
      28: invokevirtual #17                 // Method java/lang/StringBuilder.append:(Ljava/lang/String;)Ljava/lang/StringBuilder;
      31: aload_0
      32: invokevirtual #32                 // Method retrofit2/Response.message:()Ljava/lang/String;
      35: invokevirtual #17                 // Method java/lang/StringBuilder.append:(Ljava/lang/String;)Ljava/lang/StringBuilder;
      38: invokevirtual #36                 // Method java/lang/StringBuilder.toString:()Ljava/lang/String;
      41: areturn

  public retrofit2.HttpException(retrofit2.Response<?>);
    Code:
       0: aload_0
       1: aload_1
       2: invokestatic  #39                 // Method getMessage:(Lretrofit2/Response;)Ljava/lang/String;
       5: invokespecial #45                 // Method java/lang/RuntimeException."<init>":(Ljava/lang/String;)V
       8: aload_0
       9: aload_1
      10: invokevirtual #21                 // Method retrofit2/Response.code:()I
      13: putfield      #50                 // Field code:I
      16: aload_0
      17: aload_1
      18: invokevirtual #32                 // Method retrofit2/Response.message:()Ljava/lang/String;
      21: putfield      #53                 // Field message:Ljava/lang/String;
      24: aload_0
      25: aload_1
      26: putfield      #56                 // Field response:Lretrofit2/Response;
      29: return

  public int code();
    Code:
       0: aload_0
       1: getfield      #50                 // Field code:I
       4: ireturn

  public java.lang.String message();
    Code:
       0: aload_0
       1: getfield      #53                 // Field message:Ljava/lang/String;
       4: areturn

  public retrofit2.Response<?> response();
    Code:
       0: aload_0
       1: getfield      #56                 // Field response:Lretrofit2/Response;
       4: areturn
}
