Compiled from "Invocation.java"
public final class retrofit2.Invocation {
  private final java.lang.reflect.Method method;

  private final java.util.List<?> arguments;

  public static retrofit2.Invocation of(java.lang.reflect.Method, java.util.List<?>);
    Code:
       0: aload_0
       1: ldc           #1                  // String method == null
       3: invokestatic  #3                  // Method java/util/Objects.requireNonNull:(Ljava/lang/Object;Ljava/lang/String;)Ljava/lang/Object;
       6: pop
       7: aload_1
       8: ldc           #9                  // String arguments == null
      10: invokestatic  #3                  // Method java/util/Objects.requireNonNull:(Ljava/lang/Object;Ljava/lang/String;)Ljava/lang/Object;
      13: pop
      14: new           #11                 // class retrofit2/Invocation
      17: dup
      18: aload_0
      19: new           #13                 // class java/util/ArrayList
      22: dup
      23: aload_1
      24: invokespecial #15                 // Method java/util/ArrayList."<init>":(Ljava/util/Collection;)V
      27: invokespecial #19                 // Method "<init>":(Ljava/lang/reflect/Method;Ljava/util/List;)V
      30: areturn

  retrofit2.Invocation(java.lang.reflect.Method, java.util.List<?>);
    Code:
       0: aload_0
       1: invokespecial #22                 // Method java/lang/Object."<init>":()V
       4: aload_0
       5: aload_1
       6: putfield      #27                 // Field method:Ljava/lang/reflect/Method;
       9: aload_0
      10: aload_2
      11: invokestatic  #31                 // Method java/util/Collections.unmodifiableList:(Ljava/util/List;)Ljava/util/List;
      14: putfield      #37                 // Field arguments:Ljava/util/List;
      17: return

  public java.lang.reflect.Method method();
    Code:
       0: aload_0
       1: getfield      #27                 // Field method:Ljava/lang/reflect/Method;
       4: areturn

  public java.util.List<?> arguments();
    Code:
       0: aload_0
       1: getfield      #37                 // Field arguments:Ljava/util/List;
       4: areturn

  public java.lang.String toString();
    Code:
       0: ldc           #41                 // String %s.%s() %s
       2: iconst_3
       3: anewarray     #23                 // class java/lang/Object
       6: dup
       7: iconst_0
       8: aload_0
       9: getfield      #27                 // Field method:Ljava/lang/reflect/Method;
      12: invokevirtual #43                 // Method java/lang/reflect/Method.getDeclaringClass:()Ljava/lang/Class;
      15: invokevirtual #49                 // Method java/lang/Class.getName:()Ljava/lang/String;
      18: aastore
      19: dup
      20: iconst_1
      21: aload_0
      22: getfield      #27                 // Field method:Ljava/lang/reflect/Method;
      25: invokevirtual #55                 // Method java/lang/reflect/Method.getName:()Ljava/lang/String;
      28: aastore
      29: dup
      30: iconst_2
      31: aload_0
      32: getfield      #37                 // Field arguments:Ljava/util/List;
      35: aastore
      36: invokestatic  #56                 // Method java/lang/String.format:(Ljava/lang/String;[Ljava/lang/Object;)Ljava/lang/String;
      39: areturn
}
