Compiled from "KotlinExtensions.kt"
final class retrofit2.KotlinExtensions$awaitResponse$$inlined$suspendCancellableCoroutine$lambda$1 extends kotlin.jvm.internal.Lambda implements kotlin.jvm.functions.Function1<java.lang.Throwable, kotlin.Unit> {
  final retrofit2.Call $this_awaitResponse$inlined;

  retrofit2.KotlinExtensions$awaitResponse$$inlined$suspendCancellableCoroutine$lambda$1(retrofit2.Call);
    Code:
       0: aload_0
       1: aload_1
       2: putfield      #18                 // Field $this_awaitResponse$inlined:Lretrofit2/Call;
       5: aload_0
       6: iconst_1
       7: invokespecial #21                 // Method kotlin/jvm/internal/Lambda."<init>":(I)V
      10: return

  public java.lang.Object invoke(java.lang.Object);
    Code:
       0: aload_0
       1: aload_1
       2: checkcast     #25                 // class java/lang/Throwable
       5: invokevirtual #28                 // Method invoke:(Ljava/lang/Throwable;)V
       8: getstatic     #34                 // Field kotlin/Unit.INSTANCE:Lkotlin/Unit;
      11: areturn

  public final void invoke(java.lang.Throwable);
    Code:
       0: aload_0
       1: getfield      #18                 // Field $this_awaitResponse$inlined:Lretrofit2/Call;
       4: invokeinterface #41,  1           // InterfaceMethod retrofit2/Call.cancel:()V
       9: return
}
