Compiled from "KotlinExtensions.kt"
final class retrofit2.KotlinExtensions$suspendAndThrow$1 extends kotlin.coroutines.jvm.internal.ContinuationImpl {
  java.lang.Object result;

  int label;

  java.lang.Object L$0;

  public final java.lang.Object invokeSuspend(java.lang.Object);
    Code:
       0: aload_0
       1: aload_1
       2: putfield      #12                 // Field result:Ljava/lang/Object;
       5: aload_0
       6: aload_0
       7: getfield      #16                 // Field label:I
      10: ldc           #17                 // int -2147483648
      12: ior
      13: putfield      #16                 // Field label:I
      16: aconst_null
      17: aload_0
      18: invokestatic  #23                 // Method retrofit2/KotlinExtensions.suspendAndThrow:(Ljava/lang/Exception;Lkotlin/coroutines/Continuation;)Ljava/lang/Object;
      21: areturn

  retrofit2.KotlinExtensions$suspendAndThrow$1(kotlin.coroutines.Continuation);
    Code:
       0: aload_0
       1: aload_1
       2: invokespecial #30                 // Method kotlin/coroutines/jvm/internal/ContinuationImpl."<init>":(Lkotlin/coroutines/Continuation;)V
       5: return
}
