Compiled from "KotlinExtensions.kt"
public final class retrofit2.KotlinExtensions$await$4$2 implements retrofit2.Callback<T> {
  final kotlinx.coroutines.CancellableContinuation $continuation;

  public void onResponse(retrofit2.Call<T>, retrofit2.Response<T>);
    Code:
       0: aload_1
       1: ldc           #18                 // String call
       3: invokestatic  #24                 // Method kotlin/jvm/internal/Intrinsics.checkParameterIsNotNull:(Ljava/lang/Object;Ljava/lang/String;)V
       6: aload_2
       7: ldc           #26                 // String response
       9: invokestatic  #24                 // Method kotlin/jvm/internal/Intrinsics.checkParameterIsNotNull:(Ljava/lang/Object;Ljava/lang/String;)V
      12: aload_2
      13: invokevirtual #32                 // Method retrofit2/Response.isSuccessful:()Z
      16: ifeq          66
      19: aload_0
      20: getfield      #36                 // Field $continuation:Lkotlinx/coroutines/CancellableContinuation;
      23: checkcast     #38                 // class kotlin/coroutines/Continuation
      26: astore_3
      27: aload_2
      28: invokevirtual #42                 // Method retrofit2/Response.body:()Ljava/lang/Object;
      31: astore        4
      33: iconst_0
      34: istore        5
      36: aload_3
      37: getstatic     #48                 // Field kotlin/Result.Companion:Lkotlin/Result$Companion;
      40: astore        6
      42: astore        7
      44: iconst_0
      45: istore        8
      47: aload         4
      49: invokestatic  #52                 // Method kotlin/Result."constructor-impl":(Ljava/lang/Object;)Ljava/lang/Object;
      52: astore        9
      54: aload         7
      56: aload         9
      58: invokeinterface #56,  2           // InterfaceMethod kotlin/coroutines/Continuation.resumeWith:(Ljava/lang/Object;)V
      63: goto          120
      66: aload_0
      67: getfield      #36                 // Field $continuation:Lkotlinx/coroutines/CancellableContinuation;
      70: checkcast     #38                 // class kotlin/coroutines/Continuation
      73: astore_3
      74: new           #58                 // class retrofit2/HttpException
      77: dup
      78: aload_2
      79: invokespecial #62                 // Method retrofit2/HttpException."<init>":(Lretrofit2/Response;)V
      82: checkcast     #64                 // class java/lang/Throwable
      85: astore        4
      87: iconst_0
      88: istore        5
      90: aload_3
      91: getstatic     #48                 // Field kotlin/Result.Companion:Lkotlin/Result$Companion;
      94: astore        6
      96: astore        7
      98: iconst_0
      99: istore        8
     101: aload         4
     103: invokestatic  #70                 // Method kotlin/ResultKt.createFailure:(Ljava/lang/Throwable;)Ljava/lang/Object;
     106: invokestatic  #52                 // Method kotlin/Result."constructor-impl":(Ljava/lang/Object;)Ljava/lang/Object;
     109: astore        9
     111: aload         7
     113: aload         9
     115: invokeinterface #56,  2           // InterfaceMethod kotlin/coroutines/Continuation.resumeWith:(Ljava/lang/Object;)V
     120: return

  public void onFailure(retrofit2.Call<T>, java.lang.Throwable);
    Code:
       0: aload_1
       1: ldc           #18                 // String call
       3: invokestatic  #24                 // Method kotlin/jvm/internal/Intrinsics.checkParameterIsNotNull:(Ljava/lang/Object;Ljava/lang/String;)V
       6: aload_2
       7: ldc           #83                 // String t
       9: invokestatic  #24                 // Method kotlin/jvm/internal/Intrinsics.checkParameterIsNotNull:(Ljava/lang/Object;Ljava/lang/String;)V
      12: aload_0
      13: getfield      #36                 // Field $continuation:Lkotlinx/coroutines/CancellableContinuation;
      16: checkcast     #38                 // class kotlin/coroutines/Continuation
      19: astore_3
      20: iconst_0
      21: istore        4
      23: aload_3
      24: getstatic     #48                 // Field kotlin/Result.Companion:Lkotlin/Result$Companion;
      27: astore        5
      29: astore        6
      31: iconst_0
      32: istore        7
      34: aload_2
      35: invokestatic  #70                 // Method kotlin/ResultKt.createFailure:(Ljava/lang/Throwable;)Ljava/lang/Object;
      38: invokestatic  #52                 // Method kotlin/Result."constructor-impl":(Ljava/lang/Object;)Ljava/lang/Object;
      41: astore        8
      43: aload         6
      45: aload         8
      47: invokeinterface #56,  2           // InterfaceMethod kotlin/coroutines/Continuation.resumeWith:(Ljava/lang/Object;)V
      52: return

  retrofit2.KotlinExtensions$await$4$2(kotlinx.coroutines.CancellableContinuation);
    Code:
       0: aload_0
       1: aload_1
       2: putfield      #36                 // Field $continuation:Lkotlinx/coroutines/CancellableContinuation;
       5: aload_0
       6: invokespecial #88                 // Method java/lang/Object."<init>":()V
       9: return
}
