Compiled from "KotlinExtensions.kt"
public final class retrofit2.KotlinExtensions {
  public static final <T> T create(retrofit2.Retrofit);
    Code:
       0: ldc           #12                 // int 0
       2: istore_1
       3: aload_0
       4: ldc           #14                 // String $this$create
       6: invokestatic  #20                 // Method kotlin/jvm/internal/Intrinsics.checkParameterIsNotNull:(Ljava/lang/Object;Ljava/lang/String;)V
       9: aload_0
      10: iconst_4
      11: ldc           #22                 // String T
      13: invokestatic  #26                 // Method kotlin/jvm/internal/Intrinsics.reifiedOperationMarker:(ILjava/lang/String;)V
      16: ldc           #4                  // class java/lang/Object
      18: invokevirtual #31                 // Method retrofit2/Retrofit.create:(Ljava/lang/Class;)Ljava/lang/Object;
      21: areturn

  public static final <T> java.lang.Object await(retrofit2.Call<T>, kotlin.coroutines.Continuation<? super T>);
    Code:
       0: iconst_0
       1: istore_2
       2: aload_1
       3: astore_3
       4: iconst_0
       5: istore        4
       7: new           #40                 // class kotlinx/coroutines/CancellableContinuationImpl
      10: dup
      11: aload_3
      12: invokestatic  #46                 // Method kotlin/coroutines/intrinsics/IntrinsicsKt.intercepted:(Lkotlin/coroutines/Continuation;)Lkotlin/coroutines/Continuation;
      15: iconst_1
      16: invokespecial #50                 // Method kotlinx/coroutines/CancellableContinuationImpl."<init>":(Lkotlin/coroutines/Continuation;I)V
      19: astore        5
      21: aload         5
      23: checkcast     #52                 // class kotlinx/coroutines/CancellableContinuation
      26: astore        6
      28: iconst_0
      29: istore        7
      31: aload         6
      33: new           #54                 // class retrofit2/KotlinExtensions$await$$inlined$suspendCancellableCoroutine$lambda$1
      36: dup
      37: aload_0
      38: invokespecial #57                 // Method retrofit2/KotlinExtensions$await$$inlined$suspendCancellableCoroutine$lambda$1."<init>":(Lretrofit2/Call;)V
      41: checkcast     #59                 // class kotlin/jvm/functions/Function1
      44: invokeinterface #63,  2           // InterfaceMethod kotlinx/coroutines/CancellableContinuation.invokeOnCancellation:(Lkotlin/jvm/functions/Function1;)V
      49: aload_0
      50: new           #65                 // class retrofit2/KotlinExtensions$await$2$2
      53: dup
      54: aload         6
      56: invokespecial #68                 // Method retrofit2/KotlinExtensions$await$2$2."<init>":(Lkotlinx/coroutines/CancellableContinuation;)V
      59: checkcast     #70                 // class retrofit2/Callback
      62: invokeinterface #76,  2           // InterfaceMethod retrofit2/Call.enqueue:(Lretrofit2/Callback;)V
      67: nop
      68: aload         5
      70: invokevirtual #80                 // Method kotlinx/coroutines/CancellableContinuationImpl.getResult:()Ljava/lang/Object;
      73: nop
      74: dup
      75: invokestatic  #83                 // Method kotlin/coroutines/intrinsics/IntrinsicsKt.getCOROUTINE_SUSPENDED:()Ljava/lang/Object;
      78: if_acmpne     85
      81: aload_1
      82: invokestatic  #89                 // Method kotlin/coroutines/jvm/internal/DebugProbesKt.probeCoroutineSuspended:(Lkotlin/coroutines/Continuation;)V
      85: areturn

  public static final <T> java.lang.Object awaitNullable(retrofit2.Call<T>, kotlin.coroutines.Continuation<? super T>);
    Code:
       0: iconst_0
       1: istore_2
       2: aload_1
       3: astore_3
       4: iconst_0
       5: istore        4
       7: new           #40                 // class kotlinx/coroutines/CancellableContinuationImpl
      10: dup
      11: aload_3
      12: invokestatic  #46                 // Method kotlin/coroutines/intrinsics/IntrinsicsKt.intercepted:(Lkotlin/coroutines/Continuation;)Lkotlin/coroutines/Continuation;
      15: iconst_1
      16: invokespecial #50                 // Method kotlinx/coroutines/CancellableContinuationImpl."<init>":(Lkotlin/coroutines/Continuation;I)V
      19: astore        5
      21: aload         5
      23: checkcast     #52                 // class kotlinx/coroutines/CancellableContinuation
      26: astore        6
      28: iconst_0
      29: istore        7
      31: aload         6
      33: new           #106                // class retrofit2/KotlinExtensions$await$$inlined$suspendCancellableCoroutine$lambda$2
      36: dup
      37: aload_0
      38: invokespecial #107                // Method retrofit2/KotlinExtensions$await$$inlined$suspendCancellableCoroutine$lambda$2."<init>":(Lretrofit2/Call;)V
      41: checkcast     #59                 // class kotlin/jvm/functions/Function1
      44: invokeinterface #63,  2           // InterfaceMethod kotlinx/coroutines/CancellableContinuation.invokeOnCancellation:(Lkotlin/jvm/functions/Function1;)V
      49: aload_0
      50: new           #109                // class retrofit2/KotlinExtensions$await$4$2
      53: dup
      54: aload         6
      56: invokespecial #110                // Method retrofit2/KotlinExtensions$await$4$2."<init>":(Lkotlinx/coroutines/CancellableContinuation;)V
      59: checkcast     #70                 // class retrofit2/Callback
      62: invokeinterface #76,  2           // InterfaceMethod retrofit2/Call.enqueue:(Lretrofit2/Callback;)V
      67: nop
      68: aload         5
      70: invokevirtual #80                 // Method kotlinx/coroutines/CancellableContinuationImpl.getResult:()Ljava/lang/Object;
      73: nop
      74: dup
      75: invokestatic  #83                 // Method kotlin/coroutines/intrinsics/IntrinsicsKt.getCOROUTINE_SUSPENDED:()Ljava/lang/Object;
      78: if_acmpne     85
      81: aload_1
      82: invokestatic  #89                 // Method kotlin/coroutines/jvm/internal/DebugProbesKt.probeCoroutineSuspended:(Lkotlin/coroutines/Continuation;)V
      85: areturn

  public static final <T> java.lang.Object awaitResponse(retrofit2.Call<T>, kotlin.coroutines.Continuation<? super retrofit2.Response<T>>);
    Code:
       0: iconst_0
       1: istore_2
       2: aload_1
       3: astore_3
       4: iconst_0
       5: istore        4
       7: new           #40                 // class kotlinx/coroutines/CancellableContinuationImpl
      10: dup
      11: aload_3
      12: invokestatic  #46                 // Method kotlin/coroutines/intrinsics/IntrinsicsKt.intercepted:(Lkotlin/coroutines/Continuation;)Lkotlin/coroutines/Continuation;
      15: iconst_1
      16: invokespecial #50                 // Method kotlinx/coroutines/CancellableContinuationImpl."<init>":(Lkotlin/coroutines/Continuation;I)V
      19: astore        5
      21: aload         5
      23: checkcast     #52                 // class kotlinx/coroutines/CancellableContinuation
      26: astore        6
      28: iconst_0
      29: istore        7
      31: aload         6
      33: new           #115                // class retrofit2/KotlinExtensions$awaitResponse$$inlined$suspendCancellableCoroutine$lambda$1
      36: dup
      37: aload_0
      38: invokespecial #116                // Method retrofit2/KotlinExtensions$awaitResponse$$inlined$suspendCancellableCoroutine$lambda$1."<init>":(Lretrofit2/Call;)V
      41: checkcast     #59                 // class kotlin/jvm/functions/Function1
      44: invokeinterface #63,  2           // InterfaceMethod kotlinx/coroutines/CancellableContinuation.invokeOnCancellation:(Lkotlin/jvm/functions/Function1;)V
      49: aload_0
      50: new           #118                // class retrofit2/KotlinExtensions$awaitResponse$2$2
      53: dup
      54: aload         6
      56: invokespecial #119                // Method retrofit2/KotlinExtensions$awaitResponse$2$2."<init>":(Lkotlinx/coroutines/CancellableContinuation;)V
      59: checkcast     #70                 // class retrofit2/Callback
      62: invokeinterface #76,  2           // InterfaceMethod retrofit2/Call.enqueue:(Lretrofit2/Callback;)V
      67: nop
      68: aload         5
      70: invokevirtual #80                 // Method kotlinx/coroutines/CancellableContinuationImpl.getResult:()Ljava/lang/Object;
      73: nop
      74: dup
      75: invokestatic  #83                 // Method kotlin/coroutines/intrinsics/IntrinsicsKt.getCOROUTINE_SUSPENDED:()Ljava/lang/Object;
      78: if_acmpne     85
      81: aload_1
      82: invokestatic  #89                 // Method kotlin/coroutines/jvm/internal/DebugProbesKt.probeCoroutineSuspended:(Lkotlin/coroutines/Continuation;)V
      85: areturn

  public static final java.lang.Object suspendAndThrow(java.lang.Exception, kotlin.coroutines.Continuation<?>);
    Code:
       0: aload_1
       1: instanceof    #126                // class retrofit2/KotlinExtensions$suspendAndThrow$1
       4: ifeq          39
       7: aload_1
       8: checkcast     #126                // class retrofit2/KotlinExtensions$suspendAndThrow$1
      11: astore        5
      13: aload         5
      15: getfield      #129                // Field retrofit2/KotlinExtensions$suspendAndThrow$1.label:I
      18: ldc           #130                // int -2147483648
      20: iand
      21: ifeq          39
      24: aload         5
      26: dup
      27: getfield      #129                // Field retrofit2/KotlinExtensions$suspendAndThrow$1.label:I
      30: ldc           #130                // int -2147483648
      32: isub
      33: putfield      #129                // Field retrofit2/KotlinExtensions$suspendAndThrow$1.label:I
      36: goto          49
      39: new           #126                // class retrofit2/KotlinExtensions$suspendAndThrow$1
      42: dup
      43: aload_1
      44: invokespecial #132                // Method retrofit2/KotlinExtensions$suspendAndThrow$1."<init>":(Lkotlin/coroutines/Continuation;)V
      47: astore        5
      49: aload         5
      51: getfield      #136                // Field retrofit2/KotlinExtensions$suspendAndThrow$1.result:Ljava/lang/Object;
      54: astore        4
      56: invokestatic  #83                 // Method kotlin/coroutines/intrinsics/IntrinsicsKt.getCOROUTINE_SUSPENDED:()Ljava/lang/Object;
      59: astore        6
      61: aload         5
      63: getfield      #129                // Field retrofit2/KotlinExtensions$suspendAndThrow$1.label:I
      66: tableswitch   { // 0 to 1
                     0: 88
                     1: 164
               default: 185
          }
      88: aload         4
      90: invokestatic  #142                // Method kotlin/ResultKt.throwOnFailure:(Ljava/lang/Object;)V
      93: aload         5
      95: aload_0
      96: putfield      #145                // Field retrofit2/KotlinExtensions$suspendAndThrow$1.L$0:Ljava/lang/Object;
      99: aload         5
     101: iconst_1
     102: putfield      #129                // Field retrofit2/KotlinExtensions$suspendAndThrow$1.label:I
     105: aload         5
     107: checkcast     #103                // class kotlin/coroutines/Continuation
     110: astore_2
     111: iconst_0
     112: istore_3
     113: invokestatic  #151                // Method kotlinx/coroutines/Dispatchers.getDefault:()Lkotlinx/coroutines/CoroutineDispatcher;
     116: aload_2
     117: invokeinterface #155,  1          // InterfaceMethod kotlin/coroutines/Continuation.getContext:()Lkotlin/coroutines/CoroutineContext;
     122: new           #157                // class retrofit2/KotlinExtensions$suspendAndThrow$$inlined$suspendCoroutineUninterceptedOrReturn$lambda$1
     125: dup
     126: aload_2
     127: aload_0
     128: invokespecial #160                // Method retrofit2/KotlinExtensions$suspendAndThrow$$inlined$suspendCoroutineUninterceptedOrReturn$lambda$1."<init>":(Lkotlin/coroutines/Continuation;Ljava/lang/Exception;)V
     131: checkcast     #162                // class java/lang/Runnable
     134: invokevirtual #168                // Method kotlinx/coroutines/CoroutineDispatcher.dispatch:(Lkotlin/coroutines/CoroutineContext;Ljava/lang/Runnable;)V
     137: invokestatic  #83                 // Method kotlin/coroutines/intrinsics/IntrinsicsKt.getCOROUTINE_SUSPENDED:()Ljava/lang/Object;
     140: dup
     141: invokestatic  #83                 // Method kotlin/coroutines/intrinsics/IntrinsicsKt.getCOROUTINE_SUSPENDED:()Ljava/lang/Object;
     144: if_acmpne     155
     147: aload         5
     149: checkcast     #103                // class kotlin/coroutines/Continuation
     152: invokestatic  #89                 // Method kotlin/coroutines/jvm/internal/DebugProbesKt.probeCoroutineSuspended:(Lkotlin/coroutines/Continuation;)V
     155: dup
     156: aload         6
     158: if_acmpne     180
     161: aload         6
     163: areturn
     164: aload         5
     166: getfield      #145                // Field retrofit2/KotlinExtensions$suspendAndThrow$1.L$0:Ljava/lang/Object;
     169: checkcast     #170                // class java/lang/Exception
     172: astore_0
     173: aload         4
     175: invokestatic  #142                // Method kotlin/ResultKt.throwOnFailure:(Ljava/lang/Object;)V
     178: aload         4
     180: pop
     181: getstatic     #176                // Field kotlin/Unit.INSTANCE:Lkotlin/Unit;
     184: areturn
     185: new           #178                // class java/lang/IllegalStateException
     188: dup
     189: ldc           #180                // String call to \'resume\' before \'invoke\' with coroutine
     191: invokespecial #183                // Method java/lang/IllegalStateException."<init>":(Ljava/lang/String;)V
     194: athrow
}
