Compiled from "KotlinExtensions.kt"
final class retrofit2.KotlinExtensions$suspendAndThrow$$inlined$suspendCoroutineUninterceptedOrReturn$lambda$1 implements java.lang.Runnable {
  final kotlin.coroutines.Continuation $continuation;

  final java.lang.Exception $this_suspendAndThrow$inlined;

  retrofit2.KotlinExtensions$suspendAndThrow$$inlined$suspendCoroutineUninterceptedOrReturn$lambda$1(kotlin.coroutines.Continuation, java.lang.Exception);
    Code:
       0: aload_0
       1: aload_1
       2: putfield      #17                 // Field $continuation:Lkotlin/coroutines/Continuation;
       5: aload_0
       6: aload_2
       7: putfield      #21                 // Field $this_suspendAndThrow$inlined:Ljava/lang/Exception;
      10: aload_0
      11: invokespecial #24                 // Method java/lang/Object."<init>":()V
      14: return

  public final void run();
    Code:
       0: aload_0
       1: getfield      #17                 // Field $continuation:Lkotlin/coroutines/Continuation;
       4: invokestatic  #31                 // Method kotlin/coroutines/intrinsics/IntrinsicsKt.intercepted:(Lkotlin/coroutines/Continuation;)Lkotlin/coroutines/Continuation;
       7: astore_1
       8: aload_0
       9: getfield      #21                 // Field $this_suspendAndThrow$inlined:Ljava/lang/Exception;
      12: checkcast     #33                 // class java/lang/Throwable
      15: astore_2
      16: iconst_0
      17: istore_3
      18: aload_1
      19: getstatic     #39                 // Field kotlin/Result.Companion:Lkotlin/Result$Companion;
      22: astore        4
      24: astore        5
      26: iconst_0
      27: istore        6
      29: aload_2
      30: invokestatic  #45                 // Method kotlin/ResultKt.createFailure:(Ljava/lang/Throwable;)Ljava/lang/Object;
      33: invokestatic  #49                 // Method kotlin/Result."constructor-impl":(Ljava/lang/Object;)Ljava/lang/Object;
      36: astore        7
      38: aload         5
      40: aload         7
      42: invokeinterface #55,  2           // InterfaceMethod kotlin/coroutines/Continuation.resumeWith:(Ljava/lang/Object;)V
      47: return
}
