Compiled from "KotlinExtensions.kt"
public final class retrofit2.KotlinExtensions$await$2$2 implements retrofit2.Callback<T> {
  final kotlinx.coroutines.CancellableContinuation $continuation;

  public void onResponse(retrofit2.Call<T>, retrofit2.Response<T>);
    Code:
       0: aload_1
       1: ldc           #18                 // String call
       3: invokestatic  #24                 // Method kotlin/jvm/internal/Intrinsics.checkParameterIsNotNull:(Ljava/lang/Object;Ljava/lang/String;)V
       6: aload_2
       7: ldc           #26                 // String response
       9: invokestatic  #24                 // Method kotlin/jvm/internal/Intrinsics.checkParameterIsNotNull:(Ljava/lang/Object;Ljava/lang/String;)V
      12: aload_2
      13: invokevirtual #32                 // Method retrofit2/Response.isSuccessful:()Z
      16: ifeq          220
      19: aload_2
      20: invokevirtual #36                 // Method retrofit2/Response.body:()Ljava/lang/Object;
      23: astore_3
      24: aload_3
      25: ifnonnull     178
      28: aload_1
      29: invokeinterface #42,  1           // InterfaceMethod retrofit2/Call.request:()Lokhttp3/Request;
      34: ldc           #44                 // class retrofit2/Invocation
      36: invokevirtual #50                 // Method okhttp3/Request.tag:(Ljava/lang/Class;)Ljava/lang/Object;
      39: dup
      40: ifnonnull     46
      43: invokestatic  #54                 // Method kotlin/jvm/internal/Intrinsics.throwNpe:()V
      46: dup
      47: ldc           #56                 // String call.request().tag(Invocation::class.java)!!
      49: invokestatic  #59                 // Method kotlin/jvm/internal/Intrinsics.checkExpressionValueIsNotNull:(Ljava/lang/Object;Ljava/lang/String;)V
      52: checkcast     #44                 // class retrofit2/Invocation
      55: astore        4
      57: aload         4
      59: invokevirtual #63                 // Method retrofit2/Invocation.method:()Ljava/lang/reflect/Method;
      62: astore        5
      64: new           #65                 // class kotlin/KotlinNullPointerException
      67: dup
      68: new           #67                 // class java/lang/StringBuilder
      71: dup
      72: invokespecial #70                 // Method java/lang/StringBuilder."<init>":()V
      75: ldc           #72                 // String Response from
      77: invokevirtual #76                 // Method java/lang/StringBuilder.append:(Ljava/lang/String;)Ljava/lang/StringBuilder;
      80: aload         5
      82: dup
      83: ldc           #77                 // String method
      85: invokestatic  #59                 // Method kotlin/jvm/internal/Intrinsics.checkExpressionValueIsNotNull:(Ljava/lang/Object;Ljava/lang/String;)V
      88: invokevirtual #83                 // Method java/lang/reflect/Method.getDeclaringClass:()Ljava/lang/Class;
      91: dup
      92: ldc           #85                 // String method.declaringClass
      94: invokestatic  #59                 // Method kotlin/jvm/internal/Intrinsics.checkExpressionValueIsNotNull:(Ljava/lang/Object;Ljava/lang/String;)V
      97: invokevirtual #91                 // Method java/lang/Class.getName:()Ljava/lang/String;
     100: invokevirtual #76                 // Method java/lang/StringBuilder.append:(Ljava/lang/String;)Ljava/lang/StringBuilder;
     103: bipush        46
     105: invokevirtual #94                 // Method java/lang/StringBuilder.append:(C)Ljava/lang/StringBuilder;
     108: aload         5
     110: invokevirtual #95                 // Method java/lang/reflect/Method.getName:()Ljava/lang/String;
     113: invokevirtual #76                 // Method java/lang/StringBuilder.append:(Ljava/lang/String;)Ljava/lang/StringBuilder;
     116: ldc           #97                 // String  was null but response body type was declared as non-null
     118: invokevirtual #76                 // Method java/lang/StringBuilder.append:(Ljava/lang/String;)Ljava/lang/StringBuilder;
     121: invokevirtual #100                // Method java/lang/StringBuilder.toString:()Ljava/lang/String;
     124: invokespecial #103                // Method kotlin/KotlinNullPointerException."<init>":(Ljava/lang/String;)V
     127: astore        6
     129: aload_0
     130: getfield      #107                // Field $continuation:Lkotlinx/coroutines/CancellableContinuation;
     133: checkcast     #109                // class kotlin/coroutines/Continuation
     136: astore        7
     138: iconst_0
     139: istore        8
     141: aload         7
     143: getstatic     #115                // Field kotlin/Result.Companion:Lkotlin/Result$Companion;
     146: astore        9
     148: astore        10
     150: iconst_0
     151: istore        11
     153: aload         6
     155: checkcast     #117                // class java/lang/Throwable
     158: invokestatic  #123                // Method kotlin/ResultKt.createFailure:(Ljava/lang/Throwable;)Ljava/lang/Object;
     161: invokestatic  #127                // Method kotlin/Result."constructor-impl":(Ljava/lang/Object;)Ljava/lang/Object;
     164: astore        12
     166: aload         10
     168: aload         12
     170: invokeinterface #131,  2          // InterfaceMethod kotlin/coroutines/Continuation.resumeWith:(Ljava/lang/Object;)V
     175: goto          274
     178: aload_0
     179: getfield      #107                // Field $continuation:Lkotlinx/coroutines/CancellableContinuation;
     182: checkcast     #109                // class kotlin/coroutines/Continuation
     185: astore        4
     187: iconst_0
     188: istore        5
     190: aload         4
     192: getstatic     #115                // Field kotlin/Result.Companion:Lkotlin/Result$Companion;
     195: astore        6
     197: astore        7
     199: iconst_0
     200: istore        8
     202: aload_3
     203: invokestatic  #127                // Method kotlin/Result."constructor-impl":(Ljava/lang/Object;)Ljava/lang/Object;
     206: astore        9
     208: aload         7
     210: aload         9
     212: invokeinterface #131,  2          // InterfaceMethod kotlin/coroutines/Continuation.resumeWith:(Ljava/lang/Object;)V
     217: goto          274
     220: aload_0
     221: getfield      #107                // Field $continuation:Lkotlinx/coroutines/CancellableContinuation;
     224: checkcast     #109                // class kotlin/coroutines/Continuation
     227: astore_3
     228: new           #133                // class retrofit2/HttpException
     231: dup
     232: aload_2
     233: invokespecial #136                // Method retrofit2/HttpException."<init>":(Lretrofit2/Response;)V
     236: checkcast     #117                // class java/lang/Throwable
     239: astore        4
     241: iconst_0
     242: istore        5
     244: aload_3
     245: getstatic     #115                // Field kotlin/Result.Companion:Lkotlin/Result$Companion;
     248: astore        6
     250: astore        7
     252: iconst_0
     253: istore        8
     255: aload         4
     257: invokestatic  #123                // Method kotlin/ResultKt.createFailure:(Ljava/lang/Throwable;)Ljava/lang/Object;
     260: invokestatic  #127                // Method kotlin/Result."constructor-impl":(Ljava/lang/Object;)Ljava/lang/Object;
     263: astore        9
     265: aload         7
     267: aload         9
     269: invokeinterface #131,  2          // InterfaceMethod kotlin/coroutines/Continuation.resumeWith:(Ljava/lang/Object;)V
     274: return

  public void onFailure(retrofit2.Call<T>, java.lang.Throwable);
    Code:
       0: aload_1
       1: ldc           #18                 // String call
       3: invokestatic  #24                 // Method kotlin/jvm/internal/Intrinsics.checkParameterIsNotNull:(Ljava/lang/Object;Ljava/lang/String;)V
       6: aload_2
       7: ldc           #151                // String t
       9: invokestatic  #24                 // Method kotlin/jvm/internal/Intrinsics.checkParameterIsNotNull:(Ljava/lang/Object;Ljava/lang/String;)V
      12: aload_0
      13: getfield      #107                // Field $continuation:Lkotlinx/coroutines/CancellableContinuation;
      16: checkcast     #109                // class kotlin/coroutines/Continuation
      19: astore_3
      20: iconst_0
      21: istore        4
      23: aload_3
      24: getstatic     #115                // Field kotlin/Result.Companion:Lkotlin/Result$Companion;
      27: astore        5
      29: astore        6
      31: iconst_0
      32: istore        7
      34: aload_2
      35: invokestatic  #123                // Method kotlin/ResultKt.createFailure:(Ljava/lang/Throwable;)Ljava/lang/Object;
      38: invokestatic  #127                // Method kotlin/Result."constructor-impl":(Ljava/lang/Object;)Ljava/lang/Object;
      41: astore        8
      43: aload         6
      45: aload         8
      47: invokeinterface #131,  2          // InterfaceMethod kotlin/coroutines/Continuation.resumeWith:(Ljava/lang/Object;)V
      52: return

  retrofit2.KotlinExtensions$await$2$2(kotlinx.coroutines.CancellableContinuation);
    Code:
       0: aload_0
       1: aload_1
       2: putfield      #107                // Field $continuation:Lkotlinx/coroutines/CancellableContinuation;
       5: aload_0
       6: invokespecial #154                // Method java/lang/Object."<init>":()V
       9: return
}
