Compiled from "OkHttpCall.java"
final class retrofit2.OkHttpCall$NoContentResponseBody extends okhttp3.ResponseBody {
  private final okhttp3.MediaType contentType;

  private final long contentLength;

  retrofit2.OkHttpCall$NoContentResponseBody(okhttp3.MediaType, long);
    Code:
       0: aload_0
       1: invokespecial #1                  // Method okhttp3/ResponseBody."<init>":()V
       4: aload_0
       5: aload_1
       6: putfield      #7                  // Field contentType:Lokhttp3/MediaType;
       9: aload_0
      10: lload_2
      11: putfield      #13                 // Field contentLength:J
      14: return

  public okhttp3.MediaType contentType();
    Code:
       0: aload_0
       1: getfield      #7                  // Field contentType:Lokhttp3/MediaType;
       4: areturn

  public long contentLength();
    Code:
       0: aload_0
       1: getfield      #13                 // Field contentLength:J
       4: lreturn

  public okio.BufferedSource source();
    Code:
       0: new           #17                 // class java/lang/IllegalStateException
       3: dup
       4: ldc           #19                 // String Cannot read raw response body of a converted body.
       6: invokespecial #21                 // Method java/lang/IllegalStateException."<init>":(Ljava/lang/String;)V
       9: athrow
}
