Compiled from "OkHttpCall.java"
class retrofit2.OkHttpCall$1 implements okhttp3.Callback {
  final retrofit2.Callback val$callback;

  final retrofit2.OkHttpCall this$0;

  retrofit2.OkHttpCall$1();
    Code:
       0: aload_0
       1: aload_1
       2: putfield      #1                  // Field this$0:Lretrofit2/OkHttpCall;
       5: aload_0
       6: aload_2
       7: putfield      #7                  // Field val$callback:Lretrofit2/Callback;
      10: aload_0
      11: invokespecial #11                 // Method java/lang/Object."<init>":()V
      14: return

  public void onResponse(okhttp3.Call, okhttp3.Response);
    Code:
       0: aload_0
       1: getfield      #1                  // Field this$0:Lretrofit2/OkHttpCall;
       4: aload_2
       5: invokevirtual #17                 // Method retrofit2/OkHttpCall.parseResponse:(Lokhttp3/Response;)Lretrofit2/Response;
       8: astore_3
       9: goto          26
      12: astore        4
      14: aload         4
      16: invokestatic  #25                 // Method retrofit2/Utils.throwIfFatal:(Ljava/lang/Throwable;)V
      19: aload_0
      20: aload         4
      22: invokespecial #31                 // Method callFailure:(Ljava/lang/Throwable;)V
      25: return
      26: aload_0
      27: getfield      #7                  // Field val$callback:Lretrofit2/Callback;
      30: aload_0
      31: getfield      #1                  // Field this$0:Lretrofit2/OkHttpCall;
      34: aload_3
      35: invokeinterface #34,  3           // InterfaceMethod retrofit2/Callback.onResponse:(Lretrofit2/Call;Lretrofit2/Response;)V
      40: goto          55
      43: astore        4
      45: aload         4
      47: invokestatic  #25                 // Method retrofit2/Utils.throwIfFatal:(Ljava/lang/Throwable;)V
      50: aload         4
      52: invokevirtual #40                 // Method java/lang/Throwable.printStackTrace:()V
      55: return
    Exception table:
       from    to  target type
           0     9    12   Class java/lang/Throwable
          26    40    43   Class java/lang/Throwable

  public void onFailure(okhttp3.Call, java.io.IOException);
    Code:
       0: aload_0
       1: aload_2
       2: invokespecial #31                 // Method callFailure:(Ljava/lang/Throwable;)V
       5: return

  private void callFailure(java.lang.Throwable);
    Code:
       0: aload_0
       1: getfield      #7                  // Field val$callback:Lretrofit2/Callback;
       4: aload_0
       5: getfield      #1                  // Field this$0:Lretrofit2/OkHttpCall;
       8: aload_1
       9: invokeinterface #43,  3           // InterfaceMethod retrofit2/Callback.onFailure:(Lretrofit2/Call;Ljava/lang/Throwable;)V
      14: goto          26
      17: astore_2
      18: aload_2
      19: invokestatic  #25                 // Method retrofit2/Utils.throwIfFatal:(Ljava/lang/Throwable;)V
      22: aload_2
      23: invokevirtual #40                 // Method java/lang/Throwable.printStackTrace:()V
      26: return
    Exception table:
       from    to  target type
           0    14    17   Class java/lang/Throwable
}
