Compiled from "OkHttpCall.java"
final class retrofit2.OkHttpCall$ExceptionCatchingResponseBody extends okhttp3.ResponseBody {
  private final okhttp3.ResponseBody delegate;

  private final okio.BufferedSource delegateSource;

  java.io.IOException thrownException;

  retrofit2.OkHttpCall$ExceptionCatchingResponseBody(okhttp3.ResponseBody);
    Code:
       0: aload_0
       1: invokespecial #1                  // Method okhttp3/ResponseBody."<init>":()V
       4: aload_0
       5: aload_1
       6: putfield      #7                  // Field delegate:Lokhttp3/ResponseBody;
       9: aload_0
      10: new           #13                 // class retrofit2/OkHttpCall$ExceptionCatchingResponseBody$1
      13: dup
      14: aload_0
      15: aload_1
      16: invokevirtual #15                 // Method okhttp3/ResponseBody.source:()Lokio/BufferedSource;
      19: invokespecial #19                 // Method retrofit2/OkHttpCall$ExceptionCatchingResponseBody$1."<init>":(Lretrofit2/OkHttpCall$ExceptionCatchingResponseBody;Lokio/Source;)V
      22: invokestatic  #22                 // Method okio/Okio.buffer:(Lokio/Source;)Lokio/BufferedSource;
      25: putfield      #28                 // Field delegateSource:Lokio/BufferedSource;
      28: return

  public okhttp3.MediaType contentType();
    Code:
       0: aload_0
       1: getfield      #7                  // Field delegate:Lokhttp3/ResponseBody;
       4: invokevirtual #32                 // Method okhttp3/ResponseBody.contentType:()Lokhttp3/MediaType;
       7: areturn

  public long contentLength();
    Code:
       0: aload_0
       1: getfield      #7                  // Field delegate:Lokhttp3/ResponseBody;
       4: invokevirtual #36                 // Method okhttp3/ResponseBody.contentLength:()J
       7: lreturn

  public okio.BufferedSource source();
    Code:
       0: aload_0
       1: getfield      #28                 // Field delegateSource:Lokio/BufferedSource;
       4: areturn

  public void close();
    Code:
       0: aload_0
       1: getfield      #7                  // Field delegate:Lokhttp3/ResponseBody;
       4: invokevirtual #40                 // Method okhttp3/ResponseBody.close:()V
       7: return

  void throwIfCaught() throws java.io.IOException;
    Code:
       0: aload_0
       1: getfield      #43                 // Field thrownException:Ljava/io/IOException;
       4: ifnull        12
       7: aload_0
       8: getfield      #43                 // Field thrownException:Ljava/io/IOException;
      11: athrow
      12: return
}
