Compiled from "OkHttpCall.java"
class retrofit2.OkHttpCall$ExceptionCatchingResponseBody$1 extends okio.ForwardingSource {
  final retrofit2.OkHttpCall$ExceptionCatchingResponseBody this$0;

  retrofit2.OkHttpCall$ExceptionCatchingResponseBody$1(retrofit2.OkHttpCall$ExceptionCatchingResponseBody, okio.Source);
    Code:
       0: aload_0
       1: aload_1
       2: putfield      #1                  // Field this$0:Lretrofit2/OkHttpCall$ExceptionCatchingResponseBody;
       5: aload_0
       6: aload_2
       7: invokespecial #7                  // Method okio/ForwardingSource."<init>":(Lokio/Source;)V
      10: return

  public long read(okio.Buffer, long) throws java.io.IOException;
    Code:
       0: aload_0
       1: aload_1
       2: lload_2
       3: invokespecial #13                 // Method okio/ForwardingSource.read:(Lokio/Buffer;J)J
       6: lreturn
       7: astore        4
       9: aload_0
      10: getfield      #1                  // Field this$0:Lretrofit2/OkHttpCall$ExceptionCatchingResponseBody;
      13: aload         4
      15: putfield      #19                 // Field retrofit2/OkHttpCall$ExceptionCatchingResponseBody.thrownException:Ljava/io/IOException;
      18: aload         4
      20: athrow
    Exception table:
       from    to  target type
           0     6     7   Class java/io/IOException
}
