Compiled from "OptionalConverterFactory.java"
final class retrofit2.OptionalConverterFactory$OptionalConverter<T> implements retrofit2.Converter<okhttp3.ResponseBody, java.util.Optional<T>> {
  final retrofit2.Converter<okhttp3.ResponseBody, T> delegate;

  retrofit2.OptionalConverterFactory$OptionalConverter(retrofit2.Converter<okhttp3.ResponseBody, T>);
    Code:
       0: aload_0
       1: invokespecial #1                  // Method java/lang/Object."<init>":()V
       4: aload_0
       5: aload_1
       6: putfield      #7                  // Field delegate:Lretrofit2/Converter;
       9: return

  public java.util.Optional<T> convert(okhttp3.ResponseBody) throws java.io.IOException;
    Code:
       0: aload_0
       1: getfield      #7                  // Field delegate:Lretrofit2/Converter;
       4: aload_1
       5: invokeinterface #13,  2           // InterfaceMethod retrofit2/Converter.convert:(Ljava/lang/Object;)Ljava/lang/Object;
      10: invokestatic  #19                 // Method java/util/Optional.ofNullable:(Ljava/lang/Object;)Ljava/util/Optional;
      13: areturn

  public java.lang.Object convert(java.lang.Object) throws java.io.IOException;
    Code:
       0: aload_0
       1: aload_1
       2: checkcast     #25                 // class okhttp3/ResponseBody
       5: invokevirtual #27                 // Method convert:(Lokhttp3/ResponseBody;)Ljava/util/Optional;
       8: areturn
}
