Compiled from "ParameterHandler.java"
final class retrofit2.ParameterHandler$Body<T> extends retrofit2.ParameterHandler<T> {
  private final java.lang.reflect.Method method;

  private final int p;

  private final retrofit2.Converter<T, okhttp3.RequestBody> converter;

  retrofit2.ParameterHandler$Body(java.lang.reflect.Method, int, retrofit2.Converter<T, okhttp3.RequestBody>);
    Code:
       0: aload_0
       1: invokespecial #1                  // Method retrofit2/ParameterHandler."<init>":()V
       4: aload_0
       5: aload_1
       6: putfield      #7                  // Field method:Ljava/lang/reflect/Method;
       9: aload_0
      10: iload_2
      11: putfield      #13                 // Field p:I
      14: aload_0
      15: aload_3
      16: putfield      #17                 // Field converter:Lretrofit2/Converter;
      19: return

  void apply(retrofit2.RequestBuilder, T);
    Code:
       0: aload_2
       1: ifnonnull     22
       4: aload_0
       5: getfield      #7                  // Field method:Ljava/lang/reflect/Method;
       8: aload_0
       9: getfield      #13                 // Field p:I
      12: ldc           #21                 // String Body parameter value must not be null.
      14: iconst_0
      15: anewarray     #23                 // class java/lang/Object
      18: invokestatic  #25                 // Method retrofit2/Utils.parameterError:(Ljava/lang/reflect/Method;ILjava/lang/String;[Ljava/lang/Object;)Ljava/lang/RuntimeException;
      21: athrow
      22: aload_0
      23: getfield      #17                 // Field converter:Lretrofit2/Converter;
      26: aload_2
      27: invokeinterface #31,  2           // InterfaceMethod retrofit2/Converter.convert:(Ljava/lang/Object;)Ljava/lang/Object;
      32: checkcast     #37                 // class okhttp3/RequestBody
      35: astore_3
      36: goto          83
      39: astore        4
      41: aload_0
      42: getfield      #7                  // Field method:Ljava/lang/reflect/Method;
      45: aload         4
      47: aload_0
      48: getfield      #13                 // Field p:I
      51: new           #41                 // class java/lang/StringBuilder
      54: dup
      55: invokespecial #43                 // Method java/lang/StringBuilder."<init>":()V
      58: ldc           #44                 // String Unable to convert
      60: invokevirtual #46                 // Method java/lang/StringBuilder.append:(Ljava/lang/String;)Ljava/lang/StringBuilder;
      63: aload_2
      64: invokevirtual #50                 // Method java/lang/StringBuilder.append:(Ljava/lang/Object;)Ljava/lang/StringBuilder;
      67: ldc           #53                 // String  to RequestBody
      69: invokevirtual #46                 // Method java/lang/StringBuilder.append:(Ljava/lang/String;)Ljava/lang/StringBuilder;
      72: invokevirtual #55                 // Method java/lang/StringBuilder.toString:()Ljava/lang/String;
      75: iconst_0
      76: anewarray     #23                 // class java/lang/Object
      79: invokestatic  #59                 // Method retrofit2/Utils.parameterError:(Ljava/lang/reflect/Method;Ljava/lang/Throwable;ILjava/lang/String;[Ljava/lang/Object;)Ljava/lang/RuntimeException;
      82: athrow
      83: aload_1
      84: aload_3
      85: invokevirtual #62                 // Method retrofit2/RequestBuilder.setBody:(Lokhttp3/RequestBody;)V
      88: return
    Exception table:
       from    to  target type
          22    36    39   Class java/io/IOException
}
