Compiled from "ParameterHandler.java"
final class retrofit2.ParameterHandler$RawPart extends retrofit2.ParameterHandler<okhttp3.MultipartBody$Part> {
  static final retrofit2.ParameterHandler$RawPart INSTANCE;

  private retrofit2.ParameterHandler$RawPart();
    Code:
       0: aload_0
       1: invokespecial #1                  // Method retrofit2/ParameterHandler."<init>":()V
       4: return

  void apply(retrofit2.RequestBuilder, okhttp3.MultipartBody$Part);
    Code:
       0: aload_2
       1: ifnull        9
       4: aload_1
       5: aload_2
       6: invokevirtual #7                  // Method retrofit2/RequestBuilder.addPart:(Lokhttp3/MultipartBody$Part;)V
       9: return

  void apply(retrofit2.RequestBuilder, java.lang.Object) throws java.io.IOException;
    Code:
       0: aload_0
       1: aload_1
       2: aload_2
       3: checkcast     #13                 // class okhttp3/MultipartBody$Part
       6: invokevirtual #15                 // Method apply:(Lretrofit2/RequestBuilder;Lokhttp3/MultipartBody$Part;)V
       9: return

  static {};
    Code:
       0: new           #16                 // class retrofit2/ParameterHandler$RawPart
       3: dup
       4: invokespecial #21                 // Method "<init>":()V
       7: putstatic     #22                 // Field INSTANCE:Lretrofit2/ParameterHandler$RawPart;
      10: return
}
