Compiled from "ParameterHandler.java"
class retrofit2.ParameterHandler$2 extends retrofit2.ParameterHandler<java.lang.Object> {
  final retrofit2.ParameterHandler this$0;

  retrofit2.ParameterHandler$2(retrofit2.ParameterHandler);
    Code:
       0: aload_0
       1: aload_1
       2: putfield      #1                  // Field this$0:Lretrofit2/ParameterHandler;
       5: aload_0
       6: invokespecial #7                  // Method retrofit2/ParameterHandler."<init>":()V
       9: return

  void apply(retrofit2.RequestBuilder, java.lang.Object) throws java.io.IOException;
    Code:
       0: aload_2
       1: ifnonnull     5
       4: return
       5: iconst_0
       6: istore_3
       7: aload_2
       8: invokestatic  #13                 // Method java/lang/reflect/Array.getLength:(Ljava/lang/Object;)I
      11: istore        4
      13: iload_3
      14: iload         4
      16: if_icmpge     38
      19: aload_0
      20: getfield      #1                  // Field this$0:Lretrofit2/ParameterHandler;
      23: aload_1
      24: aload_2
      25: iload_3
      26: invokestatic  #19                 // Method java/lang/reflect/Array.get:(Ljava/lang/Object;I)Ljava/lang/Object;
      29: invokevirtual #23                 // Method retrofit2/ParameterHandler.apply:(Lretrofit2/RequestBuilder;Ljava/lang/Object;)V
      32: iinc          3, 1
      35: goto          13
      38: return
}
