Compiled from "ParameterHandler.java"
abstract class retrofit2.ParameterHandler<T> {
  retrofit2.ParameterHandler();
    Code:
       0: aload_0
       1: invokespecial #1                  // Method java/lang/Object."<init>":()V
       4: return

  abstract void apply(retrofit2.RequestBuilder, T) throws java.io.IOException;

  final retrofit2.ParameterHandler<java.lang.Iterable<T>> iterable();
    Code:
       0: new           #7                  // class retrofit2/ParameterHandler$1
       3: dup
       4: aload_0
       5: invokespecial #9                  // Method retrofit2/ParameterHandler$1."<init>":(Lretrofit2/ParameterHandler;)V
       8: areturn

  final retrofit2.ParameterHandler<java.lang.Object> array();
    Code:
       0: new           #12                 // class retrofit2/ParameterHandler$2
       3: dup
       4: aload_0
       5: invokespecial #14                 // Method retrofit2/ParameterHandler$2."<init>":(Lretrofit2/ParameterHandler;)V
       8: areturn
}
