Compiled from "ParameterHandler.java"
final class retrofit2.ParameterHandler$Tag<T> extends retrofit2.ParameterHandler<T> {
  final java.lang.Class<T> cls;

  retrofit2.ParameterHandler$Tag(java.lang.Class<T>);
    Code:
       0: aload_0
       1: invokespecial #1                  // Method retrofit2/ParameterHandler."<init>":()V
       4: aload_0
       5: aload_1
       6: putfield      #7                  // Field cls:Ljava/lang/Class;
       9: return

  void apply(retrofit2.RequestBuilder, T);
    Code:
       0: aload_1
       1: aload_0
       2: getfield      #7                  // Field cls:Ljava/lang/Class;
       5: aload_2
       6: invokevirtual #13                 // Method retrofit2/RequestBuilder.addTag:(Ljava/lang/Class;Ljava/lang/Object;)V
       9: return
}
