Compiled from "ParameterHandler.java"
final class retrofit2.ParameterHandler$Headers extends retrofit2.ParameterHandler<okhttp3.Headers> {
  private final java.lang.reflect.Method method;

  private final int p;

  retrofit2.ParameterHandler$Headers(java.lang.reflect.Method, int);
    Code:
       0: aload_0
       1: invokespecial #1                  // Method retrofit2/ParameterHandler."<init>":()V
       4: aload_0
       5: aload_1
       6: putfield      #7                  // Field method:Ljava/lang/reflect/Method;
       9: aload_0
      10: iload_2
      11: putfield      #13                 // Field p:I
      14: return

  void apply(retrofit2.RequestBuilder, okhttp3.Headers);
    Code:
       0: aload_2
       1: ifnonnull     22
       4: aload_0
       5: getfield      #7                  // Field method:Ljava/lang/reflect/Method;
       8: aload_0
       9: getfield      #13                 // Field p:I
      12: ldc           #17                 // String Headers parameter must not be null.
      14: iconst_0
      15: anewarray     #19                 // class java/lang/Object
      18: invokestatic  #21                 // Method retrofit2/Utils.parameterError:(Ljava/lang/reflect/Method;ILjava/lang/String;[Ljava/lang/Object;)Ljava/lang/RuntimeException;
      21: athrow
      22: aload_1
      23: aload_2
      24: invokevirtual #27                 // Method retrofit2/RequestBuilder.addHeaders:(Lokhttp3/Headers;)V
      27: return

  void apply(retrofit2.RequestBuilder, java.lang.Object) throws java.io.IOException;
    Code:
       0: aload_0
       1: aload_1
       2: aload_2
       3: checkcast     #33                 // class okhttp3/Headers
       6: invokevirtual #35                 // Method apply:(Lretrofit2/RequestBuilder;Lokhttp3/Headers;)V
       9: return
}
