Compiled from "ParameterHandler.java"
class retrofit2.ParameterHandler$1 extends retrofit2.ParameterHandler<java.lang.Iterable<T>> {
  final retrofit2.ParameterHandler this$0;

  retrofit2.ParameterHandler$1(retrofit2.ParameterHandler);
    Code:
       0: aload_0
       1: aload_1
       2: putfield      #1                  // Field this$0:Lretrofit2/ParameterHandler;
       5: aload_0
       6: invokespecial #7                  // Method retrofit2/ParameterHandler."<init>":()V
       9: return

  void apply(retrofit2.RequestBuilder, java.lang.Iterable<T>) throws java.io.IOException;
    Code:
       0: aload_2
       1: ifnonnull     5
       4: return
       5: aload_2
       6: invokeinterface #13,  1           // InterfaceMethod java/lang/Iterable.iterator:()Ljava/util/Iterator;
      11: astore_3
      12: aload_3
      13: invokeinterface #19,  1           // InterfaceMethod java/util/Iterator.hasNext:()Z
      18: ifeq          42
      21: aload_3
      22: invokeinterface #25,  1           // InterfaceMethod java/util/Iterator.next:()Ljava/lang/Object;
      27: astore        4
      29: aload_0
      30: getfield      #1                  // Field this$0:Lretrofit2/ParameterHandler;
      33: aload_1
      34: aload         4
      36: invokevirtual #29                 // Method retrofit2/ParameterHandler.apply:(Lretrofit2/RequestBuilder;Ljava/lang/Object;)V
      39: goto          12
      42: return

  void apply(retrofit2.RequestBuilder, java.lang.Object) throws java.io.IOException;
    Code:
       0: aload_0
       1: aload_1
       2: aload_2
       3: checkcast     #14                 // class java/lang/Iterable
       6: invokevirtual #33                 // Method apply:(Lretrofit2/RequestBuilder;Ljava/lang/Iterable;)V
       9: return
}
