Compiled from "ParameterHandler.java"
final class retrofit2.ParameterHandler$Path<T> extends retrofit2.ParameterHandler<T> {
  private final java.lang.reflect.Method method;

  private final int p;

  private final java.lang.String name;

  private final retrofit2.Converter<T, java.lang.String> valueConverter;

  private final boolean encoded;

  retrofit2.ParameterHandler$Path(java.lang.reflect.Method, int, java.lang.String, retrofit2.Converter<T, java.lang.String>, boolean);
    Code:
       0: aload_0
       1: invokespecial #1                  // Method retrofit2/ParameterHandler."<init>":()V
       4: aload_0
       5: aload_1
       6: putfield      #7                  // Field method:Ljava/lang/reflect/Method;
       9: aload_0
      10: iload_2
      11: putfield      #13                 // Field p:I
      14: aload_0
      15: aload_3
      16: ldc           #17                 // String name == null
      18: invokestatic  #19                 // Method java/util/Objects.requireNonNull:(Ljava/lang/Object;Ljava/lang/String;)Ljava/lang/Object;
      21: checkcast     #25                 // class java/lang/String
      24: putfield      #27                 // Field name:Ljava/lang/String;
      27: aload_0
      28: aload         4
      30: putfield      #31                 // Field valueConverter:Lretrofit2/Converter;
      33: aload_0
      34: iload         5
      36: putfield      #35                 // Field encoded:Z
      39: return

  void apply(retrofit2.RequestBuilder, T) throws java.io.IOException;
    Code:
       0: aload_2
       1: ifnonnull     47
       4: aload_0
       5: getfield      #7                  // Field method:Ljava/lang/reflect/Method;
       8: aload_0
       9: getfield      #13                 // Field p:I
      12: new           #39                 // class java/lang/StringBuilder
      15: dup
      16: invokespecial #41                 // Method java/lang/StringBuilder."<init>":()V
      19: ldc           #42                 // String Path parameter \"
      21: invokevirtual #44                 // Method java/lang/StringBuilder.append:(Ljava/lang/String;)Ljava/lang/StringBuilder;
      24: aload_0
      25: getfield      #27                 // Field name:Ljava/lang/String;
      28: invokevirtual #44                 // Method java/lang/StringBuilder.append:(Ljava/lang/String;)Ljava/lang/StringBuilder;
      31: ldc           #48                 // String \" value must not be null.
      33: invokevirtual #44                 // Method java/lang/StringBuilder.append:(Ljava/lang/String;)Ljava/lang/StringBuilder;
      36: invokevirtual #50                 // Method java/lang/StringBuilder.toString:()Ljava/lang/String;
      39: iconst_0
      40: anewarray     #54                 // class java/lang/Object
      43: invokestatic  #56                 // Method retrofit2/Utils.parameterError:(Ljava/lang/reflect/Method;ILjava/lang/String;[Ljava/lang/Object;)Ljava/lang/RuntimeException;
      46: athrow
      47: aload_1
      48: aload_0
      49: getfield      #27                 // Field name:Ljava/lang/String;
      52: aload_0
      53: getfield      #31                 // Field valueConverter:Lretrofit2/Converter;
      56: aload_2
      57: invokeinterface #62,  2           // InterfaceMethod retrofit2/Converter.convert:(Ljava/lang/Object;)Ljava/lang/Object;
      62: checkcast     #25                 // class java/lang/String
      65: aload_0
      66: getfield      #35                 // Field encoded:Z
      69: invokevirtual #68                 // Method retrofit2/RequestBuilder.addPathParam:(Ljava/lang/String;Ljava/lang/String;Z)V
      72: return
}
