Compiled from "Platform.java"
class retrofit2.Platform {
  private static final retrofit2.Platform PLATFORM;

  private final boolean hasJava8Types;

  private final java.lang.reflect.Constructor<java.lang.invoke.MethodHandles$Lookup> lookupConstructor;

  static retrofit2.Platform get();
    Code:
       0: getstatic     #1                  // Field PLATFORM:Lretrofit2/Platform;
       3: areturn

  private static retrofit2.Platform findPlatform();
    Code:
       0: ldc           #7                  // String Dalvik
       2: ldc           #9                  // String java.vm.name
       4: invokestatic  #11                 // Method java/lang/System.getProperty:(Ljava/lang/String;)Ljava/lang/String;
       7: invokevirtual #17                 // Method java/lang/String.equals:(Ljava/lang/Object;)Z
      10: ifeq          23
      13: new           #23                 // class retrofit2/Platform$Android
      16: dup
      17: invokespecial #25                 // Method retrofit2/Platform$Android."<init>":()V
      20: goto          31
      23: new           #2                  // class retrofit2/Platform
      26: dup
      27: iconst_1
      28: invokespecial #29                 // Method "<init>":(Z)V
      31: areturn

  retrofit2.Platform(boolean);
    Code:
       0: aload_0
       1: invokespecial #32                 // Method java/lang/Object."<init>":()V
       4: aload_0
       5: iload_1
       6: putfield      #35                 // Field hasJava8Types:Z
       9: aconst_null
      10: astore_2
      11: iload_1
      12: ifeq          49
      15: ldc           #39                 // class java/lang/invoke/MethodHandles$Lookup
      17: iconst_2
      18: anewarray     #41                 // class java/lang/Class
      21: dup
      22: iconst_0
      23: ldc           #41                 // class java/lang/Class
      25: aastore
      26: dup
      27: iconst_1
      28: getstatic     #43                 // Field java/lang/Integer.TYPE:Ljava/lang/Class;
      31: aastore
      32: invokevirtual #49                 // Method java/lang/Class.getDeclaredConstructor:([Ljava/lang/Class;)Ljava/lang/reflect/Constructor;
      35: astore_2
      36: aload_2
      37: iconst_1
      38: invokevirtual #53                 // Method java/lang/reflect/Constructor.setAccessible:(Z)V
      41: goto          49
      44: astore_3
      45: goto          49
      48: astore_3
      49: aload_0
      50: aload_2
      51: putfield      #62                 // Field lookupConstructor:Ljava/lang/reflect/Constructor;
      54: return
    Exception table:
       from    to  target type
          15    41    44   Class java/lang/NoClassDefFoundError
          15    41    48   Class java/lang/NoSuchMethodException

  java.util.concurrent.Executor defaultCallbackExecutor();
    Code:
       0: aconst_null
       1: areturn

  java.util.List<? extends retrofit2.CallAdapter$Factory> defaultCallAdapterFactories(java.util.concurrent.Executor);
    Code:
       0: new           #66                 // class retrofit2/DefaultCallAdapterFactory
       3: dup
       4: aload_1
       5: invokespecial #68                 // Method retrofit2/DefaultCallAdapterFactory."<init>":(Ljava/util/concurrent/Executor;)V
       8: astore_2
       9: aload_0
      10: getfield      #35                 // Field hasJava8Types:Z
      13: ifeq          36
      16: iconst_2
      17: anewarray     #71                 // class retrofit2/CallAdapter$Factory
      20: dup
      21: iconst_0
      22: getstatic     #73                 // Field retrofit2/CompletableFutureCallAdapterFactory.INSTANCE:Lretrofit2/CallAdapter$Factory;
      25: aastore
      26: dup
      27: iconst_1
      28: aload_2
      29: aastore
      30: invokestatic  #79                 // Method java/util/Arrays.asList:([Ljava/lang/Object;)Ljava/util/List;
      33: goto          40
      36: aload_2
      37: invokestatic  #85                 // Method java/util/Collections.singletonList:(Ljava/lang/Object;)Ljava/util/List;
      40: areturn

  int defaultCallAdapterFactoriesSize();
    Code:
       0: aload_0
       1: getfield      #35                 // Field hasJava8Types:Z
       4: ifeq          11
       7: iconst_2
       8: goto          12
      11: iconst_1
      12: ireturn

  java.util.List<? extends retrofit2.Converter$Factory> defaultConverterFactories();
    Code:
       0: aload_0
       1: getfield      #35                 // Field hasJava8Types:Z
       4: ifeq          16
       7: getstatic     #91                 // Field retrofit2/OptionalConverterFactory.INSTANCE:Lretrofit2/Converter$Factory;
      10: invokestatic  #85                 // Method java/util/Collections.singletonList:(Ljava/lang/Object;)Ljava/util/List;
      13: goto          19
      16: invokestatic  #96                 // Method java/util/Collections.emptyList:()Ljava/util/List;
      19: areturn

  int defaultConverterFactoriesSize();
    Code:
       0: aload_0
       1: getfield      #35                 // Field hasJava8Types:Z
       4: ifeq          11
       7: iconst_1
       8: goto          12
      11: iconst_0
      12: ireturn

  boolean isDefaultMethod(java.lang.reflect.Method);
    Code:
       0: aload_0
       1: getfield      #35                 // Field hasJava8Types:Z
       4: ifeq          18
       7: aload_1
       8: invokevirtual #100                // Method java/lang/reflect/Method.isDefault:()Z
      11: ifeq          18
      14: iconst_1
      15: goto          19
      18: iconst_0
      19: ireturn

  java.lang.Object invokeDefaultMethod(java.lang.reflect.Method, java.lang.Class<?>, java.lang.Object, java.lang.Object...) throws java.lang.Throwable;
    Code:
       0: aload_0
       1: getfield      #62                 // Field lookupConstructor:Ljava/lang/reflect/Constructor;
       4: ifnull        35
       7: aload_0
       8: getfield      #62                 // Field lookupConstructor:Ljava/lang/reflect/Constructor;
      11: iconst_2
      12: anewarray     #33                 // class java/lang/Object
      15: dup
      16: iconst_0
      17: aload_2
      18: aastore
      19: dup
      20: iconst_1
      21: iconst_m1
      22: invokestatic  #106                // Method java/lang/Integer.valueOf:(I)Ljava/lang/Integer;
      25: aastore
      26: invokevirtual #110                // Method java/lang/reflect/Constructor.newInstance:([Ljava/lang/Object;)Ljava/lang/Object;
      29: checkcast     #39                 // class java/lang/invoke/MethodHandles$Lookup
      32: goto          38
      35: invokestatic  #114                // Method java/lang/invoke/MethodHandles.lookup:()Ljava/lang/invoke/MethodHandles$Lookup;
      38: astore        5
      40: aload         5
      42: aload_1
      43: aload_2
      44: invokevirtual #120                // Method java/lang/invoke/MethodHandles$Lookup.unreflectSpecial:(Ljava/lang/reflect/Method;Ljava/lang/Class;)Ljava/lang/invoke/MethodHandle;
      47: aload_3
      48: invokevirtual #124                // Method java/lang/invoke/MethodHandle.bindTo:(Ljava/lang/Object;)Ljava/lang/invoke/MethodHandle;
      51: aload         4
      53: invokevirtual #130                // Method java/lang/invoke/MethodHandle.invokeWithArguments:([Ljava/lang/Object;)Ljava/lang/Object;
      56: areturn

  static {};
    Code:
       0: invokestatic  #133                // Method findPlatform:()Lretrofit2/Platform;
       3: putstatic     #1                  // Field PLATFORM:Lretrofit2/Platform;
       6: return
}
