Compiled from "Platform.java"
final class retrofit2.Platform$Android$MainThreadExecutor implements java.util.concurrent.Executor {
  private final android.os.Handler handler;

  retrofit2.Platform$Android$MainThreadExecutor();
    Code:
       0: aload_0
       1: invokespecial #1                  // Method java/lang/Object."<init>":()V
       4: aload_0
       5: new           #7                  // class android/os/Handler
       8: dup
       9: invokestatic  #9                  // Method android/os/Looper.getMainLooper:()Landroid/os/Looper;
      12: invokespecial #15                 // Method android/os/Handler."<init>":(Landroid/os/Looper;)V
      15: putfield      #18                 // Field handler:Landroid/os/Handler;
      18: return

  public void execute(java.lang.Runnable);
    Code:
       0: aload_0
       1: getfield      #18                 // Field handler:Landroid/os/Handler;
       4: aload_1
       5: invokevirtual #24                 // Method android/os/Handler.post:(Ljava/lang/Runnable;)Z
       8: pop
       9: return
}
