Compiled from "Platform.java"
final class retrofit2.Platform$Android extends retrofit2.Platform {
  retrofit2.Platform$Android();
    Code:
       0: aload_0
       1: getstatic     #1                  // Field android/os/Build$VERSION.SDK_INT:I
       4: bipush        24
       6: if_icmplt     13
       9: iconst_1
      10: goto          14
      13: iconst_0
      14: invokespecial #7                  // Method retrofit2/Platform."<init>":(Z)V
      17: return

  public java.util.concurrent.Executor defaultCallbackExecutor();
    Code:
       0: new           #13                 // class retrofit2/Platform$Android$MainThreadExecutor
       3: dup
       4: invokespecial #15                 // Method retrofit2/Platform$Android$MainThreadExecutor."<init>":()V
       7: areturn

  java.lang.Object invokeDefaultMethod(java.lang.reflect.Method, java.lang.Class<?>, java.lang.Object, java.lang.Object...) throws java.lang.Throwable;
    Code:
       0: getstatic     #1                  // Field android/os/Build$VERSION.SDK_INT:I
       3: bipush        26
       5: if_icmpge     18
       8: new           #18                 // class java/lang/UnsupportedOperationException
      11: dup
      12: ldc           #20                 // String Calling default methods on API 24 and 25 is not supported
      14: invokespecial #22                 // Method java/lang/UnsupportedOperationException."<init>":(Ljava/lang/String;)V
      17: athrow
      18: aload_0
      19: aload_1
      20: aload_2
      21: aload_3
      22: aload         4
      24: invokespecial #25                 // Method retrofit2/Platform.invokeDefaultMethod:(Ljava/lang/reflect/Method;Ljava/lang/Class;Ljava/lang/Object;[Ljava/lang/Object;)Ljava/lang/Object;
      27: areturn
}
