Compiled from "RequestFactory.java"
final class retrofit2.RequestFactory$Builder {
  private static final java.lang.String PARAM;

  private static final java.util.regex.Pattern PARAM_URL_REGEX;

  private static final java.util.regex.Pattern PARAM_NAME_REGEX;

  final retrofit2.Retrofit retrofit;

  final java.lang.reflect.Method method;

  final java.lang.annotation.Annotation[] methodAnnotations;

  final java.lang.annotation.Annotation[][] parameterAnnotationsArray;

  final java.lang.reflect.Type[] parameterTypes;

  boolean gotField;

  boolean gotPart;

  boolean gotBody;

  boolean gotPath;

  boolean gotQuery;

  boolean gotQueryName;

  boolean gotQueryMap;

  boolean gotUrl;

  java.lang.String httpMethod;

  boolean hasBody;

  boolean isFormEncoded;

  boolean isMultipart;

  java.lang.String relativeUrl;

  okhttp3.Headers headers;

  okhttp3.MediaType contentType;

  java.util.Set<java.lang.String> relativeUrlParamNames;

  retrofit2.ParameterHandler<?>[] parameterHandlers;

  boolean isKotlinSuspendFunction;

  retrofit2.RequestFactory$Builder(retrofit2.Retrofit, java.lang.reflect.Method);
    Code:
       0: aload_0
       1: invokespecial #1                  // Method java/lang/Object."<init>":()V
       4: aload_0
       5: aload_1
       6: putfield      #7                  // Field retrofit:Lretrofit2/Retrofit;
       9: aload_0
      10: aload_2
      11: putfield      #13                 // Field method:Ljava/lang/reflect/Method;
      14: aload_0
      15: aload_2
      16: invokevirtual #17                 // Method java/lang/reflect/Method.getAnnotations:()[Ljava/lang/annotation/Annotation;
      19: putfield      #23                 // Field methodAnnotations:[Ljava/lang/annotation/Annotation;
      22: aload_0
      23: aload_2
      24: invokevirtual #27                 // Method java/lang/reflect/Method.getGenericParameterTypes:()[Ljava/lang/reflect/Type;
      27: putfield      #31                 // Field parameterTypes:[Ljava/lang/reflect/Type;
      30: aload_0
      31: aload_2
      32: invokevirtual #35                 // Method java/lang/reflect/Method.getParameterAnnotations:()[[Ljava/lang/annotation/Annotation;
      35: putfield      #39                 // Field parameterAnnotationsArray:[[Ljava/lang/annotation/Annotation;
      38: return

  retrofit2.RequestFactory build();
    Code:
       0: aload_0
       1: getfield      #23                 // Field methodAnnotations:[Ljava/lang/annotation/Annotation;
       4: astore_1
       5: aload_1
       6: arraylength
       7: istore_2
       8: iconst_0
       9: istore_3
      10: iload_3
      11: iload_2
      12: if_icmpge     32
      15: aload_1
      16: iload_3
      17: aaload
      18: astore        4
      20: aload_0
      21: aload         4
      23: invokespecial #43                 // Method parseMethodAnnotation:(Ljava/lang/annotation/Annotation;)V
      26: iinc          3, 1
      29: goto          10
      32: aload_0
      33: getfield      #47                 // Field httpMethod:Ljava/lang/String;
      36: ifnonnull     53
      39: aload_0
      40: getfield      #13                 // Field method:Ljava/lang/reflect/Method;
      43: ldc           #51                 // String HTTP method annotation is required (e.g., @GET, @POST, etc.).
      45: iconst_0
      46: anewarray     #2                  // class java/lang/Object
      49: invokestatic  #53                 // Method retrofit2/Utils.methodError:(Ljava/lang/reflect/Method;Ljava/lang/String;[Ljava/lang/Object;)Ljava/lang/RuntimeException;
      52: athrow
      53: aload_0
      54: getfield      #59                 // Field hasBody:Z
      57: ifne          102
      60: aload_0
      61: getfield      #63                 // Field isMultipart:Z
      64: ifeq          81
      67: aload_0
      68: getfield      #13                 // Field method:Ljava/lang/reflect/Method;
      71: ldc           #66                 // String Multipart can only be specified on HTTP methods with request body (e.g., @POST).
      73: iconst_0
      74: anewarray     #2                  // class java/lang/Object
      77: invokestatic  #53                 // Method retrofit2/Utils.methodError:(Ljava/lang/reflect/Method;Ljava/lang/String;[Ljava/lang/Object;)Ljava/lang/RuntimeException;
      80: athrow
      81: aload_0
      82: getfield      #68                 // Field isFormEncoded:Z
      85: ifeq          102
      88: aload_0
      89: getfield      #13                 // Field method:Ljava/lang/reflect/Method;
      92: ldc           #71                 // String FormUrlEncoded can only be specified on HTTP methods with request body (e.g., @POST).
      94: iconst_0
      95: anewarray     #2                  // class java/lang/Object
      98: invokestatic  #53                 // Method retrofit2/Utils.methodError:(Ljava/lang/reflect/Method;Ljava/lang/String;[Ljava/lang/Object;)Ljava/lang/RuntimeException;
     101: athrow
     102: aload_0
     103: getfield      #39                 // Field parameterAnnotationsArray:[[Ljava/lang/annotation/Annotation;
     106: arraylength
     107: istore_1
     108: aload_0
     109: iload_1
     110: anewarray     #73                 // class retrofit2/ParameterHandler
     113: putfield      #75                 // Field parameterHandlers:[Lretrofit2/ParameterHandler;
     116: iconst_0
     117: istore_2
     118: iload_1
     119: iconst_1
     120: isub
     121: istore_3
     122: iload_2
     123: iload_1
     124: if_icmpge     166
     127: aload_0
     128: getfield      #75                 // Field parameterHandlers:[Lretrofit2/ParameterHandler;
     131: iload_2
     132: aload_0
     133: iload_2
     134: aload_0
     135: getfield      #31                 // Field parameterTypes:[Ljava/lang/reflect/Type;
     138: iload_2
     139: aaload
     140: aload_0
     141: getfield      #39                 // Field parameterAnnotationsArray:[[Ljava/lang/annotation/Annotation;
     144: iload_2
     145: aaload
     146: iload_2
     147: iload_3
     148: if_icmpne     155
     151: iconst_1
     152: goto          156
     155: iconst_0
     156: invokespecial #79                 // Method parseParameter:(ILjava/lang/reflect/Type;[Ljava/lang/annotation/Annotation;Z)Lretrofit2/ParameterHandler;
     159: aastore
     160: iinc          2, 1
     163: goto          122
     166: aload_0
     167: getfield      #83                 // Field relativeUrl:Ljava/lang/String;
     170: ifnonnull     201
     173: aload_0
     174: getfield      #86                 // Field gotUrl:Z
     177: ifne          201
     180: aload_0
     181: getfield      #13                 // Field method:Ljava/lang/reflect/Method;
     184: ldc           #89                 // String Missing either @%s URL or @Url parameter.
     186: iconst_1
     187: anewarray     #2                  // class java/lang/Object
     190: dup
     191: iconst_0
     192: aload_0
     193: getfield      #47                 // Field httpMethod:Ljava/lang/String;
     196: aastore
     197: invokestatic  #53                 // Method retrofit2/Utils.methodError:(Ljava/lang/reflect/Method;Ljava/lang/String;[Ljava/lang/Object;)Ljava/lang/RuntimeException;
     200: athrow
     201: aload_0
     202: getfield      #68                 // Field isFormEncoded:Z
     205: ifne          243
     208: aload_0
     209: getfield      #63                 // Field isMultipart:Z
     212: ifne          243
     215: aload_0
     216: getfield      #59                 // Field hasBody:Z
     219: ifne          243
     222: aload_0
     223: getfield      #91                 // Field gotBody:Z
     226: ifeq          243
     229: aload_0
     230: getfield      #13                 // Field method:Ljava/lang/reflect/Method;
     233: ldc           #94                 // String Non-body HTTP method cannot contain @Body.
     235: iconst_0
     236: anewarray     #2                  // class java/lang/Object
     239: invokestatic  #53                 // Method retrofit2/Utils.methodError:(Ljava/lang/reflect/Method;Ljava/lang/String;[Ljava/lang/Object;)Ljava/lang/RuntimeException;
     242: athrow
     243: aload_0
     244: getfield      #68                 // Field isFormEncoded:Z
     247: ifeq          271
     250: aload_0
     251: getfield      #96                 // Field gotField:Z
     254: ifne          271
     257: aload_0
     258: getfield      #13                 // Field method:Ljava/lang/reflect/Method;
     261: ldc           #99                 // String Form-encoded method must contain at least one @Field.
     263: iconst_0
     264: anewarray     #2                  // class java/lang/Object
     267: invokestatic  #53                 // Method retrofit2/Utils.methodError:(Ljava/lang/reflect/Method;Ljava/lang/String;[Ljava/lang/Object;)Ljava/lang/RuntimeException;
     270: athrow
     271: aload_0
     272: getfield      #63                 // Field isMultipart:Z
     275: ifeq          299
     278: aload_0
     279: getfield      #101                // Field gotPart:Z
     282: ifne          299
     285: aload_0
     286: getfield      #13                 // Field method:Ljava/lang/reflect/Method;
     289: ldc           #104                // String Multipart method must contain at least one @Part.
     291: iconst_0
     292: anewarray     #2                  // class java/lang/Object
     295: invokestatic  #53                 // Method retrofit2/Utils.methodError:(Ljava/lang/reflect/Method;Ljava/lang/String;[Ljava/lang/Object;)Ljava/lang/RuntimeException;
     298: athrow
     299: new           #106                // class retrofit2/RequestFactory
     302: dup
     303: aload_0
     304: invokespecial #108                // Method retrofit2/RequestFactory."<init>":(Lretrofit2/RequestFactory$Builder;)V
     307: areturn

  private void parseMethodAnnotation(java.lang.annotation.Annotation);
    Code:
       0: aload_1
       1: instanceof    #111                // class retrofit2/http/DELETE
       4: ifeq          26
       7: aload_0
       8: ldc           #113                // String DELETE
      10: aload_1
      11: checkcast     #111                // class retrofit2/http/DELETE
      14: invokeinterface #115,  1          // InterfaceMethod retrofit2/http/DELETE.value:()Ljava/lang/String;
      19: iconst_0
      20: invokespecial #119                // Method parseHttpMethodAndPath:(Ljava/lang/String;Ljava/lang/String;Z)V
      23: goto          336
      26: aload_1
      27: instanceof    #123                // class retrofit2/http/GET
      30: ifeq          52
      33: aload_0
      34: ldc           #125                // String GET
      36: aload_1
      37: checkcast     #123                // class retrofit2/http/GET
      40: invokeinterface #127,  1          // InterfaceMethod retrofit2/http/GET.value:()Ljava/lang/String;
      45: iconst_0
      46: invokespecial #119                // Method parseHttpMethodAndPath:(Ljava/lang/String;Ljava/lang/String;Z)V
      49: goto          336
      52: aload_1
      53: instanceof    #128                // class retrofit2/http/HEAD
      56: ifeq          78
      59: aload_0
      60: ldc           #130                // String HEAD
      62: aload_1
      63: checkcast     #128                // class retrofit2/http/HEAD
      66: invokeinterface #132,  1          // InterfaceMethod retrofit2/http/HEAD.value:()Ljava/lang/String;
      71: iconst_0
      72: invokespecial #119                // Method parseHttpMethodAndPath:(Ljava/lang/String;Ljava/lang/String;Z)V
      75: goto          336
      78: aload_1
      79: instanceof    #133                // class retrofit2/http/PATCH
      82: ifeq          104
      85: aload_0
      86: ldc           #135                // String PATCH
      88: aload_1
      89: checkcast     #133                // class retrofit2/http/PATCH
      92: invokeinterface #137,  1          // InterfaceMethod retrofit2/http/PATCH.value:()Ljava/lang/String;
      97: iconst_1
      98: invokespecial #119                // Method parseHttpMethodAndPath:(Ljava/lang/String;Ljava/lang/String;Z)V
     101: goto          336
     104: aload_1
     105: instanceof    #138                // class retrofit2/http/POST
     108: ifeq          130
     111: aload_0
     112: ldc           #140                // String POST
     114: aload_1
     115: checkcast     #138                // class retrofit2/http/POST
     118: invokeinterface #142,  1          // InterfaceMethod retrofit2/http/POST.value:()Ljava/lang/String;
     123: iconst_1
     124: invokespecial #119                // Method parseHttpMethodAndPath:(Ljava/lang/String;Ljava/lang/String;Z)V
     127: goto          336
     130: aload_1
     131: instanceof    #143                // class retrofit2/http/PUT
     134: ifeq          156
     137: aload_0
     138: ldc           #145                // String PUT
     140: aload_1
     141: checkcast     #143                // class retrofit2/http/PUT
     144: invokeinterface #147,  1          // InterfaceMethod retrofit2/http/PUT.value:()Ljava/lang/String;
     149: iconst_1
     150: invokespecial #119                // Method parseHttpMethodAndPath:(Ljava/lang/String;Ljava/lang/String;Z)V
     153: goto          336
     156: aload_1
     157: instanceof    #148                // class retrofit2/http/OPTIONS
     160: ifeq          182
     163: aload_0
     164: ldc           #150                // String OPTIONS
     166: aload_1
     167: checkcast     #148                // class retrofit2/http/OPTIONS
     170: invokeinterface #152,  1          // InterfaceMethod retrofit2/http/OPTIONS.value:()Ljava/lang/String;
     175: iconst_0
     176: invokespecial #119                // Method parseHttpMethodAndPath:(Ljava/lang/String;Ljava/lang/String;Z)V
     179: goto          336
     182: aload_1
     183: instanceof    #153                // class retrofit2/http/HTTP
     186: ifeq          219
     189: aload_1
     190: checkcast     #153                // class retrofit2/http/HTTP
     193: astore_2
     194: aload_0
     195: aload_2
     196: invokeinterface #155,  1          // InterfaceMethod retrofit2/http/HTTP.method:()Ljava/lang/String;
     201: aload_2
     202: invokeinterface #157,  1          // InterfaceMethod retrofit2/http/HTTP.path:()Ljava/lang/String;
     207: aload_2
     208: invokeinterface #160,  1          // InterfaceMethod retrofit2/http/HTTP.hasBody:()Z
     213: invokespecial #119                // Method parseHttpMethodAndPath:(Ljava/lang/String;Ljava/lang/String;Z)V
     216: goto          336
     219: aload_1
     220: instanceof    #163                // class retrofit2/http/Headers
     223: ifeq          267
     226: aload_1
     227: checkcast     #163                // class retrofit2/http/Headers
     230: invokeinterface #165,  1          // InterfaceMethod retrofit2/http/Headers.value:()[Ljava/lang/String;
     235: astore_2
     236: aload_2
     237: arraylength
     238: ifne          255
     241: aload_0
     242: getfield      #13                 // Field method:Ljava/lang/reflect/Method;
     245: ldc           #168                // String @Headers annotation is empty.
     247: iconst_0
     248: anewarray     #2                  // class java/lang/Object
     251: invokestatic  #53                 // Method retrofit2/Utils.methodError:(Ljava/lang/reflect/Method;Ljava/lang/String;[Ljava/lang/Object;)Ljava/lang/RuntimeException;
     254: athrow
     255: aload_0
     256: aload_0
     257: aload_2
     258: invokespecial #170                // Method parseHeaders:([Ljava/lang/String;)Lokhttp3/Headers;
     261: putfield      #174                // Field headers:Lokhttp3/Headers;
     264: goto          336
     267: aload_1
     268: instanceof    #178                // class retrofit2/http/Multipart
     271: ifeq          303
     274: aload_0
     275: getfield      #68                 // Field isFormEncoded:Z
     278: ifeq          295
     281: aload_0
     282: getfield      #13                 // Field method:Ljava/lang/reflect/Method;
     285: ldc           #180                // String Only one encoding annotation is allowed.
     287: iconst_0
     288: anewarray     #2                  // class java/lang/Object
     291: invokestatic  #53                 // Method retrofit2/Utils.methodError:(Ljava/lang/reflect/Method;Ljava/lang/String;[Ljava/lang/Object;)Ljava/lang/RuntimeException;
     294: athrow
     295: aload_0
     296: iconst_1
     297: putfield      #63                 // Field isMultipart:Z
     300: goto          336
     303: aload_1
     304: instanceof    #182                // class retrofit2/http/FormUrlEncoded
     307: ifeq          336
     310: aload_0
     311: getfield      #63                 // Field isMultipart:Z
     314: ifeq          331
     317: aload_0
     318: getfield      #13                 // Field method:Ljava/lang/reflect/Method;
     321: ldc           #180                // String Only one encoding annotation is allowed.
     323: iconst_0
     324: anewarray     #2                  // class java/lang/Object
     327: invokestatic  #53                 // Method retrofit2/Utils.methodError:(Ljava/lang/reflect/Method;Ljava/lang/String;[Ljava/lang/Object;)Ljava/lang/RuntimeException;
     330: athrow
     331: aload_0
     332: iconst_1
     333: putfield      #68                 // Field isFormEncoded:Z
     336: return

  private void parseHttpMethodAndPath(java.lang.String, java.lang.String, boolean);
    Code:
       0: aload_0
       1: getfield      #47                 // Field httpMethod:Ljava/lang/String;
       4: ifnull        32
       7: aload_0
       8: getfield      #13                 // Field method:Ljava/lang/reflect/Method;
      11: ldc           #184                // String Only one HTTP method is allowed. Found: %s and %s.
      13: iconst_2
      14: anewarray     #2                  // class java/lang/Object
      17: dup
      18: iconst_0
      19: aload_0
      20: getfield      #47                 // Field httpMethod:Ljava/lang/String;
      23: aastore
      24: dup
      25: iconst_1
      26: aload_1
      27: aastore
      28: invokestatic  #53                 // Method retrofit2/Utils.methodError:(Ljava/lang/reflect/Method;Ljava/lang/String;[Ljava/lang/Object;)Ljava/lang/RuntimeException;
      31: athrow
      32: aload_0
      33: aload_1
      34: putfield      #47                 // Field httpMethod:Ljava/lang/String;
      37: aload_0
      38: iload_3
      39: putfield      #59                 // Field hasBody:Z
      42: aload_2
      43: invokevirtual #186                // Method java/lang/String.isEmpty:()Z
      46: ifeq          50
      49: return
      50: aload_2
      51: bipush        63
      53: invokevirtual #191                // Method java/lang/String.indexOf:(I)I
      56: istore        4
      58: iload         4
      60: iconst_m1
      61: if_icmpeq     122
      64: iload         4
      66: aload_2
      67: invokevirtual #195                // Method java/lang/String.length:()I
      70: iconst_1
      71: isub
      72: if_icmpge     122
      75: aload_2
      76: iload         4
      78: iconst_1
      79: iadd
      80: invokevirtual #199                // Method java/lang/String.substring:(I)Ljava/lang/String;
      83: astore        5
      85: getstatic     #203                // Field PARAM_URL_REGEX:Ljava/util/regex/Pattern;
      88: aload         5
      90: invokevirtual #207                // Method java/util/regex/Pattern.matcher:(Ljava/lang/CharSequence;)Ljava/util/regex/Matcher;
      93: astore        6
      95: aload         6
      97: invokevirtual #213                // Method java/util/regex/Matcher.find:()Z
     100: ifeq          122
     103: aload_0
     104: getfield      #13                 // Field method:Ljava/lang/reflect/Method;
     107: ldc           #218                // String URL query string \"%s\" must not have replace block. For dynamic query parameters use @Query.
     109: iconst_1
     110: anewarray     #2                  // class java/lang/Object
     113: dup
     114: iconst_0
     115: aload         5
     117: aastore
     118: invokestatic  #53                 // Method retrofit2/Utils.methodError:(Ljava/lang/reflect/Method;Ljava/lang/String;[Ljava/lang/Object;)Ljava/lang/RuntimeException;
     121: athrow
     122: aload_0
     123: aload_2
     124: putfield      #83                 // Field relativeUrl:Ljava/lang/String;
     127: aload_0
     128: aload_2
     129: invokestatic  #220                // Method parsePathParameters:(Ljava/lang/String;)Ljava/util/Set;
     132: putfield      #224                // Field relativeUrlParamNames:Ljava/util/Set;
     135: return

  private okhttp3.Headers parseHeaders(java.lang.String[]);
    Code:
       0: new           #228                // class okhttp3/Headers$Builder
       3: dup
       4: invokespecial #230                // Method okhttp3/Headers$Builder."<init>":()V
       7: astore_2
       8: aload_1
       9: astore_3
      10: aload_3
      11: arraylength
      12: istore        4
      14: iconst_0
      15: istore        5
      17: iload         5
      19: iload         4
      21: if_icmpge     166
      24: aload_3
      25: iload         5
      27: aaload
      28: astore        6
      30: aload         6
      32: bipush        58
      34: invokevirtual #191                // Method java/lang/String.indexOf:(I)I
      37: istore        7
      39: iload         7
      41: iconst_m1
      42: if_icmpeq     62
      45: iload         7
      47: ifeq          62
      50: iload         7
      52: aload         6
      54: invokevirtual #195                // Method java/lang/String.length:()I
      57: iconst_1
      58: isub
      59: if_icmpne     81
      62: aload_0
      63: getfield      #13                 // Field method:Ljava/lang/reflect/Method;
      66: ldc           #231                // String @Headers value must be in the form \"Name: Value\". Found: \"%s\"
      68: iconst_1
      69: anewarray     #2                  // class java/lang/Object
      72: dup
      73: iconst_0
      74: aload         6
      76: aastore
      77: invokestatic  #53                 // Method retrofit2/Utils.methodError:(Ljava/lang/reflect/Method;Ljava/lang/String;[Ljava/lang/Object;)Ljava/lang/RuntimeException;
      80: athrow
      81: aload         6
      83: iconst_0
      84: iload         7
      86: invokevirtual #233                // Method java/lang/String.substring:(II)Ljava/lang/String;
      89: astore        8
      91: aload         6
      93: iload         7
      95: iconst_1
      96: iadd
      97: invokevirtual #199                // Method java/lang/String.substring:(I)Ljava/lang/String;
     100: invokevirtual #236                // Method java/lang/String.trim:()Ljava/lang/String;
     103: astore        9
     105: ldc           #239                // String Content-Type
     107: aload         8
     109: invokevirtual #241                // Method java/lang/String.equalsIgnoreCase:(Ljava/lang/String;)Z
     112: ifeq          151
     115: aload_0
     116: aload         9
     118: invokestatic  #245                // Method okhttp3/MediaType.get:(Ljava/lang/String;)Lokhttp3/MediaType;
     121: putfield      #251                // Field contentType:Lokhttp3/MediaType;
     124: goto          160
     127: astore        10
     129: aload_0
     130: getfield      #13                 // Field method:Ljava/lang/reflect/Method;
     133: aload         10
     135: ldc_w         #257                // String Malformed content type: %s
     138: iconst_1
     139: anewarray     #2                  // class java/lang/Object
     142: dup
     143: iconst_0
     144: aload         9
     146: aastore
     147: invokestatic  #259                // Method retrofit2/Utils.methodError:(Ljava/lang/reflect/Method;Ljava/lang/Throwable;Ljava/lang/String;[Ljava/lang/Object;)Ljava/lang/RuntimeException;
     150: athrow
     151: aload_2
     152: aload         8
     154: aload         9
     156: invokevirtual #262                // Method okhttp3/Headers$Builder.add:(Ljava/lang/String;Ljava/lang/String;)Lokhttp3/Headers$Builder;
     159: pop
     160: iinc          5, 1
     163: goto          17
     166: aload_2
     167: invokevirtual #266                // Method okhttp3/Headers$Builder.build:()Lokhttp3/Headers;
     170: areturn
    Exception table:
       from    to  target type
         115   124   127   Class java/lang/IllegalArgumentException

  private retrofit2.ParameterHandler<?> parseParameter(int, java.lang.reflect.Type, java.lang.annotation.Annotation[], boolean);
    Code:
       0: aconst_null
       1: astore        5
       3: aload_3
       4: ifnull        82
       7: aload_3
       8: astore        6
      10: aload         6
      12: arraylength
      13: istore        7
      15: iconst_0
      16: istore        8
      18: iload         8
      20: iload         7
      22: if_icmpge     82
      25: aload         6
      27: iload         8
      29: aaload
      30: astore        9
      32: aload_0
      33: iload_1
      34: aload_2
      35: aload_3
      36: aload         9
      38: invokespecial #270                // Method parseParameterAnnotation:(ILjava/lang/reflect/Type;[Ljava/lang/annotation/Annotation;Ljava/lang/annotation/Annotation;)Lretrofit2/ParameterHandler;
      41: astore        10
      43: aload         10
      45: ifnonnull     51
      48: goto          76
      51: aload         5
      53: ifnull        72
      56: aload_0
      57: getfield      #13                 // Field method:Ljava/lang/reflect/Method;
      60: iload_1
      61: ldc_w         #274                // String Multiple Retrofit annotations found, only one allowed.
      64: iconst_0
      65: anewarray     #2                  // class java/lang/Object
      68: invokestatic  #276                // Method retrofit2/Utils.parameterError:(Ljava/lang/reflect/Method;ILjava/lang/String;[Ljava/lang/Object;)Ljava/lang/RuntimeException;
      71: athrow
      72: aload         10
      74: astore        5
      76: iinc          8, 1
      79: goto          18
      82: aload         5
      84: ifnonnull     130
      87: iload         4
      89: ifeq          114
      92: aload_2
      93: invokestatic  #280                // Method retrofit2/Utils.getRawType:(Ljava/lang/reflect/Type;)Ljava/lang/Class;
      96: ldc_w         #284                // class kotlin/coroutines/Continuation
      99: if_acmpne     109
     102: aload_0
     103: iconst_1
     104: putfield      #286                // Field isKotlinSuspendFunction:Z
     107: aconst_null
     108: areturn
     109: goto          114
     112: astore        6
     114: aload_0
     115: getfield      #13                 // Field method:Ljava/lang/reflect/Method;
     118: iload_1
     119: ldc_w         #291                // String No Retrofit annotation found.
     122: iconst_0
     123: anewarray     #2                  // class java/lang/Object
     126: invokestatic  #276                // Method retrofit2/Utils.parameterError:(Ljava/lang/reflect/Method;ILjava/lang/String;[Ljava/lang/Object;)Ljava/lang/RuntimeException;
     129: athrow
     130: aload         5
     132: areturn
    Exception table:
       from    to  target type
          92   108   112   Class java/lang/NoClassDefFoundError

  private retrofit2.ParameterHandler<?> parseParameterAnnotation(int, java.lang.reflect.Type, java.lang.annotation.Annotation[], java.lang.annotation.Annotation);
    Code:
       0: aload         4
       2: instanceof    #293                // class retrofit2/http/Url
       5: ifeq          236
       8: aload_0
       9: iload_1
      10: aload_2
      11: invokespecial #295                // Method validateResolvableType:(ILjava/lang/reflect/Type;)V
      14: aload_0
      15: getfield      #86                 // Field gotUrl:Z
      18: ifeq          37
      21: aload_0
      22: getfield      #13                 // Field method:Ljava/lang/reflect/Method;
      25: iload_1
      26: ldc_w         #299                // String Multiple @Url method annotations found.
      29: iconst_0
      30: anewarray     #2                  // class java/lang/Object
      33: invokestatic  #276                // Method retrofit2/Utils.parameterError:(Ljava/lang/reflect/Method;ILjava/lang/String;[Ljava/lang/Object;)Ljava/lang/RuntimeException;
      36: athrow
      37: aload_0
      38: getfield      #301                // Field gotPath:Z
      41: ifeq          60
      44: aload_0
      45: getfield      #13                 // Field method:Ljava/lang/reflect/Method;
      48: iload_1
      49: ldc_w         #304                // String @Path parameters may not be used with @Url.
      52: iconst_0
      53: anewarray     #2                  // class java/lang/Object
      56: invokestatic  #276                // Method retrofit2/Utils.parameterError:(Ljava/lang/reflect/Method;ILjava/lang/String;[Ljava/lang/Object;)Ljava/lang/RuntimeException;
      59: athrow
      60: aload_0
      61: getfield      #306                // Field gotQuery:Z
      64: ifeq          83
      67: aload_0
      68: getfield      #13                 // Field method:Ljava/lang/reflect/Method;
      71: iload_1
      72: ldc_w         #309                // String A @Url parameter must not come after a @Query.
      75: iconst_0
      76: anewarray     #2                  // class java/lang/Object
      79: invokestatic  #276                // Method retrofit2/Utils.parameterError:(Ljava/lang/reflect/Method;ILjava/lang/String;[Ljava/lang/Object;)Ljava/lang/RuntimeException;
      82: athrow
      83: aload_0
      84: getfield      #311                // Field gotQueryName:Z
      87: ifeq          106
      90: aload_0
      91: getfield      #13                 // Field method:Ljava/lang/reflect/Method;
      94: iload_1
      95: ldc_w         #314                // String A @Url parameter must not come after a @QueryName.
      98: iconst_0
      99: anewarray     #2                  // class java/lang/Object
     102: invokestatic  #276                // Method retrofit2/Utils.parameterError:(Ljava/lang/reflect/Method;ILjava/lang/String;[Ljava/lang/Object;)Ljava/lang/RuntimeException;
     105: athrow
     106: aload_0
     107: getfield      #316                // Field gotQueryMap:Z
     110: ifeq          129
     113: aload_0
     114: getfield      #13                 // Field method:Ljava/lang/reflect/Method;
     117: iload_1
     118: ldc_w         #319                // String A @Url parameter must not come after a @QueryMap.
     121: iconst_0
     122: anewarray     #2                  // class java/lang/Object
     125: invokestatic  #276                // Method retrofit2/Utils.parameterError:(Ljava/lang/reflect/Method;ILjava/lang/String;[Ljava/lang/Object;)Ljava/lang/RuntimeException;
     128: athrow
     129: aload_0
     130: getfield      #83                 // Field relativeUrl:Ljava/lang/String;
     133: ifnull        159
     136: aload_0
     137: getfield      #13                 // Field method:Ljava/lang/reflect/Method;
     140: iload_1
     141: ldc_w         #321                // String @Url cannot be used with @%s URL
     144: iconst_1
     145: anewarray     #2                  // class java/lang/Object
     148: dup
     149: iconst_0
     150: aload_0
     151: getfield      #47                 // Field httpMethod:Ljava/lang/String;
     154: aastore
     155: invokestatic  #276                // Method retrofit2/Utils.parameterError:(Ljava/lang/reflect/Method;ILjava/lang/String;[Ljava/lang/Object;)Ljava/lang/RuntimeException;
     158: athrow
     159: aload_0
     160: iconst_1
     161: putfield      #86                 // Field gotUrl:Z
     164: aload_2
     165: ldc_w         #323                // class okhttp3/HttpUrl
     168: if_acmpeq     207
     171: aload_2
     172: ldc           #187                // class java/lang/String
     174: if_acmpeq     207
     177: aload_2
     178: ldc_w         #325                // class java/net/URI
     181: if_acmpeq     207
     184: aload_2
     185: instanceof    #327                // class java/lang/Class
     188: ifeq          220
     191: ldc_w         #329                // String android.net.Uri
     194: aload_2
     195: checkcast     #327                // class java/lang/Class
     198: invokevirtual #331                // Method java/lang/Class.getName:()Ljava/lang/String;
     201: invokevirtual #334                // Method java/lang/String.equals:(Ljava/lang/Object;)Z
     204: ifeq          220
     207: new           #338                // class retrofit2/ParameterHandler$RelativeUrl
     210: dup
     211: aload_0
     212: getfield      #13                 // Field method:Ljava/lang/reflect/Method;
     215: iload_1
     216: invokespecial #340                // Method retrofit2/ParameterHandler$RelativeUrl."<init>":(Ljava/lang/reflect/Method;I)V
     219: areturn
     220: aload_0
     221: getfield      #13                 // Field method:Ljava/lang/reflect/Method;
     224: iload_1
     225: ldc_w         #343                // String @Url must be okhttp3.HttpUrl, String, java.net.URI, or android.net.Uri type.
     228: iconst_0
     229: anewarray     #2                  // class java/lang/Object
     232: invokestatic  #276                // Method retrofit2/Utils.parameterError:(Ljava/lang/reflect/Method;ILjava/lang/String;[Ljava/lang/Object;)Ljava/lang/RuntimeException;
     235: athrow
     236: aload         4
     238: instanceof    #345                // class retrofit2/http/Path
     241: ifeq          435
     244: aload_0
     245: iload_1
     246: aload_2
     247: invokespecial #295                // Method validateResolvableType:(ILjava/lang/reflect/Type;)V
     250: aload_0
     251: getfield      #306                // Field gotQuery:Z
     254: ifeq          273
     257: aload_0
     258: getfield      #13                 // Field method:Ljava/lang/reflect/Method;
     261: iload_1
     262: ldc_w         #347                // String A @Path parameter must not come after a @Query.
     265: iconst_0
     266: anewarray     #2                  // class java/lang/Object
     269: invokestatic  #276                // Method retrofit2/Utils.parameterError:(Ljava/lang/reflect/Method;ILjava/lang/String;[Ljava/lang/Object;)Ljava/lang/RuntimeException;
     272: athrow
     273: aload_0
     274: getfield      #311                // Field gotQueryName:Z
     277: ifeq          296
     280: aload_0
     281: getfield      #13                 // Field method:Ljava/lang/reflect/Method;
     284: iload_1
     285: ldc_w         #349                // String A @Path parameter must not come after a @QueryName.
     288: iconst_0
     289: anewarray     #2                  // class java/lang/Object
     292: invokestatic  #276                // Method retrofit2/Utils.parameterError:(Ljava/lang/reflect/Method;ILjava/lang/String;[Ljava/lang/Object;)Ljava/lang/RuntimeException;
     295: athrow
     296: aload_0
     297: getfield      #316                // Field gotQueryMap:Z
     300: ifeq          319
     303: aload_0
     304: getfield      #13                 // Field method:Ljava/lang/reflect/Method;
     307: iload_1
     308: ldc_w         #351                // String A @Path parameter must not come after a @QueryMap.
     311: iconst_0
     312: anewarray     #2                  // class java/lang/Object
     315: invokestatic  #276                // Method retrofit2/Utils.parameterError:(Ljava/lang/reflect/Method;ILjava/lang/String;[Ljava/lang/Object;)Ljava/lang/RuntimeException;
     318: athrow
     319: aload_0
     320: getfield      #86                 // Field gotUrl:Z
     323: ifeq          342
     326: aload_0
     327: getfield      #13                 // Field method:Ljava/lang/reflect/Method;
     330: iload_1
     331: ldc_w         #304                // String @Path parameters may not be used with @Url.
     334: iconst_0
     335: anewarray     #2                  // class java/lang/Object
     338: invokestatic  #276                // Method retrofit2/Utils.parameterError:(Ljava/lang/reflect/Method;ILjava/lang/String;[Ljava/lang/Object;)Ljava/lang/RuntimeException;
     341: athrow
     342: aload_0
     343: getfield      #83                 // Field relativeUrl:Ljava/lang/String;
     346: ifnonnull     372
     349: aload_0
     350: getfield      #13                 // Field method:Ljava/lang/reflect/Method;
     353: iload_1
     354: ldc_w         #353                // String @Path can only be used with relative url on @%s
     357: iconst_1
     358: anewarray     #2                  // class java/lang/Object
     361: dup
     362: iconst_0
     363: aload_0
     364: getfield      #47                 // Field httpMethod:Ljava/lang/String;
     367: aastore
     368: invokestatic  #276                // Method retrofit2/Utils.parameterError:(Ljava/lang/reflect/Method;ILjava/lang/String;[Ljava/lang/Object;)Ljava/lang/RuntimeException;
     371: athrow
     372: aload_0
     373: iconst_1
     374: putfield      #301                // Field gotPath:Z
     377: aload         4
     379: checkcast     #345                // class retrofit2/http/Path
     382: astore        5
     384: aload         5
     386: invokeinterface #355,  1          // InterfaceMethod retrofit2/http/Path.value:()Ljava/lang/String;
     391: astore        6
     393: aload_0
     394: iload_1
     395: aload         6
     397: invokespecial #356                // Method validatePathName:(ILjava/lang/String;)V
     400: aload_0
     401: getfield      #7                  // Field retrofit:Lretrofit2/Retrofit;
     404: aload_2
     405: aload_3
     406: invokevirtual #360                // Method retrofit2/Retrofit.stringConverter:(Ljava/lang/reflect/Type;[Ljava/lang/annotation/Annotation;)Lretrofit2/Converter;
     409: astore        7
     411: new           #366                // class retrofit2/ParameterHandler$Path
     414: dup
     415: aload_0
     416: getfield      #13                 // Field method:Ljava/lang/reflect/Method;
     419: iload_1
     420: aload         6
     422: aload         7
     424: aload         5
     426: invokeinterface #368,  1          // InterfaceMethod retrofit2/http/Path.encoded:()Z
     431: invokespecial #371                // Method retrofit2/ParameterHandler$Path."<init>":(Ljava/lang/reflect/Method;ILjava/lang/String;Lretrofit2/Converter;Z)V
     434: areturn
     435: aload         4
     437: instanceof    #374                // class retrofit2/http/Query
     440: ifeq          669
     443: aload_0
     444: iload_1
     445: aload_2
     446: invokespecial #295                // Method validateResolvableType:(ILjava/lang/reflect/Type;)V
     449: aload         4
     451: checkcast     #374                // class retrofit2/http/Query
     454: astore        5
     456: aload         5
     458: invokeinterface #376,  1          // InterfaceMethod retrofit2/http/Query.value:()Ljava/lang/String;
     463: astore        6
     465: aload         5
     467: invokeinterface #377,  1          // InterfaceMethod retrofit2/http/Query.encoded:()Z
     472: istore        7
     474: aload_2
     475: invokestatic  #280                // Method retrofit2/Utils.getRawType:(Ljava/lang/reflect/Type;)Ljava/lang/Class;
     478: astore        8
     480: aload_0
     481: iconst_1
     482: putfield      #306                // Field gotQuery:Z
     485: ldc_w         #378                // class java/lang/Iterable
     488: aload         8
     490: invokevirtual #380                // Method java/lang/Class.isAssignableFrom:(Ljava/lang/Class;)Z
     493: ifeq          597
     496: aload_2
     497: instanceof    #384                // class java/lang/reflect/ParameterizedType
     500: ifne          554
     503: aload_0
     504: getfield      #13                 // Field method:Ljava/lang/reflect/Method;
     507: iload_1
     508: new           #386                // class java/lang/StringBuilder
     511: dup
     512: invokespecial #388                // Method java/lang/StringBuilder."<init>":()V
     515: aload         8
     517: invokevirtual #389                // Method java/lang/Class.getSimpleName:()Ljava/lang/String;
     520: invokevirtual #392                // Method java/lang/StringBuilder.append:(Ljava/lang/String;)Ljava/lang/StringBuilder;
     523: ldc_w         #396                // String  must include generic type (e.g.,
     526: invokevirtual #392                // Method java/lang/StringBuilder.append:(Ljava/lang/String;)Ljava/lang/StringBuilder;
     529: aload         8
     531: invokevirtual #389                // Method java/lang/Class.getSimpleName:()Ljava/lang/String;
     534: invokevirtual #392                // Method java/lang/StringBuilder.append:(Ljava/lang/String;)Ljava/lang/StringBuilder;
     537: ldc_w         #398                // String <String>)
     540: invokevirtual #392                // Method java/lang/StringBuilder.append:(Ljava/lang/String;)Ljava/lang/StringBuilder;
     543: invokevirtual #400                // Method java/lang/StringBuilder.toString:()Ljava/lang/String;
     546: iconst_0
     547: anewarray     #2                  // class java/lang/Object
     550: invokestatic  #276                // Method retrofit2/Utils.parameterError:(Ljava/lang/reflect/Method;ILjava/lang/String;[Ljava/lang/Object;)Ljava/lang/RuntimeException;
     553: athrow
     554: aload_2
     555: checkcast     #384                // class java/lang/reflect/ParameterizedType
     558: astore        9
     560: iconst_0
     561: aload         9
     563: invokestatic  #403                // Method retrofit2/Utils.getParameterUpperBound:(ILjava/lang/reflect/ParameterizedType;)Ljava/lang/reflect/Type;
     566: astore        10
     568: aload_0
     569: getfield      #7                  // Field retrofit:Lretrofit2/Retrofit;
     572: aload         10
     574: aload_3
     575: invokevirtual #360                // Method retrofit2/Retrofit.stringConverter:(Ljava/lang/reflect/Type;[Ljava/lang/annotation/Annotation;)Lretrofit2/Converter;
     578: astore        11
     580: new           #407                // class retrofit2/ParameterHandler$Query
     583: dup
     584: aload         6
     586: aload         11
     588: iload         7
     590: invokespecial #409                // Method retrofit2/ParameterHandler$Query."<init>":(Ljava/lang/String;Lretrofit2/Converter;Z)V
     593: invokevirtual #412                // Method retrofit2/ParameterHandler$Query.iterable:()Lretrofit2/ParameterHandler;
     596: areturn
     597: aload         8
     599: invokevirtual #416                // Method java/lang/Class.isArray:()Z
     602: ifeq          644
     605: aload         8
     607: invokevirtual #419                // Method java/lang/Class.getComponentType:()Ljava/lang/Class;
     610: invokestatic  #423                // Method boxIfPrimitive:(Ljava/lang/Class;)Ljava/lang/Class;
     613: astore        9
     615: aload_0
     616: getfield      #7                  // Field retrofit:Lretrofit2/Retrofit;
     619: aload         9
     621: aload_3
     622: invokevirtual #360                // Method retrofit2/Retrofit.stringConverter:(Ljava/lang/reflect/Type;[Ljava/lang/annotation/Annotation;)Lretrofit2/Converter;
     625: astore        10
     627: new           #407                // class retrofit2/ParameterHandler$Query
     630: dup
     631: aload         6
     633: aload         10
     635: iload         7
     637: invokespecial #409                // Method retrofit2/ParameterHandler$Query."<init>":(Ljava/lang/String;Lretrofit2/Converter;Z)V
     640: invokevirtual #427                // Method retrofit2/ParameterHandler$Query.array:()Lretrofit2/ParameterHandler;
     643: areturn
     644: aload_0
     645: getfield      #7                  // Field retrofit:Lretrofit2/Retrofit;
     648: aload_2
     649: aload_3
     650: invokevirtual #360                // Method retrofit2/Retrofit.stringConverter:(Ljava/lang/reflect/Type;[Ljava/lang/annotation/Annotation;)Lretrofit2/Converter;
     653: astore        9
     655: new           #407                // class retrofit2/ParameterHandler$Query
     658: dup
     659: aload         6
     661: aload         9
     663: iload         7
     665: invokespecial #409                // Method retrofit2/ParameterHandler$Query."<init>":(Ljava/lang/String;Lretrofit2/Converter;Z)V
     668: areturn
     669: aload         4
     671: instanceof    #430                // class retrofit2/http/QueryName
     674: ifeq          888
     677: aload_0
     678: iload_1
     679: aload_2
     680: invokespecial #295                // Method validateResolvableType:(ILjava/lang/reflect/Type;)V
     683: aload         4
     685: checkcast     #430                // class retrofit2/http/QueryName
     688: astore        5
     690: aload         5
     692: invokeinterface #432,  1          // InterfaceMethod retrofit2/http/QueryName.encoded:()Z
     697: istore        6
     699: aload_2
     700: invokestatic  #280                // Method retrofit2/Utils.getRawType:(Ljava/lang/reflect/Type;)Ljava/lang/Class;
     703: astore        7
     705: aload_0
     706: iconst_1
     707: putfield      #311                // Field gotQueryName:Z
     710: ldc_w         #378                // class java/lang/Iterable
     713: aload         7
     715: invokevirtual #380                // Method java/lang/Class.isAssignableFrom:(Ljava/lang/Class;)Z
     718: ifeq          820
     721: aload_2
     722: instanceof    #384                // class java/lang/reflect/ParameterizedType
     725: ifne          779
     728: aload_0
     729: getfield      #13                 // Field method:Ljava/lang/reflect/Method;
     732: iload_1
     733: new           #386                // class java/lang/StringBuilder
     736: dup
     737: invokespecial #388                // Method java/lang/StringBuilder."<init>":()V
     740: aload         7
     742: invokevirtual #389                // Method java/lang/Class.getSimpleName:()Ljava/lang/String;
     745: invokevirtual #392                // Method java/lang/StringBuilder.append:(Ljava/lang/String;)Ljava/lang/StringBuilder;
     748: ldc_w         #396                // String  must include generic type (e.g.,
     751: invokevirtual #392                // Method java/lang/StringBuilder.append:(Ljava/lang/String;)Ljava/lang/StringBuilder;
     754: aload         7
     756: invokevirtual #389                // Method java/lang/Class.getSimpleName:()Ljava/lang/String;
     759: invokevirtual #392                // Method java/lang/StringBuilder.append:(Ljava/lang/String;)Ljava/lang/StringBuilder;
     762: ldc_w         #398                // String <String>)
     765: invokevirtual #392                // Method java/lang/StringBuilder.append:(Ljava/lang/String;)Ljava/lang/StringBuilder;
     768: invokevirtual #400                // Method java/lang/StringBuilder.toString:()Ljava/lang/String;
     771: iconst_0
     772: anewarray     #2                  // class java/lang/Object
     775: invokestatic  #276                // Method retrofit2/Utils.parameterError:(Ljava/lang/reflect/Method;ILjava/lang/String;[Ljava/lang/Object;)Ljava/lang/RuntimeException;
     778: athrow
     779: aload_2
     780: checkcast     #384                // class java/lang/reflect/ParameterizedType
     783: astore        8
     785: iconst_0
     786: aload         8
     788: invokestatic  #403                // Method retrofit2/Utils.getParameterUpperBound:(ILjava/lang/reflect/ParameterizedType;)Ljava/lang/reflect/Type;
     791: astore        9
     793: aload_0
     794: getfield      #7                  // Field retrofit:Lretrofit2/Retrofit;
     797: aload         9
     799: aload_3
     800: invokevirtual #360                // Method retrofit2/Retrofit.stringConverter:(Ljava/lang/reflect/Type;[Ljava/lang/annotation/Annotation;)Lretrofit2/Converter;
     803: astore        10
     805: new           #433                // class retrofit2/ParameterHandler$QueryName
     808: dup
     809: aload         10
     811: iload         6
     813: invokespecial #435                // Method retrofit2/ParameterHandler$QueryName."<init>":(Lretrofit2/Converter;Z)V
     816: invokevirtual #438                // Method retrofit2/ParameterHandler$QueryName.iterable:()Lretrofit2/ParameterHandler;
     819: areturn
     820: aload         7
     822: invokevirtual #416                // Method java/lang/Class.isArray:()Z
     825: ifeq          865
     828: aload         7
     830: invokevirtual #419                // Method java/lang/Class.getComponentType:()Ljava/lang/Class;
     833: invokestatic  #423                // Method boxIfPrimitive:(Ljava/lang/Class;)Ljava/lang/Class;
     836: astore        8
     838: aload_0
     839: getfield      #7                  // Field retrofit:Lretrofit2/Retrofit;
     842: aload         8
     844: aload_3
     845: invokevirtual #360                // Method retrofit2/Retrofit.stringConverter:(Ljava/lang/reflect/Type;[Ljava/lang/annotation/Annotation;)Lretrofit2/Converter;
     848: astore        9
     850: new           #433                // class retrofit2/ParameterHandler$QueryName
     853: dup
     854: aload         9
     856: iload         6
     858: invokespecial #435                // Method retrofit2/ParameterHandler$QueryName."<init>":(Lretrofit2/Converter;Z)V
     861: invokevirtual #439                // Method retrofit2/ParameterHandler$QueryName.array:()Lretrofit2/ParameterHandler;
     864: areturn
     865: aload_0
     866: getfield      #7                  // Field retrofit:Lretrofit2/Retrofit;
     869: aload_2
     870: aload_3
     871: invokevirtual #360                // Method retrofit2/Retrofit.stringConverter:(Ljava/lang/reflect/Type;[Ljava/lang/annotation/Annotation;)Lretrofit2/Converter;
     874: astore        8
     876: new           #433                // class retrofit2/ParameterHandler$QueryName
     879: dup
     880: aload         8
     882: iload         6
     884: invokespecial #435                // Method retrofit2/ParameterHandler$QueryName."<init>":(Lretrofit2/Converter;Z)V
     887: areturn
     888: aload         4
     890: instanceof    #440                // class retrofit2/http/QueryMap
     893: ifeq          1076
     896: aload_0
     897: iload_1
     898: aload_2
     899: invokespecial #295                // Method validateResolvableType:(ILjava/lang/reflect/Type;)V
     902: aload_2
     903: invokestatic  #280                // Method retrofit2/Utils.getRawType:(Ljava/lang/reflect/Type;)Ljava/lang/Class;
     906: astore        5
     908: aload_0
     909: iconst_1
     910: putfield      #316                // Field gotQueryMap:Z
     913: ldc_w         #442                // class java/util/Map
     916: aload         5
     918: invokevirtual #380                // Method java/lang/Class.isAssignableFrom:(Ljava/lang/Class;)Z
     921: ifne          940
     924: aload_0
     925: getfield      #13                 // Field method:Ljava/lang/reflect/Method;
     928: iload_1
     929: ldc_w         #444                // String @QueryMap parameter type must be Map.
     932: iconst_0
     933: anewarray     #2                  // class java/lang/Object
     936: invokestatic  #276                // Method retrofit2/Utils.parameterError:(Ljava/lang/reflect/Method;ILjava/lang/String;[Ljava/lang/Object;)Ljava/lang/RuntimeException;
     939: athrow
     940: aload_2
     941: aload         5
     943: ldc_w         #442                // class java/util/Map
     946: invokestatic  #446                // Method retrofit2/Utils.getSupertype:(Ljava/lang/reflect/Type;Ljava/lang/Class;Ljava/lang/Class;)Ljava/lang/reflect/Type;
     949: astore        6
     951: aload         6
     953: instanceof    #384                // class java/lang/reflect/ParameterizedType
     956: ifne          975
     959: aload_0
     960: getfield      #13                 // Field method:Ljava/lang/reflect/Method;
     963: iload_1
     964: ldc_w         #450                // String Map must include generic types (e.g., Map<String, String>)
     967: iconst_0
     968: anewarray     #2                  // class java/lang/Object
     971: invokestatic  #276                // Method retrofit2/Utils.parameterError:(Ljava/lang/reflect/Method;ILjava/lang/String;[Ljava/lang/Object;)Ljava/lang/RuntimeException;
     974: athrow
     975: aload         6
     977: checkcast     #384                // class java/lang/reflect/ParameterizedType
     980: astore        7
     982: iconst_0
     983: aload         7
     985: invokestatic  #403                // Method retrofit2/Utils.getParameterUpperBound:(ILjava/lang/reflect/ParameterizedType;)Ljava/lang/reflect/Type;
     988: astore        8
     990: ldc           #187                // class java/lang/String
     992: aload         8
     994: if_acmpeq     1031
     997: aload_0
     998: getfield      #13                 // Field method:Ljava/lang/reflect/Method;
    1001: iload_1
    1002: new           #386                // class java/lang/StringBuilder
    1005: dup
    1006: invokespecial #388                // Method java/lang/StringBuilder."<init>":()V
    1009: ldc_w         #452                // String @QueryMap keys must be of type String:
    1012: invokevirtual #392                // Method java/lang/StringBuilder.append:(Ljava/lang/String;)Ljava/lang/StringBuilder;
    1015: aload         8
    1017: invokevirtual #454                // Method java/lang/StringBuilder.append:(Ljava/lang/Object;)Ljava/lang/StringBuilder;
    1020: invokevirtual #400                // Method java/lang/StringBuilder.toString:()Ljava/lang/String;
    1023: iconst_0
    1024: anewarray     #2                  // class java/lang/Object
    1027: invokestatic  #276                // Method retrofit2/Utils.parameterError:(Ljava/lang/reflect/Method;ILjava/lang/String;[Ljava/lang/Object;)Ljava/lang/RuntimeException;
    1030: athrow
    1031: iconst_1
    1032: aload         7
    1034: invokestatic  #403                // Method retrofit2/Utils.getParameterUpperBound:(ILjava/lang/reflect/ParameterizedType;)Ljava/lang/reflect/Type;
    1037: astore        9
    1039: aload_0
    1040: getfield      #7                  // Field retrofit:Lretrofit2/Retrofit;
    1043: aload         9
    1045: aload_3
    1046: invokevirtual #360                // Method retrofit2/Retrofit.stringConverter:(Ljava/lang/reflect/Type;[Ljava/lang/annotation/Annotation;)Lretrofit2/Converter;
    1049: astore        10
    1051: new           #457                // class retrofit2/ParameterHandler$QueryMap
    1054: dup
    1055: aload_0
    1056: getfield      #13                 // Field method:Ljava/lang/reflect/Method;
    1059: iload_1
    1060: aload         10
    1062: aload         4
    1064: checkcast     #440                // class retrofit2/http/QueryMap
    1067: invokeinterface #459,  1          // InterfaceMethod retrofit2/http/QueryMap.encoded:()Z
    1072: invokespecial #460                // Method retrofit2/ParameterHandler$QueryMap."<init>":(Ljava/lang/reflect/Method;ILretrofit2/Converter;Z)V
    1075: areturn
    1076: aload         4
    1078: instanceof    #463                // class retrofit2/http/Header
    1081: ifeq          1290
    1084: aload_0
    1085: iload_1
    1086: aload_2
    1087: invokespecial #295                // Method validateResolvableType:(ILjava/lang/reflect/Type;)V
    1090: aload         4
    1092: checkcast     #463                // class retrofit2/http/Header
    1095: astore        5
    1097: aload         5
    1099: invokeinterface #465,  1          // InterfaceMethod retrofit2/http/Header.value:()Ljava/lang/String;
    1104: astore        6
    1106: aload_2
    1107: invokestatic  #280                // Method retrofit2/Utils.getRawType:(Ljava/lang/reflect/Type;)Ljava/lang/Class;
    1110: astore        7
    1112: ldc_w         #378                // class java/lang/Iterable
    1115: aload         7
    1117: invokevirtual #380                // Method java/lang/Class.isAssignableFrom:(Ljava/lang/Class;)Z
    1120: ifeq          1222
    1123: aload_2
    1124: instanceof    #384                // class java/lang/reflect/ParameterizedType
    1127: ifne          1181
    1130: aload_0
    1131: getfield      #13                 // Field method:Ljava/lang/reflect/Method;
    1134: iload_1
    1135: new           #386                // class java/lang/StringBuilder
    1138: dup
    1139: invokespecial #388                // Method java/lang/StringBuilder."<init>":()V
    1142: aload         7
    1144: invokevirtual #389                // Method java/lang/Class.getSimpleName:()Ljava/lang/String;
    1147: invokevirtual #392                // Method java/lang/StringBuilder.append:(Ljava/lang/String;)Ljava/lang/StringBuilder;
    1150: ldc_w         #396                // String  must include generic type (e.g.,
    1153: invokevirtual #392                // Method java/lang/StringBuilder.append:(Ljava/lang/String;)Ljava/lang/StringBuilder;
    1156: aload         7
    1158: invokevirtual #389                // Method java/lang/Class.getSimpleName:()Ljava/lang/String;
    1161: invokevirtual #392                // Method java/lang/StringBuilder.append:(Ljava/lang/String;)Ljava/lang/StringBuilder;
    1164: ldc_w         #398                // String <String>)
    1167: invokevirtual #392                // Method java/lang/StringBuilder.append:(Ljava/lang/String;)Ljava/lang/StringBuilder;
    1170: invokevirtual #400                // Method java/lang/StringBuilder.toString:()Ljava/lang/String;
    1173: iconst_0
    1174: anewarray     #2                  // class java/lang/Object
    1177: invokestatic  #276                // Method retrofit2/Utils.parameterError:(Ljava/lang/reflect/Method;ILjava/lang/String;[Ljava/lang/Object;)Ljava/lang/RuntimeException;
    1180: athrow
    1181: aload_2
    1182: checkcast     #384                // class java/lang/reflect/ParameterizedType
    1185: astore        8
    1187: iconst_0
    1188: aload         8
    1190: invokestatic  #403                // Method retrofit2/Utils.getParameterUpperBound:(ILjava/lang/reflect/ParameterizedType;)Ljava/lang/reflect/Type;
    1193: astore        9
    1195: aload_0
    1196: getfield      #7                  // Field retrofit:Lretrofit2/Retrofit;
    1199: aload         9
    1201: aload_3
    1202: invokevirtual #360                // Method retrofit2/Retrofit.stringConverter:(Ljava/lang/reflect/Type;[Ljava/lang/annotation/Annotation;)Lretrofit2/Converter;
    1205: astore        10
    1207: new           #466                // class retrofit2/ParameterHandler$Header
    1210: dup
    1211: aload         6
    1213: aload         10
    1215: invokespecial #468                // Method retrofit2/ParameterHandler$Header."<init>":(Ljava/lang/String;Lretrofit2/Converter;)V
    1218: invokevirtual #471                // Method retrofit2/ParameterHandler$Header.iterable:()Lretrofit2/ParameterHandler;
    1221: areturn
    1222: aload         7
    1224: invokevirtual #416                // Method java/lang/Class.isArray:()Z
    1227: ifeq          1267
    1230: aload         7
    1232: invokevirtual #419                // Method java/lang/Class.getComponentType:()Ljava/lang/Class;
    1235: invokestatic  #423                // Method boxIfPrimitive:(Ljava/lang/Class;)Ljava/lang/Class;
    1238: astore        8
    1240: aload_0
    1241: getfield      #7                  // Field retrofit:Lretrofit2/Retrofit;
    1244: aload         8
    1246: aload_3
    1247: invokevirtual #360                // Method retrofit2/Retrofit.stringConverter:(Ljava/lang/reflect/Type;[Ljava/lang/annotation/Annotation;)Lretrofit2/Converter;
    1250: astore        9
    1252: new           #466                // class retrofit2/ParameterHandler$Header
    1255: dup
    1256: aload         6
    1258: aload         9
    1260: invokespecial #468                // Method retrofit2/ParameterHandler$Header."<init>":(Ljava/lang/String;Lretrofit2/Converter;)V
    1263: invokevirtual #472                // Method retrofit2/ParameterHandler$Header.array:()Lretrofit2/ParameterHandler;
    1266: areturn
    1267: aload_0
    1268: getfield      #7                  // Field retrofit:Lretrofit2/Retrofit;
    1271: aload_2
    1272: aload_3
    1273: invokevirtual #360                // Method retrofit2/Retrofit.stringConverter:(Ljava/lang/reflect/Type;[Ljava/lang/annotation/Annotation;)Lretrofit2/Converter;
    1276: astore        8
    1278: new           #466                // class retrofit2/ParameterHandler$Header
    1281: dup
    1282: aload         6
    1284: aload         8
    1286: invokespecial #468                // Method retrofit2/ParameterHandler$Header."<init>":(Ljava/lang/String;Lretrofit2/Converter;)V
    1289: areturn
    1290: aload         4
    1292: instanceof    #473                // class retrofit2/http/HeaderMap
    1295: ifeq          1483
    1298: aload_2
    1299: ldc_w         #475                // class okhttp3/Headers
    1302: if_acmpne     1318
    1305: new           #477                // class retrofit2/ParameterHandler$Headers
    1308: dup
    1309: aload_0
    1310: getfield      #13                 // Field method:Ljava/lang/reflect/Method;
    1313: iload_1
    1314: invokespecial #479                // Method retrofit2/ParameterHandler$Headers."<init>":(Ljava/lang/reflect/Method;I)V
    1317: areturn
    1318: aload_0
    1319: iload_1
    1320: aload_2
    1321: invokespecial #295                // Method validateResolvableType:(ILjava/lang/reflect/Type;)V
    1324: aload_2
    1325: invokestatic  #280                // Method retrofit2/Utils.getRawType:(Ljava/lang/reflect/Type;)Ljava/lang/Class;
    1328: astore        5
    1330: ldc_w         #442                // class java/util/Map
    1333: aload         5
    1335: invokevirtual #380                // Method java/lang/Class.isAssignableFrom:(Ljava/lang/Class;)Z
    1338: ifne          1357
    1341: aload_0
    1342: getfield      #13                 // Field method:Ljava/lang/reflect/Method;
    1345: iload_1
    1346: ldc_w         #480                // String @HeaderMap parameter type must be Map.
    1349: iconst_0
    1350: anewarray     #2                  // class java/lang/Object
    1353: invokestatic  #276                // Method retrofit2/Utils.parameterError:(Ljava/lang/reflect/Method;ILjava/lang/String;[Ljava/lang/Object;)Ljava/lang/RuntimeException;
    1356: athrow
    1357: aload_2
    1358: aload         5
    1360: ldc_w         #442                // class java/util/Map
    1363: invokestatic  #446                // Method retrofit2/Utils.getSupertype:(Ljava/lang/reflect/Type;Ljava/lang/Class;Ljava/lang/Class;)Ljava/lang/reflect/Type;
    1366: astore        6
    1368: aload         6
    1370: instanceof    #384                // class java/lang/reflect/ParameterizedType
    1373: ifne          1392
    1376: aload_0
    1377: getfield      #13                 // Field method:Ljava/lang/reflect/Method;
    1380: iload_1
    1381: ldc_w         #450                // String Map must include generic types (e.g., Map<String, String>)
    1384: iconst_0
    1385: anewarray     #2                  // class java/lang/Object
    1388: invokestatic  #276                // Method retrofit2/Utils.parameterError:(Ljava/lang/reflect/Method;ILjava/lang/String;[Ljava/lang/Object;)Ljava/lang/RuntimeException;
    1391: athrow
    1392: aload         6
    1394: checkcast     #384                // class java/lang/reflect/ParameterizedType
    1397: astore        7
    1399: iconst_0
    1400: aload         7
    1402: invokestatic  #403                // Method retrofit2/Utils.getParameterUpperBound:(ILjava/lang/reflect/ParameterizedType;)Ljava/lang/reflect/Type;
    1405: astore        8
    1407: ldc           #187                // class java/lang/String
    1409: aload         8
    1411: if_acmpeq     1448
    1414: aload_0
    1415: getfield      #13                 // Field method:Ljava/lang/reflect/Method;
    1418: iload_1
    1419: new           #386                // class java/lang/StringBuilder
    1422: dup
    1423: invokespecial #388                // Method java/lang/StringBuilder."<init>":()V
    1426: ldc_w         #482                // String @HeaderMap keys must be of type String:
    1429: invokevirtual #392                // Method java/lang/StringBuilder.append:(Ljava/lang/String;)Ljava/lang/StringBuilder;
    1432: aload         8
    1434: invokevirtual #454                // Method java/lang/StringBuilder.append:(Ljava/lang/Object;)Ljava/lang/StringBuilder;
    1437: invokevirtual #400                // Method java/lang/StringBuilder.toString:()Ljava/lang/String;
    1440: iconst_0
    1441: anewarray     #2                  // class java/lang/Object
    1444: invokestatic  #276                // Method retrofit2/Utils.parameterError:(Ljava/lang/reflect/Method;ILjava/lang/String;[Ljava/lang/Object;)Ljava/lang/RuntimeException;
    1447: athrow
    1448: iconst_1
    1449: aload         7
    1451: invokestatic  #403                // Method retrofit2/Utils.getParameterUpperBound:(ILjava/lang/reflect/ParameterizedType;)Ljava/lang/reflect/Type;
    1454: astore        9
    1456: aload_0
    1457: getfield      #7                  // Field retrofit:Lretrofit2/Retrofit;
    1460: aload         9
    1462: aload_3
    1463: invokevirtual #360                // Method retrofit2/Retrofit.stringConverter:(Ljava/lang/reflect/Type;[Ljava/lang/annotation/Annotation;)Lretrofit2/Converter;
    1466: astore        10
    1468: new           #484                // class retrofit2/ParameterHandler$HeaderMap
    1471: dup
    1472: aload_0
    1473: getfield      #13                 // Field method:Ljava/lang/reflect/Method;
    1476: iload_1
    1477: aload         10
    1479: invokespecial #486                // Method retrofit2/ParameterHandler$HeaderMap."<init>":(Ljava/lang/reflect/Method;ILretrofit2/Converter;)V
    1482: areturn
    1483: aload         4
    1485: instanceof    #489                // class retrofit2/http/Field
    1488: ifeq          1740
    1491: aload_0
    1492: iload_1
    1493: aload_2
    1494: invokespecial #295                // Method validateResolvableType:(ILjava/lang/reflect/Type;)V
    1497: aload_0
    1498: getfield      #68                 // Field isFormEncoded:Z
    1501: ifne          1520
    1504: aload_0
    1505: getfield      #13                 // Field method:Ljava/lang/reflect/Method;
    1508: iload_1
    1509: ldc_w         #491                // String @Field parameters can only be used with form encoding.
    1512: iconst_0
    1513: anewarray     #2                  // class java/lang/Object
    1516: invokestatic  #276                // Method retrofit2/Utils.parameterError:(Ljava/lang/reflect/Method;ILjava/lang/String;[Ljava/lang/Object;)Ljava/lang/RuntimeException;
    1519: athrow
    1520: aload         4
    1522: checkcast     #489                // class retrofit2/http/Field
    1525: astore        5
    1527: aload         5
    1529: invokeinterface #493,  1          // InterfaceMethod retrofit2/http/Field.value:()Ljava/lang/String;
    1534: astore        6
    1536: aload         5
    1538: invokeinterface #494,  1          // InterfaceMethod retrofit2/http/Field.encoded:()Z
    1543: istore        7
    1545: aload_0
    1546: iconst_1
    1547: putfield      #96                 // Field gotField:Z
    1550: aload_2
    1551: invokestatic  #280                // Method retrofit2/Utils.getRawType:(Ljava/lang/reflect/Type;)Ljava/lang/Class;
    1554: astore        8
    1556: ldc_w         #378                // class java/lang/Iterable
    1559: aload         8
    1561: invokevirtual #380                // Method java/lang/Class.isAssignableFrom:(Ljava/lang/Class;)Z
    1564: ifeq          1668
    1567: aload_2
    1568: instanceof    #384                // class java/lang/reflect/ParameterizedType
    1571: ifne          1625
    1574: aload_0
    1575: getfield      #13                 // Field method:Ljava/lang/reflect/Method;
    1578: iload_1
    1579: new           #386                // class java/lang/StringBuilder
    1582: dup
    1583: invokespecial #388                // Method java/lang/StringBuilder."<init>":()V
    1586: aload         8
    1588: invokevirtual #389                // Method java/lang/Class.getSimpleName:()Ljava/lang/String;
    1591: invokevirtual #392                // Method java/lang/StringBuilder.append:(Ljava/lang/String;)Ljava/lang/StringBuilder;
    1594: ldc_w         #396                // String  must include generic type (e.g.,
    1597: invokevirtual #392                // Method java/lang/StringBuilder.append:(Ljava/lang/String;)Ljava/lang/StringBuilder;
    1600: aload         8
    1602: invokevirtual #389                // Method java/lang/Class.getSimpleName:()Ljava/lang/String;
    1605: invokevirtual #392                // Method java/lang/StringBuilder.append:(Ljava/lang/String;)Ljava/lang/StringBuilder;
    1608: ldc_w         #398                // String <String>)
    1611: invokevirtual #392                // Method java/lang/StringBuilder.append:(Ljava/lang/String;)Ljava/lang/StringBuilder;
    1614: invokevirtual #400                // Method java/lang/StringBuilder.toString:()Ljava/lang/String;
    1617: iconst_0
    1618: anewarray     #2                  // class java/lang/Object
    1621: invokestatic  #276                // Method retrofit2/Utils.parameterError:(Ljava/lang/reflect/Method;ILjava/lang/String;[Ljava/lang/Object;)Ljava/lang/RuntimeException;
    1624: athrow
    1625: aload_2
    1626: checkcast     #384                // class java/lang/reflect/ParameterizedType
    1629: astore        9
    1631: iconst_0
    1632: aload         9
    1634: invokestatic  #403                // Method retrofit2/Utils.getParameterUpperBound:(ILjava/lang/reflect/ParameterizedType;)Ljava/lang/reflect/Type;
    1637: astore        10
    1639: aload_0
    1640: getfield      #7                  // Field retrofit:Lretrofit2/Retrofit;
    1643: aload         10
    1645: aload_3
    1646: invokevirtual #360                // Method retrofit2/Retrofit.stringConverter:(Ljava/lang/reflect/Type;[Ljava/lang/annotation/Annotation;)Lretrofit2/Converter;
    1649: astore        11
    1651: new           #495                // class retrofit2/ParameterHandler$Field
    1654: dup
    1655: aload         6
    1657: aload         11
    1659: iload         7
    1661: invokespecial #497                // Method retrofit2/ParameterHandler$Field."<init>":(Ljava/lang/String;Lretrofit2/Converter;Z)V
    1664: invokevirtual #498                // Method retrofit2/ParameterHandler$Field.iterable:()Lretrofit2/ParameterHandler;
    1667: areturn
    1668: aload         8
    1670: invokevirtual #416                // Method java/lang/Class.isArray:()Z
    1673: ifeq          1715
    1676: aload         8
    1678: invokevirtual #419                // Method java/lang/Class.getComponentType:()Ljava/lang/Class;
    1681: invokestatic  #423                // Method boxIfPrimitive:(Ljava/lang/Class;)Ljava/lang/Class;
    1684: astore        9
    1686: aload_0
    1687: getfield      #7                  // Field retrofit:Lretrofit2/Retrofit;
    1690: aload         9
    1692: aload_3
    1693: invokevirtual #360                // Method retrofit2/Retrofit.stringConverter:(Ljava/lang/reflect/Type;[Ljava/lang/annotation/Annotation;)Lretrofit2/Converter;
    1696: astore        10
    1698: new           #495                // class retrofit2/ParameterHandler$Field
    1701: dup
    1702: aload         6
    1704: aload         10
    1706: iload         7
    1708: invokespecial #497                // Method retrofit2/ParameterHandler$Field."<init>":(Ljava/lang/String;Lretrofit2/Converter;Z)V
    1711: invokevirtual #499                // Method retrofit2/ParameterHandler$Field.array:()Lretrofit2/ParameterHandler;
    1714: areturn
    1715: aload_0
    1716: getfield      #7                  // Field retrofit:Lretrofit2/Retrofit;
    1719: aload_2
    1720: aload_3
    1721: invokevirtual #360                // Method retrofit2/Retrofit.stringConverter:(Ljava/lang/reflect/Type;[Ljava/lang/annotation/Annotation;)Lretrofit2/Converter;
    1724: astore        9
    1726: new           #495                // class retrofit2/ParameterHandler$Field
    1729: dup
    1730: aload         6
    1732: aload         9
    1734: iload         7
    1736: invokespecial #497                // Method retrofit2/ParameterHandler$Field."<init>":(Ljava/lang/String;Lretrofit2/Converter;Z)V
    1739: areturn
    1740: aload         4
    1742: instanceof    #500                // class retrofit2/http/FieldMap
    1745: ifeq          1951
    1748: aload_0
    1749: iload_1
    1750: aload_2
    1751: invokespecial #295                // Method validateResolvableType:(ILjava/lang/reflect/Type;)V
    1754: aload_0
    1755: getfield      #68                 // Field isFormEncoded:Z
    1758: ifne          1777
    1761: aload_0
    1762: getfield      #13                 // Field method:Ljava/lang/reflect/Method;
    1765: iload_1
    1766: ldc_w         #502                // String @FieldMap parameters can only be used with form encoding.
    1769: iconst_0
    1770: anewarray     #2                  // class java/lang/Object
    1773: invokestatic  #276                // Method retrofit2/Utils.parameterError:(Ljava/lang/reflect/Method;ILjava/lang/String;[Ljava/lang/Object;)Ljava/lang/RuntimeException;
    1776: athrow
    1777: aload_2
    1778: invokestatic  #280                // Method retrofit2/Utils.getRawType:(Ljava/lang/reflect/Type;)Ljava/lang/Class;
    1781: astore        5
    1783: ldc_w         #442                // class java/util/Map
    1786: aload         5
    1788: invokevirtual #380                // Method java/lang/Class.isAssignableFrom:(Ljava/lang/Class;)Z
    1791: ifne          1810
    1794: aload_0
    1795: getfield      #13                 // Field method:Ljava/lang/reflect/Method;
    1798: iload_1
    1799: ldc_w         #504                // String @FieldMap parameter type must be Map.
    1802: iconst_0
    1803: anewarray     #2                  // class java/lang/Object
    1806: invokestatic  #276                // Method retrofit2/Utils.parameterError:(Ljava/lang/reflect/Method;ILjava/lang/String;[Ljava/lang/Object;)Ljava/lang/RuntimeException;
    1809: athrow
    1810: aload_2
    1811: aload         5
    1813: ldc_w         #442                // class java/util/Map
    1816: invokestatic  #446                // Method retrofit2/Utils.getSupertype:(Ljava/lang/reflect/Type;Ljava/lang/Class;Ljava/lang/Class;)Ljava/lang/reflect/Type;
    1819: astore        6
    1821: aload         6
    1823: instanceof    #384                // class java/lang/reflect/ParameterizedType
    1826: ifne          1845
    1829: aload_0
    1830: getfield      #13                 // Field method:Ljava/lang/reflect/Method;
    1833: iload_1
    1834: ldc_w         #450                // String Map must include generic types (e.g., Map<String, String>)
    1837: iconst_0
    1838: anewarray     #2                  // class java/lang/Object
    1841: invokestatic  #276                // Method retrofit2/Utils.parameterError:(Ljava/lang/reflect/Method;ILjava/lang/String;[Ljava/lang/Object;)Ljava/lang/RuntimeException;
    1844: athrow
    1845: aload         6
    1847: checkcast     #384                // class java/lang/reflect/ParameterizedType
    1850: astore        7
    1852: iconst_0
    1853: aload         7
    1855: invokestatic  #403                // Method retrofit2/Utils.getParameterUpperBound:(ILjava/lang/reflect/ParameterizedType;)Ljava/lang/reflect/Type;
    1858: astore        8
    1860: ldc           #187                // class java/lang/String
    1862: aload         8
    1864: if_acmpeq     1901
    1867: aload_0
    1868: getfield      #13                 // Field method:Ljava/lang/reflect/Method;
    1871: iload_1
    1872: new           #386                // class java/lang/StringBuilder
    1875: dup
    1876: invokespecial #388                // Method java/lang/StringBuilder."<init>":()V
    1879: ldc_w         #506                // String @FieldMap keys must be of type String:
    1882: invokevirtual #392                // Method java/lang/StringBuilder.append:(Ljava/lang/String;)Ljava/lang/StringBuilder;
    1885: aload         8
    1887: invokevirtual #454                // Method java/lang/StringBuilder.append:(Ljava/lang/Object;)Ljava/lang/StringBuilder;
    1890: invokevirtual #400                // Method java/lang/StringBuilder.toString:()Ljava/lang/String;
    1893: iconst_0
    1894: anewarray     #2                  // class java/lang/Object
    1897: invokestatic  #276                // Method retrofit2/Utils.parameterError:(Ljava/lang/reflect/Method;ILjava/lang/String;[Ljava/lang/Object;)Ljava/lang/RuntimeException;
    1900: athrow
    1901: iconst_1
    1902: aload         7
    1904: invokestatic  #403                // Method retrofit2/Utils.getParameterUpperBound:(ILjava/lang/reflect/ParameterizedType;)Ljava/lang/reflect/Type;
    1907: astore        9
    1909: aload_0
    1910: getfield      #7                  // Field retrofit:Lretrofit2/Retrofit;
    1913: aload         9
    1915: aload_3
    1916: invokevirtual #360                // Method retrofit2/Retrofit.stringConverter:(Ljava/lang/reflect/Type;[Ljava/lang/annotation/Annotation;)Lretrofit2/Converter;
    1919: astore        10
    1921: aload_0
    1922: iconst_1
    1923: putfield      #96                 // Field gotField:Z
    1926: new           #508                // class retrofit2/ParameterHandler$FieldMap
    1929: dup
    1930: aload_0
    1931: getfield      #13                 // Field method:Ljava/lang/reflect/Method;
    1934: iload_1
    1935: aload         10
    1937: aload         4
    1939: checkcast     #500                // class retrofit2/http/FieldMap
    1942: invokeinterface #510,  1          // InterfaceMethod retrofit2/http/FieldMap.encoded:()Z
    1947: invokespecial #511                // Method retrofit2/ParameterHandler$FieldMap."<init>":(Ljava/lang/reflect/Method;ILretrofit2/Converter;Z)V
    1950: areturn
    1951: aload         4
    1953: instanceof    #512                // class retrofit2/http/Part
    1956: ifeq          2573
    1959: aload_0
    1960: iload_1
    1961: aload_2
    1962: invokespecial #295                // Method validateResolvableType:(ILjava/lang/reflect/Type;)V
    1965: aload_0
    1966: getfield      #63                 // Field isMultipart:Z
    1969: ifne          1988
    1972: aload_0
    1973: getfield      #13                 // Field method:Ljava/lang/reflect/Method;
    1976: iload_1
    1977: ldc_w         #514                // String @Part parameters can only be used with multipart encoding.
    1980: iconst_0
    1981: anewarray     #2                  // class java/lang/Object
    1984: invokestatic  #276                // Method retrofit2/Utils.parameterError:(Ljava/lang/reflect/Method;ILjava/lang/String;[Ljava/lang/Object;)Ljava/lang/RuntimeException;
    1987: athrow
    1988: aload         4
    1990: checkcast     #512                // class retrofit2/http/Part
    1993: astore        5
    1995: aload_0
    1996: iconst_1
    1997: putfield      #101                // Field gotPart:Z
    2000: aload         5
    2002: invokeinterface #516,  1          // InterfaceMethod retrofit2/http/Part.value:()Ljava/lang/String;
    2007: astore        6
    2009: aload_2
    2010: invokestatic  #280                // Method retrofit2/Utils.getRawType:(Ljava/lang/reflect/Type;)Ljava/lang/Class;
    2013: astore        7
    2015: aload         6
    2017: invokevirtual #186                // Method java/lang/String.isEmpty:()Z
    2020: ifeq          2223
    2023: ldc_w         #378                // class java/lang/Iterable
    2026: aload         7
    2028: invokevirtual #380                // Method java/lang/Class.isAssignableFrom:(Ljava/lang/Class;)Z
    2031: ifeq          2143
    2034: aload_2
    2035: instanceof    #384                // class java/lang/reflect/ParameterizedType
    2038: ifne          2092
    2041: aload_0
    2042: getfield      #13                 // Field method:Ljava/lang/reflect/Method;
    2045: iload_1
    2046: new           #386                // class java/lang/StringBuilder
    2049: dup
    2050: invokespecial #388                // Method java/lang/StringBuilder."<init>":()V
    2053: aload         7
    2055: invokevirtual #389                // Method java/lang/Class.getSimpleName:()Ljava/lang/String;
    2058: invokevirtual #392                // Method java/lang/StringBuilder.append:(Ljava/lang/String;)Ljava/lang/StringBuilder;
    2061: ldc_w         #396                // String  must include generic type (e.g.,
    2064: invokevirtual #392                // Method java/lang/StringBuilder.append:(Ljava/lang/String;)Ljava/lang/StringBuilder;
    2067: aload         7
    2069: invokevirtual #389                // Method java/lang/Class.getSimpleName:()Ljava/lang/String;
    2072: invokevirtual #392                // Method java/lang/StringBuilder.append:(Ljava/lang/String;)Ljava/lang/StringBuilder;
    2075: ldc_w         #398                // String <String>)
    2078: invokevirtual #392                // Method java/lang/StringBuilder.append:(Ljava/lang/String;)Ljava/lang/StringBuilder;
    2081: invokevirtual #400                // Method java/lang/StringBuilder.toString:()Ljava/lang/String;
    2084: iconst_0
    2085: anewarray     #2                  // class java/lang/Object
    2088: invokestatic  #276                // Method retrofit2/Utils.parameterError:(Ljava/lang/reflect/Method;ILjava/lang/String;[Ljava/lang/Object;)Ljava/lang/RuntimeException;
    2091: athrow
    2092: aload_2
    2093: checkcast     #384                // class java/lang/reflect/ParameterizedType
    2096: astore        8
    2098: iconst_0
    2099: aload         8
    2101: invokestatic  #403                // Method retrofit2/Utils.getParameterUpperBound:(ILjava/lang/reflect/ParameterizedType;)Ljava/lang/reflect/Type;
    2104: astore        9
    2106: ldc_w         #517                // class okhttp3/MultipartBody$Part
    2109: aload         9
    2111: invokestatic  #280                // Method retrofit2/Utils.getRawType:(Ljava/lang/reflect/Type;)Ljava/lang/Class;
    2114: invokevirtual #380                // Method java/lang/Class.isAssignableFrom:(Ljava/lang/Class;)Z
    2117: ifne          2136
    2120: aload_0
    2121: getfield      #13                 // Field method:Ljava/lang/reflect/Method;
    2124: iload_1
    2125: ldc_w         #519                // String @Part annotation must supply a name or use MultipartBody.Part parameter type.
    2128: iconst_0
    2129: anewarray     #2                  // class java/lang/Object
    2132: invokestatic  #276                // Method retrofit2/Utils.parameterError:(Ljava/lang/reflect/Method;ILjava/lang/String;[Ljava/lang/Object;)Ljava/lang/RuntimeException;
    2135: athrow
    2136: getstatic     #521                // Field retrofit2/ParameterHandler$RawPart.INSTANCE:Lretrofit2/ParameterHandler$RawPart;
    2139: invokevirtual #527                // Method retrofit2/ParameterHandler$RawPart.iterable:()Lretrofit2/ParameterHandler;
    2142: areturn
    2143: aload         7
    2145: invokevirtual #416                // Method java/lang/Class.isArray:()Z
    2148: ifeq          2192
    2151: aload         7
    2153: invokevirtual #419                // Method java/lang/Class.getComponentType:()Ljava/lang/Class;
    2156: astore        8
    2158: ldc_w         #517                // class okhttp3/MultipartBody$Part
    2161: aload         8
    2163: invokevirtual #380                // Method java/lang/Class.isAssignableFrom:(Ljava/lang/Class;)Z
    2166: ifne          2185
    2169: aload_0
    2170: getfield      #13                 // Field method:Ljava/lang/reflect/Method;
    2173: iload_1
    2174: ldc_w         #519                // String @Part annotation must supply a name or use MultipartBody.Part parameter type.
    2177: iconst_0
    2178: anewarray     #2                  // class java/lang/Object
    2181: invokestatic  #276                // Method retrofit2/Utils.parameterError:(Ljava/lang/reflect/Method;ILjava/lang/String;[Ljava/lang/Object;)Ljava/lang/RuntimeException;
    2184: athrow
    2185: getstatic     #521                // Field retrofit2/ParameterHandler$RawPart.INSTANCE:Lretrofit2/ParameterHandler$RawPart;
    2188: invokevirtual #528                // Method retrofit2/ParameterHandler$RawPart.array:()Lretrofit2/ParameterHandler;
    2191: areturn
    2192: ldc_w         #517                // class okhttp3/MultipartBody$Part
    2195: aload         7
    2197: invokevirtual #380                // Method java/lang/Class.isAssignableFrom:(Ljava/lang/Class;)Z
    2200: ifeq          2207
    2203: getstatic     #521                // Field retrofit2/ParameterHandler$RawPart.INSTANCE:Lretrofit2/ParameterHandler$RawPart;
    2206: areturn
    2207: aload_0
    2208: getfield      #13                 // Field method:Ljava/lang/reflect/Method;
    2211: iload_1
    2212: ldc_w         #519                // String @Part annotation must supply a name or use MultipartBody.Part parameter type.
    2215: iconst_0
    2216: anewarray     #2                  // class java/lang/Object
    2219: invokestatic  #276                // Method retrofit2/Utils.parameterError:(Ljava/lang/reflect/Method;ILjava/lang/String;[Ljava/lang/Object;)Ljava/lang/RuntimeException;
    2222: athrow
    2223: iconst_4
    2224: anewarray     #187                // class java/lang/String
    2227: dup
    2228: iconst_0
    2229: ldc_w         #529                // String Content-Disposition
    2232: aastore
    2233: dup
    2234: iconst_1
    2235: new           #386                // class java/lang/StringBuilder
    2238: dup
    2239: invokespecial #388                // Method java/lang/StringBuilder."<init>":()V
    2242: ldc_w         #531                // String form-data; name=\"
    2245: invokevirtual #392                // Method java/lang/StringBuilder.append:(Ljava/lang/String;)Ljava/lang/StringBuilder;
    2248: aload         6
    2250: invokevirtual #392                // Method java/lang/StringBuilder.append:(Ljava/lang/String;)Ljava/lang/StringBuilder;
    2253: ldc_w         #533                // String \"
    2256: invokevirtual #392                // Method java/lang/StringBuilder.append:(Ljava/lang/String;)Ljava/lang/StringBuilder;
    2259: invokevirtual #400                // Method java/lang/StringBuilder.toString:()Ljava/lang/String;
    2262: aastore
    2263: dup
    2264: iconst_2
    2265: ldc_w         #535                // String Content-Transfer-Encoding
    2268: aastore
    2269: dup
    2270: iconst_3
    2271: aload         5
    2273: invokeinterface #537,  1          // InterfaceMethod retrofit2/http/Part.encoding:()Ljava/lang/String;
    2278: aastore
    2279: invokestatic  #540                // Method okhttp3/Headers.of:([Ljava/lang/String;)Lokhttp3/Headers;
    2282: astore        8
    2284: ldc_w         #378                // class java/lang/Iterable
    2287: aload         7
    2289: invokevirtual #380                // Method java/lang/Class.isAssignableFrom:(Ljava/lang/Class;)Z
    2292: ifeq          2433
    2295: aload_2
    2296: instanceof    #384                // class java/lang/reflect/ParameterizedType
    2299: ifne          2353
    2302: aload_0
    2303: getfield      #13                 // Field method:Ljava/lang/reflect/Method;
    2306: iload_1
    2307: new           #386                // class java/lang/StringBuilder
    2310: dup
    2311: invokespecial #388                // Method java/lang/StringBuilder."<init>":()V
    2314: aload         7
    2316: invokevirtual #389                // Method java/lang/Class.getSimpleName:()Ljava/lang/String;
    2319: invokevirtual #392                // Method java/lang/StringBuilder.append:(Ljava/lang/String;)Ljava/lang/StringBuilder;
    2322: ldc_w         #396                // String  must include generic type (e.g.,
    2325: invokevirtual #392                // Method java/lang/StringBuilder.append:(Ljava/lang/String;)Ljava/lang/StringBuilder;
    2328: aload         7
    2330: invokevirtual #389                // Method java/lang/Class.getSimpleName:()Ljava/lang/String;
    2333: invokevirtual #392                // Method java/lang/StringBuilder.append:(Ljava/lang/String;)Ljava/lang/StringBuilder;
    2336: ldc_w         #398                // String <String>)
    2339: invokevirtual #392                // Method java/lang/StringBuilder.append:(Ljava/lang/String;)Ljava/lang/StringBuilder;
    2342: invokevirtual #400                // Method java/lang/StringBuilder.toString:()Ljava/lang/String;
    2345: iconst_0
    2346: anewarray     #2                  // class java/lang/Object
    2349: invokestatic  #276                // Method retrofit2/Utils.parameterError:(Ljava/lang/reflect/Method;ILjava/lang/String;[Ljava/lang/Object;)Ljava/lang/RuntimeException;
    2352: athrow
    2353: aload_2
    2354: checkcast     #384                // class java/lang/reflect/ParameterizedType
    2357: astore        9
    2359: iconst_0
    2360: aload         9
    2362: invokestatic  #403                // Method retrofit2/Utils.getParameterUpperBound:(ILjava/lang/reflect/ParameterizedType;)Ljava/lang/reflect/Type;
    2365: astore        10
    2367: ldc_w         #517                // class okhttp3/MultipartBody$Part
    2370: aload         10
    2372: invokestatic  #280                // Method retrofit2/Utils.getRawType:(Ljava/lang/reflect/Type;)Ljava/lang/Class;
    2375: invokevirtual #380                // Method java/lang/Class.isAssignableFrom:(Ljava/lang/Class;)Z
    2378: ifeq          2397
    2381: aload_0
    2382: getfield      #13                 // Field method:Ljava/lang/reflect/Method;
    2385: iload_1
    2386: ldc_w         #543                // String @Part parameters using the MultipartBody.Part must not include a part name in the annotation.
    2389: iconst_0
    2390: anewarray     #2                  // class java/lang/Object
    2393: invokestatic  #276                // Method retrofit2/Utils.parameterError:(Ljava/lang/reflect/Method;ILjava/lang/String;[Ljava/lang/Object;)Ljava/lang/RuntimeException;
    2396: athrow
    2397: aload_0
    2398: getfield      #7                  // Field retrofit:Lretrofit2/Retrofit;
    2401: aload         10
    2403: aload_3
    2404: aload_0
    2405: getfield      #23                 // Field methodAnnotations:[Ljava/lang/annotation/Annotation;
    2408: invokevirtual #545                // Method retrofit2/Retrofit.requestBodyConverter:(Ljava/lang/reflect/Type;[Ljava/lang/annotation/Annotation;[Ljava/lang/annotation/Annotation;)Lretrofit2/Converter;
    2411: astore        11
    2413: new           #549                // class retrofit2/ParameterHandler$Part
    2416: dup
    2417: aload_0
    2418: getfield      #13                 // Field method:Ljava/lang/reflect/Method;
    2421: iload_1
    2422: aload         8
    2424: aload         11
    2426: invokespecial #551                // Method retrofit2/ParameterHandler$Part."<init>":(Ljava/lang/reflect/Method;ILokhttp3/Headers;Lretrofit2/Converter;)V
    2429: invokevirtual #554                // Method retrofit2/ParameterHandler$Part.iterable:()Lretrofit2/ParameterHandler;
    2432: areturn
    2433: aload         7
    2435: invokevirtual #416                // Method java/lang/Class.isArray:()Z
    2438: ifeq          2514
    2441: aload         7
    2443: invokevirtual #419                // Method java/lang/Class.getComponentType:()Ljava/lang/Class;
    2446: invokestatic  #423                // Method boxIfPrimitive:(Ljava/lang/Class;)Ljava/lang/Class;
    2449: astore        9
    2451: ldc_w         #517                // class okhttp3/MultipartBody$Part
    2454: aload         9
    2456: invokevirtual #380                // Method java/lang/Class.isAssignableFrom:(Ljava/lang/Class;)Z
    2459: ifeq          2478
    2462: aload_0
    2463: getfield      #13                 // Field method:Ljava/lang/reflect/Method;
    2466: iload_1
    2467: ldc_w         #543                // String @Part parameters using the MultipartBody.Part must not include a part name in the annotation.
    2470: iconst_0
    2471: anewarray     #2                  // class java/lang/Object
    2474: invokestatic  #276                // Method retrofit2/Utils.parameterError:(Ljava/lang/reflect/Method;ILjava/lang/String;[Ljava/lang/Object;)Ljava/lang/RuntimeException;
    2477: athrow
    2478: aload_0
    2479: getfield      #7                  // Field retrofit:Lretrofit2/Retrofit;
    2482: aload         9
    2484: aload_3
    2485: aload_0
    2486: getfield      #23                 // Field methodAnnotations:[Ljava/lang/annotation/Annotation;
    2489: invokevirtual #545                // Method retrofit2/Retrofit.requestBodyConverter:(Ljava/lang/reflect/Type;[Ljava/lang/annotation/Annotation;[Ljava/lang/annotation/Annotation;)Lretrofit2/Converter;
    2492: astore        10
    2494: new           #549                // class retrofit2/ParameterHandler$Part
    2497: dup
    2498: aload_0
    2499: getfield      #13                 // Field method:Ljava/lang/reflect/Method;
    2502: iload_1
    2503: aload         8
    2505: aload         10
    2507: invokespecial #551                // Method retrofit2/ParameterHandler$Part."<init>":(Ljava/lang/reflect/Method;ILokhttp3/Headers;Lretrofit2/Converter;)V
    2510: invokevirtual #555                // Method retrofit2/ParameterHandler$Part.array:()Lretrofit2/ParameterHandler;
    2513: areturn
    2514: ldc_w         #517                // class okhttp3/MultipartBody$Part
    2517: aload         7
    2519: invokevirtual #380                // Method java/lang/Class.isAssignableFrom:(Ljava/lang/Class;)Z
    2522: ifeq          2541
    2525: aload_0
    2526: getfield      #13                 // Field method:Ljava/lang/reflect/Method;
    2529: iload_1
    2530: ldc_w         #543                // String @Part parameters using the MultipartBody.Part must not include a part name in the annotation.
    2533: iconst_0
    2534: anewarray     #2                  // class java/lang/Object
    2537: invokestatic  #276                // Method retrofit2/Utils.parameterError:(Ljava/lang/reflect/Method;ILjava/lang/String;[Ljava/lang/Object;)Ljava/lang/RuntimeException;
    2540: athrow
    2541: aload_0
    2542: getfield      #7                  // Field retrofit:Lretrofit2/Retrofit;
    2545: aload_2
    2546: aload_3
    2547: aload_0
    2548: getfield      #23                 // Field methodAnnotations:[Ljava/lang/annotation/Annotation;
    2551: invokevirtual #545                // Method retrofit2/Retrofit.requestBodyConverter:(Ljava/lang/reflect/Type;[Ljava/lang/annotation/Annotation;[Ljava/lang/annotation/Annotation;)Lretrofit2/Converter;
    2554: astore        9
    2556: new           #549                // class retrofit2/ParameterHandler$Part
    2559: dup
    2560: aload_0
    2561: getfield      #13                 // Field method:Ljava/lang/reflect/Method;
    2564: iload_1
    2565: aload         8
    2567: aload         9
    2569: invokespecial #551                // Method retrofit2/ParameterHandler$Part."<init>":(Ljava/lang/reflect/Method;ILokhttp3/Headers;Lretrofit2/Converter;)V
    2572: areturn
    2573: aload         4
    2575: instanceof    #556                // class retrofit2/http/PartMap
    2578: ifeq          2822
    2581: aload_0
    2582: iload_1
    2583: aload_2
    2584: invokespecial #295                // Method validateResolvableType:(ILjava/lang/reflect/Type;)V
    2587: aload_0
    2588: getfield      #63                 // Field isMultipart:Z
    2591: ifne          2610
    2594: aload_0
    2595: getfield      #13                 // Field method:Ljava/lang/reflect/Method;
    2598: iload_1
    2599: ldc_w         #558                // String @PartMap parameters can only be used with multipart encoding.
    2602: iconst_0
    2603: anewarray     #2                  // class java/lang/Object
    2606: invokestatic  #276                // Method retrofit2/Utils.parameterError:(Ljava/lang/reflect/Method;ILjava/lang/String;[Ljava/lang/Object;)Ljava/lang/RuntimeException;
    2609: athrow
    2610: aload_0
    2611: iconst_1
    2612: putfield      #101                // Field gotPart:Z
    2615: aload_2
    2616: invokestatic  #280                // Method retrofit2/Utils.getRawType:(Ljava/lang/reflect/Type;)Ljava/lang/Class;
    2619: astore        5
    2621: ldc_w         #442                // class java/util/Map
    2624: aload         5
    2626: invokevirtual #380                // Method java/lang/Class.isAssignableFrom:(Ljava/lang/Class;)Z
    2629: ifne          2648
    2632: aload_0
    2633: getfield      #13                 // Field method:Ljava/lang/reflect/Method;
    2636: iload_1
    2637: ldc_w         #560                // String @PartMap parameter type must be Map.
    2640: iconst_0
    2641: anewarray     #2                  // class java/lang/Object
    2644: invokestatic  #276                // Method retrofit2/Utils.parameterError:(Ljava/lang/reflect/Method;ILjava/lang/String;[Ljava/lang/Object;)Ljava/lang/RuntimeException;
    2647: athrow
    2648: aload_2
    2649: aload         5
    2651: ldc_w         #442                // class java/util/Map
    2654: invokestatic  #446                // Method retrofit2/Utils.getSupertype:(Ljava/lang/reflect/Type;Ljava/lang/Class;Ljava/lang/Class;)Ljava/lang/reflect/Type;
    2657: astore        6
    2659: aload         6
    2661: instanceof    #384                // class java/lang/reflect/ParameterizedType
    2664: ifne          2683
    2667: aload_0
    2668: getfield      #13                 // Field method:Ljava/lang/reflect/Method;
    2671: iload_1
    2672: ldc_w         #450                // String Map must include generic types (e.g., Map<String, String>)
    2675: iconst_0
    2676: anewarray     #2                  // class java/lang/Object
    2679: invokestatic  #276                // Method retrofit2/Utils.parameterError:(Ljava/lang/reflect/Method;ILjava/lang/String;[Ljava/lang/Object;)Ljava/lang/RuntimeException;
    2682: athrow
    2683: aload         6
    2685: checkcast     #384                // class java/lang/reflect/ParameterizedType
    2688: astore        7
    2690: iconst_0
    2691: aload         7
    2693: invokestatic  #403                // Method retrofit2/Utils.getParameterUpperBound:(ILjava/lang/reflect/ParameterizedType;)Ljava/lang/reflect/Type;
    2696: astore        8
    2698: ldc           #187                // class java/lang/String
    2700: aload         8
    2702: if_acmpeq     2739
    2705: aload_0
    2706: getfield      #13                 // Field method:Ljava/lang/reflect/Method;
    2709: iload_1
    2710: new           #386                // class java/lang/StringBuilder
    2713: dup
    2714: invokespecial #388                // Method java/lang/StringBuilder."<init>":()V
    2717: ldc_w         #562                // String @PartMap keys must be of type String:
    2720: invokevirtual #392                // Method java/lang/StringBuilder.append:(Ljava/lang/String;)Ljava/lang/StringBuilder;
    2723: aload         8
    2725: invokevirtual #454                // Method java/lang/StringBuilder.append:(Ljava/lang/Object;)Ljava/lang/StringBuilder;
    2728: invokevirtual #400                // Method java/lang/StringBuilder.toString:()Ljava/lang/String;
    2731: iconst_0
    2732: anewarray     #2                  // class java/lang/Object
    2735: invokestatic  #276                // Method retrofit2/Utils.parameterError:(Ljava/lang/reflect/Method;ILjava/lang/String;[Ljava/lang/Object;)Ljava/lang/RuntimeException;
    2738: athrow
    2739: iconst_1
    2740: aload         7
    2742: invokestatic  #403                // Method retrofit2/Utils.getParameterUpperBound:(ILjava/lang/reflect/ParameterizedType;)Ljava/lang/reflect/Type;
    2745: astore        9
    2747: ldc_w         #517                // class okhttp3/MultipartBody$Part
    2750: aload         9
    2752: invokestatic  #280                // Method retrofit2/Utils.getRawType:(Ljava/lang/reflect/Type;)Ljava/lang/Class;
    2755: invokevirtual #380                // Method java/lang/Class.isAssignableFrom:(Ljava/lang/Class;)Z
    2758: ifeq          2777
    2761: aload_0
    2762: getfield      #13                 // Field method:Ljava/lang/reflect/Method;
    2765: iload_1
    2766: ldc_w         #564                // String @PartMap values cannot be MultipartBody.Part. Use @Part List<Part> or a different value type instead.
    2769: iconst_0
    2770: anewarray     #2                  // class java/lang/Object
    2773: invokestatic  #276                // Method retrofit2/Utils.parameterError:(Ljava/lang/reflect/Method;ILjava/lang/String;[Ljava/lang/Object;)Ljava/lang/RuntimeException;
    2776: athrow
    2777: aload_0
    2778: getfield      #7                  // Field retrofit:Lretrofit2/Retrofit;
    2781: aload         9
    2783: aload_3
    2784: aload_0
    2785: getfield      #23                 // Field methodAnnotations:[Ljava/lang/annotation/Annotation;
    2788: invokevirtual #545                // Method retrofit2/Retrofit.requestBodyConverter:(Ljava/lang/reflect/Type;[Ljava/lang/annotation/Annotation;[Ljava/lang/annotation/Annotation;)Lretrofit2/Converter;
    2791: astore        10
    2793: aload         4
    2795: checkcast     #556                // class retrofit2/http/PartMap
    2798: astore        11
    2800: new           #566                // class retrofit2/ParameterHandler$PartMap
    2803: dup
    2804: aload_0
    2805: getfield      #13                 // Field method:Ljava/lang/reflect/Method;
    2808: iload_1
    2809: aload         10
    2811: aload         11
    2813: invokeinterface #568,  1          // InterfaceMethod retrofit2/http/PartMap.encoding:()Ljava/lang/String;
    2818: invokespecial #569                // Method retrofit2/ParameterHandler$PartMap."<init>":(Ljava/lang/reflect/Method;ILretrofit2/Converter;Ljava/lang/String;)V
    2821: areturn
    2822: aload         4
    2824: instanceof    #572                // class retrofit2/http/Body
    2827: ifeq          2951
    2830: aload_0
    2831: iload_1
    2832: aload_2
    2833: invokespecial #295                // Method validateResolvableType:(ILjava/lang/reflect/Type;)V
    2836: aload_0
    2837: getfield      #68                 // Field isFormEncoded:Z
    2840: ifne          2850
    2843: aload_0
    2844: getfield      #63                 // Field isMultipart:Z
    2847: ifeq          2866
    2850: aload_0
    2851: getfield      #13                 // Field method:Ljava/lang/reflect/Method;
    2854: iload_1
    2855: ldc_w         #574                // String @Body parameters cannot be used with form or multi-part encoding.
    2858: iconst_0
    2859: anewarray     #2                  // class java/lang/Object
    2862: invokestatic  #276                // Method retrofit2/Utils.parameterError:(Ljava/lang/reflect/Method;ILjava/lang/String;[Ljava/lang/Object;)Ljava/lang/RuntimeException;
    2865: athrow
    2866: aload_0
    2867: getfield      #91                 // Field gotBody:Z
    2870: ifeq          2889
    2873: aload_0
    2874: getfield      #13                 // Field method:Ljava/lang/reflect/Method;
    2877: iload_1
    2878: ldc_w         #576                // String Multiple @Body method annotations found.
    2881: iconst_0
    2882: anewarray     #2                  // class java/lang/Object
    2885: invokestatic  #276                // Method retrofit2/Utils.parameterError:(Ljava/lang/reflect/Method;ILjava/lang/String;[Ljava/lang/Object;)Ljava/lang/RuntimeException;
    2888: athrow
    2889: aload_0
    2890: getfield      #7                  // Field retrofit:Lretrofit2/Retrofit;
    2893: aload_2
    2894: aload_3
    2895: aload_0
    2896: getfield      #23                 // Field methodAnnotations:[Ljava/lang/annotation/Annotation;
    2899: invokevirtual #545                // Method retrofit2/Retrofit.requestBodyConverter:(Ljava/lang/reflect/Type;[Ljava/lang/annotation/Annotation;[Ljava/lang/annotation/Annotation;)Lretrofit2/Converter;
    2902: astore        5
    2904: goto          2931
    2907: astore        6
    2909: aload_0
    2910: getfield      #13                 // Field method:Ljava/lang/reflect/Method;
    2913: aload         6
    2915: iload_1
    2916: ldc_w         #580                // String Unable to create @Body converter for %s
    2919: iconst_1
    2920: anewarray     #2                  // class java/lang/Object
    2923: dup
    2924: iconst_0
    2925: aload_2
    2926: aastore
    2927: invokestatic  #582                // Method retrofit2/Utils.parameterError:(Ljava/lang/reflect/Method;Ljava/lang/Throwable;ILjava/lang/String;[Ljava/lang/Object;)Ljava/lang/RuntimeException;
    2930: athrow
    2931: aload_0
    2932: iconst_1
    2933: putfield      #91                 // Field gotBody:Z
    2936: new           #585                // class retrofit2/ParameterHandler$Body
    2939: dup
    2940: aload_0
    2941: getfield      #13                 // Field method:Ljava/lang/reflect/Method;
    2944: iload_1
    2945: aload         5
    2947: invokespecial #587                // Method retrofit2/ParameterHandler$Body."<init>":(Ljava/lang/reflect/Method;ILretrofit2/Converter;)V
    2950: areturn
    2951: aload         4
    2953: instanceof    #588                // class retrofit2/http/Tag
    2956: ifeq          3086
    2959: aload_0
    2960: iload_1
    2961: aload_2
    2962: invokespecial #295                // Method validateResolvableType:(ILjava/lang/reflect/Type;)V
    2965: aload_2
    2966: invokestatic  #280                // Method retrofit2/Utils.getRawType:(Ljava/lang/reflect/Type;)Ljava/lang/Class;
    2969: astore        5
    2971: iload_1
    2972: iconst_1
    2973: isub
    2974: istore        6
    2976: iload         6
    2978: iflt          3076
    2981: aload_0
    2982: getfield      #75                 // Field parameterHandlers:[Lretrofit2/ParameterHandler;
    2985: iload         6
    2987: aaload
    2988: astore        7
    2990: aload         7
    2992: instanceof    #590                // class retrofit2/ParameterHandler$Tag
    2995: ifeq          3070
    2998: aload         7
    3000: checkcast     #590                // class retrofit2/ParameterHandler$Tag
    3003: getfield      #592                // Field retrofit2/ParameterHandler$Tag.cls:Ljava/lang/Class;
    3006: aload         5
    3008: invokevirtual #596                // Method java/lang/Object.equals:(Ljava/lang/Object;)Z
    3011: ifeq          3070
    3014: aload_0
    3015: getfield      #13                 // Field method:Ljava/lang/reflect/Method;
    3018: iload_1
    3019: new           #386                // class java/lang/StringBuilder
    3022: dup
    3023: invokespecial #388                // Method java/lang/StringBuilder."<init>":()V
    3026: ldc_w         #597                // String @Tag type
    3029: invokevirtual #392                // Method java/lang/StringBuilder.append:(Ljava/lang/String;)Ljava/lang/StringBuilder;
    3032: aload         5
    3034: invokevirtual #331                // Method java/lang/Class.getName:()Ljava/lang/String;
    3037: invokevirtual #392                // Method java/lang/StringBuilder.append:(Ljava/lang/String;)Ljava/lang/StringBuilder;
    3040: ldc_w         #599                // String  is duplicate of parameter #
    3043: invokevirtual #392                // Method java/lang/StringBuilder.append:(Ljava/lang/String;)Ljava/lang/StringBuilder;
    3046: iload         6
    3048: iconst_1
    3049: iadd
    3050: invokevirtual #601                // Method java/lang/StringBuilder.append:(I)Ljava/lang/StringBuilder;
    3053: ldc_w         #604                // String  and would always overwrite its value.
    3056: invokevirtual #392                // Method java/lang/StringBuilder.append:(Ljava/lang/String;)Ljava/lang/StringBuilder;
    3059: invokevirtual #400                // Method java/lang/StringBuilder.toString:()Ljava/lang/String;
    3062: iconst_0
    3063: anewarray     #2                  // class java/lang/Object
    3066: invokestatic  #276                // Method retrofit2/Utils.parameterError:(Ljava/lang/reflect/Method;ILjava/lang/String;[Ljava/lang/Object;)Ljava/lang/RuntimeException;
    3069: athrow
    3070: iinc          6, -1
    3073: goto          2976
    3076: new           #590                // class retrofit2/ParameterHandler$Tag
    3079: dup
    3080: aload         5
    3082: invokespecial #606                // Method retrofit2/ParameterHandler$Tag."<init>":(Ljava/lang/Class;)V
    3085: areturn
    3086: aconst_null
    3087: areturn
    Exception table:
       from    to  target type
        2889  2904  2907   Class java/lang/RuntimeException

  private void validateResolvableType(int, java.lang.reflect.Type);
    Code:
       0: aload_2
       1: invokestatic  #609                // Method retrofit2/Utils.hasUnresolvableType:(Ljava/lang/reflect/Type;)Z
       4: ifeq          27
       7: aload_0
       8: getfield      #13                 // Field method:Ljava/lang/reflect/Method;
      11: iload_1
      12: ldc_w         #613                // String Parameter type must not include a type variable or wildcard: %s
      15: iconst_1
      16: anewarray     #2                  // class java/lang/Object
      19: dup
      20: iconst_0
      21: aload_2
      22: aastore
      23: invokestatic  #276                // Method retrofit2/Utils.parameterError:(Ljava/lang/reflect/Method;ILjava/lang/String;[Ljava/lang/Object;)Ljava/lang/RuntimeException;
      26: athrow
      27: return

  private void validatePathName(int, java.lang.String);
    Code:
       0: getstatic     #615                // Field PARAM_NAME_REGEX:Ljava/util/regex/Pattern;
       3: aload_2
       4: invokevirtual #207                // Method java/util/regex/Pattern.matcher:(Ljava/lang/CharSequence;)Ljava/util/regex/Matcher;
       7: invokevirtual #618                // Method java/util/regex/Matcher.matches:()Z
      10: ifne          42
      13: aload_0
      14: getfield      #13                 // Field method:Ljava/lang/reflect/Method;
      17: iload_1
      18: ldc_w         #621                // String @Path parameter name must match %s. Found: %s
      21: iconst_2
      22: anewarray     #2                  // class java/lang/Object
      25: dup
      26: iconst_0
      27: getstatic     #203                // Field PARAM_URL_REGEX:Ljava/util/regex/Pattern;
      30: invokevirtual #623                // Method java/util/regex/Pattern.pattern:()Ljava/lang/String;
      33: aastore
      34: dup
      35: iconst_1
      36: aload_2
      37: aastore
      38: invokestatic  #276                // Method retrofit2/Utils.parameterError:(Ljava/lang/reflect/Method;ILjava/lang/String;[Ljava/lang/Object;)Ljava/lang/RuntimeException;
      41: athrow
      42: aload_0
      43: getfield      #224                // Field relativeUrlParamNames:Ljava/util/Set;
      46: aload_2
      47: invokeinterface #626,  2          // InterfaceMethod java/util/Set.contains:(Ljava/lang/Object;)Z
      52: ifne          82
      55: aload_0
      56: getfield      #13                 // Field method:Ljava/lang/reflect/Method;
      59: iload_1
      60: ldc_w         #631                // String URL \"%s\" does not contain \"{%s}\".
      63: iconst_2
      64: anewarray     #2                  // class java/lang/Object
      67: dup
      68: iconst_0
      69: aload_0
      70: getfield      #83                 // Field relativeUrl:Ljava/lang/String;
      73: aastore
      74: dup
      75: iconst_1
      76: aload_2
      77: aastore
      78: invokestatic  #276                // Method retrofit2/Utils.parameterError:(Ljava/lang/reflect/Method;ILjava/lang/String;[Ljava/lang/Object;)Ljava/lang/RuntimeException;
      81: athrow
      82: return

  static java.util.Set<java.lang.String> parsePathParameters(java.lang.String);
    Code:
       0: getstatic     #203                // Field PARAM_URL_REGEX:Ljava/util/regex/Pattern;
       3: aload_0
       4: invokevirtual #207                // Method java/util/regex/Pattern.matcher:(Ljava/lang/CharSequence;)Ljava/util/regex/Matcher;
       7: astore_1
       8: new           #633                // class java/util/LinkedHashSet
      11: dup
      12: invokespecial #635                // Method java/util/LinkedHashSet."<init>":()V
      15: astore_2
      16: aload_1
      17: invokevirtual #213                // Method java/util/regex/Matcher.find:()Z
      20: ifeq          38
      23: aload_2
      24: aload_1
      25: iconst_1
      26: invokevirtual #636                // Method java/util/regex/Matcher.group:(I)Ljava/lang/String;
      29: invokeinterface #639,  2          // InterfaceMethod java/util/Set.add:(Ljava/lang/Object;)Z
      34: pop
      35: goto          16
      38: aload_2
      39: areturn

  private static java.lang.Class<?> boxIfPrimitive(java.lang.Class<?>);
    Code:
       0: getstatic     #641                // Field java/lang/Boolean.TYPE:Ljava/lang/Class;
       3: aload_0
       4: if_acmpne     11
       7: ldc_w         #642                // class java/lang/Boolean
      10: areturn
      11: getstatic     #646                // Field java/lang/Byte.TYPE:Ljava/lang/Class;
      14: aload_0
      15: if_acmpne     22
      18: ldc_w         #647                // class java/lang/Byte
      21: areturn
      22: getstatic     #649                // Field java/lang/Character.TYPE:Ljava/lang/Class;
      25: aload_0
      26: if_acmpne     33
      29: ldc_w         #650                // class java/lang/Character
      32: areturn
      33: getstatic     #652                // Field java/lang/Double.TYPE:Ljava/lang/Class;
      36: aload_0
      37: if_acmpne     44
      40: ldc_w         #653                // class java/lang/Double
      43: areturn
      44: getstatic     #655                // Field java/lang/Float.TYPE:Ljava/lang/Class;
      47: aload_0
      48: if_acmpne     55
      51: ldc_w         #656                // class java/lang/Float
      54: areturn
      55: getstatic     #658                // Field java/lang/Integer.TYPE:Ljava/lang/Class;
      58: aload_0
      59: if_acmpne     66
      62: ldc_w         #659                // class java/lang/Integer
      65: areturn
      66: getstatic     #661                // Field java/lang/Long.TYPE:Ljava/lang/Class;
      69: aload_0
      70: if_acmpne     77
      73: ldc_w         #662                // class java/lang/Long
      76: areturn
      77: getstatic     #664                // Field java/lang/Short.TYPE:Ljava/lang/Class;
      80: aload_0
      81: if_acmpne     88
      84: ldc_w         #665                // class java/lang/Short
      87: areturn
      88: aload_0
      89: areturn

  static {};
    Code:
       0: ldc_w         #667                // String \\{([a-zA-Z][a-zA-Z0-9_-]*)\\}
       3: invokestatic  #669                // Method java/util/regex/Pattern.compile:(Ljava/lang/String;)Ljava/util/regex/Pattern;
       6: putstatic     #203                // Field PARAM_URL_REGEX:Ljava/util/regex/Pattern;
       9: ldc_w         #673                // String [a-zA-Z][a-zA-Z0-9_-]*
      12: invokestatic  #669                // Method java/util/regex/Pattern.compile:(Ljava/lang/String;)Ljava/util/regex/Pattern;
      15: putstatic     #615                // Field PARAM_NAME_REGEX:Ljava/util/regex/Pattern;
      18: return
}
