Compiled from "RequestBuilder.java"
class retrofit2.RequestBuilder$ContentTypeOverridingRequestBody extends okhttp3.RequestBody {
  private final okhttp3.RequestBody delegate;

  private final okhttp3.MediaType contentType;

  retrofit2.RequestBuilder$ContentTypeOverridingRequestBody(okhttp3.RequestBody, okhttp3.MediaType);
    Code:
       0: aload_0
       1: invokespecial #1                  // Method okhttp3/RequestBody."<init>":()V
       4: aload_0
       5: aload_1
       6: putfield      #7                  // Field delegate:Lokhttp3/RequestBody;
       9: aload_0
      10: aload_2
      11: putfield      #13                 // Field contentType:Lokhttp3/MediaType;
      14: return

  public okhttp3.MediaType contentType();
    Code:
       0: aload_0
       1: getfield      #13                 // Field contentType:Lokhttp3/MediaType;
       4: areturn

  public long contentLength() throws java.io.IOException;
    Code:
       0: aload_0
       1: getfield      #7                  // Field delegate:Lokhttp3/RequestBody;
       4: invokevirtual #17                 // Method okhttp3/RequestBody.contentLength:()J
       7: lreturn

  public void writeTo(okio.BufferedSink) throws java.io.IOException;
    Code:
       0: aload_0
       1: getfield      #7                  // Field delegate:Lokhttp3/RequestBody;
       4: aload_1
       5: invokevirtual #21                 // Method okhttp3/RequestBody.writeTo:(Lokio/BufferedSink;)V
       8: return
}
