Compiled from "RequestFactory.java"
final class retrofit2.RequestFactory {
  private final java.lang.reflect.Method method;

  private final okhttp3.HttpUrl baseUrl;

  final java.lang.String httpMethod;

  private final java.lang.String relativeUrl;

  private final okhttp3.Headers headers;

  private final okhttp3.MediaType contentType;

  private final boolean hasBody;

  private final boolean isFormEncoded;

  private final boolean isMultipart;

  private final retrofit2.ParameterHandler<?>[] parameterHandlers;

  final boolean isKotlinSuspendFunction;

  static retrofit2.RequestFactory parseAnnotations(retrofit2.Retrofit, java.lang.reflect.Method);
    Code:
       0: new           #1                  // class retrofit2/RequestFactory$Builder
       3: dup
       4: aload_0
       5: aload_1
       6: invokespecial #3                  // Method retrofit2/RequestFactory$Builder."<init>":(Lretrofit2/Retrofit;Ljava/lang/reflect/Method;)V
       9: invokevirtual #7                  // Method retrofit2/RequestFactory$Builder.build:()Lretrofit2/RequestFactory;
      12: areturn

  retrofit2.RequestFactory(retrofit2.RequestFactory$Builder);
    Code:
       0: aload_0
       1: invokespecial #11                 // Method java/lang/Object."<init>":()V
       4: aload_0
       5: aload_1
       6: getfield      #16                 // Field retrofit2/RequestFactory$Builder.method:Ljava/lang/reflect/Method;
       9: putfield      #20                 // Field method:Ljava/lang/reflect/Method;
      12: aload_0
      13: aload_1
      14: getfield      #23                 // Field retrofit2/RequestFactory$Builder.retrofit:Lretrofit2/Retrofit;
      17: getfield      #27                 // Field retrofit2/Retrofit.baseUrl:Lokhttp3/HttpUrl;
      20: putfield      #33                 // Field baseUrl:Lokhttp3/HttpUrl;
      23: aload_0
      24: aload_1
      25: getfield      #34                 // Field retrofit2/RequestFactory$Builder.httpMethod:Ljava/lang/String;
      28: putfield      #38                 // Field httpMethod:Ljava/lang/String;
      31: aload_0
      32: aload_1
      33: getfield      #39                 // Field retrofit2/RequestFactory$Builder.relativeUrl:Ljava/lang/String;
      36: putfield      #42                 // Field relativeUrl:Ljava/lang/String;
      39: aload_0
      40: aload_1
      41: getfield      #43                 // Field retrofit2/RequestFactory$Builder.headers:Lokhttp3/Headers;
      44: putfield      #47                 // Field headers:Lokhttp3/Headers;
      47: aload_0
      48: aload_1
      49: getfield      #48                 // Field retrofit2/RequestFactory$Builder.contentType:Lokhttp3/MediaType;
      52: putfield      #52                 // Field contentType:Lokhttp3/MediaType;
      55: aload_0
      56: aload_1
      57: getfield      #53                 // Field retrofit2/RequestFactory$Builder.hasBody:Z
      60: putfield      #57                 // Field hasBody:Z
      63: aload_0
      64: aload_1
      65: getfield      #58                 // Field retrofit2/RequestFactory$Builder.isFormEncoded:Z
      68: putfield      #61                 // Field isFormEncoded:Z
      71: aload_0
      72: aload_1
      73: getfield      #62                 // Field retrofit2/RequestFactory$Builder.isMultipart:Z
      76: putfield      #65                 // Field isMultipart:Z
      79: aload_0
      80: aload_1
      81: getfield      #66                 // Field retrofit2/RequestFactory$Builder.parameterHandlers:[Lretrofit2/ParameterHandler;
      84: putfield      #70                 // Field parameterHandlers:[Lretrofit2/ParameterHandler;
      87: aload_0
      88: aload_1
      89: getfield      #71                 // Field retrofit2/RequestFactory$Builder.isKotlinSuspendFunction:Z
      92: putfield      #74                 // Field isKotlinSuspendFunction:Z
      95: return

  okhttp3.Request create(java.lang.Object[]) throws java.io.IOException;
    Code:
       0: aload_0
       1: getfield      #70                 // Field parameterHandlers:[Lretrofit2/ParameterHandler;
       4: astore_2
       5: aload_1
       6: arraylength
       7: istore_3
       8: iload_3
       9: aload_2
      10: arraylength
      11: if_icmpeq     56
      14: new           #75                 // class java/lang/IllegalArgumentException
      17: dup
      18: new           #77                 // class java/lang/StringBuilder
      21: dup
      22: invokespecial #79                 // Method java/lang/StringBuilder."<init>":()V
      25: ldc           #80                 // String Argument count (
      27: invokevirtual #82                 // Method java/lang/StringBuilder.append:(Ljava/lang/String;)Ljava/lang/StringBuilder;
      30: iload_3
      31: invokevirtual #86                 // Method java/lang/StringBuilder.append:(I)Ljava/lang/StringBuilder;
      34: ldc           #89                 // String ) doesn\'t match expected count (
      36: invokevirtual #82                 // Method java/lang/StringBuilder.append:(Ljava/lang/String;)Ljava/lang/StringBuilder;
      39: aload_2
      40: arraylength
      41: invokevirtual #86                 // Method java/lang/StringBuilder.append:(I)Ljava/lang/StringBuilder;
      44: ldc           #91                 // String )
      46: invokevirtual #82                 // Method java/lang/StringBuilder.append:(Ljava/lang/String;)Ljava/lang/StringBuilder;
      49: invokevirtual #93                 // Method java/lang/StringBuilder.toString:()Ljava/lang/String;
      52: invokespecial #97                 // Method java/lang/IllegalArgumentException."<init>":(Ljava/lang/String;)V
      55: athrow
      56: new           #100                // class retrofit2/RequestBuilder
      59: dup
      60: aload_0
      61: getfield      #38                 // Field httpMethod:Ljava/lang/String;
      64: aload_0
      65: getfield      #33                 // Field baseUrl:Lokhttp3/HttpUrl;
      68: aload_0
      69: getfield      #42                 // Field relativeUrl:Ljava/lang/String;
      72: aload_0
      73: getfield      #47                 // Field headers:Lokhttp3/Headers;
      76: aload_0
      77: getfield      #52                 // Field contentType:Lokhttp3/MediaType;
      80: aload_0
      81: getfield      #57                 // Field hasBody:Z
      84: aload_0
      85: getfield      #61                 // Field isFormEncoded:Z
      88: aload_0
      89: getfield      #65                 // Field isMultipart:Z
      92: invokespecial #102                // Method retrofit2/RequestBuilder."<init>":(Ljava/lang/String;Lokhttp3/HttpUrl;Ljava/lang/String;Lokhttp3/Headers;Lokhttp3/MediaType;ZZZ)V
      95: astore        4
      97: aload_0
      98: getfield      #74                 // Field isKotlinSuspendFunction:Z
     101: ifeq          107
     104: iinc          3, -1
     107: new           #105                // class java/util/ArrayList
     110: dup
     111: iload_3
     112: invokespecial #107                // Method java/util/ArrayList."<init>":(I)V
     115: astore        5
     117: iconst_0
     118: istore        6
     120: iload         6
     122: iload_3
     123: if_icmpge     157
     126: aload         5
     128: aload_1
     129: iload         6
     131: aaload
     132: invokeinterface #110,  2          // InterfaceMethod java/util/List.add:(Ljava/lang/Object;)Z
     137: pop
     138: aload_2
     139: iload         6
     141: aaload
     142: aload         4
     144: aload_1
     145: iload         6
     147: aaload
     148: invokevirtual #116                // Method retrofit2/ParameterHandler.apply:(Lretrofit2/RequestBuilder;Ljava/lang/Object;)V
     151: iinc          6, 1
     154: goto          120
     157: aload         4
     159: invokevirtual #122                // Method retrofit2/RequestBuilder.get:()Lokhttp3/Request$Builder;
     162: ldc           #126                // class retrofit2/Invocation
     164: new           #126                // class retrofit2/Invocation
     167: dup
     168: aload_0
     169: getfield      #20                 // Field method:Ljava/lang/reflect/Method;
     172: aload         5
     174: invokespecial #128                // Method retrofit2/Invocation."<init>":(Ljava/lang/reflect/Method;Ljava/util/List;)V
     177: invokevirtual #131                // Method okhttp3/Request$Builder.tag:(Ljava/lang/Class;Ljava/lang/Object;)Lokhttp3/Request$Builder;
     180: invokevirtual #137                // Method okhttp3/Request$Builder.build:()Lokhttp3/Request;
     183: areturn
}
