Compiled from "Retrofit.java"
public final class retrofit2.Retrofit {
  private final java.util.Map<java.lang.reflect.Method, retrofit2.ServiceMethod<?>> serviceMethodCache;

  final okhttp3.Call$Factory callFactory;

  final okhttp3.HttpUrl baseUrl;

  final java.util.List<retrofit2.Converter$Factory> converterFactories;

  final java.util.List<retrofit2.CallAdapter$Factory> callAdapterFactories;

  final java.util.concurrent.Executor callbackExecutor;

  final boolean validateEagerly;

  retrofit2.Retrofit(okhttp3.Call$Factory, okhttp3.HttpUrl, java.util.List<retrofit2.Converter$Factory>, java.util.List<retrofit2.CallAdapter$Factory>, java.util.concurrent.Executor, boolean);
    Code:
       0: aload_0
       1: invokespecial #1                  // Method java/lang/Object."<init>":()V
       4: aload_0
       5: new           #7                  // class java/util/concurrent/ConcurrentHashMap
       8: dup
       9: invokespecial #9                  // Method java/util/concurrent/ConcurrentHashMap."<init>":()V
      12: putfield      #10                 // Field serviceMethodCache:Ljava/util/Map;
      15: aload_0
      16: aload_1
      17: putfield      #16                 // Field callFactory:Lokhttp3/Call$Factory;
      20: aload_0
      21: aload_2
      22: putfield      #20                 // Field baseUrl:Lokhttp3/HttpUrl;
      25: aload_0
      26: aload_3
      27: putfield      #24                 // Field converterFactories:Ljava/util/List;
      30: aload_0
      31: aload         4
      33: putfield      #28                 // Field callAdapterFactories:Ljava/util/List;
      36: aload_0
      37: aload         5
      39: putfield      #31                 // Field callbackExecutor:Ljava/util/concurrent/Executor;
      42: aload_0
      43: iload         6
      45: putfield      #35                 // Field validateEagerly:Z
      48: return

  public <T> T create(java.lang.Class<T>);
    Code:
       0: aload_0
       1: aload_1
       2: invokespecial #39                 // Method validateServiceInterface:(Ljava/lang/Class;)V
       5: aload_1
       6: invokevirtual #43                 // Method java/lang/Class.getClassLoader:()Ljava/lang/ClassLoader;
       9: iconst_1
      10: anewarray     #44                 // class java/lang/Class
      13: dup
      14: iconst_0
      15: aload_1
      16: aastore
      17: new           #49                 // class retrofit2/Retrofit$1
      20: dup
      21: aload_0
      22: aload_1
      23: invokespecial #51                 // Method retrofit2/Retrofit$1."<init>":(Lretrofit2/Retrofit;Ljava/lang/Class;)V
      26: invokestatic  #54                 // Method java/lang/reflect/Proxy.newProxyInstance:(Ljava/lang/ClassLoader;[Ljava/lang/Class;Ljava/lang/reflect/InvocationHandler;)Ljava/lang/Object;
      29: areturn

  private void validateServiceInterface(java.lang.Class<?>);
    Code:
       0: aload_1
       1: invokevirtual #60                 // Method java/lang/Class.isInterface:()Z
       4: ifne          17
       7: new           #64                 // class java/lang/IllegalArgumentException
      10: dup
      11: ldc           #66                 // String API declarations must be interfaces.
      13: invokespecial #68                 // Method java/lang/IllegalArgumentException."<init>":(Ljava/lang/String;)V
      16: athrow
      17: new           #71                 // class java/util/ArrayDeque
      20: dup
      21: iconst_1
      22: invokespecial #73                 // Method java/util/ArrayDeque."<init>":(I)V
      25: astore_2
      26: aload_2
      27: aload_1
      28: invokeinterface #76,  2           // InterfaceMethod java/util/Deque.add:(Ljava/lang/Object;)Z
      33: pop
      34: aload_2
      35: invokeinterface #82,  1           // InterfaceMethod java/util/Deque.isEmpty:()Z
      40: ifne          124
      43: aload_2
      44: invokeinterface #85,  1           // InterfaceMethod java/util/Deque.removeFirst:()Ljava/lang/Object;
      49: checkcast     #44                 // class java/lang/Class
      52: astore_3
      53: aload_3
      54: invokevirtual #89                 // Method java/lang/Class.getTypeParameters:()[Ljava/lang/reflect/TypeVariable;
      57: arraylength
      58: ifeq          112
      61: new           #93                 // class java/lang/StringBuilder
      64: dup
      65: ldc           #95                 // String Type parameters are unsupported on
      67: invokespecial #97                 // Method java/lang/StringBuilder."<init>":(Ljava/lang/String;)V
      70: aload_3
      71: invokevirtual #98                 // Method java/lang/Class.getName:()Ljava/lang/String;
      74: invokevirtual #102                // Method java/lang/StringBuilder.append:(Ljava/lang/String;)Ljava/lang/StringBuilder;
      77: astore        4
      79: aload_3
      80: aload_1
      81: if_acmpeq     99
      84: aload         4
      86: ldc           #106                // String  which is an interface of
      88: invokevirtual #102                // Method java/lang/StringBuilder.append:(Ljava/lang/String;)Ljava/lang/StringBuilder;
      91: aload_1
      92: invokevirtual #98                 // Method java/lang/Class.getName:()Ljava/lang/String;
      95: invokevirtual #102                // Method java/lang/StringBuilder.append:(Ljava/lang/String;)Ljava/lang/StringBuilder;
      98: pop
      99: new           #64                 // class java/lang/IllegalArgumentException
     102: dup
     103: aload         4
     105: invokevirtual #108                // Method java/lang/StringBuilder.toString:()Ljava/lang/String;
     108: invokespecial #68                 // Method java/lang/IllegalArgumentException."<init>":(Ljava/lang/String;)V
     111: athrow
     112: aload_2
     113: aload_3
     114: invokevirtual #111                // Method java/lang/Class.getInterfaces:()[Ljava/lang/Class;
     117: invokestatic  #115                // Method java/util/Collections.addAll:(Ljava/util/Collection;[Ljava/lang/Object;)Z
     120: pop
     121: goto          34
     124: aload_0
     125: getfield      #35                 // Field validateEagerly:Z
     128: ifeq          196
     131: invokestatic  #121                // Method retrofit2/Platform.get:()Lretrofit2/Platform;
     134: astore_3
     135: aload_1
     136: invokevirtual #127                // Method java/lang/Class.getDeclaredMethods:()[Ljava/lang/reflect/Method;
     139: astore        4
     141: aload         4
     143: arraylength
     144: istore        5
     146: iconst_0
     147: istore        6
     149: iload         6
     151: iload         5
     153: if_icmpge     196
     156: aload         4
     158: iload         6
     160: aaload
     161: astore        7
     163: aload_3
     164: aload         7
     166: invokevirtual #131                // Method retrofit2/Platform.isDefaultMethod:(Ljava/lang/reflect/Method;)Z
     169: ifne          190
     172: aload         7
     174: invokevirtual #135                // Method java/lang/reflect/Method.getModifiers:()I
     177: invokestatic  #141                // Method java/lang/reflect/Modifier.isStatic:(I)Z
     180: ifne          190
     183: aload_0
     184: aload         7
     186: invokevirtual #147                // Method loadServiceMethod:(Ljava/lang/reflect/Method;)Lretrofit2/ServiceMethod;
     189: pop
     190: iinc          6, 1
     193: goto          149
     196: return

  retrofit2.ServiceMethod<?> loadServiceMethod(java.lang.reflect.Method);
    Code:
       0: aload_0
       1: getfield      #10                 // Field serviceMethodCache:Ljava/util/Map;
       4: aload_1
       5: invokeinterface #151,  2          // InterfaceMethod java/util/Map.get:(Ljava/lang/Object;)Ljava/lang/Object;
      10: checkcast     #156                // class retrofit2/ServiceMethod
      13: astore_2
      14: aload_2
      15: ifnull        20
      18: aload_2
      19: areturn
      20: aload_0
      21: getfield      #10                 // Field serviceMethodCache:Ljava/util/Map;
      24: dup
      25: astore_3
      26: monitorenter
      27: aload_0
      28: getfield      #10                 // Field serviceMethodCache:Ljava/util/Map;
      31: aload_1
      32: invokeinterface #151,  2          // InterfaceMethod java/util/Map.get:(Ljava/lang/Object;)Ljava/lang/Object;
      37: checkcast     #156                // class retrofit2/ServiceMethod
      40: astore_2
      41: aload_2
      42: ifnonnull     63
      45: aload_0
      46: aload_1
      47: invokestatic  #158                // Method retrofit2/ServiceMethod.parseAnnotations:(Lretrofit2/Retrofit;Ljava/lang/reflect/Method;)Lretrofit2/ServiceMethod;
      50: astore_2
      51: aload_0
      52: getfield      #10                 // Field serviceMethodCache:Ljava/util/Map;
      55: aload_1
      56: aload_2
      57: invokeinterface #162,  3          // InterfaceMethod java/util/Map.put:(Ljava/lang/Object;Ljava/lang/Object;)Ljava/lang/Object;
      62: pop
      63: aload_3
      64: monitorexit
      65: goto          75
      68: astore        4
      70: aload_3
      71: monitorexit
      72: aload         4
      74: athrow
      75: aload_2
      76: areturn
    Exception table:
       from    to  target type
          27    65    68   any
          68    72    68   any

  public okhttp3.Call$Factory callFactory();
    Code:
       0: aload_0
       1: getfield      #16                 // Field callFactory:Lokhttp3/Call$Factory;
       4: areturn

  public okhttp3.HttpUrl baseUrl();
    Code:
       0: aload_0
       1: getfield      #20                 // Field baseUrl:Lokhttp3/HttpUrl;
       4: areturn

  public java.util.List<retrofit2.CallAdapter$Factory> callAdapterFactories();
    Code:
       0: aload_0
       1: getfield      #28                 // Field callAdapterFactories:Ljava/util/List;
       4: areturn

  public retrofit2.CallAdapter<?, ?> callAdapter(java.lang.reflect.Type, java.lang.annotation.Annotation[]);
    Code:
       0: aload_0
       1: aconst_null
       2: aload_1
       3: aload_2
       4: invokevirtual #166                // Method nextCallAdapter:(Lretrofit2/CallAdapter$Factory;Ljava/lang/reflect/Type;[Ljava/lang/annotation/Annotation;)Lretrofit2/CallAdapter;
       7: areturn

  public retrofit2.CallAdapter<?, ?> nextCallAdapter(retrofit2.CallAdapter$Factory, java.lang.reflect.Type, java.lang.annotation.Annotation[]);
    Code:
       0: aload_2
       1: ldc           #170                // String returnType == null
       3: invokestatic  #172                // Method java/util/Objects.requireNonNull:(Ljava/lang/Object;Ljava/lang/String;)Ljava/lang/Object;
       6: pop
       7: aload_3
       8: ldc           #178                // String annotations == null
      10: invokestatic  #172                // Method java/util/Objects.requireNonNull:(Ljava/lang/Object;Ljava/lang/String;)Ljava/lang/Object;
      13: pop
      14: aload_0
      15: getfield      #28                 // Field callAdapterFactories:Ljava/util/List;
      18: aload_1
      19: invokeinterface #180,  2          // InterfaceMethod java/util/List.indexOf:(Ljava/lang/Object;)I
      24: iconst_1
      25: iadd
      26: istore        4
      28: iload         4
      30: istore        5
      32: aload_0
      33: getfield      #28                 // Field callAdapterFactories:Ljava/util/List;
      36: invokeinterface #186,  1          // InterfaceMethod java/util/List.size:()I
      41: istore        6
      43: iload         5
      45: iload         6
      47: if_icmpge     86
      50: aload_0
      51: getfield      #28                 // Field callAdapterFactories:Ljava/util/List;
      54: iload         5
      56: invokeinterface #189,  2          // InterfaceMethod java/util/List.get:(I)Ljava/lang/Object;
      61: checkcast     #192                // class retrofit2/CallAdapter$Factory
      64: aload_2
      65: aload_3
      66: aload_0
      67: invokevirtual #194                // Method retrofit2/CallAdapter$Factory.get:(Ljava/lang/reflect/Type;[Ljava/lang/annotation/Annotation;Lretrofit2/Retrofit;)Lretrofit2/CallAdapter;
      70: astore        7
      72: aload         7
      74: ifnull        80
      77: aload         7
      79: areturn
      80: iinc          5, 1
      83: goto          43
      86: new           #93                 // class java/lang/StringBuilder
      89: dup
      90: ldc           #197                // String Could not locate call adapter for
      92: invokespecial #97                 // Method java/lang/StringBuilder."<init>":(Ljava/lang/String;)V
      95: aload_2
      96: invokevirtual #199                // Method java/lang/StringBuilder.append:(Ljava/lang/Object;)Ljava/lang/StringBuilder;
      99: ldc           #202                // String .\n
     101: invokevirtual #102                // Method java/lang/StringBuilder.append:(Ljava/lang/String;)Ljava/lang/StringBuilder;
     104: astore        5
     106: aload_1
     107: ifnull        173
     110: aload         5
     112: ldc           #204                // String   Skipped:
     114: invokevirtual #102                // Method java/lang/StringBuilder.append:(Ljava/lang/String;)Ljava/lang/StringBuilder;
     117: pop
     118: iconst_0
     119: istore        6
     121: iload         6
     123: iload         4
     125: if_icmpge     165
     128: aload         5
     130: ldc           #206                // String \n   *
     132: invokevirtual #102                // Method java/lang/StringBuilder.append:(Ljava/lang/String;)Ljava/lang/StringBuilder;
     135: aload_0
     136: getfield      #28                 // Field callAdapterFactories:Ljava/util/List;
     139: iload         6
     141: invokeinterface #189,  2          // InterfaceMethod java/util/List.get:(I)Ljava/lang/Object;
     146: checkcast     #192                // class retrofit2/CallAdapter$Factory
     149: invokevirtual #208                // Method java/lang/Object.getClass:()Ljava/lang/Class;
     152: invokevirtual #98                 // Method java/lang/Class.getName:()Ljava/lang/String;
     155: invokevirtual #102                // Method java/lang/StringBuilder.append:(Ljava/lang/String;)Ljava/lang/StringBuilder;
     158: pop
     159: iinc          6, 1
     162: goto          121
     165: aload         5
     167: bipush        10
     169: invokevirtual #212                // Method java/lang/StringBuilder.append:(C)Ljava/lang/StringBuilder;
     172: pop
     173: aload         5
     175: ldc           #215                // String   Tried:
     177: invokevirtual #102                // Method java/lang/StringBuilder.append:(Ljava/lang/String;)Ljava/lang/StringBuilder;
     180: pop
     181: iload         4
     183: istore        6
     185: aload_0
     186: getfield      #28                 // Field callAdapterFactories:Ljava/util/List;
     189: invokeinterface #186,  1          // InterfaceMethod java/util/List.size:()I
     194: istore        7
     196: iload         6
     198: iload         7
     200: if_icmpge     240
     203: aload         5
     205: ldc           #206                // String \n   *
     207: invokevirtual #102                // Method java/lang/StringBuilder.append:(Ljava/lang/String;)Ljava/lang/StringBuilder;
     210: aload_0
     211: getfield      #28                 // Field callAdapterFactories:Ljava/util/List;
     214: iload         6
     216: invokeinterface #189,  2          // InterfaceMethod java/util/List.get:(I)Ljava/lang/Object;
     221: checkcast     #192                // class retrofit2/CallAdapter$Factory
     224: invokevirtual #208                // Method java/lang/Object.getClass:()Ljava/lang/Class;
     227: invokevirtual #98                 // Method java/lang/Class.getName:()Ljava/lang/String;
     230: invokevirtual #102                // Method java/lang/StringBuilder.append:(Ljava/lang/String;)Ljava/lang/StringBuilder;
     233: pop
     234: iinc          6, 1
     237: goto          196
     240: new           #64                 // class java/lang/IllegalArgumentException
     243: dup
     244: aload         5
     246: invokevirtual #108                // Method java/lang/StringBuilder.toString:()Ljava/lang/String;
     249: invokespecial #68                 // Method java/lang/IllegalArgumentException."<init>":(Ljava/lang/String;)V
     252: athrow

  public java.util.List<retrofit2.Converter$Factory> converterFactories();
    Code:
       0: aload_0
       1: getfield      #24                 // Field converterFactories:Ljava/util/List;
       4: areturn

  public <T> retrofit2.Converter<T, okhttp3.RequestBody> requestBodyConverter(java.lang.reflect.Type, java.lang.annotation.Annotation[], java.lang.annotation.Annotation[]);
    Code:
       0: aload_0
       1: aconst_null
       2: aload_1
       3: aload_2
       4: aload_3
       5: invokevirtual #217                // Method nextRequestBodyConverter:(Lretrofit2/Converter$Factory;Ljava/lang/reflect/Type;[Ljava/lang/annotation/Annotation;[Ljava/lang/annotation/Annotation;)Lretrofit2/Converter;
       8: areturn

  public <T> retrofit2.Converter<T, okhttp3.RequestBody> nextRequestBodyConverter(retrofit2.Converter$Factory, java.lang.reflect.Type, java.lang.annotation.Annotation[], java.lang.annotation.Annotation[]);
    Code:
       0: aload_2
       1: ldc           #221                // String type == null
       3: invokestatic  #172                // Method java/util/Objects.requireNonNull:(Ljava/lang/Object;Ljava/lang/String;)Ljava/lang/Object;
       6: pop
       7: aload_3
       8: ldc           #223                // String parameterAnnotations == null
      10: invokestatic  #172                // Method java/util/Objects.requireNonNull:(Ljava/lang/Object;Ljava/lang/String;)Ljava/lang/Object;
      13: pop
      14: aload         4
      16: ldc           #225                // String methodAnnotations == null
      18: invokestatic  #172                // Method java/util/Objects.requireNonNull:(Ljava/lang/Object;Ljava/lang/String;)Ljava/lang/Object;
      21: pop
      22: aload_0
      23: getfield      #24                 // Field converterFactories:Ljava/util/List;
      26: aload_1
      27: invokeinterface #180,  2          // InterfaceMethod java/util/List.indexOf:(Ljava/lang/Object;)I
      32: iconst_1
      33: iadd
      34: istore        5
      36: iload         5
      38: istore        6
      40: aload_0
      41: getfield      #24                 // Field converterFactories:Ljava/util/List;
      44: invokeinterface #186,  1          // InterfaceMethod java/util/List.size:()I
      49: istore        7
      51: iload         6
      53: iload         7
      55: if_icmpge     100
      58: aload_0
      59: getfield      #24                 // Field converterFactories:Ljava/util/List;
      62: iload         6
      64: invokeinterface #189,  2          // InterfaceMethod java/util/List.get:(I)Ljava/lang/Object;
      69: checkcast     #227                // class retrofit2/Converter$Factory
      72: astore        8
      74: aload         8
      76: aload_2
      77: aload_3
      78: aload         4
      80: aload_0
      81: invokevirtual #229                // Method retrofit2/Converter$Factory.requestBodyConverter:(Ljava/lang/reflect/Type;[Ljava/lang/annotation/Annotation;[Ljava/lang/annotation/Annotation;Lretrofit2/Retrofit;)Lretrofit2/Converter;
      84: astore        9
      86: aload         9
      88: ifnull        94
      91: aload         9
      93: areturn
      94: iinc          6, 1
      97: goto          51
     100: new           #93                 // class java/lang/StringBuilder
     103: dup
     104: ldc           #233                // String Could not locate RequestBody converter for
     106: invokespecial #97                 // Method java/lang/StringBuilder."<init>":(Ljava/lang/String;)V
     109: aload_2
     110: invokevirtual #199                // Method java/lang/StringBuilder.append:(Ljava/lang/Object;)Ljava/lang/StringBuilder;
     113: ldc           #202                // String .\n
     115: invokevirtual #102                // Method java/lang/StringBuilder.append:(Ljava/lang/String;)Ljava/lang/StringBuilder;
     118: astore        6
     120: aload_1
     121: ifnull        187
     124: aload         6
     126: ldc           #204                // String   Skipped:
     128: invokevirtual #102                // Method java/lang/StringBuilder.append:(Ljava/lang/String;)Ljava/lang/StringBuilder;
     131: pop
     132: iconst_0
     133: istore        7
     135: iload         7
     137: iload         5
     139: if_icmpge     179
     142: aload         6
     144: ldc           #206                // String \n   *
     146: invokevirtual #102                // Method java/lang/StringBuilder.append:(Ljava/lang/String;)Ljava/lang/StringBuilder;
     149: aload_0
     150: getfield      #24                 // Field converterFactories:Ljava/util/List;
     153: iload         7
     155: invokeinterface #189,  2          // InterfaceMethod java/util/List.get:(I)Ljava/lang/Object;
     160: checkcast     #227                // class retrofit2/Converter$Factory
     163: invokevirtual #208                // Method java/lang/Object.getClass:()Ljava/lang/Class;
     166: invokevirtual #98                 // Method java/lang/Class.getName:()Ljava/lang/String;
     169: invokevirtual #102                // Method java/lang/StringBuilder.append:(Ljava/lang/String;)Ljava/lang/StringBuilder;
     172: pop
     173: iinc          7, 1
     176: goto          135
     179: aload         6
     181: bipush        10
     183: invokevirtual #212                // Method java/lang/StringBuilder.append:(C)Ljava/lang/StringBuilder;
     186: pop
     187: aload         6
     189: ldc           #215                // String   Tried:
     191: invokevirtual #102                // Method java/lang/StringBuilder.append:(Ljava/lang/String;)Ljava/lang/StringBuilder;
     194: pop
     195: iload         5
     197: istore        7
     199: aload_0
     200: getfield      #24                 // Field converterFactories:Ljava/util/List;
     203: invokeinterface #186,  1          // InterfaceMethod java/util/List.size:()I
     208: istore        8
     210: iload         7
     212: iload         8
     214: if_icmpge     254
     217: aload         6
     219: ldc           #206                // String \n   *
     221: invokevirtual #102                // Method java/lang/StringBuilder.append:(Ljava/lang/String;)Ljava/lang/StringBuilder;
     224: aload_0
     225: getfield      #24                 // Field converterFactories:Ljava/util/List;
     228: iload         7
     230: invokeinterface #189,  2          // InterfaceMethod java/util/List.get:(I)Ljava/lang/Object;
     235: checkcast     #227                // class retrofit2/Converter$Factory
     238: invokevirtual #208                // Method java/lang/Object.getClass:()Ljava/lang/Class;
     241: invokevirtual #98                 // Method java/lang/Class.getName:()Ljava/lang/String;
     244: invokevirtual #102                // Method java/lang/StringBuilder.append:(Ljava/lang/String;)Ljava/lang/StringBuilder;
     247: pop
     248: iinc          7, 1
     251: goto          210
     254: new           #64                 // class java/lang/IllegalArgumentException
     257: dup
     258: aload         6
     260: invokevirtual #108                // Method java/lang/StringBuilder.toString:()Ljava/lang/String;
     263: invokespecial #68                 // Method java/lang/IllegalArgumentException."<init>":(Ljava/lang/String;)V
     266: athrow

  public <T> retrofit2.Converter<okhttp3.ResponseBody, T> responseBodyConverter(java.lang.reflect.Type, java.lang.annotation.Annotation[]);
    Code:
       0: aload_0
       1: aconst_null
       2: aload_1
       3: aload_2
       4: invokevirtual #235                // Method nextResponseBodyConverter:(Lretrofit2/Converter$Factory;Ljava/lang/reflect/Type;[Ljava/lang/annotation/Annotation;)Lretrofit2/Converter;
       7: areturn

  public <T> retrofit2.Converter<okhttp3.ResponseBody, T> nextResponseBodyConverter(retrofit2.Converter$Factory, java.lang.reflect.Type, java.lang.annotation.Annotation[]);
    Code:
       0: aload_2
       1: ldc           #221                // String type == null
       3: invokestatic  #172                // Method java/util/Objects.requireNonNull:(Ljava/lang/Object;Ljava/lang/String;)Ljava/lang/Object;
       6: pop
       7: aload_3
       8: ldc           #178                // String annotations == null
      10: invokestatic  #172                // Method java/util/Objects.requireNonNull:(Ljava/lang/Object;Ljava/lang/String;)Ljava/lang/Object;
      13: pop
      14: aload_0
      15: getfield      #24                 // Field converterFactories:Ljava/util/List;
      18: aload_1
      19: invokeinterface #180,  2          // InterfaceMethod java/util/List.indexOf:(Ljava/lang/Object;)I
      24: iconst_1
      25: iadd
      26: istore        4
      28: iload         4
      30: istore        5
      32: aload_0
      33: getfield      #24                 // Field converterFactories:Ljava/util/List;
      36: invokeinterface #186,  1          // InterfaceMethod java/util/List.size:()I
      41: istore        6
      43: iload         5
      45: iload         6
      47: if_icmpge     86
      50: aload_0
      51: getfield      #24                 // Field converterFactories:Ljava/util/List;
      54: iload         5
      56: invokeinterface #189,  2          // InterfaceMethod java/util/List.get:(I)Ljava/lang/Object;
      61: checkcast     #227                // class retrofit2/Converter$Factory
      64: aload_2
      65: aload_3
      66: aload_0
      67: invokevirtual #239                // Method retrofit2/Converter$Factory.responseBodyConverter:(Ljava/lang/reflect/Type;[Ljava/lang/annotation/Annotation;Lretrofit2/Retrofit;)Lretrofit2/Converter;
      70: astore        7
      72: aload         7
      74: ifnull        80
      77: aload         7
      79: areturn
      80: iinc          5, 1
      83: goto          43
      86: new           #93                 // class java/lang/StringBuilder
      89: dup
      90: ldc           #243                // String Could not locate ResponseBody converter for
      92: invokespecial #97                 // Method java/lang/StringBuilder."<init>":(Ljava/lang/String;)V
      95: aload_2
      96: invokevirtual #199                // Method java/lang/StringBuilder.append:(Ljava/lang/Object;)Ljava/lang/StringBuilder;
      99: ldc           #202                // String .\n
     101: invokevirtual #102                // Method java/lang/StringBuilder.append:(Ljava/lang/String;)Ljava/lang/StringBuilder;
     104: astore        5
     106: aload_1
     107: ifnull        173
     110: aload         5
     112: ldc           #204                // String   Skipped:
     114: invokevirtual #102                // Method java/lang/StringBuilder.append:(Ljava/lang/String;)Ljava/lang/StringBuilder;
     117: pop
     118: iconst_0
     119: istore        6
     121: iload         6
     123: iload         4
     125: if_icmpge     165
     128: aload         5
     130: ldc           #206                // String \n   *
     132: invokevirtual #102                // Method java/lang/StringBuilder.append:(Ljava/lang/String;)Ljava/lang/StringBuilder;
     135: aload_0
     136: getfield      #24                 // Field converterFactories:Ljava/util/List;
     139: iload         6
     141: invokeinterface #189,  2          // InterfaceMethod java/util/List.get:(I)Ljava/lang/Object;
     146: checkcast     #227                // class retrofit2/Converter$Factory
     149: invokevirtual #208                // Method java/lang/Object.getClass:()Ljava/lang/Class;
     152: invokevirtual #98                 // Method java/lang/Class.getName:()Ljava/lang/String;
     155: invokevirtual #102                // Method java/lang/StringBuilder.append:(Ljava/lang/String;)Ljava/lang/StringBuilder;
     158: pop
     159: iinc          6, 1
     162: goto          121
     165: aload         5
     167: bipush        10
     169: invokevirtual #212                // Method java/lang/StringBuilder.append:(C)Ljava/lang/StringBuilder;
     172: pop
     173: aload         5
     175: ldc           #215                // String   Tried:
     177: invokevirtual #102                // Method java/lang/StringBuilder.append:(Ljava/lang/String;)Ljava/lang/StringBuilder;
     180: pop
     181: iload         4
     183: istore        6
     185: aload_0
     186: getfield      #24                 // Field converterFactories:Ljava/util/List;
     189: invokeinterface #186,  1          // InterfaceMethod java/util/List.size:()I
     194: istore        7
     196: iload         6
     198: iload         7
     200: if_icmpge     240
     203: aload         5
     205: ldc           #206                // String \n   *
     207: invokevirtual #102                // Method java/lang/StringBuilder.append:(Ljava/lang/String;)Ljava/lang/StringBuilder;
     210: aload_0
     211: getfield      #24                 // Field converterFactories:Ljava/util/List;
     214: iload         6
     216: invokeinterface #189,  2          // InterfaceMethod java/util/List.get:(I)Ljava/lang/Object;
     221: checkcast     #227                // class retrofit2/Converter$Factory
     224: invokevirtual #208                // Method java/lang/Object.getClass:()Ljava/lang/Class;
     227: invokevirtual #98                 // Method java/lang/Class.getName:()Ljava/lang/String;
     230: invokevirtual #102                // Method java/lang/StringBuilder.append:(Ljava/lang/String;)Ljava/lang/StringBuilder;
     233: pop
     234: iinc          6, 1
     237: goto          196
     240: new           #64                 // class java/lang/IllegalArgumentException
     243: dup
     244: aload         5
     246: invokevirtual #108                // Method java/lang/StringBuilder.toString:()Ljava/lang/String;
     249: invokespecial #68                 // Method java/lang/IllegalArgumentException."<init>":(Ljava/lang/String;)V
     252: athrow

  public <T> retrofit2.Converter<T, java.lang.String> stringConverter(java.lang.reflect.Type, java.lang.annotation.Annotation[]);
    Code:
       0: aload_1
       1: ldc           #221                // String type == null
       3: invokestatic  #172                // Method java/util/Objects.requireNonNull:(Ljava/lang/Object;Ljava/lang/String;)Ljava/lang/Object;
       6: pop
       7: aload_2
       8: ldc           #178                // String annotations == null
      10: invokestatic  #172                // Method java/util/Objects.requireNonNull:(Ljava/lang/Object;Ljava/lang/String;)Ljava/lang/Object;
      13: pop
      14: iconst_0
      15: istore_3
      16: aload_0
      17: getfield      #24                 // Field converterFactories:Ljava/util/List;
      20: invokeinterface #186,  1          // InterfaceMethod java/util/List.size:()I
      25: istore        4
      27: iload_3
      28: iload         4
      30: if_icmpge     68
      33: aload_0
      34: getfield      #24                 // Field converterFactories:Ljava/util/List;
      37: iload_3
      38: invokeinterface #189,  2          // InterfaceMethod java/util/List.get:(I)Ljava/lang/Object;
      43: checkcast     #227                // class retrofit2/Converter$Factory
      46: aload_1
      47: aload_2
      48: aload_0
      49: invokevirtual #245                // Method retrofit2/Converter$Factory.stringConverter:(Ljava/lang/reflect/Type;[Ljava/lang/annotation/Annotation;Lretrofit2/Retrofit;)Lretrofit2/Converter;
      52: astore        5
      54: aload         5
      56: ifnull        62
      59: aload         5
      61: areturn
      62: iinc          3, 1
      65: goto          27
      68: getstatic     #248                // Field retrofit2/BuiltInConverters$ToStringConverter.INSTANCE:Lretrofit2/BuiltInConverters$ToStringConverter;
      71: areturn

  public java.util.concurrent.Executor callbackExecutor();
    Code:
       0: aload_0
       1: getfield      #31                 // Field callbackExecutor:Ljava/util/concurrent/Executor;
       4: areturn

  public retrofit2.Retrofit$Builder newBuilder();
    Code:
       0: new           #254                // class retrofit2/Retrofit$Builder
       3: dup
       4: aload_0
       5: invokespecial #256                // Method retrofit2/Retrofit$Builder."<init>":(Lretrofit2/Retrofit;)V
       8: areturn
}
