Compiled from "ServiceMethod.java"
abstract class retrofit2.ServiceMethod<T> {
  retrofit2.ServiceMethod();
    Code:
       0: aload_0
       1: invokespecial #1                  // Method java/lang/Object."<init>":()V
       4: return

  static <T> retrofit2.ServiceMethod<T> parseAnnotations(retrofit2.Retrofit, java.lang.reflect.Method);
    Code:
       0: aload_0
       1: aload_1
       2: invokestatic  #7                  // Method retrofit2/RequestFactory.parseAnnotations:(Lretrofit2/Retrofit;Ljava/lang/reflect/Method;)Lretrofit2/RequestFactory;
       5: astore_2
       6: aload_1
       7: invokevirtual #13                 // Method java/lang/reflect/Method.getGenericReturnType:()Ljava/lang/reflect/Type;
      10: astore_3
      11: aload_3
      12: invokestatic  #19                 // Method retrofit2/Utils.hasUnresolvableType:(Ljava/lang/reflect/Type;)Z
      15: ifeq          33
      18: aload_1
      19: ldc           #25                 // String Method return type must not include a type variable or wildcard: %s
      21: iconst_1
      22: anewarray     #2                  // class java/lang/Object
      25: dup
      26: iconst_0
      27: aload_3
      28: aastore
      29: invokestatic  #27                 // Method retrofit2/Utils.methodError:(Ljava/lang/reflect/Method;Ljava/lang/String;[Ljava/lang/Object;)Ljava/lang/RuntimeException;
      32: athrow
      33: aload_3
      34: getstatic     #31                 // Field java/lang/Void.TYPE:Ljava/lang/Class;
      37: if_acmpne     51
      40: aload_1
      41: ldc           #37                 // String Service methods cannot return void.
      43: iconst_0
      44: anewarray     #2                  // class java/lang/Object
      47: invokestatic  #27                 // Method retrofit2/Utils.methodError:(Ljava/lang/reflect/Method;Ljava/lang/String;[Ljava/lang/Object;)Ljava/lang/RuntimeException;
      50: athrow
      51: aload_0
      52: aload_1
      53: aload_2
      54: invokestatic  #39                 // Method retrofit2/HttpServiceMethod.parseAnnotations:(Lretrofit2/Retrofit;Ljava/lang/reflect/Method;Lretrofit2/RequestFactory;)Lretrofit2/HttpServiceMethod;
      57: areturn

  abstract T invoke(java.lang.Object[]);
}
