Compiled from "SkipCallbackExecutorImpl.java"
final class retrofit2.SkipCallbackExecutorImpl implements retrofit2.SkipCallbackExecutor {
  private static final retrofit2.SkipCallbackExecutor INSTANCE;

  retrofit2.SkipCallbackExecutorImpl();
    Code:
       0: aload_0
       1: invokespecial #1                  // Method java/lang/Object."<init>":()V
       4: return

  static java.lang.annotation.Annotation[] ensurePresent(java.lang.annotation.Annotation[]);
    Code:
       0: aload_0
       1: ldc           #7                  // class retrofit2/SkipCallbackExecutor
       3: invokestatic  #9                  // Method retrofit2/Utils.isAnnotationPresent:([Ljava/lang/annotation/Annotation;Ljava/lang/Class;)Z
       6: ifeq          11
       9: aload_0
      10: areturn
      11: aload_0
      12: arraylength
      13: iconst_1
      14: iadd
      15: anewarray     #15                 // class java/lang/annotation/Annotation
      18: astore_1
      19: aload_1
      20: iconst_0
      21: getstatic     #17                 // Field INSTANCE:Lretrofit2/SkipCallbackExecutor;
      24: aastore
      25: aload_0
      26: iconst_0
      27: aload_1
      28: iconst_1
      29: aload_0
      30: arraylength
      31: invokestatic  #23                 // Method java/lang/System.arraycopy:(Ljava/lang/Object;ILjava/lang/Object;II)V
      34: aload_1
      35: areturn

  public java.lang.Class<? extends java.lang.annotation.Annotation> annotationType();
    Code:
       0: ldc           #7                  // class retrofit2/SkipCallbackExecutor
       2: areturn

  public boolean equals(java.lang.Object);
    Code:
       0: aload_1
       1: instanceof    #7                  // class retrofit2/SkipCallbackExecutor
       4: ireturn

  public int hashCode();
    Code:
       0: iconst_0
       1: ireturn

  public java.lang.String toString();
    Code:
       0: new           #29                 // class java/lang/StringBuilder
       3: dup
       4: invokespecial #31                 // Method java/lang/StringBuilder."<init>":()V
       7: ldc           #32                 // String @
       9: invokevirtual #34                 // Method java/lang/StringBuilder.append:(Ljava/lang/String;)Ljava/lang/StringBuilder;
      12: ldc           #7                  // class retrofit2/SkipCallbackExecutor
      14: invokevirtual #38                 // Method java/lang/Class.getName:()Ljava/lang/String;
      17: invokevirtual #34                 // Method java/lang/StringBuilder.append:(Ljava/lang/String;)Ljava/lang/StringBuilder;
      20: ldc           #44                 // String ()
      22: invokevirtual #34                 // Method java/lang/StringBuilder.append:(Ljava/lang/String;)Ljava/lang/StringBuilder;
      25: invokevirtual #46                 // Method java/lang/StringBuilder.toString:()Ljava/lang/String;
      28: areturn

  static {};
    Code:
       0: new           #18                 // class retrofit2/SkipCallbackExecutorImpl
       3: dup
       4: invokespecial #49                 // Method "<init>":()V
       7: putstatic     #17                 // Field INSTANCE:Lretrofit2/SkipCallbackExecutor;
      10: return
}
