Compiled from "Utils.java"
final class retrofit2.Utils {
  static final java.lang.reflect.Type[] EMPTY_TYPE_ARRAY;

  private retrofit2.Utils();
    Code:
       0: aload_0
       1: invokespecial #1                  // Method java/lang/Object."<init>":()V
       4: return

  static java.lang.RuntimeException methodError(java.lang.reflect.Method, java.lang.String, java.lang.Object...);
    Code:
       0: aload_0
       1: aconst_null
       2: aload_1
       3: aload_2
       4: invokestatic  #7                  // Method methodError:(Ljava/lang/reflect/Method;Ljava/lang/Throwable;Ljava/lang/String;[Ljava/lang/Object;)Ljava/lang/RuntimeException;
       7: areturn

  static java.lang.RuntimeException methodError(java.lang.reflect.Method, java.lang.Throwable, java.lang.String, java.lang.Object...);
    Code:
       0: aload_2
       1: aload_3
       2: invokestatic  #13                 // Method java/lang/String.format:(Ljava/lang/String;[Ljava/lang/Object;)Ljava/lang/String;
       5: astore_2
       6: new           #19                 // class java/lang/IllegalArgumentException
       9: dup
      10: new           #21                 // class java/lang/StringBuilder
      13: dup
      14: invokespecial #23                 // Method java/lang/StringBuilder."<init>":()V
      17: aload_2
      18: invokevirtual #24                 // Method java/lang/StringBuilder.append:(Ljava/lang/String;)Ljava/lang/StringBuilder;
      21: ldc           #28                 // String \n    for method
      23: invokevirtual #24                 // Method java/lang/StringBuilder.append:(Ljava/lang/String;)Ljava/lang/StringBuilder;
      26: aload_0
      27: invokevirtual #30                 // Method java/lang/reflect/Method.getDeclaringClass:()Ljava/lang/Class;
      30: invokevirtual #36                 // Method java/lang/Class.getSimpleName:()Ljava/lang/String;
      33: invokevirtual #24                 // Method java/lang/StringBuilder.append:(Ljava/lang/String;)Ljava/lang/StringBuilder;
      36: ldc           #42                 // String .
      38: invokevirtual #24                 // Method java/lang/StringBuilder.append:(Ljava/lang/String;)Ljava/lang/StringBuilder;
      41: aload_0
      42: invokevirtual #44                 // Method java/lang/reflect/Method.getName:()Ljava/lang/String;
      45: invokevirtual #24                 // Method java/lang/StringBuilder.append:(Ljava/lang/String;)Ljava/lang/StringBuilder;
      48: invokevirtual #47                 // Method java/lang/StringBuilder.toString:()Ljava/lang/String;
      51: aload_1
      52: invokespecial #50                 // Method java/lang/IllegalArgumentException."<init>":(Ljava/lang/String;Ljava/lang/Throwable;)V
      55: areturn

  static java.lang.RuntimeException parameterError(java.lang.reflect.Method, java.lang.Throwable, int, java.lang.String, java.lang.Object...);
    Code:
       0: aload_0
       1: aload_1
       2: new           #21                 // class java/lang/StringBuilder
       5: dup
       6: invokespecial #23                 // Method java/lang/StringBuilder."<init>":()V
       9: aload_3
      10: invokevirtual #24                 // Method java/lang/StringBuilder.append:(Ljava/lang/String;)Ljava/lang/StringBuilder;
      13: ldc           #53                 // String  (parameter #
      15: invokevirtual #24                 // Method java/lang/StringBuilder.append:(Ljava/lang/String;)Ljava/lang/StringBuilder;
      18: iload_2
      19: iconst_1
      20: iadd
      21: invokevirtual #55                 // Method java/lang/StringBuilder.append:(I)Ljava/lang/StringBuilder;
      24: ldc           #58                 // String )
      26: invokevirtual #24                 // Method java/lang/StringBuilder.append:(Ljava/lang/String;)Ljava/lang/StringBuilder;
      29: invokevirtual #47                 // Method java/lang/StringBuilder.toString:()Ljava/lang/String;
      32: aload         4
      34: invokestatic  #7                  // Method methodError:(Ljava/lang/reflect/Method;Ljava/lang/Throwable;Ljava/lang/String;[Ljava/lang/Object;)Ljava/lang/RuntimeException;
      37: areturn

  static java.lang.RuntimeException parameterError(java.lang.reflect.Method, int, java.lang.String, java.lang.Object...);
    Code:
       0: aload_0
       1: new           #21                 // class java/lang/StringBuilder
       4: dup
       5: invokespecial #23                 // Method java/lang/StringBuilder."<init>":()V
       8: aload_2
       9: invokevirtual #24                 // Method java/lang/StringBuilder.append:(Ljava/lang/String;)Ljava/lang/StringBuilder;
      12: ldc           #53                 // String  (parameter #
      14: invokevirtual #24                 // Method java/lang/StringBuilder.append:(Ljava/lang/String;)Ljava/lang/StringBuilder;
      17: iload_1
      18: iconst_1
      19: iadd
      20: invokevirtual #55                 // Method java/lang/StringBuilder.append:(I)Ljava/lang/StringBuilder;
      23: ldc           #58                 // String )
      25: invokevirtual #24                 // Method java/lang/StringBuilder.append:(Ljava/lang/String;)Ljava/lang/StringBuilder;
      28: invokevirtual #47                 // Method java/lang/StringBuilder.toString:()Ljava/lang/String;
      31: aload_3
      32: invokestatic  #60                 // Method methodError:(Ljava/lang/reflect/Method;Ljava/lang/String;[Ljava/lang/Object;)Ljava/lang/RuntimeException;
      35: areturn

  static java.lang.Class<?> getRawType(java.lang.reflect.Type);
    Code:
       0: aload_0
       1: ldc           #63                 // String type == null
       3: invokestatic  #65                 // Method java/util/Objects.requireNonNull:(Ljava/lang/Object;Ljava/lang/String;)Ljava/lang/Object;
       6: pop
       7: aload_0
       8: instanceof    #37                 // class java/lang/Class
      11: ifeq          19
      14: aload_0
      15: checkcast     #37                 // class java/lang/Class
      18: areturn
      19: aload_0
      20: instanceof    #71                 // class java/lang/reflect/ParameterizedType
      23: ifeq          58
      26: aload_0
      27: checkcast     #71                 // class java/lang/reflect/ParameterizedType
      30: astore_1
      31: aload_1
      32: invokeinterface #73,  1           // InterfaceMethod java/lang/reflect/ParameterizedType.getRawType:()Ljava/lang/reflect/Type;
      37: astore_2
      38: aload_2
      39: instanceof    #37                 // class java/lang/Class
      42: ifne          53
      45: new           #19                 // class java/lang/IllegalArgumentException
      48: dup
      49: invokespecial #77                 // Method java/lang/IllegalArgumentException."<init>":()V
      52: athrow
      53: aload_2
      54: checkcast     #37                 // class java/lang/Class
      57: areturn
      58: aload_0
      59: instanceof    #78                 // class java/lang/reflect/GenericArrayType
      62: ifeq          87
      65: aload_0
      66: checkcast     #78                 // class java/lang/reflect/GenericArrayType
      69: invokeinterface #80,  1           // InterfaceMethod java/lang/reflect/GenericArrayType.getGenericComponentType:()Ljava/lang/reflect/Type;
      74: astore_1
      75: aload_1
      76: invokestatic  #83                 // Method getRawType:(Ljava/lang/reflect/Type;)Ljava/lang/Class;
      79: iconst_0
      80: invokestatic  #86                 // Method java/lang/reflect/Array.newInstance:(Ljava/lang/Class;I)Ljava/lang/Object;
      83: invokevirtual #92                 // Method java/lang/Object.getClass:()Ljava/lang/Class;
      86: areturn
      87: aload_0
      88: instanceof    #95                 // class java/lang/reflect/TypeVariable
      91: ifeq          97
      94: ldc           #2                  // class java/lang/Object
      96: areturn
      97: aload_0
      98: instanceof    #97                 // class java/lang/reflect/WildcardType
     101: ifeq          119
     104: aload_0
     105: checkcast     #97                 // class java/lang/reflect/WildcardType
     108: invokeinterface #99,  1           // InterfaceMethod java/lang/reflect/WildcardType.getUpperBounds:()[Ljava/lang/reflect/Type;
     113: iconst_0
     114: aaload
     115: invokestatic  #83                 // Method getRawType:(Ljava/lang/reflect/Type;)Ljava/lang/Class;
     118: areturn
     119: new           #19                 // class java/lang/IllegalArgumentException
     122: dup
     123: new           #21                 // class java/lang/StringBuilder
     126: dup
     127: invokespecial #23                 // Method java/lang/StringBuilder."<init>":()V
     130: ldc           #103                // String Expected a Class, ParameterizedType, or GenericArrayType, but <
     132: invokevirtual #24                 // Method java/lang/StringBuilder.append:(Ljava/lang/String;)Ljava/lang/StringBuilder;
     135: aload_0
     136: invokevirtual #105                // Method java/lang/StringBuilder.append:(Ljava/lang/Object;)Ljava/lang/StringBuilder;
     139: ldc           #108                // String > is of type
     141: invokevirtual #24                 // Method java/lang/StringBuilder.append:(Ljava/lang/String;)Ljava/lang/StringBuilder;
     144: aload_0
     145: invokevirtual #92                 // Method java/lang/Object.getClass:()Ljava/lang/Class;
     148: invokevirtual #110                // Method java/lang/Class.getName:()Ljava/lang/String;
     151: invokevirtual #24                 // Method java/lang/StringBuilder.append:(Ljava/lang/String;)Ljava/lang/StringBuilder;
     154: invokevirtual #47                 // Method java/lang/StringBuilder.toString:()Ljava/lang/String;
     157: invokespecial #111                // Method java/lang/IllegalArgumentException."<init>":(Ljava/lang/String;)V
     160: athrow

  static boolean equals(java.lang.reflect.Type, java.lang.reflect.Type);
    Code:
       0: aload_0
       1: aload_1
       2: if_acmpne     7
       5: iconst_1
       6: ireturn
       7: aload_0
       8: instanceof    #37                 // class java/lang/Class
      11: ifeq          20
      14: aload_0
      15: aload_1
      16: invokevirtual #114                // Method java/lang/Object.equals:(Ljava/lang/Object;)Z
      19: ireturn
      20: aload_0
      21: instanceof    #71                 // class java/lang/reflect/ParameterizedType
      24: ifeq          126
      27: aload_1
      28: instanceof    #71                 // class java/lang/reflect/ParameterizedType
      31: ifne          36
      34: iconst_0
      35: ireturn
      36: aload_0
      37: checkcast     #71                 // class java/lang/reflect/ParameterizedType
      40: astore_2
      41: aload_1
      42: checkcast     #71                 // class java/lang/reflect/ParameterizedType
      45: astore_3
      46: aload_2
      47: invokeinterface #118,  1          // InterfaceMethod java/lang/reflect/ParameterizedType.getOwnerType:()Ljava/lang/reflect/Type;
      52: astore        4
      54: aload_3
      55: invokeinterface #118,  1          // InterfaceMethod java/lang/reflect/ParameterizedType.getOwnerType:()Ljava/lang/reflect/Type;
      60: astore        5
      62: aload         4
      64: aload         5
      66: if_acmpeq     84
      69: aload         4
      71: ifnull        124
      74: aload         4
      76: aload         5
      78: invokevirtual #114                // Method java/lang/Object.equals:(Ljava/lang/Object;)Z
      81: ifeq          124
      84: aload_2
      85: invokeinterface #73,  1           // InterfaceMethod java/lang/reflect/ParameterizedType.getRawType:()Ljava/lang/reflect/Type;
      90: aload_3
      91: invokeinterface #73,  1           // InterfaceMethod java/lang/reflect/ParameterizedType.getRawType:()Ljava/lang/reflect/Type;
      96: invokevirtual #114                // Method java/lang/Object.equals:(Ljava/lang/Object;)Z
      99: ifeq          124
     102: aload_2
     103: invokeinterface #121,  1          // InterfaceMethod java/lang/reflect/ParameterizedType.getActualTypeArguments:()[Ljava/lang/reflect/Type;
     108: aload_3
     109: invokeinterface #121,  1          // InterfaceMethod java/lang/reflect/ParameterizedType.getActualTypeArguments:()[Ljava/lang/reflect/Type;
     114: invokestatic  #124                // Method java/util/Arrays.equals:([Ljava/lang/Object;[Ljava/lang/Object;)Z
     117: ifeq          124
     120: iconst_1
     121: goto          125
     124: iconst_0
     125: ireturn
     126: aload_0
     127: instanceof    #78                 // class java/lang/reflect/GenericArrayType
     130: ifeq          168
     133: aload_1
     134: instanceof    #78                 // class java/lang/reflect/GenericArrayType
     137: ifne          142
     140: iconst_0
     141: ireturn
     142: aload_0
     143: checkcast     #78                 // class java/lang/reflect/GenericArrayType
     146: astore_2
     147: aload_1
     148: checkcast     #78                 // class java/lang/reflect/GenericArrayType
     151: astore_3
     152: aload_2
     153: invokeinterface #80,  1           // InterfaceMethod java/lang/reflect/GenericArrayType.getGenericComponentType:()Ljava/lang/reflect/Type;
     158: aload_3
     159: invokeinterface #80,  1           // InterfaceMethod java/lang/reflect/GenericArrayType.getGenericComponentType:()Ljava/lang/reflect/Type;
     164: invokestatic  #129                // Method equals:(Ljava/lang/reflect/Type;Ljava/lang/reflect/Type;)Z
     167: ireturn
     168: aload_0
     169: instanceof    #97                 // class java/lang/reflect/WildcardType
     172: ifeq          236
     175: aload_1
     176: instanceof    #97                 // class java/lang/reflect/WildcardType
     179: ifne          184
     182: iconst_0
     183: ireturn
     184: aload_0
     185: checkcast     #97                 // class java/lang/reflect/WildcardType
     188: astore_2
     189: aload_1
     190: checkcast     #97                 // class java/lang/reflect/WildcardType
     193: astore_3
     194: aload_2
     195: invokeinterface #99,  1           // InterfaceMethod java/lang/reflect/WildcardType.getUpperBounds:()[Ljava/lang/reflect/Type;
     200: aload_3
     201: invokeinterface #99,  1           // InterfaceMethod java/lang/reflect/WildcardType.getUpperBounds:()[Ljava/lang/reflect/Type;
     206: invokestatic  #124                // Method java/util/Arrays.equals:([Ljava/lang/Object;[Ljava/lang/Object;)Z
     209: ifeq          234
     212: aload_2
     213: invokeinterface #132,  1          // InterfaceMethod java/lang/reflect/WildcardType.getLowerBounds:()[Ljava/lang/reflect/Type;
     218: aload_3
     219: invokeinterface #132,  1          // InterfaceMethod java/lang/reflect/WildcardType.getLowerBounds:()[Ljava/lang/reflect/Type;
     224: invokestatic  #124                // Method java/util/Arrays.equals:([Ljava/lang/Object;[Ljava/lang/Object;)Z
     227: ifeq          234
     230: iconst_1
     231: goto          235
     234: iconst_0
     235: ireturn
     236: aload_0
     237: instanceof    #95                 // class java/lang/reflect/TypeVariable
     240: ifeq          301
     243: aload_1
     244: instanceof    #95                 // class java/lang/reflect/TypeVariable
     247: ifne          252
     250: iconst_0
     251: ireturn
     252: aload_0
     253: checkcast     #95                 // class java/lang/reflect/TypeVariable
     256: astore_2
     257: aload_1
     258: checkcast     #95                 // class java/lang/reflect/TypeVariable
     261: astore_3
     262: aload_2
     263: invokeinterface #135,  1          // InterfaceMethod java/lang/reflect/TypeVariable.getGenericDeclaration:()Ljava/lang/reflect/GenericDeclaration;
     268: aload_3
     269: invokeinterface #135,  1          // InterfaceMethod java/lang/reflect/TypeVariable.getGenericDeclaration:()Ljava/lang/reflect/GenericDeclaration;
     274: if_acmpne     299
     277: aload_2
     278: invokeinterface #139,  1          // InterfaceMethod java/lang/reflect/TypeVariable.getName:()Ljava/lang/String;
     283: aload_3
     284: invokeinterface #139,  1          // InterfaceMethod java/lang/reflect/TypeVariable.getName:()Ljava/lang/String;
     289: invokevirtual #140                // Method java/lang/String.equals:(Ljava/lang/Object;)Z
     292: ifeq          299
     295: iconst_1
     296: goto          300
     299: iconst_0
     300: ireturn
     301: iconst_0
     302: ireturn

  static java.lang.reflect.Type getGenericSupertype(java.lang.reflect.Type, java.lang.Class<?>, java.lang.Class<?>);
    Code:
       0: aload_2
       1: aload_1
       2: if_acmpne     7
       5: aload_0
       6: areturn
       7: aload_2
       8: invokevirtual #141                // Method java/lang/Class.isInterface:()Z
      11: ifeq          82
      14: aload_1
      15: invokevirtual #145                // Method java/lang/Class.getInterfaces:()[Ljava/lang/Class;
      18: astore_3
      19: iconst_0
      20: istore        4
      22: aload_3
      23: arraylength
      24: istore        5
      26: iload         4
      28: iload         5
      30: if_icmpge     82
      33: aload_3
      34: iload         4
      36: aaload
      37: aload_2
      38: if_acmpne     49
      41: aload_1
      42: invokevirtual #149                // Method java/lang/Class.getGenericInterfaces:()[Ljava/lang/reflect/Type;
      45: iload         4
      47: aaload
      48: areturn
      49: aload_2
      50: aload_3
      51: iload         4
      53: aaload
      54: invokevirtual #152                // Method java/lang/Class.isAssignableFrom:(Ljava/lang/Class;)Z
      57: ifeq          76
      60: aload_1
      61: invokevirtual #149                // Method java/lang/Class.getGenericInterfaces:()[Ljava/lang/reflect/Type;
      64: iload         4
      66: aaload
      67: aload_3
      68: iload         4
      70: aaload
      71: aload_2
      72: invokestatic  #156                // Method getGenericSupertype:(Ljava/lang/reflect/Type;Ljava/lang/Class;Ljava/lang/Class;)Ljava/lang/reflect/Type;
      75: areturn
      76: iinc          4, 1
      79: goto          26
      82: aload_1
      83: invokevirtual #141                // Method java/lang/Class.isInterface:()Z
      86: ifne          133
      89: aload_1
      90: ldc           #2                  // class java/lang/Object
      92: if_acmpeq     133
      95: aload_1
      96: invokevirtual #160                // Method java/lang/Class.getSuperclass:()Ljava/lang/Class;
      99: astore_3
     100: aload_3
     101: aload_2
     102: if_acmpne     110
     105: aload_1
     106: invokevirtual #163                // Method java/lang/Class.getGenericSuperclass:()Ljava/lang/reflect/Type;
     109: areturn
     110: aload_2
     111: aload_3
     112: invokevirtual #152                // Method java/lang/Class.isAssignableFrom:(Ljava/lang/Class;)Z
     115: ifeq          128
     118: aload_1
     119: invokevirtual #163                // Method java/lang/Class.getGenericSuperclass:()Ljava/lang/reflect/Type;
     122: aload_3
     123: aload_2
     124: invokestatic  #156                // Method getGenericSupertype:(Ljava/lang/reflect/Type;Ljava/lang/Class;Ljava/lang/Class;)Ljava/lang/reflect/Type;
     127: areturn
     128: aload_3
     129: astore_1
     130: goto          89
     133: aload_2
     134: areturn

  private static int indexOf(java.lang.Object[], java.lang.Object);
    Code:
       0: iconst_0
       1: istore_2
       2: iload_2
       3: aload_0
       4: arraylength
       5: if_icmpge     26
       8: aload_1
       9: aload_0
      10: iload_2
      11: aaload
      12: invokevirtual #114                // Method java/lang/Object.equals:(Ljava/lang/Object;)Z
      15: ifeq          20
      18: iload_2
      19: ireturn
      20: iinc          2, 1
      23: goto          2
      26: new           #166                // class java/util/NoSuchElementException
      29: dup
      30: invokespecial #168                // Method java/util/NoSuchElementException."<init>":()V
      33: athrow

  static java.lang.String typeToString(java.lang.reflect.Type);
    Code:
       0: aload_0
       1: instanceof    #37                 // class java/lang/Class
       4: ifeq          17
       7: aload_0
       8: checkcast     #37                 // class java/lang/Class
      11: invokevirtual #110                // Method java/lang/Class.getName:()Ljava/lang/String;
      14: goto          21
      17: aload_0
      18: invokevirtual #169                // Method java/lang/Object.toString:()Ljava/lang/String;
      21: areturn

  static java.lang.reflect.Type getSupertype(java.lang.reflect.Type, java.lang.Class<?>, java.lang.Class<?>);
    Code:
       0: aload_2
       1: aload_1
       2: invokevirtual #152                // Method java/lang/Class.isAssignableFrom:(Ljava/lang/Class;)Z
       5: ifne          16
       8: new           #19                 // class java/lang/IllegalArgumentException
      11: dup
      12: invokespecial #77                 // Method java/lang/IllegalArgumentException."<init>":()V
      15: athrow
      16: aload_0
      17: aload_1
      18: aload_0
      19: aload_1
      20: aload_2
      21: invokestatic  #156                // Method getGenericSupertype:(Ljava/lang/reflect/Type;Ljava/lang/Class;Ljava/lang/Class;)Ljava/lang/reflect/Type;
      24: invokestatic  #170                // Method resolve:(Ljava/lang/reflect/Type;Ljava/lang/Class;Ljava/lang/reflect/Type;)Ljava/lang/reflect/Type;
      27: areturn

  static java.lang.reflect.Type resolve(java.lang.reflect.Type, java.lang.Class<?>, java.lang.reflect.Type);
    Code:
       0: aload_2
       1: instanceof    #95                 // class java/lang/reflect/TypeVariable
       4: ifeq          29
       7: aload_2
       8: checkcast     #95                 // class java/lang/reflect/TypeVariable
      11: astore_3
      12: aload_0
      13: aload_1
      14: aload_3
      15: invokestatic  #174                // Method resolveTypeVariable:(Ljava/lang/reflect/Type;Ljava/lang/Class;Ljava/lang/reflect/TypeVariable;)Ljava/lang/reflect/Type;
      18: astore_2
      19: aload_2
      20: aload_3
      21: if_acmpne     26
      24: aload_2
      25: areturn
      26: goto          0
      29: aload_2
      30: instanceof    #37                 // class java/lang/Class
      33: ifeq          87
      36: aload_2
      37: checkcast     #37                 // class java/lang/Class
      40: invokevirtual #178                // Method java/lang/Class.isArray:()Z
      43: ifeq          87
      46: aload_2
      47: checkcast     #37                 // class java/lang/Class
      50: astore_3
      51: aload_3
      52: invokevirtual #181                // Method java/lang/Class.getComponentType:()Ljava/lang/Class;
      55: astore        4
      57: aload_0
      58: aload_1
      59: aload         4
      61: invokestatic  #170                // Method resolve:(Ljava/lang/reflect/Type;Ljava/lang/Class;Ljava/lang/reflect/Type;)Ljava/lang/reflect/Type;
      64: astore        5
      66: aload         4
      68: aload         5
      70: if_acmpne     77
      73: aload_3
      74: goto          86
      77: new           #184                // class retrofit2/Utils$GenericArrayTypeImpl
      80: dup
      81: aload         5
      83: invokespecial #186                // Method retrofit2/Utils$GenericArrayTypeImpl."<init>":(Ljava/lang/reflect/Type;)V
      86: areturn
      87: aload_2
      88: instanceof    #78                 // class java/lang/reflect/GenericArrayType
      91: ifeq          137
      94: aload_2
      95: checkcast     #78                 // class java/lang/reflect/GenericArrayType
      98: astore_3
      99: aload_3
     100: invokeinterface #80,  1           // InterfaceMethod java/lang/reflect/GenericArrayType.getGenericComponentType:()Ljava/lang/reflect/Type;
     105: astore        4
     107: aload_0
     108: aload_1
     109: aload         4
     111: invokestatic  #170                // Method resolve:(Ljava/lang/reflect/Type;Ljava/lang/Class;Ljava/lang/reflect/Type;)Ljava/lang/reflect/Type;
     114: astore        5
     116: aload         4
     118: aload         5
     120: if_acmpne     127
     123: aload_3
     124: goto          136
     127: new           #184                // class retrofit2/Utils$GenericArrayTypeImpl
     130: dup
     131: aload         5
     133: invokespecial #186                // Method retrofit2/Utils$GenericArrayTypeImpl."<init>":(Ljava/lang/reflect/Type;)V
     136: areturn
     137: aload_2
     138: instanceof    #71                 // class java/lang/reflect/ParameterizedType
     141: ifeq          283
     144: aload_2
     145: checkcast     #71                 // class java/lang/reflect/ParameterizedType
     148: astore_3
     149: aload_3
     150: invokeinterface #118,  1          // InterfaceMethod java/lang/reflect/ParameterizedType.getOwnerType:()Ljava/lang/reflect/Type;
     155: astore        4
     157: aload_0
     158: aload_1
     159: aload         4
     161: invokestatic  #170                // Method resolve:(Ljava/lang/reflect/Type;Ljava/lang/Class;Ljava/lang/reflect/Type;)Ljava/lang/reflect/Type;
     164: astore        5
     166: aload         5
     168: aload         4
     170: if_acmpeq     177
     173: iconst_1
     174: goto          178
     177: iconst_0
     178: istore        6
     180: aload_3
     181: invokeinterface #121,  1          // InterfaceMethod java/lang/reflect/ParameterizedType.getActualTypeArguments:()[Ljava/lang/reflect/Type;
     186: astore        7
     188: iconst_0
     189: istore        8
     191: aload         7
     193: arraylength
     194: istore        9
     196: iload         8
     198: iload         9
     200: if_icmpge     256
     203: aload_0
     204: aload_1
     205: aload         7
     207: iload         8
     209: aaload
     210: invokestatic  #170                // Method resolve:(Ljava/lang/reflect/Type;Ljava/lang/Class;Ljava/lang/reflect/Type;)Ljava/lang/reflect/Type;
     213: astore        10
     215: aload         10
     217: aload         7
     219: iload         8
     221: aaload
     222: if_acmpeq     250
     225: iload         6
     227: ifne          243
     230: aload         7
     232: invokevirtual #189                // Method "[Ljava/lang/reflect/Type;".clone:()Ljava/lang/Object;
     235: checkcast     #190                // class "[Ljava/lang/reflect/Type;"
     238: astore        7
     240: iconst_1
     241: istore        6
     243: aload         7
     245: iload         8
     247: aload         10
     249: aastore
     250: iinc          8, 1
     253: goto          196
     256: iload         6
     258: ifeq          281
     261: new           #195                // class retrofit2/Utils$ParameterizedTypeImpl
     264: dup
     265: aload         5
     267: aload_3
     268: invokeinterface #73,  1           // InterfaceMethod java/lang/reflect/ParameterizedType.getRawType:()Ljava/lang/reflect/Type;
     273: aload         7
     275: invokespecial #197                // Method retrofit2/Utils$ParameterizedTypeImpl."<init>":(Ljava/lang/reflect/Type;Ljava/lang/reflect/Type;[Ljava/lang/reflect/Type;)V
     278: goto          282
     281: aload_3
     282: areturn
     283: aload_2
     284: instanceof    #97                 // class java/lang/reflect/WildcardType
     287: ifeq          416
     290: aload_2
     291: checkcast     #97                 // class java/lang/reflect/WildcardType
     294: astore_3
     295: aload_3
     296: invokeinterface #132,  1          // InterfaceMethod java/lang/reflect/WildcardType.getLowerBounds:()[Ljava/lang/reflect/Type;
     301: astore        4
     303: aload_3
     304: invokeinterface #99,  1           // InterfaceMethod java/lang/reflect/WildcardType.getUpperBounds:()[Ljava/lang/reflect/Type;
     309: astore        5
     311: aload         4
     313: arraylength
     314: iconst_1
     315: if_icmpne     367
     318: aload_0
     319: aload_1
     320: aload         4
     322: iconst_0
     323: aaload
     324: invokestatic  #170                // Method resolve:(Ljava/lang/reflect/Type;Ljava/lang/Class;Ljava/lang/reflect/Type;)Ljava/lang/reflect/Type;
     327: astore        6
     329: aload         6
     331: aload         4
     333: iconst_0
     334: aaload
     335: if_acmpeq     364
     338: new           #200                // class retrofit2/Utils$WildcardTypeImpl
     341: dup
     342: iconst_1
     343: anewarray     #202                // class java/lang/reflect/Type
     346: dup
     347: iconst_0
     348: ldc           #2                  // class java/lang/Object
     350: aastore
     351: iconst_1
     352: anewarray     #202                // class java/lang/reflect/Type
     355: dup
     356: iconst_0
     357: aload         6
     359: aastore
     360: invokespecial #204                // Method retrofit2/Utils$WildcardTypeImpl."<init>":([Ljava/lang/reflect/Type;[Ljava/lang/reflect/Type;)V
     363: areturn
     364: goto          414
     367: aload         5
     369: arraylength
     370: iconst_1
     371: if_icmpne     414
     374: aload_0
     375: aload_1
     376: aload         5
     378: iconst_0
     379: aaload
     380: invokestatic  #170                // Method resolve:(Ljava/lang/reflect/Type;Ljava/lang/Class;Ljava/lang/reflect/Type;)Ljava/lang/reflect/Type;
     383: astore        6
     385: aload         6
     387: aload         5
     389: iconst_0
     390: aaload
     391: if_acmpeq     414
     394: new           #200                // class retrofit2/Utils$WildcardTypeImpl
     397: dup
     398: iconst_1
     399: anewarray     #202                // class java/lang/reflect/Type
     402: dup
     403: iconst_0
     404: aload         6
     406: aastore
     407: getstatic     #207                // Field EMPTY_TYPE_ARRAY:[Ljava/lang/reflect/Type;
     410: invokespecial #204                // Method retrofit2/Utils$WildcardTypeImpl."<init>":([Ljava/lang/reflect/Type;[Ljava/lang/reflect/Type;)V
     413: areturn
     414: aload_3
     415: areturn
     416: aload_2
     417: areturn

  private static java.lang.reflect.Type resolveTypeVariable(java.lang.reflect.Type, java.lang.Class<?>, java.lang.reflect.TypeVariable<?>);
    Code:
       0: aload_2
       1: invokestatic  #210                // Method declaringClassOf:(Ljava/lang/reflect/TypeVariable;)Ljava/lang/Class;
       4: astore_3
       5: aload_3
       6: ifnonnull     11
       9: aload_2
      10: areturn
      11: aload_0
      12: aload_1
      13: aload_3
      14: invokestatic  #156                // Method getGenericSupertype:(Ljava/lang/reflect/Type;Ljava/lang/Class;Ljava/lang/Class;)Ljava/lang/reflect/Type;
      17: astore        4
      19: aload         4
      21: instanceof    #71                 // class java/lang/reflect/ParameterizedType
      24: ifeq          51
      27: aload_3
      28: invokevirtual #214                // Method java/lang/Class.getTypeParameters:()[Ljava/lang/reflect/TypeVariable;
      31: aload_2
      32: invokestatic  #218                // Method indexOf:([Ljava/lang/Object;Ljava/lang/Object;)I
      35: istore        5
      37: aload         4
      39: checkcast     #71                 // class java/lang/reflect/ParameterizedType
      42: invokeinterface #121,  1          // InterfaceMethod java/lang/reflect/ParameterizedType.getActualTypeArguments:()[Ljava/lang/reflect/Type;
      47: iload         5
      49: aaload
      50: areturn
      51: aload_2
      52: areturn

  private static java.lang.Class<?> declaringClassOf(java.lang.reflect.TypeVariable<?>);
    Code:
       0: aload_0
       1: invokeinterface #135,  1          // InterfaceMethod java/lang/reflect/TypeVariable.getGenericDeclaration:()Ljava/lang/reflect/GenericDeclaration;
       6: astore_1
       7: aload_1
       8: instanceof    #37                 // class java/lang/Class
      11: ifeq          21
      14: aload_1
      15: checkcast     #37                 // class java/lang/Class
      18: goto          22
      21: aconst_null
      22: areturn

  static void checkNotPrimitive(java.lang.reflect.Type);
    Code:
       0: aload_0
       1: instanceof    #37                 // class java/lang/Class
       4: ifeq          25
       7: aload_0
       8: checkcast     #37                 // class java/lang/Class
      11: invokevirtual #222                // Method java/lang/Class.isPrimitive:()Z
      14: ifeq          25
      17: new           #19                 // class java/lang/IllegalArgumentException
      20: dup
      21: invokespecial #77                 // Method java/lang/IllegalArgumentException."<init>":()V
      24: athrow
      25: return

  static boolean isAnnotationPresent(java.lang.annotation.Annotation[], java.lang.Class<? extends java.lang.annotation.Annotation>);
    Code:
       0: aload_0
       1: astore_2
       2: aload_2
       3: arraylength
       4: istore_3
       5: iconst_0
       6: istore        4
       8: iload         4
      10: iload_3
      11: if_icmpge     37
      14: aload_2
      15: iload         4
      17: aaload
      18: astore        5
      20: aload_1
      21: aload         5
      23: invokevirtual #225                // Method java/lang/Class.isInstance:(Ljava/lang/Object;)Z
      26: ifeq          31
      29: iconst_1
      30: ireturn
      31: iinc          4, 1
      34: goto          8
      37: iconst_0
      38: ireturn

  static okhttp3.ResponseBody buffer(okhttp3.ResponseBody) throws java.io.IOException;
    Code:
       0: new           #228                // class okio/Buffer
       3: dup
       4: invokespecial #230                // Method okio/Buffer."<init>":()V
       7: astore_1
       8: aload_0
       9: invokevirtual #231                // Method okhttp3/ResponseBody.source:()Lokio/BufferedSource;
      12: aload_1
      13: invokeinterface #237,  2          // InterfaceMethod okio/BufferedSource.readAll:(Lokio/Sink;)J
      18: pop2
      19: aload_0
      20: invokevirtual #243                // Method okhttp3/ResponseBody.contentType:()Lokhttp3/MediaType;
      23: aload_0
      24: invokevirtual #247                // Method okhttp3/ResponseBody.contentLength:()J
      27: aload_1
      28: invokestatic  #251                // Method okhttp3/ResponseBody.create:(Lokhttp3/MediaType;JLokio/BufferedSource;)Lokhttp3/ResponseBody;
      31: areturn

  static java.lang.reflect.Type getParameterUpperBound(int, java.lang.reflect.ParameterizedType);
    Code:
       0: aload_1
       1: invokeinterface #121,  1          // InterfaceMethod java/lang/reflect/ParameterizedType.getActualTypeArguments:()[Ljava/lang/reflect/Type;
       6: astore_2
       7: iload_0
       8: iflt          17
      11: iload_0
      12: aload_2
      13: arraylength
      14: if_icmplt     65
      17: new           #19                 // class java/lang/IllegalArgumentException
      20: dup
      21: new           #21                 // class java/lang/StringBuilder
      24: dup
      25: invokespecial #23                 // Method java/lang/StringBuilder."<init>":()V
      28: ldc           #255                // String Index
      30: invokevirtual #24                 // Method java/lang/StringBuilder.append:(Ljava/lang/String;)Ljava/lang/StringBuilder;
      33: iload_0
      34: invokevirtual #55                 // Method java/lang/StringBuilder.append:(I)Ljava/lang/StringBuilder;
      37: ldc_w         #257                // String  not in range [0,
      40: invokevirtual #24                 // Method java/lang/StringBuilder.append:(Ljava/lang/String;)Ljava/lang/StringBuilder;
      43: aload_2
      44: arraylength
      45: invokevirtual #55                 // Method java/lang/StringBuilder.append:(I)Ljava/lang/StringBuilder;
      48: ldc_w         #259                // String ) for
      51: invokevirtual #24                 // Method java/lang/StringBuilder.append:(Ljava/lang/String;)Ljava/lang/StringBuilder;
      54: aload_1
      55: invokevirtual #105                // Method java/lang/StringBuilder.append:(Ljava/lang/Object;)Ljava/lang/StringBuilder;
      58: invokevirtual #47                 // Method java/lang/StringBuilder.toString:()Ljava/lang/String;
      61: invokespecial #111                // Method java/lang/IllegalArgumentException."<init>":(Ljava/lang/String;)V
      64: athrow
      65: aload_2
      66: iload_0
      67: aaload
      68: astore_3
      69: aload_3
      70: instanceof    #97                 // class java/lang/reflect/WildcardType
      73: ifeq          88
      76: aload_3
      77: checkcast     #97                 // class java/lang/reflect/WildcardType
      80: invokeinterface #99,  1           // InterfaceMethod java/lang/reflect/WildcardType.getUpperBounds:()[Ljava/lang/reflect/Type;
      85: iconst_0
      86: aaload
      87: areturn
      88: aload_3
      89: areturn

  static java.lang.reflect.Type getParameterLowerBound(int, java.lang.reflect.ParameterizedType);
    Code:
       0: aload_1
       1: invokeinterface #121,  1          // InterfaceMethod java/lang/reflect/ParameterizedType.getActualTypeArguments:()[Ljava/lang/reflect/Type;
       6: iload_0
       7: aaload
       8: astore_2
       9: aload_2
      10: instanceof    #97                 // class java/lang/reflect/WildcardType
      13: ifeq          28
      16: aload_2
      17: checkcast     #97                 // class java/lang/reflect/WildcardType
      20: invokeinterface #132,  1          // InterfaceMethod java/lang/reflect/WildcardType.getLowerBounds:()[Ljava/lang/reflect/Type;
      25: iconst_0
      26: aaload
      27: areturn
      28: aload_2
      29: areturn

  static boolean hasUnresolvableType(java.lang.reflect.Type);
    Code:
       0: aload_0
       1: instanceof    #37                 // class java/lang/Class
       4: ifeq          9
       7: iconst_0
       8: ireturn
       9: aload_0
      10: instanceof    #71                 // class java/lang/reflect/ParameterizedType
      13: ifeq          64
      16: aload_0
      17: checkcast     #71                 // class java/lang/reflect/ParameterizedType
      20: astore_1
      21: aload_1
      22: invokeinterface #121,  1          // InterfaceMethod java/lang/reflect/ParameterizedType.getActualTypeArguments:()[Ljava/lang/reflect/Type;
      27: astore_2
      28: aload_2
      29: arraylength
      30: istore_3
      31: iconst_0
      32: istore        4
      34: iload         4
      36: iload_3
      37: if_icmpge     62
      40: aload_2
      41: iload         4
      43: aaload
      44: astore        5
      46: aload         5
      48: invokestatic  #261                // Method hasUnresolvableType:(Ljava/lang/reflect/Type;)Z
      51: ifeq          56
      54: iconst_1
      55: ireturn
      56: iinc          4, 1
      59: goto          34
      62: iconst_0
      63: ireturn
      64: aload_0
      65: instanceof    #78                 // class java/lang/reflect/GenericArrayType
      68: ifeq          84
      71: aload_0
      72: checkcast     #78                 // class java/lang/reflect/GenericArrayType
      75: invokeinterface #80,  1           // InterfaceMethod java/lang/reflect/GenericArrayType.getGenericComponentType:()Ljava/lang/reflect/Type;
      80: invokestatic  #261                // Method hasUnresolvableType:(Ljava/lang/reflect/Type;)Z
      83: ireturn
      84: aload_0
      85: instanceof    #95                 // class java/lang/reflect/TypeVariable
      88: ifeq          93
      91: iconst_1
      92: ireturn
      93: aload_0
      94: instanceof    #97                 // class java/lang/reflect/WildcardType
      97: ifeq          102
     100: iconst_1
     101: ireturn
     102: aload_0
     103: ifnonnull     112
     106: ldc_w         #265                // String null
     109: goto          119
     112: aload_0
     113: invokevirtual #92                 // Method java/lang/Object.getClass:()Ljava/lang/Class;
     116: invokevirtual #110                // Method java/lang/Class.getName:()Ljava/lang/String;
     119: astore_1
     120: new           #19                 // class java/lang/IllegalArgumentException
     123: dup
     124: new           #21                 // class java/lang/StringBuilder
     127: dup
     128: invokespecial #23                 // Method java/lang/StringBuilder."<init>":()V
     131: ldc           #103                // String Expected a Class, ParameterizedType, or GenericArrayType, but <
     133: invokevirtual #24                 // Method java/lang/StringBuilder.append:(Ljava/lang/String;)Ljava/lang/StringBuilder;
     136: aload_0
     137: invokevirtual #105                // Method java/lang/StringBuilder.append:(Ljava/lang/Object;)Ljava/lang/StringBuilder;
     140: ldc           #108                // String > is of type
     142: invokevirtual #24                 // Method java/lang/StringBuilder.append:(Ljava/lang/String;)Ljava/lang/StringBuilder;
     145: aload_1
     146: invokevirtual #24                 // Method java/lang/StringBuilder.append:(Ljava/lang/String;)Ljava/lang/StringBuilder;
     149: invokevirtual #47                 // Method java/lang/StringBuilder.toString:()Ljava/lang/String;
     152: invokespecial #111                // Method java/lang/IllegalArgumentException."<init>":(Ljava/lang/String;)V
     155: athrow

  static void throwIfFatal(java.lang.Throwable);
    Code:
       0: aload_0
       1: instanceof    #267                // class java/lang/VirtualMachineError
       4: ifeq          12
       7: aload_0
       8: checkcast     #267                // class java/lang/VirtualMachineError
      11: athrow
      12: aload_0
      13: instanceof    #269                // class java/lang/ThreadDeath
      16: ifeq          24
      19: aload_0
      20: checkcast     #269                // class java/lang/ThreadDeath
      23: athrow
      24: aload_0
      25: instanceof    #271                // class java/lang/LinkageError
      28: ifeq          36
      31: aload_0
      32: checkcast     #271                // class java/lang/LinkageError
      35: athrow
      36: return

  static {};
    Code:
       0: iconst_0
       1: anewarray     #202                // class java/lang/reflect/Type
       4: putstatic     #207                // Field EMPTY_TYPE_ARRAY:[Ljava/lang/reflect/Type;
       7: return
}
