Compiled from "DefaultConstants.java"
public interface org.apache.dubbo.metrics.DefaultConstants {
  public static final java.lang.String METRIC_FILTER_EVENT;

  public static final java.lang.String METRIC_THROWABLE;

  public static final java.util.List<org.apache.dubbo.metrics.model.key.MetricsKeyWrapper> METHOD_LEVEL_KEYS;

  static {};
    Code:
       0: bipush        22
       2: anewarray     #1                  // class org/apache/dubbo/metrics/model/key/MetricsKeyWrapper
       5: dup
       6: iconst_0
       7: new           #1                  // class org/apache/dubbo/metrics/model/key/MetricsKeyWrapper
      10: dup
      11: getstatic     #2                  // Field org/apache/dubbo/metrics/model/key/MetricsKey.METRIC_REQUESTS:Lorg/apache/dubbo/metrics/model/key/MetricsKey;
      14: ldc           #4                  // String provider
      16: getstatic     #5                  // Field org/apache/dubbo/metrics/model/key/MetricsLevel.METHOD:Lorg/apache/dubbo/metrics/model/key/MetricsLevel;
      19: invokestatic  #6                  // Method org/apache/dubbo/metrics/model/key/MetricsPlaceValue.of:(Ljava/lang/String;Lorg/apache/dubbo/metrics/model/key/MetricsLevel;)Lorg/apache/dubbo/metrics/model/key/MetricsPlaceValue;
      22: invokespecial #7                  // Method org/apache/dubbo/metrics/model/key/MetricsKeyWrapper."<init>":(Lorg/apache/dubbo/metrics/model/key/MetricsKey;Lorg/apache/dubbo/metrics/model/key/MetricsPlaceValue;)V
      25: aastore
      26: dup
      27: iconst_1
      28: new           #1                  // class org/apache/dubbo/metrics/model/key/MetricsKeyWrapper
      31: dup
      32: getstatic     #2                  // Field org/apache/dubbo/metrics/model/key/MetricsKey.METRIC_REQUESTS:Lorg/apache/dubbo/metrics/model/key/MetricsKey;
      35: ldc           #8                  // String consumer
      37: getstatic     #5                  // Field org/apache/dubbo/metrics/model/key/MetricsLevel.METHOD:Lorg/apache/dubbo/metrics/model/key/MetricsLevel;
      40: invokestatic  #6                  // Method org/apache/dubbo/metrics/model/key/MetricsPlaceValue.of:(Ljava/lang/String;Lorg/apache/dubbo/metrics/model/key/MetricsLevel;)Lorg/apache/dubbo/metrics/model/key/MetricsPlaceValue;
      43: invokespecial #7                  // Method org/apache/dubbo/metrics/model/key/MetricsKeyWrapper."<init>":(Lorg/apache/dubbo/metrics/model/key/MetricsKey;Lorg/apache/dubbo/metrics/model/key/MetricsPlaceValue;)V
      46: aastore
      47: dup
      48: iconst_2
      49: new           #1                  // class org/apache/dubbo/metrics/model/key/MetricsKeyWrapper
      52: dup
      53: getstatic     #9                  // Field org/apache/dubbo/metrics/model/key/MetricsKey.METRIC_REQUESTS_PROCESSING:Lorg/apache/dubbo/metrics/model/key/MetricsKey;
      56: ldc           #4                  // String provider
      58: getstatic     #5                  // Field org/apache/dubbo/metrics/model/key/MetricsLevel.METHOD:Lorg/apache/dubbo/metrics/model/key/MetricsLevel;
      61: invokestatic  #6                  // Method org/apache/dubbo/metrics/model/key/MetricsPlaceValue.of:(Ljava/lang/String;Lorg/apache/dubbo/metrics/model/key/MetricsLevel;)Lorg/apache/dubbo/metrics/model/key/MetricsPlaceValue;
      64: invokespecial #7                  // Method org/apache/dubbo/metrics/model/key/MetricsKeyWrapper."<init>":(Lorg/apache/dubbo/metrics/model/key/MetricsKey;Lorg/apache/dubbo/metrics/model/key/MetricsPlaceValue;)V
      67: aastore
      68: dup
      69: iconst_3
      70: new           #1                  // class org/apache/dubbo/metrics/model/key/MetricsKeyWrapper
      73: dup
      74: getstatic     #9                  // Field org/apache/dubbo/metrics/model/key/MetricsKey.METRIC_REQUESTS_PROCESSING:Lorg/apache/dubbo/metrics/model/key/MetricsKey;
      77: ldc           #8                  // String consumer
      79: getstatic     #5                  // Field org/apache/dubbo/metrics/model/key/MetricsLevel.METHOD:Lorg/apache/dubbo/metrics/model/key/MetricsLevel;
      82: invokestatic  #6                  // Method org/apache/dubbo/metrics/model/key/MetricsPlaceValue.of:(Ljava/lang/String;Lorg/apache/dubbo/metrics/model/key/MetricsLevel;)Lorg/apache/dubbo/metrics/model/key/MetricsPlaceValue;
      85: invokespecial #7                  // Method org/apache/dubbo/metrics/model/key/MetricsKeyWrapper."<init>":(Lorg/apache/dubbo/metrics/model/key/MetricsKey;Lorg/apache/dubbo/metrics/model/key/MetricsPlaceValue;)V
      88: aastore
      89: dup
      90: iconst_4
      91: new           #1                  // class org/apache/dubbo/metrics/model/key/MetricsKeyWrapper
      94: dup
      95: getstatic     #10                 // Field org/apache/dubbo/metrics/model/key/MetricsKey.METRIC_REQUESTS_SUCCEED:Lorg/apache/dubbo/metrics/model/key/MetricsKey;
      98: ldc           #4                  // String provider
     100: getstatic     #5                  // Field org/apache/dubbo/metrics/model/key/MetricsLevel.METHOD:Lorg/apache/dubbo/metrics/model/key/MetricsLevel;
     103: invokestatic  #6                  // Method org/apache/dubbo/metrics/model/key/MetricsPlaceValue.of:(Ljava/lang/String;Lorg/apache/dubbo/metrics/model/key/MetricsLevel;)Lorg/apache/dubbo/metrics/model/key/MetricsPlaceValue;
     106: invokespecial #7                  // Method org/apache/dubbo/metrics/model/key/MetricsKeyWrapper."<init>":(Lorg/apache/dubbo/metrics/model/key/MetricsKey;Lorg/apache/dubbo/metrics/model/key/MetricsPlaceValue;)V
     109: aastore
     110: dup
     111: iconst_5
     112: new           #1                  // class org/apache/dubbo/metrics/model/key/MetricsKeyWrapper
     115: dup
     116: getstatic     #10                 // Field org/apache/dubbo/metrics/model/key/MetricsKey.METRIC_REQUESTS_SUCCEED:Lorg/apache/dubbo/metrics/model/key/MetricsKey;
     119: ldc           #8                  // String consumer
     121: getstatic     #5                  // Field org/apache/dubbo/metrics/model/key/MetricsLevel.METHOD:Lorg/apache/dubbo/metrics/model/key/MetricsLevel;
     124: invokestatic  #6                  // Method org/apache/dubbo/metrics/model/key/MetricsPlaceValue.of:(Ljava/lang/String;Lorg/apache/dubbo/metrics/model/key/MetricsLevel;)Lorg/apache/dubbo/metrics/model/key/MetricsPlaceValue;
     127: invokespecial #7                  // Method org/apache/dubbo/metrics/model/key/MetricsKeyWrapper."<init>":(Lorg/apache/dubbo/metrics/model/key/MetricsKey;Lorg/apache/dubbo/metrics/model/key/MetricsPlaceValue;)V
     130: aastore
     131: dup
     132: bipush        6
     134: new           #1                  // class org/apache/dubbo/metrics/model/key/MetricsKeyWrapper
     137: dup
     138: getstatic     #11                 // Field org/apache/dubbo/metrics/model/key/MetricsKey.METRIC_REQUEST_BUSINESS_FAILED:Lorg/apache/dubbo/metrics/model/key/MetricsKey;
     141: ldc           #4                  // String provider
     143: getstatic     #5                  // Field org/apache/dubbo/metrics/model/key/MetricsLevel.METHOD:Lorg/apache/dubbo/metrics/model/key/MetricsLevel;
     146: invokestatic  #6                  // Method org/apache/dubbo/metrics/model/key/MetricsPlaceValue.of:(Ljava/lang/String;Lorg/apache/dubbo/metrics/model/key/MetricsLevel;)Lorg/apache/dubbo/metrics/model/key/MetricsPlaceValue;
     149: invokespecial #7                  // Method org/apache/dubbo/metrics/model/key/MetricsKeyWrapper."<init>":(Lorg/apache/dubbo/metrics/model/key/MetricsKey;Lorg/apache/dubbo/metrics/model/key/MetricsPlaceValue;)V
     152: aastore
     153: dup
     154: bipush        7
     156: new           #1                  // class org/apache/dubbo/metrics/model/key/MetricsKeyWrapper
     159: dup
     160: getstatic     #11                 // Field org/apache/dubbo/metrics/model/key/MetricsKey.METRIC_REQUEST_BUSINESS_FAILED:Lorg/apache/dubbo/metrics/model/key/MetricsKey;
     163: ldc           #8                  // String consumer
     165: getstatic     #5                  // Field org/apache/dubbo/metrics/model/key/MetricsLevel.METHOD:Lorg/apache/dubbo/metrics/model/key/MetricsLevel;
     168: invokestatic  #6                  // Method org/apache/dubbo/metrics/model/key/MetricsPlaceValue.of:(Ljava/lang/String;Lorg/apache/dubbo/metrics/model/key/MetricsLevel;)Lorg/apache/dubbo/metrics/model/key/MetricsPlaceValue;
     171: invokespecial #7                  // Method org/apache/dubbo/metrics/model/key/MetricsKeyWrapper."<init>":(Lorg/apache/dubbo/metrics/model/key/MetricsKey;Lorg/apache/dubbo/metrics/model/key/MetricsPlaceValue;)V
     174: aastore
     175: dup
     176: bipush        8
     178: new           #1                  // class org/apache/dubbo/metrics/model/key/MetricsKeyWrapper
     181: dup
     182: getstatic     #12                 // Field org/apache/dubbo/metrics/model/key/MetricsKey.METRIC_REQUESTS_TIMEOUT:Lorg/apache/dubbo/metrics/model/key/MetricsKey;
     185: ldc           #4                  // String provider
     187: getstatic     #5                  // Field org/apache/dubbo/metrics/model/key/MetricsLevel.METHOD:Lorg/apache/dubbo/metrics/model/key/MetricsLevel;
     190: invokestatic  #6                  // Method org/apache/dubbo/metrics/model/key/MetricsPlaceValue.of:(Ljava/lang/String;Lorg/apache/dubbo/metrics/model/key/MetricsLevel;)Lorg/apache/dubbo/metrics/model/key/MetricsPlaceValue;
     193: invokespecial #7                  // Method org/apache/dubbo/metrics/model/key/MetricsKeyWrapper."<init>":(Lorg/apache/dubbo/metrics/model/key/MetricsKey;Lorg/apache/dubbo/metrics/model/key/MetricsPlaceValue;)V
     196: aastore
     197: dup
     198: bipush        9
     200: new           #1                  // class org/apache/dubbo/metrics/model/key/MetricsKeyWrapper
     203: dup
     204: getstatic     #12                 // Field org/apache/dubbo/metrics/model/key/MetricsKey.METRIC_REQUESTS_TIMEOUT:Lorg/apache/dubbo/metrics/model/key/MetricsKey;
     207: ldc           #8                  // String consumer
     209: getstatic     #5                  // Field org/apache/dubbo/metrics/model/key/MetricsLevel.METHOD:Lorg/apache/dubbo/metrics/model/key/MetricsLevel;
     212: invokestatic  #6                  // Method org/apache/dubbo/metrics/model/key/MetricsPlaceValue.of:(Ljava/lang/String;Lorg/apache/dubbo/metrics/model/key/MetricsLevel;)Lorg/apache/dubbo/metrics/model/key/MetricsPlaceValue;
     215: invokespecial #7                  // Method org/apache/dubbo/metrics/model/key/MetricsKeyWrapper."<init>":(Lorg/apache/dubbo/metrics/model/key/MetricsKey;Lorg/apache/dubbo/metrics/model/key/MetricsPlaceValue;)V
     218: aastore
     219: dup
     220: bipush        10
     222: new           #1                  // class org/apache/dubbo/metrics/model/key/MetricsKeyWrapper
     225: dup
     226: getstatic     #13                 // Field org/apache/dubbo/metrics/model/key/MetricsKey.METRIC_REQUESTS_LIMIT:Lorg/apache/dubbo/metrics/model/key/MetricsKey;
     229: ldc           #4                  // String provider
     231: getstatic     #5                  // Field org/apache/dubbo/metrics/model/key/MetricsLevel.METHOD:Lorg/apache/dubbo/metrics/model/key/MetricsLevel;
     234: invokestatic  #6                  // Method org/apache/dubbo/metrics/model/key/MetricsPlaceValue.of:(Ljava/lang/String;Lorg/apache/dubbo/metrics/model/key/MetricsLevel;)Lorg/apache/dubbo/metrics/model/key/MetricsPlaceValue;
     237: invokespecial #7                  // Method org/apache/dubbo/metrics/model/key/MetricsKeyWrapper."<init>":(Lorg/apache/dubbo/metrics/model/key/MetricsKey;Lorg/apache/dubbo/metrics/model/key/MetricsPlaceValue;)V
     240: aastore
     241: dup
     242: bipush        11
     244: new           #1                  // class org/apache/dubbo/metrics/model/key/MetricsKeyWrapper
     247: dup
     248: getstatic     #13                 // Field org/apache/dubbo/metrics/model/key/MetricsKey.METRIC_REQUESTS_LIMIT:Lorg/apache/dubbo/metrics/model/key/MetricsKey;
     251: ldc           #8                  // String consumer
     253: getstatic     #5                  // Field org/apache/dubbo/metrics/model/key/MetricsLevel.METHOD:Lorg/apache/dubbo/metrics/model/key/MetricsLevel;
     256: invokestatic  #6                  // Method org/apache/dubbo/metrics/model/key/MetricsPlaceValue.of:(Ljava/lang/String;Lorg/apache/dubbo/metrics/model/key/MetricsLevel;)Lorg/apache/dubbo/metrics/model/key/MetricsPlaceValue;
     259: invokespecial #7                  // Method org/apache/dubbo/metrics/model/key/MetricsKeyWrapper."<init>":(Lorg/apache/dubbo/metrics/model/key/MetricsKey;Lorg/apache/dubbo/metrics/model/key/MetricsPlaceValue;)V
     262: aastore
     263: dup
     264: bipush        12
     266: new           #1                  // class org/apache/dubbo/metrics/model/key/MetricsKeyWrapper
     269: dup
     270: getstatic     #14                 // Field org/apache/dubbo/metrics/model/key/MetricsKey.METRIC_REQUESTS_FAILED:Lorg/apache/dubbo/metrics/model/key/MetricsKey;
     273: ldc           #4                  // String provider
     275: getstatic     #5                  // Field org/apache/dubbo/metrics/model/key/MetricsLevel.METHOD:Lorg/apache/dubbo/metrics/model/key/MetricsLevel;
     278: invokestatic  #6                  // Method org/apache/dubbo/metrics/model/key/MetricsPlaceValue.of:(Ljava/lang/String;Lorg/apache/dubbo/metrics/model/key/MetricsLevel;)Lorg/apache/dubbo/metrics/model/key/MetricsPlaceValue;
     281: invokespecial #7                  // Method org/apache/dubbo/metrics/model/key/MetricsKeyWrapper."<init>":(Lorg/apache/dubbo/metrics/model/key/MetricsKey;Lorg/apache/dubbo/metrics/model/key/MetricsPlaceValue;)V
     284: aastore
     285: dup
     286: bipush        13
     288: new           #1                  // class org/apache/dubbo/metrics/model/key/MetricsKeyWrapper
     291: dup
     292: getstatic     #14                 // Field org/apache/dubbo/metrics/model/key/MetricsKey.METRIC_REQUESTS_FAILED:Lorg/apache/dubbo/metrics/model/key/MetricsKey;
     295: ldc           #8                  // String consumer
     297: getstatic     #5                  // Field org/apache/dubbo/metrics/model/key/MetricsLevel.METHOD:Lorg/apache/dubbo/metrics/model/key/MetricsLevel;
     300: invokestatic  #6                  // Method org/apache/dubbo/metrics/model/key/MetricsPlaceValue.of:(Ljava/lang/String;Lorg/apache/dubbo/metrics/model/key/MetricsLevel;)Lorg/apache/dubbo/metrics/model/key/MetricsPlaceValue;
     303: invokespecial #7                  // Method org/apache/dubbo/metrics/model/key/MetricsKeyWrapper."<init>":(Lorg/apache/dubbo/metrics/model/key/MetricsKey;Lorg/apache/dubbo/metrics/model/key/MetricsPlaceValue;)V
     306: aastore
     307: dup
     308: bipush        14
     310: new           #1                  // class org/apache/dubbo/metrics/model/key/MetricsKeyWrapper
     313: dup
     314: getstatic     #15                 // Field org/apache/dubbo/metrics/model/key/MetricsKey.METRIC_REQUESTS_TOTAL_FAILED:Lorg/apache/dubbo/metrics/model/key/MetricsKey;
     317: ldc           #4                  // String provider
     319: getstatic     #5                  // Field org/apache/dubbo/metrics/model/key/MetricsLevel.METHOD:Lorg/apache/dubbo/metrics/model/key/MetricsLevel;
     322: invokestatic  #6                  // Method org/apache/dubbo/metrics/model/key/MetricsPlaceValue.of:(Ljava/lang/String;Lorg/apache/dubbo/metrics/model/key/MetricsLevel;)Lorg/apache/dubbo/metrics/model/key/MetricsPlaceValue;
     325: invokespecial #7                  // Method org/apache/dubbo/metrics/model/key/MetricsKeyWrapper."<init>":(Lorg/apache/dubbo/metrics/model/key/MetricsKey;Lorg/apache/dubbo/metrics/model/key/MetricsPlaceValue;)V
     328: aastore
     329: dup
     330: bipush        15
     332: new           #1                  // class org/apache/dubbo/metrics/model/key/MetricsKeyWrapper
     335: dup
     336: getstatic     #15                 // Field org/apache/dubbo/metrics/model/key/MetricsKey.METRIC_REQUESTS_TOTAL_FAILED:Lorg/apache/dubbo/metrics/model/key/MetricsKey;
     339: ldc           #8                  // String consumer
     341: getstatic     #5                  // Field org/apache/dubbo/metrics/model/key/MetricsLevel.METHOD:Lorg/apache/dubbo/metrics/model/key/MetricsLevel;
     344: invokestatic  #6                  // Method org/apache/dubbo/metrics/model/key/MetricsPlaceValue.of:(Ljava/lang/String;Lorg/apache/dubbo/metrics/model/key/MetricsLevel;)Lorg/apache/dubbo/metrics/model/key/MetricsPlaceValue;
     347: invokespecial #7                  // Method org/apache/dubbo/metrics/model/key/MetricsKeyWrapper."<init>":(Lorg/apache/dubbo/metrics/model/key/MetricsKey;Lorg/apache/dubbo/metrics/model/key/MetricsPlaceValue;)V
     350: aastore
     351: dup
     352: bipush        16
     354: new           #1                  // class org/apache/dubbo/metrics/model/key/MetricsKeyWrapper
     357: dup
     358: getstatic     #16                 // Field org/apache/dubbo/metrics/model/key/MetricsKey.METRIC_REQUESTS_NETWORK_FAILED:Lorg/apache/dubbo/metrics/model/key/MetricsKey;
     361: ldc           #4                  // String provider
     363: getstatic     #5                  // Field org/apache/dubbo/metrics/model/key/MetricsLevel.METHOD:Lorg/apache/dubbo/metrics/model/key/MetricsLevel;
     366: invokestatic  #6                  // Method org/apache/dubbo/metrics/model/key/MetricsPlaceValue.of:(Ljava/lang/String;Lorg/apache/dubbo/metrics/model/key/MetricsLevel;)Lorg/apache/dubbo/metrics/model/key/MetricsPlaceValue;
     369: invokespecial #7                  // Method org/apache/dubbo/metrics/model/key/MetricsKeyWrapper."<init>":(Lorg/apache/dubbo/metrics/model/key/MetricsKey;Lorg/apache/dubbo/metrics/model/key/MetricsPlaceValue;)V
     372: aastore
     373: dup
     374: bipush        17
     376: new           #1                  // class org/apache/dubbo/metrics/model/key/MetricsKeyWrapper
     379: dup
     380: getstatic     #16                 // Field org/apache/dubbo/metrics/model/key/MetricsKey.METRIC_REQUESTS_NETWORK_FAILED:Lorg/apache/dubbo/metrics/model/key/MetricsKey;
     383: ldc           #8                  // String consumer
     385: getstatic     #5                  // Field org/apache/dubbo/metrics/model/key/MetricsLevel.METHOD:Lorg/apache/dubbo/metrics/model/key/MetricsLevel;
     388: invokestatic  #6                  // Method org/apache/dubbo/metrics/model/key/MetricsPlaceValue.of:(Ljava/lang/String;Lorg/apache/dubbo/metrics/model/key/MetricsLevel;)Lorg/apache/dubbo/metrics/model/key/MetricsPlaceValue;
     391: invokespecial #7                  // Method org/apache/dubbo/metrics/model/key/MetricsKeyWrapper."<init>":(Lorg/apache/dubbo/metrics/model/key/MetricsKey;Lorg/apache/dubbo/metrics/model/key/MetricsPlaceValue;)V
     394: aastore
     395: dup
     396: bipush        18
     398: new           #1                  // class org/apache/dubbo/metrics/model/key/MetricsKeyWrapper
     401: dup
     402: getstatic     #17                 // Field org/apache/dubbo/metrics/model/key/MetricsKey.METRIC_REQUESTS_SERVICE_UNAVAILABLE_FAILED:Lorg/apache/dubbo/metrics/model/key/MetricsKey;
     405: ldc           #4                  // String provider
     407: getstatic     #5                  // Field org/apache/dubbo/metrics/model/key/MetricsLevel.METHOD:Lorg/apache/dubbo/metrics/model/key/MetricsLevel;
     410: invokestatic  #6                  // Method org/apache/dubbo/metrics/model/key/MetricsPlaceValue.of:(Ljava/lang/String;Lorg/apache/dubbo/metrics/model/key/MetricsLevel;)Lorg/apache/dubbo/metrics/model/key/MetricsPlaceValue;
     413: invokespecial #7                  // Method org/apache/dubbo/metrics/model/key/MetricsKeyWrapper."<init>":(Lorg/apache/dubbo/metrics/model/key/MetricsKey;Lorg/apache/dubbo/metrics/model/key/MetricsPlaceValue;)V
     416: aastore
     417: dup
     418: bipush        19
     420: new           #1                  // class org/apache/dubbo/metrics/model/key/MetricsKeyWrapper
     423: dup
     424: getstatic     #17                 // Field org/apache/dubbo/metrics/model/key/MetricsKey.METRIC_REQUESTS_SERVICE_UNAVAILABLE_FAILED:Lorg/apache/dubbo/metrics/model/key/MetricsKey;
     427: ldc           #8                  // String consumer
     429: getstatic     #5                  // Field org/apache/dubbo/metrics/model/key/MetricsLevel.METHOD:Lorg/apache/dubbo/metrics/model/key/MetricsLevel;
     432: invokestatic  #6                  // Method org/apache/dubbo/metrics/model/key/MetricsPlaceValue.of:(Ljava/lang/String;Lorg/apache/dubbo/metrics/model/key/MetricsLevel;)Lorg/apache/dubbo/metrics/model/key/MetricsPlaceValue;
     435: invokespecial #7                  // Method org/apache/dubbo/metrics/model/key/MetricsKeyWrapper."<init>":(Lorg/apache/dubbo/metrics/model/key/MetricsKey;Lorg/apache/dubbo/metrics/model/key/MetricsPlaceValue;)V
     438: aastore
     439: dup
     440: bipush        20
     442: new           #1                  // class org/apache/dubbo/metrics/model/key/MetricsKeyWrapper
     445: dup
     446: getstatic     #18                 // Field org/apache/dubbo/metrics/model/key/MetricsKey.METRIC_REQUESTS_CODEC_FAILED:Lorg/apache/dubbo/metrics/model/key/MetricsKey;
     449: ldc           #4                  // String provider
     451: getstatic     #5                  // Field org/apache/dubbo/metrics/model/key/MetricsLevel.METHOD:Lorg/apache/dubbo/metrics/model/key/MetricsLevel;
     454: invokestatic  #6                  // Method org/apache/dubbo/metrics/model/key/MetricsPlaceValue.of:(Ljava/lang/String;Lorg/apache/dubbo/metrics/model/key/MetricsLevel;)Lorg/apache/dubbo/metrics/model/key/MetricsPlaceValue;
     457: invokespecial #7                  // Method org/apache/dubbo/metrics/model/key/MetricsKeyWrapper."<init>":(Lorg/apache/dubbo/metrics/model/key/MetricsKey;Lorg/apache/dubbo/metrics/model/key/MetricsPlaceValue;)V
     460: aastore
     461: dup
     462: bipush        21
     464: new           #1                  // class org/apache/dubbo/metrics/model/key/MetricsKeyWrapper
     467: dup
     468: getstatic     #18                 // Field org/apache/dubbo/metrics/model/key/MetricsKey.METRIC_REQUESTS_CODEC_FAILED:Lorg/apache/dubbo/metrics/model/key/MetricsKey;
     471: ldc           #8                  // String consumer
     473: getstatic     #5                  // Field org/apache/dubbo/metrics/model/key/MetricsLevel.METHOD:Lorg/apache/dubbo/metrics/model/key/MetricsLevel;
     476: invokestatic  #6                  // Method org/apache/dubbo/metrics/model/key/MetricsPlaceValue.of:(Ljava/lang/String;Lorg/apache/dubbo/metrics/model/key/MetricsLevel;)Lorg/apache/dubbo/metrics/model/key/MetricsPlaceValue;
     479: invokespecial #7                  // Method org/apache/dubbo/metrics/model/key/MetricsKeyWrapper."<init>":(Lorg/apache/dubbo/metrics/model/key/MetricsKey;Lorg/apache/dubbo/metrics/model/key/MetricsPlaceValue;)V
     482: aastore
     483: invokestatic  #19                 // Method java/util/Arrays.asList:([Ljava/lang/Object;)Ljava/util/List;
     486: putstatic     #20                 // Field METHOD_LEVEL_KEYS:Ljava/util/List;
     489: return
}
