Compiled from "NacosConfigServiceWrapper.java"
public class org.apache.dubbo.configcenter.support.nacos.NacosConfigServiceWrapper {
  private static final java.lang.String INNERCLASS_SYMBOL;

  private static final java.lang.String INNERCLASS_COMPATIBLE_SYMBOL;

  private static final long DEFAULT_TIMEOUT;

  private final com.alibaba.nacos.api.config.ConfigService configService;

  public org.apache.dubbo.configcenter.support.nacos.NacosConfigServiceWrapper(com.alibaba.nacos.api.config.ConfigService);
    Code:
       0: aload_0
       1: invokespecial #2                  // Method java/lang/Object."<init>":()V
       4: aload_0
       5: aload_1
       6: putfield      #3                  // Field configService:Lcom/alibaba/nacos/api/config/ConfigService;
       9: return

  public com.alibaba.nacos.api.config.ConfigService getConfigService();
    Code:
       0: aload_0
       1: getfield      #3                  // Field configService:Lcom/alibaba/nacos/api/config/ConfigService;
       4: areturn

  public void addListener(java.lang.String, java.lang.String, com.alibaba.nacos.api.config.listener.Listener) throws com.alibaba.nacos.api.exception.NacosException;
    Code:
       0: aload_0
       1: getfield      #3                  // Field configService:Lcom/alibaba/nacos/api/config/ConfigService;
       4: aload_0
       5: aload_1
       6: invokespecial #4                  // Method handleInnerSymbol:(Ljava/lang/String;)Ljava/lang/String;
       9: aload_0
      10: aload_2
      11: invokespecial #4                  // Method handleInnerSymbol:(Ljava/lang/String;)Ljava/lang/String;
      14: aload_3
      15: invokeinterface #5,  4            // InterfaceMethod com/alibaba/nacos/api/config/ConfigService.addListener:(Ljava/lang/String;Ljava/lang/String;Lcom/alibaba/nacos/api/config/listener/Listener;)V
      20: return

  public java.lang.String getConfig(java.lang.String, java.lang.String) throws com.alibaba.nacos.api.exception.NacosException;
    Code:
       0: aload_0
       1: getfield      #3                  // Field configService:Lcom/alibaba/nacos/api/config/ConfigService;
       4: aload_0
       5: aload_1
       6: invokespecial #4                  // Method handleInnerSymbol:(Ljava/lang/String;)Ljava/lang/String;
       9: aload_0
      10: aload_2
      11: invokespecial #4                  // Method handleInnerSymbol:(Ljava/lang/String;)Ljava/lang/String;
      14: ldc2_w        #7                  // long 3000l
      17: invokeinterface #9,  5            // InterfaceMethod com/alibaba/nacos/api/config/ConfigService.getConfig:(Ljava/lang/String;Ljava/lang/String;J)Ljava/lang/String;
      22: areturn

  public java.lang.String getConfig(java.lang.String, java.lang.String, long) throws com.alibaba.nacos.api.exception.NacosException;
    Code:
       0: aload_0
       1: getfield      #3                  // Field configService:Lcom/alibaba/nacos/api/config/ConfigService;
       4: aload_0
       5: aload_1
       6: invokespecial #4                  // Method handleInnerSymbol:(Ljava/lang/String;)Ljava/lang/String;
       9: aload_0
      10: aload_2
      11: invokespecial #4                  // Method handleInnerSymbol:(Ljava/lang/String;)Ljava/lang/String;
      14: lload_3
      15: invokeinterface #9,  5            // InterfaceMethod com/alibaba/nacos/api/config/ConfigService.getConfig:(Ljava/lang/String;Ljava/lang/String;J)Ljava/lang/String;
      20: areturn

  public boolean publishConfig(java.lang.String, java.lang.String, java.lang.String) throws com.alibaba.nacos.api.exception.NacosException;
    Code:
       0: aload_0
       1: getfield      #3                  // Field configService:Lcom/alibaba/nacos/api/config/ConfigService;
       4: aload_0
       5: aload_1
       6: invokespecial #4                  // Method handleInnerSymbol:(Ljava/lang/String;)Ljava/lang/String;
       9: aload_0
      10: aload_2
      11: invokespecial #4                  // Method handleInnerSymbol:(Ljava/lang/String;)Ljava/lang/String;
      14: aload_3
      15: invokeinterface #10,  4           // InterfaceMethod com/alibaba/nacos/api/config/ConfigService.publishConfig:(Ljava/lang/String;Ljava/lang/String;Ljava/lang/String;)Z
      20: ireturn

  public boolean publishConfigCas(java.lang.String, java.lang.String, java.lang.String, java.lang.String) throws com.alibaba.nacos.api.exception.NacosException;
    Code:
       0: aload_0
       1: getfield      #3                  // Field configService:Lcom/alibaba/nacos/api/config/ConfigService;
       4: aload_0
       5: aload_1
       6: invokespecial #4                  // Method handleInnerSymbol:(Ljava/lang/String;)Ljava/lang/String;
       9: aload_0
      10: aload_2
      11: invokespecial #4                  // Method handleInnerSymbol:(Ljava/lang/String;)Ljava/lang/String;
      14: aload_3
      15: aload         4
      17: invokeinterface #11,  5           // InterfaceMethod com/alibaba/nacos/api/config/ConfigService.publishConfigCas:(Ljava/lang/String;Ljava/lang/String;Ljava/lang/String;Ljava/lang/String;)Z
      22: ireturn

  public boolean removeConfig(java.lang.String, java.lang.String) throws com.alibaba.nacos.api.exception.NacosException;
    Code:
       0: aload_0
       1: getfield      #3                  // Field configService:Lcom/alibaba/nacos/api/config/ConfigService;
       4: aload_0
       5: aload_1
       6: invokespecial #4                  // Method handleInnerSymbol:(Ljava/lang/String;)Ljava/lang/String;
       9: aload_0
      10: aload_2
      11: invokespecial #4                  // Method handleInnerSymbol:(Ljava/lang/String;)Ljava/lang/String;
      14: invokeinterface #12,  3           // InterfaceMethod com/alibaba/nacos/api/config/ConfigService.removeConfig:(Ljava/lang/String;Ljava/lang/String;)Z
      19: ireturn

  public void shutdown() throws com.alibaba.nacos.api.exception.NacosException;
    Code:
       0: aload_0
       1: getfield      #3                  // Field configService:Lcom/alibaba/nacos/api/config/ConfigService;
       4: invokeinterface #13,  1           // InterfaceMethod com/alibaba/nacos/api/config/ConfigService.shutDown:()V
       9: return

  private java.lang.String handleInnerSymbol(java.lang.String);
    Code:
       0: aload_1
       1: ifnonnull     6
       4: aconst_null
       5: areturn
       6: aload_1
       7: ldc           #14                 // String $
       9: ldc           #15                 // String ___
      11: invokevirtual #16                 // Method java/lang/String.replace:(Ljava/lang/CharSequence;Ljava/lang/CharSequence;)Ljava/lang/String;
      14: bipush        47
      16: bipush        45
      18: invokevirtual #17                 // Method java/lang/String.replace:(CC)Ljava/lang/String;
      21: areturn
}
