Compiled from "NacosDynamicConfigurationFactory.java"
public class org.apache.dubbo.configcenter.support.nacos.NacosDynamicConfigurationFactory extends org.apache.dubbo.common.config.configcenter.AbstractDynamicConfigurationFactory {
  private org.apache.dubbo.rpc.model.ApplicationModel applicationModel;

  public org.apache.dubbo.configcenter.support.nacos.NacosDynamicConfigurationFactory(org.apache.dubbo.rpc.model.ApplicationModel);
    Code:
       0: aload_0
       1: invokespecial #1                  // Method org/apache/dubbo/common/config/configcenter/AbstractDynamicConfigurationFactory."<init>":()V
       4: aload_0
       5: aload_1
       6: putfield      #2                  // Field applicationModel:Lorg/apache/dubbo/rpc/model/ApplicationModel;
       9: return

  protected org.apache.dubbo.common.config.configcenter.DynamicConfiguration createDynamicConfiguration(org.apache.dubbo.common.URL);
    Code:
       0: aload_1
       1: astore_2
       2: ldc           #4                  // String dubbo
       4: aload_1
       5: ldc           #6                  // String namespace
       7: invokevirtual #7                  // Method org/apache/dubbo/common/URL.getParameter:(Ljava/lang/String;)Ljava/lang/String;
      10: invokevirtual #8                  // Method java/lang/String.equals:(Ljava/lang/Object;)Z
      13: ifeq          23
      16: aload_1
      17: ldc           #6                  // String namespace
      19: invokevirtual #9                  // Method org/apache/dubbo/common/URL.removeParameter:(Ljava/lang/String;)Lorg/apache/dubbo/common/URL;
      22: astore_2
      23: new           #10                 // class org/apache/dubbo/configcenter/support/nacos/NacosDynamicConfiguration
      26: dup
      27: aload_2
      28: aload_0
      29: getfield      #2                  // Field applicationModel:Lorg/apache/dubbo/rpc/model/ApplicationModel;
      32: invokespecial #11                 // Method org/apache/dubbo/configcenter/support/nacos/NacosDynamicConfiguration."<init>":(Lorg/apache/dubbo/common/URL;Lorg/apache/dubbo/rpc/model/ApplicationModel;)V
      35: areturn
}
