Compiled from "CallSite.java"
public class jadx.api.plugins.input.data.impl.CallSite implements jadx.api.plugins.input.data.ICallSite {
  private final java.util.List<jadx.api.plugins.input.data.annotations.EncodedValue> values;

  public jadx.api.plugins.input.data.impl.CallSite(java.util.List<jadx.api.plugins.input.data.annotations.EncodedValue>);
    Code:
       0: aload_0
       1: invokespecial #1                  // Method java/lang/Object."<init>":()V
       4: aload_0
       5: aload_1
       6: putfield      #2                  // Field values:Ljava/util/List;
       9: return

  public void load();
    Code:
       0: aload_0
       1: getfield      #2                  // Field values:Ljava/util/List;
       4: invokeinterface #3,  1            // InterfaceMethod java/util/List.iterator:()Ljava/util/Iterator;
       9: astore_1
      10: aload_1
      11: invokeinterface #4,  1            // InterfaceMethod java/util/Iterator.hasNext:()Z
      16: ifeq          98
      19: aload_1
      20: invokeinterface #5,  1            // InterfaceMethod java/util/Iterator.next:()Ljava/lang/Object;
      25: checkcast     #6                  // class jadx/api/plugins/input/data/annotations/EncodedValue
      28: astore_2
      29: getstatic     #7                  // Field jadx/api/plugins/input/data/impl/CallSite$1.$SwitchMap$jadx$api$plugins$input$data$annotations$EncodedType:[I
      32: aload_2
      33: invokevirtual #8                  // Method jadx/api/plugins/input/data/annotations/EncodedValue.getType:()Ljadx/api/plugins/input/data/annotations/EncodedType;
      36: invokevirtual #9                  // Method jadx/api/plugins/input/data/annotations/EncodedType.ordinal:()I
      39: iaload
      40: lookupswitch  { // 2
                     1: 68
                     2: 83
               default: 95
          }
      68: aload_2
      69: invokevirtual #10                 // Method jadx/api/plugins/input/data/annotations/EncodedValue.getValue:()Ljava/lang/Object;
      72: checkcast     #11                 // class jadx/api/plugins/input/data/IMethodHandle
      75: invokeinterface #12,  1           // InterfaceMethod jadx/api/plugins/input/data/IMethodHandle.load:()V
      80: goto          95
      83: aload_2
      84: invokevirtual #10                 // Method jadx/api/plugins/input/data/annotations/EncodedValue.getValue:()Ljava/lang/Object;
      87: checkcast     #13                 // class jadx/api/plugins/input/data/IMethodRef
      90: invokeinterface #14,  1           // InterfaceMethod jadx/api/plugins/input/data/IMethodRef.load:()V
      95: goto          10
      98: return

  public java.util.List<jadx.api.plugins.input.data.annotations.EncodedValue> getValues();
    Code:
       0: aload_0
       1: getfield      #2                  // Field values:Ljava/util/List;
       4: areturn

  public java.lang.String toString();
    Code:
       0: new           #15                 // class java/lang/StringBuilder
       3: dup
       4: invokespecial #16                 // Method java/lang/StringBuilder."<init>":()V
       7: ldc           #17                 // String CallSite{
       9: invokevirtual #18                 // Method java/lang/StringBuilder.append:(Ljava/lang/String;)Ljava/lang/StringBuilder;
      12: aload_0
      13: getfield      #2                  // Field values:Ljava/util/List;
      16: invokevirtual #19                 // Method java/lang/StringBuilder.append:(Ljava/lang/Object;)Ljava/lang/StringBuilder;
      19: bipush        125
      21: invokevirtual #20                 // Method java/lang/StringBuilder.append:(C)Ljava/lang/StringBuilder;
      24: invokevirtual #21                 // Method java/lang/StringBuilder.toString:()Ljava/lang/String;
      27: areturn
}
