Compiled from "CallSite.java"
class jadx.api.plugins.input.data.impl.CallSite$1 {
  static final int[] $SwitchMap$jadx$api$plugins$input$data$annotations$EncodedType;

  static {};
    Code:
       0: invokestatic  #1                  // Method jadx/api/plugins/input/data/annotations/EncodedType.values:()[Ljadx/api/plugins/input/data/annotations/EncodedType;
       3: arraylength
       4: newarray       int
       6: putstatic     #2                  // Field $SwitchMap$jadx$api$plugins$input$data$annotations$EncodedType:[I
       9: getstatic     #2                  // Field $SwitchMap$jadx$api$plugins$input$data$annotations$EncodedType:[I
      12: getstatic     #3                  // Field jadx/api/plugins/input/data/annotations/EncodedType.ENCODED_METHOD_HANDLE:Ljadx/api/plugins/input/data/annotations/EncodedType;
      15: invokevirtual #4                  // Method jadx/api/plugins/input/data/annotations/EncodedType.ordinal:()I
      18: iconst_1
      19: iastore
      20: goto          24
      23: astore_0
      24: getstatic     #2                  // Field $SwitchMap$jadx$api$plugins$input$data$annotations$EncodedType:[I
      27: getstatic     #6                  // Field jadx/api/plugins/input/data/annotations/EncodedType.ENCODED_METHOD:Ljadx/api/plugins/input/data/annotations/EncodedType;
      30: invokevirtual #4                  // Method jadx/api/plugins/input/data/annotations/EncodedType.ordinal:()I
      33: iconst_2
      34: iastore
      35: goto          39
      38: astore_0
      39: return
    Exception table:
       from    to  target type
           9    20    23   Class java/lang/NoSuchFieldError
          24    35    38   Class java/lang/NoSuchFieldError
}
