Compiled from "DebugInfo.java"
public class jadx.api.plugins.input.data.impl.DebugInfo implements jadx.api.plugins.input.data.IDebugInfo {
  private final java.util.Map<java.lang.Integer, java.lang.Integer> sourceLineMap;

  private final java.util.List<jadx.api.plugins.input.data.ILocalVar> localVars;

  public jadx.api.plugins.input.data.impl.DebugInfo(java.util.Map<java.lang.Integer, java.lang.Integer>, java.util.List<jadx.api.plugins.input.data.ILocalVar>);
    Code:
       0: aload_0
       1: invokespecial #1                  // Method java/lang/Object."<init>":()V
       4: aload_0
       5: aload_1
       6: putfield      #2                  // Field sourceLineMap:Ljava/util/Map;
       9: aload_0
      10: aload_2
      11: putfield      #3                  // Field localVars:Ljava/util/List;
      14: return

  public java.util.Map<java.lang.Integer, java.lang.Integer> getSourceLineMapping();
    Code:
       0: aload_0
       1: getfield      #2                  // Field sourceLineMap:Ljava/util/Map;
       4: areturn

  public java.util.List<jadx.api.plugins.input.data.ILocalVar> getLocalVars();
    Code:
       0: aload_0
       1: getfield      #3                  // Field localVars:Ljava/util/List;
       4: areturn

  public java.lang.String toString();
    Code:
       0: new           #4                  // class java/lang/StringBuilder
       3: dup
       4: invokespecial #5                  // Method java/lang/StringBuilder."<init>":()V
       7: ldc           #6                  // String DebugInfo{lines=
       9: invokevirtual #7                  // Method java/lang/StringBuilder.append:(Ljava/lang/String;)Ljava/lang/StringBuilder;
      12: aload_0
      13: getfield      #2                  // Field sourceLineMap:Ljava/util/Map;
      16: invokevirtual #8                  // Method java/lang/StringBuilder.append:(Ljava/lang/Object;)Ljava/lang/StringBuilder;
      19: ldc           #9                  // String , localVars=
      21: invokevirtual #7                  // Method java/lang/StringBuilder.append:(Ljava/lang/String;)Ljava/lang/StringBuilder;
      24: aload_0
      25: getfield      #3                  // Field localVars:Ljava/util/List;
      28: invokevirtual #8                  // Method java/lang/StringBuilder.append:(Ljava/lang/Object;)Ljava/lang/StringBuilder;
      31: bipush        125
      33: invokevirtual #10                 // Method java/lang/StringBuilder.append:(C)Ljava/lang/StringBuilder;
      36: invokevirtual #11                 // Method java/lang/StringBuilder.toString:()Ljava/lang/String;
      39: areturn
}
