Compiled from "EmptyLoadResult.java"
public class jadx.api.plugins.input.data.impl.EmptyLoadResult implements jadx.api.plugins.input.data.ILoadResult {
  public static final jadx.api.plugins.input.data.impl.EmptyLoadResult INSTANCE;

  public jadx.api.plugins.input.data.impl.EmptyLoadResult();
    Code:
       0: aload_0
       1: invokespecial #1                  // Method java/lang/Object."<init>":()V
       4: return

  public boolean isEmpty();
    Code:
       0: iconst_1
       1: ireturn

  public void visitClasses(java.util.function.Consumer<jadx.api.plugins.input.data.IClassData>);
    Code:
       0: return

  public void visitResources(java.util.function.Consumer<jadx.api.plugins.input.data.IResourceData>);
    Code:
       0: return

  public void close() throws java.io.IOException;
    Code:
       0: return

  static {};
    Code:
       0: new           #2                  // class jadx/api/plugins/input/data/impl/EmptyLoadResult
       3: dup
       4: invokespecial #3                  // Method "<init>":()V
       7: putstatic     #4                  // Field INSTANCE:Ljadx/api/plugins/input/data/impl/EmptyLoadResult;
      10: return
}
