Compiled from "ListConsumer.java"
public class jadx.api.plugins.input.data.impl.ListConsumer<T, R> implements jadx.api.plugins.input.data.ISeqConsumer<T> {
  private final java.util.function.Function<T, R> convert;

  private java.util.List<R> list;

  public jadx.api.plugins.input.data.impl.ListConsumer(java.util.function.Function<T, R>);
    Code:
       0: aload_0
       1: invokespecial #1                  // Method java/lang/Object."<init>":()V
       4: aload_0
       5: aload_1
       6: putfield      #2                  // Field convert:Ljava/util/function/Function;
       9: return

  public void init(int);
    Code:
       0: aload_0
       1: iload_1
       2: ifne          11
       5: invokestatic  #3                  // Method java/util/Collections.emptyList:()Ljava/util/List;
       8: goto          19
      11: new           #4                  // class java/util/ArrayList
      14: dup
      15: iload_1
      16: invokespecial #5                  // Method java/util/ArrayList."<init>":(I)V
      19: putfield      #6                  // Field list:Ljava/util/List;
      22: return

  public void accept(T);
    Code:
       0: aload_0
       1: getfield      #6                  // Field list:Ljava/util/List;
       4: aload_0
       5: getfield      #2                  // Field convert:Ljava/util/function/Function;
       8: aload_1
       9: invokeinterface #7,  2            // InterfaceMethod java/util/function/Function.apply:(Ljava/lang/Object;)Ljava/lang/Object;
      14: invokeinterface #8,  2            // InterfaceMethod java/util/List.add:(Ljava/lang/Object;)Z
      19: pop
      20: return

  public java.util.List<R> getResult();
    Code:
       0: aload_0
       1: getfield      #6                  // Field list:Ljava/util/List;
       4: ifnonnull     11
       7: invokestatic  #3                  // Method java/util/Collections.emptyList:()Ljava/util/List;
      10: areturn
      11: aload_0
      12: getfield      #6                  // Field list:Ljava/util/List;
      15: areturn
}
