Compiled from "MethodRefHandle.java"
public class jadx.api.plugins.input.data.impl.MethodRefHandle implements jadx.api.plugins.input.data.IMethodHandle {
  private final jadx.api.plugins.input.data.MethodHandleType type;

  private final jadx.api.plugins.input.data.IMethodRef methodRef;

  public jadx.api.plugins.input.data.impl.MethodRefHandle(jadx.api.plugins.input.data.MethodHandleType, jadx.api.plugins.input.data.IMethodRef);
    Code:
       0: aload_0
       1: invokespecial #1                  // Method java/lang/Object."<init>":()V
       4: aload_0
       5: aload_1
       6: putfield      #2                  // Field type:Ljadx/api/plugins/input/data/MethodHandleType;
       9: aload_0
      10: aload_2
      11: putfield      #3                  // Field methodRef:Ljadx/api/plugins/input/data/IMethodRef;
      14: return

  public jadx.api.plugins.input.data.MethodHandleType getType();
    Code:
       0: aload_0
       1: getfield      #2                  // Field type:Ljadx/api/plugins/input/data/MethodHandleType;
       4: areturn

  public jadx.api.plugins.input.data.IMethodRef getMethodRef();
    Code:
       0: aload_0
       1: getfield      #3                  // Field methodRef:Ljadx/api/plugins/input/data/IMethodRef;
       4: areturn

  public jadx.api.plugins.input.data.IFieldData getFieldRef();
    Code:
       0: aconst_null
       1: areturn

  public void load();
    Code:
       0: aload_0
       1: getfield      #3                  // Field methodRef:Ljadx/api/plugins/input/data/IMethodRef;
       4: invokeinterface #4,  1            // InterfaceMethod jadx/api/plugins/input/data/IMethodRef.load:()V
       9: return

  public java.lang.String toString();
    Code:
       0: new           #5                  // class java/lang/StringBuilder
       3: dup
       4: invokespecial #6                  // Method java/lang/StringBuilder."<init>":()V
       7: aload_0
       8: getfield      #2                  // Field type:Ljadx/api/plugins/input/data/MethodHandleType;
      11: invokevirtual #7                  // Method java/lang/StringBuilder.append:(Ljava/lang/Object;)Ljava/lang/StringBuilder;
      14: ldc           #8                  // String :
      16: invokevirtual #9                  // Method java/lang/StringBuilder.append:(Ljava/lang/String;)Ljava/lang/StringBuilder;
      19: aload_0
      20: getfield      #3                  // Field methodRef:Ljadx/api/plugins/input/data/IMethodRef;
      23: invokevirtual #7                  // Method java/lang/StringBuilder.append:(Ljava/lang/Object;)Ljava/lang/StringBuilder;
      26: invokevirtual #10                 // Method java/lang/StringBuilder.toString:()Ljava/lang/String;
      29: areturn

  public jadx.api.plugins.input.data.IFieldRef getFieldRef();
    Code:
       0: aload_0
       1: invokevirtual #11                 // Method getFieldRef:()Ljadx/api/plugins/input/data/IFieldData;
       4: areturn
}
