Compiled from "TryData.java"
public class jadx.api.plugins.input.data.impl.TryData implements jadx.api.plugins.input.data.ITry {
  private final int startOffset;

  private final int endOffset;

  private final jadx.api.plugins.input.data.ICatch catchHandler;

  public jadx.api.plugins.input.data.impl.TryData(int, int, jadx.api.plugins.input.data.ICatch);
    Code:
       0: aload_0
       1: invokespecial #1                  // Method java/lang/Object."<init>":()V
       4: aload_0
       5: iload_1
       6: putfield      #2                  // Field startOffset:I
       9: aload_0
      10: iload_2
      11: putfield      #3                  // Field endOffset:I
      14: aload_0
      15: aload_3
      16: putfield      #4                  // Field catchHandler:Ljadx/api/plugins/input/data/ICatch;
      19: return

  public jadx.api.plugins.input.data.ICatch getCatch();
    Code:
       0: aload_0
       1: getfield      #4                  // Field catchHandler:Ljadx/api/plugins/input/data/ICatch;
       4: areturn

  public int getStartOffset();
    Code:
       0: aload_0
       1: getfield      #2                  // Field startOffset:I
       4: ireturn

  public int getEndOffset();
    Code:
       0: aload_0
       1: getfield      #3                  // Field endOffset:I
       4: ireturn

  public java.lang.String toString();
    Code:
       0: new           #5                  // class java/lang/StringBuilder
       3: dup
       4: invokespecial #6                  // Method java/lang/StringBuilder."<init>":()V
       7: ldc           #7                  // String Try{
       9: invokevirtual #8                  // Method java/lang/StringBuilder.append:(Ljava/lang/String;)Ljava/lang/StringBuilder;
      12: aload_0
      13: getfield      #2                  // Field startOffset:I
      16: invokestatic  #9                  // Method jadx/api/plugins/utils/Utils.formatOffset:(I)Ljava/lang/String;
      19: invokevirtual #8                  // Method java/lang/StringBuilder.append:(Ljava/lang/String;)Ljava/lang/StringBuilder;
      22: ldc           #10                 // String  -
      24: invokevirtual #8                  // Method java/lang/StringBuilder.append:(Ljava/lang/String;)Ljava/lang/StringBuilder;
      27: aload_0
      28: getfield      #3                  // Field endOffset:I
      31: invokestatic  #9                  // Method jadx/api/plugins/utils/Utils.formatOffset:(I)Ljava/lang/String;
      34: invokevirtual #8                  // Method java/lang/StringBuilder.append:(Ljava/lang/String;)Ljava/lang/StringBuilder;
      37: ldc           #11                 // String :
      39: invokevirtual #8                  // Method java/lang/StringBuilder.append:(Ljava/lang/String;)Ljava/lang/StringBuilder;
      42: aload_0
      43: getfield      #4                  // Field catchHandler:Ljadx/api/plugins/input/data/ICatch;
      46: invokevirtual #12                 // Method java/lang/StringBuilder.append:(Ljava/lang/Object;)Ljava/lang/StringBuilder;
      49: bipush        125
      51: invokevirtual #13                 // Method java/lang/StringBuilder.append:(C)Ljava/lang/StringBuilder;
      54: invokevirtual #14                 // Method java/lang/StringBuilder.toString:()Ljava/lang/String;
      57: areturn
}
