Compiled from "MetadataReport.java"
public interface org.apache.dubbo.metadata.report.MetadataReport {
  public abstract void storeProviderMetadata(org.apache.dubbo.metadata.report.identifier.MetadataIdentifier, org.apache.dubbo.metadata.definition.model.ServiceDefinition);

  public abstract java.lang.String getServiceDefinition(org.apache.dubbo.metadata.report.identifier.MetadataIdentifier);

  public default void publishAppMetadata(org.apache.dubbo.metadata.report.identifier.SubscriberMetadataIdentifier, org.apache.dubbo.metadata.MetadataInfo);
    Code:
       0: return

  public default void unPublishAppMetadata(org.apache.dubbo.metadata.report.identifier.SubscriberMetadataIdentifier, org.apache.dubbo.metadata.MetadataInfo);
    Code:
       0: return

  public default org.apache.dubbo.metadata.MetadataInfo getAppMetadata(org.apache.dubbo.metadata.report.identifier.SubscriberMetadataIdentifier, java.util.Map<java.lang.String, java.lang.String>);
    Code:
       0: aconst_null
       1: areturn

  public abstract void storeConsumerMetadata(org.apache.dubbo.metadata.report.identifier.MetadataIdentifier, java.util.Map<java.lang.String, java.lang.String>);

  public abstract java.util.List<java.lang.String> getExportedURLs(org.apache.dubbo.metadata.report.identifier.ServiceMetadataIdentifier);

  public abstract void destroy();

  public abstract void saveServiceMetadata(org.apache.dubbo.metadata.report.identifier.ServiceMetadataIdentifier, org.apache.dubbo.common.URL);

  public abstract void removeServiceMetadata(org.apache.dubbo.metadata.report.identifier.ServiceMetadataIdentifier);

  public abstract void saveSubscribedData(org.apache.dubbo.metadata.report.identifier.SubscriberMetadataIdentifier, java.util.Set<java.lang.String>);

  public abstract java.util.List<java.lang.String> getSubscribedURLs(org.apache.dubbo.metadata.report.identifier.SubscriberMetadataIdentifier);

  public default org.apache.dubbo.common.config.configcenter.ConfigItem getConfigItem(java.lang.String, java.lang.String);
    Code:
       0: new           #1                  // class org/apache/dubbo/common/config/configcenter/ConfigItem
       3: dup
       4: invokespecial #2                  // Method org/apache/dubbo/common/config/configcenter/ConfigItem."<init>":()V
       7: areturn

  public default boolean registerServiceAppMapping(java.lang.String, java.lang.String, java.lang.String, java.lang.Object);
    Code:
       0: iconst_0
       1: ireturn

  public default boolean registerServiceAppMapping(java.lang.String, java.lang.String, org.apache.dubbo.common.URL);
    Code:
       0: iconst_0
       1: ireturn

  public default void removeServiceAppMappingListener(java.lang.String, org.apache.dubbo.metadata.MappingListener);
    Code:
       0: return

  public default java.util.Set<java.lang.String> getServiceAppMapping(java.lang.String, org.apache.dubbo.metadata.MappingListener, org.apache.dubbo.common.URL);
    Code:
       0: invokestatic  #3                  // Method java/util/Collections.emptySet:()Ljava/util/Set;
       3: areturn

  public default java.util.Set<java.lang.String> getServiceAppMapping(java.lang.String, org.apache.dubbo.common.URL);
    Code:
       0: invokestatic  #3                  // Method java/util/Collections.emptySet:()Ljava/util/Set;
       3: areturn

  public abstract boolean shouldReportDefinition();

  public abstract boolean shouldReportMetadata();
}
