Compiled from "HttpWebServiceMessageSenderBuilder.java"
public class org.springframework.boot.webservices.client.HttpWebServiceMessageSenderBuilder {
  private java.time.Duration connectTimeout;

  private java.time.Duration readTimeout;

  private org.springframework.boot.ssl.SslBundle sslBundle;

  private java.util.function.Function<org.springframework.boot.web.client.ClientHttpRequestFactorySettings, org.springframework.http.client.ClientHttpRequestFactory> requestFactory;

  public org.springframework.boot.webservices.client.HttpWebServiceMessageSenderBuilder();
    Code:
       0: aload_0
       1: invokespecial #1                  // Method java/lang/Object."<init>":()V
       4: return

  public org.springframework.boot.webservices.client.HttpWebServiceMessageSenderBuilder setConnectTimeout(java.time.Duration);
    Code:
       0: aload_0
       1: aload_1
       2: putfield      #7                  // Field connectTimeout:Ljava/time/Duration;
       5: aload_0
       6: areturn

  public org.springframework.boot.webservices.client.HttpWebServiceMessageSenderBuilder setReadTimeout(java.time.Duration);
    Code:
       0: aload_0
       1: aload_1
       2: putfield      #13                 // Field readTimeout:Ljava/time/Duration;
       5: aload_0
       6: areturn

  public org.springframework.boot.webservices.client.HttpWebServiceMessageSenderBuilder sslBundle(org.springframework.boot.ssl.SslBundle);
    Code:
       0: aload_0
       1: aload_1
       2: putfield      #16                 // Field sslBundle:Lorg/springframework/boot/ssl/SslBundle;
       5: aload_0
       6: areturn

  public org.springframework.boot.webservices.client.HttpWebServiceMessageSenderBuilder requestFactory(java.util.function.Supplier<org.springframework.http.client.ClientHttpRequestFactory>);
    Code:
       0: aload_1
       1: ldc           #20                 // String RequestFactorySupplier must not be null
       3: invokestatic  #22                 // Method org/springframework/util/Assert.notNull:(Ljava/lang/Object;Ljava/lang/String;)V
       6: aload_0
       7: aload_1
       8: invokedynamic #28,  0             // InvokeDynamic #0:apply:(Ljava/util/function/Supplier;)Ljava/util/function/Function;
      13: putfield      #32                 // Field requestFactory:Ljava/util/function/Function;
      16: aload_0
      17: areturn

  public org.springframework.boot.webservices.client.HttpWebServiceMessageSenderBuilder requestFactory(java.util.function.Function<org.springframework.boot.web.client.ClientHttpRequestFactorySettings, org.springframework.http.client.ClientHttpRequestFactory>);
    Code:
       0: aload_1
       1: ldc           #36                 // String RequestFactoryFunction must not be null
       3: invokestatic  #22                 // Method org/springframework/util/Assert.notNull:(Ljava/lang/Object;Ljava/lang/String;)V
       6: aload_0
       7: aload_1
       8: putfield      #32                 // Field requestFactory:Ljava/util/function/Function;
      11: aload_0
      12: areturn

  public org.springframework.ws.transport.WebServiceMessageSender build();
    Code:
       0: new           #38                 // class org/springframework/ws/transport/http/ClientHttpRequestMessageSender
       3: dup
       4: aload_0
       5: invokevirtual #40                 // Method getRequestFactory:()Lorg/springframework/http/client/ClientHttpRequestFactory;
       8: invokespecial #44                 // Method org/springframework/ws/transport/http/ClientHttpRequestMessageSender."<init>":(Lorg/springframework/http/client/ClientHttpRequestFactory;)V
      11: areturn

  private org.springframework.http.client.ClientHttpRequestFactory getRequestFactory();
    Code:
       0: new           #47                 // class org/springframework/boot/web/client/ClientHttpRequestFactorySettings
       3: dup
       4: aload_0
       5: getfield      #7                  // Field connectTimeout:Ljava/time/Duration;
       8: aload_0
       9: getfield      #13                 // Field readTimeout:Ljava/time/Duration;
      12: aconst_null
      13: aload_0
      14: getfield      #16                 // Field sslBundle:Lorg/springframework/boot/ssl/SslBundle;
      17: invokespecial #49                 // Method org/springframework/boot/web/client/ClientHttpRequestFactorySettings."<init>":(Ljava/time/Duration;Ljava/time/Duration;Ljava/lang/Boolean;Lorg/springframework/boot/ssl/SslBundle;)V
      20: astore_1
      21: aload_0
      22: getfield      #32                 // Field requestFactory:Ljava/util/function/Function;
      25: ifnull        44
      28: aload_0
      29: getfield      #32                 // Field requestFactory:Ljava/util/function/Function;
      32: aload_1
      33: invokeinterface #52,  2           // InterfaceMethod java/util/function/Function.apply:(Ljava/lang/Object;)Ljava/lang/Object;
      38: checkcast     #57                 // class org/springframework/http/client/ClientHttpRequestFactory
      41: goto          48
      44: aload_1
      45: invokestatic  #59                 // Method org/springframework/boot/web/client/ClientHttpRequestFactories.get:(Lorg/springframework/boot/web/client/ClientHttpRequestFactorySettings;)Lorg/springframework/http/client/ClientHttpRequestFactory;
      48: areturn

  private static org.springframework.http.client.ClientHttpRequestFactory lambda$requestFactory$0(java.util.function.Supplier, org.springframework.boot.web.client.ClientHttpRequestFactorySettings);
    Code:
       0: aload_0
       1: aload_1
       2: invokestatic  #65                 // Method org/springframework/boot/web/client/ClientHttpRequestFactories.get:(Ljava/util/function/Supplier;Lorg/springframework/boot/web/client/ClientHttpRequestFactorySettings;)Lorg/springframework/http/client/ClientHttpRequestFactory;
       5: areturn
}
