Compiled from "WebServiceTemplateBuilder.java"
final class org.springframework.boot.webservices.client.WebServiceTemplateBuilder$FaultMessageResolverCustomizer implements org.springframework.boot.webservices.client.WebServiceTemplateCustomizer {
  private final org.springframework.ws.client.core.FaultMessageResolver faultMessageResolver;

  private org.springframework.boot.webservices.client.WebServiceTemplateBuilder$FaultMessageResolverCustomizer(org.springframework.ws.client.core.FaultMessageResolver);
    Code:
       0: aload_0
       1: invokespecial #1                  // Method java/lang/Object."<init>":()V
       4: aload_0
       5: aload_1
       6: putfield      #7                  // Field faultMessageResolver:Lorg/springframework/ws/client/core/FaultMessageResolver;
       9: return

  public void customize(org.springframework.ws.client.core.WebServiceTemplate);
    Code:
       0: aload_1
       1: aload_0
       2: getfield      #7                  // Field faultMessageResolver:Lorg/springframework/ws/client/core/FaultMessageResolver;
       5: invokevirtual #13                 // Method org/springframework/ws/client/core/WebServiceTemplate.setFaultMessageResolver:(Lorg/springframework/ws/client/core/FaultMessageResolver;)V
       8: return
}
