Compiled from "BackpressureKind.java"
public final class io.reactivex.rxjava3.annotations.BackpressureKind extends java.lang.Enum<io.reactivex.rxjava3.annotations.BackpressureKind> {
  public static final io.reactivex.rxjava3.annotations.BackpressureKind PASS_THROUGH;

  public static final io.reactivex.rxjava3.annotations.BackpressureKind FULL;

  public static final io.reactivex.rxjava3.annotations.BackpressureKind SPECIAL;

  public static final io.reactivex.rxjava3.annotations.BackpressureKind UNBOUNDED_IN;

  public static final io.reactivex.rxjava3.annotations.BackpressureKind ERROR;

  public static final io.reactivex.rxjava3.annotations.BackpressureKind NONE;

  private static final io.reactivex.rxjava3.annotations.BackpressureKind[] $VALUES;

  public static io.reactivex.rxjava3.annotations.BackpressureKind[] values();
    Code:
       0: getstatic     #1                  // Field $VALUES:[Lio/reactivex/rxjava3/annotations/BackpressureKind;
       3: invokevirtual #2                  // Method "[Lio/reactivex/rxjava3/annotations/BackpressureKind;".clone:()Ljava/lang/Object;
       6: checkcast     #3                  // class "[Lio/reactivex/rxjava3/annotations/BackpressureKind;"
       9: areturn

  public static io.reactivex.rxjava3.annotations.BackpressureKind valueOf(java.lang.String);
    Code:
       0: ldc           #4                  // class io/reactivex/rxjava3/annotations/BackpressureKind
       2: aload_0
       3: invokestatic  #5                  // Method java/lang/Enum.valueOf:(Ljava/lang/Class;Ljava/lang/String;)Ljava/lang/Enum;
       6: checkcast     #4                  // class io/reactivex/rxjava3/annotations/BackpressureKind
       9: areturn

  private io.reactivex.rxjava3.annotations.BackpressureKind();
    Code:
       0: aload_0
       1: aload_1
       2: iload_2
       3: invokespecial #6                  // Method java/lang/Enum."<init>":(Ljava/lang/String;I)V
       6: return

  static {};
    Code:
       0: new           #4                  // class io/reactivex/rxjava3/annotations/BackpressureKind
       3: dup
       4: ldc           #7                  // String PASS_THROUGH
       6: iconst_0
       7: invokespecial #8                  // Method "<init>":(Ljava/lang/String;I)V
      10: putstatic     #9                  // Field PASS_THROUGH:Lio/reactivex/rxjava3/annotations/BackpressureKind;
      13: new           #4                  // class io/reactivex/rxjava3/annotations/BackpressureKind
      16: dup
      17: ldc           #10                 // String FULL
      19: iconst_1
      20: invokespecial #8                  // Method "<init>":(Ljava/lang/String;I)V
      23: putstatic     #11                 // Field FULL:Lio/reactivex/rxjava3/annotations/BackpressureKind;
      26: new           #4                  // class io/reactivex/rxjava3/annotations/BackpressureKind
      29: dup
      30: ldc           #12                 // String SPECIAL
      32: iconst_2
      33: invokespecial #8                  // Method "<init>":(Ljava/lang/String;I)V
      36: putstatic     #13                 // Field SPECIAL:Lio/reactivex/rxjava3/annotations/BackpressureKind;
      39: new           #4                  // class io/reactivex/rxjava3/annotations/BackpressureKind
      42: dup
      43: ldc           #14                 // String UNBOUNDED_IN
      45: iconst_3
      46: invokespecial #8                  // Method "<init>":(Ljava/lang/String;I)V
      49: putstatic     #15                 // Field UNBOUNDED_IN:Lio/reactivex/rxjava3/annotations/BackpressureKind;
      52: new           #4                  // class io/reactivex/rxjava3/annotations/BackpressureKind
      55: dup
      56: ldc           #16                 // String ERROR
      58: iconst_4
      59: invokespecial #8                  // Method "<init>":(Ljava/lang/String;I)V
      62: putstatic     #17                 // Field ERROR:Lio/reactivex/rxjava3/annotations/BackpressureKind;
      65: new           #4                  // class io/reactivex/rxjava3/annotations/BackpressureKind
      68: dup
      69: ldc           #18                 // String NONE
      71: iconst_5
      72: invokespecial #8                  // Method "<init>":(Ljava/lang/String;I)V
      75: putstatic     #19                 // Field NONE:Lio/reactivex/rxjava3/annotations/BackpressureKind;
      78: bipush        6
      80: anewarray     #4                  // class io/reactivex/rxjava3/annotations/BackpressureKind
      83: dup
      84: iconst_0
      85: getstatic     #9                  // Field PASS_THROUGH:Lio/reactivex/rxjava3/annotations/BackpressureKind;
      88: aastore
      89: dup
      90: iconst_1
      91: getstatic     #11                 // Field FULL:Lio/reactivex/rxjava3/annotations/BackpressureKind;
      94: aastore
      95: dup
      96: iconst_2
      97: getstatic     #13                 // Field SPECIAL:Lio/reactivex/rxjava3/annotations/BackpressureKind;
     100: aastore
     101: dup
     102: iconst_3
     103: getstatic     #15                 // Field UNBOUNDED_IN:Lio/reactivex/rxjava3/annotations/BackpressureKind;
     106: aastore
     107: dup
     108: iconst_4
     109: getstatic     #17                 // Field ERROR:Lio/reactivex/rxjava3/annotations/BackpressureKind;
     112: aastore
     113: dup
     114: iconst_5
     115: getstatic     #19                 // Field NONE:Lio/reactivex/rxjava3/annotations/BackpressureKind;
     118: aastore
     119: putstatic     #1                  // Field $VALUES:[Lio/reactivex/rxjava3/annotations/BackpressureKind;
     122: return
}
