Compiled from "AbstractPortUnificationServer.java"
public abstract class org.apache.dubbo.remoting.api.pu.AbstractPortUnificationServer extends org.apache.dubbo.remoting.transport.AbstractServer {
  private final java.util.List<org.apache.dubbo.remoting.api.WireProtocol> protocols;

  private final java.util.Map<java.lang.String, org.apache.dubbo.common.URL> supportedUrls;

  private final java.util.Map<java.lang.String, org.apache.dubbo.remoting.ChannelHandler> supportedHandlers;

  public org.apache.dubbo.remoting.api.pu.AbstractPortUnificationServer(org.apache.dubbo.common.URL, org.apache.dubbo.remoting.ChannelHandler) throws org.apache.dubbo.remoting.RemotingException;
    Code:
       0: aload_0
       1: aload_1
       2: aload_2
       3: invokespecial #1                  // Method org/apache/dubbo/remoting/transport/AbstractServer."<init>":(Lorg/apache/dubbo/common/URL;Lorg/apache/dubbo/remoting/ChannelHandler;)V
       6: aload_0
       7: new           #2                  // class java/util/concurrent/ConcurrentHashMap
      10: dup
      11: invokespecial #3                  // Method java/util/concurrent/ConcurrentHashMap."<init>":()V
      14: putfield      #4                  // Field supportedUrls:Ljava/util/Map;
      17: aload_0
      18: new           #2                  // class java/util/concurrent/ConcurrentHashMap
      21: dup
      22: invokespecial #3                  // Method java/util/concurrent/ConcurrentHashMap."<init>":()V
      25: putfield      #5                  // Field supportedHandlers:Ljava/util/Map;
      28: aload_0
      29: aload_1
      30: invokevirtual #6                  // Method org/apache/dubbo/common/URL.getOrDefaultFrameworkModel:()Lorg/apache/dubbo/rpc/model/FrameworkModel;
      33: ldc           #7                  // class org/apache/dubbo/remoting/api/WireProtocol
      35: invokevirtual #8                  // Method org/apache/dubbo/rpc/model/FrameworkModel.getExtensionLoader:(Ljava/lang/Class;)Lorg/apache/dubbo/common/extension/ExtensionLoader;
      38: aload_1
      39: iconst_0
      40: anewarray     #9                  // class java/lang/String
      43: invokevirtual #10                 // Method org/apache/dubbo/common/extension/ExtensionLoader.getActivateExtension:(Lorg/apache/dubbo/common/URL;[Ljava/lang/String;)Ljava/util/List;
      46: putfield      #11                 // Field protocols:Ljava/util/List;
      49: return

  public java.util.List<org.apache.dubbo.remoting.api.WireProtocol> getProtocols();
    Code:
       0: aload_0
       1: getfield      #11                 // Field protocols:Ljava/util/List;
       4: areturn

  public void addSupportedProtocol(org.apache.dubbo.common.URL, org.apache.dubbo.remoting.ChannelHandler);
    Code:
       0: aload_0
       1: getfield      #4                  // Field supportedUrls:Ljava/util/Map;
       4: aload_1
       5: invokevirtual #12                 // Method org/apache/dubbo/common/URL.getProtocol:()Ljava/lang/String;
       8: aload_1
       9: invokeinterface #13,  3           // InterfaceMethod java/util/Map.put:(Ljava/lang/Object;Ljava/lang/Object;)Ljava/lang/Object;
      14: pop
      15: aload_0
      16: getfield      #5                  // Field supportedHandlers:Ljava/util/Map;
      19: aload_1
      20: invokevirtual #12                 // Method org/apache/dubbo/common/URL.getProtocol:()Ljava/lang/String;
      23: aload_2
      24: invokeinterface #13,  3           // InterfaceMethod java/util/Map.put:(Ljava/lang/Object;Ljava/lang/Object;)Ljava/lang/Object;
      29: pop
      30: return

  protected java.util.Map<java.lang.String, org.apache.dubbo.common.URL> getSupportedUrls();
    Code:
       0: aload_0
       1: getfield      #4                  // Field supportedUrls:Ljava/util/Map;
       4: areturn

  public java.util.Map<java.lang.String, org.apache.dubbo.remoting.ChannelHandler> getSupportedHandlers();
    Code:
       0: aload_0
       1: getfield      #5                  // Field supportedHandlers:Ljava/util/Map;
       4: areturn
}
