Compiled from "ChannelHandlerPretender.java"
public class org.apache.dubbo.remoting.api.pu.ChannelHandlerPretender extends org.apache.dubbo.remoting.transport.ChannelHandlerAdapter {
  private final java.lang.Object realHandler;

  public org.apache.dubbo.remoting.api.pu.ChannelHandlerPretender(java.lang.Object);
    Code:
       0: aload_0
       1: invokespecial #1                  // Method org/apache/dubbo/remoting/transport/ChannelHandlerAdapter."<init>":()V
       4: aload_0
       5: aload_1
       6: putfield      #2                  // Field realHandler:Ljava/lang/Object;
       9: return

  public java.lang.Object getRealHandler();
    Code:
       0: aload_0
       1: getfield      #2                  // Field realHandler:Ljava/lang/Object;
       4: areturn
}
