Compiled from "DefaultPuHandler.java"
public class org.apache.dubbo.remoting.api.pu.DefaultPuHandler implements org.apache.dubbo.remoting.ChannelHandler {
  public org.apache.dubbo.remoting.api.pu.DefaultPuHandler();
    Code:
       0: aload_0
       1: invokespecial #1                  // Method java/lang/Object."<init>":()V
       4: return

  public void connected(org.apache.dubbo.remoting.Channel) throws org.apache.dubbo.remoting.RemotingException;
    Code:
       0: return

  public void disconnected(org.apache.dubbo.remoting.Channel) throws org.apache.dubbo.remoting.RemotingException;
    Code:
       0: return

  public void sent(org.apache.dubbo.remoting.Channel, java.lang.Object) throws org.apache.dubbo.remoting.RemotingException;
    Code:
       0: return

  public void received(org.apache.dubbo.remoting.Channel, java.lang.Object) throws org.apache.dubbo.remoting.RemotingException;
    Code:
       0: return

  public void caught(org.apache.dubbo.remoting.Channel, java.lang.Throwable) throws org.apache.dubbo.remoting.RemotingException;
    Code:
       0: return
}
