Compiled from "Schedulers.java"
final class io.reactivex.rxjava3.schedulers.Schedulers$SingleHolder {
  static final io.reactivex.rxjava3.core.Scheduler DEFAULT;

  io.reactivex.rxjava3.schedulers.Schedulers$SingleHolder();
    Code:
       0: aload_0
       1: invokespecial #1                  // Method java/lang/Object."<init>":()V
       4: return

  static {};
    Code:
       0: new           #2                  // class io/reactivex/rxjava3/internal/schedulers/SingleScheduler
       3: dup
       4: invokespecial #3                  // Method io/reactivex/rxjava3/internal/schedulers/SingleScheduler."<init>":()V
       7: putstatic     #4                  // Field DEFAULT:Lio/reactivex/rxjava3/core/Scheduler;
      10: return
}
