Compiled from "Schedulers.java"
final class io.reactivex.rxjava3.schedulers.Schedulers$IOTask implements io.reactivex.rxjava3.functions.Supplier<io.reactivex.rxjava3.core.Scheduler> {
  io.reactivex.rxjava3.schedulers.Schedulers$IOTask();
    Code:
       0: aload_0
       1: invokespecial #1                  // Method java/lang/Object."<init>":()V
       4: return

  public io.reactivex.rxjava3.core.Scheduler get();
    Code:
       0: getstatic     #2                  // Field io/reactivex/rxjava3/schedulers/Schedulers$IoHolder.DEFAULT:Lio/reactivex/rxjava3/core/Scheduler;
       3: areturn

  public java.lang.Object get() throws java.lang.Throwable;
    Code:
       0: aload_0
       1: invokevirtual #3                  // Method get:()Lio/reactivex/rxjava3/core/Scheduler;
       4: areturn
}
