Compiled from "Schedulers.java"
public final class io.reactivex.rxjava3.schedulers.Schedulers {
  static final io.reactivex.rxjava3.core.Scheduler SINGLE;

  static final io.reactivex.rxjava3.core.Scheduler COMPUTATION;

  static final io.reactivex.rxjava3.core.Scheduler IO;

  static final io.reactivex.rxjava3.core.Scheduler TRAMPOLINE;

  static final io.reactivex.rxjava3.core.Scheduler NEW_THREAD;

  private io.reactivex.rxjava3.schedulers.Schedulers();
    Code:
       0: aload_0
       1: invokespecial #1                  // Method java/lang/Object."<init>":()V
       4: new           #2                  // class java/lang/IllegalStateException
       7: dup
       8: ldc           #3                  // String No instances!
      10: invokespecial #4                  // Method java/lang/IllegalStateException."<init>":(Ljava/lang/String;)V
      13: athrow

  public static io.reactivex.rxjava3.core.Scheduler computation();
    Code:
       0: getstatic     #5                  // Field COMPUTATION:Lio/reactivex/rxjava3/core/Scheduler;
       3: invokestatic  #6                  // Method io/reactivex/rxjava3/plugins/RxJavaPlugins.onComputationScheduler:(Lio/reactivex/rxjava3/core/Scheduler;)Lio/reactivex/rxjava3/core/Scheduler;
       6: areturn

  public static io.reactivex.rxjava3.core.Scheduler io();
    Code:
       0: getstatic     #7                  // Field IO:Lio/reactivex/rxjava3/core/Scheduler;
       3: invokestatic  #8                  // Method io/reactivex/rxjava3/plugins/RxJavaPlugins.onIoScheduler:(Lio/reactivex/rxjava3/core/Scheduler;)Lio/reactivex/rxjava3/core/Scheduler;
       6: areturn

  public static io.reactivex.rxjava3.core.Scheduler trampoline();
    Code:
       0: getstatic     #9                  // Field TRAMPOLINE:Lio/reactivex/rxjava3/core/Scheduler;
       3: areturn

  public static io.reactivex.rxjava3.core.Scheduler newThread();
    Code:
       0: getstatic     #10                 // Field NEW_THREAD:Lio/reactivex/rxjava3/core/Scheduler;
       3: invokestatic  #11                 // Method io/reactivex/rxjava3/plugins/RxJavaPlugins.onNewThreadScheduler:(Lio/reactivex/rxjava3/core/Scheduler;)Lio/reactivex/rxjava3/core/Scheduler;
       6: areturn

  public static io.reactivex.rxjava3.core.Scheduler single();
    Code:
       0: getstatic     #12                 // Field SINGLE:Lio/reactivex/rxjava3/core/Scheduler;
       3: invokestatic  #13                 // Method io/reactivex/rxjava3/plugins/RxJavaPlugins.onSingleScheduler:(Lio/reactivex/rxjava3/core/Scheduler;)Lio/reactivex/rxjava3/core/Scheduler;
       6: areturn

  public static io.reactivex.rxjava3.core.Scheduler from(java.util.concurrent.Executor);
    Code:
       0: aload_0
       1: iconst_0
       2: iconst_0
       3: invokestatic  #14                 // Method from:(Ljava/util/concurrent/Executor;ZZ)Lio/reactivex/rxjava3/core/Scheduler;
       6: areturn

  public static io.reactivex.rxjava3.core.Scheduler from(java.util.concurrent.Executor, boolean);
    Code:
       0: aload_0
       1: iload_1
       2: iconst_0
       3: invokestatic  #14                 // Method from:(Ljava/util/concurrent/Executor;ZZ)Lio/reactivex/rxjava3/core/Scheduler;
       6: areturn

  public static io.reactivex.rxjava3.core.Scheduler from(java.util.concurrent.Executor, boolean, boolean);
    Code:
       0: aload_0
       1: iload_1
       2: iload_2
       3: invokestatic  #15                 // Method io/reactivex/rxjava3/plugins/RxJavaPlugins.createExecutorScheduler:(Ljava/util/concurrent/Executor;ZZ)Lio/reactivex/rxjava3/core/Scheduler;
       6: areturn

  public static void shutdown();
    Code:
       0: invokestatic  #16                 // Method computation:()Lio/reactivex/rxjava3/core/Scheduler;
       3: invokevirtual #17                 // Method io/reactivex/rxjava3/core/Scheduler.shutdown:()V
       6: invokestatic  #18                 // Method io:()Lio/reactivex/rxjava3/core/Scheduler;
       9: invokevirtual #17                 // Method io/reactivex/rxjava3/core/Scheduler.shutdown:()V
      12: invokestatic  #19                 // Method newThread:()Lio/reactivex/rxjava3/core/Scheduler;
      15: invokevirtual #17                 // Method io/reactivex/rxjava3/core/Scheduler.shutdown:()V
      18: invokestatic  #20                 // Method single:()Lio/reactivex/rxjava3/core/Scheduler;
      21: invokevirtual #17                 // Method io/reactivex/rxjava3/core/Scheduler.shutdown:()V
      24: invokestatic  #21                 // Method trampoline:()Lio/reactivex/rxjava3/core/Scheduler;
      27: invokevirtual #17                 // Method io/reactivex/rxjava3/core/Scheduler.shutdown:()V
      30: return

  public static void start();
    Code:
       0: invokestatic  #16                 // Method computation:()Lio/reactivex/rxjava3/core/Scheduler;
       3: invokevirtual #22                 // Method io/reactivex/rxjava3/core/Scheduler.start:()V
       6: invokestatic  #18                 // Method io:()Lio/reactivex/rxjava3/core/Scheduler;
       9: invokevirtual #22                 // Method io/reactivex/rxjava3/core/Scheduler.start:()V
      12: invokestatic  #19                 // Method newThread:()Lio/reactivex/rxjava3/core/Scheduler;
      15: invokevirtual #22                 // Method io/reactivex/rxjava3/core/Scheduler.start:()V
      18: invokestatic  #20                 // Method single:()Lio/reactivex/rxjava3/core/Scheduler;
      21: invokevirtual #22                 // Method io/reactivex/rxjava3/core/Scheduler.start:()V
      24: invokestatic  #21                 // Method trampoline:()Lio/reactivex/rxjava3/core/Scheduler;
      27: invokevirtual #22                 // Method io/reactivex/rxjava3/core/Scheduler.start:()V
      30: return

  static {};
    Code:
       0: new           #23                 // class io/reactivex/rxjava3/schedulers/Schedulers$SingleTask
       3: dup
       4: invokespecial #24                 // Method io/reactivex/rxjava3/schedulers/Schedulers$SingleTask."<init>":()V
       7: invokestatic  #25                 // Method io/reactivex/rxjava3/plugins/RxJavaPlugins.initSingleScheduler:(Lio/reactivex/rxjava3/functions/Supplier;)Lio/reactivex/rxjava3/core/Scheduler;
      10: putstatic     #12                 // Field SINGLE:Lio/reactivex/rxjava3/core/Scheduler;
      13: new           #26                 // class io/reactivex/rxjava3/schedulers/Schedulers$ComputationTask
      16: dup
      17: invokespecial #27                 // Method io/reactivex/rxjava3/schedulers/Schedulers$ComputationTask."<init>":()V
      20: invokestatic  #28                 // Method io/reactivex/rxjava3/plugins/RxJavaPlugins.initComputationScheduler:(Lio/reactivex/rxjava3/functions/Supplier;)Lio/reactivex/rxjava3/core/Scheduler;
      23: putstatic     #5                  // Field COMPUTATION:Lio/reactivex/rxjava3/core/Scheduler;
      26: new           #29                 // class io/reactivex/rxjava3/schedulers/Schedulers$IOTask
      29: dup
      30: invokespecial #30                 // Method io/reactivex/rxjava3/schedulers/Schedulers$IOTask."<init>":()V
      33: invokestatic  #31                 // Method io/reactivex/rxjava3/plugins/RxJavaPlugins.initIoScheduler:(Lio/reactivex/rxjava3/functions/Supplier;)Lio/reactivex/rxjava3/core/Scheduler;
      36: putstatic     #7                  // Field IO:Lio/reactivex/rxjava3/core/Scheduler;
      39: invokestatic  #32                 // Method io/reactivex/rxjava3/internal/schedulers/TrampolineScheduler.instance:()Lio/reactivex/rxjava3/internal/schedulers/TrampolineScheduler;
      42: putstatic     #9                  // Field TRAMPOLINE:Lio/reactivex/rxjava3/core/Scheduler;
      45: new           #33                 // class io/reactivex/rxjava3/schedulers/Schedulers$NewThreadTask
      48: dup
      49: invokespecial #34                 // Method io/reactivex/rxjava3/schedulers/Schedulers$NewThreadTask."<init>":()V
      52: invokestatic  #35                 // Method io/reactivex/rxjava3/plugins/RxJavaPlugins.initNewThreadScheduler:(Lio/reactivex/rxjava3/functions/Supplier;)Lio/reactivex/rxjava3/core/Scheduler;
      55: putstatic     #10                 // Field NEW_THREAD:Lio/reactivex/rxjava3/core/Scheduler;
      58: return
}
