Compiled from "TestScheduler.java"
final class io.reactivex.rxjava3.schedulers.TestScheduler$TimedRunnable implements java.lang.Comparable<io.reactivex.rxjava3.schedulers.TestScheduler$TimedRunnable> {
  final long time;

  final java.lang.Runnable run;

  final io.reactivex.rxjava3.schedulers.TestScheduler$TestWorker scheduler;

  final long count;

  io.reactivex.rxjava3.schedulers.TestScheduler$TimedRunnable(io.reactivex.rxjava3.schedulers.TestScheduler$TestWorker, long, java.lang.Runnable, long);
    Code:
       0: aload_0
       1: invokespecial #1                  // Method java/lang/Object."<init>":()V
       4: aload_0
       5: lload_2
       6: putfield      #2                  // Field time:J
       9: aload_0
      10: aload         4
      12: putfield      #3                  // Field run:Ljava/lang/Runnable;
      15: aload_0
      16: aload_1
      17: putfield      #4                  // Field scheduler:Lio/reactivex/rxjava3/schedulers/TestScheduler$TestWorker;
      20: aload_0
      21: lload         5
      23: putfield      #5                  // Field count:J
      26: return

  public java.lang.String toString();
    Code:
       0: ldc           #6                  // String TimedRunnable(time = %d, run = %s)
       2: iconst_2
       3: anewarray     #7                  // class java/lang/Object
       6: dup
       7: iconst_0
       8: aload_0
       9: getfield      #2                  // Field time:J
      12: invokestatic  #8                  // Method java/lang/Long.valueOf:(J)Ljava/lang/Long;
      15: aastore
      16: dup
      17: iconst_1
      18: aload_0
      19: getfield      #3                  // Field run:Ljava/lang/Runnable;
      22: invokevirtual #9                  // Method java/lang/Object.toString:()Ljava/lang/String;
      25: aastore
      26: invokestatic  #10                 // Method java/lang/String.format:(Ljava/lang/String;[Ljava/lang/Object;)Ljava/lang/String;
      29: areturn

  public int compareTo(io.reactivex.rxjava3.schedulers.TestScheduler$TimedRunnable);
    Code:
       0: aload_0
       1: getfield      #2                  // Field time:J
       4: aload_1
       5: getfield      #2                  // Field time:J
       8: lcmp
       9: ifne          24
      12: aload_0
      13: getfield      #5                  // Field count:J
      16: aload_1
      17: getfield      #5                  // Field count:J
      20: invokestatic  #11                 // Method java/lang/Long.compare:(JJ)I
      23: ireturn
      24: aload_0
      25: getfield      #2                  // Field time:J
      28: aload_1
      29: getfield      #2                  // Field time:J
      32: invokestatic  #11                 // Method java/lang/Long.compare:(JJ)I
      35: ireturn

  public int compareTo(java.lang.Object);
    Code:
       0: aload_0
       1: aload_1
       2: checkcast     #12                 // class io/reactivex/rxjava3/schedulers/TestScheduler$TimedRunnable
       5: invokevirtual #13                 // Method compareTo:(Lio/reactivex/rxjava3/schedulers/TestScheduler$TimedRunnable;)I
       8: ireturn
}
