Compiled from "TestScheduler.java"
public final class io.reactivex.rxjava3.schedulers.TestScheduler extends io.reactivex.rxjava3.core.Scheduler {
  final java.util.Queue<io.reactivex.rxjava3.schedulers.TestScheduler$TimedRunnable> queue;

  final boolean useOnScheduleHook;

  long counter;

  volatile long time;

  public io.reactivex.rxjava3.schedulers.TestScheduler();
    Code:
       0: aload_0
       1: iconst_0
       2: invokespecial #1                  // Method "<init>":(Z)V
       5: return

  public io.reactivex.rxjava3.schedulers.TestScheduler(boolean);
    Code:
       0: aload_0
       1: invokespecial #2                  // Method io/reactivex/rxjava3/core/Scheduler."<init>":()V
       4: aload_0
       5: new           #3                  // class java/util/concurrent/PriorityBlockingQueue
       8: dup
       9: bipush        11
      11: invokespecial #4                  // Method java/util/concurrent/PriorityBlockingQueue."<init>":(I)V
      14: putfield      #5                  // Field queue:Ljava/util/Queue;
      17: aload_0
      18: iload_1
      19: putfield      #6                  // Field useOnScheduleHook:Z
      22: return

  public io.reactivex.rxjava3.schedulers.TestScheduler(long, java.util.concurrent.TimeUnit);
    Code:
       0: aload_0
       1: lload_1
       2: aload_3
       3: iconst_0
       4: invokespecial #7                  // Method "<init>":(JLjava/util/concurrent/TimeUnit;Z)V
       7: return

  public io.reactivex.rxjava3.schedulers.TestScheduler(long, java.util.concurrent.TimeUnit, boolean);
    Code:
       0: aload_0
       1: invokespecial #2                  // Method io/reactivex/rxjava3/core/Scheduler."<init>":()V
       4: aload_0
       5: new           #3                  // class java/util/concurrent/PriorityBlockingQueue
       8: dup
       9: bipush        11
      11: invokespecial #4                  // Method java/util/concurrent/PriorityBlockingQueue."<init>":(I)V
      14: putfield      #5                  // Field queue:Ljava/util/Queue;
      17: aload_0
      18: aload_3
      19: lload_1
      20: invokevirtual #8                  // Method java/util/concurrent/TimeUnit.toNanos:(J)J
      23: putfield      #9                  // Field time:J
      26: aload_0
      27: iload         4
      29: putfield      #6                  // Field useOnScheduleHook:Z
      32: return

  public long now(java.util.concurrent.TimeUnit);
    Code:
       0: aload_1
       1: aload_0
       2: getfield      #9                  // Field time:J
       5: getstatic     #10                 // Field java/util/concurrent/TimeUnit.NANOSECONDS:Ljava/util/concurrent/TimeUnit;
       8: invokevirtual #11                 // Method java/util/concurrent/TimeUnit.convert:(JLjava/util/concurrent/TimeUnit;)J
      11: lreturn

  public void advanceTimeBy(long, java.util.concurrent.TimeUnit);
    Code:
       0: aload_0
       1: aload_0
       2: getfield      #9                  // Field time:J
       5: aload_3
       6: lload_1
       7: invokevirtual #8                  // Method java/util/concurrent/TimeUnit.toNanos:(J)J
      10: ladd
      11: getstatic     #10                 // Field java/util/concurrent/TimeUnit.NANOSECONDS:Ljava/util/concurrent/TimeUnit;
      14: invokevirtual #12                 // Method advanceTimeTo:(JLjava/util/concurrent/TimeUnit;)V
      17: return

  public void advanceTimeTo(long, java.util.concurrent.TimeUnit);
    Code:
       0: aload_3
       1: lload_1
       2: invokevirtual #8                  // Method java/util/concurrent/TimeUnit.toNanos:(J)J
       5: lstore        4
       7: aload_0
       8: lload         4
      10: invokespecial #13                 // Method triggerActions:(J)V
      13: return

  public void triggerActions();
    Code:
       0: aload_0
       1: aload_0
       2: getfield      #9                  // Field time:J
       5: invokespecial #13                 // Method triggerActions:(J)V
       8: return

  private void triggerActions(long);
    Code:
       0: aload_0
       1: getfield      #5                  // Field queue:Ljava/util/Queue;
       4: invokeinterface #14,  1           // InterfaceMethod java/util/Queue.peek:()Ljava/lang/Object;
       9: checkcast     #15                 // class io/reactivex/rxjava3/schedulers/TestScheduler$TimedRunnable
      12: astore_3
      13: aload_3
      14: ifnull        86
      17: aload_3
      18: getfield      #16                 // Field io/reactivex/rxjava3/schedulers/TestScheduler$TimedRunnable.time:J
      21: lload_1
      22: lcmp
      23: ifle          29
      26: goto          86
      29: aload_0
      30: aload_3
      31: getfield      #16                 // Field io/reactivex/rxjava3/schedulers/TestScheduler$TimedRunnable.time:J
      34: lconst_0
      35: lcmp
      36: ifne          46
      39: aload_0
      40: getfield      #9                  // Field time:J
      43: goto          50
      46: aload_3
      47: getfield      #16                 // Field io/reactivex/rxjava3/schedulers/TestScheduler$TimedRunnable.time:J
      50: putfield      #9                  // Field time:J
      53: aload_0
      54: getfield      #5                  // Field queue:Ljava/util/Queue;
      57: aload_3
      58: invokeinterface #17,  2           // InterfaceMethod java/util/Queue.remove:(Ljava/lang/Object;)Z
      63: pop
      64: aload_3
      65: getfield      #18                 // Field io/reactivex/rxjava3/schedulers/TestScheduler$TimedRunnable.scheduler:Lio/reactivex/rxjava3/schedulers/TestScheduler$TestWorker;
      68: getfield      #19                 // Field io/reactivex/rxjava3/schedulers/TestScheduler$TestWorker.disposed:Z
      71: ifne          83
      74: aload_3
      75: getfield      #20                 // Field io/reactivex/rxjava3/schedulers/TestScheduler$TimedRunnable.run:Ljava/lang/Runnable;
      78: invokeinterface #21,  1           // InterfaceMethod java/lang/Runnable.run:()V
      83: goto          0
      86: aload_0
      87: lload_1
      88: putfield      #9                  // Field time:J
      91: return

  public io.reactivex.rxjava3.core.Scheduler$Worker createWorker();
    Code:
       0: new           #22                 // class io/reactivex/rxjava3/schedulers/TestScheduler$TestWorker
       3: dup
       4: aload_0
       5: invokespecial #23                 // Method io/reactivex/rxjava3/schedulers/TestScheduler$TestWorker."<init>":(Lio/reactivex/rxjava3/schedulers/TestScheduler;)V
       8: areturn
}
