Compiled from "TestScheduler.java"
final class io.reactivex.rxjava3.schedulers.TestScheduler$TestWorker$QueueRemove extends java.util.concurrent.atomic.AtomicReference<io.reactivex.rxjava3.schedulers.TestScheduler$TimedRunnable> implements io.reactivex.rxjava3.disposables.Disposable {
  private static final long serialVersionUID;

  final io.reactivex.rxjava3.schedulers.TestScheduler$TestWorker this$1;

  io.reactivex.rxjava3.schedulers.TestScheduler$TestWorker$QueueRemove(io.reactivex.rxjava3.schedulers.TestScheduler$TestWorker, io.reactivex.rxjava3.schedulers.TestScheduler$TimedRunnable);
    Code:
       0: aload_0
       1: aload_1
       2: putfield      #1                  // Field this$1:Lio/reactivex/rxjava3/schedulers/TestScheduler$TestWorker;
       5: aload_0
       6: invokespecial #2                  // Method java/util/concurrent/atomic/AtomicReference."<init>":()V
       9: aload_0
      10: aload_2
      11: invokevirtual #3                  // Method lazySet:(Ljava/lang/Object;)V
      14: return

  public void dispose();
    Code:
       0: aload_0
       1: aconst_null
       2: invokevirtual #4                  // Method getAndSet:(Ljava/lang/Object;)Ljava/lang/Object;
       5: checkcast     #5                  // class io/reactivex/rxjava3/schedulers/TestScheduler$TimedRunnable
       8: astore_1
       9: aload_1
      10: ifnull        30
      13: aload_0
      14: getfield      #1                  // Field this$1:Lio/reactivex/rxjava3/schedulers/TestScheduler$TestWorker;
      17: getfield      #6                  // Field io/reactivex/rxjava3/schedulers/TestScheduler$TestWorker.this$0:Lio/reactivex/rxjava3/schedulers/TestScheduler;
      20: getfield      #7                  // Field io/reactivex/rxjava3/schedulers/TestScheduler.queue:Ljava/util/Queue;
      23: aload_1
      24: invokeinterface #8,  2            // InterfaceMethod java/util/Queue.remove:(Ljava/lang/Object;)Z
      29: pop
      30: return

  public boolean isDisposed();
    Code:
       0: aload_0
       1: invokevirtual #9                  // Method get:()Ljava/lang/Object;
       4: ifnonnull     11
       7: iconst_1
       8: goto          12
      11: iconst_0
      12: ireturn
}
