Compiled from "TestScheduler.java"
final class io.reactivex.rxjava3.schedulers.TestScheduler$TestWorker extends io.reactivex.rxjava3.core.Scheduler$Worker {
  volatile boolean disposed;

  final io.reactivex.rxjava3.schedulers.TestScheduler this$0;

  io.reactivex.rxjava3.schedulers.TestScheduler$TestWorker(io.reactivex.rxjava3.schedulers.TestScheduler);
    Code:
       0: aload_0
       1: aload_1
       2: putfield      #1                  // Field this$0:Lio/reactivex/rxjava3/schedulers/TestScheduler;
       5: aload_0
       6: invokespecial #2                  // Method io/reactivex/rxjava3/core/Scheduler$Worker."<init>":()V
       9: return

  public void dispose();
    Code:
       0: aload_0
       1: iconst_1
       2: putfield      #3                  // Field disposed:Z
       5: return

  public boolean isDisposed();
    Code:
       0: aload_0
       1: getfield      #3                  // Field disposed:Z
       4: ireturn

  public io.reactivex.rxjava3.disposables.Disposable schedule(java.lang.Runnable, long, java.util.concurrent.TimeUnit);
    Code:
       0: aload_0
       1: getfield      #3                  // Field disposed:Z
       4: ifeq          11
       7: getstatic     #4                  // Field io/reactivex/rxjava3/internal/disposables/EmptyDisposable.INSTANCE:Lio/reactivex/rxjava3/internal/disposables/EmptyDisposable;
      10: areturn
      11: aload_0
      12: getfield      #1                  // Field this$0:Lio/reactivex/rxjava3/schedulers/TestScheduler;
      15: getfield      #5                  // Field io/reactivex/rxjava3/schedulers/TestScheduler.useOnScheduleHook:Z
      18: ifeq          26
      21: aload_1
      22: invokestatic  #6                  // Method io/reactivex/rxjava3/plugins/RxJavaPlugins.onSchedule:(Ljava/lang/Runnable;)Ljava/lang/Runnable;
      25: astore_1
      26: new           #7                  // class io/reactivex/rxjava3/schedulers/TestScheduler$TimedRunnable
      29: dup
      30: aload_0
      31: aload_0
      32: getfield      #1                  // Field this$0:Lio/reactivex/rxjava3/schedulers/TestScheduler;
      35: getfield      #8                  // Field io/reactivex/rxjava3/schedulers/TestScheduler.time:J
      38: aload         4
      40: lload_2
      41: invokevirtual #9                  // Method java/util/concurrent/TimeUnit.toNanos:(J)J
      44: ladd
      45: aload_1
      46: aload_0
      47: getfield      #1                  // Field this$0:Lio/reactivex/rxjava3/schedulers/TestScheduler;
      50: dup
      51: getfield      #10                 // Field io/reactivex/rxjava3/schedulers/TestScheduler.counter:J
      54: dup2_x1
      55: lconst_1
      56: ladd
      57: putfield      #10                 // Field io/reactivex/rxjava3/schedulers/TestScheduler.counter:J
      60: invokespecial #11                 // Method io/reactivex/rxjava3/schedulers/TestScheduler$TimedRunnable."<init>":(Lio/reactivex/rxjava3/schedulers/TestScheduler$TestWorker;JLjava/lang/Runnable;J)V
      63: astore        5
      65: aload_0
      66: getfield      #1                  // Field this$0:Lio/reactivex/rxjava3/schedulers/TestScheduler;
      69: getfield      #12                 // Field io/reactivex/rxjava3/schedulers/TestScheduler.queue:Ljava/util/Queue;
      72: aload         5
      74: invokeinterface #13,  2           // InterfaceMethod java/util/Queue.add:(Ljava/lang/Object;)Z
      79: pop
      80: new           #14                 // class io/reactivex/rxjava3/schedulers/TestScheduler$TestWorker$QueueRemove
      83: dup
      84: aload_0
      85: aload         5
      87: invokespecial #15                 // Method io/reactivex/rxjava3/schedulers/TestScheduler$TestWorker$QueueRemove."<init>":(Lio/reactivex/rxjava3/schedulers/TestScheduler$TestWorker;Lio/reactivex/rxjava3/schedulers/TestScheduler$TimedRunnable;)V
      90: areturn

  public io.reactivex.rxjava3.disposables.Disposable schedule(java.lang.Runnable);
    Code:
       0: aload_0
       1: getfield      #3                  // Field disposed:Z
       4: ifeq          11
       7: getstatic     #4                  // Field io/reactivex/rxjava3/internal/disposables/EmptyDisposable.INSTANCE:Lio/reactivex/rxjava3/internal/disposables/EmptyDisposable;
      10: areturn
      11: aload_0
      12: getfield      #1                  // Field this$0:Lio/reactivex/rxjava3/schedulers/TestScheduler;
      15: getfield      #5                  // Field io/reactivex/rxjava3/schedulers/TestScheduler.useOnScheduleHook:Z
      18: ifeq          26
      21: aload_1
      22: invokestatic  #6                  // Method io/reactivex/rxjava3/plugins/RxJavaPlugins.onSchedule:(Ljava/lang/Runnable;)Ljava/lang/Runnable;
      25: astore_1
      26: new           #7                  // class io/reactivex/rxjava3/schedulers/TestScheduler$TimedRunnable
      29: dup
      30: aload_0
      31: lconst_0
      32: aload_1
      33: aload_0
      34: getfield      #1                  // Field this$0:Lio/reactivex/rxjava3/schedulers/TestScheduler;
      37: dup
      38: getfield      #10                 // Field io/reactivex/rxjava3/schedulers/TestScheduler.counter:J
      41: dup2_x1
      42: lconst_1
      43: ladd
      44: putfield      #10                 // Field io/reactivex/rxjava3/schedulers/TestScheduler.counter:J
      47: invokespecial #11                 // Method io/reactivex/rxjava3/schedulers/TestScheduler$TimedRunnable."<init>":(Lio/reactivex/rxjava3/schedulers/TestScheduler$TestWorker;JLjava/lang/Runnable;J)V
      50: astore_2
      51: aload_0
      52: getfield      #1                  // Field this$0:Lio/reactivex/rxjava3/schedulers/TestScheduler;
      55: getfield      #12                 // Field io/reactivex/rxjava3/schedulers/TestScheduler.queue:Ljava/util/Queue;
      58: aload_2
      59: invokeinterface #13,  2           // InterfaceMethod java/util/Queue.add:(Ljava/lang/Object;)Z
      64: pop
      65: new           #14                 // class io/reactivex/rxjava3/schedulers/TestScheduler$TestWorker$QueueRemove
      68: dup
      69: aload_0
      70: aload_2
      71: invokespecial #15                 // Method io/reactivex/rxjava3/schedulers/TestScheduler$TestWorker$QueueRemove."<init>":(Lio/reactivex/rxjava3/schedulers/TestScheduler$TestWorker;Lio/reactivex/rxjava3/schedulers/TestScheduler$TimedRunnable;)V
      74: areturn

  public long now(java.util.concurrent.TimeUnit);
    Code:
       0: aload_0
       1: getfield      #1                  // Field this$0:Lio/reactivex/rxjava3/schedulers/TestScheduler;
       4: aload_1
       5: invokevirtual #16                 // Method io/reactivex/rxjava3/schedulers/TestScheduler.now:(Ljava/util/concurrent/TimeUnit;)J
       8: lreturn
}
