Compiled from "Timed.java"
public final class io.reactivex.rxjava3.schedulers.Timed<T> {
  final T value;

  final long time;

  final java.util.concurrent.TimeUnit unit;

  public io.reactivex.rxjava3.schedulers.Timed(T, long, java.util.concurrent.TimeUnit);
    Code:
       0: aload_0
       1: invokespecial #1                  // Method java/lang/Object."<init>":()V
       4: aload_0
       5: aload_1
       6: ldc           #2                  // String value is null
       8: invokestatic  #3                  // Method java/util/Objects.requireNonNull:(Ljava/lang/Object;Ljava/lang/String;)Ljava/lang/Object;
      11: putfield      #4                  // Field value:Ljava/lang/Object;
      14: aload_0
      15: lload_2
      16: putfield      #5                  // Field time:J
      19: aload_0
      20: aload         4
      22: ldc           #6                  // String unit is null
      24: invokestatic  #3                  // Method java/util/Objects.requireNonNull:(Ljava/lang/Object;Ljava/lang/String;)Ljava/lang/Object;
      27: checkcast     #7                  // class java/util/concurrent/TimeUnit
      30: putfield      #8                  // Field unit:Ljava/util/concurrent/TimeUnit;
      33: return

  public T value();
    Code:
       0: aload_0
       1: getfield      #4                  // Field value:Ljava/lang/Object;
       4: areturn

  public java.util.concurrent.TimeUnit unit();
    Code:
       0: aload_0
       1: getfield      #8                  // Field unit:Ljava/util/concurrent/TimeUnit;
       4: areturn

  public long time();
    Code:
       0: aload_0
       1: getfield      #5                  // Field time:J
       4: lreturn

  public long time(java.util.concurrent.TimeUnit);
    Code:
       0: aload_1
       1: aload_0
       2: getfield      #5                  // Field time:J
       5: aload_0
       6: getfield      #8                  // Field unit:Ljava/util/concurrent/TimeUnit;
       9: invokevirtual #9                  // Method java/util/concurrent/TimeUnit.convert:(JLjava/util/concurrent/TimeUnit;)J
      12: lreturn

  public boolean equals(java.lang.Object);
    Code:
       0: aload_1
       1: instanceof    #10                 // class io/reactivex/rxjava3/schedulers/Timed
       4: ifeq          58
       7: aload_1
       8: checkcast     #10                 // class io/reactivex/rxjava3/schedulers/Timed
      11: astore_2
      12: aload_0
      13: getfield      #4                  // Field value:Ljava/lang/Object;
      16: aload_2
      17: getfield      #4                  // Field value:Ljava/lang/Object;
      20: invokestatic  #11                 // Method java/util/Objects.equals:(Ljava/lang/Object;Ljava/lang/Object;)Z
      23: ifeq          56
      26: aload_0
      27: getfield      #5                  // Field time:J
      30: aload_2
      31: getfield      #5                  // Field time:J
      34: lcmp
      35: ifne          56
      38: aload_0
      39: getfield      #8                  // Field unit:Ljava/util/concurrent/TimeUnit;
      42: aload_2
      43: getfield      #8                  // Field unit:Ljava/util/concurrent/TimeUnit;
      46: invokestatic  #11                 // Method java/util/Objects.equals:(Ljava/lang/Object;Ljava/lang/Object;)Z
      49: ifeq          56
      52: iconst_1
      53: goto          57
      56: iconst_0
      57: ireturn
      58: iconst_0
      59: ireturn

  public int hashCode();
    Code:
       0: aload_0
       1: getfield      #4                  // Field value:Ljava/lang/Object;
       4: invokevirtual #12                 // Method java/lang/Object.hashCode:()I
       7: istore_1
       8: iload_1
       9: bipush        31
      11: imul
      12: aload_0
      13: getfield      #5                  // Field time:J
      16: bipush        31
      18: lushr
      19: aload_0
      20: getfield      #5                  // Field time:J
      23: lxor
      24: l2i
      25: iadd
      26: istore_1
      27: iload_1
      28: bipush        31
      30: imul
      31: aload_0
      32: getfield      #8                  // Field unit:Ljava/util/concurrent/TimeUnit;
      35: invokevirtual #13                 // Method java/util/concurrent/TimeUnit.hashCode:()I
      38: iadd
      39: istore_1
      40: iload_1
      41: ireturn

  public java.lang.String toString();
    Code:
       0: new           #14                 // class java/lang/StringBuilder
       3: dup
       4: invokespecial #15                 // Method java/lang/StringBuilder."<init>":()V
       7: ldc           #16                 // String Timed[time=
       9: invokevirtual #17                 // Method java/lang/StringBuilder.append:(Ljava/lang/String;)Ljava/lang/StringBuilder;
      12: aload_0
      13: getfield      #5                  // Field time:J
      16: invokevirtual #18                 // Method java/lang/StringBuilder.append:(J)Ljava/lang/StringBuilder;
      19: ldc           #19                 // String , unit=
      21: invokevirtual #17                 // Method java/lang/StringBuilder.append:(Ljava/lang/String;)Ljava/lang/StringBuilder;
      24: aload_0
      25: getfield      #8                  // Field unit:Ljava/util/concurrent/TimeUnit;
      28: invokevirtual #20                 // Method java/lang/StringBuilder.append:(Ljava/lang/Object;)Ljava/lang/StringBuilder;
      31: ldc           #21                 // String , value=
      33: invokevirtual #17                 // Method java/lang/StringBuilder.append:(Ljava/lang/String;)Ljava/lang/StringBuilder;
      36: aload_0
      37: getfield      #4                  // Field value:Ljava/lang/Object;
      40: invokevirtual #20                 // Method java/lang/StringBuilder.append:(Ljava/lang/Object;)Ljava/lang/StringBuilder;
      43: ldc           #22                 // String ]
      45: invokevirtual #17                 // Method java/lang/StringBuilder.append:(Ljava/lang/String;)Ljava/lang/StringBuilder;
      48: invokevirtual #23                 // Method java/lang/StringBuilder.toString:()Ljava/lang/String;
      51: areturn
}
