Compiled from "AbstractInterfaceConfig.java"
public abstract class org.apache.dubbo.config.AbstractInterfaceConfig extends org.apache.dubbo.config.AbstractMethodConfig {
  private static final long serialVersionUID;

  protected java.lang.String interfaceName;

  protected transient java.lang.ClassLoader interfaceClassLoader;

  protected java.lang.String version;

  protected java.lang.String group;

  protected org.apache.dubbo.rpc.model.ServiceMetadata serviceMetadata;

  protected java.lang.String local;

  protected java.lang.String stub;

  protected org.apache.dubbo.config.MonitorConfig monitor;

  protected java.lang.String proxy;

  protected java.lang.String cluster;

  protected java.lang.String filter;

  protected java.lang.String listener;

  protected java.lang.String owner;

  protected java.lang.Integer connections;

  protected java.lang.String layer;

  protected org.apache.dubbo.config.ApplicationConfig application;

  protected org.apache.dubbo.config.ModuleConfig module;

  protected java.util.List<org.apache.dubbo.config.RegistryConfig> registries;

  private java.util.List<org.apache.dubbo.config.MethodConfig> methods;

  protected java.lang.String registryIds;

  protected java.lang.String onconnect;

  protected java.lang.String ondisconnect;

  protected org.apache.dubbo.config.MetadataReportConfig metadataReportConfig;

  protected org.apache.dubbo.config.ConfigCenterConfig configCenter;

  private java.lang.Integer callbacks;

  private java.lang.String scope;

  protected java.lang.String tag;

  private java.lang.Boolean auth;

  private java.lang.Boolean singleton;

  protected final transient java.util.List<org.apache.dubbo.common.URL> urls;

  public org.apache.dubbo.config.AbstractInterfaceConfig();
    Code:
       0: aload_0
       1: invokespecial #4                  // Method org/apache/dubbo/config/AbstractMethodConfig."<init>":()V
       4: aload_0
       5: new           #5                  // class java/util/ArrayList
       8: dup
       9: invokespecial #6                  // Method java/util/ArrayList."<init>":()V
      12: putfield      #7                  // Field urls:Ljava/util/List;
      15: return

  public org.apache.dubbo.config.AbstractInterfaceConfig(org.apache.dubbo.rpc.model.ModuleModel);
    Code:
       0: aload_0
       1: aload_1
       2: invokespecial #8                  // Method org/apache/dubbo/config/AbstractMethodConfig."<init>":(Lorg/apache/dubbo/rpc/model/ModuleModel;)V
       5: aload_0
       6: new           #5                  // class java/util/ArrayList
       9: dup
      10: invokespecial #6                  // Method java/util/ArrayList."<init>":()V
      13: putfield      #7                  // Field urls:Ljava/util/List;
      16: return

  public java.util.List<org.apache.dubbo.common.URL> getExportedUrls();
    Code:
       0: aload_0
       1: getfield      #7                  // Field urls:Ljava/util/List;
       4: areturn

  public org.apache.dubbo.common.URL toUrl();
    Code:
       0: aload_0
       1: getfield      #7                  // Field urls:Ljava/util/List;
       4: invokeinterface #9,  1            // InterfaceMethod java/util/List.isEmpty:()Z
       9: ifeq          16
      12: aconst_null
      13: goto          33
      16: aload_0
      17: getfield      #7                  // Field urls:Ljava/util/List;
      20: invokeinterface #10,  1           // InterfaceMethod java/util/List.iterator:()Ljava/util/Iterator;
      25: invokeinterface #11,  1           // InterfaceMethod java/util/Iterator.next:()Ljava/lang/Object;
      30: checkcast     #12                 // class org/apache/dubbo/common/URL
      33: areturn

  public java.util.List<org.apache.dubbo.common.URL> toUrls();
    Code:
       0: aload_0
       1: getfield      #7                  // Field urls:Ljava/util/List;
       4: areturn

  protected void postProcessAfterScopeModelChanged(org.apache.dubbo.rpc.model.ScopeModel, org.apache.dubbo.rpc.model.ScopeModel);
    Code:
       0: aload_0
       1: aload_1
       2: aload_2
       3: invokespecial #13                 // Method org/apache/dubbo/config/AbstractMethodConfig.postProcessAfterScopeModelChanged:(Lorg/apache/dubbo/rpc/model/ScopeModel;Lorg/apache/dubbo/rpc/model/ScopeModel;)V
       6: aload_0
       7: invokevirtual #14                 // Method getScopeModel:()Lorg/apache/dubbo/rpc/model/ModuleModel;
      10: invokestatic  #15                 // Method org/apache/dubbo/rpc/model/ScopeModelUtil.getApplicationModel:(Lorg/apache/dubbo/rpc/model/ScopeModel;)Lorg/apache/dubbo/rpc/model/ApplicationModel;
      13: astore_3
      14: aload_0
      15: getfield      #16                 // Field configCenter:Lorg/apache/dubbo/config/ConfigCenterConfig;
      18: ifnull        40
      21: aload_0
      22: getfield      #16                 // Field configCenter:Lorg/apache/dubbo/config/ConfigCenterConfig;
      25: invokevirtual #17                 // Method org/apache/dubbo/config/ConfigCenterConfig.getScopeModel:()Lorg/apache/dubbo/rpc/model/ScopeModel;
      28: aload_3
      29: if_acmpeq     40
      32: aload_0
      33: getfield      #16                 // Field configCenter:Lorg/apache/dubbo/config/ConfigCenterConfig;
      36: aload_3
      37: invokevirtual #18                 // Method org/apache/dubbo/config/ConfigCenterConfig.setScopeModel:(Lorg/apache/dubbo/rpc/model/ScopeModel;)V
      40: aload_0
      41: getfield      #19                 // Field metadataReportConfig:Lorg/apache/dubbo/config/MetadataReportConfig;
      44: ifnull        66
      47: aload_0
      48: getfield      #19                 // Field metadataReportConfig:Lorg/apache/dubbo/config/MetadataReportConfig;
      51: invokevirtual #20                 // Method org/apache/dubbo/config/MetadataReportConfig.getScopeModel:()Lorg/apache/dubbo/rpc/model/ScopeModel;
      54: aload_3
      55: if_acmpeq     66
      58: aload_0
      59: getfield      #19                 // Field metadataReportConfig:Lorg/apache/dubbo/config/MetadataReportConfig;
      62: aload_3
      63: invokevirtual #21                 // Method org/apache/dubbo/config/MetadataReportConfig.setScopeModel:(Lorg/apache/dubbo/rpc/model/ScopeModel;)V
      66: aload_0
      67: getfield      #22                 // Field monitor:Lorg/apache/dubbo/config/MonitorConfig;
      70: ifnull        92
      73: aload_0
      74: getfield      #22                 // Field monitor:Lorg/apache/dubbo/config/MonitorConfig;
      77: invokevirtual #23                 // Method org/apache/dubbo/config/MonitorConfig.getScopeModel:()Lorg/apache/dubbo/rpc/model/ScopeModel;
      80: aload_3
      81: if_acmpeq     92
      84: aload_0
      85: getfield      #22                 // Field monitor:Lorg/apache/dubbo/config/MonitorConfig;
      88: aload_3
      89: invokevirtual #24                 // Method org/apache/dubbo/config/MonitorConfig.setScopeModel:(Lorg/apache/dubbo/rpc/model/ScopeModel;)V
      92: aload_0
      93: getfield      #25                 // Field registries:Ljava/util/List;
      96: invokestatic  #26                 // Method org/apache/dubbo/common/utils/CollectionUtils.isNotEmpty:(Ljava/util/Collection;)Z
      99: ifeq          117
     102: aload_0
     103: getfield      #25                 // Field registries:Ljava/util/List;
     106: aload_3
     107: invokedynamic #27,  0             // InvokeDynamic #0:accept:(Lorg/apache/dubbo/rpc/model/ApplicationModel;)Ljava/util/function/Consumer;
     112: invokeinterface #28,  2           // InterfaceMethod java/util/List.forEach:(Ljava/util/function/Consumer;)V
     117: return

  protected void checkRegistry();
    Code:
       0: aload_0
       1: invokespecial #29                 // Method convertRegistryIdsToRegistries:()V
       4: aload_0
       5: getfield      #25                 // Field registries:Ljava/util/List;
       8: invokeinterface #10,  1           // InterfaceMethod java/util/List.iterator:()Ljava/util/Iterator;
      13: astore_1
      14: aload_1
      15: invokeinterface #30,  1           // InterfaceMethod java/util/Iterator.hasNext:()Z
      20: ifeq          70
      23: aload_1
      24: invokeinterface #11,  1           // InterfaceMethod java/util/Iterator.next:()Ljava/lang/Object;
      29: checkcast     #31                 // class org/apache/dubbo/config/RegistryConfig
      32: astore_2
      33: aload_2
      34: invokevirtual #32                 // Method org/apache/dubbo/config/RegistryConfig.isValid:()Z
      37: ifne          67
      40: new           #33                 // class java/lang/IllegalStateException
      43: dup
      44: new           #34                 // class java/lang/StringBuilder
      47: dup
      48: invokespecial #35                 // Method java/lang/StringBuilder."<init>":()V
      51: ldc           #36                 // String No registry config found or it\'s not a valid config! The registry config is:
      53: invokevirtual #37                 // Method java/lang/StringBuilder.append:(Ljava/lang/String;)Ljava/lang/StringBuilder;
      56: aload_2
      57: invokevirtual #38                 // Method java/lang/StringBuilder.append:(Ljava/lang/Object;)Ljava/lang/StringBuilder;
      60: invokevirtual #39                 // Method java/lang/StringBuilder.toString:()Ljava/lang/String;
      63: invokespecial #40                 // Method java/lang/IllegalStateException."<init>":(Ljava/lang/String;)V
      66: athrow
      67: goto          14
      70: return

  public static void appendRuntimeParameters(java.util.Map<java.lang.String, java.lang.String>);
    Code:
       0: aload_0
       1: ldc           #41                 // String dubbo
       3: invokestatic  #42                 // Method org/apache/dubbo/common/Version.getProtocolVersion:()Ljava/lang/String;
       6: invokeinterface #43,  3           // InterfaceMethod java/util/Map.put:(Ljava/lang/Object;Ljava/lang/Object;)Ljava/lang/Object;
      11: pop
      12: aload_0
      13: ldc           #44                 // String release
      15: invokestatic  #45                 // Method org/apache/dubbo/common/Version.getVersion:()Ljava/lang/String;
      18: invokeinterface #43,  3           // InterfaceMethod java/util/Map.put:(Ljava/lang/Object;Ljava/lang/Object;)Ljava/lang/Object;
      23: pop
      24: aload_0
      25: ldc           #46                 // String timestamp
      27: invokestatic  #47                 // Method java/lang/System.currentTimeMillis:()J
      30: invokestatic  #48                 // Method java/lang/String.valueOf:(J)Ljava/lang/String;
      33: invokeinterface #43,  3           // InterfaceMethod java/util/Map.put:(Ljava/lang/Object;Ljava/lang/Object;)Ljava/lang/Object;
      38: pop
      39: invokestatic  #49                 // Method org/apache/dubbo/common/utils/ConfigUtils.getPid:()I
      42: ifle          60
      45: aload_0
      46: ldc           #50                 // String pid
      48: invokestatic  #49                 // Method org/apache/dubbo/common/utils/ConfigUtils.getPid:()I
      51: invokestatic  #51                 // Method java/lang/String.valueOf:(I)Ljava/lang/String;
      54: invokeinterface #43,  3           // InterfaceMethod java/util/Map.put:(Ljava/lang/Object;Ljava/lang/Object;)Ljava/lang/Object;
      59: pop
      60: return

  protected void appendMetricsCompatible(java.util.Map<java.lang.String, java.lang.String>);
    Code:
       0: aload_0
       1: invokevirtual #52                 // Method getConfigManager:()Lorg/apache/dubbo/config/context/ConfigManager;
       4: invokevirtual #53                 // Method org/apache/dubbo/config/context/ConfigManager.getMetrics:()Ljava/util/Optional;
       7: aconst_null
       8: invokevirtual #54                 // Method java/util/Optional.orElse:(Ljava/lang/Object;)Ljava/lang/Object;
      11: checkcast     #55                 // class org/apache/dubbo/config/MetricsConfig
      14: astore_2
      15: aload_2
      16: ifnull        73
      19: aload_2
      20: invokevirtual #56                 // Method org/apache/dubbo/config/MetricsConfig.getProtocol:()Ljava/lang/String;
      23: ifnull        73
      26: aload_2
      27: invokevirtual #56                 // Method org/apache/dubbo/config/MetricsConfig.getProtocol:()Ljava/lang/String;
      30: ldc           #57                 // String prometheus
      32: invokestatic  #58                 // Method org/apache/dubbo/common/utils/StringUtils.isEquals:(Ljava/lang/String;Ljava/lang/String;)Z
      35: ifne          73
      38: aload_2
      39: invokevirtual #59                 // Method org/apache/dubbo/config/MetricsConfig.getPort:()Ljava/lang/String;
      42: ldc           #60                 // String Metrics port cannot be null
      44: invokestatic  #61                 // Method org/apache/dubbo/common/utils/Assert.notEmptyString:(Ljava/lang/String;Ljava/lang/String;)V
      47: aload_1
      48: ldc           #62                 // String metrics.protocol
      50: aload_2
      51: invokevirtual #56                 // Method org/apache/dubbo/config/MetricsConfig.getProtocol:()Ljava/lang/String;
      54: invokeinterface #43,  3           // InterfaceMethod java/util/Map.put:(Ljava/lang/Object;Ljava/lang/Object;)Ljava/lang/Object;
      59: pop
      60: aload_1
      61: ldc           #63                 // String metrics.port
      63: aload_2
      64: invokevirtual #59                 // Method org/apache/dubbo/config/MetricsConfig.getPort:()Ljava/lang/String;
      67: invokeinterface #43,  3           // InterfaceMethod java/util/Map.put:(Ljava/lang/Object;Ljava/lang/Object;)Ljava/lang/Object;
      72: pop
      73: return

  protected java.lang.String[] methods(java.lang.Class<?>);
    Code:
       0: aload_0
       1: invokevirtual #64                 // Method getEnvironment:()Lorg/apache/dubbo/common/config/Environment;
       4: invokevirtual #65                 // Method org/apache/dubbo/common/config/Environment.getConfiguration:()Lorg/apache/dubbo/common/config/CompositeConfiguration;
       7: ldc           #66                 // String native
       9: iconst_0
      10: invokevirtual #67                 // Method org/apache/dubbo/common/config/CompositeConfiguration.getBoolean:(Ljava/lang/String;Z)Z
      13: istore_2
      14: iload_2
      15: ifeq          49
      18: aload_1
      19: invokevirtual #68                 // Method java/lang/Class.getMethods:()[Ljava/lang/reflect/Method;
      22: invokestatic  #69                 // Method java/util/Arrays.stream:([Ljava/lang/Object;)Ljava/util/stream/Stream;
      25: invokedynamic #70,  0             // InvokeDynamic #1:apply:()Ljava/util/function/Function;
      30: invokeinterface #71,  2           // InterfaceMethod java/util/stream/Stream.map:(Ljava/util/function/Function;)Ljava/util/stream/Stream;
      35: invokedynamic #72,  0             // InvokeDynamic #2:apply:()Ljava/util/function/IntFunction;
      40: invokeinterface #73,  2           // InterfaceMethod java/util/stream/Stream.toArray:(Ljava/util/function/IntFunction;)[Ljava/lang/Object;
      45: checkcast     #74                 // class "[Ljava/lang/String;"
      48: areturn
      49: aload_1
      50: invokestatic  #75                 // Method org/apache/dubbo/common/utils/ClassUtils.getMethodNames:(Ljava/lang/Class;)[Ljava/lang/String;
      53: areturn

  protected org.apache.dubbo.common.config.Environment getEnvironment();
    Code:
       0: aload_0
       1: invokevirtual #14                 // Method getScopeModel:()Lorg/apache/dubbo/rpc/model/ModuleModel;
       4: invokevirtual #76                 // Method org/apache/dubbo/rpc/model/ModuleModel.getModelEnvironment:()Lorg/apache/dubbo/common/config/ModuleEnvironment;
       7: areturn

  protected void processExtraRefresh(java.lang.String, org.apache.dubbo.common.config.InmemoryConfiguration);
    Code:
       0: aload_0
       1: getfield      #77                 // Field interfaceName:Ljava/lang/String;
       4: invokestatic  #78                 // Method org/apache/dubbo/common/utils/StringUtils.hasText:(Ljava/lang/CharSequence;)Z
       7: ifeq          341
      10: aload_0
      11: getfield      #77                 // Field interfaceName:Ljava/lang/String;
      14: invokestatic  #79                 // Method org/apache/dubbo/common/utils/ClassUtils.forName:(Ljava/lang/String;)Ljava/lang/Class;
      17: astore_3
      18: goto          24
      21: astore        4
      23: return
      24: aload_3
      25: invokevirtual #81                 // Method java/lang/Class.isInterface:()Z
      28: ifne          68
      31: aload_0
      32: invokevirtual #82                 // Method canSkipInterfaceCheck:()Z
      35: ifne          68
      38: new           #33                 // class java/lang/IllegalStateException
      41: dup
      42: new           #34                 // class java/lang/StringBuilder
      45: dup
      46: invokespecial #35                 // Method java/lang/StringBuilder."<init>":()V
      49: aload_0
      50: getfield      #77                 // Field interfaceName:Ljava/lang/String;
      53: invokevirtual #37                 // Method java/lang/StringBuilder.append:(Ljava/lang/String;)Ljava/lang/StringBuilder;
      56: ldc           #83                 // String  is not an interface
      58: invokevirtual #37                 // Method java/lang/StringBuilder.append:(Ljava/lang/String;)Ljava/lang/StringBuilder;
      61: invokevirtual #39                 // Method java/lang/StringBuilder.toString:()Ljava/lang/String;
      64: invokespecial #40                 // Method java/lang/IllegalStateException."<init>":(Ljava/lang/String;)V
      67: athrow
      68: aload_2
      69: invokevirtual #84                 // Method org/apache/dubbo/common/config/InmemoryConfiguration.getProperties:()Ljava/util/Map;
      72: astore        4
      74: aload_3
      75: invokevirtual #68                 // Method java/lang/Class.getMethods:()[Ljava/lang/reflect/Method;
      78: astore        5
      80: goto          86
      83: astore        6
      85: return
      86: aload         5
      88: astore        6
      90: aload         6
      92: arraylength
      93: istore        7
      95: iconst_0
      96: istore        8
      98: iload         8
     100: iload         7
     102: if_icmpge     249
     105: aload         6
     107: iload         8
     109: aaload
     110: astore        9
     112: aload         4
     114: aload         9
     116: invokevirtual #86                 // Method java/lang/reflect/Method.getName:()Ljava/lang/String;
     119: invokestatic  #87                 // Method org/apache/dubbo/common/config/ConfigurationUtils.hasSubProperties:(Ljava/util/Map;Ljava/lang/String;)Z
     122: ifeq          243
     125: aload_0
     126: aload         9
     128: invokevirtual #86                 // Method java/lang/reflect/Method.getName:()Ljava/lang/String;
     131: invokevirtual #88                 // Method getMethodByName:(Ljava/lang/String;)Lorg/apache/dubbo/config/MethodConfig;
     134: astore        10
     136: aload         10
     138: ifnonnull     166
     141: new           #89                 // class org/apache/dubbo/config/MethodConfig
     144: dup
     145: invokespecial #90                 // Method org/apache/dubbo/config/MethodConfig."<init>":()V
     148: astore        10
     150: aload         10
     152: aload         9
     154: invokevirtual #86                 // Method java/lang/reflect/Method.getName:()Ljava/lang/String;
     157: invokevirtual #91                 // Method org/apache/dubbo/config/MethodConfig.setName:(Ljava/lang/String;)V
     160: aload_0
     161: aload         10
     163: invokevirtual #92                 // Method addMethod:(Lorg/apache/dubbo/config/MethodConfig;)V
     166: aload         9
     168: invokevirtual #93                 // Method java/lang/reflect/Method.getParameters:()[Ljava/lang/reflect/Parameter;
     171: astore        11
     173: iconst_0
     174: istore        12
     176: iload         12
     178: aload         11
     180: arraylength
     181: if_icmpge     243
     184: aload_0
     185: aload         10
     187: iload         12
     189: invokespecial #94                 // Method getArgumentByIndex:(Lorg/apache/dubbo/config/MethodConfig;I)Lorg/apache/dubbo/config/ArgumentConfig;
     192: ifnonnull     237
     195: aload_0
     196: aload         4
     198: aload         10
     200: invokevirtual #95                 // Method org/apache/dubbo/config/MethodConfig.getName:()Ljava/lang/String;
     203: iload         12
     205: invokespecial #96                 // Method hasArgumentConfigProps:(Ljava/util/Map;Ljava/lang/String;I)Z
     208: ifeq          237
     211: new           #97                 // class org/apache/dubbo/config/ArgumentConfig
     214: dup
     215: invokespecial #98                 // Method org/apache/dubbo/config/ArgumentConfig."<init>":()V
     218: astore        13
     220: aload         13
     222: iload         12
     224: invokestatic  #99                 // Method java/lang/Integer.valueOf:(I)Ljava/lang/Integer;
     227: invokevirtual #100                // Method org/apache/dubbo/config/ArgumentConfig.setIndex:(Ljava/lang/Integer;)V
     230: aload         10
     232: aload         13
     234: invokevirtual #101                // Method org/apache/dubbo/config/MethodConfig.addArgument:(Lorg/apache/dubbo/config/ArgumentConfig;)V
     237: iinc          12, 1
     240: goto          176
     243: iinc          8, 1
     246: goto          98
     249: aload_0
     250: invokevirtual #102                // Method getMethods:()Ljava/util/List;
     253: astore        6
     255: aload         6
     257: ifnull        341
     260: aload         6
     262: invokeinterface #103,  1          // InterfaceMethod java/util/List.size:()I
     267: ifle          341
     270: aload_0
     271: invokevirtual #64                 // Method getEnvironment:()Lorg/apache/dubbo/common/config/Environment;
     274: invokevirtual #65                 // Method org/apache/dubbo/common/config/Environment.getConfiguration:()Lorg/apache/dubbo/common/config/CompositeConfiguration;
     277: ldc           #105                // String dubbo.config.ignore-invalid-method-config
     279: ldc           #106                // String false
     281: invokevirtual #107                // Method org/apache/dubbo/common/config/CompositeConfiguration.getProperty:(Ljava/lang/String;Ljava/lang/Object;)Ljava/lang/Object;
     284: astore        7
     286: aload         7
     288: invokevirtual #108                // Method java/lang/Object.toString:()Ljava/lang/String;
     291: invokestatic  #109                // Method java/lang/Boolean.parseBoolean:(Ljava/lang/String;)Z
     294: istore        8
     296: aload_3
     297: astore        9
     299: aload         6
     301: invokeinterface #110,  1          // InterfaceMethod java/util/List.stream:()Ljava/util/stream/Stream;
     306: aload_0
     307: aload_1
     308: aload         9
     310: iload         8
     312: invokedynamic #111,  0            // InvokeDynamic #3:test:(Lorg/apache/dubbo/config/AbstractInterfaceConfig;Ljava/lang/String;Ljava/lang/Class;Z)Ljava/util/function/Predicate;
     317: invokeinterface #112,  2          // InterfaceMethod java/util/stream/Stream.filter:(Ljava/util/function/Predicate;)Ljava/util/stream/Stream;
     322: invokestatic  #113                // Method java/util/stream/Collectors.toList:()Ljava/util/stream/Collector;
     325: invokeinterface #114,  2          // InterfaceMethod java/util/stream/Stream.collect:(Ljava/util/stream/Collector;)Ljava/lang/Object;
     330: checkcast     #115                // class java/util/List
     333: astore        10
     335: aload_0
     336: aload         10
     338: invokevirtual #116                // Method setMethods:(Ljava/util/List;)V
     341: return
    Exception table:
       from    to  target type
          10    18    21   Class java/lang/ClassNotFoundException
          74    80    83   Class java/lang/Throwable

  protected boolean canSkipInterfaceCheck();
    Code:
       0: iconst_0
       1: ireturn

  protected boolean verifyMethodConfig(org.apache.dubbo.config.MethodConfig, java.lang.Class<?>, boolean);
    Code:
       0: aload_1
       1: invokevirtual #95                 // Method org/apache/dubbo/config/MethodConfig.getName:()Ljava/lang/String;
       4: astore        4
       6: aload         4
       8: invokestatic  #117                // Method org/apache/dubbo/common/utils/StringUtils.isEmpty:(Ljava/lang/String;)Z
      11: ifeq          75
      14: new           #34                 // class java/lang/StringBuilder
      17: dup
      18: invokespecial #35                 // Method java/lang/StringBuilder."<init>":()V
      21: ldc           #118                // String <dubbo:method> name attribute is required! Please check: <dubbo:service interface=\"
      23: invokevirtual #37                 // Method java/lang/StringBuilder.append:(Ljava/lang/String;)Ljava/lang/StringBuilder;
      26: aload_0
      27: getfield      #77                 // Field interfaceName:Ljava/lang/String;
      30: invokevirtual #37                 // Method java/lang/StringBuilder.append:(Ljava/lang/String;)Ljava/lang/StringBuilder;
      33: ldc           #119                // String \" ... ><dubbo:method name=\"\" ... /></<dubbo:reference>
      35: invokevirtual #37                 // Method java/lang/StringBuilder.append:(Ljava/lang/String;)Ljava/lang/StringBuilder;
      38: invokevirtual #39                 // Method java/lang/StringBuilder.toString:()Ljava/lang/String;
      41: astore        5
      43: iload_3
      44: ifeq          65
      47: getstatic     #120                // Field logger:Lorg/apache/dubbo/common/logger/ErrorTypeAwareLogger;
      50: ldc           #121                // String 5-4
      52: ldc           #122                // String
      54: ldc           #122                // String
      56: aload         5
      58: invokeinterface #123,  5          // InterfaceMethod org/apache/dubbo/common/logger/ErrorTypeAwareLogger.warn:(Ljava/lang/String;Ljava/lang/String;Ljava/lang/String;Ljava/lang/String;)V
      63: iconst_0
      64: ireturn
      65: new           #33                 // class java/lang/IllegalStateException
      68: dup
      69: aload         5
      71: invokespecial #40                 // Method java/lang/IllegalStateException."<init>":(Ljava/lang/String;)V
      74: athrow
      75: aload_2
      76: invokevirtual #68                 // Method java/lang/Class.getMethods:()[Ljava/lang/reflect/Method;
      79: invokestatic  #69                 // Method java/util/Arrays.stream:([Ljava/lang/Object;)Ljava/util/stream/Stream;
      82: aload         4
      84: invokedynamic #124,  0            // InvokeDynamic #4:test:(Ljava/lang/String;)Ljava/util/function/Predicate;
      89: invokeinterface #125,  2          // InterfaceMethod java/util/stream/Stream.anyMatch:(Ljava/util/function/Predicate;)Z
      94: istore        5
      96: iload         5
      98: ifne          229
     101: new           #34                 // class java/lang/StringBuilder
     104: dup
     105: invokespecial #35                 // Method java/lang/StringBuilder."<init>":()V
     108: ldc           #126                // String Found invalid method config, the interface
     110: invokevirtual #37                 // Method java/lang/StringBuilder.append:(Ljava/lang/String;)Ljava/lang/StringBuilder;
     113: aload_2
     114: invokevirtual #127                // Method java/lang/Class.getName:()Ljava/lang/String;
     117: invokevirtual #37                 // Method java/lang/StringBuilder.append:(Ljava/lang/String;)Ljava/lang/StringBuilder;
     120: ldc           #128                // String  not found method \"
     122: invokevirtual #37                 // Method java/lang/StringBuilder.append:(Ljava/lang/String;)Ljava/lang/StringBuilder;
     125: aload         4
     127: invokevirtual #37                 // Method java/lang/StringBuilder.append:(Ljava/lang/String;)Ljava/lang/StringBuilder;
     130: ldc           #129                // String \" : [
     132: invokevirtual #37                 // Method java/lang/StringBuilder.append:(Ljava/lang/String;)Ljava/lang/StringBuilder;
     135: aload_1
     136: invokevirtual #38                 // Method java/lang/StringBuilder.append:(Ljava/lang/Object;)Ljava/lang/StringBuilder;
     139: ldc           #130                // String ]
     141: invokevirtual #37                 // Method java/lang/StringBuilder.append:(Ljava/lang/String;)Ljava/lang/StringBuilder;
     144: invokevirtual #39                 // Method java/lang/StringBuilder.toString:()Ljava/lang/String;
     147: astore        6
     149: iload_3
     150: ifeq          171
     153: getstatic     #120                // Field logger:Lorg/apache/dubbo/common/logger/ErrorTypeAwareLogger;
     156: ldc           #121                // String 5-4
     158: ldc           #122                // String
     160: ldc           #122                // String
     162: aload         6
     164: invokeinterface #123,  5          // InterfaceMethod org/apache/dubbo/common/logger/ErrorTypeAwareLogger.warn:(Ljava/lang/String;Ljava/lang/String;Ljava/lang/String;Ljava/lang/String;)V
     169: iconst_0
     170: ireturn
     171: aload_0
     172: invokevirtual #131                // Method isNeedCheckMethod:()Z
     175: ifne          219
     178: new           #34                 // class java/lang/StringBuilder
     181: dup
     182: invokespecial #35                 // Method java/lang/StringBuilder."<init>":()V
     185: ldc           #132                // String Generic call:
     187: invokevirtual #37                 // Method java/lang/StringBuilder.append:(Ljava/lang/String;)Ljava/lang/StringBuilder;
     190: aload         6
     192: invokevirtual #37                 // Method java/lang/StringBuilder.append:(Ljava/lang/String;)Ljava/lang/StringBuilder;
     195: invokevirtual #39                 // Method java/lang/StringBuilder.toString:()Ljava/lang/String;
     198: astore        6
     200: getstatic     #120                // Field logger:Lorg/apache/dubbo/common/logger/ErrorTypeAwareLogger;
     203: ldc           #121                // String 5-4
     205: ldc           #122                // String
     207: ldc           #122                // String
     209: aload         6
     211: invokeinterface #123,  5          // InterfaceMethod org/apache/dubbo/common/logger/ErrorTypeAwareLogger.warn:(Ljava/lang/String;Ljava/lang/String;Ljava/lang/String;Ljava/lang/String;)V
     216: goto          229
     219: new           #33                 // class java/lang/IllegalStateException
     222: dup
     223: aload         6
     225: invokespecial #40                 // Method java/lang/IllegalStateException."<init>":(Ljava/lang/String;)V
     228: athrow
     229: iconst_1
     230: ireturn

  private org.apache.dubbo.config.ArgumentConfig getArgumentByIndex(org.apache.dubbo.config.MethodConfig, int);
    Code:
       0: aload_1
       1: invokevirtual #133                // Method org/apache/dubbo/config/MethodConfig.getArguments:()Ljava/util/List;
       4: ifnull        75
       7: aload_1
       8: invokevirtual #133                // Method org/apache/dubbo/config/MethodConfig.getArguments:()Ljava/util/List;
      11: invokeinterface #103,  1          // InterfaceMethod java/util/List.size:()I
      16: ifle          75
      19: aload_1
      20: invokevirtual #133                // Method org/apache/dubbo/config/MethodConfig.getArguments:()Ljava/util/List;
      23: invokeinterface #10,  1           // InterfaceMethod java/util/List.iterator:()Ljava/util/Iterator;
      28: astore_3
      29: aload_3
      30: invokeinterface #30,  1           // InterfaceMethod java/util/Iterator.hasNext:()Z
      35: ifeq          75
      38: aload_3
      39: invokeinterface #11,  1           // InterfaceMethod java/util/Iterator.next:()Ljava/lang/Object;
      44: checkcast     #97                 // class org/apache/dubbo/config/ArgumentConfig
      47: astore        4
      49: aload         4
      51: invokevirtual #134                // Method org/apache/dubbo/config/ArgumentConfig.getIndex:()Ljava/lang/Integer;
      54: ifnull        72
      57: aload         4
      59: invokevirtual #134                // Method org/apache/dubbo/config/ArgumentConfig.getIndex:()Ljava/lang/Integer;
      62: invokevirtual #135                // Method java/lang/Integer.intValue:()I
      65: iload_2
      66: if_icmpne     72
      69: aload         4
      71: areturn
      72: goto          29
      75: aconst_null
      76: areturn

  protected boolean isNeedCheckMethod();
    Code:
       0: iconst_1
       1: ireturn

  private boolean hasArgumentConfigProps(java.util.Map<java.lang.String, java.lang.String>, java.lang.String, int);
    Code:
       0: new           #34                 // class java/lang/StringBuilder
       3: dup
       4: invokespecial #35                 // Method java/lang/StringBuilder."<init>":()V
       7: aload_2
       8: invokevirtual #37                 // Method java/lang/StringBuilder.append:(Ljava/lang/String;)Ljava/lang/StringBuilder;
      11: ldc           #136                // String .
      13: invokevirtual #37                 // Method java/lang/StringBuilder.append:(Ljava/lang/String;)Ljava/lang/StringBuilder;
      16: iload_3
      17: invokevirtual #137                // Method java/lang/StringBuilder.append:(I)Ljava/lang/StringBuilder;
      20: ldc           #136                // String .
      22: invokevirtual #37                 // Method java/lang/StringBuilder.append:(Ljava/lang/String;)Ljava/lang/StringBuilder;
      25: invokevirtual #39                 // Method java/lang/StringBuilder.toString:()Ljava/lang/String;
      28: astore        4
      30: aload_1
      31: aload         4
      33: invokestatic  #87                 // Method org/apache/dubbo/common/config/ConfigurationUtils.hasSubProperties:(Ljava/util/Map;Ljava/lang/String;)Z
      36: ireturn

  protected org.apache.dubbo.config.MethodConfig getMethodByName(java.lang.String);
    Code:
       0: aload_0
       1: getfield      #138                // Field methods:Ljava/util/List;
       4: ifnull        64
       7: aload_0
       8: getfield      #138                // Field methods:Ljava/util/List;
      11: invokeinterface #103,  1          // InterfaceMethod java/util/List.size:()I
      16: ifle          64
      19: aload_0
      20: getfield      #138                // Field methods:Ljava/util/List;
      23: invokeinterface #10,  1           // InterfaceMethod java/util/List.iterator:()Ljava/util/Iterator;
      28: astore_2
      29: aload_2
      30: invokeinterface #30,  1           // InterfaceMethod java/util/Iterator.hasNext:()Z
      35: ifeq          64
      38: aload_2
      39: invokeinterface #11,  1           // InterfaceMethod java/util/Iterator.next:()Ljava/lang/Object;
      44: checkcast     #89                 // class org/apache/dubbo/config/MethodConfig
      47: astore_3
      48: aload_3
      49: invokevirtual #95                 // Method org/apache/dubbo/config/MethodConfig.getName:()Ljava/lang/String;
      52: aload_1
      53: invokestatic  #58                 // Method org/apache/dubbo/common/utils/StringUtils.isEquals:(Ljava/lang/String;Ljava/lang/String;)Z
      56: ifeq          61
      59: aload_3
      60: areturn
      61: goto          29
      64: aconst_null
      65: areturn

  protected void checkStubAndLocal(java.lang.Class<?>);
    Code:
       0: aload_0
       1: aload_0
       2: getfield      #139                // Field local:Ljava/lang/String;
       5: ldc           #140                // String Local
       7: aload_1
       8: invokespecial #141                // Method verifyStubAndLocal:(Ljava/lang/String;Ljava/lang/String;Ljava/lang/Class;)V
      11: aload_0
      12: aload_0
      13: getfield      #142                // Field stub:Ljava/lang/String;
      16: ldc           #143                // String Stub
      18: aload_1
      19: invokespecial #141                // Method verifyStubAndLocal:(Ljava/lang/String;Ljava/lang/String;Ljava/lang/Class;)V
      22: return

  private void verifyStubAndLocal(java.lang.String, java.lang.String, java.lang.Class<?>);
    Code:
       0: aload_1
       1: invokestatic  #144                // Method org/apache/dubbo/common/utils/ConfigUtils.isNotEmpty:(Ljava/lang/String;)Z
       4: ifeq          54
       7: aload_1
       8: invokestatic  #145                // Method org/apache/dubbo/common/utils/ConfigUtils.isDefault:(Ljava/lang/String;)Z
      11: ifeq          41
      14: new           #34                 // class java/lang/StringBuilder
      17: dup
      18: invokespecial #35                 // Method java/lang/StringBuilder."<init>":()V
      21: aload_3
      22: invokevirtual #127                // Method java/lang/Class.getName:()Ljava/lang/String;
      25: invokevirtual #37                 // Method java/lang/StringBuilder.append:(Ljava/lang/String;)Ljava/lang/StringBuilder;
      28: aload_2
      29: invokevirtual #37                 // Method java/lang/StringBuilder.append:(Ljava/lang/String;)Ljava/lang/StringBuilder;
      32: invokevirtual #39                 // Method java/lang/StringBuilder.toString:()Ljava/lang/String;
      35: invokestatic  #146                // Method org/apache/dubbo/common/utils/ReflectUtils.forName:(Ljava/lang/String;)Ljava/lang/Class;
      38: goto          45
      41: aload_1
      42: invokestatic  #146                // Method org/apache/dubbo/common/utils/ReflectUtils.forName:(Ljava/lang/String;)Ljava/lang/Class;
      45: astore        4
      47: aload_0
      48: aload_3
      49: aload         4
      51: invokespecial #147                // Method verify:(Ljava/lang/Class;Ljava/lang/Class;)V
      54: return

  private void verify(java.lang.Class<?>, java.lang.Class<?>);
    Code:
       0: aload_1
       1: aload_2
       2: invokevirtual #148                // Method java/lang/Class.isAssignableFrom:(Ljava/lang/Class;)Z
       5: ifne          50
       8: new           #33                 // class java/lang/IllegalStateException
      11: dup
      12: new           #34                 // class java/lang/StringBuilder
      15: dup
      16: invokespecial #35                 // Method java/lang/StringBuilder."<init>":()V
      19: ldc           #149                // String The local implementation class
      21: invokevirtual #37                 // Method java/lang/StringBuilder.append:(Ljava/lang/String;)Ljava/lang/StringBuilder;
      24: aload_2
      25: invokevirtual #127                // Method java/lang/Class.getName:()Ljava/lang/String;
      28: invokevirtual #37                 // Method java/lang/StringBuilder.append:(Ljava/lang/String;)Ljava/lang/StringBuilder;
      31: ldc           #150                // String  not implement interface
      33: invokevirtual #37                 // Method java/lang/StringBuilder.append:(Ljava/lang/String;)Ljava/lang/StringBuilder;
      36: aload_1
      37: invokevirtual #127                // Method java/lang/Class.getName:()Ljava/lang/String;
      40: invokevirtual #37                 // Method java/lang/StringBuilder.append:(Ljava/lang/String;)Ljava/lang/StringBuilder;
      43: invokevirtual #39                 // Method java/lang/StringBuilder.toString:()Ljava/lang/String;
      46: invokespecial #40                 // Method java/lang/IllegalStateException."<init>":(Ljava/lang/String;)V
      49: athrow
      50: aload_2
      51: aload_1
      52: invokestatic  #151                // Method org/apache/dubbo/common/utils/ReflectUtils.findConstructor:(Ljava/lang/Class;Ljava/lang/Class;)Ljava/lang/reflect/Constructor;
      55: pop
      56: goto          114
      59: astore_3
      60: new           #33                 // class java/lang/IllegalStateException
      63: dup
      64: new           #34                 // class java/lang/StringBuilder
      67: dup
      68: invokespecial #35                 // Method java/lang/StringBuilder."<init>":()V
      71: ldc           #153                // String No such constructor \"public
      73: invokevirtual #37                 // Method java/lang/StringBuilder.append:(Ljava/lang/String;)Ljava/lang/StringBuilder;
      76: aload_2
      77: invokevirtual #154                // Method java/lang/Class.getSimpleName:()Ljava/lang/String;
      80: invokevirtual #37                 // Method java/lang/StringBuilder.append:(Ljava/lang/String;)Ljava/lang/StringBuilder;
      83: ldc           #155                // String (
      85: invokevirtual #37                 // Method java/lang/StringBuilder.append:(Ljava/lang/String;)Ljava/lang/StringBuilder;
      88: aload_1
      89: invokevirtual #127                // Method java/lang/Class.getName:()Ljava/lang/String;
      92: invokevirtual #37                 // Method java/lang/StringBuilder.append:(Ljava/lang/String;)Ljava/lang/StringBuilder;
      95: ldc           #156                // String )\" in local implementation class
      97: invokevirtual #37                 // Method java/lang/StringBuilder.append:(Ljava/lang/String;)Ljava/lang/StringBuilder;
     100: aload_2
     101: invokevirtual #127                // Method java/lang/Class.getName:()Ljava/lang/String;
     104: invokevirtual #37                 // Method java/lang/StringBuilder.append:(Ljava/lang/String;)Ljava/lang/StringBuilder;
     107: invokevirtual #39                 // Method java/lang/StringBuilder.toString:()Ljava/lang/String;
     110: invokespecial #40                 // Method java/lang/IllegalStateException."<init>":(Ljava/lang/String;)V
     113: athrow
     114: return
    Exception table:
       from    to  target type
          50    56    59   Class java/lang/NoSuchMethodException

  private void convertRegistryIdsToRegistries();
    Code:
       0: aload_0
       1: invokevirtual #157                // Method computeValidRegistryIds:()V
       4: aload_0
       5: getfield      #158                // Field registryIds:Ljava/lang/String;
       8: invokestatic  #117                // Method org/apache/dubbo/common/utils/StringUtils.isEmpty:(Ljava/lang/String;)Z
      11: ifeq          49
      14: aload_0
      15: getfield      #25                 // Field registries:Ljava/util/List;
      18: invokestatic  #159                // Method org/apache/dubbo/common/utils/CollectionUtils.isEmpty:(Ljava/util/Collection;)Z
      21: ifeq          89
      24: aload_0
      25: invokevirtual #52                 // Method getConfigManager:()Lorg/apache/dubbo/config/context/ConfigManager;
      28: invokevirtual #160                // Method org/apache/dubbo/config/context/ConfigManager.getDefaultRegistries:()Ljava/util/List;
      31: astore_1
      32: new           #5                  // class java/util/ArrayList
      35: dup
      36: aload_1
      37: invokespecial #161                // Method java/util/ArrayList."<init>":(Ljava/util/Collection;)V
      40: astore_1
      41: aload_0
      42: aload_1
      43: invokevirtual #162                // Method setRegistries:(Ljava/util/List;)V
      46: goto          89
      49: getstatic     #163                // Field org/apache/dubbo/common/constants/CommonConstants.COMMA_SPLIT_PATTERN:Ljava/util/regex/Pattern;
      52: aload_0
      53: getfield      #158                // Field registryIds:Ljava/lang/String;
      56: invokevirtual #164                // Method java/util/regex/Pattern.split:(Ljava/lang/CharSequence;)[Ljava/lang/String;
      59: astore_1
      60: new           #5                  // class java/util/ArrayList
      63: dup
      64: invokespecial #6                  // Method java/util/ArrayList."<init>":()V
      67: astore_2
      68: aload_1
      69: invokestatic  #69                 // Method java/util/Arrays.stream:([Ljava/lang/Object;)Ljava/util/stream/Stream;
      72: aload_0
      73: aload_2
      74: invokedynamic #165,  0            // InvokeDynamic #5:accept:(Lorg/apache/dubbo/config/AbstractInterfaceConfig;Ljava/util/List;)Ljava/util/function/Consumer;
      79: invokeinterface #166,  2          // InterfaceMethod java/util/stream/Stream.forEach:(Ljava/util/function/Consumer;)V
      84: aload_0
      85: aload_2
      86: invokevirtual #162                // Method setRegistries:(Ljava/util/List;)V
      89: return

  protected boolean notHasSelfRegistryProperty();
    Code:
       0: aload_0
       1: getfield      #25                 // Field registries:Ljava/util/List;
       4: invokestatic  #159                // Method org/apache/dubbo/common/utils/CollectionUtils.isEmpty:(Ljava/util/Collection;)Z
       7: ifeq          24
      10: aload_0
      11: getfield      #158                // Field registryIds:Ljava/lang/String;
      14: invokestatic  #117                // Method org/apache/dubbo/common/utils/StringUtils.isEmpty:(Ljava/lang/String;)Z
      17: ifeq          24
      20: iconst_1
      21: goto          25
      24: iconst_0
      25: ireturn

  protected void completeCompoundConfigs(org.apache.dubbo.config.AbstractInterfaceConfig);
    Code:
       0: aload_1
       1: ifnull        72
       4: aload_0
       5: getfield      #167                // Field application:Lorg/apache/dubbo/config/ApplicationConfig;
       8: ifnonnull     19
      11: aload_0
      12: aload_1
      13: invokevirtual #168                // Method getApplication:()Lorg/apache/dubbo/config/ApplicationConfig;
      16: invokevirtual #169                // Method setApplication:(Lorg/apache/dubbo/config/ApplicationConfig;)V
      19: aload_0
      20: getfield      #170                // Field module:Lorg/apache/dubbo/config/ModuleConfig;
      23: ifnonnull     34
      26: aload_0
      27: aload_1
      28: invokevirtual #171                // Method getModule:()Lorg/apache/dubbo/config/ModuleConfig;
      31: invokevirtual #172                // Method setModule:(Lorg/apache/dubbo/config/ModuleConfig;)V
      34: aload_0
      35: invokevirtual #173                // Method notHasSelfRegistryProperty:()Z
      38: ifeq          57
      41: aload_0
      42: aload_1
      43: invokevirtual #174                // Method getRegistries:()Ljava/util/List;
      46: invokevirtual #162                // Method setRegistries:(Ljava/util/List;)V
      49: aload_0
      50: aload_1
      51: invokevirtual #175                // Method getRegistryIds:()Ljava/lang/String;
      54: invokevirtual #176                // Method setRegistryIds:(Ljava/lang/String;)V
      57: aload_0
      58: getfield      #22                 // Field monitor:Lorg/apache/dubbo/config/MonitorConfig;
      61: ifnonnull     72
      64: aload_0
      65: aload_1
      66: invokevirtual #177                // Method getMonitor:()Lorg/apache/dubbo/config/MonitorConfig;
      69: invokevirtual #178                // Method setMonitor:(Lorg/apache/dubbo/config/MonitorConfig;)V
      72: aload_0
      73: getfield      #170                // Field module:Lorg/apache/dubbo/config/ModuleConfig;
      76: ifnull        115
      79: aload_0
      80: invokevirtual #173                // Method notHasSelfRegistryProperty:()Z
      83: ifeq          97
      86: aload_0
      87: aload_0
      88: getfield      #170                // Field module:Lorg/apache/dubbo/config/ModuleConfig;
      91: invokevirtual #179                // Method org/apache/dubbo/config/ModuleConfig.getRegistries:()Ljava/util/List;
      94: invokevirtual #162                // Method setRegistries:(Ljava/util/List;)V
      97: aload_0
      98: getfield      #22                 // Field monitor:Lorg/apache/dubbo/config/MonitorConfig;
     101: ifnonnull     115
     104: aload_0
     105: aload_0
     106: getfield      #170                // Field module:Lorg/apache/dubbo/config/ModuleConfig;
     109: invokevirtual #180                // Method org/apache/dubbo/config/ModuleConfig.getMonitor:()Lorg/apache/dubbo/config/MonitorConfig;
     112: invokevirtual #178                // Method setMonitor:(Lorg/apache/dubbo/config/MonitorConfig;)V
     115: aload_0
     116: getfield      #167                // Field application:Lorg/apache/dubbo/config/ApplicationConfig;
     119: ifnull        169
     122: aload_0
     123: invokevirtual #173                // Method notHasSelfRegistryProperty:()Z
     126: ifeq          151
     129: aload_0
     130: aload_0
     131: getfield      #167                // Field application:Lorg/apache/dubbo/config/ApplicationConfig;
     134: invokevirtual #181                // Method org/apache/dubbo/config/ApplicationConfig.getRegistries:()Ljava/util/List;
     137: invokevirtual #162                // Method setRegistries:(Ljava/util/List;)V
     140: aload_0
     141: aload_0
     142: getfield      #167                // Field application:Lorg/apache/dubbo/config/ApplicationConfig;
     145: invokevirtual #182                // Method org/apache/dubbo/config/ApplicationConfig.getRegistryIds:()Ljava/lang/String;
     148: invokevirtual #176                // Method setRegistryIds:(Ljava/lang/String;)V
     151: aload_0
     152: getfield      #22                 // Field monitor:Lorg/apache/dubbo/config/MonitorConfig;
     155: ifnonnull     169
     158: aload_0
     159: aload_0
     160: getfield      #167                // Field application:Lorg/apache/dubbo/config/ApplicationConfig;
     163: invokevirtual #183                // Method org/apache/dubbo/config/ApplicationConfig.getMonitor:()Lorg/apache/dubbo/config/MonitorConfig;
     166: invokevirtual #178                // Method setMonitor:(Lorg/apache/dubbo/config/MonitorConfig;)V
     169: return

  protected void computeValidRegistryIds();
    Code:
       0: aload_0
       1: getfield      #167                // Field application:Lorg/apache/dubbo/config/ApplicationConfig;
       4: ifnull        36
       7: aload_0
       8: invokevirtual #173                // Method notHasSelfRegistryProperty:()Z
      11: ifeq          36
      14: aload_0
      15: aload_0
      16: getfield      #167                // Field application:Lorg/apache/dubbo/config/ApplicationConfig;
      19: invokevirtual #181                // Method org/apache/dubbo/config/ApplicationConfig.getRegistries:()Ljava/util/List;
      22: invokevirtual #162                // Method setRegistries:(Ljava/util/List;)V
      25: aload_0
      26: aload_0
      27: getfield      #167                // Field application:Lorg/apache/dubbo/config/ApplicationConfig;
      30: invokevirtual #182                // Method org/apache/dubbo/config/ApplicationConfig.getRegistryIds:()Ljava/lang/String;
      33: invokevirtual #176                // Method setRegistryIds:(Ljava/lang/String;)V
      36: return

  public java.lang.String getLocal();
    Code:
       0: aload_0
       1: getfield      #139                // Field local:Ljava/lang/String;
       4: areturn

  public void setLocal(java.lang.Boolean);
    Code:
       0: aload_1
       1: ifnonnull     15
       4: aload_0
       5: aconst_null
       6: checkcast     #184                // class java/lang/String
       9: invokevirtual #185                // Method setLocal:(Ljava/lang/String;)V
      12: goto          23
      15: aload_0
      16: aload_1
      17: invokevirtual #186                // Method java/lang/Boolean.toString:()Ljava/lang/String;
      20: invokevirtual #185                // Method setLocal:(Ljava/lang/String;)V
      23: return

  public void setLocal(java.lang.String);
    Code:
       0: aload_0
       1: aload_1
       2: putfield      #139                // Field local:Ljava/lang/String;
       5: return

  public java.lang.String getStub();
    Code:
       0: aload_0
       1: getfield      #142                // Field stub:Ljava/lang/String;
       4: areturn

  public void setStub(java.lang.Boolean);
    Code:
       0: aload_1
       1: ifnonnull     15
       4: aload_0
       5: aconst_null
       6: checkcast     #184                // class java/lang/String
       9: invokevirtual #187                // Method setStub:(Ljava/lang/String;)V
      12: goto          23
      15: aload_0
      16: aload_1
      17: invokevirtual #186                // Method java/lang/Boolean.toString:()Ljava/lang/String;
      20: invokevirtual #187                // Method setStub:(Ljava/lang/String;)V
      23: return

  public void setStub(java.lang.String);
    Code:
       0: aload_0
       1: aload_1
       2: putfield      #142                // Field stub:Ljava/lang/String;
       5: return

  public java.lang.String getCluster();
    Code:
       0: aload_0
       1: getfield      #188                // Field cluster:Ljava/lang/String;
       4: areturn

  public void setCluster(java.lang.String);
    Code:
       0: aload_0
       1: aload_1
       2: putfield      #188                // Field cluster:Ljava/lang/String;
       5: return

  public java.lang.String getProxy();
    Code:
       0: aload_0
       1: getfield      #189                // Field proxy:Ljava/lang/String;
       4: areturn

  public void setProxy(java.lang.String);
    Code:
       0: aload_0
       1: aload_1
       2: putfield      #189                // Field proxy:Ljava/lang/String;
       5: return

  public java.lang.Integer getConnections();
    Code:
       0: aload_0
       1: getfield      #190                // Field connections:Ljava/lang/Integer;
       4: areturn

  public void setConnections(java.lang.Integer);
    Code:
       0: aload_0
       1: aload_1
       2: putfield      #190                // Field connections:Ljava/lang/Integer;
       5: return

  public java.lang.String getFilter();
    Code:
       0: aload_0
       1: getfield      #191                // Field filter:Ljava/lang/String;
       4: areturn

  public void setFilter(java.lang.String);
    Code:
       0: aload_0
       1: aload_1
       2: putfield      #191                // Field filter:Ljava/lang/String;
       5: return

  public java.lang.String getListener();
    Code:
       0: aload_0
       1: getfield      #192                // Field listener:Ljava/lang/String;
       4: areturn

  public void setListener(java.lang.String);
    Code:
       0: aload_0
       1: aload_1
       2: putfield      #192                // Field listener:Ljava/lang/String;
       5: return

  public java.lang.String getLayer();
    Code:
       0: aload_0
       1: getfield      #193                // Field layer:Ljava/lang/String;
       4: areturn

  public void setLayer(java.lang.String);
    Code:
       0: aload_0
       1: aload_1
       2: putfield      #193                // Field layer:Ljava/lang/String;
       5: return

  public org.apache.dubbo.config.ApplicationConfig getApplication();
    Code:
       0: aload_0
       1: getfield      #167                // Field application:Lorg/apache/dubbo/config/ApplicationConfig;
       4: ifnull        12
       7: aload_0
       8: getfield      #167                // Field application:Lorg/apache/dubbo/config/ApplicationConfig;
      11: areturn
      12: aload_0
      13: invokevirtual #52                 // Method getConfigManager:()Lorg/apache/dubbo/config/context/ConfigManager;
      16: invokevirtual #194                // Method org/apache/dubbo/config/context/ConfigManager.getApplicationOrElseThrow:()Lorg/apache/dubbo/config/ApplicationConfig;
      19: areturn

  public void setApplication(org.apache.dubbo.config.ApplicationConfig);
    Code:
       0: aload_0
       1: aload_1
       2: putfield      #167                // Field application:Lorg/apache/dubbo/config/ApplicationConfig;
       5: aload_1
       6: ifnull        17
       9: aload_0
      10: invokevirtual #52                 // Method getConfigManager:()Lorg/apache/dubbo/config/context/ConfigManager;
      13: aload_1
      14: invokevirtual #195                // Method org/apache/dubbo/config/context/ConfigManager.setApplication:(Lorg/apache/dubbo/config/ApplicationConfig;)V
      17: return

  public org.apache.dubbo.config.ModuleConfig getModule();
    Code:
       0: aload_0
       1: getfield      #170                // Field module:Lorg/apache/dubbo/config/ModuleConfig;
       4: ifnull        12
       7: aload_0
       8: getfield      #170                // Field module:Lorg/apache/dubbo/config/ModuleConfig;
      11: areturn
      12: aload_0
      13: invokevirtual #196                // Method getModuleConfigManager:()Lorg/apache/dubbo/config/context/ModuleConfigManager;
      16: invokevirtual #197                // Method org/apache/dubbo/config/context/ModuleConfigManager.getModule:()Ljava/util/Optional;
      19: aconst_null
      20: invokevirtual #54                 // Method java/util/Optional.orElse:(Ljava/lang/Object;)Ljava/lang/Object;
      23: checkcast     #198                // class org/apache/dubbo/config/ModuleConfig
      26: areturn

  public void setModule(org.apache.dubbo.config.ModuleConfig);
    Code:
       0: aload_0
       1: aload_1
       2: putfield      #170                // Field module:Lorg/apache/dubbo/config/ModuleConfig;
       5: aload_1
       6: ifnull        17
       9: aload_0
      10: invokevirtual #196                // Method getModuleConfigManager:()Lorg/apache/dubbo/config/context/ModuleConfigManager;
      13: aload_1
      14: invokevirtual #199                // Method org/apache/dubbo/config/context/ModuleConfigManager.setModule:(Lorg/apache/dubbo/config/ModuleConfig;)V
      17: return

  public org.apache.dubbo.config.RegistryConfig getRegistry();
    Code:
       0: aload_0
       1: getfield      #25                 // Field registries:Ljava/util/List;
       4: invokestatic  #159                // Method org/apache/dubbo/common/utils/CollectionUtils.isEmpty:(Ljava/util/Collection;)Z
       7: ifeq          14
      10: aconst_null
      11: goto          27
      14: aload_0
      15: getfield      #25                 // Field registries:Ljava/util/List;
      18: iconst_0
      19: invokeinterface #200,  2          // InterfaceMethod java/util/List.get:(I)Ljava/lang/Object;
      24: checkcast     #31                 // class org/apache/dubbo/config/RegistryConfig
      27: areturn

  public void setRegistry(org.apache.dubbo.config.RegistryConfig);
    Code:
       0: new           #5                  // class java/util/ArrayList
       3: dup
       4: iconst_1
       5: invokespecial #201                // Method java/util/ArrayList."<init>":(I)V
       8: astore_2
       9: aload_2
      10: aload_1
      11: invokeinterface #202,  2          // InterfaceMethod java/util/List.add:(Ljava/lang/Object;)Z
      16: pop
      17: aload_0
      18: aload_2
      19: invokevirtual #162                // Method setRegistries:(Ljava/util/List;)V
      22: return

  public java.util.List<org.apache.dubbo.config.RegistryConfig> getRegistries();
    Code:
       0: aload_0
       1: getfield      #25                 // Field registries:Ljava/util/List;
       4: areturn

  public void setRegistries(java.util.List<? extends org.apache.dubbo.config.RegistryConfig>);
    Code:
       0: aload_0
       1: aload_1
       2: putfield      #25                 // Field registries:Ljava/util/List;
       5: return

  public java.lang.String getRegistryIds();
    Code:
       0: aload_0
       1: getfield      #158                // Field registryIds:Ljava/lang/String;
       4: areturn

  public void setRegistryIds(java.lang.String);
    Code:
       0: aload_0
       1: aload_1
       2: putfield      #158                // Field registryIds:Ljava/lang/String;
       5: return

  public java.util.List<org.apache.dubbo.config.MethodConfig> getMethods();
    Code:
       0: aload_0
       1: getfield      #138                // Field methods:Ljava/util/List;
       4: areturn

  public void setMethods(java.util.List<? extends org.apache.dubbo.config.MethodConfig>);
    Code:
       0: aload_0
       1: aload_1
       2: ifnull        16
       5: new           #5                  // class java/util/ArrayList
       8: dup
       9: aload_1
      10: invokespecial #161                // Method java/util/ArrayList."<init>":(Ljava/util/Collection;)V
      13: goto          17
      16: aconst_null
      17: putfield      #138                // Field methods:Ljava/util/List;
      20: return

  public void addMethod(org.apache.dubbo.config.MethodConfig);
    Code:
       0: aload_0
       1: getfield      #138                // Field methods:Ljava/util/List;
       4: ifnonnull     18
       7: aload_0
       8: new           #5                  // class java/util/ArrayList
      11: dup
      12: invokespecial #6                  // Method java/util/ArrayList."<init>":()V
      15: putfield      #138                // Field methods:Ljava/util/List;
      18: aload_0
      19: getfield      #138                // Field methods:Ljava/util/List;
      22: aload_1
      23: invokeinterface #202,  2          // InterfaceMethod java/util/List.add:(Ljava/lang/Object;)Z
      28: pop
      29: return

  public org.apache.dubbo.config.MonitorConfig getMonitor();
    Code:
       0: aload_0
       1: getfield      #22                 // Field monitor:Lorg/apache/dubbo/config/MonitorConfig;
       4: ifnull        12
       7: aload_0
       8: getfield      #22                 // Field monitor:Lorg/apache/dubbo/config/MonitorConfig;
      11: areturn
      12: aload_0
      13: invokevirtual #52                 // Method getConfigManager:()Lorg/apache/dubbo/config/context/ConfigManager;
      16: invokevirtual #203                // Method org/apache/dubbo/config/context/ConfigManager.getMonitor:()Ljava/util/Optional;
      19: aconst_null
      20: invokevirtual #54                 // Method java/util/Optional.orElse:(Ljava/lang/Object;)Ljava/lang/Object;
      23: checkcast     #204                // class org/apache/dubbo/config/MonitorConfig
      26: areturn

  public void setMonitor(java.lang.String);
    Code:
       0: aload_0
       1: new           #204                // class org/apache/dubbo/config/MonitorConfig
       4: dup
       5: aload_1
       6: invokespecial #205                // Method org/apache/dubbo/config/MonitorConfig."<init>":(Ljava/lang/String;)V
       9: invokevirtual #178                // Method setMonitor:(Lorg/apache/dubbo/config/MonitorConfig;)V
      12: return

  public void setMonitor(org.apache.dubbo.config.MonitorConfig);
    Code:
       0: aload_0
       1: aload_1
       2: putfield      #22                 // Field monitor:Lorg/apache/dubbo/config/MonitorConfig;
       5: aload_1
       6: ifnull        17
       9: aload_0
      10: invokevirtual #52                 // Method getConfigManager:()Lorg/apache/dubbo/config/context/ConfigManager;
      13: aload_1
      14: invokevirtual #206                // Method org/apache/dubbo/config/context/ConfigManager.setMonitor:(Lorg/apache/dubbo/config/MonitorConfig;)V
      17: return

  public java.lang.String getOwner();
    Code:
       0: aload_0
       1: getfield      #207                // Field owner:Ljava/lang/String;
       4: areturn

  public void setOwner(java.lang.String);
    Code:
       0: aload_0
       1: aload_1
       2: putfield      #207                // Field owner:Ljava/lang/String;
       5: return

  public org.apache.dubbo.config.ConfigCenterConfig getConfigCenter();
    Code:
       0: aload_0
       1: getfield      #16                 // Field configCenter:Lorg/apache/dubbo/config/ConfigCenterConfig;
       4: ifnull        12
       7: aload_0
       8: getfield      #16                 // Field configCenter:Lorg/apache/dubbo/config/ConfigCenterConfig;
      11: areturn
      12: aload_0
      13: invokevirtual #52                 // Method getConfigManager:()Lorg/apache/dubbo/config/context/ConfigManager;
      16: invokevirtual #208                // Method org/apache/dubbo/config/context/ConfigManager.getConfigCenters:()Ljava/util/Collection;
      19: astore_1
      20: aload_1
      21: invokestatic  #26                 // Method org/apache/dubbo/common/utils/CollectionUtils.isNotEmpty:(Ljava/util/Collection;)Z
      24: ifeq          42
      27: aload_1
      28: invokeinterface #209,  1          // InterfaceMethod java/util/Collection.iterator:()Ljava/util/Iterator;
      33: invokeinterface #11,  1           // InterfaceMethod java/util/Iterator.next:()Ljava/lang/Object;
      38: checkcast     #210                // class org/apache/dubbo/config/ConfigCenterConfig
      41: areturn
      42: aconst_null
      43: areturn

  public void setConfigCenter(org.apache.dubbo.config.ConfigCenterConfig);
    Code:
       0: aload_0
       1: aload_1
       2: putfield      #16                 // Field configCenter:Lorg/apache/dubbo/config/ConfigCenterConfig;
       5: aload_1
       6: ifnull        17
       9: aload_0
      10: invokevirtual #52                 // Method getConfigManager:()Lorg/apache/dubbo/config/context/ConfigManager;
      13: aload_1
      14: invokevirtual #211                // Method org/apache/dubbo/config/context/ConfigManager.addConfigCenter:(Lorg/apache/dubbo/config/ConfigCenterConfig;)V
      17: return

  public java.lang.Integer getCallbacks();
    Code:
       0: aload_0
       1: getfield      #212                // Field callbacks:Ljava/lang/Integer;
       4: areturn

  public void setCallbacks(java.lang.Integer);
    Code:
       0: aload_0
       1: aload_1
       2: putfield      #212                // Field callbacks:Ljava/lang/Integer;
       5: return

  public java.lang.String getOnconnect();
    Code:
       0: aload_0
       1: getfield      #213                // Field onconnect:Ljava/lang/String;
       4: areturn

  public void setOnconnect(java.lang.String);
    Code:
       0: aload_0
       1: aload_1
       2: putfield      #213                // Field onconnect:Ljava/lang/String;
       5: return

  public java.lang.String getOndisconnect();
    Code:
       0: aload_0
       1: getfield      #214                // Field ondisconnect:Ljava/lang/String;
       4: areturn

  public void setOndisconnect(java.lang.String);
    Code:
       0: aload_0
       1: aload_1
       2: putfield      #214                // Field ondisconnect:Ljava/lang/String;
       5: return

  public java.lang.String getScope();
    Code:
       0: aload_0
       1: getfield      #215                // Field scope:Ljava/lang/String;
       4: areturn

  public void setScope(java.lang.String);
    Code:
       0: aload_0
       1: aload_1
       2: putfield      #215                // Field scope:Ljava/lang/String;
       5: return

  public org.apache.dubbo.config.MetadataReportConfig getMetadataReportConfig();
    Code:
       0: aload_0
       1: getfield      #19                 // Field metadataReportConfig:Lorg/apache/dubbo/config/MetadataReportConfig;
       4: ifnull        12
       7: aload_0
       8: getfield      #19                 // Field metadataReportConfig:Lorg/apache/dubbo/config/MetadataReportConfig;
      11: areturn
      12: aload_0
      13: invokevirtual #52                 // Method getConfigManager:()Lorg/apache/dubbo/config/context/ConfigManager;
      16: invokevirtual #216                // Method org/apache/dubbo/config/context/ConfigManager.getMetadataConfigs:()Ljava/util/Collection;
      19: astore_1
      20: aload_1
      21: invokestatic  #26                 // Method org/apache/dubbo/common/utils/CollectionUtils.isNotEmpty:(Ljava/util/Collection;)Z
      24: ifeq          42
      27: aload_1
      28: invokeinterface #209,  1          // InterfaceMethod java/util/Collection.iterator:()Ljava/util/Iterator;
      33: invokeinterface #11,  1           // InterfaceMethod java/util/Iterator.next:()Ljava/lang/Object;
      38: checkcast     #217                // class org/apache/dubbo/config/MetadataReportConfig
      41: areturn
      42: aconst_null
      43: areturn

  public void setMetadataReportConfig(org.apache.dubbo.config.MetadataReportConfig);
    Code:
       0: aload_0
       1: aload_1
       2: putfield      #19                 // Field metadataReportConfig:Lorg/apache/dubbo/config/MetadataReportConfig;
       5: aload_1
       6: ifnull        17
       9: aload_0
      10: invokevirtual #52                 // Method getConfigManager:()Lorg/apache/dubbo/config/context/ConfigManager;
      13: aload_1
      14: invokevirtual #218                // Method org/apache/dubbo/config/context/ConfigManager.addMetadataReport:(Lorg/apache/dubbo/config/MetadataReportConfig;)V
      17: return

  public java.lang.String getTag();
    Code:
       0: aload_0
       1: getfield      #219                // Field tag:Ljava/lang/String;
       4: areturn

  public void setTag(java.lang.String);
    Code:
       0: aload_0
       1: aload_1
       2: putfield      #219                // Field tag:Ljava/lang/String;
       5: return

  public java.lang.Boolean getAuth();
    Code:
       0: aload_0
       1: getfield      #220                // Field auth:Ljava/lang/Boolean;
       4: areturn

  public void setAuth(java.lang.Boolean);
    Code:
       0: aload_0
       1: aload_1
       2: putfield      #220                // Field auth:Ljava/lang/Boolean;
       5: return

  public org.apache.dubbo.config.SslConfig getSslConfig();
    Code:
       0: aload_0
       1: invokevirtual #52                 // Method getConfigManager:()Lorg/apache/dubbo/config/context/ConfigManager;
       4: invokevirtual #221                // Method org/apache/dubbo/config/context/ConfigManager.getSsl:()Ljava/util/Optional;
       7: aconst_null
       8: invokevirtual #54                 // Method java/util/Optional.orElse:(Ljava/lang/Object;)Ljava/lang/Object;
      11: checkcast     #222                // class org/apache/dubbo/config/SslConfig
      14: areturn

  public java.lang.Boolean getSingleton();
    Code:
       0: aload_0
       1: getfield      #223                // Field singleton:Ljava/lang/Boolean;
       4: areturn

  public void setSingleton(java.lang.Boolean);
    Code:
       0: aload_0
       1: aload_1
       2: putfield      #223                // Field singleton:Ljava/lang/Boolean;
       5: return

  protected void initServiceMetadata(org.apache.dubbo.config.AbstractInterfaceConfig);
    Code:
       0: aload_0
       1: getfield      #224                // Field serviceMetadata:Lorg/apache/dubbo/rpc/model/ServiceMetadata;
       4: aload_0
       5: aload_1
       6: invokevirtual #225                // Method getVersion:(Lorg/apache/dubbo/config/AbstractInterfaceConfig;)Ljava/lang/String;
       9: invokevirtual #226                // Method org/apache/dubbo/rpc/model/ServiceMetadata.setVersion:(Ljava/lang/String;)V
      12: aload_0
      13: getfield      #224                // Field serviceMetadata:Lorg/apache/dubbo/rpc/model/ServiceMetadata;
      16: aload_0
      17: aload_1
      18: invokevirtual #227                // Method getGroup:(Lorg/apache/dubbo/config/AbstractInterfaceConfig;)Ljava/lang/String;
      21: invokevirtual #228                // Method org/apache/dubbo/rpc/model/ServiceMetadata.setGroup:(Ljava/lang/String;)V
      24: aload_0
      25: getfield      #224                // Field serviceMetadata:Lorg/apache/dubbo/rpc/model/ServiceMetadata;
      28: aload_0
      29: aload_1
      30: invokevirtual #227                // Method getGroup:(Lorg/apache/dubbo/config/AbstractInterfaceConfig;)Ljava/lang/String;
      33: invokevirtual #229                // Method org/apache/dubbo/rpc/model/ServiceMetadata.setDefaultGroup:(Ljava/lang/String;)V
      36: aload_0
      37: getfield      #224                // Field serviceMetadata:Lorg/apache/dubbo/rpc/model/ServiceMetadata;
      40: aload_0
      41: invokevirtual #230                // Method getInterface:()Ljava/lang/String;
      44: invokevirtual #231                // Method org/apache/dubbo/rpc/model/ServiceMetadata.setServiceInterfaceName:(Ljava/lang/String;)V
      47: return

  public java.lang.String getGroup(org.apache.dubbo.config.AbstractInterfaceConfig);
    Code:
       0: aload_0
       1: invokevirtual #232                // Method getGroup:()Ljava/lang/String;
       4: invokestatic  #117                // Method org/apache/dubbo/common/utils/StringUtils.isEmpty:(Ljava/lang/String;)Z
       7: ifeq          28
      10: aload_1
      11: ifnull        21
      14: aload_1
      15: invokevirtual #232                // Method getGroup:()Ljava/lang/String;
      18: goto          32
      21: aload_0
      22: invokevirtual #232                // Method getGroup:()Ljava/lang/String;
      25: goto          32
      28: aload_0
      29: invokevirtual #232                // Method getGroup:()Ljava/lang/String;
      32: areturn

  public java.lang.String getVersion(org.apache.dubbo.config.AbstractInterfaceConfig);
    Code:
       0: aload_0
       1: invokevirtual #233                // Method getVersion:()Ljava/lang/String;
       4: invokestatic  #117                // Method org/apache/dubbo/common/utils/StringUtils.isEmpty:(Ljava/lang/String;)Z
       7: ifeq          28
      10: aload_1
      11: ifnull        21
      14: aload_1
      15: invokevirtual #233                // Method getVersion:()Ljava/lang/String;
      18: goto          32
      21: aload_0
      22: invokevirtual #233                // Method getVersion:()Ljava/lang/String;
      25: goto          32
      28: aload_0
      29: invokevirtual #233                // Method getVersion:()Ljava/lang/String;
      32: areturn

  public java.lang.String getVersion();
    Code:
       0: aload_0
       1: getfield      #234                // Field version:Ljava/lang/String;
       4: areturn

  public void setVersion(java.lang.String);
    Code:
       0: aload_0
       1: aload_1
       2: putfield      #234                // Field version:Ljava/lang/String;
       5: return

  public java.lang.String getGroup();
    Code:
       0: aload_0
       1: getfield      #235                // Field group:Ljava/lang/String;
       4: areturn

  public void setGroup(java.lang.String);
    Code:
       0: aload_0
       1: aload_1
       2: putfield      #235                // Field group:Ljava/lang/String;
       5: return

  public java.lang.String getInterface();
    Code:
       0: aload_0
       1: getfield      #77                 // Field interfaceName:Ljava/lang/String;
       4: areturn

  public void setInterface(java.lang.String);
    Code:
       0: aload_0
       1: aload_1
       2: putfield      #77                 // Field interfaceName:Ljava/lang/String;
       5: return

  public java.lang.ClassLoader getInterfaceClassLoader();
    Code:
       0: aload_0
       1: getfield      #236                // Field interfaceClassLoader:Ljava/lang/ClassLoader;
       4: areturn

  public void setInterfaceClassLoader(java.lang.ClassLoader);
    Code:
       0: aload_0
       1: aload_1
       2: putfield      #236                // Field interfaceClassLoader:Ljava/lang/ClassLoader;
       5: return

  private void lambda$convertRegistryIdsToRegistries$5(java.util.List, java.lang.String);
    Code:
       0: aload_1
       1: invokeinterface #110,  1          // InterfaceMethod java/util/List.stream:()Ljava/util/stream/Stream;
       6: aload_2
       7: invokedynamic #237,  0            // InvokeDynamic #6:test:(Ljava/lang/String;)Ljava/util/function/Predicate;
      12: invokeinterface #238,  2          // InterfaceMethod java/util/stream/Stream.noneMatch:(Ljava/util/function/Predicate;)Z
      17: ifeq          77
      20: aload_0
      21: invokevirtual #52                 // Method getConfigManager:()Lorg/apache/dubbo/config/context/ConfigManager;
      24: aload_2
      25: invokevirtual #239                // Method org/apache/dubbo/config/context/ConfigManager.getRegistry:(Ljava/lang/String;)Ljava/util/Optional;
      28: astore_3
      29: aload_3
      30: invokevirtual #240                // Method java/util/Optional.isPresent:()Z
      33: ifeq          50
      36: aload_1
      37: aload_3
      38: invokevirtual #241                // Method java/util/Optional.get:()Ljava/lang/Object;
      41: invokeinterface #202,  2          // InterfaceMethod java/util/List.add:(Ljava/lang/Object;)Z
      46: pop
      47: goto          77
      50: new           #33                 // class java/lang/IllegalStateException
      53: dup
      54: new           #34                 // class java/lang/StringBuilder
      57: dup
      58: invokespecial #35                 // Method java/lang/StringBuilder."<init>":()V
      61: ldc           #242                // String Registry not found:
      63: invokevirtual #37                 // Method java/lang/StringBuilder.append:(Ljava/lang/String;)Ljava/lang/StringBuilder;
      66: aload_2
      67: invokevirtual #37                 // Method java/lang/StringBuilder.append:(Ljava/lang/String;)Ljava/lang/StringBuilder;
      70: invokevirtual #39                 // Method java/lang/StringBuilder.toString:()Ljava/lang/String;
      73: invokespecial #40                 // Method java/lang/IllegalStateException."<init>":(Ljava/lang/String;)V
      76: athrow
      77: return

  private static boolean lambda$null$4(java.lang.String, org.apache.dubbo.config.RegistryConfig);
    Code:
       0: aload_1
       1: invokevirtual #243                // Method org/apache/dubbo/config/RegistryConfig.getId:()Ljava/lang/String;
       4: aload_0
       5: invokevirtual #244                // Method java/lang/String.equals:(Ljava/lang/Object;)Z
       8: ireturn

  private static boolean lambda$verifyMethodConfig$3(java.lang.String, java.lang.reflect.Method);
    Code:
       0: aload_1
       1: invokevirtual #86                 // Method java/lang/reflect/Method.getName:()Ljava/lang/String;
       4: aload_0
       5: invokevirtual #244                // Method java/lang/String.equals:(Ljava/lang/Object;)Z
       8: ireturn

  private boolean lambda$processExtraRefresh$2(java.lang.String, java.lang.Class, boolean, org.apache.dubbo.config.MethodConfig);
    Code:
       0: aload         4
       2: aload_1
       3: invokevirtual #245                // Method org/apache/dubbo/config/MethodConfig.setParentPrefix:(Ljava/lang/String;)V
       6: aload         4
       8: aload_0
       9: invokevirtual #14                 // Method getScopeModel:()Lorg/apache/dubbo/rpc/model/ModuleModel;
      12: invokevirtual #246                // Method org/apache/dubbo/config/MethodConfig.setScopeModel:(Lorg/apache/dubbo/rpc/model/ScopeModel;)V
      15: aload         4
      17: invokevirtual #247                // Method org/apache/dubbo/config/MethodConfig.refresh:()V
      20: aload_0
      21: aload         4
      23: aload_2
      24: iload_3
      25: invokevirtual #248                // Method verifyMethodConfig:(Lorg/apache/dubbo/config/MethodConfig;Ljava/lang/Class;Z)Z
      28: ireturn

  private static java.lang.String[] lambda$methods$1(int);
    Code:
       0: iload_0
       1: anewarray     #184                // class java/lang/String
       4: areturn

  private static void lambda$postProcessAfterScopeModelChanged$0(org.apache.dubbo.rpc.model.ApplicationModel, org.apache.dubbo.config.RegistryConfig);
    Code:
       0: aload_1
       1: invokevirtual #249                // Method org/apache/dubbo/config/RegistryConfig.getScopeModel:()Lorg/apache/dubbo/rpc/model/ScopeModel;
       4: aload_0
       5: if_acmpeq     13
       8: aload_1
       9: aload_0
      10: invokevirtual #250                // Method org/apache/dubbo/config/RegistryConfig.setScopeModel:(Lorg/apache/dubbo/rpc/model/ScopeModel;)V
      13: return
}
