Compiled from "AbstractConfig.java"
public abstract class org.apache.dubbo.config.AbstractConfig implements java.io.Serializable {
  protected static final org.apache.dubbo.common.logger.ErrorTypeAwareLogger logger;

  private static final long serialVersionUID;

  private static final java.util.concurrent.ConcurrentMap<java.lang.Class, java.lang.String> tagNameCache;

  private static final java.util.concurrent.ConcurrentMap<java.lang.Class, java.util.List<java.lang.reflect.Method>> attributedMethodCache;

  private static final java.lang.String[] SUFFIXES;

  private java.lang.String id;

  protected final java.util.concurrent.atomic.AtomicBoolean refreshed;

  protected java.lang.Boolean isDefault;

  private volatile transient org.apache.dubbo.rpc.model.ScopeModel scopeModel;

  public org.apache.dubbo.config.AbstractConfig();
    Code:
       0: aload_0
       1: aconst_null
       2: invokespecial #3                  // Method "<init>":(Lorg/apache/dubbo/rpc/model/ScopeModel;)V
       5: return

  public org.apache.dubbo.config.AbstractConfig(org.apache.dubbo.rpc.model.ScopeModel);
    Code:
       0: aload_0
       1: invokespecial #4                  // Method java/lang/Object."<init>":()V
       4: aload_0
       5: new           #5                  // class java/util/concurrent/atomic/AtomicBoolean
       8: dup
       9: iconst_0
      10: invokespecial #6                  // Method java/util/concurrent/atomic/AtomicBoolean."<init>":(Z)V
      13: putfield      #7                  // Field refreshed:Ljava/util/concurrent/atomic/AtomicBoolean;
      16: aload_0
      17: aload_1
      18: invokevirtual #8                  // Method setScopeModel:(Lorg/apache/dubbo/rpc/model/ScopeModel;)V
      21: return

  public static java.lang.String getTagName(java.lang.Class<?>);
    Code:
       0: getstatic     #9                  // Field tagNameCache:Ljava/util/concurrent/ConcurrentMap;
       3: aload_0
       4: aload_0
       5: invokedynamic #10,  0             // InvokeDynamic #0:apply:(Ljava/lang/Class;)Ljava/util/function/Function;
      10: invokestatic  #11                 // Method org/apache/dubbo/common/utils/ConcurrentHashMapUtils.computeIfAbsent:(Ljava/util/concurrent/ConcurrentMap;Ljava/lang/Object;Ljava/util/function/Function;)Ljava/lang/Object;
      13: checkcast     #12                 // class java/lang/String
      16: areturn

  public static java.lang.String getPluralTagName(java.lang.Class<?>);
    Code:
       0: aload_0
       1: invokestatic  #13                 // Method getTagName:(Ljava/lang/Class;)Ljava/lang/String;
       4: astore_1
       5: aload_1
       6: ldc           #14                 // String y
       8: invokevirtual #15                 // Method java/lang/String.endsWith:(Ljava/lang/String;)Z
      11: ifeq          44
      14: new           #16                 // class java/lang/StringBuilder
      17: dup
      18: invokespecial #17                 // Method java/lang/StringBuilder."<init>":()V
      21: aload_1
      22: iconst_0
      23: aload_1
      24: invokevirtual #18                 // Method java/lang/String.length:()I
      27: iconst_1
      28: isub
      29: invokevirtual #19                 // Method java/lang/String.substring:(II)Ljava/lang/String;
      32: invokevirtual #20                 // Method java/lang/StringBuilder.append:(Ljava/lang/String;)Ljava/lang/StringBuilder;
      35: ldc           #21                 // String ies
      37: invokevirtual #20                 // Method java/lang/StringBuilder.append:(Ljava/lang/String;)Ljava/lang/StringBuilder;
      40: invokevirtual #22                 // Method java/lang/StringBuilder.toString:()Ljava/lang/String;
      43: areturn
      44: aload_1
      45: ldc           #23                 // String s
      47: invokevirtual #15                 // Method java/lang/String.endsWith:(Ljava/lang/String;)Z
      50: ifeq          73
      53: new           #16                 // class java/lang/StringBuilder
      56: dup
      57: invokespecial #17                 // Method java/lang/StringBuilder."<init>":()V
      60: aload_1
      61: invokevirtual #20                 // Method java/lang/StringBuilder.append:(Ljava/lang/String;)Ljava/lang/StringBuilder;
      64: ldc           #24                 // String es
      66: invokevirtual #20                 // Method java/lang/StringBuilder.append:(Ljava/lang/String;)Ljava/lang/StringBuilder;
      69: invokevirtual #22                 // Method java/lang/StringBuilder.toString:()Ljava/lang/String;
      72: areturn
      73: new           #16                 // class java/lang/StringBuilder
      76: dup
      77: invokespecial #17                 // Method java/lang/StringBuilder."<init>":()V
      80: aload_1
      81: invokevirtual #20                 // Method java/lang/StringBuilder.append:(Ljava/lang/String;)Ljava/lang/StringBuilder;
      84: ldc           #23                 // String s
      86: invokevirtual #20                 // Method java/lang/StringBuilder.append:(Ljava/lang/String;)Ljava/lang/StringBuilder;
      89: invokevirtual #22                 // Method java/lang/StringBuilder.toString:()Ljava/lang/String;
      92: areturn

  public static void appendParameters(java.util.Map<java.lang.String, java.lang.String>, java.lang.Object);
    Code:
       0: aload_0
       1: aload_1
       2: aconst_null
       3: invokestatic  #25                 // Method appendParameters:(Ljava/util/Map;Ljava/lang/Object;Ljava/lang/String;)V
       6: return

  public static void appendParameters(java.util.Map<java.lang.String, java.lang.String>, java.lang.Object, java.lang.String);
    Code:
       0: aload_0
       1: aload_1
       2: aload_2
       3: iconst_1
       4: invokestatic  #26                 // Method appendParameters0:(Ljava/util/Map;Ljava/lang/Object;Ljava/lang/String;Z)V
       7: return

  public static void appendAttributes(java.util.Map<java.lang.String, java.lang.String>, java.lang.Object);
    Code:
       0: aload_0
       1: aload_1
       2: aconst_null
       3: iconst_0
       4: invokestatic  #26                 // Method appendParameters0:(Ljava/util/Map;Ljava/lang/Object;Ljava/lang/String;Z)V
       7: return

  public static void appendAttributes(java.util.Map<java.lang.String, java.lang.String>, java.lang.Object, java.lang.String);
    Code:
       0: aload_0
       1: aload_1
       2: aload_2
       3: iconst_0
       4: invokestatic  #26                 // Method appendParameters0:(Ljava/util/Map;Ljava/lang/Object;Ljava/lang/String;Z)V
       7: return

  private static void appendParameters0(java.util.Map<java.lang.String, java.lang.String>, java.lang.Object, java.lang.String, boolean);
    Code:
       0: aload_1
       1: ifnonnull     5
       4: return
       5: aload_1
       6: invokevirtual #27                 // Method java/lang/Object.getClass:()Ljava/lang/Class;
       9: invokestatic  #28                 // Method getBeanInfo:(Ljava/lang/Class;)Ljava/beans/BeanInfo;
      12: astore        4
      14: aload         4
      16: invokeinterface #29,  1           // InterfaceMethod java/beans/BeanInfo.getMethodDescriptors:()[Ljava/beans/MethodDescriptor;
      21: astore        5
      23: aload         5
      25: arraylength
      26: istore        6
      28: iconst_0
      29: istore        7
      31: iload         7
      33: iload         6
      35: if_icmpge     646
      38: aload         5
      40: iload         7
      42: aaload
      43: astore        8
      45: aload         8
      47: invokevirtual #30                 // Method java/beans/MethodDescriptor.getMethod:()Ljava/lang/reflect/Method;
      50: astore        9
      52: aload         9
      54: invokevirtual #31                 // Method java/lang/reflect/Method.getName:()Ljava/lang/String;
      57: astore        10
      59: aload         9
      61: invokestatic  #32                 // InterfaceMethod org/apache/dubbo/common/utils/MethodUtils.isGetter:(Ljava/lang/reflect/Method;)Z
      64: ifeq          451
      67: aload         9
      69: invokevirtual #33                 // Method java/lang/reflect/Method.getReturnType:()Ljava/lang/Class;
      72: ldc           #34                 // class java/lang/Object
      74: if_acmpne     80
      77: goto          640
      80: aload         9
      82: ldc           #35                 // class org/apache/dubbo/config/support/Parameter
      84: invokevirtual #36                 // Method java/lang/reflect/Method.getAnnotation:(Ljava/lang/Class;)Ljava/lang/annotation/Annotation;
      87: checkcast     #35                 // class org/apache/dubbo/config/support/Parameter
      90: astore        12
      92: iload_3
      93: ifeq          154
      96: aload         12
      98: ifnull        114
     101: aload         12
     103: invokeinterface #37,  1           // InterfaceMethod org/apache/dubbo/config/support/Parameter.excluded:()Z
     108: ifeq          114
     111: goto          640
     114: aload         12
     116: ifnull        144
     119: aload         12
     121: invokeinterface #38,  1           // InterfaceMethod org/apache/dubbo/config/support/Parameter.key:()Ljava/lang/String;
     126: invokevirtual #18                 // Method java/lang/String.length:()I
     129: ifle          144
     132: aload         12
     134: invokeinterface #38,  1           // InterfaceMethod org/apache/dubbo/config/support/Parameter.key:()Ljava/lang/String;
     139: astore        11
     141: goto          188
     144: aload         10
     146: invokestatic  #39                 // Method calculatePropertyFromGetter:(Ljava/lang/String;)Ljava/lang/String;
     149: astore        11
     151: goto          188
     154: aload         12
     156: ifnull        172
     159: aload         12
     161: invokeinterface #40,  1           // InterfaceMethod org/apache/dubbo/config/support/Parameter.attribute:()Z
     166: ifne          172
     169: goto          640
     172: aload         10
     174: invokestatic  #41                 // Method calculateAttributeFromGetter:(Ljava/lang/String;)Ljava/lang/String;
     177: astore        13
     179: aload         13
     181: ldc           #42                 // String -
     183: invokestatic  #43                 // Method org/apache/dubbo/common/utils/StringUtils.convertToSplitName:(Ljava/lang/String;Ljava/lang/String;)Ljava/lang/String;
     186: astore        11
     188: aload         9
     190: aload_1
     191: iconst_0
     192: anewarray     #34                 // class java/lang/Object
     195: invokevirtual #44                 // Method java/lang/reflect/Method.invoke:(Ljava/lang/Object;[Ljava/lang/Object;)Ljava/lang/Object;
     198: astore        13
     200: aload         13
     202: invokestatic  #45                 // Method java/lang/String.valueOf:(Ljava/lang/Object;)Ljava/lang/String;
     205: invokevirtual #46                 // Method java/lang/String.trim:()Ljava/lang/String;
     208: astore        14
     210: aload         13
     212: ifnull        386
     215: aload         14
     217: invokevirtual #18                 // Method java/lang/String.length:()I
     220: ifle          386
     223: iload_3
     224: ifeq          249
     227: aload         12
     229: ifnull        249
     232: aload         12
     234: invokeinterface #47,  1           // InterfaceMethod org/apache/dubbo/config/support/Parameter.escaped:()Z
     239: ifeq          249
     242: aload         14
     244: invokestatic  #48                 // Method org/apache/dubbo/common/URL.encode:(Ljava/lang/String;)Ljava/lang/String;
     247: astore        14
     249: aload         12
     251: ifnull        335
     254: aload         12
     256: invokeinterface #49,  1           // InterfaceMethod org/apache/dubbo/config/support/Parameter.append:()Z
     261: ifeq          335
     264: aload_0
     265: aload         11
     267: invokeinterface #50,  2           // InterfaceMethod java/util/Map.get:(Ljava/lang/Object;)Ljava/lang/Object;
     272: checkcast     #12                 // class java/lang/String
     275: astore        15
     277: aload         15
     279: ifnull        335
     282: aload         15
     284: invokevirtual #18                 // Method java/lang/String.length:()I
     287: ifle          335
     290: new           #16                 // class java/lang/StringBuilder
     293: dup
     294: invokespecial #17                 // Method java/lang/StringBuilder."<init>":()V
     297: aload         15
     299: invokevirtual #20                 // Method java/lang/StringBuilder.append:(Ljava/lang/String;)Ljava/lang/StringBuilder;
     302: ldc           #51                 // String ,
     304: invokevirtual #20                 // Method java/lang/StringBuilder.append:(Ljava/lang/String;)Ljava/lang/StringBuilder;
     307: aload         14
     309: invokevirtual #20                 // Method java/lang/StringBuilder.append:(Ljava/lang/String;)Ljava/lang/StringBuilder;
     312: invokevirtual #22                 // Method java/lang/StringBuilder.toString:()Ljava/lang/String;
     315: astore        14
     317: aload         14
     319: bipush        44
     321: invokestatic  #52                 // Method org/apache/dubbo/common/utils/StringUtils.splitToSet:(Ljava/lang/String;C)Ljava/util/Set;
     324: astore        16
     326: aload         16
     328: ldc           #51                 // String ,
     330: invokestatic  #53                 // Method org/apache/dubbo/common/utils/StringUtils.join:(Ljava/util/Collection;Ljava/lang/String;)Ljava/lang/String;
     333: astore        14
     335: aload_2
     336: ifnull        372
     339: aload_2
     340: invokevirtual #18                 // Method java/lang/String.length:()I
     343: ifle          372
     346: new           #16                 // class java/lang/StringBuilder
     349: dup
     350: invokespecial #17                 // Method java/lang/StringBuilder."<init>":()V
     353: aload_2
     354: invokevirtual #20                 // Method java/lang/StringBuilder.append:(Ljava/lang/String;)Ljava/lang/StringBuilder;
     357: ldc           #54                 // String .
     359: invokevirtual #20                 // Method java/lang/StringBuilder.append:(Ljava/lang/String;)Ljava/lang/StringBuilder;
     362: aload         11
     364: invokevirtual #20                 // Method java/lang/StringBuilder.append:(Ljava/lang/String;)Ljava/lang/StringBuilder;
     367: invokevirtual #22                 // Method java/lang/StringBuilder.toString:()Ljava/lang/String;
     370: astore        11
     372: aload_0
     373: aload         11
     375: aload         14
     377: invokeinterface #55,  3           // InterfaceMethod java/util/Map.put:(Ljava/lang/Object;Ljava/lang/Object;)Ljava/lang/Object;
     382: pop
     383: goto          448
     386: iload_3
     387: ifeq          448
     390: aload         12
     392: ifnull        448
     395: aload         12
     397: invokeinterface #56,  1           // InterfaceMethod org/apache/dubbo/config/support/Parameter.required:()Z
     402: ifeq          448
     405: new           #57                 // class java/lang/IllegalStateException
     408: dup
     409: new           #16                 // class java/lang/StringBuilder
     412: dup
     413: invokespecial #17                 // Method java/lang/StringBuilder."<init>":()V
     416: aload_1
     417: invokevirtual #27                 // Method java/lang/Object.getClass:()Ljava/lang/Class;
     420: invokevirtual #58                 // Method java/lang/Class.getSimpleName:()Ljava/lang/String;
     423: invokevirtual #20                 // Method java/lang/StringBuilder.append:(Ljava/lang/String;)Ljava/lang/StringBuilder;
     426: ldc           #54                 // String .
     428: invokevirtual #20                 // Method java/lang/StringBuilder.append:(Ljava/lang/String;)Ljava/lang/StringBuilder;
     431: aload         11
     433: invokevirtual #20                 // Method java/lang/StringBuilder.append:(Ljava/lang/String;)Ljava/lang/StringBuilder;
     436: ldc           #59                 // String  == null
     438: invokevirtual #20                 // Method java/lang/StringBuilder.append:(Ljava/lang/String;)Ljava/lang/StringBuilder;
     441: invokevirtual #22                 // Method java/lang/StringBuilder.toString:()Ljava/lang/String;
     444: invokespecial #60                 // Method java/lang/IllegalStateException."<init>":(Ljava/lang/String;)V
     447: athrow
     448: goto          602
     451: aload         9
     453: invokestatic  #61                 // Method isParametersGetter:(Ljava/lang/reflect/Method;)Z
     456: ifeq          530
     459: aload         9
     461: aload_1
     462: iconst_0
     463: anewarray     #34                 // class java/lang/Object
     466: invokevirtual #44                 // Method java/lang/reflect/Method.invoke:(Ljava/lang/Object;[Ljava/lang/Object;)Ljava/lang/Object;
     469: checkcast     #62                 // class java/util/Map
     472: astore        11
     474: aload         11
     476: aload_2
     477: invokestatic  #63                 // Method convert:(Ljava/util/Map;Ljava/lang/String;)Ljava/util/Map;
     480: astore        11
     482: iload_3
     483: ifeq          497
     486: aload_0
     487: aload         11
     489: invokeinterface #64,  2           // InterfaceMethod java/util/Map.putAll:(Ljava/util/Map;)V
     494: goto          527
     497: aload         10
     499: invokestatic  #39                 // Method calculatePropertyFromGetter:(Ljava/lang/String;)Ljava/lang/String;
     502: astore        12
     504: aload         11
     506: invokestatic  #65                 // Method org/apache/dubbo/common/utils/StringUtils.encodeParameters:(Ljava/util/Map;)Ljava/lang/String;
     509: astore        13
     511: aload         13
     513: ifnull        527
     516: aload_0
     517: aload         12
     519: aload         13
     521: invokeinterface #55,  3           // InterfaceMethod java/util/Map.put:(Ljava/lang/Object;Ljava/lang/Object;)Ljava/lang/Object;
     526: pop
     527: goto          602
     530: aload_1
     531: aload         9
     533: invokestatic  #66                 // Method isNestedGetter:(Ljava/lang/Object;Ljava/lang/reflect/Method;)Z
     536: ifeq          602
     539: aload         9
     541: aload_1
     542: iconst_0
     543: anewarray     #34                 // class java/lang/Object
     546: invokevirtual #44                 // Method java/lang/reflect/Method.invoke:(Ljava/lang/Object;[Ljava/lang/Object;)Ljava/lang/Object;
     549: astore        11
     551: aload         9
     553: invokestatic  #67                 // InterfaceMethod org/apache/dubbo/common/utils/MethodUtils.extractFieldName:(Ljava/lang/reflect/Method;)Ljava/lang/String;
     556: astore        12
     558: aload_2
     559: ifnonnull     567
     562: aload         12
     564: goto          591
     567: new           #16                 // class java/lang/StringBuilder
     570: dup
     571: invokespecial #17                 // Method java/lang/StringBuilder."<init>":()V
     574: aload_2
     575: invokevirtual #20                 // Method java/lang/StringBuilder.append:(Ljava/lang/String;)Ljava/lang/StringBuilder;
     578: ldc           #54                 // String .
     580: invokevirtual #20                 // Method java/lang/StringBuilder.append:(Ljava/lang/String;)Ljava/lang/StringBuilder;
     583: aload         12
     585: invokevirtual #20                 // Method java/lang/StringBuilder.append:(Ljava/lang/String;)Ljava/lang/StringBuilder;
     588: invokevirtual #22                 // Method java/lang/StringBuilder.toString:()Ljava/lang/String;
     591: astore        13
     593: aload_0
     594: aload         11
     596: aload         13
     598: iload_3
     599: invokestatic  #26                 // Method appendParameters0:(Ljava/util/Map;Ljava/lang/Object;Ljava/lang/String;Z)V
     602: goto          640
     605: astore        10
     607: new           #57                 // class java/lang/IllegalStateException
     610: dup
     611: new           #16                 // class java/lang/StringBuilder
     614: dup
     615: invokespecial #17                 // Method java/lang/StringBuilder."<init>":()V
     618: ldc           #69                 // String Append parameters failed:
     620: invokevirtual #20                 // Method java/lang/StringBuilder.append:(Ljava/lang/String;)Ljava/lang/StringBuilder;
     623: aload         10
     625: invokevirtual #70                 // Method java/lang/Exception.getMessage:()Ljava/lang/String;
     628: invokevirtual #20                 // Method java/lang/StringBuilder.append:(Ljava/lang/String;)Ljava/lang/StringBuilder;
     631: invokevirtual #22                 // Method java/lang/StringBuilder.toString:()Ljava/lang/String;
     634: aload         10
     636: invokespecial #71                 // Method java/lang/IllegalStateException."<init>":(Ljava/lang/String;Ljava/lang/Throwable;)V
     639: athrow
     640: iinc          7, 1
     643: goto          31
     646: return
    Exception table:
       from    to  target type
          52    77   605   Class java/lang/Exception
          80   111   605   Class java/lang/Exception
         114   169   605   Class java/lang/Exception
         172   602   605   Class java/lang/Exception

  protected static java.lang.String extractPropertyName(java.lang.String);
    Code:
       0: aload_0
       1: ldc           #72                 // String set
       3: invokevirtual #18                 // Method java/lang/String.length:()I
       6: invokevirtual #73                 // Method java/lang/String.substring:(I)Ljava/lang/String;
       9: astore_1
      10: new           #16                 // class java/lang/StringBuilder
      13: dup
      14: invokespecial #17                 // Method java/lang/StringBuilder."<init>":()V
      17: aload_1
      18: iconst_0
      19: iconst_1
      20: invokevirtual #19                 // Method java/lang/String.substring:(II)Ljava/lang/String;
      23: invokevirtual #74                 // Method java/lang/String.toLowerCase:()Ljava/lang/String;
      26: invokevirtual #20                 // Method java/lang/StringBuilder.append:(Ljava/lang/String;)Ljava/lang/StringBuilder;
      29: aload_1
      30: iconst_1
      31: invokevirtual #73                 // Method java/lang/String.substring:(I)Ljava/lang/String;
      34: invokevirtual #20                 // Method java/lang/StringBuilder.append:(Ljava/lang/String;)Ljava/lang/StringBuilder;
      37: invokevirtual #22                 // Method java/lang/StringBuilder.toString:()Ljava/lang/String;
      40: astore_1
      41: aload_1
      42: areturn

  private static java.lang.String calculatePropertyToGetter(java.lang.String);
    Code:
       0: new           #16                 // class java/lang/StringBuilder
       3: dup
       4: invokespecial #17                 // Method java/lang/StringBuilder."<init>":()V
       7: ldc           #75                 // String get
       9: invokevirtual #20                 // Method java/lang/StringBuilder.append:(Ljava/lang/String;)Ljava/lang/StringBuilder;
      12: aload_0
      13: iconst_0
      14: iconst_1
      15: invokevirtual #19                 // Method java/lang/String.substring:(II)Ljava/lang/String;
      18: invokevirtual #76                 // Method java/lang/String.toUpperCase:()Ljava/lang/String;
      21: invokevirtual #20                 // Method java/lang/StringBuilder.append:(Ljava/lang/String;)Ljava/lang/StringBuilder;
      24: aload_0
      25: iconst_1
      26: invokevirtual #73                 // Method java/lang/String.substring:(I)Ljava/lang/String;
      29: invokevirtual #20                 // Method java/lang/StringBuilder.append:(Ljava/lang/String;)Ljava/lang/StringBuilder;
      32: invokevirtual #22                 // Method java/lang/StringBuilder.toString:()Ljava/lang/String;
      35: areturn

  private static java.lang.String calculatePropertyToSetter(java.lang.String);
    Code:
       0: new           #16                 // class java/lang/StringBuilder
       3: dup
       4: invokespecial #17                 // Method java/lang/StringBuilder."<init>":()V
       7: ldc           #72                 // String set
       9: invokevirtual #20                 // Method java/lang/StringBuilder.append:(Ljava/lang/String;)Ljava/lang/StringBuilder;
      12: aload_0
      13: iconst_0
      14: iconst_1
      15: invokevirtual #19                 // Method java/lang/String.substring:(II)Ljava/lang/String;
      18: invokevirtual #76                 // Method java/lang/String.toUpperCase:()Ljava/lang/String;
      21: invokevirtual #20                 // Method java/lang/StringBuilder.append:(Ljava/lang/String;)Ljava/lang/StringBuilder;
      24: aload_0
      25: iconst_1
      26: invokevirtual #73                 // Method java/lang/String.substring:(I)Ljava/lang/String;
      29: invokevirtual #20                 // Method java/lang/StringBuilder.append:(Ljava/lang/String;)Ljava/lang/StringBuilder;
      32: invokevirtual #22                 // Method java/lang/StringBuilder.toString:()Ljava/lang/String;
      35: areturn

  private static java.lang.String calculatePropertyFromGetter(java.lang.String);
    Code:
       0: aload_0
       1: ldc           #75                 // String get
       3: invokevirtual #77                 // Method java/lang/String.startsWith:(Ljava/lang/String;)Z
       6: ifeq          13
       9: iconst_3
      10: goto          14
      13: iconst_2
      14: istore_1
      15: new           #16                 // class java/lang/StringBuilder
      18: dup
      19: invokespecial #17                 // Method java/lang/StringBuilder."<init>":()V
      22: aload_0
      23: iload_1
      24: iload_1
      25: iconst_1
      26: iadd
      27: invokevirtual #19                 // Method java/lang/String.substring:(II)Ljava/lang/String;
      30: invokevirtual #74                 // Method java/lang/String.toLowerCase:()Ljava/lang/String;
      33: invokevirtual #20                 // Method java/lang/StringBuilder.append:(Ljava/lang/String;)Ljava/lang/StringBuilder;
      36: aload_0
      37: iload_1
      38: iconst_1
      39: iadd
      40: invokevirtual #73                 // Method java/lang/String.substring:(I)Ljava/lang/String;
      43: invokevirtual #20                 // Method java/lang/StringBuilder.append:(Ljava/lang/String;)Ljava/lang/StringBuilder;
      46: invokevirtual #22                 // Method java/lang/StringBuilder.toString:()Ljava/lang/String;
      49: ldc           #54                 // String .
      51: invokestatic  #78                 // Method org/apache/dubbo/common/utils/StringUtils.camelToSplitName:(Ljava/lang/String;Ljava/lang/String;)Ljava/lang/String;
      54: areturn

  private static java.lang.String calculateAttributeFromGetter(java.lang.String);
    Code:
       0: aload_0
       1: ldc           #75                 // String get
       3: invokevirtual #77                 // Method java/lang/String.startsWith:(Ljava/lang/String;)Z
       6: ifeq          13
       9: iconst_3
      10: goto          14
      13: iconst_2
      14: istore_1
      15: new           #16                 // class java/lang/StringBuilder
      18: dup
      19: invokespecial #17                 // Method java/lang/StringBuilder."<init>":()V
      22: aload_0
      23: iload_1
      24: iload_1
      25: iconst_1
      26: iadd
      27: invokevirtual #19                 // Method java/lang/String.substring:(II)Ljava/lang/String;
      30: invokevirtual #74                 // Method java/lang/String.toLowerCase:()Ljava/lang/String;
      33: invokevirtual #20                 // Method java/lang/StringBuilder.append:(Ljava/lang/String;)Ljava/lang/StringBuilder;
      36: aload_0
      37: iload_1
      38: iconst_1
      39: iadd
      40: invokevirtual #73                 // Method java/lang/String.substring:(I)Ljava/lang/String;
      43: invokevirtual #20                 // Method java/lang/StringBuilder.append:(Ljava/lang/String;)Ljava/lang/StringBuilder;
      46: invokevirtual #22                 // Method java/lang/StringBuilder.toString:()Ljava/lang/String;
      49: areturn

  private static void invokeSetParameters(java.lang.Class, java.lang.Object, java.util.Map);
    Code:
       0: aload_0
       1: ldc           #79                 // String setParameters
       3: iconst_1
       4: anewarray     #12                 // class java/lang/String
       7: dup
       8: iconst_0
       9: ldc           #62                 // class java/util/Map
      11: invokevirtual #80                 // Method java/lang/Class.getName:()Ljava/lang/String;
      14: aastore
      15: invokestatic  #81                 // Method org/apache/dubbo/common/utils/ReflectUtils.findMethodByMethodSignature:(Ljava/lang/Class;Ljava/lang/String;[Ljava/lang/String;)Ljava/lang/reflect/Method;
      18: astore_3
      19: aload_3
      20: ifnull        44
      23: aload_3
      24: invokestatic  #82                 // Method isParametersSetter:(Ljava/lang/reflect/Method;)Z
      27: ifeq          44
      30: aload_3
      31: aload_1
      32: iconst_1
      33: anewarray     #34                 // class java/lang/Object
      36: dup
      37: iconst_0
      38: aload_2
      39: aastore
      40: invokevirtual #44                 // Method java/lang/reflect/Method.invoke:(Ljava/lang/Object;[Ljava/lang/Object;)Ljava/lang/Object;
      43: pop
      44: goto          48
      47: astore_3
      48: return
    Exception table:
       from    to  target type
           0    44    47   Class java/lang/Throwable

  private static java.util.Map<java.lang.String, java.lang.String> invokeGetParameters(java.lang.Class, java.lang.Object);
    Code:
       0: aload_0
       1: ldc           #84                 // String getParameters
       3: aconst_null
       4: invokestatic  #81                 // Method org/apache/dubbo/common/utils/ReflectUtils.findMethodByMethodSignature:(Ljava/lang/Class;Ljava/lang/String;[Ljava/lang/String;)Ljava/lang/reflect/Method;
       7: astore_2
       8: aload_2
       9: ifnull        32
      12: aload_2
      13: invokestatic  #61                 // Method isParametersGetter:(Ljava/lang/reflect/Method;)Z
      16: ifeq          32
      19: aload_2
      20: aload_1
      21: iconst_0
      22: anewarray     #34                 // class java/lang/Object
      25: invokevirtual #44                 // Method java/lang/reflect/Method.invoke:(Ljava/lang/Object;[Ljava/lang/Object;)Ljava/lang/Object;
      28: checkcast     #62                 // class java/util/Map
      31: areturn
      32: goto          36
      35: astore_2
      36: aconst_null
      37: areturn
    Exception table:
       from    to  target type
           0    31    35   Class java/lang/Throwable

  private static boolean isParametersGetter(java.lang.reflect.Method);
    Code:
       0: aload_0
       1: invokevirtual #31                 // Method java/lang/reflect/Method.getName:()Ljava/lang/String;
       4: astore_1
       5: ldc           #84                 // String getParameters
       7: aload_1
       8: invokevirtual #85                 // Method java/lang/String.equals:(Ljava/lang/Object;)Z
      11: ifeq          45
      14: aload_0
      15: invokevirtual #86                 // Method java/lang/reflect/Method.getModifiers:()I
      18: invokestatic  #87                 // Method java/lang/reflect/Modifier.isPublic:(I)Z
      21: ifeq          45
      24: aload_0
      25: invokevirtual #88                 // Method java/lang/reflect/Method.getParameterTypes:()[Ljava/lang/Class;
      28: arraylength
      29: ifne          45
      32: aload_0
      33: invokevirtual #33                 // Method java/lang/reflect/Method.getReturnType:()Ljava/lang/Class;
      36: ldc           #62                 // class java/util/Map
      38: if_acmpne     45
      41: iconst_1
      42: goto          46
      45: iconst_0
      46: ireturn

  private static boolean isParametersSetter(java.lang.reflect.Method);
    Code:
       0: ldc           #79                 // String setParameters
       2: aload_0
       3: invokevirtual #31                 // Method java/lang/reflect/Method.getName:()Ljava/lang/String;
       6: invokevirtual #85                 // Method java/lang/String.equals:(Ljava/lang/Object;)Z
       9: ifeq          55
      12: aload_0
      13: invokevirtual #86                 // Method java/lang/reflect/Method.getModifiers:()I
      16: invokestatic  #87                 // Method java/lang/reflect/Modifier.isPublic:(I)Z
      19: ifeq          55
      22: aload_0
      23: invokevirtual #89                 // Method java/lang/reflect/Method.getParameterCount:()I
      26: iconst_1
      27: if_icmpne     55
      30: ldc           #62                 // class java/util/Map
      32: aload_0
      33: invokevirtual #88                 // Method java/lang/reflect/Method.getParameterTypes:()[Ljava/lang/Class;
      36: iconst_0
      37: aaload
      38: if_acmpne     55
      41: aload_0
      42: invokevirtual #33                 // Method java/lang/reflect/Method.getReturnType:()Ljava/lang/Class;
      45: getstatic     #90                 // Field java/lang/Void.TYPE:Ljava/lang/Class;
      48: if_acmpne     55
      51: iconst_1
      52: goto          56
      55: iconst_0
      56: ireturn

  private static boolean isNestedGetter(java.lang.Object, java.lang.reflect.Method);
    Code:
       0: aload_1
       1: invokevirtual #31                 // Method java/lang/reflect/Method.getName:()Ljava/lang/String;
       4: astore_2
       5: aload_2
       6: ldc           #75                 // String get
       8: invokevirtual #77                 // Method java/lang/String.startsWith:(Ljava/lang/String;)Z
      11: ifne          23
      14: aload_2
      15: ldc           #91                 // String is
      17: invokevirtual #77                 // Method java/lang/String.startsWith:(Ljava/lang/String;)Z
      20: ifeq          101
      23: ldc           #75                 // String get
      25: aload_2
      26: invokevirtual #85                 // Method java/lang/String.equals:(Ljava/lang/Object;)Z
      29: ifne          101
      32: ldc           #91                 // String is
      34: aload_2
      35: invokevirtual #85                 // Method java/lang/String.equals:(Ljava/lang/Object;)Z
      38: ifne          101
      41: ldc           #92                 // String getClass
      43: aload_2
      44: invokevirtual #85                 // Method java/lang/String.equals:(Ljava/lang/Object;)Z
      47: ifne          101
      50: ldc           #93                 // String getObject
      52: aload_2
      53: invokevirtual #85                 // Method java/lang/String.equals:(Ljava/lang/Object;)Z
      56: ifne          101
      59: aload_1
      60: invokevirtual #86                 // Method java/lang/reflect/Method.getModifiers:()I
      63: invokestatic  #87                 // Method java/lang/reflect/Modifier.isPublic:(I)Z
      66: ifeq          101
      69: aload_1
      70: invokevirtual #88                 // Method java/lang/reflect/Method.getParameterTypes:()[Ljava/lang/Class;
      73: arraylength
      74: ifne          101
      77: aload_1
      78: invokevirtual #33                 // Method java/lang/reflect/Method.getReturnType:()Ljava/lang/Class;
      81: invokevirtual #94                 // Method java/lang/Class.isPrimitive:()Z
      84: ifne          101
      87: aload_1
      88: invokevirtual #33                 // Method java/lang/reflect/Method.getReturnType:()Ljava/lang/Class;
      91: invokestatic  #95                 // Method org/apache/dubbo/common/utils/ClassUtils.isSimpleType:(Ljava/lang/Class;)Z
      94: ifne          101
      97: iconst_1
      98: goto          102
     101: iconst_0
     102: istore_3
     103: iload_3
     104: ifne          109
     107: iconst_0
     108: ireturn
     109: aload_1
     110: invokestatic  #67                 // InterfaceMethod org/apache/dubbo/common/utils/MethodUtils.extractFieldName:(Ljava/lang/reflect/Method;)Ljava/lang/String;
     113: astore        4
     115: aload_0
     116: invokevirtual #27                 // Method java/lang/Object.getClass:()Ljava/lang/Class;
     119: aload         4
     121: invokestatic  #96                 // InterfaceMethod org/apache/dubbo/common/utils/FieldUtils.getDeclaredField:(Ljava/lang/Class;Ljava/lang/String;)Ljava/lang/reflect/Field;
     124: astore        5
     126: aload         5
     128: ifnull        145
     131: aload         5
     133: ldc           #97                 // class org/apache/dubbo/config/support/Nested
     135: invokevirtual #98                 // Method java/lang/reflect/Field.isAnnotationPresent:(Ljava/lang/Class;)Z
     138: ifeq          145
     141: iconst_1
     142: goto          146
     145: iconst_0
     146: ireturn

  private static boolean isNestedSetter(java.lang.Object, java.lang.reflect.Method);
    Code:
       0: aload_1
       1: invokevirtual #31                 // Method java/lang/reflect/Method.getName:()Ljava/lang/String;
       4: ldc           #72                 // String set
       6: invokevirtual #77                 // Method java/lang/String.startsWith:(Ljava/lang/String;)Z
       9: ifeq          79
      12: ldc           #72                 // String set
      14: aload_1
      15: invokevirtual #31                 // Method java/lang/reflect/Method.getName:()Ljava/lang/String;
      18: invokevirtual #85                 // Method java/lang/String.equals:(Ljava/lang/Object;)Z
      21: ifne          79
      24: aload_1
      25: invokevirtual #86                 // Method java/lang/reflect/Method.getModifiers:()I
      28: invokestatic  #87                 // Method java/lang/reflect/Modifier.isPublic:(I)Z
      31: ifeq          79
      34: aload_1
      35: invokevirtual #89                 // Method java/lang/reflect/Method.getParameterCount:()I
      38: iconst_1
      39: if_icmpne     79
      42: aload_1
      43: invokevirtual #88                 // Method java/lang/reflect/Method.getParameterTypes:()[Ljava/lang/Class;
      46: iconst_0
      47: aaload
      48: ifnull        79
      51: aload_1
      52: invokevirtual #88                 // Method java/lang/reflect/Method.getParameterTypes:()[Ljava/lang/Class;
      55: iconst_0
      56: aaload
      57: invokevirtual #94                 // Method java/lang/Class.isPrimitive:()Z
      60: ifne          79
      63: aload_1
      64: invokevirtual #88                 // Method java/lang/reflect/Method.getParameterTypes:()[Ljava/lang/Class;
      67: iconst_0
      68: aaload
      69: invokestatic  #95                 // Method org/apache/dubbo/common/utils/ClassUtils.isSimpleType:(Ljava/lang/Class;)Z
      72: ifne          79
      75: iconst_1
      76: goto          80
      79: iconst_0
      80: istore_2
      81: iload_2
      82: ifne          87
      85: iconst_0
      86: ireturn
      87: aload_1
      88: invokestatic  #67                 // InterfaceMethod org/apache/dubbo/common/utils/MethodUtils.extractFieldName:(Ljava/lang/reflect/Method;)Ljava/lang/String;
      91: astore_3
      92: aload_0
      93: invokevirtual #27                 // Method java/lang/Object.getClass:()Ljava/lang/Class;
      96: aload_3
      97: invokestatic  #96                 // InterfaceMethod org/apache/dubbo/common/utils/FieldUtils.getDeclaredField:(Ljava/lang/Class;Ljava/lang/String;)Ljava/lang/reflect/Field;
     100: astore        4
     102: aload         4
     104: ifnull        121
     107: aload         4
     109: ldc           #97                 // class org/apache/dubbo/config/support/Nested
     111: invokevirtual #98                 // Method java/lang/reflect/Field.isAnnotationPresent:(Ljava/lang/Class;)Z
     114: ifeq          121
     117: iconst_1
     118: goto          122
     121: iconst_0
     122: ireturn

  protected static java.util.Map<java.lang.String, java.lang.String> convert(java.util.Map<java.lang.String, java.lang.String>, java.lang.String);
    Code:
       0: aload_0
       1: ifnull        13
       4: aload_0
       5: invokeinterface #99,  1           // InterfaceMethod java/util/Map.isEmpty:()Z
      10: ifeq          21
      13: new           #100                // class java/util/HashMap
      16: dup
      17: invokespecial #101                // Method java/util/HashMap."<init>":()V
      20: areturn
      21: new           #100                // class java/util/HashMap
      24: dup
      25: invokespecial #101                // Method java/util/HashMap."<init>":()V
      28: astore_2
      29: aload_1
      30: invokestatic  #102                // Method org/apache/dubbo/common/utils/StringUtils.isNotEmpty:(Ljava/lang/String;)Z
      33: ifeq          58
      36: new           #16                 // class java/lang/StringBuilder
      39: dup
      40: invokespecial #17                 // Method java/lang/StringBuilder."<init>":()V
      43: aload_1
      44: invokevirtual #20                 // Method java/lang/StringBuilder.append:(Ljava/lang/String;)Ljava/lang/StringBuilder;
      47: ldc           #54                 // String .
      49: invokevirtual #20                 // Method java/lang/StringBuilder.append:(Ljava/lang/String;)Ljava/lang/StringBuilder;
      52: invokevirtual #22                 // Method java/lang/StringBuilder.toString:()Ljava/lang/String;
      55: goto          60
      58: ldc           #103                // String
      60: astore_3
      61: aload_0
      62: invokeinterface #104,  1          // InterfaceMethod java/util/Map.entrySet:()Ljava/util/Set;
      67: invokeinterface #105,  1          // InterfaceMethod java/util/Set.iterator:()Ljava/util/Iterator;
      72: astore        4
      74: aload         4
      76: invokeinterface #106,  1          // InterfaceMethod java/util/Iterator.hasNext:()Z
      81: ifeq          197
      84: aload         4
      86: invokeinterface #107,  1          // InterfaceMethod java/util/Iterator.next:()Ljava/lang/Object;
      91: checkcast     #108                // class java/util/Map$Entry
      94: astore        5
      96: aload         5
      98: invokeinterface #109,  1          // InterfaceMethod java/util/Map$Entry.getKey:()Ljava/lang/Object;
     103: checkcast     #12                 // class java/lang/String
     106: astore        6
     108: aload         5
     110: invokeinterface #110,  1          // InterfaceMethod java/util/Map$Entry.getValue:()Ljava/lang/Object;
     115: checkcast     #12                 // class java/lang/String
     118: astore        7
     120: aload_2
     121: new           #16                 // class java/lang/StringBuilder
     124: dup
     125: invokespecial #17                 // Method java/lang/StringBuilder."<init>":()V
     128: aload_3
     129: invokevirtual #20                 // Method java/lang/StringBuilder.append:(Ljava/lang/String;)Ljava/lang/StringBuilder;
     132: aload         6
     134: invokevirtual #20                 // Method java/lang/StringBuilder.append:(Ljava/lang/String;)Ljava/lang/StringBuilder;
     137: invokevirtual #22                 // Method java/lang/StringBuilder.toString:()Ljava/lang/String;
     140: aload         7
     142: invokeinterface #55,  3           // InterfaceMethod java/util/Map.put:(Ljava/lang/Object;Ljava/lang/Object;)Ljava/lang/Object;
     147: pop
     148: getstatic     #111                // Field org/apache/dubbo/config/Constants.DOT_COMPATIBLE_KEYS:[Ljava/lang/String;
     151: aload         6
     153: invokestatic  #112                // Method java/util/Arrays.binarySearch:([Ljava/lang/Object;Ljava/lang/Object;)I
     156: iflt          194
     159: aload_2
     160: new           #16                 // class java/lang/StringBuilder
     163: dup
     164: invokespecial #17                 // Method java/lang/StringBuilder."<init>":()V
     167: aload_3
     168: invokevirtual #20                 // Method java/lang/StringBuilder.append:(Ljava/lang/String;)Ljava/lang/StringBuilder;
     171: aload         6
     173: bipush        45
     175: bipush        46
     177: invokevirtual #113                // Method java/lang/String.replace:(CC)Ljava/lang/String;
     180: invokevirtual #20                 // Method java/lang/StringBuilder.append:(Ljava/lang/String;)Ljava/lang/StringBuilder;
     183: invokevirtual #22                 // Method java/lang/StringBuilder.toString:()Ljava/lang/String;
     186: aload         7
     188: invokeinterface #55,  3           // InterfaceMethod java/util/Map.put:(Ljava/lang/Object;Ljava/lang/Object;)Ljava/lang/Object;
     193: pop
     194: goto          74
     197: aload_2
     198: areturn

  public org.apache.dubbo.rpc.model.ApplicationModel getApplicationModel();
    Code:
       0: aload_0
       1: getfield      #114                // Field scopeModel:Lorg/apache/dubbo/rpc/model/ScopeModel;
       4: ifnonnull     15
       7: aload_0
       8: aload_0
       9: invokevirtual #115                // Method getDefaultModel:()Lorg/apache/dubbo/rpc/model/ScopeModel;
      12: invokevirtual #8                  // Method setScopeModel:(Lorg/apache/dubbo/rpc/model/ScopeModel;)V
      15: aload_0
      16: getfield      #114                // Field scopeModel:Lorg/apache/dubbo/rpc/model/ScopeModel;
      19: instanceof    #116                // class org/apache/dubbo/rpc/model/ApplicationModel
      22: ifeq          33
      25: aload_0
      26: getfield      #114                // Field scopeModel:Lorg/apache/dubbo/rpc/model/ScopeModel;
      29: checkcast     #116                // class org/apache/dubbo/rpc/model/ApplicationModel
      32: areturn
      33: aload_0
      34: getfield      #114                // Field scopeModel:Lorg/apache/dubbo/rpc/model/ScopeModel;
      37: instanceof    #117                // class org/apache/dubbo/rpc/model/ModuleModel
      40: ifeq          54
      43: aload_0
      44: getfield      #114                // Field scopeModel:Lorg/apache/dubbo/rpc/model/ScopeModel;
      47: checkcast     #117                // class org/apache/dubbo/rpc/model/ModuleModel
      50: invokevirtual #118                // Method org/apache/dubbo/rpc/model/ModuleModel.getApplicationModel:()Lorg/apache/dubbo/rpc/model/ApplicationModel;
      53: areturn
      54: new           #57                 // class java/lang/IllegalStateException
      57: dup
      58: new           #16                 // class java/lang/StringBuilder
      61: dup
      62: invokespecial #17                 // Method java/lang/StringBuilder."<init>":()V
      65: ldc           #119                // String scope model is invalid:
      67: invokevirtual #20                 // Method java/lang/StringBuilder.append:(Ljava/lang/String;)Ljava/lang/StringBuilder;
      70: aload_0
      71: getfield      #114                // Field scopeModel:Lorg/apache/dubbo/rpc/model/ScopeModel;
      74: invokevirtual #120                // Method java/lang/StringBuilder.append:(Ljava/lang/Object;)Ljava/lang/StringBuilder;
      77: invokevirtual #22                 // Method java/lang/StringBuilder.toString:()Ljava/lang/String;
      80: invokespecial #60                 // Method java/lang/IllegalStateException."<init>":(Ljava/lang/String;)V
      83: athrow

  public org.apache.dubbo.rpc.model.ScopeModel getScopeModel();
    Code:
       0: aload_0
       1: getfield      #114                // Field scopeModel:Lorg/apache/dubbo/rpc/model/ScopeModel;
       4: ifnonnull     15
       7: aload_0
       8: aload_0
       9: invokevirtual #115                // Method getDefaultModel:()Lorg/apache/dubbo/rpc/model/ScopeModel;
      12: invokevirtual #8                  // Method setScopeModel:(Lorg/apache/dubbo/rpc/model/ScopeModel;)V
      15: aload_0
      16: getfield      #114                // Field scopeModel:Lorg/apache/dubbo/rpc/model/ScopeModel;
      19: areturn

  protected org.apache.dubbo.rpc.model.ScopeModel getDefaultModel();
    Code:
       0: invokestatic  #121                // Method org/apache/dubbo/rpc/model/ApplicationModel.defaultModel:()Lorg/apache/dubbo/rpc/model/ApplicationModel;
       3: areturn

  public final void setScopeModel(org.apache.dubbo.rpc.model.ScopeModel);
    Code:
       0: aload_1
       1: ifnull        36
       4: aload_0
       5: getfield      #114                // Field scopeModel:Lorg/apache/dubbo/rpc/model/ScopeModel;
       8: aload_1
       9: if_acmpeq     36
      12: aload_0
      13: aload_1
      14: invokevirtual #122                // Method checkScopeModel:(Lorg/apache/dubbo/rpc/model/ScopeModel;)V
      17: aload_0
      18: getfield      #114                // Field scopeModel:Lorg/apache/dubbo/rpc/model/ScopeModel;
      21: astore_2
      22: aload_0
      23: aload_1
      24: putfield      #114                // Field scopeModel:Lorg/apache/dubbo/rpc/model/ScopeModel;
      27: aload_0
      28: aload_2
      29: aload_0
      30: getfield      #114                // Field scopeModel:Lorg/apache/dubbo/rpc/model/ScopeModel;
      33: invokevirtual #123                // Method postProcessAfterScopeModelChanged:(Lorg/apache/dubbo/rpc/model/ScopeModel;Lorg/apache/dubbo/rpc/model/ScopeModel;)V
      36: return

  protected void checkScopeModel(org.apache.dubbo.rpc.model.ScopeModel);
    Code:
       0: aload_1
       1: ifnonnull     14
       4: new           #124                // class java/lang/IllegalArgumentException
       7: dup
       8: ldc           #125                // String scopeModel cannot be null
      10: invokespecial #126                // Method java/lang/IllegalArgumentException."<init>":(Ljava/lang/String;)V
      13: athrow
      14: aload_1
      15: instanceof    #116                // class org/apache/dubbo/rpc/model/ApplicationModel
      18: ifne          48
      21: new           #124                // class java/lang/IllegalArgumentException
      24: dup
      25: new           #16                 // class java/lang/StringBuilder
      28: dup
      29: invokespecial #17                 // Method java/lang/StringBuilder."<init>":()V
      32: ldc           #127                // String Invalid scope model, expect to be a ApplicationModel but got:
      34: invokevirtual #20                 // Method java/lang/StringBuilder.append:(Ljava/lang/String;)Ljava/lang/StringBuilder;
      37: aload_1
      38: invokevirtual #120                // Method java/lang/StringBuilder.append:(Ljava/lang/Object;)Ljava/lang/StringBuilder;
      41: invokevirtual #22                 // Method java/lang/StringBuilder.toString:()Ljava/lang/String;
      44: invokespecial #126                // Method java/lang/IllegalArgumentException."<init>":(Ljava/lang/String;)V
      47: athrow
      48: return

  protected void postProcessAfterScopeModelChanged(org.apache.dubbo.rpc.model.ScopeModel, org.apache.dubbo.rpc.model.ScopeModel);
    Code:
       0: return

  protected <T> org.apache.dubbo.common.extension.ExtensionLoader<T> getExtensionLoader(java.lang.Class<T>);
    Code:
       0: aload_0
       1: getfield      #114                // Field scopeModel:Lorg/apache/dubbo/rpc/model/ScopeModel;
       4: ifnonnull     15
       7: aload_0
       8: aload_0
       9: invokevirtual #128                // Method getScopeModel:()Lorg/apache/dubbo/rpc/model/ScopeModel;
      12: invokevirtual #8                  // Method setScopeModel:(Lorg/apache/dubbo/rpc/model/ScopeModel;)V
      15: aload_0
      16: getfield      #114                // Field scopeModel:Lorg/apache/dubbo/rpc/model/ScopeModel;
      19: aload_1
      20: invokevirtual #129                // Method org/apache/dubbo/rpc/model/ScopeModel.getExtensionLoader:(Ljava/lang/Class;)Lorg/apache/dubbo/common/extension/ExtensionLoader;
      23: areturn

  public java.lang.String getId();
    Code:
       0: aload_0
       1: getfield      #130                // Field id:Ljava/lang/String;
       4: areturn

  public void setId(java.lang.String);
    Code:
       0: aload_0
       1: aload_1
       2: putfield      #130                // Field id:Ljava/lang/String;
       5: return

  protected void appendAnnotation(java.lang.Class<?>, java.lang.Object);
    Code:
       0: aload_1
       1: invokevirtual #131                // Method java/lang/Class.getMethods:()[Ljava/lang/reflect/Method;
       4: astore_3
       5: aload_3
       6: astore        4
       8: aload         4
      10: arraylength
      11: istore        5
      13: iconst_0
      14: istore        6
      16: iload         6
      18: iload         5
      20: if_icmpge     312
      23: aload         4
      25: iload         6
      27: aaload
      28: astore        7
      30: aload         7
      32: invokevirtual #132                // Method java/lang/reflect/Method.getDeclaringClass:()Ljava/lang/Class;
      35: ldc           #34                 // class java/lang/Object
      37: if_acmpeq     306
      40: aload         7
      42: invokevirtual #132                // Method java/lang/reflect/Method.getDeclaringClass:()Ljava/lang/Class;
      45: ldc           #133                // class java/lang/annotation/Annotation
      47: if_acmpeq     306
      50: aload         7
      52: invokevirtual #33                 // Method java/lang/reflect/Method.getReturnType:()Ljava/lang/Class;
      55: getstatic     #90                 // Field java/lang/Void.TYPE:Ljava/lang/Class;
      58: if_acmpeq     306
      61: aload         7
      63: invokevirtual #88                 // Method java/lang/reflect/Method.getParameterTypes:()[Ljava/lang/Class;
      66: arraylength
      67: ifne          306
      70: aload         7
      72: invokevirtual #86                 // Method java/lang/reflect/Method.getModifiers:()I
      75: invokestatic  #87                 // Method java/lang/reflect/Modifier.isPublic:(I)Z
      78: ifeq          306
      81: aload         7
      83: invokevirtual #86                 // Method java/lang/reflect/Method.getModifiers:()I
      86: invokestatic  #134                // Method java/lang/reflect/Modifier.isStatic:(I)Z
      89: ifne          306
      92: aload         7
      94: invokevirtual #31                 // Method java/lang/reflect/Method.getName:()Ljava/lang/String;
      97: astore        8
      99: ldc           #135                // String interfaceClass
     101: aload         8
     103: invokevirtual #85                 // Method java/lang/String.equals:(Ljava/lang/Object;)Z
     106: ifne          119
     109: ldc           #136                // String interfaceName
     111: aload         8
     113: invokevirtual #85                 // Method java/lang/String.equals:(Ljava/lang/Object;)Z
     116: ifeq          123
     119: ldc           #137                // String interface
     121: astore        8
     123: aload         8
     125: invokestatic  #138                // Method calculatePropertyToSetter:(Ljava/lang/String;)Ljava/lang/String;
     128: astore        9
     130: aload         7
     132: aload_2
     133: iconst_0
     134: anewarray     #34                 // class java/lang/Object
     137: invokevirtual #44                 // Method java/lang/reflect/Method.invoke:(Ljava/lang/Object;[Ljava/lang/Object;)Ljava/lang/Object;
     140: astore        10
     142: aload         10
     144: ifnull        280
     147: aload         10
     149: aload         7
     151: invokevirtual #139                // Method java/lang/reflect/Method.getDefaultValue:()Ljava/lang/Object;
     154: invokevirtual #140                // Method java/lang/Object.equals:(Ljava/lang/Object;)Z
     157: ifne          280
     160: aload         7
     162: invokevirtual #33                 // Method java/lang/reflect/Method.getReturnType:()Ljava/lang/Class;
     165: invokestatic  #141                // Method org/apache/dubbo/common/utils/ReflectUtils.getBoxedClass:(Ljava/lang/Class;)Ljava/lang/Class;
     168: astore        11
     170: ldc           #142                // String filter
     172: aload         8
     174: invokevirtual #85                 // Method java/lang/String.equals:(Ljava/lang/Object;)Z
     177: ifne          190
     180: ldc           #143                // String listener
     182: aload         8
     184: invokevirtual #85                 // Method java/lang/String.equals:(Ljava/lang/Object;)Z
     187: ifeq          212
     190: ldc           #12                 // class java/lang/String
     192: astore        11
     194: aload         10
     196: checkcast     #144                // class "[Ljava/lang/String;"
     199: checkcast     #144                // class "[Ljava/lang/String;"
     202: ldc           #51                 // String ,
     204: invokestatic  #145                // Method org/apache/dubbo/common/utils/StringUtils.join:([Ljava/lang/String;Ljava/lang/String;)Ljava/lang/String;
     207: astore        10
     209: goto          239
     212: ldc           #146                // String parameters
     214: aload         8
     216: invokevirtual #85                 // Method java/lang/String.equals:(Ljava/lang/Object;)Z
     219: ifeq          239
     222: ldc           #62                 // class java/util/Map
     224: astore        11
     226: aload         10
     228: checkcast     #144                // class "[Ljava/lang/String;"
     231: checkcast     #144                // class "[Ljava/lang/String;"
     234: invokestatic  #147                // Method org/apache/dubbo/common/utils/CollectionUtils.toStringMap:([Ljava/lang/String;)Ljava/util/Map;
     237: astore        10
     239: aload_0
     240: invokevirtual #27                 // Method java/lang/Object.getClass:()Ljava/lang/Class;
     243: aload         9
     245: iconst_1
     246: anewarray     #148                // class java/lang/Class
     249: dup
     250: iconst_0
     251: aload         11
     253: aastore
     254: invokevirtual #149                // Method java/lang/Class.getMethod:(Ljava/lang/String;[Ljava/lang/Class;)Ljava/lang/reflect/Method;
     257: astore        12
     259: aload         12
     261: aload_0
     262: iconst_1
     263: anewarray     #34                 // class java/lang/Object
     266: dup
     267: iconst_0
     268: aload         10
     270: aastore
     271: invokevirtual #44                 // Method java/lang/reflect/Method.invoke:(Ljava/lang/Object;[Ljava/lang/Object;)Ljava/lang/Object;
     274: pop
     275: goto          280
     278: astore        12
     280: goto          306
     283: astore        8
     285: getstatic     #151                // Field logger:Lorg/apache/dubbo/common/logger/ErrorTypeAwareLogger;
     288: ldc           #152                // String 0-8
     290: ldc           #103                // String
     292: ldc           #103                // String
     294: aload         8
     296: invokevirtual #153                // Method java/lang/Throwable.getMessage:()Ljava/lang/String;
     299: aload         8
     301: invokeinterface #154,  6          // InterfaceMethod org/apache/dubbo/common/logger/ErrorTypeAwareLogger.error:(Ljava/lang/String;Ljava/lang/String;Ljava/lang/String;Ljava/lang/String;Ljava/lang/Throwable;)V
     306: iinc          6, 1
     309: goto          16
     312: return
    Exception table:
       from    to  target type
         239   275   278   Class java/lang/NoSuchMethodException
          92   280   283   Class java/lang/Throwable

  public java.util.Map<java.lang.String, java.lang.String> getMetaData();
    Code:
       0: aload_0
       1: aconst_null
       2: invokevirtual #155                // Method getMetaData:(Ljava/lang/String;)Ljava/util/Map;
       5: areturn

  public java.util.Map<java.lang.String, java.lang.String> getMetaData(java.lang.String);
    Code:
       0: new           #100                // class java/util/HashMap
       3: dup
       4: invokespecial #101                // Method java/util/HashMap."<init>":()V
       7: astore_2
       8: aload_2
       9: aload_0
      10: aload_1
      11: invokestatic  #156                // Method appendAttributes:(Ljava/util/Map;Ljava/lang/Object;Ljava/lang/String;)V
      14: aload_2
      15: areturn

  private static java.beans.BeanInfo getBeanInfo(java.lang.Class);
    Code:
       0: aload_0
       1: invokestatic  #157                // Method java/beans/Introspector.getBeanInfo:(Ljava/lang/Class;)Ljava/beans/BeanInfo;
       4: astore_1
       5: goto          22
       8: astore_2
       9: new           #57                 // class java/lang/IllegalStateException
      12: dup
      13: aload_2
      14: invokevirtual #159                // Method java/beans/IntrospectionException.getMessage:()Ljava/lang/String;
      17: aload_2
      18: invokespecial #71                 // Method java/lang/IllegalStateException."<init>":(Ljava/lang/String;Ljava/lang/Throwable;)V
      21: athrow
      22: aload_1
      23: areturn
    Exception table:
       from    to  target type
           0     5     8   Class java/beans/IntrospectionException

  private static boolean isWritableProperty(java.beans.BeanInfo, java.lang.String);
    Code:
       0: aload_0
       1: invokeinterface #160,  1          // InterfaceMethod java/beans/BeanInfo.getPropertyDescriptors:()[Ljava/beans/PropertyDescriptor;
       6: astore_2
       7: aload_2
       8: arraylength
       9: istore_3
      10: iconst_0
      11: istore        4
      13: iload         4
      15: iload_3
      16: if_icmpge     57
      19: aload_2
      20: iload         4
      22: aaload
      23: astore        5
      25: aload_1
      26: aload         5
      28: invokevirtual #161                // Method java/beans/PropertyDescriptor.getName:()Ljava/lang/String;
      31: invokevirtual #85                 // Method java/lang/String.equals:(Ljava/lang/Object;)Z
      34: ifeq          51
      37: aload         5
      39: invokevirtual #162                // Method java/beans/PropertyDescriptor.getWriteMethod:()Ljava/lang/reflect/Method;
      42: ifnull        49
      45: iconst_1
      46: goto          50
      49: iconst_0
      50: ireturn
      51: iinc          4, 1
      54: goto          13
      57: iconst_0
      58: ireturn

  public java.util.List<java.lang.String> getPrefixes();
    Code:
       0: new           #163                // class java/util/ArrayList
       3: dup
       4: invokespecial #164                // Method java/util/ArrayList."<init>":()V
       7: astore_1
       8: aload_0
       9: invokevirtual #165                // Method getId:()Ljava/lang/String;
      12: invokestatic  #166                // Method org/apache/dubbo/common/utils/StringUtils.hasText:(Ljava/lang/CharSequence;)Z
      15: ifeq          62
      18: aload_1
      19: new           #16                 // class java/lang/StringBuilder
      22: dup
      23: invokespecial #17                 // Method java/lang/StringBuilder."<init>":()V
      26: ldc           #168                // String dubbo.
      28: invokevirtual #20                 // Method java/lang/StringBuilder.append:(Ljava/lang/String;)Ljava/lang/StringBuilder;
      31: aload_0
      32: invokevirtual #27                 // Method java/lang/Object.getClass:()Ljava/lang/Class;
      35: invokestatic  #169                // Method getPluralTagName:(Ljava/lang/Class;)Ljava/lang/String;
      38: invokevirtual #20                 // Method java/lang/StringBuilder.append:(Ljava/lang/String;)Ljava/lang/StringBuilder;
      41: ldc           #54                 // String .
      43: invokevirtual #20                 // Method java/lang/StringBuilder.append:(Ljava/lang/String;)Ljava/lang/StringBuilder;
      46: aload_0
      47: invokevirtual #165                // Method getId:()Ljava/lang/String;
      50: invokevirtual #20                 // Method java/lang/StringBuilder.append:(Ljava/lang/String;)Ljava/lang/StringBuilder;
      53: invokevirtual #22                 // Method java/lang/StringBuilder.toString:()Ljava/lang/String;
      56: invokeinterface #170,  2          // InterfaceMethod java/util/List.add:(Ljava/lang/Object;)Z
      61: pop
      62: aload_0
      63: ldc           #171                // String getName
      65: invokestatic  #172                // Method org/apache/dubbo/common/utils/ReflectUtils.getProperty:(Ljava/lang/Object;Ljava/lang/String;)Ljava/lang/Object;
      68: checkcast     #12                 // class java/lang/String
      71: astore_2
      72: aload_2
      73: invokestatic  #166                // Method org/apache/dubbo/common/utils/StringUtils.hasText:(Ljava/lang/CharSequence;)Z
      76: ifeq          132
      79: new           #16                 // class java/lang/StringBuilder
      82: dup
      83: invokespecial #17                 // Method java/lang/StringBuilder."<init>":()V
      86: ldc           #168                // String dubbo.
      88: invokevirtual #20                 // Method java/lang/StringBuilder.append:(Ljava/lang/String;)Ljava/lang/StringBuilder;
      91: aload_0
      92: invokevirtual #27                 // Method java/lang/Object.getClass:()Ljava/lang/Class;
      95: invokestatic  #169                // Method getPluralTagName:(Ljava/lang/Class;)Ljava/lang/String;
      98: invokevirtual #20                 // Method java/lang/StringBuilder.append:(Ljava/lang/String;)Ljava/lang/StringBuilder;
     101: ldc           #54                 // String .
     103: invokevirtual #20                 // Method java/lang/StringBuilder.append:(Ljava/lang/String;)Ljava/lang/StringBuilder;
     106: aload_2
     107: invokevirtual #20                 // Method java/lang/StringBuilder.append:(Ljava/lang/String;)Ljava/lang/StringBuilder;
     110: invokevirtual #22                 // Method java/lang/StringBuilder.toString:()Ljava/lang/String;
     113: astore_3
     114: aload_1
     115: aload_3
     116: invokeinterface #173,  2          // InterfaceMethod java/util/List.contains:(Ljava/lang/Object;)Z
     121: ifne          132
     124: aload_1
     125: aload_3
     126: invokeinterface #170,  2          // InterfaceMethod java/util/List.add:(Ljava/lang/Object;)Z
     131: pop
     132: aload_1
     133: aload_0
     134: invokevirtual #27                 // Method java/lang/Object.getClass:()Ljava/lang/Class;
     137: invokestatic  #174                // Method getTypePrefix:(Ljava/lang/Class;)Ljava/lang/String;
     140: invokeinterface #170,  2          // InterfaceMethod java/util/List.add:(Ljava/lang/Object;)Z
     145: pop
     146: aload_1
     147: areturn

  public static java.lang.String getTypePrefix(java.lang.Class<? extends org.apache.dubbo.config.AbstractConfig>);
    Code:
       0: new           #16                 // class java/lang/StringBuilder
       3: dup
       4: invokespecial #17                 // Method java/lang/StringBuilder."<init>":()V
       7: ldc           #168                // String dubbo.
       9: invokevirtual #20                 // Method java/lang/StringBuilder.append:(Ljava/lang/String;)Ljava/lang/StringBuilder;
      12: aload_0
      13: invokestatic  #13                 // Method getTagName:(Ljava/lang/Class;)Ljava/lang/String;
      16: invokevirtual #20                 // Method java/lang/StringBuilder.append:(Ljava/lang/String;)Ljava/lang/StringBuilder;
      19: invokevirtual #22                 // Method java/lang/StringBuilder.toString:()Ljava/lang/String;
      22: areturn

  public org.apache.dubbo.config.context.ConfigMode getConfigMode();
    Code:
       0: aload_0
       1: invokevirtual #175                // Method getApplicationModel:()Lorg/apache/dubbo/rpc/model/ApplicationModel;
       4: invokevirtual #176                // Method org/apache/dubbo/rpc/model/ApplicationModel.getApplicationConfigManager:()Lorg/apache/dubbo/config/context/ConfigManager;
       7: invokevirtual #177                // Method org/apache/dubbo/config/context/ConfigManager.getConfigMode:()Lorg/apache/dubbo/config/context/ConfigMode;
      10: areturn

  public void overrideWithConfig(org.apache.dubbo.config.AbstractConfig, boolean);
    Code:
       0: aload_0
       1: invokevirtual #27                 // Method java/lang/Object.getClass:()Ljava/lang/Class;
       4: aload_1
       5: invokevirtual #27                 // Method java/lang/Object.getClass:()Ljava/lang/Class;
       8: invokestatic  #178                // Method java/util/Objects.equals:(Ljava/lang/Object;Ljava/lang/Object;)Z
      11: ifne          15
      14: return
      15: aload_0
      16: invokevirtual #27                 // Method java/lang/Object.getClass:()Ljava/lang/Class;
      19: iconst_1
      20: anewarray     #179                // class java/util/function/Predicate
      23: dup
      24: iconst_0
      25: invokedynamic #180,  0            // InvokeDynamic #1:test:()Ljava/util/function/Predicate;
      30: aastore
      31: invokestatic  #181                // InterfaceMethod org/apache/dubbo/common/utils/MethodUtils.getMethods:(Ljava/lang/Class;[Ljava/util/function/Predicate;)Ljava/util/List;
      34: astore_3
      35: aload_3
      36: invokeinterface #182,  1          // InterfaceMethod java/util/List.iterator:()Ljava/util/Iterator;
      41: astore        4
      43: aload         4
      45: invokeinterface #106,  1          // InterfaceMethod java/util/Iterator.hasNext:()Z
      50: ifeq          397
      53: aload         4
      55: invokeinterface #107,  1          // InterfaceMethod java/util/Iterator.next:()Ljava/lang/Object;
      60: checkcast     #183                // class java/lang/reflect/Method
      63: astore        5
      65: aload         5
      67: invokevirtual #31                 // Method java/lang/reflect/Method.getName:()Ljava/lang/String;
      70: invokestatic  #184                // Method extractPropertyName:(Ljava/lang/String;)Ljava/lang/String;
      73: astore        7
      75: aload         7
      77: invokestatic  #185                // Method calculatePropertyToGetter:(Ljava/lang/String;)Ljava/lang/String;
      80: astore        8
      82: aload_0
      83: invokevirtual #27                 // Method java/lang/Object.getClass:()Ljava/lang/Class;
      86: aload         8
      88: iconst_0
      89: anewarray     #148                // class java/lang/Class
      92: invokevirtual #149                // Method java/lang/Class.getMethod:(Ljava/lang/String;[Ljava/lang/Class;)Ljava/lang/reflect/Method;
      95: astore        6
      97: goto          105
     100: astore        7
     102: goto          43
     105: aload         5
     107: invokestatic  #186                // InterfaceMethod org/apache/dubbo/common/utils/MethodUtils.isSetter:(Ljava/lang/reflect/Method;)Z
     110: ifeq          180
     113: aload         6
     115: aload_0
     116: iconst_0
     117: anewarray     #34                 // class java/lang/Object
     120: invokevirtual #44                 // Method java/lang/reflect/Method.invoke:(Ljava/lang/Object;[Ljava/lang/Object;)Ljava/lang/Object;
     123: astore        7
     125: iload_2
     126: ifne          134
     129: aload         7
     131: ifnonnull     177
     134: aload         6
     136: aload_1
     137: iconst_0
     138: anewarray     #34                 // class java/lang/Object
     141: invokevirtual #44                 // Method java/lang/reflect/Method.invoke:(Ljava/lang/Object;[Ljava/lang/Object;)Ljava/lang/Object;
     144: astore        8
     146: aload         8
     148: ifnull        177
     151: aload         8
     153: aload         7
     155: invokestatic  #178                // Method java/util/Objects.equals:(Ljava/lang/Object;Ljava/lang/Object;)Z
     158: ifne          177
     161: aload         5
     163: aload_0
     164: iconst_1
     165: anewarray     #34                 // class java/lang/Object
     168: dup
     169: iconst_0
     170: aload         8
     172: aastore
     173: invokevirtual #44                 // Method java/lang/reflect/Method.invoke:(Ljava/lang/Object;[Ljava/lang/Object;)Ljava/lang/Object;
     176: pop
     177: goto          325
     180: aload         5
     182: invokestatic  #82                 // Method isParametersSetter:(Ljava/lang/reflect/Method;)Z
     185: ifeq          316
     188: aload         6
     190: aload_0
     191: iconst_0
     192: anewarray     #34                 // class java/lang/Object
     195: invokevirtual #44                 // Method java/lang/reflect/Method.invoke:(Ljava/lang/Object;[Ljava/lang/Object;)Ljava/lang/Object;
     198: astore        7
     200: aload         6
     202: aload_1
     203: iconst_0
     204: anewarray     #34                 // class java/lang/Object
     207: invokevirtual #44                 // Method java/lang/reflect/Method.invoke:(Ljava/lang/Object;[Ljava/lang/Object;)Ljava/lang/Object;
     210: astore        8
     212: aconst_null
     213: astore        9
     215: aload         7
     217: instanceof    #62                 // class java/util/Map
     220: ifeq          230
     223: aload         7
     225: checkcast     #62                 // class java/util/Map
     228: astore        9
     230: aconst_null
     231: astore        10
     233: aload         8
     235: instanceof    #62                 // class java/util/Map
     238: ifeq          248
     241: aload         8
     243: checkcast     #62                 // class java/util/Map
     246: astore        10
     248: aload         10
     250: ifnonnull     256
     253: goto          43
     256: aload         9
     258: ifnonnull     271
     261: aload_0
     262: aload         10
     264: aload_0
     265: invokespecial #187                // Method invokeSetParameters:(Ljava/util/Map;Ljava/lang/Object;)V
     268: goto          43
     271: iload_2
     272: ifeq          297
     275: aload         9
     277: aload         10
     279: dup
     280: invokevirtual #27                 // Method java/lang/Object.getClass:()Ljava/lang/Class;
     283: pop
     284: invokedynamic #188,  0            // InvokeDynamic #2:accept:(Ljava/util/Map;)Ljava/util/function/BiConsumer;
     289: invokeinterface #189,  2          // InterfaceMethod java/util/Map.forEach:(Ljava/util/function/BiConsumer;)V
     294: goto          306
     297: aload         10
     299: aload         9
     301: invokeinterface #64,  2           // InterfaceMethod java/util/Map.putAll:(Ljava/util/Map;)V
     306: aload_0
     307: aload         10
     309: aload_0
     310: invokespecial #187                // Method invokeSetParameters:(Ljava/util/Map;Ljava/lang/Object;)V
     313: goto          325
     316: aload_0
     317: aload         5
     319: invokestatic  #190                // Method isNestedSetter:(Ljava/lang/Object;Ljava/lang/reflect/Method;)Z
     322: ifeq          325
     325: goto          394
     328: astore        6
     330: getstatic     #151                // Field logger:Lorg/apache/dubbo/common/logger/ErrorTypeAwareLogger;
     333: ldc           #191                // String 0-24
     335: ldc           #103                // String
     337: ldc           #103                // String
     339: new           #16                 // class java/lang/StringBuilder
     342: dup
     343: invokespecial #17                 // Method java/lang/StringBuilder."<init>":()V
     346: ldc           #192                // String Failed to override field value of config bean:
     348: invokevirtual #20                 // Method java/lang/StringBuilder.append:(Ljava/lang/String;)Ljava/lang/StringBuilder;
     351: aload_0
     352: invokevirtual #120                // Method java/lang/StringBuilder.append:(Ljava/lang/Object;)Ljava/lang/StringBuilder;
     355: invokevirtual #22                 // Method java/lang/StringBuilder.toString:()Ljava/lang/String;
     358: aload         6
     360: invokeinterface #154,  6          // InterfaceMethod org/apache/dubbo/common/logger/ErrorTypeAwareLogger.error:(Ljava/lang/String;Ljava/lang/String;Ljava/lang/String;Ljava/lang/String;Ljava/lang/Throwable;)V
     365: new           #57                 // class java/lang/IllegalStateException
     368: dup
     369: new           #16                 // class java/lang/StringBuilder
     372: dup
     373: invokespecial #17                 // Method java/lang/StringBuilder."<init>":()V
     376: ldc           #192                // String Failed to override field value of config bean:
     378: invokevirtual #20                 // Method java/lang/StringBuilder.append:(Ljava/lang/String;)Ljava/lang/StringBuilder;
     381: aload_0
     382: invokevirtual #120                // Method java/lang/StringBuilder.append:(Ljava/lang/Object;)Ljava/lang/StringBuilder;
     385: invokevirtual #22                 // Method java/lang/StringBuilder.toString:()Ljava/lang/String;
     388: aload         6
     390: invokespecial #71                 // Method java/lang/IllegalStateException."<init>":(Ljava/lang/String;Ljava/lang/Throwable;)V
     393: athrow
     394: goto          43
     397: return
    Exception table:
       from    to  target type
          65    97   100   Class java/lang/Exception
          65   102   328   Class java/lang/Throwable
         105   253   328   Class java/lang/Throwable
         256   268   328   Class java/lang/Throwable
         271   325   328   Class java/lang/Throwable

  public void refresh();
    Code:
       0: aload_0
       1: invokevirtual #193                // Method preProcessRefresh:()V
       4: aload_0
       5: aload_0
       6: invokevirtual #194                // Method getPrefixes:()Ljava/util/List;
       9: aload_0
      10: invokevirtual #195                // Method getConfigMode:()Lorg/apache/dubbo/config/context/ConfigMode;
      13: invokevirtual #196                // Method refreshWithPrefixes:(Ljava/util/List;Lorg/apache/dubbo/config/context/ConfigMode;)V
      16: goto          82
      19: astore_1
      20: getstatic     #151                // Field logger:Lorg/apache/dubbo/common/logger/ErrorTypeAwareLogger;
      23: ldc           #191                // String 0-24
      25: ldc           #103                // String
      27: ldc           #103                // String
      29: new           #16                 // class java/lang/StringBuilder
      32: dup
      33: invokespecial #17                 // Method java/lang/StringBuilder."<init>":()V
      36: ldc           #192                // String Failed to override field value of config bean:
      38: invokevirtual #20                 // Method java/lang/StringBuilder.append:(Ljava/lang/String;)Ljava/lang/StringBuilder;
      41: aload_0
      42: invokevirtual #120                // Method java/lang/StringBuilder.append:(Ljava/lang/Object;)Ljava/lang/StringBuilder;
      45: invokevirtual #22                 // Method java/lang/StringBuilder.toString:()Ljava/lang/String;
      48: aload_1
      49: invokeinterface #154,  6          // InterfaceMethod org/apache/dubbo/common/logger/ErrorTypeAwareLogger.error:(Ljava/lang/String;Ljava/lang/String;Ljava/lang/String;Ljava/lang/String;Ljava/lang/Throwable;)V
      54: new           #57                 // class java/lang/IllegalStateException
      57: dup
      58: new           #16                 // class java/lang/StringBuilder
      61: dup
      62: invokespecial #17                 // Method java/lang/StringBuilder."<init>":()V
      65: ldc           #192                // String Failed to override field value of config bean:
      67: invokevirtual #20                 // Method java/lang/StringBuilder.append:(Ljava/lang/String;)Ljava/lang/StringBuilder;
      70: aload_0
      71: invokevirtual #120                // Method java/lang/StringBuilder.append:(Ljava/lang/Object;)Ljava/lang/StringBuilder;
      74: invokevirtual #22                 // Method java/lang/StringBuilder.toString:()Ljava/lang/String;
      77: aload_1
      78: invokespecial #71                 // Method java/lang/IllegalStateException."<init>":(Ljava/lang/String;Ljava/lang/Throwable;)V
      81: athrow
      82: aload_0
      83: invokevirtual #197                // Method postProcessRefresh:()V
      86: aload_0
      87: getfield      #7                  // Field refreshed:Ljava/util/concurrent/atomic/AtomicBoolean;
      90: iconst_1
      91: invokevirtual #198                // Method java/util/concurrent/atomic/AtomicBoolean.set:(Z)V
      94: return
    Exception table:
       from    to  target type
           0    16    19   Class java/lang/Exception

  protected void refreshWithPrefixes(java.util.List<java.lang.String>, org.apache.dubbo.config.context.ConfigMode);
    Code:
       0: aload_0
       1: invokevirtual #128                // Method getScopeModel:()Lorg/apache/dubbo/rpc/model/ScopeModel;
       4: invokevirtual #199                // Method org/apache/dubbo/rpc/model/ScopeModel.getModelEnvironment:()Lorg/apache/dubbo/common/config/Environment;
       7: astore_3
       8: aload_3
       9: invokevirtual #200                // Method org/apache/dubbo/common/config/Environment.getConfigurationMaps:()Ljava/util/List;
      12: astore        4
      14: aconst_null
      15: astore        5
      17: aload_1
      18: invokeinterface #182,  1          // InterfaceMethod java/util/List.iterator:()Ljava/util/Iterator;
      23: astore        6
      25: aload         6
      27: invokeinterface #106,  1          // InterfaceMethod java/util/Iterator.hasNext:()Z
      32: ifeq          67
      35: aload         6
      37: invokeinterface #107,  1          // InterfaceMethod java/util/Iterator.next:()Ljava/lang/Object;
      42: checkcast     #12                 // class java/lang/String
      45: astore        7
      47: aload         4
      49: aload         7
      51: invokestatic  #201                // Method org/apache/dubbo/common/config/ConfigurationUtils.hasSubProperties:(Ljava/util/Collection;Ljava/lang/String;)Z
      54: ifeq          64
      57: aload         7
      59: astore        5
      61: goto          67
      64: goto          25
      67: aload         5
      69: ifnonnull     84
      72: aload_1
      73: iconst_0
      74: invokeinterface #202,  2          // InterfaceMethod java/util/List.get:(I)Ljava/lang/Object;
      79: checkcast     #12                 // class java/lang/String
      82: astore        5
      84: aload_3
      85: aload_0
      86: aload         5
      88: invokevirtual #203                // Method org/apache/dubbo/common/config/Environment.getConfigurationMaps:(Lorg/apache/dubbo/config/AbstractConfig;Ljava/lang/String;)Ljava/util/List;
      91: astore        6
      93: aload         6
      95: aload         5
      97: invokestatic  #204                // Method org/apache/dubbo/common/config/ConfigurationUtils.getSubProperties:(Ljava/util/Collection;Ljava/lang/String;)Ljava/util/Map;
     100: astore        7
     102: new           #205                // class org/apache/dubbo/common/config/InmemoryConfiguration
     105: dup
     106: aload         7
     108: invokespecial #206                // Method org/apache/dubbo/common/config/InmemoryConfiguration."<init>":(Ljava/util/Map;)V
     111: astore        8
     113: getstatic     #151                // Field logger:Lorg/apache/dubbo/common/logger/ErrorTypeAwareLogger;
     116: invokeinterface #207,  1          // InterfaceMethod org/apache/dubbo/common/logger/ErrorTypeAwareLogger.isDebugEnabled:()Z
     121: ifeq          274
     124: ldc           #103                // String
     126: astore        9
     128: aload_0
     129: invokevirtual #165                // Method getId:()Ljava/lang/String;
     132: invokestatic  #166                // Method org/apache/dubbo/common/utils/StringUtils.hasText:(Ljava/lang/CharSequence;)Z
     135: ifeq          170
     138: new           #16                 // class java/lang/StringBuilder
     141: dup
     142: invokespecial #17                 // Method java/lang/StringBuilder."<init>":()V
     145: ldc           #208                // String [id=
     147: invokevirtual #20                 // Method java/lang/StringBuilder.append:(Ljava/lang/String;)Ljava/lang/StringBuilder;
     150: aload_0
     151: invokevirtual #165                // Method getId:()Ljava/lang/String;
     154: invokevirtual #20                 // Method java/lang/StringBuilder.append:(Ljava/lang/String;)Ljava/lang/StringBuilder;
     157: ldc           #209                // String ]
     159: invokevirtual #20                 // Method java/lang/StringBuilder.append:(Ljava/lang/String;)Ljava/lang/StringBuilder;
     162: invokevirtual #22                 // Method java/lang/StringBuilder.toString:()Ljava/lang/String;
     165: astore        9
     167: goto          216
     170: aload_0
     171: ldc           #171                // String getName
     173: invokestatic  #172                // Method org/apache/dubbo/common/utils/ReflectUtils.getProperty:(Ljava/lang/Object;Ljava/lang/String;)Ljava/lang/Object;
     176: checkcast     #12                 // class java/lang/String
     179: astore        10
     181: aload         10
     183: invokestatic  #166                // Method org/apache/dubbo/common/utils/StringUtils.hasText:(Ljava/lang/CharSequence;)Z
     186: ifeq          216
     189: new           #16                 // class java/lang/StringBuilder
     192: dup
     193: invokespecial #17                 // Method java/lang/StringBuilder."<init>":()V
     196: ldc           #210                // String [name=
     198: invokevirtual #20                 // Method java/lang/StringBuilder.append:(Ljava/lang/String;)Ljava/lang/StringBuilder;
     201: aload         10
     203: invokevirtual #20                 // Method java/lang/StringBuilder.append:(Ljava/lang/String;)Ljava/lang/StringBuilder;
     206: ldc           #209                // String ]
     208: invokevirtual #20                 // Method java/lang/StringBuilder.append:(Ljava/lang/String;)Ljava/lang/StringBuilder;
     211: invokevirtual #22                 // Method java/lang/StringBuilder.toString:()Ljava/lang/String;
     214: astore        9
     216: getstatic     #151                // Field logger:Lorg/apache/dubbo/common/logger/ErrorTypeAwareLogger;
     219: new           #16                 // class java/lang/StringBuilder
     222: dup
     223: invokespecial #17                 // Method java/lang/StringBuilder."<init>":()V
     226: ldc           #211                // String Refreshing
     228: invokevirtual #20                 // Method java/lang/StringBuilder.append:(Ljava/lang/String;)Ljava/lang/StringBuilder;
     231: aload_0
     232: invokevirtual #27                 // Method java/lang/Object.getClass:()Ljava/lang/Class;
     235: invokevirtual #58                 // Method java/lang/Class.getSimpleName:()Ljava/lang/String;
     238: invokevirtual #20                 // Method java/lang/StringBuilder.append:(Ljava/lang/String;)Ljava/lang/StringBuilder;
     241: aload         9
     243: invokevirtual #20                 // Method java/lang/StringBuilder.append:(Ljava/lang/String;)Ljava/lang/StringBuilder;
     246: ldc           #212                // String  with prefix [
     248: invokevirtual #20                 // Method java/lang/StringBuilder.append:(Ljava/lang/String;)Ljava/lang/StringBuilder;
     251: aload         5
     253: invokevirtual #20                 // Method java/lang/StringBuilder.append:(Ljava/lang/String;)Ljava/lang/StringBuilder;
     256: ldc           #213                // String ], extracted props:
     258: invokevirtual #20                 // Method java/lang/StringBuilder.append:(Ljava/lang/String;)Ljava/lang/StringBuilder;
     261: aload         7
     263: invokevirtual #120                // Method java/lang/StringBuilder.append:(Ljava/lang/Object;)Ljava/lang/StringBuilder;
     266: invokevirtual #22                 // Method java/lang/StringBuilder.toString:()Ljava/lang/String;
     269: invokeinterface #214,  2          // InterfaceMethod org/apache/dubbo/common/logger/ErrorTypeAwareLogger.debug:(Ljava/lang/String;)V
     274: aload_0
     275: aload_0
     276: aload_3
     277: aload         7
     279: aload         8
     281: aload_2
     282: invokespecial #215                // Method assignProperties:(Ljava/lang/Object;Lorg/apache/dubbo/common/config/Environment;Ljava/util/Map;Lorg/apache/dubbo/common/config/InmemoryConfiguration;Lorg/apache/dubbo/config/context/ConfigMode;)V
     285: aload_0
     286: aload         5
     288: aload         8
     290: invokevirtual #216                // Method processExtraRefresh:(Ljava/lang/String;Lorg/apache/dubbo/common/config/InmemoryConfiguration;)V
     293: return

  private void assignProperties(java.lang.Object, org.apache.dubbo.common.config.Environment, java.util.Map<java.lang.String, java.lang.String>, org.apache.dubbo.common.config.InmemoryConfiguration, org.apache.dubbo.config.context.ConfigMode);
    Code:
       0: aload         5
       2: getstatic     #217                // Field org/apache/dubbo/config/context/ConfigMode.OVERRIDE_IF_ABSENT:Lorg/apache/dubbo/config/context/ConfigMode;
       5: if_acmpne     12
       8: iconst_1
       9: goto          13
      12: iconst_0
      13: istore        6
      15: aload         5
      17: getstatic     #218                // Field org/apache/dubbo/config/context/ConfigMode.OVERRIDE_ALL:Lorg/apache/dubbo/config/context/ConfigMode;
      20: if_acmpne     27
      23: iconst_1
      24: goto          28
      27: iconst_0
      28: istore        7
      30: aload_1
      31: invokevirtual #27                 // Method java/lang/Object.getClass:()Ljava/lang/Class;
      34: iconst_1
      35: anewarray     #179                // class java/util/function/Predicate
      38: dup
      39: iconst_0
      40: invokedynamic #219,  0            // InvokeDynamic #3:test:()Ljava/util/function/Predicate;
      45: aastore
      46: invokestatic  #181                // InterfaceMethod org/apache/dubbo/common/utils/MethodUtils.getMethods:(Ljava/lang/Class;[Ljava/util/function/Predicate;)Ljava/util/List;
      49: astore        8
      51: aload         8
      53: invokeinterface #182,  1          // InterfaceMethod java/util/List.iterator:()Ljava/util/Iterator;
      58: astore        9
      60: aload         9
      62: invokeinterface #106,  1          // InterfaceMethod java/util/Iterator.hasNext:()Z
      67: ifeq          626
      70: aload         9
      72: invokeinterface #107,  1          // InterfaceMethod java/util/Iterator.next:()Ljava/lang/Object;
      77: checkcast     #183                // class java/lang/reflect/Method
      80: astore        10
      82: aload         10
      84: invokestatic  #186                // InterfaceMethod org/apache/dubbo/common/utils/MethodUtils.isSetter:(Ljava/lang/reflect/Method;)Z
      87: ifeq          293
      90: aload         10
      92: invokevirtual #31                 // Method java/lang/reflect/Method.getName:()Ljava/lang/String;
      95: invokestatic  #184                // Method extractPropertyName:(Ljava/lang/String;)Ljava/lang/String;
      98: astore        11
     100: iload         6
     102: ifeq          119
     105: aload_0
     106: aload         8
     108: aload         11
     110: invokespecial #220                // Method isPropertySet:(Ljava/util/List;Ljava/lang/String;)Z
     113: ifeq          119
     116: goto          60
     119: aload         11
     121: ldc           #42                 // String -
     123: invokestatic  #43                 // Method org/apache/dubbo/common/utils/StringUtils.convertToSplitName:(Ljava/lang/String;Ljava/lang/String;)Ljava/lang/String;
     126: astore        12
     128: aload         4
     130: aload         12
     132: invokevirtual #221                // Method org/apache/dubbo/common/config/InmemoryConfiguration.getString:(Ljava/lang/String;)Ljava/lang/String;
     135: invokestatic  #222                // Method org/apache/dubbo/common/utils/StringUtils.trim:(Ljava/lang/String;)Ljava/lang/String;
     138: astore        13
     140: aload         13
     142: invokestatic  #166                // Method org/apache/dubbo/common/utils/StringUtils.hasText:(Ljava/lang/CharSequence;)Z
     145: ifeq          234
     148: aload         10
     150: invokevirtual #88                 // Method java/lang/reflect/Method.getParameterTypes:()[Ljava/lang/Class;
     153: iconst_0
     154: aaload
     155: aload         13
     157: invokestatic  #223                // Method org/apache/dubbo/common/utils/ClassUtils.isTypeMatch:(Ljava/lang/Class;Ljava/lang/String;)Z
     160: ifeq          234
     163: aload_0
     164: aload_1
     165: invokevirtual #27                 // Method java/lang/Object.getClass:()Ljava/lang/Class;
     168: aload         11
     170: invokespecial #224                // Method isIgnoredAttribute:(Ljava/lang/Class;Ljava/lang/String;)Z
     173: ifne          234
     176: aload_2
     177: aload         13
     179: invokevirtual #225                // Method org/apache/dubbo/common/config/Environment.resolvePlaceholders:(Ljava/lang/String;)Ljava/lang/String;
     182: astore        13
     184: aload         13
     186: invokestatic  #166                // Method org/apache/dubbo/common/utils/StringUtils.hasText:(Ljava/lang/CharSequence;)Z
     189: ifeq          234
     192: aload_0
     193: invokevirtual #128                // Method getScopeModel:()Lorg/apache/dubbo/rpc/model/ScopeModel;
     196: invokestatic  #226                // Method org/apache/dubbo/rpc/model/ScopeModelUtil.getFrameworkModel:(Lorg/apache/dubbo/rpc/model/ScopeModel;)Lorg/apache/dubbo/rpc/model/FrameworkModel;
     199: aload         10
     201: invokevirtual #88                 // Method java/lang/reflect/Method.getParameterTypes:()[Ljava/lang/Class;
     204: iconst_0
     205: aaload
     206: aload         13
     208: invokestatic  #227                // Method org/apache/dubbo/common/utils/ClassUtils.convertPrimitive:(Lorg/apache/dubbo/rpc/model/FrameworkModel;Ljava/lang/Class;Ljava/lang/String;)Ljava/lang/Object;
     211: astore        14
     213: aload         14
     215: ifnull        234
     218: aload         10
     220: aload_1
     221: iconst_1
     222: anewarray     #34                 // class java/lang/Object
     225: dup
     226: iconst_0
     227: aload         14
     229: aastore
     230: invokevirtual #44                 // Method java/lang/reflect/Method.invoke:(Ljava/lang/Object;[Ljava/lang/Object;)Ljava/lang/Object;
     233: pop
     234: goto          290
     237: astore        13
     239: getstatic     #151                // Field logger:Lorg/apache/dubbo/common/logger/ErrorTypeAwareLogger;
     242: new           #16                 // class java/lang/StringBuilder
     245: dup
     246: invokespecial #17                 // Method java/lang/StringBuilder."<init>":()V
     249: ldc           #228                // String Failed to override the property
     251: invokevirtual #20                 // Method java/lang/StringBuilder.append:(Ljava/lang/String;)Ljava/lang/StringBuilder;
     254: aload         10
     256: invokevirtual #31                 // Method java/lang/reflect/Method.getName:()Ljava/lang/String;
     259: invokevirtual #20                 // Method java/lang/StringBuilder.append:(Ljava/lang/String;)Ljava/lang/StringBuilder;
     262: ldc           #229                // String  in
     264: invokevirtual #20                 // Method java/lang/StringBuilder.append:(Ljava/lang/String;)Ljava/lang/StringBuilder;
     267: aload_1
     268: invokevirtual #27                 // Method java/lang/Object.getClass:()Ljava/lang/Class;
     271: invokevirtual #58                 // Method java/lang/Class.getSimpleName:()Ljava/lang/String;
     274: invokevirtual #20                 // Method java/lang/StringBuilder.append:(Ljava/lang/String;)Ljava/lang/StringBuilder;
     277: ldc           #230                // String , please make sure every property has getter/setter method provided.
     279: invokevirtual #20                 // Method java/lang/StringBuilder.append:(Ljava/lang/String;)Ljava/lang/StringBuilder;
     282: invokevirtual #22                 // Method java/lang/StringBuilder.toString:()Ljava/lang/String;
     285: invokeinterface #231,  2          // InterfaceMethod org/apache/dubbo/common/logger/ErrorTypeAwareLogger.info:(Ljava/lang/String;)V
     290: goto          623
     293: aload         10
     295: invokestatic  #82                 // Method isParametersSetter:(Ljava/lang/reflect/Method;)Z
     298: ifeq          492
     301: aload         10
     303: invokevirtual #31                 // Method java/lang/reflect/Method.getName:()Ljava/lang/String;
     306: invokestatic  #184                // Method extractPropertyName:(Ljava/lang/String;)Ljava/lang/String;
     309: astore        11
     311: aload         4
     313: aload         11
     315: invokevirtual #221                // Method org/apache/dubbo/common/config/InmemoryConfiguration.getString:(Ljava/lang/String;)Ljava/lang/String;
     318: invokestatic  #222                // Method org/apache/dubbo/common/utils/StringUtils.trim:(Ljava/lang/String;)Ljava/lang/String;
     321: astore        12
     323: aload         12
     325: invokestatic  #166                // Method org/apache/dubbo/common/utils/StringUtils.hasText:(Ljava/lang/CharSequence;)Z
     328: ifeq          341
     331: aload         12
     333: invokestatic  #232                // Method org/apache/dubbo/common/utils/StringUtils.parseParameters:(Ljava/lang/String;)Ljava/util/Map;
     336: astore        13
     338: goto          349
     341: aload_3
     342: ldc           #146                // String parameters
     344: invokestatic  #233                // Method org/apache/dubbo/common/config/ConfigurationUtils.getSubProperties:(Ljava/util/Map;Ljava/lang/String;)Ljava/util/Map;
     347: astore        13
     349: aload         13
     351: ldc           #103                // String
     353: invokestatic  #63                 // Method convert:(Ljava/util/Map;Ljava/lang/String;)Ljava/util/Map;
     356: astore        14
     358: aload         14
     360: invokestatic  #234                // Method org/apache/dubbo/common/utils/CollectionUtils.isEmptyMap:(Ljava/util/Map;)Z
     363: ifeq          369
     366: goto          60
     369: aconst_null
     370: astore        15
     372: aload         11
     374: invokestatic  #185                // Method calculatePropertyToGetter:(Ljava/lang/String;)Ljava/lang/String;
     377: astore        16
     379: aload_0
     380: invokevirtual #27                 // Method java/lang/Object.getClass:()Ljava/lang/Class;
     383: aload         16
     385: iconst_0
     386: anewarray     #148                // class java/lang/Class
     389: invokevirtual #149                // Method java/lang/Class.getMethod:(Ljava/lang/String;[Ljava/lang/Class;)Ljava/lang/reflect/Method;
     392: astore        17
     394: aload         17
     396: aload_0
     397: iconst_0
     398: anewarray     #34                 // class java/lang/Object
     401: invokevirtual #44                 // Method java/lang/reflect/Method.invoke:(Ljava/lang/Object;[Ljava/lang/Object;)Ljava/lang/Object;
     404: astore        18
     406: aload         18
     408: instanceof    #62                 // class java/util/Map
     411: ifeq          421
     414: aload         18
     416: checkcast     #62                 // class java/util/Map
     419: astore        15
     421: goto          426
     424: astore        16
     426: aload         15
     428: ifnonnull     441
     431: aload_0
     432: aload         14
     434: aload_1
     435: invokespecial #187                // Method invokeSetParameters:(Ljava/util/Map;Ljava/lang/Object;)V
     438: goto          60
     441: iload         6
     443: ifeq          458
     446: aload         14
     448: aload         15
     450: invokeinterface #64,  2           // InterfaceMethod java/util/Map.putAll:(Ljava/util/Map;)V
     455: goto          482
     458: iload         7
     460: ifeq          482
     463: aload         15
     465: aload         14
     467: dup
     468: invokevirtual #27                 // Method java/lang/Object.getClass:()Ljava/lang/Class;
     471: pop
     472: invokedynamic #188,  0            // InvokeDynamic #2:accept:(Ljava/util/Map;)Ljava/util/function/BiConsumer;
     477: invokeinterface #189,  2          // InterfaceMethod java/util/Map.forEach:(Ljava/util/function/BiConsumer;)V
     482: aload_0
     483: aload         14
     485: aload_1
     486: invokespecial #187                // Method invokeSetParameters:(Ljava/util/Map;Ljava/lang/Object;)V
     489: goto          623
     492: aload_1
     493: aload         10
     495: invokestatic  #190                // Method isNestedSetter:(Ljava/lang/Object;Ljava/lang/reflect/Method;)Z
     498: ifeq          623
     501: aload         10
     503: invokevirtual #88                 // Method java/lang/reflect/Method.getParameterTypes:()[Ljava/lang/Class;
     506: iconst_0
     507: aaload
     508: astore        11
     510: aload         11
     512: iconst_0
     513: anewarray     #148                // class java/lang/Class
     516: invokevirtual #235                // Method java/lang/Class.getDeclaredConstructor:([Ljava/lang/Class;)Ljava/lang/reflect/Constructor;
     519: iconst_0
     520: anewarray     #34                 // class java/lang/Object
     523: invokevirtual #236                // Method java/lang/reflect/Constructor.newInstance:([Ljava/lang/Object;)Ljava/lang/Object;
     526: astore        12
     528: aload         10
     530: invokestatic  #67                 // InterfaceMethod org/apache/dubbo/common/utils/MethodUtils.extractFieldName:(Ljava/lang/reflect/Method;)Ljava/lang/String;
     533: astore        13
     535: aload_3
     536: aload         13
     538: invokestatic  #233                // Method org/apache/dubbo/common/config/ConfigurationUtils.getSubProperties:(Ljava/util/Map;Ljava/lang/String;)Ljava/util/Map;
     541: astore        14
     543: new           #205                // class org/apache/dubbo/common/config/InmemoryConfiguration
     546: dup
     547: aload         14
     549: invokespecial #206                // Method org/apache/dubbo/common/config/InmemoryConfiguration."<init>":(Ljava/util/Map;)V
     552: astore        15
     554: aload_0
     555: aload         12
     557: aload_2
     558: aload         14
     560: aload         15
     562: aload         5
     564: invokespecial #215                // Method assignProperties:(Ljava/lang/Object;Lorg/apache/dubbo/common/config/Environment;Ljava/util/Map;Lorg/apache/dubbo/common/config/InmemoryConfiguration;Lorg/apache/dubbo/config/context/ConfigMode;)V
     567: aload         10
     569: aload_1
     570: iconst_1
     571: anewarray     #34                 // class java/lang/Object
     574: dup
     575: iconst_0
     576: aload         12
     578: aastore
     579: invokevirtual #44                 // Method java/lang/reflect/Method.invoke:(Ljava/lang/Object;[Ljava/lang/Object;)Ljava/lang/Object;
     582: pop
     583: goto          623
     586: astore        11
     588: new           #57                 // class java/lang/IllegalStateException
     591: dup
     592: new           #16                 // class java/lang/StringBuilder
     595: dup
     596: invokespecial #17                 // Method java/lang/StringBuilder."<init>":()V
     599: ldc           #238                // String Cannot assign nested class when refreshing config:
     601: invokevirtual #20                 // Method java/lang/StringBuilder.append:(Ljava/lang/String;)Ljava/lang/StringBuilder;
     604: aload_1
     605: invokevirtual #27                 // Method java/lang/Object.getClass:()Ljava/lang/Class;
     608: invokevirtual #80                 // Method java/lang/Class.getName:()Ljava/lang/String;
     611: invokevirtual #20                 // Method java/lang/StringBuilder.append:(Ljava/lang/String;)Ljava/lang/StringBuilder;
     614: invokevirtual #22                 // Method java/lang/StringBuilder.toString:()Ljava/lang/String;
     617: aload         11
     619: invokespecial #71                 // Method java/lang/IllegalStateException."<init>":(Ljava/lang/String;Ljava/lang/Throwable;)V
     622: athrow
     623: goto          60
     626: return
    Exception table:
       from    to  target type
         128   234   237   Class java/lang/Exception
         372   421   424   Class java/lang/Exception
         501   583   586   Class java/lang/ReflectiveOperationException

  private boolean isPropertySet(java.util.List<java.lang.reflect.Method>, java.lang.String);
    Code:
       0: aload_2
       1: invokestatic  #185                // Method calculatePropertyToGetter:(Ljava/lang/String;)Ljava/lang/String;
       4: astore_3
       5: aload_0
       6: aload_1
       7: aload_3
       8: invokespecial #239                // Method findGetMethod:(Ljava/util/List;Ljava/lang/String;)Ljava/lang/reflect/Method;
      11: astore        4
      13: aload         4
      15: ifnonnull     20
      18: iconst_0
      19: ireturn
      20: aload         4
      22: aload_0
      23: iconst_0
      24: anewarray     #34                 // class java/lang/Object
      27: invokevirtual #44                 // Method java/lang/reflect/Method.invoke:(Ljava/lang/Object;[Ljava/lang/Object;)Ljava/lang/Object;
      30: astore        5
      32: aload         5
      34: ifnull        39
      37: iconst_1
      38: ireturn
      39: goto          43
      42: astore_3
      43: iconst_0
      44: ireturn
    Exception table:
       from    to  target type
           0    19    42   Class java/lang/Exception
          20    38    42   Class java/lang/Exception

  private java.lang.reflect.Method findGetMethod(java.util.List<java.lang.reflect.Method>, java.lang.String);
    Code:
       0: aload_1
       1: invokeinterface #182,  1          // InterfaceMethod java/util/List.iterator:()Ljava/util/Iterator;
       6: astore_3
       7: aload_3
       8: invokeinterface #106,  1          // InterfaceMethod java/util/Iterator.hasNext:()Z
      13: ifeq          53
      16: aload_3
      17: invokeinterface #107,  1          // InterfaceMethod java/util/Iterator.next:()Ljava/lang/Object;
      22: checkcast     #183                // class java/lang/reflect/Method
      25: astore        4
      27: aload         4
      29: invokevirtual #31                 // Method java/lang/reflect/Method.getName:()Ljava/lang/String;
      32: aload_2
      33: invokevirtual #85                 // Method java/lang/String.equals:(Ljava/lang/Object;)Z
      36: ifeq          50
      39: aload         4
      41: invokevirtual #89                 // Method java/lang/reflect/Method.getParameterCount:()I
      44: ifne          50
      47: aload         4
      49: areturn
      50: goto          7
      53: aconst_null
      54: areturn

  private void invokeSetParameters(java.util.Map<java.lang.String, java.lang.String>, java.lang.Object);
    Code:
       0: aload_1
       1: invokestatic  #234                // Method org/apache/dubbo/common/utils/CollectionUtils.isEmptyMap:(Ljava/util/Map;)Z
       4: ifeq          8
       7: return
       8: new           #100                // class java/util/HashMap
      11: dup
      12: invokespecial #101                // Method java/util/HashMap."<init>":()V
      15: astore_3
      16: aload_2
      17: invokevirtual #27                 // Method java/lang/Object.getClass:()Ljava/lang/Class;
      20: aload_2
      21: invokestatic  #240                // Method invokeGetParameters:(Ljava/lang/Class;Ljava/lang/Object;)Ljava/util/Map;
      24: astore        4
      26: aload         4
      28: ifnull        49
      31: aload         4
      33: invokeinterface #99,  1           // InterfaceMethod java/util/Map.isEmpty:()Z
      38: ifne          49
      41: aload_3
      42: aload         4
      44: invokeinterface #64,  2           // InterfaceMethod java/util/Map.putAll:(Ljava/util/Map;)V
      49: aload_3
      50: aload_1
      51: invokeinterface #64,  2           // InterfaceMethod java/util/Map.putAll:(Ljava/util/Map;)V
      56: aload_2
      57: invokevirtual #27                 // Method java/lang/Object.getClass:()Ljava/lang/Class;
      60: aload_2
      61: aload_3
      62: invokestatic  #241                // Method invokeSetParameters:(Ljava/lang/Class;Ljava/lang/Object;Ljava/util/Map;)V
      65: return

  private boolean isIgnoredAttribute(java.lang.Class<?>, java.lang.String);
    Code:
       0: aconst_null
       1: astore_3
       2: new           #16                 // class java/lang/StringBuilder
       5: dup
       6: invokespecial #17                 // Method java/lang/StringBuilder."<init>":()V
       9: aload_2
      10: iconst_0
      11: iconst_1
      12: invokevirtual #19                 // Method java/lang/String.substring:(II)Ljava/lang/String;
      15: invokevirtual #76                 // Method java/lang/String.toUpperCase:()Ljava/lang/String;
      18: invokevirtual #20                 // Method java/lang/StringBuilder.append:(Ljava/lang/String;)Ljava/lang/StringBuilder;
      21: aload_2
      22: iconst_1
      23: invokevirtual #73                 // Method java/lang/String.substring:(I)Ljava/lang/String;
      26: invokevirtual #20                 // Method java/lang/StringBuilder.append:(Ljava/lang/String;)Ljava/lang/StringBuilder;
      29: invokevirtual #22                 // Method java/lang/StringBuilder.toString:()Ljava/lang/String;
      32: astore        4
      34: aload_1
      35: new           #16                 // class java/lang/StringBuilder
      38: dup
      39: invokespecial #17                 // Method java/lang/StringBuilder."<init>":()V
      42: ldc           #75                 // String get
      44: invokevirtual #20                 // Method java/lang/StringBuilder.append:(Ljava/lang/String;)Ljava/lang/StringBuilder;
      47: aload         4
      49: invokevirtual #20                 // Method java/lang/StringBuilder.append:(Ljava/lang/String;)Ljava/lang/StringBuilder;
      52: invokevirtual #22                 // Method java/lang/StringBuilder.toString:()Ljava/lang/String;
      55: iconst_0
      56: anewarray     #148                // class java/lang/Class
      59: invokevirtual #149                // Method java/lang/Class.getMethod:(Ljava/lang/String;[Ljava/lang/Class;)Ljava/lang/reflect/Method;
      62: astore_3
      63: goto          102
      66: astore        5
      68: aload_1
      69: new           #16                 // class java/lang/StringBuilder
      72: dup
      73: invokespecial #17                 // Method java/lang/StringBuilder."<init>":()V
      76: ldc           #91                 // String is
      78: invokevirtual #20                 // Method java/lang/StringBuilder.append:(Ljava/lang/String;)Ljava/lang/StringBuilder;
      81: aload         4
      83: invokevirtual #20                 // Method java/lang/StringBuilder.append:(Ljava/lang/String;)Ljava/lang/StringBuilder;
      86: invokevirtual #22                 // Method java/lang/StringBuilder.toString:()Ljava/lang/String;
      89: iconst_0
      90: anewarray     #148                // class java/lang/Class
      93: invokevirtual #149                // Method java/lang/Class.getMethod:(Ljava/lang/String;[Ljava/lang/Class;)Ljava/lang/reflect/Method;
      96: astore_3
      97: goto          102
     100: astore        6
     102: aload_3
     103: ifnonnull     108
     106: iconst_1
     107: ireturn
     108: aload_3
     109: ldc           #35                 // class org/apache/dubbo/config/support/Parameter
     111: invokevirtual #36                 // Method java/lang/reflect/Method.getAnnotation:(Ljava/lang/Class;)Ljava/lang/annotation/Annotation;
     114: checkcast     #35                 // class org/apache/dubbo/config/support/Parameter
     117: astore        5
     119: aload         5
     121: ifnull        138
     124: aload         5
     126: invokeinterface #40,  1           // InterfaceMethod org/apache/dubbo/config/support/Parameter.attribute:()Z
     131: ifne          138
     134: iconst_1
     135: goto          139
     138: iconst_0
     139: ireturn
    Exception table:
       from    to  target type
          34    63    66   Class java/lang/NoSuchMethodException
          68    97   100   Class java/lang/NoSuchMethodException

  protected void processExtraRefresh(java.lang.String, org.apache.dubbo.common.config.InmemoryConfiguration);
    Code:
       0: return

  protected void preProcessRefresh();
    Code:
       0: return

  protected void postProcessRefresh();
    Code:
       0: aload_0
       1: invokevirtual #242                // Method checkDefault:()V
       4: return

  protected void checkDefault();
    Code:
       0: return

  public boolean isRefreshed();
    Code:
       0: aload_0
       1: getfield      #7                  // Field refreshed:Ljava/util/concurrent/atomic/AtomicBoolean;
       4: invokevirtual #243                // Method java/util/concurrent/atomic/AtomicBoolean.get:()Z
       7: ireturn

  public boolean isValid();
    Code:
       0: iconst_1
       1: ireturn

  public java.lang.Boolean isDefault();
    Code:
       0: aload_0
       1: getfield      #244                // Field isDefault:Ljava/lang/Boolean;
       4: areturn

  public void setDefault(java.lang.Boolean);
    Code:
       0: aload_0
       1: aload_1
       2: putfield      #244                // Field isDefault:Ljava/lang/Boolean;
       5: return

  public java.lang.String toString();
    Code:
       0: new           #16                 // class java/lang/StringBuilder
       3: dup
       4: invokespecial #17                 // Method java/lang/StringBuilder."<init>":()V
       7: astore_1
       8: aload_1
       9: ldc           #245                // String <dubbo:
      11: invokevirtual #20                 // Method java/lang/StringBuilder.append:(Ljava/lang/String;)Ljava/lang/StringBuilder;
      14: pop
      15: aload_1
      16: aload_0
      17: invokevirtual #27                 // Method java/lang/Object.getClass:()Ljava/lang/Class;
      20: invokestatic  #13                 // Method getTagName:(Ljava/lang/Class;)Ljava/lang/String;
      23: invokevirtual #20                 // Method java/lang/StringBuilder.append:(Ljava/lang/String;)Ljava/lang/StringBuilder;
      26: pop
      27: aload_0
      28: invokespecial #246                // Method getAttributedMethods:()Ljava/util/List;
      31: invokeinterface #182,  1          // InterfaceMethod java/util/List.iterator:()Ljava/util/Iterator;
      36: astore_2
      37: aload_2
      38: invokeinterface #106,  1          // InterfaceMethod java/util/Iterator.hasNext:()Z
      43: ifeq          164
      46: aload_2
      47: invokeinterface #107,  1          // InterfaceMethod java/util/Iterator.next:()Ljava/lang/Object;
      52: checkcast     #183                // class java/lang/reflect/Method
      55: astore_3
      56: aload_3
      57: invokevirtual #31                 // Method java/lang/reflect/Method.getName:()Ljava/lang/String;
      60: astore        4
      62: aload         4
      64: invokestatic  #41                 // Method calculateAttributeFromGetter:(Ljava/lang/String;)Ljava/lang/String;
      67: astore        5
      69: aload_3
      70: aload_0
      71: iconst_0
      72: anewarray     #34                 // class java/lang/Object
      75: invokevirtual #44                 // Method java/lang/reflect/Method.invoke:(Ljava/lang/Object;[Ljava/lang/Object;)Ljava/lang/Object;
      78: astore        6
      80: aload         6
      82: ifnull        135
      85: aload_1
      86: bipush        32
      88: invokevirtual #247                // Method java/lang/StringBuilder.append:(C)Ljava/lang/StringBuilder;
      91: pop
      92: aload_1
      93: aload         5
      95: invokevirtual #20                 // Method java/lang/StringBuilder.append:(Ljava/lang/String;)Ljava/lang/StringBuilder;
      98: pop
      99: aload_1
     100: ldc           #248                // String =\"
     102: invokevirtual #20                 // Method java/lang/StringBuilder.append:(Ljava/lang/String;)Ljava/lang/StringBuilder;
     105: pop
     106: aload_1
     107: aload         5
     109: ldc           #249                // String password
     111: invokevirtual #85                 // Method java/lang/String.equals:(Ljava/lang/Object;)Z
     114: ifeq          122
     117: ldc           #250                // String ******
     119: goto          124
     122: aload         6
     124: invokevirtual #120                // Method java/lang/StringBuilder.append:(Ljava/lang/Object;)Ljava/lang/StringBuilder;
     127: pop
     128: aload_1
     129: bipush        34
     131: invokevirtual #247                // Method java/lang/StringBuilder.append:(C)Ljava/lang/StringBuilder;
     134: pop
     135: goto          161
     138: astore        4
     140: getstatic     #151                // Field logger:Lorg/apache/dubbo/common/logger/ErrorTypeAwareLogger;
     143: ldc           #251                // String 0-12
     145: ldc           #103                // String
     147: ldc           #103                // String
     149: aload         4
     151: invokevirtual #70                 // Method java/lang/Exception.getMessage:()Ljava/lang/String;
     154: aload         4
     156: invokeinterface #252,  6          // InterfaceMethod org/apache/dubbo/common/logger/ErrorTypeAwareLogger.warn:(Ljava/lang/String;Ljava/lang/String;Ljava/lang/String;Ljava/lang/String;Ljava/lang/Throwable;)V
     161: goto          37
     164: aload_1
     165: ldc           #253                // String  />
     167: invokevirtual #20                 // Method java/lang/StringBuilder.append:(Ljava/lang/String;)Ljava/lang/StringBuilder;
     170: pop
     171: aload_1
     172: invokevirtual #22                 // Method java/lang/StringBuilder.toString:()Ljava/lang/String;
     175: areturn
     176: astore_1
     177: getstatic     #151                // Field logger:Lorg/apache/dubbo/common/logger/ErrorTypeAwareLogger;
     180: ldc           #251                // String 0-12
     182: ldc           #103                // String
     184: ldc           #103                // String
     186: aload_1
     187: invokevirtual #153                // Method java/lang/Throwable.getMessage:()Ljava/lang/String;
     190: aload_1
     191: invokeinterface #252,  6          // InterfaceMethod org/apache/dubbo/common/logger/ErrorTypeAwareLogger.warn:(Ljava/lang/String;Ljava/lang/String;Ljava/lang/String;Ljava/lang/String;Ljava/lang/Throwable;)V
     196: aload_0
     197: invokespecial #254                // Method java/lang/Object.toString:()Ljava/lang/String;
     200: areturn
    Exception table:
       from    to  target type
          56   135   138   Class java/lang/Exception
           0   175   176   Class java/lang/Throwable

  public boolean equals(java.lang.Object);
    Code:
       0: aload_1
       1: ifnull        15
       4: aload_1
       5: invokevirtual #27                 // Method java/lang/Object.getClass:()Ljava/lang/Class;
       8: aload_0
       9: invokevirtual #27                 // Method java/lang/Object.getClass:()Ljava/lang/Class;
      12: if_acmpeq     17
      15: iconst_0
      16: ireturn
      17: aload_1
      18: aload_0
      19: if_acmpne     24
      22: iconst_1
      23: ireturn
      24: aload_0
      25: invokespecial #246                // Method getAttributedMethods:()Ljava/util/List;
      28: invokeinterface #182,  1          // InterfaceMethod java/util/List.iterator:()Ljava/util/Iterator;
      33: astore_2
      34: aload_2
      35: invokeinterface #106,  1          // InterfaceMethod java/util/Iterator.hasNext:()Z
      40: ifeq          123
      43: aload_2
      44: invokeinterface #107,  1          // InterfaceMethod java/util/Iterator.next:()Ljava/lang/Object;
      49: checkcast     #183                // class java/lang/reflect/Method
      52: astore_3
      53: ldc           #255                // String getId
      55: aload_3
      56: invokevirtual #31                 // Method java/lang/reflect/Method.getName:()Ljava/lang/String;
      59: invokevirtual #85                 // Method java/lang/String.equals:(Ljava/lang/Object;)Z
      62: ifeq          68
      65: goto          34
      68: aload_3
      69: aload_0
      70: iconst_0
      71: anewarray     #34                 // class java/lang/Object
      74: invokevirtual #44                 // Method java/lang/reflect/Method.invoke:(Ljava/lang/Object;[Ljava/lang/Object;)Ljava/lang/Object;
      77: astore        4
      79: aload_3
      80: aload_1
      81: iconst_0
      82: anewarray     #34                 // class java/lang/Object
      85: invokevirtual #44                 // Method java/lang/reflect/Method.invoke:(Ljava/lang/Object;[Ljava/lang/Object;)Ljava/lang/Object;
      88: astore        5
      90: aload         4
      92: aload         5
      94: invokestatic  #178                // Method java/util/Objects.equals:(Ljava/lang/Object;Ljava/lang/Object;)Z
      97: ifne          102
     100: iconst_0
     101: ireturn
     102: goto          120
     105: astore        4
     107: new           #57                 // class java/lang/IllegalStateException
     110: dup
     111: ldc_w         #256                // String compare config instances failed
     114: aload         4
     116: invokespecial #71                 // Method java/lang/IllegalStateException."<init>":(Ljava/lang/String;Ljava/lang/Throwable;)V
     119: athrow
     120: goto          34
     123: iconst_1
     124: ireturn
    Exception table:
       from    to  target type
          68   101   105   Class java/lang/Exception

  public int hashCode();
    Code:
       0: iconst_1
       1: istore_1
       2: aload_0
       3: invokespecial #246                // Method getAttributedMethods:()Ljava/util/List;
       6: invokeinterface #182,  1          // InterfaceMethod java/util/List.iterator:()Ljava/util/Iterator;
      11: astore_2
      12: aload_2
      13: invokeinterface #106,  1          // InterfaceMethod java/util/Iterator.hasNext:()Z
      18: ifeq          81
      21: aload_2
      22: invokeinterface #107,  1          // InterfaceMethod java/util/Iterator.next:()Ljava/lang/Object;
      27: checkcast     #183                // class java/lang/reflect/Method
      30: astore_3
      31: ldc           #255                // String getId
      33: aload_3
      34: invokevirtual #31                 // Method java/lang/reflect/Method.getName:()Ljava/lang/String;
      37: invokevirtual #85                 // Method java/lang/String.equals:(Ljava/lang/Object;)Z
      40: ifeq          46
      43: goto          12
      46: aload_3
      47: aload_0
      48: iconst_0
      49: anewarray     #34                 // class java/lang/Object
      52: invokevirtual #44                 // Method java/lang/reflect/Method.invoke:(Ljava/lang/Object;[Ljava/lang/Object;)Ljava/lang/Object;
      55: astore        4
      57: aload         4
      59: ifnull        73
      62: bipush        31
      64: iload_1
      65: imul
      66: aload         4
      68: invokevirtual #257                // Method java/lang/Object.hashCode:()I
      71: iadd
      72: istore_1
      73: goto          78
      76: astore        4
      78: goto          12
      81: iload_1
      82: ifne          87
      85: iconst_1
      86: istore_1
      87: iload_1
      88: ireturn
    Exception table:
       from    to  target type
          46    73    76   Class java/lang/Exception

  private java.util.List<java.lang.reflect.Method> getAttributedMethods();
    Code:
       0: aload_0
       1: invokevirtual #27                 // Method java/lang/Object.getClass:()Ljava/lang/Class;
       4: astore_1
       5: getstatic     #258                // Field attributedMethodCache:Ljava/util/concurrent/ConcurrentMap;
       8: aload_1
       9: aload_0
      10: invokedynamic #259,  0            // InvokeDynamic #4:apply:(Lorg/apache/dubbo/config/AbstractConfig;)Ljava/util/function/Function;
      15: invokestatic  #11                 // Method org/apache/dubbo/common/utils/ConcurrentHashMapUtils.computeIfAbsent:(Ljava/util/concurrent/ConcurrentMap;Ljava/lang/Object;Ljava/util/function/Function;)Ljava/lang/Object;
      18: checkcast     #260                // class java/util/List
      21: areturn

  protected java.util.List<java.lang.reflect.Method> computeAttributedMethods();
    Code:
       0: aload_0
       1: invokevirtual #27                 // Method java/lang/Object.getClass:()Ljava/lang/Class;
       4: astore_1
       5: aload_1
       6: invokestatic  #28                 // Method getBeanInfo:(Ljava/lang/Class;)Ljava/beans/BeanInfo;
       9: astore_2
      10: new           #163                // class java/util/ArrayList
      13: dup
      14: aload_2
      15: invokeinterface #29,  1           // InterfaceMethod java/beans/BeanInfo.getMethodDescriptors:()[Ljava/beans/MethodDescriptor;
      20: arraylength
      21: invokespecial #261                // Method java/util/ArrayList."<init>":(I)V
      24: astore_3
      25: aload_2
      26: invokeinterface #29,  1           // InterfaceMethod java/beans/BeanInfo.getMethodDescriptors:()[Ljava/beans/MethodDescriptor;
      31: astore        4
      33: aload         4
      35: arraylength
      36: istore        5
      38: iconst_0
      39: istore        6
      41: iload         6
      43: iload         5
      45: if_icmpge     145
      48: aload         4
      50: iload         6
      52: aaload
      53: astore        7
      55: aload         7
      57: invokevirtual #30                 // Method java/beans/MethodDescriptor.getMethod:()Ljava/lang/reflect/Method;
      60: astore        8
      62: aload         8
      64: invokestatic  #32                 // InterfaceMethod org/apache/dubbo/common/utils/MethodUtils.isGetter:(Ljava/lang/reflect/Method;)Z
      67: ifne          78
      70: aload         8
      72: invokestatic  #61                 // Method isParametersGetter:(Ljava/lang/reflect/Method;)Z
      75: ifeq          139
      78: aload         8
      80: ldc           #35                 // class org/apache/dubbo/config/support/Parameter
      82: invokevirtual #36                 // Method java/lang/reflect/Method.getAnnotation:(Ljava/lang/Class;)Ljava/lang/annotation/Annotation;
      85: checkcast     #35                 // class org/apache/dubbo/config/support/Parameter
      88: astore        9
      90: aload         9
      92: ifnull        108
      95: aload         9
      97: invokeinterface #40,  1           // InterfaceMethod org/apache/dubbo/config/support/Parameter.attribute:()Z
     102: ifne          108
     105: goto          139
     108: aload         8
     110: invokevirtual #31                 // Method java/lang/reflect/Method.getName:()Ljava/lang/String;
     113: invokestatic  #41                 // Method calculateAttributeFromGetter:(Ljava/lang/String;)Ljava/lang/String;
     116: astore        10
     118: aload_2
     119: aload         10
     121: invokestatic  #262                // Method isWritableProperty:(Ljava/beans/BeanInfo;Ljava/lang/String;)Z
     124: ifne          130
     127: goto          139
     130: aload_3
     131: aload         8
     133: invokeinterface #170,  2          // InterfaceMethod java/util/List.add:(Ljava/lang/Object;)Z
     138: pop
     139: iinc          6, 1
     142: goto          41
     145: aload_3
     146: areturn

  protected org.apache.dubbo.config.context.ConfigManager getConfigManager();
    Code:
       0: aload_0
       1: invokevirtual #175                // Method getApplicationModel:()Lorg/apache/dubbo/rpc/model/ApplicationModel;
       4: invokevirtual #176                // Method org/apache/dubbo/rpc/model/ApplicationModel.getApplicationConfigManager:()Lorg/apache/dubbo/config/context/ConfigManager;
       7: areturn

  private java.util.List lambda$getAttributedMethods$3(java.lang.Class);
    Code:
       0: aload_0
       1: invokevirtual #263                // Method computeAttributedMethods:()Ljava/util/List;
       4: areturn

  private static boolean lambda$assignProperties$2(java.lang.reflect.Method);
    Code:
       0: aload_0
       1: invokevirtual #132                // Method java/lang/reflect/Method.getDeclaringClass:()Ljava/lang/Class;
       4: ldc           #34                 // class java/lang/Object
       6: if_acmpeq     13
       9: iconst_1
      10: goto          14
      13: iconst_0
      14: ireturn

  private static boolean lambda$overrideWithConfig$1(java.lang.reflect.Method);
    Code:
       0: aload_0
       1: invokevirtual #132                // Method java/lang/reflect/Method.getDeclaringClass:()Ljava/lang/Class;
       4: ldc           #34                 // class java/lang/Object
       6: if_acmpeq     13
       9: iconst_1
      10: goto          14
      13: iconst_0
      14: ireturn

  private static java.lang.String lambda$getTagName$0(java.lang.Class, java.lang.Class);
    Code:
       0: aload_0
       1: invokevirtual #58                 // Method java/lang/Class.getSimpleName:()Ljava/lang/String;
       4: astore_2
       5: getstatic     #264                // Field SUFFIXES:[Ljava/lang/String;
       8: astore_3
       9: aload_3
      10: arraylength
      11: istore        4
      13: iconst_0
      14: istore        5
      16: iload         5
      18: iload         4
      20: if_icmpge     63
      23: aload_3
      24: iload         5
      26: aaload
      27: astore        6
      29: aload_2
      30: aload         6
      32: invokevirtual #15                 // Method java/lang/String.endsWith:(Ljava/lang/String;)Z
      35: ifeq          57
      38: aload_2
      39: iconst_0
      40: aload_2
      41: invokevirtual #18                 // Method java/lang/String.length:()I
      44: aload         6
      46: invokevirtual #18                 // Method java/lang/String.length:()I
      49: isub
      50: invokevirtual #19                 // Method java/lang/String.substring:(II)Ljava/lang/String;
      53: astore_2
      54: goto          63
      57: iinc          5, 1
      60: goto          16
      63: aload_2
      64: ldc           #42                 // String -
      66: invokestatic  #78                 // Method org/apache/dubbo/common/utils/StringUtils.camelToSplitName:(Ljava/lang/String;Ljava/lang/String;)Ljava/lang/String;
      69: areturn

  static {};
    Code:
       0: ldc_w         #265                // class org/apache/dubbo/config/AbstractConfig
       3: invokestatic  #266                // Method org/apache/dubbo/common/logger/LoggerFactory.getErrorTypeAwareLogger:(Ljava/lang/Class;)Lorg/apache/dubbo/common/logger/ErrorTypeAwareLogger;
       6: putstatic     #151                // Field logger:Lorg/apache/dubbo/common/logger/ErrorTypeAwareLogger;
       9: new           #267                // class java/util/concurrent/ConcurrentHashMap
      12: dup
      13: invokespecial #268                // Method java/util/concurrent/ConcurrentHashMap."<init>":()V
      16: putstatic     #9                  // Field tagNameCache:Ljava/util/concurrent/ConcurrentMap;
      19: new           #267                // class java/util/concurrent/ConcurrentHashMap
      22: dup
      23: invokespecial #268                // Method java/util/concurrent/ConcurrentHashMap."<init>":()V
      26: putstatic     #258                // Field attributedMethodCache:Ljava/util/concurrent/ConcurrentMap;
      29: iconst_3
      30: anewarray     #12                 // class java/lang/String
      33: dup
      34: iconst_0
      35: ldc_w         #269                // String Config
      38: aastore
      39: dup
      40: iconst_1
      41: ldc_w         #270                // String Bean
      44: aastore
      45: dup
      46: iconst_2
      47: ldc_w         #271                // String ConfigBase
      50: aastore
      51: putstatic     #264                // Field SUFFIXES:[Ljava/lang/String;
      54: return
}
