Compiled from "AbstractServiceConfig.java"
public abstract class org.apache.dubbo.config.AbstractServiceConfig extends org.apache.dubbo.config.AbstractInterfaceConfig {
  private static final long serialVersionUID;

  protected java.lang.String version;

  protected java.lang.String group;

  protected java.lang.Boolean deprecated;

  protected java.lang.Integer delay;

  protected java.lang.Boolean export;

  protected java.lang.Integer weight;

  protected java.lang.String document;

  protected java.lang.Boolean dynamic;

  protected java.lang.String token;

  protected java.lang.String accesslog;

  protected java.util.List<org.apache.dubbo.config.ProtocolConfig> protocols;

  protected java.lang.String protocolIds;

  private java.lang.Integer executes;

  private java.lang.Boolean register;

  private java.lang.Integer warmup;

  private java.lang.String serialization;

  private java.lang.String preferSerialization;

  private java.lang.Boolean exportAsync;

  private java.util.concurrent.Executor executor;

  private java.lang.Integer payload;

  public org.apache.dubbo.config.AbstractServiceConfig();
    Code:
       0: aload_0
       1: invokespecial #1                  // Method org/apache/dubbo/config/AbstractInterfaceConfig."<init>":()V
       4: return

  public org.apache.dubbo.config.AbstractServiceConfig(org.apache.dubbo.rpc.model.ModuleModel);
    Code:
       0: aload_0
       1: aload_1
       2: invokespecial #2                  // Method org/apache/dubbo/config/AbstractInterfaceConfig."<init>":(Lorg/apache/dubbo/rpc/model/ModuleModel;)V
       5: return

  protected void checkDefault();
    Code:
       0: aload_0
       1: invokespecial #3                  // Method org/apache/dubbo/config/AbstractInterfaceConfig.checkDefault:()V
       4: aload_0
       5: getfield      #4                  // Field deprecated:Ljava/lang/Boolean;
       8: ifnonnull     19
      11: aload_0
      12: iconst_0
      13: invokestatic  #5                  // Method java/lang/Boolean.valueOf:(Z)Ljava/lang/Boolean;
      16: putfield      #4                  // Field deprecated:Ljava/lang/Boolean;
      19: aload_0
      20: getfield      #6                  // Field dynamic:Ljava/lang/Boolean;
      23: ifnonnull     34
      26: aload_0
      27: iconst_1
      28: invokestatic  #5                  // Method java/lang/Boolean.valueOf:(Z)Ljava/lang/Boolean;
      31: putfield      #6                  // Field dynamic:Ljava/lang/Boolean;
      34: aload_0
      35: getfield      #7                  // Field preferSerialization:Ljava/lang/String;
      38: invokestatic  #8                  // Method org/apache/dubbo/common/utils/StringUtils.isBlank:(Ljava/lang/CharSequence;)Z
      41: ifeq          52
      44: aload_0
      45: aload_0
      46: getfield      #9                  // Field serialization:Ljava/lang/String;
      49: putfield      #7                  // Field preferSerialization:Ljava/lang/String;
      52: return

  public java.lang.String getVersion();
    Code:
       0: aload_0
       1: getfield      #10                 // Field version:Ljava/lang/String;
       4: areturn

  public void setVersion(java.lang.String);
    Code:
       0: aload_0
       1: aload_1
       2: putfield      #10                 // Field version:Ljava/lang/String;
       5: return

  public java.lang.String getGroup();
    Code:
       0: aload_0
       1: getfield      #11                 // Field group:Ljava/lang/String;
       4: areturn

  public void setGroup(java.lang.String);
    Code:
       0: aload_0
       1: aload_1
       2: putfield      #11                 // Field group:Ljava/lang/String;
       5: return

  public java.lang.Integer getDelay();
    Code:
       0: aload_0
       1: getfield      #12                 // Field delay:Ljava/lang/Integer;
       4: areturn

  public void setDelay(java.lang.Integer);
    Code:
       0: aload_0
       1: aload_1
       2: putfield      #12                 // Field delay:Ljava/lang/Integer;
       5: return

  public java.lang.Boolean getExport();
    Code:
       0: aload_0
       1: getfield      #13                 // Field export:Ljava/lang/Boolean;
       4: areturn

  public void setExport(java.lang.Boolean);
    Code:
       0: aload_0
       1: aload_1
       2: putfield      #13                 // Field export:Ljava/lang/Boolean;
       5: return

  public java.lang.Integer getWeight();
    Code:
       0: aload_0
       1: getfield      #14                 // Field weight:Ljava/lang/Integer;
       4: areturn

  public void setWeight(java.lang.Integer);
    Code:
       0: aload_0
       1: aload_1
       2: putfield      #14                 // Field weight:Ljava/lang/Integer;
       5: return

  public java.lang.String getDocument();
    Code:
       0: aload_0
       1: getfield      #15                 // Field document:Ljava/lang/String;
       4: areturn

  public void setDocument(java.lang.String);
    Code:
       0: aload_0
       1: aload_1
       2: putfield      #15                 // Field document:Ljava/lang/String;
       5: return

  public java.lang.String getToken();
    Code:
       0: aload_0
       1: getfield      #16                 // Field token:Ljava/lang/String;
       4: areturn

  public void setToken(java.lang.Boolean);
    Code:
       0: aload_1
       1: ifnonnull     15
       4: aload_0
       5: aconst_null
       6: checkcast     #17                 // class java/lang/String
       9: invokevirtual #18                 // Method setToken:(Ljava/lang/String;)V
      12: goto          23
      15: aload_0
      16: aload_1
      17: invokestatic  #19                 // Method java/lang/String.valueOf:(Ljava/lang/Object;)Ljava/lang/String;
      20: invokevirtual #18                 // Method setToken:(Ljava/lang/String;)V
      23: return

  public void setToken(java.lang.String);
    Code:
       0: aload_0
       1: aload_1
       2: putfield      #16                 // Field token:Ljava/lang/String;
       5: return

  public java.lang.Boolean isDeprecated();
    Code:
       0: aload_0
       1: getfield      #4                  // Field deprecated:Ljava/lang/Boolean;
       4: areturn

  public void setDeprecated(java.lang.Boolean);
    Code:
       0: aload_0
       1: aload_1
       2: putfield      #4                  // Field deprecated:Ljava/lang/Boolean;
       5: return

  public java.lang.Boolean isDynamic();
    Code:
       0: aload_0
       1: getfield      #6                  // Field dynamic:Ljava/lang/Boolean;
       4: areturn

  public void setDynamic(java.lang.Boolean);
    Code:
       0: aload_0
       1: aload_1
       2: putfield      #6                  // Field dynamic:Ljava/lang/Boolean;
       5: return

  public java.util.List<org.apache.dubbo.config.ProtocolConfig> getProtocols();
    Code:
       0: aload_0
       1: getfield      #20                 // Field protocols:Ljava/util/List;
       4: areturn

  public void setProtocols(java.util.List<? extends org.apache.dubbo.config.ProtocolConfig>);
    Code:
       0: aload_0
       1: aload_1
       2: putfield      #20                 // Field protocols:Ljava/util/List;
       5: return

  public org.apache.dubbo.config.ProtocolConfig getProtocol();
    Code:
       0: aload_0
       1: getfield      #20                 // Field protocols:Ljava/util/List;
       4: invokestatic  #21                 // Method org/apache/dubbo/common/utils/CollectionUtils.isEmpty:(Ljava/util/Collection;)Z
       7: ifeq          14
      10: aconst_null
      11: goto          27
      14: aload_0
      15: getfield      #20                 // Field protocols:Ljava/util/List;
      18: iconst_0
      19: invokeinterface #22,  2           // InterfaceMethod java/util/List.get:(I)Ljava/lang/Object;
      24: checkcast     #23                 // class org/apache/dubbo/config/ProtocolConfig
      27: areturn

  public void setProtocol(org.apache.dubbo.config.ProtocolConfig);
    Code:
       0: aload_0
       1: new           #24                 // class java/util/ArrayList
       4: dup
       5: iconst_1
       6: anewarray     #23                 // class org/apache/dubbo/config/ProtocolConfig
       9: dup
      10: iconst_0
      11: aload_1
      12: aastore
      13: invokestatic  #25                 // Method java/util/Arrays.asList:([Ljava/lang/Object;)Ljava/util/List;
      16: invokespecial #26                 // Method java/util/ArrayList."<init>":(Ljava/util/Collection;)V
      19: invokevirtual #27                 // Method setProtocols:(Ljava/util/List;)V
      22: return

  public java.lang.String getProtocolIds();
    Code:
       0: aload_0
       1: getfield      #28                 // Field protocolIds:Ljava/lang/String;
       4: areturn

  public void setProtocolIds(java.lang.String);
    Code:
       0: aload_0
       1: aload_1
       2: putfield      #28                 // Field protocolIds:Ljava/lang/String;
       5: return

  public java.lang.String getAccesslog();
    Code:
       0: aload_0
       1: getfield      #29                 // Field accesslog:Ljava/lang/String;
       4: areturn

  public void setAccesslog(java.lang.Boolean);
    Code:
       0: aload_1
       1: ifnonnull     15
       4: aload_0
       5: aconst_null
       6: checkcast     #17                 // class java/lang/String
       9: invokevirtual #30                 // Method setAccesslog:(Ljava/lang/String;)V
      12: goto          23
      15: aload_0
      16: aload_1
      17: invokestatic  #19                 // Method java/lang/String.valueOf:(Ljava/lang/Object;)Ljava/lang/String;
      20: invokevirtual #30                 // Method setAccesslog:(Ljava/lang/String;)V
      23: return

  public void setAccesslog(java.lang.String);
    Code:
       0: aload_0
       1: aload_1
       2: putfield      #29                 // Field accesslog:Ljava/lang/String;
       5: return

  public java.lang.Integer getExecutes();
    Code:
       0: aload_0
       1: getfield      #31                 // Field executes:Ljava/lang/Integer;
       4: areturn

  public void setExecutes(java.lang.Integer);
    Code:
       0: aload_0
       1: aload_1
       2: putfield      #31                 // Field executes:Ljava/lang/Integer;
       5: return

  public java.lang.String getFilter();
    Code:
       0: aload_0
       1: invokespecial #32                 // Method org/apache/dubbo/config/AbstractInterfaceConfig.getFilter:()Ljava/lang/String;
       4: areturn

  public java.lang.String getListener();
    Code:
       0: aload_0
       1: getfield      #33                 // Field listener:Ljava/lang/String;
       4: areturn

  public void setListener(java.lang.String);
    Code:
       0: aload_0
       1: aload_1
       2: putfield      #33                 // Field listener:Ljava/lang/String;
       5: return

  public java.lang.Boolean isRegister();
    Code:
       0: aload_0
       1: getfield      #34                 // Field register:Ljava/lang/Boolean;
       4: areturn

  public void setRegister(java.lang.Boolean);
    Code:
       0: aload_0
       1: aload_1
       2: putfield      #34                 // Field register:Ljava/lang/Boolean;
       5: return

  public java.lang.Integer getWarmup();
    Code:
       0: aload_0
       1: getfield      #35                 // Field warmup:Ljava/lang/Integer;
       4: areturn

  public void setWarmup(java.lang.Integer);
    Code:
       0: aload_0
       1: aload_1
       2: putfield      #35                 // Field warmup:Ljava/lang/Integer;
       5: return

  public java.lang.String getSerialization();
    Code:
       0: aload_0
       1: getfield      #9                  // Field serialization:Ljava/lang/String;
       4: areturn

  public void setSerialization(java.lang.String);
    Code:
       0: aload_0
       1: aload_1
       2: putfield      #9                  // Field serialization:Ljava/lang/String;
       5: return

  public java.lang.String getPreferSerialization();
    Code:
       0: aload_0
       1: getfield      #7                  // Field preferSerialization:Ljava/lang/String;
       4: areturn

  public void setPreferSerialization(java.lang.String);
    Code:
       0: aload_0
       1: aload_1
       2: putfield      #7                  // Field preferSerialization:Ljava/lang/String;
       5: return

  public java.lang.Boolean getExportAsync();
    Code:
       0: aload_0
       1: getfield      #36                 // Field exportAsync:Ljava/lang/Boolean;
       4: areturn

  public void setExportAsync(java.lang.Boolean);
    Code:
       0: aload_0
       1: aload_1
       2: putfield      #36                 // Field exportAsync:Ljava/lang/Boolean;
       5: return

  public void setExecutor(java.util.concurrent.Executor);
    Code:
       0: aload_0
       1: aload_1
       2: putfield      #37                 // Field executor:Ljava/util/concurrent/Executor;
       5: return

  public java.util.concurrent.Executor getExecutor();
    Code:
       0: aload_0
       1: getfield      #37                 // Field executor:Ljava/util/concurrent/Executor;
       4: areturn

  public java.lang.Integer getPayload();
    Code:
       0: aload_0
       1: getfield      #38                 // Field payload:Ljava/lang/Integer;
       4: areturn

  public void setPayload(java.lang.Integer);
    Code:
       0: aload_0
       1: aload_1
       2: putfield      #38                 // Field payload:Ljava/lang/Integer;
       5: return
}
