Compiled from "AbstractReferenceConfig.java"
public abstract class org.apache.dubbo.config.AbstractReferenceConfig extends org.apache.dubbo.config.AbstractInterfaceConfig {
  private static final long serialVersionUID;

  protected java.lang.Boolean check;

  protected java.lang.Boolean init;

  protected java.lang.String generic;

  protected java.lang.Boolean injvm;

  protected java.lang.Boolean lazy;

  protected java.lang.String reconnect;

  protected java.lang.Boolean sticky;

  protected java.lang.Boolean stubevent;

  protected java.lang.String providedBy;

  protected java.lang.Integer providerPort;

  protected java.lang.String providerNamespace;

  protected java.lang.String router;

  private java.lang.Boolean referAsync;

  protected java.lang.String client;

  protected java.lang.String protocol;

  public org.apache.dubbo.config.AbstractReferenceConfig();
    Code:
       0: aload_0
       1: invokespecial #1                  // Method org/apache/dubbo/config/AbstractInterfaceConfig."<init>":()V
       4: return

  public org.apache.dubbo.config.AbstractReferenceConfig(org.apache.dubbo.rpc.model.ModuleModel);
    Code:
       0: aload_0
       1: aload_1
       2: invokespecial #2                  // Method org/apache/dubbo/config/AbstractInterfaceConfig."<init>":(Lorg/apache/dubbo/rpc/model/ModuleModel;)V
       5: return

  protected void checkDefault();
    Code:
       0: aload_0
       1: invokespecial #3                  // Method org/apache/dubbo/config/AbstractInterfaceConfig.checkDefault:()V
       4: aload_0
       5: getfield      #4                  // Field sticky:Ljava/lang/Boolean;
       8: ifnonnull     19
      11: aload_0
      12: iconst_0
      13: invokestatic  #5                  // Method java/lang/Boolean.valueOf:(Z)Ljava/lang/Boolean;
      16: putfield      #4                  // Field sticky:Ljava/lang/Boolean;
      19: return

  public java.lang.Boolean isCheck();
    Code:
       0: aload_0
       1: getfield      #6                  // Field check:Ljava/lang/Boolean;
       4: areturn

  public void setCheck(java.lang.Boolean);
    Code:
       0: aload_0
       1: aload_1
       2: putfield      #6                  // Field check:Ljava/lang/Boolean;
       5: return

  public java.lang.Boolean isInit();
    Code:
       0: aload_0
       1: getfield      #7                  // Field init:Ljava/lang/Boolean;
       4: areturn

  public void setInit(java.lang.Boolean);
    Code:
       0: aload_0
       1: aload_1
       2: putfield      #7                  // Field init:Ljava/lang/Boolean;
       5: return

  public java.lang.Boolean isGeneric();
    Code:
       0: aload_0
       1: getfield      #8                  // Field generic:Ljava/lang/String;
       4: ifnull        20
       7: aload_0
       8: getfield      #8                  // Field generic:Ljava/lang/String;
      11: invokestatic  #9                  // Method org/apache/dubbo/rpc/support/ProtocolUtils.isGeneric:(Ljava/lang/String;)Z
      14: invokestatic  #5                  // Method java/lang/Boolean.valueOf:(Z)Ljava/lang/Boolean;
      17: goto          21
      20: aconst_null
      21: areturn

  public void setGeneric(java.lang.Boolean);
    Code:
       0: aload_1
       1: ifnull        12
       4: aload_0
       5: aload_1
       6: invokevirtual #10                 // Method java/lang/Boolean.toString:()Ljava/lang/String;
       9: putfield      #8                  // Field generic:Ljava/lang/String;
      12: return

  public java.lang.String getGeneric();
    Code:
       0: aload_0
       1: getfield      #8                  // Field generic:Ljava/lang/String;
       4: areturn

  public void setGeneric(java.lang.String);
    Code:
       0: aload_1
       1: invokestatic  #11                 // Method org/apache/dubbo/common/utils/StringUtils.isEmpty:(Ljava/lang/String;)Z
       4: ifeq          8
       7: return
       8: aload_1
       9: invokestatic  #12                 // Method org/apache/dubbo/rpc/support/ProtocolUtils.isValidGenericValue:(Ljava/lang/String;)Z
      12: ifeq          23
      15: aload_0
      16: aload_1
      17: putfield      #8                  // Field generic:Ljava/lang/String;
      20: goto          50
      23: new           #13                 // class java/lang/IllegalArgumentException
      26: dup
      27: new           #14                 // class java/lang/StringBuilder
      30: dup
      31: invokespecial #15                 // Method java/lang/StringBuilder."<init>":()V
      34: ldc           #16                 // String Unsupported generic type
      36: invokevirtual #17                 // Method java/lang/StringBuilder.append:(Ljava/lang/String;)Ljava/lang/StringBuilder;
      39: aload_1
      40: invokevirtual #17                 // Method java/lang/StringBuilder.append:(Ljava/lang/String;)Ljava/lang/StringBuilder;
      43: invokevirtual #18                 // Method java/lang/StringBuilder.toString:()Ljava/lang/String;
      46: invokespecial #19                 // Method java/lang/IllegalArgumentException."<init>":(Ljava/lang/String;)V
      49: athrow
      50: return

  protected boolean isNeedCheckMethod();
    Code:
       0: aload_0
       1: invokevirtual #20                 // Method getGeneric:()Ljava/lang/String;
       4: invokestatic  #11                 // Method org/apache/dubbo/common/utils/StringUtils.isEmpty:(Ljava/lang/String;)Z
       7: ireturn

  public java.lang.Boolean isInjvm();
    Code:
       0: aload_0
       1: getfield      #21                 // Field injvm:Ljava/lang/Boolean;
       4: areturn

  public void setInjvm(java.lang.Boolean);
    Code:
       0: aload_0
       1: aload_1
       2: putfield      #21                 // Field injvm:Ljava/lang/Boolean;
       5: return

  public java.lang.String getFilter();
    Code:
       0: aload_0
       1: invokespecial #22                 // Method org/apache/dubbo/config/AbstractInterfaceConfig.getFilter:()Ljava/lang/String;
       4: areturn

  public java.lang.String getListener();
    Code:
       0: aload_0
       1: invokespecial #23                 // Method org/apache/dubbo/config/AbstractInterfaceConfig.getListener:()Ljava/lang/String;
       4: areturn

  public void setListener(java.lang.String);
    Code:
       0: aload_0
       1: aload_1
       2: invokespecial #24                 // Method org/apache/dubbo/config/AbstractInterfaceConfig.setListener:(Ljava/lang/String;)V
       5: return

  public java.lang.Boolean getLazy();
    Code:
       0: aload_0
       1: getfield      #25                 // Field lazy:Ljava/lang/Boolean;
       4: areturn

  public void setLazy(java.lang.Boolean);
    Code:
       0: aload_0
       1: aload_1
       2: putfield      #25                 // Field lazy:Ljava/lang/Boolean;
       5: return

  public void setOnconnect(java.lang.String);
    Code:
       0: aload_1
       1: ifnull        19
       4: aload_1
       5: invokevirtual #26                 // Method java/lang/String.length:()I
       8: ifle          19
      11: aload_0
      12: iconst_1
      13: invokestatic  #5                  // Method java/lang/Boolean.valueOf:(Z)Ljava/lang/Boolean;
      16: putfield      #27                 // Field stubevent:Ljava/lang/Boolean;
      19: aload_0
      20: aload_1
      21: invokespecial #28                 // Method org/apache/dubbo/config/AbstractInterfaceConfig.setOnconnect:(Ljava/lang/String;)V
      24: return

  public void setOndisconnect(java.lang.String);
    Code:
       0: aload_1
       1: ifnull        19
       4: aload_1
       5: invokevirtual #26                 // Method java/lang/String.length:()I
       8: ifle          19
      11: aload_0
      12: iconst_1
      13: invokestatic  #5                  // Method java/lang/Boolean.valueOf:(Z)Ljava/lang/Boolean;
      16: putfield      #27                 // Field stubevent:Ljava/lang/Boolean;
      19: aload_0
      20: aload_1
      21: invokespecial #29                 // Method org/apache/dubbo/config/AbstractInterfaceConfig.setOndisconnect:(Ljava/lang/String;)V
      24: return

  public java.lang.Boolean getStubevent();
    Code:
       0: aload_0
       1: getfield      #27                 // Field stubevent:Ljava/lang/Boolean;
       4: areturn

  public java.lang.String getReconnect();
    Code:
       0: aload_0
       1: getfield      #30                 // Field reconnect:Ljava/lang/String;
       4: areturn

  public void setReconnect(java.lang.String);
    Code:
       0: aload_0
       1: aload_1
       2: putfield      #30                 // Field reconnect:Ljava/lang/String;
       5: return

  public java.lang.Boolean getSticky();
    Code:
       0: aload_0
       1: getfield      #4                  // Field sticky:Ljava/lang/Boolean;
       4: areturn

  public void setSticky(java.lang.Boolean);
    Code:
       0: aload_0
       1: aload_1
       2: putfield      #4                  // Field sticky:Ljava/lang/Boolean;
       5: return

  public java.lang.String getProvidedBy();
    Code:
       0: aload_0
       1: getfield      #31                 // Field providedBy:Ljava/lang/String;
       4: areturn

  public void setProvidedBy(java.lang.String);
    Code:
       0: aload_0
       1: aload_1
       2: putfield      #31                 // Field providedBy:Ljava/lang/String;
       5: return

  public java.lang.Integer getProviderPort();
    Code:
       0: aload_0
       1: getfield      #32                 // Field providerPort:Ljava/lang/Integer;
       4: areturn

  public void setProviderPort(java.lang.Integer);
    Code:
       0: aload_0
       1: aload_1
       2: putfield      #32                 // Field providerPort:Ljava/lang/Integer;
       5: return

  public java.lang.String getProviderNamespace();
    Code:
       0: aload_0
       1: getfield      #33                 // Field providerNamespace:Ljava/lang/String;
       4: areturn

  public void setProviderNamespace(java.lang.String);
    Code:
       0: aload_0
       1: aload_1
       2: putfield      #33                 // Field providerNamespace:Ljava/lang/String;
       5: return

  public java.lang.String getRouter();
    Code:
       0: aload_0
       1: getfield      #34                 // Field router:Ljava/lang/String;
       4: areturn

  public void setRouter(java.lang.String);
    Code:
       0: aload_0
       1: aload_1
       2: putfield      #34                 // Field router:Ljava/lang/String;
       5: return

  public java.lang.Boolean getReferAsync();
    Code:
       0: aload_0
       1: getfield      #35                 // Field referAsync:Ljava/lang/Boolean;
       4: areturn

  public void setReferAsync(java.lang.Boolean);
    Code:
       0: aload_0
       1: aload_1
       2: putfield      #35                 // Field referAsync:Ljava/lang/Boolean;
       5: return

  public java.lang.String getClient();
    Code:
       0: aload_0
       1: getfield      #36                 // Field client:Ljava/lang/String;
       4: areturn

  public void setClient(java.lang.String);
    Code:
       0: aload_0
       1: aload_1
       2: putfield      #36                 // Field client:Ljava/lang/String;
       5: return

  public java.lang.String getProtocol();
    Code:
       0: aload_0
       1: getfield      #37                 // Field protocol:Ljava/lang/String;
       4: areturn

  public void setProtocol(java.lang.String);
    Code:
       0: aload_0
       1: aload_1
       2: putfield      #37                 // Field protocol:Ljava/lang/String;
       5: return
}
