Compiled from "ArgumentConfig.java"
public class org.apache.dubbo.config.ArgumentConfig implements java.io.Serializable {
  private static final long serialVersionUID;

  private java.lang.Integer index;

  private java.lang.String type;

  private java.lang.Boolean callback;

  public org.apache.dubbo.config.ArgumentConfig();
    Code:
       0: aload_0
       1: invokespecial #1                  // Method java/lang/Object."<init>":()V
       4: aload_0
       5: iconst_m1
       6: invokestatic  #2                  // Method java/lang/Integer.valueOf:(I)Ljava/lang/Integer;
       9: putfield      #3                  // Field index:Ljava/lang/Integer;
      12: return

  public org.apache.dubbo.config.ArgumentConfig(org.apache.dubbo.config.annotation.Argument);
    Code:
       0: aload_0
       1: invokespecial #1                  // Method java/lang/Object."<init>":()V
       4: aload_0
       5: iconst_m1
       6: invokestatic  #2                  // Method java/lang/Integer.valueOf:(I)Ljava/lang/Integer;
       9: putfield      #3                  // Field index:Ljava/lang/Integer;
      12: aload_0
      13: aload_1
      14: invokeinterface #4,  1            // InterfaceMethod org/apache/dubbo/config/annotation/Argument.index:()I
      19: invokestatic  #2                  // Method java/lang/Integer.valueOf:(I)Ljava/lang/Integer;
      22: putfield      #3                  // Field index:Ljava/lang/Integer;
      25: aload_0
      26: aload_1
      27: invokeinterface #5,  1            // InterfaceMethod org/apache/dubbo/config/annotation/Argument.type:()Ljava/lang/String;
      32: putfield      #6                  // Field type:Ljava/lang/String;
      35: aload_0
      36: aload_1
      37: invokeinterface #7,  1            // InterfaceMethod org/apache/dubbo/config/annotation/Argument.callback:()Z
      42: invokestatic  #8                  // Method java/lang/Boolean.valueOf:(Z)Ljava/lang/Boolean;
      45: putfield      #9                  // Field callback:Ljava/lang/Boolean;
      48: return

  public java.lang.Integer getIndex();
    Code:
       0: aload_0
       1: getfield      #3                  // Field index:Ljava/lang/Integer;
       4: areturn

  public void setIndex(java.lang.Integer);
    Code:
       0: aload_0
       1: aload_1
       2: putfield      #3                  // Field index:Ljava/lang/Integer;
       5: return

  public java.lang.String getType();
    Code:
       0: aload_0
       1: getfield      #6                  // Field type:Ljava/lang/String;
       4: areturn

  public void setType(java.lang.String);
    Code:
       0: aload_0
       1: aload_1
       2: putfield      #6                  // Field type:Ljava/lang/String;
       5: return

  public void setCallback(java.lang.Boolean);
    Code:
       0: aload_0
       1: aload_1
       2: putfield      #9                  // Field callback:Ljava/lang/Boolean;
       5: return

  public java.lang.Boolean isCallback();
    Code:
       0: aload_0
       1: getfield      #9                  // Field callback:Ljava/lang/Boolean;
       4: areturn
}
