Compiled from "ConfigCenterConfig.java"
public class org.apache.dubbo.config.ConfigCenterConfig extends org.apache.dubbo.config.AbstractConfig {
  private final java.util.concurrent.atomic.AtomicBoolean initialized;

  private java.lang.String protocol;

  private java.lang.String address;

  private java.lang.Integer port;

  private java.lang.String cluster;

  private java.lang.String namespace;

  private java.lang.String group;

  private java.lang.String username;

  private java.lang.String password;

  private java.lang.Long timeout;

  private java.lang.Boolean highestPriority;

  private java.lang.Boolean check;

  private java.lang.String configFile;

  private java.lang.String appConfigFile;

  private java.util.Map<java.lang.String, java.lang.String> parameters;

  private java.util.Map<java.lang.String, java.lang.String> externalConfiguration;

  private java.util.Map<java.lang.String, java.lang.String> appExternalConfiguration;

  public org.apache.dubbo.config.ConfigCenterConfig();
    Code:
       0: aload_0
       1: invokespecial #4                  // Method org/apache/dubbo/config/AbstractConfig."<init>":()V
       4: aload_0
       5: new           #5                  // class java/util/concurrent/atomic/AtomicBoolean
       8: dup
       9: iconst_0
      10: invokespecial #6                  // Method java/util/concurrent/atomic/AtomicBoolean."<init>":(Z)V
      13: putfield      #7                  // Field initialized:Ljava/util/concurrent/atomic/AtomicBoolean;
      16: return

  public org.apache.dubbo.config.ConfigCenterConfig(org.apache.dubbo.rpc.model.ApplicationModel);
    Code:
       0: aload_0
       1: aload_1
       2: invokespecial #8                  // Method org/apache/dubbo/config/AbstractConfig."<init>":(Lorg/apache/dubbo/rpc/model/ScopeModel;)V
       5: aload_0
       6: new           #5                  // class java/util/concurrent/atomic/AtomicBoolean
       9: dup
      10: iconst_0
      11: invokespecial #6                  // Method java/util/concurrent/atomic/AtomicBoolean."<init>":(Z)V
      14: putfield      #7                  // Field initialized:Ljava/util/concurrent/atomic/AtomicBoolean;
      17: return

  protected void checkDefault();
    Code:
       0: aload_0
       1: invokespecial #9                  // Method org/apache/dubbo/config/AbstractConfig.checkDefault:()V
       4: aload_0
       5: getfield      #10                 // Field namespace:Ljava/lang/String;
       8: ifnonnull     17
      11: aload_0
      12: ldc           #11                 // String dubbo
      14: putfield      #10                 // Field namespace:Ljava/lang/String;
      17: aload_0
      18: getfield      #12                 // Field group:Ljava/lang/String;
      21: ifnonnull     30
      24: aload_0
      25: ldc           #11                 // String dubbo
      27: putfield      #12                 // Field group:Ljava/lang/String;
      30: aload_0
      31: getfield      #13                 // Field timeout:Ljava/lang/Long;
      34: ifnonnull     47
      37: aload_0
      38: ldc2_w        #14                 // long 30000l
      41: invokestatic  #16                 // Method java/lang/Long.valueOf:(J)Ljava/lang/Long;
      44: putfield      #13                 // Field timeout:Ljava/lang/Long;
      47: aload_0
      48: getfield      #17                 // Field check:Ljava/lang/Boolean;
      51: ifnonnull     62
      54: aload_0
      55: iconst_1
      56: invokestatic  #18                 // Method java/lang/Boolean.valueOf:(Z)Ljava/lang/Boolean;
      59: putfield      #17                 // Field check:Ljava/lang/Boolean;
      62: aload_0
      63: getfield      #19                 // Field configFile:Ljava/lang/String;
      66: ifnonnull     75
      69: aload_0
      70: ldc           #20                 // String dubbo.properties
      72: putfield      #19                 // Field configFile:Ljava/lang/String;
      75: return

  public org.apache.dubbo.common.URL toUrl();
    Code:
       0: new           #21                 // class java/util/HashMap
       3: dup
       4: invokespecial #22                 // Method java/util/HashMap."<init>":()V
       7: astore_1
       8: aload_1
       9: aload_0
      10: invokestatic  #23                 // Method appendParameters:(Ljava/util/Map;Ljava/lang/Object;)V
      13: aload_0
      14: getfield      #24                 // Field address:Ljava/lang/String;
      17: invokestatic  #25                 // Method org/apache/dubbo/common/utils/StringUtils.isEmpty:(Ljava/lang/String;)Z
      20: ifeq          29
      23: aload_0
      24: ldc           #26                 // String 0.0.0.0
      26: putfield      #24                 // Field address:Ljava/lang/String;
      29: aload_1
      30: ldc           #27                 // String path
      32: ldc           #28                 // class org/apache/dubbo/config/ConfigCenterConfig
      34: invokevirtual #29                 // Method java/lang/Class.getName:()Ljava/lang/String;
      37: invokeinterface #30,  3           // InterfaceMethod java/util/Map.put:(Ljava/lang/Object;Ljava/lang/Object;)Ljava/lang/Object;
      42: pop
      43: aload_1
      44: ldc           #31                 // String protocol
      46: invokeinterface #32,  2           // InterfaceMethod java/util/Map.get:(Ljava/lang/Object;)Ljava/lang/Object;
      51: checkcast     #33                 // class java/lang/String
      54: invokestatic  #25                 // Method org/apache/dubbo/common/utils/StringUtils.isEmpty:(Ljava/lang/String;)Z
      57: ifeq          71
      60: aload_1
      61: ldc           #31                 // String protocol
      63: ldc           #34                 // String zookeeper
      65: invokeinterface #30,  3           // InterfaceMethod java/util/Map.put:(Ljava/lang/Object;Ljava/lang/Object;)Ljava/lang/Object;
      70: pop
      71: aload_0
      72: getfield      #24                 // Field address:Ljava/lang/String;
      75: aload_1
      76: invokestatic  #35                 // Method org/apache/dubbo/common/utils/UrlUtils.parseURL:(Ljava/lang/String;Ljava/util/Map;)Lorg/apache/dubbo/common/URL;
      79: aload_0
      80: invokevirtual #36                 // Method getScopeModel:()Lorg/apache/dubbo/rpc/model/ScopeModel;
      83: invokevirtual #37                 // Method org/apache/dubbo/common/URL.setScopeModel:(Lorg/apache/dubbo/rpc/model/ScopeModel;)Lorg/apache/dubbo/common/URL;
      86: areturn

  public boolean checkOrUpdateInitialized(boolean);
    Code:
       0: aload_0
       1: getfield      #7                  // Field initialized:Ljava/util/concurrent/atomic/AtomicBoolean;
       4: iconst_0
       5: iload_1
       6: invokevirtual #38                 // Method java/util/concurrent/atomic/AtomicBoolean.compareAndSet:(ZZ)Z
       9: ireturn

  public void setInitialized(boolean);
    Code:
       0: aload_0
       1: getfield      #7                  // Field initialized:Ljava/util/concurrent/atomic/AtomicBoolean;
       4: iload_1
       5: invokevirtual #39                 // Method java/util/concurrent/atomic/AtomicBoolean.set:(Z)V
       8: return

  public java.util.Map<java.lang.String, java.lang.String> getExternalConfiguration();
    Code:
       0: aload_0
       1: getfield      #40                 // Field externalConfiguration:Ljava/util/Map;
       4: areturn

  public java.util.Map<java.lang.String, java.lang.String> getAppExternalConfiguration();
    Code:
       0: aload_0
       1: getfield      #41                 // Field appExternalConfiguration:Ljava/util/Map;
       4: areturn

  public void setExternalConfig(java.util.Map<java.lang.String, java.lang.String>);
    Code:
       0: aload_0
       1: aload_1
       2: putfield      #40                 // Field externalConfiguration:Ljava/util/Map;
       5: return

  public void setAppExternalConfig(java.util.Map<java.lang.String, java.lang.String>);
    Code:
       0: aload_0
       1: aload_1
       2: putfield      #41                 // Field appExternalConfiguration:Ljava/util/Map;
       5: return

  public java.lang.String getProtocol();
    Code:
       0: aload_0
       1: getfield      #42                 // Field protocol:Ljava/lang/String;
       4: areturn

  public void setProtocol(java.lang.String);
    Code:
       0: aload_0
       1: aload_1
       2: putfield      #42                 // Field protocol:Ljava/lang/String;
       5: return

  public java.lang.String getAddress();
    Code:
       0: aload_0
       1: getfield      #24                 // Field address:Ljava/lang/String;
       4: areturn

  public void setAddress(java.lang.String);
    Code:
       0: aload_0
       1: aload_1
       2: putfield      #24                 // Field address:Ljava/lang/String;
       5: aload_1
       6: ifnull        123
       9: aload_1
      10: invokestatic  #43                 // Method org/apache/dubbo/common/URL.valueOf:(Ljava/lang/String;)Lorg/apache/dubbo/common/URL;
      13: astore_2
      14: aload_0
      15: invokedynamic #44,  0             // InvokeDynamic #0:get:(Lorg/apache/dubbo/config/ConfigCenterConfig;)Ljava/util/function/Supplier;
      20: aload_0
      21: invokedynamic #45,  0             // InvokeDynamic #1:accept:(Lorg/apache/dubbo/config/ConfigCenterConfig;)Ljava/util/function/Consumer;
      26: aload_2
      27: invokevirtual #46                 // Method org/apache/dubbo/common/URL.getUsername:()Ljava/lang/String;
      30: invokestatic  #47                 // Method org/apache/dubbo/common/utils/PojoUtils.updatePropertyIfAbsent:(Ljava/util/function/Supplier;Ljava/util/function/Consumer;Ljava/lang/Object;)V
      33: aload_0
      34: invokedynamic #48,  0             // InvokeDynamic #2:get:(Lorg/apache/dubbo/config/ConfigCenterConfig;)Ljava/util/function/Supplier;
      39: aload_0
      40: invokedynamic #49,  0             // InvokeDynamic #3:accept:(Lorg/apache/dubbo/config/ConfigCenterConfig;)Ljava/util/function/Consumer;
      45: aload_2
      46: invokevirtual #50                 // Method org/apache/dubbo/common/URL.getPassword:()Ljava/lang/String;
      49: invokestatic  #47                 // Method org/apache/dubbo/common/utils/PojoUtils.updatePropertyIfAbsent:(Ljava/util/function/Supplier;Ljava/util/function/Consumer;Ljava/lang/Object;)V
      52: aload_0
      53: invokedynamic #51,  0             // InvokeDynamic #4:get:(Lorg/apache/dubbo/config/ConfigCenterConfig;)Ljava/util/function/Supplier;
      58: aload_0
      59: invokedynamic #52,  0             // InvokeDynamic #5:accept:(Lorg/apache/dubbo/config/ConfigCenterConfig;)Ljava/util/function/Consumer;
      64: aload_2
      65: invokevirtual #53                 // Method org/apache/dubbo/common/URL.getProtocol:()Ljava/lang/String;
      68: invokestatic  #47                 // Method org/apache/dubbo/common/utils/PojoUtils.updatePropertyIfAbsent:(Ljava/util/function/Supplier;Ljava/util/function/Consumer;Ljava/lang/Object;)V
      71: aload_0
      72: invokedynamic #54,  0             // InvokeDynamic #6:get:(Lorg/apache/dubbo/config/ConfigCenterConfig;)Ljava/util/function/Supplier;
      77: aload_0
      78: invokedynamic #55,  0             // InvokeDynamic #7:accept:(Lorg/apache/dubbo/config/ConfigCenterConfig;)Ljava/util/function/Consumer;
      83: aload_2
      84: invokevirtual #56                 // Method org/apache/dubbo/common/URL.getPort:()I
      87: invokestatic  #57                 // Method java/lang/Integer.valueOf:(I)Ljava/lang/Integer;
      90: invokestatic  #47                 // Method org/apache/dubbo/common/utils/PojoUtils.updatePropertyIfAbsent:(Ljava/util/function/Supplier;Ljava/util/function/Consumer;Ljava/lang/Object;)V
      93: aload_2
      94: invokevirtual #58                 // Method org/apache/dubbo/common/URL.getParameters:()Ljava/util/Map;
      97: astore_3
      98: aload_3
      99: invokestatic  #59                 // Method org/apache/dubbo/common/utils/CollectionUtils.isNotEmptyMap:(Ljava/util/Map;)Z
     102: ifeq          114
     105: aload_3
     106: ldc           #60                 // String backup
     108: invokeinterface #61,  2           // InterfaceMethod java/util/Map.remove:(Ljava/lang/Object;)Ljava/lang/Object;
     113: pop
     114: aload_0
     115: aload_3
     116: invokevirtual #62                 // Method updateParameters:(Ljava/util/Map;)V
     119: goto          123
     122: astore_2
     123: return
    Exception table:
       from    to  target type
           9   119   122   Class java/lang/Exception

  public java.lang.Integer getPort();
    Code:
       0: aload_0
       1: getfield      #64                 // Field port:Ljava/lang/Integer;
       4: areturn

  public void setPort(java.lang.Integer);
    Code:
       0: aload_0
       1: aload_1
       2: putfield      #64                 // Field port:Ljava/lang/Integer;
       5: return

  public java.lang.String getCluster();
    Code:
       0: aload_0
       1: getfield      #65                 // Field cluster:Ljava/lang/String;
       4: areturn

  public void setCluster(java.lang.String);
    Code:
       0: aload_0
       1: aload_1
       2: putfield      #65                 // Field cluster:Ljava/lang/String;
       5: return

  public java.lang.String getNamespace();
    Code:
       0: aload_0
       1: getfield      #10                 // Field namespace:Ljava/lang/String;
       4: areturn

  public void setNamespace(java.lang.String);
    Code:
       0: aload_0
       1: aload_1
       2: putfield      #10                 // Field namespace:Ljava/lang/String;
       5: return

  public java.lang.String getGroup();
    Code:
       0: aload_0
       1: getfield      #12                 // Field group:Ljava/lang/String;
       4: areturn

  public void setGroup(java.lang.String);
    Code:
       0: aload_0
       1: aload_1
       2: putfield      #12                 // Field group:Ljava/lang/String;
       5: return

  public java.lang.Boolean isCheck();
    Code:
       0: aload_0
       1: getfield      #17                 // Field check:Ljava/lang/Boolean;
       4: areturn

  public void setCheck(java.lang.Boolean);
    Code:
       0: aload_0
       1: aload_1
       2: putfield      #17                 // Field check:Ljava/lang/Boolean;
       5: return

  public java.lang.Boolean isHighestPriority();
    Code:
       0: aload_0
       1: getfield      #66                 // Field highestPriority:Ljava/lang/Boolean;
       4: areturn

  public void setHighestPriority(java.lang.Boolean);
    Code:
       0: aload_0
       1: aload_1
       2: putfield      #66                 // Field highestPriority:Ljava/lang/Boolean;
       5: return

  public java.lang.String getUsername();
    Code:
       0: aload_0
       1: getfield      #67                 // Field username:Ljava/lang/String;
       4: areturn

  public void setUsername(java.lang.String);
    Code:
       0: aload_0
       1: aload_1
       2: putfield      #67                 // Field username:Ljava/lang/String;
       5: return

  public java.lang.String getPassword();
    Code:
       0: aload_0
       1: getfield      #68                 // Field password:Ljava/lang/String;
       4: areturn

  public void setPassword(java.lang.String);
    Code:
       0: aload_0
       1: aload_1
       2: putfield      #68                 // Field password:Ljava/lang/String;
       5: return

  public java.lang.Long getTimeout();
    Code:
       0: aload_0
       1: getfield      #13                 // Field timeout:Ljava/lang/Long;
       4: areturn

  public void setTimeout(java.lang.Long);
    Code:
       0: aload_0
       1: aload_1
       2: putfield      #13                 // Field timeout:Ljava/lang/Long;
       5: return

  public java.lang.String getConfigFile();
    Code:
       0: aload_0
       1: getfield      #19                 // Field configFile:Ljava/lang/String;
       4: areturn

  public void setConfigFile(java.lang.String);
    Code:
       0: aload_0
       1: aload_1
       2: putfield      #19                 // Field configFile:Ljava/lang/String;
       5: return

  public java.lang.String getAppConfigFile();
    Code:
       0: aload_0
       1: getfield      #69                 // Field appConfigFile:Ljava/lang/String;
       4: areturn

  public void setAppConfigFile(java.lang.String);
    Code:
       0: aload_0
       1: aload_1
       2: putfield      #69                 // Field appConfigFile:Ljava/lang/String;
       5: return

  public java.util.Map<java.lang.String, java.lang.String> getParameters();
    Code:
       0: aload_0
       1: getfield      #70                 // Field parameters:Ljava/util/Map;
       4: areturn

  public void setParameters(java.util.Map<java.lang.String, java.lang.String>);
    Code:
       0: aload_0
       1: aload_1
       2: putfield      #70                 // Field parameters:Ljava/util/Map;
       5: return

  public boolean isValid();
    Code:
       0: aload_0
       1: getfield      #24                 // Field address:Ljava/lang/String;
       4: invokestatic  #25                 // Method org/apache/dubbo/common/utils/StringUtils.isEmpty:(Ljava/lang/String;)Z
       7: ifeq          12
      10: iconst_0
      11: ireturn
      12: aload_0
      13: getfield      #24                 // Field address:Ljava/lang/String;
      16: ldc           #71                 // String ://
      18: invokevirtual #72                 // Method java/lang/String.contains:(Ljava/lang/CharSequence;)Z
      21: ifne          34
      24: aload_0
      25: getfield      #42                 // Field protocol:Ljava/lang/String;
      28: invokestatic  #73                 // Method org/apache/dubbo/common/utils/StringUtils.isNotEmpty:(Ljava/lang/String;)Z
      31: ifeq          38
      34: iconst_1
      35: goto          39
      38: iconst_0
      39: ireturn

  public void updateParameters(java.util.Map<java.lang.String, java.lang.String>);
    Code:
       0: aload_1
       1: invokestatic  #74                 // Method org/apache/dubbo/common/utils/CollectionUtils.isEmptyMap:(Ljava/util/Map;)Z
       4: ifeq          8
       7: return
       8: aload_0
       9: getfield      #70                 // Field parameters:Ljava/util/Map;
      12: ifnonnull     23
      15: aload_0
      16: aload_1
      17: putfield      #70                 // Field parameters:Ljava/util/Map;
      20: goto          33
      23: aload_0
      24: getfield      #70                 // Field parameters:Ljava/util/Map;
      27: aload_1
      28: invokeinterface #75,  2           // InterfaceMethod java/util/Map.putAll:(Ljava/util/Map;)V
      33: return
}
