Compiled from "ConfigScopeModelInitializer.java"
public class org.apache.dubbo.config.ConfigScopeModelInitializer implements org.apache.dubbo.rpc.model.ScopeModelInitializer {
  public org.apache.dubbo.config.ConfigScopeModelInitializer();
    Code:
       0: aload_0
       1: invokespecial #1                  // Method java/lang/Object."<init>":()V
       4: return

  public void initializeFrameworkModel(org.apache.dubbo.rpc.model.FrameworkModel);
    Code:
       0: aload_1
       1: new           #2                  // class org/apache/dubbo/config/deploy/FrameworkModelCleaner
       4: dup
       5: invokespecial #3                  // Method org/apache/dubbo/config/deploy/FrameworkModelCleaner."<init>":()V
       8: invokevirtual #4                  // Method org/apache/dubbo/rpc/model/FrameworkModel.addDestroyListener:(Lorg/apache/dubbo/rpc/model/ScopeModelDestroyListener;)V
      11: return

  public void initializeApplicationModel(org.apache.dubbo.rpc.model.ApplicationModel);
    Code:
       0: aload_1
       1: invokevirtual #5                  // Method org/apache/dubbo/rpc/model/ApplicationModel.getBeanFactory:()Lorg/apache/dubbo/common/beans/factory/ScopeBeanFactory;
       4: astore_2
       5: aload_2
       6: ldc           #6                  // class org/apache/dubbo/config/utils/DefaultConfigValidator
       8: invokevirtual #7                  // Method org/apache/dubbo/common/beans/factory/ScopeBeanFactory.registerBean:(Ljava/lang/Class;)Ljava/lang/Object;
      11: pop
      12: aload_2
      13: ldc           #8                  // class org/apache/dubbo/config/deploy/DefaultApplicationDeployer
      15: invokevirtual #7                  // Method org/apache/dubbo/common/beans/factory/ScopeBeanFactory.registerBean:(Ljava/lang/Class;)Ljava/lang/Object;
      18: checkcast     #9                  // class org/apache/dubbo/common/deploy/ApplicationDeployer
      21: astore_3
      22: aload_1
      23: aload_3
      24: invokevirtual #10                 // Method org/apache/dubbo/rpc/model/ApplicationModel.setDeployer:(Lorg/apache/dubbo/common/deploy/ApplicationDeployer;)V
      27: return

  public void initializeModuleModel(org.apache.dubbo.rpc.model.ModuleModel);
    Code:
       0: aload_1
       1: invokevirtual #11                 // Method org/apache/dubbo/rpc/model/ModuleModel.getBeanFactory:()Lorg/apache/dubbo/common/beans/factory/ScopeBeanFactory;
       4: astore_2
       5: aload_2
       6: ldc           #12                 // class org/apache/dubbo/config/deploy/DefaultModuleDeployer
       8: invokevirtual #7                  // Method org/apache/dubbo/common/beans/factory/ScopeBeanFactory.registerBean:(Ljava/lang/Class;)Ljava/lang/Object;
      11: checkcast     #13                 // class org/apache/dubbo/common/deploy/ModuleDeployer
      14: astore_3
      15: aload_1
      16: aload_3
      17: invokevirtual #14                 // Method org/apache/dubbo/rpc/model/ModuleModel.setDeployer:(Lorg/apache/dubbo/common/deploy/ModuleDeployer;)V
      20: return
}
