Compiled from "ConsumerConfig.java"
public class org.apache.dubbo.config.ConsumerConfig extends org.apache.dubbo.config.AbstractReferenceConfig {
  private static final long serialVersionUID;

  private java.lang.String threadpool;

  private java.lang.Integer corethreads;

  private java.lang.Integer threads;

  private java.lang.Integer queues;

  private java.lang.Integer shareconnections;

  private java.lang.String urlMergeProcessor;

  private java.lang.Integer referThreadNum;

  private java.lang.Boolean referBackground;

  private java.lang.Boolean meshEnable;

  public org.apache.dubbo.config.ConsumerConfig();
    Code:
       0: aload_0
       1: invokespecial #1                  // Method org/apache/dubbo/config/AbstractReferenceConfig."<init>":()V
       4: return

  public org.apache.dubbo.config.ConsumerConfig(org.apache.dubbo.rpc.model.ModuleModel);
    Code:
       0: aload_0
       1: aload_1
       2: invokespecial #2                  // Method org/apache/dubbo/config/AbstractReferenceConfig."<init>":(Lorg/apache/dubbo/rpc/model/ModuleModel;)V
       5: return

  public void setTimeout(java.lang.Integer);
    Code:
       0: aload_0
       1: aload_1
       2: invokespecial #3                  // Method org/apache/dubbo/config/AbstractReferenceConfig.setTimeout:(Ljava/lang/Integer;)V
       5: ldc           #4                  // String sun.rmi.transport.tcp.responseTimeout
       7: invokestatic  #5                  // Method java/lang/System.getProperty:(Ljava/lang/String;)Ljava/lang/String;
      10: astore_2
      11: aload_1
      12: ifnull        39
      15: aload_1
      16: invokevirtual #6                  // Method java/lang/Integer.intValue:()I
      19: ifle          39
      22: aload_2
      23: invokestatic  #7                  // Method org/apache/dubbo/common/utils/StringUtils.isEmpty:(Ljava/lang/String;)Z
      26: ifeq          39
      29: ldc           #4                  // String sun.rmi.transport.tcp.responseTimeout
      31: aload_1
      32: invokestatic  #8                  // Method java/lang/String.valueOf:(Ljava/lang/Object;)Ljava/lang/String;
      35: invokestatic  #9                  // Method java/lang/System.setProperty:(Ljava/lang/String;Ljava/lang/String;)Ljava/lang/String;
      38: pop
      39: return

  public java.lang.String getThreadpool();
    Code:
       0: aload_0
       1: getfield      #10                 // Field threadpool:Ljava/lang/String;
       4: areturn

  public void setThreadpool(java.lang.String);
    Code:
       0: aload_0
       1: aload_1
       2: putfield      #10                 // Field threadpool:Ljava/lang/String;
       5: return

  public java.lang.Integer getCorethreads();
    Code:
       0: aload_0
       1: getfield      #11                 // Field corethreads:Ljava/lang/Integer;
       4: areturn

  public void setCorethreads(java.lang.Integer);
    Code:
       0: aload_0
       1: aload_1
       2: putfield      #11                 // Field corethreads:Ljava/lang/Integer;
       5: return

  public java.lang.Integer getThreads();
    Code:
       0: aload_0
       1: getfield      #12                 // Field threads:Ljava/lang/Integer;
       4: areturn

  public void setThreads(java.lang.Integer);
    Code:
       0: aload_0
       1: aload_1
       2: putfield      #12                 // Field threads:Ljava/lang/Integer;
       5: return

  public java.lang.Integer getQueues();
    Code:
       0: aload_0
       1: getfield      #13                 // Field queues:Ljava/lang/Integer;
       4: areturn

  public void setQueues(java.lang.Integer);
    Code:
       0: aload_0
       1: aload_1
       2: putfield      #13                 // Field queues:Ljava/lang/Integer;
       5: return

  public java.lang.Integer getShareconnections();
    Code:
       0: aload_0
       1: getfield      #14                 // Field shareconnections:Ljava/lang/Integer;
       4: areturn

  public void setShareconnections(java.lang.Integer);
    Code:
       0: aload_0
       1: aload_1
       2: putfield      #14                 // Field shareconnections:Ljava/lang/Integer;
       5: return

  public java.lang.String getUrlMergeProcessor();
    Code:
       0: aload_0
       1: getfield      #15                 // Field urlMergeProcessor:Ljava/lang/String;
       4: areturn

  public void setUrlMergeProcessor(java.lang.String);
    Code:
       0: aload_0
       1: aload_1
       2: putfield      #15                 // Field urlMergeProcessor:Ljava/lang/String;
       5: return

  public java.lang.Integer getReferThreadNum();
    Code:
       0: aload_0
       1: getfield      #16                 // Field referThreadNum:Ljava/lang/Integer;
       4: areturn

  public void setReferThreadNum(java.lang.Integer);
    Code:
       0: aload_0
       1: aload_1
       2: putfield      #16                 // Field referThreadNum:Ljava/lang/Integer;
       5: return

  public java.lang.Boolean getReferBackground();
    Code:
       0: aload_0
       1: getfield      #17                 // Field referBackground:Ljava/lang/Boolean;
       4: areturn

  public void setReferBackground(java.lang.Boolean);
    Code:
       0: aload_0
       1: aload_1
       2: putfield      #17                 // Field referBackground:Ljava/lang/Boolean;
       5: return

  public java.lang.Boolean getMeshEnable();
    Code:
       0: aload_0
       1: getfield      #18                 // Field meshEnable:Ljava/lang/Boolean;
       4: areturn

  public void setMeshEnable(java.lang.Boolean);
    Code:
       0: aload_0
       1: aload_1
       2: putfield      #18                 // Field meshEnable:Ljava/lang/Boolean;
       5: return
}
