Compiled from "MetadataReportConfig.java"
public class org.apache.dubbo.config.MetadataReportConfig extends org.apache.dubbo.config.AbstractConfig {
  private static final long serialVersionUID;

  private java.lang.String protocol;

  private java.lang.String address;

  private java.lang.Integer port;

  private java.lang.String username;

  private java.lang.String password;

  private java.lang.Integer timeout;

  private java.lang.String group;

  private java.util.Map<java.lang.String, java.lang.String> parameters;

  private java.lang.Integer retryTimes;

  private java.lang.Integer retryPeriod;

  private java.lang.Boolean cycleReport;

  private java.lang.Boolean syncReport;

  private java.lang.Boolean cluster;

  private java.lang.String registry;

  private java.lang.String file;

  private java.lang.Boolean check;

  private java.lang.Boolean reportMetadata;

  private java.lang.Boolean reportDefinition;

  public org.apache.dubbo.config.MetadataReportConfig();
    Code:
       0: aload_0
       1: invokespecial #3                  // Method org/apache/dubbo/config/AbstractConfig."<init>":()V
       4: return

  public org.apache.dubbo.config.MetadataReportConfig(org.apache.dubbo.rpc.model.ApplicationModel);
    Code:
       0: aload_0
       1: aload_1
       2: invokespecial #4                  // Method org/apache/dubbo/config/AbstractConfig."<init>":(Lorg/apache/dubbo/rpc/model/ScopeModel;)V
       5: return

  public org.apache.dubbo.config.MetadataReportConfig(java.lang.String);
    Code:
       0: aload_0
       1: invokespecial #3                  // Method org/apache/dubbo/config/AbstractConfig."<init>":()V
       4: aload_0
       5: aload_1
       6: invokevirtual #5                  // Method setAddress:(Ljava/lang/String;)V
       9: return

  public org.apache.dubbo.config.MetadataReportConfig(org.apache.dubbo.rpc.model.ApplicationModel, java.lang.String);
    Code:
       0: aload_0
       1: aload_1
       2: invokespecial #4                  // Method org/apache/dubbo/config/AbstractConfig."<init>":(Lorg/apache/dubbo/rpc/model/ScopeModel;)V
       5: aload_0
       6: aload_2
       7: invokevirtual #5                  // Method setAddress:(Ljava/lang/String;)V
      10: return

  public org.apache.dubbo.common.URL toUrl() throws java.lang.IllegalArgumentException;
    Code:
       0: aload_0
       1: invokevirtual #6                  // Method getAddress:()Ljava/lang/String;
       4: astore_1
       5: aload_1
       6: invokestatic  #7                  // Method org/apache/dubbo/common/utils/StringUtils.isEmpty:(Ljava/lang/String;)Z
       9: ifeq          22
      12: new           #8                  // class java/lang/IllegalArgumentException
      15: dup
      16: ldc           #9                  // String The address of metadata report is invalid.
      18: invokespecial #10                 // Method java/lang/IllegalArgumentException."<init>":(Ljava/lang/String;)V
      21: athrow
      22: new           #11                 // class java/util/HashMap
      25: dup
      26: invokespecial #12                 // Method java/util/HashMap."<init>":()V
      29: astore_2
      30: aload_1
      31: aload_0
      32: invokevirtual #13                 // Method getScopeModel:()Lorg/apache/dubbo/rpc/model/ScopeModel;
      35: invokestatic  #14                 // Method org/apache/dubbo/common/URL.valueOf:(Ljava/lang/String;Lorg/apache/dubbo/rpc/model/ScopeModel;)Lorg/apache/dubbo/common/URL;
      38: astore_3
      39: aload_2
      40: aload_3
      41: invokevirtual #15                 // Method org/apache/dubbo/common/URL.getParameters:()Ljava/util/Map;
      44: invokeinterface #16,  2           // InterfaceMethod java/util/Map.putAll:(Ljava/util/Map;)V
      49: aload_2
      50: aload_0
      51: invokestatic  #17                 // Method appendParameters:(Ljava/util/Map;Ljava/lang/Object;)V
      54: aload_2
      55: aload_2
      56: aconst_null
      57: invokestatic  #18                 // Method convert:(Ljava/util/Map;Ljava/lang/String;)Ljava/util/Map;
      60: invokeinterface #16,  2           // InterfaceMethod java/util/Map.putAll:(Ljava/util/Map;)V
      65: aload_2
      66: ldc           #19                 // String metadata
      68: aload_3
      69: invokevirtual #20                 // Method org/apache/dubbo/common/URL.getProtocol:()Ljava/lang/String;
      72: invokestatic  #7                  // Method org/apache/dubbo/common/utils/StringUtils.isEmpty:(Ljava/lang/String;)Z
      75: ifeq          92
      78: aload_2
      79: ldc           #21                 // String protocol
      81: invokeinterface #22,  2           // InterfaceMethod java/util/Map.get:(Ljava/lang/Object;)Ljava/lang/Object;
      86: checkcast     #23                 // class java/lang/String
      89: goto          96
      92: aload_3
      93: invokevirtual #20                 // Method org/apache/dubbo/common/URL.getProtocol:()Ljava/lang/String;
      96: invokeinterface #24,  3           // InterfaceMethod java/util/Map.put:(Ljava/lang/Object;Ljava/lang/Object;)Ljava/lang/Object;
     101: pop
     102: new           #25                 // class org/apache/dubbo/common/url/component/ServiceConfigURL
     105: dup
     106: ldc           #19                 // String metadata
     108: aload_3
     109: invokevirtual #26                 // Method org/apache/dubbo/common/URL.getUsername:()Ljava/lang/String;
     112: invokestatic  #27                 // Method org/apache/dubbo/common/utils/StringUtils.isBlank:(Ljava/lang/CharSequence;)Z
     115: ifeq          125
     118: aload_0
     119: invokevirtual #28                 // Method getUsername:()Ljava/lang/String;
     122: goto          129
     125: aload_3
     126: invokevirtual #26                 // Method org/apache/dubbo/common/URL.getUsername:()Ljava/lang/String;
     129: aload_3
     130: invokevirtual #29                 // Method org/apache/dubbo/common/URL.getPassword:()Ljava/lang/String;
     133: invokestatic  #27                 // Method org/apache/dubbo/common/utils/StringUtils.isBlank:(Ljava/lang/CharSequence;)Z
     136: ifeq          146
     139: aload_0
     140: invokevirtual #30                 // Method getPassword:()Ljava/lang/String;
     143: goto          150
     146: aload_3
     147: invokevirtual #29                 // Method org/apache/dubbo/common/URL.getPassword:()Ljava/lang/String;
     150: aload_3
     151: invokevirtual #31                 // Method org/apache/dubbo/common/URL.getHost:()Ljava/lang/String;
     154: aload_3
     155: invokevirtual #32                 // Method org/apache/dubbo/common/URL.getPort:()I
     158: aload_3
     159: invokevirtual #33                 // Method org/apache/dubbo/common/URL.getPath:()Ljava/lang/String;
     162: aload_2
     163: invokespecial #34                 // Method org/apache/dubbo/common/url/component/ServiceConfigURL."<init>":(Ljava/lang/String;Ljava/lang/String;Ljava/lang/String;Ljava/lang/String;ILjava/lang/String;Ljava/util/Map;)V
     166: aload_0
     167: invokevirtual #13                 // Method getScopeModel:()Lorg/apache/dubbo/rpc/model/ScopeModel;
     170: invokevirtual #35                 // Method org/apache/dubbo/common/url/component/ServiceConfigURL.setScopeModel:(Lorg/apache/dubbo/rpc/model/ScopeModel;)Lorg/apache/dubbo/common/URL;
     173: areturn

  public java.lang.String getProtocol();
    Code:
       0: aload_0
       1: getfield      #36                 // Field protocol:Ljava/lang/String;
       4: areturn

  public void setProtocol(java.lang.String);
    Code:
       0: aload_0
       1: aload_1
       2: putfield      #36                 // Field protocol:Ljava/lang/String;
       5: return

  public java.lang.String getAddress();
    Code:
       0: aload_0
       1: getfield      #37                 // Field address:Ljava/lang/String;
       4: areturn

  public void setAddress(java.lang.String);
    Code:
       0: aload_0
       1: aload_1
       2: putfield      #37                 // Field address:Ljava/lang/String;
       5: aload_1
       6: ifnull        123
       9: aload_1
      10: invokestatic  #38                 // Method org/apache/dubbo/common/URL.valueOf:(Ljava/lang/String;)Lorg/apache/dubbo/common/URL;
      13: astore_2
      14: aload_0
      15: invokedynamic #39,  0             // InvokeDynamic #0:get:(Lorg/apache/dubbo/config/MetadataReportConfig;)Ljava/util/function/Supplier;
      20: aload_0
      21: invokedynamic #40,  0             // InvokeDynamic #1:accept:(Lorg/apache/dubbo/config/MetadataReportConfig;)Ljava/util/function/Consumer;
      26: aload_2
      27: invokevirtual #26                 // Method org/apache/dubbo/common/URL.getUsername:()Ljava/lang/String;
      30: invokestatic  #41                 // Method org/apache/dubbo/common/utils/PojoUtils.updatePropertyIfAbsent:(Ljava/util/function/Supplier;Ljava/util/function/Consumer;Ljava/lang/Object;)V
      33: aload_0
      34: invokedynamic #42,  0             // InvokeDynamic #2:get:(Lorg/apache/dubbo/config/MetadataReportConfig;)Ljava/util/function/Supplier;
      39: aload_0
      40: invokedynamic #43,  0             // InvokeDynamic #3:accept:(Lorg/apache/dubbo/config/MetadataReportConfig;)Ljava/util/function/Consumer;
      45: aload_2
      46: invokevirtual #29                 // Method org/apache/dubbo/common/URL.getPassword:()Ljava/lang/String;
      49: invokestatic  #41                 // Method org/apache/dubbo/common/utils/PojoUtils.updatePropertyIfAbsent:(Ljava/util/function/Supplier;Ljava/util/function/Consumer;Ljava/lang/Object;)V
      52: aload_0
      53: invokedynamic #44,  0             // InvokeDynamic #4:get:(Lorg/apache/dubbo/config/MetadataReportConfig;)Ljava/util/function/Supplier;
      58: aload_0
      59: invokedynamic #45,  0             // InvokeDynamic #5:accept:(Lorg/apache/dubbo/config/MetadataReportConfig;)Ljava/util/function/Consumer;
      64: aload_2
      65: invokevirtual #20                 // Method org/apache/dubbo/common/URL.getProtocol:()Ljava/lang/String;
      68: invokestatic  #41                 // Method org/apache/dubbo/common/utils/PojoUtils.updatePropertyIfAbsent:(Ljava/util/function/Supplier;Ljava/util/function/Consumer;Ljava/lang/Object;)V
      71: aload_0
      72: invokedynamic #46,  0             // InvokeDynamic #6:get:(Lorg/apache/dubbo/config/MetadataReportConfig;)Ljava/util/function/Supplier;
      77: aload_0
      78: invokedynamic #47,  0             // InvokeDynamic #7:accept:(Lorg/apache/dubbo/config/MetadataReportConfig;)Ljava/util/function/Consumer;
      83: aload_2
      84: invokevirtual #32                 // Method org/apache/dubbo/common/URL.getPort:()I
      87: invokestatic  #48                 // Method java/lang/Integer.valueOf:(I)Ljava/lang/Integer;
      90: invokestatic  #41                 // Method org/apache/dubbo/common/utils/PojoUtils.updatePropertyIfAbsent:(Ljava/util/function/Supplier;Ljava/util/function/Consumer;Ljava/lang/Object;)V
      93: aload_2
      94: invokevirtual #15                 // Method org/apache/dubbo/common/URL.getParameters:()Ljava/util/Map;
      97: astore_3
      98: aload_3
      99: invokestatic  #49                 // Method org/apache/dubbo/common/utils/CollectionUtils.isNotEmptyMap:(Ljava/util/Map;)Z
     102: ifeq          114
     105: aload_3
     106: ldc           #50                 // String backup
     108: invokeinterface #51,  2           // InterfaceMethod java/util/Map.remove:(Ljava/lang/Object;)Ljava/lang/Object;
     113: pop
     114: aload_0
     115: aload_3
     116: invokevirtual #52                 // Method updateParameters:(Ljava/util/Map;)V
     119: goto          123
     122: astore_2
     123: return
    Exception table:
       from    to  target type
           9   119   122   Class java/lang/Exception

  public java.lang.Integer getPort();
    Code:
       0: aload_0
       1: getfield      #54                 // Field port:Ljava/lang/Integer;
       4: areturn

  public void setPort(java.lang.Integer);
    Code:
       0: aload_0
       1: aload_1
       2: putfield      #54                 // Field port:Ljava/lang/Integer;
       5: return

  public java.lang.String getUsername();
    Code:
       0: aload_0
       1: getfield      #55                 // Field username:Ljava/lang/String;
       4: areturn

  public void setUsername(java.lang.String);
    Code:
       0: aload_0
       1: aload_1
       2: putfield      #55                 // Field username:Ljava/lang/String;
       5: return

  public java.lang.String getPassword();
    Code:
       0: aload_0
       1: getfield      #56                 // Field password:Ljava/lang/String;
       4: areturn

  public void setPassword(java.lang.String);
    Code:
       0: aload_0
       1: aload_1
       2: putfield      #56                 // Field password:Ljava/lang/String;
       5: return

  public java.lang.Integer getTimeout();
    Code:
       0: aload_0
       1: getfield      #57                 // Field timeout:Ljava/lang/Integer;
       4: areturn

  public void setTimeout(java.lang.Integer);
    Code:
       0: aload_0
       1: aload_1
       2: putfield      #57                 // Field timeout:Ljava/lang/Integer;
       5: return

  public java.util.Map<java.lang.String, java.lang.String> getParameters();
    Code:
       0: aload_0
       1: getfield      #58                 // Field parameters:Ljava/util/Map;
       4: areturn

  public void setParameters(java.util.Map<java.lang.String, java.lang.String>);
    Code:
       0: aload_0
       1: aload_1
       2: putfield      #58                 // Field parameters:Ljava/util/Map;
       5: return

  public java.lang.Integer getRetryTimes();
    Code:
       0: aload_0
       1: getfield      #59                 // Field retryTimes:Ljava/lang/Integer;
       4: areturn

  public void setRetryTimes(java.lang.Integer);
    Code:
       0: aload_0
       1: aload_1
       2: putfield      #59                 // Field retryTimes:Ljava/lang/Integer;
       5: return

  public java.lang.Integer getRetryPeriod();
    Code:
       0: aload_0
       1: getfield      #60                 // Field retryPeriod:Ljava/lang/Integer;
       4: areturn

  public void setRetryPeriod(java.lang.Integer);
    Code:
       0: aload_0
       1: aload_1
       2: putfield      #60                 // Field retryPeriod:Ljava/lang/Integer;
       5: return

  public java.lang.Boolean getCycleReport();
    Code:
       0: aload_0
       1: getfield      #61                 // Field cycleReport:Ljava/lang/Boolean;
       4: areturn

  public void setCycleReport(java.lang.Boolean);
    Code:
       0: aload_0
       1: aload_1
       2: putfield      #61                 // Field cycleReport:Ljava/lang/Boolean;
       5: return

  public java.lang.Boolean getSyncReport();
    Code:
       0: aload_0
       1: getfield      #62                 // Field syncReport:Ljava/lang/Boolean;
       4: areturn

  public void setSyncReport(java.lang.Boolean);
    Code:
       0: aload_0
       1: aload_1
       2: putfield      #62                 // Field syncReport:Ljava/lang/Boolean;
       5: return

  public boolean isValid();
    Code:
       0: aload_0
       1: getfield      #37                 // Field address:Ljava/lang/String;
       4: invokestatic  #63                 // Method org/apache/dubbo/common/utils/StringUtils.isNotEmpty:(Ljava/lang/String;)Z
       7: ireturn

  public java.lang.String getGroup();
    Code:
       0: aload_0
       1: getfield      #64                 // Field group:Ljava/lang/String;
       4: areturn

  public void setGroup(java.lang.String);
    Code:
       0: aload_0
       1: aload_1
       2: putfield      #64                 // Field group:Ljava/lang/String;
       5: return

  public java.lang.Boolean getCluster();
    Code:
       0: aload_0
       1: getfield      #65                 // Field cluster:Ljava/lang/Boolean;
       4: areturn

  public void setCluster(java.lang.Boolean);
    Code:
       0: aload_0
       1: aload_1
       2: putfield      #65                 // Field cluster:Ljava/lang/Boolean;
       5: return

  public java.lang.String getRegistry();
    Code:
       0: aload_0
       1: getfield      #66                 // Field registry:Ljava/lang/String;
       4: areturn

  public void setRegistry(java.lang.String);
    Code:
       0: aload_0
       1: aload_1
       2: putfield      #66                 // Field registry:Ljava/lang/String;
       5: return

  public java.lang.String getFile();
    Code:
       0: aload_0
       1: getfield      #67                 // Field file:Ljava/lang/String;
       4: areturn

  public void setFile(java.lang.String);
    Code:
       0: aload_0
       1: aload_1
       2: putfield      #67                 // Field file:Ljava/lang/String;
       5: return

  public void updateParameters(java.util.Map<java.lang.String, java.lang.String>);
    Code:
       0: aload_1
       1: invokestatic  #68                 // Method org/apache/dubbo/common/utils/CollectionUtils.isEmptyMap:(Ljava/util/Map;)Z
       4: ifeq          8
       7: return
       8: aload_0
       9: getfield      #58                 // Field parameters:Ljava/util/Map;
      12: ifnonnull     23
      15: aload_0
      16: aload_1
      17: putfield      #58                 // Field parameters:Ljava/util/Map;
      20: goto          33
      23: aload_0
      24: getfield      #58                 // Field parameters:Ljava/util/Map;
      27: aload_1
      28: invokeinterface #16,  2           // InterfaceMethod java/util/Map.putAll:(Ljava/util/Map;)V
      33: return

  public java.lang.Boolean isCheck();
    Code:
       0: aload_0
       1: getfield      #69                 // Field check:Ljava/lang/Boolean;
       4: areturn

  public void setCheck(java.lang.Boolean);
    Code:
       0: aload_0
       1: aload_1
       2: putfield      #69                 // Field check:Ljava/lang/Boolean;
       5: return

  public java.lang.Boolean getReportMetadata();
    Code:
       0: aload_0
       1: getfield      #70                 // Field reportMetadata:Ljava/lang/Boolean;
       4: areturn

  public void setReportMetadata(java.lang.Boolean);
    Code:
       0: aload_0
       1: aload_1
       2: putfield      #70                 // Field reportMetadata:Ljava/lang/Boolean;
       5: return

  public java.lang.Boolean getReportDefinition();
    Code:
       0: aload_0
       1: getfield      #71                 // Field reportDefinition:Ljava/lang/Boolean;
       4: areturn

  public void setReportDefinition(java.lang.Boolean);
    Code:
       0: aload_0
       1: aload_1
       2: putfield      #71                 // Field reportDefinition:Ljava/lang/Boolean;
       5: return
}
