Compiled from "MethodConfig.java"
public class org.apache.dubbo.config.MethodConfig extends org.apache.dubbo.config.AbstractMethodConfig {
  private static final long serialVersionUID;

  private java.lang.String name;

  private java.lang.Integer stat;

  private java.lang.Boolean retry;

  private java.lang.Boolean reliable;

  private java.lang.Integer executes;

  private java.lang.Boolean deprecated;

  private java.lang.Boolean sticky;

  private java.lang.Boolean isReturn;

  private java.lang.Object oninvoke;

  private java.lang.String oninvokeMethod;

  private java.lang.Object onreturn;

  private java.lang.String onreturnMethod;

  private java.lang.Object onthrow;

  private java.lang.String onthrowMethod;

  private java.util.List<org.apache.dubbo.config.ArgumentConfig> arguments;

  private java.lang.String service;

  private java.lang.String serviceId;

  private java.lang.String parentPrefix;

  public org.apache.dubbo.config.MethodConfig();
    Code:
       0: aload_0
       1: invokespecial #1                  // Method org/apache/dubbo/config/AbstractMethodConfig."<init>":()V
       4: return

  public org.apache.dubbo.config.MethodConfig(org.apache.dubbo.rpc.model.ModuleModel);
    Code:
       0: aload_0
       1: aload_1
       2: invokespecial #2                  // Method org/apache/dubbo/config/AbstractMethodConfig."<init>":(Lorg/apache/dubbo/rpc/model/ModuleModel;)V
       5: return

  public org.apache.dubbo.config.MethodConfig(org.apache.dubbo.config.annotation.Method);
    Code:
       0: aload_0
       1: invokespecial #1                  // Method org/apache/dubbo/config/AbstractMethodConfig."<init>":()V
       4: aload_0
       5: ldc           #3                  // class org/apache/dubbo/config/annotation/Method
       7: aload_1
       8: invokevirtual #4                  // Method appendAnnotation:(Ljava/lang/Class;Ljava/lang/Object;)V
      11: aload_0
      12: aload_1
      13: invokeinterface #5,  1            // InterfaceMethod org/apache/dubbo/config/annotation/Method.isReturn:()Z
      18: invokestatic  #6                  // Method java/lang/Boolean.valueOf:(Z)Ljava/lang/Boolean;
      21: invokevirtual #7                  // Method setReturn:(Ljava/lang/Boolean;)V
      24: ldc           #8                  // String .
      26: astore_2
      27: ldc           #9                  // String
      29: aload_1
      30: invokeinterface #10,  1           // InterfaceMethod org/apache/dubbo/config/annotation/Method.oninvoke:()Ljava/lang/String;
      35: invokevirtual #11                 // Method java/lang/String.equals:(Ljava/lang/Object;)Z
      38: ifne          104
      41: aload_1
      42: invokeinterface #10,  1           // InterfaceMethod org/apache/dubbo/config/annotation/Method.oninvoke:()Ljava/lang/String;
      47: aload_2
      48: invokevirtual #12                 // Method java/lang/String.lastIndexOf:(Ljava/lang/String;)I
      51: ifle          104
      54: aload_1
      55: invokeinterface #10,  1           // InterfaceMethod org/apache/dubbo/config/annotation/Method.oninvoke:()Ljava/lang/String;
      60: aload_2
      61: invokevirtual #12                 // Method java/lang/String.lastIndexOf:(Ljava/lang/String;)I
      64: istore_3
      65: aload_1
      66: invokeinterface #10,  1           // InterfaceMethod org/apache/dubbo/config/annotation/Method.oninvoke:()Ljava/lang/String;
      71: iconst_0
      72: iload_3
      73: invokevirtual #13                 // Method java/lang/String.substring:(II)Ljava/lang/String;
      76: astore        4
      78: aload_1
      79: invokeinterface #10,  1           // InterfaceMethod org/apache/dubbo/config/annotation/Method.oninvoke:()Ljava/lang/String;
      84: iload_3
      85: iconst_1
      86: iadd
      87: invokevirtual #14                 // Method java/lang/String.substring:(I)Ljava/lang/String;
      90: astore        5
      92: aload_0
      93: aload         4
      95: invokevirtual #15                 // Method setOninvoke:(Ljava/lang/Object;)V
      98: aload_0
      99: aload         5
     101: invokevirtual #16                 // Method setOninvokeMethod:(Ljava/lang/String;)V
     104: ldc           #9                  // String
     106: aload_1
     107: invokeinterface #17,  1           // InterfaceMethod org/apache/dubbo/config/annotation/Method.onreturn:()Ljava/lang/String;
     112: invokevirtual #11                 // Method java/lang/String.equals:(Ljava/lang/Object;)Z
     115: ifne          181
     118: aload_1
     119: invokeinterface #17,  1           // InterfaceMethod org/apache/dubbo/config/annotation/Method.onreturn:()Ljava/lang/String;
     124: aload_2
     125: invokevirtual #12                 // Method java/lang/String.lastIndexOf:(Ljava/lang/String;)I
     128: ifle          181
     131: aload_1
     132: invokeinterface #17,  1           // InterfaceMethod org/apache/dubbo/config/annotation/Method.onreturn:()Ljava/lang/String;
     137: aload_2
     138: invokevirtual #12                 // Method java/lang/String.lastIndexOf:(Ljava/lang/String;)I
     141: istore_3
     142: aload_1
     143: invokeinterface #17,  1           // InterfaceMethod org/apache/dubbo/config/annotation/Method.onreturn:()Ljava/lang/String;
     148: iconst_0
     149: iload_3
     150: invokevirtual #13                 // Method java/lang/String.substring:(II)Ljava/lang/String;
     153: astore        4
     155: aload_1
     156: invokeinterface #17,  1           // InterfaceMethod org/apache/dubbo/config/annotation/Method.onreturn:()Ljava/lang/String;
     161: iload_3
     162: iconst_1
     163: iadd
     164: invokevirtual #14                 // Method java/lang/String.substring:(I)Ljava/lang/String;
     167: astore        5
     169: aload_0
     170: aload         4
     172: invokevirtual #18                 // Method setOnreturn:(Ljava/lang/Object;)V
     175: aload_0
     176: aload         5
     178: invokevirtual #19                 // Method setOnreturnMethod:(Ljava/lang/String;)V
     181: ldc           #9                  // String
     183: aload_1
     184: invokeinterface #20,  1           // InterfaceMethod org/apache/dubbo/config/annotation/Method.onthrow:()Ljava/lang/String;
     189: invokevirtual #11                 // Method java/lang/String.equals:(Ljava/lang/Object;)Z
     192: ifne          258
     195: aload_1
     196: invokeinterface #20,  1           // InterfaceMethod org/apache/dubbo/config/annotation/Method.onthrow:()Ljava/lang/String;
     201: aload_2
     202: invokevirtual #12                 // Method java/lang/String.lastIndexOf:(Ljava/lang/String;)I
     205: ifle          258
     208: aload_1
     209: invokeinterface #20,  1           // InterfaceMethod org/apache/dubbo/config/annotation/Method.onthrow:()Ljava/lang/String;
     214: aload_2
     215: invokevirtual #12                 // Method java/lang/String.lastIndexOf:(Ljava/lang/String;)I
     218: istore_3
     219: aload_1
     220: invokeinterface #20,  1           // InterfaceMethod org/apache/dubbo/config/annotation/Method.onthrow:()Ljava/lang/String;
     225: iconst_0
     226: iload_3
     227: invokevirtual #13                 // Method java/lang/String.substring:(II)Ljava/lang/String;
     230: astore        4
     232: aload_1
     233: invokeinterface #20,  1           // InterfaceMethod org/apache/dubbo/config/annotation/Method.onthrow:()Ljava/lang/String;
     238: iload_3
     239: iconst_1
     240: iadd
     241: invokevirtual #14                 // Method java/lang/String.substring:(I)Ljava/lang/String;
     244: astore        5
     246: aload_0
     247: aload         4
     249: invokevirtual #21                 // Method setOnthrow:(Ljava/lang/Object;)V
     252: aload_0
     253: aload         5
     255: invokevirtual #22                 // Method setOnthrowMethod:(Ljava/lang/String;)V
     258: aload_1
     259: invokeinterface #23,  1           // InterfaceMethod org/apache/dubbo/config/annotation/Method.arguments:()[Lorg/apache/dubbo/config/annotation/Argument;
     264: ifnull        345
     267: aload_1
     268: invokeinterface #23,  1           // InterfaceMethod org/apache/dubbo/config/annotation/Method.arguments:()[Lorg/apache/dubbo/config/annotation/Argument;
     273: arraylength
     274: ifeq          345
     277: new           #24                 // class java/util/ArrayList
     280: dup
     281: aload_1
     282: invokeinterface #23,  1           // InterfaceMethod org/apache/dubbo/config/annotation/Method.arguments:()[Lorg/apache/dubbo/config/annotation/Argument;
     287: arraylength
     288: invokespecial #25                 // Method java/util/ArrayList."<init>":(I)V
     291: astore_3
     292: aload_0
     293: aload_3
     294: invokevirtual #26                 // Method setArguments:(Ljava/util/List;)V
     297: iconst_0
     298: istore        4
     300: iload         4
     302: aload_1
     303: invokeinterface #23,  1           // InterfaceMethod org/apache/dubbo/config/annotation/Method.arguments:()[Lorg/apache/dubbo/config/annotation/Argument;
     308: arraylength
     309: if_icmpge     345
     312: new           #27                 // class org/apache/dubbo/config/ArgumentConfig
     315: dup
     316: aload_1
     317: invokeinterface #23,  1           // InterfaceMethod org/apache/dubbo/config/annotation/Method.arguments:()[Lorg/apache/dubbo/config/annotation/Argument;
     322: iload         4
     324: aaload
     325: invokespecial #28                 // Method org/apache/dubbo/config/ArgumentConfig."<init>":(Lorg/apache/dubbo/config/annotation/Argument;)V
     328: astore        5
     330: aload_3
     331: aload         5
     333: invokeinterface #29,  2           // InterfaceMethod java/util/List.add:(Ljava/lang/Object;)Z
     338: pop
     339: iinc          4, 1
     342: goto          300
     345: return

  public static java.util.List<org.apache.dubbo.config.MethodConfig> constructMethodConfig(org.apache.dubbo.config.annotation.Method[]);
    Code:
       0: aload_0
       1: ifnull        54
       4: aload_0
       5: arraylength
       6: ifeq          54
       9: new           #24                 // class java/util/ArrayList
      12: dup
      13: aload_0
      14: arraylength
      15: invokespecial #25                 // Method java/util/ArrayList."<init>":(I)V
      18: astore_1
      19: iconst_0
      20: istore_2
      21: iload_2
      22: aload_0
      23: arraylength
      24: if_icmpge     52
      27: new           #30                 // class org/apache/dubbo/config/MethodConfig
      30: dup
      31: aload_0
      32: iload_2
      33: aaload
      34: invokespecial #31                 // Method "<init>":(Lorg/apache/dubbo/config/annotation/Method;)V
      37: astore_3
      38: aload_1
      39: aload_3
      40: invokeinterface #29,  2           // InterfaceMethod java/util/List.add:(Ljava/lang/Object;)Z
      45: pop
      46: iinc          2, 1
      49: goto          21
      52: aload_1
      53: areturn
      54: invokestatic  #32                 // Method java/util/Collections.emptyList:()Ljava/util/List;
      57: areturn

  public java.util.List<java.lang.String> getPrefixes();
    Code:
       0: aload_0
       1: getfield      #33                 // Field parentPrefix:Ljava/lang/String;
       4: ifnull        53
       7: new           #24                 // class java/util/ArrayList
      10: dup
      11: invokespecial #34                 // Method java/util/ArrayList."<init>":()V
      14: astore_1
      15: aload_1
      16: new           #35                 // class java/lang/StringBuilder
      19: dup
      20: invokespecial #36                 // Method java/lang/StringBuilder."<init>":()V
      23: aload_0
      24: getfield      #33                 // Field parentPrefix:Ljava/lang/String;
      27: invokevirtual #37                 // Method java/lang/StringBuilder.append:(Ljava/lang/String;)Ljava/lang/StringBuilder;
      30: ldc           #8                  // String .
      32: invokevirtual #37                 // Method java/lang/StringBuilder.append:(Ljava/lang/String;)Ljava/lang/StringBuilder;
      35: aload_0
      36: invokevirtual #38                 // Method getName:()Ljava/lang/String;
      39: invokevirtual #37                 // Method java/lang/StringBuilder.append:(Ljava/lang/String;)Ljava/lang/StringBuilder;
      42: invokevirtual #39                 // Method java/lang/StringBuilder.toString:()Ljava/lang/String;
      45: invokeinterface #29,  2           // InterfaceMethod java/util/List.add:(Ljava/lang/Object;)Z
      50: pop
      51: aload_1
      52: areturn
      53: new           #40                 // class java/lang/IllegalStateException
      56: dup
      57: ldc           #41                 // String The parent prefix of MethodConfig is null
      59: invokespecial #42                 // Method java/lang/IllegalStateException."<init>":(Ljava/lang/String;)V
      62: athrow

  protected void processExtraRefresh(java.lang.String, org.apache.dubbo.common.config.InmemoryConfiguration);
    Code:
       0: aload_0
       1: invokevirtual #43                 // Method getArguments:()Ljava/util/List;
       4: ifnull        59
       7: aload_0
       8: invokevirtual #43                 // Method getArguments:()Ljava/util/List;
      11: invokeinterface #44,  1           // InterfaceMethod java/util/List.size:()I
      16: ifle          59
      19: aload_0
      20: invokevirtual #43                 // Method getArguments:()Ljava/util/List;
      23: invokeinterface #45,  1           // InterfaceMethod java/util/List.iterator:()Ljava/util/Iterator;
      28: astore_3
      29: aload_3
      30: invokeinterface #46,  1           // InterfaceMethod java/util/Iterator.hasNext:()Z
      35: ifeq          59
      38: aload_3
      39: invokeinterface #47,  1           // InterfaceMethod java/util/Iterator.next:()Ljava/lang/Object;
      44: checkcast     #27                 // class org/apache/dubbo/config/ArgumentConfig
      47: astore        4
      49: aload_0
      50: aload         4
      52: aload_2
      53: invokespecial #48                 // Method refreshArgument:(Lorg/apache/dubbo/config/ArgumentConfig;Lorg/apache/dubbo/common/config/InmemoryConfiguration;)V
      56: goto          29
      59: return

  private void refreshArgument(org.apache.dubbo.config.ArgumentConfig, org.apache.dubbo.common.config.InmemoryConfiguration);
    Code:
       0: aload_1
       1: invokevirtual #49                 // Method org/apache/dubbo/config/ArgumentConfig.getIndex:()Ljava/lang/Integer;
       4: ifnull        303
       7: aload_1
       8: invokevirtual #49                 // Method org/apache/dubbo/config/ArgumentConfig.getIndex:()Ljava/lang/Integer;
      11: invokevirtual #50                 // Method java/lang/Integer.intValue:()I
      14: iflt          303
      17: new           #35                 // class java/lang/StringBuilder
      20: dup
      21: invokespecial #36                 // Method java/lang/StringBuilder."<init>":()V
      24: aload_1
      25: invokevirtual #49                 // Method org/apache/dubbo/config/ArgumentConfig.getIndex:()Ljava/lang/Integer;
      28: invokevirtual #51                 // Method java/lang/StringBuilder.append:(Ljava/lang/Object;)Ljava/lang/StringBuilder;
      31: ldc           #8                  // String .
      33: invokevirtual #37                 // Method java/lang/StringBuilder.append:(Ljava/lang/String;)Ljava/lang/StringBuilder;
      36: invokevirtual #39                 // Method java/lang/StringBuilder.toString:()Ljava/lang/String;
      39: astore_3
      40: aload_0
      41: invokevirtual #52                 // Method getScopeModel:()Lorg/apache/dubbo/rpc/model/ModuleModel;
      44: invokevirtual #53                 // Method org/apache/dubbo/rpc/model/ModuleModel.getModelEnvironment:()Lorg/apache/dubbo/common/config/ModuleEnvironment;
      47: astore        4
      49: aload_1
      50: invokevirtual #54                 // Method java/lang/Object.getClass:()Ljava/lang/Class;
      53: iconst_1
      54: anewarray     #55                 // class java/util/function/Predicate
      57: dup
      58: iconst_0
      59: invokedynamic #56,  0             // InvokeDynamic #0:test:()Ljava/util/function/Predicate;
      64: aastore
      65: invokestatic  #57                 // InterfaceMethod org/apache/dubbo/common/utils/MethodUtils.getMethods:(Ljava/lang/Class;[Ljava/util/function/Predicate;)Ljava/util/List;
      68: astore        5
      70: aload         5
      72: invokeinterface #45,  1           // InterfaceMethod java/util/List.iterator:()Ljava/util/Iterator;
      77: astore        6
      79: aload         6
      81: invokeinterface #46,  1           // InterfaceMethod java/util/Iterator.hasNext:()Z
      86: ifeq          303
      89: aload         6
      91: invokeinterface #47,  1           // InterfaceMethod java/util/Iterator.next:()Ljava/lang/Object;
      96: checkcast     #58                 // class java/lang/reflect/Method
      99: astore        7
     101: aload         7
     103: invokestatic  #59                 // InterfaceMethod org/apache/dubbo/common/utils/MethodUtils.isSetter:(Ljava/lang/reflect/Method;)Z
     106: ifeq          300
     109: aload         7
     111: invokevirtual #60                 // Method java/lang/reflect/Method.getName:()Ljava/lang/String;
     114: invokestatic  #61                 // Method extractPropertyName:(Ljava/lang/String;)Ljava/lang/String;
     117: astore        8
     119: aload         8
     121: ldc           #62                 // String index
     123: invokestatic  #63                 // Method org/apache/dubbo/common/utils/StringUtils.isEquals:(Ljava/lang/String;Ljava/lang/String;)Z
     126: ifne          79
     129: aload         8
     131: ldc           #64                 // String type
     133: invokestatic  #63                 // Method org/apache/dubbo/common/utils/StringUtils.isEquals:(Ljava/lang/String;Ljava/lang/String;)Z
     136: ifeq          142
     139: goto          79
     142: new           #35                 // class java/lang/StringBuilder
     145: dup
     146: invokespecial #36                 // Method java/lang/StringBuilder."<init>":()V
     149: aload_3
     150: invokevirtual #37                 // Method java/lang/StringBuilder.append:(Ljava/lang/String;)Ljava/lang/StringBuilder;
     153: aload         8
     155: ldc           #65                 // String -
     157: invokestatic  #66                 // Method org/apache/dubbo/common/utils/StringUtils.convertToSplitName:(Ljava/lang/String;Ljava/lang/String;)Ljava/lang/String;
     160: invokevirtual #37                 // Method java/lang/StringBuilder.append:(Ljava/lang/String;)Ljava/lang/StringBuilder;
     163: invokevirtual #39                 // Method java/lang/StringBuilder.toString:()Ljava/lang/String;
     166: astore        9
     168: aload_2
     169: aload         9
     171: invokevirtual #67                 // Method org/apache/dubbo/common/config/InmemoryConfiguration.getString:(Ljava/lang/String;)Ljava/lang/String;
     174: invokestatic  #68                 // Method org/apache/dubbo/common/utils/StringUtils.trim:(Ljava/lang/String;)Ljava/lang/String;
     177: astore        10
     179: aload         10
     181: invokestatic  #69                 // Method org/apache/dubbo/common/utils/StringUtils.hasText:(Ljava/lang/CharSequence;)Z
     184: ifeq          244
     187: aload         7
     189: invokevirtual #70                 // Method java/lang/reflect/Method.getParameterTypes:()[Ljava/lang/Class;
     192: iconst_0
     193: aaload
     194: aload         10
     196: invokestatic  #71                 // Method org/apache/dubbo/common/utils/ClassUtils.isTypeMatch:(Ljava/lang/Class;Ljava/lang/String;)Z
     199: ifeq          244
     202: aload         4
     204: aload         10
     206: invokevirtual #72                 // Method org/apache/dubbo/common/config/Environment.resolvePlaceholders:(Ljava/lang/String;)Ljava/lang/String;
     209: astore        10
     211: aload         7
     213: aload_1
     214: iconst_1
     215: anewarray     #73                 // class java/lang/Object
     218: dup
     219: iconst_0
     220: aload_0
     221: invokevirtual #52                 // Method getScopeModel:()Lorg/apache/dubbo/rpc/model/ModuleModel;
     224: invokestatic  #74                 // Method org/apache/dubbo/rpc/model/ScopeModelUtil.getFrameworkModel:(Lorg/apache/dubbo/rpc/model/ScopeModel;)Lorg/apache/dubbo/rpc/model/FrameworkModel;
     227: aload         7
     229: invokevirtual #70                 // Method java/lang/reflect/Method.getParameterTypes:()[Ljava/lang/Class;
     232: iconst_0
     233: aaload
     234: aload         10
     236: invokestatic  #75                 // Method org/apache/dubbo/common/utils/ClassUtils.convertPrimitive:(Lorg/apache/dubbo/rpc/model/FrameworkModel;Ljava/lang/Class;Ljava/lang/String;)Ljava/lang/Object;
     239: aastore
     240: invokevirtual #76                 // Method java/lang/reflect/Method.invoke:(Ljava/lang/Object;[Ljava/lang/Object;)Ljava/lang/Object;
     243: pop
     244: goto          300
     247: astore        10
     249: getstatic     #78                 // Field logger:Lorg/apache/dubbo/common/logger/ErrorTypeAwareLogger;
     252: new           #35                 // class java/lang/StringBuilder
     255: dup
     256: invokespecial #36                 // Method java/lang/StringBuilder."<init>":()V
     259: ldc           #79                 // String Failed to override the property
     261: invokevirtual #37                 // Method java/lang/StringBuilder.append:(Ljava/lang/String;)Ljava/lang/StringBuilder;
     264: aload         7
     266: invokevirtual #60                 // Method java/lang/reflect/Method.getName:()Ljava/lang/String;
     269: invokevirtual #37                 // Method java/lang/StringBuilder.append:(Ljava/lang/String;)Ljava/lang/StringBuilder;
     272: ldc           #80                 // String  in
     274: invokevirtual #37                 // Method java/lang/StringBuilder.append:(Ljava/lang/String;)Ljava/lang/StringBuilder;
     277: aload_0
     278: invokevirtual #54                 // Method java/lang/Object.getClass:()Ljava/lang/Class;
     281: invokevirtual #81                 // Method java/lang/Class.getSimpleName:()Ljava/lang/String;
     284: invokevirtual #37                 // Method java/lang/StringBuilder.append:(Ljava/lang/String;)Ljava/lang/StringBuilder;
     287: ldc           #82                 // String , please make sure every property has getter/setter method provided.
     289: invokevirtual #37                 // Method java/lang/StringBuilder.append:(Ljava/lang/String;)Ljava/lang/StringBuilder;
     292: invokevirtual #39                 // Method java/lang/StringBuilder.toString:()Ljava/lang/String;
     295: invokeinterface #83,  2           // InterfaceMethod org/apache/dubbo/common/logger/ErrorTypeAwareLogger.info:(Ljava/lang/String;)V
     300: goto          79
     303: return
    Exception table:
       from    to  target type
         168   244   247   Class java/lang/Exception

  public org.apache.dubbo.rpc.model.AsyncMethodInfo convertMethodConfig2AsyncInfo();
    Code:
       0: aload_0
       1: invokevirtual #84                 // Method getOninvoke:()Ljava/lang/Object;
       4: ifnonnull     23
       7: aload_0
       8: invokevirtual #85                 // Method getOnreturn:()Ljava/lang/Object;
      11: ifnonnull     23
      14: aload_0
      15: invokevirtual #86                 // Method getOnthrow:()Ljava/lang/Object;
      18: ifnonnull     23
      21: aconst_null
      22: areturn
      23: getstatic     #87                 // Field java/lang/Boolean.FALSE:Ljava/lang/Boolean;
      26: aload_0
      27: invokevirtual #88                 // Method isReturn:()Ljava/lang/Boolean;
      30: invokevirtual #89                 // Method java/lang/Boolean.equals:(Ljava/lang/Object;)Z
      33: ifeq          60
      36: aload_0
      37: invokevirtual #85                 // Method getOnreturn:()Ljava/lang/Object;
      40: ifnonnull     50
      43: aload_0
      44: invokevirtual #86                 // Method getOnthrow:()Ljava/lang/Object;
      47: ifnull        60
      50: new           #40                 // class java/lang/IllegalStateException
      53: dup
      54: ldc           #90                 // String method config error : return attribute must be set true when on-return or on-throw has been set.
      56: invokespecial #42                 // Method java/lang/IllegalStateException."<init>":(Ljava/lang/String;)V
      59: athrow
      60: new           #91                 // class org/apache/dubbo/rpc/model/AsyncMethodInfo
      63: dup
      64: invokespecial #92                 // Method org/apache/dubbo/rpc/model/AsyncMethodInfo."<init>":()V
      67: astore_1
      68: aload_1
      69: aload_0
      70: invokevirtual #84                 // Method getOninvoke:()Ljava/lang/Object;
      73: invokevirtual #93                 // Method org/apache/dubbo/rpc/model/AsyncMethodInfo.setOninvokeInstance:(Ljava/lang/Object;)V
      76: aload_1
      77: aload_0
      78: invokevirtual #85                 // Method getOnreturn:()Ljava/lang/Object;
      81: invokevirtual #94                 // Method org/apache/dubbo/rpc/model/AsyncMethodInfo.setOnreturnInstance:(Ljava/lang/Object;)V
      84: aload_1
      85: aload_0
      86: invokevirtual #86                 // Method getOnthrow:()Ljava/lang/Object;
      89: invokevirtual #95                 // Method org/apache/dubbo/rpc/model/AsyncMethodInfo.setOnthrowInstance:(Ljava/lang/Object;)V
      92: aload_0
      93: getfield      #96                 // Field oninvokeMethod:Ljava/lang/String;
      96: invokestatic  #97                 // Method org/apache/dubbo/common/utils/StringUtils.isNotEmpty:(Ljava/lang/String;)Z
      99: ifeq          121
     102: aload_1
     103: aload_0
     104: aload_0
     105: invokevirtual #84                 // Method getOninvoke:()Ljava/lang/Object;
     108: invokevirtual #54                 // Method java/lang/Object.getClass:()Ljava/lang/Class;
     111: aload_0
     112: getfield      #96                 // Field oninvokeMethod:Ljava/lang/String;
     115: invokespecial #98                 // Method getMethodByName:(Ljava/lang/Class;Ljava/lang/String;)Ljava/lang/reflect/Method;
     118: invokevirtual #99                 // Method org/apache/dubbo/rpc/model/AsyncMethodInfo.setOninvokeMethod:(Ljava/lang/reflect/Method;)V
     121: aload_0
     122: getfield      #100                // Field onreturnMethod:Ljava/lang/String;
     125: invokestatic  #97                 // Method org/apache/dubbo/common/utils/StringUtils.isNotEmpty:(Ljava/lang/String;)Z
     128: ifeq          150
     131: aload_1
     132: aload_0
     133: aload_0
     134: invokevirtual #85                 // Method getOnreturn:()Ljava/lang/Object;
     137: invokevirtual #54                 // Method java/lang/Object.getClass:()Ljava/lang/Class;
     140: aload_0
     141: getfield      #100                // Field onreturnMethod:Ljava/lang/String;
     144: invokespecial #98                 // Method getMethodByName:(Ljava/lang/Class;Ljava/lang/String;)Ljava/lang/reflect/Method;
     147: invokevirtual #101                // Method org/apache/dubbo/rpc/model/AsyncMethodInfo.setOnreturnMethod:(Ljava/lang/reflect/Method;)V
     150: aload_0
     151: getfield      #102                // Field onthrowMethod:Ljava/lang/String;
     154: invokestatic  #97                 // Method org/apache/dubbo/common/utils/StringUtils.isNotEmpty:(Ljava/lang/String;)Z
     157: ifeq          179
     160: aload_1
     161: aload_0
     162: aload_0
     163: invokevirtual #86                 // Method getOnthrow:()Ljava/lang/Object;
     166: invokevirtual #54                 // Method java/lang/Object.getClass:()Ljava/lang/Class;
     169: aload_0
     170: getfield      #102                // Field onthrowMethod:Ljava/lang/String;
     173: invokespecial #98                 // Method getMethodByName:(Ljava/lang/Class;Ljava/lang/String;)Ljava/lang/reflect/Method;
     176: invokevirtual #103                // Method org/apache/dubbo/rpc/model/AsyncMethodInfo.setOnthrowMethod:(Ljava/lang/reflect/Method;)V
     179: goto          196
     182: astore_2
     183: new           #40                 // class java/lang/IllegalStateException
     186: dup
     187: aload_2
     188: invokevirtual #104                // Method java/lang/Exception.getMessage:()Ljava/lang/String;
     191: aload_2
     192: invokespecial #105                // Method java/lang/IllegalStateException."<init>":(Ljava/lang/String;Ljava/lang/Throwable;)V
     195: athrow
     196: aload_1
     197: areturn
    Exception table:
       from    to  target type
          92   179   182   Class java/lang/Exception

  private java.lang.reflect.Method getMethodByName(java.lang.Class<?>, java.lang.String);
    Code:
       0: aload_1
       1: aload_2
       2: invokestatic  #106                // Method org/apache/dubbo/common/utils/ReflectUtils.findMethodByMethodName:(Ljava/lang/Class;Ljava/lang/String;)Ljava/lang/reflect/Method;
       5: areturn
       6: astore_3
       7: new           #40                 // class java/lang/IllegalStateException
      10: dup
      11: aload_3
      12: invokespecial #107                // Method java/lang/IllegalStateException."<init>":(Ljava/lang/Throwable;)V
      15: athrow
    Exception table:
       from    to  target type
           0     5     6   Class java/lang/Exception

  protected void checkDefault();
    Code:
       0: aload_0
       1: invokespecial #108                // Method org/apache/dubbo/config/AbstractMethodConfig.checkDefault:()V
       4: aload_0
       5: invokevirtual #88                 // Method isReturn:()Ljava/lang/Boolean;
       8: ifnonnull     19
      11: aload_0
      12: iconst_1
      13: invokestatic  #6                  // Method java/lang/Boolean.valueOf:(Z)Ljava/lang/Boolean;
      16: invokevirtual #7                  // Method setReturn:(Ljava/lang/Boolean;)V
      19: aload_0
      20: invokevirtual #109                // Method getSent:()Ljava/lang/Boolean;
      23: ifnonnull     34
      26: aload_0
      27: iconst_1
      28: invokestatic  #6                  // Method java/lang/Boolean.valueOf:(Z)Ljava/lang/Boolean;
      31: invokevirtual #110                // Method setSent:(Ljava/lang/Boolean;)V
      34: return

  public java.lang.String getName();
    Code:
       0: aload_0
       1: getfield      #111                // Field name:Ljava/lang/String;
       4: areturn

  public void setName(java.lang.String);
    Code:
       0: aload_0
       1: aload_1
       2: putfield      #111                // Field name:Ljava/lang/String;
       5: return

  public java.lang.Integer getStat();
    Code:
       0: aload_0
       1: getfield      #112                // Field stat:Ljava/lang/Integer;
       4: areturn

  public void setStat(java.lang.Integer);
    Code:
       0: aload_0
       1: aload_1
       2: putfield      #112                // Field stat:Ljava/lang/Integer;
       5: return

  public java.lang.Boolean isRetry();
    Code:
       0: aload_0
       1: getfield      #113                // Field retry:Ljava/lang/Boolean;
       4: areturn

  public void setRetry(java.lang.Boolean);
    Code:
       0: aload_0
       1: aload_1
       2: putfield      #113                // Field retry:Ljava/lang/Boolean;
       5: return

  public java.lang.Boolean isReliable();
    Code:
       0: aload_0
       1: getfield      #114                // Field reliable:Ljava/lang/Boolean;
       4: areturn

  public void setReliable(java.lang.Boolean);
    Code:
       0: aload_0
       1: aload_1
       2: putfield      #114                // Field reliable:Ljava/lang/Boolean;
       5: return

  public java.lang.Integer getExecutes();
    Code:
       0: aload_0
       1: getfield      #115                // Field executes:Ljava/lang/Integer;
       4: areturn

  public void setExecutes(java.lang.Integer);
    Code:
       0: aload_0
       1: aload_1
       2: putfield      #115                // Field executes:Ljava/lang/Integer;
       5: return

  public java.lang.Boolean getDeprecated();
    Code:
       0: aload_0
       1: getfield      #116                // Field deprecated:Ljava/lang/Boolean;
       4: areturn

  public void setDeprecated(java.lang.Boolean);
    Code:
       0: aload_0
       1: aload_1
       2: putfield      #116                // Field deprecated:Ljava/lang/Boolean;
       5: return

  public java.util.List<org.apache.dubbo.config.ArgumentConfig> getArguments();
    Code:
       0: aload_0
       1: getfield      #117                // Field arguments:Ljava/util/List;
       4: areturn

  public void setArguments(java.util.List<? extends org.apache.dubbo.config.ArgumentConfig>);
    Code:
       0: aload_0
       1: aload_1
       2: putfield      #117                // Field arguments:Ljava/util/List;
       5: return

  public java.lang.Boolean getSticky();
    Code:
       0: aload_0
       1: getfield      #118                // Field sticky:Ljava/lang/Boolean;
       4: areturn

  public void setSticky(java.lang.Boolean);
    Code:
       0: aload_0
       1: aload_1
       2: putfield      #118                // Field sticky:Ljava/lang/Boolean;
       5: return

  public java.lang.Object getOnreturn();
    Code:
       0: aload_0
       1: getfield      #119                // Field onreturn:Ljava/lang/Object;
       4: areturn

  public void setOnreturn(java.lang.Object);
    Code:
       0: aload_0
       1: aload_1
       2: putfield      #119                // Field onreturn:Ljava/lang/Object;
       5: return

  public java.lang.String getOnreturnMethod();
    Code:
       0: aload_0
       1: getfield      #100                // Field onreturnMethod:Ljava/lang/String;
       4: areturn

  public void setOnreturnMethod(java.lang.String);
    Code:
       0: aload_0
       1: aload_1
       2: putfield      #100                // Field onreturnMethod:Ljava/lang/String;
       5: return

  public java.lang.Object getOnthrow();
    Code:
       0: aload_0
       1: getfield      #120                // Field onthrow:Ljava/lang/Object;
       4: areturn

  public void setOnthrow(java.lang.Object);
    Code:
       0: aload_0
       1: aload_1
       2: putfield      #120                // Field onthrow:Ljava/lang/Object;
       5: return

  public java.lang.String getOnthrowMethod();
    Code:
       0: aload_0
       1: getfield      #102                // Field onthrowMethod:Ljava/lang/String;
       4: areturn

  public void setOnthrowMethod(java.lang.String);
    Code:
       0: aload_0
       1: aload_1
       2: putfield      #102                // Field onthrowMethod:Ljava/lang/String;
       5: return

  public java.lang.Object getOninvoke();
    Code:
       0: aload_0
       1: getfield      #121                // Field oninvoke:Ljava/lang/Object;
       4: areturn

  public void setOninvoke(java.lang.Object);
    Code:
       0: aload_0
       1: aload_1
       2: putfield      #121                // Field oninvoke:Ljava/lang/Object;
       5: return

  public java.lang.String getOninvokeMethod();
    Code:
       0: aload_0
       1: getfield      #96                 // Field oninvokeMethod:Ljava/lang/String;
       4: areturn

  public void setOninvokeMethod(java.lang.String);
    Code:
       0: aload_0
       1: aload_1
       2: putfield      #96                 // Field oninvokeMethod:Ljava/lang/String;
       5: return

  public java.lang.Boolean isReturn();
    Code:
       0: aload_0
       1: getfield      #122                // Field isReturn:Ljava/lang/Boolean;
       4: areturn

  public void setReturn(java.lang.Boolean);
    Code:
       0: aload_0
       1: aload_1
       2: putfield      #122                // Field isReturn:Ljava/lang/Boolean;
       5: return

  public java.lang.String getService();
    Code:
       0: aload_0
       1: getfield      #123                // Field service:Ljava/lang/String;
       4: areturn

  public void setService(java.lang.String);
    Code:
       0: aload_0
       1: aload_1
       2: putfield      #123                // Field service:Ljava/lang/String;
       5: return

  public java.lang.String getServiceId();
    Code:
       0: aload_0
       1: getfield      #124                // Field serviceId:Ljava/lang/String;
       4: areturn

  public void setServiceId(java.lang.String);
    Code:
       0: aload_0
       1: aload_1
       2: putfield      #124                // Field serviceId:Ljava/lang/String;
       5: return

  public void setParentPrefix(java.lang.String);
    Code:
       0: aload_0
       1: aload_1
       2: putfield      #33                 // Field parentPrefix:Ljava/lang/String;
       5: return

  public java.lang.String getParentPrefix();
    Code:
       0: aload_0
       1: getfield      #33                 // Field parentPrefix:Ljava/lang/String;
       4: areturn

  public void addArgument(org.apache.dubbo.config.ArgumentConfig);
    Code:
       0: aload_0
       1: getfield      #117                // Field arguments:Ljava/util/List;
       4: ifnonnull     18
       7: aload_0
       8: new           #24                 // class java/util/ArrayList
      11: dup
      12: invokespecial #34                 // Method java/util/ArrayList."<init>":()V
      15: putfield      #117                // Field arguments:Ljava/util/List;
      18: aload_0
      19: getfield      #117                // Field arguments:Ljava/util/List;
      22: aload_1
      23: invokeinterface #29,  2           // InterfaceMethod java/util/List.add:(Ljava/lang/Object;)Z
      28: pop
      29: return

  private static boolean lambda$refreshArgument$0(java.lang.reflect.Method);
    Code:
       0: aload_0
       1: invokevirtual #125                // Method java/lang/reflect/Method.getDeclaringClass:()Ljava/lang/Class;
       4: ldc           #73                 // class java/lang/Object
       6: if_acmpeq     13
       9: iconst_1
      10: goto          14
      13: iconst_0
      14: ireturn
}
