Compiled from "MetricsConfig.java"
public class org.apache.dubbo.config.MetricsConfig extends org.apache.dubbo.config.AbstractConfig {
  private static final long serialVersionUID;

  private java.lang.String protocol;

  private java.lang.Boolean enableJvm;

  private java.lang.Boolean enableThreadpool;

  private java.lang.Boolean enableRegistry;

  private java.lang.Boolean enableMetadata;

  private java.lang.Boolean exportMetricsService;

  private java.lang.String port;

  private org.apache.dubbo.config.nested.PrometheusConfig prometheus;

  private org.apache.dubbo.config.nested.AggregationConfig aggregation;

  private org.apache.dubbo.config.nested.HistogramConfig histogram;

  private java.lang.String exportServiceProtocol;

  private java.lang.Integer exportServicePort;

  private java.lang.Boolean useGlobalRegistry;

  public org.apache.dubbo.config.MetricsConfig();
    Code:
       0: aload_0
       1: invokespecial #1                  // Method org/apache/dubbo/config/AbstractConfig."<init>":()V
       4: return

  public org.apache.dubbo.config.MetricsConfig(org.apache.dubbo.rpc.model.ApplicationModel);
    Code:
       0: aload_0
       1: aload_1
       2: invokespecial #2                  // Method org/apache/dubbo/config/AbstractConfig."<init>":(Lorg/apache/dubbo/rpc/model/ScopeModel;)V
       5: return

  public org.apache.dubbo.common.URL toUrl();
    Code:
       0: new           #3                  // class java/util/HashMap
       3: dup
       4: invokespecial #4                  // Method java/util/HashMap."<init>":()V
       7: astore_1
       8: aload_1
       9: aload_0
      10: invokestatic  #5                  // Method appendParameters:(Ljava/util/Map;Ljava/lang/Object;)V
      13: ldc           #6                  // String localhost
      15: aload_1
      16: invokestatic  #7                  // Method org/apache/dubbo/common/utils/UrlUtils.parseURL:(Ljava/lang/String;Ljava/util/Map;)Lorg/apache/dubbo/common/URL;
      19: astore_2
      20: aload_2
      21: aload_0
      22: invokevirtual #8                  // Method getScopeModel:()Lorg/apache/dubbo/rpc/model/ScopeModel;
      25: invokevirtual #9                  // Method org/apache/dubbo/common/URL.setScopeModel:(Lorg/apache/dubbo/rpc/model/ScopeModel;)Lorg/apache/dubbo/common/URL;
      28: astore_2
      29: aload_2
      30: areturn

  public java.lang.String getProtocol();
    Code:
       0: aload_0
       1: getfield      #10                 // Field protocol:Ljava/lang/String;
       4: areturn

  public void setProtocol(java.lang.String);
    Code:
       0: aload_0
       1: aload_1
       2: putfield      #10                 // Field protocol:Ljava/lang/String;
       5: return

  public java.lang.Boolean getEnableJvm();
    Code:
       0: aload_0
       1: getfield      #11                 // Field enableJvm:Ljava/lang/Boolean;
       4: areturn

  public void setEnableJvm(java.lang.Boolean);
    Code:
       0: aload_0
       1: aload_1
       2: putfield      #11                 // Field enableJvm:Ljava/lang/Boolean;
       5: return

  public java.lang.Boolean getEnableRegistry();
    Code:
       0: aload_0
       1: getfield      #12                 // Field enableRegistry:Ljava/lang/Boolean;
       4: areturn

  public void setEnableRegistry(java.lang.Boolean);
    Code:
       0: aload_0
       1: aload_1
       2: putfield      #12                 // Field enableRegistry:Ljava/lang/Boolean;
       5: return

  public java.lang.String getPort();
    Code:
       0: aload_0
       1: getfield      #13                 // Field port:Ljava/lang/String;
       4: areturn

  public void setPort(java.lang.String);
    Code:
       0: aload_0
       1: aload_1
       2: putfield      #13                 // Field port:Ljava/lang/String;
       5: return

  public org.apache.dubbo.config.nested.PrometheusConfig getPrometheus();
    Code:
       0: aload_0
       1: getfield      #14                 // Field prometheus:Lorg/apache/dubbo/config/nested/PrometheusConfig;
       4: areturn

  public void setPrometheus(org.apache.dubbo.config.nested.PrometheusConfig);
    Code:
       0: aload_0
       1: aload_1
       2: putfield      #14                 // Field prometheus:Lorg/apache/dubbo/config/nested/PrometheusConfig;
       5: return

  public org.apache.dubbo.config.nested.AggregationConfig getAggregation();
    Code:
       0: aload_0
       1: getfield      #15                 // Field aggregation:Lorg/apache/dubbo/config/nested/AggregationConfig;
       4: areturn

  public void setAggregation(org.apache.dubbo.config.nested.AggregationConfig);
    Code:
       0: aload_0
       1: aload_1
       2: putfield      #15                 // Field aggregation:Lorg/apache/dubbo/config/nested/AggregationConfig;
       5: return

  public org.apache.dubbo.config.nested.HistogramConfig getHistogram();
    Code:
       0: aload_0
       1: getfield      #16                 // Field histogram:Lorg/apache/dubbo/config/nested/HistogramConfig;
       4: areturn

  public void setHistogram(org.apache.dubbo.config.nested.HistogramConfig);
    Code:
       0: aload_0
       1: aload_1
       2: putfield      #16                 // Field histogram:Lorg/apache/dubbo/config/nested/HistogramConfig;
       5: return

  public java.lang.String getExportServiceProtocol();
    Code:
       0: aload_0
       1: getfield      #17                 // Field exportServiceProtocol:Ljava/lang/String;
       4: areturn

  public void setExportServiceProtocol(java.lang.String);
    Code:
       0: aload_0
       1: aload_1
       2: putfield      #17                 // Field exportServiceProtocol:Ljava/lang/String;
       5: return

  public java.lang.Integer getExportServicePort();
    Code:
       0: aload_0
       1: getfield      #18                 // Field exportServicePort:Ljava/lang/Integer;
       4: areturn

  public void setExportServicePort(java.lang.Integer);
    Code:
       0: aload_0
       1: aload_1
       2: putfield      #18                 // Field exportServicePort:Ljava/lang/Integer;
       5: return

  public java.lang.Boolean getEnableMetadata();
    Code:
       0: aload_0
       1: getfield      #19                 // Field enableMetadata:Ljava/lang/Boolean;
       4: areturn

  public void setEnableMetadata(java.lang.Boolean);
    Code:
       0: aload_0
       1: aload_1
       2: putfield      #19                 // Field enableMetadata:Ljava/lang/Boolean;
       5: return

  public java.lang.Boolean getExportMetricsService();
    Code:
       0: aload_0
       1: getfield      #20                 // Field exportMetricsService:Ljava/lang/Boolean;
       4: areturn

  public void setExportMetricsService(java.lang.Boolean);
    Code:
       0: aload_0
       1: aload_1
       2: putfield      #20                 // Field exportMetricsService:Ljava/lang/Boolean;
       5: return

  public java.lang.Boolean getEnableThreadpool();
    Code:
       0: aload_0
       1: getfield      #21                 // Field enableThreadpool:Ljava/lang/Boolean;
       4: areturn

  public void setEnableThreadpool(java.lang.Boolean);
    Code:
       0: aload_0
       1: aload_1
       2: putfield      #21                 // Field enableThreadpool:Ljava/lang/Boolean;
       5: return

  public java.lang.Boolean getUseGlobalRegistry();
    Code:
       0: aload_0
       1: getfield      #22                 // Field useGlobalRegistry:Ljava/lang/Boolean;
       4: areturn

  public void setUseGlobalRegistry(java.lang.Boolean);
    Code:
       0: aload_0
       1: aload_1
       2: putfield      #22                 // Field useGlobalRegistry:Ljava/lang/Boolean;
       5: return
}
