Compiled from "ModuleConfig.java"
public class org.apache.dubbo.config.ModuleConfig extends org.apache.dubbo.config.AbstractConfig {
  private static final long serialVersionUID;

  private java.lang.String name;

  private java.lang.String version;

  private java.lang.String owner;

  private java.lang.String organization;

  private java.util.List<org.apache.dubbo.config.RegistryConfig> registries;

  private org.apache.dubbo.config.MonitorConfig monitor;

  private java.lang.Boolean background;

  private java.lang.Boolean referAsync;

  private java.lang.Integer referThreadNum;

  private java.lang.Boolean exportAsync;

  private java.lang.Integer exportThreadNum;

  public org.apache.dubbo.config.ModuleConfig();
    Code:
       0: aload_0
       1: invokespecial #1                  // Method org/apache/dubbo/config/AbstractConfig."<init>":()V
       4: return

  public org.apache.dubbo.config.ModuleConfig(org.apache.dubbo.rpc.model.ModuleModel);
    Code:
       0: aload_0
       1: aload_1
       2: invokespecial #2                  // Method org/apache/dubbo/config/AbstractConfig."<init>":(Lorg/apache/dubbo/rpc/model/ScopeModel;)V
       5: return

  public org.apache.dubbo.config.ModuleConfig(java.lang.String);
    Code:
       0: aload_0
       1: invokespecial #3                  // Method "<init>":()V
       4: aload_0
       5: aload_1
       6: invokevirtual #4                  // Method setName:(Ljava/lang/String;)V
       9: return

  public org.apache.dubbo.config.ModuleConfig(org.apache.dubbo.rpc.model.ModuleModel, java.lang.String);
    Code:
       0: aload_0
       1: aload_1
       2: invokespecial #5                  // Method "<init>":(Lorg/apache/dubbo/rpc/model/ModuleModel;)V
       5: aload_0
       6: aload_2
       7: invokevirtual #4                  // Method setName:(Ljava/lang/String;)V
      10: return

  protected void checkDefault();
    Code:
       0: aload_0
       1: invokespecial #6                  // Method org/apache/dubbo/config/AbstractConfig.checkDefault:()V
       4: aload_0
       5: getfield      #7                  // Field background:Ljava/lang/Boolean;
       8: ifnonnull     19
      11: aload_0
      12: iconst_0
      13: invokestatic  #8                  // Method java/lang/Boolean.valueOf:(Z)Ljava/lang/Boolean;
      16: putfield      #7                  // Field background:Ljava/lang/Boolean;
      19: return

  protected void checkScopeModel(org.apache.dubbo.rpc.model.ScopeModel);
    Code:
       0: aload_1
       1: ifnonnull     14
       4: new           #9                  // class java/lang/IllegalArgumentException
       7: dup
       8: ldc           #10                 // String scopeModel cannot be null
      10: invokespecial #11                 // Method java/lang/IllegalArgumentException."<init>":(Ljava/lang/String;)V
      13: athrow
      14: aload_1
      15: instanceof    #12                 // class org/apache/dubbo/rpc/model/ModuleModel
      18: ifne          48
      21: new           #9                  // class java/lang/IllegalArgumentException
      24: dup
      25: new           #13                 // class java/lang/StringBuilder
      28: dup
      29: invokespecial #14                 // Method java/lang/StringBuilder."<init>":()V
      32: ldc           #15                 // String Invalid scope model, expect to be a ModuleModel but got:
      34: invokevirtual #16                 // Method java/lang/StringBuilder.append:(Ljava/lang/String;)Ljava/lang/StringBuilder;
      37: aload_1
      38: invokevirtual #17                 // Method java/lang/StringBuilder.append:(Ljava/lang/Object;)Ljava/lang/StringBuilder;
      41: invokevirtual #18                 // Method java/lang/StringBuilder.toString:()Ljava/lang/String;
      44: invokespecial #11                 // Method java/lang/IllegalArgumentException."<init>":(Ljava/lang/String;)V
      47: athrow
      48: return

  public org.apache.dubbo.rpc.model.ModuleModel getScopeModel();
    Code:
       0: aload_0
       1: invokespecial #19                 // Method org/apache/dubbo/config/AbstractConfig.getScopeModel:()Lorg/apache/dubbo/rpc/model/ScopeModel;
       4: checkcast     #12                 // class org/apache/dubbo/rpc/model/ModuleModel
       7: areturn

  protected org.apache.dubbo.rpc.model.ScopeModel getDefaultModel();
    Code:
       0: invokestatic  #20                 // Method org/apache/dubbo/rpc/model/ApplicationModel.defaultModel:()Lorg/apache/dubbo/rpc/model/ApplicationModel;
       3: invokevirtual #21                 // Method org/apache/dubbo/rpc/model/ApplicationModel.getDefaultModule:()Lorg/apache/dubbo/rpc/model/ModuleModel;
       6: areturn

  public java.lang.String getName();
    Code:
       0: aload_0
       1: getfield      #22                 // Field name:Ljava/lang/String;
       4: areturn

  public void setName(java.lang.String);
    Code:
       0: aload_0
       1: aload_1
       2: putfield      #22                 // Field name:Ljava/lang/String;
       5: return

  public java.lang.String getVersion();
    Code:
       0: aload_0
       1: getfield      #23                 // Field version:Ljava/lang/String;
       4: areturn

  public void setVersion(java.lang.String);
    Code:
       0: aload_0
       1: aload_1
       2: putfield      #23                 // Field version:Ljava/lang/String;
       5: return

  public java.lang.String getOwner();
    Code:
       0: aload_0
       1: getfield      #24                 // Field owner:Ljava/lang/String;
       4: areturn

  public void setOwner(java.lang.String);
    Code:
       0: aload_0
       1: aload_1
       2: putfield      #24                 // Field owner:Ljava/lang/String;
       5: return

  public java.lang.String getOrganization();
    Code:
       0: aload_0
       1: getfield      #25                 // Field organization:Ljava/lang/String;
       4: areturn

  public void setOrganization(java.lang.String);
    Code:
       0: aload_0
       1: aload_1
       2: putfield      #25                 // Field organization:Ljava/lang/String;
       5: return

  public org.apache.dubbo.config.RegistryConfig getRegistry();
    Code:
       0: aload_0
       1: getfield      #26                 // Field registries:Ljava/util/List;
       4: invokestatic  #27                 // Method org/apache/dubbo/common/utils/CollectionUtils.isEmpty:(Ljava/util/Collection;)Z
       7: ifeq          14
      10: aconst_null
      11: goto          27
      14: aload_0
      15: getfield      #26                 // Field registries:Ljava/util/List;
      18: iconst_0
      19: invokeinterface #28,  2           // InterfaceMethod java/util/List.get:(I)Ljava/lang/Object;
      24: checkcast     #29                 // class org/apache/dubbo/config/RegistryConfig
      27: areturn

  public void setRegistry(org.apache.dubbo.config.RegistryConfig);
    Code:
       0: new           #30                 // class java/util/ArrayList
       3: dup
       4: iconst_1
       5: invokespecial #31                 // Method java/util/ArrayList."<init>":(I)V
       8: astore_2
       9: aload_2
      10: aload_1
      11: invokeinterface #32,  2           // InterfaceMethod java/util/List.add:(Ljava/lang/Object;)Z
      16: pop
      17: aload_0
      18: aload_2
      19: putfield      #26                 // Field registries:Ljava/util/List;
      22: return

  public java.util.List<org.apache.dubbo.config.RegistryConfig> getRegistries();
    Code:
       0: aload_0
       1: getfield      #26                 // Field registries:Ljava/util/List;
       4: areturn

  public void setRegistries(java.util.List<? extends org.apache.dubbo.config.RegistryConfig>);
    Code:
       0: aload_0
       1: aload_1
       2: putfield      #26                 // Field registries:Ljava/util/List;
       5: return

  public org.apache.dubbo.config.MonitorConfig getMonitor();
    Code:
       0: aload_0
       1: getfield      #33                 // Field monitor:Lorg/apache/dubbo/config/MonitorConfig;
       4: areturn

  public void setMonitor(org.apache.dubbo.config.MonitorConfig);
    Code:
       0: aload_0
       1: aload_1
       2: putfield      #33                 // Field monitor:Lorg/apache/dubbo/config/MonitorConfig;
       5: return

  public void setMonitor(java.lang.String);
    Code:
       0: aload_0
       1: new           #34                 // class org/apache/dubbo/config/MonitorConfig
       4: dup
       5: aload_1
       6: invokespecial #35                 // Method org/apache/dubbo/config/MonitorConfig."<init>":(Ljava/lang/String;)V
       9: putfield      #33                 // Field monitor:Lorg/apache/dubbo/config/MonitorConfig;
      12: return

  public java.lang.Boolean getBackground();
    Code:
       0: aload_0
       1: getfield      #7                  // Field background:Ljava/lang/Boolean;
       4: areturn

  public void setBackground(java.lang.Boolean);
    Code:
       0: aload_0
       1: aload_1
       2: putfield      #7                  // Field background:Ljava/lang/Boolean;
       5: return

  public java.lang.Integer getReferThreadNum();
    Code:
       0: aload_0
       1: getfield      #36                 // Field referThreadNum:Ljava/lang/Integer;
       4: areturn

  public void setReferThreadNum(java.lang.Integer);
    Code:
       0: aload_0
       1: aload_1
       2: putfield      #36                 // Field referThreadNum:Ljava/lang/Integer;
       5: return

  public java.lang.Integer getExportThreadNum();
    Code:
       0: aload_0
       1: getfield      #37                 // Field exportThreadNum:Ljava/lang/Integer;
       4: areturn

  public void setExportThreadNum(java.lang.Integer);
    Code:
       0: aload_0
       1: aload_1
       2: putfield      #37                 // Field exportThreadNum:Ljava/lang/Integer;
       5: return

  public java.lang.Boolean getReferAsync();
    Code:
       0: aload_0
       1: getfield      #38                 // Field referAsync:Ljava/lang/Boolean;
       4: areturn

  public void setReferAsync(java.lang.Boolean);
    Code:
       0: aload_0
       1: aload_1
       2: putfield      #38                 // Field referAsync:Ljava/lang/Boolean;
       5: return

  public java.lang.Boolean getExportAsync();
    Code:
       0: aload_0
       1: getfield      #39                 // Field exportAsync:Ljava/lang/Boolean;
       4: areturn

  public void setExportAsync(java.lang.Boolean);
    Code:
       0: aload_0
       1: aload_1
       2: putfield      #39                 // Field exportAsync:Ljava/lang/Boolean;
       5: return

  public org.apache.dubbo.rpc.model.ScopeModel getScopeModel();
    Code:
       0: aload_0
       1: invokevirtual #40                 // Method getScopeModel:()Lorg/apache/dubbo/rpc/model/ModuleModel;
       4: areturn
}
