Compiled from "MonitorConfig.java"
public class org.apache.dubbo.config.MonitorConfig extends org.apache.dubbo.config.AbstractConfig {
  private static final long serialVersionUID;

  private java.lang.String protocol;

  private java.lang.String address;

  private java.lang.String username;

  private java.lang.String password;

  private java.lang.String group;

  private java.lang.String version;

  private java.lang.String interval;

  private java.util.Map<java.lang.String, java.lang.String> parameters;

  public org.apache.dubbo.config.MonitorConfig();
    Code:
       0: aload_0
       1: invokespecial #1                  // Method org/apache/dubbo/config/AbstractConfig."<init>":()V
       4: return

  public org.apache.dubbo.config.MonitorConfig(org.apache.dubbo.rpc.model.ApplicationModel);
    Code:
       0: aload_0
       1: aload_1
       2: invokespecial #2                  // Method org/apache/dubbo/config/AbstractConfig."<init>":(Lorg/apache/dubbo/rpc/model/ScopeModel;)V
       5: return

  public org.apache.dubbo.config.MonitorConfig(java.lang.String);
    Code:
       0: aload_0
       1: invokespecial #1                  // Method org/apache/dubbo/config/AbstractConfig."<init>":()V
       4: aload_0
       5: aload_1
       6: putfield      #3                  // Field address:Ljava/lang/String;
       9: return

  public org.apache.dubbo.config.MonitorConfig(org.apache.dubbo.rpc.model.ApplicationModel, java.lang.String);
    Code:
       0: aload_0
       1: aload_1
       2: invokespecial #2                  // Method org/apache/dubbo/config/AbstractConfig."<init>":(Lorg/apache/dubbo/rpc/model/ScopeModel;)V
       5: aload_0
       6: aload_2
       7: putfield      #3                  // Field address:Ljava/lang/String;
      10: return

  public java.lang.String getAddress();
    Code:
       0: aload_0
       1: getfield      #3                  // Field address:Ljava/lang/String;
       4: areturn

  public void setAddress(java.lang.String);
    Code:
       0: aload_0
       1: aload_1
       2: putfield      #3                  // Field address:Ljava/lang/String;
       5: return

  public java.lang.String getProtocol();
    Code:
       0: aload_0
       1: getfield      #4                  // Field protocol:Ljava/lang/String;
       4: areturn

  public void setProtocol(java.lang.String);
    Code:
       0: aload_0
       1: aload_1
       2: putfield      #4                  // Field protocol:Ljava/lang/String;
       5: return

  public java.lang.String getUsername();
    Code:
       0: aload_0
       1: getfield      #5                  // Field username:Ljava/lang/String;
       4: areturn

  public void setUsername(java.lang.String);
    Code:
       0: aload_0
       1: aload_1
       2: putfield      #5                  // Field username:Ljava/lang/String;
       5: return

  public java.lang.String getPassword();
    Code:
       0: aload_0
       1: getfield      #6                  // Field password:Ljava/lang/String;
       4: areturn

  public void setPassword(java.lang.String);
    Code:
       0: aload_0
       1: aload_1
       2: putfield      #6                  // Field password:Ljava/lang/String;
       5: return

  public java.lang.String getGroup();
    Code:
       0: aload_0
       1: getfield      #7                  // Field group:Ljava/lang/String;
       4: areturn

  public void setGroup(java.lang.String);
    Code:
       0: aload_0
       1: aload_1
       2: putfield      #7                  // Field group:Ljava/lang/String;
       5: return

  public java.lang.String getVersion();
    Code:
       0: aload_0
       1: getfield      #8                  // Field version:Ljava/lang/String;
       4: areturn

  public void setVersion(java.lang.String);
    Code:
       0: aload_0
       1: aload_1
       2: putfield      #8                  // Field version:Ljava/lang/String;
       5: return

  public java.util.Map<java.lang.String, java.lang.String> getParameters();
    Code:
       0: aload_0
       1: getfield      #9                  // Field parameters:Ljava/util/Map;
       4: areturn

  public void setParameters(java.util.Map<java.lang.String, java.lang.String>);
    Code:
       0: aload_0
       1: aload_1
       2: putfield      #9                  // Field parameters:Ljava/util/Map;
       5: return

  public java.lang.String getInterval();
    Code:
       0: aload_0
       1: getfield      #10                 // Field interval:Ljava/lang/String;
       4: areturn

  public void setInterval(java.lang.String);
    Code:
       0: aload_0
       1: aload_1
       2: putfield      #10                 // Field interval:Ljava/lang/String;
       5: return

  public boolean isValid();
    Code:
       0: aload_0
       1: getfield      #3                  // Field address:Ljava/lang/String;
       4: invokestatic  #11                 // Method org/apache/dubbo/common/utils/StringUtils.isNotEmpty:(Ljava/lang/String;)Z
       7: ifne          22
      10: ldc           #13                 // String registry
      12: aload_0
      13: getfield      #4                  // Field protocol:Ljava/lang/String;
      16: invokevirtual #14                 // Method java/lang/String.equals:(Ljava/lang/Object;)Z
      19: ifeq          26
      22: iconst_1
      23: goto          27
      26: iconst_0
      27: ireturn
}
