Compiled from "ProviderConfig.java"
public class org.apache.dubbo.config.ProviderConfig extends org.apache.dubbo.config.AbstractServiceConfig {
  private static final long serialVersionUID;

  private java.lang.String host;

  private java.lang.Integer port;

  private java.lang.String contextpath;

  private java.lang.String threadpool;

  private java.lang.String threadname;

  private java.lang.Integer threads;

  private java.lang.Integer iothreads;

  private java.lang.Integer alive;

  private java.lang.Integer queues;

  private java.lang.Integer accepts;

  private java.lang.String codec;

  private java.lang.String charset;

  private java.lang.Integer payload;

  private java.lang.Integer buffer;

  private java.lang.String transporter;

  private java.lang.String exchanger;

  private java.lang.String dispatcher;

  private java.lang.String networker;

  private java.lang.String server;

  private java.lang.String client;

  private java.lang.String telnet;

  private java.lang.String prompt;

  private java.lang.String status;

  private java.lang.Integer wait;

  private java.lang.Integer exportThreadNum;

  private java.lang.Boolean exportBackground;

  public org.apache.dubbo.config.ProviderConfig();
    Code:
       0: aload_0
       1: invokespecial #1                  // Method org/apache/dubbo/config/AbstractServiceConfig."<init>":()V
       4: return

  public org.apache.dubbo.config.ProviderConfig(org.apache.dubbo.rpc.model.ModuleModel);
    Code:
       0: aload_0
       1: aload_1
       2: invokespecial #2                  // Method org/apache/dubbo/config/AbstractServiceConfig."<init>":(Lorg/apache/dubbo/rpc/model/ModuleModel;)V
       5: return

  public void setProtocol(java.lang.String);
    Code:
       0: aload_0
       1: new           #3                  // class java/util/ArrayList
       4: dup
       5: iconst_1
       6: anewarray     #4                  // class org/apache/dubbo/config/ProtocolConfig
       9: dup
      10: iconst_0
      11: new           #4                  // class org/apache/dubbo/config/ProtocolConfig
      14: dup
      15: aload_1
      16: invokespecial #5                  // Method org/apache/dubbo/config/ProtocolConfig."<init>":(Ljava/lang/String;)V
      19: aastore
      20: invokestatic  #6                  // Method java/util/Arrays.asList:([Ljava/lang/Object;)Ljava/util/List;
      23: invokespecial #7                  // Method java/util/ArrayList."<init>":(Ljava/util/Collection;)V
      26: putfield      #8                  // Field protocols:Ljava/util/List;
      29: return

  public java.lang.String getHost();
    Code:
       0: aload_0
       1: getfield      #9                  // Field host:Ljava/lang/String;
       4: areturn

  public void setHost(java.lang.String);
    Code:
       0: aload_0
       1: aload_1
       2: putfield      #9                  // Field host:Ljava/lang/String;
       5: return

  public java.lang.Integer getPort();
    Code:
       0: aload_0
       1: getfield      #10                 // Field port:Ljava/lang/Integer;
       4: areturn

  public void setPort(java.lang.Integer);
    Code:
       0: aload_0
       1: aload_1
       2: putfield      #10                 // Field port:Ljava/lang/Integer;
       5: return

  public java.lang.String getPath();
    Code:
       0: aload_0
       1: invokevirtual #11                 // Method getContextpath:()Ljava/lang/String;
       4: areturn

  public void setPath(java.lang.String);
    Code:
       0: aload_0
       1: aload_1
       2: invokevirtual #12                 // Method setContextpath:(Ljava/lang/String;)V
       5: return

  public java.lang.String getContextpath();
    Code:
       0: aload_0
       1: getfield      #13                 // Field contextpath:Ljava/lang/String;
       4: areturn

  public void setContextpath(java.lang.String);
    Code:
       0: aload_0
       1: aload_1
       2: putfield      #13                 // Field contextpath:Ljava/lang/String;
       5: return

  public java.lang.String getThreadpool();
    Code:
       0: aload_0
       1: getfield      #14                 // Field threadpool:Ljava/lang/String;
       4: areturn

  public void setThreadpool(java.lang.String);
    Code:
       0: aload_0
       1: aload_1
       2: putfield      #14                 // Field threadpool:Ljava/lang/String;
       5: return

  public java.lang.String getThreadname();
    Code:
       0: aload_0
       1: getfield      #15                 // Field threadname:Ljava/lang/String;
       4: areturn

  public void setThreadname(java.lang.String);
    Code:
       0: aload_0
       1: aload_1
       2: putfield      #15                 // Field threadname:Ljava/lang/String;
       5: return

  public java.lang.Integer getThreads();
    Code:
       0: aload_0
       1: getfield      #16                 // Field threads:Ljava/lang/Integer;
       4: areturn

  public void setThreads(java.lang.Integer);
    Code:
       0: aload_0
       1: aload_1
       2: putfield      #16                 // Field threads:Ljava/lang/Integer;
       5: return

  public java.lang.Integer getIothreads();
    Code:
       0: aload_0
       1: getfield      #17                 // Field iothreads:Ljava/lang/Integer;
       4: areturn

  public void setIothreads(java.lang.Integer);
    Code:
       0: aload_0
       1: aload_1
       2: putfield      #17                 // Field iothreads:Ljava/lang/Integer;
       5: return

  public java.lang.Integer getAlive();
    Code:
       0: aload_0
       1: getfield      #18                 // Field alive:Ljava/lang/Integer;
       4: areturn

  public void setAlive(java.lang.Integer);
    Code:
       0: aload_0
       1: aload_1
       2: putfield      #18                 // Field alive:Ljava/lang/Integer;
       5: return

  public java.lang.Integer getQueues();
    Code:
       0: aload_0
       1: getfield      #19                 // Field queues:Ljava/lang/Integer;
       4: areturn

  public void setQueues(java.lang.Integer);
    Code:
       0: aload_0
       1: aload_1
       2: putfield      #19                 // Field queues:Ljava/lang/Integer;
       5: return

  public java.lang.Integer getAccepts();
    Code:
       0: aload_0
       1: getfield      #20                 // Field accepts:Ljava/lang/Integer;
       4: areturn

  public void setAccepts(java.lang.Integer);
    Code:
       0: aload_0
       1: aload_1
       2: putfield      #20                 // Field accepts:Ljava/lang/Integer;
       5: return

  public java.lang.String getCodec();
    Code:
       0: aload_0
       1: getfield      #21                 // Field codec:Ljava/lang/String;
       4: areturn

  public void setCodec(java.lang.String);
    Code:
       0: aload_0
       1: aload_1
       2: putfield      #21                 // Field codec:Ljava/lang/String;
       5: return

  public java.lang.String getCharset();
    Code:
       0: aload_0
       1: getfield      #22                 // Field charset:Ljava/lang/String;
       4: areturn

  public void setCharset(java.lang.String);
    Code:
       0: aload_0
       1: aload_1
       2: putfield      #22                 // Field charset:Ljava/lang/String;
       5: return

  public java.lang.Integer getPayload();
    Code:
       0: aload_0
       1: getfield      #23                 // Field payload:Ljava/lang/Integer;
       4: areturn

  public void setPayload(java.lang.Integer);
    Code:
       0: aload_0
       1: aload_1
       2: putfield      #23                 // Field payload:Ljava/lang/Integer;
       5: return

  public java.lang.Integer getBuffer();
    Code:
       0: aload_0
       1: getfield      #24                 // Field buffer:Ljava/lang/Integer;
       4: areturn

  public void setBuffer(java.lang.Integer);
    Code:
       0: aload_0
       1: aload_1
       2: putfield      #24                 // Field buffer:Ljava/lang/Integer;
       5: return

  public java.lang.String getServer();
    Code:
       0: aload_0
       1: getfield      #25                 // Field server:Ljava/lang/String;
       4: areturn

  public void setServer(java.lang.String);
    Code:
       0: aload_0
       1: aload_1
       2: putfield      #25                 // Field server:Ljava/lang/String;
       5: return

  public java.lang.String getClient();
    Code:
       0: aload_0
       1: getfield      #26                 // Field client:Ljava/lang/String;
       4: areturn

  public void setClient(java.lang.String);
    Code:
       0: aload_0
       1: aload_1
       2: putfield      #26                 // Field client:Ljava/lang/String;
       5: return

  public java.lang.String getTelnet();
    Code:
       0: aload_0
       1: getfield      #27                 // Field telnet:Ljava/lang/String;
       4: areturn

  public void setTelnet(java.lang.String);
    Code:
       0: aload_0
       1: aload_1
       2: putfield      #27                 // Field telnet:Ljava/lang/String;
       5: return

  public java.lang.String getPrompt();
    Code:
       0: aload_0
       1: getfield      #28                 // Field prompt:Ljava/lang/String;
       4: areturn

  public void setPrompt(java.lang.String);
    Code:
       0: aload_0
       1: aload_1
       2: putfield      #28                 // Field prompt:Ljava/lang/String;
       5: return

  public java.lang.String getStatus();
    Code:
       0: aload_0
       1: getfield      #29                 // Field status:Ljava/lang/String;
       4: areturn

  public void setStatus(java.lang.String);
    Code:
       0: aload_0
       1: aload_1
       2: putfield      #29                 // Field status:Ljava/lang/String;
       5: return

  public java.lang.String getTransporter();
    Code:
       0: aload_0
       1: getfield      #30                 // Field transporter:Ljava/lang/String;
       4: areturn

  public void setTransporter(java.lang.String);
    Code:
       0: aload_0
       1: aload_1
       2: putfield      #30                 // Field transporter:Ljava/lang/String;
       5: return

  public java.lang.String getExchanger();
    Code:
       0: aload_0
       1: getfield      #31                 // Field exchanger:Ljava/lang/String;
       4: areturn

  public void setExchanger(java.lang.String);
    Code:
       0: aload_0
       1: aload_1
       2: putfield      #31                 // Field exchanger:Ljava/lang/String;
       5: return

  public java.lang.String getDispather();
    Code:
       0: aload_0
       1: invokevirtual #32                 // Method getDispatcher:()Ljava/lang/String;
       4: areturn

  public void setDispather(java.lang.String);
    Code:
       0: aload_0
       1: aload_1
       2: invokevirtual #33                 // Method setDispatcher:(Ljava/lang/String;)V
       5: return

  public java.lang.String getDispatcher();
    Code:
       0: aload_0
       1: getfield      #34                 // Field dispatcher:Ljava/lang/String;
       4: areturn

  public void setDispatcher(java.lang.String);
    Code:
       0: aload_0
       1: aload_1
       2: putfield      #34                 // Field dispatcher:Ljava/lang/String;
       5: return

  public java.lang.String getNetworker();
    Code:
       0: aload_0
       1: getfield      #35                 // Field networker:Ljava/lang/String;
       4: areturn

  public void setNetworker(java.lang.String);
    Code:
       0: aload_0
       1: aload_1
       2: putfield      #35                 // Field networker:Ljava/lang/String;
       5: return

  public java.lang.Integer getWait();
    Code:
       0: aload_0
       1: getfield      #36                 // Field wait:Ljava/lang/Integer;
       4: areturn

  public void setWait(java.lang.Integer);
    Code:
       0: aload_0
       1: aload_1
       2: putfield      #36                 // Field wait:Ljava/lang/Integer;
       5: return

  public java.lang.Integer getExportThreadNum();
    Code:
       0: aload_0
       1: getfield      #37                 // Field exportThreadNum:Ljava/lang/Integer;
       4: areturn

  public void setExportThreadNum(java.lang.Integer);
    Code:
       0: aload_0
       1: aload_1
       2: putfield      #37                 // Field exportThreadNum:Ljava/lang/Integer;
       5: return

  public java.lang.Boolean getExportBackground();
    Code:
       0: aload_0
       1: getfield      #38                 // Field exportBackground:Ljava/lang/Boolean;
       4: areturn

  public void setExportBackground(java.lang.Boolean);
    Code:
       0: aload_0
       1: aload_1
       2: putfield      #38                 // Field exportBackground:Ljava/lang/Boolean;
       5: return
}
