Compiled from "ReferenceConfig.java"
public class org.apache.dubbo.config.ReferenceConfig<T> extends org.apache.dubbo.config.ReferenceConfigBase<T> {
  public static final org.apache.dubbo.common.logger.ErrorTypeAwareLogger logger;

  private org.apache.dubbo.rpc.Protocol protocolSPI;

  private org.apache.dubbo.rpc.ProxyFactory proxyFactory;

  private org.apache.dubbo.rpc.model.ConsumerModel consumerModel;

  private volatile transient T ref;

  private volatile transient org.apache.dubbo.rpc.Invoker<?> invoker;

  private volatile transient boolean initialized;

  private volatile transient boolean destroyed;

  private java.lang.String services;

  public org.apache.dubbo.config.ReferenceConfig();
    Code:
       0: aload_0
       1: invokespecial #8                  // Method org/apache/dubbo/config/ReferenceConfigBase."<init>":()V
       4: return

  public org.apache.dubbo.config.ReferenceConfig(org.apache.dubbo.rpc.model.ModuleModel);
    Code:
       0: aload_0
       1: aload_1
       2: invokespecial #9                  // Method org/apache/dubbo/config/ReferenceConfigBase."<init>":(Lorg/apache/dubbo/rpc/model/ModuleModel;)V
       5: return

  public org.apache.dubbo.config.ReferenceConfig(org.apache.dubbo.config.annotation.Reference);
    Code:
       0: aload_0
       1: aload_1
       2: invokespecial #10                 // Method org/apache/dubbo/config/ReferenceConfigBase."<init>":(Lorg/apache/dubbo/config/annotation/Reference;)V
       5: return

  public org.apache.dubbo.config.ReferenceConfig(org.apache.dubbo.rpc.model.ModuleModel, org.apache.dubbo.config.annotation.Reference);
    Code:
       0: aload_0
       1: aload_1
       2: aload_2
       3: invokespecial #11                 // Method org/apache/dubbo/config/ReferenceConfigBase."<init>":(Lorg/apache/dubbo/rpc/model/ModuleModel;Lorg/apache/dubbo/config/annotation/Reference;)V
       6: return

  protected void postProcessAfterScopeModelChanged(org.apache.dubbo.rpc.model.ScopeModel, org.apache.dubbo.rpc.model.ScopeModel);
    Code:
       0: aload_0
       1: aload_1
       2: aload_2
       3: invokespecial #12                 // Method org/apache/dubbo/config/ReferenceConfigBase.postProcessAfterScopeModelChanged:(Lorg/apache/dubbo/rpc/model/ScopeModel;Lorg/apache/dubbo/rpc/model/ScopeModel;)V
       6: aload_0
       7: aload_0
       8: ldc           #13                 // class org/apache/dubbo/rpc/Protocol
      10: invokevirtual #14                 // Method getExtensionLoader:(Ljava/lang/Class;)Lorg/apache/dubbo/common/extension/ExtensionLoader;
      13: invokevirtual #15                 // Method org/apache/dubbo/common/extension/ExtensionLoader.getAdaptiveExtension:()Ljava/lang/Object;
      16: checkcast     #13                 // class org/apache/dubbo/rpc/Protocol
      19: putfield      #16                 // Field protocolSPI:Lorg/apache/dubbo/rpc/Protocol;
      22: aload_0
      23: aload_0
      24: ldc           #17                 // class org/apache/dubbo/rpc/ProxyFactory
      26: invokevirtual #14                 // Method getExtensionLoader:(Ljava/lang/Class;)Lorg/apache/dubbo/common/extension/ExtensionLoader;
      29: invokevirtual #15                 // Method org/apache/dubbo/common/extension/ExtensionLoader.getAdaptiveExtension:()Ljava/lang/Object;
      32: checkcast     #17                 // class org/apache/dubbo/rpc/ProxyFactory
      35: putfield      #18                 // Field proxyFactory:Lorg/apache/dubbo/rpc/ProxyFactory;
      38: return

  public java.lang.String getServices();
    Code:
       0: aload_0
       1: getfield      #19                 // Field services:Ljava/lang/String;
       4: areturn

  public java.util.Set<java.lang.String> getSubscribedServices();
    Code:
       0: aload_0
       1: invokevirtual #20                 // Method getServices:()Ljava/lang/String;
       4: bipush        44
       6: invokestatic  #21                 // Method org/apache/dubbo/common/utils/StringUtils.splitToSet:(Ljava/lang/String;C)Ljava/util/Set;
       9: areturn

  public void setServices(java.lang.String);
    Code:
       0: aload_0
       1: aload_1
       2: putfield      #19                 // Field services:Ljava/lang/String;
       5: return

  public T get();
    Code:
       0: aload_0
       1: getfield      #22                 // Field destroyed:Z
       4: ifeq          42
       7: new           #23                 // class java/lang/IllegalStateException
      10: dup
      11: new           #24                 // class java/lang/StringBuilder
      14: dup
      15: invokespecial #25                 // Method java/lang/StringBuilder."<init>":()V
      18: ldc           #26                 // String The invoker of ReferenceConfig(
      20: invokevirtual #27                 // Method java/lang/StringBuilder.append:(Ljava/lang/String;)Ljava/lang/StringBuilder;
      23: aload_0
      24: getfield      #28                 // Field url:Ljava/lang/String;
      27: invokevirtual #27                 // Method java/lang/StringBuilder.append:(Ljava/lang/String;)Ljava/lang/StringBuilder;
      30: ldc           #29                 // String ) has already destroyed!
      32: invokevirtual #27                 // Method java/lang/StringBuilder.append:(Ljava/lang/String;)Ljava/lang/StringBuilder;
      35: invokevirtual #30                 // Method java/lang/StringBuilder.toString:()Ljava/lang/String;
      38: invokespecial #31                 // Method java/lang/IllegalStateException."<init>":(Ljava/lang/String;)V
      41: athrow
      42: aload_0
      43: getfield      #32                 // Field ref:Ljava/lang/Object;
      46: ifnonnull     66
      49: aload_0
      50: invokevirtual #33                 // Method getScopeModel:()Lorg/apache/dubbo/rpc/model/ModuleModel;
      53: invokevirtual #34                 // Method org/apache/dubbo/rpc/model/ModuleModel.getDeployer:()Lorg/apache/dubbo/common/deploy/ModuleDeployer;
      56: invokeinterface #35,  1           // InterfaceMethod org/apache/dubbo/common/deploy/ModuleDeployer.start:()Ljava/util/concurrent/Future;
      61: pop
      62: aload_0
      63: invokevirtual #36                 // Method init:()V
      66: aload_0
      67: getfield      #32                 // Field ref:Ljava/lang/Object;
      70: areturn

  public synchronized void destroy();
    Code:
       0: aload_0
       1: invokespecial #37                 // Method org/apache/dubbo/config/ReferenceConfigBase.destroy:()V
       4: aload_0
       5: getfield      #22                 // Field destroyed:Z
       8: ifeq          12
      11: return
      12: aload_0
      13: iconst_1
      14: putfield      #22                 // Field destroyed:Z
      17: aload_0
      18: getfield      #38                 // Field invoker:Lorg/apache/dubbo/rpc/Invoker;
      21: ifnull        33
      24: aload_0
      25: getfield      #38                 // Field invoker:Lorg/apache/dubbo/rpc/Invoker;
      28: invokeinterface #39,  1           // InterfaceMethod org/apache/dubbo/rpc/Invoker.destroy:()V
      33: goto          79
      36: astore_1
      37: getstatic     #41                 // Field logger:Lorg/apache/dubbo/common/logger/ErrorTypeAwareLogger;
      40: ldc           #42                 // String 5-3
      42: ldc           #43                 // String
      44: ldc           #43                 // String
      46: new           #24                 // class java/lang/StringBuilder
      49: dup
      50: invokespecial #25                 // Method java/lang/StringBuilder."<init>":()V
      53: ldc           #44                 // String Unexpected error occurred when destroy invoker of ReferenceConfig(
      55: invokevirtual #27                 // Method java/lang/StringBuilder.append:(Ljava/lang/String;)Ljava/lang/StringBuilder;
      58: aload_0
      59: getfield      #28                 // Field url:Ljava/lang/String;
      62: invokevirtual #27                 // Method java/lang/StringBuilder.append:(Ljava/lang/String;)Ljava/lang/StringBuilder;
      65: ldc           #45                 // String ).
      67: invokevirtual #27                 // Method java/lang/StringBuilder.append:(Ljava/lang/String;)Ljava/lang/StringBuilder;
      70: invokevirtual #30                 // Method java/lang/StringBuilder.toString:()Ljava/lang/String;
      73: aload_1
      74: invokeinterface #46,  6           // InterfaceMethod org/apache/dubbo/common/logger/ErrorTypeAwareLogger.warn:(Ljava/lang/String;Ljava/lang/String;Ljava/lang/String;Ljava/lang/String;Ljava/lang/Throwable;)V
      79: aload_0
      80: aconst_null
      81: putfield      #38                 // Field invoker:Lorg/apache/dubbo/rpc/Invoker;
      84: aload_0
      85: aconst_null
      86: putfield      #32                 // Field ref:Ljava/lang/Object;
      89: aload_0
      90: getfield      #47                 // Field consumerModel:Lorg/apache/dubbo/rpc/model/ConsumerModel;
      93: ifnull        112
      96: aload_0
      97: invokevirtual #33                 // Method getScopeModel:()Lorg/apache/dubbo/rpc/model/ModuleModel;
     100: invokevirtual #48                 // Method org/apache/dubbo/rpc/model/ModuleModel.getServiceRepository:()Lorg/apache/dubbo/rpc/model/ModuleServiceRepository;
     103: astore_1
     104: aload_1
     105: aload_0
     106: getfield      #47                 // Field consumerModel:Lorg/apache/dubbo/rpc/model/ConsumerModel;
     109: invokevirtual #49                 // Method org/apache/dubbo/rpc/model/ModuleServiceRepository.unregisterConsumer:(Lorg/apache/dubbo/rpc/model/ConsumerModel;)V
     112: return
    Exception table:
       from    to  target type
          17    33    36   Class java/lang/Throwable

  protected synchronized void init();
    Code:
       0: aload_0
       1: getfield      #50                 // Field initialized:Z
       4: ifeq          15
       7: aload_0
       8: getfield      #32                 // Field ref:Ljava/lang/Object;
      11: ifnull        15
      14: return
      15: aload_0
      16: invokevirtual #51                 // Method isRefreshed:()Z
      19: ifne          26
      22: aload_0
      23: invokevirtual #52                 // Method refresh:()V
      26: aload_0
      27: invokevirtual #53                 // Method getProxy:()Ljava/lang/String;
      30: astore_1
      31: aload_1
      32: invokestatic  #54                 // Method org/apache/dubbo/common/utils/StringUtils.isBlank:(Ljava/lang/CharSequence;)Z
      35: ifeq          56
      38: ldc           #55                 // class org/apache/dubbo/rpc/model/DubboStub
      40: aload_0
      41: getfield      #56                 // Field interfaceClass:Ljava/lang/Class;
      44: invokevirtual #57                 // Method java/lang/Class.isAssignableFrom:(Ljava/lang/Class;)Z
      47: ifeq          56
      50: aload_0
      51: ldc           #58                 // String nativestub
      53: invokevirtual #59                 // Method setProxy:(Ljava/lang/String;)V
      56: aload_0
      57: aload_0
      58: getfield      #60                 // Field consumer:Lorg/apache/dubbo/config/ConsumerConfig;
      61: invokevirtual #61                 // Method initServiceMetadata:(Lorg/apache/dubbo/config/AbstractInterfaceConfig;)V
      64: aload_0
      65: getfield      #62                 // Field serviceMetadata:Lorg/apache/dubbo/rpc/model/ServiceMetadata;
      68: aload_0
      69: invokevirtual #63                 // Method getServiceInterfaceClass:()Ljava/lang/Class;
      72: invokevirtual #64                 // Method org/apache/dubbo/rpc/model/ServiceMetadata.setServiceType:(Ljava/lang/Class;)V
      75: aload_0
      76: getfield      #62                 // Field serviceMetadata:Lorg/apache/dubbo/rpc/model/ServiceMetadata;
      79: invokevirtual #65                 // Method org/apache/dubbo/rpc/model/ServiceMetadata.generateServiceKey:()V
      82: aload_0
      83: invokespecial #66                 // Method appendConfig:()Ljava/util/Map;
      86: astore_2
      87: aload_0
      88: invokevirtual #33                 // Method getScopeModel:()Lorg/apache/dubbo/rpc/model/ModuleModel;
      91: invokevirtual #48                 // Method org/apache/dubbo/rpc/model/ModuleModel.getServiceRepository:()Lorg/apache/dubbo/rpc/model/ModuleServiceRepository;
      94: astore_3
      95: ldc           #58                 // String nativestub
      97: aload_0
      98: invokevirtual #53                 // Method getProxy:()Ljava/lang/String;
     101: invokevirtual #67                 // Method java/lang/String.equals:(Ljava/lang/Object;)Z
     104: ifeq          126
     107: aload_0
     108: getfield      #68                 // Field interfaceName:Ljava/lang/String;
     111: invokestatic  #69                 // Method org/apache/dubbo/rpc/stub/StubSuppliers.getServiceDescriptor:(Ljava/lang/String;)Lorg/apache/dubbo/rpc/model/ServiceDescriptor;
     114: astore        4
     116: aload_3
     117: aload         4
     119: invokevirtual #70                 // Method org/apache/dubbo/rpc/model/ModuleServiceRepository.registerService:(Lorg/apache/dubbo/rpc/model/ServiceDescriptor;)Lorg/apache/dubbo/rpc/model/ServiceDescriptor;
     122: pop
     123: goto          136
     126: aload_3
     127: aload_0
     128: getfield      #56                 // Field interfaceClass:Ljava/lang/Class;
     131: invokevirtual #71                 // Method org/apache/dubbo/rpc/model/ModuleServiceRepository.registerService:(Ljava/lang/Class;)Lorg/apache/dubbo/rpc/model/ServiceDescriptor;
     134: astore        4
     136: aload_0
     137: new           #72                 // class org/apache/dubbo/rpc/model/ConsumerModel
     140: dup
     141: aload_0
     142: getfield      #62                 // Field serviceMetadata:Lorg/apache/dubbo/rpc/model/ServiceMetadata;
     145: invokevirtual #73                 // Method org/apache/dubbo/rpc/model/ServiceMetadata.getServiceKey:()Ljava/lang/String;
     148: aload_0
     149: getfield      #74                 // Field proxy:Ljava/lang/String;
     152: aload         4
     154: aload_0
     155: invokevirtual #33                 // Method getScopeModel:()Lorg/apache/dubbo/rpc/model/ModuleModel;
     158: aload_0
     159: getfield      #62                 // Field serviceMetadata:Lorg/apache/dubbo/rpc/model/ServiceMetadata;
     162: aload_0
     163: invokespecial #75                 // Method createAsyncMethodInfo:()Ljava/util/Map;
     166: aload_0
     167: getfield      #76                 // Field interfaceClassLoader:Ljava/lang/ClassLoader;
     170: invokespecial #77                 // Method org/apache/dubbo/rpc/model/ConsumerModel."<init>":(Ljava/lang/String;Ljava/lang/Object;Lorg/apache/dubbo/rpc/model/ServiceDescriptor;Lorg/apache/dubbo/rpc/model/ModuleModel;Lorg/apache/dubbo/rpc/model/ServiceMetadata;Ljava/util/Map;Ljava/lang/ClassLoader;)V
     173: putfield      #47                 // Field consumerModel:Lorg/apache/dubbo/rpc/model/ConsumerModel;
     176: aload_0
     177: getfield      #47                 // Field consumerModel:Lorg/apache/dubbo/rpc/model/ConsumerModel;
     180: aload_0
     181: invokevirtual #78                 // Method org/apache/dubbo/rpc/model/ConsumerModel.setConfig:(Lorg/apache/dubbo/config/AbstractInterfaceConfig;)V
     184: aload_3
     185: aload_0
     186: getfield      #47                 // Field consumerModel:Lorg/apache/dubbo/rpc/model/ConsumerModel;
     189: invokevirtual #79                 // Method org/apache/dubbo/rpc/model/ModuleServiceRepository.registerConsumer:(Lorg/apache/dubbo/rpc/model/ConsumerModel;)V
     192: aload_0
     193: getfield      #62                 // Field serviceMetadata:Lorg/apache/dubbo/rpc/model/ServiceMetadata;
     196: invokevirtual #80                 // Method org/apache/dubbo/rpc/model/ServiceMetadata.getAttachments:()Ljava/util/Map;
     199: aload_2
     200: invokeinterface #81,  2           // InterfaceMethod java/util/Map.putAll:(Ljava/util/Map;)V
     205: aload_0
     206: aload_0
     207: aload_2
     208: invokespecial #82                 // Method createProxy:(Ljava/util/Map;)Ljava/lang/Object;
     211: putfield      #32                 // Field ref:Ljava/lang/Object;
     214: aload_0
     215: getfield      #62                 // Field serviceMetadata:Lorg/apache/dubbo/rpc/model/ServiceMetadata;
     218: aload_0
     219: getfield      #32                 // Field ref:Ljava/lang/Object;
     222: invokevirtual #83                 // Method org/apache/dubbo/rpc/model/ServiceMetadata.setTarget:(Ljava/lang/Object;)V
     225: aload_0
     226: getfield      #62                 // Field serviceMetadata:Lorg/apache/dubbo/rpc/model/ServiceMetadata;
     229: ldc           #84                 // String refClass
     231: aload_0
     232: getfield      #32                 // Field ref:Ljava/lang/Object;
     235: invokevirtual #85                 // Method org/apache/dubbo/rpc/model/ServiceMetadata.addAttribute:(Ljava/lang/String;Ljava/lang/Object;)V
     238: aload_0
     239: getfield      #47                 // Field consumerModel:Lorg/apache/dubbo/rpc/model/ConsumerModel;
     242: aload_0
     243: invokevirtual #86                 // Method getDestroyRunner:()Ljava/lang/Runnable;
     246: invokevirtual #87                 // Method org/apache/dubbo/rpc/model/ConsumerModel.setDestroyRunner:(Ljava/lang/Runnable;)V
     249: aload_0
     250: getfield      #47                 // Field consumerModel:Lorg/apache/dubbo/rpc/model/ConsumerModel;
     253: aload_0
     254: getfield      #32                 // Field ref:Ljava/lang/Object;
     257: invokevirtual #88                 // Method org/apache/dubbo/rpc/model/ConsumerModel.setProxyObject:(Ljava/lang/Object;)V
     260: aload_0
     261: getfield      #47                 // Field consumerModel:Lorg/apache/dubbo/rpc/model/ConsumerModel;
     264: invokevirtual #89                 // Method org/apache/dubbo/rpc/model/ConsumerModel.initMethodModels:()V
     267: aload_0
     268: invokespecial #90                 // Method checkInvokerAvailable:()V
     271: goto          443
     274: astore_1
     275: aload_0
     276: getfield      #38                 // Field invoker:Lorg/apache/dubbo/rpc/Invoker;
     279: ifnull        291
     282: aload_0
     283: getfield      #38                 // Field invoker:Lorg/apache/dubbo/rpc/Invoker;
     286: invokeinterface #39,  1           // InterfaceMethod org/apache/dubbo/rpc/Invoker.destroy:()V
     291: goto          337
     294: astore_2
     295: getstatic     #41                 // Field logger:Lorg/apache/dubbo/common/logger/ErrorTypeAwareLogger;
     298: ldc           #42                 // String 5-3
     300: ldc           #43                 // String
     302: ldc           #43                 // String
     304: new           #24                 // class java/lang/StringBuilder
     307: dup
     308: invokespecial #25                 // Method java/lang/StringBuilder."<init>":()V
     311: ldc           #44                 // String Unexpected error occurred when destroy invoker of ReferenceConfig(
     313: invokevirtual #27                 // Method java/lang/StringBuilder.append:(Ljava/lang/String;)Ljava/lang/StringBuilder;
     316: aload_0
     317: getfield      #28                 // Field url:Ljava/lang/String;
     320: invokevirtual #27                 // Method java/lang/StringBuilder.append:(Ljava/lang/String;)Ljava/lang/StringBuilder;
     323: ldc           #45                 // String ).
     325: invokevirtual #27                 // Method java/lang/StringBuilder.append:(Ljava/lang/String;)Ljava/lang/StringBuilder;
     328: invokevirtual #30                 // Method java/lang/StringBuilder.toString:()Ljava/lang/String;
     331: aload_1
     332: invokeinterface #46,  6           // InterfaceMethod org/apache/dubbo/common/logger/ErrorTypeAwareLogger.warn:(Ljava/lang/String;Ljava/lang/String;Ljava/lang/String;Ljava/lang/String;Ljava/lang/Throwable;)V
     337: aload_0
     338: getfield      #47                 // Field consumerModel:Lorg/apache/dubbo/rpc/model/ConsumerModel;
     341: ifnull        360
     344: aload_0
     345: invokevirtual #33                 // Method getScopeModel:()Lorg/apache/dubbo/rpc/model/ModuleModel;
     348: invokevirtual #48                 // Method org/apache/dubbo/rpc/model/ModuleModel.getServiceRepository:()Lorg/apache/dubbo/rpc/model/ModuleServiceRepository;
     351: astore_2
     352: aload_2
     353: aload_0
     354: getfield      #47                 // Field consumerModel:Lorg/apache/dubbo/rpc/model/ConsumerModel;
     357: invokevirtual #49                 // Method org/apache/dubbo/rpc/model/ModuleServiceRepository.unregisterConsumer:(Lorg/apache/dubbo/rpc/model/ConsumerModel;)V
     360: aload_0
     361: iconst_0
     362: putfield      #50                 // Field initialized:Z
     365: aload_0
     366: aconst_null
     367: putfield      #38                 // Field invoker:Lorg/apache/dubbo/rpc/Invoker;
     370: aload_0
     371: aconst_null
     372: putfield      #32                 // Field ref:Ljava/lang/Object;
     375: aload_0
     376: aconst_null
     377: putfield      #47                 // Field consumerModel:Lorg/apache/dubbo/rpc/model/ConsumerModel;
     380: aload_0
     381: getfield      #62                 // Field serviceMetadata:Lorg/apache/dubbo/rpc/model/ServiceMetadata;
     384: aconst_null
     385: invokevirtual #83                 // Method org/apache/dubbo/rpc/model/ServiceMetadata.setTarget:(Ljava/lang/Object;)V
     388: aload_0
     389: getfield      #62                 // Field serviceMetadata:Lorg/apache/dubbo/rpc/model/ServiceMetadata;
     392: invokevirtual #91                 // Method org/apache/dubbo/rpc/model/ServiceMetadata.getAttributeMap:()Ljava/util/Map;
     395: ldc           #84                 // String refClass
     397: invokeinterface #92,  2           // InterfaceMethod java/util/Map.remove:(Ljava/lang/Object;)Ljava/lang/Object;
     402: pop
     403: aload_1
     404: invokevirtual #93                 // Method java/lang/Object.getClass:()Ljava/lang/Class;
     407: ldc           #23                 // class java/lang/IllegalStateException
     409: if_acmpne     441
     412: aload_1
     413: invokevirtual #94                 // Method java/lang/Throwable.getMessage:()Ljava/lang/String;
     416: ldc           #95                 // String No provider available for the service
     418: invokevirtual #96                 // Method java/lang/String.contains:(Ljava/lang/CharSequence;)Z
     421: ifeq          441
     424: getstatic     #41                 // Field logger:Lorg/apache/dubbo/common/logger/ErrorTypeAwareLogger;
     427: ldc           #97                 // String 2-2
     429: ldc           #98                 // String server crashed
     431: ldc           #43                 // String
     433: ldc           #99                 // String No provider available.
     435: aload_1
     436: invokeinterface #100,  6          // InterfaceMethod org/apache/dubbo/common/logger/ErrorTypeAwareLogger.error:(Ljava/lang/String;Ljava/lang/String;Ljava/lang/String;Ljava/lang/String;Ljava/lang/Throwable;)V
     441: aload_1
     442: athrow
     443: aload_0
     444: iconst_1
     445: putfield      #50                 // Field initialized:Z
     448: return
    Exception table:
       from    to  target type
          15   271   274   Class java/lang/Throwable
         275   291   294   Class java/lang/Throwable

  private java.util.Map<java.lang.String, org.apache.dubbo.rpc.model.AsyncMethodInfo> createAsyncMethodInfo();
    Code:
       0: aconst_null
       1: astore_1
       2: aload_0
       3: invokevirtual #101                // Method getMethods:()Ljava/util/List;
       6: invokestatic  #102                // Method org/apache/dubbo/common/utils/CollectionUtils.isNotEmpty:(Ljava/util/Collection;)Z
       9: ifeq          78
      12: new           #103                // class java/util/HashMap
      15: dup
      16: bipush        16
      18: invokespecial #104                // Method java/util/HashMap."<init>":(I)V
      21: astore_1
      22: aload_0
      23: invokevirtual #101                // Method getMethods:()Ljava/util/List;
      26: invokeinterface #105,  1          // InterfaceMethod java/util/List.iterator:()Ljava/util/Iterator;
      31: astore_2
      32: aload_2
      33: invokeinterface #106,  1          // InterfaceMethod java/util/Iterator.hasNext:()Z
      38: ifeq          78
      41: aload_2
      42: invokeinterface #107,  1          // InterfaceMethod java/util/Iterator.next:()Ljava/lang/Object;
      47: checkcast     #108                // class org/apache/dubbo/config/MethodConfig
      50: astore_3
      51: aload_3
      52: invokevirtual #109                // Method org/apache/dubbo/config/MethodConfig.convertMethodConfig2AsyncInfo:()Lorg/apache/dubbo/rpc/model/AsyncMethodInfo;
      55: astore        4
      57: aload         4
      59: ifnull        75
      62: aload_1
      63: aload_3
      64: invokevirtual #110                // Method org/apache/dubbo/config/MethodConfig.getName:()Ljava/lang/String;
      67: aload         4
      69: invokeinterface #111,  3          // InterfaceMethod java/util/Map.put:(Ljava/lang/Object;Ljava/lang/Object;)Ljava/lang/Object;
      74: pop
      75: goto          32
      78: aload_1
      79: areturn

  private java.util.Map<java.lang.String, java.lang.String> appendConfig();
    Code:
       0: new           #103                // class java/util/HashMap
       3: dup
       4: bipush        16
       6: invokespecial #104                // Method java/util/HashMap."<init>":(I)V
       9: astore_1
      10: aload_1
      11: ldc           #112                // String interface
      13: aload_0
      14: getfield      #68                 // Field interfaceName:Ljava/lang/String;
      17: invokeinterface #111,  3          // InterfaceMethod java/util/Map.put:(Ljava/lang/Object;Ljava/lang/Object;)Ljava/lang/Object;
      22: pop
      23: aload_1
      24: ldc           #113                // String side
      26: ldc           #114                // String consumer
      28: invokeinterface #111,  3          // InterfaceMethod java/util/Map.put:(Ljava/lang/Object;Ljava/lang/Object;)Ljava/lang/Object;
      33: pop
      34: aload_1
      35: invokestatic  #115                // Method org/apache/dubbo/config/ReferenceConfigBase.appendRuntimeParameters:(Ljava/util/Map;)V
      38: aload_0
      39: getfield      #116                // Field generic:Ljava/lang/String;
      42: invokestatic  #117                // Method org/apache/dubbo/rpc/support/ProtocolUtils.isGeneric:(Ljava/lang/String;)Z
      45: ifne          183
      48: aload_0
      49: getfield      #56                 // Field interfaceClass:Ljava/lang/Class;
      52: aload_0
      53: getfield      #118                // Field version:Ljava/lang/String;
      56: invokestatic  #119                // Method org/apache/dubbo/common/Version.getVersion:(Ljava/lang/Class;Ljava/lang/String;)Ljava/lang/String;
      59: astore_2
      60: aload_2
      61: invokestatic  #120                // Method org/apache/dubbo/common/utils/StringUtils.isNotEmpty:(Ljava/lang/String;)Z
      64: ifeq          77
      67: aload_1
      68: ldc           #121                // String revision
      70: aload_2
      71: invokeinterface #111,  3          // InterfaceMethod java/util/Map.put:(Ljava/lang/Object;Ljava/lang/Object;)Ljava/lang/Object;
      76: pop
      77: aload_0
      78: aload_0
      79: getfield      #56                 // Field interfaceClass:Ljava/lang/Class;
      82: invokevirtual #122                // Method methods:(Ljava/lang/Class;)[Ljava/lang/String;
      85: astore_3
      86: aload_3
      87: arraylength
      88: ifne          144
      91: getstatic     #41                 // Field logger:Lorg/apache/dubbo/common/logger/ErrorTypeAwareLogger;
      94: ldc           #123                // String 5-4
      96: ldc           #43                 // String
      98: ldc           #43                 // String
     100: new           #24                 // class java/lang/StringBuilder
     103: dup
     104: invokespecial #25                 // Method java/lang/StringBuilder."<init>":()V
     107: ldc           #124                // String No method found in service interface:
     109: invokevirtual #27                 // Method java/lang/StringBuilder.append:(Ljava/lang/String;)Ljava/lang/StringBuilder;
     112: aload_0
     113: getfield      #56                 // Field interfaceClass:Ljava/lang/Class;
     116: invokevirtual #125                // Method java/lang/Class.getName:()Ljava/lang/String;
     119: invokevirtual #27                 // Method java/lang/StringBuilder.append:(Ljava/lang/String;)Ljava/lang/StringBuilder;
     122: invokevirtual #30                 // Method java/lang/StringBuilder.toString:()Ljava/lang/String;
     125: invokeinterface #126,  5          // InterfaceMethod org/apache/dubbo/common/logger/ErrorTypeAwareLogger.warn:(Ljava/lang/String;Ljava/lang/String;Ljava/lang/String;Ljava/lang/String;)V
     130: aload_1
     131: ldc           #127                // String methods
     133: ldc           #128                // String *
     135: invokeinterface #111,  3          // InterfaceMethod java/util/Map.put:(Ljava/lang/Object;Ljava/lang/Object;)Ljava/lang/Object;
     140: pop
     141: goto          183
     144: new           #129                // class java/util/ArrayList
     147: dup
     148: aload_3
     149: invokestatic  #130                // Method java/util/Arrays.asList:([Ljava/lang/Object;)Ljava/util/List;
     152: invokespecial #131                // Method java/util/ArrayList."<init>":(Ljava/util/Collection;)V
     155: astore        4
     157: aload         4
     159: invokestatic  #132                // InterfaceMethod java/util/Comparator.naturalOrder:()Ljava/util/Comparator;
     162: invokeinterface #133,  2          // InterfaceMethod java/util/List.sort:(Ljava/util/Comparator;)V
     167: aload_1
     168: ldc           #127                // String methods
     170: ldc           #134                // String ,
     172: aload         4
     174: invokestatic  #135                // Method java/lang/String.join:(Ljava/lang/CharSequence;Ljava/lang/Iterable;)Ljava/lang/String;
     177: invokeinterface #111,  3          // InterfaceMethod java/util/Map.put:(Ljava/lang/Object;Ljava/lang/Object;)Ljava/lang/Object;
     182: pop
     183: aload_1
     184: aload_0
     185: invokevirtual #136                // Method getApplication:()Lorg/apache/dubbo/config/ApplicationConfig;
     188: invokestatic  #137                // Method org/apache/dubbo/config/AbstractConfig.appendParameters:(Ljava/util/Map;Ljava/lang/Object;)V
     191: aload_1
     192: aload_0
     193: invokevirtual #138                // Method getModule:()Lorg/apache/dubbo/config/ModuleConfig;
     196: invokestatic  #137                // Method org/apache/dubbo/config/AbstractConfig.appendParameters:(Ljava/util/Map;Ljava/lang/Object;)V
     199: aload_1
     200: aload_0
     201: getfield      #60                 // Field consumer:Lorg/apache/dubbo/config/ConsumerConfig;
     204: invokestatic  #137                // Method org/apache/dubbo/config/AbstractConfig.appendParameters:(Ljava/util/Map;Ljava/lang/Object;)V
     207: aload_1
     208: aload_0
     209: invokestatic  #137                // Method org/apache/dubbo/config/AbstractConfig.appendParameters:(Ljava/util/Map;Ljava/lang/Object;)V
     212: aload_0
     213: aload_1
     214: invokevirtual #139                // Method appendMetricsCompatible:(Ljava/util/Map;)V
     217: ldc           #140                // String DUBBO_IP_TO_REGISTRY
     219: invokestatic  #141                // Method org/apache/dubbo/common/utils/ConfigUtils.getSystemProperty:(Ljava/lang/String;)Ljava/lang/String;
     222: astore_2
     223: aload_2
     224: invokestatic  #142                // Method org/apache/dubbo/common/utils/StringUtils.isEmpty:(Ljava/lang/String;)Z
     227: ifeq          237
     230: invokestatic  #143                // Method org/apache/dubbo/common/utils/NetUtils.getLocalHost:()Ljava/lang/String;
     233: astore_2
     234: goto          271
     237: aload_2
     238: invokestatic  #144                // Method org/apache/dubbo/common/utils/NetUtils.isInvalidLocalHost:(Ljava/lang/String;)Z
     241: ifeq          271
     244: new           #145                // class java/lang/IllegalArgumentException
     247: dup
     248: new           #24                 // class java/lang/StringBuilder
     251: dup
     252: invokespecial #25                 // Method java/lang/StringBuilder."<init>":()V
     255: ldc           #146                // String Specified invalid registry ip from property:DUBBO_IP_TO_REGISTRY, value:
     257: invokevirtual #27                 // Method java/lang/StringBuilder.append:(Ljava/lang/String;)Ljava/lang/StringBuilder;
     260: aload_2
     261: invokevirtual #27                 // Method java/lang/StringBuilder.append:(Ljava/lang/String;)Ljava/lang/StringBuilder;
     264: invokevirtual #30                 // Method java/lang/StringBuilder.toString:()Ljava/lang/String;
     267: invokespecial #147                // Method java/lang/IllegalArgumentException."<init>":(Ljava/lang/String;)V
     270: athrow
     271: aload_1
     272: ldc           #148                // String register.ip
     274: aload_2
     275: invokeinterface #111,  3          // InterfaceMethod java/util/Map.put:(Ljava/lang/Object;Ljava/lang/Object;)Ljava/lang/Object;
     280: pop
     281: aload_0
     282: invokevirtual #101                // Method getMethods:()Ljava/util/List;
     285: invokestatic  #102                // Method org/apache/dubbo/common/utils/CollectionUtils.isNotEmpty:(Ljava/util/Collection;)Z
     288: ifeq          426
     291: aload_0
     292: invokevirtual #101                // Method getMethods:()Ljava/util/List;
     295: invokeinterface #105,  1          // InterfaceMethod java/util/List.iterator:()Ljava/util/Iterator;
     300: astore_3
     301: aload_3
     302: invokeinterface #106,  1          // InterfaceMethod java/util/Iterator.hasNext:()Z
     307: ifeq          426
     310: aload_3
     311: invokeinterface #107,  1          // InterfaceMethod java/util/Iterator.next:()Ljava/lang/Object;
     316: checkcast     #108                // class org/apache/dubbo/config/MethodConfig
     319: astore        4
     321: aload_1
     322: aload         4
     324: aload         4
     326: invokevirtual #110                // Method org/apache/dubbo/config/MethodConfig.getName:()Ljava/lang/String;
     329: invokestatic  #149                // Method org/apache/dubbo/config/AbstractConfig.appendParameters:(Ljava/util/Map;Ljava/lang/Object;Ljava/lang/String;)V
     332: new           #24                 // class java/lang/StringBuilder
     335: dup
     336: invokespecial #25                 // Method java/lang/StringBuilder."<init>":()V
     339: aload         4
     341: invokevirtual #110                // Method org/apache/dubbo/config/MethodConfig.getName:()Ljava/lang/String;
     344: invokevirtual #27                 // Method java/lang/StringBuilder.append:(Ljava/lang/String;)Ljava/lang/StringBuilder;
     347: ldc           #150                // String .retry
     349: invokevirtual #27                 // Method java/lang/StringBuilder.append:(Ljava/lang/String;)Ljava/lang/StringBuilder;
     352: invokevirtual #30                 // Method java/lang/StringBuilder.toString:()Ljava/lang/String;
     355: astore        5
     357: aload_1
     358: aload         5
     360: invokeinterface #151,  2          // InterfaceMethod java/util/Map.containsKey:(Ljava/lang/Object;)Z
     365: ifeq          423
     368: aload_1
     369: aload         5
     371: invokeinterface #92,  2           // InterfaceMethod java/util/Map.remove:(Ljava/lang/Object;)Ljava/lang/Object;
     376: checkcast     #152                // class java/lang/String
     379: astore        6
     381: ldc           #153                // String false
     383: aload         6
     385: invokevirtual #67                 // Method java/lang/String.equals:(Ljava/lang/Object;)Z
     388: ifeq          423
     391: aload_1
     392: new           #24                 // class java/lang/StringBuilder
     395: dup
     396: invokespecial #25                 // Method java/lang/StringBuilder."<init>":()V
     399: aload         4
     401: invokevirtual #110                // Method org/apache/dubbo/config/MethodConfig.getName:()Ljava/lang/String;
     404: invokevirtual #27                 // Method java/lang/StringBuilder.append:(Ljava/lang/String;)Ljava/lang/StringBuilder;
     407: ldc           #154                // String .retries
     409: invokevirtual #27                 // Method java/lang/StringBuilder.append:(Ljava/lang/String;)Ljava/lang/StringBuilder;
     412: invokevirtual #30                 // Method java/lang/StringBuilder.toString:()Ljava/lang/String;
     415: ldc           #155                // String 0
     417: invokeinterface #111,  3          // InterfaceMethod java/util/Map.put:(Ljava/lang/Object;Ljava/lang/Object;)Ljava/lang/Object;
     422: pop
     423: goto          301
     426: aload_1
     427: areturn

  private T createProxy(java.util.Map<java.lang.String, java.lang.String>);
    Code:
       0: aload_0
       1: getfield      #156                // Field urls:Ljava/util/List;
       4: invokeinterface #157,  1          // InterfaceMethod java/util/List.clear:()V
       9: aload_0
      10: aload_1
      11: invokespecial #158                // Method meshModeHandleUrl:(Ljava/util/Map;)V
      14: aload_0
      15: getfield      #28                 // Field url:Ljava/lang/String;
      18: invokestatic  #120                // Method org/apache/dubbo/common/utils/StringUtils.isNotEmpty:(Ljava/lang/String;)Z
      21: ifeq          32
      24: aload_0
      25: aload_1
      26: invokespecial #159                // Method parseUrl:(Ljava/util/Map;)V
      29: goto          37
      32: aload_0
      33: aload_1
      34: invokespecial #160                // Method aggregateUrlFromRegistry:(Ljava/util/Map;)V
      37: aload_0
      38: invokespecial #161                // Method createInvoker:()V
      41: getstatic     #41                 // Field logger:Lorg/apache/dubbo/common/logger/ErrorTypeAwareLogger;
      44: invokeinterface #162,  1          // InterfaceMethod org/apache/dubbo/common/logger/ErrorTypeAwareLogger.isInfoEnabled:()Z
      49: ifeq          121
      52: getstatic     #41                 // Field logger:Lorg/apache/dubbo/common/logger/ErrorTypeAwareLogger;
      55: new           #24                 // class java/lang/StringBuilder
      58: dup
      59: invokespecial #25                 // Method java/lang/StringBuilder."<init>":()V
      62: ldc           #163                // String Referred dubbo service: [
      64: invokevirtual #27                 // Method java/lang/StringBuilder.append:(Ljava/lang/String;)Ljava/lang/StringBuilder;
      67: aload_1
      68: ldc           #112                // String interface
      70: invokeinterface #164,  2          // InterfaceMethod java/util/Map.get:(Ljava/lang/Object;)Ljava/lang/Object;
      75: checkcast     #152                // class java/lang/String
      78: invokevirtual #27                 // Method java/lang/StringBuilder.append:(Ljava/lang/String;)Ljava/lang/StringBuilder;
      81: ldc           #165                // String ].
      83: invokevirtual #27                 // Method java/lang/StringBuilder.append:(Ljava/lang/String;)Ljava/lang/StringBuilder;
      86: aload_1
      87: ldc           #166                // String generic
      89: invokeinterface #164,  2          // InterfaceMethod java/util/Map.get:(Ljava/lang/Object;)Ljava/lang/Object;
      94: checkcast     #152                // class java/lang/String
      97: invokestatic  #167                // Method java/lang/Boolean.parseBoolean:(Ljava/lang/String;)Z
     100: ifeq          108
     103: ldc           #168                // String  it\'s GenericService reference
     105: goto          110
     108: ldc           #169                // String  it\'s not GenericService reference
     110: invokevirtual #27                 // Method java/lang/StringBuilder.append:(Ljava/lang/String;)Ljava/lang/StringBuilder;
     113: invokevirtual #30                 // Method java/lang/StringBuilder.toString:()Ljava/lang/String;
     116: invokeinterface #170,  2          // InterfaceMethod org/apache/dubbo/common/logger/ErrorTypeAwareLogger.info:(Ljava/lang/String;)V
     121: new           #171                // class org/apache/dubbo/common/url/component/ServiceConfigURL
     124: dup
     125: ldc           #114                // String consumer
     127: aload_1
     128: ldc           #148                // String register.ip
     130: invokeinterface #164,  2          // InterfaceMethod java/util/Map.get:(Ljava/lang/Object;)Ljava/lang/Object;
     135: checkcast     #152                // class java/lang/String
     138: iconst_0
     139: aload_1
     140: ldc           #112                // String interface
     142: invokeinterface #164,  2          // InterfaceMethod java/util/Map.get:(Ljava/lang/Object;)Ljava/lang/Object;
     147: checkcast     #152                // class java/lang/String
     150: aload_1
     151: invokespecial #172                // Method org/apache/dubbo/common/url/component/ServiceConfigURL."<init>":(Ljava/lang/String;Ljava/lang/String;ILjava/lang/String;Ljava/util/Map;)V
     154: astore_2
     155: aload_2
     156: aload_0
     157: invokevirtual #33                 // Method getScopeModel:()Lorg/apache/dubbo/rpc/model/ModuleModel;
     160: invokevirtual #173                // Method org/apache/dubbo/common/URL.setScopeModel:(Lorg/apache/dubbo/rpc/model/ScopeModel;)Lorg/apache/dubbo/common/URL;
     163: astore_2
     164: aload_2
     165: aload_0
     166: getfield      #47                 // Field consumerModel:Lorg/apache/dubbo/rpc/model/ConsumerModel;
     169: invokevirtual #174                // Method org/apache/dubbo/common/URL.setServiceModel:(Lorg/apache/dubbo/rpc/model/ServiceModel;)Lorg/apache/dubbo/common/URL;
     172: astore_2
     173: aload_2
     174: aload_0
     175: getfield      #47                 // Field consumerModel:Lorg/apache/dubbo/rpc/model/ConsumerModel;
     178: invokevirtual #175                // Method org/apache/dubbo/rpc/model/ConsumerModel.getServiceModel:()Lorg/apache/dubbo/rpc/model/ServiceDescriptor;
     181: aload_0
     182: invokevirtual #176                // Method getApplicationModel:()Lorg/apache/dubbo/rpc/model/ApplicationModel;
     185: invokestatic  #177                // Method org/apache/dubbo/registry/client/metadata/MetadataUtils.publishServiceDefinition:(Lorg/apache/dubbo/common/URL;Lorg/apache/dubbo/rpc/model/ServiceDescriptor;Lorg/apache/dubbo/rpc/model/ApplicationModel;)V
     188: aload_0
     189: getfield      #18                 // Field proxyFactory:Lorg/apache/dubbo/rpc/ProxyFactory;
     192: aload_0
     193: getfield      #38                 // Field invoker:Lorg/apache/dubbo/rpc/Invoker;
     196: aload_0
     197: getfield      #116                // Field generic:Ljava/lang/String;
     200: invokestatic  #117                // Method org/apache/dubbo/rpc/support/ProtocolUtils.isGeneric:(Ljava/lang/String;)Z
     203: invokeinterface #178,  3          // InterfaceMethod org/apache/dubbo/rpc/ProxyFactory.getProxy:(Lorg/apache/dubbo/rpc/Invoker;Z)Ljava/lang/Object;
     208: areturn

  private void meshModeHandleUrl(java.util.Map<java.lang.String, java.lang.String>);
    Code:
       0: aload_0
       1: aload_1
       2: invokespecial #179                // Method checkMeshConfig:(Ljava/util/Map;)Z
       5: ifne          9
       8: return
       9: aload_0
      10: getfield      #28                 // Field url:Ljava/lang/String;
      13: invokestatic  #120                // Method org/apache/dubbo/common/utils/StringUtils.isNotEmpty:(Ljava/lang/String;)Z
      16: ifeq          61
      19: getstatic     #41                 // Field logger:Lorg/apache/dubbo/common/logger/ErrorTypeAwareLogger;
      22: invokeinterface #162,  1          // InterfaceMethod org/apache/dubbo/common/logger/ErrorTypeAwareLogger.isInfoEnabled:()Z
      27: ifeq          60
      30: getstatic     #41                 // Field logger:Lorg/apache/dubbo/common/logger/ErrorTypeAwareLogger;
      33: new           #24                 // class java/lang/StringBuilder
      36: dup
      37: invokespecial #25                 // Method java/lang/StringBuilder."<init>":()V
      40: ldc           #180                // String The url already exists, mesh no longer processes url:
      42: invokevirtual #27                 // Method java/lang/StringBuilder.append:(Ljava/lang/String;)Ljava/lang/StringBuilder;
      45: aload_0
      46: getfield      #28                 // Field url:Ljava/lang/String;
      49: invokevirtual #27                 // Method java/lang/StringBuilder.append:(Ljava/lang/String;)Ljava/lang/StringBuilder;
      52: invokevirtual #30                 // Method java/lang/StringBuilder.toString:()Ljava/lang/String;
      55: invokeinterface #170,  2          // InterfaceMethod org/apache/dubbo/common/logger/ErrorTypeAwareLogger.info:(Ljava/lang/String;)V
      60: return
      61: aload_1
      62: ldc           #181                // String provider-namespace
      64: invokeinterface #164,  2          // InterfaceMethod java/util/Map.get:(Ljava/lang/Object;)Ljava/lang/Object;
      69: checkcast     #152                // class java/lang/String
      72: astore_2
      73: aload_2
      74: invokestatic  #142                // Method org/apache/dubbo/common/utils/StringUtils.isEmpty:(Ljava/lang/String;)Z
      77: ifeq          130
      80: ldc           #182                // String POD_NAMESPACE
      82: invokestatic  #183                // Method java/lang/System.getenv:(Ljava/lang/String;)Ljava/lang/String;
      85: invokestatic  #142                // Method org/apache/dubbo/common/utils/StringUtils.isEmpty:(Ljava/lang/String;)Z
      88: ifeq          124
      91: getstatic     #41                 // Field logger:Lorg/apache/dubbo/common/logger/ErrorTypeAwareLogger;
      94: invokeinterface #184,  1          // InterfaceMethod org/apache/dubbo/common/logger/ErrorTypeAwareLogger.isWarnEnabled:()Z
      99: ifeq          118
     102: getstatic     #41                 // Field logger:Lorg/apache/dubbo/common/logger/ErrorTypeAwareLogger;
     105: ldc           #185                // String 5-5
     107: ldc           #43                 // String
     109: ldc           #43                 // String
     111: ldc           #186                // String Can not get env variable: POD_NAMESPACE, it may not be running in the K8S environment , finally use \'default\' replace.
     113: invokeinterface #126,  5          // InterfaceMethod org/apache/dubbo/common/logger/ErrorTypeAwareLogger.warn:(Ljava/lang/String;Ljava/lang/String;Ljava/lang/String;Ljava/lang/String;)V
     118: ldc           #187                // String default
     120: astore_2
     121: goto          130
     124: ldc           #182                // String POD_NAMESPACE
     126: invokestatic  #183                // Method java/lang/System.getenv:(Ljava/lang/String;)Ljava/lang/String;
     129: astore_2
     130: aload_1
     131: ldc           #188                // String provided-by
     133: invokeinterface #164,  2          // InterfaceMethod java/util/Map.get:(Ljava/lang/Object;)Ljava/lang/Object;
     138: checkcast     #152                // class java/lang/String
     141: astore_3
     142: ldc           #189                // String CLUSTER_DOMAIN
     144: invokestatic  #183                // Method java/lang/System.getenv:(Ljava/lang/String;)Ljava/lang/String;
     147: invokestatic  #190                // Method java/util/Optional.ofNullable:(Ljava/lang/Object;)Ljava/util/Optional;
     150: ldc           #191                // String cluster.local
     152: invokevirtual #192                // Method java/util/Optional.orElse:(Ljava/lang/Object;)Ljava/lang/Object;
     155: checkcast     #152                // class java/lang/String
     158: astore        4
     160: aload_0
     161: invokevirtual #193                // Method getProviderPort:()Ljava/lang/Integer;
     164: invokestatic  #190                // Method java/util/Optional.ofNullable:(Ljava/lang/Object;)Ljava/util/Optional;
     167: getstatic     #194                // Field org/apache/dubbo/common/constants/CommonConstants.DEFAULT_MESH_PORT:Ljava/lang/Integer;
     170: invokevirtual #192                // Method java/util/Optional.orElse:(Ljava/lang/Object;)Ljava/lang/Object;
     173: checkcast     #195                // class java/lang/Integer
     176: astore        5
     178: aload         5
     180: invokevirtual #196                // Method java/lang/Integer.intValue:()I
     183: iconst_m1
     184: if_icmple     192
     187: aload         5
     189: goto          195
     192: getstatic     #194                // Field org/apache/dubbo/common/constants/CommonConstants.DEFAULT_MESH_PORT:Ljava/lang/Integer;
     195: astore        5
     197: aload_0
     198: new           #24                 // class java/lang/StringBuilder
     201: dup
     202: invokespecial #25                 // Method java/lang/StringBuilder."<init>":()V
     205: ldc           #197                // String tri://
     207: invokevirtual #27                 // Method java/lang/StringBuilder.append:(Ljava/lang/String;)Ljava/lang/StringBuilder;
     210: aload_3
     211: invokevirtual #27                 // Method java/lang/StringBuilder.append:(Ljava/lang/String;)Ljava/lang/StringBuilder;
     214: ldc           #198                // String .
     216: invokevirtual #27                 // Method java/lang/StringBuilder.append:(Ljava/lang/String;)Ljava/lang/StringBuilder;
     219: aload_2
     220: invokevirtual #27                 // Method java/lang/StringBuilder.append:(Ljava/lang/String;)Ljava/lang/StringBuilder;
     223: ldc           #199                // String .svc.
     225: invokevirtual #27                 // Method java/lang/StringBuilder.append:(Ljava/lang/String;)Ljava/lang/StringBuilder;
     228: aload         4
     230: invokevirtual #27                 // Method java/lang/StringBuilder.append:(Ljava/lang/String;)Ljava/lang/StringBuilder;
     233: ldc           #200                // String :
     235: invokevirtual #27                 // Method java/lang/StringBuilder.append:(Ljava/lang/String;)Ljava/lang/StringBuilder;
     238: aload         5
     240: invokevirtual #201                // Method java/lang/StringBuilder.append:(Ljava/lang/Object;)Ljava/lang/StringBuilder;
     243: invokevirtual #30                 // Method java/lang/StringBuilder.toString:()Ljava/lang/String;
     246: putfield      #28                 // Field url:Ljava/lang/String;
     249: return

  private boolean checkMeshConfig(java.util.Map<java.lang.String, java.lang.String>);
    Code:
       0: ldc           #202                // String true
       2: aload_1
       3: ldc           #203                // String mesh-enable
       5: ldc           #153                // String false
       7: invokeinterface #204,  3          // InterfaceMethod java/util/Map.getOrDefault:(Ljava/lang/Object;Ljava/lang/Object;)Ljava/lang/Object;
      12: invokevirtual #67                 // Method java/lang/String.equals:(Ljava/lang/Object;)Z
      15: ifne          31
      18: aload_1
      19: ldc           #205                // String unloadClusterRelated
      21: ldc           #153                // String false
      23: invokeinterface #111,  3          // InterfaceMethod java/util/Map.put:(Ljava/lang/Object;Ljava/lang/Object;)Ljava/lang/Object;
      28: pop
      29: iconst_0
      30: ireturn
      31: aload_0
      32: invokevirtual #33                 // Method getScopeModel:()Lorg/apache/dubbo/rpc/model/ModuleModel;
      35: invokevirtual #206                // Method org/apache/dubbo/rpc/model/ModuleModel.getConfigManager:()Lorg/apache/dubbo/config/context/ModuleConfigManager;
      38: ldc           #207                // String tri
      40: invokevirtual #208                // Method org/apache/dubbo/config/context/ModuleConfigManager.getProtocol:(Ljava/lang/String;)Ljava/util/Optional;
      43: invokedynamic #209,  0            // InvokeDynamic #0:get:()Ljava/util/function/Supplier;
      48: invokevirtual #210                // Method java/util/Optional.orElseThrow:(Ljava/util/function/Supplier;)Ljava/lang/Object;
      51: pop
      52: aload_1
      53: ldc           #188                // String provided-by
      55: invokeinterface #164,  2          // InterfaceMethod java/util/Map.get:(Ljava/lang/Object;)Ljava/lang/Object;
      60: checkcast     #152                // class java/lang/String
      63: astore_2
      64: aload_2
      65: invokestatic  #142                // Method org/apache/dubbo/common/utils/StringUtils.isEmpty:(Ljava/lang/String;)Z
      68: ifeq          81
      71: new           #23                 // class java/lang/IllegalStateException
      74: dup
      75: ldc           #211                // String In mesh mode, the providedBy of ReferenceConfig is must be set
      77: invokespecial #31                 // Method java/lang/IllegalStateException."<init>":(Ljava/lang/String;)V
      80: athrow
      81: iconst_1
      82: ireturn

  private void parseUrl(java.util.Map<java.lang.String, java.lang.String>);
    Code:
       0: getstatic     #212                // Field org/apache/dubbo/common/constants/CommonConstants.SEMICOLON_SPLIT_PATTERN:Ljava/util/regex/Pattern;
       3: aload_0
       4: getfield      #28                 // Field url:Ljava/lang/String;
       7: invokevirtual #213                // Method java/util/regex/Pattern.split:(Ljava/lang/CharSequence;)[Ljava/lang/String;
      10: astore_2
      11: aload_2
      12: invokestatic  #214                // Method org/apache/dubbo/common/utils/ArrayUtils.isNotEmpty:([Ljava/lang/Object;)Z
      15: ifeq          177
      18: aload_2
      19: astore_3
      20: aload_3
      21: arraylength
      22: istore        4
      24: iconst_0
      25: istore        5
      27: iload         5
      29: iload         4
      31: if_icmpge     177
      34: aload_3
      35: iload         5
      37: aaload
      38: astore        6
      40: aload         6
      42: invokestatic  #215                // Method org/apache/dubbo/common/URL.valueOf:(Ljava/lang/String;)Lorg/apache/dubbo/common/URL;
      45: astore        7
      47: aload         7
      49: invokevirtual #216                // Method org/apache/dubbo/common/URL.getPath:()Ljava/lang/String;
      52: invokestatic  #142                // Method org/apache/dubbo/common/utils/StringUtils.isEmpty:(Ljava/lang/String;)Z
      55: ifeq          69
      58: aload         7
      60: aload_0
      61: getfield      #68                 // Field interfaceName:Ljava/lang/String;
      64: invokevirtual #217                // Method org/apache/dubbo/common/URL.setPath:(Ljava/lang/String;)Lorg/apache/dubbo/common/URL;
      67: astore        7
      69: aload         7
      71: aload_0
      72: invokevirtual #33                 // Method getScopeModel:()Lorg/apache/dubbo/rpc/model/ModuleModel;
      75: invokevirtual #173                // Method org/apache/dubbo/common/URL.setScopeModel:(Lorg/apache/dubbo/rpc/model/ScopeModel;)Lorg/apache/dubbo/common/URL;
      78: astore        7
      80: aload         7
      82: aload_0
      83: getfield      #47                 // Field consumerModel:Lorg/apache/dubbo/rpc/model/ConsumerModel;
      86: invokevirtual #174                // Method org/apache/dubbo/common/URL.setServiceModel:(Lorg/apache/dubbo/rpc/model/ServiceModel;)Lorg/apache/dubbo/common/URL;
      89: astore        7
      91: aload         7
      93: invokestatic  #218                // Method org/apache/dubbo/common/utils/UrlUtils.isRegistry:(Lorg/apache/dubbo/common/URL;)Z
      96: ifeq          120
      99: aload_0
     100: getfield      #156                // Field urls:Ljava/util/List;
     103: aload         7
     105: ldc           #219                // String refer
     107: aload_1
     108: invokevirtual #220                // Method org/apache/dubbo/common/URL.putAttribute:(Ljava/lang/String;Ljava/lang/Object;)Lorg/apache/dubbo/common/URL;
     111: invokeinterface #221,  2          // InterfaceMethod java/util/List.add:(Ljava/lang/Object;)Z
     116: pop
     117: goto          171
     120: aload_0
     121: invokevirtual #33                 // Method getScopeModel:()Lorg/apache/dubbo/rpc/model/ModuleModel;
     124: invokevirtual #222                // Method org/apache/dubbo/rpc/model/ModuleModel.getApplicationModel:()Lorg/apache/dubbo/rpc/model/ApplicationModel;
     127: invokevirtual #223                // Method org/apache/dubbo/rpc/model/ApplicationModel.getBeanFactory:()Lorg/apache/dubbo/common/beans/factory/ScopeBeanFactory;
     130: ldc           #224                // class org/apache/dubbo/rpc/cluster/support/ClusterUtils
     132: invokevirtual #225                // Method org/apache/dubbo/common/beans/factory/ScopeBeanFactory.getBean:(Ljava/lang/Class;)Ljava/lang/Object;
     135: checkcast     #224                // class org/apache/dubbo/rpc/cluster/support/ClusterUtils
     138: aload         7
     140: aload_1
     141: invokevirtual #226                // Method org/apache/dubbo/rpc/cluster/support/ClusterUtils.mergeUrl:(Lorg/apache/dubbo/common/URL;Ljava/util/Map;)Lorg/apache/dubbo/common/URL;
     144: astore        8
     146: aload         8
     148: ldc           #227                // String peer
     150: iconst_1
     151: invokestatic  #228                // Method java/lang/Boolean.valueOf:(Z)Ljava/lang/Boolean;
     154: invokevirtual #220                // Method org/apache/dubbo/common/URL.putAttribute:(Ljava/lang/String;Ljava/lang/Object;)Lorg/apache/dubbo/common/URL;
     157: astore        8
     159: aload_0
     160: getfield      #156                // Field urls:Ljava/util/List;
     163: aload         8
     165: invokeinterface #221,  2          // InterfaceMethod java/util/List.add:(Ljava/lang/Object;)Z
     170: pop
     171: iinc          5, 1
     174: goto          27
     177: return

  private void aggregateUrlFromRegistry(java.util.Map<java.lang.String, java.lang.String>);
    Code:
       0: aload_0
       1: invokevirtual #229                // Method checkRegistry:()V
       4: aload_0
       5: iconst_0
       6: invokestatic  #230                // Method org/apache/dubbo/config/utils/ConfigValidationUtils.loadRegistries:(Lorg/apache/dubbo/config/AbstractInterfaceConfig;Z)Ljava/util/List;
       9: astore_2
      10: aload_2
      11: invokestatic  #102                // Method org/apache/dubbo/common/utils/CollectionUtils.isNotEmpty:(Ljava/util/Collection;)Z
      14: ifeq          138
      17: aload_2
      18: invokeinterface #105,  1          // InterfaceMethod java/util/List.iterator:()Ljava/util/Iterator;
      23: astore_3
      24: aload_3
      25: invokeinterface #106,  1          // InterfaceMethod java/util/Iterator.hasNext:()Z
      30: ifeq          138
      33: aload_3
      34: invokeinterface #107,  1          // InterfaceMethod java/util/Iterator.next:()Ljava/lang/Object;
      39: checkcast     #231                // class org/apache/dubbo/common/URL
      42: astore        4
      44: aload_0
      45: aload         4
      47: invokestatic  #232                // Method org/apache/dubbo/config/utils/ConfigValidationUtils.loadMonitor:(Lorg/apache/dubbo/config/AbstractInterfaceConfig;Lorg/apache/dubbo/common/URL;)Lorg/apache/dubbo/common/URL;
      50: astore        5
      52: aload         5
      54: ifnull        68
      57: aload         4
      59: ldc           #233                // String monitor
      61: aload         5
      63: invokevirtual #220                // Method org/apache/dubbo/common/URL.putAttribute:(Ljava/lang/String;Ljava/lang/Object;)Lorg/apache/dubbo/common/URL;
      66: astore        4
      68: aload         4
      70: aload_0
      71: invokevirtual #33                 // Method getScopeModel:()Lorg/apache/dubbo/rpc/model/ModuleModel;
      74: invokevirtual #173                // Method org/apache/dubbo/common/URL.setScopeModel:(Lorg/apache/dubbo/rpc/model/ScopeModel;)Lorg/apache/dubbo/common/URL;
      77: astore        4
      79: aload         4
      81: aload_0
      82: getfield      #47                 // Field consumerModel:Lorg/apache/dubbo/rpc/model/ConsumerModel;
      85: invokevirtual #174                // Method org/apache/dubbo/common/URL.setServiceModel:(Lorg/apache/dubbo/rpc/model/ServiceModel;)Lorg/apache/dubbo/common/URL;
      88: astore        4
      90: aload_0
      91: invokevirtual #234                // Method isInjvm:()Ljava/lang/Boolean;
      94: ifnull        117
      97: aload_0
      98: invokevirtual #234                // Method isInjvm:()Ljava/lang/Boolean;
     101: invokevirtual #235                // Method java/lang/Boolean.booleanValue:()Z
     104: ifeq          117
     107: aload         4
     109: ldc           #236                // String injvm
     111: iconst_1
     112: invokevirtual #237                // Method org/apache/dubbo/common/URL.addParameter:(Ljava/lang/String;Z)Lorg/apache/dubbo/common/URL;
     115: astore        4
     117: aload_0
     118: getfield      #156                // Field urls:Ljava/util/List;
     121: aload         4
     123: ldc           #219                // String refer
     125: aload_1
     126: invokevirtual #220                // Method org/apache/dubbo/common/URL.putAttribute:(Ljava/lang/String;Ljava/lang/Object;)Lorg/apache/dubbo/common/URL;
     129: invokeinterface #221,  2          // InterfaceMethod java/util/List.add:(Ljava/lang/Object;)Z
     134: pop
     135: goto          24
     138: aload_0
     139: getfield      #156                // Field urls:Ljava/util/List;
     142: invokeinterface #238,  1          // InterfaceMethod java/util/List.isEmpty:()Z
     147: ifeq          217
     150: aload_0
     151: aload_1
     152: invokevirtual #239                // Method shouldJvmRefer:(Ljava/util/Map;)Z
     155: ifeq          217
     158: new           #231                // class org/apache/dubbo/common/URL
     161: dup
     162: ldc           #236                // String injvm
     164: ldc           #240                // String 127.0.0.1
     166: iconst_0
     167: aload_0
     168: getfield      #56                 // Field interfaceClass:Ljava/lang/Class;
     171: invokevirtual #125                // Method java/lang/Class.getName:()Ljava/lang/String;
     174: invokespecial #241                // Method org/apache/dubbo/common/URL."<init>":(Ljava/lang/String;Ljava/lang/String;ILjava/lang/String;)V
     177: aload_1
     178: invokevirtual #242                // Method org/apache/dubbo/common/URL.addParameters:(Ljava/util/Map;)Lorg/apache/dubbo/common/URL;
     181: astore_3
     182: aload_3
     183: aload_0
     184: invokevirtual #33                 // Method getScopeModel:()Lorg/apache/dubbo/rpc/model/ModuleModel;
     187: invokevirtual #173                // Method org/apache/dubbo/common/URL.setScopeModel:(Lorg/apache/dubbo/rpc/model/ScopeModel;)Lorg/apache/dubbo/common/URL;
     190: astore_3
     191: aload_3
     192: aload_0
     193: getfield      #47                 // Field consumerModel:Lorg/apache/dubbo/rpc/model/ConsumerModel;
     196: invokevirtual #174                // Method org/apache/dubbo/common/URL.setServiceModel:(Lorg/apache/dubbo/rpc/model/ServiceModel;)Lorg/apache/dubbo/common/URL;
     199: astore_3
     200: aload_0
     201: getfield      #156                // Field urls:Ljava/util/List;
     204: aload_3
     205: ldc           #219                // String refer
     207: aload_1
     208: invokevirtual #220                // Method org/apache/dubbo/common/URL.putAttribute:(Ljava/lang/String;Ljava/lang/Object;)Lorg/apache/dubbo/common/URL;
     211: invokeinterface #221,  2          // InterfaceMethod java/util/List.add:(Ljava/lang/Object;)Z
     216: pop
     217: aload_0
     218: getfield      #156                // Field urls:Ljava/util/List;
     221: invokeinterface #238,  1          // InterfaceMethod java/util/List.isEmpty:()Z
     226: ifeq          286
     229: new           #23                 // class java/lang/IllegalStateException
     232: dup
     233: new           #24                 // class java/lang/StringBuilder
     236: dup
     237: invokespecial #25                 // Method java/lang/StringBuilder."<init>":()V
     240: ldc           #243                // String No such any registry to reference
     242: invokevirtual #27                 // Method java/lang/StringBuilder.append:(Ljava/lang/String;)Ljava/lang/StringBuilder;
     245: aload_0
     246: getfield      #68                 // Field interfaceName:Ljava/lang/String;
     249: invokevirtual #27                 // Method java/lang/StringBuilder.append:(Ljava/lang/String;)Ljava/lang/StringBuilder;
     252: ldc           #244                // String  on the consumer
     254: invokevirtual #27                 // Method java/lang/StringBuilder.append:(Ljava/lang/String;)Ljava/lang/StringBuilder;
     257: invokestatic  #143                // Method org/apache/dubbo/common/utils/NetUtils.getLocalHost:()Ljava/lang/String;
     260: invokevirtual #27                 // Method java/lang/StringBuilder.append:(Ljava/lang/String;)Ljava/lang/StringBuilder;
     263: ldc           #245                // String  use dubbo version
     265: invokevirtual #27                 // Method java/lang/StringBuilder.append:(Ljava/lang/String;)Ljava/lang/StringBuilder;
     268: invokestatic  #246                // Method org/apache/dubbo/common/Version.getVersion:()Ljava/lang/String;
     271: invokevirtual #27                 // Method java/lang/StringBuilder.append:(Ljava/lang/String;)Ljava/lang/StringBuilder;
     274: ldc           #247                // String , please config <dubbo:registry address=\"...\" /> to your spring config.
     276: invokevirtual #27                 // Method java/lang/StringBuilder.append:(Ljava/lang/String;)Ljava/lang/StringBuilder;
     279: invokevirtual #30                 // Method java/lang/StringBuilder.toString:()Ljava/lang/String;
     282: invokespecial #31                 // Method java/lang/IllegalStateException."<init>":(Ljava/lang/String;)V
     285: athrow
     286: return

  private void createInvoker();
    Code:
       0: aload_0
       1: getfield      #156                // Field urls:Ljava/util/List;
       4: invokeinterface #248,  1          // InterfaceMethod java/util/List.size:()I
       9: iconst_1
      10: if_icmpne     112
      13: aload_0
      14: getfield      #156                // Field urls:Ljava/util/List;
      17: iconst_0
      18: invokeinterface #249,  2          // InterfaceMethod java/util/List.get:(I)Ljava/lang/Object;
      23: checkcast     #231                // class org/apache/dubbo/common/URL
      26: astore_1
      27: aload_0
      28: aload_0
      29: getfield      #16                 // Field protocolSPI:Lorg/apache/dubbo/rpc/Protocol;
      32: aload_0
      33: getfield      #56                 // Field interfaceClass:Ljava/lang/Class;
      36: aload_1
      37: invokeinterface #250,  3          // InterfaceMethod org/apache/dubbo/rpc/Protocol.refer:(Ljava/lang/Class;Lorg/apache/dubbo/common/URL;)Lorg/apache/dubbo/rpc/Invoker;
      42: putfield      #38                 // Field invoker:Lorg/apache/dubbo/rpc/Invoker;
      45: aload_1
      46: invokestatic  #218                // Method org/apache/dubbo/common/utils/UrlUtils.isRegistry:(Lorg/apache/dubbo/common/URL;)Z
      49: ifne          109
      52: aload_1
      53: ldc           #205                // String unloadClusterRelated
      55: iconst_0
      56: invokevirtual #251                // Method org/apache/dubbo/common/URL.getParameter:(Ljava/lang/String;Z)Z
      59: ifne          109
      62: new           #129                // class java/util/ArrayList
      65: dup
      66: invokespecial #252                // Method java/util/ArrayList."<init>":()V
      69: astore_2
      70: aload_2
      71: aload_0
      72: getfield      #38                 // Field invoker:Lorg/apache/dubbo/rpc/Invoker;
      75: invokeinterface #221,  2          // InterfaceMethod java/util/List.add:(Ljava/lang/Object;)Z
      80: pop
      81: aload_0
      82: aload_0
      83: invokevirtual #33                 // Method getScopeModel:()Lorg/apache/dubbo/rpc/model/ModuleModel;
      86: ldc           #254                // String failover
      88: invokestatic  #255                // InterfaceMethod org/apache/dubbo/rpc/cluster/Cluster.getCluster:(Lorg/apache/dubbo/rpc/model/ScopeModel;Ljava/lang/String;)Lorg/apache/dubbo/rpc/cluster/Cluster;
      91: new           #256                // class org/apache/dubbo/rpc/cluster/directory/StaticDirectory
      94: dup
      95: aload_1
      96: aload_2
      97: invokespecial #257                // Method org/apache/dubbo/rpc/cluster/directory/StaticDirectory."<init>":(Lorg/apache/dubbo/common/URL;Ljava/util/List;)V
     100: iconst_1
     101: invokeinterface #258,  3          // InterfaceMethod org/apache/dubbo/rpc/cluster/Cluster.join:(Lorg/apache/dubbo/rpc/cluster/Directory;Z)Lorg/apache/dubbo/rpc/Invoker;
     106: putfield      #38                 // Field invoker:Lorg/apache/dubbo/rpc/Invoker;
     109: goto          307
     112: new           #129                // class java/util/ArrayList
     115: dup
     116: invokespecial #252                // Method java/util/ArrayList."<init>":()V
     119: astore_1
     120: aconst_null
     121: astore_2
     122: aload_0
     123: getfield      #156                // Field urls:Ljava/util/List;
     126: invokeinterface #105,  1          // InterfaceMethod java/util/List.iterator:()Ljava/util/Iterator;
     131: astore_3
     132: aload_3
     133: invokeinterface #106,  1          // InterfaceMethod java/util/Iterator.hasNext:()Z
     138: ifeq          188
     141: aload_3
     142: invokeinterface #107,  1          // InterfaceMethod java/util/Iterator.next:()Ljava/lang/Object;
     147: checkcast     #231                // class org/apache/dubbo/common/URL
     150: astore        4
     152: aload_1
     153: aload_0
     154: getfield      #16                 // Field protocolSPI:Lorg/apache/dubbo/rpc/Protocol;
     157: aload_0
     158: getfield      #56                 // Field interfaceClass:Ljava/lang/Class;
     161: aload         4
     163: invokeinterface #250,  3          // InterfaceMethod org/apache/dubbo/rpc/Protocol.refer:(Ljava/lang/Class;Lorg/apache/dubbo/common/URL;)Lorg/apache/dubbo/rpc/Invoker;
     168: invokeinterface #221,  2          // InterfaceMethod java/util/List.add:(Ljava/lang/Object;)Z
     173: pop
     174: aload         4
     176: invokestatic  #218                // Method org/apache/dubbo/common/utils/UrlUtils.isRegistry:(Lorg/apache/dubbo/common/URL;)Z
     179: ifeq          185
     182: aload         4
     184: astore_2
     185: goto          132
     188: aload_2
     189: ifnull        234
     192: aload_2
     193: ldc_w         #259                // String cluster
     196: ldc_w         #261                // String zone-aware
     199: invokevirtual #262                // Method org/apache/dubbo/common/URL.getParameter:(Ljava/lang/String;Ljava/lang/String;)Ljava/lang/String;
     202: astore_3
     203: aload_0
     204: aload_2
     205: invokevirtual #263                // Method org/apache/dubbo/common/URL.getScopeModel:()Lorg/apache/dubbo/rpc/model/ScopeModel;
     208: aload_3
     209: iconst_0
     210: invokestatic  #264                // InterfaceMethod org/apache/dubbo/rpc/cluster/Cluster.getCluster:(Lorg/apache/dubbo/rpc/model/ScopeModel;Ljava/lang/String;Z)Lorg/apache/dubbo/rpc/cluster/Cluster;
     213: new           #256                // class org/apache/dubbo/rpc/cluster/directory/StaticDirectory
     216: dup
     217: aload_2
     218: aload_1
     219: invokespecial #257                // Method org/apache/dubbo/rpc/cluster/directory/StaticDirectory."<init>":(Lorg/apache/dubbo/common/URL;Ljava/util/List;)V
     222: iconst_0
     223: invokeinterface #258,  3          // InterfaceMethod org/apache/dubbo/rpc/cluster/Cluster.join:(Lorg/apache/dubbo/rpc/cluster/Directory;Z)Lorg/apache/dubbo/rpc/Invoker;
     228: putfield      #38                 // Field invoker:Lorg/apache/dubbo/rpc/Invoker;
     231: goto          307
     234: aload_1
     235: invokestatic  #265                // Method org/apache/dubbo/common/utils/CollectionUtils.isEmpty:(Ljava/util/Collection;)Z
     238: ifeq          252
     241: new           #145                // class java/lang/IllegalArgumentException
     244: dup
     245: ldc_w         #266                // String invokers == null
     248: invokespecial #147                // Method java/lang/IllegalArgumentException."<init>":(Ljava/lang/String;)V
     251: athrow
     252: aload_1
     253: iconst_0
     254: invokeinterface #249,  2          // InterfaceMethod java/util/List.get:(I)Ljava/lang/Object;
     259: checkcast     #267                // class org/apache/dubbo/rpc/Invoker
     262: invokeinterface #268,  1          // InterfaceMethod org/apache/dubbo/rpc/Invoker.getUrl:()Lorg/apache/dubbo/common/URL;
     267: astore_3
     268: aload_3
     269: ldc_w         #259                // String cluster
     272: ldc           #254                // String failover
     274: invokevirtual #262                // Method org/apache/dubbo/common/URL.getParameter:(Ljava/lang/String;Ljava/lang/String;)Ljava/lang/String;
     277: astore        4
     279: aload_0
     280: aload_0
     281: invokevirtual #33                 // Method getScopeModel:()Lorg/apache/dubbo/rpc/model/ModuleModel;
     284: aload         4
     286: invokestatic  #255                // InterfaceMethod org/apache/dubbo/rpc/cluster/Cluster.getCluster:(Lorg/apache/dubbo/rpc/model/ScopeModel;Ljava/lang/String;)Lorg/apache/dubbo/rpc/cluster/Cluster;
     289: new           #256                // class org/apache/dubbo/rpc/cluster/directory/StaticDirectory
     292: dup
     293: aload_3
     294: aload_1
     295: invokespecial #257                // Method org/apache/dubbo/rpc/cluster/directory/StaticDirectory."<init>":(Lorg/apache/dubbo/common/URL;Ljava/util/List;)V
     298: iconst_1
     299: invokeinterface #258,  3          // InterfaceMethod org/apache/dubbo/rpc/cluster/Cluster.join:(Lorg/apache/dubbo/rpc/cluster/Directory;Z)Lorg/apache/dubbo/rpc/Invoker;
     304: putfield      #38                 // Field invoker:Lorg/apache/dubbo/rpc/Invoker;
     307: return

  private void checkInvokerAvailable() throws java.lang.IllegalStateException;
    Code:
       0: aload_0
       1: invokevirtual #269                // Method shouldCheck:()Z
       4: ifeq          199
       7: aload_0
       8: getfield      #38                 // Field invoker:Lorg/apache/dubbo/rpc/Invoker;
      11: invokeinterface #270,  1          // InterfaceMethod org/apache/dubbo/rpc/Invoker.isAvailable:()Z
      16: ifne          199
      19: new           #23                 // class java/lang/IllegalStateException
      22: dup
      23: new           #24                 // class java/lang/StringBuilder
      26: dup
      27: invokespecial #25                 // Method java/lang/StringBuilder."<init>":()V
      30: ldc_w         #271                // String Failed to check the status of the service
      33: invokevirtual #27                 // Method java/lang/StringBuilder.append:(Ljava/lang/String;)Ljava/lang/StringBuilder;
      36: aload_0
      37: getfield      #68                 // Field interfaceName:Ljava/lang/String;
      40: invokevirtual #27                 // Method java/lang/StringBuilder.append:(Ljava/lang/String;)Ljava/lang/StringBuilder;
      43: ldc_w         #272                // String . No provider available for the service
      46: invokevirtual #27                 // Method java/lang/StringBuilder.append:(Ljava/lang/String;)Ljava/lang/StringBuilder;
      49: aload_0
      50: getfield      #273                // Field group:Ljava/lang/String;
      53: ifnonnull     61
      56: ldc           #43                 // String
      58: goto          84
      61: new           #24                 // class java/lang/StringBuilder
      64: dup
      65: invokespecial #25                 // Method java/lang/StringBuilder."<init>":()V
      68: aload_0
      69: getfield      #273                // Field group:Ljava/lang/String;
      72: invokevirtual #27                 // Method java/lang/StringBuilder.append:(Ljava/lang/String;)Ljava/lang/StringBuilder;
      75: ldc_w         #274                // String /
      78: invokevirtual #27                 // Method java/lang/StringBuilder.append:(Ljava/lang/String;)Ljava/lang/StringBuilder;
      81: invokevirtual #30                 // Method java/lang/StringBuilder.toString:()Ljava/lang/String;
      84: invokevirtual #27                 // Method java/lang/StringBuilder.append:(Ljava/lang/String;)Ljava/lang/StringBuilder;
      87: aload_0
      88: getfield      #68                 // Field interfaceName:Ljava/lang/String;
      91: invokevirtual #27                 // Method java/lang/StringBuilder.append:(Ljava/lang/String;)Ljava/lang/StringBuilder;
      94: aload_0
      95: getfield      #118                // Field version:Ljava/lang/String;
      98: ifnonnull     106
     101: ldc           #43                 // String
     103: goto          128
     106: new           #24                 // class java/lang/StringBuilder
     109: dup
     110: invokespecial #25                 // Method java/lang/StringBuilder."<init>":()V
     113: ldc           #200                // String :
     115: invokevirtual #27                 // Method java/lang/StringBuilder.append:(Ljava/lang/String;)Ljava/lang/StringBuilder;
     118: aload_0
     119: getfield      #118                // Field version:Ljava/lang/String;
     122: invokevirtual #27                 // Method java/lang/StringBuilder.append:(Ljava/lang/String;)Ljava/lang/StringBuilder;
     125: invokevirtual #30                 // Method java/lang/StringBuilder.toString:()Ljava/lang/String;
     128: invokevirtual #27                 // Method java/lang/StringBuilder.append:(Ljava/lang/String;)Ljava/lang/StringBuilder;
     131: ldc_w         #275                // String  from the url
     134: invokevirtual #27                 // Method java/lang/StringBuilder.append:(Ljava/lang/String;)Ljava/lang/StringBuilder;
     137: aload_0
     138: getfield      #38                 // Field invoker:Lorg/apache/dubbo/rpc/Invoker;
     141: invokeinterface #268,  1          // InterfaceMethod org/apache/dubbo/rpc/Invoker.getUrl:()Lorg/apache/dubbo/common/URL;
     146: invokevirtual #201                // Method java/lang/StringBuilder.append:(Ljava/lang/Object;)Ljava/lang/StringBuilder;
     149: ldc_w         #276                // String  to the consumer
     152: invokevirtual #27                 // Method java/lang/StringBuilder.append:(Ljava/lang/String;)Ljava/lang/StringBuilder;
     155: invokestatic  #143                // Method org/apache/dubbo/common/utils/NetUtils.getLocalHost:()Ljava/lang/String;
     158: invokevirtual #27                 // Method java/lang/StringBuilder.append:(Ljava/lang/String;)Ljava/lang/StringBuilder;
     161: ldc           #245                // String  use dubbo version
     163: invokevirtual #27                 // Method java/lang/StringBuilder.append:(Ljava/lang/String;)Ljava/lang/StringBuilder;
     166: invokestatic  #246                // Method org/apache/dubbo/common/Version.getVersion:()Ljava/lang/String;
     169: invokevirtual #27                 // Method java/lang/StringBuilder.append:(Ljava/lang/String;)Ljava/lang/StringBuilder;
     172: invokevirtual #30                 // Method java/lang/StringBuilder.toString:()Ljava/lang/String;
     175: invokespecial #31                 // Method java/lang/IllegalStateException."<init>":(Ljava/lang/String;)V
     178: astore_1
     179: getstatic     #41                 // Field logger:Lorg/apache/dubbo/common/logger/ErrorTypeAwareLogger;
     182: ldc           #97                 // String 2-2
     184: ldc_w         #277                // String provider not started
     187: ldc           #43                 // String
     189: ldc           #99                 // String No provider available.
     191: aload_1
     192: invokeinterface #100,  6          // InterfaceMethod org/apache/dubbo/common/logger/ErrorTypeAwareLogger.error:(Ljava/lang/String;Ljava/lang/String;Ljava/lang/String;Ljava/lang/String;Ljava/lang/Throwable;)V
     197: aload_1
     198: athrow
     199: return

  protected void checkAndUpdateSubConfigs();
    Code:
       0: aload_0
       1: getfield      #68                 // Field interfaceName:Ljava/lang/String;
       4: invokestatic  #142                // Method org/apache/dubbo/common/utils/StringUtils.isEmpty:(Ljava/lang/String;)Z
       7: ifeq          21
      10: new           #23                 // class java/lang/IllegalStateException
      13: dup
      14: ldc_w         #278                // String <dubbo:reference interface=\"\" /> interface not allow null!
      17: invokespecial #31                 // Method java/lang/IllegalStateException."<init>":(Ljava/lang/String;)V
      20: athrow
      21: aload_0
      22: invokevirtual #279                // Method completeCompoundConfigs:()V
      25: aload_0
      26: ldc_w         #280                // class org/apache/dubbo/config/ConfigInitializer
      29: invokevirtual #14                 // Method getExtensionLoader:(Ljava/lang/Class;)Lorg/apache/dubbo/common/extension/ExtensionLoader;
      32: ldc_w         #281                // String configInitializer://
      35: invokestatic  #215                // Method org/apache/dubbo/common/URL.valueOf:(Ljava/lang/String;)Lorg/apache/dubbo/common/URL;
      38: aconst_null
      39: checkcast     #282                // class "[Ljava/lang/String;"
      42: invokevirtual #283                // Method org/apache/dubbo/common/extension/ExtensionLoader.getActivateExtension:(Lorg/apache/dubbo/common/URL;[Ljava/lang/String;)Ljava/util/List;
      45: astore_1
      46: aload_1
      47: aload_0
      48: invokedynamic #284,  0            // InvokeDynamic #1:accept:(Lorg/apache/dubbo/config/ReferenceConfig;)Ljava/util/function/Consumer;
      53: invokeinterface #285,  2          // InterfaceMethod java/util/List.forEach:(Ljava/util/function/Consumer;)V
      58: aload_0
      59: invokevirtual #286                // Method getGeneric:()Ljava/lang/String;
      62: ifnonnull     83
      65: aload_0
      66: invokevirtual #287                // Method getConsumer:()Lorg/apache/dubbo/config/ConsumerConfig;
      69: ifnull        83
      72: aload_0
      73: aload_0
      74: invokevirtual #287                // Method getConsumer:()Lorg/apache/dubbo/config/ConsumerConfig;
      77: invokevirtual #288                // Method org/apache/dubbo/config/ConsumerConfig.getGeneric:()Ljava/lang/String;
      80: invokevirtual #289                // Method setGeneric:(Ljava/lang/String;)V
      83: aload_0
      84: getfield      #116                // Field generic:Ljava/lang/String;
      87: invokestatic  #117                // Method org/apache/dubbo/rpc/support/ProtocolUtils.isGeneric:(Ljava/lang/String;)Z
      90: ifeq          193
      93: aload_0
      94: getfield      #56                 // Field interfaceClass:Ljava/lang/Class;
      97: ifnull        183
     100: aload_0
     101: getfield      #56                 // Field interfaceClass:Ljava/lang/Class;
     104: ldc_w         #290                // class org/apache/dubbo/rpc/service/GenericService
     107: invokevirtual #291                // Method java/lang/Object.equals:(Ljava/lang/Object;)Z
     110: ifne          183
     113: getstatic     #41                 // Field logger:Lorg/apache/dubbo/common/logger/ErrorTypeAwareLogger;
     116: ldc_w         #292                // String 5-6
     119: ldc           #43                 // String
     121: ldc           #43                 // String
     123: ldc_w         #293                // String Found conflicting attributes for interface type: [interfaceClass=%s] and [generic=%s], because the \'generic\' attribute has higher priority than \'interfaceClass\', so change \'interfaceClass\' to \'%s\'. Note: it will make this reference bean as a candidate bean of type \'%s\' instead of \'%s\' when resolving dependency in Spring.
     126: iconst_5
     127: anewarray     #294                // class java/lang/Object
     130: dup
     131: iconst_0
     132: aload_0
     133: getfield      #56                 // Field interfaceClass:Ljava/lang/Class;
     136: invokevirtual #125                // Method java/lang/Class.getName:()Ljava/lang/String;
     139: aastore
     140: dup
     141: iconst_1
     142: aload_0
     143: getfield      #116                // Field generic:Ljava/lang/String;
     146: aastore
     147: dup
     148: iconst_2
     149: ldc_w         #290                // class org/apache/dubbo/rpc/service/GenericService
     152: invokevirtual #125                // Method java/lang/Class.getName:()Ljava/lang/String;
     155: aastore
     156: dup
     157: iconst_3
     158: ldc_w         #290                // class org/apache/dubbo/rpc/service/GenericService
     161: invokevirtual #125                // Method java/lang/Class.getName:()Ljava/lang/String;
     164: aastore
     165: dup
     166: iconst_4
     167: aload_0
     168: getfield      #56                 // Field interfaceClass:Ljava/lang/Class;
     171: invokevirtual #125                // Method java/lang/Class.getName:()Ljava/lang/String;
     174: aastore
     175: invokestatic  #295                // Method java/lang/String.format:(Ljava/lang/String;[Ljava/lang/Object;)Ljava/lang/String;
     178: invokeinterface #126,  5          // InterfaceMethod org/apache/dubbo/common/logger/ErrorTypeAwareLogger.warn:(Ljava/lang/String;Ljava/lang/String;Ljava/lang/String;Ljava/lang/String;)V
     183: aload_0
     184: ldc_w         #290                // class org/apache/dubbo/rpc/service/GenericService
     187: putfield      #56                 // Field interfaceClass:Ljava/lang/Class;
     190: goto          282
     193: aload_0
     194: invokevirtual #296                // Method getInterfaceClassLoader:()Ljava/lang/ClassLoader;
     197: ifnull        240
     200: aload_0
     201: getfield      #56                 // Field interfaceClass:Ljava/lang/Class;
     204: ifnull        221
     207: aload_0
     208: getfield      #56                 // Field interfaceClass:Ljava/lang/Class;
     211: invokevirtual #297                // Method java/lang/Class.getClassLoader:()Ljava/lang/ClassLoader;
     214: aload_0
     215: invokevirtual #296                // Method getInterfaceClassLoader:()Ljava/lang/ClassLoader;
     218: if_acmpeq     240
     221: aload_0
     222: aload_0
     223: getfield      #68                 // Field interfaceName:Ljava/lang/String;
     226: iconst_1
     227: aload_0
     228: invokevirtual #296                // Method getInterfaceClassLoader:()Ljava/lang/ClassLoader;
     231: invokestatic  #298                // Method java/lang/Class.forName:(Ljava/lang/String;ZLjava/lang/ClassLoader;)Ljava/lang/Class;
     234: putfield      #56                 // Field interfaceClass:Ljava/lang/Class;
     237: goto          265
     240: aload_0
     241: getfield      #56                 // Field interfaceClass:Ljava/lang/Class;
     244: ifnonnull     265
     247: aload_0
     248: aload_0
     249: getfield      #68                 // Field interfaceName:Ljava/lang/String;
     252: iconst_1
     253: invokestatic  #299                // Method java/lang/Thread.currentThread:()Ljava/lang/Thread;
     256: invokevirtual #300                // Method java/lang/Thread.getContextClassLoader:()Ljava/lang/ClassLoader;
     259: invokestatic  #298                // Method java/lang/Class.forName:(Ljava/lang/String;ZLjava/lang/ClassLoader;)Ljava/lang/Class;
     262: putfield      #56                 // Field interfaceClass:Ljava/lang/Class;
     265: goto          282
     268: astore_2
     269: new           #23                 // class java/lang/IllegalStateException
     272: dup
     273: aload_2
     274: invokevirtual #302                // Method java/lang/ClassNotFoundException.getMessage:()Ljava/lang/String;
     277: aload_2
     278: invokespecial #303                // Method java/lang/IllegalStateException."<init>":(Ljava/lang/String;Ljava/lang/Throwable;)V
     281: athrow
     282: aload_0
     283: aload_0
     284: getfield      #56                 // Field interfaceClass:Ljava/lang/Class;
     287: invokevirtual #304                // Method checkStubAndLocal:(Ljava/lang/Class;)V
     290: aload_0
     291: getfield      #56                 // Field interfaceClass:Ljava/lang/Class;
     294: aload_0
     295: invokestatic  #305                // Method org/apache/dubbo/config/utils/ConfigValidationUtils.checkMock:(Ljava/lang/Class;Lorg/apache/dubbo/config/AbstractInterfaceConfig;)V
     298: aload_0
     299: invokevirtual #306                // Method resolveFile:()V
     302: aload_0
     303: invokestatic  #307                // Method org/apache/dubbo/config/utils/ConfigValidationUtils.validateReferenceConfig:(Lorg/apache/dubbo/config/ReferenceConfig;)V
     306: aload_0
     307: invokespecial #308                // Method postProcessConfig:()V
     310: return
    Exception table:
       from    to  target type
         193   265   268   Class java/lang/ClassNotFoundException

  protected void postProcessRefresh();
    Code:
       0: aload_0
       1: invokespecial #309                // Method org/apache/dubbo/config/ReferenceConfigBase.postProcessRefresh:()V
       4: aload_0
       5: invokevirtual #310                // Method checkAndUpdateSubConfigs:()V
       8: return

  protected void completeCompoundConfigs();
    Code:
       0: aload_0
       1: aload_0
       2: getfield      #60                 // Field consumer:Lorg/apache/dubbo/config/ConsumerConfig;
       5: invokespecial #311                // Method org/apache/dubbo/config/ReferenceConfigBase.completeCompoundConfigs:(Lorg/apache/dubbo/config/AbstractInterfaceConfig;)V
       8: aload_0
       9: getfield      #60                 // Field consumer:Lorg/apache/dubbo/config/ConsumerConfig;
      12: ifnull        36
      15: aload_0
      16: getfield      #312                // Field registryIds:Ljava/lang/String;
      19: invokestatic  #142                // Method org/apache/dubbo/common/utils/StringUtils.isEmpty:(Ljava/lang/String;)Z
      22: ifeq          36
      25: aload_0
      26: aload_0
      27: getfield      #60                 // Field consumer:Lorg/apache/dubbo/config/ConsumerConfig;
      30: invokevirtual #313                // Method org/apache/dubbo/config/ConsumerConfig.getRegistryIds:()Ljava/lang/String;
      33: invokevirtual #314                // Method setRegistryIds:(Ljava/lang/String;)V
      36: return

  protected boolean shouldJvmRefer(java.util.Map<java.lang.String, java.lang.String>);
    Code:
       0: aload_0
       1: invokevirtual #234                // Method isInjvm:()Ljava/lang/Boolean;
       4: ifnonnull     53
       7: aload_0
       8: getfield      #28                 // Field url:Ljava/lang/String;
      11: invokestatic  #120                // Method org/apache/dubbo/common/utils/StringUtils.isNotEmpty:(Ljava/lang/String;)Z
      14: ifeq          22
      17: iconst_0
      18: istore_2
      19: goto          61
      22: new           #171                // class org/apache/dubbo/common/url/component/ServiceConfigURL
      25: dup
      26: ldc_w         #315                // String temp
      29: ldc_w         #316                // String localhost
      32: iconst_0
      33: aload_1
      34: invokespecial #317                // Method org/apache/dubbo/common/url/component/ServiceConfigURL."<init>":(Ljava/lang/String;Ljava/lang/String;ILjava/util/Map;)V
      37: astore_3
      38: aload_0
      39: invokevirtual #33                 // Method getScopeModel:()Lorg/apache/dubbo/rpc/model/ModuleModel;
      42: invokestatic  #318                // Method org/apache/dubbo/rpc/protocol/injvm/InjvmProtocol.getInjvmProtocol:(Lorg/apache/dubbo/rpc/model/ScopeModel;)Lorg/apache/dubbo/rpc/protocol/injvm/InjvmProtocol;
      45: aload_3
      46: invokevirtual #319                // Method org/apache/dubbo/rpc/protocol/injvm/InjvmProtocol.isInjvmRefer:(Lorg/apache/dubbo/common/URL;)Z
      49: istore_2
      50: goto          61
      53: aload_0
      54: invokevirtual #234                // Method isInjvm:()Ljava/lang/Boolean;
      57: invokevirtual #235                // Method java/lang/Boolean.booleanValue:()Z
      60: istore_2
      61: iload_2
      62: ireturn

  private void postProcessConfig();
    Code:
       0: aload_0
       1: ldc_w         #320                // class org/apache/dubbo/config/ConfigPostProcessor
       4: invokevirtual #14                 // Method getExtensionLoader:(Ljava/lang/Class;)Lorg/apache/dubbo/common/extension/ExtensionLoader;
       7: ldc_w         #321                // String configPostProcessor://
      10: invokestatic  #215                // Method org/apache/dubbo/common/URL.valueOf:(Ljava/lang/String;)Lorg/apache/dubbo/common/URL;
      13: aconst_null
      14: checkcast     #282                // class "[Ljava/lang/String;"
      17: invokevirtual #283                // Method org/apache/dubbo/common/extension/ExtensionLoader.getActivateExtension:(Lorg/apache/dubbo/common/URL;[Ljava/lang/String;)Ljava/util/List;
      20: astore_1
      21: aload_1
      22: aload_0
      23: invokedynamic #322,  0            // InvokeDynamic #2:accept:(Lorg/apache/dubbo/config/ReferenceConfig;)Ljava/util/function/Consumer;
      28: invokeinterface #285,  2          // InterfaceMethod java/util/List.forEach:(Ljava/util/function/Consumer;)V
      33: return

  public org.apache.dubbo.rpc.Invoker<?> getInvoker();
    Code:
       0: aload_0
       1: getfield      #38                 // Field invoker:Lorg/apache/dubbo/rpc/Invoker;
       4: areturn

  public java.lang.Runnable getDestroyRunner();
    Code:
       0: aload_0
       1: invokedynamic #323,  0            // InvokeDynamic #3:run:(Lorg/apache/dubbo/config/ReferenceConfig;)Ljava/lang/Runnable;
       6: areturn

  private void lambda$postProcessConfig$2(org.apache.dubbo.config.ConfigPostProcessor);
    Code:
       0: aload_1
       1: aload_0
       2: invokeinterface #324,  2          // InterfaceMethod org/apache/dubbo/config/ConfigPostProcessor.postProcessReferConfig:(Lorg/apache/dubbo/config/ReferenceConfig;)V
       7: return

  private void lambda$checkAndUpdateSubConfigs$1(org.apache.dubbo.config.ConfigInitializer);
    Code:
       0: aload_1
       1: aload_0
       2: invokeinterface #325,  2          // InterfaceMethod org/apache/dubbo/config/ConfigInitializer.initReferConfig:(Lorg/apache/dubbo/config/ReferenceConfig;)V
       7: return

  private static java.lang.IllegalStateException lambda$checkMeshConfig$0();
    Code:
       0: new           #23                 // class java/lang/IllegalStateException
       3: dup
       4: ldc_w         #326                // String In mesh mode, a triple protocol must be specified
       7: invokespecial #31                 // Method java/lang/IllegalStateException."<init>":(Ljava/lang/String;)V
      10: areturn

  static {};
    Code:
       0: ldc_w         #327                // class org/apache/dubbo/config/ReferenceConfig
       3: invokestatic  #328                // Method org/apache/dubbo/common/logger/LoggerFactory.getErrorTypeAwareLogger:(Ljava/lang/Class;)Lorg/apache/dubbo/common/logger/ErrorTypeAwareLogger;
       6: putstatic     #41                 // Field logger:Lorg/apache/dubbo/common/logger/ErrorTypeAwareLogger;
       9: return
}
