Compiled from "ReferenceConfigBase.java"
public abstract class org.apache.dubbo.config.ReferenceConfigBase<T> extends org.apache.dubbo.config.AbstractReferenceConfig {
  private static final long serialVersionUID;

  private static final java.lang.String ORIGIN_CONFIG;

  protected java.lang.Class<?> interfaceClass;

  protected java.lang.String url;

  protected org.apache.dubbo.config.ConsumerConfig consumer;

  protected java.lang.Boolean unloadClusterRelated;

  public org.apache.dubbo.config.ReferenceConfigBase();
    Code:
       0: aload_0
       1: invokespecial #3                  // Method org/apache/dubbo/config/AbstractReferenceConfig."<init>":()V
       4: aload_0
       5: new           #4                  // class org/apache/dubbo/rpc/model/ServiceMetadata
       8: dup
       9: invokespecial #5                  // Method org/apache/dubbo/rpc/model/ServiceMetadata."<init>":()V
      12: putfield      #6                  // Field serviceMetadata:Lorg/apache/dubbo/rpc/model/ServiceMetadata;
      15: aload_0
      16: getfield      #6                  // Field serviceMetadata:Lorg/apache/dubbo/rpc/model/ServiceMetadata;
      19: ldc           #8                  // String ORIGIN_CONFIG
      21: aload_0
      22: invokevirtual #9                  // Method org/apache/dubbo/rpc/model/ServiceMetadata.addAttribute:(Ljava/lang/String;Ljava/lang/Object;)V
      25: return

  public org.apache.dubbo.config.ReferenceConfigBase(org.apache.dubbo.rpc.model.ModuleModel);
    Code:
       0: aload_0
       1: aload_1
       2: invokespecial #10                 // Method org/apache/dubbo/config/AbstractReferenceConfig."<init>":(Lorg/apache/dubbo/rpc/model/ModuleModel;)V
       5: aload_0
       6: new           #4                  // class org/apache/dubbo/rpc/model/ServiceMetadata
       9: dup
      10: invokespecial #5                  // Method org/apache/dubbo/rpc/model/ServiceMetadata."<init>":()V
      13: putfield      #6                  // Field serviceMetadata:Lorg/apache/dubbo/rpc/model/ServiceMetadata;
      16: aload_0
      17: getfield      #6                  // Field serviceMetadata:Lorg/apache/dubbo/rpc/model/ServiceMetadata;
      20: ldc           #8                  // String ORIGIN_CONFIG
      22: aload_0
      23: invokevirtual #9                  // Method org/apache/dubbo/rpc/model/ServiceMetadata.addAttribute:(Ljava/lang/String;Ljava/lang/Object;)V
      26: return

  public org.apache.dubbo.config.ReferenceConfigBase(org.apache.dubbo.config.annotation.Reference);
    Code:
       0: aload_0
       1: invokespecial #3                  // Method org/apache/dubbo/config/AbstractReferenceConfig."<init>":()V
       4: aload_0
       5: new           #4                  // class org/apache/dubbo/rpc/model/ServiceMetadata
       8: dup
       9: invokespecial #5                  // Method org/apache/dubbo/rpc/model/ServiceMetadata."<init>":()V
      12: putfield      #6                  // Field serviceMetadata:Lorg/apache/dubbo/rpc/model/ServiceMetadata;
      15: aload_0
      16: getfield      #6                  // Field serviceMetadata:Lorg/apache/dubbo/rpc/model/ServiceMetadata;
      19: ldc           #8                  // String ORIGIN_CONFIG
      21: aload_0
      22: invokevirtual #9                  // Method org/apache/dubbo/rpc/model/ServiceMetadata.addAttribute:(Ljava/lang/String;Ljava/lang/Object;)V
      25: aload_0
      26: ldc           #11                 // class org/apache/dubbo/config/annotation/Reference
      28: aload_1
      29: invokevirtual #12                 // Method appendAnnotation:(Ljava/lang/Class;Ljava/lang/Object;)V
      32: aload_0
      33: aload_1
      34: invokeinterface #13,  1           // InterfaceMethod org/apache/dubbo/config/annotation/Reference.methods:()[Lorg/apache/dubbo/config/annotation/Method;
      39: invokestatic  #14                 // Method org/apache/dubbo/config/MethodConfig.constructMethodConfig:([Lorg/apache/dubbo/config/annotation/Method;)Ljava/util/List;
      42: invokevirtual #15                 // Method setMethods:(Ljava/util/List;)V
      45: return

  public org.apache.dubbo.config.ReferenceConfigBase(org.apache.dubbo.rpc.model.ModuleModel, org.apache.dubbo.config.annotation.Reference);
    Code:
       0: aload_0
       1: aload_1
       2: invokespecial #10                 // Method org/apache/dubbo/config/AbstractReferenceConfig."<init>":(Lorg/apache/dubbo/rpc/model/ModuleModel;)V
       5: aload_0
       6: new           #4                  // class org/apache/dubbo/rpc/model/ServiceMetadata
       9: dup
      10: invokespecial #5                  // Method org/apache/dubbo/rpc/model/ServiceMetadata."<init>":()V
      13: putfield      #6                  // Field serviceMetadata:Lorg/apache/dubbo/rpc/model/ServiceMetadata;
      16: aload_0
      17: getfield      #6                  // Field serviceMetadata:Lorg/apache/dubbo/rpc/model/ServiceMetadata;
      20: ldc           #8                  // String ORIGIN_CONFIG
      22: aload_0
      23: invokevirtual #9                  // Method org/apache/dubbo/rpc/model/ServiceMetadata.addAttribute:(Ljava/lang/String;Ljava/lang/Object;)V
      26: aload_0
      27: ldc           #11                 // class org/apache/dubbo/config/annotation/Reference
      29: aload_2
      30: invokevirtual #12                 // Method appendAnnotation:(Ljava/lang/Class;Ljava/lang/Object;)V
      33: aload_0
      34: aload_2
      35: invokeinterface #13,  1           // InterfaceMethod org/apache/dubbo/config/annotation/Reference.methods:()[Lorg/apache/dubbo/config/annotation/Method;
      40: invokestatic  #14                 // Method org/apache/dubbo/config/MethodConfig.constructMethodConfig:([Lorg/apache/dubbo/config/annotation/Method;)Ljava/util/List;
      43: invokevirtual #15                 // Method setMethods:(Ljava/util/List;)V
      46: return

  public boolean shouldCheck();
    Code:
       0: aload_0
       1: invokevirtual #16                 // Method checkDefault:()V
       4: aload_0
       5: invokevirtual #17                 // Method isCheck:()Ljava/lang/Boolean;
       8: astore_1
       9: aload_1
      10: ifnonnull     28
      13: aload_0
      14: invokevirtual #18                 // Method getConsumer:()Lorg/apache/dubbo/config/ConsumerConfig;
      17: ifnull        28
      20: aload_0
      21: invokevirtual #18                 // Method getConsumer:()Lorg/apache/dubbo/config/ConsumerConfig;
      24: invokevirtual #19                 // Method org/apache/dubbo/config/ConsumerConfig.isCheck:()Ljava/lang/Boolean;
      27: astore_1
      28: aload_1
      29: ifnonnull     37
      32: iconst_1
      33: invokestatic  #20                 // Method java/lang/Boolean.valueOf:(Z)Ljava/lang/Boolean;
      36: astore_1
      37: aload_1
      38: invokevirtual #21                 // Method java/lang/Boolean.booleanValue:()Z
      41: ireturn

  public boolean shouldInit();
    Code:
       0: aload_0
       1: invokevirtual #16                 // Method checkDefault:()V
       4: aload_0
       5: invokevirtual #22                 // Method isInit:()Ljava/lang/Boolean;
       8: astore_1
       9: aload_1
      10: ifnonnull     28
      13: aload_0
      14: invokevirtual #18                 // Method getConsumer:()Lorg/apache/dubbo/config/ConsumerConfig;
      17: ifnull        28
      20: aload_0
      21: invokevirtual #18                 // Method getConsumer:()Lorg/apache/dubbo/config/ConsumerConfig;
      24: invokevirtual #23                 // Method org/apache/dubbo/config/ConsumerConfig.isInit:()Ljava/lang/Boolean;
      27: astore_1
      28: aload_1
      29: ifnonnull     34
      32: iconst_1
      33: ireturn
      34: aload_1
      35: invokevirtual #21                 // Method java/lang/Boolean.booleanValue:()Z
      38: ireturn

  protected void preProcessRefresh();
    Code:
       0: aload_0
       1: invokespecial #24                 // Method org/apache/dubbo/config/AbstractReferenceConfig.preProcessRefresh:()V
       4: aload_0
       5: getfield      #25                 // Field consumer:Lorg/apache/dubbo/config/ConsumerConfig;
       8: ifnonnull     33
      11: aload_0
      12: aload_0
      13: invokevirtual #26                 // Method getModuleConfigManager:()Lorg/apache/dubbo/config/context/ModuleConfigManager;
      16: invokevirtual #27                 // Method org/apache/dubbo/config/context/ModuleConfigManager.getDefaultConsumer:()Ljava/util/Optional;
      19: invokedynamic #28,  0             // InvokeDynamic #0:get:()Ljava/util/function/Supplier;
      24: invokevirtual #29                 // Method java/util/Optional.orElseThrow:(Ljava/util/function/Supplier;)Ljava/lang/Object;
      27: checkcast     #30                 // class org/apache/dubbo/config/ConsumerConfig
      30: putfield      #25                 // Field consumer:Lorg/apache/dubbo/config/ConsumerConfig;
      33: aload_0
      34: aload_0
      35: invokespecial #31                 // Method org/apache/dubbo/config/AbstractReferenceConfig.getPrefixes:()Ljava/util/List;
      38: getstatic     #32                 // Field org/apache/dubbo/config/context/ConfigMode.OVERRIDE_IF_ABSENT:Lorg/apache/dubbo/config/context/ConfigMode;
      41: invokevirtual #33                 // Method refreshWithPrefixes:(Ljava/util/List;Lorg/apache/dubbo/config/context/ConfigMode;)V
      44: return

  public java.util.List<java.lang.String> getPrefixes();
    Code:
       0: new           #34                 // class java/util/ArrayList
       3: dup
       4: invokespecial #35                 // Method java/util/ArrayList."<init>":()V
       7: astore_1
       8: aload_1
       9: new           #36                 // class java/lang/StringBuilder
      12: dup
      13: invokespecial #37                 // Method java/lang/StringBuilder."<init>":()V
      16: ldc           #38                 // String dubbo.reference.
      18: invokevirtual #39                 // Method java/lang/StringBuilder.append:(Ljava/lang/String;)Ljava/lang/StringBuilder;
      21: aload_0
      22: getfield      #40                 // Field interfaceName:Ljava/lang/String;
      25: invokevirtual #39                 // Method java/lang/StringBuilder.append:(Ljava/lang/String;)Ljava/lang/StringBuilder;
      28: invokevirtual #41                 // Method java/lang/StringBuilder.toString:()Ljava/lang/String;
      31: invokeinterface #42,  2           // InterfaceMethod java/util/List.add:(Ljava/lang/Object;)Z
      36: pop
      37: aload_1
      38: areturn

  public java.util.Map<java.lang.String, java.lang.String> getMetaData();
    Code:
       0: aload_0
       1: aconst_null
       2: invokevirtual #43                 // Method getMetaData:(Ljava/lang/String;)Ljava/util/Map;
       5: areturn

  public java.util.Map<java.lang.String, java.lang.String> getMetaData(java.lang.String);
    Code:
       0: new           #44                 // class java/util/HashMap
       3: dup
       4: invokespecial #45                 // Method java/util/HashMap."<init>":()V
       7: astore_2
       8: aload_0
       9: invokevirtual #18                 // Method getConsumer:()Lorg/apache/dubbo/config/ConsumerConfig;
      12: astore_3
      13: aload_0
      14: invokevirtual #46                 // Method isRefreshed:()Z
      17: ifeq          34
      20: aload_3
      21: ifnonnull     34
      24: new           #47                 // class java/lang/IllegalStateException
      27: dup
      28: ldc           #48                 // String Consumer is not initialized
      30: invokespecial #49                 // Method java/lang/IllegalStateException."<init>":(Ljava/lang/String;)V
      33: athrow
      34: aload_2
      35: aload_3
      36: aload_1
      37: invokestatic  #50                 // Method appendAttributes:(Ljava/util/Map;Ljava/lang/Object;Ljava/lang/String;)V
      40: aload_2
      41: aload_0
      42: aload_1
      43: invokestatic  #50                 // Method appendAttributes:(Ljava/util/Map;Ljava/lang/Object;Ljava/lang/String;)V
      46: aload_2
      47: areturn

  public java.lang.Class<?> getServiceInterfaceClass();
    Code:
       0: aload_0
       1: getfield      #51                 // Field interfaceClass:Ljava/lang/Class;
       4: astore_1
       5: aload_0
       6: getfield      #51                 // Field interfaceClass:Ljava/lang/Class;
       9: ldc           #52                 // class org/apache/dubbo/rpc/service/GenericService
      11: if_acmpne     51
      14: aload_0
      15: invokevirtual #53                 // Method getInterfaceClassLoader:()Ljava/lang/ClassLoader;
      18: ifnull        37
      21: aload_0
      22: getfield      #40                 // Field interfaceName:Ljava/lang/String;
      25: iconst_0
      26: aload_0
      27: invokevirtual #53                 // Method getInterfaceClassLoader:()Ljava/lang/ClassLoader;
      30: invokestatic  #54                 // Method java/lang/Class.forName:(Ljava/lang/String;ZLjava/lang/ClassLoader;)Ljava/lang/Class;
      33: astore_1
      34: goto          45
      37: aload_0
      38: getfield      #40                 // Field interfaceName:Ljava/lang/String;
      41: invokestatic  #55                 // Method java/lang/Class.forName:(Ljava/lang/String;)Ljava/lang/Class;
      44: astore_1
      45: goto          51
      48: astore_2
      49: aconst_null
      50: areturn
      51: aload_1
      52: areturn
    Exception table:
       from    to  target type
          14    45    48   Class java/lang/ClassNotFoundException

  public java.lang.Class<?> getInterfaceClass();
    Code:
       0: aload_0
       1: getfield      #51                 // Field interfaceClass:Ljava/lang/Class;
       4: ifnull        12
       7: aload_0
       8: getfield      #51                 // Field interfaceClass:Ljava/lang/Class;
      11: areturn
      12: aload_0
      13: invokevirtual #57                 // Method getGeneric:()Ljava/lang/String;
      16: astore_1
      17: aload_1
      18: invokestatic  #58                 // Method org/apache/dubbo/common/utils/StringUtils.isBlank:(Ljava/lang/CharSequence;)Z
      21: ifeq          39
      24: aload_0
      25: invokevirtual #18                 // Method getConsumer:()Lorg/apache/dubbo/config/ConsumerConfig;
      28: ifnull        39
      31: aload_0
      32: invokevirtual #18                 // Method getConsumer:()Lorg/apache/dubbo/config/ConsumerConfig;
      35: invokevirtual #59                 // Method org/apache/dubbo/config/ConsumerConfig.getGeneric:()Ljava/lang/String;
      38: astore_1
      39: aload_0
      40: invokevirtual #53                 // Method getInterfaceClassLoader:()Ljava/lang/ClassLoader;
      43: ifnull        65
      46: aload_0
      47: aload_1
      48: aload_0
      49: getfield      #40                 // Field interfaceName:Ljava/lang/String;
      52: aload_0
      53: invokevirtual #53                 // Method getInterfaceClassLoader:()Ljava/lang/ClassLoader;
      56: invokestatic  #60                 // Method determineInterfaceClass:(Ljava/lang/String;Ljava/lang/String;Ljava/lang/ClassLoader;)Ljava/lang/Class;
      59: putfield      #51                 // Field interfaceClass:Ljava/lang/Class;
      62: goto          77
      65: aload_0
      66: aload_1
      67: aload_0
      68: getfield      #40                 // Field interfaceName:Ljava/lang/String;
      71: invokestatic  #61                 // Method determineInterfaceClass:(Ljava/lang/String;Ljava/lang/String;)Ljava/lang/Class;
      74: putfield      #51                 // Field interfaceClass:Ljava/lang/Class;
      77: aload_0
      78: getfield      #51                 // Field interfaceClass:Ljava/lang/Class;
      81: areturn

  public static java.lang.Class<?> determineInterfaceClass(java.lang.String, java.lang.String);
    Code:
       0: aload_0
       1: aload_1
       2: invokestatic  #62                 // Method org/apache/dubbo/common/utils/ClassUtils.getClassLoader:()Ljava/lang/ClassLoader;
       5: invokestatic  #60                 // Method determineInterfaceClass:(Ljava/lang/String;Ljava/lang/String;Ljava/lang/ClassLoader;)Ljava/lang/Class;
       8: areturn

  public static java.lang.Class<?> determineInterfaceClass(java.lang.String, java.lang.String, java.lang.ClassLoader);
    Code:
       0: aload_0
       1: invokestatic  #63                 // Method org/apache/dubbo/rpc/support/ProtocolUtils.isGeneric:(Ljava/lang/String;)Z
       4: ifeq          10
       7: ldc           #52                 // class org/apache/dubbo/rpc/service/GenericService
       9: areturn
      10: aload_1
      11: invokestatic  #64                 // Method org/apache/dubbo/common/utils/StringUtils.isNotEmpty:(Ljava/lang/String;)Z
      14: ifeq          24
      17: aload_1
      18: iconst_1
      19: aload_2
      20: invokestatic  #54                 // Method java/lang/Class.forName:(Ljava/lang/String;ZLjava/lang/ClassLoader;)Ljava/lang/Class;
      23: areturn
      24: goto          41
      27: astore_3
      28: new           #47                 // class java/lang/IllegalStateException
      31: dup
      32: aload_3
      33: invokevirtual #65                 // Method java/lang/ClassNotFoundException.getMessage:()Ljava/lang/String;
      36: aload_3
      37: invokespecial #66                 // Method java/lang/IllegalStateException."<init>":(Ljava/lang/String;Ljava/lang/Throwable;)V
      40: athrow
      41: aconst_null
      42: areturn
    Exception table:
       from    to  target type
          10    23    27   Class java/lang/ClassNotFoundException

  protected void postProcessAfterScopeModelChanged(org.apache.dubbo.rpc.model.ScopeModel, org.apache.dubbo.rpc.model.ScopeModel);
    Code:
       0: aload_0
       1: aload_1
       2: aload_2
       3: invokespecial #67                 // Method org/apache/dubbo/config/AbstractReferenceConfig.postProcessAfterScopeModelChanged:(Lorg/apache/dubbo/rpc/model/ScopeModel;Lorg/apache/dubbo/rpc/model/ScopeModel;)V
       6: aload_0
       7: getfield      #25                 // Field consumer:Lorg/apache/dubbo/config/ConsumerConfig;
      10: ifnull        38
      13: aload_0
      14: getfield      #25                 // Field consumer:Lorg/apache/dubbo/config/ConsumerConfig;
      17: invokevirtual #68                 // Method org/apache/dubbo/config/ConsumerConfig.getScopeModel:()Lorg/apache/dubbo/rpc/model/ModuleModel;
      20: aload_0
      21: invokevirtual #69                 // Method getScopeModel:()Lorg/apache/dubbo/rpc/model/ModuleModel;
      24: if_acmpeq     38
      27: aload_0
      28: getfield      #25                 // Field consumer:Lorg/apache/dubbo/config/ConsumerConfig;
      31: aload_0
      32: invokevirtual #69                 // Method getScopeModel:()Lorg/apache/dubbo/rpc/model/ModuleModel;
      35: invokevirtual #70                 // Method org/apache/dubbo/config/ConsumerConfig.setScopeModel:(Lorg/apache/dubbo/rpc/model/ScopeModel;)V
      38: return

  public void setInterface(java.lang.Class<?>);
    Code:
       0: aload_1
       1: ifnull        43
       4: aload_1
       5: invokevirtual #71                 // Method java/lang/Class.isInterface:()Z
       8: ifne          43
      11: new           #47                 // class java/lang/IllegalStateException
      14: dup
      15: new           #36                 // class java/lang/StringBuilder
      18: dup
      19: invokespecial #37                 // Method java/lang/StringBuilder."<init>":()V
      22: ldc           #72                 // String The interface class
      24: invokevirtual #39                 // Method java/lang/StringBuilder.append:(Ljava/lang/String;)Ljava/lang/StringBuilder;
      27: aload_1
      28: invokevirtual #73                 // Method java/lang/StringBuilder.append:(Ljava/lang/Object;)Ljava/lang/StringBuilder;
      31: ldc           #74                 // String  is not a interface!
      33: invokevirtual #39                 // Method java/lang/StringBuilder.append:(Ljava/lang/String;)Ljava/lang/StringBuilder;
      36: invokevirtual #41                 // Method java/lang/StringBuilder.toString:()Ljava/lang/String;
      39: invokespecial #49                 // Method java/lang/IllegalStateException."<init>":(Ljava/lang/String;)V
      42: athrow
      43: aload_0
      44: aload_1
      45: ifnonnull     52
      48: aconst_null
      49: goto          56
      52: aload_1
      53: invokevirtual #75                 // Method java/lang/Class.getName:()Ljava/lang/String;
      56: invokevirtual #76                 // Method setInterface:(Ljava/lang/String;)V
      59: aload_0
      60: aload_1
      61: putfield      #51                 // Field interfaceClass:Ljava/lang/Class;
      64: aload_0
      65: invokevirtual #53                 // Method getInterfaceClassLoader:()Ljava/lang/ClassLoader;
      68: ifnonnull     90
      71: aload_0
      72: aload_1
      73: ifnonnull     80
      76: aconst_null
      77: goto          84
      80: aload_1
      81: invokevirtual #77                 // Method java/lang/Class.getClassLoader:()Ljava/lang/ClassLoader;
      84: invokevirtual #78                 // Method setInterfaceClassLoader:(Ljava/lang/ClassLoader;)V
      87: goto          133
      90: aload_1
      91: ifnull        133
      94: aload_1
      95: aload_1
      96: invokevirtual #75                 // Method java/lang/Class.getName:()Ljava/lang/String;
      99: iconst_0
     100: aload_0
     101: invokevirtual #53                 // Method getInterfaceClassLoader:()Ljava/lang/ClassLoader;
     104: invokestatic  #54                 // Method java/lang/Class.forName:(Ljava/lang/String;ZLjava/lang/ClassLoader;)Ljava/lang/Class;
     107: invokevirtual #79                 // Method java/lang/Object.equals:(Ljava/lang/Object;)Z
     110: ifne          121
     113: aload_0
     114: aload_1
     115: invokevirtual #77                 // Method java/lang/Class.getClassLoader:()Ljava/lang/ClassLoader;
     118: invokevirtual #78                 // Method setInterfaceClassLoader:(Ljava/lang/ClassLoader;)V
     121: goto          133
     124: astore_2
     125: aload_0
     126: aload_1
     127: invokevirtual #77                 // Method java/lang/Class.getClassLoader:()Ljava/lang/ClassLoader;
     130: invokevirtual #78                 // Method setInterfaceClassLoader:(Ljava/lang/ClassLoader;)V
     133: return
    Exception table:
       from    to  target type
          94   121   124   Class java/lang/ClassNotFoundException

  public java.lang.String getUrl();
    Code:
       0: aload_0
       1: getfield      #80                 // Field url:Ljava/lang/String;
       4: areturn

  public void setUrl(java.lang.String);
    Code:
       0: aload_0
       1: aload_1
       2: putfield      #80                 // Field url:Ljava/lang/String;
       5: return

  public org.apache.dubbo.config.ConsumerConfig getConsumer();
    Code:
       0: aload_0
       1: getfield      #25                 // Field consumer:Lorg/apache/dubbo/config/ConsumerConfig;
       4: areturn

  public void setConsumer(org.apache.dubbo.config.ConsumerConfig);
    Code:
       0: aload_0
       1: aload_1
       2: putfield      #25                 // Field consumer:Lorg/apache/dubbo/config/ConsumerConfig;
       5: return

  public java.lang.Boolean getUnloadClusterRelated();
    Code:
       0: aload_0
       1: getfield      #81                 // Field unloadClusterRelated:Ljava/lang/Boolean;
       4: areturn

  public void setUnloadClusterRelated(java.lang.Boolean);
    Code:
       0: aload_0
       1: aload_1
       2: putfield      #81                 // Field unloadClusterRelated:Ljava/lang/Boolean;
       5: return

  public org.apache.dubbo.rpc.model.ServiceMetadata getServiceMetadata();
    Code:
       0: aload_0
       1: getfield      #6                  // Field serviceMetadata:Lorg/apache/dubbo/rpc/model/ServiceMetadata;
       4: areturn

  protected void resolveFile();
    Code:
       0: aload_0
       1: getfield      #40                 // Field interfaceName:Ljava/lang/String;
       4: invokestatic  #82                 // Method java/lang/System.getProperty:(Ljava/lang/String;)Ljava/lang/String;
       7: astore_1
       8: aconst_null
       9: astore_2
      10: aload_1
      11: invokestatic  #83                 // Method org/apache/dubbo/common/utils/StringUtils.isEmpty:(Ljava/lang/String;)Z
      14: ifeq          245
      17: ldc           #84                 // String dubbo.resolve.file
      19: invokestatic  #82                 // Method java/lang/System.getProperty:(Ljava/lang/String;)Ljava/lang/String;
      22: astore_2
      23: aload_2
      24: invokestatic  #83                 // Method org/apache/dubbo/common/utils/StringUtils.isEmpty:(Ljava/lang/String;)Z
      27: ifeq          64
      30: new           #85                 // class java/io/File
      33: dup
      34: new           #85                 // class java/io/File
      37: dup
      38: ldc           #86                 // String user.home
      40: invokestatic  #82                 // Method java/lang/System.getProperty:(Ljava/lang/String;)Ljava/lang/String;
      43: invokespecial #87                 // Method java/io/File."<init>":(Ljava/lang/String;)V
      46: ldc           #88                 // String dubbo-resolve.properties
      48: invokespecial #89                 // Method java/io/File."<init>":(Ljava/io/File;Ljava/lang/String;)V
      51: astore_3
      52: aload_3
      53: invokevirtual #90                 // Method java/io/File.exists:()Z
      56: ifeq          64
      59: aload_3
      60: invokevirtual #91                 // Method java/io/File.getAbsolutePath:()Ljava/lang/String;
      63: astore_2
      64: aload_2
      65: ifnull        245
      68: aload_2
      69: invokevirtual #92                 // Method java/lang/String.length:()I
      72: ifle          245
      75: new           #93                 // class org/apache/dubbo/common/utils/RegexProperties
      78: dup
      79: invokespecial #94                 // Method org/apache/dubbo/common/utils/RegexProperties."<init>":()V
      82: astore_3
      83: new           #95                 // class java/io/FileInputStream
      86: dup
      87: aload_2
      88: invokespecial #96                 // Method java/io/FileInputStream."<init>":(Ljava/lang/String;)V
      91: astore        4
      93: aconst_null
      94: astore        5
      96: aload_3
      97: aload         4
      99: invokevirtual #97                 // Method java/util/Properties.load:(Ljava/io/InputStream;)V
     102: aload         4
     104: ifnull        189
     107: aload         5
     109: ifnull        132
     112: aload         4
     114: invokevirtual #98                 // Method java/io/FileInputStream.close:()V
     117: goto          189
     120: astore        6
     122: aload         5
     124: aload         6
     126: invokevirtual #100                // Method java/lang/Throwable.addSuppressed:(Ljava/lang/Throwable;)V
     129: goto          189
     132: aload         4
     134: invokevirtual #98                 // Method java/io/FileInputStream.close:()V
     137: goto          189
     140: astore        6
     142: aload         6
     144: astore        5
     146: aload         6
     148: athrow
     149: astore        7
     151: aload         4
     153: ifnull        186
     156: aload         5
     158: ifnull        181
     161: aload         4
     163: invokevirtual #98                 // Method java/io/FileInputStream.close:()V
     166: goto          186
     169: astore        8
     171: aload         5
     173: aload         8
     175: invokevirtual #100                // Method java/lang/Throwable.addSuppressed:(Ljava/lang/Throwable;)V
     178: goto          186
     181: aload         4
     183: invokevirtual #98                 // Method java/io/FileInputStream.close:()V
     186: aload         7
     188: athrow
     189: goto          236
     192: astore        4
     194: new           #47                 // class java/lang/IllegalStateException
     197: dup
     198: new           #36                 // class java/lang/StringBuilder
     201: dup
     202: invokespecial #37                 // Method java/lang/StringBuilder."<init>":()V
     205: ldc           #102                // String Failed to load
     207: invokevirtual #39                 // Method java/lang/StringBuilder.append:(Ljava/lang/String;)Ljava/lang/StringBuilder;
     210: aload_2
     211: invokevirtual #39                 // Method java/lang/StringBuilder.append:(Ljava/lang/String;)Ljava/lang/StringBuilder;
     214: ldc           #103                // String , cause:
     216: invokevirtual #39                 // Method java/lang/StringBuilder.append:(Ljava/lang/String;)Ljava/lang/StringBuilder;
     219: aload         4
     221: invokevirtual #104                // Method java/io/IOException.getMessage:()Ljava/lang/String;
     224: invokevirtual #39                 // Method java/lang/StringBuilder.append:(Ljava/lang/String;)Ljava/lang/StringBuilder;
     227: invokevirtual #41                 // Method java/lang/StringBuilder.toString:()Ljava/lang/String;
     230: aload         4
     232: invokespecial #66                 // Method java/lang/IllegalStateException."<init>":(Ljava/lang/String;Ljava/lang/Throwable;)V
     235: athrow
     236: aload_3
     237: aload_0
     238: getfield      #40                 // Field interfaceName:Ljava/lang/String;
     241: invokevirtual #105                // Method java/util/Properties.getProperty:(Ljava/lang/String;)Ljava/lang/String;
     244: astore_1
     245: aload_1
     246: invokestatic  #64                 // Method org/apache/dubbo/common/utils/StringUtils.isNotEmpty:(Ljava/lang/String;)Z
     249: ifeq          384
     252: aload_0
     253: aload_1
     254: putfield      #80                 // Field url:Ljava/lang/String;
     257: getstatic     #106                // Field logger:Lorg/apache/dubbo/common/logger/ErrorTypeAwareLogger;
     260: invokeinterface #107,  1          // InterfaceMethod org/apache/dubbo/common/logger/ErrorTypeAwareLogger.isWarnEnabled:()Z
     265: ifeq          384
     268: aload_2
     269: ifnull        334
     272: getstatic     #106                // Field logger:Lorg/apache/dubbo/common/logger/ErrorTypeAwareLogger;
     275: ldc           #108                // String 0-12
     277: ldc           #109                // String
     279: ldc           #109                // String
     281: new           #36                 // class java/lang/StringBuilder
     284: dup
     285: invokespecial #37                 // Method java/lang/StringBuilder."<init>":()V
     288: ldc           #110                // String Using default dubbo resolve file
     290: invokevirtual #39                 // Method java/lang/StringBuilder.append:(Ljava/lang/String;)Ljava/lang/StringBuilder;
     293: aload_2
     294: invokevirtual #39                 // Method java/lang/StringBuilder.append:(Ljava/lang/String;)Ljava/lang/StringBuilder;
     297: ldc           #111                // String  replace
     299: invokevirtual #39                 // Method java/lang/StringBuilder.append:(Ljava/lang/String;)Ljava/lang/StringBuilder;
     302: aload_0
     303: getfield      #40                 // Field interfaceName:Ljava/lang/String;
     306: invokevirtual #39                 // Method java/lang/StringBuilder.append:(Ljava/lang/String;)Ljava/lang/StringBuilder;
     309: ldc           #109                // String
     311: invokevirtual #39                 // Method java/lang/StringBuilder.append:(Ljava/lang/String;)Ljava/lang/StringBuilder;
     314: aload_1
     315: invokevirtual #39                 // Method java/lang/StringBuilder.append:(Ljava/lang/String;)Ljava/lang/StringBuilder;
     318: ldc           #112                // String  to p2p invoke remote service.
     320: invokevirtual #39                 // Method java/lang/StringBuilder.append:(Ljava/lang/String;)Ljava/lang/StringBuilder;
     323: invokevirtual #41                 // Method java/lang/StringBuilder.toString:()Ljava/lang/String;
     326: invokeinterface #113,  5          // InterfaceMethod org/apache/dubbo/common/logger/ErrorTypeAwareLogger.warn:(Ljava/lang/String;Ljava/lang/String;Ljava/lang/String;Ljava/lang/String;)V
     331: goto          384
     334: getstatic     #106                // Field logger:Lorg/apache/dubbo/common/logger/ErrorTypeAwareLogger;
     337: ldc           #108                // String 0-12
     339: ldc           #109                // String
     341: ldc           #109                // String
     343: new           #36                 // class java/lang/StringBuilder
     346: dup
     347: invokespecial #37                 // Method java/lang/StringBuilder."<init>":()V
     350: ldc           #114                // String Using -D
     352: invokevirtual #39                 // Method java/lang/StringBuilder.append:(Ljava/lang/String;)Ljava/lang/StringBuilder;
     355: aload_0
     356: getfield      #40                 // Field interfaceName:Ljava/lang/String;
     359: invokevirtual #39                 // Method java/lang/StringBuilder.append:(Ljava/lang/String;)Ljava/lang/StringBuilder;
     362: ldc           #115                // String =
     364: invokevirtual #39                 // Method java/lang/StringBuilder.append:(Ljava/lang/String;)Ljava/lang/StringBuilder;
     367: aload_1
     368: invokevirtual #39                 // Method java/lang/StringBuilder.append:(Ljava/lang/String;)Ljava/lang/StringBuilder;
     371: ldc           #112                // String  to p2p invoke remote service.
     373: invokevirtual #39                 // Method java/lang/StringBuilder.append:(Ljava/lang/String;)Ljava/lang/StringBuilder;
     376: invokevirtual #41                 // Method java/lang/StringBuilder.toString:()Ljava/lang/String;
     379: invokeinterface #113,  5          // InterfaceMethod org/apache/dubbo/common/logger/ErrorTypeAwareLogger.warn:(Ljava/lang/String;Ljava/lang/String;Ljava/lang/String;Ljava/lang/String;)V
     384: return
    Exception table:
       from    to  target type
         112   117   120   Class java/lang/Throwable
          96   102   140   Class java/lang/Throwable
          96   102   149   any
         161   166   169   Class java/lang/Throwable
         140   151   149   any
          83   189   192   Class java/io/IOException

  protected void computeValidRegistryIds();
    Code:
       0: aload_0
       1: getfield      #25                 // Field consumer:Lorg/apache/dubbo/config/ConsumerConfig;
       4: ifnull        36
       7: aload_0
       8: invokevirtual #116                // Method notHasSelfRegistryProperty:()Z
      11: ifeq          36
      14: aload_0
      15: aload_0
      16: getfield      #25                 // Field consumer:Lorg/apache/dubbo/config/ConsumerConfig;
      19: invokevirtual #117                // Method org/apache/dubbo/config/ConsumerConfig.getRegistries:()Ljava/util/List;
      22: invokevirtual #118                // Method setRegistries:(Ljava/util/List;)V
      25: aload_0
      26: aload_0
      27: getfield      #25                 // Field consumer:Lorg/apache/dubbo/config/ConsumerConfig;
      30: invokevirtual #119                // Method org/apache/dubbo/config/ConsumerConfig.getRegistryIds:()Ljava/lang/String;
      33: invokevirtual #120                // Method setRegistryIds:(Ljava/lang/String;)V
      36: aload_0
      37: invokespecial #121                // Method org/apache/dubbo/config/AbstractReferenceConfig.computeValidRegistryIds:()V
      40: return

  public java.lang.String getUniqueServiceName();
    Code:
       0: aload_0
       1: getfield      #40                 // Field interfaceName:Ljava/lang/String;
       4: ifnull        25
       7: aload_0
       8: getfield      #40                 // Field interfaceName:Ljava/lang/String;
      11: aload_0
      12: invokevirtual #122                // Method getGroup:()Ljava/lang/String;
      15: aload_0
      16: invokevirtual #123                // Method getVersion:()Ljava/lang/String;
      19: invokestatic  #124                // Method org/apache/dubbo/common/URL.buildKey:(Ljava/lang/String;Ljava/lang/String;Ljava/lang/String;)Ljava/lang/String;
      22: goto          26
      25: aconst_null
      26: areturn

  public java.lang.String getVersion();
    Code:
       0: aload_0
       1: getfield      #125                // Field version:Ljava/lang/String;
       4: invokestatic  #83                 // Method org/apache/dubbo/common/utils/StringUtils.isEmpty:(Ljava/lang/String;)Z
       7: ifeq          34
      10: aload_0
      11: getfield      #25                 // Field consumer:Lorg/apache/dubbo/config/ConsumerConfig;
      14: ifnull        27
      17: aload_0
      18: getfield      #25                 // Field consumer:Lorg/apache/dubbo/config/ConsumerConfig;
      21: invokevirtual #126                // Method org/apache/dubbo/config/ConsumerConfig.getVersion:()Ljava/lang/String;
      24: goto          38
      27: aload_0
      28: getfield      #125                // Field version:Ljava/lang/String;
      31: goto          38
      34: aload_0
      35: getfield      #125                // Field version:Ljava/lang/String;
      38: areturn

  public java.lang.String getGroup();
    Code:
       0: aload_0
       1: getfield      #127                // Field group:Ljava/lang/String;
       4: invokestatic  #83                 // Method org/apache/dubbo/common/utils/StringUtils.isEmpty:(Ljava/lang/String;)Z
       7: ifeq          34
      10: aload_0
      11: getfield      #25                 // Field consumer:Lorg/apache/dubbo/config/ConsumerConfig;
      14: ifnull        27
      17: aload_0
      18: getfield      #25                 // Field consumer:Lorg/apache/dubbo/config/ConsumerConfig;
      21: invokevirtual #128                // Method org/apache/dubbo/config/ConsumerConfig.getGroup:()Ljava/lang/String;
      24: goto          38
      27: aload_0
      28: getfield      #127                // Field group:Ljava/lang/String;
      31: goto          38
      34: aload_0
      35: getfield      #127                // Field group:Ljava/lang/String;
      38: areturn

  public java.lang.Boolean shouldReferAsync();
    Code:
       0: aload_0
       1: invokevirtual #129                // Method getReferAsync:()Ljava/lang/Boolean;
       4: astore_1
       5: aload_1
       6: ifnonnull     48
       9: aload_0
      10: getfield      #25                 // Field consumer:Lorg/apache/dubbo/config/ConsumerConfig;
      13: ifnull        43
      16: aload_0
      17: getfield      #25                 // Field consumer:Lorg/apache/dubbo/config/ConsumerConfig;
      20: invokevirtual #130                // Method org/apache/dubbo/config/ConsumerConfig.getReferAsync:()Ljava/lang/Boolean;
      23: ifnull        43
      26: aload_0
      27: getfield      #25                 // Field consumer:Lorg/apache/dubbo/config/ConsumerConfig;
      30: invokevirtual #130                // Method org/apache/dubbo/config/ConsumerConfig.getReferAsync:()Ljava/lang/Boolean;
      33: invokevirtual #21                 // Method java/lang/Boolean.booleanValue:()Z
      36: ifeq          43
      39: iconst_1
      40: goto          44
      43: iconst_0
      44: invokestatic  #20                 // Method java/lang/Boolean.valueOf:(Z)Ljava/lang/Boolean;
      47: astore_1
      48: aload_1
      49: areturn

  public abstract T get();

  public void destroy();
    Code:
       0: aload_0
       1: invokevirtual #26                 // Method getModuleConfigManager:()Lorg/apache/dubbo/config/context/ModuleConfigManager;
       4: aload_0
       5: invokevirtual #131                // Method org/apache/dubbo/config/context/ModuleConfigManager.removeConfig:(Lorg/apache/dubbo/config/AbstractConfig;)Z
       8: pop
       9: return

  private static java.lang.IllegalStateException lambda$preProcessRefresh$0();
    Code:
       0: new           #47                 // class java/lang/IllegalStateException
       3: dup
       4: ldc           #132                // String Default consumer is not initialized
       6: invokespecial #49                 // Method java/lang/IllegalStateException."<init>":(Ljava/lang/String;)V
       9: areturn
}
