Compiled from "RegistryConfig.java"
public class org.apache.dubbo.config.RegistryConfig extends org.apache.dubbo.config.AbstractConfig {
  public static final java.lang.String NO_AVAILABLE;

  private static final long serialVersionUID;

  private java.lang.String address;

  private java.lang.String username;

  private java.lang.String password;

  private java.lang.Integer port;

  private java.lang.String protocol;

  private java.lang.String transporter;

  private java.lang.String server;

  private java.lang.String client;

  private java.lang.String cluster;

  private java.lang.String zone;

  private java.lang.String group;

  private java.lang.String version;

  private java.lang.Integer timeout;

  private java.lang.Integer session;

  private java.lang.String file;

  private java.lang.Integer wait;

  private java.lang.Boolean check;

  private java.lang.Boolean dynamic;

  private java.lang.Boolean register;

  private java.lang.Boolean subscribe;

  private java.util.Map<java.lang.String, java.lang.String> parameters;

  private java.lang.Boolean simplified;

  private java.lang.String extraKeys;

  private java.lang.Boolean useAsConfigCenter;

  private java.lang.Boolean useAsMetadataCenter;

  private java.lang.String accepts;

  private java.lang.Boolean preferred;

  private java.lang.Integer weight;

  private java.lang.String registerMode;

  private java.lang.Boolean enableEmptyProtection;

  private java.lang.String secure;

  public java.lang.String getSecure();
    Code:
       0: aload_0
       1: getfield      #3                  // Field secure:Ljava/lang/String;
       4: areturn

  public void setSecure(java.lang.String);
    Code:
       0: aload_0
       1: aload_1
       2: putfield      #3                  // Field secure:Ljava/lang/String;
       5: return

  public org.apache.dubbo.config.RegistryConfig();
    Code:
       0: aload_0
       1: invokespecial #4                  // Method org/apache/dubbo/config/AbstractConfig."<init>":()V
       4: return

  public org.apache.dubbo.config.RegistryConfig(org.apache.dubbo.rpc.model.ApplicationModel);
    Code:
       0: aload_0
       1: aload_1
       2: invokespecial #5                  // Method org/apache/dubbo/config/AbstractConfig."<init>":(Lorg/apache/dubbo/rpc/model/ScopeModel;)V
       5: return

  public org.apache.dubbo.config.RegistryConfig(java.lang.String);
    Code:
       0: aload_0
       1: invokespecial #4                  // Method org/apache/dubbo/config/AbstractConfig."<init>":()V
       4: aload_0
       5: aload_1
       6: invokevirtual #6                  // Method setAddress:(Ljava/lang/String;)V
       9: return

  public org.apache.dubbo.config.RegistryConfig(org.apache.dubbo.rpc.model.ApplicationModel, java.lang.String);
    Code:
       0: aload_0
       1: aload_1
       2: invokespecial #5                  // Method org/apache/dubbo/config/AbstractConfig."<init>":(Lorg/apache/dubbo/rpc/model/ScopeModel;)V
       5: aload_0
       6: aload_2
       7: invokevirtual #6                  // Method setAddress:(Ljava/lang/String;)V
      10: return

  public org.apache.dubbo.config.RegistryConfig(java.lang.String, java.lang.String);
    Code:
       0: aload_0
       1: invokespecial #4                  // Method org/apache/dubbo/config/AbstractConfig."<init>":()V
       4: aload_0
       5: aload_1
       6: invokevirtual #6                  // Method setAddress:(Ljava/lang/String;)V
       9: aload_0
      10: aload_2
      11: invokevirtual #7                  // Method setProtocol:(Ljava/lang/String;)V
      14: return

  public org.apache.dubbo.config.RegistryConfig(org.apache.dubbo.rpc.model.ApplicationModel, java.lang.String, java.lang.String);
    Code:
       0: aload_0
       1: aload_1
       2: invokespecial #5                  // Method org/apache/dubbo/config/AbstractConfig."<init>":(Lorg/apache/dubbo/rpc/model/ScopeModel;)V
       5: aload_0
       6: aload_2
       7: invokevirtual #6                  // Method setAddress:(Ljava/lang/String;)V
      10: aload_0
      11: aload_3
      12: invokevirtual #7                  // Method setProtocol:(Ljava/lang/String;)V
      15: return

  public java.lang.String getId();
    Code:
       0: aload_0
       1: invokespecial #8                  // Method org/apache/dubbo/config/AbstractConfig.getId:()Ljava/lang/String;
       4: areturn

  public java.lang.String getProtocol();
    Code:
       0: aload_0
       1: getfield      #9                  // Field protocol:Ljava/lang/String;
       4: areturn

  public void setProtocol(java.lang.String);
    Code:
       0: aload_0
       1: aload_1
       2: putfield      #9                  // Field protocol:Ljava/lang/String;
       5: return

  public java.lang.String getAddress();
    Code:
       0: aload_0
       1: getfield      #10                 // Field address:Ljava/lang/String;
       4: areturn

  public void setAddress(java.lang.String);
    Code:
       0: aload_0
       1: aload_1
       2: putfield      #10                 // Field address:Ljava/lang/String;
       5: aload_1
       6: ifnull        123
       9: aload_1
      10: invokestatic  #11                 // Method org/apache/dubbo/common/URL.valueOf:(Ljava/lang/String;)Lorg/apache/dubbo/common/URL;
      13: astore_2
      14: aload_0
      15: invokedynamic #12,  0             // InvokeDynamic #0:get:(Lorg/apache/dubbo/config/RegistryConfig;)Ljava/util/function/Supplier;
      20: aload_0
      21: invokedynamic #13,  0             // InvokeDynamic #1:accept:(Lorg/apache/dubbo/config/RegistryConfig;)Ljava/util/function/Consumer;
      26: aload_2
      27: invokevirtual #14                 // Method org/apache/dubbo/common/URL.getUsername:()Ljava/lang/String;
      30: invokestatic  #15                 // Method org/apache/dubbo/common/utils/PojoUtils.updatePropertyIfAbsent:(Ljava/util/function/Supplier;Ljava/util/function/Consumer;Ljava/lang/Object;)V
      33: aload_0
      34: invokedynamic #16,  0             // InvokeDynamic #2:get:(Lorg/apache/dubbo/config/RegistryConfig;)Ljava/util/function/Supplier;
      39: aload_0
      40: invokedynamic #17,  0             // InvokeDynamic #3:accept:(Lorg/apache/dubbo/config/RegistryConfig;)Ljava/util/function/Consumer;
      45: aload_2
      46: invokevirtual #18                 // Method org/apache/dubbo/common/URL.getPassword:()Ljava/lang/String;
      49: invokestatic  #15                 // Method org/apache/dubbo/common/utils/PojoUtils.updatePropertyIfAbsent:(Ljava/util/function/Supplier;Ljava/util/function/Consumer;Ljava/lang/Object;)V
      52: aload_0
      53: invokedynamic #19,  0             // InvokeDynamic #4:get:(Lorg/apache/dubbo/config/RegistryConfig;)Ljava/util/function/Supplier;
      58: aload_0
      59: invokedynamic #20,  0             // InvokeDynamic #5:accept:(Lorg/apache/dubbo/config/RegistryConfig;)Ljava/util/function/Consumer;
      64: aload_2
      65: invokevirtual #21                 // Method org/apache/dubbo/common/URL.getProtocol:()Ljava/lang/String;
      68: invokestatic  #15                 // Method org/apache/dubbo/common/utils/PojoUtils.updatePropertyIfAbsent:(Ljava/util/function/Supplier;Ljava/util/function/Consumer;Ljava/lang/Object;)V
      71: aload_0
      72: invokedynamic #22,  0             // InvokeDynamic #6:get:(Lorg/apache/dubbo/config/RegistryConfig;)Ljava/util/function/Supplier;
      77: aload_0
      78: invokedynamic #23,  0             // InvokeDynamic #7:accept:(Lorg/apache/dubbo/config/RegistryConfig;)Ljava/util/function/Consumer;
      83: aload_2
      84: invokevirtual #24                 // Method org/apache/dubbo/common/URL.getPort:()I
      87: invokestatic  #25                 // Method java/lang/Integer.valueOf:(I)Ljava/lang/Integer;
      90: invokestatic  #15                 // Method org/apache/dubbo/common/utils/PojoUtils.updatePropertyIfAbsent:(Ljava/util/function/Supplier;Ljava/util/function/Consumer;Ljava/lang/Object;)V
      93: aload_2
      94: invokevirtual #26                 // Method org/apache/dubbo/common/URL.getParameters:()Ljava/util/Map;
      97: astore_3
      98: aload_3
      99: invokestatic  #27                 // Method org/apache/dubbo/common/utils/CollectionUtils.isNotEmptyMap:(Ljava/util/Map;)Z
     102: ifeq          114
     105: aload_3
     106: ldc           #28                 // String backup
     108: invokeinterface #29,  2           // InterfaceMethod java/util/Map.remove:(Ljava/lang/Object;)Ljava/lang/Object;
     113: pop
     114: aload_0
     115: aload_3
     116: invokevirtual #30                 // Method updateParameters:(Ljava/util/Map;)V
     119: goto          123
     122: astore_2
     123: return
    Exception table:
       from    to  target type
           9   119   122   Class java/lang/Exception

  public java.lang.Integer getPort();
    Code:
       0: aload_0
       1: getfield      #32                 // Field port:Ljava/lang/Integer;
       4: areturn

  public void setPort(java.lang.Integer);
    Code:
       0: aload_0
       1: aload_1
       2: putfield      #32                 // Field port:Ljava/lang/Integer;
       5: return

  public java.lang.String getUsername();
    Code:
       0: aload_0
       1: getfield      #33                 // Field username:Ljava/lang/String;
       4: areturn

  public void setUsername(java.lang.String);
    Code:
       0: aload_0
       1: aload_1
       2: putfield      #33                 // Field username:Ljava/lang/String;
       5: return

  public java.lang.String getPassword();
    Code:
       0: aload_0
       1: getfield      #34                 // Field password:Ljava/lang/String;
       4: areturn

  public void setPassword(java.lang.String);
    Code:
       0: aload_0
       1: aload_1
       2: putfield      #34                 // Field password:Ljava/lang/String;
       5: return

  public java.lang.Integer getWait();
    Code:
       0: aload_0
       1: getfield      #35                 // Field wait:Ljava/lang/Integer;
       4: areturn

  public void setWait(java.lang.Integer);
    Code:
       0: aload_0
       1: aload_1
       2: putfield      #35                 // Field wait:Ljava/lang/Integer;
       5: aload_1
       6: ifnull        26
       9: aload_1
      10: invokevirtual #36                 // Method java/lang/Integer.intValue:()I
      13: ifle          26
      16: ldc           #37                 // String dubbo.service.shutdown.wait
      18: aload_1
      19: invokestatic  #38                 // Method java/lang/String.valueOf:(Ljava/lang/Object;)Ljava/lang/String;
      22: invokestatic  #39                 // Method java/lang/System.setProperty:(Ljava/lang/String;Ljava/lang/String;)Ljava/lang/String;
      25: pop
      26: return

  public java.lang.Boolean isCheck();
    Code:
       0: aload_0
       1: getfield      #40                 // Field check:Ljava/lang/Boolean;
       4: areturn

  public void setCheck(java.lang.Boolean);
    Code:
       0: aload_0
       1: aload_1
       2: putfield      #40                 // Field check:Ljava/lang/Boolean;
       5: return

  public java.lang.String getFile();
    Code:
       0: aload_0
       1: getfield      #41                 // Field file:Ljava/lang/String;
       4: areturn

  public void setFile(java.lang.String);
    Code:
       0: aload_0
       1: aload_1
       2: putfield      #41                 // Field file:Ljava/lang/String;
       5: return

  public java.lang.String getTransport();
    Code:
       0: aload_0
       1: invokevirtual #42                 // Method getTransporter:()Ljava/lang/String;
       4: areturn

  public void setTransport(java.lang.String);
    Code:
       0: aload_0
       1: aload_1
       2: invokevirtual #43                 // Method setTransporter:(Ljava/lang/String;)V
       5: return

  public java.lang.String getTransporter();
    Code:
       0: aload_0
       1: getfield      #44                 // Field transporter:Ljava/lang/String;
       4: areturn

  public void setTransporter(java.lang.String);
    Code:
       0: aload_0
       1: aload_1
       2: putfield      #44                 // Field transporter:Ljava/lang/String;
       5: return

  public java.lang.String getServer();
    Code:
       0: aload_0
       1: getfield      #45                 // Field server:Ljava/lang/String;
       4: areturn

  public void setServer(java.lang.String);
    Code:
       0: aload_0
       1: aload_1
       2: putfield      #45                 // Field server:Ljava/lang/String;
       5: return

  public java.lang.String getClient();
    Code:
       0: aload_0
       1: getfield      #46                 // Field client:Ljava/lang/String;
       4: areturn

  public void setClient(java.lang.String);
    Code:
       0: aload_0
       1: aload_1
       2: putfield      #46                 // Field client:Ljava/lang/String;
       5: return

  public java.lang.Integer getTimeout();
    Code:
       0: aload_0
       1: getfield      #47                 // Field timeout:Ljava/lang/Integer;
       4: areturn

  public void setTimeout(java.lang.Integer);
    Code:
       0: aload_0
       1: aload_1
       2: putfield      #47                 // Field timeout:Ljava/lang/Integer;
       5: return

  public java.lang.Integer getSession();
    Code:
       0: aload_0
       1: getfield      #48                 // Field session:Ljava/lang/Integer;
       4: areturn

  public void setSession(java.lang.Integer);
    Code:
       0: aload_0
       1: aload_1
       2: putfield      #48                 // Field session:Ljava/lang/Integer;
       5: return

  public java.lang.Boolean isDynamic();
    Code:
       0: aload_0
       1: getfield      #49                 // Field dynamic:Ljava/lang/Boolean;
       4: areturn

  public void setDynamic(java.lang.Boolean);
    Code:
       0: aload_0
       1: aload_1
       2: putfield      #49                 // Field dynamic:Ljava/lang/Boolean;
       5: return

  public java.lang.Boolean isRegister();
    Code:
       0: aload_0
       1: getfield      #50                 // Field register:Ljava/lang/Boolean;
       4: areturn

  public void setRegister(java.lang.Boolean);
    Code:
       0: aload_0
       1: aload_1
       2: putfield      #50                 // Field register:Ljava/lang/Boolean;
       5: return

  public java.lang.Boolean isSubscribe();
    Code:
       0: aload_0
       1: getfield      #51                 // Field subscribe:Ljava/lang/Boolean;
       4: areturn

  public void setSubscribe(java.lang.Boolean);
    Code:
       0: aload_0
       1: aload_1
       2: putfield      #51                 // Field subscribe:Ljava/lang/Boolean;
       5: return

  public java.lang.String getCluster();
    Code:
       0: aload_0
       1: getfield      #52                 // Field cluster:Ljava/lang/String;
       4: areturn

  public void setCluster(java.lang.String);
    Code:
       0: aload_0
       1: aload_1
       2: putfield      #52                 // Field cluster:Ljava/lang/String;
       5: return

  public java.lang.String getZone();
    Code:
       0: aload_0
       1: getfield      #53                 // Field zone:Ljava/lang/String;
       4: areturn

  public void setZone(java.lang.String);
    Code:
       0: aload_0
       1: aload_1
       2: putfield      #53                 // Field zone:Ljava/lang/String;
       5: return

  public java.lang.String getGroup();
    Code:
       0: aload_0
       1: getfield      #54                 // Field group:Ljava/lang/String;
       4: areturn

  public void setGroup(java.lang.String);
    Code:
       0: aload_0
       1: aload_1
       2: putfield      #54                 // Field group:Ljava/lang/String;
       5: return

  public java.lang.String getVersion();
    Code:
       0: aload_0
       1: getfield      #55                 // Field version:Ljava/lang/String;
       4: areturn

  public void setVersion(java.lang.String);
    Code:
       0: aload_0
       1: aload_1
       2: putfield      #55                 // Field version:Ljava/lang/String;
       5: return

  public java.util.Map<java.lang.String, java.lang.String> getParameters();
    Code:
       0: aload_0
       1: getfield      #56                 // Field parameters:Ljava/util/Map;
       4: areturn

  public void setParameters(java.util.Map<java.lang.String, java.lang.String>);
    Code:
       0: aload_0
       1: aload_1
       2: putfield      #56                 // Field parameters:Ljava/util/Map;
       5: return

  public void updateParameters(java.util.Map<java.lang.String, java.lang.String>);
    Code:
       0: aload_1
       1: invokestatic  #57                 // Method org/apache/dubbo/common/utils/CollectionUtils.isEmptyMap:(Ljava/util/Map;)Z
       4: ifeq          8
       7: return
       8: aload_0
       9: getfield      #56                 // Field parameters:Ljava/util/Map;
      12: ifnonnull     23
      15: aload_0
      16: aload_1
      17: putfield      #56                 // Field parameters:Ljava/util/Map;
      20: goto          33
      23: aload_0
      24: getfield      #56                 // Field parameters:Ljava/util/Map;
      27: aload_1
      28: invokeinterface #58,  2           // InterfaceMethod java/util/Map.putAll:(Ljava/util/Map;)V
      33: return

  public java.lang.Boolean getSimplified();
    Code:
       0: aload_0
       1: getfield      #59                 // Field simplified:Ljava/lang/Boolean;
       4: areturn

  public void setSimplified(java.lang.Boolean);
    Code:
       0: aload_0
       1: aload_1
       2: putfield      #59                 // Field simplified:Ljava/lang/Boolean;
       5: return

  public java.lang.String getExtraKeys();
    Code:
       0: aload_0
       1: getfield      #60                 // Field extraKeys:Ljava/lang/String;
       4: areturn

  public void setExtraKeys(java.lang.String);
    Code:
       0: aload_0
       1: aload_1
       2: putfield      #60                 // Field extraKeys:Ljava/lang/String;
       5: return

  public java.lang.Boolean getUseAsConfigCenter();
    Code:
       0: aload_0
       1: getfield      #61                 // Field useAsConfigCenter:Ljava/lang/Boolean;
       4: areturn

  public void setUseAsConfigCenter(java.lang.Boolean);
    Code:
       0: aload_0
       1: aload_1
       2: putfield      #61                 // Field useAsConfigCenter:Ljava/lang/Boolean;
       5: return

  public java.lang.Boolean getUseAsMetadataCenter();
    Code:
       0: aload_0
       1: getfield      #62                 // Field useAsMetadataCenter:Ljava/lang/Boolean;
       4: areturn

  public void setUseAsMetadataCenter(java.lang.Boolean);
    Code:
       0: aload_0
       1: aload_1
       2: putfield      #62                 // Field useAsMetadataCenter:Ljava/lang/Boolean;
       5: return

  public java.lang.String getAccepts();
    Code:
       0: aload_0
       1: getfield      #63                 // Field accepts:Ljava/lang/String;
       4: areturn

  public void setAccepts(java.lang.String);
    Code:
       0: aload_0
       1: aload_1
       2: putfield      #63                 // Field accepts:Ljava/lang/String;
       5: return

  public java.lang.Boolean getPreferred();
    Code:
       0: aload_0
       1: getfield      #64                 // Field preferred:Ljava/lang/Boolean;
       4: areturn

  public void setPreferred(java.lang.Boolean);
    Code:
       0: aload_0
       1: aload_1
       2: putfield      #64                 // Field preferred:Ljava/lang/Boolean;
       5: return

  public java.lang.Integer getWeight();
    Code:
       0: aload_0
       1: getfield      #65                 // Field weight:Ljava/lang/Integer;
       4: areturn

  public void setWeight(java.lang.Integer);
    Code:
       0: aload_0
       1: aload_1
       2: putfield      #65                 // Field weight:Ljava/lang/Integer;
       5: return

  public java.lang.String getRegisterMode();
    Code:
       0: aload_0
       1: getfield      #66                 // Field registerMode:Ljava/lang/String;
       4: areturn

  public void setRegisterMode(java.lang.String);
    Code:
       0: aload_0
       1: aload_1
       2: putfield      #66                 // Field registerMode:Ljava/lang/String;
       5: return

  public java.lang.Boolean getEnableEmptyProtection();
    Code:
       0: aload_0
       1: getfield      #67                 // Field enableEmptyProtection:Ljava/lang/Boolean;
       4: areturn

  public void setEnableEmptyProtection(java.lang.Boolean);
    Code:
       0: aload_0
       1: aload_1
       2: putfield      #67                 // Field enableEmptyProtection:Ljava/lang/Boolean;
       5: return

  public boolean isValid();
    Code:
       0: aload_0
       1: getfield      #10                 // Field address:Ljava/lang/String;
       4: invokestatic  #68                 // Method org/apache/dubbo/common/utils/StringUtils.isEmpty:(Ljava/lang/String;)Z
       7: ifeq          20
      10: aload_0
      11: getfield      #9                  // Field protocol:Ljava/lang/String;
      14: invokestatic  #68                 // Method org/apache/dubbo/common/utils/StringUtils.isEmpty:(Ljava/lang/String;)Z
      17: ifne          24
      20: iconst_1
      21: goto          25
      24: iconst_0
      25: ireturn

  public java.lang.Boolean isDefault();
    Code:
       0: aload_0
       1: getfield      #69                 // Field isDefault:Ljava/lang/Boolean;
       4: areturn
}
