Compiled from "ServiceConfig.java"
public class org.apache.dubbo.config.ServiceConfig<T> extends org.apache.dubbo.config.ServiceConfigBase<T> {
  private static final long serialVersionUID;

  private static final org.apache.dubbo.common.logger.ErrorTypeAwareLogger logger;

  private static final java.util.Map<java.lang.String, java.lang.Integer> RANDOM_PORT_MAP;

  private org.apache.dubbo.rpc.Protocol protocolSPI;

  private org.apache.dubbo.rpc.ProxyFactory proxyFactory;

  private org.apache.dubbo.rpc.model.ProviderModel providerModel;

  private volatile transient boolean exported;

  private volatile transient boolean unexported;

  private volatile transient java.util.concurrent.atomic.AtomicBoolean initialized;

  private final java.util.List<org.apache.dubbo.rpc.Exporter<?>> exporters;

  private final java.util.List<org.apache.dubbo.config.ServiceListener> serviceListeners;

  public org.apache.dubbo.config.ServiceConfig();
    Code:
       0: aload_0
       1: invokespecial #9                  // Method org/apache/dubbo/config/ServiceConfigBase."<init>":()V
       4: aload_0
       5: new           #10                 // class java/util/concurrent/atomic/AtomicBoolean
       8: dup
       9: iconst_0
      10: invokespecial #11                 // Method java/util/concurrent/atomic/AtomicBoolean."<init>":(Z)V
      13: putfield      #12                 // Field initialized:Ljava/util/concurrent/atomic/AtomicBoolean;
      16: aload_0
      17: new           #13                 // class java/util/ArrayList
      20: dup
      21: invokespecial #14                 // Method java/util/ArrayList."<init>":()V
      24: putfield      #15                 // Field exporters:Ljava/util/List;
      27: aload_0
      28: new           #13                 // class java/util/ArrayList
      31: dup
      32: invokespecial #14                 // Method java/util/ArrayList."<init>":()V
      35: putfield      #16                 // Field serviceListeners:Ljava/util/List;
      38: return

  public org.apache.dubbo.config.ServiceConfig(org.apache.dubbo.rpc.model.ModuleModel);
    Code:
       0: aload_0
       1: aload_1
       2: invokespecial #17                 // Method org/apache/dubbo/config/ServiceConfigBase."<init>":(Lorg/apache/dubbo/rpc/model/ModuleModel;)V
       5: aload_0
       6: new           #10                 // class java/util/concurrent/atomic/AtomicBoolean
       9: dup
      10: iconst_0
      11: invokespecial #11                 // Method java/util/concurrent/atomic/AtomicBoolean."<init>":(Z)V
      14: putfield      #12                 // Field initialized:Ljava/util/concurrent/atomic/AtomicBoolean;
      17: aload_0
      18: new           #13                 // class java/util/ArrayList
      21: dup
      22: invokespecial #14                 // Method java/util/ArrayList."<init>":()V
      25: putfield      #15                 // Field exporters:Ljava/util/List;
      28: aload_0
      29: new           #13                 // class java/util/ArrayList
      32: dup
      33: invokespecial #14                 // Method java/util/ArrayList."<init>":()V
      36: putfield      #16                 // Field serviceListeners:Ljava/util/List;
      39: return

  public org.apache.dubbo.config.ServiceConfig(org.apache.dubbo.config.annotation.Service);
    Code:
       0: aload_0
       1: aload_1
       2: invokespecial #18                 // Method org/apache/dubbo/config/ServiceConfigBase."<init>":(Lorg/apache/dubbo/config/annotation/Service;)V
       5: aload_0
       6: new           #10                 // class java/util/concurrent/atomic/AtomicBoolean
       9: dup
      10: iconst_0
      11: invokespecial #11                 // Method java/util/concurrent/atomic/AtomicBoolean."<init>":(Z)V
      14: putfield      #12                 // Field initialized:Ljava/util/concurrent/atomic/AtomicBoolean;
      17: aload_0
      18: new           #13                 // class java/util/ArrayList
      21: dup
      22: invokespecial #14                 // Method java/util/ArrayList."<init>":()V
      25: putfield      #15                 // Field exporters:Ljava/util/List;
      28: aload_0
      29: new           #13                 // class java/util/ArrayList
      32: dup
      33: invokespecial #14                 // Method java/util/ArrayList."<init>":()V
      36: putfield      #16                 // Field serviceListeners:Ljava/util/List;
      39: return

  public org.apache.dubbo.config.ServiceConfig(org.apache.dubbo.rpc.model.ModuleModel, org.apache.dubbo.config.annotation.Service);
    Code:
       0: aload_0
       1: aload_1
       2: aload_2
       3: invokespecial #19                 // Method org/apache/dubbo/config/ServiceConfigBase."<init>":(Lorg/apache/dubbo/rpc/model/ModuleModel;Lorg/apache/dubbo/config/annotation/Service;)V
       6: aload_0
       7: new           #10                 // class java/util/concurrent/atomic/AtomicBoolean
      10: dup
      11: iconst_0
      12: invokespecial #11                 // Method java/util/concurrent/atomic/AtomicBoolean."<init>":(Z)V
      15: putfield      #12                 // Field initialized:Ljava/util/concurrent/atomic/AtomicBoolean;
      18: aload_0
      19: new           #13                 // class java/util/ArrayList
      22: dup
      23: invokespecial #14                 // Method java/util/ArrayList."<init>":()V
      26: putfield      #15                 // Field exporters:Ljava/util/List;
      29: aload_0
      30: new           #13                 // class java/util/ArrayList
      33: dup
      34: invokespecial #14                 // Method java/util/ArrayList."<init>":()V
      37: putfield      #16                 // Field serviceListeners:Ljava/util/List;
      40: return

  protected void postProcessAfterScopeModelChanged(org.apache.dubbo.rpc.model.ScopeModel, org.apache.dubbo.rpc.model.ScopeModel);
    Code:
       0: aload_0
       1: aload_1
       2: aload_2
       3: invokespecial #20                 // Method org/apache/dubbo/config/ServiceConfigBase.postProcessAfterScopeModelChanged:(Lorg/apache/dubbo/rpc/model/ScopeModel;Lorg/apache/dubbo/rpc/model/ScopeModel;)V
       6: aload_0
       7: aload_0
       8: ldc           #21                 // class org/apache/dubbo/rpc/Protocol
      10: invokevirtual #22                 // Method getExtensionLoader:(Ljava/lang/Class;)Lorg/apache/dubbo/common/extension/ExtensionLoader;
      13: invokevirtual #23                 // Method org/apache/dubbo/common/extension/ExtensionLoader.getAdaptiveExtension:()Ljava/lang/Object;
      16: checkcast     #21                 // class org/apache/dubbo/rpc/Protocol
      19: putfield      #24                 // Field protocolSPI:Lorg/apache/dubbo/rpc/Protocol;
      22: aload_0
      23: aload_0
      24: ldc           #25                 // class org/apache/dubbo/rpc/ProxyFactory
      26: invokevirtual #22                 // Method getExtensionLoader:(Ljava/lang/Class;)Lorg/apache/dubbo/common/extension/ExtensionLoader;
      29: invokevirtual #23                 // Method org/apache/dubbo/common/extension/ExtensionLoader.getAdaptiveExtension:()Ljava/lang/Object;
      32: checkcast     #25                 // class org/apache/dubbo/rpc/ProxyFactory
      35: putfield      #26                 // Field proxyFactory:Lorg/apache/dubbo/rpc/ProxyFactory;
      38: return

  public boolean isExported();
    Code:
       0: aload_0
       1: getfield      #27                 // Field exported:Z
       4: ireturn

  public boolean isUnexported();
    Code:
       0: aload_0
       1: getfield      #28                 // Field unexported:Z
       4: ireturn

  public void unexport();
    Code:
       0: aload_0
       1: getfield      #27                 // Field exported:Z
       4: ifne          8
       7: return
       8: aload_0
       9: getfield      #28                 // Field unexported:Z
      12: ifeq          16
      15: return
      16: aload_0
      17: getfield      #15                 // Field exporters:Ljava/util/List;
      20: invokeinterface #29,  1           // InterfaceMethod java/util/List.isEmpty:()Z
      25: ifne          193
      28: aload_0
      29: getfield      #15                 // Field exporters:Ljava/util/List;
      32: invokeinterface #30,  1           // InterfaceMethod java/util/List.iterator:()Ljava/util/Iterator;
      37: astore_1
      38: aload_1
      39: invokeinterface #31,  1           // InterfaceMethod java/util/Iterator.hasNext:()Z
      44: ifeq          104
      47: aload_1
      48: invokeinterface #32,  1           // InterfaceMethod java/util/Iterator.next:()Ljava/lang/Object;
      53: checkcast     #33                 // class org/apache/dubbo/rpc/Exporter
      56: astore_2
      57: aload_2
      58: invokeinterface #34,  1           // InterfaceMethod org/apache/dubbo/rpc/Exporter.unregister:()V
      63: goto          101
      66: astore_3
      67: getstatic     #36                 // Field logger:Lorg/apache/dubbo/common/logger/ErrorTypeAwareLogger;
      70: ldc           #37                 // String 5-7
      72: ldc           #38                 // String
      74: ldc           #38                 // String
      76: new           #39                 // class java/lang/StringBuilder
      79: dup
      80: invokespecial #40                 // Method java/lang/StringBuilder."<init>":()V
      83: ldc           #41                 // String Unexpected error occurred when unexport
      85: invokevirtual #42                 // Method java/lang/StringBuilder.append:(Ljava/lang/String;)Ljava/lang/StringBuilder;
      88: aload_2
      89: invokevirtual #43                 // Method java/lang/StringBuilder.append:(Ljava/lang/Object;)Ljava/lang/StringBuilder;
      92: invokevirtual #44                 // Method java/lang/StringBuilder.toString:()Ljava/lang/String;
      95: aload_3
      96: invokeinterface #45,  6           // InterfaceMethod org/apache/dubbo/common/logger/ErrorTypeAwareLogger.warn:(Ljava/lang/String;Ljava/lang/String;Ljava/lang/String;Ljava/lang/String;Ljava/lang/Throwable;)V
     101: goto          38
     104: aload_0
     105: invokespecial #46                 // Method waitForIdle:()V
     108: aload_0
     109: getfield      #15                 // Field exporters:Ljava/util/List;
     112: invokeinterface #30,  1           // InterfaceMethod java/util/List.iterator:()Ljava/util/Iterator;
     117: astore_1
     118: aload_1
     119: invokeinterface #31,  1           // InterfaceMethod java/util/Iterator.hasNext:()Z
     124: ifeq          184
     127: aload_1
     128: invokeinterface #32,  1           // InterfaceMethod java/util/Iterator.next:()Ljava/lang/Object;
     133: checkcast     #33                 // class org/apache/dubbo/rpc/Exporter
     136: astore_2
     137: aload_2
     138: invokeinterface #47,  1           // InterfaceMethod org/apache/dubbo/rpc/Exporter.unexport:()V
     143: goto          181
     146: astore_3
     147: getstatic     #36                 // Field logger:Lorg/apache/dubbo/common/logger/ErrorTypeAwareLogger;
     150: ldc           #37                 // String 5-7
     152: ldc           #38                 // String
     154: ldc           #38                 // String
     156: new           #39                 // class java/lang/StringBuilder
     159: dup
     160: invokespecial #40                 // Method java/lang/StringBuilder."<init>":()V
     163: ldc           #41                 // String Unexpected error occurred when unexport
     165: invokevirtual #42                 // Method java/lang/StringBuilder.append:(Ljava/lang/String;)Ljava/lang/StringBuilder;
     168: aload_2
     169: invokevirtual #43                 // Method java/lang/StringBuilder.append:(Ljava/lang/Object;)Ljava/lang/StringBuilder;
     172: invokevirtual #44                 // Method java/lang/StringBuilder.toString:()Ljava/lang/String;
     175: aload_3
     176: invokeinterface #45,  6           // InterfaceMethod org/apache/dubbo/common/logger/ErrorTypeAwareLogger.warn:(Ljava/lang/String;Ljava/lang/String;Ljava/lang/String;Ljava/lang/String;Ljava/lang/Throwable;)V
     181: goto          118
     184: aload_0
     185: getfield      #15                 // Field exporters:Ljava/util/List;
     188: invokeinterface #48,  1           // InterfaceMethod java/util/List.clear:()V
     193: aload_0
     194: iconst_1
     195: putfield      #28                 // Field unexported:Z
     198: aload_0
     199: invokevirtual #49                 // Method onUnexpoted:()V
     202: aload_0
     203: invokevirtual #50                 // Method getScopeModel:()Lorg/apache/dubbo/rpc/model/ModuleModel;
     206: invokevirtual #51                 // Method org/apache/dubbo/rpc/model/ModuleModel.getServiceRepository:()Lorg/apache/dubbo/rpc/model/ModuleServiceRepository;
     209: astore_1
     210: aload_1
     211: aload_0
     212: getfield      #52                 // Field providerModel:Lorg/apache/dubbo/rpc/model/ProviderModel;
     215: invokevirtual #53                 // Method org/apache/dubbo/rpc/model/ModuleServiceRepository.unregisterProvider:(Lorg/apache/dubbo/rpc/model/ProviderModel;)V
     218: return
    Exception table:
       from    to  target type
          57    63    66   Class java/lang/Throwable
         137   143   146   Class java/lang/Throwable

  private void waitForIdle();
    Code:
       0: aload_0
       1: invokevirtual #50                 // Method getScopeModel:()Lorg/apache/dubbo/rpc/model/ModuleModel;
       4: invokestatic  #54                 // Method org/apache/dubbo/common/config/ConfigurationUtils.getServerShutdownTimeout:(Lorg/apache/dubbo/rpc/model/ScopeModel;)I
       7: istore_1
       8: invokestatic  #55                 // Method java/lang/System.currentTimeMillis:()J
      11: aload_0
      12: getfield      #52                 // Field providerModel:Lorg/apache/dubbo/rpc/model/ProviderModel;
      15: invokevirtual #56                 // Method org/apache/dubbo/rpc/model/ProviderModel.getLastInvokeTime:()J
      18: lsub
      19: lstore_2
      20: lload_2
      21: iload_1
      22: i2l
      23: lcmp
      24: ifle          28
      27: return
      28: iload_1
      29: iconst_3
      30: idiv
      31: istore        4
      33: iload_1
      34: i2l
      35: lload_2
      36: lsub
      37: iload         4
      39: i2l
      40: lcmp
      41: ifge          140
      44: getstatic     #36                 // Field logger:Lorg/apache/dubbo/common/logger/ErrorTypeAwareLogger;
      47: new           #39                 // class java/lang/StringBuilder
      50: dup
      51: invokespecial #40                 // Method java/lang/StringBuilder."<init>":()V
      54: ldc           #57                 // String Service
      56: invokevirtual #42                 // Method java/lang/StringBuilder.append:(Ljava/lang/String;)Ljava/lang/StringBuilder;
      59: aload_0
      60: invokevirtual #58                 // Method getUniqueServiceName:()Ljava/lang/String;
      63: invokevirtual #42                 // Method java/lang/StringBuilder.append:(Ljava/lang/String;)Ljava/lang/StringBuilder;
      66: ldc           #59                 // String  has idle for
      68: invokevirtual #42                 // Method java/lang/StringBuilder.append:(Ljava/lang/String;)Ljava/lang/StringBuilder;
      71: lload_2
      72: invokevirtual #60                 // Method java/lang/StringBuilder.append:(J)Ljava/lang/StringBuilder;
      75: ldc           #61                 // String  ms, wait for
      77: invokevirtual #42                 // Method java/lang/StringBuilder.append:(Ljava/lang/String;)Ljava/lang/StringBuilder;
      80: iload_1
      81: i2l
      82: lload_2
      83: lsub
      84: invokevirtual #60                 // Method java/lang/StringBuilder.append:(J)Ljava/lang/StringBuilder;
      87: ldc           #62                 // String  ms to un-export
      89: invokevirtual #42                 // Method java/lang/StringBuilder.append:(Ljava/lang/String;)Ljava/lang/StringBuilder;
      92: invokevirtual #44                 // Method java/lang/StringBuilder.toString:()Ljava/lang/String;
      95: invokeinterface #63,  2           // InterfaceMethod org/apache/dubbo/common/logger/ErrorTypeAwareLogger.info:(Ljava/lang/String;)V
     100: iload_1
     101: i2l
     102: lload_2
     103: lsub
     104: invokestatic  #64                 // Method java/lang/Thread.sleep:(J)V
     107: goto          139
     110: astore        5
     112: getstatic     #36                 // Field logger:Lorg/apache/dubbo/common/logger/ErrorTypeAwareLogger;
     115: ldc           #66                 // String 99-0
     117: ldc           #67                 // String unknown error in registry module
     119: ldc           #38                 // String
     121: aload         5
     123: invokevirtual #68                 // Method java/lang/InterruptedException.getMessage:()Ljava/lang/String;
     126: aload         5
     128: invokeinterface #45,  6           // InterfaceMethod org/apache/dubbo/common/logger/ErrorTypeAwareLogger.warn:(Ljava/lang/String;Ljava/lang/String;Ljava/lang/String;Ljava/lang/String;Ljava/lang/Throwable;)V
     133: invokestatic  #69                 // Method java/lang/Thread.currentThread:()Ljava/lang/Thread;
     136: invokevirtual #70                 // Method java/lang/Thread.interrupt:()V
     139: return
     140: lconst_0
     141: lstore_2
     142: invokestatic  #55                 // Method java/lang/System.currentTimeMillis:()J
     145: lstore        5
     147: lload_2
     148: iload         4
     150: i2l
     151: lcmp
     152: ifge          306
     155: invokestatic  #55                 // Method java/lang/System.currentTimeMillis:()J
     158: aload_0
     159: getfield      #52                 // Field providerModel:Lorg/apache/dubbo/rpc/model/ProviderModel;
     162: invokevirtual #56                 // Method org/apache/dubbo/rpc/model/ProviderModel.getLastInvokeTime:()J
     165: lload         5
     167: invokestatic  #71                 // Method java/lang/Math.max:(JJ)J
     170: lsub
     171: lstore_2
     172: lload_2
     173: iload         4
     175: i2l
     176: lcmp
     177: ifge          192
     180: invokestatic  #55                 // Method java/lang/System.currentTimeMillis:()J
     183: lload         5
     185: lsub
     186: iload_1
     187: i2l
     188: lcmp
     189: ifle          193
     192: return
     193: iload         4
     195: i2l
     196: lload_2
     197: lsub
     198: iload_1
     199: i2l
     200: lload         5
     202: ladd
     203: invokestatic  #55                 // Method java/lang/System.currentTimeMillis:()J
     206: lsub
     207: invokestatic  #72                 // Method java/lang/Math.min:(JJ)J
     210: lstore        7
     212: getstatic     #36                 // Field logger:Lorg/apache/dubbo/common/logger/ErrorTypeAwareLogger;
     215: new           #39                 // class java/lang/StringBuilder
     218: dup
     219: invokespecial #40                 // Method java/lang/StringBuilder."<init>":()V
     222: ldc           #57                 // String Service
     224: invokevirtual #42                 // Method java/lang/StringBuilder.append:(Ljava/lang/String;)Ljava/lang/StringBuilder;
     227: aload_0
     228: invokevirtual #58                 // Method getUniqueServiceName:()Ljava/lang/String;
     231: invokevirtual #42                 // Method java/lang/StringBuilder.append:(Ljava/lang/String;)Ljava/lang/StringBuilder;
     234: ldc           #59                 // String  has idle for
     236: invokevirtual #42                 // Method java/lang/StringBuilder.append:(Ljava/lang/String;)Ljava/lang/StringBuilder;
     239: lload_2
     240: invokevirtual #60                 // Method java/lang/StringBuilder.append:(J)Ljava/lang/StringBuilder;
     243: ldc           #61                 // String  ms, wait for
     245: invokevirtual #42                 // Method java/lang/StringBuilder.append:(Ljava/lang/String;)Ljava/lang/StringBuilder;
     248: lload         7
     250: invokevirtual #60                 // Method java/lang/StringBuilder.append:(J)Ljava/lang/StringBuilder;
     253: ldc           #62                 // String  ms to un-export
     255: invokevirtual #42                 // Method java/lang/StringBuilder.append:(Ljava/lang/String;)Ljava/lang/StringBuilder;
     258: invokevirtual #44                 // Method java/lang/StringBuilder.toString:()Ljava/lang/String;
     261: invokeinterface #63,  2           // InterfaceMethod org/apache/dubbo/common/logger/ErrorTypeAwareLogger.info:(Ljava/lang/String;)V
     266: lload         7
     268: invokestatic  #64                 // Method java/lang/Thread.sleep:(J)V
     271: goto          303
     274: astore        9
     276: getstatic     #36                 // Field logger:Lorg/apache/dubbo/common/logger/ErrorTypeAwareLogger;
     279: ldc           #66                 // String 99-0
     281: ldc           #67                 // String unknown error in registry module
     283: ldc           #38                 // String
     285: aload         9
     287: invokevirtual #68                 // Method java/lang/InterruptedException.getMessage:()Ljava/lang/String;
     290: aload         9
     292: invokeinterface #45,  6           // InterfaceMethod org/apache/dubbo/common/logger/ErrorTypeAwareLogger.warn:(Ljava/lang/String;Ljava/lang/String;Ljava/lang/String;Ljava/lang/String;Ljava/lang/Throwable;)V
     297: invokestatic  #69                 // Method java/lang/Thread.currentThread:()Ljava/lang/Thread;
     300: invokevirtual #70                 // Method java/lang/Thread.interrupt:()V
     303: goto          147
     306: return
    Exception table:
       from    to  target type
         100   107   110   Class java/lang/InterruptedException
         266   271   274   Class java/lang/InterruptedException

  public void init();
    Code:
       0: aload_0
       1: getfield      #12                 // Field initialized:Ljava/util/concurrent/atomic/AtomicBoolean;
       4: iconst_0
       5: iconst_1
       6: invokevirtual #73                 // Method java/util/concurrent/atomic/AtomicBoolean.compareAndSet:(ZZ)Z
       9: ifeq          33
      12: aload_0
      13: ldc           #74                 // class org/apache/dubbo/config/ServiceListener
      15: invokevirtual #22                 // Method getExtensionLoader:(Ljava/lang/Class;)Lorg/apache/dubbo/common/extension/ExtensionLoader;
      18: astore_1
      19: aload_0
      20: getfield      #16                 // Field serviceListeners:Ljava/util/List;
      23: aload_1
      24: invokevirtual #75                 // Method org/apache/dubbo/common/extension/ExtensionLoader.getSupportedExtensionInstances:()Ljava/util/Set;
      27: invokeinterface #76,  2           // InterfaceMethod java/util/List.addAll:(Ljava/util/Collection;)Z
      32: pop
      33: aload_0
      34: aload_0
      35: getfield      #77                 // Field provider:Lorg/apache/dubbo/config/ProviderConfig;
      38: invokevirtual #78                 // Method initServiceMetadata:(Lorg/apache/dubbo/config/AbstractInterfaceConfig;)V
      41: aload_0
      42: getfield      #79                 // Field serviceMetadata:Lorg/apache/dubbo/rpc/model/ServiceMetadata;
      45: aload_0
      46: invokevirtual #80                 // Method getInterfaceClass:()Ljava/lang/Class;
      49: invokevirtual #81                 // Method org/apache/dubbo/rpc/model/ServiceMetadata.setServiceType:(Ljava/lang/Class;)V
      52: aload_0
      53: getfield      #79                 // Field serviceMetadata:Lorg/apache/dubbo/rpc/model/ServiceMetadata;
      56: aload_0
      57: invokevirtual #82                 // Method getRef:()Ljava/lang/Object;
      60: invokevirtual #83                 // Method org/apache/dubbo/rpc/model/ServiceMetadata.setTarget:(Ljava/lang/Object;)V
      63: aload_0
      64: getfield      #79                 // Field serviceMetadata:Lorg/apache/dubbo/rpc/model/ServiceMetadata;
      67: invokevirtual #84                 // Method org/apache/dubbo/rpc/model/ServiceMetadata.generateServiceKey:()V
      70: return

  public void export();
    Code:
       0: aload_0
       1: getfield      #27                 // Field exported:Z
       4: ifeq          8
       7: return
       8: aload_0
       9: invokevirtual #50                 // Method getScopeModel:()Lorg/apache/dubbo/rpc/model/ModuleModel;
      12: invokevirtual #85                 // Method org/apache/dubbo/rpc/model/ModuleModel.getDeployer:()Lorg/apache/dubbo/common/deploy/ModuleDeployer;
      15: invokeinterface #86,  1           // InterfaceMethod org/apache/dubbo/common/deploy/ModuleDeployer.start:()Ljava/util/concurrent/Future;
      20: pop
      21: aload_0
      22: dup
      23: astore_1
      24: monitorenter
      25: aload_0
      26: getfield      #27                 // Field exported:Z
      29: ifeq          35
      32: aload_1
      33: monitorexit
      34: return
      35: aload_0
      36: invokevirtual #87                 // Method isRefreshed:()Z
      39: ifne          46
      42: aload_0
      43: invokevirtual #88                 // Method refresh:()V
      46: aload_0
      47: invokevirtual #89                 // Method shouldExport:()Z
      50: ifeq          75
      53: aload_0
      54: invokevirtual #90                 // Method init:()V
      57: aload_0
      58: invokevirtual #91                 // Method shouldDelay:()Z
      61: ifeq          71
      64: aload_0
      65: invokevirtual #92                 // Method doDelayExport:()V
      68: goto          75
      71: aload_0
      72: invokevirtual #93                 // Method doExport:()V
      75: aload_1
      76: monitorexit
      77: goto          85
      80: astore_2
      81: aload_1
      82: monitorexit
      83: aload_2
      84: athrow
      85: return
    Exception table:
       from    to  target type
          25    34    80   any
          35    77    80   any
          80    83    80   any

  protected void doDelayExport();
    Code:
       0: aload_0
       1: invokevirtual #50                 // Method getScopeModel:()Lorg/apache/dubbo/rpc/model/ModuleModel;
       4: invokevirtual #94                 // Method org/apache/dubbo/rpc/model/ModuleModel.getApplicationModel:()Lorg/apache/dubbo/rpc/model/ApplicationModel;
       7: invokestatic  #95                 // InterfaceMethod org/apache/dubbo/common/threadpool/manager/ExecutorRepository.getInstance:(Lorg/apache/dubbo/rpc/model/ApplicationModel;)Lorg/apache/dubbo/common/threadpool/manager/ExecutorRepository;
      10: invokeinterface #96,  1           // InterfaceMethod org/apache/dubbo/common/threadpool/manager/ExecutorRepository.getServiceExportExecutor:()Ljava/util/concurrent/ScheduledExecutorService;
      15: aload_0
      16: invokedynamic #97,  0             // InvokeDynamic #0:run:(Lorg/apache/dubbo/config/ServiceConfig;)Ljava/lang/Runnable;
      21: aload_0
      22: invokevirtual #98                 // Method getDelay:()Ljava/lang/Integer;
      25: invokevirtual #99                 // Method java/lang/Integer.intValue:()I
      28: i2l
      29: getstatic     #100                // Field java/util/concurrent/TimeUnit.MILLISECONDS:Ljava/util/concurrent/TimeUnit;
      32: invokeinterface #101,  5          // InterfaceMethod java/util/concurrent/ScheduledExecutorService.schedule:(Ljava/lang/Runnable;JLjava/util/concurrent/TimeUnit;)Ljava/util/concurrent/ScheduledFuture;
      37: pop
      38: return

  protected void exported();
    Code:
       0: aload_0
       1: iconst_1
       2: putfield      #27                 // Field exported:Z
       5: aload_0
       6: invokevirtual #102                // Method getExportedUrls:()Ljava/util/List;
       9: astore_1
      10: aload_1
      11: aload_0
      12: invokedynamic #103,  0            // InvokeDynamic #1:accept:(Lorg/apache/dubbo/config/ServiceConfig;)Ljava/util/function/Consumer;
      17: invokeinterface #104,  2          // InterfaceMethod java/util/List.forEach:(Ljava/util/function/Consumer;)V
      22: aload_0
      23: invokevirtual #105                // Method onExported:()V
      26: return

  protected void mapServiceName(org.apache.dubbo.common.URL, org.apache.dubbo.metadata.ServiceNameMapping, java.util.concurrent.ScheduledExecutorService);
    Code:
       0: aload_0
       1: getfield      #27                 // Field exported:Z
       4: ifne          8
       7: return
       8: getstatic     #36                 // Field logger:Lorg/apache/dubbo/common/logger/ErrorTypeAwareLogger;
      11: new           #39                 // class java/lang/StringBuilder
      14: dup
      15: invokespecial #40                 // Method java/lang/StringBuilder."<init>":()V
      18: ldc           #106                // String Try to register interface application mapping for service
      20: invokevirtual #42                 // Method java/lang/StringBuilder.append:(Ljava/lang/String;)Ljava/lang/StringBuilder;
      23: aload_1
      24: invokevirtual #107                // Method org/apache/dubbo/common/URL.getServiceKey:()Ljava/lang/String;
      27: invokevirtual #42                 // Method java/lang/StringBuilder.append:(Ljava/lang/String;)Ljava/lang/StringBuilder;
      30: invokevirtual #44                 // Method java/lang/StringBuilder.toString:()Ljava/lang/String;
      33: invokeinterface #63,  2           // InterfaceMethod org/apache/dubbo/common/logger/ErrorTypeAwareLogger.info:(Ljava/lang/String;)V
      38: iconst_0
      39: istore        4
      41: aload_2
      42: aload_1
      43: invokeinterface #108,  2          // InterfaceMethod org/apache/dubbo/metadata/ServiceNameMapping.map:(Lorg/apache/dubbo/common/URL;)Z
      48: istore        4
      50: iload         4
      52: ifeq          88
      55: getstatic     #36                 // Field logger:Lorg/apache/dubbo/common/logger/ErrorTypeAwareLogger;
      58: new           #39                 // class java/lang/StringBuilder
      61: dup
      62: invokespecial #40                 // Method java/lang/StringBuilder."<init>":()V
      65: ldc           #109                // String Successfully registered interface application mapping for service
      67: invokevirtual #42                 // Method java/lang/StringBuilder.append:(Ljava/lang/String;)Ljava/lang/StringBuilder;
      70: aload_1
      71: invokevirtual #107                // Method org/apache/dubbo/common/URL.getServiceKey:()Ljava/lang/String;
      74: invokevirtual #42                 // Method java/lang/StringBuilder.append:(Ljava/lang/String;)Ljava/lang/StringBuilder;
      77: invokevirtual #44                 // Method java/lang/StringBuilder.toString:()Ljava/lang/String;
      80: invokeinterface #63,  2           // InterfaceMethod org/apache/dubbo/common/logger/ErrorTypeAwareLogger.info:(Ljava/lang/String;)V
      85: goto          124
      88: getstatic     #36                 // Field logger:Lorg/apache/dubbo/common/logger/ErrorTypeAwareLogger;
      91: ldc           #110                // String 5-10
      93: ldc           #111                // String configuration server disconnected
      95: ldc           #38                 // String
      97: new           #39                 // class java/lang/StringBuilder
     100: dup
     101: invokespecial #40                 // Method java/lang/StringBuilder."<init>":()V
     104: ldc           #112                // String Failed register interface application mapping for service
     106: invokevirtual #42                 // Method java/lang/StringBuilder.append:(Ljava/lang/String;)Ljava/lang/StringBuilder;
     109: aload_1
     110: invokevirtual #107                // Method org/apache/dubbo/common/URL.getServiceKey:()Ljava/lang/String;
     113: invokevirtual #42                 // Method java/lang/StringBuilder.append:(Ljava/lang/String;)Ljava/lang/StringBuilder;
     116: invokevirtual #44                 // Method java/lang/StringBuilder.toString:()Ljava/lang/String;
     119: invokeinterface #113,  5          // InterfaceMethod org/apache/dubbo/common/logger/ErrorTypeAwareLogger.error:(Ljava/lang/String;Ljava/lang/String;Ljava/lang/String;Ljava/lang/String;)V
     124: goto          167
     127: astore        5
     129: getstatic     #36                 // Field logger:Lorg/apache/dubbo/common/logger/ErrorTypeAwareLogger;
     132: ldc           #110                // String 5-10
     134: ldc           #111                // String configuration server disconnected
     136: ldc           #38                 // String
     138: new           #39                 // class java/lang/StringBuilder
     141: dup
     142: invokespecial #40                 // Method java/lang/StringBuilder."<init>":()V
     145: ldc           #112                // String Failed register interface application mapping for service
     147: invokevirtual #42                 // Method java/lang/StringBuilder.append:(Ljava/lang/String;)Ljava/lang/StringBuilder;
     150: aload_1
     151: invokevirtual #107                // Method org/apache/dubbo/common/URL.getServiceKey:()Ljava/lang/String;
     154: invokevirtual #42                 // Method java/lang/StringBuilder.append:(Ljava/lang/String;)Ljava/lang/StringBuilder;
     157: invokevirtual #44                 // Method java/lang/StringBuilder.toString:()Ljava/lang/String;
     160: aload         5
     162: invokeinterface #115,  6          // InterfaceMethod org/apache/dubbo/common/logger/ErrorTypeAwareLogger.error:(Ljava/lang/String;Ljava/lang/String;Ljava/lang/String;Ljava/lang/String;Ljava/lang/Throwable;)V
     167: iload         4
     169: ifne          188
     172: aload_2
     173: invokeinterface #116,  1          // InterfaceMethod org/apache/dubbo/metadata/ServiceNameMapping.hasValidMetadataCenter:()Z
     178: ifeq          188
     181: aload_0
     182: aload_3
     183: aload_2
     184: aload_1
     185: invokespecial #117                // Method scheduleToMapping:(Ljava/util/concurrent/ScheduledExecutorService;Lorg/apache/dubbo/metadata/ServiceNameMapping;Lorg/apache/dubbo/common/URL;)V
     188: return
    Exception table:
       from    to  target type
          41   124   127   Class java/lang/Exception

  private void scheduleToMapping(java.util.concurrent.ScheduledExecutorService, org.apache.dubbo.metadata.ServiceNameMapping, org.apache.dubbo.common.URL);
    Code:
       0: aload_0
       1: invokevirtual #118                // Method getApplication:()Lorg/apache/dubbo/config/ApplicationConfig;
       4: invokevirtual #119                // Method org/apache/dubbo/config/ApplicationConfig.getMappingRetryInterval:()Ljava/lang/Integer;
       7: astore        4
       9: aload_1
      10: aload_0
      11: aload_3
      12: aload_2
      13: aload_1
      14: invokedynamic #120,  0            // InvokeDynamic #2:run:(Lorg/apache/dubbo/config/ServiceConfig;Lorg/apache/dubbo/common/URL;Lorg/apache/dubbo/metadata/ServiceNameMapping;Ljava/util/concurrent/ScheduledExecutorService;)Ljava/lang/Runnable;
      19: aload         4
      21: ifnonnull     30
      24: ldc2_w        #121                // long 5000l
      27: goto          36
      30: aload         4
      32: invokevirtual #99                 // Method java/lang/Integer.intValue:()I
      35: i2l
      36: getstatic     #100                // Field java/util/concurrent/TimeUnit.MILLISECONDS:Ljava/util/concurrent/TimeUnit;
      39: invokeinterface #101,  5          // InterfaceMethod java/util/concurrent/ScheduledExecutorService.schedule:(Ljava/lang/Runnable;JLjava/util/concurrent/TimeUnit;)Ljava/util/concurrent/ScheduledFuture;
      44: pop
      45: return

  private void checkAndUpdateSubConfigs();
    Code:
       0: aload_0
       1: invokevirtual #123                // Method completeCompoundConfigs:()V
       4: aload_0
       5: invokevirtual #124                // Method checkProtocol:()V
       8: aload_0
       9: ldc           #125                // class org/apache/dubbo/config/ConfigInitializer
      11: invokevirtual #22                 // Method getExtensionLoader:(Ljava/lang/Class;)Lorg/apache/dubbo/common/extension/ExtensionLoader;
      14: ldc           #126                // String configInitializer://
      16: aload_0
      17: invokevirtual #50                 // Method getScopeModel:()Lorg/apache/dubbo/rpc/model/ModuleModel;
      20: invokestatic  #127                // Method org/apache/dubbo/common/URL.valueOf:(Ljava/lang/String;Lorg/apache/dubbo/rpc/model/ScopeModel;)Lorg/apache/dubbo/common/URL;
      23: aconst_null
      24: checkcast     #128                // class "[Ljava/lang/String;"
      27: invokevirtual #129                // Method org/apache/dubbo/common/extension/ExtensionLoader.getActivateExtension:(Lorg/apache/dubbo/common/URL;[Ljava/lang/String;)Ljava/util/List;
      30: astore_1
      31: aload_1
      32: aload_0
      33: invokedynamic #130,  0            // InvokeDynamic #3:accept:(Lorg/apache/dubbo/config/ServiceConfig;)Ljava/util/function/Consumer;
      38: invokeinterface #104,  2          // InterfaceMethod java/util/List.forEach:(Ljava/util/function/Consumer;)V
      43: aload_0
      44: invokespecial #131                // Method isOnlyInJvm:()Z
      47: ifne          54
      50: aload_0
      51: invokevirtual #132                // Method checkRegistry:()V
      54: aload_0
      55: getfield      #133                // Field interfaceName:Ljava/lang/String;
      58: invokestatic  #134                // Method org/apache/dubbo/common/utils/StringUtils.isEmpty:(Ljava/lang/String;)Z
      61: ifeq          74
      64: new           #135                // class java/lang/IllegalStateException
      67: dup
      68: ldc           #136                // String <dubbo:service interface=\"\" /> interface not allow null!
      70: invokespecial #137                // Method java/lang/IllegalStateException."<init>":(Ljava/lang/String;)V
      73: athrow
      74: aload_0
      75: getfield      #138                // Field ref:Ljava/lang/Object;
      78: instanceof    #139                // class org/apache/dubbo/rpc/service/GenericService
      81: ifeq          113
      84: aload_0
      85: ldc           #139                // class org/apache/dubbo/rpc/service/GenericService
      87: putfield      #140                // Field interfaceClass:Ljava/lang/Class;
      90: aload_0
      91: getfield      #141                // Field generic:Ljava/lang/String;
      94: invokestatic  #134                // Method org/apache/dubbo/common/utils/StringUtils.isEmpty:(Ljava/lang/String;)Z
      97: ifeq          188
     100: aload_0
     101: getstatic     #142                // Field java/lang/Boolean.TRUE:Ljava/lang/Boolean;
     104: invokevirtual #143                // Method java/lang/Boolean.toString:()Ljava/lang/String;
     107: putfield      #141                // Field generic:Ljava/lang/String;
     110: goto          188
     113: aload_0
     114: invokevirtual #144                // Method getInterfaceClassLoader:()Ljava/lang/ClassLoader;
     117: ifnull        139
     120: aload_0
     121: aload_0
     122: getfield      #133                // Field interfaceName:Ljava/lang/String;
     125: iconst_1
     126: aload_0
     127: invokevirtual #144                // Method getInterfaceClassLoader:()Ljava/lang/ClassLoader;
     130: invokestatic  #145                // Method java/lang/Class.forName:(Ljava/lang/String;ZLjava/lang/ClassLoader;)Ljava/lang/Class;
     133: putfield      #140                // Field interfaceClass:Ljava/lang/Class;
     136: goto          157
     139: aload_0
     140: aload_0
     141: getfield      #133                // Field interfaceName:Ljava/lang/String;
     144: iconst_1
     145: invokestatic  #69                 // Method java/lang/Thread.currentThread:()Ljava/lang/Thread;
     148: invokevirtual #146                // Method java/lang/Thread.getContextClassLoader:()Ljava/lang/ClassLoader;
     151: invokestatic  #145                // Method java/lang/Class.forName:(Ljava/lang/String;ZLjava/lang/ClassLoader;)Ljava/lang/Class;
     154: putfield      #140                // Field interfaceClass:Ljava/lang/Class;
     157: goto          174
     160: astore_2
     161: new           #135                // class java/lang/IllegalStateException
     164: dup
     165: aload_2
     166: invokevirtual #148                // Method java/lang/ClassNotFoundException.getMessage:()Ljava/lang/String;
     169: aload_2
     170: invokespecial #149                // Method java/lang/IllegalStateException."<init>":(Ljava/lang/String;Ljava/lang/Throwable;)V
     173: athrow
     174: aload_0
     175: invokevirtual #150                // Method checkRef:()V
     178: aload_0
     179: getstatic     #151                // Field java/lang/Boolean.FALSE:Ljava/lang/Boolean;
     182: invokevirtual #143                // Method java/lang/Boolean.toString:()Ljava/lang/String;
     185: putfield      #141                // Field generic:Ljava/lang/String;
     188: aload_0
     189: getfield      #152                // Field local:Ljava/lang/String;
     192: ifnull        311
     195: ldc           #153                // String true
     197: aload_0
     198: getfield      #152                // Field local:Ljava/lang/String;
     201: invokevirtual #154                // Method java/lang/String.equals:(Ljava/lang/Object;)Z
     204: ifeq          233
     207: aload_0
     208: new           #39                 // class java/lang/StringBuilder
     211: dup
     212: invokespecial #40                 // Method java/lang/StringBuilder."<init>":()V
     215: aload_0
     216: getfield      #133                // Field interfaceName:Ljava/lang/String;
     219: invokevirtual #42                 // Method java/lang/StringBuilder.append:(Ljava/lang/String;)Ljava/lang/StringBuilder;
     222: ldc           #155                // String Local
     224: invokevirtual #42                 // Method java/lang/StringBuilder.append:(Ljava/lang/String;)Ljava/lang/StringBuilder;
     227: invokevirtual #44                 // Method java/lang/StringBuilder.toString:()Ljava/lang/String;
     230: putfield      #152                // Field local:Ljava/lang/String;
     233: aload_0
     234: getfield      #152                // Field local:Ljava/lang/String;
     237: invokestatic  #156                // Method org/apache/dubbo/common/utils/ClassUtils.forNameWithThreadContextClassLoader:(Ljava/lang/String;)Ljava/lang/Class;
     240: astore_2
     241: goto          258
     244: astore_3
     245: new           #135                // class java/lang/IllegalStateException
     248: dup
     249: aload_3
     250: invokevirtual #148                // Method java/lang/ClassNotFoundException.getMessage:()Ljava/lang/String;
     253: aload_3
     254: invokespecial #149                // Method java/lang/IllegalStateException."<init>":(Ljava/lang/String;Ljava/lang/Throwable;)V
     257: athrow
     258: aload_0
     259: getfield      #140                // Field interfaceClass:Ljava/lang/Class;
     262: aload_2
     263: invokevirtual #157                // Method java/lang/Class.isAssignableFrom:(Ljava/lang/Class;)Z
     266: ifne          311
     269: new           #135                // class java/lang/IllegalStateException
     272: dup
     273: new           #39                 // class java/lang/StringBuilder
     276: dup
     277: invokespecial #40                 // Method java/lang/StringBuilder."<init>":()V
     280: ldc           #158                // String The local implementation class
     282: invokevirtual #42                 // Method java/lang/StringBuilder.append:(Ljava/lang/String;)Ljava/lang/StringBuilder;
     285: aload_2
     286: invokevirtual #159                // Method java/lang/Class.getName:()Ljava/lang/String;
     289: invokevirtual #42                 // Method java/lang/StringBuilder.append:(Ljava/lang/String;)Ljava/lang/StringBuilder;
     292: ldc           #160                // String  not implement interface
     294: invokevirtual #42                 // Method java/lang/StringBuilder.append:(Ljava/lang/String;)Ljava/lang/StringBuilder;
     297: aload_0
     298: getfield      #133                // Field interfaceName:Ljava/lang/String;
     301: invokevirtual #42                 // Method java/lang/StringBuilder.append:(Ljava/lang/String;)Ljava/lang/StringBuilder;
     304: invokevirtual #44                 // Method java/lang/StringBuilder.toString:()Ljava/lang/String;
     307: invokespecial #137                // Method java/lang/IllegalStateException."<init>":(Ljava/lang/String;)V
     310: athrow
     311: aload_0
     312: getfield      #161                // Field stub:Ljava/lang/String;
     315: ifnull        434
     318: ldc           #153                // String true
     320: aload_0
     321: getfield      #161                // Field stub:Ljava/lang/String;
     324: invokevirtual #154                // Method java/lang/String.equals:(Ljava/lang/Object;)Z
     327: ifeq          356
     330: aload_0
     331: new           #39                 // class java/lang/StringBuilder
     334: dup
     335: invokespecial #40                 // Method java/lang/StringBuilder."<init>":()V
     338: aload_0
     339: getfield      #133                // Field interfaceName:Ljava/lang/String;
     342: invokevirtual #42                 // Method java/lang/StringBuilder.append:(Ljava/lang/String;)Ljava/lang/StringBuilder;
     345: ldc           #162                // String Stub
     347: invokevirtual #42                 // Method java/lang/StringBuilder.append:(Ljava/lang/String;)Ljava/lang/StringBuilder;
     350: invokevirtual #44                 // Method java/lang/StringBuilder.toString:()Ljava/lang/String;
     353: putfield      #161                // Field stub:Ljava/lang/String;
     356: aload_0
     357: getfield      #161                // Field stub:Ljava/lang/String;
     360: invokestatic  #156                // Method org/apache/dubbo/common/utils/ClassUtils.forNameWithThreadContextClassLoader:(Ljava/lang/String;)Ljava/lang/Class;
     363: astore_2
     364: goto          381
     367: astore_3
     368: new           #135                // class java/lang/IllegalStateException
     371: dup
     372: aload_3
     373: invokevirtual #148                // Method java/lang/ClassNotFoundException.getMessage:()Ljava/lang/String;
     376: aload_3
     377: invokespecial #149                // Method java/lang/IllegalStateException."<init>":(Ljava/lang/String;Ljava/lang/Throwable;)V
     380: athrow
     381: aload_0
     382: getfield      #140                // Field interfaceClass:Ljava/lang/Class;
     385: aload_2
     386: invokevirtual #157                // Method java/lang/Class.isAssignableFrom:(Ljava/lang/Class;)Z
     389: ifne          434
     392: new           #135                // class java/lang/IllegalStateException
     395: dup
     396: new           #39                 // class java/lang/StringBuilder
     399: dup
     400: invokespecial #40                 // Method java/lang/StringBuilder."<init>":()V
     403: ldc           #163                // String The stub implementation class
     405: invokevirtual #42                 // Method java/lang/StringBuilder.append:(Ljava/lang/String;)Ljava/lang/StringBuilder;
     408: aload_2
     409: invokevirtual #159                // Method java/lang/Class.getName:()Ljava/lang/String;
     412: invokevirtual #42                 // Method java/lang/StringBuilder.append:(Ljava/lang/String;)Ljava/lang/StringBuilder;
     415: ldc           #160                // String  not implement interface
     417: invokevirtual #42                 // Method java/lang/StringBuilder.append:(Ljava/lang/String;)Ljava/lang/StringBuilder;
     420: aload_0
     421: getfield      #133                // Field interfaceName:Ljava/lang/String;
     424: invokevirtual #42                 // Method java/lang/StringBuilder.append:(Ljava/lang/String;)Ljava/lang/StringBuilder;
     427: invokevirtual #44                 // Method java/lang/StringBuilder.toString:()Ljava/lang/String;
     430: invokespecial #137                // Method java/lang/IllegalStateException."<init>":(Ljava/lang/String;)V
     433: athrow
     434: aload_0
     435: aload_0
     436: getfield      #140                // Field interfaceClass:Ljava/lang/Class;
     439: invokevirtual #164                // Method checkStubAndLocal:(Ljava/lang/Class;)V
     442: aload_0
     443: getfield      #140                // Field interfaceClass:Ljava/lang/Class;
     446: aload_0
     447: invokestatic  #165                // Method org/apache/dubbo/config/utils/ConfigValidationUtils.checkMock:(Ljava/lang/Class;Lorg/apache/dubbo/config/AbstractInterfaceConfig;)V
     450: aload_0
     451: invokestatic  #166                // Method org/apache/dubbo/config/utils/ConfigValidationUtils.validateServiceConfig:(Lorg/apache/dubbo/config/ServiceConfig;)V
     454: aload_0
     455: invokespecial #167                // Method postProcessConfig:()V
     458: return
    Exception table:
       from    to  target type
         113   157   160   Class java/lang/ClassNotFoundException
         233   241   244   Class java/lang/ClassNotFoundException
         356   364   367   Class java/lang/ClassNotFoundException

  protected void postProcessRefresh();
    Code:
       0: aload_0
       1: invokespecial #168                // Method org/apache/dubbo/config/ServiceConfigBase.postProcessRefresh:()V
       4: aload_0
       5: invokespecial #169                // Method checkAndUpdateSubConfigs:()V
       8: return

  protected synchronized void doExport();
    Code:
       0: aload_0
       1: getfield      #28                 // Field unexported:Z
       4: ifeq          45
       7: new           #135                // class java/lang/IllegalStateException
      10: dup
      11: new           #39                 // class java/lang/StringBuilder
      14: dup
      15: invokespecial #40                 // Method java/lang/StringBuilder."<init>":()V
      18: ldc           #170                // String The service
      20: invokevirtual #42                 // Method java/lang/StringBuilder.append:(Ljava/lang/String;)Ljava/lang/StringBuilder;
      23: aload_0
      24: getfield      #140                // Field interfaceClass:Ljava/lang/Class;
      27: invokevirtual #159                // Method java/lang/Class.getName:()Ljava/lang/String;
      30: invokevirtual #42                 // Method java/lang/StringBuilder.append:(Ljava/lang/String;)Ljava/lang/StringBuilder;
      33: ldc           #171                // String  has already unexported!
      35: invokevirtual #42                 // Method java/lang/StringBuilder.append:(Ljava/lang/String;)Ljava/lang/StringBuilder;
      38: invokevirtual #44                 // Method java/lang/StringBuilder.toString:()Ljava/lang/String;
      41: invokespecial #137                // Method java/lang/IllegalStateException."<init>":(Ljava/lang/String;)V
      44: athrow
      45: aload_0
      46: getfield      #27                 // Field exported:Z
      49: ifeq          53
      52: return
      53: aload_0
      54: getfield      #172                // Field path:Ljava/lang/String;
      57: invokestatic  #134                // Method org/apache/dubbo/common/utils/StringUtils.isEmpty:(Ljava/lang/String;)Z
      60: ifeq          71
      63: aload_0
      64: aload_0
      65: getfield      #133                // Field interfaceName:Ljava/lang/String;
      68: putfield      #172                // Field path:Ljava/lang/String;
      71: aload_0
      72: invokespecial #173                // Method doExportUrls:()V
      75: aload_0
      76: invokevirtual #174                // Method exported:()V
      79: return

  private void doExportUrls();
    Code:
       0: aload_0
       1: invokevirtual #50                 // Method getScopeModel:()Lorg/apache/dubbo/rpc/model/ModuleModel;
       4: invokevirtual #51                 // Method org/apache/dubbo/rpc/model/ModuleModel.getServiceRepository:()Lorg/apache/dubbo/rpc/model/ModuleServiceRepository;
       7: astore_1
       8: aload_0
       9: getfield      #138                // Field ref:Ljava/lang/Object;
      12: instanceof    #175                // class org/apache/dubbo/rpc/ServerService
      15: istore_3
      16: iload_3
      17: ifeq          42
      20: aload_0
      21: getfield      #138                // Field ref:Ljava/lang/Object;
      24: checkcast     #175                // class org/apache/dubbo/rpc/ServerService
      27: invokeinterface #176,  1          // InterfaceMethod org/apache/dubbo/rpc/ServerService.getServiceDescriptor:()Lorg/apache/dubbo/rpc/model/ServiceDescriptor;
      32: astore_2
      33: aload_1
      34: aload_2
      35: invokevirtual #177                // Method org/apache/dubbo/rpc/model/ModuleServiceRepository.registerService:(Lorg/apache/dubbo/rpc/model/ServiceDescriptor;)Lorg/apache/dubbo/rpc/model/ServiceDescriptor;
      38: pop
      39: goto          51
      42: aload_1
      43: aload_0
      44: invokevirtual #80                 // Method getInterfaceClass:()Ljava/lang/Class;
      47: invokevirtual #178                // Method org/apache/dubbo/rpc/model/ModuleServiceRepository.registerService:(Ljava/lang/Class;)Lorg/apache/dubbo/rpc/model/ServiceDescriptor;
      50: astore_2
      51: aload_0
      52: new           #179                // class org/apache/dubbo/rpc/model/ProviderModel
      55: dup
      56: aload_0
      57: getfield      #79                 // Field serviceMetadata:Lorg/apache/dubbo/rpc/model/ServiceMetadata;
      60: invokevirtual #180                // Method org/apache/dubbo/rpc/model/ServiceMetadata.getServiceKey:()Ljava/lang/String;
      63: aload_0
      64: getfield      #138                // Field ref:Ljava/lang/Object;
      67: aload_2
      68: aload_0
      69: invokevirtual #50                 // Method getScopeModel:()Lorg/apache/dubbo/rpc/model/ModuleModel;
      72: aload_0
      73: getfield      #79                 // Field serviceMetadata:Lorg/apache/dubbo/rpc/model/ServiceMetadata;
      76: aload_0
      77: getfield      #181                // Field interfaceClassLoader:Ljava/lang/ClassLoader;
      80: invokespecial #182                // Method org/apache/dubbo/rpc/model/ProviderModel."<init>":(Ljava/lang/String;Ljava/lang/Object;Lorg/apache/dubbo/rpc/model/ServiceDescriptor;Lorg/apache/dubbo/rpc/model/ModuleModel;Lorg/apache/dubbo/rpc/model/ServiceMetadata;Ljava/lang/ClassLoader;)V
      83: putfield      #52                 // Field providerModel:Lorg/apache/dubbo/rpc/model/ProviderModel;
      86: aload_0
      87: getfield      #52                 // Field providerModel:Lorg/apache/dubbo/rpc/model/ProviderModel;
      90: aload_0
      91: invokevirtual #183                // Method org/apache/dubbo/rpc/model/ProviderModel.setConfig:(Lorg/apache/dubbo/config/AbstractInterfaceConfig;)V
      94: aload_0
      95: getfield      #52                 // Field providerModel:Lorg/apache/dubbo/rpc/model/ProviderModel;
      98: aload_0
      99: invokevirtual #184                // Method getDestroyRunner:()Ljava/lang/Runnable;
     102: invokevirtual #185                // Method org/apache/dubbo/rpc/model/ProviderModel.setDestroyRunner:(Ljava/lang/Runnable;)V
     105: aload_1
     106: aload_0
     107: getfield      #52                 // Field providerModel:Lorg/apache/dubbo/rpc/model/ProviderModel;
     110: invokevirtual #186                // Method org/apache/dubbo/rpc/model/ModuleServiceRepository.registerProvider:(Lorg/apache/dubbo/rpc/model/ProviderModel;)V
     113: aload_0
     114: iconst_1
     115: invokestatic  #187                // Method org/apache/dubbo/config/utils/ConfigValidationUtils.loadRegistries:(Lorg/apache/dubbo/config/AbstractInterfaceConfig;Z)Ljava/util/List;
     118: astore        4
     120: aload_0
     121: getfield      #188                // Field module:Lorg/apache/dubbo/config/ModuleConfig;
     124: invokevirtual #189                // Method org/apache/dubbo/config/ModuleConfig.getApplicationModel:()Lorg/apache/dubbo/rpc/model/ApplicationModel;
     127: aload_0
     128: invokevirtual #58                 // Method getUniqueServiceName:()Ljava/lang/String;
     131: aload_0
     132: getfield      #190                // Field protocols:Ljava/util/List;
     135: invokeinterface #191,  1          // InterfaceMethod java/util/List.size:()I
     140: aload         4
     142: invokeinterface #191,  1          // InterfaceMethod java/util/List.size:()I
     147: imul
     148: invokestatic  #192                // Method org/apache/dubbo/metrics/registry/event/RegistryEvent.toRsEvent:(Lorg/apache/dubbo/rpc/model/ApplicationModel;Ljava/lang/String;I)Lorg/apache/dubbo/metrics/registry/event/RegistryEvent;
     151: aload_0
     152: iload_3
     153: aload_1
     154: aload         4
     156: invokedynamic #193,  0            // InvokeDynamic #4:get:(Lorg/apache/dubbo/config/ServiceConfig;ZLorg/apache/dubbo/rpc/model/ModuleServiceRepository;Ljava/util/List;)Ljava/util/function/Supplier;
     161: invokestatic  #194                // Method org/apache/dubbo/metrics/event/MetricsEventBus.post:(Lorg/apache/dubbo/metrics/event/MetricsEvent;Ljava/util/function/Supplier;)Ljava/lang/Object;
     164: pop
     165: aload_0
     166: getfield      #52                 // Field providerModel:Lorg/apache/dubbo/rpc/model/ProviderModel;
     169: aload_0
     170: getfield      #195                // Field urls:Ljava/util/List;
     173: invokevirtual #196                // Method org/apache/dubbo/rpc/model/ProviderModel.setServiceUrls:(Ljava/util/List;)V
     176: return

  private void doExportUrlsFor1Protocol(org.apache.dubbo.config.ProtocolConfig, java.util.List<org.apache.dubbo.common.URL>);
    Code:
       0: aload_0
       1: aload_1
       2: invokespecial #197                // Method buildAttributes:(Lorg/apache/dubbo/config/ProtocolConfig;)Ljava/util/Map;
       5: astore_3
       6: aload_3
       7: invokeinterface #198,  1          // InterfaceMethod java/util/Map.keySet:()Ljava/util/Set;
      12: aload_3
      13: invokedynamic #199,  0            // InvokeDynamic #5:test:(Ljava/util/Map;)Ljava/util/function/Predicate;
      18: invokeinterface #200,  2          // InterfaceMethod java/util/Set.removeIf:(Ljava/util/function/Predicate;)Z
      23: pop
      24: aload_0
      25: getfield      #79                 // Field serviceMetadata:Lorg/apache/dubbo/rpc/model/ServiceMetadata;
      28: invokevirtual #201                // Method org/apache/dubbo/rpc/model/ServiceMetadata.getAttachments:()Ljava/util/Map;
      31: aload_3
      32: invokeinterface #202,  2          // InterfaceMethod java/util/Map.putAll:(Ljava/util/Map;)V
      37: aload_0
      38: aload_1
      39: aload_3
      40: invokespecial #203                // Method buildUrl:(Lorg/apache/dubbo/config/ProtocolConfig;Ljava/util/Map;)Lorg/apache/dubbo/common/URL;
      43: astore        4
      45: aload_0
      46: aload         4
      48: invokespecial #204                // Method processServiceExecutor:(Lorg/apache/dubbo/common/URL;)V
      51: aload_0
      52: aload         4
      54: aload_2
      55: invokespecial #205                // Method exportUrl:(Lorg/apache/dubbo/common/URL;Ljava/util/List;)V
      58: return

  private void processServiceExecutor(org.apache.dubbo.common.URL);
    Code:
       0: aload_0
       1: invokevirtual #206                // Method getExecutor:()Ljava/util/concurrent/Executor;
       4: ifnull        100
       7: aload_0
       8: getfield      #207                // Field application:Lorg/apache/dubbo/config/ApplicationConfig;
      11: invokevirtual #208                // Method org/apache/dubbo/config/ApplicationConfig.getExecutorManagementMode:()Ljava/lang/String;
      14: astore_2
      15: ldc           #209                // String isolation
      17: aload_2
      18: invokevirtual #154                // Method java/lang/String.equals:(Ljava/lang/Object;)Z
      21: ifne          68
      24: getstatic     #36                 // Field logger:Lorg/apache/dubbo/common/logger/ErrorTypeAwareLogger;
      27: ldc           #210                // String 0-27
      29: ldc           #38                 // String
      31: ldc           #38                 // String
      33: new           #39                 // class java/lang/StringBuilder
      36: dup
      37: invokespecial #40                 // Method java/lang/StringBuilder."<init>":()V
      40: ldc           #211                // String The current executor management mode is
      42: invokevirtual #42                 // Method java/lang/StringBuilder.append:(Ljava/lang/String;)Ljava/lang/StringBuilder;
      45: aload_2
      46: invokevirtual #42                 // Method java/lang/StringBuilder.append:(Ljava/lang/String;)Ljava/lang/StringBuilder;
      49: ldc           #212                // String , the configured service executor cannot take effect unless the mode is configured as
      51: invokevirtual #42                 // Method java/lang/StringBuilder.append:(Ljava/lang/String;)Ljava/lang/StringBuilder;
      54: ldc           #209                // String isolation
      56: invokevirtual #42                 // Method java/lang/StringBuilder.append:(Ljava/lang/String;)Ljava/lang/StringBuilder;
      59: invokevirtual #44                 // Method java/lang/StringBuilder.toString:()Ljava/lang/String;
      62: invokeinterface #213,  5          // InterfaceMethod org/apache/dubbo/common/logger/ErrorTypeAwareLogger.warn:(Ljava/lang/String;Ljava/lang/String;Ljava/lang/String;Ljava/lang/String;)V
      67: return
      68: aload_0
      69: getfield      #52                 // Field providerModel:Lorg/apache/dubbo/rpc/model/ProviderModel;
      72: invokevirtual #214                // Method org/apache/dubbo/rpc/model/ProviderModel.getServiceMetadata:()Lorg/apache/dubbo/rpc/model/ServiceMetadata;
      75: ldc           #215                // String service-executor
      77: aload_0
      78: invokevirtual #206                // Method getExecutor:()Ljava/util/concurrent/Executor;
      81: invokevirtual #216                // Method org/apache/dubbo/rpc/model/ServiceMetadata.addAttribute:(Ljava/lang/String;Ljava/lang/Object;)V
      84: aload_1
      85: invokevirtual #217                // Method org/apache/dubbo/common/URL.getAttributes:()Ljava/util/Map;
      88: ldc           #215                // String service-executor
      90: aload_0
      91: invokevirtual #206                // Method getExecutor:()Ljava/util/concurrent/Executor;
      94: invokeinterface #218,  3          // InterfaceMethod java/util/Map.put:(Ljava/lang/Object;Ljava/lang/Object;)Ljava/lang/Object;
      99: pop
     100: return

  private java.util.Map<java.lang.String, java.lang.String> buildAttributes(org.apache.dubbo.config.ProtocolConfig);
    Code:
       0: new           #219                // class java/util/HashMap
       3: dup
       4: invokespecial #220                // Method java/util/HashMap."<init>":()V
       7: astore_2
       8: aload_2
       9: ldc           #221                // String side
      11: ldc           #222                // String provider
      13: invokeinterface #218,  3          // InterfaceMethod java/util/Map.put:(Ljava/lang/Object;Ljava/lang/Object;)Ljava/lang/Object;
      18: pop
      19: aload_2
      20: invokestatic  #223                // Method appendRuntimeParameters:(Ljava/util/Map;)V
      23: aload_2
      24: aload_0
      25: invokevirtual #118                // Method getApplication:()Lorg/apache/dubbo/config/ApplicationConfig;
      28: invokestatic  #224                // Method org/apache/dubbo/config/AbstractConfig.appendParameters:(Ljava/util/Map;Ljava/lang/Object;)V
      31: aload_2
      32: aload_0
      33: invokevirtual #225                // Method getModule:()Lorg/apache/dubbo/config/ModuleConfig;
      36: invokestatic  #224                // Method org/apache/dubbo/config/AbstractConfig.appendParameters:(Ljava/util/Map;Ljava/lang/Object;)V
      39: aload_2
      40: aload_0
      41: getfield      #77                 // Field provider:Lorg/apache/dubbo/config/ProviderConfig;
      44: invokestatic  #224                // Method org/apache/dubbo/config/AbstractConfig.appendParameters:(Ljava/util/Map;Ljava/lang/Object;)V
      47: aload_2
      48: aload_1
      49: invokestatic  #224                // Method org/apache/dubbo/config/AbstractConfig.appendParameters:(Ljava/util/Map;Ljava/lang/Object;)V
      52: aload_2
      53: aload_0
      54: invokestatic  #224                // Method org/apache/dubbo/config/AbstractConfig.appendParameters:(Ljava/util/Map;Ljava/lang/Object;)V
      57: aload_0
      58: aload_2
      59: invokevirtual #226                // Method appendMetricsCompatible:(Ljava/util/Map;)V
      62: aload_0
      63: invokevirtual #227                // Method getMethods:()Ljava/util/List;
      66: invokestatic  #228                // Method org/apache/dubbo/common/utils/CollectionUtils.isNotEmpty:(Ljava/util/Collection;)Z
      69: ifeq          88
      72: aload_0
      73: invokevirtual #227                // Method getMethods:()Ljava/util/List;
      76: aload_0
      77: aload_2
      78: invokedynamic #229,  0            // InvokeDynamic #6:accept:(Lorg/apache/dubbo/config/ServiceConfig;Ljava/util/Map;)Ljava/util/function/Consumer;
      83: invokeinterface #104,  2          // InterfaceMethod java/util/List.forEach:(Ljava/util/function/Consumer;)V
      88: aload_0
      89: getfield      #141                // Field generic:Ljava/lang/String;
      92: invokestatic  #230                // Method org/apache/dubbo/rpc/support/ProtocolUtils.isGeneric:(Ljava/lang/String;)Z
      95: ifeq          125
      98: aload_2
      99: ldc           #231                // String generic
     101: aload_0
     102: getfield      #141                // Field generic:Ljava/lang/String;
     105: invokeinterface #218,  3          // InterfaceMethod java/util/Map.put:(Ljava/lang/Object;Ljava/lang/Object;)Ljava/lang/Object;
     110: pop
     111: aload_2
     112: ldc           #232                // String methods
     114: ldc           #233                // String *
     116: invokeinterface #218,  3          // InterfaceMethod java/util/Map.put:(Ljava/lang/Object;Ljava/lang/Object;)Ljava/lang/Object;
     121: pop
     122: goto          263
     125: aload_0
     126: getfield      #140                // Field interfaceClass:Ljava/lang/Class;
     129: aload_0
     130: getfield      #234                // Field version:Ljava/lang/String;
     133: invokestatic  #235                // Method org/apache/dubbo/common/Version.getVersion:(Ljava/lang/Class;Ljava/lang/String;)Ljava/lang/String;
     136: astore_3
     137: aload_3
     138: invokestatic  #236                // Method org/apache/dubbo/common/utils/StringUtils.isNotEmpty:(Ljava/lang/String;)Z
     141: ifeq          154
     144: aload_2
     145: ldc           #237                // String revision
     147: aload_3
     148: invokeinterface #218,  3          // InterfaceMethod java/util/Map.put:(Ljava/lang/Object;Ljava/lang/Object;)Ljava/lang/Object;
     153: pop
     154: aload_0
     155: aload_0
     156: getfield      #140                // Field interfaceClass:Ljava/lang/Class;
     159: invokevirtual #238                // Method methods:(Ljava/lang/Class;)[Ljava/lang/String;
     162: astore        4
     164: aload         4
     166: arraylength
     167: ifne          223
     170: getstatic     #36                 // Field logger:Lorg/apache/dubbo/common/logger/ErrorTypeAwareLogger;
     173: ldc           #239                // String 5-4
     175: ldc           #38                 // String
     177: ldc           #38                 // String
     179: new           #39                 // class java/lang/StringBuilder
     182: dup
     183: invokespecial #40                 // Method java/lang/StringBuilder."<init>":()V
     186: ldc           #240                // String No method found in service interface:
     188: invokevirtual #42                 // Method java/lang/StringBuilder.append:(Ljava/lang/String;)Ljava/lang/StringBuilder;
     191: aload_0
     192: getfield      #140                // Field interfaceClass:Ljava/lang/Class;
     195: invokevirtual #159                // Method java/lang/Class.getName:()Ljava/lang/String;
     198: invokevirtual #42                 // Method java/lang/StringBuilder.append:(Ljava/lang/String;)Ljava/lang/StringBuilder;
     201: invokevirtual #44                 // Method java/lang/StringBuilder.toString:()Ljava/lang/String;
     204: invokeinterface #213,  5          // InterfaceMethod org/apache/dubbo/common/logger/ErrorTypeAwareLogger.warn:(Ljava/lang/String;Ljava/lang/String;Ljava/lang/String;Ljava/lang/String;)V
     209: aload_2
     210: ldc           #232                // String methods
     212: ldc           #233                // String *
     214: invokeinterface #218,  3          // InterfaceMethod java/util/Map.put:(Ljava/lang/Object;Ljava/lang/Object;)Ljava/lang/Object;
     219: pop
     220: goto          263
     223: new           #13                 // class java/util/ArrayList
     226: dup
     227: aload         4
     229: invokestatic  #241                // Method java/util/Arrays.asList:([Ljava/lang/Object;)Ljava/util/List;
     232: invokespecial #242                // Method java/util/ArrayList."<init>":(Ljava/util/Collection;)V
     235: astore        5
     237: aload         5
     239: invokestatic  #243                // InterfaceMethod java/util/Comparator.naturalOrder:()Ljava/util/Comparator;
     242: invokeinterface #244,  2          // InterfaceMethod java/util/List.sort:(Ljava/util/Comparator;)V
     247: aload_2
     248: ldc           #232                // String methods
     250: ldc           #245                // String ,
     252: aload         5
     254: invokestatic  #246                // Method java/lang/String.join:(Ljava/lang/CharSequence;Ljava/lang/Iterable;)Ljava/lang/String;
     257: invokeinterface #218,  3          // InterfaceMethod java/util/Map.put:(Ljava/lang/Object;Ljava/lang/Object;)Ljava/lang/Object;
     262: pop
     263: aload_0
     264: getfield      #247                // Field token:Ljava/lang/String;
     267: invokestatic  #248                // Method org/apache/dubbo/common/utils/ConfigUtils.isEmpty:(Ljava/lang/String;)Z
     270: ifeq          291
     273: aload_0
     274: getfield      #77                 // Field provider:Lorg/apache/dubbo/config/ProviderConfig;
     277: ifnull        291
     280: aload_0
     281: aload_0
     282: getfield      #77                 // Field provider:Lorg/apache/dubbo/config/ProviderConfig;
     285: invokevirtual #249                // Method org/apache/dubbo/config/ProviderConfig.getToken:()Ljava/lang/String;
     288: putfield      #247                // Field token:Ljava/lang/String;
     291: aload_0
     292: getfield      #247                // Field token:Ljava/lang/String;
     295: invokestatic  #248                // Method org/apache/dubbo/common/utils/ConfigUtils.isEmpty:(Ljava/lang/String;)Z
     298: ifne          342
     301: aload_0
     302: getfield      #247                // Field token:Ljava/lang/String;
     305: invokestatic  #250                // Method org/apache/dubbo/common/utils/ConfigUtils.isDefault:(Ljava/lang/String;)Z
     308: ifeq          329
     311: aload_2
     312: ldc           #251                // String token
     314: invokestatic  #252                // Method java/util/UUID.randomUUID:()Ljava/util/UUID;
     317: invokevirtual #253                // Method java/util/UUID.toString:()Ljava/lang/String;
     320: invokeinterface #218,  3          // InterfaceMethod java/util/Map.put:(Ljava/lang/Object;Ljava/lang/Object;)Ljava/lang/Object;
     325: pop
     326: goto          342
     329: aload_2
     330: ldc           #251                // String token
     332: aload_0
     333: getfield      #247                // Field token:Ljava/lang/String;
     336: invokeinterface #218,  3          // InterfaceMethod java/util/Map.put:(Ljava/lang/Object;Ljava/lang/Object;)Ljava/lang/Object;
     341: pop
     342: aload_0
     343: getfield      #138                // Field ref:Ljava/lang/Object;
     346: instanceof    #175                // class org/apache/dubbo/rpc/ServerService
     349: ifeq          363
     352: aload_2
     353: ldc           #254                // String proxy
     355: ldc           #255                // String nativestub
     357: invokeinterface #218,  3          // InterfaceMethod java/util/Map.put:(Ljava/lang/Object;Ljava/lang/Object;)Ljava/lang/Object;
     362: pop
     363: aload_2
     364: areturn

  private void appendParametersWithMethod(org.apache.dubbo.config.MethodConfig, java.util.Map<java.lang.String, java.lang.String>);
    Code:
       0: aload_2
       1: aload_1
       2: aload_1
       3: invokevirtual #256                // Method org/apache/dubbo/config/MethodConfig.getName:()Ljava/lang/String;
       6: invokestatic  #257                // Method org/apache/dubbo/config/AbstractConfig.appendParameters:(Ljava/util/Map;Ljava/lang/Object;Ljava/lang/String;)V
       9: new           #39                 // class java/lang/StringBuilder
      12: dup
      13: invokespecial #40                 // Method java/lang/StringBuilder."<init>":()V
      16: aload_1
      17: invokevirtual #256                // Method org/apache/dubbo/config/MethodConfig.getName:()Ljava/lang/String;
      20: invokevirtual #42                 // Method java/lang/StringBuilder.append:(Ljava/lang/String;)Ljava/lang/StringBuilder;
      23: ldc_w         #258                // String .retry
      26: invokevirtual #42                 // Method java/lang/StringBuilder.append:(Ljava/lang/String;)Ljava/lang/StringBuilder;
      29: invokevirtual #44                 // Method java/lang/StringBuilder.toString:()Ljava/lang/String;
      32: astore_3
      33: aload_2
      34: aload_3
      35: invokeinterface #259,  2          // InterfaceMethod java/util/Map.containsKey:(Ljava/lang/Object;)Z
      40: ifeq          99
      43: aload_2
      44: aload_3
      45: invokeinterface #260,  2          // InterfaceMethod java/util/Map.remove:(Ljava/lang/Object;)Ljava/lang/Object;
      50: checkcast     #261                // class java/lang/String
      53: astore        4
      55: ldc_w         #262                // String false
      58: aload         4
      60: invokevirtual #154                // Method java/lang/String.equals:(Ljava/lang/Object;)Z
      63: ifeq          99
      66: aload_2
      67: new           #39                 // class java/lang/StringBuilder
      70: dup
      71: invokespecial #40                 // Method java/lang/StringBuilder."<init>":()V
      74: aload_1
      75: invokevirtual #256                // Method org/apache/dubbo/config/MethodConfig.getName:()Ljava/lang/String;
      78: invokevirtual #42                 // Method java/lang/StringBuilder.append:(Ljava/lang/String;)Ljava/lang/StringBuilder;
      81: ldc_w         #263                // String .retries
      84: invokevirtual #42                 // Method java/lang/StringBuilder.append:(Ljava/lang/String;)Ljava/lang/StringBuilder;
      87: invokevirtual #44                 // Method java/lang/StringBuilder.toString:()Ljava/lang/String;
      90: ldc_w         #264                // String 0
      93: invokeinterface #218,  3          // InterfaceMethod java/util/Map.put:(Ljava/lang/Object;Ljava/lang/Object;)Ljava/lang/Object;
      98: pop
      99: aload_1
     100: invokevirtual #265                // Method org/apache/dubbo/config/MethodConfig.getArguments:()Ljava/util/List;
     103: astore        4
     105: aload         4
     107: invokestatic  #228                // Method org/apache/dubbo/common/utils/CollectionUtils.isNotEmpty:(Ljava/util/Collection;)Z
     110: ifeq          141
     113: aload_0
     114: aload_1
     115: invokespecial #266                // Method findMatchedMethod:(Lorg/apache/dubbo/config/MethodConfig;)Ljava/lang/reflect/Method;
     118: astore        5
     120: aload         5
     122: ifnull        141
     125: aload         4
     127: aload_0
     128: aload         5
     130: aload_2
     131: invokedynamic #267,  0            // InvokeDynamic #7:accept:(Lorg/apache/dubbo/config/ServiceConfig;Ljava/lang/reflect/Method;Ljava/util/Map;)Ljava/util/function/Consumer;
     136: invokeinterface #104,  2          // InterfaceMethod java/util/List.forEach:(Ljava/util/function/Consumer;)V
     141: return

  private java.lang.reflect.Method findMatchedMethod(org.apache.dubbo.config.MethodConfig);
    Code:
       0: aload_0
       1: getfield      #140                // Field interfaceClass:Ljava/lang/Class;
       4: invokevirtual #268                // Method java/lang/Class.getMethods:()[Ljava/lang/reflect/Method;
       7: astore_2
       8: aload_2
       9: arraylength
      10: istore_3
      11: iconst_0
      12: istore        4
      14: iload         4
      16: iload_3
      17: if_icmpge     50
      20: aload_2
      21: iload         4
      23: aaload
      24: astore        5
      26: aload         5
      28: invokevirtual #269                // Method java/lang/reflect/Method.getName:()Ljava/lang/String;
      31: aload_1
      32: invokevirtual #256                // Method org/apache/dubbo/config/MethodConfig.getName:()Ljava/lang/String;
      35: invokevirtual #154                // Method java/lang/String.equals:(Ljava/lang/Object;)Z
      38: ifeq          44
      41: aload         5
      43: areturn
      44: iinc          4, 1
      47: goto          14
      50: aconst_null
      51: areturn

  private void appendArgumentConfig(org.apache.dubbo.config.ArgumentConfig, java.lang.reflect.Method, java.util.Map<java.lang.String, java.lang.String>);
    Code:
       0: aload_1
       1: invokevirtual #270                // Method org/apache/dubbo/config/ArgumentConfig.getType:()Ljava/lang/String;
       4: invokestatic  #236                // Method org/apache/dubbo/common/utils/StringUtils.isNotEmpty:(Ljava/lang/String;)Z
       7: ifeq          54
      10: aload_0
      11: aload_1
      12: aload_2
      13: invokespecial #271                // Method findArgumentIndexIndexWithGivenType:(Lorg/apache/dubbo/config/ArgumentConfig;Ljava/lang/reflect/Method;)Ljava/lang/Integer;
      16: astore        4
      18: aload_3
      19: aload_1
      20: new           #39                 // class java/lang/StringBuilder
      23: dup
      24: invokespecial #40                 // Method java/lang/StringBuilder."<init>":()V
      27: aload_2
      28: invokevirtual #269                // Method java/lang/reflect/Method.getName:()Ljava/lang/String;
      31: invokevirtual #42                 // Method java/lang/StringBuilder.append:(Ljava/lang/String;)Ljava/lang/StringBuilder;
      34: ldc_w         #272                // String .
      37: invokevirtual #42                 // Method java/lang/StringBuilder.append:(Ljava/lang/String;)Ljava/lang/StringBuilder;
      40: aload         4
      42: invokevirtual #43                 // Method java/lang/StringBuilder.append:(Ljava/lang/Object;)Ljava/lang/StringBuilder;
      45: invokevirtual #44                 // Method java/lang/StringBuilder.toString:()Ljava/lang/String;
      48: invokestatic  #257                // Method org/apache/dubbo/config/AbstractConfig.appendParameters:(Ljava/util/Map;Ljava/lang/Object;Ljava/lang/String;)V
      51: goto          111
      54: aload_0
      55: aload_1
      56: invokespecial #273                // Method hasIndex:(Lorg/apache/dubbo/config/ArgumentConfig;)Z
      59: ifeq          100
      62: aload_3
      63: aload_1
      64: new           #39                 // class java/lang/StringBuilder
      67: dup
      68: invokespecial #40                 // Method java/lang/StringBuilder."<init>":()V
      71: aload_2
      72: invokevirtual #269                // Method java/lang/reflect/Method.getName:()Ljava/lang/String;
      75: invokevirtual #42                 // Method java/lang/StringBuilder.append:(Ljava/lang/String;)Ljava/lang/StringBuilder;
      78: ldc_w         #272                // String .
      81: invokevirtual #42                 // Method java/lang/StringBuilder.append:(Ljava/lang/String;)Ljava/lang/StringBuilder;
      84: aload_1
      85: invokevirtual #274                // Method org/apache/dubbo/config/ArgumentConfig.getIndex:()Ljava/lang/Integer;
      88: invokevirtual #43                 // Method java/lang/StringBuilder.append:(Ljava/lang/Object;)Ljava/lang/StringBuilder;
      91: invokevirtual #44                 // Method java/lang/StringBuilder.toString:()Ljava/lang/String;
      94: invokestatic  #257                // Method org/apache/dubbo/config/AbstractConfig.appendParameters:(Ljava/util/Map;Ljava/lang/Object;Ljava/lang/String;)V
      97: goto          111
     100: new           #275                // class java/lang/IllegalArgumentException
     103: dup
     104: ldc_w         #276                // String Argument config must set index or type attribute.eg: <dubbo:argument index=\'0\' .../> or <dubbo:argument type=xxx .../>
     107: invokespecial #277                // Method java/lang/IllegalArgumentException."<init>":(Ljava/lang/String;)V
     110: athrow
     111: return

  private boolean hasIndex(org.apache.dubbo.config.ArgumentConfig);
    Code:
       0: aload_1
       1: invokevirtual #274                // Method org/apache/dubbo/config/ArgumentConfig.getIndex:()Ljava/lang/Integer;
       4: invokevirtual #99                 // Method java/lang/Integer.intValue:()I
       7: iconst_m1
       8: if_icmpeq     15
      11: iconst_1
      12: goto          16
      15: iconst_0
      16: ireturn

  private boolean isTypeMatched(java.lang.String, java.lang.Integer, java.lang.Class<?>[]);
    Code:
       0: aload_2
       1: ifnull        40
       4: aload_2
       5: invokevirtual #99                 // Method java/lang/Integer.intValue:()I
       8: iflt          40
      11: aload_2
      12: invokevirtual #99                 // Method java/lang/Integer.intValue:()I
      15: aload_3
      16: arraylength
      17: if_icmpge     40
      20: aload_3
      21: aload_2
      22: invokevirtual #99                 // Method java/lang/Integer.intValue:()I
      25: aaload
      26: invokevirtual #159                // Method java/lang/Class.getName:()Ljava/lang/String;
      29: aload_1
      30: invokevirtual #154                // Method java/lang/String.equals:(Ljava/lang/Object;)Z
      33: ifeq          40
      36: iconst_1
      37: goto          41
      40: iconst_0
      41: ireturn

  private java.lang.Integer findArgumentIndexIndexWithGivenType(org.apache.dubbo.config.ArgumentConfig, java.lang.reflect.Method);
    Code:
       0: aload_2
       1: invokevirtual #278                // Method java/lang/reflect/Method.getParameterTypes:()[Ljava/lang/Class;
       4: astore_3
       5: aload_0
       6: aload_1
       7: invokespecial #273                // Method hasIndex:(Lorg/apache/dubbo/config/ArgumentConfig;)Z
      10: ifeq          84
      13: aload_1
      14: invokevirtual #274                // Method org/apache/dubbo/config/ArgumentConfig.getIndex:()Ljava/lang/Integer;
      17: astore        4
      19: aload_1
      20: invokevirtual #270                // Method org/apache/dubbo/config/ArgumentConfig.getType:()Ljava/lang/String;
      23: astore        5
      25: aload_0
      26: aload         5
      28: aload         4
      30: aload_3
      31: invokespecial #279                // Method isTypeMatched:(Ljava/lang/String;Ljava/lang/Integer;[Ljava/lang/Class;)Z
      34: ifeq          40
      37: aload         4
      39: areturn
      40: new           #275                // class java/lang/IllegalArgumentException
      43: dup
      44: new           #39                 // class java/lang/StringBuilder
      47: dup
      48: invokespecial #40                 // Method java/lang/StringBuilder."<init>":()V
      51: ldc_w         #280                // String Argument config error : the index attribute and type attribute not match :index :
      54: invokevirtual #42                 // Method java/lang/StringBuilder.append:(Ljava/lang/String;)Ljava/lang/StringBuilder;
      57: aload_1
      58: invokevirtual #274                // Method org/apache/dubbo/config/ArgumentConfig.getIndex:()Ljava/lang/Integer;
      61: invokevirtual #43                 // Method java/lang/StringBuilder.append:(Ljava/lang/Object;)Ljava/lang/StringBuilder;
      64: ldc_w         #281                // String , type:
      67: invokevirtual #42                 // Method java/lang/StringBuilder.append:(Ljava/lang/String;)Ljava/lang/StringBuilder;
      70: aload_1
      71: invokevirtual #270                // Method org/apache/dubbo/config/ArgumentConfig.getType:()Ljava/lang/String;
      74: invokevirtual #42                 // Method java/lang/StringBuilder.append:(Ljava/lang/String;)Ljava/lang/StringBuilder;
      77: invokevirtual #44                 // Method java/lang/StringBuilder.toString:()Ljava/lang/String;
      80: invokespecial #277                // Method java/lang/IllegalArgumentException."<init>":(Ljava/lang/String;)V
      83: athrow
      84: iconst_0
      85: istore        4
      87: iload         4
      89: aload_3
      90: arraylength
      91: if_icmpge     123
      94: aload_0
      95: aload_1
      96: invokevirtual #270                // Method org/apache/dubbo/config/ArgumentConfig.getType:()Ljava/lang/String;
      99: iload         4
     101: invokestatic  #282                // Method java/lang/Integer.valueOf:(I)Ljava/lang/Integer;
     104: aload_3
     105: invokespecial #279                // Method isTypeMatched:(Ljava/lang/String;Ljava/lang/Integer;[Ljava/lang/Class;)Z
     108: ifeq          117
     111: iload         4
     113: invokestatic  #282                // Method java/lang/Integer.valueOf:(I)Ljava/lang/Integer;
     116: areturn
     117: iinc          4, 1
     120: goto          87
     123: new           #275                // class java/lang/IllegalArgumentException
     126: dup
     127: new           #39                 // class java/lang/StringBuilder
     130: dup
     131: invokespecial #40                 // Method java/lang/StringBuilder."<init>":()V
     134: ldc_w         #283                // String Argument config error : no argument matched with the type:
     137: invokevirtual #42                 // Method java/lang/StringBuilder.append:(Ljava/lang/String;)Ljava/lang/StringBuilder;
     140: aload_1
     141: invokevirtual #270                // Method org/apache/dubbo/config/ArgumentConfig.getType:()Ljava/lang/String;
     144: invokevirtual #42                 // Method java/lang/StringBuilder.append:(Ljava/lang/String;)Ljava/lang/StringBuilder;
     147: invokevirtual #44                 // Method java/lang/StringBuilder.toString:()Ljava/lang/String;
     150: invokespecial #277                // Method java/lang/IllegalArgumentException."<init>":(Ljava/lang/String;)V
     153: athrow

  private org.apache.dubbo.common.URL buildUrl(org.apache.dubbo.config.ProtocolConfig, java.util.Map<java.lang.String, java.lang.String>);
    Code:
       0: aload_1
       1: invokevirtual #284                // Method org/apache/dubbo/config/ProtocolConfig.getName:()Ljava/lang/String;
       4: astore_3
       5: aload_3
       6: invokestatic  #134                // Method org/apache/dubbo/common/utils/StringUtils.isEmpty:(Ljava/lang/String;)Z
       9: ifeq          16
      12: ldc_w         #285                // String dubbo
      15: astore_3
      16: aload_1
      17: aload_0
      18: getfield      #77                 // Field provider:Lorg/apache/dubbo/config/ProviderConfig;
      21: aload_2
      22: invokestatic  #286                // Method findConfiguredHosts:(Lorg/apache/dubbo/config/ProtocolConfig;Lorg/apache/dubbo/config/ProviderConfig;Ljava/util/Map;)Ljava/lang/String;
      25: astore        4
      27: aload         4
      29: invokestatic  #287                // Method org/apache/dubbo/common/utils/NetUtils.isIPV6URLStdFormat:(Ljava/lang/String;)Z
      32: ifeq          78
      35: aload         4
      37: ldc_w         #288                // String [
      40: invokevirtual #289                // Method java/lang/String.contains:(Ljava/lang/CharSequence;)Z
      43: ifne          101
      46: new           #39                 // class java/lang/StringBuilder
      49: dup
      50: invokespecial #40                 // Method java/lang/StringBuilder."<init>":()V
      53: ldc_w         #288                // String [
      56: invokevirtual #42                 // Method java/lang/StringBuilder.append:(Ljava/lang/String;)Ljava/lang/StringBuilder;
      59: aload         4
      61: invokevirtual #42                 // Method java/lang/StringBuilder.append:(Ljava/lang/String;)Ljava/lang/StringBuilder;
      64: ldc_w         #290                // String ]
      67: invokevirtual #42                 // Method java/lang/StringBuilder.append:(Ljava/lang/String;)Ljava/lang/StringBuilder;
      70: invokevirtual #44                 // Method java/lang/StringBuilder.toString:()Ljava/lang/String;
      73: astore        4
      75: goto          101
      78: invokestatic  #291                // Method org/apache/dubbo/common/utils/NetUtils.getLocalHostV6:()Ljava/lang/String;
      81: ifnull        101
      84: invokestatic  #291                // Method org/apache/dubbo/common/utils/NetUtils.getLocalHostV6:()Ljava/lang/String;
      87: astore        5
      89: aload_2
      90: ldc_w         #292                // String ipv6
      93: aload         5
      95: invokeinterface #218,  3          // InterfaceMethod java/util/Map.put:(Ljava/lang/Object;Ljava/lang/Object;)Ljava/lang/Object;
     100: pop
     101: aload_1
     102: aload_0
     103: getfield      #77                 // Field provider:Lorg/apache/dubbo/config/ProviderConfig;
     106: aload_0
     107: ldc           #21                 // class org/apache/dubbo/rpc/Protocol
     109: invokevirtual #22                 // Method getExtensionLoader:(Ljava/lang/Class;)Lorg/apache/dubbo/common/extension/ExtensionLoader;
     112: aload_3
     113: aload_2
     114: invokestatic  #293                // Method findConfiguredPort:(Lorg/apache/dubbo/config/ProtocolConfig;Lorg/apache/dubbo/config/ProviderConfig;Lorg/apache/dubbo/common/extension/ExtensionLoader;Ljava/lang/String;Ljava/util/Map;)Ljava/lang/Integer;
     117: astore        5
     119: new           #294                // class org/apache/dubbo/common/url/component/ServiceConfigURL
     122: dup
     123: aload_3
     124: aconst_null
     125: aconst_null
     126: aload         4
     128: aload         5
     130: invokevirtual #99                 // Method java/lang/Integer.intValue:()I
     133: aload_0
     134: aload_1
     135: invokevirtual #295                // Method getContextPath:(Lorg/apache/dubbo/config/ProtocolConfig;)Ljava/util/Optional;
     138: aload_0
     139: invokedynamic #296,  0            // InvokeDynamic #8:apply:(Lorg/apache/dubbo/config/ServiceConfig;)Ljava/util/function/Function;
     144: invokevirtual #297                // Method java/util/Optional.map:(Ljava/util/function/Function;)Ljava/util/Optional;
     147: aload_0
     148: getfield      #172                // Field path:Ljava/lang/String;
     151: invokevirtual #298                // Method java/util/Optional.orElse:(Ljava/lang/Object;)Ljava/lang/Object;
     154: checkcast     #261                // class java/lang/String
     157: aload_2
     158: invokespecial #299                // Method org/apache/dubbo/common/url/component/ServiceConfigURL."<init>":(Ljava/lang/String;Ljava/lang/String;Ljava/lang/String;Ljava/lang/String;ILjava/lang/String;Ljava/util/Map;)V
     161: astore        6
     163: aload_0
     164: ldc_w         #300                // class org/apache/dubbo/rpc/cluster/ConfiguratorFactory
     167: invokevirtual #22                 // Method getExtensionLoader:(Ljava/lang/Class;)Lorg/apache/dubbo/common/extension/ExtensionLoader;
     170: aload         6
     172: invokevirtual #301                // Method org/apache/dubbo/common/URL.getProtocol:()Ljava/lang/String;
     175: invokevirtual #302                // Method org/apache/dubbo/common/extension/ExtensionLoader.hasExtension:(Ljava/lang/String;)Z
     178: ifeq          215
     181: aload_0
     182: ldc_w         #300                // class org/apache/dubbo/rpc/cluster/ConfiguratorFactory
     185: invokevirtual #22                 // Method getExtensionLoader:(Ljava/lang/Class;)Lorg/apache/dubbo/common/extension/ExtensionLoader;
     188: aload         6
     190: invokevirtual #301                // Method org/apache/dubbo/common/URL.getProtocol:()Ljava/lang/String;
     193: invokevirtual #303                // Method org/apache/dubbo/common/extension/ExtensionLoader.getExtension:(Ljava/lang/String;)Ljava/lang/Object;
     196: checkcast     #300                // class org/apache/dubbo/rpc/cluster/ConfiguratorFactory
     199: aload         6
     201: invokeinterface #304,  2          // InterfaceMethod org/apache/dubbo/rpc/cluster/ConfiguratorFactory.getConfigurator:(Lorg/apache/dubbo/common/URL;)Lorg/apache/dubbo/rpc/cluster/Configurator;
     206: aload         6
     208: invokeinterface #305,  2          // InterfaceMethod org/apache/dubbo/rpc/cluster/Configurator.configure:(Lorg/apache/dubbo/common/URL;)Lorg/apache/dubbo/common/URL;
     213: astore        6
     215: aload         6
     217: aload_0
     218: invokevirtual #50                 // Method getScopeModel:()Lorg/apache/dubbo/rpc/model/ModuleModel;
     221: invokevirtual #306                // Method org/apache/dubbo/common/URL.setScopeModel:(Lorg/apache/dubbo/rpc/model/ScopeModel;)Lorg/apache/dubbo/common/URL;
     224: astore        6
     226: aload         6
     228: aload_0
     229: getfield      #52                 // Field providerModel:Lorg/apache/dubbo/rpc/model/ProviderModel;
     232: invokevirtual #307                // Method org/apache/dubbo/common/URL.setServiceModel:(Lorg/apache/dubbo/rpc/model/ServiceModel;)Lorg/apache/dubbo/common/URL;
     235: astore        6
     237: aload         6
     239: areturn

  private void exportUrl(org.apache.dubbo.common.URL, java.util.List<org.apache.dubbo.common.URL>);
    Code:
       0: aload_1
       1: ldc_w         #308                // String scope
       4: invokevirtual #309                // Method org/apache/dubbo/common/URL.getParameter:(Ljava/lang/String;)Ljava/lang/String;
       7: astore_3
       8: ldc_w         #310                // String none
      11: aload_3
      12: invokevirtual #311                // Method java/lang/String.equalsIgnoreCase:(Ljava/lang/String;)Z
      15: ifne          283
      18: ldc_w         #312                // String remote
      21: aload_3
      22: invokevirtual #311                // Method java/lang/String.equalsIgnoreCase:(Ljava/lang/String;)Z
      25: ifne          33
      28: aload_0
      29: aload_1
      30: invokespecial #313                // Method exportLocal:(Lorg/apache/dubbo/common/URL;)V
      33: ldc_w         #314                // String local
      36: aload_3
      37: invokevirtual #311                // Method java/lang/String.equalsIgnoreCase:(Ljava/lang/String;)Z
      40: ifne          283
      43: aload_1
      44: ldc_w         #315                // String ext.protocol
      47: ldc           #38                 // String
      49: invokevirtual #316                // Method org/apache/dubbo/common/URL.getParameter:(Ljava/lang/String;Ljava/lang/String;)Ljava/lang/String;
      52: astore        4
      54: new           #13                 // class java/util/ArrayList
      57: dup
      58: invokespecial #14                 // Method java/util/ArrayList."<init>":()V
      61: astore        5
      63: aload         4
      65: invokestatic  #317                // Method org/apache/dubbo/common/utils/StringUtils.isNotBlank:(Ljava/lang/CharSequence;)Z
      68: ifeq          97
      71: aload_1
      72: invokestatic  #318                // Method org/apache/dubbo/common/URLBuilder.from:(Lorg/apache/dubbo/common/URL;)Lorg/apache/dubbo/common/URLBuilder;
      75: ldc_w         #319                // String ispuserver
      78: getstatic     #142                // Field java/lang/Boolean.TRUE:Ljava/lang/Boolean;
      81: invokevirtual #143                // Method java/lang/Boolean.toString:()Ljava/lang/String;
      84: invokevirtual #320                // Method org/apache/dubbo/common/URLBuilder.addParameter:(Ljava/lang/String;Ljava/lang/String;)Lorg/apache/dubbo/common/URLBuilder;
      87: ldc_w         #315                // String ext.protocol
      90: invokevirtual #321                // Method org/apache/dubbo/common/URLBuilder.removeParameter:(Ljava/lang/String;)Lorg/apache/dubbo/common/URLBuilder;
      93: invokevirtual #322                // Method org/apache/dubbo/common/URLBuilder.build:()Lorg/apache/dubbo/common/url/component/ServiceConfigURL;
      96: astore_1
      97: aload_0
      98: aload_1
      99: aload_2
     100: invokespecial #323                // Method exportRemote:(Lorg/apache/dubbo/common/URL;Ljava/util/List;)Lorg/apache/dubbo/common/URL;
     103: astore_1
     104: aload_0
     105: getfield      #141                // Field generic:Ljava/lang/String;
     108: invokestatic  #230                // Method org/apache/dubbo/rpc/support/ProtocolUtils.isGeneric:(Ljava/lang/String;)Z
     111: ifne          139
     114: aload_0
     115: invokevirtual #50                 // Method getScopeModel:()Lorg/apache/dubbo/rpc/model/ModuleModel;
     118: invokevirtual #324                // Method org/apache/dubbo/rpc/model/ModuleModel.isInternal:()Z
     121: ifne          139
     124: aload_1
     125: aload_0
     126: getfield      #52                 // Field providerModel:Lorg/apache/dubbo/rpc/model/ProviderModel;
     129: invokevirtual #325                // Method org/apache/dubbo/rpc/model/ProviderModel.getServiceModel:()Lorg/apache/dubbo/rpc/model/ServiceDescriptor;
     132: aload_0
     133: invokevirtual #326                // Method getApplicationModel:()Lorg/apache/dubbo/rpc/model/ApplicationModel;
     136: invokestatic  #327                // Method org/apache/dubbo/registry/client/metadata/MetadataUtils.publishServiceDefinition:(Lorg/apache/dubbo/common/URL;Lorg/apache/dubbo/rpc/model/ServiceDescriptor;Lorg/apache/dubbo/rpc/model/ApplicationModel;)V
     139: aload         4
     141: invokestatic  #317                // Method org/apache/dubbo/common/utils/StringUtils.isNotBlank:(Ljava/lang/CharSequence;)Z
     144: ifeq          170
     147: aload         4
     149: ldc           #245                // String ,
     151: iconst_m1
     152: invokevirtual #328                // Method java/lang/String.split:(Ljava/lang/String;I)[Ljava/lang/String;
     155: astore        6
     157: aload         5
     159: aload         6
     161: invokestatic  #241                // Method java/util/Arrays.asList:([Ljava/lang/Object;)Ljava/util/List;
     164: invokeinterface #76,  2           // InterfaceMethod java/util/List.addAll:(Ljava/util/Collection;)Z
     169: pop
     170: aload         5
     172: invokeinterface #30,  1           // InterfaceMethod java/util/List.iterator:()Ljava/util/Iterator;
     177: astore        6
     179: aload         6
     181: invokeinterface #31,  1           // InterfaceMethod java/util/Iterator.hasNext:()Z
     186: ifeq          283
     189: aload         6
     191: invokeinterface #32,  1           // InterfaceMethod java/util/Iterator.next:()Ljava/lang/Object;
     196: checkcast     #261                // class java/lang/String
     199: astore        7
     201: aload         7
     203: invokestatic  #317                // Method org/apache/dubbo/common/utils/StringUtils.isNotBlank:(Ljava/lang/CharSequence;)Z
     206: ifeq          280
     209: aload_1
     210: invokestatic  #318                // Method org/apache/dubbo/common/URLBuilder.from:(Lorg/apache/dubbo/common/URL;)Lorg/apache/dubbo/common/URLBuilder;
     213: aload         7
     215: invokevirtual #329                // Method org/apache/dubbo/common/URLBuilder.setProtocol:(Ljava/lang/String;)Lorg/apache/dubbo/common/URLBuilder;
     218: invokevirtual #322                // Method org/apache/dubbo/common/URLBuilder.build:()Lorg/apache/dubbo/common/url/component/ServiceConfigURL;
     221: astore        8
     223: aload_0
     224: aload         8
     226: aload_2
     227: invokespecial #323                // Method exportRemote:(Lorg/apache/dubbo/common/URL;Ljava/util/List;)Lorg/apache/dubbo/common/URL;
     230: astore        8
     232: aload_0
     233: getfield      #141                // Field generic:Ljava/lang/String;
     236: invokestatic  #230                // Method org/apache/dubbo/rpc/support/ProtocolUtils.isGeneric:(Ljava/lang/String;)Z
     239: ifne          268
     242: aload_0
     243: invokevirtual #50                 // Method getScopeModel:()Lorg/apache/dubbo/rpc/model/ModuleModel;
     246: invokevirtual #324                // Method org/apache/dubbo/rpc/model/ModuleModel.isInternal:()Z
     249: ifne          268
     252: aload         8
     254: aload_0
     255: getfield      #52                 // Field providerModel:Lorg/apache/dubbo/rpc/model/ProviderModel;
     258: invokevirtual #325                // Method org/apache/dubbo/rpc/model/ProviderModel.getServiceModel:()Lorg/apache/dubbo/rpc/model/ServiceDescriptor;
     261: aload_0
     262: invokevirtual #326                // Method getApplicationModel:()Lorg/apache/dubbo/rpc/model/ApplicationModel;
     265: invokestatic  #327                // Method org/apache/dubbo/registry/client/metadata/MetadataUtils.publishServiceDefinition:(Lorg/apache/dubbo/common/URL;Lorg/apache/dubbo/rpc/model/ServiceDescriptor;Lorg/apache/dubbo/rpc/model/ApplicationModel;)V
     268: aload_0
     269: getfield      #195                // Field urls:Ljava/util/List;
     272: aload         8
     274: invokeinterface #330,  2          // InterfaceMethod java/util/List.add:(Ljava/lang/Object;)Z
     279: pop
     280: goto          179
     283: aload_0
     284: getfield      #195                // Field urls:Ljava/util/List;
     287: aload_1
     288: invokeinterface #330,  2          // InterfaceMethod java/util/List.add:(Ljava/lang/Object;)Z
     293: pop
     294: return

  private org.apache.dubbo.common.URL exportRemote(org.apache.dubbo.common.URL, java.util.List<org.apache.dubbo.common.URL>);
    Code:
       0: aload_2
       1: invokestatic  #228                // Method org/apache/dubbo/common/utils/CollectionUtils.isNotEmpty:(Ljava/util/Collection;)Z
       4: ifeq          287
       7: aload_2
       8: invokeinterface #30,  1           // InterfaceMethod java/util/List.iterator:()Ljava/util/Iterator;
      13: astore_3
      14: aload_3
      15: invokeinterface #31,  1           // InterfaceMethod java/util/Iterator.hasNext:()Z
      20: ifeq          284
      23: aload_3
      24: invokeinterface #32,  1           // InterfaceMethod java/util/Iterator.next:()Ljava/lang/Object;
      29: checkcast     #331                // class org/apache/dubbo/common/URL
      32: astore        4
      34: ldc_w         #332                // String service-discovery-registry
      37: aload         4
      39: invokevirtual #301                // Method org/apache/dubbo/common/URL.getProtocol:()Ljava/lang/String;
      42: invokevirtual #154                // Method java/lang/String.equals:(Ljava/lang/Object;)Z
      45: ifeq          58
      48: aload_1
      49: ldc_w         #333                // String service-name-mapping
      52: ldc           #153                // String true
      54: invokevirtual #334                // Method org/apache/dubbo/common/URL.addParameterIfAbsent:(Ljava/lang/String;Ljava/lang/String;)Lorg/apache/dubbo/common/URL;
      57: astore_1
      58: ldc_w         #335                // String injvm
      61: aload_1
      62: invokevirtual #301                // Method org/apache/dubbo/common/URL.getProtocol:()Ljava/lang/String;
      65: invokevirtual #311                // Method java/lang/String.equalsIgnoreCase:(Ljava/lang/String;)Z
      68: ifeq          74
      71: goto          14
      74: aload_1
      75: ldc_w         #336                // String dynamic
      78: aload         4
      80: ldc_w         #336                // String dynamic
      83: invokevirtual #309                // Method org/apache/dubbo/common/URL.getParameter:(Ljava/lang/String;)Ljava/lang/String;
      86: invokevirtual #334                // Method org/apache/dubbo/common/URL.addParameterIfAbsent:(Ljava/lang/String;Ljava/lang/String;)Lorg/apache/dubbo/common/URL;
      89: astore_1
      90: aload_0
      91: aload         4
      93: invokestatic  #337                // Method org/apache/dubbo/config/utils/ConfigValidationUtils.loadMonitor:(Lorg/apache/dubbo/config/AbstractInterfaceConfig;Lorg/apache/dubbo/common/URL;)Lorg/apache/dubbo/common/URL;
      96: astore        5
      98: aload         5
     100: ifnull        113
     103: aload_1
     104: ldc_w         #338                // String monitor
     107: aload         5
     109: invokevirtual #339                // Method org/apache/dubbo/common/URL.putAttribute:(Ljava/lang/String;Ljava/lang/Object;)Lorg/apache/dubbo/common/URL;
     112: astore_1
     113: aload_1
     114: ldc           #254                // String proxy
     116: invokevirtual #309                // Method org/apache/dubbo/common/URL.getParameter:(Ljava/lang/String;)Ljava/lang/String;
     119: astore        6
     121: aload         6
     123: invokestatic  #236                // Method org/apache/dubbo/common/utils/StringUtils.isNotEmpty:(Ljava/lang/String;)Z
     126: ifeq          140
     129: aload         4
     131: ldc           #254                // String proxy
     133: aload         6
     135: invokevirtual #340                // Method org/apache/dubbo/common/URL.addParameter:(Ljava/lang/String;Ljava/lang/String;)Lorg/apache/dubbo/common/URL;
     138: astore        4
     140: getstatic     #36                 // Field logger:Lorg/apache/dubbo/common/logger/ErrorTypeAwareLogger;
     143: invokeinterface #341,  1          // InterfaceMethod org/apache/dubbo/common/logger/ErrorTypeAwareLogger.isInfoEnabled:()Z
     148: ifeq          267
     151: aload_1
     152: ldc_w         #342                // String register
     155: iconst_1
     156: invokevirtual #343                // Method org/apache/dubbo/common/URL.getParameter:(Ljava/lang/String;Z)Z
     159: ifeq          223
     162: getstatic     #36                 // Field logger:Lorg/apache/dubbo/common/logger/ErrorTypeAwareLogger;
     165: new           #39                 // class java/lang/StringBuilder
     168: dup
     169: invokespecial #40                 // Method java/lang/StringBuilder."<init>":()V
     172: ldc_w         #344                // String Register dubbo service
     175: invokevirtual #42                 // Method java/lang/StringBuilder.append:(Ljava/lang/String;)Ljava/lang/StringBuilder;
     178: aload_0
     179: getfield      #140                // Field interfaceClass:Ljava/lang/Class;
     182: invokevirtual #159                // Method java/lang/Class.getName:()Ljava/lang/String;
     185: invokevirtual #42                 // Method java/lang/StringBuilder.append:(Ljava/lang/String;)Ljava/lang/StringBuilder;
     188: ldc_w         #345                // String  url
     191: invokevirtual #42                 // Method java/lang/StringBuilder.append:(Ljava/lang/String;)Ljava/lang/StringBuilder;
     194: aload_1
     195: invokevirtual #43                 // Method java/lang/StringBuilder.append:(Ljava/lang/Object;)Ljava/lang/StringBuilder;
     198: ldc_w         #346                // String  to registry
     201: invokevirtual #42                 // Method java/lang/StringBuilder.append:(Ljava/lang/String;)Ljava/lang/StringBuilder;
     204: aload         4
     206: invokevirtual #347                // Method org/apache/dubbo/common/URL.getAddress:()Ljava/lang/String;
     209: invokevirtual #42                 // Method java/lang/StringBuilder.append:(Ljava/lang/String;)Ljava/lang/StringBuilder;
     212: invokevirtual #44                 // Method java/lang/StringBuilder.toString:()Ljava/lang/String;
     215: invokeinterface #63,  2           // InterfaceMethod org/apache/dubbo/common/logger/ErrorTypeAwareLogger.info:(Ljava/lang/String;)V
     220: goto          267
     223: getstatic     #36                 // Field logger:Lorg/apache/dubbo/common/logger/ErrorTypeAwareLogger;
     226: new           #39                 // class java/lang/StringBuilder
     229: dup
     230: invokespecial #40                 // Method java/lang/StringBuilder."<init>":()V
     233: ldc_w         #348                // String Export dubbo service
     236: invokevirtual #42                 // Method java/lang/StringBuilder.append:(Ljava/lang/String;)Ljava/lang/StringBuilder;
     239: aload_0
     240: getfield      #140                // Field interfaceClass:Ljava/lang/Class;
     243: invokevirtual #159                // Method java/lang/Class.getName:()Ljava/lang/String;
     246: invokevirtual #42                 // Method java/lang/StringBuilder.append:(Ljava/lang/String;)Ljava/lang/StringBuilder;
     249: ldc_w         #349                // String  to url
     252: invokevirtual #42                 // Method java/lang/StringBuilder.append:(Ljava/lang/String;)Ljava/lang/StringBuilder;
     255: aload_1
     256: invokevirtual #43                 // Method java/lang/StringBuilder.append:(Ljava/lang/Object;)Ljava/lang/StringBuilder;
     259: invokevirtual #44                 // Method java/lang/StringBuilder.toString:()Ljava/lang/String;
     262: invokeinterface #63,  2           // InterfaceMethod org/apache/dubbo/common/logger/ErrorTypeAwareLogger.info:(Ljava/lang/String;)V
     267: aload_0
     268: aload         4
     270: ldc_w         #350                // String export
     273: aload_1
     274: invokevirtual #339                // Method org/apache/dubbo/common/URL.putAttribute:(Ljava/lang/String;Ljava/lang/Object;)Lorg/apache/dubbo/common/URL;
     277: iconst_1
     278: invokespecial #351                // Method doExportUrl:(Lorg/apache/dubbo/common/URL;Z)V
     281: goto          14
     284: goto          348
     287: getstatic     #36                 // Field logger:Lorg/apache/dubbo/common/logger/ErrorTypeAwareLogger;
     290: invokeinterface #341,  1          // InterfaceMethod org/apache/dubbo/common/logger/ErrorTypeAwareLogger.isInfoEnabled:()Z
     295: ifeq          342
     298: getstatic     #36                 // Field logger:Lorg/apache/dubbo/common/logger/ErrorTypeAwareLogger;
     301: new           #39                 // class java/lang/StringBuilder
     304: dup
     305: invokespecial #40                 // Method java/lang/StringBuilder."<init>":()V
     308: ldc_w         #348                // String Export dubbo service
     311: invokevirtual #42                 // Method java/lang/StringBuilder.append:(Ljava/lang/String;)Ljava/lang/StringBuilder;
     314: aload_0
     315: getfield      #140                // Field interfaceClass:Ljava/lang/Class;
     318: invokevirtual #159                // Method java/lang/Class.getName:()Ljava/lang/String;
     321: invokevirtual #42                 // Method java/lang/StringBuilder.append:(Ljava/lang/String;)Ljava/lang/StringBuilder;
     324: ldc_w         #349                // String  to url
     327: invokevirtual #42                 // Method java/lang/StringBuilder.append:(Ljava/lang/String;)Ljava/lang/StringBuilder;
     330: aload_1
     331: invokevirtual #43                 // Method java/lang/StringBuilder.append:(Ljava/lang/Object;)Ljava/lang/StringBuilder;
     334: invokevirtual #44                 // Method java/lang/StringBuilder.toString:()Ljava/lang/String;
     337: invokeinterface #63,  2           // InterfaceMethod org/apache/dubbo/common/logger/ErrorTypeAwareLogger.info:(Ljava/lang/String;)V
     342: aload_0
     343: aload_1
     344: iconst_1
     345: invokespecial #351                // Method doExportUrl:(Lorg/apache/dubbo/common/URL;Z)V
     348: aload_1
     349: areturn

  private void doExportUrl(org.apache.dubbo.common.URL, boolean);
    Code:
       0: aload_0
       1: getfield      #26                 // Field proxyFactory:Lorg/apache/dubbo/rpc/ProxyFactory;
       4: aload_0
       5: getfield      #138                // Field ref:Ljava/lang/Object;
       8: aload_0
       9: getfield      #140                // Field interfaceClass:Ljava/lang/Class;
      12: aload_1
      13: invokeinterface #352,  4          // InterfaceMethod org/apache/dubbo/rpc/ProxyFactory.getInvoker:(Ljava/lang/Object;Ljava/lang/Class;Lorg/apache/dubbo/common/URL;)Lorg/apache/dubbo/rpc/Invoker;
      18: astore_3
      19: iload_2
      20: ifeq          33
      23: new           #353                // class org/apache/dubbo/config/invoker/DelegateProviderMetaDataInvoker
      26: dup
      27: aload_3
      28: aload_0
      29: invokespecial #354                // Method org/apache/dubbo/config/invoker/DelegateProviderMetaDataInvoker."<init>":(Lorg/apache/dubbo/rpc/Invoker;Lorg/apache/dubbo/config/ServiceConfig;)V
      32: astore_3
      33: aload_0
      34: getfield      #24                 // Field protocolSPI:Lorg/apache/dubbo/rpc/Protocol;
      37: aload_3
      38: invokeinterface #355,  2          // InterfaceMethod org/apache/dubbo/rpc/Protocol.export:(Lorg/apache/dubbo/rpc/Invoker;)Lorg/apache/dubbo/rpc/Exporter;
      43: astore        4
      45: aload_0
      46: getfield      #15                 // Field exporters:Ljava/util/List;
      49: aload         4
      51: invokeinterface #330,  2          // InterfaceMethod java/util/List.add:(Ljava/lang/Object;)Z
      56: pop
      57: return

  private void exportLocal(org.apache.dubbo.common.URL);
    Code:
       0: aload_1
       1: invokestatic  #318                // Method org/apache/dubbo/common/URLBuilder.from:(Lorg/apache/dubbo/common/URL;)Lorg/apache/dubbo/common/URLBuilder;
       4: ldc_w         #335                // String injvm
       7: invokevirtual #329                // Method org/apache/dubbo/common/URLBuilder.setProtocol:(Ljava/lang/String;)Lorg/apache/dubbo/common/URLBuilder;
      10: ldc_w         #356                // String 127.0.0.1
      13: invokevirtual #357                // Method org/apache/dubbo/common/URLBuilder.setHost:(Ljava/lang/String;)Lorg/apache/dubbo/common/URLBuilder;
      16: iconst_0
      17: invokevirtual #358                // Method org/apache/dubbo/common/URLBuilder.setPort:(I)Lorg/apache/dubbo/common/URLBuilder;
      20: invokevirtual #322                // Method org/apache/dubbo/common/URLBuilder.build:()Lorg/apache/dubbo/common/url/component/ServiceConfigURL;
      23: astore_2
      24: aload_2
      25: aload_0
      26: invokevirtual #50                 // Method getScopeModel:()Lorg/apache/dubbo/rpc/model/ModuleModel;
      29: invokevirtual #306                // Method org/apache/dubbo/common/URL.setScopeModel:(Lorg/apache/dubbo/rpc/model/ScopeModel;)Lorg/apache/dubbo/common/URL;
      32: aload_0
      33: getfield      #52                 // Field providerModel:Lorg/apache/dubbo/rpc/model/ProviderModel;
      36: invokevirtual #307                // Method org/apache/dubbo/common/URL.setServiceModel:(Lorg/apache/dubbo/rpc/model/ServiceModel;)Lorg/apache/dubbo/common/URL;
      39: astore_2
      40: aload_2
      41: ldc_w         #359                // String exporter.listener
      44: ldc_w         #335                // String injvm
      47: invokevirtual #340                // Method org/apache/dubbo/common/URL.addParameter:(Ljava/lang/String;Ljava/lang/String;)Lorg/apache/dubbo/common/URL;
      50: astore_2
      51: aload_0
      52: aload_2
      53: iconst_0
      54: invokespecial #351                // Method doExportUrl:(Lorg/apache/dubbo/common/URL;Z)V
      57: getstatic     #36                 // Field logger:Lorg/apache/dubbo/common/logger/ErrorTypeAwareLogger;
      60: new           #39                 // class java/lang/StringBuilder
      63: dup
      64: invokespecial #40                 // Method java/lang/StringBuilder."<init>":()V
      67: ldc_w         #348                // String Export dubbo service
      70: invokevirtual #42                 // Method java/lang/StringBuilder.append:(Ljava/lang/String;)Ljava/lang/StringBuilder;
      73: aload_0
      74: getfield      #140                // Field interfaceClass:Ljava/lang/Class;
      77: invokevirtual #159                // Method java/lang/Class.getName:()Ljava/lang/String;
      80: invokevirtual #42                 // Method java/lang/StringBuilder.append:(Ljava/lang/String;)Ljava/lang/StringBuilder;
      83: ldc_w         #360                // String  to local registry url :
      86: invokevirtual #42                 // Method java/lang/StringBuilder.append:(Ljava/lang/String;)Ljava/lang/StringBuilder;
      89: aload_2
      90: invokevirtual #43                 // Method java/lang/StringBuilder.append:(Ljava/lang/Object;)Ljava/lang/StringBuilder;
      93: invokevirtual #44                 // Method java/lang/StringBuilder.toString:()Ljava/lang/String;
      96: invokeinterface #63,  2           // InterfaceMethod org/apache/dubbo/common/logger/ErrorTypeAwareLogger.info:(Ljava/lang/String;)V
     101: return

  private boolean isOnlyInJvm();
    Code:
       0: aload_0
       1: invokevirtual #361                // Method getProtocols:()Ljava/util/List;
       4: invokeinterface #191,  1          // InterfaceMethod java/util/List.size:()I
       9: iconst_1
      10: if_icmpne     42
      13: ldc_w         #335                // String injvm
      16: aload_0
      17: invokevirtual #361                // Method getProtocols:()Ljava/util/List;
      20: iconst_0
      21: invokeinterface #362,  2          // InterfaceMethod java/util/List.get:(I)Ljava/lang/Object;
      26: checkcast     #363                // class org/apache/dubbo/config/ProtocolConfig
      29: invokevirtual #284                // Method org/apache/dubbo/config/ProtocolConfig.getName:()Ljava/lang/String;
      32: invokevirtual #311                // Method java/lang/String.equalsIgnoreCase:(Ljava/lang/String;)Z
      35: ifeq          42
      38: iconst_1
      39: goto          43
      42: iconst_0
      43: ireturn

  private void postProcessConfig();
    Code:
       0: aload_0
       1: ldc_w         #364                // class org/apache/dubbo/config/ConfigPostProcessor
       4: invokevirtual #22                 // Method getExtensionLoader:(Ljava/lang/Class;)Lorg/apache/dubbo/common/extension/ExtensionLoader;
       7: ldc_w         #365                // String configPostProcessor://
      10: aload_0
      11: invokevirtual #50                 // Method getScopeModel:()Lorg/apache/dubbo/rpc/model/ModuleModel;
      14: invokestatic  #127                // Method org/apache/dubbo/common/URL.valueOf:(Ljava/lang/String;Lorg/apache/dubbo/rpc/model/ScopeModel;)Lorg/apache/dubbo/common/URL;
      17: aconst_null
      18: checkcast     #128                // class "[Ljava/lang/String;"
      21: invokevirtual #129                // Method org/apache/dubbo/common/extension/ExtensionLoader.getActivateExtension:(Lorg/apache/dubbo/common/URL;[Ljava/lang/String;)Ljava/util/List;
      24: astore_1
      25: aload_1
      26: aload_0
      27: invokedynamic #366,  0            // InvokeDynamic #9:accept:(Lorg/apache/dubbo/config/ServiceConfig;)Ljava/util/function/Consumer;
      32: invokeinterface #104,  2          // InterfaceMethod java/util/List.forEach:(Ljava/util/function/Consumer;)V
      37: return

  public void addServiceListener(org.apache.dubbo.config.ServiceListener);
    Code:
       0: aload_0
       1: getfield      #16                 // Field serviceListeners:Ljava/util/List;
       4: aload_1
       5: invokeinterface #330,  2          // InterfaceMethod java/util/List.add:(Ljava/lang/Object;)Z
      10: pop
      11: return

  protected void onExported();
    Code:
       0: aload_0
       1: getfield      #16                 // Field serviceListeners:Ljava/util/List;
       4: invokeinterface #30,  1           // InterfaceMethod java/util/List.iterator:()Ljava/util/Iterator;
       9: astore_1
      10: aload_1
      11: invokeinterface #31,  1           // InterfaceMethod java/util/Iterator.hasNext:()Z
      16: ifeq          39
      19: aload_1
      20: invokeinterface #32,  1           // InterfaceMethod java/util/Iterator.next:()Ljava/lang/Object;
      25: checkcast     #74                 // class org/apache/dubbo/config/ServiceListener
      28: astore_2
      29: aload_2
      30: aload_0
      31: invokeinterface #367,  2          // InterfaceMethod org/apache/dubbo/config/ServiceListener.exported:(Lorg/apache/dubbo/config/ServiceConfig;)V
      36: goto          10
      39: return

  protected void onUnexpoted();
    Code:
       0: aload_0
       1: getfield      #16                 // Field serviceListeners:Ljava/util/List;
       4: invokeinterface #30,  1           // InterfaceMethod java/util/List.iterator:()Ljava/util/Iterator;
       9: astore_1
      10: aload_1
      11: invokeinterface #31,  1           // InterfaceMethod java/util/Iterator.hasNext:()Z
      16: ifeq          39
      19: aload_1
      20: invokeinterface #32,  1           // InterfaceMethod java/util/Iterator.next:()Ljava/lang/Object;
      25: checkcast     #74                 // class org/apache/dubbo/config/ServiceListener
      28: astore_2
      29: aload_2
      30: aload_0
      31: invokeinterface #368,  2          // InterfaceMethod org/apache/dubbo/config/ServiceListener.unexported:(Lorg/apache/dubbo/config/ServiceConfig;)V
      36: goto          10
      39: return

  private static java.lang.String findConfiguredHosts(org.apache.dubbo.config.ProtocolConfig, org.apache.dubbo.config.ProviderConfig, java.util.Map<java.lang.String, java.lang.String>);
    Code:
       0: iconst_0
       1: istore_3
       2: aload_0
       3: ldc_w         #369                // String DUBBO_IP_TO_BIND
       6: invokestatic  #370                // Method getValueFromConfig:(Lorg/apache/dubbo/config/ProtocolConfig;Ljava/lang/String;)Ljava/lang/String;
       9: astore        4
      11: aload         4
      13: invokestatic  #236                // Method org/apache/dubbo/common/utils/StringUtils.isNotEmpty:(Ljava/lang/String;)Z
      16: ifeq          56
      19: aload         4
      21: invokestatic  #371                // Method org/apache/dubbo/common/utils/NetUtils.isInvalidLocalHost:(Ljava/lang/String;)Z
      24: ifeq          56
      27: new           #275                // class java/lang/IllegalArgumentException
      30: dup
      31: new           #39                 // class java/lang/StringBuilder
      34: dup
      35: invokespecial #40                 // Method java/lang/StringBuilder."<init>":()V
      38: ldc_w         #372                // String Specified invalid bind ip from property:DUBBO_IP_TO_BIND, value:
      41: invokevirtual #42                 // Method java/lang/StringBuilder.append:(Ljava/lang/String;)Ljava/lang/StringBuilder;
      44: aload         4
      46: invokevirtual #42                 // Method java/lang/StringBuilder.append:(Ljava/lang/String;)Ljava/lang/StringBuilder;
      49: invokevirtual #44                 // Method java/lang/StringBuilder.toString:()Ljava/lang/String;
      52: invokespecial #277                // Method java/lang/IllegalArgumentException."<init>":(Ljava/lang/String;)V
      55: athrow
      56: aload         4
      58: invokestatic  #134                // Method org/apache/dubbo/common/utils/StringUtils.isEmpty:(Ljava/lang/String;)Z
      61: ifeq          125
      64: aload_0
      65: invokevirtual #373                // Method org/apache/dubbo/config/ProtocolConfig.getHost:()Ljava/lang/String;
      68: astore        4
      70: aload_1
      71: ifnull        88
      74: aload         4
      76: invokestatic  #134                // Method org/apache/dubbo/common/utils/StringUtils.isEmpty:(Ljava/lang/String;)Z
      79: ifeq          88
      82: aload_1
      83: invokevirtual #374                // Method org/apache/dubbo/config/ProviderConfig.getHost:()Ljava/lang/String;
      86: astore        4
      88: aload         4
      90: invokestatic  #371                // Method org/apache/dubbo/common/utils/NetUtils.isInvalidLocalHost:(Ljava/lang/String;)Z
      93: ifeq          125
      96: iconst_1
      97: istore_3
      98: getstatic     #36                 // Field logger:Lorg/apache/dubbo/common/logger/ErrorTypeAwareLogger;
     101: invokeinterface #375,  1          // InterfaceMethod org/apache/dubbo/common/logger/ErrorTypeAwareLogger.isDebugEnabled:()Z
     106: ifeq          120
     109: getstatic     #36                 // Field logger:Lorg/apache/dubbo/common/logger/ErrorTypeAwareLogger;
     112: ldc_w         #376                // String No valid ip found from environment, try to get local host.
     115: invokeinterface #377,  2          // InterfaceMethod org/apache/dubbo/common/logger/ErrorTypeAwareLogger.debug:(Ljava/lang/String;)V
     120: invokestatic  #378                // Method org/apache/dubbo/common/utils/NetUtils.getLocalHost:()Ljava/lang/String;
     123: astore        4
     125: aload_2
     126: ldc_w         #379                // String bind.ip
     129: aload         4
     131: invokeinterface #218,  3          // InterfaceMethod java/util/Map.put:(Ljava/lang/Object;Ljava/lang/Object;)Ljava/lang/Object;
     136: pop
     137: aload_0
     138: ldc_w         #380                // String DUBBO_IP_TO_REGISTRY
     141: invokestatic  #370                // Method getValueFromConfig:(Lorg/apache/dubbo/config/ProtocolConfig;Ljava/lang/String;)Ljava/lang/String;
     144: astore        5
     146: aload         5
     148: invokestatic  #236                // Method org/apache/dubbo/common/utils/StringUtils.isNotEmpty:(Ljava/lang/String;)Z
     151: ifeq          191
     154: aload         5
     156: invokestatic  #371                // Method org/apache/dubbo/common/utils/NetUtils.isInvalidLocalHost:(Ljava/lang/String;)Z
     159: ifeq          191
     162: new           #275                // class java/lang/IllegalArgumentException
     165: dup
     166: new           #39                 // class java/lang/StringBuilder
     169: dup
     170: invokespecial #40                 // Method java/lang/StringBuilder."<init>":()V
     173: ldc_w         #381                // String Specified invalid registry ip from property:DUBBO_IP_TO_REGISTRY, value:
     176: invokevirtual #42                 // Method java/lang/StringBuilder.append:(Ljava/lang/String;)Ljava/lang/StringBuilder;
     179: aload         5
     181: invokevirtual #42                 // Method java/lang/StringBuilder.append:(Ljava/lang/String;)Ljava/lang/StringBuilder;
     184: invokevirtual #44                 // Method java/lang/StringBuilder.toString:()Ljava/lang/String;
     187: invokespecial #277                // Method java/lang/IllegalArgumentException."<init>":(Ljava/lang/String;)V
     190: athrow
     191: aload         5
     193: invokestatic  #134                // Method org/apache/dubbo/common/utils/StringUtils.isEmpty:(Ljava/lang/String;)Z
     196: ifeq          203
     199: aload         4
     201: astore        5
     203: aload_2
     204: ldc_w         #382                // String anyhost
     207: iload_3
     208: invokestatic  #383                // Method java/lang/String.valueOf:(Z)Ljava/lang/String;
     211: invokeinterface #218,  3          // InterfaceMethod java/util/Map.put:(Ljava/lang/Object;Ljava/lang/Object;)Ljava/lang/Object;
     216: pop
     217: aload         5
     219: areturn

  private static synchronized java.lang.Integer findConfiguredPort(org.apache.dubbo.config.ProtocolConfig, org.apache.dubbo.config.ProviderConfig, org.apache.dubbo.common.extension.ExtensionLoader<org.apache.dubbo.rpc.Protocol>, java.lang.String, java.util.Map<java.lang.String, java.lang.String>);
    Code:
       0: aload_0
       1: ldc_w         #384                // String DUBBO_PORT_TO_BIND
       4: invokestatic  #370                // Method getValueFromConfig:(Lorg/apache/dubbo/config/ProtocolConfig;Ljava/lang/String;)Ljava/lang/String;
       7: astore        6
       9: aload         6
      11: invokestatic  #385                // Method parsePort:(Ljava/lang/String;)Ljava/lang/Integer;
      14: astore        5
      16: aload         5
      18: ifnonnull     128
      21: aload_0
      22: invokevirtual #386                // Method org/apache/dubbo/config/ProtocolConfig.getPort:()Ljava/lang/Integer;
      25: astore        5
      27: aload_1
      28: ifnull        50
      31: aload         5
      33: ifnull        44
      36: aload         5
      38: invokevirtual #99                 // Method java/lang/Integer.intValue:()I
      41: ifne          50
      44: aload_1
      45: invokevirtual #387                // Method org/apache/dubbo/config/ProviderConfig.getPort:()Ljava/lang/Integer;
      48: astore        5
      50: aload_2
      51: aload_3
      52: invokevirtual #303                // Method org/apache/dubbo/common/extension/ExtensionLoader.getExtension:(Ljava/lang/String;)Ljava/lang/Object;
      55: checkcast     #21                 // class org/apache/dubbo/rpc/Protocol
      58: invokeinterface #388,  1          // InterfaceMethod org/apache/dubbo/rpc/Protocol.getDefaultPort:()I
      63: istore        7
      65: aload         5
      67: ifnull        78
      70: aload         5
      72: invokevirtual #99                 // Method java/lang/Integer.intValue:()I
      75: ifne          85
      78: iload         7
      80: invokestatic  #282                // Method java/lang/Integer.valueOf:(I)Ljava/lang/Integer;
      83: astore        5
      85: aload         5
      87: invokevirtual #99                 // Method java/lang/Integer.intValue:()I
      90: ifgt          128
      93: aload_3
      94: invokestatic  #389                // Method getRandomPort:(Ljava/lang/String;)Ljava/lang/Integer;
      97: astore        5
      99: aload         5
     101: ifnull        112
     104: aload         5
     106: invokevirtual #99                 // Method java/lang/Integer.intValue:()I
     109: ifge          128
     112: iload         7
     114: invokestatic  #390                // Method org/apache/dubbo/common/utils/NetUtils.getAvailablePort:(I)I
     117: invokestatic  #282                // Method java/lang/Integer.valueOf:(I)Ljava/lang/Integer;
     120: astore        5
     122: aload_3
     123: aload         5
     125: invokestatic  #391                // Method putRandomPort:(Ljava/lang/String;Ljava/lang/Integer;)V
     128: aload         4
     130: ldc_w         #392                // String bind.port
     133: aload         5
     135: invokestatic  #393                // Method java/lang/String.valueOf:(Ljava/lang/Object;)Ljava/lang/String;
     138: invokeinterface #218,  3          // InterfaceMethod java/util/Map.put:(Ljava/lang/Object;Ljava/lang/Object;)Ljava/lang/Object;
     143: pop
     144: aload_0
     145: ldc_w         #394                // String DUBBO_PORT_TO_REGISTRY
     148: invokestatic  #370                // Method getValueFromConfig:(Lorg/apache/dubbo/config/ProtocolConfig;Ljava/lang/String;)Ljava/lang/String;
     151: astore        7
     153: aload         7
     155: invokestatic  #385                // Method parsePort:(Ljava/lang/String;)Ljava/lang/Integer;
     158: astore        8
     160: aload         8
     162: ifnonnull     169
     165: aload         5
     167: astore        8
     169: aload         8
     171: areturn

  private static java.lang.Integer parsePort(java.lang.String);
    Code:
       0: aconst_null
       1: astore_1
       2: aload_0
       3: invokestatic  #236                // Method org/apache/dubbo/common/utils/StringUtils.isNotEmpty:(Ljava/lang/String;)Z
       6: ifeq          86
       9: aload_0
      10: invokestatic  #395                // Method java/lang/Integer.parseInt:(Ljava/lang/String;)I
      13: istore_2
      14: iload_2
      15: invokestatic  #396                // Method org/apache/dubbo/common/utils/NetUtils.isInvalidPort:(I)Z
      18: ifeq          49
      21: new           #275                // class java/lang/IllegalArgumentException
      24: dup
      25: new           #39                 // class java/lang/StringBuilder
      28: dup
      29: invokespecial #40                 // Method java/lang/StringBuilder."<init>":()V
      32: ldc_w         #397                // String Specified invalid port from env value:
      35: invokevirtual #42                 // Method java/lang/StringBuilder.append:(Ljava/lang/String;)Ljava/lang/StringBuilder;
      38: aload_0
      39: invokevirtual #42                 // Method java/lang/StringBuilder.append:(Ljava/lang/String;)Ljava/lang/StringBuilder;
      42: invokevirtual #44                 // Method java/lang/StringBuilder.toString:()Ljava/lang/String;
      45: invokespecial #277                // Method java/lang/IllegalArgumentException."<init>":(Ljava/lang/String;)V
      48: athrow
      49: iload_2
      50: invokestatic  #282                // Method java/lang/Integer.valueOf:(I)Ljava/lang/Integer;
      53: astore_1
      54: goto          86
      57: astore_2
      58: new           #275                // class java/lang/IllegalArgumentException
      61: dup
      62: new           #39                 // class java/lang/StringBuilder
      65: dup
      66: invokespecial #40                 // Method java/lang/StringBuilder."<init>":()V
      69: ldc_w         #397                // String Specified invalid port from env value:
      72: invokevirtual #42                 // Method java/lang/StringBuilder.append:(Ljava/lang/String;)Ljava/lang/StringBuilder;
      75: aload_0
      76: invokevirtual #42                 // Method java/lang/StringBuilder.append:(Ljava/lang/String;)Ljava/lang/StringBuilder;
      79: invokevirtual #44                 // Method java/lang/StringBuilder.toString:()Ljava/lang/String;
      82: invokespecial #277                // Method java/lang/IllegalArgumentException."<init>":(Ljava/lang/String;)V
      85: athrow
      86: aload_1
      87: areturn
    Exception table:
       from    to  target type
           9    54    57   Class java/lang/Exception

  private static java.lang.String getValueFromConfig(org.apache.dubbo.config.ProtocolConfig, java.lang.String);
    Code:
       0: new           #39                 // class java/lang/StringBuilder
       3: dup
       4: invokespecial #40                 // Method java/lang/StringBuilder."<init>":()V
       7: aload_0
       8: invokevirtual #284                // Method org/apache/dubbo/config/ProtocolConfig.getName:()Ljava/lang/String;
      11: invokevirtual #398                // Method java/lang/String.toUpperCase:()Ljava/lang/String;
      14: invokevirtual #42                 // Method java/lang/StringBuilder.append:(Ljava/lang/String;)Ljava/lang/StringBuilder;
      17: ldc_w         #399                // String _
      20: invokevirtual #42                 // Method java/lang/StringBuilder.append:(Ljava/lang/String;)Ljava/lang/StringBuilder;
      23: invokevirtual #44                 // Method java/lang/StringBuilder.toString:()Ljava/lang/String;
      26: astore_2
      27: new           #39                 // class java/lang/StringBuilder
      30: dup
      31: invokespecial #40                 // Method java/lang/StringBuilder."<init>":()V
      34: aload_2
      35: invokevirtual #42                 // Method java/lang/StringBuilder.append:(Ljava/lang/String;)Ljava/lang/StringBuilder;
      38: aload_1
      39: invokevirtual #42                 // Method java/lang/StringBuilder.append:(Ljava/lang/String;)Ljava/lang/StringBuilder;
      42: invokevirtual #44                 // Method java/lang/StringBuilder.toString:()Ljava/lang/String;
      45: invokestatic  #400                // Method org/apache/dubbo/common/utils/ConfigUtils.getSystemProperty:(Ljava/lang/String;)Ljava/lang/String;
      48: astore_3
      49: aload_3
      50: invokestatic  #134                // Method org/apache/dubbo/common/utils/StringUtils.isEmpty:(Ljava/lang/String;)Z
      53: ifeq          61
      56: aload_1
      57: invokestatic  #400                // Method org/apache/dubbo/common/utils/ConfigUtils.getSystemProperty:(Ljava/lang/String;)Ljava/lang/String;
      60: astore_3
      61: aload_3
      62: areturn

  private static java.lang.Integer getRandomPort(java.lang.String);
    Code:
       0: aload_0
       1: invokevirtual #401                // Method java/lang/String.toLowerCase:()Ljava/lang/String;
       4: astore_0
       5: getstatic     #402                // Field RANDOM_PORT_MAP:Ljava/util/Map;
       8: aload_0
       9: ldc_w         #404                // int -2147483648
      12: invokestatic  #282                // Method java/lang/Integer.valueOf:(I)Ljava/lang/Integer;
      15: invokeinterface #405,  3          // InterfaceMethod java/util/Map.getOrDefault:(Ljava/lang/Object;Ljava/lang/Object;)Ljava/lang/Object;
      20: checkcast     #403                // class java/lang/Integer
      23: areturn

  private static void putRandomPort(java.lang.String, java.lang.Integer);
    Code:
       0: aload_0
       1: invokevirtual #401                // Method java/lang/String.toLowerCase:()Ljava/lang/String;
       4: astore_0
       5: getstatic     #402                // Field RANDOM_PORT_MAP:Ljava/util/Map;
       8: aload_0
       9: invokeinterface #259,  2          // InterfaceMethod java/util/Map.containsKey:(Ljava/lang/Object;)Z
      14: ifne          73
      17: getstatic     #402                // Field RANDOM_PORT_MAP:Ljava/util/Map;
      20: aload_0
      21: aload_1
      22: invokeinterface #218,  3          // InterfaceMethod java/util/Map.put:(Ljava/lang/Object;Ljava/lang/Object;)Ljava/lang/Object;
      27: pop
      28: getstatic     #36                 // Field logger:Lorg/apache/dubbo/common/logger/ErrorTypeAwareLogger;
      31: ldc_w         #406                // String 5-8
      34: ldc           #38                 // String
      36: ldc           #38                 // String
      38: new           #39                 // class java/lang/StringBuilder
      41: dup
      42: invokespecial #40                 // Method java/lang/StringBuilder."<init>":()V
      45: ldc_w         #407                // String Use random available port(
      48: invokevirtual #42                 // Method java/lang/StringBuilder.append:(Ljava/lang/String;)Ljava/lang/StringBuilder;
      51: aload_1
      52: invokevirtual #43                 // Method java/lang/StringBuilder.append:(Ljava/lang/Object;)Ljava/lang/StringBuilder;
      55: ldc_w         #408                // String ) for protocol
      58: invokevirtual #42                 // Method java/lang/StringBuilder.append:(Ljava/lang/String;)Ljava/lang/StringBuilder;
      61: aload_0
      62: invokevirtual #42                 // Method java/lang/StringBuilder.append:(Ljava/lang/String;)Ljava/lang/StringBuilder;
      65: invokevirtual #44                 // Method java/lang/StringBuilder.toString:()Ljava/lang/String;
      68: invokeinterface #213,  5          // InterfaceMethod org/apache/dubbo/common/logger/ErrorTypeAwareLogger.warn:(Ljava/lang/String;Ljava/lang/String;Ljava/lang/String;Ljava/lang/String;)V
      73: return

  public java.lang.Runnable getDestroyRunner();
    Code:
       0: aload_0
       1: invokedynamic #409,  0            // InvokeDynamic #10:run:(Lorg/apache/dubbo/config/ServiceConfig;)Ljava/lang/Runnable;
       6: areturn

  private void lambda$postProcessConfig$10(org.apache.dubbo.config.ConfigPostProcessor);
    Code:
       0: aload_1
       1: aload_0
       2: invokeinterface #410,  2          // InterfaceMethod org/apache/dubbo/config/ConfigPostProcessor.postProcessServiceConfig:(Lorg/apache/dubbo/config/ServiceConfig;)V
       7: return

  private java.lang.String lambda$buildUrl$9(java.lang.String);
    Code:
       0: new           #39                 // class java/lang/StringBuilder
       3: dup
       4: invokespecial #40                 // Method java/lang/StringBuilder."<init>":()V
       7: aload_1
       8: invokevirtual #42                 // Method java/lang/StringBuilder.append:(Ljava/lang/String;)Ljava/lang/StringBuilder;
      11: ldc_w         #411                // String /
      14: invokevirtual #42                 // Method java/lang/StringBuilder.append:(Ljava/lang/String;)Ljava/lang/StringBuilder;
      17: aload_0
      18: getfield      #172                // Field path:Ljava/lang/String;
      21: invokevirtual #42                 // Method java/lang/StringBuilder.append:(Ljava/lang/String;)Ljava/lang/StringBuilder;
      24: invokevirtual #44                 // Method java/lang/StringBuilder.toString:()Ljava/lang/String;
      27: areturn

  private void lambda$appendParametersWithMethod$8(java.lang.reflect.Method, java.util.Map, org.apache.dubbo.config.ArgumentConfig);
    Code:
       0: aload_0
       1: aload_3
       2: aload_1
       3: aload_2
       4: invokespecial #412                // Method appendArgumentConfig:(Lorg/apache/dubbo/config/ArgumentConfig;Ljava/lang/reflect/Method;Ljava/util/Map;)V
       7: return

  private void lambda$buildAttributes$7(java.util.Map, org.apache.dubbo.config.MethodConfig);
    Code:
       0: aload_0
       1: aload_2
       2: aload_1
       3: invokespecial #413                // Method appendParametersWithMethod:(Lorg/apache/dubbo/config/MethodConfig;Ljava/util/Map;)V
       6: return

  private static boolean lambda$doExportUrlsFor1Protocol$6(java.util.Map, java.lang.String);
    Code:
       0: aload_1
       1: invokestatic  #134                // Method org/apache/dubbo/common/utils/StringUtils.isEmpty:(Ljava/lang/String;)Z
       4: ifne          23
       7: aload_0
       8: aload_1
       9: invokeinterface #414,  2          // InterfaceMethod java/util/Map.get:(Ljava/lang/Object;)Ljava/lang/Object;
      14: checkcast     #261                // class java/lang/String
      17: invokestatic  #134                // Method org/apache/dubbo/common/utils/StringUtils.isEmpty:(Ljava/lang/String;)Z
      20: ifeq          27
      23: iconst_1
      24: goto          28
      27: iconst_0
      28: ireturn

  private java.lang.Object lambda$doExportUrls$5(boolean, org.apache.dubbo.rpc.model.ModuleServiceRepository, java.util.List);
    Code:
       0: aload_0
       1: getfield      #190                // Field protocols:Ljava/util/List;
       4: invokeinterface #30,  1           // InterfaceMethod java/util/List.iterator:()Ljava/util/Iterator;
       9: astore        4
      11: aload         4
      13: invokeinterface #31,  1           // InterfaceMethod java/util/Iterator.hasNext:()Z
      18: ifeq          96
      21: aload         4
      23: invokeinterface #32,  1           // InterfaceMethod java/util/Iterator.next:()Ljava/lang/Object;
      28: checkcast     #363                // class org/apache/dubbo/config/ProtocolConfig
      31: astore        5
      33: aload_0
      34: aload         5
      36: invokevirtual #295                // Method getContextPath:(Lorg/apache/dubbo/config/ProtocolConfig;)Ljava/util/Optional;
      39: aload_0
      40: invokedynamic #415,  0            // InvokeDynamic #11:apply:(Lorg/apache/dubbo/config/ServiceConfig;)Ljava/util/function/Function;
      45: invokevirtual #297                // Method java/util/Optional.map:(Ljava/util/function/Function;)Ljava/util/Optional;
      48: aload_0
      49: getfield      #172                // Field path:Ljava/lang/String;
      52: invokevirtual #298                // Method java/util/Optional.orElse:(Ljava/lang/Object;)Ljava/lang/Object;
      55: checkcast     #261                // class java/lang/String
      58: aload_0
      59: getfield      #416                // Field group:Ljava/lang/String;
      62: aload_0
      63: getfield      #234                // Field version:Ljava/lang/String;
      66: invokestatic  #417                // Method org/apache/dubbo/common/URL.buildKey:(Ljava/lang/String;Ljava/lang/String;Ljava/lang/String;)Ljava/lang/String;
      69: astore        6
      71: iload_1
      72: ifne          86
      75: aload_2
      76: aload         6
      78: aload_0
      79: getfield      #140                // Field interfaceClass:Ljava/lang/Class;
      82: invokevirtual #418                // Method org/apache/dubbo/rpc/model/ModuleServiceRepository.registerService:(Ljava/lang/String;Ljava/lang/Class;)Lorg/apache/dubbo/rpc/model/ServiceDescriptor;
      85: pop
      86: aload_0
      87: aload         5
      89: aload_3
      90: invokespecial #419                // Method doExportUrlsFor1Protocol:(Lorg/apache/dubbo/config/ProtocolConfig;Ljava/util/List;)V
      93: goto          11
      96: aconst_null
      97: areturn

  private java.lang.String lambda$null$4(java.lang.String);
    Code:
       0: new           #39                 // class java/lang/StringBuilder
       3: dup
       4: invokespecial #40                 // Method java/lang/StringBuilder."<init>":()V
       7: aload_1
       8: invokevirtual #42                 // Method java/lang/StringBuilder.append:(Ljava/lang/String;)Ljava/lang/StringBuilder;
      11: ldc_w         #411                // String /
      14: invokevirtual #42                 // Method java/lang/StringBuilder.append:(Ljava/lang/String;)Ljava/lang/StringBuilder;
      17: aload_0
      18: getfield      #172                // Field path:Ljava/lang/String;
      21: invokevirtual #42                 // Method java/lang/StringBuilder.append:(Ljava/lang/String;)Ljava/lang/StringBuilder;
      24: invokevirtual #44                 // Method java/lang/StringBuilder.toString:()Ljava/lang/String;
      27: areturn

  private void lambda$checkAndUpdateSubConfigs$3(org.apache.dubbo.config.ConfigInitializer);
    Code:
       0: aload_1
       1: aload_0
       2: invokeinterface #420,  2          // InterfaceMethod org/apache/dubbo/config/ConfigInitializer.initServiceConfig:(Lorg/apache/dubbo/config/ServiceConfig;)V
       7: return

  private void lambda$scheduleToMapping$2(org.apache.dubbo.common.URL, org.apache.dubbo.metadata.ServiceNameMapping, java.util.concurrent.ScheduledExecutorService);
    Code:
       0: aload_0
       1: aload_1
       2: aload_2
       3: aload_3
       4: invokevirtual #421                // Method mapServiceName:(Lorg/apache/dubbo/common/URL;Lorg/apache/dubbo/metadata/ServiceNameMapping;Ljava/util/concurrent/ScheduledExecutorService;)V
       7: return

  private void lambda$exported$1(org.apache.dubbo.common.URL);
    Code:
       0: aload_1
       1: invokevirtual #422                // Method org/apache/dubbo/common/URL.getParameters:()Ljava/util/Map;
       4: ldc_w         #333                // String service-name-mapping
       7: invokeinterface #259,  2          // InterfaceMethod java/util/Map.containsKey:(Ljava/lang/Object;)Z
      12: ifeq          50
      15: aload_0
      16: invokevirtual #50                 // Method getScopeModel:()Lorg/apache/dubbo/rpc/model/ModuleModel;
      19: invokestatic  #423                // InterfaceMethod org/apache/dubbo/metadata/ServiceNameMapping.getDefaultExtension:(Lorg/apache/dubbo/rpc/model/ScopeModel;)Lorg/apache/dubbo/metadata/ServiceNameMapping;
      22: astore_2
      23: aload_0
      24: invokevirtual #50                 // Method getScopeModel:()Lorg/apache/dubbo/rpc/model/ModuleModel;
      27: invokevirtual #424                // Method org/apache/dubbo/rpc/model/ModuleModel.getBeanFactory:()Lorg/apache/dubbo/common/beans/factory/ScopeBeanFactory;
      30: ldc_w         #425                // class org/apache/dubbo/common/threadpool/manager/FrameworkExecutorRepository
      33: invokevirtual #426                // Method org/apache/dubbo/common/beans/factory/ScopeBeanFactory.getBean:(Ljava/lang/Class;)Ljava/lang/Object;
      36: checkcast     #425                // class org/apache/dubbo/common/threadpool/manager/FrameworkExecutorRepository
      39: invokevirtual #427                // Method org/apache/dubbo/common/threadpool/manager/FrameworkExecutorRepository.getSharedScheduledExecutor:()Ljava/util/concurrent/ScheduledExecutorService;
      42: astore_3
      43: aload_0
      44: aload_1
      45: aload_2
      46: aload_3
      47: invokevirtual #421                // Method mapServiceName:(Lorg/apache/dubbo/common/URL;Lorg/apache/dubbo/metadata/ServiceNameMapping;Ljava/util/concurrent/ScheduledExecutorService;)V
      50: return

  private void lambda$doDelayExport$0();
    Code:
       0: aload_0
       1: invokevirtual #93                 // Method doExport:()V
       4: goto          47
       7: astore_1
       8: getstatic     #36                 // Field logger:Lorg/apache/dubbo/common/logger/ErrorTypeAwareLogger;
      11: ldc_w         #428                // String 5-9
      14: ldc           #111                // String configuration server disconnected
      16: ldc           #38                 // String
      18: new           #39                 // class java/lang/StringBuilder
      21: dup
      22: invokespecial #40                 // Method java/lang/StringBuilder."<init>":()V
      25: ldc_w         #429                // String Failed to (async)export service config:
      28: invokevirtual #42                 // Method java/lang/StringBuilder.append:(Ljava/lang/String;)Ljava/lang/StringBuilder;
      31: aload_0
      32: getfield      #133                // Field interfaceName:Ljava/lang/String;
      35: invokevirtual #42                 // Method java/lang/StringBuilder.append:(Ljava/lang/String;)Ljava/lang/StringBuilder;
      38: invokevirtual #44                 // Method java/lang/StringBuilder.toString:()Ljava/lang/String;
      41: aload_1
      42: invokeinterface #115,  6          // InterfaceMethod org/apache/dubbo/common/logger/ErrorTypeAwareLogger.error:(Ljava/lang/String;Ljava/lang/String;Ljava/lang/String;Ljava/lang/String;Ljava/lang/Throwable;)V
      47: return
    Exception table:
       from    to  target type
           0     4     7   Class java/lang/Exception

  static {};
    Code:
       0: ldc_w         #430                // class org/apache/dubbo/config/ServiceConfig
       3: invokestatic  #431                // Method org/apache/dubbo/common/logger/LoggerFactory.getErrorTypeAwareLogger:(Ljava/lang/Class;)Lorg/apache/dubbo/common/logger/ErrorTypeAwareLogger;
       6: putstatic     #36                 // Field logger:Lorg/apache/dubbo/common/logger/ErrorTypeAwareLogger;
       9: new           #219                // class java/util/HashMap
      12: dup
      13: invokespecial #220                // Method java/util/HashMap."<init>":()V
      16: putstatic     #402                // Field RANDOM_PORT_MAP:Ljava/util/Map;
      19: return
}
