Compiled from "ServiceConfigBase.java"
public abstract class org.apache.dubbo.config.ServiceConfigBase<T> extends org.apache.dubbo.config.AbstractServiceConfig {
  private static final long serialVersionUID;

  protected java.lang.Class<?> interfaceClass;

  protected transient T ref;

  protected java.lang.String path;

  protected org.apache.dubbo.config.ProviderConfig provider;

  protected java.lang.String providerIds;

  protected volatile java.lang.String generic;

  public org.apache.dubbo.config.ServiceConfigBase();
    Code:
       0: aload_0
       1: invokespecial #2                  // Method org/apache/dubbo/config/AbstractServiceConfig."<init>":()V
       4: aload_0
       5: new           #3                  // class org/apache/dubbo/rpc/model/ServiceMetadata
       8: dup
       9: invokespecial #4                  // Method org/apache/dubbo/rpc/model/ServiceMetadata."<init>":()V
      12: putfield      #5                  // Field serviceMetadata:Lorg/apache/dubbo/rpc/model/ServiceMetadata;
      15: aload_0
      16: getfield      #5                  // Field serviceMetadata:Lorg/apache/dubbo/rpc/model/ServiceMetadata;
      19: ldc           #6                  // String ORIGIN_CONFIG
      21: aload_0
      22: invokevirtual #7                  // Method org/apache/dubbo/rpc/model/ServiceMetadata.addAttribute:(Ljava/lang/String;Ljava/lang/Object;)V
      25: return

  public org.apache.dubbo.config.ServiceConfigBase(org.apache.dubbo.rpc.model.ModuleModel);
    Code:
       0: aload_0
       1: aload_1
       2: invokespecial #8                  // Method org/apache/dubbo/config/AbstractServiceConfig."<init>":(Lorg/apache/dubbo/rpc/model/ModuleModel;)V
       5: aload_0
       6: new           #3                  // class org/apache/dubbo/rpc/model/ServiceMetadata
       9: dup
      10: invokespecial #4                  // Method org/apache/dubbo/rpc/model/ServiceMetadata."<init>":()V
      13: putfield      #5                  // Field serviceMetadata:Lorg/apache/dubbo/rpc/model/ServiceMetadata;
      16: aload_0
      17: getfield      #5                  // Field serviceMetadata:Lorg/apache/dubbo/rpc/model/ServiceMetadata;
      20: ldc           #6                  // String ORIGIN_CONFIG
      22: aload_0
      23: invokevirtual #7                  // Method org/apache/dubbo/rpc/model/ServiceMetadata.addAttribute:(Ljava/lang/String;Ljava/lang/Object;)V
      26: return

  public org.apache.dubbo.config.ServiceConfigBase(org.apache.dubbo.config.annotation.Service);
    Code:
       0: aload_0
       1: invokespecial #2                  // Method org/apache/dubbo/config/AbstractServiceConfig."<init>":()V
       4: aload_0
       5: new           #3                  // class org/apache/dubbo/rpc/model/ServiceMetadata
       8: dup
       9: invokespecial #4                  // Method org/apache/dubbo/rpc/model/ServiceMetadata."<init>":()V
      12: putfield      #5                  // Field serviceMetadata:Lorg/apache/dubbo/rpc/model/ServiceMetadata;
      15: aload_0
      16: getfield      #5                  // Field serviceMetadata:Lorg/apache/dubbo/rpc/model/ServiceMetadata;
      19: ldc           #6                  // String ORIGIN_CONFIG
      21: aload_0
      22: invokevirtual #7                  // Method org/apache/dubbo/rpc/model/ServiceMetadata.addAttribute:(Ljava/lang/String;Ljava/lang/Object;)V
      25: aload_0
      26: ldc           #9                  // class org/apache/dubbo/config/annotation/Service
      28: aload_1
      29: invokevirtual #10                 // Method appendAnnotation:(Ljava/lang/Class;Ljava/lang/Object;)V
      32: aload_0
      33: aload_1
      34: invokeinterface #11,  1           // InterfaceMethod org/apache/dubbo/config/annotation/Service.methods:()[Lorg/apache/dubbo/config/annotation/Method;
      39: invokestatic  #12                 // Method org/apache/dubbo/config/MethodConfig.constructMethodConfig:([Lorg/apache/dubbo/config/annotation/Method;)Ljava/util/List;
      42: invokevirtual #13                 // Method setMethods:(Ljava/util/List;)V
      45: return

  public org.apache.dubbo.config.ServiceConfigBase(org.apache.dubbo.rpc.model.ModuleModel, org.apache.dubbo.config.annotation.Service);
    Code:
       0: aload_0
       1: aload_1
       2: invokespecial #8                  // Method org/apache/dubbo/config/AbstractServiceConfig."<init>":(Lorg/apache/dubbo/rpc/model/ModuleModel;)V
       5: aload_0
       6: new           #3                  // class org/apache/dubbo/rpc/model/ServiceMetadata
       9: dup
      10: invokespecial #4                  // Method org/apache/dubbo/rpc/model/ServiceMetadata."<init>":()V
      13: putfield      #5                  // Field serviceMetadata:Lorg/apache/dubbo/rpc/model/ServiceMetadata;
      16: aload_0
      17: getfield      #5                  // Field serviceMetadata:Lorg/apache/dubbo/rpc/model/ServiceMetadata;
      20: ldc           #6                  // String ORIGIN_CONFIG
      22: aload_0
      23: invokevirtual #7                  // Method org/apache/dubbo/rpc/model/ServiceMetadata.addAttribute:(Ljava/lang/String;Ljava/lang/Object;)V
      26: aload_0
      27: ldc           #9                  // class org/apache/dubbo/config/annotation/Service
      29: aload_2
      30: invokevirtual #10                 // Method appendAnnotation:(Ljava/lang/Class;Ljava/lang/Object;)V
      33: aload_0
      34: aload_2
      35: invokeinterface #11,  1           // InterfaceMethod org/apache/dubbo/config/annotation/Service.methods:()[Lorg/apache/dubbo/config/annotation/Method;
      40: invokestatic  #12                 // Method org/apache/dubbo/config/MethodConfig.constructMethodConfig:([Lorg/apache/dubbo/config/annotation/Method;)Ljava/util/List;
      43: invokevirtual #13                 // Method setMethods:(Ljava/util/List;)V
      46: return

  protected void postProcessAfterScopeModelChanged(org.apache.dubbo.rpc.model.ScopeModel, org.apache.dubbo.rpc.model.ScopeModel);
    Code:
       0: aload_0
       1: aload_1
       2: aload_2
       3: invokespecial #14                 // Method org/apache/dubbo/config/AbstractServiceConfig.postProcessAfterScopeModelChanged:(Lorg/apache/dubbo/rpc/model/ScopeModel;Lorg/apache/dubbo/rpc/model/ScopeModel;)V
       6: aload_0
       7: getfield      #15                 // Field provider:Lorg/apache/dubbo/config/ProviderConfig;
      10: ifnull        38
      13: aload_0
      14: getfield      #15                 // Field provider:Lorg/apache/dubbo/config/ProviderConfig;
      17: invokevirtual #16                 // Method org/apache/dubbo/config/ProviderConfig.getScopeModel:()Lorg/apache/dubbo/rpc/model/ModuleModel;
      20: aload_0
      21: invokevirtual #17                 // Method getScopeModel:()Lorg/apache/dubbo/rpc/model/ModuleModel;
      24: if_acmpeq     38
      27: aload_0
      28: getfield      #15                 // Field provider:Lorg/apache/dubbo/config/ProviderConfig;
      31: aload_0
      32: invokevirtual #17                 // Method getScopeModel:()Lorg/apache/dubbo/rpc/model/ModuleModel;
      35: invokevirtual #18                 // Method org/apache/dubbo/config/ProviderConfig.setScopeModel:(Lorg/apache/dubbo/rpc/model/ScopeModel;)V
      38: return

  public boolean shouldExport();
    Code:
       0: aload_0
       1: invokevirtual #19                 // Method getExport:()Ljava/lang/Boolean;
       4: astore_1
       5: aload_1
       6: ifnonnull     13
       9: iconst_1
      10: goto          17
      13: aload_1
      14: invokevirtual #20                 // Method java/lang/Boolean.booleanValue:()Z
      17: ireturn

  public java.lang.Boolean getExport();
    Code:
       0: aload_0
       1: getfield      #21                 // Field export:Ljava/lang/Boolean;
       4: ifnonnull     24
       7: aload_0
       8: getfield      #15                 // Field provider:Lorg/apache/dubbo/config/ProviderConfig;
      11: ifnull        24
      14: aload_0
      15: getfield      #15                 // Field provider:Lorg/apache/dubbo/config/ProviderConfig;
      18: invokevirtual #22                 // Method org/apache/dubbo/config/ProviderConfig.getExport:()Ljava/lang/Boolean;
      21: goto          28
      24: aload_0
      25: getfield      #21                 // Field export:Ljava/lang/Boolean;
      28: areturn

  public boolean shouldDelay();
    Code:
       0: aload_0
       1: invokevirtual #23                 // Method getDelay:()Ljava/lang/Integer;
       4: astore_1
       5: aload_1
       6: ifnull        20
       9: aload_1
      10: invokevirtual #24                 // Method java/lang/Integer.intValue:()I
      13: ifle          20
      16: iconst_1
      17: goto          21
      20: iconst_0
      21: ireturn

  public java.lang.Integer getDelay();
    Code:
       0: aload_0
       1: getfield      #25                 // Field delay:Ljava/lang/Integer;
       4: ifnonnull     24
       7: aload_0
       8: getfield      #15                 // Field provider:Lorg/apache/dubbo/config/ProviderConfig;
      11: ifnull        24
      14: aload_0
      15: getfield      #15                 // Field provider:Lorg/apache/dubbo/config/ProviderConfig;
      18: invokevirtual #26                 // Method org/apache/dubbo/config/ProviderConfig.getDelay:()Ljava/lang/Integer;
      21: goto          28
      24: aload_0
      25: getfield      #25                 // Field delay:Ljava/lang/Integer;
      28: areturn

  protected void checkRef();
    Code:
       0: aload_0
       1: getfield      #27                 // Field ref:Ljava/lang/Object;
       4: ifnonnull     17
       7: new           #28                 // class java/lang/IllegalStateException
      10: dup
      11: ldc           #29                 // String ref not allow null!
      13: invokespecial #30                 // Method java/lang/IllegalStateException."<init>":(Ljava/lang/String;)V
      16: athrow
      17: aload_0
      18: getfield      #31                 // Field interfaceClass:Ljava/lang/Class;
      21: aload_0
      22: getfield      #27                 // Field ref:Ljava/lang/Object;
      25: invokevirtual #32                 // Method java/lang/Class.isInstance:(Ljava/lang/Object;)Z
      28: ifne          89
      31: new           #28                 // class java/lang/IllegalStateException
      34: dup
      35: new           #33                 // class java/lang/StringBuilder
      38: dup
      39: invokespecial #34                 // Method java/lang/StringBuilder."<init>":()V
      42: ldc           #35                 // String The class
      44: invokevirtual #36                 // Method java/lang/StringBuilder.append:(Ljava/lang/String;)Ljava/lang/StringBuilder;
      47: aload_0
      48: aload_0
      49: getfield      #27                 // Field ref:Ljava/lang/Object;
      52: invokevirtual #37                 // Method java/lang/Object.getClass:()Ljava/lang/Class;
      55: invokespecial #38                 // Method getClassDesc:(Ljava/lang/Class;)Ljava/lang/String;
      58: invokevirtual #36                 // Method java/lang/StringBuilder.append:(Ljava/lang/String;)Ljava/lang/StringBuilder;
      61: ldc           #39                 // String  unimplemented interface
      63: invokevirtual #36                 // Method java/lang/StringBuilder.append:(Ljava/lang/String;)Ljava/lang/StringBuilder;
      66: aload_0
      67: aload_0
      68: getfield      #31                 // Field interfaceClass:Ljava/lang/Class;
      71: invokespecial #38                 // Method getClassDesc:(Ljava/lang/Class;)Ljava/lang/String;
      74: invokevirtual #36                 // Method java/lang/StringBuilder.append:(Ljava/lang/String;)Ljava/lang/StringBuilder;
      77: ldc           #40                 // String !
      79: invokevirtual #36                 // Method java/lang/StringBuilder.append:(Ljava/lang/String;)Ljava/lang/StringBuilder;
      82: invokevirtual #41                 // Method java/lang/StringBuilder.toString:()Ljava/lang/String;
      85: invokespecial #30                 // Method java/lang/IllegalStateException."<init>":(Ljava/lang/String;)V
      88: athrow
      89: return

  private java.lang.String getClassDesc(java.lang.Class);
    Code:
       0: aload_1
       1: invokevirtual #42                 // Method java/lang/Class.getClassLoader:()Ljava/lang/ClassLoader;
       4: astore_2
       5: new           #33                 // class java/lang/StringBuilder
       8: dup
       9: invokespecial #34                 // Method java/lang/StringBuilder."<init>":()V
      12: aload_1
      13: invokevirtual #43                 // Method java/lang/Class.getName:()Ljava/lang/String;
      16: invokevirtual #36                 // Method java/lang/StringBuilder.append:(Ljava/lang/String;)Ljava/lang/StringBuilder;
      19: ldc           #44                 // String [classloader=
      21: invokevirtual #36                 // Method java/lang/StringBuilder.append:(Ljava/lang/String;)Ljava/lang/StringBuilder;
      24: aload_2
      25: invokevirtual #37                 // Method java/lang/Object.getClass:()Ljava/lang/Class;
      28: invokevirtual #43                 // Method java/lang/Class.getName:()Ljava/lang/String;
      31: invokevirtual #36                 // Method java/lang/StringBuilder.append:(Ljava/lang/String;)Ljava/lang/StringBuilder;
      34: ldc           #45                 // String @
      36: invokevirtual #36                 // Method java/lang/StringBuilder.append:(Ljava/lang/String;)Ljava/lang/StringBuilder;
      39: aload_2
      40: invokevirtual #46                 // Method java/lang/Object.hashCode:()I
      43: invokevirtual #47                 // Method java/lang/StringBuilder.append:(I)Ljava/lang/StringBuilder;
      46: ldc           #48                 // String ]
      48: invokevirtual #36                 // Method java/lang/StringBuilder.append:(Ljava/lang/String;)Ljava/lang/StringBuilder;
      51: invokevirtual #41                 // Method java/lang/StringBuilder.toString:()Ljava/lang/String;
      54: areturn

  public java.util.Optional<java.lang.String> getContextPath(org.apache.dubbo.config.ProtocolConfig);
    Code:
       0: aload_1
       1: invokevirtual #49                 // Method org/apache/dubbo/config/ProtocolConfig.getContextpath:()Ljava/lang/String;
       4: astore_2
       5: aload_2
       6: invokestatic  #50                 // Method org/apache/dubbo/common/utils/StringUtils.isEmpty:(Ljava/lang/String;)Z
       9: ifeq          27
      12: aload_0
      13: getfield      #15                 // Field provider:Lorg/apache/dubbo/config/ProviderConfig;
      16: ifnull        27
      19: aload_0
      20: getfield      #15                 // Field provider:Lorg/apache/dubbo/config/ProviderConfig;
      23: invokevirtual #51                 // Method org/apache/dubbo/config/ProviderConfig.getContextpath:()Ljava/lang/String;
      26: astore_2
      27: aload_2
      28: invokestatic  #52                 // Method java/util/Optional.ofNullable:(Ljava/lang/Object;)Ljava/util/Optional;
      31: areturn

  protected java.lang.Class getServiceClass(T);
    Code:
       0: aload_1
       1: invokevirtual #37                 // Method java/lang/Object.getClass:()Ljava/lang/Class;
       4: areturn

  protected void preProcessRefresh();
    Code:
       0: aload_0
       1: invokespecial #53                 // Method org/apache/dubbo/config/AbstractServiceConfig.preProcessRefresh:()V
       4: aload_0
       5: invokevirtual #54                 // Method convertProviderIdToProvider:()V
       8: aload_0
       9: getfield      #15                 // Field provider:Lorg/apache/dubbo/config/ProviderConfig;
      12: ifnonnull     37
      15: aload_0
      16: aload_0
      17: invokevirtual #55                 // Method getModuleConfigManager:()Lorg/apache/dubbo/config/context/ModuleConfigManager;
      20: invokevirtual #56                 // Method org/apache/dubbo/config/context/ModuleConfigManager.getDefaultProvider:()Ljava/util/Optional;
      23: invokedynamic #57,  0             // InvokeDynamic #0:get:()Ljava/util/function/Supplier;
      28: invokevirtual #58                 // Method java/util/Optional.orElseThrow:(Ljava/util/function/Supplier;)Ljava/lang/Object;
      31: checkcast     #59                 // class org/apache/dubbo/config/ProviderConfig
      34: putfield      #15                 // Field provider:Lorg/apache/dubbo/config/ProviderConfig;
      37: aload_0
      38: aload_0
      39: invokespecial #60                 // Method org/apache/dubbo/config/AbstractServiceConfig.getPrefixes:()Ljava/util/List;
      42: getstatic     #61                 // Field org/apache/dubbo/config/context/ConfigMode.OVERRIDE_IF_ABSENT:Lorg/apache/dubbo/config/context/ConfigMode;
      45: invokevirtual #62                 // Method refreshWithPrefixes:(Ljava/util/List;Lorg/apache/dubbo/config/context/ConfigMode;)V
      48: return

  public java.util.Map<java.lang.String, java.lang.String> getMetaData();
    Code:
       0: aload_0
       1: aconst_null
       2: invokevirtual #63                 // Method getMetaData:(Ljava/lang/String;)Ljava/util/Map;
       5: areturn

  public java.util.Map<java.lang.String, java.lang.String> getMetaData(java.lang.String);
    Code:
       0: new           #64                 // class java/util/HashMap
       3: dup
       4: invokespecial #65                 // Method java/util/HashMap."<init>":()V
       7: astore_2
       8: aload_0
       9: invokevirtual #66                 // Method getProvider:()Lorg/apache/dubbo/config/ProviderConfig;
      12: astore_3
      13: aload_0
      14: invokevirtual #67                 // Method isRefreshed:()Z
      17: ifeq          34
      20: aload_3
      21: ifnonnull     34
      24: new           #28                 // class java/lang/IllegalStateException
      27: dup
      28: ldc           #68                 // String Provider is not initialized
      30: invokespecial #30                 // Method java/lang/IllegalStateException."<init>":(Ljava/lang/String;)V
      33: athrow
      34: aload_2
      35: aload_3
      36: aload_1
      37: invokestatic  #69                 // Method appendAttributes:(Ljava/util/Map;Ljava/lang/Object;Ljava/lang/String;)V
      40: aload_2
      41: aload_0
      42: aload_1
      43: invokestatic  #69                 // Method appendAttributes:(Ljava/util/Map;Ljava/lang/Object;Ljava/lang/String;)V
      46: aload_2
      47: areturn

  protected void checkProtocol();
    Code:
       0: aload_0
       1: getfield      #15                 // Field provider:Lorg/apache/dubbo/config/ProviderConfig;
       4: ifnull        36
       7: aload_0
       8: invokespecial #70                 // Method notHasSelfProtocolProperty:()Z
      11: ifeq          36
      14: aload_0
      15: aload_0
      16: getfield      #15                 // Field provider:Lorg/apache/dubbo/config/ProviderConfig;
      19: invokevirtual #71                 // Method org/apache/dubbo/config/ProviderConfig.getProtocols:()Ljava/util/List;
      22: invokevirtual #72                 // Method setProtocols:(Ljava/util/List;)V
      25: aload_0
      26: aload_0
      27: getfield      #15                 // Field provider:Lorg/apache/dubbo/config/ProviderConfig;
      30: invokevirtual #73                 // Method org/apache/dubbo/config/ProviderConfig.getProtocolIds:()Ljava/lang/String;
      33: invokevirtual #74                 // Method setProtocolIds:(Ljava/lang/String;)V
      36: aload_0
      37: invokevirtual #75                 // Method convertProtocolIdsToProtocols:()V
      40: return

  private boolean notHasSelfProtocolProperty();
    Code:
       0: aload_0
       1: getfield      #76                 // Field protocols:Ljava/util/List;
       4: invokestatic  #77                 // Method org/apache/dubbo/common/utils/CollectionUtils.isEmpty:(Ljava/util/Collection;)Z
       7: ifeq          24
      10: aload_0
      11: getfield      #78                 // Field protocolIds:Ljava/lang/String;
      14: invokestatic  #50                 // Method org/apache/dubbo/common/utils/StringUtils.isEmpty:(Ljava/lang/String;)Z
      17: ifeq          24
      20: iconst_1
      21: goto          25
      24: iconst_0
      25: ireturn

  protected void completeCompoundConfigs();
    Code:
       0: aload_0
       1: aload_0
       2: getfield      #15                 // Field provider:Lorg/apache/dubbo/config/ProviderConfig;
       5: invokespecial #79                 // Method org/apache/dubbo/config/AbstractServiceConfig.completeCompoundConfigs:(Lorg/apache/dubbo/config/AbstractInterfaceConfig;)V
       8: aload_0
       9: getfield      #15                 // Field provider:Lorg/apache/dubbo/config/ProviderConfig;
      12: ifnull        62
      15: aload_0
      16: invokespecial #70                 // Method notHasSelfProtocolProperty:()Z
      19: ifeq          44
      22: aload_0
      23: aload_0
      24: getfield      #15                 // Field provider:Lorg/apache/dubbo/config/ProviderConfig;
      27: invokevirtual #71                 // Method org/apache/dubbo/config/ProviderConfig.getProtocols:()Ljava/util/List;
      30: invokevirtual #72                 // Method setProtocols:(Ljava/util/List;)V
      33: aload_0
      34: aload_0
      35: getfield      #15                 // Field provider:Lorg/apache/dubbo/config/ProviderConfig;
      38: invokevirtual #73                 // Method org/apache/dubbo/config/ProviderConfig.getProtocolIds:()Ljava/lang/String;
      41: invokevirtual #74                 // Method setProtocolIds:(Ljava/lang/String;)V
      44: aload_0
      45: getfield      #80                 // Field configCenter:Lorg/apache/dubbo/config/ConfigCenterConfig;
      48: ifnonnull     62
      51: aload_0
      52: aload_0
      53: getfield      #15                 // Field provider:Lorg/apache/dubbo/config/ProviderConfig;
      56: invokevirtual #81                 // Method org/apache/dubbo/config/ProviderConfig.getConfigCenter:()Lorg/apache/dubbo/config/ConfigCenterConfig;
      59: invokevirtual #82                 // Method setConfigCenter:(Lorg/apache/dubbo/config/ConfigCenterConfig;)V
      62: return

  protected void convertProviderIdToProvider();
    Code:
       0: aload_0
       1: getfield      #15                 // Field provider:Lorg/apache/dubbo/config/ProviderConfig;
       4: ifnonnull     44
       7: aload_0
       8: getfield      #83                 // Field providerIds:Ljava/lang/String;
      11: invokestatic  #84                 // Method org/apache/dubbo/common/utils/StringUtils.hasText:(Ljava/lang/CharSequence;)Z
      14: ifeq          44
      17: aload_0
      18: aload_0
      19: invokevirtual #55                 // Method getModuleConfigManager:()Lorg/apache/dubbo/config/context/ModuleConfigManager;
      22: aload_0
      23: getfield      #83                 // Field providerIds:Ljava/lang/String;
      26: invokevirtual #85                 // Method org/apache/dubbo/config/context/ModuleConfigManager.getProvider:(Ljava/lang/String;)Ljava/util/Optional;
      29: aload_0
      30: invokedynamic #86,  0             // InvokeDynamic #1:get:(Lorg/apache/dubbo/config/ServiceConfigBase;)Ljava/util/function/Supplier;
      35: invokevirtual #58                 // Method java/util/Optional.orElseThrow:(Ljava/util/function/Supplier;)Ljava/lang/Object;
      38: checkcast     #59                 // class org/apache/dubbo/config/ProviderConfig
      41: putfield      #15                 // Field provider:Lorg/apache/dubbo/config/ProviderConfig;
      44: return

  protected void convertProtocolIdsToProtocols();
    Code:
       0: aload_0
       1: getfield      #78                 // Field protocolIds:Ljava/lang/String;
       4: invokestatic  #50                 // Method org/apache/dubbo/common/utils/StringUtils.isEmpty:(Ljava/lang/String;)Z
       7: ifeq          55
      10: aload_0
      11: getfield      #76                 // Field protocols:Ljava/util/List;
      14: invokestatic  #77                 // Method org/apache/dubbo/common/utils/CollectionUtils.isEmpty:(Ljava/util/Collection;)Z
      17: ifeq          186
      20: aload_0
      21: invokevirtual #87                 // Method getConfigManager:()Lorg/apache/dubbo/config/context/ConfigManager;
      24: invokevirtual #88                 // Method org/apache/dubbo/config/context/ConfigManager.getDefaultProtocols:()Ljava/util/List;
      27: astore_1
      28: aload_1
      29: invokeinterface #89,  1           // InterfaceMethod java/util/List.isEmpty:()Z
      34: ifeq          47
      37: new           #28                 // class java/lang/IllegalStateException
      40: dup
      41: ldc           #90                 // String The default protocol has not been initialized.
      43: invokespecial #30                 // Method java/lang/IllegalStateException."<init>":(Ljava/lang/String;)V
      46: athrow
      47: aload_0
      48: aload_1
      49: invokevirtual #72                 // Method setProtocols:(Ljava/util/List;)V
      52: goto          186
      55: getstatic     #91                 // Field org/apache/dubbo/common/constants/CommonConstants.COMMA_SPLIT_PATTERN:Ljava/util/regex/Pattern;
      58: aload_0
      59: getfield      #78                 // Field protocolIds:Ljava/lang/String;
      62: invokevirtual #92                 // Method java/util/regex/Pattern.split:(Ljava/lang/CharSequence;)[Ljava/lang/String;
      65: astore_1
      66: new           #93                 // class java/util/LinkedHashSet
      69: dup
      70: aload_1
      71: invokestatic  #94                 // Method java/util/Arrays.asList:([Ljava/lang/Object;)Ljava/util/List;
      74: invokespecial #95                 // Method java/util/LinkedHashSet."<init>":(Ljava/util/Collection;)V
      77: astore_2
      78: new           #96                 // class java/util/ArrayList
      81: dup
      82: invokespecial #97                 // Method java/util/ArrayList."<init>":()V
      85: astore_3
      86: aload_2
      87: invokeinterface #98,  1           // InterfaceMethod java/util/Set.iterator:()Ljava/util/Iterator;
      92: astore        4
      94: aload         4
      96: invokeinterface #99,  1           // InterfaceMethod java/util/Iterator.hasNext:()Z
     101: ifeq          181
     104: aload         4
     106: invokeinterface #100,  1          // InterfaceMethod java/util/Iterator.next:()Ljava/lang/Object;
     111: checkcast     #101                // class java/lang/String
     114: astore        5
     116: aload_0
     117: invokevirtual #87                 // Method getConfigManager:()Lorg/apache/dubbo/config/context/ConfigManager;
     120: aload         5
     122: invokevirtual #102                // Method org/apache/dubbo/config/context/ConfigManager.getProtocol:(Ljava/lang/String;)Ljava/util/Optional;
     125: astore        6
     127: aload         6
     129: invokevirtual #103                // Method java/util/Optional.isPresent:()Z
     132: ifeq          150
     135: aload_3
     136: aload         6
     138: invokevirtual #104                // Method java/util/Optional.get:()Ljava/lang/Object;
     141: invokeinterface #105,  2          // InterfaceMethod java/util/List.add:(Ljava/lang/Object;)Z
     146: pop
     147: goto          178
     150: new           #28                 // class java/lang/IllegalStateException
     153: dup
     154: new           #33                 // class java/lang/StringBuilder
     157: dup
     158: invokespecial #34                 // Method java/lang/StringBuilder."<init>":()V
     161: ldc           #106                // String Protocol not found:
     163: invokevirtual #36                 // Method java/lang/StringBuilder.append:(Ljava/lang/String;)Ljava/lang/StringBuilder;
     166: aload         5
     168: invokevirtual #36                 // Method java/lang/StringBuilder.append:(Ljava/lang/String;)Ljava/lang/StringBuilder;
     171: invokevirtual #41                 // Method java/lang/StringBuilder.toString:()Ljava/lang/String;
     174: invokespecial #30                 // Method java/lang/IllegalStateException."<init>":(Ljava/lang/String;)V
     177: athrow
     178: goto          94
     181: aload_0
     182: aload_3
     183: invokevirtual #72                 // Method setProtocols:(Ljava/util/List;)V
     186: return

  public java.lang.Class<?> getInterfaceClass();
    Code:
       0: aload_0
       1: getfield      #31                 // Field interfaceClass:Ljava/lang/Class;
       4: ifnull        12
       7: aload_0
       8: getfield      #31                 // Field interfaceClass:Ljava/lang/Class;
      11: areturn
      12: aload_0
      13: getfield      #27                 // Field ref:Ljava/lang/Object;
      16: instanceof    #107                // class org/apache/dubbo/rpc/service/GenericService
      19: ifeq          25
      22: ldc           #107                // class org/apache/dubbo/rpc/service/GenericService
      24: areturn
      25: aload_0
      26: getfield      #108                // Field interfaceName:Ljava/lang/String;
      29: invokestatic  #109                // Method org/apache/dubbo/common/utils/StringUtils.isNotEmpty:(Ljava/lang/String;)Z
      32: ifeq          53
      35: aload_0
      36: aload_0
      37: getfield      #108                // Field interfaceName:Ljava/lang/String;
      40: iconst_1
      41: invokestatic  #110                // Method java/lang/Thread.currentThread:()Ljava/lang/Thread;
      44: invokevirtual #111                // Method java/lang/Thread.getContextClassLoader:()Ljava/lang/ClassLoader;
      47: invokestatic  #112                // Method java/lang/Class.forName:(Ljava/lang/String;ZLjava/lang/ClassLoader;)Ljava/lang/Class;
      50: putfield      #31                 // Field interfaceClass:Ljava/lang/Class;
      53: goto          70
      56: astore_1
      57: new           #28                 // class java/lang/IllegalStateException
      60: dup
      61: aload_1
      62: invokevirtual #114                // Method java/lang/ClassNotFoundException.getMessage:()Ljava/lang/String;
      65: aload_1
      66: invokespecial #115                // Method java/lang/IllegalStateException."<init>":(Ljava/lang/String;Ljava/lang/Throwable;)V
      69: athrow
      70: aload_0
      71: getfield      #31                 // Field interfaceClass:Ljava/lang/Class;
      74: areturn
    Exception table:
       from    to  target type
          25    53    56   Class java/lang/ClassNotFoundException

  public void setInterfaceClass(java.lang.Class<?>);
    Code:
       0: aload_0
       1: aload_1
       2: invokevirtual #116                // Method setInterface:(Ljava/lang/Class;)V
       5: return

  public void setInterface(java.lang.Class<?>);
    Code:
       0: aload_1
       1: ifnull        50
       4: aload_1
       5: invokevirtual #117                // Method java/lang/Class.isInterface:()Z
       8: ifne          50
      11: aload_0
      12: invokevirtual #118                // Method canSkipInterfaceCheck:()Z
      15: ifne          50
      18: new           #28                 // class java/lang/IllegalStateException
      21: dup
      22: new           #33                 // class java/lang/StringBuilder
      25: dup
      26: invokespecial #34                 // Method java/lang/StringBuilder."<init>":()V
      29: ldc           #119                // String The interface class
      31: invokevirtual #36                 // Method java/lang/StringBuilder.append:(Ljava/lang/String;)Ljava/lang/StringBuilder;
      34: aload_1
      35: invokevirtual #120                // Method java/lang/StringBuilder.append:(Ljava/lang/Object;)Ljava/lang/StringBuilder;
      38: ldc           #121                // String  is not a interface!
      40: invokevirtual #36                 // Method java/lang/StringBuilder.append:(Ljava/lang/String;)Ljava/lang/StringBuilder;
      43: invokevirtual #41                 // Method java/lang/StringBuilder.toString:()Ljava/lang/String;
      46: invokespecial #30                 // Method java/lang/IllegalStateException."<init>":(Ljava/lang/String;)V
      49: athrow
      50: aload_0
      51: aload_1
      52: putfield      #31                 // Field interfaceClass:Ljava/lang/Class;
      55: aload_0
      56: aload_1
      57: ifnonnull     64
      60: aconst_null
      61: goto          68
      64: aload_1
      65: invokevirtual #43                 // Method java/lang/Class.getName:()Ljava/lang/String;
      68: invokevirtual #122                // Method setInterface:(Ljava/lang/String;)V
      71: aload_0
      72: invokevirtual #123                // Method getInterfaceClassLoader:()Ljava/lang/ClassLoader;
      75: ifnonnull     94
      78: aload_0
      79: aload_1
      80: ifnonnull     87
      83: aconst_null
      84: goto          91
      87: aload_1
      88: invokevirtual #42                 // Method java/lang/Class.getClassLoader:()Ljava/lang/ClassLoader;
      91: invokevirtual #124                // Method setInterfaceClassLoader:(Ljava/lang/ClassLoader;)V
      94: return

  public boolean canSkipInterfaceCheck();
    Code:
       0: aload_0
       1: invokevirtual #125                // Method getProtocols:()Ljava/util/List;
       4: astore_1
       5: aload_1
       6: ifnonnull     11
       9: iconst_0
      10: ireturn
      11: aload_1
      12: invokeinterface #126,  1          // InterfaceMethod java/util/List.iterator:()Ljava/util/Iterator;
      17: astore_2
      18: aload_2
      19: invokeinterface #99,  1           // InterfaceMethod java/util/Iterator.hasNext:()Z
      24: ifeq          54
      27: aload_2
      28: invokeinterface #100,  1          // InterfaceMethod java/util/Iterator.next:()Ljava/lang/Object;
      33: checkcast     #127                // class org/apache/dubbo/config/ProtocolConfig
      36: astore_3
      37: ldc           #129                // String rest
      39: aload_3
      40: invokevirtual #130                // Method org/apache/dubbo/config/ProtocolConfig.getName:()Ljava/lang/String;
      43: invokevirtual #131                // Method java/lang/String.equals:(Ljava/lang/Object;)Z
      46: ifeq          51
      49: iconst_1
      50: ireturn
      51: goto          18
      54: iconst_0
      55: ireturn

  public T getRef();
    Code:
       0: aload_0
       1: getfield      #27                 // Field ref:Ljava/lang/Object;
       4: areturn

  public void setRef(T);
    Code:
       0: aload_0
       1: aload_1
       2: putfield      #27                 // Field ref:Ljava/lang/Object;
       5: return

  public java.lang.String getPath();
    Code:
       0: aload_0
       1: getfield      #132                // Field path:Ljava/lang/String;
       4: areturn

  public void setPath(java.lang.String);
    Code:
       0: aload_0
       1: aload_1
       2: putfield      #132                // Field path:Ljava/lang/String;
       5: return

  public org.apache.dubbo.config.ProviderConfig getProvider();
    Code:
       0: aload_0
       1: getfield      #15                 // Field provider:Lorg/apache/dubbo/config/ProviderConfig;
       4: areturn

  public void setProvider(org.apache.dubbo.config.ProviderConfig);
    Code:
       0: aload_0
       1: invokevirtual #55                 // Method getModuleConfigManager:()Lorg/apache/dubbo/config/context/ModuleConfigManager;
       4: aload_1
       5: invokevirtual #133                // Method org/apache/dubbo/config/context/ModuleConfigManager.addProvider:(Lorg/apache/dubbo/config/ProviderConfig;)V
       8: aload_0
       9: aload_1
      10: putfield      #15                 // Field provider:Lorg/apache/dubbo/config/ProviderConfig;
      13: return

  public java.lang.String getProviderIds();
    Code:
       0: aload_0
       1: getfield      #83                 // Field providerIds:Ljava/lang/String;
       4: areturn

  public void setProviderIds(java.lang.String);
    Code:
       0: aload_0
       1: aload_1
       2: putfield      #83                 // Field providerIds:Ljava/lang/String;
       5: return

  public java.lang.String getGeneric();
    Code:
       0: aload_0
       1: getfield      #134                // Field generic:Ljava/lang/String;
       4: areturn

  public void setGeneric(java.lang.String);
    Code:
       0: aload_1
       1: invokestatic  #50                 // Method org/apache/dubbo/common/utils/StringUtils.isEmpty:(Ljava/lang/String;)Z
       4: ifeq          8
       7: return
       8: aload_1
       9: invokestatic  #135                // Method org/apache/dubbo/rpc/support/ProtocolUtils.isValidGenericValue:(Ljava/lang/String;)Z
      12: ifeq          23
      15: aload_0
      16: aload_1
      17: putfield      #134                // Field generic:Ljava/lang/String;
      20: goto          50
      23: new           #136                // class java/lang/IllegalArgumentException
      26: dup
      27: new           #33                 // class java/lang/StringBuilder
      30: dup
      31: invokespecial #34                 // Method java/lang/StringBuilder."<init>":()V
      34: ldc           #137                // String Unsupported generic type
      36: invokevirtual #36                 // Method java/lang/StringBuilder.append:(Ljava/lang/String;)Ljava/lang/StringBuilder;
      39: aload_1
      40: invokevirtual #36                 // Method java/lang/StringBuilder.append:(Ljava/lang/String;)Ljava/lang/StringBuilder;
      43: invokevirtual #41                 // Method java/lang/StringBuilder.toString:()Ljava/lang/String;
      46: invokespecial #138                // Method java/lang/IllegalArgumentException."<init>":(Ljava/lang/String;)V
      49: athrow
      50: return

  public org.apache.dubbo.rpc.model.ServiceMetadata getServiceMetadata();
    Code:
       0: aload_0
       1: getfield      #5                  // Field serviceMetadata:Lorg/apache/dubbo/rpc/model/ServiceMetadata;
       4: areturn

  public java.util.List<java.lang.String> getPrefixes();
    Code:
       0: new           #96                 // class java/util/ArrayList
       3: dup
       4: invokespecial #97                 // Method java/util/ArrayList."<init>":()V
       7: astore_1
       8: aload_1
       9: new           #33                 // class java/lang/StringBuilder
      12: dup
      13: invokespecial #34                 // Method java/lang/StringBuilder."<init>":()V
      16: ldc           #139                // String dubbo.service.
      18: invokevirtual #36                 // Method java/lang/StringBuilder.append:(Ljava/lang/String;)Ljava/lang/StringBuilder;
      21: aload_0
      22: getfield      #108                // Field interfaceName:Ljava/lang/String;
      25: invokevirtual #36                 // Method java/lang/StringBuilder.append:(Ljava/lang/String;)Ljava/lang/StringBuilder;
      28: invokevirtual #41                 // Method java/lang/StringBuilder.toString:()Ljava/lang/String;
      31: invokeinterface #105,  2          // InterfaceMethod java/util/List.add:(Ljava/lang/Object;)Z
      36: pop
      37: aload_1
      38: areturn

  public java.lang.String getUniqueServiceName();
    Code:
       0: aload_0
       1: getfield      #108                // Field interfaceName:Ljava/lang/String;
       4: ifnull        25
       7: aload_0
       8: getfield      #108                // Field interfaceName:Ljava/lang/String;
      11: aload_0
      12: invokevirtual #140                // Method getGroup:()Ljava/lang/String;
      15: aload_0
      16: invokevirtual #141                // Method getVersion:()Ljava/lang/String;
      19: invokestatic  #142                // Method org/apache/dubbo/common/URL.buildKey:(Ljava/lang/String;Ljava/lang/String;Ljava/lang/String;)Ljava/lang/String;
      22: goto          26
      25: aconst_null
      26: areturn

  public java.lang.String getGroup();
    Code:
       0: aload_0
       1: getfield      #143                // Field group:Ljava/lang/String;
       4: invokestatic  #50                 // Method org/apache/dubbo/common/utils/StringUtils.isEmpty:(Ljava/lang/String;)Z
       7: ifeq          34
      10: aload_0
      11: getfield      #15                 // Field provider:Lorg/apache/dubbo/config/ProviderConfig;
      14: ifnull        27
      17: aload_0
      18: getfield      #15                 // Field provider:Lorg/apache/dubbo/config/ProviderConfig;
      21: invokevirtual #144                // Method org/apache/dubbo/config/ProviderConfig.getGroup:()Ljava/lang/String;
      24: goto          38
      27: aload_0
      28: getfield      #143                // Field group:Ljava/lang/String;
      31: goto          38
      34: aload_0
      35: getfield      #143                // Field group:Ljava/lang/String;
      38: areturn

  public java.lang.String getVersion();
    Code:
       0: aload_0
       1: getfield      #145                // Field version:Ljava/lang/String;
       4: invokestatic  #50                 // Method org/apache/dubbo/common/utils/StringUtils.isEmpty:(Ljava/lang/String;)Z
       7: ifeq          34
      10: aload_0
      11: getfield      #15                 // Field provider:Lorg/apache/dubbo/config/ProviderConfig;
      14: ifnull        27
      17: aload_0
      18: getfield      #15                 // Field provider:Lorg/apache/dubbo/config/ProviderConfig;
      21: invokevirtual #146                // Method org/apache/dubbo/config/ProviderConfig.getVersion:()Ljava/lang/String;
      24: goto          38
      27: aload_0
      28: getfield      #145                // Field version:Ljava/lang/String;
      31: goto          38
      34: aload_0
      35: getfield      #145                // Field version:Ljava/lang/String;
      38: areturn

  protected void computeValidRegistryIds();
    Code:
       0: aload_0
       1: getfield      #15                 // Field provider:Lorg/apache/dubbo/config/ProviderConfig;
       4: ifnull        36
       7: aload_0
       8: invokevirtual #147                // Method notHasSelfRegistryProperty:()Z
      11: ifeq          36
      14: aload_0
      15: aload_0
      16: getfield      #15                 // Field provider:Lorg/apache/dubbo/config/ProviderConfig;
      19: invokevirtual #148                // Method org/apache/dubbo/config/ProviderConfig.getRegistries:()Ljava/util/List;
      22: invokevirtual #149                // Method setRegistries:(Ljava/util/List;)V
      25: aload_0
      26: aload_0
      27: getfield      #15                 // Field provider:Lorg/apache/dubbo/config/ProviderConfig;
      30: invokevirtual #150                // Method org/apache/dubbo/config/ProviderConfig.getRegistryIds:()Ljava/lang/String;
      33: invokevirtual #151                // Method setRegistryIds:(Ljava/lang/String;)V
      36: aload_0
      37: invokespecial #152                // Method org/apache/dubbo/config/AbstractServiceConfig.computeValidRegistryIds:()V
      40: return

  public java.lang.Boolean shouldExportAsync();
    Code:
       0: aload_0
       1: invokevirtual #153                // Method getExportAsync:()Ljava/lang/Boolean;
       4: astore_1
       5: aload_1
       6: ifnonnull     48
       9: aload_0
      10: getfield      #15                 // Field provider:Lorg/apache/dubbo/config/ProviderConfig;
      13: ifnull        43
      16: aload_0
      17: getfield      #15                 // Field provider:Lorg/apache/dubbo/config/ProviderConfig;
      20: invokevirtual #154                // Method org/apache/dubbo/config/ProviderConfig.getExportAsync:()Ljava/lang/Boolean;
      23: ifnull        43
      26: aload_0
      27: getfield      #15                 // Field provider:Lorg/apache/dubbo/config/ProviderConfig;
      30: invokevirtual #154                // Method org/apache/dubbo/config/ProviderConfig.getExportAsync:()Ljava/lang/Boolean;
      33: invokevirtual #20                 // Method java/lang/Boolean.booleanValue:()Z
      36: ifeq          43
      39: iconst_1
      40: goto          44
      43: iconst_0
      44: invokestatic  #155                // Method java/lang/Boolean.valueOf:(Z)Ljava/lang/Boolean;
      47: astore_1
      48: aload_1
      49: areturn

  public abstract void export();

  public abstract void unexport();

  public abstract boolean isExported();

  public abstract boolean isUnexported();

  private java.lang.IllegalStateException lambda$convertProviderIdToProvider$1();
    Code:
       0: new           #28                 // class java/lang/IllegalStateException
       3: dup
       4: new           #33                 // class java/lang/StringBuilder
       7: dup
       8: invokespecial #34                 // Method java/lang/StringBuilder."<init>":()V
      11: ldc           #156                // String Provider config not found:
      13: invokevirtual #36                 // Method java/lang/StringBuilder.append:(Ljava/lang/String;)Ljava/lang/StringBuilder;
      16: aload_0
      17: getfield      #83                 // Field providerIds:Ljava/lang/String;
      20: invokevirtual #36                 // Method java/lang/StringBuilder.append:(Ljava/lang/String;)Ljava/lang/StringBuilder;
      23: invokevirtual #41                 // Method java/lang/StringBuilder.toString:()Ljava/lang/String;
      26: invokespecial #30                 // Method java/lang/IllegalStateException."<init>":(Ljava/lang/String;)V
      29: areturn

  private static java.lang.IllegalStateException lambda$preProcessRefresh$0();
    Code:
       0: new           #28                 // class java/lang/IllegalStateException
       3: dup
       4: ldc           #157                // String Default provider is not initialized
       6: invokespecial #30                 // Method java/lang/IllegalStateException."<init>":(Ljava/lang/String;)V
       9: areturn
}
