Compiled from "SslConfig.java"
public class org.apache.dubbo.config.SslConfig extends org.apache.dubbo.config.AbstractConfig {
  private static final org.apache.dubbo.common.logger.Logger logger;

  public static final java.lang.String SERVER_KEY_CERT_CHAIN_PATH;

  public static final java.lang.String SERVER_PRIVATE_KEY_PATH;

  public static final java.lang.String SERVER_KEY_PASSWORD;

  public static final java.lang.String SERVER_TRUST_CERT_COLLECTION_PATH;

  public static final java.lang.String CLIENT_KEY_CERT_CHAIN_PATH;

  public static final java.lang.String CLIENT_PRIVATE_KEY_PATH;

  public static final java.lang.String CLIENT_KEY_PASSWORD;

  public static final java.lang.String CLIENT_TRUST_CERT_COLLECTION_PATH;

  private java.lang.String serverKeyCertChainPath;

  private java.lang.String serverPrivateKeyPath;

  private java.lang.String serverKeyPassword;

  private java.lang.String serverTrustCertCollectionPath;

  private java.lang.String clientKeyCertChainPath;

  private java.lang.String clientPrivateKeyPath;

  private java.lang.String clientKeyPassword;

  private java.lang.String clientTrustCertCollectionPath;

  private java.io.InputStream serverKeyCertChainPathStream;

  private java.io.InputStream serverPrivateKeyPathStream;

  private java.io.InputStream serverTrustCertCollectionPathStream;

  private java.io.InputStream clientKeyCertChainPathStream;

  private java.io.InputStream clientPrivateKeyPathStream;

  private java.io.InputStream clientTrustCertCollectionPathStream;

  private java.lang.String caAddress;

  private java.lang.String envType;

  private java.lang.String caCertPath;

  private java.lang.String oidcTokenPath;

  public org.apache.dubbo.config.SslConfig();
    Code:
       0: aload_0
       1: invokespecial #1                  // Method org/apache/dubbo/config/AbstractConfig."<init>":()V
       4: return

  public org.apache.dubbo.config.SslConfig(org.apache.dubbo.rpc.model.ApplicationModel);
    Code:
       0: aload_0
       1: aload_1
       2: invokespecial #2                  // Method org/apache/dubbo/config/AbstractConfig."<init>":(Lorg/apache/dubbo/rpc/model/ScopeModel;)V
       5: return

  public java.lang.String getServerKeyCertChainPath();
    Code:
       0: aload_0
       1: getfield      #3                  // Field serverKeyCertChainPath:Ljava/lang/String;
       4: areturn

  public void setServerKeyCertChainPath(java.lang.String);
    Code:
       0: aload_0
       1: aload_1
       2: putfield      #3                  // Field serverKeyCertChainPath:Ljava/lang/String;
       5: return

  public java.lang.String getServerPrivateKeyPath();
    Code:
       0: aload_0
       1: getfield      #4                  // Field serverPrivateKeyPath:Ljava/lang/String;
       4: areturn

  public void setServerPrivateKeyPath(java.lang.String);
    Code:
       0: aload_0
       1: aload_1
       2: putfield      #4                  // Field serverPrivateKeyPath:Ljava/lang/String;
       5: return

  public java.lang.String getServerKeyPassword();
    Code:
       0: aload_0
       1: getfield      #5                  // Field serverKeyPassword:Ljava/lang/String;
       4: areturn

  public void setServerKeyPassword(java.lang.String);
    Code:
       0: aload_0
       1: aload_1
       2: putfield      #5                  // Field serverKeyPassword:Ljava/lang/String;
       5: return

  public java.lang.String getServerTrustCertCollectionPath();
    Code:
       0: aload_0
       1: getfield      #6                  // Field serverTrustCertCollectionPath:Ljava/lang/String;
       4: areturn

  public void setServerTrustCertCollectionPath(java.lang.String);
    Code:
       0: aload_0
       1: aload_1
       2: putfield      #6                  // Field serverTrustCertCollectionPath:Ljava/lang/String;
       5: return

  public java.lang.String getClientKeyCertChainPath();
    Code:
       0: aload_0
       1: getfield      #7                  // Field clientKeyCertChainPath:Ljava/lang/String;
       4: areturn

  public void setClientKeyCertChainPath(java.lang.String);
    Code:
       0: aload_0
       1: aload_1
       2: putfield      #7                  // Field clientKeyCertChainPath:Ljava/lang/String;
       5: return

  public java.lang.String getClientPrivateKeyPath();
    Code:
       0: aload_0
       1: getfield      #8                  // Field clientPrivateKeyPath:Ljava/lang/String;
       4: areturn

  public void setClientPrivateKeyPath(java.lang.String);
    Code:
       0: aload_0
       1: aload_1
       2: putfield      #8                  // Field clientPrivateKeyPath:Ljava/lang/String;
       5: return

  public java.lang.String getClientKeyPassword();
    Code:
       0: aload_0
       1: getfield      #9                  // Field clientKeyPassword:Ljava/lang/String;
       4: areturn

  public void setClientKeyPassword(java.lang.String);
    Code:
       0: aload_0
       1: aload_1
       2: putfield      #9                  // Field clientKeyPassword:Ljava/lang/String;
       5: return

  public java.lang.String getClientTrustCertCollectionPath();
    Code:
       0: aload_0
       1: getfield      #10                 // Field clientTrustCertCollectionPath:Ljava/lang/String;
       4: areturn

  public void setClientTrustCertCollectionPath(java.lang.String);
    Code:
       0: aload_0
       1: aload_1
       2: putfield      #10                 // Field clientTrustCertCollectionPath:Ljava/lang/String;
       5: return

  public java.lang.String getCaAddress();
    Code:
       0: aload_0
       1: getfield      #11                 // Field caAddress:Ljava/lang/String;
       4: areturn

  public void setCaAddress(java.lang.String);
    Code:
       0: aload_0
       1: aload_1
       2: putfield      #11                 // Field caAddress:Ljava/lang/String;
       5: return

  public java.lang.String getEnvType();
    Code:
       0: aload_0
       1: getfield      #12                 // Field envType:Ljava/lang/String;
       4: areturn

  public void setEnvType(java.lang.String);
    Code:
       0: aload_0
       1: aload_1
       2: putfield      #12                 // Field envType:Ljava/lang/String;
       5: return

  public java.lang.String getCaCertPath();
    Code:
       0: aload_0
       1: getfield      #13                 // Field caCertPath:Ljava/lang/String;
       4: areturn

  public void setCaCertPath(java.lang.String);
    Code:
       0: aload_0
       1: aload_1
       2: putfield      #13                 // Field caCertPath:Ljava/lang/String;
       5: return

  public java.lang.String getOidcTokenPath();
    Code:
       0: aload_0
       1: getfield      #14                 // Field oidcTokenPath:Ljava/lang/String;
       4: areturn

  public void setOidcTokenPath(java.lang.String);
    Code:
       0: aload_0
       1: aload_1
       2: putfield      #14                 // Field oidcTokenPath:Ljava/lang/String;
       5: return

  public java.io.InputStream getServerKeyCertChainPathStream() throws java.io.IOException;
    Code:
       0: aload_0
       1: getfield      #3                  // Field serverKeyCertChainPath:Ljava/lang/String;
       4: ifnull        21
       7: aload_0
       8: aload_0
       9: getfield      #3                  // Field serverKeyCertChainPath:Ljava/lang/String;
      12: invokestatic  #15                 // Method org/apache/dubbo/common/utils/IOUtils.getURL:(Ljava/lang/String;)Ljava/net/URL;
      15: invokevirtual #16                 // Method java/net/URL.openStream:()Ljava/io/InputStream;
      18: putfield      #17                 // Field serverKeyCertChainPathStream:Ljava/io/InputStream;
      21: aload_0
      22: getfield      #17                 // Field serverKeyCertChainPathStream:Ljava/io/InputStream;
      25: areturn

  public void setServerKeyCertChainPathStream(java.io.InputStream);
    Code:
       0: aload_0
       1: aload_1
       2: putfield      #17                 // Field serverKeyCertChainPathStream:Ljava/io/InputStream;
       5: return

  public java.io.InputStream getServerPrivateKeyPathStream() throws java.io.IOException;
    Code:
       0: aload_0
       1: getfield      #4                  // Field serverPrivateKeyPath:Ljava/lang/String;
       4: ifnull        21
       7: aload_0
       8: aload_0
       9: getfield      #4                  // Field serverPrivateKeyPath:Ljava/lang/String;
      12: invokestatic  #15                 // Method org/apache/dubbo/common/utils/IOUtils.getURL:(Ljava/lang/String;)Ljava/net/URL;
      15: invokevirtual #16                 // Method java/net/URL.openStream:()Ljava/io/InputStream;
      18: putfield      #18                 // Field serverPrivateKeyPathStream:Ljava/io/InputStream;
      21: aload_0
      22: getfield      #18                 // Field serverPrivateKeyPathStream:Ljava/io/InputStream;
      25: areturn

  public void setServerPrivateKeyPathStream(java.io.InputStream);
    Code:
       0: aload_0
       1: aload_1
       2: putfield      #18                 // Field serverPrivateKeyPathStream:Ljava/io/InputStream;
       5: return

  public java.io.InputStream getServerTrustCertCollectionPathStream() throws java.io.IOException;
    Code:
       0: aload_0
       1: getfield      #6                  // Field serverTrustCertCollectionPath:Ljava/lang/String;
       4: ifnull        21
       7: aload_0
       8: aload_0
       9: getfield      #6                  // Field serverTrustCertCollectionPath:Ljava/lang/String;
      12: invokestatic  #15                 // Method org/apache/dubbo/common/utils/IOUtils.getURL:(Ljava/lang/String;)Ljava/net/URL;
      15: invokevirtual #16                 // Method java/net/URL.openStream:()Ljava/io/InputStream;
      18: putfield      #19                 // Field serverTrustCertCollectionPathStream:Ljava/io/InputStream;
      21: aload_0
      22: getfield      #19                 // Field serverTrustCertCollectionPathStream:Ljava/io/InputStream;
      25: areturn

  public void setServerTrustCertCollectionPathStream(java.io.InputStream);
    Code:
       0: aload_0
       1: aload_1
       2: putfield      #19                 // Field serverTrustCertCollectionPathStream:Ljava/io/InputStream;
       5: return

  public java.io.InputStream getClientKeyCertChainPathStream() throws java.io.IOException;
    Code:
       0: aload_0
       1: getfield      #7                  // Field clientKeyCertChainPath:Ljava/lang/String;
       4: ifnull        21
       7: aload_0
       8: aload_0
       9: getfield      #7                  // Field clientKeyCertChainPath:Ljava/lang/String;
      12: invokestatic  #15                 // Method org/apache/dubbo/common/utils/IOUtils.getURL:(Ljava/lang/String;)Ljava/net/URL;
      15: invokevirtual #16                 // Method java/net/URL.openStream:()Ljava/io/InputStream;
      18: putfield      #20                 // Field clientKeyCertChainPathStream:Ljava/io/InputStream;
      21: aload_0
      22: getfield      #20                 // Field clientKeyCertChainPathStream:Ljava/io/InputStream;
      25: areturn

  public void setClientKeyCertChainPathStream(java.io.InputStream);
    Code:
       0: aload_0
       1: aload_1
       2: putfield      #20                 // Field clientKeyCertChainPathStream:Ljava/io/InputStream;
       5: return

  public java.io.InputStream getClientPrivateKeyPathStream() throws java.io.IOException;
    Code:
       0: aload_0
       1: getfield      #8                  // Field clientPrivateKeyPath:Ljava/lang/String;
       4: ifnull        21
       7: aload_0
       8: aload_0
       9: getfield      #8                  // Field clientPrivateKeyPath:Ljava/lang/String;
      12: invokestatic  #15                 // Method org/apache/dubbo/common/utils/IOUtils.getURL:(Ljava/lang/String;)Ljava/net/URL;
      15: invokevirtual #16                 // Method java/net/URL.openStream:()Ljava/io/InputStream;
      18: putfield      #21                 // Field clientPrivateKeyPathStream:Ljava/io/InputStream;
      21: aload_0
      22: getfield      #21                 // Field clientPrivateKeyPathStream:Ljava/io/InputStream;
      25: areturn

  public void setClientPrivateKeyPathStream(java.io.InputStream);
    Code:
       0: aload_0
       1: aload_1
       2: putfield      #21                 // Field clientPrivateKeyPathStream:Ljava/io/InputStream;
       5: return

  public java.io.InputStream getClientTrustCertCollectionPathStream() throws java.io.IOException;
    Code:
       0: aload_0
       1: getfield      #10                 // Field clientTrustCertCollectionPath:Ljava/lang/String;
       4: ifnull        21
       7: aload_0
       8: aload_0
       9: getfield      #10                 // Field clientTrustCertCollectionPath:Ljava/lang/String;
      12: invokestatic  #15                 // Method org/apache/dubbo/common/utils/IOUtils.getURL:(Ljava/lang/String;)Ljava/net/URL;
      15: invokevirtual #16                 // Method java/net/URL.openStream:()Ljava/io/InputStream;
      18: putfield      #22                 // Field clientTrustCertCollectionPathStream:Ljava/io/InputStream;
      21: aload_0
      22: getfield      #22                 // Field clientTrustCertCollectionPathStream:Ljava/io/InputStream;
      25: areturn

  public void setClientTrustCertCollectionPathStream(java.io.InputStream);
    Code:
       0: aload_0
       1: aload_1
       2: putfield      #22                 // Field clientTrustCertCollectionPathStream:Ljava/io/InputStream;
       5: return

  static {};
    Code:
       0: ldc           #23                 // class org/apache/dubbo/config/SslConfig
       2: invokestatic  #24                 // Method org/apache/dubbo/common/logger/LoggerFactory.getLogger:(Ljava/lang/Class;)Lorg/apache/dubbo/common/logger/Logger;
       5: putstatic     #25                 // Field logger:Lorg/apache/dubbo/common/logger/Logger;
       8: return
}
