Compiled from "TracingConfig.java"
public class org.apache.dubbo.config.TracingConfig extends org.apache.dubbo.config.AbstractConfig {
  private static final long serialVersionUID;

  private java.lang.Boolean enabled;

  private org.apache.dubbo.config.nested.SamplingConfig sampling;

  private org.apache.dubbo.config.nested.BaggageConfig baggage;

  private org.apache.dubbo.config.nested.PropagationConfig propagation;

  private org.apache.dubbo.config.nested.ExporterConfig tracingExporter;

  public org.apache.dubbo.config.TracingConfig();
    Code:
       0: aload_0
       1: invokespecial #1                  // Method org/apache/dubbo/config/AbstractConfig."<init>":()V
       4: aload_0
       5: iconst_0
       6: invokestatic  #2                  // Method java/lang/Boolean.valueOf:(Z)Ljava/lang/Boolean;
       9: putfield      #3                  // Field enabled:Ljava/lang/Boolean;
      12: aload_0
      13: new           #4                  // class org/apache/dubbo/config/nested/SamplingConfig
      16: dup
      17: invokespecial #5                  // Method org/apache/dubbo/config/nested/SamplingConfig."<init>":()V
      20: putfield      #6                  // Field sampling:Lorg/apache/dubbo/config/nested/SamplingConfig;
      23: aload_0
      24: new           #7                  // class org/apache/dubbo/config/nested/BaggageConfig
      27: dup
      28: invokespecial #8                  // Method org/apache/dubbo/config/nested/BaggageConfig."<init>":()V
      31: putfield      #9                  // Field baggage:Lorg/apache/dubbo/config/nested/BaggageConfig;
      34: aload_0
      35: new           #10                 // class org/apache/dubbo/config/nested/PropagationConfig
      38: dup
      39: invokespecial #11                 // Method org/apache/dubbo/config/nested/PropagationConfig."<init>":()V
      42: putfield      #12                 // Field propagation:Lorg/apache/dubbo/config/nested/PropagationConfig;
      45: aload_0
      46: new           #13                 // class org/apache/dubbo/config/nested/ExporterConfig
      49: dup
      50: invokespecial #14                 // Method org/apache/dubbo/config/nested/ExporterConfig."<init>":()V
      53: putfield      #15                 // Field tracingExporter:Lorg/apache/dubbo/config/nested/ExporterConfig;
      56: return

  public org.apache.dubbo.config.TracingConfig(org.apache.dubbo.rpc.model.ApplicationModel);
    Code:
       0: aload_0
       1: aload_1
       2: invokespecial #16                 // Method org/apache/dubbo/config/AbstractConfig."<init>":(Lorg/apache/dubbo/rpc/model/ScopeModel;)V
       5: aload_0
       6: iconst_0
       7: invokestatic  #2                  // Method java/lang/Boolean.valueOf:(Z)Ljava/lang/Boolean;
      10: putfield      #3                  // Field enabled:Ljava/lang/Boolean;
      13: aload_0
      14: new           #4                  // class org/apache/dubbo/config/nested/SamplingConfig
      17: dup
      18: invokespecial #5                  // Method org/apache/dubbo/config/nested/SamplingConfig."<init>":()V
      21: putfield      #6                  // Field sampling:Lorg/apache/dubbo/config/nested/SamplingConfig;
      24: aload_0
      25: new           #7                  // class org/apache/dubbo/config/nested/BaggageConfig
      28: dup
      29: invokespecial #8                  // Method org/apache/dubbo/config/nested/BaggageConfig."<init>":()V
      32: putfield      #9                  // Field baggage:Lorg/apache/dubbo/config/nested/BaggageConfig;
      35: aload_0
      36: new           #10                 // class org/apache/dubbo/config/nested/PropagationConfig
      39: dup
      40: invokespecial #11                 // Method org/apache/dubbo/config/nested/PropagationConfig."<init>":()V
      43: putfield      #12                 // Field propagation:Lorg/apache/dubbo/config/nested/PropagationConfig;
      46: aload_0
      47: new           #13                 // class org/apache/dubbo/config/nested/ExporterConfig
      50: dup
      51: invokespecial #14                 // Method org/apache/dubbo/config/nested/ExporterConfig."<init>":()V
      54: putfield      #15                 // Field tracingExporter:Lorg/apache/dubbo/config/nested/ExporterConfig;
      57: return

  public java.lang.Boolean getEnabled();
    Code:
       0: aload_0
       1: getfield      #3                  // Field enabled:Ljava/lang/Boolean;
       4: areturn

  public void setEnabled(java.lang.Boolean);
    Code:
       0: aload_0
       1: aload_1
       2: putfield      #3                  // Field enabled:Ljava/lang/Boolean;
       5: return

  public org.apache.dubbo.config.nested.SamplingConfig getSampling();
    Code:
       0: aload_0
       1: getfield      #6                  // Field sampling:Lorg/apache/dubbo/config/nested/SamplingConfig;
       4: areturn

  public void setSampling(org.apache.dubbo.config.nested.SamplingConfig);
    Code:
       0: aload_0
       1: aload_1
       2: putfield      #6                  // Field sampling:Lorg/apache/dubbo/config/nested/SamplingConfig;
       5: return

  public org.apache.dubbo.config.nested.BaggageConfig getBaggage();
    Code:
       0: aload_0
       1: getfield      #9                  // Field baggage:Lorg/apache/dubbo/config/nested/BaggageConfig;
       4: areturn

  public void setBaggage(org.apache.dubbo.config.nested.BaggageConfig);
    Code:
       0: aload_0
       1: aload_1
       2: putfield      #9                  // Field baggage:Lorg/apache/dubbo/config/nested/BaggageConfig;
       5: return

  public org.apache.dubbo.config.nested.PropagationConfig getPropagation();
    Code:
       0: aload_0
       1: getfield      #12                 // Field propagation:Lorg/apache/dubbo/config/nested/PropagationConfig;
       4: areturn

  public void setPropagation(org.apache.dubbo.config.nested.PropagationConfig);
    Code:
       0: aload_0
       1: aload_1
       2: putfield      #12                 // Field propagation:Lorg/apache/dubbo/config/nested/PropagationConfig;
       5: return

  public org.apache.dubbo.config.nested.ExporterConfig getTracingExporter();
    Code:
       0: aload_0
       1: getfield      #15                 // Field tracingExporter:Lorg/apache/dubbo/config/nested/ExporterConfig;
       4: areturn

  public void setTracingExporter(org.apache.dubbo.config.nested.ExporterConfig);
    Code:
       0: aload_0
       1: aload_1
       2: putfield      #15                 // Field tracingExporter:Lorg/apache/dubbo/config/nested/ExporterConfig;
       5: return
}
