Compiled from "EnvironmentAdapter.java"
public class org.apache.dubbo.common.infra.support.EnvironmentAdapter implements org.apache.dubbo.common.infra.InfraAdapter,org.apache.dubbo.rpc.model.ScopeModelAware {
  private org.apache.dubbo.rpc.model.ApplicationModel applicationModel;

  public org.apache.dubbo.common.infra.support.EnvironmentAdapter();
    Code:
       0: aload_0
       1: invokespecial #2                  // Method java/lang/Object."<init>":()V
       4: return

  public void setApplicationModel(org.apache.dubbo.rpc.model.ApplicationModel);
    Code:
       0: aload_0
       1: aload_1
       2: putfield      #3                  // Field applicationModel:Lorg/apache/dubbo/rpc/model/ApplicationModel;
       5: return

  public java.util.Map<java.lang.String, java.lang.String> getExtraAttributes(java.util.Map<java.lang.String, java.lang.String>);
    Code:
       0: new           #4                  // class java/util/HashMap
       3: dup
       4: invokespecial #5                  // Method java/util/HashMap."<init>":()V
       7: astore_2
       8: aload_0
       9: getfield      #3                  // Field applicationModel:Lorg/apache/dubbo/rpc/model/ApplicationModel;
      12: ldc           #6                  // String dubbo.labels
      14: invokestatic  #7                  // Method org/apache/dubbo/common/config/ConfigurationUtils.getProperty:(Lorg/apache/dubbo/rpc/model/ScopeModel;Ljava/lang/String;)Ljava/lang/String;
      17: astore_3
      18: aload_3
      19: invokestatic  #8                  // Method org/apache/dubbo/common/utils/StringUtils.isNotEmpty:(Ljava/lang/String;)Z
      22: ifeq          98
      25: getstatic     #9                  // Field org/apache/dubbo/common/constants/CommonConstants.SEMICOLON_SPLIT_PATTERN:Ljava/util/regex/Pattern;
      28: aload_3
      29: invokevirtual #10                 // Method java/util/regex/Pattern.split:(Ljava/lang/CharSequence;)[Ljava/lang/String;
      32: astore        4
      34: aload         4
      36: astore        5
      38: aload         5
      40: arraylength
      41: istore        6
      43: iconst_0
      44: istore        7
      46: iload         7
      48: iload         6
      50: if_icmpge     98
      53: aload         5
      55: iload         7
      57: aaload
      58: astore        8
      60: getstatic     #11                 // Field org/apache/dubbo/common/constants/CommonConstants.EQUAL_SPLIT_PATTERN:Ljava/util/regex/Pattern;
      63: aload         8
      65: invokevirtual #10                 // Method java/util/regex/Pattern.split:(Ljava/lang/CharSequence;)[Ljava/lang/String;
      68: astore        9
      70: aload         9
      72: arraylength
      73: iconst_2
      74: if_icmpne     92
      77: aload_2
      78: aload         9
      80: iconst_0
      81: aaload
      82: aload         9
      84: iconst_1
      85: aaload
      86: invokeinterface #12,  3           // InterfaceMethod java/util/Map.put:(Ljava/lang/Object;Ljava/lang/Object;)Ljava/lang/Object;
      91: pop
      92: iinc          7, 1
      95: goto          46
      98: aload_0
      99: getfield      #3                  // Field applicationModel:Lorg/apache/dubbo/rpc/model/ApplicationModel;
     102: ldc           #13                 // String dubbo.env.keys
     104: invokestatic  #7                  // Method org/apache/dubbo/common/config/ConfigurationUtils.getProperty:(Lorg/apache/dubbo/rpc/model/ScopeModel;Ljava/lang/String;)Ljava/lang/String;
     107: astore        4
     109: aload         4
     111: invokestatic  #8                  // Method org/apache/dubbo/common/utils/StringUtils.isNotEmpty:(Ljava/lang/String;)Z
     114: ifeq          200
     117: getstatic     #14                 // Field org/apache/dubbo/common/constants/CommonConstants.COMMA_SPLIT_PATTERN:Ljava/util/regex/Pattern;
     120: aload         4
     122: invokevirtual #10                 // Method java/util/regex/Pattern.split:(Ljava/lang/CharSequence;)[Ljava/lang/String;
     125: astore        5
     127: aload         5
     129: astore        6
     131: aload         6
     133: arraylength
     134: istore        7
     136: iconst_0
     137: istore        8
     139: iload         8
     141: iload         7
     143: if_icmpge     200
     146: aload         6
     148: iload         8
     150: aaload
     151: astore        9
     153: aload_0
     154: getfield      #3                  // Field applicationModel:Lorg/apache/dubbo/rpc/model/ApplicationModel;
     157: aload         9
     159: invokestatic  #7                  // Method org/apache/dubbo/common/config/ConfigurationUtils.getProperty:(Lorg/apache/dubbo/rpc/model/ScopeModel;Ljava/lang/String;)Ljava/lang/String;
     162: astore        10
     164: aload         10
     166: ifnull        194
     169: aload_2
     170: aload         9
     172: invokevirtual #15                 // Method java/lang/String.toLowerCase:()Ljava/lang/String;
     175: aload         10
     177: invokeinterface #12,  3           // InterfaceMethod java/util/Map.put:(Ljava/lang/Object;Ljava/lang/Object;)Ljava/lang/Object;
     182: pop
     183: aload_2
     184: aload         9
     186: aload         10
     188: invokeinterface #12,  3           // InterfaceMethod java/util/Map.put:(Ljava/lang/Object;Ljava/lang/Object;)Ljava/lang/Object;
     193: pop
     194: iinc          8, 1
     197: goto          139
     200: aload_2
     201: areturn

  public java.lang.String getAttribute(java.lang.String);
    Code:
       0: aload_0
       1: getfield      #3                  // Field applicationModel:Lorg/apache/dubbo/rpc/model/ApplicationModel;
       4: aload_1
       5: invokestatic  #7                  // Method org/apache/dubbo/common/config/ConfigurationUtils.getProperty:(Lorg/apache/dubbo/rpc/model/ScopeModel;Ljava/lang/String;)Ljava/lang/String;
       8: areturn
}
