Compiled from "AztecWriter.java"
public final class com.google.zxing.aztec.AztecWriter implements com.google.zxing.Writer {
  public com.google.zxing.aztec.AztecWriter();
    Code:
       0: aload_0
       1: invokespecial #1                  // Method java/lang/Object."<init>":()V
       4: return

  public com.google.zxing.common.BitMatrix encode(java.lang.String, com.google.zxing.BarcodeFormat, int, int);
    Code:
       0: aload_0
       1: aload_1
       2: aload_2
       3: iload_3
       4: iload         4
       6: aconst_null
       7: invokevirtual #2                  // Method encode:(Ljava/lang/String;Lcom/google/zxing/BarcodeFormat;IILjava/util/Map;)Lcom/google/zxing/common/BitMatrix;
      10: areturn

  public com.google.zxing.common.BitMatrix encode(java.lang.String, com.google.zxing.BarcodeFormat, int, int, java.util.Map<com.google.zxing.EncodeHintType, ?>);
    Code:
       0: aconst_null
       1: astore        6
       3: bipush        33
       5: istore        7
       7: iconst_0
       8: istore        8
      10: aload         5
      12: ifnull        108
      15: aload         5
      17: getstatic     #4                  // Field com/google/zxing/EncodeHintType.CHARACTER_SET:Lcom/google/zxing/EncodeHintType;
      20: invokeinterface #5,  2            // InterfaceMethod java/util/Map.containsKey:(Ljava/lang/Object;)Z
      25: ifeq          46
      28: aload         5
      30: getstatic     #4                  // Field com/google/zxing/EncodeHintType.CHARACTER_SET:Lcom/google/zxing/EncodeHintType;
      33: invokeinterface #6,  2            // InterfaceMethod java/util/Map.get:(Ljava/lang/Object;)Ljava/lang/Object;
      38: invokevirtual #7                  // Method java/lang/Object.toString:()Ljava/lang/String;
      41: invokestatic  #8                  // Method java/nio/charset/Charset.forName:(Ljava/lang/String;)Ljava/nio/charset/Charset;
      44: astore        6
      46: aload         5
      48: getstatic     #9                  // Field com/google/zxing/EncodeHintType.ERROR_CORRECTION:Lcom/google/zxing/EncodeHintType;
      51: invokeinterface #5,  2            // InterfaceMethod java/util/Map.containsKey:(Ljava/lang/Object;)Z
      56: ifeq          77
      59: aload         5
      61: getstatic     #9                  // Field com/google/zxing/EncodeHintType.ERROR_CORRECTION:Lcom/google/zxing/EncodeHintType;
      64: invokeinterface #6,  2            // InterfaceMethod java/util/Map.get:(Ljava/lang/Object;)Ljava/lang/Object;
      69: invokevirtual #7                  // Method java/lang/Object.toString:()Ljava/lang/String;
      72: invokestatic  #10                 // Method java/lang/Integer.parseInt:(Ljava/lang/String;)I
      75: istore        7
      77: aload         5
      79: getstatic     #11                 // Field com/google/zxing/EncodeHintType.AZTEC_LAYERS:Lcom/google/zxing/EncodeHintType;
      82: invokeinterface #5,  2            // InterfaceMethod java/util/Map.containsKey:(Ljava/lang/Object;)Z
      87: ifeq          108
      90: aload         5
      92: getstatic     #11                 // Field com/google/zxing/EncodeHintType.AZTEC_LAYERS:Lcom/google/zxing/EncodeHintType;
      95: invokeinterface #6,  2            // InterfaceMethod java/util/Map.get:(Ljava/lang/Object;)Ljava/lang/Object;
     100: invokevirtual #7                  // Method java/lang/Object.toString:()Ljava/lang/String;
     103: invokestatic  #10                 // Method java/lang/Integer.parseInt:(Ljava/lang/String;)I
     106: istore        8
     108: aload_1
     109: aload_2
     110: iload_3
     111: iload         4
     113: aload         6
     115: iload         7
     117: iload         8
     119: invokestatic  #12                 // Method encode:(Ljava/lang/String;Lcom/google/zxing/BarcodeFormat;IILjava/nio/charset/Charset;II)Lcom/google/zxing/common/BitMatrix;
     122: areturn

  private static com.google.zxing.common.BitMatrix encode(java.lang.String, com.google.zxing.BarcodeFormat, int, int, java.nio.charset.Charset, int, int);
    Code:
       0: aload_1
       1: getstatic     #13                 // Field com/google/zxing/BarcodeFormat.AZTEC:Lcom/google/zxing/BarcodeFormat;
       4: if_acmpeq     34
       7: new           #14                 // class java/lang/IllegalArgumentException
      10: dup
      11: new           #15                 // class java/lang/StringBuilder
      14: dup
      15: invokespecial #16                 // Method java/lang/StringBuilder."<init>":()V
      18: ldc           #17                 // String Can only encode AZTEC, but got
      20: invokevirtual #18                 // Method java/lang/StringBuilder.append:(Ljava/lang/String;)Ljava/lang/StringBuilder;
      23: aload_1
      24: invokevirtual #19                 // Method java/lang/StringBuilder.append:(Ljava/lang/Object;)Ljava/lang/StringBuilder;
      27: invokevirtual #20                 // Method java/lang/StringBuilder.toString:()Ljava/lang/String;
      30: invokespecial #21                 // Method java/lang/IllegalArgumentException."<init>":(Ljava/lang/String;)V
      33: athrow
      34: aload_0
      35: iload         5
      37: iload         6
      39: aload         4
      41: invokestatic  #22                 // Method com/google/zxing/aztec/encoder/Encoder.encode:(Ljava/lang/String;IILjava/nio/charset/Charset;)Lcom/google/zxing/aztec/encoder/AztecCode;
      44: astore        7
      46: aload         7
      48: iload_2
      49: iload_3
      50: invokestatic  #23                 // Method renderResult:(Lcom/google/zxing/aztec/encoder/AztecCode;II)Lcom/google/zxing/common/BitMatrix;
      53: areturn

  private static com.google.zxing.common.BitMatrix renderResult(com.google.zxing.aztec.encoder.AztecCode, int, int);
    Code:
       0: aload_0
       1: invokevirtual #24                 // Method com/google/zxing/aztec/encoder/AztecCode.getMatrix:()Lcom/google/zxing/common/BitMatrix;
       4: astore_3
       5: aload_3
       6: ifnonnull     17
       9: new           #25                 // class java/lang/IllegalStateException
      12: dup
      13: invokespecial #26                 // Method java/lang/IllegalStateException."<init>":()V
      16: athrow
      17: aload_3
      18: invokevirtual #27                 // Method com/google/zxing/common/BitMatrix.getWidth:()I
      21: istore        4
      23: aload_3
      24: invokevirtual #28                 // Method com/google/zxing/common/BitMatrix.getHeight:()I
      27: istore        5
      29: iload_1
      30: iload         4
      32: invokestatic  #29                 // Method java/lang/Math.max:(II)I
      35: istore        6
      37: iload_2
      38: iload         5
      40: invokestatic  #29                 // Method java/lang/Math.max:(II)I
      43: istore        7
      45: iload         6
      47: iload         4
      49: idiv
      50: iload         7
      52: iload         5
      54: idiv
      55: invokestatic  #30                 // Method java/lang/Math.min:(II)I
      58: istore        8
      60: iload         6
      62: iload         4
      64: iload         8
      66: imul
      67: isub
      68: iconst_2
      69: idiv
      70: istore        9
      72: iload         7
      74: iload         5
      76: iload         8
      78: imul
      79: isub
      80: iconst_2
      81: idiv
      82: istore        10
      84: new           #31                 // class com/google/zxing/common/BitMatrix
      87: dup
      88: iload         6
      90: iload         7
      92: invokespecial #32                 // Method com/google/zxing/common/BitMatrix."<init>":(II)V
      95: astore        11
      97: iconst_0
      98: istore        12
     100: iload         10
     102: istore        13
     104: iload         12
     106: iload         5
     108: if_icmpge     175
     111: iconst_0
     112: istore        14
     114: iload         9
     116: istore        15
     118: iload         14
     120: iload         4
     122: if_icmpge     162
     125: aload_3
     126: iload         14
     128: iload         12
     130: invokevirtual #33                 // Method com/google/zxing/common/BitMatrix.get:(II)Z
     133: ifeq          149
     136: aload         11
     138: iload         15
     140: iload         13
     142: iload         8
     144: iload         8
     146: invokevirtual #34                 // Method com/google/zxing/common/BitMatrix.setRegion:(IIII)V
     149: iinc          14, 1
     152: iload         15
     154: iload         8
     156: iadd
     157: istore        15
     159: goto          118
     162: iinc          12, 1
     165: iload         13
     167: iload         8
     169: iadd
     170: istore        13
     172: goto          104
     175: aload         11
     177: areturn
}
