Compiled from "AztecDetectorResult.java"
public final class com.google.zxing.aztec.AztecDetectorResult extends com.google.zxing.common.DetectorResult {
  private final boolean compact;

  private final int nbDatablocks;

  private final int nbLayers;

  public com.google.zxing.aztec.AztecDetectorResult(com.google.zxing.common.BitMatrix, com.google.zxing.ResultPoint[], boolean, int, int);
    Code:
       0: aload_0
       1: aload_1
       2: aload_2
       3: invokespecial #1                  // Method com/google/zxing/common/DetectorResult."<init>":(Lcom/google/zxing/common/BitMatrix;[Lcom/google/zxing/ResultPoint;)V
       6: aload_0
       7: iload_3
       8: putfield      #2                  // Field compact:Z
      11: aload_0
      12: iload         4
      14: putfield      #3                  // Field nbDatablocks:I
      17: aload_0
      18: iload         5
      20: putfield      #4                  // Field nbLayers:I
      23: return

  public int getNbLayers();
    Code:
       0: aload_0
       1: getfield      #4                  // Field nbLayers:I
       4: ireturn

  public int getNbDatablocks();
    Code:
       0: aload_0
       1: getfield      #3                  // Field nbDatablocks:I
       4: ireturn

  public boolean isCompact();
    Code:
       0: aload_0
       1: getfield      #2                  // Field compact:Z
       4: ireturn
}
