Compiled from "AztecReader.java"
public final class com.google.zxing.aztec.AztecReader implements com.google.zxing.Reader {
  public com.google.zxing.aztec.AztecReader();
    Code:
       0: aload_0
       1: invokespecial #1                  // Method java/lang/Object."<init>":()V
       4: return

  public com.google.zxing.Result decode(com.google.zxing.BinaryBitmap) throws com.google.zxing.NotFoundException, com.google.zxing.FormatException;
    Code:
       0: aload_0
       1: aload_1
       2: aconst_null
       3: invokevirtual #2                  // Method decode:(Lcom/google/zxing/BinaryBitmap;Ljava/util/Map;)Lcom/google/zxing/Result;
       6: areturn

  public com.google.zxing.Result decode(com.google.zxing.BinaryBitmap, java.util.Map<com.google.zxing.DecodeHintType, ?>) throws com.google.zxing.NotFoundException, com.google.zxing.FormatException;
    Code:
       0: aconst_null
       1: astore_3
       2: aconst_null
       3: astore        4
       5: new           #3                  // class com/google/zxing/aztec/detector/Detector
       8: dup
       9: aload_1
      10: invokevirtual #4                  // Method com/google/zxing/BinaryBitmap.getBlackMatrix:()Lcom/google/zxing/common/BitMatrix;
      13: invokespecial #5                  // Method com/google/zxing/aztec/detector/Detector."<init>":(Lcom/google/zxing/common/BitMatrix;)V
      16: astore        5
      18: aconst_null
      19: astore        6
      21: aconst_null
      22: astore        7
      24: aload         5
      26: iconst_0
      27: invokevirtual #6                  // Method com/google/zxing/aztec/detector/Detector.detect:(Z)Lcom/google/zxing/aztec/AztecDetectorResult;
      30: astore        8
      32: aload         8
      34: invokevirtual #7                  // Method com/google/zxing/aztec/AztecDetectorResult.getPoints:()[Lcom/google/zxing/ResultPoint;
      37: astore        6
      39: new           #8                  // class com/google/zxing/aztec/decoder/Decoder
      42: dup
      43: invokespecial #9                  // Method com/google/zxing/aztec/decoder/Decoder."<init>":()V
      46: aload         8
      48: invokevirtual #10                 // Method com/google/zxing/aztec/decoder/Decoder.decode:(Lcom/google/zxing/aztec/AztecDetectorResult;)Lcom/google/zxing/common/DecoderResult;
      51: astore        7
      53: goto          70
      56: astore        8
      58: aload         8
      60: astore_3
      61: goto          70
      64: astore        8
      66: aload         8
      68: astore        4
      70: aload         7
      72: ifnonnull     126
      75: aload         5
      77: iconst_1
      78: invokevirtual #6                  // Method com/google/zxing/aztec/detector/Detector.detect:(Z)Lcom/google/zxing/aztec/AztecDetectorResult;
      81: astore        8
      83: aload         8
      85: invokevirtual #7                  // Method com/google/zxing/aztec/AztecDetectorResult.getPoints:()[Lcom/google/zxing/ResultPoint;
      88: astore        6
      90: new           #8                  // class com/google/zxing/aztec/decoder/Decoder
      93: dup
      94: invokespecial #9                  // Method com/google/zxing/aztec/decoder/Decoder."<init>":()V
      97: aload         8
      99: invokevirtual #10                 // Method com/google/zxing/aztec/decoder/Decoder.decode:(Lcom/google/zxing/aztec/AztecDetectorResult;)Lcom/google/zxing/common/DecoderResult;
     102: astore        7
     104: goto          126
     107: astore        8
     109: aload_3
     110: ifnull        115
     113: aload_3
     114: athrow
     115: aload         4
     117: ifnull        123
     120: aload         4
     122: athrow
     123: aload         8
     125: athrow
     126: aload_2
     127: ifnull        190
     130: aload_2
     131: getstatic     #13                 // Field com/google/zxing/DecodeHintType.NEED_RESULT_POINT_CALLBACK:Lcom/google/zxing/DecodeHintType;
     134: invokeinterface #14,  2           // InterfaceMethod java/util/Map.get:(Ljava/lang/Object;)Ljava/lang/Object;
     139: checkcast     #15                 // class com/google/zxing/ResultPointCallback
     142: astore        8
     144: aload         8
     146: ifnull        190
     149: aload         6
     151: astore        9
     153: aload         9
     155: arraylength
     156: istore        10
     158: iconst_0
     159: istore        11
     161: iload         11
     163: iload         10
     165: if_icmpge     190
     168: aload         9
     170: iload         11
     172: aaload
     173: astore        12
     175: aload         8
     177: aload         12
     179: invokeinterface #16,  2           // InterfaceMethod com/google/zxing/ResultPointCallback.foundPossibleResultPoint:(Lcom/google/zxing/ResultPoint;)V
     184: iinc          11, 1
     187: goto          161
     190: new           #17                 // class com/google/zxing/Result
     193: dup
     194: aload         7
     196: invokevirtual #18                 // Method com/google/zxing/common/DecoderResult.getText:()Ljava/lang/String;
     199: aload         7
     201: invokevirtual #19                 // Method com/google/zxing/common/DecoderResult.getRawBytes:()[B
     204: aload         7
     206: invokevirtual #20                 // Method com/google/zxing/common/DecoderResult.getNumBits:()I
     209: aload         6
     211: getstatic     #21                 // Field com/google/zxing/BarcodeFormat.AZTEC:Lcom/google/zxing/BarcodeFormat;
     214: invokestatic  #22                 // Method java/lang/System.currentTimeMillis:()J
     217: invokespecial #23                 // Method com/google/zxing/Result."<init>":(Ljava/lang/String;[BI[Lcom/google/zxing/ResultPoint;Lcom/google/zxing/BarcodeFormat;J)V
     220: astore        8
     222: aload         7
     224: invokevirtual #24                 // Method com/google/zxing/common/DecoderResult.getByteSegments:()Ljava/util/List;
     227: astore        9
     229: aload         9
     231: ifnull        244
     234: aload         8
     236: getstatic     #25                 // Field com/google/zxing/ResultMetadataType.BYTE_SEGMENTS:Lcom/google/zxing/ResultMetadataType;
     239: aload         9
     241: invokevirtual #26                 // Method com/google/zxing/Result.putMetadata:(Lcom/google/zxing/ResultMetadataType;Ljava/lang/Object;)V
     244: aload         7
     246: invokevirtual #27                 // Method com/google/zxing/common/DecoderResult.getECLevel:()Ljava/lang/String;
     249: astore        10
     251: aload         10
     253: ifnull        266
     256: aload         8
     258: getstatic     #28                 // Field com/google/zxing/ResultMetadataType.ERROR_CORRECTION_LEVEL:Lcom/google/zxing/ResultMetadataType;
     261: aload         10
     263: invokevirtual #26                 // Method com/google/zxing/Result.putMetadata:(Lcom/google/zxing/ResultMetadataType;Ljava/lang/Object;)V
     266: aload         8
     268: getstatic     #29                 // Field com/google/zxing/ResultMetadataType.SYMBOLOGY_IDENTIFIER:Lcom/google/zxing/ResultMetadataType;
     271: new           #30                 // class java/lang/StringBuilder
     274: dup
     275: invokespecial #31                 // Method java/lang/StringBuilder."<init>":()V
     278: ldc           #32                 // String ]z
     280: invokevirtual #33                 // Method java/lang/StringBuilder.append:(Ljava/lang/String;)Ljava/lang/StringBuilder;
     283: aload         7
     285: invokevirtual #34                 // Method com/google/zxing/common/DecoderResult.getSymbologyModifier:()I
     288: invokevirtual #35                 // Method java/lang/StringBuilder.append:(I)Ljava/lang/StringBuilder;
     291: invokevirtual #36                 // Method java/lang/StringBuilder.toString:()Ljava/lang/String;
     294: invokevirtual #26                 // Method com/google/zxing/Result.putMetadata:(Lcom/google/zxing/ResultMetadataType;Ljava/lang/Object;)V
     297: aload         8
     299: areturn
    Exception table:
       from    to  target type
          24    53    56   Class com/google/zxing/NotFoundException
          24    53    64   Class com/google/zxing/FormatException
          75   104   107   Class com/google/zxing/NotFoundException
          75   104   107   Class com/google/zxing/FormatException

  public void reset();
    Code:
       0: return
}
