Compiled from "AccessKeyAuthenticator.java"
public class org.apache.dubbo.auth.AccessKeyAuthenticator implements org.apache.dubbo.auth.spi.Authenticator {
  private final org.apache.dubbo.rpc.model.ApplicationModel applicationModel;

  public org.apache.dubbo.auth.AccessKeyAuthenticator(org.apache.dubbo.rpc.model.ApplicationModel);
    Code:
       0: aload_0
       1: invokespecial #1                  // Method java/lang/Object."<init>":()V
       4: aload_0
       5: aload_1
       6: putfield      #2                  // Field applicationModel:Lorg/apache/dubbo/rpc/model/ApplicationModel;
       9: return

  public void sign(org.apache.dubbo.rpc.Invocation, org.apache.dubbo.common.URL);
    Code:
       0: invokestatic  #3                  // Method java/lang/System.currentTimeMillis:()J
       3: invokestatic  #4                  // Method java/lang/String.valueOf:(J)Ljava/lang/String;
       6: astore_3
       7: aload_0
       8: aload_1
       9: aload_2
      10: invokevirtual #5                  // Method getAccessKeyPair:(Lorg/apache/dubbo/rpc/Invocation;Lorg/apache/dubbo/common/URL;)Lorg/apache/dubbo/auth/model/AccessKeyPair;
      13: astore        4
      15: aload_1
      16: ldc           #7                  // String signature
      18: aload_0
      19: aload_2
      20: aload_1
      21: aload         4
      23: invokevirtual #8                  // Method org/apache/dubbo/auth/model/AccessKeyPair.getSecretKey:()Ljava/lang/String;
      26: aload_3
      27: invokevirtual #9                  // Method getSignature:(Lorg/apache/dubbo/common/URL;Lorg/apache/dubbo/rpc/Invocation;Ljava/lang/String;Ljava/lang/String;)Ljava/lang/String;
      30: invokeinterface #10,  3           // InterfaceMethod org/apache/dubbo/rpc/Invocation.setAttachment:(Ljava/lang/String;Ljava/lang/String;)V
      35: aload_1
      36: ldc           #11                 // String timestamp
      38: aload_3
      39: invokeinterface #10,  3           // InterfaceMethod org/apache/dubbo/rpc/Invocation.setAttachment:(Ljava/lang/String;Ljava/lang/String;)V
      44: aload_1
      45: ldc           #12                 // String ak
      47: aload         4
      49: invokevirtual #13                 // Method org/apache/dubbo/auth/model/AccessKeyPair.getAccessKey:()Ljava/lang/String;
      52: invokeinterface #10,  3           // InterfaceMethod org/apache/dubbo/rpc/Invocation.setAttachment:(Ljava/lang/String;Ljava/lang/String;)V
      57: aload_1
      58: ldc           #15                 // String consumer
      60: aload_2
      61: invokevirtual #16                 // Method org/apache/dubbo/common/URL.getApplication:()Ljava/lang/String;
      64: invokeinterface #10,  3           // InterfaceMethod org/apache/dubbo/rpc/Invocation.setAttachment:(Ljava/lang/String;Ljava/lang/String;)V
      69: return

  public void authenticate(org.apache.dubbo.rpc.Invocation, org.apache.dubbo.common.URL) throws org.apache.dubbo.auth.exception.RpcAuthenticationException;
    Code:
       0: aload_1
       1: ldc           #12                 // String ak
       3: invokeinterface #17,  2           // InterfaceMethod org/apache/dubbo/rpc/Invocation.getAttachment:(Ljava/lang/String;)Ljava/lang/String;
       8: invokestatic  #18                 // Method java/lang/String.valueOf:(Ljava/lang/Object;)Ljava/lang/String;
      11: astore_3
      12: aload_1
      13: ldc           #11                 // String timestamp
      15: invokeinterface #17,  2           // InterfaceMethod org/apache/dubbo/rpc/Invocation.getAttachment:(Ljava/lang/String;)Ljava/lang/String;
      20: invokestatic  #18                 // Method java/lang/String.valueOf:(Ljava/lang/Object;)Ljava/lang/String;
      23: astore        4
      25: aload_1
      26: ldc           #7                  // String signature
      28: invokeinterface #17,  2           // InterfaceMethod org/apache/dubbo/rpc/Invocation.getAttachment:(Ljava/lang/String;)Ljava/lang/String;
      33: invokestatic  #18                 // Method java/lang/String.valueOf:(Ljava/lang/Object;)Ljava/lang/String;
      36: astore        5
      38: aload_1
      39: ldc           #15                 // String consumer
      41: invokeinterface #17,  2           // InterfaceMethod org/apache/dubbo/rpc/Invocation.getAttachment:(Ljava/lang/String;)Ljava/lang/String;
      46: invokestatic  #18                 // Method java/lang/String.valueOf:(Ljava/lang/Object;)Ljava/lang/String;
      49: astore        6
      51: iconst_4
      52: anewarray     #19                 // class java/lang/String
      55: dup
      56: iconst_0
      57: aload_3
      58: aastore
      59: dup
      60: iconst_1
      61: aload         6
      63: aastore
      64: dup
      65: iconst_2
      66: aload         4
      68: aastore
      69: dup
      70: iconst_3
      71: aload         5
      73: aastore
      74: invokestatic  #20                 // Method org/apache/dubbo/common/utils/StringUtils.isAnyEmpty:([Ljava/lang/String;)Z
      77: ifeq          90
      80: new           #21                 // class org/apache/dubbo/auth/exception/RpcAuthenticationException
      83: dup
      84: ldc           #22                 // String Failed to authenticate, maybe consumer side did not enable the auth
      86: invokespecial #23                 // Method org/apache/dubbo/auth/exception/RpcAuthenticationException."<init>":(Ljava/lang/String;)V
      89: athrow
      90: aload_0
      91: aload_1
      92: aload_2
      93: invokevirtual #5                  // Method getAccessKeyPair:(Lorg/apache/dubbo/rpc/Invocation;Lorg/apache/dubbo/common/URL;)Lorg/apache/dubbo/auth/model/AccessKeyPair;
      96: astore        7
      98: goto          115
     101: astore        8
     103: new           #21                 // class org/apache/dubbo/auth/exception/RpcAuthenticationException
     106: dup
     107: ldc           #25                 // String Failed to authenticate , can\'t load the accessKeyPair
     109: aload         8
     111: invokespecial #26                 // Method org/apache/dubbo/auth/exception/RpcAuthenticationException."<init>":(Ljava/lang/String;Ljava/lang/Throwable;)V
     114: athrow
     115: aload_0
     116: aload_2
     117: aload_1
     118: aload         7
     120: invokevirtual #8                  // Method org/apache/dubbo/auth/model/AccessKeyPair.getSecretKey:()Ljava/lang/String;
     123: aload         4
     125: invokevirtual #9                  // Method getSignature:(Lorg/apache/dubbo/common/URL;Lorg/apache/dubbo/rpc/Invocation;Ljava/lang/String;Ljava/lang/String;)Ljava/lang/String;
     128: astore        8
     130: aload         8
     132: aload         5
     134: invokevirtual #27                 // Method java/lang/String.equals:(Ljava/lang/Object;)Z
     137: istore        9
     139: iload         9
     141: ifne          154
     144: new           #21                 // class org/apache/dubbo/auth/exception/RpcAuthenticationException
     147: dup
     148: ldc           #28                 // String Failed to authenticate, signature is not correct
     150: invokespecial #23                 // Method org/apache/dubbo/auth/exception/RpcAuthenticationException."<init>":(Ljava/lang/String;)V
     153: athrow
     154: return
    Exception table:
       from    to  target type
          90    98   101   Class java/lang/Exception

  org.apache.dubbo.auth.model.AccessKeyPair getAccessKeyPair(org.apache.dubbo.rpc.Invocation, org.apache.dubbo.common.URL);
    Code:
       0: aload_0
       1: getfield      #2                  // Field applicationModel:Lorg/apache/dubbo/rpc/model/ApplicationModel;
       4: ldc           #29                 // class org/apache/dubbo/auth/spi/AccessKeyStorage
       6: invokevirtual #30                 // Method org/apache/dubbo/rpc/model/ApplicationModel.getExtensionLoader:(Ljava/lang/Class;)Lorg/apache/dubbo/common/extension/ExtensionLoader;
       9: aload_2
      10: ldc           #31                 // String accessKey.storage
      12: ldc           #32                 // String urlstorage
      14: invokevirtual #33                 // Method org/apache/dubbo/common/URL.getParameter:(Ljava/lang/String;Ljava/lang/String;)Ljava/lang/String;
      17: invokevirtual #34                 // Method org/apache/dubbo/common/extension/ExtensionLoader.getExtension:(Ljava/lang/String;)Ljava/lang/Object;
      20: checkcast     #29                 // class org/apache/dubbo/auth/spi/AccessKeyStorage
      23: astore_3
      24: aload_3
      25: aload_2
      26: aload_1
      27: invokeinterface #35,  3           // InterfaceMethod org/apache/dubbo/auth/spi/AccessKeyStorage.getAccessKey:(Lorg/apache/dubbo/common/URL;Lorg/apache/dubbo/rpc/Invocation;)Lorg/apache/dubbo/auth/model/AccessKeyPair;
      32: astore        4
      34: aload         4
      36: ifnull        65
      39: iconst_2
      40: anewarray     #19                 // class java/lang/String
      43: dup
      44: iconst_0
      45: aload         4
      47: invokevirtual #13                 // Method org/apache/dubbo/auth/model/AccessKeyPair.getAccessKey:()Ljava/lang/String;
      50: aastore
      51: dup
      52: iconst_1
      53: aload         4
      55: invokevirtual #8                  // Method org/apache/dubbo/auth/model/AccessKeyPair.getSecretKey:()Ljava/lang/String;
      58: aastore
      59: invokestatic  #20                 // Method org/apache/dubbo/common/utils/StringUtils.isAnyEmpty:([Ljava/lang/String;)Z
      62: ifeq          75
      65: new           #36                 // class org/apache/dubbo/auth/exception/AccessKeyNotFoundException
      68: dup
      69: ldc           #37                 // String AccessKeyId or secretAccessKey not found
      71: invokespecial #38                 // Method org/apache/dubbo/auth/exception/AccessKeyNotFoundException."<init>":(Ljava/lang/String;)V
      74: athrow
      75: goto          92
      78: astore        5
      80: new           #39                 // class java/lang/RuntimeException
      83: dup
      84: ldc           #40                 // String Can\'t load the AccessKeyPair from accessKeyStorage
      86: aload         5
      88: invokespecial #41                 // Method java/lang/RuntimeException."<init>":(Ljava/lang/String;Ljava/lang/Throwable;)V
      91: athrow
      92: aload         4
      94: areturn
    Exception table:
       from    to  target type
          24    75    78   Class java/lang/Exception

  java.lang.String getSignature(org.apache.dubbo.common.URL, org.apache.dubbo.rpc.Invocation, java.lang.String, java.lang.String);
    Code:
       0: ldc           #42                 // String %s#%s#%s#%s
       2: iconst_4
       3: anewarray     #43                 // class java/lang/Object
       6: dup
       7: iconst_0
       8: aload_1
       9: invokevirtual #44                 // Method org/apache/dubbo/common/URL.getColonSeparatedKey:()Ljava/lang/String;
      12: aastore
      13: dup
      14: iconst_1
      15: aload_2
      16: invokeinterface #45,  1           // InterfaceMethod org/apache/dubbo/rpc/Invocation.getMethodName:()Ljava/lang/String;
      21: aastore
      22: dup
      23: iconst_2
      24: aload_3
      25: aastore
      26: dup
      27: iconst_3
      28: aload         4
      30: aastore
      31: invokestatic  #46                 // Method java/lang/String.format:(Ljava/lang/String;[Ljava/lang/Object;)Ljava/lang/String;
      34: astore        5
      36: aload_1
      37: ldc           #47                 // String param.sign
      39: iconst_0
      40: invokevirtual #48                 // Method org/apache/dubbo/common/URL.getParameter:(Ljava/lang/String;Z)Z
      43: istore        6
      45: iload         6
      47: ifeq          63
      50: aload_2
      51: invokeinterface #49,  1           // InterfaceMethod org/apache/dubbo/rpc/Invocation.getArguments:()[Ljava/lang/Object;
      56: aload         5
      58: aload_3
      59: invokestatic  #50                 // Method org/apache/dubbo/auth/utils/SignatureUtils.sign:([Ljava/lang/Object;Ljava/lang/String;Ljava/lang/String;)Ljava/lang/String;
      62: areturn
      63: aload         5
      65: aload_3
      66: invokestatic  #51                 // Method org/apache/dubbo/auth/utils/SignatureUtils.sign:(Ljava/lang/String;Ljava/lang/String;)Ljava/lang/String;
      69: areturn
}
