Compiled from "DefaultAccessKeyStorage.java"
public class org.apache.dubbo.auth.DefaultAccessKeyStorage implements org.apache.dubbo.auth.spi.AccessKeyStorage {
  public org.apache.dubbo.auth.DefaultAccessKeyStorage();
    Code:
       0: aload_0
       1: invokespecial #1                  // Method java/lang/Object."<init>":()V
       4: return

  public org.apache.dubbo.auth.model.AccessKeyPair getAccessKey(org.apache.dubbo.common.URL, org.apache.dubbo.rpc.Invocation);
    Code:
       0: new           #2                  // class org/apache/dubbo/auth/model/AccessKeyPair
       3: dup
       4: invokespecial #3                  // Method org/apache/dubbo/auth/model/AccessKeyPair."<init>":()V
       7: astore_3
       8: aload_1
       9: ldc           #5                  // String .accessKeyId
      11: invokevirtual #6                  // Method org/apache/dubbo/common/URL.getParameter:(Ljava/lang/String;)Ljava/lang/String;
      14: astore        4
      16: aload_1
      17: ldc           #7                  // String .secretAccessKey
      19: invokevirtual #6                  // Method org/apache/dubbo/common/URL.getParameter:(Ljava/lang/String;)Ljava/lang/String;
      22: astore        5
      24: aload_3
      25: aload         4
      27: invokevirtual #8                  // Method org/apache/dubbo/auth/model/AccessKeyPair.setAccessKey:(Ljava/lang/String;)V
      30: aload_3
      31: aload         5
      33: invokevirtual #9                  // Method org/apache/dubbo/auth/model/AccessKeyPair.setSecretKey:(Ljava/lang/String;)V
      36: aload_3
      37: areturn
}
