Compiled from "ClusterWeight.java"
public class org.apache.dubbo.rpc.cluster.router.xds.rule.ClusterWeight {
  private final java.lang.String name;

  private final int weight;

  public org.apache.dubbo.rpc.cluster.router.xds.rule.ClusterWeight(java.lang.String, int);
    Code:
       0: aload_0
       1: invokespecial #1                  // Method java/lang/Object."<init>":()V
       4: aload_0
       5: aload_1
       6: putfield      #2                  // Field name:Ljava/lang/String;
       9: aload_0
      10: iload_2
      11: putfield      #3                  // Field weight:I
      14: return

  public java.lang.String getName();
    Code:
       0: aload_0
       1: getfield      #2                  // Field name:Ljava/lang/String;
       4: areturn

  public int getWeight();
    Code:
       0: aload_0
       1: getfield      #3                  // Field weight:I
       4: ireturn
}
