Compiled from "DestinationSubset.java"
public class org.apache.dubbo.rpc.cluster.router.xds.rule.DestinationSubset<T> {
  private final java.lang.String clusterName;

  private java.util.Set<org.apache.dubbo.registry.xds.util.protocol.message.Endpoint> endpoints;

  private org.apache.dubbo.rpc.cluster.router.state.BitList<org.apache.dubbo.rpc.Invoker<T>> invokers;

  public org.apache.dubbo.rpc.cluster.router.xds.rule.DestinationSubset(java.lang.String);
    Code:
       0: aload_0
       1: invokespecial #1                  // Method java/lang/Object."<init>":()V
       4: aload_0
       5: new           #2                  // class java/util/HashSet
       8: dup
       9: invokespecial #3                  // Method java/util/HashSet."<init>":()V
      12: putfield      #4                  // Field endpoints:Ljava/util/Set;
      15: aload_0
      16: aload_1
      17: putfield      #5                  // Field clusterName:Ljava/lang/String;
      20: return

  public java.lang.String getClusterName();
    Code:
       0: aload_0
       1: getfield      #5                  // Field clusterName:Ljava/lang/String;
       4: areturn

  public java.util.Set<org.apache.dubbo.registry.xds.util.protocol.message.Endpoint> getEndpoints();
    Code:
       0: aload_0
       1: getfield      #4                  // Field endpoints:Ljava/util/Set;
       4: areturn

  public void setEndpoints(java.util.Set<org.apache.dubbo.registry.xds.util.protocol.message.Endpoint>);
    Code:
       0: aload_0
       1: aload_1
       2: putfield      #4                  // Field endpoints:Ljava/util/Set;
       5: return

  public org.apache.dubbo.rpc.cluster.router.state.BitList<org.apache.dubbo.rpc.Invoker<T>> getInvokers();
    Code:
       0: aload_0
       1: getfield      #6                  // Field invokers:Lorg/apache/dubbo/rpc/cluster/router/state/BitList;
       4: areturn

  public void setInvokers(org.apache.dubbo.rpc.cluster.router.state.BitList<org.apache.dubbo.rpc.Invoker<T>>);
    Code:
       0: aload_0
       1: aload_1
       2: putfield      #6                  // Field invokers:Lorg/apache/dubbo/rpc/cluster/router/state/BitList;
       5: return
}
