Compiled from "HeaderMatcher.java"
public class org.apache.dubbo.rpc.cluster.router.xds.rule.HeaderMatcher {
  public java.lang.String name;

  public java.lang.String exactValue;

  private java.lang.String regex;

  public org.apache.dubbo.rpc.cluster.router.xds.rule.LongRangeMatch range;

  public java.lang.Boolean present;

  public java.lang.String prefix;

  public java.lang.String suffix;

  public boolean inverted;

  public org.apache.dubbo.rpc.cluster.router.xds.rule.HeaderMatcher();
    Code:
       0: aload_0
       1: invokespecial #1                  // Method java/lang/Object."<init>":()V
       4: return

  public java.lang.String getName();
    Code:
       0: aload_0
       1: getfield      #2                  // Field name:Ljava/lang/String;
       4: areturn

  public void setName(java.lang.String);
    Code:
       0: aload_0
       1: aload_1
       2: putfield      #2                  // Field name:Ljava/lang/String;
       5: return

  public java.lang.String getExactValue();
    Code:
       0: aload_0
       1: getfield      #3                  // Field exactValue:Ljava/lang/String;
       4: areturn

  public void setExactValue(java.lang.String);
    Code:
       0: aload_0
       1: aload_1
       2: putfield      #3                  // Field exactValue:Ljava/lang/String;
       5: return

  public java.lang.String getRegex();
    Code:
       0: aload_0
       1: getfield      #4                  // Field regex:Ljava/lang/String;
       4: areturn

  public void setRegex(java.lang.String);
    Code:
       0: aload_0
       1: aload_1
       2: putfield      #4                  // Field regex:Ljava/lang/String;
       5: return

  public org.apache.dubbo.rpc.cluster.router.xds.rule.LongRangeMatch getRange();
    Code:
       0: aload_0
       1: getfield      #5                  // Field range:Lorg/apache/dubbo/rpc/cluster/router/xds/rule/LongRangeMatch;
       4: areturn

  public void setRange(org.apache.dubbo.rpc.cluster.router.xds.rule.LongRangeMatch);
    Code:
       0: aload_0
       1: aload_1
       2: putfield      #5                  // Field range:Lorg/apache/dubbo/rpc/cluster/router/xds/rule/LongRangeMatch;
       5: return

  public java.lang.Boolean getPresent();
    Code:
       0: aload_0
       1: getfield      #6                  // Field present:Ljava/lang/Boolean;
       4: areturn

  public void setPresent(java.lang.Boolean);
    Code:
       0: aload_0
       1: aload_1
       2: putfield      #6                  // Field present:Ljava/lang/Boolean;
       5: return

  public java.lang.String getPrefix();
    Code:
       0: aload_0
       1: getfield      #7                  // Field prefix:Ljava/lang/String;
       4: areturn

  public void setPrefix(java.lang.String);
    Code:
       0: aload_0
       1: aload_1
       2: putfield      #7                  // Field prefix:Ljava/lang/String;
       5: return

  public java.lang.String getSuffix();
    Code:
       0: aload_0
       1: getfield      #8                  // Field suffix:Ljava/lang/String;
       4: areturn

  public void setSuffix(java.lang.String);
    Code:
       0: aload_0
       1: aload_1
       2: putfield      #8                  // Field suffix:Ljava/lang/String;
       5: return

  public boolean isInverted();
    Code:
       0: aload_0
       1: getfield      #9                  // Field inverted:Z
       4: ireturn

  public void setInverted(boolean);
    Code:
       0: aload_0
       1: iload_1
       2: putfield      #9                  // Field inverted:Z
       5: return

  public boolean match(java.lang.String);
    Code:
       0: aload_0
       1: invokevirtual #10                 // Method getPresent:()Ljava/lang/Boolean;
       4: ifnull        39
       7: aload_1
       8: ifnonnull     15
      11: iconst_1
      12: goto          16
      15: iconst_0
      16: aload_0
      17: invokevirtual #10                 // Method getPresent:()Ljava/lang/Boolean;
      20: aload_0
      21: invokevirtual #11                 // Method isInverted:()Z
      24: invokestatic  #12                 // Method java/lang/Boolean.valueOf:(Z)Ljava/lang/Boolean;
      27: invokevirtual #13                 // Method java/lang/Boolean.equals:(Ljava/lang/Object;)Z
      30: if_icmpne     37
      33: iconst_1
      34: goto          38
      37: iconst_0
      38: ireturn
      39: aload_1
      40: ifnonnull     45
      43: iconst_0
      44: ireturn
      45: aload_0
      46: invokevirtual #14                 // Method getExactValue:()Ljava/lang/String;
      49: ifnull        73
      52: aload_0
      53: invokevirtual #14                 // Method getExactValue:()Ljava/lang/String;
      56: aload_1
      57: invokevirtual #15                 // Method java/lang/String.equals:(Ljava/lang/Object;)Z
      60: aload_0
      61: invokevirtual #11                 // Method isInverted:()Z
      64: if_icmpeq     71
      67: iconst_1
      68: goto          72
      71: iconst_0
      72: ireturn
      73: aload_0
      74: invokevirtual #16                 // Method getRegex:()Ljava/lang/String;
      77: ifnull        101
      80: aload_1
      81: aload_0
      82: invokevirtual #16                 // Method getRegex:()Ljava/lang/String;
      85: invokevirtual #17                 // Method java/lang/String.matches:(Ljava/lang/String;)Z
      88: aload_0
      89: invokevirtual #11                 // Method isInverted:()Z
      92: if_icmpeq     99
      95: iconst_1
      96: goto          100
      99: iconst_0
     100: ireturn
     101: aload_0
     102: invokevirtual #18                 // Method getRange:()Lorg/apache/dubbo/rpc/cluster/router/xds/rule/LongRangeMatch;
     105: ifnull        129
     108: aload_0
     109: invokevirtual #18                 // Method getRange:()Lorg/apache/dubbo/rpc/cluster/router/xds/rule/LongRangeMatch;
     112: aload_1
     113: invokevirtual #19                 // Method org/apache/dubbo/rpc/cluster/router/xds/rule/LongRangeMatch.isMatch:(Ljava/lang/String;)Z
     116: aload_0
     117: invokevirtual #11                 // Method isInverted:()Z
     120: if_icmpeq     127
     123: iconst_1
     124: goto          128
     127: iconst_0
     128: ireturn
     129: aload_0
     130: invokevirtual #20                 // Method getPrefix:()Ljava/lang/String;
     133: ifnull        157
     136: aload_1
     137: aload_0
     138: invokevirtual #20                 // Method getPrefix:()Ljava/lang/String;
     141: invokevirtual #21                 // Method java/lang/String.startsWith:(Ljava/lang/String;)Z
     144: aload_0
     145: invokevirtual #11                 // Method isInverted:()Z
     148: if_icmpeq     155
     151: iconst_1
     152: goto          156
     155: iconst_0
     156: ireturn
     157: aload_0
     158: invokevirtual #22                 // Method getSuffix:()Ljava/lang/String;
     161: ifnull        185
     164: aload_1
     165: aload_0
     166: invokevirtual #22                 // Method getSuffix:()Ljava/lang/String;
     169: invokevirtual #23                 // Method java/lang/String.endsWith:(Ljava/lang/String;)Z
     172: aload_0
     173: invokevirtual #11                 // Method isInverted:()Z
     176: if_icmpeq     183
     179: iconst_1
     180: goto          184
     183: iconst_0
     184: ireturn
     185: iconst_0
     186: ireturn
}
