Compiled from "HttpRequestMatch.java"
public class org.apache.dubbo.rpc.cluster.router.xds.rule.HttpRequestMatch {
  private final org.apache.dubbo.rpc.cluster.router.xds.rule.PathMatcher pathMatcher;

  private final java.util.List<org.apache.dubbo.rpc.cluster.router.xds.rule.HeaderMatcher> headerMatcherList;

  public org.apache.dubbo.rpc.cluster.router.xds.rule.HttpRequestMatch(org.apache.dubbo.rpc.cluster.router.xds.rule.PathMatcher, java.util.List<org.apache.dubbo.rpc.cluster.router.xds.rule.HeaderMatcher>);
    Code:
       0: aload_0
       1: invokespecial #1                  // Method java/lang/Object."<init>":()V
       4: aload_0
       5: aload_1
       6: putfield      #2                  // Field pathMatcher:Lorg/apache/dubbo/rpc/cluster/router/xds/rule/PathMatcher;
       9: aload_0
      10: aload_2
      11: putfield      #3                  // Field headerMatcherList:Ljava/util/List;
      14: return

  public org.apache.dubbo.rpc.cluster.router.xds.rule.PathMatcher getPathMatcher();
    Code:
       0: aload_0
       1: getfield      #2                  // Field pathMatcher:Lorg/apache/dubbo/rpc/cluster/router/xds/rule/PathMatcher;
       4: areturn

  public java.util.List<org.apache.dubbo.rpc.cluster.router.xds.rule.HeaderMatcher> getHeaderMatcherList();
    Code:
       0: aload_0
       1: getfield      #3                  // Field headerMatcherList:Ljava/util/List;
       4: areturn
}
