Compiled from "HTTPRouteDestination.java"
public class org.apache.dubbo.rpc.cluster.router.xds.rule.HTTPRouteDestination {
  private java.lang.String cluster;

  private java.util.List<org.apache.dubbo.rpc.cluster.router.xds.rule.ClusterWeight> weightedClusters;

  public org.apache.dubbo.rpc.cluster.router.xds.rule.HTTPRouteDestination();
    Code:
       0: aload_0
       1: invokespecial #1                  // Method java/lang/Object."<init>":()V
       4: return

  public java.lang.String getCluster();
    Code:
       0: aload_0
       1: getfield      #2                  // Field cluster:Ljava/lang/String;
       4: areturn

  public void setCluster(java.lang.String);
    Code:
       0: aload_0
       1: aload_1
       2: putfield      #2                  // Field cluster:Ljava/lang/String;
       5: return

  public java.util.List<org.apache.dubbo.rpc.cluster.router.xds.rule.ClusterWeight> getWeightedClusters();
    Code:
       0: aload_0
       1: getfield      #3                  // Field weightedClusters:Ljava/util/List;
       4: areturn

  public void setWeightedClusters(java.util.List<org.apache.dubbo.rpc.cluster.router.xds.rule.ClusterWeight>);
    Code:
       0: aload_0
       1: aload_1
       2: putfield      #3                  // Field weightedClusters:Ljava/util/List;
       5: return
}
