Compiled from "LongRangeMatch.java"
public class org.apache.dubbo.rpc.cluster.router.xds.rule.LongRangeMatch {
  private long start;

  private long end;

  public org.apache.dubbo.rpc.cluster.router.xds.rule.LongRangeMatch();
    Code:
       0: aload_0
       1: invokespecial #1                  // Method java/lang/Object."<init>":()V
       4: return

  public long getStart();
    Code:
       0: aload_0
       1: getfield      #2                  // Field start:J
       4: lreturn

  public void setStart(long);
    Code:
       0: aload_0
       1: lload_1
       2: putfield      #2                  // Field start:J
       5: return

  public long getEnd();
    Code:
       0: aload_0
       1: getfield      #3                  // Field end:J
       4: lreturn

  public void setEnd(long);
    Code:
       0: aload_0
       1: lload_1
       2: putfield      #3                  // Field end:J
       5: return

  public boolean isMatch(java.lang.String);
    Code:
       0: aload_1
       1: invokestatic  #4                  // Method java/lang/Long.parseLong:(Ljava/lang/String;)J
       4: lstore_2
       5: lload_2
       6: aload_0
       7: invokevirtual #5                  // Method getStart:()J
      10: lcmp
      11: iflt          27
      14: lload_2
      15: aload_0
      16: invokevirtual #6                  // Method getEnd:()J
      19: lcmp
      20: ifgt          27
      23: iconst_1
      24: goto          28
      27: iconst_0
      28: ireturn
      29: astore_2
      30: iconst_0
      31: ireturn
    Exception table:
       from    to  target type
           0    28    29   Class java/lang/NumberFormatException
}
