Compiled from "XdsRouteRule.java"
public class org.apache.dubbo.rpc.cluster.router.xds.rule.XdsRouteRule {
  private final org.apache.dubbo.rpc.cluster.router.xds.rule.HttpRequestMatch match;

  private final org.apache.dubbo.rpc.cluster.router.xds.rule.HTTPRouteDestination route;

  public org.apache.dubbo.rpc.cluster.router.xds.rule.XdsRouteRule(org.apache.dubbo.rpc.cluster.router.xds.rule.HttpRequestMatch, org.apache.dubbo.rpc.cluster.router.xds.rule.HTTPRouteDestination);
    Code:
       0: aload_0
       1: invokespecial #1                  // Method java/lang/Object."<init>":()V
       4: aload_0
       5: aload_1
       6: putfield      #2                  // Field match:Lorg/apache/dubbo/rpc/cluster/router/xds/rule/HttpRequestMatch;
       9: aload_0
      10: aload_2
      11: putfield      #3                  // Field route:Lorg/apache/dubbo/rpc/cluster/router/xds/rule/HTTPRouteDestination;
      14: return

  public org.apache.dubbo.rpc.cluster.router.xds.rule.HttpRequestMatch getMatch();
    Code:
       0: aload_0
       1: getfield      #2                  // Field match:Lorg/apache/dubbo/rpc/cluster/router/xds/rule/HttpRequestMatch;
       4: areturn

  public org.apache.dubbo.rpc.cluster.router.xds.rule.HTTPRouteDestination getRoute();
    Code:
       0: aload_0
       1: getfield      #3                  // Field route:Lorg/apache/dubbo/rpc/cluster/router/xds/rule/HTTPRouteDestination;
       4: areturn
}
