Compiled from "AbstractFallbackJdkProxyFactory.java"
public abstract class org.apache.dubbo.rpc.proxy.AbstractFallbackJdkProxyFactory extends org.apache.dubbo.rpc.proxy.AbstractProxyFactory {
  protected final org.apache.dubbo.common.logger.ErrorTypeAwareLogger logger;

  private final org.apache.dubbo.rpc.proxy.jdk.JdkProxyFactory jdkProxyFactory;

  public org.apache.dubbo.rpc.proxy.AbstractFallbackJdkProxyFactory();
    Code:
       0: aload_0
       1: invokespecial #2                  // Method org/apache/dubbo/rpc/proxy/AbstractProxyFactory."<init>":()V
       4: aload_0
       5: aload_0
       6: invokevirtual #3                  // Method java/lang/Object.getClass:()Ljava/lang/Class;
       9: invokestatic  #4                  // Method org/apache/dubbo/common/logger/LoggerFactory.getErrorTypeAwareLogger:(Ljava/lang/Class;)Lorg/apache/dubbo/common/logger/ErrorTypeAwareLogger;
      12: putfield      #5                  // Field logger:Lorg/apache/dubbo/common/logger/ErrorTypeAwareLogger;
      15: aload_0
      16: new           #6                  // class org/apache/dubbo/rpc/proxy/jdk/JdkProxyFactory
      19: dup
      20: invokespecial #7                  // Method org/apache/dubbo/rpc/proxy/jdk/JdkProxyFactory."<init>":()V
      23: putfield      #8                  // Field jdkProxyFactory:Lorg/apache/dubbo/rpc/proxy/jdk/JdkProxyFactory;
      26: return

  public <T> org.apache.dubbo.rpc.Invoker<T> getInvoker(T, java.lang.Class<T>, org.apache.dubbo.common.URL) throws org.apache.dubbo.rpc.RpcException;
    Code:
       0: aload_0
       1: aload_1
       2: aload_2
       3: aload_3
       4: invokevirtual #9                  // Method doGetInvoker:(Ljava/lang/Object;Ljava/lang/Class;Lorg/apache/dubbo/common/URL;)Lorg/apache/dubbo/rpc/Invoker;
       7: areturn
       8: astore        4
      10: aload_0
      11: invokevirtual #3                  // Method java/lang/Object.getClass:()Ljava/lang/Class;
      14: invokevirtual #11                 // Method java/lang/Class.getSimpleName:()Ljava/lang/String;
      17: astore        5
      19: aload_0
      20: getfield      #8                  // Field jdkProxyFactory:Lorg/apache/dubbo/rpc/proxy/jdk/JdkProxyFactory;
      23: aload_1
      24: aload_2
      25: aload_3
      26: invokevirtual #12                 // Method org/apache/dubbo/rpc/proxy/jdk/JdkProxyFactory.getInvoker:(Ljava/lang/Object;Ljava/lang/Class;Lorg/apache/dubbo/common/URL;)Lorg/apache/dubbo/rpc/Invoker;
      29: astore        6
      31: aload_0
      32: getfield      #5                  // Field logger:Lorg/apache/dubbo/common/logger/ErrorTypeAwareLogger;
      35: ldc           #13                 // String 3-8
      37: ldc           #14                 // String
      39: ldc           #14                 // String
      41: new           #15                 // class java/lang/StringBuilder
      44: dup
      45: invokespecial #16                 // Method java/lang/StringBuilder."<init>":()V
      48: ldc           #17                 // String Failed to generate invoker by
      50: invokevirtual #18                 // Method java/lang/StringBuilder.append:(Ljava/lang/String;)Ljava/lang/StringBuilder;
      53: aload         5
      55: invokevirtual #18                 // Method java/lang/StringBuilder.append:(Ljava/lang/String;)Ljava/lang/StringBuilder;
      58: ldc           #19                 // String  failed. Fallback to use JDK proxy success. Interfaces:
      60: invokevirtual #18                 // Method java/lang/StringBuilder.append:(Ljava/lang/String;)Ljava/lang/StringBuilder;
      63: aload_2
      64: invokevirtual #20                 // Method java/lang/StringBuilder.append:(Ljava/lang/Object;)Ljava/lang/StringBuilder;
      67: invokevirtual #21                 // Method java/lang/StringBuilder.toString:()Ljava/lang/String;
      70: aload         4
      72: invokeinterface #22,  6           // InterfaceMethod org/apache/dubbo/common/logger/ErrorTypeAwareLogger.error:(Ljava/lang/String;Ljava/lang/String;Ljava/lang/String;Ljava/lang/String;Ljava/lang/Throwable;)V
      77: aload         6
      79: areturn
      80: astore        6
      82: aload_0
      83: getfield      #5                  // Field logger:Lorg/apache/dubbo/common/logger/ErrorTypeAwareLogger;
      86: ldc           #13                 // String 3-8
      88: ldc           #14                 // String
      90: ldc           #14                 // String
      92: new           #15                 // class java/lang/StringBuilder
      95: dup
      96: invokespecial #16                 // Method java/lang/StringBuilder."<init>":()V
      99: ldc           #17                 // String Failed to generate invoker by
     101: invokevirtual #18                 // Method java/lang/StringBuilder.append:(Ljava/lang/String;)Ljava/lang/StringBuilder;
     104: aload         5
     106: invokevirtual #18                 // Method java/lang/StringBuilder.append:(Ljava/lang/String;)Ljava/lang/StringBuilder;
     109: ldc           #23                 // String  failed. Fallback to use JDK proxy is also failed. Interfaces:
     111: invokevirtual #18                 // Method java/lang/StringBuilder.append:(Ljava/lang/String;)Ljava/lang/StringBuilder;
     114: aload_2
     115: invokevirtual #20                 // Method java/lang/StringBuilder.append:(Ljava/lang/Object;)Ljava/lang/StringBuilder;
     118: ldc           #24                 // String  Javassist Error.
     120: invokevirtual #18                 // Method java/lang/StringBuilder.append:(Ljava/lang/String;)Ljava/lang/StringBuilder;
     123: invokevirtual #21                 // Method java/lang/StringBuilder.toString:()Ljava/lang/String;
     126: aload         4
     128: invokeinterface #22,  6           // InterfaceMethod org/apache/dubbo/common/logger/ErrorTypeAwareLogger.error:(Ljava/lang/String;Ljava/lang/String;Ljava/lang/String;Ljava/lang/String;Ljava/lang/Throwable;)V
     133: aload_0
     134: getfield      #5                  // Field logger:Lorg/apache/dubbo/common/logger/ErrorTypeAwareLogger;
     137: ldc           #13                 // String 3-8
     139: ldc           #14                 // String
     141: ldc           #14                 // String
     143: new           #15                 // class java/lang/StringBuilder
     146: dup
     147: invokespecial #16                 // Method java/lang/StringBuilder."<init>":()V
     150: ldc           #17                 // String Failed to generate invoker by
     152: invokevirtual #18                 // Method java/lang/StringBuilder.append:(Ljava/lang/String;)Ljava/lang/StringBuilder;
     155: aload         5
     157: invokevirtual #18                 // Method java/lang/StringBuilder.append:(Ljava/lang/String;)Ljava/lang/StringBuilder;
     160: ldc           #23                 // String  failed. Fallback to use JDK proxy is also failed. Interfaces:
     162: invokevirtual #18                 // Method java/lang/StringBuilder.append:(Ljava/lang/String;)Ljava/lang/StringBuilder;
     165: aload_2
     166: invokevirtual #20                 // Method java/lang/StringBuilder.append:(Ljava/lang/Object;)Ljava/lang/StringBuilder;
     169: ldc           #25                 // String  JDK Error.
     171: invokevirtual #18                 // Method java/lang/StringBuilder.append:(Ljava/lang/String;)Ljava/lang/StringBuilder;
     174: invokevirtual #21                 // Method java/lang/StringBuilder.toString:()Ljava/lang/String;
     177: aload         6
     179: invokeinterface #22,  6           // InterfaceMethod org/apache/dubbo/common/logger/ErrorTypeAwareLogger.error:(Ljava/lang/String;Ljava/lang/String;Ljava/lang/String;Ljava/lang/String;Ljava/lang/Throwable;)V
     184: aload         4
     186: athrow
    Exception table:
       from    to  target type
           0     7     8   Class java/lang/Throwable
          19    79    80   Class java/lang/Throwable

  public <T> T getProxy(org.apache.dubbo.rpc.Invoker<T>, java.lang.Class<?>[]);
    Code:
       0: aload_0
       1: aload_1
       2: aload_2
       3: invokevirtual #26                 // Method doGetProxy:(Lorg/apache/dubbo/rpc/Invoker;[Ljava/lang/Class;)Ljava/lang/Object;
       6: areturn
       7: astore_3
       8: aload_0
       9: invokevirtual #3                  // Method java/lang/Object.getClass:()Ljava/lang/Class;
      12: invokevirtual #11                 // Method java/lang/Class.getSimpleName:()Ljava/lang/String;
      15: astore        4
      17: aload_0
      18: getfield      #8                  // Field jdkProxyFactory:Lorg/apache/dubbo/rpc/proxy/jdk/JdkProxyFactory;
      21: aload_1
      22: aload_2
      23: invokevirtual #27                 // Method org/apache/dubbo/rpc/proxy/jdk/JdkProxyFactory.getProxy:(Lorg/apache/dubbo/rpc/Invoker;[Ljava/lang/Class;)Ljava/lang/Object;
      26: astore        5
      28: aload_0
      29: getfield      #5                  // Field logger:Lorg/apache/dubbo/common/logger/ErrorTypeAwareLogger;
      32: ldc           #13                 // String 3-8
      34: ldc           #14                 // String
      36: ldc           #14                 // String
      38: new           #15                 // class java/lang/StringBuilder
      41: dup
      42: invokespecial #16                 // Method java/lang/StringBuilder."<init>":()V
      45: ldc           #28                 // String Failed to generate proxy by
      47: invokevirtual #18                 // Method java/lang/StringBuilder.append:(Ljava/lang/String;)Ljava/lang/StringBuilder;
      50: aload         4
      52: invokevirtual #18                 // Method java/lang/StringBuilder.append:(Ljava/lang/String;)Ljava/lang/StringBuilder;
      55: ldc           #19                 // String  failed. Fallback to use JDK proxy success. Interfaces:
      57: invokevirtual #18                 // Method java/lang/StringBuilder.append:(Ljava/lang/String;)Ljava/lang/StringBuilder;
      60: aload_2
      61: invokestatic  #29                 // Method java/util/Arrays.toString:([Ljava/lang/Object;)Ljava/lang/String;
      64: invokevirtual #18                 // Method java/lang/StringBuilder.append:(Ljava/lang/String;)Ljava/lang/StringBuilder;
      67: invokevirtual #21                 // Method java/lang/StringBuilder.toString:()Ljava/lang/String;
      70: aload_3
      71: invokeinterface #22,  6           // InterfaceMethod org/apache/dubbo/common/logger/ErrorTypeAwareLogger.error:(Ljava/lang/String;Ljava/lang/String;Ljava/lang/String;Ljava/lang/String;Ljava/lang/Throwable;)V
      76: aload         5
      78: areturn
      79: astore        5
      81: aload_0
      82: getfield      #5                  // Field logger:Lorg/apache/dubbo/common/logger/ErrorTypeAwareLogger;
      85: ldc           #13                 // String 3-8
      87: ldc           #14                 // String
      89: ldc           #14                 // String
      91: new           #15                 // class java/lang/StringBuilder
      94: dup
      95: invokespecial #16                 // Method java/lang/StringBuilder."<init>":()V
      98: ldc           #28                 // String Failed to generate proxy by
     100: invokevirtual #18                 // Method java/lang/StringBuilder.append:(Ljava/lang/String;)Ljava/lang/StringBuilder;
     103: aload         4
     105: invokevirtual #18                 // Method java/lang/StringBuilder.append:(Ljava/lang/String;)Ljava/lang/StringBuilder;
     108: ldc           #23                 // String  failed. Fallback to use JDK proxy is also failed. Interfaces:
     110: invokevirtual #18                 // Method java/lang/StringBuilder.append:(Ljava/lang/String;)Ljava/lang/StringBuilder;
     113: aload_2
     114: invokestatic  #29                 // Method java/util/Arrays.toString:([Ljava/lang/Object;)Ljava/lang/String;
     117: invokevirtual #18                 // Method java/lang/StringBuilder.append:(Ljava/lang/String;)Ljava/lang/StringBuilder;
     120: ldc           #24                 // String  Javassist Error.
     122: invokevirtual #18                 // Method java/lang/StringBuilder.append:(Ljava/lang/String;)Ljava/lang/StringBuilder;
     125: invokevirtual #21                 // Method java/lang/StringBuilder.toString:()Ljava/lang/String;
     128: aload_3
     129: invokeinterface #22,  6           // InterfaceMethod org/apache/dubbo/common/logger/ErrorTypeAwareLogger.error:(Ljava/lang/String;Ljava/lang/String;Ljava/lang/String;Ljava/lang/String;Ljava/lang/Throwable;)V
     134: aload_0
     135: getfield      #5                  // Field logger:Lorg/apache/dubbo/common/logger/ErrorTypeAwareLogger;
     138: ldc           #13                 // String 3-8
     140: ldc           #14                 // String
     142: ldc           #14                 // String
     144: new           #15                 // class java/lang/StringBuilder
     147: dup
     148: invokespecial #16                 // Method java/lang/StringBuilder."<init>":()V
     151: ldc           #28                 // String Failed to generate proxy by
     153: invokevirtual #18                 // Method java/lang/StringBuilder.append:(Ljava/lang/String;)Ljava/lang/StringBuilder;
     156: aload         4
     158: invokevirtual #18                 // Method java/lang/StringBuilder.append:(Ljava/lang/String;)Ljava/lang/StringBuilder;
     161: ldc           #23                 // String  failed. Fallback to use JDK proxy is also failed. Interfaces:
     163: invokevirtual #18                 // Method java/lang/StringBuilder.append:(Ljava/lang/String;)Ljava/lang/StringBuilder;
     166: aload_2
     167: invokestatic  #29                 // Method java/util/Arrays.toString:([Ljava/lang/Object;)Ljava/lang/String;
     170: invokevirtual #18                 // Method java/lang/StringBuilder.append:(Ljava/lang/String;)Ljava/lang/StringBuilder;
     173: ldc           #25                 // String  JDK Error.
     175: invokevirtual #18                 // Method java/lang/StringBuilder.append:(Ljava/lang/String;)Ljava/lang/StringBuilder;
     178: invokevirtual #21                 // Method java/lang/StringBuilder.toString:()Ljava/lang/String;
     181: aload         5
     183: invokeinterface #22,  6           // InterfaceMethod org/apache/dubbo/common/logger/ErrorTypeAwareLogger.error:(Ljava/lang/String;Ljava/lang/String;Ljava/lang/String;Ljava/lang/String;Ljava/lang/Throwable;)V
     188: aload_3
     189: athrow
    Exception table:
       from    to  target type
           0     6     7   Class java/lang/Throwable
          17    78    79   Class java/lang/Throwable

  protected abstract <T> org.apache.dubbo.rpc.Invoker<T> doGetInvoker(T, java.lang.Class<T>, org.apache.dubbo.common.URL);

  protected abstract <T> T doGetProxy(org.apache.dubbo.rpc.Invoker<T>, java.lang.Class<?>[]);
}
