Compiled from "AbstractProxyFactory.java"
public abstract class org.apache.dubbo.rpc.proxy.AbstractProxyFactory implements org.apache.dubbo.rpc.ProxyFactory {
  private static final java.lang.Class<?>[] INTERNAL_INTERFACES;

  private static final org.apache.dubbo.common.logger.ErrorTypeAwareLogger logger;

  public org.apache.dubbo.rpc.proxy.AbstractProxyFactory();
    Code:
       0: aload_0
       1: invokespecial #3                  // Method java/lang/Object."<init>":()V
       4: return

  public <T> T getProxy(org.apache.dubbo.rpc.Invoker<T>) throws org.apache.dubbo.rpc.RpcException;
    Code:
       0: aload_0
       1: aload_1
       2: iconst_0
       3: invokevirtual #4                  // Method getProxy:(Lorg/apache/dubbo/rpc/Invoker;Z)Ljava/lang/Object;
       6: areturn

  public <T> T getProxy(org.apache.dubbo.rpc.Invoker<T>, boolean) throws org.apache.dubbo.rpc.RpcException;
    Code:
       0: new           #5                  // class java/util/LinkedHashSet
       3: dup
       4: invokespecial #6                  // Method java/util/LinkedHashSet."<init>":()V
       7: astore_3
       8: aload_0
       9: aload_1
      10: invokespecial #7                  // Method getClassLoader:(Lorg/apache/dubbo/rpc/Invoker;)Ljava/lang/ClassLoader;
      13: astore        4
      15: aload_1
      16: invokeinterface #8,  1            // InterfaceMethod org/apache/dubbo/rpc/Invoker.getUrl:()Lorg/apache/dubbo/common/URL;
      21: ldc           #9                  // String interfaces
      23: invokevirtual #10                 // Method org/apache/dubbo/common/URL.getParameter:(Ljava/lang/String;)Ljava/lang/String;
      26: astore        5
      28: aload         5
      30: invokestatic  #11                 // Method org/apache/dubbo/common/utils/StringUtils.isNotEmpty:(Ljava/lang/String;)Z
      33: ifeq          95
      36: getstatic     #12                 // Field org/apache/dubbo/common/constants/CommonConstants.COMMA_SPLIT_PATTERN:Ljava/util/regex/Pattern;
      39: aload         5
      41: invokevirtual #13                 // Method java/util/regex/Pattern.split:(Ljava/lang/CharSequence;)[Ljava/lang/String;
      44: astore        6
      46: aload         6
      48: astore        7
      50: aload         7
      52: arraylength
      53: istore        8
      55: iconst_0
      56: istore        9
      58: iload         9
      60: iload         8
      62: if_icmpge     95
      65: aload         7
      67: iload         9
      69: aaload
      70: astore        10
      72: aload_3
      73: aload         4
      75: aload         10
      77: invokestatic  #14                 // Method org/apache/dubbo/common/utils/ReflectUtils.forName:(Ljava/lang/ClassLoader;Ljava/lang/String;)Ljava/lang/Class;
      80: invokevirtual #15                 // Method java/util/LinkedHashSet.add:(Ljava/lang/Object;)Z
      83: pop
      84: goto          89
      87: astore        11
      89: iinc          9, 1
      92: goto          58
      95: aconst_null
      96: astore        6
      98: iload_2
      99: ifeq          171
     102: aload_1
     103: invokeinterface #8,  1            // InterfaceMethod org/apache/dubbo/rpc/Invoker.getUrl:()Lorg/apache/dubbo/common/URL;
     108: ldc           #17                 // String interface
     110: invokevirtual #10                 // Method org/apache/dubbo/common/URL.getParameter:(Ljava/lang/String;)Ljava/lang/String;
     113: astore        7
     115: aload         4
     117: aload         7
     119: invokestatic  #14                 // Method org/apache/dubbo/common/utils/ReflectUtils.forName:(Ljava/lang/ClassLoader;Ljava/lang/String;)Ljava/lang/Class;
     122: astore        6
     124: aload_3
     125: aload         6
     127: invokevirtual #15                 // Method java/util/LinkedHashSet.add:(Ljava/lang/Object;)Z
     130: pop
     131: goto          136
     134: astore        7
     136: ldc           #18                 // class org/apache/dubbo/rpc/service/GenericService
     138: aload_1
     139: invokeinterface #19,  1           // InterfaceMethod org/apache/dubbo/rpc/Invoker.getInterface:()Ljava/lang/Class;
     144: invokevirtual #20                 // Method java/lang/Object.equals:(Ljava/lang/Object;)Z
     147: ifne          164
     150: ldc           #18                 // class org/apache/dubbo/rpc/service/GenericService
     152: aload_1
     153: invokeinterface #19,  1           // InterfaceMethod org/apache/dubbo/rpc/Invoker.getInterface:()Ljava/lang/Class;
     158: invokevirtual #21                 // Method java/lang/Class.isAssignableFrom:(Ljava/lang/Class;)Z
     161: ifne          171
     164: aload_3
     165: ldc           #22                 // class com/alibaba/dubbo/rpc/service/GenericService
     167: invokevirtual #15                 // Method java/util/LinkedHashSet.add:(Ljava/lang/Object;)Z
     170: pop
     171: aload_3
     172: aload_1
     173: invokeinterface #19,  1           // InterfaceMethod org/apache/dubbo/rpc/Invoker.getInterface:()Ljava/lang/Class;
     178: invokevirtual #15                 // Method java/util/LinkedHashSet.add:(Ljava/lang/Object;)Z
     181: pop
     182: aload_3
     183: getstatic     #23                 // Field INTERNAL_INTERFACES:[Ljava/lang/Class;
     186: invokestatic  #24                 // Method java/util/Arrays.asList:([Ljava/lang/Object;)Ljava/util/List;
     189: invokevirtual #25                 // Method java/util/LinkedHashSet.addAll:(Ljava/util/Collection;)Z
     192: pop
     193: aload_0
     194: aload_1
     195: aload_3
     196: iconst_0
     197: anewarray     #26                 // class java/lang/Class
     200: invokevirtual #27                 // Method java/util/LinkedHashSet.toArray:([Ljava/lang/Object;)[Ljava/lang/Object;
     203: checkcast     #28                 // class "[Ljava/lang/Class;"
     206: invokevirtual #29                 // Method getProxy:(Lorg/apache/dubbo/rpc/Invoker;[Ljava/lang/Class;)Ljava/lang/Object;
     209: areturn
     210: astore        7
     212: iload_2
     213: ifeq          274
     216: aload         6
     218: ifnull        228
     221: aload_3
     222: aload         6
     224: invokevirtual #30                 // Method java/util/LinkedHashSet.remove:(Ljava/lang/Object;)Z
     227: pop
     228: aload_3
     229: aload_1
     230: invokeinterface #19,  1           // InterfaceMethod org/apache/dubbo/rpc/Invoker.getInterface:()Ljava/lang/Class;
     235: invokevirtual #30                 // Method java/util/LinkedHashSet.remove:(Ljava/lang/Object;)Z
     238: pop
     239: getstatic     #31                 // Field logger:Lorg/apache/dubbo/common/logger/ErrorTypeAwareLogger;
     242: ldc           #32                 // String 3-6
     244: ldc           #33                 // String
     246: ldc           #33                 // String
     248: ldc           #34                 // String Error occur when creating proxy. Invoker is in generic mode. Trying to create proxy without real interface class.
     250: aload         7
     252: invokeinterface #35,  6           // InterfaceMethod org/apache/dubbo/common/logger/ErrorTypeAwareLogger.error:(Ljava/lang/String;Ljava/lang/String;Ljava/lang/String;Ljava/lang/String;Ljava/lang/Throwable;)V
     257: aload_0
     258: aload_1
     259: aload_3
     260: iconst_0
     261: anewarray     #26                 // class java/lang/Class
     264: invokevirtual #27                 // Method java/util/LinkedHashSet.toArray:([Ljava/lang/Object;)[Ljava/lang/Object;
     267: checkcast     #28                 // class "[Ljava/lang/Class;"
     270: invokevirtual #29                 // Method getProxy:(Lorg/apache/dubbo/rpc/Invoker;[Ljava/lang/Class;)Ljava/lang/Object;
     273: areturn
     274: aload         7
     276: athrow
    Exception table:
       from    to  target type
          72    84    87   Class java/lang/Throwable
         102   131   134   Class java/lang/Throwable
         193   209   210   Class java/lang/Throwable

  private <T> java.lang.ClassLoader getClassLoader(org.apache.dubbo.rpc.Invoker<T>);
    Code:
       0: aload_1
       1: invokeinterface #8,  1            // InterfaceMethod org/apache/dubbo/rpc/Invoker.getUrl:()Lorg/apache/dubbo/common/URL;
       6: invokevirtual #36                 // Method org/apache/dubbo/common/URL.getServiceModel:()Lorg/apache/dubbo/rpc/model/ServiceModel;
       9: astore_2
      10: aconst_null
      11: astore_3
      12: aload_2
      13: ifnull        28
      16: aload_2
      17: invokevirtual #37                 // Method org/apache/dubbo/rpc/model/ServiceModel.getInterfaceClassLoader:()Ljava/lang/ClassLoader;
      20: ifnull        28
      23: aload_2
      24: invokevirtual #37                 // Method org/apache/dubbo/rpc/model/ServiceModel.getInterfaceClassLoader:()Ljava/lang/ClassLoader;
      27: astore_3
      28: aload_3
      29: ifnonnull     36
      32: invokestatic  #38                 // Method org/apache/dubbo/common/utils/ClassUtils.getClassLoader:()Ljava/lang/ClassLoader;
      35: astore_3
      36: aload_3
      37: areturn

  public static java.lang.Class<?>[] getInternalInterfaces();
    Code:
       0: getstatic     #23                 // Field INTERNAL_INTERFACES:[Ljava/lang/Class;
       3: invokevirtual #39                 // Method "[Ljava/lang/Class;".clone:()Ljava/lang/Object;
       6: checkcast     #28                 // class "[Ljava/lang/Class;"
       9: areturn

  public abstract <T> T getProxy(org.apache.dubbo.rpc.Invoker<T>, java.lang.Class<?>[]);

  static {};
    Code:
       0: iconst_2
       1: anewarray     #26                 // class java/lang/Class
       4: dup
       5: iconst_0
       6: ldc           #40                 // class org/apache/dubbo/rpc/service/EchoService
       8: aastore
       9: dup
      10: iconst_1
      11: ldc           #41                 // class org/apache/dubbo/rpc/service/Destroyable
      13: aastore
      14: putstatic     #23                 // Field INTERNAL_INTERFACES:[Ljava/lang/Class;
      17: ldc           #42                 // class org/apache/dubbo/rpc/proxy/AbstractProxyFactory
      19: invokestatic  #43                 // Method org/apache/dubbo/common/logger/LoggerFactory.getErrorTypeAwareLogger:(Ljava/lang/Class;)Lorg/apache/dubbo/common/logger/ErrorTypeAwareLogger;
      22: putstatic     #31                 // Field logger:Lorg/apache/dubbo/common/logger/ErrorTypeAwareLogger;
      25: return
}
