Compiled from "InvocationUtil.java"
public class org.apache.dubbo.rpc.proxy.InvocationUtil {
  private static final org.apache.dubbo.common.logger.ErrorTypeAwareLogger logger;

  public org.apache.dubbo.rpc.proxy.InvocationUtil();
    Code:
       0: aload_0
       1: invokespecial #3                  // Method java/lang/Object."<init>":()V
       4: return

  public static java.lang.Object invoke(org.apache.dubbo.rpc.Invoker<?>, org.apache.dubbo.rpc.RpcInvocation) throws java.lang.Throwable;
    Code:
       0: aload_0
       1: invokeinterface #4,  1            // InterfaceMethod org/apache/dubbo/rpc/Invoker.getUrl:()Lorg/apache/dubbo/common/URL;
       6: astore_2
       7: aload_2
       8: invokevirtual #5                  // Method org/apache/dubbo/common/URL.getServiceKey:()Ljava/lang/String;
      11: astore_3
      12: aload_1
      13: aload_3
      14: invokevirtual #6                  // Method org/apache/dubbo/rpc/RpcInvocation.setTargetServiceUniqueName:(Ljava/lang/String;)V
      17: invokestatic  #7                  // Method org/apache/dubbo/rpc/RpcServiceContext.getServiceContext:()Lorg/apache/dubbo/rpc/RpcServiceContext;
      20: aload_2
      21: invokevirtual #8                  // Method org/apache/dubbo/rpc/RpcServiceContext.setConsumerUrl:(Lorg/apache/dubbo/common/URL;)V
      24: invokestatic  #9                  // Method org/apache/dubbo/common/profiler/ProfilerSwitch.isEnableSimpleProfiler:()Z
      27: ifeq          500
      30: invokestatic  #10                 // Method org/apache/dubbo/common/profiler/Profiler.getBizProfiler:()Lorg/apache/dubbo/common/profiler/ProfilerEntry;
      33: astore        4
      35: aload         4
      37: ifnull        81
      40: aload         4
      42: new           #11                 // class java/lang/StringBuilder
      45: dup
      46: invokespecial #12                 // Method java/lang/StringBuilder."<init>":()V
      49: ldc           #13                 // String Receive request. Client invoke begin. ServiceKey:
      51: invokevirtual #14                 // Method java/lang/StringBuilder.append:(Ljava/lang/String;)Ljava/lang/StringBuilder;
      54: aload_3
      55: invokevirtual #14                 // Method java/lang/StringBuilder.append:(Ljava/lang/String;)Ljava/lang/StringBuilder;
      58: ldc           #15                 // String  MethodName:
      60: invokevirtual #14                 // Method java/lang/StringBuilder.append:(Ljava/lang/String;)Ljava/lang/StringBuilder;
      63: aload_1
      64: invokevirtual #16                 // Method org/apache/dubbo/rpc/RpcInvocation.getMethodName:()Ljava/lang/String;
      67: invokevirtual #14                 // Method java/lang/StringBuilder.append:(Ljava/lang/String;)Ljava/lang/StringBuilder;
      70: invokevirtual #17                 // Method java/lang/StringBuilder.toString:()Ljava/lang/String;
      73: invokestatic  #18                 // Method org/apache/dubbo/common/profiler/Profiler.enter:(Lorg/apache/dubbo/common/profiler/ProfilerEntry;Ljava/lang/String;)Lorg/apache/dubbo/common/profiler/ProfilerEntry;
      76: astore        5
      78: goto          117
      81: new           #11                 // class java/lang/StringBuilder
      84: dup
      85: invokespecial #12                 // Method java/lang/StringBuilder."<init>":()V
      88: ldc           #13                 // String Receive request. Client invoke begin. ServiceKey:
      90: invokevirtual #14                 // Method java/lang/StringBuilder.append:(Ljava/lang/String;)Ljava/lang/StringBuilder;
      93: aload_3
      94: invokevirtual #14                 // Method java/lang/StringBuilder.append:(Ljava/lang/String;)Ljava/lang/StringBuilder;
      97: ldc           #15                 // String  MethodName:
      99: invokevirtual #14                 // Method java/lang/StringBuilder.append:(Ljava/lang/String;)Ljava/lang/StringBuilder;
     102: aload_1
     103: invokevirtual #16                 // Method org/apache/dubbo/rpc/RpcInvocation.getMethodName:()Ljava/lang/String;
     106: invokevirtual #14                 // Method java/lang/StringBuilder.append:(Ljava/lang/String;)Ljava/lang/StringBuilder;
     109: invokevirtual #17                 // Method java/lang/StringBuilder.toString:()Ljava/lang/String;
     112: invokestatic  #19                 // Method org/apache/dubbo/common/profiler/Profiler.start:(Ljava/lang/String;)Lorg/apache/dubbo/common/profiler/ProfilerEntry;
     115: astore        5
     117: aload_1
     118: ldc           #21                 // String DUBBO_INVOKE_PROFILER
     120: aload         5
     122: invokevirtual #22                 // Method org/apache/dubbo/rpc/RpcInvocation.put:(Ljava/lang/Object;Ljava/lang/Object;)Ljava/lang/Object;
     125: pop
     126: aload_0
     127: aload_1
     128: invokeinterface #23,  2           // InterfaceMethod org/apache/dubbo/rpc/Invoker.invoke:(Lorg/apache/dubbo/rpc/Invocation;)Lorg/apache/dubbo/rpc/Result;
     133: invokeinterface #24,  1           // InterfaceMethod org/apache/dubbo/rpc/Result.recreate:()Ljava/lang/Object;
     138: astore        6
     140: aload         5
     142: invokestatic  #25                 // Method org/apache/dubbo/common/profiler/Profiler.release:(Lorg/apache/dubbo/common/profiler/ProfilerEntry;)Lorg/apache/dubbo/common/profiler/ProfilerEntry;
     145: pop
     146: aload_1
     147: ldc           #26                 // String timeout
     149: invokevirtual #27                 // Method org/apache/dubbo/rpc/RpcInvocation.getObjectAttachmentWithoutConvert:(Ljava/lang/String;)Ljava/lang/Object;
     152: invokestatic  #28                 // Method org/apache/dubbo/rpc/support/RpcUtils.convertToNumber:(Ljava/lang/Object;)Ljava/lang/Long;
     155: astore        7
     157: aload         7
     159: ifnonnull     181
     162: aload_2
     163: aload_1
     164: invokevirtual #16                 // Method org/apache/dubbo/rpc/RpcInvocation.getMethodName:()Ljava/lang/String;
     167: ldc           #26                 // String timeout
     169: sipush        1000
     172: invokevirtual #29                 // Method org/apache/dubbo/common/URL.getMethodPositiveParameter:(Ljava/lang/String;Ljava/lang/String;I)I
     175: i2l
     176: invokestatic  #30                 // Method java/lang/Long.valueOf:(J)Ljava/lang/Long;
     179: astore        7
     181: aload         5
     183: invokevirtual #31                 // Method org/apache/dubbo/common/profiler/ProfilerEntry.getEndTime:()J
     186: aload         5
     188: invokevirtual #32                 // Method org/apache/dubbo/common/profiler/ProfilerEntry.getStartTime:()J
     191: lsub
     192: lstore        8
     194: lload         8
     196: l2d
     197: ldc2_w        #33                 // double 1000000.0d
     200: invokestatic  #35                 // Method org/apache/dubbo/common/profiler/ProfilerSwitch.getWarnPercent:()D
     203: dmul
     204: ddiv
     205: aload         7
     207: invokevirtual #36                 // Method java/lang/Long.longValue:()J
     210: l2d
     211: dcmpl
     212: ifle          316
     215: new           #11                 // class java/lang/StringBuilder
     218: dup
     219: invokespecial #12                 // Method java/lang/StringBuilder."<init>":()V
     222: astore        10
     224: aload_1
     225: aload         10
     227: invokedynamic #37,  0             // InvokeDynamic #0:accept:(Ljava/lang/StringBuilder;)Ljava/util/function/Consumer;
     232: invokevirtual #38                 // Method org/apache/dubbo/rpc/RpcInvocation.foreachAttachment:(Ljava/util/function/Consumer;)V
     235: getstatic     #39                 // Field logger:Lorg/apache/dubbo/common/logger/ErrorTypeAwareLogger;
     238: ldc           #40                 // String 3-4
     240: ldc           #41                 // String
     242: ldc           #41                 // String
     244: ldc           #42                 // String [Dubbo-Consumer] execute service %s#%s cost %d.%06d ms, this invocation almost (maybe already) timeout. Timeout: %dms\ninvocation context:\n%sthread info: \n%s
     246: bipush        7
     248: anewarray     #43                 // class java/lang/Object
     251: dup
     252: iconst_0
     253: aload_1
     254: invokevirtual #44                 // Method org/apache/dubbo/rpc/RpcInvocation.getProtocolServiceKey:()Ljava/lang/String;
     257: aastore
     258: dup
     259: iconst_1
     260: aload_1
     261: invokevirtual #16                 // Method org/apache/dubbo/rpc/RpcInvocation.getMethodName:()Ljava/lang/String;
     264: aastore
     265: dup
     266: iconst_2
     267: lload         8
     269: ldc2_w        #45                 // long 1000000l
     272: ldiv
     273: invokestatic  #30                 // Method java/lang/Long.valueOf:(J)Ljava/lang/Long;
     276: aastore
     277: dup
     278: iconst_3
     279: lload         8
     281: ldc2_w        #45                 // long 1000000l
     284: lrem
     285: invokestatic  #30                 // Method java/lang/Long.valueOf:(J)Ljava/lang/Long;
     288: aastore
     289: dup
     290: iconst_4
     291: aload         7
     293: aastore
     294: dup
     295: iconst_5
     296: aload         10
     298: aastore
     299: dup
     300: bipush        6
     302: aload         5
     304: invokestatic  #47                 // Method org/apache/dubbo/common/profiler/Profiler.buildDetail:(Lorg/apache/dubbo/common/profiler/ProfilerEntry;)Ljava/lang/String;
     307: aastore
     308: invokestatic  #48                 // Method java/lang/String.format:(Ljava/lang/String;[Ljava/lang/Object;)Ljava/lang/String;
     311: invokeinterface #49,  5           // InterfaceMethod org/apache/dubbo/common/logger/ErrorTypeAwareLogger.warn:(Ljava/lang/String;Ljava/lang/String;Ljava/lang/String;Ljava/lang/String;)V
     316: aload         6
     318: areturn
     319: astore        11
     321: aload         5
     323: invokestatic  #25                 // Method org/apache/dubbo/common/profiler/Profiler.release:(Lorg/apache/dubbo/common/profiler/ProfilerEntry;)Lorg/apache/dubbo/common/profiler/ProfilerEntry;
     326: pop
     327: aload_1
     328: ldc           #26                 // String timeout
     330: invokevirtual #27                 // Method org/apache/dubbo/rpc/RpcInvocation.getObjectAttachmentWithoutConvert:(Ljava/lang/String;)Ljava/lang/Object;
     333: invokestatic  #28                 // Method org/apache/dubbo/rpc/support/RpcUtils.convertToNumber:(Ljava/lang/Object;)Ljava/lang/Long;
     336: astore        12
     338: aload         12
     340: ifnonnull     362
     343: aload_2
     344: aload_1
     345: invokevirtual #16                 // Method org/apache/dubbo/rpc/RpcInvocation.getMethodName:()Ljava/lang/String;
     348: ldc           #26                 // String timeout
     350: sipush        1000
     353: invokevirtual #29                 // Method org/apache/dubbo/common/URL.getMethodPositiveParameter:(Ljava/lang/String;Ljava/lang/String;I)I
     356: i2l
     357: invokestatic  #30                 // Method java/lang/Long.valueOf:(J)Ljava/lang/Long;
     360: astore        12
     362: aload         5
     364: invokevirtual #31                 // Method org/apache/dubbo/common/profiler/ProfilerEntry.getEndTime:()J
     367: aload         5
     369: invokevirtual #32                 // Method org/apache/dubbo/common/profiler/ProfilerEntry.getStartTime:()J
     372: lsub
     373: lstore        13
     375: lload         13
     377: l2d
     378: ldc2_w        #33                 // double 1000000.0d
     381: invokestatic  #35                 // Method org/apache/dubbo/common/profiler/ProfilerSwitch.getWarnPercent:()D
     384: dmul
     385: ddiv
     386: aload         12
     388: invokevirtual #36                 // Method java/lang/Long.longValue:()J
     391: l2d
     392: dcmpl
     393: ifle          497
     396: new           #11                 // class java/lang/StringBuilder
     399: dup
     400: invokespecial #12                 // Method java/lang/StringBuilder."<init>":()V
     403: astore        15
     405: aload_1
     406: aload         15
     408: invokedynamic #37,  0             // InvokeDynamic #0:accept:(Ljava/lang/StringBuilder;)Ljava/util/function/Consumer;
     413: invokevirtual #38                 // Method org/apache/dubbo/rpc/RpcInvocation.foreachAttachment:(Ljava/util/function/Consumer;)V
     416: getstatic     #39                 // Field logger:Lorg/apache/dubbo/common/logger/ErrorTypeAwareLogger;
     419: ldc           #40                 // String 3-4
     421: ldc           #41                 // String
     423: ldc           #41                 // String
     425: ldc           #42                 // String [Dubbo-Consumer] execute service %s#%s cost %d.%06d ms, this invocation almost (maybe already) timeout. Timeout: %dms\ninvocation context:\n%sthread info: \n%s
     427: bipush        7
     429: anewarray     #43                 // class java/lang/Object
     432: dup
     433: iconst_0
     434: aload_1
     435: invokevirtual #44                 // Method org/apache/dubbo/rpc/RpcInvocation.getProtocolServiceKey:()Ljava/lang/String;
     438: aastore
     439: dup
     440: iconst_1
     441: aload_1
     442: invokevirtual #16                 // Method org/apache/dubbo/rpc/RpcInvocation.getMethodName:()Ljava/lang/String;
     445: aastore
     446: dup
     447: iconst_2
     448: lload         13
     450: ldc2_w        #45                 // long 1000000l
     453: ldiv
     454: invokestatic  #30                 // Method java/lang/Long.valueOf:(J)Ljava/lang/Long;
     457: aastore
     458: dup
     459: iconst_3
     460: lload         13
     462: ldc2_w        #45                 // long 1000000l
     465: lrem
     466: invokestatic  #30                 // Method java/lang/Long.valueOf:(J)Ljava/lang/Long;
     469: aastore
     470: dup
     471: iconst_4
     472: aload         12
     474: aastore
     475: dup
     476: iconst_5
     477: aload         15
     479: aastore
     480: dup
     481: bipush        6
     483: aload         5
     485: invokestatic  #47                 // Method org/apache/dubbo/common/profiler/Profiler.buildDetail:(Lorg/apache/dubbo/common/profiler/ProfilerEntry;)Ljava/lang/String;
     488: aastore
     489: invokestatic  #48                 // Method java/lang/String.format:(Ljava/lang/String;[Ljava/lang/Object;)Ljava/lang/String;
     492: invokeinterface #49,  5           // InterfaceMethod org/apache/dubbo/common/logger/ErrorTypeAwareLogger.warn:(Ljava/lang/String;Ljava/lang/String;Ljava/lang/String;Ljava/lang/String;)V
     497: aload         11
     499: athrow
     500: aload_0
     501: aload_1
     502: invokeinterface #23,  2           // InterfaceMethod org/apache/dubbo/rpc/Invoker.invoke:(Lorg/apache/dubbo/rpc/Invocation;)Lorg/apache/dubbo/rpc/Result;
     507: invokeinterface #24,  1           // InterfaceMethod org/apache/dubbo/rpc/Result.recreate:()Ljava/lang/Object;
     512: areturn
    Exception table:
       from    to  target type
         126   140   319   any
         319   321   319   any

  private static void lambda$invoke$0(java.lang.StringBuilder, java.util.Map$Entry);
    Code:
       0: aload_0
       1: aload_1
       2: invokeinterface #50,  1           // InterfaceMethod java/util/Map$Entry.getKey:()Ljava/lang/Object;
       7: checkcast     #51                 // class java/lang/String
      10: invokevirtual #14                 // Method java/lang/StringBuilder.append:(Ljava/lang/String;)Ljava/lang/StringBuilder;
      13: ldc           #52                 // String =
      15: invokevirtual #14                 // Method java/lang/StringBuilder.append:(Ljava/lang/String;)Ljava/lang/StringBuilder;
      18: aload_1
      19: invokeinterface #53,  1           // InterfaceMethod java/util/Map$Entry.getValue:()Ljava/lang/Object;
      24: invokevirtual #54                 // Method java/lang/StringBuilder.append:(Ljava/lang/Object;)Ljava/lang/StringBuilder;
      27: ldc           #55                 // String ;\n
      29: invokevirtual #14                 // Method java/lang/StringBuilder.append:(Ljava/lang/String;)Ljava/lang/StringBuilder;
      32: pop
      33: return

  static {};
    Code:
       0: ldc           #56                 // class org/apache/dubbo/rpc/proxy/InvokerInvocationHandler
       2: invokestatic  #57                 // Method org/apache/dubbo/common/logger/LoggerFactory.getErrorTypeAwareLogger:(Ljava/lang/Class;)Lorg/apache/dubbo/common/logger/ErrorTypeAwareLogger;
       5: putstatic     #39                 // Field logger:Lorg/apache/dubbo/common/logger/ErrorTypeAwareLogger;
       8: return
}
