Compiled from "InvokerInvocationHandler.java"
public class org.apache.dubbo.rpc.proxy.InvokerInvocationHandler implements java.lang.reflect.InvocationHandler {
  private static final org.apache.dubbo.common.logger.Logger logger;

  private final org.apache.dubbo.rpc.Invoker<?> invoker;

  private final org.apache.dubbo.rpc.model.ServiceModel serviceModel;

  private final java.lang.String protocolServiceKey;

  public org.apache.dubbo.rpc.proxy.InvokerInvocationHandler(org.apache.dubbo.rpc.Invoker<?>);
    Code:
       0: aload_0
       1: invokespecial #1                  // Method java/lang/Object."<init>":()V
       4: aload_0
       5: aload_1
       6: putfield      #2                  // Field invoker:Lorg/apache/dubbo/rpc/Invoker;
       9: aload_0
      10: getfield      #2                  // Field invoker:Lorg/apache/dubbo/rpc/Invoker;
      13: invokeinterface #3,  1            // InterfaceMethod org/apache/dubbo/rpc/Invoker.getUrl:()Lorg/apache/dubbo/common/URL;
      18: astore_2
      19: aload_0
      20: aload_2
      21: invokevirtual #4                  // Method org/apache/dubbo/common/URL.getProtocolServiceKey:()Ljava/lang/String;
      24: putfield      #5                  // Field protocolServiceKey:Ljava/lang/String;
      27: aload_0
      28: aload_2
      29: invokevirtual #6                  // Method org/apache/dubbo/common/URL.getServiceModel:()Lorg/apache/dubbo/rpc/model/ServiceModel;
      32: putfield      #7                  // Field serviceModel:Lorg/apache/dubbo/rpc/model/ServiceModel;
      35: return

  public java.lang.Object invoke(java.lang.Object, java.lang.reflect.Method, java.lang.Object[]) throws java.lang.Throwable;
    Code:
       0: aload_2
       1: invokevirtual #8                  // Method java/lang/reflect/Method.getDeclaringClass:()Ljava/lang/Class;
       4: ldc           #9                  // class java/lang/Object
       6: if_acmpne     19
       9: aload_2
      10: aload_0
      11: getfield      #2                  // Field invoker:Lorg/apache/dubbo/rpc/Invoker;
      14: aload_3
      15: invokevirtual #10                 // Method java/lang/reflect/Method.invoke:(Ljava/lang/Object;[Ljava/lang/Object;)Ljava/lang/Object;
      18: areturn
      19: aload_2
      20: invokevirtual #11                 // Method java/lang/reflect/Method.getName:()Ljava/lang/String;
      23: astore        4
      25: aload_2
      26: invokevirtual #12                 // Method java/lang/reflect/Method.getParameterTypes:()[Ljava/lang/Class;
      29: astore        5
      31: aload         5
      33: arraylength
      34: ifne          97
      37: ldc           #13                 // String toString
      39: aload         4
      41: invokevirtual #14                 // Method java/lang/String.equals:(Ljava/lang/Object;)Z
      44: ifeq          55
      47: aload_0
      48: getfield      #2                  // Field invoker:Lorg/apache/dubbo/rpc/Invoker;
      51: invokevirtual #15                 // Method java/lang/Object.toString:()Ljava/lang/String;
      54: areturn
      55: ldc           #16                 // String $destroy
      57: aload         4
      59: invokevirtual #14                 // Method java/lang/String.equals:(Ljava/lang/Object;)Z
      62: ifeq          76
      65: aload_0
      66: getfield      #2                  // Field invoker:Lorg/apache/dubbo/rpc/Invoker;
      69: invokeinterface #17,  1           // InterfaceMethod org/apache/dubbo/rpc/Invoker.destroy:()V
      74: aconst_null
      75: areturn
      76: ldc           #18                 // String hashCode
      78: aload         4
      80: invokevirtual #14                 // Method java/lang/String.equals:(Ljava/lang/Object;)Z
      83: ifeq          128
      86: aload_0
      87: getfield      #2                  // Field invoker:Lorg/apache/dubbo/rpc/Invoker;
      90: invokevirtual #19                 // Method java/lang/Object.hashCode:()I
      93: invokestatic  #20                 // Method java/lang/Integer.valueOf:(I)Ljava/lang/Integer;
      96: areturn
      97: aload         5
      99: arraylength
     100: iconst_1
     101: if_icmpne     128
     104: ldc           #21                 // String equals
     106: aload         4
     108: invokevirtual #14                 // Method java/lang/String.equals:(Ljava/lang/Object;)Z
     111: ifeq          128
     114: aload_0
     115: getfield      #2                  // Field invoker:Lorg/apache/dubbo/rpc/Invoker;
     118: aload_3
     119: iconst_0
     120: aaload
     121: invokevirtual #22                 // Method java/lang/Object.equals:(Ljava/lang/Object;)Z
     124: invokestatic  #23                 // Method java/lang/Boolean.valueOf:(Z)Ljava/lang/Boolean;
     127: areturn
     128: new           #24                 // class org/apache/dubbo/rpc/RpcInvocation
     131: dup
     132: aload_0
     133: getfield      #7                  // Field serviceModel:Lorg/apache/dubbo/rpc/model/ServiceModel;
     136: aload_2
     137: invokevirtual #11                 // Method java/lang/reflect/Method.getName:()Ljava/lang/String;
     140: aload_0
     141: getfield      #2                  // Field invoker:Lorg/apache/dubbo/rpc/Invoker;
     144: invokeinterface #25,  1           // InterfaceMethod org/apache/dubbo/rpc/Invoker.getInterface:()Ljava/lang/Class;
     149: invokevirtual #26                 // Method java/lang/Class.getName:()Ljava/lang/String;
     152: aload_0
     153: getfield      #5                  // Field protocolServiceKey:Ljava/lang/String;
     156: aload_2
     157: invokevirtual #12                 // Method java/lang/reflect/Method.getParameterTypes:()[Ljava/lang/Class;
     160: aload_3
     161: invokespecial #27                 // Method org/apache/dubbo/rpc/RpcInvocation."<init>":(Lorg/apache/dubbo/rpc/model/ServiceModel;Ljava/lang/String;Ljava/lang/String;Ljava/lang/String;[Ljava/lang/Class;[Ljava/lang/Object;)V
     164: astore        6
     166: aload_0
     167: getfield      #7                  // Field serviceModel:Lorg/apache/dubbo/rpc/model/ServiceModel;
     170: instanceof    #28                 // class org/apache/dubbo/rpc/model/ConsumerModel
     173: ifeq          207
     176: aload         6
     178: ldc           #30                 // String consumerModel
     180: aload_0
     181: getfield      #7                  // Field serviceModel:Lorg/apache/dubbo/rpc/model/ServiceModel;
     184: invokevirtual #31                 // Method org/apache/dubbo/rpc/RpcInvocation.put:(Ljava/lang/Object;Ljava/lang/Object;)Ljava/lang/Object;
     187: pop
     188: aload         6
     190: ldc           #32                 // String methodModel
     192: aload_0
     193: getfield      #7                  // Field serviceModel:Lorg/apache/dubbo/rpc/model/ServiceModel;
     196: checkcast     #28                 // class org/apache/dubbo/rpc/model/ConsumerModel
     199: aload_2
     200: invokevirtual #33                 // Method org/apache/dubbo/rpc/model/ConsumerModel.getMethodModel:(Ljava/lang/reflect/Method;)Lorg/apache/dubbo/rpc/model/ConsumerMethodModel;
     203: invokevirtual #31                 // Method org/apache/dubbo/rpc/RpcInvocation.put:(Ljava/lang/Object;Ljava/lang/Object;)Ljava/lang/Object;
     206: pop
     207: aload_0
     208: getfield      #2                  // Field invoker:Lorg/apache/dubbo/rpc/Invoker;
     211: aload         6
     213: invokestatic  #34                 // Method org/apache/dubbo/rpc/proxy/InvocationUtil.invoke:(Lorg/apache/dubbo/rpc/Invoker;Lorg/apache/dubbo/rpc/RpcInvocation;)Ljava/lang/Object;
     216: areturn

  static {};
    Code:
       0: ldc           #35                 // class org/apache/dubbo/rpc/proxy/InvokerInvocationHandler
       2: invokestatic  #36                 // Method org/apache/dubbo/common/logger/LoggerFactory.getLogger:(Ljava/lang/Class;)Lorg/apache/dubbo/common/logger/Logger;
       5: putstatic     #37                 // Field logger:Lorg/apache/dubbo/common/logger/Logger;
       8: return
}
