Compiled from "MethodInvoker.java"
public class org.apache.dubbo.rpc.proxy.MethodInvoker$CompositeMethodInvoker implements org.apache.dubbo.rpc.proxy.MethodInvoker {
  private final java.util.Map<java.lang.String, org.apache.dubbo.rpc.proxy.MethodInvoker> invokers;

  public org.apache.dubbo.rpc.proxy.MethodInvoker$CompositeMethodInvoker(java.util.Map<java.lang.String, org.apache.dubbo.rpc.proxy.MethodInvoker>);
    Code:
       0: aload_0
       1: invokespecial #1                  // Method java/lang/Object."<init>":()V
       4: aload_0
       5: aload_1
       6: putfield      #2                  // Field invokers:Ljava/util/Map;
       9: return

  java.util.Map<java.lang.String, org.apache.dubbo.rpc.proxy.MethodInvoker> getInvokers();
    Code:
       0: aload_0
       1: getfield      #2                  // Field invokers:Ljava/util/Map;
       4: areturn

  public java.lang.Object invoke(java.lang.Object, java.lang.String, java.lang.Class<?>[], java.lang.Object[]) throws java.lang.Throwable;
    Code:
       0: aload_0
       1: getfield      #2                  // Field invokers:Ljava/util/Map;
       4: aload_2
       5: invokeinterface #3,  2            // InterfaceMethod java/util/Map.get:(Ljava/lang/Object;)Ljava/lang/Object;
      10: checkcast     #4                  // class org/apache/dubbo/rpc/proxy/MethodInvoker
      13: astore        5
      15: aload         5
      17: ifnonnull     64
      20: new           #5                  // class java/lang/NoSuchMethodException
      23: dup
      24: new           #6                  // class java/lang/StringBuilder
      27: dup
      28: invokespecial #7                  // Method java/lang/StringBuilder."<init>":()V
      31: aload_1
      32: invokevirtual #8                  // Method java/lang/Object.getClass:()Ljava/lang/Class;
      35: invokevirtual #9                  // Method java/lang/Class.getName:()Ljava/lang/String;
      38: invokevirtual #10                 // Method java/lang/StringBuilder.append:(Ljava/lang/String;)Ljava/lang/StringBuilder;
      41: ldc           #11                 // String .
      43: invokevirtual #10                 // Method java/lang/StringBuilder.append:(Ljava/lang/String;)Ljava/lang/StringBuilder;
      46: aload_2
      47: invokevirtual #10                 // Method java/lang/StringBuilder.append:(Ljava/lang/String;)Ljava/lang/StringBuilder;
      50: aload_3
      51: invokestatic  #12                 // Method java/util/Arrays.toString:([Ljava/lang/Object;)Ljava/lang/String;
      54: invokevirtual #10                 // Method java/lang/StringBuilder.append:(Ljava/lang/String;)Ljava/lang/StringBuilder;
      57: invokevirtual #13                 // Method java/lang/StringBuilder.toString:()Ljava/lang/String;
      60: invokespecial #14                 // Method java/lang/NoSuchMethodException."<init>":(Ljava/lang/String;)V
      63: athrow
      64: aload         5
      66: aload_1
      67: aload_2
      68: aload_3
      69: aload         4
      71: invokeinterface #15,  5           // InterfaceMethod org/apache/dubbo/rpc/proxy/MethodInvoker.invoke:(Ljava/lang/Object;Ljava/lang/String;[Ljava/lang/Class;[Ljava/lang/Object;)Ljava/lang/Object;
      76: areturn
}
