Compiled from "MethodInvoker.java"
public interface org.apache.dubbo.rpc.proxy.MethodInvoker {
  public abstract java.lang.Object invoke(java.lang.Object, java.lang.String, java.lang.Class<?>[], java.lang.Object[]) throws java.lang.Throwable;

  public static org.apache.dubbo.rpc.proxy.MethodInvoker newInstance(java.lang.Class<?>);
    Code:
       0: aload_0
       1: invokevirtual #1                  // Method java/lang/Class.getMethods:()[Ljava/lang/reflect/Method;
       4: astore_1
       5: new           #2                  // class java/util/HashMap
       8: dup
       9: invokespecial #3                  // Method java/util/HashMap."<init>":()V
      12: astore_2
      13: new           #2                  // class java/util/HashMap
      16: dup
      17: invokespecial #3                  // Method java/util/HashMap."<init>":()V
      20: astore_3
      21: aload_1
      22: astore        4
      24: aload         4
      26: arraylength
      27: istore        5
      29: iconst_0
      30: istore        6
      32: iload         6
      34: iload         5
      36: if_icmpge     79
      39: aload         4
      41: iload         6
      43: aaload
      44: astore        7
      46: aload_3
      47: aload         7
      49: invokevirtual #4                  // Method java/lang/reflect/Method.getName:()Ljava/lang/String;
      52: invokedynamic #5,  0              // InvokeDynamic #0:apply:()Ljava/util/function/Function;
      57: invokeinterface #6,  3            // InterfaceMethod java/util/Map.computeIfAbsent:(Ljava/lang/Object;Ljava/util/function/Function;)Ljava/lang/Object;
      62: checkcast     #7                  // class java/util/List
      65: aload         7
      67: invokeinterface #8,  2            // InterfaceMethod java/util/List.add:(Ljava/lang/Object;)Z
      72: pop
      73: iinc          6, 1
      76: goto          32
      79: aload_3
      80: invokeinterface #9,  1            // InterfaceMethod java/util/Map.entrySet:()Ljava/util/Set;
      85: astore        4
      87: aload         4
      89: invokeinterface #10,  1           // InterfaceMethod java/util/Set.iterator:()Ljava/util/Iterator;
      94: astore        5
      96: aload         5
      98: invokeinterface #11,  1           // InterfaceMethod java/util/Iterator.hasNext:()Z
     103: ifeq          204
     106: aload         5
     108: invokeinterface #12,  1           // InterfaceMethod java/util/Iterator.next:()Ljava/lang/Object;
     113: checkcast     #13                 // class java/util/Map$Entry
     116: astore        6
     118: aload         6
     120: invokeinterface #14,  1           // InterfaceMethod java/util/Map$Entry.getKey:()Ljava/lang/Object;
     125: checkcast     #15                 // class java/lang/String
     128: astore        7
     130: aload         6
     132: invokeinterface #16,  1           // InterfaceMethod java/util/Map$Entry.getValue:()Ljava/lang/Object;
     137: checkcast     #7                  // class java/util/List
     140: astore        8
     142: aload         8
     144: invokeinterface #17,  1           // InterfaceMethod java/util/List.size:()I
     149: iconst_1
     150: if_icmpne     183
     153: aload_2
     154: aload         7
     156: new           #18                 // class org/apache/dubbo/rpc/proxy/MethodInvoker$SingleMethodInvoker
     159: dup
     160: aload         8
     162: iconst_0
     163: invokeinterface #19,  2           // InterfaceMethod java/util/List.get:(I)Ljava/lang/Object;
     168: checkcast     #20                 // class java/lang/reflect/Method
     171: invokespecial #21                 // Method org/apache/dubbo/rpc/proxy/MethodInvoker$SingleMethodInvoker."<init>":(Ljava/lang/reflect/Method;)V
     174: invokeinterface #22,  3           // InterfaceMethod java/util/Map.put:(Ljava/lang/Object;Ljava/lang/Object;)Ljava/lang/Object;
     179: pop
     180: goto          96
     183: aload_2
     184: aload         7
     186: new           #23                 // class org/apache/dubbo/rpc/proxy/MethodInvoker$OverloadMethodInvoker
     189: dup
     190: aload         8
     192: invokespecial #24                 // Method org/apache/dubbo/rpc/proxy/MethodInvoker$OverloadMethodInvoker."<init>":(Ljava/util/List;)V
     195: invokeinterface #22,  3           // InterfaceMethod java/util/Map.put:(Ljava/lang/Object;Ljava/lang/Object;)Ljava/lang/Object;
     200: pop
     201: goto          96
     204: new           #25                 // class org/apache/dubbo/rpc/proxy/MethodInvoker$CompositeMethodInvoker
     207: dup
     208: aload_2
     209: invokespecial #26                 // Method org/apache/dubbo/rpc/proxy/MethodInvoker$CompositeMethodInvoker."<init>":(Ljava/util/Map;)V
     212: areturn

  private static java.util.List lambda$newInstance$0(java.lang.String);
    Code:
       0: new           #27                 // class java/util/ArrayList
       3: dup
       4: invokespecial #28                 // Method java/util/ArrayList."<init>":()V
       7: areturn
}
