Compiled from "MethodInvoker.java"
public class org.apache.dubbo.rpc.proxy.MethodInvoker$SingleMethodInvoker implements org.apache.dubbo.rpc.proxy.MethodInvoker {
  private final java.lang.reflect.Method method;

  org.apache.dubbo.rpc.proxy.MethodInvoker$SingleMethodInvoker(java.lang.reflect.Method);
    Code:
       0: aload_0
       1: invokespecial #1                  // Method java/lang/Object."<init>":()V
       4: aload_0
       5: aload_1
       6: putfield      #2                  // Field method:Ljava/lang/reflect/Method;
       9: return

  public java.lang.Object invoke(java.lang.Object, java.lang.String, java.lang.Class<?>[], java.lang.Object[]) throws java.lang.Throwable;
    Code:
       0: aload_0
       1: getfield      #2                  // Field method:Ljava/lang/reflect/Method;
       4: aload_1
       5: aload         4
       7: invokevirtual #3                  // Method java/lang/reflect/Method.invoke:(Ljava/lang/Object;[Ljava/lang/Object;)Ljava/lang/Object;
      10: areturn
}
