Compiled from "MethodInvoker.java"
public class org.apache.dubbo.rpc.proxy.MethodInvoker$OverloadMethodInvoker implements org.apache.dubbo.rpc.proxy.MethodInvoker {
  private final org.apache.dubbo.rpc.proxy.MethodInvoker$OverloadMethodInvoker$MethodMeta[] methods;

  org.apache.dubbo.rpc.proxy.MethodInvoker$OverloadMethodInvoker(java.util.List<java.lang.reflect.Method>);
    Code:
       0: aload_0
       1: invokespecial #1                  // Method java/lang/Object."<init>":()V
       4: aload_0
       5: aload_1
       6: invokeinterface #2,  1            // InterfaceMethod java/util/List.stream:()Ljava/util/stream/Stream;
      11: invokedynamic #3,  0              // InvokeDynamic #0:apply:()Ljava/util/function/Function;
      16: invokeinterface #4,  2            // InterfaceMethod java/util/stream/Stream.map:(Ljava/util/function/Function;)Ljava/util/stream/Stream;
      21: invokedynamic #5,  0              // InvokeDynamic #1:apply:()Ljava/util/function/IntFunction;
      26: invokeinterface #6,  2            // InterfaceMethod java/util/stream/Stream.toArray:(Ljava/util/function/IntFunction;)[Ljava/lang/Object;
      31: checkcast     #7                  // class "[Lorg/apache/dubbo/rpc/proxy/MethodInvoker$OverloadMethodInvoker$MethodMeta;"
      34: putfield      #8                  // Field methods:[Lorg/apache/dubbo/rpc/proxy/MethodInvoker$OverloadMethodInvoker$MethodMeta;
      37: return

  public java.lang.Object invoke(java.lang.Object, java.lang.String, java.lang.Class<?>[], java.lang.Object[]) throws java.lang.Throwable;
    Code:
       0: aload_0
       1: getfield      #8                  // Field methods:[Lorg/apache/dubbo/rpc/proxy/MethodInvoker$OverloadMethodInvoker$MethodMeta;
       4: astore        5
       6: aload         5
       8: arraylength
       9: istore        6
      11: iconst_0
      12: istore        7
      14: iload         7
      16: iload         6
      18: if_icmpge     58
      21: aload         5
      23: iload         7
      25: aaload
      26: astore        8
      28: aload         8
      30: invokevirtual #9                  // Method org/apache/dubbo/rpc/proxy/MethodInvoker$OverloadMethodInvoker$MethodMeta.getParametersType:()[Ljava/lang/Class;
      33: aload_3
      34: invokestatic  #10                 // Method java/util/Arrays.equals:([Ljava/lang/Object;[Ljava/lang/Object;)Z
      37: ifeq          52
      40: aload         8
      42: invokevirtual #11                 // Method org/apache/dubbo/rpc/proxy/MethodInvoker$OverloadMethodInvoker$MethodMeta.getMethod:()Ljava/lang/reflect/Method;
      45: aload_1
      46: aload         4
      48: invokevirtual #12                 // Method java/lang/reflect/Method.invoke:(Ljava/lang/Object;[Ljava/lang/Object;)Ljava/lang/Object;
      51: areturn
      52: iinc          7, 1
      55: goto          14
      58: new           #13                 // class java/lang/NoSuchMethodException
      61: dup
      62: new           #14                 // class java/lang/StringBuilder
      65: dup
      66: invokespecial #15                 // Method java/lang/StringBuilder."<init>":()V
      69: aload_1
      70: invokevirtual #16                 // Method java/lang/Object.getClass:()Ljava/lang/Class;
      73: invokevirtual #17                 // Method java/lang/Class.getName:()Ljava/lang/String;
      76: invokevirtual #18                 // Method java/lang/StringBuilder.append:(Ljava/lang/String;)Ljava/lang/StringBuilder;
      79: ldc           #19                 // String .
      81: invokevirtual #18                 // Method java/lang/StringBuilder.append:(Ljava/lang/String;)Ljava/lang/StringBuilder;
      84: aload_2
      85: invokevirtual #18                 // Method java/lang/StringBuilder.append:(Ljava/lang/String;)Ljava/lang/StringBuilder;
      88: aload_3
      89: invokestatic  #20                 // Method java/util/Arrays.toString:([Ljava/lang/Object;)Ljava/lang/String;
      92: invokevirtual #18                 // Method java/lang/StringBuilder.append:(Ljava/lang/String;)Ljava/lang/StringBuilder;
      95: invokevirtual #21                 // Method java/lang/StringBuilder.toString:()Ljava/lang/String;
      98: invokespecial #22                 // Method java/lang/NoSuchMethodException."<init>":(Ljava/lang/String;)V
     101: athrow

  private static org.apache.dubbo.rpc.proxy.MethodInvoker$OverloadMethodInvoker$MethodMeta[] lambda$new$1(int);
    Code:
       0: iload_0
       1: anewarray     #23                 // class org/apache/dubbo/rpc/proxy/MethodInvoker$OverloadMethodInvoker$MethodMeta
       4: areturn

  private static org.apache.dubbo.rpc.proxy.MethodInvoker$OverloadMethodInvoker$MethodMeta lambda$new$0(java.lang.reflect.Method);
    Code:
       0: new           #23                 // class org/apache/dubbo/rpc/proxy/MethodInvoker$OverloadMethodInvoker$MethodMeta
       3: dup
       4: aload_0
       5: aconst_null
       6: invokespecial #24                 // Method org/apache/dubbo/rpc/proxy/MethodInvoker$OverloadMethodInvoker$MethodMeta."<init>":(Ljava/lang/reflect/Method;Lorg/apache/dubbo/rpc/proxy/MethodInvoker$1;)V
       9: areturn
}
