Compiled from "MethodInvoker.java"
class org.apache.dubbo.rpc.proxy.MethodInvoker$OverloadMethodInvoker$MethodMeta {
  private final java.lang.reflect.Method method;

  private final java.lang.Class<?>[] parametersType;

  private org.apache.dubbo.rpc.proxy.MethodInvoker$OverloadMethodInvoker$MethodMeta(java.lang.reflect.Method);
    Code:
       0: aload_0
       1: invokespecial #2                  // Method java/lang/Object."<init>":()V
       4: aload_0
       5: aload_1
       6: putfield      #3                  // Field method:Ljava/lang/reflect/Method;
       9: aload_0
      10: aload_1
      11: invokevirtual #4                  // Method java/lang/reflect/Method.getParameterTypes:()[Ljava/lang/Class;
      14: putfield      #5                  // Field parametersType:[Ljava/lang/Class;
      17: return

  public java.lang.reflect.Method getMethod();
    Code:
       0: aload_0
       1: getfield      #3                  // Field method:Ljava/lang/reflect/Method;
       4: areturn

  public java.lang.Class<?>[] getParametersType();
    Code:
       0: aload_0
       1: getfield      #5                  // Field parametersType:[Ljava/lang/Class;
       4: areturn

  org.apache.dubbo.rpc.proxy.MethodInvoker$OverloadMethodInvoker$MethodMeta(java.lang.reflect.Method, org.apache.dubbo.rpc.proxy.MethodInvoker$1);
    Code:
       0: aload_0
       1: aload_1
       2: invokespecial #1                  // Method "<init>":(Ljava/lang/reflect/Method;)V
       5: return
}
