Compiled from "AbstractMetadataReportFactory.java"
public abstract class org.apache.dubbo.metadata.report.support.AbstractMetadataReportFactory implements org.apache.dubbo.metadata.report.MetadataReportFactory {
  private static final org.apache.dubbo.common.logger.ErrorTypeAwareLogger logger;

  private static final java.lang.String EXPORT_KEY;

  private static final java.lang.String REFER_KEY;

  private final java.util.concurrent.locks.ReentrantLock lock;

  private final java.util.Map<java.lang.String, org.apache.dubbo.metadata.report.MetadataReport> serviceStoreMap;

  public org.apache.dubbo.metadata.report.support.AbstractMetadataReportFactory();
    Code:
       0: aload_0
       1: invokespecial #3                  // Method java/lang/Object."<init>":()V
       4: aload_0
       5: new           #4                  // class java/util/concurrent/locks/ReentrantLock
       8: dup
       9: invokespecial #5                  // Method java/util/concurrent/locks/ReentrantLock."<init>":()V
      12: putfield      #6                  // Field lock:Ljava/util/concurrent/locks/ReentrantLock;
      15: aload_0
      16: new           #7                  // class java/util/concurrent/ConcurrentHashMap
      19: dup
      20: invokespecial #8                  // Method java/util/concurrent/ConcurrentHashMap."<init>":()V
      23: putfield      #9                  // Field serviceStoreMap:Ljava/util/Map;
      26: return

  public org.apache.dubbo.metadata.report.MetadataReport getMetadataReport(org.apache.dubbo.common.URL);
    Code:
       0: aload_1
       1: ldc           #10                 // class org/apache/dubbo/metadata/report/MetadataReport
       3: invokevirtual #11                 // Method java/lang/Class.getName:()Ljava/lang/String;
       6: invokevirtual #12                 // Method org/apache/dubbo/common/URL.setPath:(Ljava/lang/String;)Lorg/apache/dubbo/common/URL;
       9: iconst_2
      10: anewarray     #13                 // class java/lang/String
      13: dup
      14: iconst_0
      15: ldc           #15                 // String export
      17: aastore
      18: dup
      19: iconst_1
      20: ldc           #16                 // String refer
      22: aastore
      23: invokevirtual #17                 // Method org/apache/dubbo/common/URL.removeParameters:([Ljava/lang/String;)Lorg/apache/dubbo/common/URL;
      26: astore_1
      27: aload_1
      28: invokevirtual #18                 // Method org/apache/dubbo/common/URL.toServiceString:()Ljava/lang/String;
      31: astore_2
      32: aload_0
      33: getfield      #9                  // Field serviceStoreMap:Ljava/util/Map;
      36: aload_2
      37: invokeinterface #19,  2           // InterfaceMethod java/util/Map.get:(Ljava/lang/Object;)Ljava/lang/Object;
      42: checkcast     #10                 // class org/apache/dubbo/metadata/report/MetadataReport
      45: astore_3
      46: aload_3
      47: ifnull        52
      50: aload_3
      51: areturn
      52: aload_0
      53: getfield      #6                  // Field lock:Ljava/util/concurrent/locks/ReentrantLock;
      56: invokevirtual #20                 // Method java/util/concurrent/locks/ReentrantLock.lock:()V
      59: aload_0
      60: getfield      #9                  // Field serviceStoreMap:Ljava/util/Map;
      63: aload_2
      64: invokeinterface #19,  2           // InterfaceMethod java/util/Map.get:(Ljava/lang/Object;)Ljava/lang/Object;
      69: checkcast     #10                 // class org/apache/dubbo/metadata/report/MetadataReport
      72: astore_3
      73: aload_3
      74: ifnull        90
      77: aload_3
      78: astore        4
      80: aload_0
      81: getfield      #6                  // Field lock:Ljava/util/concurrent/locks/ReentrantLock;
      84: invokevirtual #21                 // Method java/util/concurrent/locks/ReentrantLock.unlock:()V
      87: aload         4
      89: areturn
      90: aload_1
      91: ldc           #22                 // String check
      93: iconst_1
      94: invokevirtual #23                 // Method org/apache/dubbo/common/URL.getParameter:(Ljava/lang/String;Z)Z
      97: ifeq          111
     100: aload_1
     101: invokevirtual #24                 // Method org/apache/dubbo/common/URL.getPort:()I
     104: ifeq          111
     107: iconst_1
     108: goto          112
     111: iconst_0
     112: istore        4
     114: aload_0
     115: aload_1
     116: invokevirtual #25                 // Method createMetadataReport:(Lorg/apache/dubbo/common/URL;)Lorg/apache/dubbo/metadata/report/MetadataReport;
     119: astore_3
     120: goto          154
     123: astore        5
     125: iload         4
     127: ifne          151
     130: getstatic     #27                 // Field logger:Lorg/apache/dubbo/common/logger/ErrorTypeAwareLogger;
     133: ldc           #28                 // String 3-2
     135: ldc           #29                 // String
     137: ldc           #29                 // String
     139: ldc           #30                 // String The metadata reporter failed to initialize
     141: aload         5
     143: invokeinterface #31,  6           // InterfaceMethod org/apache/dubbo/common/logger/ErrorTypeAwareLogger.warn:(Ljava/lang/String;Ljava/lang/String;Ljava/lang/String;Ljava/lang/String;Ljava/lang/Throwable;)V
     148: goto          154
     151: aload         5
     153: athrow
     154: iload         4
     156: ifeq          190
     159: aload_3
     160: ifnonnull     190
     163: new           #32                 // class java/lang/IllegalStateException
     166: dup
     167: new           #33                 // class java/lang/StringBuilder
     170: dup
     171: invokespecial #34                 // Method java/lang/StringBuilder."<init>":()V
     174: ldc           #35                 // String Can not create metadata Report
     176: invokevirtual #36                 // Method java/lang/StringBuilder.append:(Ljava/lang/String;)Ljava/lang/StringBuilder;
     179: aload_1
     180: invokevirtual #37                 // Method java/lang/StringBuilder.append:(Ljava/lang/Object;)Ljava/lang/StringBuilder;
     183: invokevirtual #38                 // Method java/lang/StringBuilder.toString:()Ljava/lang/String;
     186: invokespecial #39                 // Method java/lang/IllegalStateException."<init>":(Ljava/lang/String;)V
     189: athrow
     190: aload_3
     191: ifnull        206
     194: aload_0
     195: getfield      #9                  // Field serviceStoreMap:Ljava/util/Map;
     198: aload_2
     199: aload_3
     200: invokeinterface #40,  3           // InterfaceMethod java/util/Map.put:(Ljava/lang/Object;Ljava/lang/Object;)Ljava/lang/Object;
     205: pop
     206: aload_3
     207: astore        5
     209: aload_0
     210: getfield      #6                  // Field lock:Ljava/util/concurrent/locks/ReentrantLock;
     213: invokevirtual #21                 // Method java/util/concurrent/locks/ReentrantLock.unlock:()V
     216: aload         5
     218: areturn
     219: astore        6
     221: aload_0
     222: getfield      #6                  // Field lock:Ljava/util/concurrent/locks/ReentrantLock;
     225: invokevirtual #21                 // Method java/util/concurrent/locks/ReentrantLock.unlock:()V
     228: aload         6
     230: athrow
    Exception table:
       from    to  target type
         114   120   123   Class java/lang/Exception
          59    80   219   any
          90   209   219   any
         219   221   219   any

  public void destroy();
    Code:
       0: aload_0
       1: getfield      #6                  // Field lock:Ljava/util/concurrent/locks/ReentrantLock;
       4: invokevirtual #20                 // Method java/util/concurrent/locks/ReentrantLock.lock:()V
       7: aload_0
       8: getfield      #9                  // Field serviceStoreMap:Ljava/util/Map;
      11: invokeinterface #41,  1           // InterfaceMethod java/util/Map.values:()Ljava/util/Collection;
      16: invokeinterface #42,  1           // InterfaceMethod java/util/Collection.iterator:()Ljava/util/Iterator;
      21: astore_1
      22: aload_1
      23: invokeinterface #43,  1           // InterfaceMethod java/util/Iterator.hasNext:()Z
      28: ifeq          73
      31: aload_1
      32: invokeinterface #44,  1           // InterfaceMethod java/util/Iterator.next:()Ljava/lang/Object;
      37: checkcast     #10                 // class org/apache/dubbo/metadata/report/MetadataReport
      40: astore_2
      41: aload_2
      42: invokeinterface #45,  1           // InterfaceMethod org/apache/dubbo/metadata/report/MetadataReport.destroy:()V
      47: goto          70
      50: astore_3
      51: getstatic     #27                 // Field logger:Lorg/apache/dubbo/common/logger/ErrorTypeAwareLogger;
      54: ldc           #47                 // String 0-12
      56: ldc           #29                 // String
      58: ldc           #29                 // String
      60: aload_3
      61: invokevirtual #48                 // Method java/lang/Throwable.getMessage:()Ljava/lang/String;
      64: aload_3
      65: invokeinterface #31,  6           // InterfaceMethod org/apache/dubbo/common/logger/ErrorTypeAwareLogger.warn:(Ljava/lang/String;Ljava/lang/String;Ljava/lang/String;Ljava/lang/String;Ljava/lang/Throwable;)V
      70: goto          22
      73: aload_0
      74: getfield      #9                  // Field serviceStoreMap:Ljava/util/Map;
      77: invokeinterface #49,  1           // InterfaceMethod java/util/Map.clear:()V
      82: aload_0
      83: getfield      #6                  // Field lock:Ljava/util/concurrent/locks/ReentrantLock;
      86: invokevirtual #21                 // Method java/util/concurrent/locks/ReentrantLock.unlock:()V
      89: goto          104
      92: astore        4
      94: aload_0
      95: getfield      #6                  // Field lock:Ljava/util/concurrent/locks/ReentrantLock;
      98: invokevirtual #21                 // Method java/util/concurrent/locks/ReentrantLock.unlock:()V
     101: aload         4
     103: athrow
     104: return
    Exception table:
       from    to  target type
          41    47    50   Class java/lang/Throwable
           7    82    92   any
          92    94    92   any

  protected abstract org.apache.dubbo.metadata.report.MetadataReport createMetadataReport(org.apache.dubbo.common.URL);

  static {};
    Code:
       0: ldc           #14                 // class org/apache/dubbo/metadata/report/support/AbstractMetadataReportFactory
       2: invokestatic  #50                 // Method org/apache/dubbo/common/logger/LoggerFactory.getErrorTypeAwareLogger:(Ljava/lang/Class;)Lorg/apache/dubbo/common/logger/ErrorTypeAwareLogger;
       5: putstatic     #27                 // Field logger:Lorg/apache/dubbo/common/logger/ErrorTypeAwareLogger;
       8: return
}
