Compiled from "AbstractMetadataReport.java"
class org.apache.dubbo.metadata.report.support.AbstractMetadataReport$SaveProperties implements java.lang.Runnable {
  private long version;

  final org.apache.dubbo.metadata.report.support.AbstractMetadataReport this$0;

  private org.apache.dubbo.metadata.report.support.AbstractMetadataReport$SaveProperties(org.apache.dubbo.metadata.report.support.AbstractMetadataReport, long);
    Code:
       0: aload_0
       1: aload_1
       2: putfield      #2                  // Field this$0:Lorg/apache/dubbo/metadata/report/support/AbstractMetadataReport;
       5: aload_0
       6: invokespecial #3                  // Method java/lang/Object."<init>":()V
       9: aload_0
      10: lload_2
      11: putfield      #4                  // Field version:J
      14: return

  public void run();
    Code:
       0: aload_0
       1: getfield      #2                  // Field this$0:Lorg/apache/dubbo/metadata/report/support/AbstractMetadataReport;
       4: aload_0
       5: getfield      #4                  // Field version:J
       8: invokestatic  #5                  // Method org/apache/dubbo/metadata/report/support/AbstractMetadataReport.access$100:(Lorg/apache/dubbo/metadata/report/support/AbstractMetadataReport;J)V
      11: return

  org.apache.dubbo.metadata.report.support.AbstractMetadataReport$SaveProperties(org.apache.dubbo.metadata.report.support.AbstractMetadataReport, long, org.apache.dubbo.metadata.report.support.AbstractMetadataReport$1);
    Code:
       0: aload_0
       1: aload_1
       2: lload_2
       3: invokespecial #1                  // Method "<init>":(Lorg/apache/dubbo/metadata/report/support/AbstractMetadataReport;J)V
       6: return
}
