Compiled from "NopMetadataReport.java"
public class org.apache.dubbo.metadata.report.support.NopMetadataReport implements org.apache.dubbo.metadata.report.MetadataReport {
  public org.apache.dubbo.metadata.report.support.NopMetadataReport();
    Code:
       0: aload_0
       1: invokespecial #1                  // Method java/lang/Object."<init>":()V
       4: return

  public void storeProviderMetadata(org.apache.dubbo.metadata.report.identifier.MetadataIdentifier, org.apache.dubbo.metadata.definition.model.ServiceDefinition);
    Code:
       0: return

  public java.lang.String getServiceDefinition(org.apache.dubbo.metadata.report.identifier.MetadataIdentifier);
    Code:
       0: aconst_null
       1: areturn

  public void storeConsumerMetadata(org.apache.dubbo.metadata.report.identifier.MetadataIdentifier, java.util.Map<java.lang.String, java.lang.String>);
    Code:
       0: return

  public java.util.List<java.lang.String> getExportedURLs(org.apache.dubbo.metadata.report.identifier.ServiceMetadataIdentifier);
    Code:
       0: aconst_null
       1: areturn

  public void destroy();
    Code:
       0: return

  public void saveServiceMetadata(org.apache.dubbo.metadata.report.identifier.ServiceMetadataIdentifier, org.apache.dubbo.common.URL);
    Code:
       0: return

  public void removeServiceMetadata(org.apache.dubbo.metadata.report.identifier.ServiceMetadataIdentifier);
    Code:
       0: return

  public void saveSubscribedData(org.apache.dubbo.metadata.report.identifier.SubscriberMetadataIdentifier, java.util.Set<java.lang.String>);
    Code:
       0: return

  public java.util.List<java.lang.String> getSubscribedURLs(org.apache.dubbo.metadata.report.identifier.SubscriberMetadataIdentifier);
    Code:
       0: aconst_null
       1: areturn

  public boolean shouldReportDefinition();
    Code:
       0: iconst_1
       1: ireturn

  public boolean shouldReportMetadata();
    Code:
       0: iconst_0
       1: ireturn
}
