Compiled from "DefaultFuture.java"
public class org.apache.dubbo.remoting.exchange.support.DefaultFuture extends java.util.concurrent.CompletableFuture<java.lang.Object> {
  private static final org.apache.dubbo.common.logger.ErrorTypeAwareLogger logger;

  private static final java.util.Map<java.lang.Long, org.apache.dubbo.remoting.Channel> CHANNELS;

  private static final java.util.Map<java.lang.Long, org.apache.dubbo.remoting.exchange.support.DefaultFuture> FUTURES;

  private static final org.apache.dubbo.common.resource.GlobalResourceInitializer<org.apache.dubbo.common.timer.Timer> TIME_OUT_TIMER;

  private final java.lang.Long id;

  private final org.apache.dubbo.remoting.Channel channel;

  private final org.apache.dubbo.remoting.exchange.Request request;

  private final int timeout;

  private final long start;

  private volatile long sent;

  private org.apache.dubbo.common.timer.Timeout timeoutCheckTask;

  private java.util.concurrent.ExecutorService executor;

  public java.util.concurrent.ExecutorService getExecutor();
    Code:
       0: aload_0
       1: getfield      #7                  // Field executor:Ljava/util/concurrent/ExecutorService;
       4: areturn

  public void setExecutor(java.util.concurrent.ExecutorService);
    Code:
       0: aload_0
       1: aload_1
       2: putfield      #7                  // Field executor:Ljava/util/concurrent/ExecutorService;
       5: return

  private org.apache.dubbo.remoting.exchange.support.DefaultFuture(org.apache.dubbo.remoting.Channel, org.apache.dubbo.remoting.exchange.Request, int);
    Code:
       0: aload_0
       1: invokespecial #8                  // Method java/util/concurrent/CompletableFuture."<init>":()V
       4: aload_0
       5: invokestatic  #9                  // Method java/lang/System.currentTimeMillis:()J
       8: putfield      #10                 // Field start:J
      11: aload_0
      12: aload_1
      13: putfield      #11                 // Field channel:Lorg/apache/dubbo/remoting/Channel;
      16: aload_0
      17: aload_2
      18: putfield      #12                 // Field request:Lorg/apache/dubbo/remoting/exchange/Request;
      21: aload_0
      22: aload_2
      23: invokevirtual #13                 // Method org/apache/dubbo/remoting/exchange/Request.getId:()J
      26: invokestatic  #14                 // Method java/lang/Long.valueOf:(J)Ljava/lang/Long;
      29: putfield      #15                 // Field id:Ljava/lang/Long;
      32: aload_0
      33: iload_3
      34: ifle          41
      37: iload_3
      38: goto          55
      41: aload_1
      42: invokeinterface #16,  1           // InterfaceMethod org/apache/dubbo/remoting/Channel.getUrl:()Lorg/apache/dubbo/common/URL;
      47: ldc           #17                 // String timeout
      49: sipush        1000
      52: invokevirtual #18                 // Method org/apache/dubbo/common/URL.getPositiveParameter:(Ljava/lang/String;I)I
      55: putfield      #19                 // Field timeout:I
      58: getstatic     #20                 // Field FUTURES:Ljava/util/Map;
      61: aload_0
      62: getfield      #15                 // Field id:Ljava/lang/Long;
      65: aload_0
      66: invokeinterface #21,  3           // InterfaceMethod java/util/Map.put:(Ljava/lang/Object;Ljava/lang/Object;)Ljava/lang/Object;
      71: pop
      72: getstatic     #22                 // Field CHANNELS:Ljava/util/Map;
      75: aload_0
      76: getfield      #15                 // Field id:Ljava/lang/Long;
      79: aload_1
      80: invokeinterface #21,  3           // InterfaceMethod java/util/Map.put:(Ljava/lang/Object;Ljava/lang/Object;)Ljava/lang/Object;
      85: pop
      86: return

  private static void timeoutCheck(org.apache.dubbo.remoting.exchange.support.DefaultFuture);
    Code:
       0: new           #23                 // class org/apache/dubbo/remoting/exchange/support/DefaultFuture$TimeoutCheckTask
       3: dup
       4: aload_0
       5: invokespecial #6                  // Method getId:()J
       8: invokestatic  #14                 // Method java/lang/Long.valueOf:(J)Ljava/lang/Long;
      11: invokespecial #24                 // Method org/apache/dubbo/remoting/exchange/support/DefaultFuture$TimeoutCheckTask."<init>":(Ljava/lang/Long;)V
      14: astore_1
      15: aload_0
      16: getstatic     #25                 // Field TIME_OUT_TIMER:Lorg/apache/dubbo/common/resource/GlobalResourceInitializer;
      19: invokevirtual #26                 // Method org/apache/dubbo/common/resource/GlobalResourceInitializer.get:()Ljava/lang/Object;
      22: checkcast     #27                 // class org/apache/dubbo/common/timer/Timer
      25: aload_1
      26: aload_0
      27: invokespecial #28                 // Method getTimeout:()I
      30: i2l
      31: getstatic     #29                 // Field java/util/concurrent/TimeUnit.MILLISECONDS:Ljava/util/concurrent/TimeUnit;
      34: invokeinterface #30,  5           // InterfaceMethod org/apache/dubbo/common/timer/Timer.newTimeout:(Lorg/apache/dubbo/common/timer/TimerTask;JLjava/util/concurrent/TimeUnit;)Lorg/apache/dubbo/common/timer/Timeout;
      39: putfield      #31                 // Field timeoutCheckTask:Lorg/apache/dubbo/common/timer/Timeout;
      42: return

  public static void destroy();
    Code:
       0: getstatic     #25                 // Field TIME_OUT_TIMER:Lorg/apache/dubbo/common/resource/GlobalResourceInitializer;
       3: invokedynamic #32,  0             // InvokeDynamic #0:accept:()Ljava/util/function/Consumer;
       8: invokevirtual #33                 // Method org/apache/dubbo/common/resource/GlobalResourceInitializer.remove:(Ljava/util/function/Consumer;)Ljava/lang/Object;
      11: pop
      12: getstatic     #20                 // Field FUTURES:Ljava/util/Map;
      15: invokeinterface #34,  1           // InterfaceMethod java/util/Map.clear:()V
      20: getstatic     #22                 // Field CHANNELS:Ljava/util/Map;
      23: invokeinterface #34,  1           // InterfaceMethod java/util/Map.clear:()V
      28: return

  public static org.apache.dubbo.remoting.exchange.support.DefaultFuture newFuture(org.apache.dubbo.remoting.Channel, org.apache.dubbo.remoting.exchange.Request, int, java.util.concurrent.ExecutorService);
    Code:
       0: new           #35                 // class org/apache/dubbo/remoting/exchange/support/DefaultFuture
       3: dup
       4: aload_0
       5: aload_1
       6: iload_2
       7: invokespecial #36                 // Method "<init>":(Lorg/apache/dubbo/remoting/Channel;Lorg/apache/dubbo/remoting/exchange/Request;I)V
      10: astore        4
      12: aload         4
      14: aload_3
      15: invokevirtual #37                 // Method setExecutor:(Ljava/util/concurrent/ExecutorService;)V
      18: aload         4
      20: invokestatic  #38                 // Method timeoutCheck:(Lorg/apache/dubbo/remoting/exchange/support/DefaultFuture;)V
      23: aload         4
      25: areturn

  public static org.apache.dubbo.remoting.exchange.support.DefaultFuture getFuture(long);
    Code:
       0: getstatic     #20                 // Field FUTURES:Ljava/util/Map;
       3: lload_0
       4: invokestatic  #14                 // Method java/lang/Long.valueOf:(J)Ljava/lang/Long;
       7: invokeinterface #39,  2           // InterfaceMethod java/util/Map.get:(Ljava/lang/Object;)Ljava/lang/Object;
      12: checkcast     #35                 // class org/apache/dubbo/remoting/exchange/support/DefaultFuture
      15: areturn

  public static boolean hasFuture(org.apache.dubbo.remoting.Channel);
    Code:
       0: getstatic     #22                 // Field CHANNELS:Ljava/util/Map;
       3: aload_0
       4: invokeinterface #40,  2           // InterfaceMethod java/util/Map.containsValue:(Ljava/lang/Object;)Z
       9: ireturn

  public static void sent(org.apache.dubbo.remoting.Channel, org.apache.dubbo.remoting.exchange.Request);
    Code:
       0: getstatic     #20                 // Field FUTURES:Ljava/util/Map;
       3: aload_1
       4: invokevirtual #13                 // Method org/apache/dubbo/remoting/exchange/Request.getId:()J
       7: invokestatic  #14                 // Method java/lang/Long.valueOf:(J)Ljava/lang/Long;
      10: invokeinterface #39,  2           // InterfaceMethod java/util/Map.get:(Ljava/lang/Object;)Ljava/lang/Object;
      15: checkcast     #35                 // class org/apache/dubbo/remoting/exchange/support/DefaultFuture
      18: astore_2
      19: aload_2
      20: ifnull        27
      23: aload_2
      24: invokespecial #41                 // Method doSent:()V
      27: return

  public static void closeChannel(org.apache.dubbo.remoting.Channel);
    Code:
       0: getstatic     #22                 // Field CHANNELS:Ljava/util/Map;
       3: invokeinterface #42,  1           // InterfaceMethod java/util/Map.entrySet:()Ljava/util/Set;
       8: invokeinterface #43,  1           // InterfaceMethod java/util/Set.iterator:()Ljava/util/Iterator;
      13: astore_1
      14: aload_1
      15: invokeinterface #44,  1           // InterfaceMethod java/util/Iterator.hasNext:()Z
      20: ifeq          159
      23: aload_1
      24: invokeinterface #45,  1           // InterfaceMethod java/util/Iterator.next:()Ljava/lang/Object;
      29: checkcast     #46                 // class java/util/Map$Entry
      32: astore_2
      33: aload_0
      34: aload_2
      35: invokeinterface #47,  1           // InterfaceMethod java/util/Map$Entry.getValue:()Ljava/lang/Object;
      40: invokevirtual #48                 // Method java/lang/Object.equals:(Ljava/lang/Object;)Z
      43: ifeq          156
      46: aload_2
      47: invokeinterface #49,  1           // InterfaceMethod java/util/Map$Entry.getKey:()Ljava/lang/Object;
      52: checkcast     #50                 // class java/lang/Long
      55: invokevirtual #51                 // Method java/lang/Long.longValue:()J
      58: invokestatic  #52                 // Method getFuture:(J)Lorg/apache/dubbo/remoting/exchange/support/DefaultFuture;
      61: astore_3
      62: aload_3
      63: ifnull        156
      66: aload_3
      67: invokevirtual #53                 // Method isDone:()Z
      70: ifne          156
      73: new           #54                 // class org/apache/dubbo/remoting/exchange/Response
      76: dup
      77: aload_3
      78: invokespecial #6                  // Method getId:()J
      81: invokespecial #55                 // Method org/apache/dubbo/remoting/exchange/Response."<init>":(J)V
      84: astore        4
      86: aload         4
      88: bipush        35
      90: invokevirtual #56                 // Method org/apache/dubbo/remoting/exchange/Response.setStatus:(B)V
      93: aload         4
      95: new           #57                 // class java/lang/StringBuilder
      98: dup
      99: invokespecial #58                 // Method java/lang/StringBuilder."<init>":()V
     102: ldc           #59                 // String Channel
     104: invokevirtual #60                 // Method java/lang/StringBuilder.append:(Ljava/lang/String;)Ljava/lang/StringBuilder;
     107: aload_0
     108: invokevirtual #61                 // Method java/lang/StringBuilder.append:(Ljava/lang/Object;)Ljava/lang/StringBuilder;
     111: ldc           #62                 // String  is inactive. Directly return the unFinished request :
     113: invokevirtual #60                 // Method java/lang/StringBuilder.append:(Ljava/lang/String;)Ljava/lang/StringBuilder;
     116: getstatic     #63                 // Field logger:Lorg/apache/dubbo/common/logger/ErrorTypeAwareLogger;
     119: invokeinterface #64,  1           // InterfaceMethod org/apache/dubbo/common/logger/ErrorTypeAwareLogger.isDebugEnabled:()Z
     124: ifeq          134
     127: aload_3
     128: invokevirtual #65                 // Method getRequest:()Lorg/apache/dubbo/remoting/exchange/Request;
     131: goto          141
     134: aload_3
     135: invokevirtual #65                 // Method getRequest:()Lorg/apache/dubbo/remoting/exchange/Request;
     138: invokevirtual #66                 // Method org/apache/dubbo/remoting/exchange/Request.copyWithoutData:()Lorg/apache/dubbo/remoting/exchange/Request;
     141: invokevirtual #61                 // Method java/lang/StringBuilder.append:(Ljava/lang/Object;)Ljava/lang/StringBuilder;
     144: invokevirtual #67                 // Method java/lang/StringBuilder.toString:()Ljava/lang/String;
     147: invokevirtual #68                 // Method org/apache/dubbo/remoting/exchange/Response.setErrorMessage:(Ljava/lang/String;)V
     150: aload_0
     151: aload         4
     153: invokestatic  #69                 // Method received:(Lorg/apache/dubbo/remoting/Channel;Lorg/apache/dubbo/remoting/exchange/Response;)V
     156: goto          14
     159: return

  public static void received(org.apache.dubbo.remoting.Channel, org.apache.dubbo.remoting.exchange.Response);
    Code:
       0: aload_0
       1: aload_1
       2: iconst_0
       3: invokestatic  #70                 // Method received:(Lorg/apache/dubbo/remoting/Channel;Lorg/apache/dubbo/remoting/exchange/Response;Z)V
       6: return

  public static void received(org.apache.dubbo.remoting.Channel, org.apache.dubbo.remoting.exchange.Response, boolean);
    Code:
       0: getstatic     #20                 // Field FUTURES:Ljava/util/Map;
       3: aload_1
       4: invokevirtual #71                 // Method org/apache/dubbo/remoting/exchange/Response.getId:()J
       7: invokestatic  #14                 // Method java/lang/Long.valueOf:(J)Ljava/lang/Long;
      10: invokeinterface #72,  2           // InterfaceMethod java/util/Map.remove:(Ljava/lang/Object;)Ljava/lang/Object;
      15: checkcast     #35                 // class org/apache/dubbo/remoting/exchange/support/DefaultFuture
      18: astore_3
      19: aload_3
      20: ifnull        49
      23: aload_3
      24: getfield      #31                 // Field timeoutCheckTask:Lorg/apache/dubbo/common/timer/Timeout;
      27: astore        4
      29: iload_2
      30: ifne          41
      33: aload         4
      35: invokeinterface #73,  1           // InterfaceMethod org/apache/dubbo/common/timer/Timeout.cancel:()Z
      40: pop
      41: aload_3
      42: aload_1
      43: invokespecial #74                 // Method doReceived:(Lorg/apache/dubbo/remoting/exchange/Response;)V
      46: goto          167
      49: getstatic     #63                 // Field logger:Lorg/apache/dubbo/common/logger/ErrorTypeAwareLogger;
      52: ldc           #75                 // String 4-13
      54: ldc           #76                 // String
      56: ldc           #76                 // String
      58: new           #57                 // class java/lang/StringBuilder
      61: dup
      62: invokespecial #58                 // Method java/lang/StringBuilder."<init>":()V
      65: ldc           #77                 // String The timeout response finally returned at
      67: invokevirtual #60                 // Method java/lang/StringBuilder.append:(Ljava/lang/String;)Ljava/lang/StringBuilder;
      70: new           #78                 // class java/text/SimpleDateFormat
      73: dup
      74: ldc           #79                 // String yyyy-MM-dd HH:mm:ss.SSS
      76: invokespecial #80                 // Method java/text/SimpleDateFormat."<init>":(Ljava/lang/String;)V
      79: new           #81                 // class java/util/Date
      82: dup
      83: invokespecial #82                 // Method java/util/Date."<init>":()V
      86: invokevirtual #83                 // Method java/text/SimpleDateFormat.format:(Ljava/util/Date;)Ljava/lang/String;
      89: invokevirtual #60                 // Method java/lang/StringBuilder.append:(Ljava/lang/String;)Ljava/lang/StringBuilder;
      92: ldc           #84                 // String , response status is
      94: invokevirtual #60                 // Method java/lang/StringBuilder.append:(Ljava/lang/String;)Ljava/lang/StringBuilder;
      97: aload_1
      98: invokevirtual #85                 // Method org/apache/dubbo/remoting/exchange/Response.getStatus:()B
     101: invokevirtual #86                 // Method java/lang/StringBuilder.append:(I)Ljava/lang/StringBuilder;
     104: aload_0
     105: ifnonnull     113
     108: ldc           #76                 // String
     110: goto          151
     113: new           #57                 // class java/lang/StringBuilder
     116: dup
     117: invokespecial #58                 // Method java/lang/StringBuilder."<init>":()V
     120: ldc           #87                 // String , channel:
     122: invokevirtual #60                 // Method java/lang/StringBuilder.append:(Ljava/lang/String;)Ljava/lang/StringBuilder;
     125: aload_0
     126: invokeinterface #88,  1           // InterfaceMethod org/apache/dubbo/remoting/Channel.getLocalAddress:()Ljava/net/InetSocketAddress;
     131: invokevirtual #61                 // Method java/lang/StringBuilder.append:(Ljava/lang/Object;)Ljava/lang/StringBuilder;
     134: ldc           #89                 // String  ->
     136: invokevirtual #60                 // Method java/lang/StringBuilder.append:(Ljava/lang/String;)Ljava/lang/StringBuilder;
     139: aload_0
     140: invokeinterface #90,  1           // InterfaceMethod org/apache/dubbo/remoting/Channel.getRemoteAddress:()Ljava/net/InetSocketAddress;
     145: invokevirtual #61                 // Method java/lang/StringBuilder.append:(Ljava/lang/Object;)Ljava/lang/StringBuilder;
     148: invokevirtual #67                 // Method java/lang/StringBuilder.toString:()Ljava/lang/String;
     151: invokevirtual #60                 // Method java/lang/StringBuilder.append:(Ljava/lang/String;)Ljava/lang/StringBuilder;
     154: ldc           #91                 // String , please check provider side for detailed result.
     156: invokevirtual #60                 // Method java/lang/StringBuilder.append:(Ljava/lang/String;)Ljava/lang/StringBuilder;
     159: invokevirtual #67                 // Method java/lang/StringBuilder.toString:()Ljava/lang/String;
     162: invokeinterface #92,  5           // InterfaceMethod org/apache/dubbo/common/logger/ErrorTypeAwareLogger.warn:(Ljava/lang/String;Ljava/lang/String;Ljava/lang/String;Ljava/lang/String;)V
     167: getstatic     #22                 // Field CHANNELS:Ljava/util/Map;
     170: aload_1
     171: invokevirtual #71                 // Method org/apache/dubbo/remoting/exchange/Response.getId:()J
     174: invokestatic  #14                 // Method java/lang/Long.valueOf:(J)Ljava/lang/Long;
     177: invokeinterface #72,  2           // InterfaceMethod java/util/Map.remove:(Ljava/lang/Object;)Ljava/lang/Object;
     182: pop
     183: goto          207
     186: astore        5
     188: getstatic     #22                 // Field CHANNELS:Ljava/util/Map;
     191: aload_1
     192: invokevirtual #71                 // Method org/apache/dubbo/remoting/exchange/Response.getId:()J
     195: invokestatic  #14                 // Method java/lang/Long.valueOf:(J)Ljava/lang/Long;
     198: invokeinterface #72,  2           // InterfaceMethod java/util/Map.remove:(Ljava/lang/Object;)Ljava/lang/Object;
     203: pop
     204: aload         5
     206: athrow
     207: return
    Exception table:
       from    to  target type
           0   167   186   any
         186   188   186   any

  public boolean cancel(boolean);
    Code:
       0: new           #54                 // class org/apache/dubbo/remoting/exchange/Response
       3: dup
       4: aload_0
       5: getfield      #15                 // Field id:Ljava/lang/Long;
       8: invokevirtual #51                 // Method java/lang/Long.longValue:()J
      11: invokespecial #55                 // Method org/apache/dubbo/remoting/exchange/Response."<init>":(J)V
      14: astore_2
      15: aload_2
      16: bipush        90
      18: invokevirtual #56                 // Method org/apache/dubbo/remoting/exchange/Response.setStatus:(B)V
      21: aload_2
      22: ldc           #93                 // String request future has been canceled.
      24: invokevirtual #68                 // Method org/apache/dubbo/remoting/exchange/Response.setErrorMessage:(Ljava/lang/String;)V
      27: aload_0
      28: aload_2
      29: invokespecial #74                 // Method doReceived:(Lorg/apache/dubbo/remoting/exchange/Response;)V
      32: getstatic     #20                 // Field FUTURES:Ljava/util/Map;
      35: aload_0
      36: getfield      #15                 // Field id:Ljava/lang/Long;
      39: invokeinterface #72,  2           // InterfaceMethod java/util/Map.remove:(Ljava/lang/Object;)Ljava/lang/Object;
      44: pop
      45: getstatic     #22                 // Field CHANNELS:Ljava/util/Map;
      48: aload_0
      49: getfield      #15                 // Field id:Ljava/lang/Long;
      52: invokeinterface #72,  2           // InterfaceMethod java/util/Map.remove:(Ljava/lang/Object;)Ljava/lang/Object;
      57: pop
      58: aload_0
      59: getfield      #31                 // Field timeoutCheckTask:Lorg/apache/dubbo/common/timer/Timeout;
      62: invokeinterface #73,  1           // InterfaceMethod org/apache/dubbo/common/timer/Timeout.cancel:()Z
      67: pop
      68: iconst_1
      69: ireturn

  public void cancel();
    Code:
       0: aload_0
       1: iconst_1
       2: invokevirtual #94                 // Method cancel:(Z)Z
       5: pop
       6: return

  private void doReceived(org.apache.dubbo.remoting.exchange.Response);
    Code:
       0: aload_1
       1: ifnonnull     14
       4: new           #95                 // class java/lang/IllegalStateException
       7: dup
       8: ldc           #96                 // String response cannot be null
      10: invokespecial #97                 // Method java/lang/IllegalStateException."<init>":(Ljava/lang/String;)V
      13: athrow
      14: aload_1
      15: invokevirtual #85                 // Method org/apache/dubbo/remoting/exchange/Response.getStatus:()B
      18: bipush        20
      20: if_icmpne     35
      23: aload_0
      24: aload_1
      25: invokevirtual #98                 // Method org/apache/dubbo/remoting/exchange/Response.getResult:()Ljava/lang/Object;
      28: invokevirtual #99                 // Method complete:(Ljava/lang/Object;)Z
      31: pop
      32: goto          110
      35: aload_1
      36: invokevirtual #85                 // Method org/apache/dubbo/remoting/exchange/Response.getStatus:()B
      39: bipush        30
      41: if_icmpeq     53
      44: aload_1
      45: invokevirtual #85                 // Method org/apache/dubbo/remoting/exchange/Response.getStatus:()B
      48: bipush        31
      50: if_icmpne     90
      53: aload_0
      54: new           #100                // class org/apache/dubbo/remoting/TimeoutException
      57: dup
      58: aload_1
      59: invokevirtual #85                 // Method org/apache/dubbo/remoting/exchange/Response.getStatus:()B
      62: bipush        31
      64: if_icmpne     71
      67: iconst_1
      68: goto          72
      71: iconst_0
      72: aload_0
      73: getfield      #11                 // Field channel:Lorg/apache/dubbo/remoting/Channel;
      76: aload_1
      77: invokevirtual #101                // Method org/apache/dubbo/remoting/exchange/Response.getErrorMessage:()Ljava/lang/String;
      80: invokespecial #102                // Method org/apache/dubbo/remoting/TimeoutException."<init>":(ZLorg/apache/dubbo/remoting/Channel;Ljava/lang/String;)V
      83: invokevirtual #103                // Method completeExceptionally:(Ljava/lang/Throwable;)Z
      86: pop
      87: goto          110
      90: aload_0
      91: new           #104                // class org/apache/dubbo/remoting/RemotingException
      94: dup
      95: aload_0
      96: getfield      #11                 // Field channel:Lorg/apache/dubbo/remoting/Channel;
      99: aload_1
     100: invokevirtual #101                // Method org/apache/dubbo/remoting/exchange/Response.getErrorMessage:()Ljava/lang/String;
     103: invokespecial #105                // Method org/apache/dubbo/remoting/RemotingException."<init>":(Lorg/apache/dubbo/remoting/Channel;Ljava/lang/String;)V
     106: invokevirtual #103                // Method completeExceptionally:(Ljava/lang/Throwable;)Z
     109: pop
     110: return

  private long getId();
    Code:
       0: aload_0
       1: getfield      #15                 // Field id:Ljava/lang/Long;
       4: invokevirtual #51                 // Method java/lang/Long.longValue:()J
       7: lreturn

  private org.apache.dubbo.remoting.Channel getChannel();
    Code:
       0: aload_0
       1: getfield      #11                 // Field channel:Lorg/apache/dubbo/remoting/Channel;
       4: areturn

  private boolean isSent();
    Code:
       0: aload_0
       1: getfield      #106                // Field sent:J
       4: lconst_0
       5: lcmp
       6: ifle          13
       9: iconst_1
      10: goto          14
      13: iconst_0
      14: ireturn

  public org.apache.dubbo.remoting.exchange.Request getRequest();
    Code:
       0: aload_0
       1: getfield      #12                 // Field request:Lorg/apache/dubbo/remoting/exchange/Request;
       4: areturn

  private int getTimeout();
    Code:
       0: aload_0
       1: getfield      #19                 // Field timeout:I
       4: ireturn

  private void doSent();
    Code:
       0: aload_0
       1: invokestatic  #9                  // Method java/lang/System.currentTimeMillis:()J
       4: putfield      #106                // Field sent:J
       7: return

  private java.lang.String getTimeoutMessage(boolean);
    Code:
       0: invokestatic  #9                  // Method java/lang/System.currentTimeMillis:()J
       3: lstore_2
       4: new           #57                 // class java/lang/StringBuilder
       7: dup
       8: invokespecial #58                 // Method java/lang/StringBuilder."<init>":()V
      11: aload_0
      12: getfield      #106                // Field sent:J
      15: lconst_0
      16: lcmp
      17: ifle          25
      20: ldc           #107                // String Waiting server-side response timeout
      22: goto          27
      25: ldc           #108                // String Sending request timeout in client-side
      27: invokevirtual #60                 // Method java/lang/StringBuilder.append:(Ljava/lang/String;)Ljava/lang/StringBuilder;
      30: iload_1
      31: ifeq          39
      34: ldc           #109                // String  by scan timer
      36: goto          41
      39: ldc           #76                 // String
      41: invokevirtual #60                 // Method java/lang/StringBuilder.append:(Ljava/lang/String;)Ljava/lang/StringBuilder;
      44: ldc           #110                // String . start time:
      46: invokevirtual #60                 // Method java/lang/StringBuilder.append:(Ljava/lang/String;)Ljava/lang/StringBuilder;
      49: new           #78                 // class java/text/SimpleDateFormat
      52: dup
      53: ldc           #79                 // String yyyy-MM-dd HH:mm:ss.SSS
      55: invokespecial #80                 // Method java/text/SimpleDateFormat."<init>":(Ljava/lang/String;)V
      58: new           #81                 // class java/util/Date
      61: dup
      62: aload_0
      63: getfield      #10                 // Field start:J
      66: invokespecial #111                // Method java/util/Date."<init>":(J)V
      69: invokevirtual #83                 // Method java/text/SimpleDateFormat.format:(Ljava/util/Date;)Ljava/lang/String;
      72: invokevirtual #60                 // Method java/lang/StringBuilder.append:(Ljava/lang/String;)Ljava/lang/StringBuilder;
      75: ldc           #112                // String , end time:
      77: invokevirtual #60                 // Method java/lang/StringBuilder.append:(Ljava/lang/String;)Ljava/lang/StringBuilder;
      80: new           #78                 // class java/text/SimpleDateFormat
      83: dup
      84: ldc           #79                 // String yyyy-MM-dd HH:mm:ss.SSS
      86: invokespecial #80                 // Method java/text/SimpleDateFormat."<init>":(Ljava/lang/String;)V
      89: new           #81                 // class java/util/Date
      92: dup
      93: lload_2
      94: invokespecial #111                // Method java/util/Date."<init>":(J)V
      97: invokevirtual #83                 // Method java/text/SimpleDateFormat.format:(Ljava/util/Date;)Ljava/lang/String;
     100: invokevirtual #60                 // Method java/lang/StringBuilder.append:(Ljava/lang/String;)Ljava/lang/StringBuilder;
     103: ldc           #113                // String ,
     105: invokevirtual #60                 // Method java/lang/StringBuilder.append:(Ljava/lang/String;)Ljava/lang/StringBuilder;
     108: aload_0
     109: getfield      #106                // Field sent:J
     112: lconst_0
     113: lcmp
     114: ifle          161
     117: new           #57                 // class java/lang/StringBuilder
     120: dup
     121: invokespecial #58                 // Method java/lang/StringBuilder."<init>":()V
     124: ldc           #114                // String  client elapsed:
     126: invokevirtual #60                 // Method java/lang/StringBuilder.append:(Ljava/lang/String;)Ljava/lang/StringBuilder;
     129: aload_0
     130: getfield      #106                // Field sent:J
     133: aload_0
     134: getfield      #10                 // Field start:J
     137: lsub
     138: invokevirtual #115                // Method java/lang/StringBuilder.append:(J)Ljava/lang/StringBuilder;
     141: ldc           #116                // String  ms, server elapsed:
     143: invokevirtual #60                 // Method java/lang/StringBuilder.append:(Ljava/lang/String;)Ljava/lang/StringBuilder;
     146: lload_2
     147: aload_0
     148: getfield      #106                // Field sent:J
     151: lsub
     152: invokevirtual #115                // Method java/lang/StringBuilder.append:(J)Ljava/lang/StringBuilder;
     155: invokevirtual #67                 // Method java/lang/StringBuilder.toString:()Ljava/lang/String;
     158: goto          185
     161: new           #57                 // class java/lang/StringBuilder
     164: dup
     165: invokespecial #58                 // Method java/lang/StringBuilder."<init>":()V
     168: ldc           #117                // String  elapsed:
     170: invokevirtual #60                 // Method java/lang/StringBuilder.append:(Ljava/lang/String;)Ljava/lang/StringBuilder;
     173: lload_2
     174: aload_0
     175: getfield      #10                 // Field start:J
     178: lsub
     179: invokevirtual #115                // Method java/lang/StringBuilder.append:(J)Ljava/lang/StringBuilder;
     182: invokevirtual #67                 // Method java/lang/StringBuilder.toString:()Ljava/lang/String;
     185: invokevirtual #60                 // Method java/lang/StringBuilder.append:(Ljava/lang/String;)Ljava/lang/StringBuilder;
     188: ldc           #118                // String  ms, timeout:
     190: invokevirtual #60                 // Method java/lang/StringBuilder.append:(Ljava/lang/String;)Ljava/lang/StringBuilder;
     193: aload_0
     194: getfield      #19                 // Field timeout:I
     197: invokevirtual #86                 // Method java/lang/StringBuilder.append:(I)Ljava/lang/StringBuilder;
     200: ldc           #119                // String  ms, request:
     202: invokevirtual #60                 // Method java/lang/StringBuilder.append:(Ljava/lang/String;)Ljava/lang/StringBuilder;
     205: getstatic     #63                 // Field logger:Lorg/apache/dubbo/common/logger/ErrorTypeAwareLogger;
     208: invokeinterface #64,  1           // InterfaceMethod org/apache/dubbo/common/logger/ErrorTypeAwareLogger.isDebugEnabled:()Z
     213: ifeq          223
     216: aload_0
     217: getfield      #12                 // Field request:Lorg/apache/dubbo/remoting/exchange/Request;
     220: goto          230
     223: aload_0
     224: getfield      #12                 // Field request:Lorg/apache/dubbo/remoting/exchange/Request;
     227: invokevirtual #66                 // Method org/apache/dubbo/remoting/exchange/Request.copyWithoutData:()Lorg/apache/dubbo/remoting/exchange/Request;
     230: invokevirtual #61                 // Method java/lang/StringBuilder.append:(Ljava/lang/Object;)Ljava/lang/StringBuilder;
     233: ldc           #87                 // String , channel:
     235: invokevirtual #60                 // Method java/lang/StringBuilder.append:(Ljava/lang/String;)Ljava/lang/StringBuilder;
     238: aload_0
     239: getfield      #11                 // Field channel:Lorg/apache/dubbo/remoting/Channel;
     242: invokeinterface #88,  1           // InterfaceMethod org/apache/dubbo/remoting/Channel.getLocalAddress:()Ljava/net/InetSocketAddress;
     247: invokevirtual #61                 // Method java/lang/StringBuilder.append:(Ljava/lang/Object;)Ljava/lang/StringBuilder;
     250: ldc           #89                 // String  ->
     252: invokevirtual #60                 // Method java/lang/StringBuilder.append:(Ljava/lang/String;)Ljava/lang/StringBuilder;
     255: aload_0
     256: getfield      #11                 // Field channel:Lorg/apache/dubbo/remoting/Channel;
     259: invokeinterface #90,  1           // InterfaceMethod org/apache/dubbo/remoting/Channel.getRemoteAddress:()Ljava/net/InetSocketAddress;
     264: invokevirtual #61                 // Method java/lang/StringBuilder.append:(Ljava/lang/Object;)Ljava/lang/StringBuilder;
     267: invokevirtual #67                 // Method java/lang/StringBuilder.toString:()Ljava/lang/String;
     270: areturn

  private static org.apache.dubbo.common.timer.Timer lambda$static$0() throws java.lang.Exception;
    Code:
       0: new           #120                // class org/apache/dubbo/common/timer/HashedWheelTimer
       3: dup
       4: new           #121                // class org/apache/dubbo/common/utils/NamedThreadFactory
       7: dup
       8: ldc           #122                // String dubbo-future-timeout
      10: iconst_1
      11: invokespecial #123                // Method org/apache/dubbo/common/utils/NamedThreadFactory."<init>":(Ljava/lang/String;Z)V
      14: ldc2_w        #124                // long 30l
      17: getstatic     #29                 // Field java/util/concurrent/TimeUnit.MILLISECONDS:Ljava/util/concurrent/TimeUnit;
      20: invokespecial #126                // Method org/apache/dubbo/common/timer/HashedWheelTimer."<init>":(Ljava/util/concurrent/ThreadFactory;JLjava/util/concurrent/TimeUnit;)V
      23: areturn

  static long access$000(org.apache.dubbo.remoting.exchange.support.DefaultFuture);
    Code:
       0: aload_0
       1: invokespecial #6                  // Method getId:()J
       4: lreturn

  static boolean access$100(org.apache.dubbo.remoting.exchange.support.DefaultFuture);
    Code:
       0: aload_0
       1: invokespecial #5                  // Method isSent:()Z
       4: ireturn

  static java.lang.String access$200(org.apache.dubbo.remoting.exchange.support.DefaultFuture, boolean);
    Code:
       0: aload_0
       1: iload_1
       2: invokespecial #4                  // Method getTimeoutMessage:(Z)Ljava/lang/String;
       5: areturn

  static org.apache.dubbo.remoting.Channel access$300(org.apache.dubbo.remoting.exchange.support.DefaultFuture);
    Code:
       0: aload_0
       1: invokespecial #3                  // Method getChannel:()Lorg/apache/dubbo/remoting/Channel;
       4: areturn

  static {};
    Code:
       0: ldc           #35                 // class org/apache/dubbo/remoting/exchange/support/DefaultFuture
       2: invokestatic  #127                // Method org/apache/dubbo/common/logger/LoggerFactory.getErrorTypeAwareLogger:(Ljava/lang/Class;)Lorg/apache/dubbo/common/logger/ErrorTypeAwareLogger;
       5: putstatic     #63                 // Field logger:Lorg/apache/dubbo/common/logger/ErrorTypeAwareLogger;
       8: new           #128                // class java/util/concurrent/ConcurrentHashMap
      11: dup
      12: invokespecial #129                // Method java/util/concurrent/ConcurrentHashMap."<init>":()V
      15: putstatic     #22                 // Field CHANNELS:Ljava/util/Map;
      18: new           #128                // class java/util/concurrent/ConcurrentHashMap
      21: dup
      22: invokespecial #129                // Method java/util/concurrent/ConcurrentHashMap."<init>":()V
      25: putstatic     #20                 // Field FUTURES:Ljava/util/Map;
      28: new           #130                // class org/apache/dubbo/common/resource/GlobalResourceInitializer
      31: dup
      32: invokedynamic #131,  0            // InvokeDynamic #1:call:()Ljava/util/concurrent/Callable;
      37: invokedynamic #132,  0            // InvokeDynamic #2:destroy:()Lorg/apache/dubbo/common/resource/Disposable;
      42: invokespecial #133                // Method org/apache/dubbo/common/resource/GlobalResourceInitializer."<init>":(Ljava/util/concurrent/Callable;Lorg/apache/dubbo/common/resource/Disposable;)V
      45: putstatic     #25                 // Field TIME_OUT_TIMER:Lorg/apache/dubbo/common/resource/GlobalResourceInitializer;
      48: return
}
