Compiled from "DefaultFuture.java"
class org.apache.dubbo.remoting.exchange.support.DefaultFuture$TimeoutCheckTask implements org.apache.dubbo.common.timer.TimerTask {
  private final java.lang.Long requestID;

  org.apache.dubbo.remoting.exchange.support.DefaultFuture$TimeoutCheckTask(java.lang.Long);
    Code:
       0: aload_0
       1: invokespecial #1                  // Method java/lang/Object."<init>":()V
       4: aload_0
       5: aload_1
       6: putfield      #2                  // Field requestID:Ljava/lang/Long;
       9: return

  public void run(org.apache.dubbo.common.timer.Timeout);
    Code:
       0: aload_0
       1: getfield      #2                  // Field requestID:Ljava/lang/Long;
       4: invokevirtual #3                  // Method java/lang/Long.longValue:()J
       7: invokestatic  #4                  // Method org/apache/dubbo/remoting/exchange/support/DefaultFuture.getFuture:(J)Lorg/apache/dubbo/remoting/exchange/support/DefaultFuture;
      10: astore_2
      11: aload_2
      12: ifnull        22
      15: aload_2
      16: invokevirtual #5                  // Method org/apache/dubbo/remoting/exchange/support/DefaultFuture.isDone:()Z
      19: ifeq          23
      22: return
      23: aload_2
      24: invokevirtual #6                  // Method org/apache/dubbo/remoting/exchange/support/DefaultFuture.getExecutor:()Ljava/util/concurrent/ExecutorService;
      27: astore_3
      28: aload_3
      29: ifnull        57
      32: aload_3
      33: invokeinterface #7,  1            // InterfaceMethod java/util/concurrent/ExecutorService.isShutdown:()Z
      38: ifne          57
      41: aload_3
      42: aload_0
      43: aload_2
      44: invokedynamic #8,  0              // InvokeDynamic #0:run:(Lorg/apache/dubbo/remoting/exchange/support/DefaultFuture$TimeoutCheckTask;Lorg/apache/dubbo/remoting/exchange/support/DefaultFuture;)Ljava/lang/Runnable;
      49: invokeinterface #9,  2            // InterfaceMethod java/util/concurrent/ExecutorService.execute:(Ljava/lang/Runnable;)V
      54: goto          62
      57: aload_0
      58: aload_2
      59: invokespecial #10                 // Method notifyTimeout:(Lorg/apache/dubbo/remoting/exchange/support/DefaultFuture;)V
      62: return

  private void notifyTimeout(org.apache.dubbo.remoting.exchange.support.DefaultFuture);
    Code:
       0: new           #11                 // class org/apache/dubbo/remoting/exchange/Response
       3: dup
       4: aload_1
       5: invokestatic  #12                 // Method org/apache/dubbo/remoting/exchange/support/DefaultFuture.access$000:(Lorg/apache/dubbo/remoting/exchange/support/DefaultFuture;)J
       8: invokespecial #13                 // Method org/apache/dubbo/remoting/exchange/Response."<init>":(J)V
      11: astore_2
      12: aload_2
      13: aload_1
      14: invokestatic  #14                 // Method org/apache/dubbo/remoting/exchange/support/DefaultFuture.access$100:(Lorg/apache/dubbo/remoting/exchange/support/DefaultFuture;)Z
      17: ifeq          25
      20: bipush        31
      22: goto          27
      25: bipush        30
      27: invokevirtual #15                 // Method org/apache/dubbo/remoting/exchange/Response.setStatus:(B)V
      30: aload_2
      31: aload_1
      32: iconst_1
      33: invokestatic  #16                 // Method org/apache/dubbo/remoting/exchange/support/DefaultFuture.access$200:(Lorg/apache/dubbo/remoting/exchange/support/DefaultFuture;Z)Ljava/lang/String;
      36: invokevirtual #17                 // Method org/apache/dubbo/remoting/exchange/Response.setErrorMessage:(Ljava/lang/String;)V
      39: aload_1
      40: invokestatic  #18                 // Method org/apache/dubbo/remoting/exchange/support/DefaultFuture.access$300:(Lorg/apache/dubbo/remoting/exchange/support/DefaultFuture;)Lorg/apache/dubbo/remoting/Channel;
      43: aload_2
      44: iconst_1
      45: invokestatic  #19                 // Method org/apache/dubbo/remoting/exchange/support/DefaultFuture.received:(Lorg/apache/dubbo/remoting/Channel;Lorg/apache/dubbo/remoting/exchange/Response;Z)V
      48: return

  private void lambda$run$0(org.apache.dubbo.remoting.exchange.support.DefaultFuture);
    Code:
       0: aload_0
       1: aload_1
       2: invokespecial #10                 // Method notifyTimeout:(Lorg/apache/dubbo/remoting/exchange/support/DefaultFuture;)V
       5: return
}
