Compiled from "ExchangeHandlerDispatcher.java"
public class org.apache.dubbo.remoting.exchange.support.ExchangeHandlerDispatcher implements org.apache.dubbo.remoting.exchange.ExchangeHandler {
  private final org.apache.dubbo.remoting.exchange.support.ReplierDispatcher replierDispatcher;

  private final org.apache.dubbo.remoting.transport.ChannelHandlerDispatcher handlerDispatcher;

  private final org.apache.dubbo.remoting.telnet.TelnetHandler telnetHandler;

  public org.apache.dubbo.remoting.exchange.support.ExchangeHandlerDispatcher();
    Code:
       0: aload_0
       1: invokestatic  #1                  // Method org/apache/dubbo/rpc/model/FrameworkModel.defaultModel:()Lorg/apache/dubbo/rpc/model/FrameworkModel;
       4: aconst_null
       5: iconst_1
       6: anewarray     #2                  // class org/apache/dubbo/remoting/ChannelHandler
       9: dup
      10: iconst_0
      11: aconst_null
      12: checkcast     #2                  // class org/apache/dubbo/remoting/ChannelHandler
      15: aastore
      16: invokespecial #3                  // Method "<init>":(Lorg/apache/dubbo/rpc/model/FrameworkModel;Lorg/apache/dubbo/remoting/exchange/support/Replier;[Lorg/apache/dubbo/remoting/ChannelHandler;)V
      19: return

  public org.apache.dubbo.remoting.exchange.support.ExchangeHandlerDispatcher(org.apache.dubbo.remoting.exchange.support.Replier<?>);
    Code:
       0: aload_0
       1: invokestatic  #1                  // Method org/apache/dubbo/rpc/model/FrameworkModel.defaultModel:()Lorg/apache/dubbo/rpc/model/FrameworkModel;
       4: aload_1
       5: iconst_1
       6: anewarray     #2                  // class org/apache/dubbo/remoting/ChannelHandler
       9: dup
      10: iconst_0
      11: aconst_null
      12: checkcast     #2                  // class org/apache/dubbo/remoting/ChannelHandler
      15: aastore
      16: invokespecial #3                  // Method "<init>":(Lorg/apache/dubbo/rpc/model/FrameworkModel;Lorg/apache/dubbo/remoting/exchange/support/Replier;[Lorg/apache/dubbo/remoting/ChannelHandler;)V
      19: return

  public org.apache.dubbo.remoting.exchange.support.ExchangeHandlerDispatcher(org.apache.dubbo.remoting.ChannelHandler...);
    Code:
       0: aload_0
       1: invokestatic  #1                  // Method org/apache/dubbo/rpc/model/FrameworkModel.defaultModel:()Lorg/apache/dubbo/rpc/model/FrameworkModel;
       4: aconst_null
       5: aload_1
       6: invokespecial #3                  // Method "<init>":(Lorg/apache/dubbo/rpc/model/FrameworkModel;Lorg/apache/dubbo/remoting/exchange/support/Replier;[Lorg/apache/dubbo/remoting/ChannelHandler;)V
       9: return

  public org.apache.dubbo.remoting.exchange.support.ExchangeHandlerDispatcher(org.apache.dubbo.rpc.model.FrameworkModel, org.apache.dubbo.remoting.exchange.support.Replier<?>, org.apache.dubbo.remoting.ChannelHandler...);
    Code:
       0: aload_0
       1: invokespecial #4                  // Method java/lang/Object."<init>":()V
       4: aload_0
       5: new           #5                  // class org/apache/dubbo/remoting/exchange/support/ReplierDispatcher
       8: dup
       9: aload_2
      10: invokespecial #6                  // Method org/apache/dubbo/remoting/exchange/support/ReplierDispatcher."<init>":(Lorg/apache/dubbo/remoting/exchange/support/Replier;)V
      13: putfield      #7                  // Field replierDispatcher:Lorg/apache/dubbo/remoting/exchange/support/ReplierDispatcher;
      16: aload_0
      17: new           #8                  // class org/apache/dubbo/remoting/transport/ChannelHandlerDispatcher
      20: dup
      21: aload_3
      22: invokespecial #9                  // Method org/apache/dubbo/remoting/transport/ChannelHandlerDispatcher."<init>":([Lorg/apache/dubbo/remoting/ChannelHandler;)V
      25: putfield      #10                 // Field handlerDispatcher:Lorg/apache/dubbo/remoting/transport/ChannelHandlerDispatcher;
      28: aload_0
      29: new           #11                 // class org/apache/dubbo/remoting/telnet/support/TelnetHandlerAdapter
      32: dup
      33: aload_1
      34: invokespecial #12                 // Method org/apache/dubbo/remoting/telnet/support/TelnetHandlerAdapter."<init>":(Lorg/apache/dubbo/rpc/model/FrameworkModel;)V
      37: putfield      #13                 // Field telnetHandler:Lorg/apache/dubbo/remoting/telnet/TelnetHandler;
      40: return

  public org.apache.dubbo.remoting.exchange.support.ExchangeHandlerDispatcher addChannelHandler(org.apache.dubbo.remoting.ChannelHandler);
    Code:
       0: aload_0
       1: getfield      #10                 // Field handlerDispatcher:Lorg/apache/dubbo/remoting/transport/ChannelHandlerDispatcher;
       4: aload_1
       5: invokevirtual #14                 // Method org/apache/dubbo/remoting/transport/ChannelHandlerDispatcher.addChannelHandler:(Lorg/apache/dubbo/remoting/ChannelHandler;)Lorg/apache/dubbo/remoting/transport/ChannelHandlerDispatcher;
       8: pop
       9: aload_0
      10: areturn

  public org.apache.dubbo.remoting.exchange.support.ExchangeHandlerDispatcher removeChannelHandler(org.apache.dubbo.remoting.ChannelHandler);
    Code:
       0: aload_0
       1: getfield      #10                 // Field handlerDispatcher:Lorg/apache/dubbo/remoting/transport/ChannelHandlerDispatcher;
       4: aload_1
       5: invokevirtual #15                 // Method org/apache/dubbo/remoting/transport/ChannelHandlerDispatcher.removeChannelHandler:(Lorg/apache/dubbo/remoting/ChannelHandler;)Lorg/apache/dubbo/remoting/transport/ChannelHandlerDispatcher;
       8: pop
       9: aload_0
      10: areturn

  public <T> org.apache.dubbo.remoting.exchange.support.ExchangeHandlerDispatcher addReplier(java.lang.Class<T>, org.apache.dubbo.remoting.exchange.support.Replier<T>);
    Code:
       0: aload_0
       1: getfield      #7                  // Field replierDispatcher:Lorg/apache/dubbo/remoting/exchange/support/ReplierDispatcher;
       4: aload_1
       5: aload_2
       6: invokevirtual #16                 // Method org/apache/dubbo/remoting/exchange/support/ReplierDispatcher.addReplier:(Ljava/lang/Class;Lorg/apache/dubbo/remoting/exchange/support/Replier;)Lorg/apache/dubbo/remoting/exchange/support/ReplierDispatcher;
       9: pop
      10: aload_0
      11: areturn

  public <T> org.apache.dubbo.remoting.exchange.support.ExchangeHandlerDispatcher removeReplier(java.lang.Class<T>);
    Code:
       0: aload_0
       1: getfield      #7                  // Field replierDispatcher:Lorg/apache/dubbo/remoting/exchange/support/ReplierDispatcher;
       4: aload_1
       5: invokevirtual #17                 // Method org/apache/dubbo/remoting/exchange/support/ReplierDispatcher.removeReplier:(Ljava/lang/Class;)Lorg/apache/dubbo/remoting/exchange/support/ReplierDispatcher;
       8: pop
       9: aload_0
      10: areturn

  public java.util.concurrent.CompletableFuture<java.lang.Object> reply(org.apache.dubbo.remoting.exchange.ExchangeChannel, java.lang.Object) throws org.apache.dubbo.remoting.RemotingException;
    Code:
       0: aload_0
       1: getfield      #7                  // Field replierDispatcher:Lorg/apache/dubbo/remoting/exchange/support/ReplierDispatcher;
       4: aload_1
       5: aload_2
       6: invokeinterface #18,  3           // InterfaceMethod org/apache/dubbo/remoting/exchange/support/Replier.reply:(Lorg/apache/dubbo/remoting/exchange/ExchangeChannel;Ljava/lang/Object;)Ljava/lang/Object;
      11: invokestatic  #19                 // Method java/util/concurrent/CompletableFuture.completedFuture:(Ljava/lang/Object;)Ljava/util/concurrent/CompletableFuture;
      14: areturn

  public void connected(org.apache.dubbo.remoting.Channel);
    Code:
       0: aload_0
       1: getfield      #10                 // Field handlerDispatcher:Lorg/apache/dubbo/remoting/transport/ChannelHandlerDispatcher;
       4: aload_1
       5: invokevirtual #20                 // Method org/apache/dubbo/remoting/transport/ChannelHandlerDispatcher.connected:(Lorg/apache/dubbo/remoting/Channel;)V
       8: return

  public void disconnected(org.apache.dubbo.remoting.Channel);
    Code:
       0: aload_0
       1: getfield      #10                 // Field handlerDispatcher:Lorg/apache/dubbo/remoting/transport/ChannelHandlerDispatcher;
       4: aload_1
       5: invokevirtual #21                 // Method org/apache/dubbo/remoting/transport/ChannelHandlerDispatcher.disconnected:(Lorg/apache/dubbo/remoting/Channel;)V
       8: return

  public void sent(org.apache.dubbo.remoting.Channel, java.lang.Object);
    Code:
       0: aload_0
       1: getfield      #10                 // Field handlerDispatcher:Lorg/apache/dubbo/remoting/transport/ChannelHandlerDispatcher;
       4: aload_1
       5: aload_2
       6: invokevirtual #22                 // Method org/apache/dubbo/remoting/transport/ChannelHandlerDispatcher.sent:(Lorg/apache/dubbo/remoting/Channel;Ljava/lang/Object;)V
       9: return

  public void received(org.apache.dubbo.remoting.Channel, java.lang.Object);
    Code:
       0: aload_0
       1: getfield      #10                 // Field handlerDispatcher:Lorg/apache/dubbo/remoting/transport/ChannelHandlerDispatcher;
       4: aload_1
       5: aload_2
       6: invokevirtual #23                 // Method org/apache/dubbo/remoting/transport/ChannelHandlerDispatcher.received:(Lorg/apache/dubbo/remoting/Channel;Ljava/lang/Object;)V
       9: return

  public void caught(org.apache.dubbo.remoting.Channel, java.lang.Throwable);
    Code:
       0: aload_0
       1: getfield      #10                 // Field handlerDispatcher:Lorg/apache/dubbo/remoting/transport/ChannelHandlerDispatcher;
       4: aload_1
       5: aload_2
       6: invokevirtual #24                 // Method org/apache/dubbo/remoting/transport/ChannelHandlerDispatcher.caught:(Lorg/apache/dubbo/remoting/Channel;Ljava/lang/Throwable;)V
       9: return

  public java.lang.String telnet(org.apache.dubbo.remoting.Channel, java.lang.String) throws org.apache.dubbo.remoting.RemotingException;
    Code:
       0: aload_0
       1: getfield      #13                 // Field telnetHandler:Lorg/apache/dubbo/remoting/telnet/TelnetHandler;
       4: aload_1
       5: aload_2
       6: invokeinterface #25,  3           // InterfaceMethod org/apache/dubbo/remoting/telnet/TelnetHandler.telnet:(Lorg/apache/dubbo/remoting/Channel;Ljava/lang/String;)Ljava/lang/String;
      11: areturn
}
