Compiled from "ExchangeServerDelegate.java"
public class org.apache.dubbo.remoting.exchange.support.ExchangeServerDelegate implements org.apache.dubbo.remoting.exchange.ExchangeServer {
  private transient org.apache.dubbo.remoting.exchange.ExchangeServer server;

  public org.apache.dubbo.remoting.exchange.support.ExchangeServerDelegate();
    Code:
       0: aload_0
       1: invokespecial #1                  // Method java/lang/Object."<init>":()V
       4: return

  public org.apache.dubbo.remoting.exchange.support.ExchangeServerDelegate(org.apache.dubbo.remoting.exchange.ExchangeServer);
    Code:
       0: aload_0
       1: invokespecial #1                  // Method java/lang/Object."<init>":()V
       4: aload_0
       5: aload_1
       6: invokevirtual #2                  // Method setServer:(Lorg/apache/dubbo/remoting/exchange/ExchangeServer;)V
       9: return

  public org.apache.dubbo.remoting.exchange.ExchangeServer getServer();
    Code:
       0: aload_0
       1: getfield      #3                  // Field server:Lorg/apache/dubbo/remoting/exchange/ExchangeServer;
       4: areturn

  public void setServer(org.apache.dubbo.remoting.exchange.ExchangeServer);
    Code:
       0: aload_0
       1: aload_1
       2: putfield      #3                  // Field server:Lorg/apache/dubbo/remoting/exchange/ExchangeServer;
       5: return

  public boolean isBound();
    Code:
       0: aload_0
       1: getfield      #3                  // Field server:Lorg/apache/dubbo/remoting/exchange/ExchangeServer;
       4: invokeinterface #4,  1            // InterfaceMethod org/apache/dubbo/remoting/exchange/ExchangeServer.isBound:()Z
       9: ireturn

  public void reset(org.apache.dubbo.common.URL);
    Code:
       0: aload_0
       1: getfield      #3                  // Field server:Lorg/apache/dubbo/remoting/exchange/ExchangeServer;
       4: aload_1
       5: invokeinterface #5,  2            // InterfaceMethod org/apache/dubbo/remoting/exchange/ExchangeServer.reset:(Lorg/apache/dubbo/common/URL;)V
      10: return

  public void reset(org.apache.dubbo.common.Parameters);
    Code:
       0: aload_0
       1: aload_0
       2: invokevirtual #6                  // Method getUrl:()Lorg/apache/dubbo/common/URL;
       5: aload_1
       6: invokevirtual #7                  // Method org/apache/dubbo/common/Parameters.getParameters:()Ljava/util/Map;
       9: invokevirtual #8                  // Method org/apache/dubbo/common/URL.addParameters:(Ljava/util/Map;)Lorg/apache/dubbo/common/URL;
      12: invokevirtual #9                  // Method reset:(Lorg/apache/dubbo/common/URL;)V
      15: return

  public java.util.Collection<org.apache.dubbo.remoting.Channel> getChannels();
    Code:
       0: aload_0
       1: getfield      #3                  // Field server:Lorg/apache/dubbo/remoting/exchange/ExchangeServer;
       4: invokeinterface #10,  1           // InterfaceMethod org/apache/dubbo/remoting/exchange/ExchangeServer.getChannels:()Ljava/util/Collection;
       9: areturn

  public org.apache.dubbo.remoting.Channel getChannel(java.net.InetSocketAddress);
    Code:
       0: aload_0
       1: getfield      #3                  // Field server:Lorg/apache/dubbo/remoting/exchange/ExchangeServer;
       4: aload_1
       5: invokeinterface #11,  2           // InterfaceMethod org/apache/dubbo/remoting/exchange/ExchangeServer.getChannel:(Ljava/net/InetSocketAddress;)Lorg/apache/dubbo/remoting/Channel;
      10: areturn

  public org.apache.dubbo.common.URL getUrl();
    Code:
       0: aload_0
       1: getfield      #3                  // Field server:Lorg/apache/dubbo/remoting/exchange/ExchangeServer;
       4: invokeinterface #12,  1           // InterfaceMethod org/apache/dubbo/remoting/exchange/ExchangeServer.getUrl:()Lorg/apache/dubbo/common/URL;
       9: areturn

  public org.apache.dubbo.remoting.ChannelHandler getChannelHandler();
    Code:
       0: aload_0
       1: getfield      #3                  // Field server:Lorg/apache/dubbo/remoting/exchange/ExchangeServer;
       4: invokeinterface #13,  1           // InterfaceMethod org/apache/dubbo/remoting/exchange/ExchangeServer.getChannelHandler:()Lorg/apache/dubbo/remoting/ChannelHandler;
       9: areturn

  public java.net.InetSocketAddress getLocalAddress();
    Code:
       0: aload_0
       1: getfield      #3                  // Field server:Lorg/apache/dubbo/remoting/exchange/ExchangeServer;
       4: invokeinterface #14,  1           // InterfaceMethod org/apache/dubbo/remoting/exchange/ExchangeServer.getLocalAddress:()Ljava/net/InetSocketAddress;
       9: areturn

  public void send(java.lang.Object) throws org.apache.dubbo.remoting.RemotingException;
    Code:
       0: aload_0
       1: getfield      #3                  // Field server:Lorg/apache/dubbo/remoting/exchange/ExchangeServer;
       4: aload_1
       5: invokeinterface #15,  2           // InterfaceMethod org/apache/dubbo/remoting/exchange/ExchangeServer.send:(Ljava/lang/Object;)V
      10: return

  public void send(java.lang.Object, boolean) throws org.apache.dubbo.remoting.RemotingException;
    Code:
       0: aload_0
       1: getfield      #3                  // Field server:Lorg/apache/dubbo/remoting/exchange/ExchangeServer;
       4: aload_1
       5: iload_2
       6: invokeinterface #16,  3           // InterfaceMethod org/apache/dubbo/remoting/exchange/ExchangeServer.send:(Ljava/lang/Object;Z)V
      11: return

  public void close();
    Code:
       0: aload_0
       1: getfield      #3                  // Field server:Lorg/apache/dubbo/remoting/exchange/ExchangeServer;
       4: invokeinterface #17,  1           // InterfaceMethod org/apache/dubbo/remoting/exchange/ExchangeServer.close:()V
       9: return

  public boolean isClosed();
    Code:
       0: aload_0
       1: getfield      #3                  // Field server:Lorg/apache/dubbo/remoting/exchange/ExchangeServer;
       4: invokeinterface #18,  1           // InterfaceMethod org/apache/dubbo/remoting/exchange/ExchangeServer.isClosed:()Z
       9: ireturn

  public java.util.Collection<org.apache.dubbo.remoting.exchange.ExchangeChannel> getExchangeChannels();
    Code:
       0: aload_0
       1: getfield      #3                  // Field server:Lorg/apache/dubbo/remoting/exchange/ExchangeServer;
       4: invokeinterface #19,  1           // InterfaceMethod org/apache/dubbo/remoting/exchange/ExchangeServer.getExchangeChannels:()Ljava/util/Collection;
       9: areturn

  public org.apache.dubbo.remoting.exchange.ExchangeChannel getExchangeChannel(java.net.InetSocketAddress);
    Code:
       0: aload_0
       1: getfield      #3                  // Field server:Lorg/apache/dubbo/remoting/exchange/ExchangeServer;
       4: aload_1
       5: invokeinterface #20,  2           // InterfaceMethod org/apache/dubbo/remoting/exchange/ExchangeServer.getExchangeChannel:(Ljava/net/InetSocketAddress;)Lorg/apache/dubbo/remoting/exchange/ExchangeChannel;
      10: areturn

  public void close(int);
    Code:
       0: aload_0
       1: getfield      #3                  // Field server:Lorg/apache/dubbo/remoting/exchange/ExchangeServer;
       4: iload_1
       5: invokeinterface #21,  2           // InterfaceMethod org/apache/dubbo/remoting/exchange/ExchangeServer.close:(I)V
      10: return

  public void startClose();
    Code:
       0: aload_0
       1: getfield      #3                  // Field server:Lorg/apache/dubbo/remoting/exchange/ExchangeServer;
       4: invokeinterface #22,  1           // InterfaceMethod org/apache/dubbo/remoting/exchange/ExchangeServer.startClose:()V
       9: return
}
