Compiled from "MultiMessage.java"
public final class org.apache.dubbo.remoting.exchange.support.MultiMessage implements java.lang.Iterable {
  private final java.util.List messages;

  private org.apache.dubbo.remoting.exchange.support.MultiMessage();
    Code:
       0: aload_0
       1: invokespecial #1                  // Method java/lang/Object."<init>":()V
       4: aload_0
       5: new           #2                  // class java/util/ArrayList
       8: dup
       9: invokespecial #3                  // Method java/util/ArrayList."<init>":()V
      12: putfield      #4                  // Field messages:Ljava/util/List;
      15: return

  public static org.apache.dubbo.remoting.exchange.support.MultiMessage createFromCollection(java.util.Collection);
    Code:
       0: new           #5                  // class org/apache/dubbo/remoting/exchange/support/MultiMessage
       3: dup
       4: invokespecial #6                  // Method "<init>":()V
       7: astore_1
       8: aload_1
       9: aload_0
      10: invokevirtual #7                  // Method addMessages:(Ljava/util/Collection;)V
      13: aload_1
      14: areturn

  public static org.apache.dubbo.remoting.exchange.support.MultiMessage createFromArray(java.lang.Object...);
    Code:
       0: aload_0
       1: invokestatic  #8                  // Method java/util/Arrays.asList:([Ljava/lang/Object;)Ljava/util/List;
       4: invokestatic  #9                  // Method createFromCollection:(Ljava/util/Collection;)Lorg/apache/dubbo/remoting/exchange/support/MultiMessage;
       7: areturn

  public static org.apache.dubbo.remoting.exchange.support.MultiMessage create();
    Code:
       0: new           #5                  // class org/apache/dubbo/remoting/exchange/support/MultiMessage
       3: dup
       4: invokespecial #6                  // Method "<init>":()V
       7: areturn

  public void addMessage(java.lang.Object);
    Code:
       0: aload_0
       1: getfield      #4                  // Field messages:Ljava/util/List;
       4: aload_1
       5: invokeinterface #10,  2           // InterfaceMethod java/util/List.add:(Ljava/lang/Object;)Z
      10: pop
      11: return

  public void addMessages(java.util.Collection);
    Code:
       0: aload_0
       1: getfield      #4                  // Field messages:Ljava/util/List;
       4: aload_1
       5: invokeinterface #11,  2           // InterfaceMethod java/util/List.addAll:(Ljava/util/Collection;)Z
      10: pop
      11: return

  public java.util.Collection getMessages();
    Code:
       0: aload_0
       1: getfield      #4                  // Field messages:Ljava/util/List;
       4: invokestatic  #12                 // Method java/util/Collections.unmodifiableCollection:(Ljava/util/Collection;)Ljava/util/Collection;
       7: areturn

  public int size();
    Code:
       0: aload_0
       1: getfield      #4                  // Field messages:Ljava/util/List;
       4: invokeinterface #13,  1           // InterfaceMethod java/util/List.size:()I
       9: ireturn

  public java.lang.Object get(int);
    Code:
       0: aload_0
       1: getfield      #4                  // Field messages:Ljava/util/List;
       4: iload_1
       5: invokeinterface #14,  2           // InterfaceMethod java/util/List.get:(I)Ljava/lang/Object;
      10: areturn

  public boolean isEmpty();
    Code:
       0: aload_0
       1: getfield      #4                  // Field messages:Ljava/util/List;
       4: invokeinterface #15,  1           // InterfaceMethod java/util/List.isEmpty:()Z
       9: ireturn

  public java.util.Collection removeMessages();
    Code:
       0: aload_0
       1: getfield      #4                  // Field messages:Ljava/util/List;
       4: invokestatic  #12                 // Method java/util/Collections.unmodifiableCollection:(Ljava/util/Collection;)Ljava/util/Collection;
       7: astore_1
       8: aload_0
       9: getfield      #4                  // Field messages:Ljava/util/List;
      12: invokeinterface #16,  1           // InterfaceMethod java/util/List.clear:()V
      17: aload_1
      18: areturn

  public java.util.Iterator iterator();
    Code:
       0: aload_0
       1: getfield      #4                  // Field messages:Ljava/util/List;
       4: invokeinterface #17,  1           // InterfaceMethod java/util/List.iterator:()Ljava/util/Iterator;
       9: areturn
}
