Compiled from "ReplierDispatcher.java"
public class org.apache.dubbo.remoting.exchange.support.ReplierDispatcher implements org.apache.dubbo.remoting.exchange.support.Replier<java.lang.Object> {
  private final org.apache.dubbo.remoting.exchange.support.Replier<?> defaultReplier;

  private final java.util.Map<java.lang.Class<?>, org.apache.dubbo.remoting.exchange.support.Replier<?>> repliers;

  public org.apache.dubbo.remoting.exchange.support.ReplierDispatcher();
    Code:
       0: aload_0
       1: aconst_null
       2: aconst_null
       3: invokespecial #1                  // Method "<init>":(Lorg/apache/dubbo/remoting/exchange/support/Replier;Ljava/util/Map;)V
       6: return

  public org.apache.dubbo.remoting.exchange.support.ReplierDispatcher(org.apache.dubbo.remoting.exchange.support.Replier<?>);
    Code:
       0: aload_0
       1: aload_1
       2: aconst_null
       3: invokespecial #1                  // Method "<init>":(Lorg/apache/dubbo/remoting/exchange/support/Replier;Ljava/util/Map;)V
       6: return

  public org.apache.dubbo.remoting.exchange.support.ReplierDispatcher(org.apache.dubbo.remoting.exchange.support.Replier<?>, java.util.Map<java.lang.Class<?>, org.apache.dubbo.remoting.exchange.support.Replier<?>>);
    Code:
       0: aload_0
       1: invokespecial #2                  // Method java/lang/Object."<init>":()V
       4: aload_0
       5: new           #3                  // class java/util/concurrent/ConcurrentHashMap
       8: dup
       9: invokespecial #4                  // Method java/util/concurrent/ConcurrentHashMap."<init>":()V
      12: putfield      #5                  // Field repliers:Ljava/util/Map;
      15: aload_0
      16: aload_1
      17: putfield      #6                  // Field defaultReplier:Lorg/apache/dubbo/remoting/exchange/support/Replier;
      20: aload_2
      21: invokestatic  #7                  // Method org/apache/dubbo/common/utils/CollectionUtils.isNotEmptyMap:(Ljava/util/Map;)Z
      24: ifeq          37
      27: aload_0
      28: getfield      #5                  // Field repliers:Ljava/util/Map;
      31: aload_2
      32: invokeinterface #8,  2            // InterfaceMethod java/util/Map.putAll:(Ljava/util/Map;)V
      37: return

  public <T> org.apache.dubbo.remoting.exchange.support.ReplierDispatcher addReplier(java.lang.Class<T>, org.apache.dubbo.remoting.exchange.support.Replier<T>);
    Code:
       0: aload_0
       1: getfield      #5                  // Field repliers:Ljava/util/Map;
       4: aload_1
       5: aload_2
       6: invokeinterface #9,  3            // InterfaceMethod java/util/Map.put:(Ljava/lang/Object;Ljava/lang/Object;)Ljava/lang/Object;
      11: pop
      12: aload_0
      13: areturn

  public <T> org.apache.dubbo.remoting.exchange.support.ReplierDispatcher removeReplier(java.lang.Class<T>);
    Code:
       0: aload_0
       1: getfield      #5                  // Field repliers:Ljava/util/Map;
       4: aload_1
       5: invokeinterface #10,  2           // InterfaceMethod java/util/Map.remove:(Ljava/lang/Object;)Ljava/lang/Object;
      10: pop
      11: aload_0
      12: areturn

  private org.apache.dubbo.remoting.exchange.support.Replier<?> getReplier(java.lang.Class<?>);
    Code:
       0: aload_0
       1: getfield      #5                  // Field repliers:Ljava/util/Map;
       4: invokeinterface #11,  1           // InterfaceMethod java/util/Map.entrySet:()Ljava/util/Set;
       9: invokeinterface #12,  1           // InterfaceMethod java/util/Set.iterator:()Ljava/util/Iterator;
      14: astore_2
      15: aload_2
      16: invokeinterface #13,  1           // InterfaceMethod java/util/Iterator.hasNext:()Z
      21: ifeq          63
      24: aload_2
      25: invokeinterface #14,  1           // InterfaceMethod java/util/Iterator.next:()Ljava/lang/Object;
      30: checkcast     #15                 // class java/util/Map$Entry
      33: astore_3
      34: aload_3
      35: invokeinterface #16,  1           // InterfaceMethod java/util/Map$Entry.getKey:()Ljava/lang/Object;
      40: checkcast     #17                 // class java/lang/Class
      43: aload_1
      44: invokevirtual #18                 // Method java/lang/Class.isAssignableFrom:(Ljava/lang/Class;)Z
      47: ifeq          60
      50: aload_3
      51: invokeinterface #19,  1           // InterfaceMethod java/util/Map$Entry.getValue:()Ljava/lang/Object;
      56: checkcast     #20                 // class org/apache/dubbo/remoting/exchange/support/Replier
      59: areturn
      60: goto          15
      63: aload_0
      64: getfield      #6                  // Field defaultReplier:Lorg/apache/dubbo/remoting/exchange/support/Replier;
      67: ifnull        75
      70: aload_0
      71: getfield      #6                  // Field defaultReplier:Lorg/apache/dubbo/remoting/exchange/support/Replier;
      74: areturn
      75: new           #21                 // class java/lang/IllegalStateException
      78: dup
      79: new           #22                 // class java/lang/StringBuilder
      82: dup
      83: invokespecial #23                 // Method java/lang/StringBuilder."<init>":()V
      86: ldc           #24                 // String Replier not found, Unsupported message object:
      88: invokevirtual #25                 // Method java/lang/StringBuilder.append:(Ljava/lang/String;)Ljava/lang/StringBuilder;
      91: aload_1
      92: invokevirtual #26                 // Method java/lang/StringBuilder.append:(Ljava/lang/Object;)Ljava/lang/StringBuilder;
      95: invokevirtual #27                 // Method java/lang/StringBuilder.toString:()Ljava/lang/String;
      98: invokespecial #28                 // Method java/lang/IllegalStateException."<init>":(Ljava/lang/String;)V
     101: athrow

  public java.lang.Object reply(org.apache.dubbo.remoting.exchange.ExchangeChannel, java.lang.Object) throws org.apache.dubbo.remoting.RemotingException;
    Code:
       0: aload_0
       1: aload_2
       2: invokevirtual #29                 // Method java/lang/Object.getClass:()Ljava/lang/Class;
       5: invokespecial #30                 // Method getReplier:(Ljava/lang/Class;)Lorg/apache/dubbo/remoting/exchange/support/Replier;
       8: aload_1
       9: aload_2
      10: invokeinterface #31,  3           // InterfaceMethod org/apache/dubbo/remoting/exchange/support/Replier.reply:(Lorg/apache/dubbo/remoting/exchange/ExchangeChannel;Ljava/lang/Object;)Ljava/lang/Object;
      15: areturn
}
