Compiled from "DubboMonitorFactory.java"
public class org.apache.dubbo.monitor.dubbo.DubboMonitorFactory extends org.apache.dubbo.monitor.support.AbstractMonitorFactory {
  private org.apache.dubbo.rpc.Protocol protocol;

  private org.apache.dubbo.rpc.ProxyFactory proxyFactory;

  public org.apache.dubbo.monitor.dubbo.DubboMonitorFactory();
    Code:
       0: aload_0
       1: invokespecial #3                  // Method org/apache/dubbo/monitor/support/AbstractMonitorFactory."<init>":()V
       4: return

  public void setProtocol(org.apache.dubbo.rpc.Protocol);
    Code:
       0: aload_0
       1: aload_1
       2: putfield      #4                  // Field protocol:Lorg/apache/dubbo/rpc/Protocol;
       5: return

  public void setProxyFactory(org.apache.dubbo.rpc.ProxyFactory);
    Code:
       0: aload_0
       1: aload_1
       2: putfield      #5                  // Field proxyFactory:Lorg/apache/dubbo/rpc/ProxyFactory;
       5: return

  protected org.apache.dubbo.monitor.Monitor createMonitor(org.apache.dubbo.common.URL);
    Code:
       0: aload_1
       1: invokestatic  #6                  // Method org/apache/dubbo/common/URLBuilder.from:(Lorg/apache/dubbo/common/URL;)Lorg/apache/dubbo/common/URLBuilder;
       4: astore_2
       5: aload_2
       6: aload_1
       7: ldc           #7                  // String protocol
       9: ldc           #8                  // String dubbo
      11: invokevirtual #9                  // Method org/apache/dubbo/common/URL.getParameter:(Ljava/lang/String;Ljava/lang/String;)Ljava/lang/String;
      14: invokevirtual #10                 // Method org/apache/dubbo/common/URLBuilder.setProtocol:(Ljava/lang/String;)Lorg/apache/dubbo/common/URLBuilder;
      17: pop
      18: aload_1
      19: invokevirtual #11                 // Method org/apache/dubbo/common/URL.getPath:()Ljava/lang/String;
      22: invokestatic  #12                 // Method org/apache/dubbo/common/utils/StringUtils.isEmpty:(Ljava/lang/String;)Z
      25: ifeq          38
      28: aload_2
      29: ldc           #13                 // class org/apache/dubbo/monitor/MonitorService
      31: invokevirtual #14                 // Method java/lang/Class.getName:()Ljava/lang/String;
      34: invokevirtual #15                 // Method org/apache/dubbo/common/URLBuilder.setPath:(Ljava/lang/String;)Lorg/apache/dubbo/common/URLBuilder;
      37: pop
      38: aload_1
      39: ldc           #16                 // String reference.filter
      41: invokevirtual #17                 // Method org/apache/dubbo/common/URL.getParameter:(Ljava/lang/String;)Ljava/lang/String;
      44: astore_3
      45: aload_3
      46: invokestatic  #12                 // Method org/apache/dubbo/common/utils/StringUtils.isEmpty:(Ljava/lang/String;)Z
      49: ifeq          58
      52: ldc           #18                 // String
      54: astore_3
      55: goto          78
      58: new           #19                 // class java/lang/StringBuilder
      61: dup
      62: invokespecial #20                 // Method java/lang/StringBuilder."<init>":()V
      65: aload_3
      66: invokevirtual #21                 // Method java/lang/StringBuilder.append:(Ljava/lang/String;)Ljava/lang/StringBuilder;
      69: ldc           #22                 // String ,
      71: invokevirtual #21                 // Method java/lang/StringBuilder.append:(Ljava/lang/String;)Ljava/lang/StringBuilder;
      74: invokevirtual #23                 // Method java/lang/StringBuilder.toString:()Ljava/lang/String;
      77: astore_3
      78: aload_2
      79: iconst_4
      80: anewarray     #24                 // class java/lang/String
      83: dup
      84: iconst_0
      85: ldc           #25                 // String check
      87: aastore
      88: dup
      89: iconst_1
      90: iconst_0
      91: invokestatic  #26                 // Method java/lang/String.valueOf:(Z)Ljava/lang/String;
      94: aastore
      95: dup
      96: iconst_2
      97: ldc           #16                 // String reference.filter
      99: aastore
     100: dup
     101: iconst_3
     102: new           #19                 // class java/lang/StringBuilder
     105: dup
     106: invokespecial #20                 // Method java/lang/StringBuilder."<init>":()V
     109: aload_3
     110: invokevirtual #21                 // Method java/lang/StringBuilder.append:(Ljava/lang/String;)Ljava/lang/StringBuilder;
     113: ldc           #27                 // String -monitor
     115: invokevirtual #21                 // Method java/lang/StringBuilder.append:(Ljava/lang/String;)Ljava/lang/StringBuilder;
     118: invokevirtual #23                 // Method java/lang/StringBuilder.toString:()Ljava/lang/String;
     121: aastore
     122: invokevirtual #28                 // Method org/apache/dubbo/common/URLBuilder.addParameters:([Ljava/lang/String;)Lorg/apache/dubbo/common/URLBuilder;
     125: pop
     126: aload_0
     127: getfield      #4                  // Field protocol:Lorg/apache/dubbo/rpc/Protocol;
     130: ldc           #13                 // class org/apache/dubbo/monitor/MonitorService
     132: aload_2
     133: invokevirtual #29                 // Method org/apache/dubbo/common/URLBuilder.build:()Lorg/apache/dubbo/common/url/component/ServiceConfigURL;
     136: invokeinterface #30,  3           // InterfaceMethod org/apache/dubbo/rpc/Protocol.refer:(Ljava/lang/Class;Lorg/apache/dubbo/common/URL;)Lorg/apache/dubbo/rpc/Invoker;
     141: astore        4
     143: aload_0
     144: getfield      #5                  // Field proxyFactory:Lorg/apache/dubbo/rpc/ProxyFactory;
     147: aload         4
     149: invokeinterface #31,  2           // InterfaceMethod org/apache/dubbo/rpc/ProxyFactory.getProxy:(Lorg/apache/dubbo/rpc/Invoker;)Ljava/lang/Object;
     154: checkcast     #13                 // class org/apache/dubbo/monitor/MonitorService
     157: astore        5
     159: new           #32                 // class org/apache/dubbo/monitor/dubbo/DubboMonitor
     162: dup
     163: aload         4
     165: aload         5
     167: invokespecial #33                 // Method org/apache/dubbo/monitor/dubbo/DubboMonitor."<init>":(Lorg/apache/dubbo/rpc/Invoker;Lorg/apache/dubbo/monitor/MonitorService;)V
     170: areturn
}
