Compiled from "DubboMonitor.java"
public class org.apache.dubbo.monitor.dubbo.DubboMonitor implements org.apache.dubbo.monitor.Monitor {
  private static final org.apache.dubbo.common.logger.ErrorTypeAwareLogger logger;

  private final java.util.concurrent.ScheduledExecutorService scheduledExecutorService;

  private final java.util.concurrent.ScheduledFuture<?> sendFuture;

  private final org.apache.dubbo.rpc.Invoker<org.apache.dubbo.monitor.MonitorService> monitorInvoker;

  private final org.apache.dubbo.monitor.MonitorService monitorService;

  private final java.util.concurrent.ConcurrentMap<org.apache.dubbo.monitor.dubbo.Statistics, java.util.concurrent.atomic.AtomicReference<org.apache.dubbo.monitor.dubbo.StatisticsItem>> statisticsMap;

  public org.apache.dubbo.monitor.dubbo.DubboMonitor(org.apache.dubbo.rpc.Invoker<org.apache.dubbo.monitor.MonitorService>, org.apache.dubbo.monitor.MonitorService);
    Code:
       0: aload_0
       1: invokespecial #4                  // Method java/lang/Object."<init>":()V
       4: aload_0
       5: new           #5                  // class java/util/concurrent/ConcurrentHashMap
       8: dup
       9: invokespecial #6                  // Method java/util/concurrent/ConcurrentHashMap."<init>":()V
      12: putfield      #7                  // Field statisticsMap:Ljava/util/concurrent/ConcurrentMap;
      15: aload_0
      16: aload_1
      17: putfield      #8                  // Field monitorInvoker:Lorg/apache/dubbo/rpc/Invoker;
      20: aload_0
      21: aload_2
      22: putfield      #9                  // Field monitorService:Lorg/apache/dubbo/monitor/MonitorService;
      25: aload_0
      26: aload_1
      27: invokeinterface #10,  1           // InterfaceMethod org/apache/dubbo/rpc/Invoker.getUrl:()Lorg/apache/dubbo/common/URL;
      32: invokevirtual #11                 // Method org/apache/dubbo/common/URL.getOrDefaultFrameworkModel:()Lorg/apache/dubbo/rpc/model/FrameworkModel;
      35: invokevirtual #12                 // Method org/apache/dubbo/rpc/model/FrameworkModel.getBeanFactory:()Lorg/apache/dubbo/common/beans/factory/ScopeBeanFactory;
      38: ldc           #13                 // class org/apache/dubbo/common/threadpool/manager/FrameworkExecutorRepository
      40: invokevirtual #14                 // Method org/apache/dubbo/common/beans/factory/ScopeBeanFactory.getBean:(Ljava/lang/Class;)Ljava/lang/Object;
      43: checkcast     #13                 // class org/apache/dubbo/common/threadpool/manager/FrameworkExecutorRepository
      46: invokevirtual #15                 // Method org/apache/dubbo/common/threadpool/manager/FrameworkExecutorRepository.getSharedScheduledExecutor:()Ljava/util/concurrent/ScheduledExecutorService;
      49: putfield      #16                 // Field scheduledExecutorService:Ljava/util/concurrent/ScheduledExecutorService;
      52: aload_1
      53: invokeinterface #10,  1           // InterfaceMethod org/apache/dubbo/rpc/Invoker.getUrl:()Lorg/apache/dubbo/common/URL;
      58: ldc           #17                 // String interval
      60: ldc           #18                 // int 60000
      62: invokevirtual #19                 // Method org/apache/dubbo/common/URL.getPositiveParameter:(Ljava/lang/String;I)I
      65: i2l
      66: lstore_3
      67: aload_0
      68: aload_0
      69: getfield      #16                 // Field scheduledExecutorService:Ljava/util/concurrent/ScheduledExecutorService;
      72: aload_0
      73: invokedynamic #20,  0             // InvokeDynamic #0:run:(Lorg/apache/dubbo/monitor/dubbo/DubboMonitor;)Ljava/lang/Runnable;
      78: lload_3
      79: lload_3
      80: getstatic     #21                 // Field java/util/concurrent/TimeUnit.MILLISECONDS:Ljava/util/concurrent/TimeUnit;
      83: invokeinterface #22,  7           // InterfaceMethod java/util/concurrent/ScheduledExecutorService.scheduleWithFixedDelay:(Ljava/lang/Runnable;JJLjava/util/concurrent/TimeUnit;)Ljava/util/concurrent/ScheduledFuture;
      88: putfield      #23                 // Field sendFuture:Ljava/util/concurrent/ScheduledFuture;
      91: return

  public void send();
    Code:
       0: getstatic     #24                 // Field logger:Lorg/apache/dubbo/common/logger/ErrorTypeAwareLogger;
       3: invokeinterface #25,  1           // InterfaceMethod org/apache/dubbo/common/logger/ErrorTypeAwareLogger.isDebugEnabled:()Z
       8: ifeq          41
      11: getstatic     #24                 // Field logger:Lorg/apache/dubbo/common/logger/ErrorTypeAwareLogger;
      14: new           #26                 // class java/lang/StringBuilder
      17: dup
      18: invokespecial #27                 // Method java/lang/StringBuilder."<init>":()V
      21: ldc           #28                 // String Send statistics to monitor
      23: invokevirtual #29                 // Method java/lang/StringBuilder.append:(Ljava/lang/String;)Ljava/lang/StringBuilder;
      26: aload_0
      27: invokevirtual #30                 // Method getUrl:()Lorg/apache/dubbo/common/URL;
      30: invokevirtual #31                 // Method java/lang/StringBuilder.append:(Ljava/lang/Object;)Ljava/lang/StringBuilder;
      33: invokevirtual #32                 // Method java/lang/StringBuilder.toString:()Ljava/lang/String;
      36: invokeinterface #33,  2           // InterfaceMethod org/apache/dubbo/common/logger/ErrorTypeAwareLogger.debug:(Ljava/lang/String;)V
      41: invokestatic  #34                 // Method java/lang/System.currentTimeMillis:()J
      44: invokestatic  #35                 // Method java/lang/String.valueOf:(J)Ljava/lang/String;
      47: astore_1
      48: aload_0
      49: getfield      #7                  // Field statisticsMap:Ljava/util/concurrent/ConcurrentMap;
      52: invokeinterface #36,  1           // InterfaceMethod java/util/concurrent/ConcurrentMap.entrySet:()Ljava/util/Set;
      57: invokeinterface #37,  1           // InterfaceMethod java/util/Set.iterator:()Ljava/util/Iterator;
      62: astore_2
      63: aload_2
      64: invokeinterface #38,  1           // InterfaceMethod java/util/Iterator.hasNext:()Z
      69: ifeq          471
      72: aload_2
      73: invokeinterface #39,  1           // InterfaceMethod java/util/Iterator.next:()Ljava/lang/Object;
      78: checkcast     #40                 // class java/util/Map$Entry
      81: astore_3
      82: aload_3
      83: invokeinterface #41,  1           // InterfaceMethod java/util/Map$Entry.getKey:()Ljava/lang/Object;
      88: checkcast     #42                 // class org/apache/dubbo/monitor/dubbo/Statistics
      91: astore        4
      93: aload_3
      94: invokeinterface #43,  1           // InterfaceMethod java/util/Map$Entry.getValue:()Ljava/lang/Object;
      99: checkcast     #44                 // class java/util/concurrent/atomic/AtomicReference
     102: astore        5
     104: aload         5
     106: invokevirtual #45                 // Method java/util/concurrent/atomic/AtomicReference.get:()Ljava/lang/Object;
     109: checkcast     #46                 // class org/apache/dubbo/monitor/dubbo/StatisticsItem
     112: astore        6
     114: aload         4
     116: invokevirtual #47                 // Method org/apache/dubbo/monitor/dubbo/Statistics.getUrl:()Lorg/apache/dubbo/common/URL;
     119: bipush        24
     121: anewarray     #48                 // class java/lang/String
     124: dup
     125: iconst_0
     126: ldc           #49                 // String timestamp
     128: aastore
     129: dup
     130: iconst_1
     131: aload_1
     132: aastore
     133: dup
     134: iconst_2
     135: ldc           #50                 // String success
     137: aastore
     138: dup
     139: iconst_3
     140: aload         6
     142: invokevirtual #51                 // Method org/apache/dubbo/monitor/dubbo/StatisticsItem.getSuccess:()J
     145: invokestatic  #35                 // Method java/lang/String.valueOf:(J)Ljava/lang/String;
     148: aastore
     149: dup
     150: iconst_4
     151: ldc           #52                 // String failure
     153: aastore
     154: dup
     155: iconst_5
     156: aload         6
     158: invokevirtual #53                 // Method org/apache/dubbo/monitor/dubbo/StatisticsItem.getFailure:()J
     161: invokestatic  #35                 // Method java/lang/String.valueOf:(J)Ljava/lang/String;
     164: aastore
     165: dup
     166: bipush        6
     168: ldc           #54                 // String input
     170: aastore
     171: dup
     172: bipush        7
     174: aload         6
     176: invokevirtual #55                 // Method org/apache/dubbo/monitor/dubbo/StatisticsItem.getInput:()J
     179: invokestatic  #35                 // Method java/lang/String.valueOf:(J)Ljava/lang/String;
     182: aastore
     183: dup
     184: bipush        8
     186: ldc           #56                 // String output
     188: aastore
     189: dup
     190: bipush        9
     192: aload         6
     194: invokevirtual #57                 // Method org/apache/dubbo/monitor/dubbo/StatisticsItem.getOutput:()J
     197: invokestatic  #35                 // Method java/lang/String.valueOf:(J)Ljava/lang/String;
     200: aastore
     201: dup
     202: bipush        10
     204: ldc           #58                 // String elapsed
     206: aastore
     207: dup
     208: bipush        11
     210: aload         6
     212: invokevirtual #59                 // Method org/apache/dubbo/monitor/dubbo/StatisticsItem.getElapsed:()J
     215: invokestatic  #35                 // Method java/lang/String.valueOf:(J)Ljava/lang/String;
     218: aastore
     219: dup
     220: bipush        12
     222: ldc           #60                 // String concurrent
     224: aastore
     225: dup
     226: bipush        13
     228: aload         6
     230: invokevirtual #61                 // Method org/apache/dubbo/monitor/dubbo/StatisticsItem.getConcurrent:()J
     233: invokestatic  #35                 // Method java/lang/String.valueOf:(J)Ljava/lang/String;
     236: aastore
     237: dup
     238: bipush        14
     240: ldc           #62                 // String max.input
     242: aastore
     243: dup
     244: bipush        15
     246: aload         6
     248: invokevirtual #63                 // Method org/apache/dubbo/monitor/dubbo/StatisticsItem.getMaxInput:()J
     251: invokestatic  #35                 // Method java/lang/String.valueOf:(J)Ljava/lang/String;
     254: aastore
     255: dup
     256: bipush        16
     258: ldc           #64                 // String max.output
     260: aastore
     261: dup
     262: bipush        17
     264: aload         6
     266: invokevirtual #65                 // Method org/apache/dubbo/monitor/dubbo/StatisticsItem.getMaxOutput:()J
     269: invokestatic  #35                 // Method java/lang/String.valueOf:(J)Ljava/lang/String;
     272: aastore
     273: dup
     274: bipush        18
     276: ldc           #66                 // String max.elapsed
     278: aastore
     279: dup
     280: bipush        19
     282: aload         6
     284: invokevirtual #67                 // Method org/apache/dubbo/monitor/dubbo/StatisticsItem.getMaxElapsed:()J
     287: invokestatic  #35                 // Method java/lang/String.valueOf:(J)Ljava/lang/String;
     290: aastore
     291: dup
     292: bipush        20
     294: ldc           #68                 // String max.concurrent
     296: aastore
     297: dup
     298: bipush        21
     300: aload         6
     302: invokevirtual #69                 // Method org/apache/dubbo/monitor/dubbo/StatisticsItem.getMaxConcurrent:()J
     305: invokestatic  #35                 // Method java/lang/String.valueOf:(J)Ljava/lang/String;
     308: aastore
     309: dup
     310: bipush        22
     312: ldc           #70                 // String dubbo
     314: aastore
     315: dup
     316: bipush        23
     318: aload_0
     319: invokevirtual #30                 // Method getUrl:()Lorg/apache/dubbo/common/URL;
     322: ldc           #70                 // String dubbo
     324: invokevirtual #71                 // Method org/apache/dubbo/common/URL.getParameter:(Ljava/lang/String;)Ljava/lang/String;
     327: aastore
     328: invokevirtual #72                 // Method org/apache/dubbo/common/URL.addParameters:([Ljava/lang/String;)Lorg/apache/dubbo/common/URL;
     331: astore        7
     333: aload_0
     334: getfield      #9                  // Field monitorService:Lorg/apache/dubbo/monitor/MonitorService;
     337: aload         7
     339: invokevirtual #73                 // Method org/apache/dubbo/common/URL.toSerializableURL:()Lorg/apache/dubbo/common/URL;
     342: invokeinterface #74,  2           // InterfaceMethod org/apache/dubbo/monitor/MonitorService.collect:(Lorg/apache/dubbo/common/URL;)V
     347: new           #46                 // class org/apache/dubbo/monitor/dubbo/StatisticsItem
     350: dup
     351: invokespecial #75                 // Method org/apache/dubbo/monitor/dubbo/StatisticsItem."<init>":()V
     354: astore        9
     356: aload         5
     358: invokevirtual #45                 // Method java/util/concurrent/atomic/AtomicReference.get:()Ljava/lang/Object;
     361: checkcast     #46                 // class org/apache/dubbo/monitor/dubbo/StatisticsItem
     364: astore        8
     366: aload         8
     368: ifnonnull     385
     371: aload         9
     373: lconst_0
     374: lconst_0
     375: lconst_0
     376: lconst_0
     377: lconst_0
     378: lconst_0
     379: invokevirtual #76                 // Method org/apache/dubbo/monitor/dubbo/StatisticsItem.setItems:(JJJJJJ)V
     382: goto          456
     385: aload         9
     387: aload         8
     389: invokevirtual #51                 // Method org/apache/dubbo/monitor/dubbo/StatisticsItem.getSuccess:()J
     392: aload         6
     394: invokevirtual #51                 // Method org/apache/dubbo/monitor/dubbo/StatisticsItem.getSuccess:()J
     397: lsub
     398: aload         8
     400: invokevirtual #53                 // Method org/apache/dubbo/monitor/dubbo/StatisticsItem.getFailure:()J
     403: aload         6
     405: invokevirtual #53                 // Method org/apache/dubbo/monitor/dubbo/StatisticsItem.getFailure:()J
     408: lsub
     409: aload         8
     411: invokevirtual #55                 // Method org/apache/dubbo/monitor/dubbo/StatisticsItem.getInput:()J
     414: aload         6
     416: invokevirtual #55                 // Method org/apache/dubbo/monitor/dubbo/StatisticsItem.getInput:()J
     419: lsub
     420: aload         8
     422: invokevirtual #57                 // Method org/apache/dubbo/monitor/dubbo/StatisticsItem.getOutput:()J
     425: aload         6
     427: invokevirtual #57                 // Method org/apache/dubbo/monitor/dubbo/StatisticsItem.getOutput:()J
     430: lsub
     431: aload         8
     433: invokevirtual #59                 // Method org/apache/dubbo/monitor/dubbo/StatisticsItem.getElapsed:()J
     436: aload         6
     438: invokevirtual #59                 // Method org/apache/dubbo/monitor/dubbo/StatisticsItem.getElapsed:()J
     441: lsub
     442: aload         8
     444: invokevirtual #61                 // Method org/apache/dubbo/monitor/dubbo/StatisticsItem.getConcurrent:()J
     447: aload         6
     449: invokevirtual #61                 // Method org/apache/dubbo/monitor/dubbo/StatisticsItem.getConcurrent:()J
     452: lsub
     453: invokevirtual #76                 // Method org/apache/dubbo/monitor/dubbo/StatisticsItem.setItems:(JJJJJJ)V
     456: aload         5
     458: aload         8
     460: aload         9
     462: invokevirtual #77                 // Method java/util/concurrent/atomic/AtomicReference.compareAndSet:(Ljava/lang/Object;Ljava/lang/Object;)Z
     465: ifeq          356
     468: goto          63
     471: return

  public void collect(org.apache.dubbo.common.URL);
    Code:
       0: aload_1
       1: ldc           #50                 // String success
       3: iconst_0
       4: invokevirtual #78                 // Method org/apache/dubbo/common/URL.getParameter:(Ljava/lang/String;I)I
       7: istore_2
       8: aload_1
       9: ldc           #52                 // String failure
      11: iconst_0
      12: invokevirtual #78                 // Method org/apache/dubbo/common/URL.getParameter:(Ljava/lang/String;I)I
      15: istore_3
      16: aload_1
      17: ldc           #54                 // String input
      19: iconst_0
      20: invokevirtual #78                 // Method org/apache/dubbo/common/URL.getParameter:(Ljava/lang/String;I)I
      23: istore        4
      25: aload_1
      26: ldc           #56                 // String output
      28: iconst_0
      29: invokevirtual #78                 // Method org/apache/dubbo/common/URL.getParameter:(Ljava/lang/String;I)I
      32: istore        5
      34: aload_1
      35: ldc           #58                 // String elapsed
      37: iconst_0
      38: invokevirtual #78                 // Method org/apache/dubbo/common/URL.getParameter:(Ljava/lang/String;I)I
      41: istore        6
      43: aload_1
      44: ldc           #60                 // String concurrent
      46: iconst_0
      47: invokevirtual #78                 // Method org/apache/dubbo/common/URL.getParameter:(Ljava/lang/String;I)I
      50: istore        7
      52: new           #42                 // class org/apache/dubbo/monitor/dubbo/Statistics
      55: dup
      56: aload_1
      57: invokespecial #79                 // Method org/apache/dubbo/monitor/dubbo/Statistics."<init>":(Lorg/apache/dubbo/common/URL;)V
      60: astore        8
      62: aload_0
      63: getfield      #7                  // Field statisticsMap:Ljava/util/concurrent/ConcurrentMap;
      66: aload         8
      68: invokedynamic #80,  0             // InvokeDynamic #1:apply:()Ljava/util/function/Function;
      73: invokestatic  #81                 // Method org/apache/dubbo/common/utils/ConcurrentHashMapUtils.computeIfAbsent:(Ljava/util/concurrent/ConcurrentMap;Ljava/lang/Object;Ljava/util/function/Function;)Ljava/lang/Object;
      76: checkcast     #44                 // class java/util/concurrent/atomic/AtomicReference
      79: astore        9
      81: new           #46                 // class org/apache/dubbo/monitor/dubbo/StatisticsItem
      84: dup
      85: invokespecial #75                 // Method org/apache/dubbo/monitor/dubbo/StatisticsItem."<init>":()V
      88: astore        11
      90: aload         9
      92: invokevirtual #45                 // Method java/util/concurrent/atomic/AtomicReference.get:()Ljava/lang/Object;
      95: checkcast     #46                 // class org/apache/dubbo/monitor/dubbo/StatisticsItem
      98: astore        10
     100: aload         10
     102: ifnonnull     141
     105: aload         11
     107: iload_2
     108: i2l
     109: iload_3
     110: i2l
     111: iload         4
     113: i2l
     114: iload         5
     116: i2l
     117: iload         6
     119: i2l
     120: iload         7
     122: i2l
     123: iload         4
     125: i2l
     126: iload         5
     128: i2l
     129: iload         6
     131: i2l
     132: iload         7
     134: i2l
     135: invokevirtual #82                 // Method org/apache/dubbo/monitor/dubbo/StatisticsItem.setItems:(JJJJJJJJJJ)V
     138: goto          294
     141: aload         11
     143: aload         10
     145: invokevirtual #51                 // Method org/apache/dubbo/monitor/dubbo/StatisticsItem.getSuccess:()J
     148: iload_2
     149: i2l
     150: ladd
     151: aload         10
     153: invokevirtual #53                 // Method org/apache/dubbo/monitor/dubbo/StatisticsItem.getFailure:()J
     156: iload_3
     157: i2l
     158: ladd
     159: aload         10
     161: invokevirtual #55                 // Method org/apache/dubbo/monitor/dubbo/StatisticsItem.getInput:()J
     164: iload         4
     166: i2l
     167: ladd
     168: aload         10
     170: invokevirtual #57                 // Method org/apache/dubbo/monitor/dubbo/StatisticsItem.getOutput:()J
     173: iload         5
     175: i2l
     176: ladd
     177: aload         10
     179: invokevirtual #59                 // Method org/apache/dubbo/monitor/dubbo/StatisticsItem.getElapsed:()J
     182: iload         6
     184: i2l
     185: ladd
     186: aload         10
     188: invokevirtual #61                 // Method org/apache/dubbo/monitor/dubbo/StatisticsItem.getConcurrent:()J
     191: iload         7
     193: i2l
     194: ladd
     195: ldc2_w        #83                 // long 2l
     198: ldiv
     199: aload         10
     201: invokevirtual #63                 // Method org/apache/dubbo/monitor/dubbo/StatisticsItem.getMaxInput:()J
     204: iload         4
     206: i2l
     207: lcmp
     208: ifle          219
     211: aload         10
     213: invokevirtual #63                 // Method org/apache/dubbo/monitor/dubbo/StatisticsItem.getMaxInput:()J
     216: goto          222
     219: iload         4
     221: i2l
     222: aload         10
     224: invokevirtual #65                 // Method org/apache/dubbo/monitor/dubbo/StatisticsItem.getMaxOutput:()J
     227: iload         5
     229: i2l
     230: lcmp
     231: ifle          242
     234: aload         10
     236: invokevirtual #65                 // Method org/apache/dubbo/monitor/dubbo/StatisticsItem.getMaxOutput:()J
     239: goto          245
     242: iload         5
     244: i2l
     245: aload         10
     247: invokevirtual #67                 // Method org/apache/dubbo/monitor/dubbo/StatisticsItem.getMaxElapsed:()J
     250: iload         6
     252: i2l
     253: lcmp
     254: ifle          265
     257: aload         10
     259: invokevirtual #67                 // Method org/apache/dubbo/monitor/dubbo/StatisticsItem.getMaxElapsed:()J
     262: goto          268
     265: iload         6
     267: i2l
     268: aload         10
     270: invokevirtual #69                 // Method org/apache/dubbo/monitor/dubbo/StatisticsItem.getMaxConcurrent:()J
     273: iload         7
     275: i2l
     276: lcmp
     277: ifle          288
     280: aload         10
     282: invokevirtual #69                 // Method org/apache/dubbo/monitor/dubbo/StatisticsItem.getMaxConcurrent:()J
     285: goto          291
     288: iload         7
     290: i2l
     291: invokevirtual #82                 // Method org/apache/dubbo/monitor/dubbo/StatisticsItem.setItems:(JJJJJJJJJJ)V
     294: aload         9
     296: aload         10
     298: aload         11
     300: invokevirtual #77                 // Method java/util/concurrent/atomic/AtomicReference.compareAndSet:(Ljava/lang/Object;Ljava/lang/Object;)Z
     303: ifeq          90
     306: return

  public java.util.List<org.apache.dubbo.common.URL> lookup(org.apache.dubbo.common.URL);
    Code:
       0: aload_0
       1: getfield      #9                  // Field monitorService:Lorg/apache/dubbo/monitor/MonitorService;
       4: aload_1
       5: invokeinterface #85,  2           // InterfaceMethod org/apache/dubbo/monitor/MonitorService.lookup:(Lorg/apache/dubbo/common/URL;)Ljava/util/List;
      10: areturn

  public org.apache.dubbo.common.URL getUrl();
    Code:
       0: aload_0
       1: getfield      #8                  // Field monitorInvoker:Lorg/apache/dubbo/rpc/Invoker;
       4: invokeinterface #10,  1           // InterfaceMethod org/apache/dubbo/rpc/Invoker.getUrl:()Lorg/apache/dubbo/common/URL;
       9: areturn

  public boolean isAvailable();
    Code:
       0: aload_0
       1: getfield      #8                  // Field monitorInvoker:Lorg/apache/dubbo/rpc/Invoker;
       4: invokeinterface #86,  1           // InterfaceMethod org/apache/dubbo/rpc/Invoker.isAvailable:()Z
       9: ireturn

  public void destroy();
    Code:
       0: aload_0
       1: getfield      #23                 // Field sendFuture:Ljava/util/concurrent/ScheduledFuture;
       4: invokestatic  #87                 // Method org/apache/dubbo/common/utils/ExecutorUtil.cancelScheduledFuture:(Ljava/util/concurrent/ScheduledFuture;)V
       7: goto          48
      10: astore_1
      11: getstatic     #24                 // Field logger:Lorg/apache/dubbo/common/logger/ErrorTypeAwareLogger;
      14: ldc           #89                 // String 0-14
      16: ldc           #90                 // String
      18: ldc           #90                 // String
      20: new           #26                 // class java/lang/StringBuilder
      23: dup
      24: invokespecial #27                 // Method java/lang/StringBuilder."<init>":()V
      27: ldc           #91                 // String Unexpected error occur at cancel sender timer, cause:
      29: invokevirtual #29                 // Method java/lang/StringBuilder.append:(Ljava/lang/String;)Ljava/lang/StringBuilder;
      32: aload_1
      33: invokevirtual #92                 // Method java/lang/Throwable.getMessage:()Ljava/lang/String;
      36: invokevirtual #29                 // Method java/lang/StringBuilder.append:(Ljava/lang/String;)Ljava/lang/StringBuilder;
      39: invokevirtual #32                 // Method java/lang/StringBuilder.toString:()Ljava/lang/String;
      42: aload_1
      43: invokeinterface #93,  6           // InterfaceMethod org/apache/dubbo/common/logger/ErrorTypeAwareLogger.error:(Ljava/lang/String;Ljava/lang/String;Ljava/lang/String;Ljava/lang/String;Ljava/lang/Throwable;)V
      48: aload_0
      49: getfield      #8                  // Field monitorInvoker:Lorg/apache/dubbo/rpc/Invoker;
      52: invokeinterface #94,  1           // InterfaceMethod org/apache/dubbo/rpc/Invoker.destroy:()V
      57: return
    Exception table:
       from    to  target type
           0     7    10   Class java/lang/Throwable

  private static java.util.concurrent.atomic.AtomicReference lambda$collect$1(org.apache.dubbo.monitor.dubbo.Statistics);
    Code:
       0: new           #44                 // class java/util/concurrent/atomic/AtomicReference
       3: dup
       4: invokespecial #95                 // Method java/util/concurrent/atomic/AtomicReference."<init>":()V
       7: areturn

  private void lambda$new$0();
    Code:
       0: aload_0
       1: invokevirtual #96                 // Method send:()V
       4: goto          45
       7: astore_1
       8: getstatic     #24                 // Field logger:Lorg/apache/dubbo/common/logger/ErrorTypeAwareLogger;
      11: ldc           #89                 // String 0-14
      13: ldc           #90                 // String
      15: ldc           #90                 // String
      17: new           #26                 // class java/lang/StringBuilder
      20: dup
      21: invokespecial #27                 // Method java/lang/StringBuilder."<init>":()V
      24: ldc           #97                 // String Unexpected error occur at send statistic, cause:
      26: invokevirtual #29                 // Method java/lang/StringBuilder.append:(Ljava/lang/String;)Ljava/lang/StringBuilder;
      29: aload_1
      30: invokevirtual #92                 // Method java/lang/Throwable.getMessage:()Ljava/lang/String;
      33: invokevirtual #29                 // Method java/lang/StringBuilder.append:(Ljava/lang/String;)Ljava/lang/StringBuilder;
      36: invokevirtual #32                 // Method java/lang/StringBuilder.toString:()Ljava/lang/String;
      39: aload_1
      40: invokeinterface #93,  6           // InterfaceMethod org/apache/dubbo/common/logger/ErrorTypeAwareLogger.error:(Ljava/lang/String;Ljava/lang/String;Ljava/lang/String;Ljava/lang/String;Ljava/lang/Throwable;)V
      45: return
    Exception table:
       from    to  target type
           0     4     7   Class java/lang/Throwable

  static {};
    Code:
       0: ldc           #98                 // class org/apache/dubbo/monitor/dubbo/DubboMonitor
       2: invokestatic  #99                 // Method org/apache/dubbo/common/logger/LoggerFactory.getErrorTypeAwareLogger:(Ljava/lang/Class;)Lorg/apache/dubbo/common/logger/ErrorTypeAwareLogger;
       5: putstatic     #24                 // Field logger:Lorg/apache/dubbo/common/logger/ErrorTypeAwareLogger;
       8: return
}
