Compiled from "MetricsFilter.java"
public class org.apache.dubbo.monitor.dubbo.MetricsFilter implements org.apache.dubbo.rpc.Filter,org.apache.dubbo.common.extension.ExtensionAccessorAware,org.apache.dubbo.rpc.model.ScopeModelAware {
  private static final org.apache.dubbo.common.logger.ErrorTypeAwareLogger logger;

  protected static volatile java.util.concurrent.atomic.AtomicBoolean exported;

  private java.lang.Integer port;

  private java.lang.String protocolName;

  private org.apache.dubbo.common.extension.ExtensionAccessor extensionAccessor;

  private org.apache.dubbo.rpc.model.ApplicationModel applicationModel;

  private static final java.lang.String METRICS_PORT;

  private static final java.lang.String METRICS_PROTOCOL;

  public org.apache.dubbo.monitor.dubbo.MetricsFilter();
    Code:
       0: aload_0
       1: invokespecial #8                  // Method java/lang/Object."<init>":()V
       4: return

  public void setApplicationModel(org.apache.dubbo.rpc.model.ApplicationModel);
    Code:
       0: aload_0
       1: aload_1
       2: putfield      #5                  // Field applicationModel:Lorg/apache/dubbo/rpc/model/ApplicationModel;
       5: return

  public org.apache.dubbo.rpc.Result invoke(org.apache.dubbo.rpc.Invoker<?>, org.apache.dubbo.rpc.Invocation) throws org.apache.dubbo.rpc.RpcException;
    Code:
       0: getstatic     #9                  // Field exported:Ljava/util/concurrent/atomic/AtomicBoolean;
       3: iconst_0
       4: iconst_1
       5: invokevirtual #10                 // Method java/util/concurrent/atomic/AtomicBoolean.compareAndSet:(ZZ)Z
       8: ifeq          171
      11: aload_0
      12: aload_1
      13: invokeinterface #11,  1           // InterfaceMethod org/apache/dubbo/rpc/Invoker.getUrl:()Lorg/apache/dubbo/common/URL;
      18: ldc           #13                 // String metrics.protocol
      20: invokevirtual #14                 // Method org/apache/dubbo/common/URL.getParameter:(Ljava/lang/String;)Ljava/lang/String;
      23: ifnonnull     31
      26: ldc           #15                 // String dubbo
      28: goto          42
      31: aload_1
      32: invokeinterface #11,  1           // InterfaceMethod org/apache/dubbo/rpc/Invoker.getUrl:()Lorg/apache/dubbo/common/URL;
      37: ldc           #13                 // String metrics.protocol
      39: invokevirtual #14                 // Method org/apache/dubbo/common/URL.getParameter:(Ljava/lang/String;)Ljava/lang/String;
      42: putfield      #6                  // Field protocolName:Ljava/lang/String;
      45: aload_0
      46: getfield      #16                 // Field extensionAccessor:Lorg/apache/dubbo/common/extension/ExtensionAccessor;
      49: ldc           #17                 // class org/apache/dubbo/rpc/Protocol
      51: invokeinterface #18,  2           // InterfaceMethod org/apache/dubbo/common/extension/ExtensionAccessor.getExtensionLoader:(Ljava/lang/Class;)Lorg/apache/dubbo/common/extension/ExtensionLoader;
      56: aload_0
      57: getfield      #6                  // Field protocolName:Ljava/lang/String;
      60: invokevirtual #19                 // Method org/apache/dubbo/common/extension/ExtensionLoader.getExtension:(Ljava/lang/String;)Ljava/lang/Object;
      63: checkcast     #17                 // class org/apache/dubbo/rpc/Protocol
      66: astore_3
      67: aload_0
      68: aload_1
      69: invokeinterface #11,  1           // InterfaceMethod org/apache/dubbo/rpc/Invoker.getUrl:()Lorg/apache/dubbo/common/URL;
      74: ldc           #20                 // String metrics.port
      76: invokevirtual #14                 // Method org/apache/dubbo/common/URL.getParameter:(Ljava/lang/String;)Ljava/lang/String;
      79: ifnonnull     91
      82: aload_3
      83: invokeinterface #21,  1           // InterfaceMethod org/apache/dubbo/rpc/Protocol.getDefaultPort:()I
      88: goto          108
      91: aload_1
      92: invokeinterface #11,  1           // InterfaceMethod org/apache/dubbo/rpc/Invoker.getUrl:()Lorg/apache/dubbo/common/URL;
      97: ldc           #20                 // String metrics.port
      99: invokevirtual #14                 // Method org/apache/dubbo/common/URL.getParameter:(Ljava/lang/String;)Ljava/lang/String;
     102: invokestatic  #22                 // Method java/lang/Integer.valueOf:(Ljava/lang/String;)Ljava/lang/Integer;
     105: invokevirtual #23                 // Method java/lang/Integer.intValue:()I
     108: invokestatic  #24                 // Method java/lang/Integer.valueOf:(I)Ljava/lang/Integer;
     111: putfield      #4                  // Field port:Ljava/lang/Integer;
     114: aload_0
     115: invokespecial #25                 // Method initMetricsInvoker:()Lorg/apache/dubbo/rpc/Invoker;
     118: astore        4
     120: aload_3
     121: aload         4
     123: invokeinterface #26,  2           // InterfaceMethod org/apache/dubbo/rpc/Protocol.export:(Lorg/apache/dubbo/rpc/Invoker;)Lorg/apache/dubbo/rpc/Exporter;
     128: pop
     129: goto          171
     132: astore        5
     134: getstatic     #28                 // Field logger:Lorg/apache/dubbo/common/logger/ErrorTypeAwareLogger;
     137: ldc           #29                 // String 0-13
     139: ldc           #30                 // String
     141: ldc           #30                 // String
     143: new           #31                 // class java/lang/StringBuilder
     146: dup
     147: invokespecial #32                 // Method java/lang/StringBuilder."<init>":()V
     150: ldc           #33                 // String Metrics Service need to be configured when multiple processes are running on a host
     152: invokevirtual #34                 // Method java/lang/StringBuilder.append:(Ljava/lang/String;)Ljava/lang/StringBuilder;
     155: aload         5
     157: invokevirtual #35                 // Method java/lang/RuntimeException.getMessage:()Ljava/lang/String;
     160: invokevirtual #34                 // Method java/lang/StringBuilder.append:(Ljava/lang/String;)Ljava/lang/StringBuilder;
     163: invokevirtual #36                 // Method java/lang/StringBuilder.toString:()Ljava/lang/String;
     166: invokeinterface #37,  5           // InterfaceMethod org/apache/dubbo/common/logger/ErrorTypeAwareLogger.error:(Ljava/lang/String;Ljava/lang/String;Ljava/lang/String;Ljava/lang/String;)V
     171: aload_1
     172: invokeinterface #11,  1           // InterfaceMethod org/apache/dubbo/rpc/Invoker.getUrl:()Lorg/apache/dubbo/common/URL;
     177: ldc           #38                 // String provider
     179: invokevirtual #39                 // Method org/apache/dubbo/common/URL.getSide:(Ljava/lang/String;)Ljava/lang/String;
     182: ldc           #38                 // String provider
     184: invokevirtual #40                 // Method java/lang/String.equalsIgnoreCase:(Ljava/lang/String;)Z
     187: istore_3
     188: invokestatic  #41                 // Method java/lang/System.currentTimeMillis:()J
     191: lstore        4
     193: aload_1
     194: aload_2
     195: invokeinterface #42,  2           // InterfaceMethod org/apache/dubbo/rpc/Invoker.invoke:(Lorg/apache/dubbo/rpc/Invocation;)Lorg/apache/dubbo/rpc/Result;
     200: astore        6
     202: invokestatic  #41                 // Method java/lang/System.currentTimeMillis:()J
     205: lload         4
     207: lsub
     208: lstore        7
     210: aload_0
     211: aload_1
     212: aload_2
     213: lload         7
     215: ldc           #43                 // String success
     217: iload_3
     218: invokespecial #44                 // Method reportMetrics:(Lorg/apache/dubbo/rpc/Invoker;Lorg/apache/dubbo/rpc/Invocation;JLjava/lang/String;Z)V
     221: aload         6
     223: areturn
     224: astore        6
     226: invokestatic  #41                 // Method java/lang/System.currentTimeMillis:()J
     229: lload         4
     231: lsub
     232: lstore        7
     234: ldc           #46                 // String error
     236: astore        9
     238: aload         6
     240: invokevirtual #47                 // Method org/apache/dubbo/rpc/RpcException.isTimeout:()Z
     243: ifeq          250
     246: ldc           #48                 // String timeoutError
     248: astore        9
     250: aload         6
     252: invokevirtual #49                 // Method org/apache/dubbo/rpc/RpcException.isBiz:()Z
     255: ifeq          262
     258: ldc           #50                 // String bisError
     260: astore        9
     262: aload         6
     264: invokevirtual #51                 // Method org/apache/dubbo/rpc/RpcException.isNetwork:()Z
     267: ifeq          274
     270: ldc           #52                 // String networkError
     272: astore        9
     274: aload         6
     276: invokevirtual #53                 // Method org/apache/dubbo/rpc/RpcException.isSerialization:()Z
     279: ifeq          286
     282: ldc           #54                 // String serializationError
     284: astore        9
     286: aload_0
     287: aload_1
     288: aload_2
     289: lload         7
     291: aload         9
     293: iload_3
     294: invokespecial #44                 // Method reportMetrics:(Lorg/apache/dubbo/rpc/Invoker;Lorg/apache/dubbo/rpc/Invocation;JLjava/lang/String;Z)V
     297: aload         6
     299: athrow
    Exception table:
       from    to  target type
         120   129   132   Class java/lang/RuntimeException
         193   223   224   Class org/apache/dubbo/rpc/RpcException

  private java.lang.String buildMethodName(org.apache.dubbo.rpc.Invocation);
    Code:
       0: aload_1
       1: invokestatic  #55                 // Method org/apache/dubbo/rpc/support/RpcUtils.getMethodName:(Lorg/apache/dubbo/rpc/Invocation;)Ljava/lang/String;
       4: astore_2
       5: new           #31                 // class java/lang/StringBuilder
       8: dup
       9: aload_2
      10: invokespecial #56                 // Method java/lang/StringBuilder."<init>":(Ljava/lang/String;)V
      13: astore_3
      14: aload_1
      15: invokestatic  #57                 // Method org/apache/dubbo/rpc/support/RpcUtils.getParameterTypes:(Lorg/apache/dubbo/rpc/Invocation;)[Ljava/lang/Class;
      18: astore        4
      20: aload_3
      21: bipush        40
      23: invokevirtual #58                 // Method java/lang/StringBuilder.append:(C)Ljava/lang/StringBuilder;
      26: pop
      27: iconst_0
      28: istore        5
      30: iload         5
      32: aload         4
      34: arraylength
      35: if_icmpge     85
      38: aload_3
      39: new           #31                 // class java/lang/StringBuilder
      42: dup
      43: invokespecial #32                 // Method java/lang/StringBuilder."<init>":()V
      46: iload         5
      48: ifne          56
      51: ldc           #30                 // String
      53: goto          58
      56: ldc           #59                 // String ,
      58: invokevirtual #34                 // Method java/lang/StringBuilder.append:(Ljava/lang/String;)Ljava/lang/StringBuilder;
      61: aload         4
      63: iload         5
      65: aaload
      66: invokevirtual #60                 // Method java/lang/Class.getSimpleName:()Ljava/lang/String;
      69: invokevirtual #34                 // Method java/lang/StringBuilder.append:(Ljava/lang/String;)Ljava/lang/StringBuilder;
      72: invokevirtual #36                 // Method java/lang/StringBuilder.toString:()Ljava/lang/String;
      75: invokevirtual #34                 // Method java/lang/StringBuilder.append:(Ljava/lang/String;)Ljava/lang/StringBuilder;
      78: pop
      79: iinc          5, 1
      82: goto          30
      85: aload_3
      86: bipush        41
      88: invokevirtual #58                 // Method java/lang/StringBuilder.append:(C)Ljava/lang/StringBuilder;
      91: pop
      92: aload_1
      93: invokestatic  #61                 // Method org/apache/dubbo/rpc/support/RpcUtils.getReturnType:(Lorg/apache/dubbo/rpc/Invocation;)Ljava/lang/Class;
      96: astore        5
      98: aconst_null
      99: astore        6
     101: aload         5
     103: ifnull        129
     106: aload         5
     108: invokevirtual #62                 // Method java/lang/Class.getTypeName:()Ljava/lang/String;
     111: astore        6
     113: aload         6
     115: aload         6
     117: ldc           #63                 // String .
     119: invokevirtual #64                 // Method java/lang/String.lastIndexOf:(Ljava/lang/String;)I
     122: iconst_1
     123: iadd
     124: invokevirtual #65                 // Method java/lang/String.substring:(I)Ljava/lang/String;
     127: astore        6
     129: new           #31                 // class java/lang/StringBuilder
     132: dup
     133: invokespecial #32                 // Method java/lang/StringBuilder."<init>":()V
     136: aload         6
     138: ifnonnull     146
     141: ldc           #66                 // String void
     143: goto          148
     146: aload         6
     148: invokevirtual #34                 // Method java/lang/StringBuilder.append:(Ljava/lang/String;)Ljava/lang/StringBuilder;
     151: ldc           #67                 // String
     153: invokevirtual #34                 // Method java/lang/StringBuilder.append:(Ljava/lang/String;)Ljava/lang/StringBuilder;
     156: aload_3
     157: invokevirtual #68                 // Method java/lang/StringBuilder.append:(Ljava/lang/Object;)Ljava/lang/StringBuilder;
     160: invokevirtual #36                 // Method java/lang/StringBuilder.toString:()Ljava/lang/String;
     163: areturn

  private void reportMetrics(org.apache.dubbo.rpc.Invoker<?>, org.apache.dubbo.rpc.Invocation, long, java.lang.String, boolean);
    Code:
       0: aload_1
       1: invokeinterface #69,  1           // InterfaceMethod org/apache/dubbo/rpc/Invoker.getInterface:()Ljava/lang/Class;
       6: invokevirtual #70                 // Method java/lang/Class.getName:()Ljava/lang/String;
       9: astore        7
      11: aload_0
      12: aload_2
      13: invokespecial #71                 // Method buildMethodName:(Lorg/apache/dubbo/rpc/Invocation;)Ljava/lang/String;
      16: astore        8
      18: iload         6
      20: ifeq          67
      23: new           #72                 // class com/alibaba/metrics/MetricName
      26: dup
      27: ldc           #73                 // String dubbo.provider
      29: getstatic     #74                 // Field com/alibaba/metrics/MetricLevel.MAJOR:Lcom/alibaba/metrics/MetricLevel;
      32: invokespecial #75                 // Method com/alibaba/metrics/MetricName."<init>":(Ljava/lang/String;Lcom/alibaba/metrics/MetricLevel;)V
      35: astore        9
      37: new           #72                 // class com/alibaba/metrics/MetricName
      40: dup
      41: ldc           #76                 // String dubbo.provider.method
      43: new           #77                 // class org/apache/dubbo/monitor/dubbo/MetricsFilter$1
      46: dup
      47: aload_0
      48: iconst_4
      49: aload         7
      51: aload         8
      53: invokespecial #78                 // Method org/apache/dubbo/monitor/dubbo/MetricsFilter$1."<init>":(Lorg/apache/dubbo/monitor/dubbo/MetricsFilter;ILjava/lang/String;Ljava/lang/String;)V
      56: getstatic     #79                 // Field com/alibaba/metrics/MetricLevel.NORMAL:Lcom/alibaba/metrics/MetricLevel;
      59: invokespecial #80                 // Method com/alibaba/metrics/MetricName."<init>":(Ljava/lang/String;Ljava/util/Map;Lcom/alibaba/metrics/MetricLevel;)V
      62: astore        10
      64: goto          108
      67: new           #72                 // class com/alibaba/metrics/MetricName
      70: dup
      71: ldc           #81                 // String dubbo.consumer
      73: getstatic     #74                 // Field com/alibaba/metrics/MetricLevel.MAJOR:Lcom/alibaba/metrics/MetricLevel;
      76: invokespecial #75                 // Method com/alibaba/metrics/MetricName."<init>":(Ljava/lang/String;Lcom/alibaba/metrics/MetricLevel;)V
      79: astore        9
      81: new           #72                 // class com/alibaba/metrics/MetricName
      84: dup
      85: ldc           #82                 // String dubbo.consumer.method
      87: new           #83                 // class org/apache/dubbo/monitor/dubbo/MetricsFilter$2
      90: dup
      91: aload_0
      92: iconst_4
      93: aload         7
      95: aload         8
      97: invokespecial #84                 // Method org/apache/dubbo/monitor/dubbo/MetricsFilter$2."<init>":(Lorg/apache/dubbo/monitor/dubbo/MetricsFilter;ILjava/lang/String;Ljava/lang/String;)V
     100: getstatic     #79                 // Field com/alibaba/metrics/MetricLevel.NORMAL:Lcom/alibaba/metrics/MetricLevel;
     103: invokespecial #80                 // Method com/alibaba/metrics/MetricName."<init>":(Ljava/lang/String;Ljava/util/Map;Lcom/alibaba/metrics/MetricLevel;)V
     106: astore        10
     108: aload_0
     109: ldc           #15                 // String dubbo
     111: aload         5
     113: lload_3
     114: iconst_2
     115: anewarray     #72                 // class com/alibaba/metrics/MetricName
     118: dup
     119: iconst_0
     120: aload         9
     122: aastore
     123: dup
     124: iconst_1
     125: aload         10
     127: aastore
     128: invokespecial #85                 // Method setCompassQuantity:(Ljava/lang/String;Ljava/lang/String;J[Lcom/alibaba/metrics/MetricName;)V
     131: return

  private void setCompassQuantity(java.lang.String, java.lang.String, long, com.alibaba.metrics.MetricName...);
    Code:
       0: aload         5
       2: astore        6
       4: aload         6
       6: arraylength
       7: istore        7
       9: iconst_0
      10: istore        8
      12: iload         8
      14: iload         7
      16: if_icmpge     49
      19: aload         6
      21: iload         8
      23: aaload
      24: astore        9
      26: aload_1
      27: aload         9
      29: invokestatic  #86                 // Method com/alibaba/metrics/MetricManager.getFastCompass:(Ljava/lang/String;Lcom/alibaba/metrics/MetricName;)Lcom/alibaba/metrics/FastCompass;
      32: astore        10
      34: aload         10
      36: lload_3
      37: aload_2
      38: invokeinterface #87,  4           // InterfaceMethod com/alibaba/metrics/FastCompass.record:(JLjava/lang/String;)V
      43: iinc          8, 1
      46: goto          12
      49: return

  private java.util.List<com.alibaba.metrics.common.MetricObject> getThreadPoolMessage();
    Code:
       0: aload_0
       1: getfield      #16                 // Field extensionAccessor:Lorg/apache/dubbo/common/extension/ExtensionAccessor;
       4: ldc           #88                 // class org/apache/dubbo/common/store/DataStore
       6: invokeinterface #18,  2           // InterfaceMethod org/apache/dubbo/common/extension/ExtensionAccessor.getExtensionLoader:(Ljava/lang/Class;)Lorg/apache/dubbo/common/extension/ExtensionLoader;
      11: invokevirtual #89                 // Method org/apache/dubbo/common/extension/ExtensionLoader.getDefaultExtension:()Ljava/lang/Object;
      14: checkcast     #88                 // class org/apache/dubbo/common/store/DataStore
      17: astore_1
      18: aload_1
      19: getstatic     #90                 // Field org/apache/dubbo/common/constants/CommonConstants.EXECUTOR_SERVICE_COMPONENT_KEY:Ljava/lang/String;
      22: invokeinterface #91,  2           // InterfaceMethod org/apache/dubbo/common/store/DataStore.get:(Ljava/lang/String;)Ljava/util/Map;
      27: astore_2
      28: new           #92                 // class java/util/ArrayList
      31: dup
      32: invokespecial #93                 // Method java/util/ArrayList."<init>":()V
      35: astore_3
      36: aload_2
      37: invokeinterface #94,  1           // InterfaceMethod java/util/Map.entrySet:()Ljava/util/Set;
      42: invokeinterface #95,  1           // InterfaceMethod java/util/Set.iterator:()Ljava/util/Iterator;
      47: astore        4
      49: aload         4
      51: invokeinterface #96,  1           // InterfaceMethod java/util/Iterator.hasNext:()Z
      56: ifeq          209
      59: aload         4
      61: invokeinterface #97,  1           // InterfaceMethod java/util/Iterator.next:()Ljava/lang/Object;
      66: checkcast     #98                 // class java/util/Map$Entry
      69: astore        5
      71: aload         5
      73: invokeinterface #99,  1           // InterfaceMethod java/util/Map$Entry.getKey:()Ljava/lang/Object;
      78: checkcast     #100                // class java/lang/String
      81: astore        6
      83: aload         5
      85: invokeinterface #101,  1          // InterfaceMethod java/util/Map$Entry.getValue:()Ljava/lang/Object;
      90: checkcast     #102                // class java/util/concurrent/ExecutorService
      93: astore        7
      95: aload         7
      97: instanceof    #103                // class java/util/concurrent/ThreadPoolExecutor
     100: ifeq          206
     103: aload         7
     105: checkcast     #103                // class java/util/concurrent/ThreadPoolExecutor
     108: astore        8
     110: aload_3
     111: aload_0
     112: ldc           #104                // String threadPool.active
     114: aload         8
     116: invokevirtual #105                // Method java/util/concurrent/ThreadPoolExecutor.getActiveCount:()I
     119: invokestatic  #24                 // Method java/lang/Integer.valueOf:(I)Ljava/lang/Integer;
     122: getstatic     #74                 // Field com/alibaba/metrics/MetricLevel.MAJOR:Lcom/alibaba/metrics/MetricLevel;
     125: invokespecial #106                // Method value2MetricObject:(Ljava/lang/String;Ljava/lang/Integer;Lcom/alibaba/metrics/MetricLevel;)Lcom/alibaba/metrics/common/MetricObject;
     128: invokeinterface #107,  2          // InterfaceMethod java/util/List.add:(Ljava/lang/Object;)Z
     133: pop
     134: aload_3
     135: aload_0
     136: ldc           #108                // String threadPool.core
     138: aload         8
     140: invokevirtual #109                // Method java/util/concurrent/ThreadPoolExecutor.getCorePoolSize:()I
     143: invokestatic  #24                 // Method java/lang/Integer.valueOf:(I)Ljava/lang/Integer;
     146: getstatic     #74                 // Field com/alibaba/metrics/MetricLevel.MAJOR:Lcom/alibaba/metrics/MetricLevel;
     149: invokespecial #106                // Method value2MetricObject:(Ljava/lang/String;Ljava/lang/Integer;Lcom/alibaba/metrics/MetricLevel;)Lcom/alibaba/metrics/common/MetricObject;
     152: invokeinterface #107,  2          // InterfaceMethod java/util/List.add:(Ljava/lang/Object;)Z
     157: pop
     158: aload_3
     159: aload_0
     160: ldc           #110                // String threadPool.max
     162: aload         8
     164: invokevirtual #111                // Method java/util/concurrent/ThreadPoolExecutor.getMaximumPoolSize:()I
     167: invokestatic  #24                 // Method java/lang/Integer.valueOf:(I)Ljava/lang/Integer;
     170: getstatic     #74                 // Field com/alibaba/metrics/MetricLevel.MAJOR:Lcom/alibaba/metrics/MetricLevel;
     173: invokespecial #106                // Method value2MetricObject:(Ljava/lang/String;Ljava/lang/Integer;Lcom/alibaba/metrics/MetricLevel;)Lcom/alibaba/metrics/common/MetricObject;
     176: invokeinterface #107,  2          // InterfaceMethod java/util/List.add:(Ljava/lang/Object;)Z
     181: pop
     182: aload_3
     183: aload_0
     184: ldc           #112                // String threadPool.current
     186: aload         8
     188: invokevirtual #113                // Method java/util/concurrent/ThreadPoolExecutor.getPoolSize:()I
     191: invokestatic  #24                 // Method java/lang/Integer.valueOf:(I)Ljava/lang/Integer;
     194: getstatic     #74                 // Field com/alibaba/metrics/MetricLevel.MAJOR:Lcom/alibaba/metrics/MetricLevel;
     197: invokespecial #106                // Method value2MetricObject:(Ljava/lang/String;Ljava/lang/Integer;Lcom/alibaba/metrics/MetricLevel;)Lcom/alibaba/metrics/common/MetricObject;
     200: invokeinterface #107,  2          // InterfaceMethod java/util/List.add:(Ljava/lang/Object;)Z
     205: pop
     206: goto          49
     209: aload_3
     210: areturn

  private com.alibaba.metrics.common.MetricObject value2MetricObject(java.lang.String, java.lang.Integer, com.alibaba.metrics.MetricLevel);
    Code:
       0: aload_1
       1: ifnull        12
       4: aload_2
       5: ifnull        12
       8: aload_3
       9: ifnonnull     14
      12: aconst_null
      13: areturn
      14: new           #114                // class com/alibaba/metrics/common/MetricObject$Builder
      17: dup
      18: aload_1
      19: invokespecial #115                // Method com/alibaba/metrics/common/MetricObject$Builder."<init>":(Ljava/lang/String;)V
      22: aload_2
      23: invokevirtual #116                // Method com/alibaba/metrics/common/MetricObject$Builder.withValue:(Ljava/lang/Object;)Lcom/alibaba/metrics/common/MetricObject$Builder;
      26: aload_3
      27: invokevirtual #117                // Method com/alibaba/metrics/common/MetricObject$Builder.withLevel:(Lcom/alibaba/metrics/MetricLevel;)Lcom/alibaba/metrics/common/MetricObject$Builder;
      30: invokevirtual #118                // Method com/alibaba/metrics/common/MetricObject$Builder.build:()Lcom/alibaba/metrics/common/MetricObject;
      33: areturn

  private org.apache.dubbo.rpc.Invoker<org.apache.dubbo.monitor.MetricsService> initMetricsInvoker();
    Code:
       0: new           #119                // class org/apache/dubbo/monitor/dubbo/MetricsFilter$3
       3: dup
       4: aload_0
       5: invokespecial #120                // Method org/apache/dubbo/monitor/dubbo/MetricsFilter$3."<init>":(Lorg/apache/dubbo/monitor/dubbo/MetricsFilter;)V
       8: astore_1
       9: aload_1
      10: areturn

  public void setExtensionAccessor(org.apache.dubbo.common.extension.ExtensionAccessor);
    Code:
       0: aload_0
       1: aload_1
       2: putfield      #16                 // Field extensionAccessor:Lorg/apache/dubbo/common/extension/ExtensionAccessor;
       5: return

  static java.util.List access$000(org.apache.dubbo.monitor.dubbo.MetricsFilter);
    Code:
       0: aload_0
       1: invokespecial #7                  // Method getThreadPoolMessage:()Ljava/util/List;
       4: areturn

  static java.lang.String access$100(org.apache.dubbo.monitor.dubbo.MetricsFilter);
    Code:
       0: aload_0
       1: getfield      #6                  // Field protocolName:Ljava/lang/String;
       4: areturn

  static org.apache.dubbo.rpc.model.ApplicationModel access$200(org.apache.dubbo.monitor.dubbo.MetricsFilter);
    Code:
       0: aload_0
       1: getfield      #5                  // Field applicationModel:Lorg/apache/dubbo/rpc/model/ApplicationModel;
       4: areturn

  static java.lang.Integer access$300(org.apache.dubbo.monitor.dubbo.MetricsFilter);
    Code:
       0: aload_0
       1: getfield      #4                  // Field port:Ljava/lang/Integer;
       4: areturn

  static {};
    Code:
       0: ldc           #12                 // class org/apache/dubbo/monitor/dubbo/MetricsFilter
       2: invokestatic  #121                // Method org/apache/dubbo/common/logger/LoggerFactory.getErrorTypeAwareLogger:(Ljava/lang/Class;)Lorg/apache/dubbo/common/logger/ErrorTypeAwareLogger;
       5: putstatic     #28                 // Field logger:Lorg/apache/dubbo/common/logger/ErrorTypeAwareLogger;
       8: new           #122                // class java/util/concurrent/atomic/AtomicBoolean
      11: dup
      12: iconst_0
      13: invokespecial #123                // Method java/util/concurrent/atomic/AtomicBoolean."<init>":(Z)V
      16: putstatic     #9                  // Field exported:Ljava/util/concurrent/atomic/AtomicBoolean;
      19: return
}
