Compiled from "MetricsFilter.java"
class org.apache.dubbo.monitor.dubbo.MetricsFilter$1 extends java.util.HashMap<java.lang.String, java.lang.String> {
  final java.lang.String val$serviceName;

  final java.lang.String val$methodName;

  final org.apache.dubbo.monitor.dubbo.MetricsFilter this$0;

  org.apache.dubbo.monitor.dubbo.MetricsFilter$1(org.apache.dubbo.monitor.dubbo.MetricsFilter, int, java.lang.String, java.lang.String);
    Code:
       0: aload_0
       1: aload_1
       2: putfield      #3                  // Field this$0:Lorg/apache/dubbo/monitor/dubbo/MetricsFilter;
       5: aload_0
       6: aload_3
       7: putfield      #4                  // Field val$serviceName:Ljava/lang/String;
      10: aload_0
      11: aload         4
      13: putfield      #5                  // Field val$methodName:Ljava/lang/String;
      16: aload_0
      17: iload_2
      18: invokespecial #6                  // Method java/util/HashMap."<init>":(I)V
      21: aload_0
      22: ldc           #7                  // String service
      24: aload_0
      25: getfield      #4                  // Field val$serviceName:Ljava/lang/String;
      28: invokevirtual #8                  // Method put:(Ljava/lang/Object;Ljava/lang/Object;)Ljava/lang/Object;
      31: pop
      32: aload_0
      33: ldc           #9                  // String method
      35: aload_0
      36: getfield      #5                  // Field val$methodName:Ljava/lang/String;
      39: invokevirtual #8                  // Method put:(Ljava/lang/Object;Ljava/lang/Object;)Ljava/lang/Object;
      42: pop
      43: return
}
