Compiled from "MetricsFilter.java"
class org.apache.dubbo.monitor.dubbo.MetricsFilter$3 implements org.apache.dubbo.rpc.Invoker<org.apache.dubbo.monitor.MetricsService> {
  final org.apache.dubbo.monitor.dubbo.MetricsFilter this$0;

  org.apache.dubbo.monitor.dubbo.MetricsFilter$3(org.apache.dubbo.monitor.dubbo.MetricsFilter);
    Code:
       0: aload_0
       1: aload_1
       2: putfield      #1                  // Field this$0:Lorg/apache/dubbo/monitor/dubbo/MetricsFilter;
       5: aload_0
       6: invokespecial #2                  // Method java/lang/Object."<init>":()V
       9: return

  public java.lang.Class<org.apache.dubbo.monitor.MetricsService> getInterface();
    Code:
       0: ldc           #3                  // class org/apache/dubbo/monitor/MetricsService
       2: areturn

  public org.apache.dubbo.rpc.Result invoke(org.apache.dubbo.rpc.Invocation) throws org.apache.dubbo.rpc.RpcException;
    Code:
       0: aload_1
       1: invokeinterface #4,  1            // InterfaceMethod org/apache/dubbo/rpc/Invocation.getArguments:()[Ljava/lang/Object;
       6: iconst_0
       7: aaload
       8: invokevirtual #5                  // Method java/lang/Object.toString:()Ljava/lang/String;
      11: astore_2
      12: invokestatic  #6                  // Method com/alibaba/metrics/MetricManager.getIMetricManager:()Lcom/alibaba/metrics/IMetricManager;
      15: aload_2
      16: invokeinterface #7,  2            // InterfaceMethod com/alibaba/metrics/IMetricManager.getMetricRegistryByGroup:(Ljava/lang/String;)Lcom/alibaba/metrics/MetricRegistry;
      21: astore_3
      22: aload_3
      23: invokevirtual #8                  // Method com/alibaba/metrics/MetricRegistry.getFastCompasses:()Ljava/util/SortedMap;
      26: astore        4
      28: invokestatic  #9                  // Method java/lang/System.currentTimeMillis:()J
      31: lstore        5
      33: getstatic     #10                 // Field java/util/concurrent/TimeUnit.SECONDS:Ljava/util/concurrent/TimeUnit;
      36: lconst_1
      37: invokevirtual #11                 // Method java/util/concurrent/TimeUnit.toSeconds:(J)J
      40: l2d
      41: dstore        7
      43: dconst_1
      44: getstatic     #12                 // Field java/util/concurrent/TimeUnit.MILLISECONDS:Ljava/util/concurrent/TimeUnit;
      47: lconst_1
      48: invokevirtual #13                 // Method java/util/concurrent/TimeUnit.toNanos:(J)J
      51: l2d
      52: ddiv
      53: dstore        9
      55: getstatic     #14                 // Field com/alibaba/metrics/common/CollectLevel.NORMAL:Lcom/alibaba/metrics/common/CollectLevel;
      58: getstatic     #15                 // Field java/util/Collections.EMPTY_MAP:Ljava/util/Map;
      61: dload         7
      63: dload         9
      65: aconst_null
      66: invokestatic  #16                 // Method com/alibaba/metrics/common/MetricsCollectorFactory.createNew:(Lcom/alibaba/metrics/common/CollectLevel;Ljava/util/Map;DDLcom/alibaba/metrics/MetricFilter;)Lcom/alibaba/metrics/common/MetricsCollector;
      69: astore        11
      71: aload         4
      73: invokeinterface #17,  1           // InterfaceMethod java/util/SortedMap.entrySet:()Ljava/util/Set;
      78: invokeinterface #18,  1           // InterfaceMethod java/util/Set.iterator:()Ljava/util/Iterator;
      83: astore        12
      85: aload         12
      87: invokeinterface #19,  1           // InterfaceMethod java/util/Iterator.hasNext:()Z
      92: ifeq          137
      95: aload         12
      97: invokeinterface #20,  1           // InterfaceMethod java/util/Iterator.next:()Ljava/lang/Object;
     102: checkcast     #21                 // class java/util/Map$Entry
     105: astore        13
     107: aload         11
     109: aload         13
     111: invokeinterface #22,  1           // InterfaceMethod java/util/Map$Entry.getKey:()Ljava/lang/Object;
     116: checkcast     #23                 // class com/alibaba/metrics/MetricName
     119: aload         13
     121: invokeinterface #24,  1           // InterfaceMethod java/util/Map$Entry.getValue:()Ljava/lang/Object;
     126: checkcast     #25                 // class com/alibaba/metrics/FastCompass
     129: lload         5
     131: invokevirtual #26                 // Method com/alibaba/metrics/common/MetricsCollector.collect:(Lcom/alibaba/metrics/MetricName;Lcom/alibaba/metrics/FastCompass;J)V
     134: goto          85
     137: aload         11
     139: invokevirtual #27                 // Method com/alibaba/metrics/common/MetricsCollector.build:()Ljava/util/List;
     142: astore        12
     144: aload         12
     146: aload_0
     147: getfield      #1                  // Field this$0:Lorg/apache/dubbo/monitor/dubbo/MetricsFilter;
     150: invokestatic  #28                 // Method org/apache/dubbo/monitor/dubbo/MetricsFilter.access$000:(Lorg/apache/dubbo/monitor/dubbo/MetricsFilter;)Ljava/util/List;
     153: invokeinterface #29,  2           // InterfaceMethod java/util/List.addAll:(Ljava/util/Collection;)Z
     158: pop
     159: aload         12
     161: invokestatic  #30                 // Method org/apache/dubbo/common/utils/JsonUtils.toJson:(Ljava/lang/Object;)Ljava/lang/String;
     164: aload_1
     165: invokestatic  #31                 // Method org/apache/dubbo/rpc/AsyncRpcResult.newDefaultAsyncResult:(Ljava/lang/Object;Lorg/apache/dubbo/rpc/Invocation;)Lorg/apache/dubbo/rpc/AsyncRpcResult;
     168: areturn

  public org.apache.dubbo.common.URL getUrl();
    Code:
       0: new           #32                 // class java/lang/StringBuilder
       3: dup
       4: invokespecial #33                 // Method java/lang/StringBuilder."<init>":()V
       7: aload_0
       8: getfield      #1                  // Field this$0:Lorg/apache/dubbo/monitor/dubbo/MetricsFilter;
      11: invokestatic  #34                 // Method org/apache/dubbo/monitor/dubbo/MetricsFilter.access$100:(Lorg/apache/dubbo/monitor/dubbo/MetricsFilter;)Ljava/lang/String;
      14: invokevirtual #35                 // Method java/lang/StringBuilder.append:(Ljava/lang/String;)Ljava/lang/StringBuilder;
      17: ldc           #36                 // String ://
      19: invokevirtual #35                 // Method java/lang/StringBuilder.append:(Ljava/lang/String;)Ljava/lang/StringBuilder;
      22: aload_0
      23: getfield      #1                  // Field this$0:Lorg/apache/dubbo/monitor/dubbo/MetricsFilter;
      26: invokestatic  #37                 // Method org/apache/dubbo/monitor/dubbo/MetricsFilter.access$200:(Lorg/apache/dubbo/monitor/dubbo/MetricsFilter;)Lorg/apache/dubbo/rpc/model/ApplicationModel;
      29: invokestatic  #38                 // Method org/apache/dubbo/common/utils/NetUtils.getIpByConfig:(Lorg/apache/dubbo/rpc/model/ScopeModel;)Ljava/lang/String;
      32: invokevirtual #35                 // Method java/lang/StringBuilder.append:(Ljava/lang/String;)Ljava/lang/StringBuilder;
      35: ldc           #39                 // String :
      37: invokevirtual #35                 // Method java/lang/StringBuilder.append:(Ljava/lang/String;)Ljava/lang/StringBuilder;
      40: aload_0
      41: getfield      #1                  // Field this$0:Lorg/apache/dubbo/monitor/dubbo/MetricsFilter;
      44: invokestatic  #40                 // Method org/apache/dubbo/monitor/dubbo/MetricsFilter.access$300:(Lorg/apache/dubbo/monitor/dubbo/MetricsFilter;)Ljava/lang/Integer;
      47: invokevirtual #41                 // Method java/lang/StringBuilder.append:(Ljava/lang/Object;)Ljava/lang/StringBuilder;
      50: ldc           #42                 // String /
      52: invokevirtual #35                 // Method java/lang/StringBuilder.append:(Ljava/lang/String;)Ljava/lang/StringBuilder;
      55: ldc           #3                  // class org/apache/dubbo/monitor/MetricsService
      57: invokevirtual #43                 // Method java/lang/Class.getName:()Ljava/lang/String;
      60: invokevirtual #35                 // Method java/lang/StringBuilder.append:(Ljava/lang/String;)Ljava/lang/StringBuilder;
      63: invokevirtual #44                 // Method java/lang/StringBuilder.toString:()Ljava/lang/String;
      66: invokestatic  #45                 // Method org/apache/dubbo/common/URL.valueOf:(Ljava/lang/String;)Lorg/apache/dubbo/common/URL;
      69: areturn

  public boolean isAvailable();
    Code:
       0: iconst_0
       1: ireturn

  public void destroy();
    Code:
       0: return
}
