Compiled from "Statistics.java"
public class org.apache.dubbo.monitor.dubbo.Statistics implements java.io.Serializable {
  private static final long serialVersionUID;

  private org.apache.dubbo.common.URL url;

  private java.lang.String application;

  private java.lang.String service;

  private java.lang.String method;

  private java.lang.String group;

  private java.lang.String version;

  private java.lang.String client;

  private java.lang.String server;

  public org.apache.dubbo.monitor.dubbo.Statistics(org.apache.dubbo.common.URL);
    Code:
       0: aload_0
       1: invokespecial #2                  // Method java/lang/Object."<init>":()V
       4: aload_0
       5: aload_1
       6: putfield      #3                  // Field url:Lorg/apache/dubbo/common/URL;
       9: aload_0
      10: aload_1
      11: ldc           #4                  // String application
      13: invokevirtual #5                  // Method org/apache/dubbo/common/URL.getParameter:(Ljava/lang/String;)Ljava/lang/String;
      16: putfield      #6                  // Field application:Ljava/lang/String;
      19: aload_0
      20: aload_1
      21: ldc           #7                  // String interface
      23: invokevirtual #5                  // Method org/apache/dubbo/common/URL.getParameter:(Ljava/lang/String;)Ljava/lang/String;
      26: putfield      #8                  // Field service:Ljava/lang/String;
      29: aload_0
      30: aload_1
      31: ldc           #9                  // String method
      33: invokevirtual #5                  // Method org/apache/dubbo/common/URL.getParameter:(Ljava/lang/String;)Ljava/lang/String;
      36: putfield      #10                 // Field method:Ljava/lang/String;
      39: aload_0
      40: aload_1
      41: ldc           #11                 // String group
      43: invokevirtual #5                  // Method org/apache/dubbo/common/URL.getParameter:(Ljava/lang/String;)Ljava/lang/String;
      46: putfield      #12                 // Field group:Ljava/lang/String;
      49: aload_0
      50: aload_1
      51: ldc           #13                 // String version
      53: invokevirtual #5                  // Method org/apache/dubbo/common/URL.getParameter:(Ljava/lang/String;)Ljava/lang/String;
      56: putfield      #14                 // Field version:Ljava/lang/String;
      59: aload_0
      60: aload_1
      61: ldc           #15                 // String consumer
      63: aload_1
      64: invokevirtual #16                 // Method org/apache/dubbo/common/URL.getAddress:()Ljava/lang/String;
      67: invokevirtual #17                 // Method org/apache/dubbo/common/URL.getParameter:(Ljava/lang/String;Ljava/lang/String;)Ljava/lang/String;
      70: putfield      #18                 // Field client:Ljava/lang/String;
      73: aload_0
      74: aload_1
      75: ldc           #19                 // String provider
      77: aload_1
      78: invokevirtual #16                 // Method org/apache/dubbo/common/URL.getAddress:()Ljava/lang/String;
      81: invokevirtual #17                 // Method org/apache/dubbo/common/URL.getParameter:(Ljava/lang/String;Ljava/lang/String;)Ljava/lang/String;
      84: putfield      #20                 // Field server:Ljava/lang/String;
      87: return

  public org.apache.dubbo.common.URL getUrl();
    Code:
       0: aload_0
       1: getfield      #3                  // Field url:Lorg/apache/dubbo/common/URL;
       4: areturn

  public void setUrl(org.apache.dubbo.common.URL);
    Code:
       0: aload_0
       1: aload_1
       2: putfield      #3                  // Field url:Lorg/apache/dubbo/common/URL;
       5: return

  public java.lang.String getApplication();
    Code:
       0: aload_0
       1: getfield      #6                  // Field application:Ljava/lang/String;
       4: areturn

  public org.apache.dubbo.monitor.dubbo.Statistics setApplication(java.lang.String);
    Code:
       0: aload_0
       1: aload_1
       2: putfield      #6                  // Field application:Ljava/lang/String;
       5: aload_0
       6: areturn

  public java.lang.String getService();
    Code:
       0: aload_0
       1: getfield      #8                  // Field service:Ljava/lang/String;
       4: areturn

  public org.apache.dubbo.monitor.dubbo.Statistics setService(java.lang.String);
    Code:
       0: aload_0
       1: aload_1
       2: putfield      #8                  // Field service:Ljava/lang/String;
       5: aload_0
       6: areturn

  public java.lang.String getGroup();
    Code:
       0: aload_0
       1: getfield      #12                 // Field group:Ljava/lang/String;
       4: areturn

  public void setGroup(java.lang.String);
    Code:
       0: aload_0
       1: aload_1
       2: putfield      #12                 // Field group:Ljava/lang/String;
       5: return

  public java.lang.String getVersion();
    Code:
       0: aload_0
       1: getfield      #14                 // Field version:Ljava/lang/String;
       4: areturn

  public void setVersion(java.lang.String);
    Code:
       0: aload_0
       1: aload_1
       2: putfield      #14                 // Field version:Ljava/lang/String;
       5: return

  public java.lang.String getMethod();
    Code:
       0: aload_0
       1: getfield      #10                 // Field method:Ljava/lang/String;
       4: areturn

  public org.apache.dubbo.monitor.dubbo.Statistics setMethod(java.lang.String);
    Code:
       0: aload_0
       1: aload_1
       2: putfield      #10                 // Field method:Ljava/lang/String;
       5: aload_0
       6: areturn

  public java.lang.String getClient();
    Code:
       0: aload_0
       1: getfield      #18                 // Field client:Ljava/lang/String;
       4: areturn

  public org.apache.dubbo.monitor.dubbo.Statistics setClient(java.lang.String);
    Code:
       0: aload_0
       1: aload_1
       2: putfield      #18                 // Field client:Ljava/lang/String;
       5: aload_0
       6: areturn

  public java.lang.String getServer();
    Code:
       0: aload_0
       1: getfield      #20                 // Field server:Ljava/lang/String;
       4: areturn

  public org.apache.dubbo.monitor.dubbo.Statistics setServer(java.lang.String);
    Code:
       0: aload_0
       1: aload_1
       2: putfield      #20                 // Field server:Ljava/lang/String;
       5: aload_0
       6: areturn

  public int hashCode();
    Code:
       0: bipush        31
       2: istore_1
       3: iconst_1
       4: istore_2
       5: bipush        31
       7: iload_2
       8: imul
       9: aload_0
      10: getfield      #6                  // Field application:Ljava/lang/String;
      13: ifnonnull     20
      16: iconst_0
      17: goto          27
      20: aload_0
      21: getfield      #6                  // Field application:Ljava/lang/String;
      24: invokevirtual #21                 // Method java/lang/String.hashCode:()I
      27: iadd
      28: istore_2
      29: bipush        31
      31: iload_2
      32: imul
      33: aload_0
      34: getfield      #18                 // Field client:Ljava/lang/String;
      37: ifnonnull     44
      40: iconst_0
      41: goto          51
      44: aload_0
      45: getfield      #18                 // Field client:Ljava/lang/String;
      48: invokevirtual #21                 // Method java/lang/String.hashCode:()I
      51: iadd
      52: istore_2
      53: bipush        31
      55: iload_2
      56: imul
      57: aload_0
      58: getfield      #12                 // Field group:Ljava/lang/String;
      61: ifnonnull     68
      64: iconst_0
      65: goto          75
      68: aload_0
      69: getfield      #12                 // Field group:Ljava/lang/String;
      72: invokevirtual #21                 // Method java/lang/String.hashCode:()I
      75: iadd
      76: istore_2
      77: bipush        31
      79: iload_2
      80: imul
      81: aload_0
      82: getfield      #10                 // Field method:Ljava/lang/String;
      85: ifnonnull     92
      88: iconst_0
      89: goto          99
      92: aload_0
      93: getfield      #10                 // Field method:Ljava/lang/String;
      96: invokevirtual #21                 // Method java/lang/String.hashCode:()I
      99: iadd
     100: istore_2
     101: bipush        31
     103: iload_2
     104: imul
     105: aload_0
     106: getfield      #20                 // Field server:Ljava/lang/String;
     109: ifnonnull     116
     112: iconst_0
     113: goto          123
     116: aload_0
     117: getfield      #20                 // Field server:Ljava/lang/String;
     120: invokevirtual #21                 // Method java/lang/String.hashCode:()I
     123: iadd
     124: istore_2
     125: bipush        31
     127: iload_2
     128: imul
     129: aload_0
     130: getfield      #8                  // Field service:Ljava/lang/String;
     133: ifnonnull     140
     136: iconst_0
     137: goto          147
     140: aload_0
     141: getfield      #8                  // Field service:Ljava/lang/String;
     144: invokevirtual #21                 // Method java/lang/String.hashCode:()I
     147: iadd
     148: istore_2
     149: bipush        31
     151: iload_2
     152: imul
     153: aload_0
     154: getfield      #14                 // Field version:Ljava/lang/String;
     157: ifnonnull     164
     160: iconst_0
     161: goto          171
     164: aload_0
     165: getfield      #14                 // Field version:Ljava/lang/String;
     168: invokevirtual #21                 // Method java/lang/String.hashCode:()I
     171: iadd
     172: istore_2
     173: iload_2
     174: ireturn

  public boolean equals(java.lang.Object);
    Code:
       0: aload_0
       1: aload_1
       2: if_acmpne     7
       5: iconst_1
       6: ireturn
       7: aload_1
       8: ifnonnull     13
      11: iconst_0
      12: ireturn
      13: aload_0
      14: invokevirtual #22                 // Method java/lang/Object.getClass:()Ljava/lang/Class;
      17: aload_1
      18: invokevirtual #22                 // Method java/lang/Object.getClass:()Ljava/lang/Class;
      21: if_acmpeq     26
      24: iconst_0
      25: ireturn
      26: aload_1
      27: checkcast     #23                 // class org/apache/dubbo/monitor/dubbo/Statistics
      30: astore_2
      31: aload_0
      32: getfield      #6                  // Field application:Ljava/lang/String;
      35: ifnonnull     47
      38: aload_2
      39: getfield      #6                  // Field application:Ljava/lang/String;
      42: ifnull        63
      45: iconst_0
      46: ireturn
      47: aload_0
      48: getfield      #6                  // Field application:Ljava/lang/String;
      51: aload_2
      52: getfield      #6                  // Field application:Ljava/lang/String;
      55: invokevirtual #24                 // Method java/lang/String.equals:(Ljava/lang/Object;)Z
      58: ifne          63
      61: iconst_0
      62: ireturn
      63: aload_0
      64: getfield      #18                 // Field client:Ljava/lang/String;
      67: ifnonnull     79
      70: aload_2
      71: getfield      #18                 // Field client:Ljava/lang/String;
      74: ifnull        95
      77: iconst_0
      78: ireturn
      79: aload_0
      80: getfield      #18                 // Field client:Ljava/lang/String;
      83: aload_2
      84: getfield      #18                 // Field client:Ljava/lang/String;
      87: invokevirtual #24                 // Method java/lang/String.equals:(Ljava/lang/Object;)Z
      90: ifne          95
      93: iconst_0
      94: ireturn
      95: aload_0
      96: getfield      #12                 // Field group:Ljava/lang/String;
      99: ifnonnull     111
     102: aload_2
     103: getfield      #12                 // Field group:Ljava/lang/String;
     106: ifnull        127
     109: iconst_0
     110: ireturn
     111: aload_0
     112: getfield      #12                 // Field group:Ljava/lang/String;
     115: aload_2
     116: getfield      #12                 // Field group:Ljava/lang/String;
     119: invokevirtual #24                 // Method java/lang/String.equals:(Ljava/lang/Object;)Z
     122: ifne          127
     125: iconst_0
     126: ireturn
     127: aload_0
     128: getfield      #10                 // Field method:Ljava/lang/String;
     131: ifnonnull     143
     134: aload_2
     135: getfield      #10                 // Field method:Ljava/lang/String;
     138: ifnull        159
     141: iconst_0
     142: ireturn
     143: aload_0
     144: getfield      #10                 // Field method:Ljava/lang/String;
     147: aload_2
     148: getfield      #10                 // Field method:Ljava/lang/String;
     151: invokevirtual #24                 // Method java/lang/String.equals:(Ljava/lang/Object;)Z
     154: ifne          159
     157: iconst_0
     158: ireturn
     159: aload_0
     160: getfield      #20                 // Field server:Ljava/lang/String;
     163: ifnonnull     175
     166: aload_2
     167: getfield      #20                 // Field server:Ljava/lang/String;
     170: ifnull        191
     173: iconst_0
     174: ireturn
     175: aload_0
     176: getfield      #20                 // Field server:Ljava/lang/String;
     179: aload_2
     180: getfield      #20                 // Field server:Ljava/lang/String;
     183: invokevirtual #24                 // Method java/lang/String.equals:(Ljava/lang/Object;)Z
     186: ifne          191
     189: iconst_0
     190: ireturn
     191: aload_0
     192: getfield      #8                  // Field service:Ljava/lang/String;
     195: ifnonnull     207
     198: aload_2
     199: getfield      #8                  // Field service:Ljava/lang/String;
     202: ifnull        223
     205: iconst_0
     206: ireturn
     207: aload_0
     208: getfield      #8                  // Field service:Ljava/lang/String;
     211: aload_2
     212: getfield      #8                  // Field service:Ljava/lang/String;
     215: invokevirtual #24                 // Method java/lang/String.equals:(Ljava/lang/Object;)Z
     218: ifne          223
     221: iconst_0
     222: ireturn
     223: aload_0
     224: getfield      #14                 // Field version:Ljava/lang/String;
     227: ifnonnull     239
     230: aload_2
     231: getfield      #14                 // Field version:Ljava/lang/String;
     234: ifnull        255
     237: iconst_0
     238: ireturn
     239: aload_0
     240: getfield      #14                 // Field version:Ljava/lang/String;
     243: aload_2
     244: getfield      #14                 // Field version:Ljava/lang/String;
     247: invokevirtual #24                 // Method java/lang/String.equals:(Ljava/lang/Object;)Z
     250: ifne          255
     253: iconst_0
     254: ireturn
     255: iconst_1
     256: ireturn

  public java.lang.String toString();
    Code:
       0: aload_0
       1: getfield      #3                  // Field url:Lorg/apache/dubbo/common/URL;
       4: invokevirtual #25                 // Method org/apache/dubbo/common/URL.toString:()Ljava/lang/String;
       7: areturn
}
