Compiled from "StatisticsItem.java"
public class org.apache.dubbo.monitor.dubbo.StatisticsItem {
  private long success;

  private long failure;

  private long input;

  private long output;

  private long elapsed;

  private long concurrent;

  private long maxInput;

  private long maxOutput;

  private long maxElapsed;

  private long maxConcurrent;

  public org.apache.dubbo.monitor.dubbo.StatisticsItem();
    Code:
       0: aload_0
       1: invokespecial #1                  // Method java/lang/Object."<init>":()V
       4: return

  public void setItems(long, long, long, long, long, long);
    Code:
       0: aload_0
       1: lload_1
       2: lload_3
       3: lload         5
       5: lload         7
       7: lload         9
       9: lload         11
      11: lconst_0
      12: lconst_0
      13: lconst_0
      14: lconst_0
      15: invokevirtual #2                  // Method setItems:(JJJJJJJJJJ)V
      18: return

  public void setItems(long, long, long, long, long, long, long, long, long, long);
    Code:
       0: aload_0
       1: lload_1
       2: putfield      #3                  // Field success:J
       5: aload_0
       6: lload_3
       7: putfield      #4                  // Field failure:J
      10: aload_0
      11: lload         5
      13: putfield      #5                  // Field input:J
      16: aload_0
      17: lload         7
      19: putfield      #6                  // Field output:J
      22: aload_0
      23: lload         9
      25: putfield      #7                  // Field elapsed:J
      28: aload_0
      29: lload         11
      31: putfield      #8                  // Field concurrent:J
      34: aload_0
      35: lload         13
      37: putfield      #9                  // Field maxInput:J
      40: aload_0
      41: lload         15
      43: putfield      #10                 // Field maxOutput:J
      46: aload_0
      47: lload         17
      49: putfield      #11                 // Field maxElapsed:J
      52: aload_0
      53: lload         19
      55: putfield      #12                 // Field maxConcurrent:J
      58: return

  public long getSuccess();
    Code:
       0: aload_0
       1: getfield      #3                  // Field success:J
       4: lreturn

  public void setSuccess(long);
    Code:
       0: aload_0
       1: lload_1
       2: putfield      #3                  // Field success:J
       5: return

  public long getFailure();
    Code:
       0: aload_0
       1: getfield      #4                  // Field failure:J
       4: lreturn

  public void setFailure(long);
    Code:
       0: aload_0
       1: lload_1
       2: putfield      #4                  // Field failure:J
       5: return

  public long getInput();
    Code:
       0: aload_0
       1: getfield      #5                  // Field input:J
       4: lreturn

  public void setInput(long);
    Code:
       0: aload_0
       1: lload_1
       2: putfield      #5                  // Field input:J
       5: return

  public long getOutput();
    Code:
       0: aload_0
       1: getfield      #6                  // Field output:J
       4: lreturn

  public void setOutput(long);
    Code:
       0: aload_0
       1: lload_1
       2: putfield      #6                  // Field output:J
       5: return

  public long getElapsed();
    Code:
       0: aload_0
       1: getfield      #7                  // Field elapsed:J
       4: lreturn

  public void setElapsed(long);
    Code:
       0: aload_0
       1: lload_1
       2: putfield      #7                  // Field elapsed:J
       5: return

  public long getConcurrent();
    Code:
       0: aload_0
       1: getfield      #8                  // Field concurrent:J
       4: lreturn

  public void setConcurrent(long);
    Code:
       0: aload_0
       1: lload_1
       2: putfield      #8                  // Field concurrent:J
       5: return

  public long getMaxInput();
    Code:
       0: aload_0
       1: getfield      #9                  // Field maxInput:J
       4: lreturn

  public void setMaxInput(long);
    Code:
       0: aload_0
       1: lload_1
       2: putfield      #9                  // Field maxInput:J
       5: return

  public long getMaxOutput();
    Code:
       0: aload_0
       1: getfield      #10                 // Field maxOutput:J
       4: lreturn

  public void setMaxOutput(long);
    Code:
       0: aload_0
       1: lload_1
       2: putfield      #10                 // Field maxOutput:J
       5: return

  public long getMaxElapsed();
    Code:
       0: aload_0
       1: getfield      #11                 // Field maxElapsed:J
       4: lreturn

  public void setMaxElapsed(long);
    Code:
       0: aload_0
       1: lload_1
       2: putfield      #11                 // Field maxElapsed:J
       5: return

  public long getMaxConcurrent();
    Code:
       0: aload_0
       1: getfield      #12                 // Field maxConcurrent:J
       4: lreturn

  public void setMaxConcurrent(long);
    Code:
       0: aload_0
       1: lload_1
       2: putfield      #12                 // Field maxConcurrent:J
       5: return
}
