Compiled from "BeanCurrentlyInCreationFailureAnalyzer.java"
class org.springframework.boot.diagnostics.analyzer.BeanCurrentlyInCreationFailureAnalyzer extends org.springframework.boot.diagnostics.AbstractFailureAnalyzer<org.springframework.beans.factory.BeanCurrentlyInCreationException> {
  private final org.springframework.beans.factory.support.AbstractAutowireCapableBeanFactory beanFactory;

  org.springframework.boot.diagnostics.analyzer.BeanCurrentlyInCreationFailureAnalyzer(org.springframework.beans.factory.BeanFactory);
    Code:
       0: aload_0
       1: invokespecial #1                  // Method org/springframework/boot/diagnostics/AbstractFailureAnalyzer."<init>":()V
       4: aload_1
       5: instanceof    #7                  // class org/springframework/beans/factory/support/AbstractAutowireCapableBeanFactory
       8: ifeq          24
      11: aload_1
      12: checkcast     #7                  // class org/springframework/beans/factory/support/AbstractAutowireCapableBeanFactory
      15: astore_2
      16: aload_0
      17: aload_2
      18: putfield      #9                  // Field beanFactory:Lorg/springframework/beans/factory/support/AbstractAutowireCapableBeanFactory;
      21: goto          29
      24: aload_0
      25: aconst_null
      26: putfield      #9                  // Field beanFactory:Lorg/springframework/beans/factory/support/AbstractAutowireCapableBeanFactory;
      29: return

  protected org.springframework.boot.diagnostics.FailureAnalysis analyze(java.lang.Throwable, org.springframework.beans.factory.BeanCurrentlyInCreationException);
    Code:
       0: aload_0
       1: aload_1
       2: invokevirtual #15                 // Method findCycle:(Ljava/lang/Throwable;)Lorg/springframework/boot/diagnostics/analyzer/BeanCurrentlyInCreationFailureAnalyzer$DependencyCycle;
       5: astore_3
       6: aload_3
       7: ifnonnull     12
      10: aconst_null
      11: areturn
      12: new           #19                 // class org/springframework/boot/diagnostics/FailureAnalysis
      15: dup
      16: aload_0
      17: aload_3
      18: invokevirtual #21                 // Method buildMessage:(Lorg/springframework/boot/diagnostics/analyzer/BeanCurrentlyInCreationFailureAnalyzer$DependencyCycle;)Ljava/lang/String;
      21: aload_0
      22: invokevirtual #25                 // Method action:()Ljava/lang/String;
      25: aload_2
      26: invokespecial #29                 // Method org/springframework/boot/diagnostics/FailureAnalysis."<init>":(Ljava/lang/String;Ljava/lang/String;Ljava/lang/Throwable;)V
      29: areturn

  private java.lang.String action();
    Code:
       0: aload_0
       1: getfield      #9                  // Field beanFactory:Lorg/springframework/beans/factory/support/AbstractAutowireCapableBeanFactory;
       4: ifnull        20
       7: aload_0
       8: getfield      #9                  // Field beanFactory:Lorg/springframework/beans/factory/support/AbstractAutowireCapableBeanFactory;
      11: invokevirtual #32                 // Method org/springframework/beans/factory/support/AbstractAutowireCapableBeanFactory.isAllowCircularReferences:()Z
      14: ifeq          20
      17: ldc           #36                 // String Despite circular references being allowed, the dependency cycle between beans could not be broken. Update your application to remove the dependency cycle.
      19: areturn
      20: ldc           #38                 // String Relying upon circular references is discouraged and they are prohibited by default. Update your application to remove the dependency cycle between beans. As a last resort, it may be possible to break the cycle automatically by setting spring.main.allow-circular-references to true.
      22: areturn

  private org.springframework.boot.diagnostics.analyzer.BeanCurrentlyInCreationFailureAnalyzer$DependencyCycle findCycle(java.lang.Throwable);
    Code:
       0: new           #40                 // class java/util/ArrayList
       3: dup
       4: invokespecial #42                 // Method java/util/ArrayList."<init>":()V
       7: astore_2
       8: aload_1
       9: astore_3
      10: iconst_m1
      11: istore        4
      13: aload_3
      14: ifnull        76
      17: aload_3
      18: invokestatic  #43                 // Method org/springframework/boot/diagnostics/analyzer/BeanCurrentlyInCreationFailureAnalyzer$BeanInCycle.get:(Ljava/lang/Throwable;)Lorg/springframework/boot/diagnostics/analyzer/BeanCurrentlyInCreationFailureAnalyzer$BeanInCycle;
      21: astore        5
      23: aload         5
      25: ifnull        68
      28: aload_2
      29: aload         5
      31: invokeinterface #49,  2           // InterfaceMethod java/util/List.indexOf:(Ljava/lang/Object;)I
      36: istore        6
      38: iload         6
      40: iconst_m1
      41: if_icmpne     53
      44: aload_2
      45: aload         5
      47: invokeinterface #55,  2           // InterfaceMethod java/util/List.add:(Ljava/lang/Object;)Z
      52: pop
      53: iload         4
      55: iconst_m1
      56: if_icmpeq     64
      59: iload         4
      61: goto          66
      64: iload         6
      66: istore        4
      68: aload_3
      69: invokevirtual #59                 // Method java/lang/Throwable.getCause:()Ljava/lang/Throwable;
      72: astore_3
      73: goto          13
      76: iload         4
      78: iconst_m1
      79: if_icmpne     84
      82: aconst_null
      83: areturn
      84: new           #65                 // class org/springframework/boot/diagnostics/analyzer/BeanCurrentlyInCreationFailureAnalyzer$DependencyCycle
      87: dup
      88: aload_2
      89: iload         4
      91: invokespecial #67                 // Method org/springframework/boot/diagnostics/analyzer/BeanCurrentlyInCreationFailureAnalyzer$DependencyCycle."<init>":(Ljava/util/List;I)V
      94: areturn

  private java.lang.String buildMessage(org.springframework.boot.diagnostics.analyzer.BeanCurrentlyInCreationFailureAnalyzer$DependencyCycle);
    Code:
       0: new           #70                 // class java/lang/StringBuilder
       3: dup
       4: invokespecial #72                 // Method java/lang/StringBuilder."<init>":()V
       7: astore_2
       8: aload_2
       9: ldc           #73                 // String The dependencies of some of the beans in the application context form a cycle:%n%n
      11: iconst_0
      12: anewarray     #75                 // class java/lang/Object
      15: invokestatic  #77                 // Method java/lang/String.format:(Ljava/lang/String;[Ljava/lang/Object;)Ljava/lang/String;
      18: invokevirtual #83                 // Method java/lang/StringBuilder.append:(Ljava/lang/String;)Ljava/lang/StringBuilder;
      21: pop
      22: aload_1
      23: invokevirtual #87                 // Method org/springframework/boot/diagnostics/analyzer/BeanCurrentlyInCreationFailureAnalyzer$DependencyCycle.getBeansInCycle:()Ljava/util/List;
      26: astore_3
      27: aload_3
      28: invokeinterface #91,  1           // InterfaceMethod java/util/List.size:()I
      33: iconst_1
      34: if_icmpne     41
      37: iconst_1
      38: goto          42
      41: iconst_0
      42: istore        4
      44: aload_1
      45: invokevirtual #95                 // Method org/springframework/boot/diagnostics/analyzer/BeanCurrentlyInCreationFailureAnalyzer$DependencyCycle.getCycleStart:()I
      48: istore        5
      50: iconst_0
      51: istore        6
      53: iload         6
      55: aload_3
      56: invokeinterface #91,  1           // InterfaceMethod java/util/List.size:()I
      61: if_icmpge     197
      64: aload_3
      65: iload         6
      67: invokeinterface #98,  2           // InterfaceMethod java/util/List.get:(I)Ljava/lang/Object;
      72: checkcast     #44                 // class org/springframework/boot/diagnostics/analyzer/BeanCurrentlyInCreationFailureAnalyzer$BeanInCycle
      75: astore        7
      77: iload         6
      79: iload         5
      81: if_icmpne     111
      84: aload_2
      85: iload         4
      87: ifeq          95
      90: ldc           #101                // String 忙式式->式式忖%n
      92: goto          97
      95: ldc           #103                // String 忙式式式式式忖%n
      97: iconst_0
      98: anewarray     #75                 // class java/lang/Object
     101: invokestatic  #77                 // Method java/lang/String.format:(Ljava/lang/String;[Ljava/lang/Object;)Ljava/lang/String;
     104: invokevirtual #83                 // Method java/lang/StringBuilder.append:(Ljava/lang/String;)Ljava/lang/StringBuilder;
     107: pop
     108: goto          151
     111: iload         6
     113: ifle          151
     116: iload         6
     118: iload         5
     120: if_icmpge     128
     123: ldc           #105                // String
     125: goto          130
     128: ldc           #107                // String ∟
     130: astore        8
     132: aload_2
     133: ldc           #109                // String %s     ⊿%n
     135: iconst_1
     136: anewarray     #75                 // class java/lang/Object
     139: dup
     140: iconst_0
     141: aload         8
     143: aastore
     144: invokestatic  #77                 // Method java/lang/String.format:(Ljava/lang/String;[Ljava/lang/Object;)Ljava/lang/String;
     147: invokevirtual #83                 // Method java/lang/StringBuilder.append:(Ljava/lang/String;)Ljava/lang/StringBuilder;
     150: pop
     151: iload         6
     153: iload         5
     155: if_icmpge     163
     158: ldc           #105                // String
     160: goto          165
     163: ldc           #111                // String |
     165: astore        8
     167: aload_2
     168: ldc           #113                // String %s  %s%n
     170: iconst_2
     171: anewarray     #75                 // class java/lang/Object
     174: dup
     175: iconst_0
     176: aload         8
     178: aastore
     179: dup
     180: iconst_1
     181: aload         7
     183: aastore
     184: invokestatic  #77                 // Method java/lang/String.format:(Ljava/lang/String;[Ljava/lang/Object;)Ljava/lang/String;
     187: invokevirtual #83                 // Method java/lang/StringBuilder.append:(Ljava/lang/String;)Ljava/lang/StringBuilder;
     190: pop
     191: iinc          6, 1
     194: goto          53
     197: aload_2
     198: iload         4
     200: ifeq          208
     203: ldc           #115                // String 戌式式<-式式戎%n
     205: goto          210
     208: ldc           #117                // String 戌式式式式式戎%n
     210: iconst_0
     211: anewarray     #75                 // class java/lang/Object
     214: invokestatic  #77                 // Method java/lang/String.format:(Ljava/lang/String;[Ljava/lang/Object;)Ljava/lang/String;
     217: invokevirtual #83                 // Method java/lang/StringBuilder.append:(Ljava/lang/String;)Ljava/lang/StringBuilder;
     220: pop
     221: aload_2
     222: invokevirtual #119                // Method java/lang/StringBuilder.toString:()Ljava/lang/String;
     225: areturn

  protected org.springframework.boot.diagnostics.FailureAnalysis analyze(java.lang.Throwable, java.lang.Throwable);
    Code:
       0: aload_0
       1: aload_1
       2: aload_2
       3: checkcast     #122                // class org/springframework/beans/factory/BeanCurrentlyInCreationException
       6: invokevirtual #124                // Method analyze:(Ljava/lang/Throwable;Lorg/springframework/beans/factory/BeanCurrentlyInCreationException;)Lorg/springframework/boot/diagnostics/FailureAnalysis;
       9: areturn
}
