Compiled from "BeanNotOfRequiredTypeFailureAnalyzer.java"
public class org.springframework.boot.diagnostics.analyzer.BeanNotOfRequiredTypeFailureAnalyzer extends org.springframework.boot.diagnostics.AbstractFailureAnalyzer<org.springframework.beans.factory.BeanNotOfRequiredTypeException> {
  private static final java.lang.String ACTION;

  public org.springframework.boot.diagnostics.analyzer.BeanNotOfRequiredTypeFailureAnalyzer();
    Code:
       0: aload_0
       1: invokespecial #1                  // Method org/springframework/boot/diagnostics/AbstractFailureAnalyzer."<init>":()V
       4: return

  protected org.springframework.boot.diagnostics.FailureAnalysis analyze(java.lang.Throwable, org.springframework.beans.factory.BeanNotOfRequiredTypeException);
    Code:
       0: aload_2
       1: invokevirtual #7                  // Method org/springframework/beans/factory/BeanNotOfRequiredTypeException.getActualType:()Ljava/lang/Class;
       4: invokestatic  #13                 // Method java/lang/reflect/Proxy.isProxyClass:(Ljava/lang/Class;)Z
       7: ifne          12
      10: aconst_null
      11: areturn
      12: new           #19                 // class org/springframework/boot/diagnostics/FailureAnalysis
      15: dup
      16: aload_0
      17: aload_2
      18: invokevirtual #21                 // Method getDescription:(Lorg/springframework/beans/factory/BeanNotOfRequiredTypeException;)Ljava/lang/String;
      21: ldc           #27                 // String Consider injecting the bean as one of its interfaces or forcing the use of CGLib-based proxies by setting proxyTargetClass=true on @EnableAsync and/or @EnableCaching.
      23: aload_2
      24: invokespecial #29                 // Method org/springframework/boot/diagnostics/FailureAnalysis."<init>":(Ljava/lang/String;Ljava/lang/String;Ljava/lang/Throwable;)V
      27: areturn

  private java.lang.String getDescription(org.springframework.beans.factory.BeanNotOfRequiredTypeException);
    Code:
       0: new           #32                 // class java/io/StringWriter
       3: dup
       4: invokespecial #34                 // Method java/io/StringWriter."<init>":()V
       7: astore_2
       8: new           #35                 // class java/io/PrintWriter
      11: dup
      12: aload_2
      13: invokespecial #37                 // Method java/io/PrintWriter."<init>":(Ljava/io/Writer;)V
      16: astore_3
      17: aload_3
      18: ldc           #40                 // String The bean \'%s\' could not be injected because it is a JDK dynamic proxy%n%n
      20: iconst_1
      21: anewarray     #42                 // class java/lang/Object
      24: dup
      25: iconst_0
      26: aload_1
      27: invokevirtual #44                 // Method org/springframework/beans/factory/BeanNotOfRequiredTypeException.getBeanName:()Ljava/lang/String;
      30: aastore
      31: invokevirtual #48                 // Method java/io/PrintWriter.printf:(Ljava/lang/String;[Ljava/lang/Object;)Ljava/io/PrintWriter;
      34: pop
      35: aload_3
      36: ldc           #52                 // String The bean is of type \'%s\' and implements:%n
      38: iconst_1
      39: anewarray     #42                 // class java/lang/Object
      42: dup
      43: iconst_0
      44: aload_1
      45: invokevirtual #7                  // Method org/springframework/beans/factory/BeanNotOfRequiredTypeException.getActualType:()Ljava/lang/Class;
      48: invokevirtual #54                 // Method java/lang/Class.getName:()Ljava/lang/String;
      51: aastore
      52: invokevirtual #48                 // Method java/io/PrintWriter.printf:(Ljava/lang/String;[Ljava/lang/Object;)Ljava/io/PrintWriter;
      55: pop
      56: aload_1
      57: invokevirtual #7                  // Method org/springframework/beans/factory/BeanNotOfRequiredTypeException.getActualType:()Ljava/lang/Class;
      60: invokevirtual #59                 // Method java/lang/Class.getInterfaces:()[Ljava/lang/Class;
      63: astore        4
      65: aload         4
      67: arraylength
      68: istore        5
      70: iconst_0
      71: istore        6
      73: iload         6
      75: iload         5
      77: if_icmpge     107
      80: aload         4
      82: iload         6
      84: aaload
      85: astore        7
      87: aload_3
      88: aload         7
      90: invokevirtual #54                 // Method java/lang/Class.getName:()Ljava/lang/String;
      93: invokedynamic #63,  0             // InvokeDynamic #0:makeConcatWithConstants:(Ljava/lang/String;)Ljava/lang/String;
      98: invokevirtual #67                 // Method java/io/PrintWriter.println:(Ljava/lang/String;)V
     101: iinc          6, 1
     104: goto          73
     107: aload_3
     108: ldc           #71                 // String %nExpected a bean of type \'%s\' which implements:%n
     110: iconst_1
     111: anewarray     #42                 // class java/lang/Object
     114: dup
     115: iconst_0
     116: aload_1
     117: invokevirtual #73                 // Method org/springframework/beans/factory/BeanNotOfRequiredTypeException.getRequiredType:()Ljava/lang/Class;
     120: invokevirtual #54                 // Method java/lang/Class.getName:()Ljava/lang/String;
     123: aastore
     124: invokevirtual #48                 // Method java/io/PrintWriter.printf:(Ljava/lang/String;[Ljava/lang/Object;)Ljava/io/PrintWriter;
     127: pop
     128: aload_1
     129: invokevirtual #73                 // Method org/springframework/beans/factory/BeanNotOfRequiredTypeException.getRequiredType:()Ljava/lang/Class;
     132: invokevirtual #59                 // Method java/lang/Class.getInterfaces:()[Ljava/lang/Class;
     135: astore        4
     137: aload         4
     139: arraylength
     140: istore        5
     142: iconst_0
     143: istore        6
     145: iload         6
     147: iload         5
     149: if_icmpge     179
     152: aload         4
     154: iload         6
     156: aaload
     157: astore        7
     159: aload_3
     160: aload         7
     162: invokevirtual #54                 // Method java/lang/Class.getName:()Ljava/lang/String;
     165: invokedynamic #63,  0             // InvokeDynamic #0:makeConcatWithConstants:(Ljava/lang/String;)Ljava/lang/String;
     170: invokevirtual #67                 // Method java/io/PrintWriter.println:(Ljava/lang/String;)V
     173: iinc          6, 1
     176: goto          145
     179: aload_2
     180: invokevirtual #76                 // Method java/io/StringWriter.toString:()Ljava/lang/String;
     183: areturn

  protected org.springframework.boot.diagnostics.FailureAnalysis analyze(java.lang.Throwable, java.lang.Throwable);
    Code:
       0: aload_0
       1: aload_1
       2: aload_2
       3: checkcast     #8                  // class org/springframework/beans/factory/BeanNotOfRequiredTypeException
       6: invokevirtual #79                 // Method analyze:(Ljava/lang/Throwable;Lorg/springframework/beans/factory/BeanNotOfRequiredTypeException;)Lorg/springframework/boot/diagnostics/FailureAnalysis;
       9: areturn
}
