Compiled from "BindFailureAnalyzer.java"
class org.springframework.boot.diagnostics.analyzer.BindFailureAnalyzer extends org.springframework.boot.diagnostics.AbstractFailureAnalyzer<org.springframework.boot.context.properties.bind.BindException> {
  org.springframework.boot.diagnostics.analyzer.BindFailureAnalyzer();
    Code:
       0: aload_0
       1: invokespecial #1                  // Method org/springframework/boot/diagnostics/AbstractFailureAnalyzer."<init>":()V
       4: return

  protected org.springframework.boot.diagnostics.FailureAnalysis analyze(java.lang.Throwable, org.springframework.boot.context.properties.bind.BindException);
    Code:
       0: aload_2
       1: invokevirtual #7                  // Method org/springframework/boot/context/properties/bind/BindException.getCause:()Ljava/lang/Throwable;
       4: astore_3
       5: aload_3
       6: instanceof    #13                 // class org/springframework/boot/context/properties/bind/validation/BindValidationException
       9: ifne          19
      12: aload_3
      13: instanceof    #15                 // class org/springframework/boot/context/properties/bind/UnboundConfigurationPropertiesException
      16: ifeq          21
      19: aconst_null
      20: areturn
      21: aload_0
      22: aload_2
      23: invokevirtual #17                 // Method analyzeGenericBindException:(Lorg/springframework/boot/context/properties/bind/BindException;)Lorg/springframework/boot/diagnostics/FailureAnalysis;
      26: areturn

  private org.springframework.boot.diagnostics.FailureAnalysis analyzeGenericBindException(org.springframework.boot.context.properties.bind.BindException);
    Code:
       0: new           #23                 // class java/lang/StringBuilder
       3: dup
       4: ldc           #25                 // String %s:%n
       6: iconst_1
       7: anewarray     #27                 // class java/lang/Object
      10: dup
      11: iconst_0
      12: aload_1
      13: invokevirtual #29                 // Method org/springframework/boot/context/properties/bind/BindException.getMessage:()Ljava/lang/String;
      16: aastore
      17: invokestatic  #33                 // Method java/lang/String.format:(Ljava/lang/String;[Ljava/lang/Object;)Ljava/lang/String;
      20: invokespecial #39                 // Method java/lang/StringBuilder."<init>":(Ljava/lang/String;)V
      23: astore_2
      24: aload_1
      25: invokevirtual #42                 // Method org/springframework/boot/context/properties/bind/BindException.getProperty:()Lorg/springframework/boot/context/properties/source/ConfigurationProperty;
      28: astore_3
      29: aload_0
      30: aload_2
      31: aload_3
      32: invokevirtual #46                 // Method buildDescription:(Ljava/lang/StringBuilder;Lorg/springframework/boot/context/properties/source/ConfigurationProperty;)V
      35: aload_2
      36: ldc           #50                 // String %n    Reason: %s
      38: iconst_1
      39: anewarray     #27                 // class java/lang/Object
      42: dup
      43: iconst_0
      44: aload_0
      45: aload_1
      46: invokevirtual #52                 // Method getMessage:(Lorg/springframework/boot/context/properties/bind/BindException;)Ljava/lang/String;
      49: aastore
      50: invokestatic  #33                 // Method java/lang/String.format:(Ljava/lang/String;[Ljava/lang/Object;)Ljava/lang/String;
      53: invokevirtual #55                 // Method java/lang/StringBuilder.append:(Ljava/lang/String;)Ljava/lang/StringBuilder;
      56: pop
      57: aload_0
      58: aload_2
      59: aload_1
      60: invokevirtual #59                 // Method getFailureAnalysis:(Ljava/lang/Object;Lorg/springframework/boot/context/properties/bind/BindException;)Lorg/springframework/boot/diagnostics/FailureAnalysis;
      63: areturn

  private void buildDescription(java.lang.StringBuilder, org.springframework.boot.context.properties.source.ConfigurationProperty);
    Code:
       0: aload_2
       1: ifnull        67
       4: aload_1
       5: ldc           #63                 // String %n    Property: %s
       7: iconst_1
       8: anewarray     #27                 // class java/lang/Object
      11: dup
      12: iconst_0
      13: aload_2
      14: invokevirtual #65                 // Method org/springframework/boot/context/properties/source/ConfigurationProperty.getName:()Lorg/springframework/boot/context/properties/source/ConfigurationPropertyName;
      17: aastore
      18: invokestatic  #33                 // Method java/lang/String.format:(Ljava/lang/String;[Ljava/lang/Object;)Ljava/lang/String;
      21: invokevirtual #55                 // Method java/lang/StringBuilder.append:(Ljava/lang/String;)Ljava/lang/StringBuilder;
      24: pop
      25: aload_1
      26: ldc           #71                 // String %n    Value: \"%s\"
      28: iconst_1
      29: anewarray     #27                 // class java/lang/Object
      32: dup
      33: iconst_0
      34: aload_2
      35: invokevirtual #73                 // Method org/springframework/boot/context/properties/source/ConfigurationProperty.getValue:()Ljava/lang/Object;
      38: aastore
      39: invokestatic  #33                 // Method java/lang/String.format:(Ljava/lang/String;[Ljava/lang/Object;)Ljava/lang/String;
      42: invokevirtual #55                 // Method java/lang/StringBuilder.append:(Ljava/lang/String;)Ljava/lang/StringBuilder;
      45: pop
      46: aload_1
      47: ldc           #77                 // String %n    Origin: %s
      49: iconst_1
      50: anewarray     #27                 // class java/lang/Object
      53: dup
      54: iconst_0
      55: aload_2
      56: invokevirtual #79                 // Method org/springframework/boot/context/properties/source/ConfigurationProperty.getOrigin:()Lorg/springframework/boot/origin/Origin;
      59: aastore
      60: invokestatic  #33                 // Method java/lang/String.format:(Ljava/lang/String;[Ljava/lang/Object;)Ljava/lang/String;
      63: invokevirtual #55                 // Method java/lang/StringBuilder.append:(Ljava/lang/String;)Ljava/lang/StringBuilder;
      66: pop
      67: return

  private java.lang.String getMessage(org.springframework.boot.context.properties.bind.BindException);
    Code:
       0: aload_0
       1: aload_1
       2: invokevirtual #7                  // Method org/springframework/boot/context/properties/bind/BindException.getCause:()Ljava/lang/Throwable;
       5: invokevirtual #83                 // Method getRootCause:(Ljava/lang/Throwable;)Ljava/lang/Throwable;
       8: astore_2
       9: aload_0
      10: aload_1
      11: ldc           #87                 // class org/springframework/core/convert/ConversionFailedException
      13: invokevirtual #89                 // Method findCause:(Ljava/lang/Throwable;Ljava/lang/Class;)Ljava/lang/Throwable;
      16: checkcast     #87                 // class org/springframework/core/convert/ConversionFailedException
      19: astore_3
      20: aload_3
      21: ifnull        60
      24: aload_3
      25: invokevirtual #93                 // Method org/springframework/core/convert/ConversionFailedException.getSourceType:()Lorg/springframework/core/convert/TypeDescriptor;
      28: aload_3
      29: invokevirtual #97                 // Method org/springframework/core/convert/ConversionFailedException.getTargetType:()Lorg/springframework/core/convert/TypeDescriptor;
      32: invokedynamic #100,  0            // InvokeDynamic #0:makeConcatWithConstants:(Lorg/springframework/core/convert/TypeDescriptor;Lorg/springframework/core/convert/TypeDescriptor;)Ljava/lang/String;
      37: astore        4
      39: aload_2
      40: ifnull        57
      43: aload         4
      45: aload_0
      46: aload_2
      47: invokevirtual #104                // Method getExceptionTypeAndMessage:(Ljava/lang/Throwable;)Ljava/lang/String;
      50: invokedynamic #108,  0            // InvokeDynamic #1:makeConcatWithConstants:(Ljava/lang/String;Ljava/lang/String;)Ljava/lang/String;
      55: astore        4
      57: aload         4
      59: areturn
      60: aload_2
      61: ifnull        80
      64: aload_2
      65: invokevirtual #111                // Method java/lang/Throwable.getMessage:()Ljava/lang/String;
      68: invokestatic  #114                // Method org/springframework/util/StringUtils.hasText:(Ljava/lang/String;)Z
      71: ifeq          80
      74: aload_0
      75: aload_2
      76: invokevirtual #104                // Method getExceptionTypeAndMessage:(Ljava/lang/Throwable;)Ljava/lang/String;
      79: areturn
      80: aload_0
      81: aload_1
      82: invokevirtual #104                // Method getExceptionTypeAndMessage:(Ljava/lang/Throwable;)Ljava/lang/String;
      85: areturn

  private java.lang.Throwable getRootCause(java.lang.Throwable);
    Code:
       0: aload_1
       1: astore_2
       2: aload_2
       3: ifnull        21
       6: aload_2
       7: invokevirtual #120                // Method java/lang/Throwable.getCause:()Ljava/lang/Throwable;
      10: ifnull        21
      13: aload_2
      14: invokevirtual #120                // Method java/lang/Throwable.getCause:()Ljava/lang/Throwable;
      17: astore_2
      18: goto          2
      21: aload_2
      22: areturn

  private java.lang.String getExceptionTypeAndMessage(java.lang.Throwable);
    Code:
       0: aload_1
       1: invokevirtual #111                // Method java/lang/Throwable.getMessage:()Ljava/lang/String;
       4: astore_2
       5: aload_1
       6: invokevirtual #121                // Method java/lang/Object.getClass:()Ljava/lang/Class;
       9: invokevirtual #125                // Method java/lang/Class.getName:()Ljava/lang/String;
      12: aload_2
      13: invokestatic  #114                // Method org/springframework/util/StringUtils.hasText:(Ljava/lang/String;)Z
      16: ifeq          28
      19: aload_2
      20: invokedynamic #129,  0            // InvokeDynamic #2:makeConcatWithConstants:(Ljava/lang/String;)Ljava/lang/String;
      25: goto          30
      28: ldc           #132                // String
      30: invokedynamic #134,  0            // InvokeDynamic #3:makeConcatWithConstants:(Ljava/lang/String;Ljava/lang/String;)Ljava/lang/String;
      35: areturn

  private org.springframework.boot.diagnostics.FailureAnalysis getFailureAnalysis(java.lang.Object, org.springframework.boot.context.properties.bind.BindException);
    Code:
       0: new           #23                 // class java/lang/StringBuilder
       3: dup
       4: ldc           #135                // String Update your application\'s configuration
       6: invokespecial #39                 // Method java/lang/StringBuilder."<init>":(Ljava/lang/String;)V
       9: astore_3
      10: aload_0
      11: aload_2
      12: invokevirtual #137                // Method findValidValues:(Lorg/springframework/boot/context/properties/bind/BindException;)Ljava/util/Collection;
      15: astore        4
      17: aload         4
      19: invokeinterface #141,  1          // InterfaceMethod java/util/Collection.isEmpty:()Z
      24: ifne          54
      27: aload_3
      28: ldc           #147                // String . The following values are valid:%n
      30: iconst_0
      31: anewarray     #27                 // class java/lang/Object
      34: invokestatic  #33                 // Method java/lang/String.format:(Ljava/lang/String;[Ljava/lang/Object;)Ljava/lang/String;
      37: invokevirtual #55                 // Method java/lang/StringBuilder.append:(Ljava/lang/String;)Ljava/lang/StringBuilder;
      40: pop
      41: aload         4
      43: aload_3
      44: invokedynamic #149,  0            // InvokeDynamic #4:accept:(Ljava/lang/StringBuilder;)Ljava/util/function/Consumer;
      49: invokeinterface #153,  2          // InterfaceMethod java/util/Collection.forEach:(Ljava/util/function/Consumer;)V
      54: new           #157                // class org/springframework/boot/diagnostics/FailureAnalysis
      57: dup
      58: aload_1
      59: invokevirtual #159                // Method java/lang/Object.toString:()Ljava/lang/String;
      62: aload_3
      63: invokevirtual #162                // Method java/lang/StringBuilder.toString:()Ljava/lang/String;
      66: aload_2
      67: invokespecial #163                // Method org/springframework/boot/diagnostics/FailureAnalysis."<init>":(Ljava/lang/String;Ljava/lang/String;Ljava/lang/Throwable;)V
      70: areturn

  private java.util.Collection<java.lang.String> findValidValues(org.springframework.boot.context.properties.bind.BindException);
    Code:
       0: aload_0
       1: aload_1
       2: ldc           #87                 // class org/springframework/core/convert/ConversionFailedException
       4: invokevirtual #89                 // Method findCause:(Ljava/lang/Throwable;Ljava/lang/Class;)Ljava/lang/Throwable;
       7: checkcast     #87                 // class org/springframework/core/convert/ConversionFailedException
      10: astore_2
      11: aload_2
      12: ifnull        61
      15: aload_2
      16: invokevirtual #97                 // Method org/springframework/core/convert/ConversionFailedException.getTargetType:()Lorg/springframework/core/convert/TypeDescriptor;
      19: invokevirtual #166                // Method org/springframework/core/convert/TypeDescriptor.getType:()Ljava/lang/Class;
      22: invokevirtual #171                // Method java/lang/Class.getEnumConstants:()[Ljava/lang/Object;
      25: astore_3
      26: aload_3
      27: ifnull        61
      30: aload_3
      31: invokestatic  #175                // InterfaceMethod java/util/stream/Stream.of:([Ljava/lang/Object;)Ljava/util/stream/Stream;
      34: invokedynamic #181,  0            // InvokeDynamic #5:apply:()Ljava/util/function/Function;
      39: invokeinterface #185,  2          // InterfaceMethod java/util/stream/Stream.map:(Ljava/util/function/Function;)Ljava/util/stream/Stream;
      44: invokedynamic #189,  0            // InvokeDynamic #6:get:()Ljava/util/function/Supplier;
      49: invokestatic  #193                // Method java/util/stream/Collectors.toCollection:(Ljava/util/function/Supplier;)Ljava/util/stream/Collector;
      52: invokeinterface #199,  2          // InterfaceMethod java/util/stream/Stream.collect:(Ljava/util/stream/Collector;)Ljava/lang/Object;
      57: checkcast     #142                // class java/util/Collection
      60: areturn
      61: invokestatic  #203                // Method java/util/Collections.emptySet:()Ljava/util/Set;
      64: areturn

  protected org.springframework.boot.diagnostics.FailureAnalysis analyze(java.lang.Throwable, java.lang.Throwable);
    Code:
       0: aload_0
       1: aload_1
       2: aload_2
       3: checkcast     #8                  // class org/springframework/boot/context/properties/bind/BindException
       6: invokevirtual #209                // Method analyze:(Ljava/lang/Throwable;Lorg/springframework/boot/context/properties/bind/BindException;)Lorg/springframework/boot/diagnostics/FailureAnalysis;
       9: areturn

  private static void lambda$getFailureAnalysis$0(java.lang.StringBuilder, java.lang.String);
    Code:
       0: aload_0
       1: ldc           #213                // String %n    %s
       3: iconst_1
       4: anewarray     #27                 // class java/lang/Object
       7: dup
       8: iconst_0
       9: aload_1
      10: aastore
      11: invokestatic  #33                 // Method java/lang/String.format:(Ljava/lang/String;[Ljava/lang/Object;)Ljava/lang/String;
      14: invokevirtual #55                 // Method java/lang/StringBuilder.append:(Ljava/lang/String;)Ljava/lang/StringBuilder;
      17: pop
      18: return
}
