Compiled from "InvalidConfigurationPropertyValueFailureAnalyzer.java"
class org.springframework.boot.diagnostics.analyzer.InvalidConfigurationPropertyValueFailureAnalyzer extends org.springframework.boot.diagnostics.AbstractFailureAnalyzer<org.springframework.boot.context.properties.source.InvalidConfigurationPropertyValueException> {
  private final org.springframework.core.env.ConfigurableEnvironment environment;

  org.springframework.boot.diagnostics.analyzer.InvalidConfigurationPropertyValueFailureAnalyzer(org.springframework.core.env.Environment);
    Code:
       0: aload_0
       1: invokespecial #1                  // Method org/springframework/boot/diagnostics/AbstractFailureAnalyzer."<init>":()V
       4: aload_0
       5: aload_1
       6: checkcast     #7                  // class org/springframework/core/env/ConfigurableEnvironment
       9: putfield      #9                  // Field environment:Lorg/springframework/core/env/ConfigurableEnvironment;
      12: return

  protected org.springframework.boot.diagnostics.FailureAnalysis analyze(java.lang.Throwable, org.springframework.boot.context.properties.source.InvalidConfigurationPropertyValueException);
    Code:
       0: aload_0
       1: aload_2
       2: invokevirtual #15                 // Method org/springframework/boot/context/properties/source/InvalidConfigurationPropertyValueException.getName:()Ljava/lang/String;
       5: invokevirtual #21                 // Method getDescriptors:(Ljava/lang/String;)Ljava/util/List;
       8: astore_3
       9: aload_3
      10: invokeinterface #25,  1           // InterfaceMethod java/util/List.isEmpty:()Z
      15: ifeq          20
      18: aconst_null
      19: areturn
      20: new           #31                 // class java/lang/StringBuilder
      23: dup
      24: invokespecial #33                 // Method java/lang/StringBuilder."<init>":()V
      27: astore        4
      29: aload_0
      30: aload         4
      32: aload_2
      33: aload_3
      34: invokevirtual #34                 // Method appendDetails:(Ljava/lang/StringBuilder;Lorg/springframework/boot/context/properties/source/InvalidConfigurationPropertyValueException;Ljava/util/List;)V
      37: aload_0
      38: aload         4
      40: aload_2
      41: invokevirtual #38                 // Method appendReason:(Ljava/lang/StringBuilder;Lorg/springframework/boot/context/properties/source/InvalidConfigurationPropertyValueException;)V
      44: aload_0
      45: aload         4
      47: aload_3
      48: invokevirtual #42                 // Method appendAdditionalProperties:(Ljava/lang/StringBuilder;Ljava/util/List;)V
      51: new           #46                 // class org/springframework/boot/diagnostics/FailureAnalysis
      54: dup
      55: aload         4
      57: invokevirtual #48                 // Method java/lang/StringBuilder.toString:()Ljava/lang/String;
      60: aload_0
      61: aload_2
      62: invokevirtual #51                 // Method getAction:(Lorg/springframework/boot/context/properties/source/InvalidConfigurationPropertyValueException;)Ljava/lang/String;
      65: aload_2
      66: invokespecial #55                 // Method org/springframework/boot/diagnostics/FailureAnalysis."<init>":(Ljava/lang/String;Ljava/lang/String;Ljava/lang/Throwable;)V
      69: areturn

  private java.util.List<org.springframework.boot.diagnostics.analyzer.InvalidConfigurationPropertyValueFailureAnalyzer$Descriptor> getDescriptors(java.lang.String);
    Code:
       0: aload_0
       1: invokevirtual #58                 // Method getPropertySources:()Ljava/util/stream/Stream;
       4: aload_1
       5: invokedynamic #62,  0             // InvokeDynamic #0:test:(Ljava/lang/String;)Ljava/util/function/Predicate;
      10: invokeinterface #66,  2           // InterfaceMethod java/util/stream/Stream.filter:(Ljava/util/function/Predicate;)Ljava/util/stream/Stream;
      15: aload_1
      16: invokedynamic #72,  0             // InvokeDynamic #1:apply:(Ljava/lang/String;)Ljava/util/function/Function;
      21: invokeinterface #76,  2           // InterfaceMethod java/util/stream/Stream.map:(Ljava/util/function/Function;)Ljava/util/stream/Stream;
      26: invokeinterface #80,  1           // InterfaceMethod java/util/stream/Stream.toList:()Ljava/util/List;
      31: areturn

  private java.util.stream.Stream<org.springframework.core.env.PropertySource<?>> getPropertySources();
    Code:
       0: aload_0
       1: getfield      #9                  // Field environment:Lorg/springframework/core/env/ConfigurableEnvironment;
       4: ifnonnull     11
       7: invokestatic  #84                 // InterfaceMethod java/util/stream/Stream.empty:()Ljava/util/stream/Stream;
      10: areturn
      11: aload_0
      12: getfield      #9                  // Field environment:Lorg/springframework/core/env/ConfigurableEnvironment;
      15: invokeinterface #87,  1           // InterfaceMethod org/springframework/core/env/ConfigurableEnvironment.getPropertySources:()Lorg/springframework/core/env/MutablePropertySources;
      20: invokevirtual #90                 // Method org/springframework/core/env/MutablePropertySources.stream:()Ljava/util/stream/Stream;
      23: invokedynamic #95,  0             // InvokeDynamic #2:test:()Ljava/util/function/Predicate;
      28: invokeinterface #66,  2           // InterfaceMethod java/util/stream/Stream.filter:(Ljava/util/function/Predicate;)Ljava/util/stream/Stream;
      33: areturn

  private void appendDetails(java.lang.StringBuilder, org.springframework.boot.context.properties.source.InvalidConfigurationPropertyValueException, java.util.List<org.springframework.boot.diagnostics.analyzer.InvalidConfigurationPropertyValueFailureAnalyzer$Descriptor>);
    Code:
       0: aload_3
       1: iconst_0
       2: invokeinterface #98,  2           // InterfaceMethod java/util/List.get:(I)Ljava/lang/Object;
       7: checkcast     #102                // class org/springframework/boot/diagnostics/analyzer/InvalidConfigurationPropertyValueFailureAnalyzer$Descriptor
      10: astore        4
      12: aload_1
      13: ldc           #104                // String Invalid value \'
      15: invokevirtual #106                // Method java/lang/StringBuilder.append:(Ljava/lang/String;)Ljava/lang/StringBuilder;
      18: aload         4
      20: invokevirtual #110                // Method org/springframework/boot/diagnostics/analyzer/InvalidConfigurationPropertyValueFailureAnalyzer$Descriptor.getValue:()Ljava/lang/Object;
      23: invokevirtual #114                // Method java/lang/StringBuilder.append:(Ljava/lang/Object;)Ljava/lang/StringBuilder;
      26: ldc           #117                // String \' for configuration property \'
      28: invokevirtual #106                // Method java/lang/StringBuilder.append:(Ljava/lang/String;)Ljava/lang/StringBuilder;
      31: pop
      32: aload_1
      33: aload_2
      34: invokevirtual #15                 // Method org/springframework/boot/context/properties/source/InvalidConfigurationPropertyValueException.getName:()Ljava/lang/String;
      37: invokevirtual #106                // Method java/lang/StringBuilder.append:(Ljava/lang/String;)Ljava/lang/StringBuilder;
      40: ldc           #119                // String \'
      42: invokevirtual #106                // Method java/lang/StringBuilder.append:(Ljava/lang/String;)Ljava/lang/StringBuilder;
      45: pop
      46: aload         4
      48: aload_1
      49: invokevirtual #121                // Method org/springframework/boot/diagnostics/analyzer/InvalidConfigurationPropertyValueFailureAnalyzer$Descriptor.appendOrigin:(Ljava/lang/StringBuilder;)V
      52: aload_1
      53: ldc           #125                // String .
      55: invokevirtual #106                // Method java/lang/StringBuilder.append:(Ljava/lang/String;)Ljava/lang/StringBuilder;
      58: pop
      59: return

  private void appendReason(java.lang.StringBuilder, org.springframework.boot.context.properties.source.InvalidConfigurationPropertyValueException);
    Code:
       0: aload_2
       1: invokevirtual #127                // Method org/springframework/boot/context/properties/source/InvalidConfigurationPropertyValueException.getReason:()Ljava/lang/String;
       4: invokestatic  #130                // Method org/springframework/util/StringUtils.hasText:(Ljava/lang/String;)Z
       7: ifeq          36
      10: aload_1
      11: ldc           #136                // String  Validation failed for the following reason:%n%n
      13: iconst_0
      14: anewarray     #138                // class java/lang/Object
      17: invokestatic  #140                // Method java/lang/String.format:(Ljava/lang/String;[Ljava/lang/Object;)Ljava/lang/String;
      20: invokevirtual #106                // Method java/lang/StringBuilder.append:(Ljava/lang/String;)Ljava/lang/StringBuilder;
      23: pop
      24: aload_1
      25: aload_2
      26: invokevirtual #127                // Method org/springframework/boot/context/properties/source/InvalidConfigurationPropertyValueException.getReason:()Ljava/lang/String;
      29: invokevirtual #106                // Method java/lang/StringBuilder.append:(Ljava/lang/String;)Ljava/lang/StringBuilder;
      32: pop
      33: goto          43
      36: aload_1
      37: ldc           #146                // String  No reason was provided.
      39: invokevirtual #106                // Method java/lang/StringBuilder.append:(Ljava/lang/String;)Ljava/lang/StringBuilder;
      42: pop
      43: return

  private void appendAdditionalProperties(java.lang.StringBuilder, java.util.List<org.springframework.boot.diagnostics.analyzer.InvalidConfigurationPropertyValueFailureAnalyzer$Descriptor>);
    Code:
       0: aload_2
       1: iconst_1
       2: aload_2
       3: invokeinterface #148,  1          // InterfaceMethod java/util/List.size:()I
       8: invokeinterface #152,  3          // InterfaceMethod java/util/List.subList:(II)Ljava/util/List;
      13: astore_3
      14: aload_3
      15: invokeinterface #25,  1           // InterfaceMethod java/util/List.isEmpty:()Z
      20: ifne          150
      23: aload_1
      24: ldc           #156                // String %n%nAdditionally, this property is also set in the following property %s:%n%n
      26: iconst_1
      27: anewarray     #138                // class java/lang/Object
      30: dup
      31: iconst_0
      32: aload_3
      33: invokeinterface #148,  1          // InterfaceMethod java/util/List.size:()I
      38: iconst_1
      39: if_icmple     47
      42: ldc           #158                // String sources
      44: goto          49
      47: ldc           #160                // String source
      49: aastore
      50: invokestatic  #140                // Method java/lang/String.format:(Ljava/lang/String;[Ljava/lang/Object;)Ljava/lang/String;
      53: invokevirtual #106                // Method java/lang/StringBuilder.append:(Ljava/lang/String;)Ljava/lang/StringBuilder;
      56: pop
      57: aload_3
      58: invokeinterface #162,  1          // InterfaceMethod java/util/List.iterator:()Ljava/util/Iterator;
      63: astore        4
      65: aload         4
      67: invokeinterface #166,  1          // InterfaceMethod java/util/Iterator.hasNext:()Z
      72: ifeq          150
      75: aload         4
      77: invokeinterface #171,  1          // InterfaceMethod java/util/Iterator.next:()Ljava/lang/Object;
      82: checkcast     #102                // class org/springframework/boot/diagnostics/analyzer/InvalidConfigurationPropertyValueFailureAnalyzer$Descriptor
      85: astore        5
      87: aload_1
      88: ldc           #174                // String \t- In \'
      90: invokevirtual #106                // Method java/lang/StringBuilder.append:(Ljava/lang/String;)Ljava/lang/StringBuilder;
      93: aload         5
      95: invokevirtual #176                // Method org/springframework/boot/diagnostics/analyzer/InvalidConfigurationPropertyValueFailureAnalyzer$Descriptor.getPropertySource:()Ljava/lang/String;
      98: invokevirtual #106                // Method java/lang/StringBuilder.append:(Ljava/lang/String;)Ljava/lang/StringBuilder;
     101: ldc           #119                // String \'
     103: invokevirtual #106                // Method java/lang/StringBuilder.append:(Ljava/lang/String;)Ljava/lang/StringBuilder;
     106: pop
     107: aload_1
     108: ldc           #179                // String  with the value \'
     110: invokevirtual #106                // Method java/lang/StringBuilder.append:(Ljava/lang/String;)Ljava/lang/StringBuilder;
     113: aload         5
     115: invokevirtual #110                // Method org/springframework/boot/diagnostics/analyzer/InvalidConfigurationPropertyValueFailureAnalyzer$Descriptor.getValue:()Ljava/lang/Object;
     118: invokevirtual #114                // Method java/lang/StringBuilder.append:(Ljava/lang/Object;)Ljava/lang/StringBuilder;
     121: ldc           #119                // String \'
     123: invokevirtual #106                // Method java/lang/StringBuilder.append:(Ljava/lang/String;)Ljava/lang/StringBuilder;
     126: pop
     127: aload         5
     129: aload_1
     130: invokevirtual #121                // Method org/springframework/boot/diagnostics/analyzer/InvalidConfigurationPropertyValueFailureAnalyzer$Descriptor.appendOrigin:(Ljava/lang/StringBuilder;)V
     133: aload_1
     134: ldc           #181                // String .%n
     136: iconst_0
     137: anewarray     #138                // class java/lang/Object
     140: invokestatic  #140                // Method java/lang/String.format:(Ljava/lang/String;[Ljava/lang/Object;)Ljava/lang/String;
     143: invokevirtual #106                // Method java/lang/StringBuilder.append:(Ljava/lang/String;)Ljava/lang/StringBuilder;
     146: pop
     147: goto          65
     150: return

  private java.lang.String getAction(org.springframework.boot.context.properties.source.InvalidConfigurationPropertyValueException);
    Code:
       0: new           #31                 // class java/lang/StringBuilder
       3: dup
       4: invokespecial #33                 // Method java/lang/StringBuilder."<init>":()V
       7: astore_2
       8: aload_2
       9: ldc           #183                // String Review the value of the property
      11: invokevirtual #106                // Method java/lang/StringBuilder.append:(Ljava/lang/String;)Ljava/lang/StringBuilder;
      14: pop
      15: aload_1
      16: invokevirtual #127                // Method org/springframework/boot/context/properties/source/InvalidConfigurationPropertyValueException.getReason:()Ljava/lang/String;
      19: ifnull        29
      22: aload_2
      23: ldc           #185                // String  with the provided reason
      25: invokevirtual #106                // Method java/lang/StringBuilder.append:(Ljava/lang/String;)Ljava/lang/StringBuilder;
      28: pop
      29: aload_2
      30: ldc           #125                // String .
      32: invokevirtual #106                // Method java/lang/StringBuilder.append:(Ljava/lang/String;)Ljava/lang/StringBuilder;
      35: pop
      36: aload_2
      37: invokevirtual #48                 // Method java/lang/StringBuilder.toString:()Ljava/lang/String;
      40: areturn

  protected org.springframework.boot.diagnostics.FailureAnalysis analyze(java.lang.Throwable, java.lang.Throwable);
    Code:
       0: aload_0
       1: aload_1
       2: aload_2
       3: checkcast     #16                 // class org/springframework/boot/context/properties/source/InvalidConfigurationPropertyValueException
       6: invokevirtual #187                // Method analyze:(Ljava/lang/Throwable;Lorg/springframework/boot/context/properties/source/InvalidConfigurationPropertyValueException;)Lorg/springframework/boot/diagnostics/FailureAnalysis;
       9: areturn

  private static boolean lambda$getPropertySources$2(org.springframework.core.env.PropertySource);
    Code:
       0: aload_0
       1: invokestatic  #191                // Method org/springframework/boot/context/properties/source/ConfigurationPropertySources.isAttachedConfigurationPropertySource:(Lorg/springframework/core/env/PropertySource;)Z
       4: ifne          11
       7: iconst_1
       8: goto          12
      11: iconst_0
      12: ireturn

  private static org.springframework.boot.diagnostics.analyzer.InvalidConfigurationPropertyValueFailureAnalyzer$Descriptor lambda$getDescriptors$1(java.lang.String, org.springframework.core.env.PropertySource);
    Code:
       0: aload_1
       1: aload_0
       2: invokestatic  #197                // Method org/springframework/boot/diagnostics/analyzer/InvalidConfigurationPropertyValueFailureAnalyzer$Descriptor.get:(Lorg/springframework/core/env/PropertySource;Ljava/lang/String;)Lorg/springframework/boot/diagnostics/analyzer/InvalidConfigurationPropertyValueFailureAnalyzer$Descriptor;
       5: areturn

  private static boolean lambda$getDescriptors$0(java.lang.String, org.springframework.core.env.PropertySource);
    Code:
       0: aload_1
       1: aload_0
       2: invokevirtual #200                // Method org/springframework/core/env/PropertySource.containsProperty:(Ljava/lang/String;)Z
       5: ireturn
}
