Compiled from "MutuallyExclusiveConfigurationPropertiesFailureAnalyzer.java"
final class org.springframework.boot.diagnostics.analyzer.MutuallyExclusiveConfigurationPropertiesFailureAnalyzer$Descriptor {
  private final java.lang.String propertyName;

  private final org.springframework.boot.origin.Origin origin;

  private org.springframework.boot.diagnostics.analyzer.MutuallyExclusiveConfigurationPropertiesFailureAnalyzer$Descriptor(java.lang.String, org.springframework.boot.origin.Origin);
    Code:
       0: aload_0
       1: invokespecial #1                  // Method java/lang/Object."<init>":()V
       4: aload_0
       5: aload_1
       6: putfield      #7                  // Field propertyName:Ljava/lang/String;
       9: aload_0
      10: aload_2
      11: putfield      #13                 // Field origin:Lorg/springframework/boot/origin/Origin;
      14: return

  static org.springframework.boot.diagnostics.analyzer.MutuallyExclusiveConfigurationPropertiesFailureAnalyzer$Descriptor get(org.springframework.core.env.PropertySource<?>, java.lang.String);
    Code:
       0: aload_0
       1: aload_1
       2: invokestatic  #17                 // InterfaceMethod org/springframework/boot/origin/OriginLookup.getOrigin:(Ljava/lang/Object;Ljava/lang/Object;)Lorg/springframework/boot/origin/Origin;
       5: astore_2
       6: new           #8                  // class org/springframework/boot/diagnostics/analyzer/MutuallyExclusiveConfigurationPropertiesFailureAnalyzer$Descriptor
       9: dup
      10: aload_1
      11: aload_2
      12: invokespecial #23                 // Method "<init>":(Ljava/lang/String;Lorg/springframework/boot/origin/Origin;)V
      15: areturn
}
