Compiled from "NoSuchMethodFailureAnalyzer.java"
class org.springframework.boot.diagnostics.analyzer.NoSuchMethodFailureAnalyzer extends org.springframework.boot.diagnostics.AbstractFailureAnalyzer<java.lang.NoSuchMethodError> {
  org.springframework.boot.diagnostics.analyzer.NoSuchMethodFailureAnalyzer();
    Code:
       0: aload_0
       1: invokespecial #1                  // Method org/springframework/boot/diagnostics/AbstractFailureAnalyzer."<init>":()V
       4: return

  protected org.springframework.boot.diagnostics.FailureAnalysis analyze(java.lang.Throwable, java.lang.NoSuchMethodError);
    Code:
       0: aload_0
       1: aload_2
       2: invokevirtual #7                  // Method getCallerMethodDescriptor:(Ljava/lang/NoSuchMethodError;)Lorg/springframework/boot/diagnostics/analyzer/NoSuchMethodFailureAnalyzer$NoSuchMethodDescriptor;
       5: astore_3
       6: aload_3
       7: ifnonnull     12
      10: aconst_null
      11: areturn
      12: aload_0
      13: aload_2
      14: invokevirtual #13                 // Method java/lang/NoSuchMethodError.getMessage:()Ljava/lang/String;
      17: invokevirtual #19                 // Method getNoSuchMethodDescriptor:(Ljava/lang/String;)Lorg/springframework/boot/diagnostics/analyzer/NoSuchMethodFailureAnalyzer$NoSuchMethodDescriptor;
      20: astore        4
      22: aload         4
      24: ifnonnull     29
      27: aconst_null
      28: areturn
      29: aload_0
      30: aload_3
      31: aload         4
      33: invokevirtual #23                 // Method getDescription:(Lorg/springframework/boot/diagnostics/analyzer/NoSuchMethodFailureAnalyzer$NoSuchMethodDescriptor;Lorg/springframework/boot/diagnostics/analyzer/NoSuchMethodFailureAnalyzer$NoSuchMethodDescriptor;)Ljava/lang/String;
      36: astore        5
      38: aload_0
      39: aload_3
      40: aload         4
      42: invokevirtual #27                 // Method getAction:(Lorg/springframework/boot/diagnostics/analyzer/NoSuchMethodFailureAnalyzer$NoSuchMethodDescriptor;Lorg/springframework/boot/diagnostics/analyzer/NoSuchMethodFailureAnalyzer$NoSuchMethodDescriptor;)Ljava/lang/String;
      45: astore        6
      47: new           #30                 // class org/springframework/boot/diagnostics/FailureAnalysis
      50: dup
      51: aload         5
      53: aload         6
      55: aload_2
      56: invokespecial #32                 // Method org/springframework/boot/diagnostics/FailureAnalysis."<init>":(Ljava/lang/String;Ljava/lang/String;Ljava/lang/Throwable;)V
      59: areturn

  private org.springframework.boot.diagnostics.analyzer.NoSuchMethodFailureAnalyzer$NoSuchMethodDescriptor getCallerMethodDescriptor(java.lang.NoSuchMethodError);
    Code:
       0: aload_1
       1: invokevirtual #35                 // Method java/lang/NoSuchMethodError.getStackTrace:()[Ljava/lang/StackTraceElement;
       4: iconst_0
       5: aaload
       6: astore_2
       7: aload_2
       8: invokevirtual #39                 // Method java/lang/StackTraceElement.toString:()Ljava/lang/String;
      11: astore_3
      12: aload_2
      13: invokevirtual #44                 // Method java/lang/StackTraceElement.getClassName:()Ljava/lang/String;
      16: astore        4
      18: aload_0
      19: aload_3
      20: aload         4
      22: invokevirtual #47                 // Method getDescriptorForClass:(Ljava/lang/String;Ljava/lang/String;)Lorg/springframework/boot/diagnostics/analyzer/NoSuchMethodFailureAnalyzer$NoSuchMethodDescriptor;
      25: areturn

  protected org.springframework.boot.diagnostics.analyzer.NoSuchMethodFailureAnalyzer$NoSuchMethodDescriptor getNoSuchMethodDescriptor(java.lang.String);
    Code:
       0: aload_0
       1: aload_1
       2: invokevirtual #51                 // Method cleanMessage:(Ljava/lang/String;)Ljava/lang/String;
       5: astore_2
       6: aload_0
       7: aload_2
       8: invokevirtual #55                 // Method extractClassName:(Ljava/lang/String;)Ljava/lang/String;
      11: astore_3
      12: aload_0
      13: aload_2
      14: aload_3
      15: invokevirtual #47                 // Method getDescriptorForClass:(Ljava/lang/String;Ljava/lang/String;)Lorg/springframework/boot/diagnostics/analyzer/NoSuchMethodFailureAnalyzer$NoSuchMethodDescriptor;
      18: areturn

  private org.springframework.boot.diagnostics.analyzer.NoSuchMethodFailureAnalyzer$NoSuchMethodDescriptor getDescriptorForClass(java.lang.String, java.lang.String);
    Code:
       0: aload_2
       1: ifnonnull     6
       4: aconst_null
       5: areturn
       6: aload_0
       7: aload_2
       8: invokevirtual #58                 // Method findCandidates:(Ljava/lang/String;)Ljava/util/List;
      11: astore_3
      12: aload_3
      13: ifnonnull     18
      16: aconst_null
      17: areturn
      18: aload_0
      19: aload_2
      20: invokevirtual #62                 // Method load:(Ljava/lang/String;)Ljava/lang/Class;
      23: astore        4
      25: aload         4
      27: ifnonnull     32
      30: aconst_null
      31: areturn
      32: aload_0
      33: aload         4
      35: invokevirtual #66                 // Method getTypeHierarchy:(Ljava/lang/Class;)Ljava/util/List;
      38: astore        5
      40: aload         5
      42: ifnonnull     47
      45: aconst_null
      46: areturn
      47: new           #70                 // class org/springframework/boot/diagnostics/analyzer/NoSuchMethodFailureAnalyzer$NoSuchMethodDescriptor
      50: dup
      51: aload_1
      52: aload_2
      53: aload_3
      54: aload         5
      56: invokespecial #72                 // Method org/springframework/boot/diagnostics/analyzer/NoSuchMethodFailureAnalyzer$NoSuchMethodDescriptor."<init>":(Ljava/lang/String;Ljava/lang/String;Ljava/util/List;Ljava/util/List;)V
      59: areturn

  private java.lang.String cleanMessage(java.lang.String);
    Code:
       0: aload_1
       1: ldc           #75                 // String  (loaded from
       3: invokevirtual #77                 // Method java/lang/String.indexOf:(Ljava/lang/String;)I
       6: istore_2
       7: iload_2
       8: iconst_m1
       9: if_icmpne     14
      12: aload_1
      13: areturn
      14: aload_1
      15: iconst_0
      16: iload_2
      17: invokevirtual #83                 // Method java/lang/String.substring:(II)Ljava/lang/String;
      20: areturn

  private java.lang.String extractClassName(java.lang.String);
    Code:
       0: aload_1
       1: ldc           #87                 // String \'
       3: invokevirtual #89                 // Method java/lang/String.startsWith:(Ljava/lang/String;)Z
       6: ifeq          40
       9: aload_1
      10: ldc           #87                 // String \'
      12: invokevirtual #93                 // Method java/lang/String.endsWith:(Ljava/lang/String;)Z
      15: ifeq          40
      18: aload_1
      19: bipush        32
      21: invokevirtual #96                 // Method java/lang/String.indexOf:(I)I
      24: istore_2
      25: iload_2
      26: iconst_m1
      27: if_icmpne     32
      30: aconst_null
      31: areturn
      32: aload_1
      33: iload_2
      34: iconst_1
      35: iadd
      36: invokevirtual #99                 // Method java/lang/String.substring:(I)Ljava/lang/String;
      39: astore_1
      40: aload_1
      41: bipush        40
      43: invokevirtual #96                 // Method java/lang/String.indexOf:(I)I
      46: istore_2
      47: iload_2
      48: iconst_m1
      49: if_icmpne     54
      52: aconst_null
      53: areturn
      54: aload_1
      55: iconst_0
      56: iload_2
      57: invokevirtual #83                 // Method java/lang/String.substring:(II)Ljava/lang/String;
      60: astore_3
      61: aload_3
      62: bipush        46
      64: invokevirtual #102                // Method java/lang/String.lastIndexOf:(I)I
      67: istore        4
      69: iload         4
      71: iconst_m1
      72: if_icmpne     77
      75: aconst_null
      76: areturn
      77: aload_3
      78: iconst_0
      79: iload         4
      81: invokevirtual #83                 // Method java/lang/String.substring:(II)Ljava/lang/String;
      84: astore        5
      86: aload         5
      88: bipush        47
      90: bipush        46
      92: invokevirtual #105                // Method java/lang/String.replace:(CC)Ljava/lang/String;
      95: areturn

  private java.util.List<java.net.URL> findCandidates(java.lang.String);
    Code:
       0: ldc           #8                  // class org/springframework/boot/diagnostics/analyzer/NoSuchMethodFailureAnalyzer
       2: invokevirtual #109                // Method java/lang/Class.getClassLoader:()Ljava/lang/ClassLoader;
       5: aload_1
       6: invokestatic  #115                // Method org/springframework/util/ClassUtils.convertClassNameToResourcePath:(Ljava/lang/String;)Ljava/lang/String;
       9: invokedynamic #120,  0            // InvokeDynamic #0:makeConcatWithConstants:(Ljava/lang/String;)Ljava/lang/String;
      14: invokevirtual #123                // Method java/lang/ClassLoader.getResources:(Ljava/lang/String;)Ljava/util/Enumeration;
      17: invokestatic  #129                // Method java/util/Collections.list:(Ljava/util/Enumeration;)Ljava/util/ArrayList;
      20: areturn
      21: astore_2
      22: aconst_null
      23: areturn
    Exception table:
       from    to  target type
           0    20    21   Class java/lang/Throwable

  private java.lang.Class<?> load(java.lang.String);
    Code:
       0: aload_1
       1: iconst_0
       2: aload_0
       3: invokevirtual #137                // Method java/lang/Object.getClass:()Ljava/lang/Class;
       6: invokevirtual #109                // Method java/lang/Class.getClassLoader:()Ljava/lang/ClassLoader;
       9: invokestatic  #143                // Method java/lang/Class.forName:(Ljava/lang/String;ZLjava/lang/ClassLoader;)Ljava/lang/Class;
      12: areturn
      13: astore_2
      14: aconst_null
      15: areturn
    Exception table:
       from    to  target type
           0    12    13   Class java/lang/Throwable

  private java.util.List<org.springframework.boot.diagnostics.analyzer.NoSuchMethodFailureAnalyzer$ClassDescriptor> getTypeHierarchy(java.lang.Class<?>);
    Code:
       0: new           #147                // class java/util/ArrayList
       3: dup
       4: invokespecial #149                // Method java/util/ArrayList."<init>":()V
       7: astore_2
       8: aload_1
       9: ifnull        57
      12: aload_1
      13: ldc           #138                // class java/lang/Object
      15: invokevirtual #150                // Method java/lang/Object.equals:(Ljava/lang/Object;)Z
      18: ifne          57
      21: aload_2
      22: new           #154                // class org/springframework/boot/diagnostics/analyzer/NoSuchMethodFailureAnalyzer$ClassDescriptor
      25: dup
      26: aload_1
      27: invokevirtual #156                // Method java/lang/Class.getCanonicalName:()Ljava/lang/String;
      30: aload_1
      31: invokevirtual #159                // Method java/lang/Class.getProtectionDomain:()Ljava/security/ProtectionDomain;
      34: invokevirtual #163                // Method java/security/ProtectionDomain.getCodeSource:()Ljava/security/CodeSource;
      37: invokevirtual #169                // Method java/security/CodeSource.getLocation:()Ljava/net/URL;
      40: invokespecial #175                // Method org/springframework/boot/diagnostics/analyzer/NoSuchMethodFailureAnalyzer$ClassDescriptor."<init>":(Ljava/lang/String;Ljava/net/URL;)V
      43: invokeinterface #178,  2          // InterfaceMethod java/util/List.add:(Ljava/lang/Object;)Z
      48: pop
      49: aload_1
      50: invokevirtual #183                // Method java/lang/Class.getSuperclass:()Ljava/lang/Class;
      53: astore_1
      54: goto          8
      57: aload_2
      58: areturn
      59: astore_2
      60: aconst_null
      61: areturn
    Exception table:
       from    to  target type
           0    58    59   Class java/lang/Throwable

  private java.lang.String getDescription(org.springframework.boot.diagnostics.analyzer.NoSuchMethodFailureAnalyzer$NoSuchMethodDescriptor, org.springframework.boot.diagnostics.analyzer.NoSuchMethodFailureAnalyzer$NoSuchMethodDescriptor);
    Code:
       0: new           #186                // class java/io/StringWriter
       3: dup
       4: invokespecial #188                // Method java/io/StringWriter."<init>":()V
       7: astore_3
       8: new           #189                // class java/io/PrintWriter
      11: dup
      12: aload_3
      13: invokespecial #191                // Method java/io/PrintWriter."<init>":(Ljava/io/Writer;)V
      16: astore        4
      18: aload         4
      20: ldc           #194                // String An attempt was made to call a method that does not exist. The attempt was made from the following location:
      22: invokevirtual #196                // Method java/io/PrintWriter.println:(Ljava/lang/String;)V
      25: aload         4
      27: invokevirtual #200                // Method java/io/PrintWriter.println:()V
      30: aload         4
      32: ldc           #202                // String     %s%n
      34: iconst_1
      35: anewarray     #138                // class java/lang/Object
      38: dup
      39: iconst_0
      40: aload_1
      41: invokevirtual #204                // Method org/springframework/boot/diagnostics/analyzer/NoSuchMethodFailureAnalyzer$NoSuchMethodDescriptor.getErrorMessage:()Ljava/lang/String;
      44: aastore
      45: invokevirtual #207                // Method java/io/PrintWriter.printf:(Ljava/lang/String;[Ljava/lang/Object;)Ljava/io/PrintWriter;
      48: pop
      49: aload         4
      51: invokevirtual #200                // Method java/io/PrintWriter.println:()V
      54: aload         4
      56: ldc           #211                // String The following method did not exist:
      58: invokevirtual #196                // Method java/io/PrintWriter.println:(Ljava/lang/String;)V
      61: aload         4
      63: invokevirtual #200                // Method java/io/PrintWriter.println:()V
      66: aload         4
      68: ldc           #202                // String     %s%n
      70: iconst_1
      71: anewarray     #138                // class java/lang/Object
      74: dup
      75: iconst_0
      76: aload_2
      77: invokevirtual #204                // Method org/springframework/boot/diagnostics/analyzer/NoSuchMethodFailureAnalyzer$NoSuchMethodDescriptor.getErrorMessage:()Ljava/lang/String;
      80: aastore
      81: invokevirtual #207                // Method java/io/PrintWriter.printf:(Ljava/lang/String;[Ljava/lang/Object;)Ljava/io/PrintWriter;
      84: pop
      85: aload         4
      87: invokevirtual #200                // Method java/io/PrintWriter.println:()V
      90: aload_1
      91: invokevirtual #213                // Method org/springframework/boot/diagnostics/analyzer/NoSuchMethodFailureAnalyzer$NoSuchMethodDescriptor.getCandidateLocations:()Ljava/util/List;
      94: invokeinterface #217,  1          // InterfaceMethod java/util/List.size:()I
      99: iconst_1
     100: if_icmple     231
     103: aload         4
     105: ldc           #221                // String The calling method\'s class, %s, is available from the following locations:%n
     107: iconst_1
     108: anewarray     #138                // class java/lang/Object
     111: dup
     112: iconst_0
     113: aload_1
     114: invokevirtual #223                // Method org/springframework/boot/diagnostics/analyzer/NoSuchMethodFailureAnalyzer$NoSuchMethodDescriptor.getClassName:()Ljava/lang/String;
     117: aastore
     118: invokevirtual #207                // Method java/io/PrintWriter.printf:(Ljava/lang/String;[Ljava/lang/Object;)Ljava/io/PrintWriter;
     121: pop
     122: aload         4
     124: invokevirtual #200                // Method java/io/PrintWriter.println:()V
     127: aload_1
     128: invokevirtual #213                // Method org/springframework/boot/diagnostics/analyzer/NoSuchMethodFailureAnalyzer$NoSuchMethodDescriptor.getCandidateLocations:()Ljava/util/List;
     131: invokeinterface #224,  1          // InterfaceMethod java/util/List.iterator:()Ljava/util/Iterator;
     136: astore        5
     138: aload         5
     140: invokeinterface #228,  1          // InterfaceMethod java/util/Iterator.hasNext:()Z
     145: ifeq          180
     148: aload         5
     150: invokeinterface #234,  1          // InterfaceMethod java/util/Iterator.next:()Ljava/lang/Object;
     155: checkcast     #238                // class java/net/URL
     158: astore        6
     160: aload         4
     162: ldc           #202                // String     %s%n
     164: iconst_1
     165: anewarray     #138                // class java/lang/Object
     168: dup
     169: iconst_0
     170: aload         6
     172: aastore
     173: invokevirtual #207                // Method java/io/PrintWriter.printf:(Ljava/lang/String;[Ljava/lang/Object;)Ljava/io/PrintWriter;
     176: pop
     177: goto          138
     180: aload         4
     182: invokevirtual #200                // Method java/io/PrintWriter.println:()V
     185: aload         4
     187: ldc           #240                // String The calling method\'s class was loaded from the following location:
     189: invokevirtual #196                // Method java/io/PrintWriter.println:(Ljava/lang/String;)V
     192: aload         4
     194: invokevirtual #200                // Method java/io/PrintWriter.println:()V
     197: aload         4
     199: ldc           #202                // String     %s%n
     201: iconst_1
     202: anewarray     #138                // class java/lang/Object
     205: dup
     206: iconst_0
     207: aload_1
     208: invokevirtual #242                // Method org/springframework/boot/diagnostics/analyzer/NoSuchMethodFailureAnalyzer$NoSuchMethodDescriptor.getTypeHierarchy:()Ljava/util/List;
     211: iconst_0
     212: invokeinterface #244,  2          // InterfaceMethod java/util/List.get:(I)Ljava/lang/Object;
     217: checkcast     #154                // class org/springframework/boot/diagnostics/analyzer/NoSuchMethodFailureAnalyzer$ClassDescriptor
     220: invokevirtual #248                // Method org/springframework/boot/diagnostics/analyzer/NoSuchMethodFailureAnalyzer$ClassDescriptor.getLocation:()Ljava/net/URL;
     223: aastore
     224: invokevirtual #207                // Method java/io/PrintWriter.printf:(Ljava/lang/String;[Ljava/lang/Object;)Ljava/io/PrintWriter;
     227: pop
     228: goto          280
     231: aload         4
     233: ldc           #249                // String The calling method\'s class, %s, was loaded from the following location:%n
     235: iconst_1
     236: anewarray     #138                // class java/lang/Object
     239: dup
     240: iconst_0
     241: aload_1
     242: invokevirtual #223                // Method org/springframework/boot/diagnostics/analyzer/NoSuchMethodFailureAnalyzer$NoSuchMethodDescriptor.getClassName:()Ljava/lang/String;
     245: aastore
     246: invokevirtual #207                // Method java/io/PrintWriter.printf:(Ljava/lang/String;[Ljava/lang/Object;)Ljava/io/PrintWriter;
     249: pop
     250: aload         4
     252: invokevirtual #200                // Method java/io/PrintWriter.println:()V
     255: aload         4
     257: ldc           #202                // String     %s%n
     259: iconst_1
     260: anewarray     #138                // class java/lang/Object
     263: dup
     264: iconst_0
     265: aload_1
     266: invokevirtual #213                // Method org/springframework/boot/diagnostics/analyzer/NoSuchMethodFailureAnalyzer$NoSuchMethodDescriptor.getCandidateLocations:()Ljava/util/List;
     269: iconst_0
     270: invokeinterface #244,  2          // InterfaceMethod java/util/List.get:(I)Ljava/lang/Object;
     275: aastore
     276: invokevirtual #207                // Method java/io/PrintWriter.printf:(Ljava/lang/String;[Ljava/lang/Object;)Ljava/io/PrintWriter;
     279: pop
     280: aload         4
     282: invokevirtual #200                // Method java/io/PrintWriter.println:()V
     285: aload         4
     287: ldc           #251                // String The called method\'s class, %s, is available from the following locations:%n
     289: iconst_1
     290: anewarray     #138                // class java/lang/Object
     293: dup
     294: iconst_0
     295: aload_2
     296: invokevirtual #223                // Method org/springframework/boot/diagnostics/analyzer/NoSuchMethodFailureAnalyzer$NoSuchMethodDescriptor.getClassName:()Ljava/lang/String;
     299: aastore
     300: invokevirtual #207                // Method java/io/PrintWriter.printf:(Ljava/lang/String;[Ljava/lang/Object;)Ljava/io/PrintWriter;
     303: pop
     304: aload         4
     306: invokevirtual #200                // Method java/io/PrintWriter.println:()V
     309: aload_2
     310: invokevirtual #213                // Method org/springframework/boot/diagnostics/analyzer/NoSuchMethodFailureAnalyzer$NoSuchMethodDescriptor.getCandidateLocations:()Ljava/util/List;
     313: invokeinterface #224,  1          // InterfaceMethod java/util/List.iterator:()Ljava/util/Iterator;
     318: astore        5
     320: aload         5
     322: invokeinterface #228,  1          // InterfaceMethod java/util/Iterator.hasNext:()Z
     327: ifeq          362
     330: aload         5
     332: invokeinterface #234,  1          // InterfaceMethod java/util/Iterator.next:()Ljava/lang/Object;
     337: checkcast     #238                // class java/net/URL
     340: astore        6
     342: aload         4
     344: ldc           #202                // String     %s%n
     346: iconst_1
     347: anewarray     #138                // class java/lang/Object
     350: dup
     351: iconst_0
     352: aload         6
     354: aastore
     355: invokevirtual #207                // Method java/io/PrintWriter.printf:(Ljava/lang/String;[Ljava/lang/Object;)Ljava/io/PrintWriter;
     358: pop
     359: goto          320
     362: aload         4
     364: invokevirtual #200                // Method java/io/PrintWriter.println:()V
     367: aload         4
     369: ldc           #253                // String The called method\'s class hierarchy was loaded from the following locations:
     371: invokevirtual #196                // Method java/io/PrintWriter.println:(Ljava/lang/String;)V
     374: aload         4
     376: invokevirtual #200                // Method java/io/PrintWriter.println:()V
     379: aload_2
     380: invokevirtual #242                // Method org/springframework/boot/diagnostics/analyzer/NoSuchMethodFailureAnalyzer$NoSuchMethodDescriptor.getTypeHierarchy:()Ljava/util/List;
     383: invokeinterface #224,  1          // InterfaceMethod java/util/List.iterator:()Ljava/util/Iterator;
     388: astore        5
     390: aload         5
     392: invokeinterface #228,  1          // InterfaceMethod java/util/Iterator.hasNext:()Z
     397: ifeq          443
     400: aload         5
     402: invokeinterface #234,  1          // InterfaceMethod java/util/Iterator.next:()Ljava/lang/Object;
     407: checkcast     #154                // class org/springframework/boot/diagnostics/analyzer/NoSuchMethodFailureAnalyzer$ClassDescriptor
     410: astore        6
     412: aload         4
     414: ldc           #255                // String     %s: %s%n
     416: iconst_2
     417: anewarray     #138                // class java/lang/Object
     420: dup
     421: iconst_0
     422: aload         6
     424: invokevirtual #257                // Method org/springframework/boot/diagnostics/analyzer/NoSuchMethodFailureAnalyzer$ClassDescriptor.getName:()Ljava/lang/String;
     427: aastore
     428: dup
     429: iconst_1
     430: aload         6
     432: invokevirtual #248                // Method org/springframework/boot/diagnostics/analyzer/NoSuchMethodFailureAnalyzer$ClassDescriptor.getLocation:()Ljava/net/URL;
     435: aastore
     436: invokevirtual #207                // Method java/io/PrintWriter.printf:(Ljava/lang/String;[Ljava/lang/Object;)Ljava/io/PrintWriter;
     439: pop
     440: goto          390
     443: aload_3
     444: invokevirtual #260                // Method java/io/StringWriter.toString:()Ljava/lang/String;
     447: areturn

  private java.lang.String getAction(org.springframework.boot.diagnostics.analyzer.NoSuchMethodFailureAnalyzer$NoSuchMethodDescriptor, org.springframework.boot.diagnostics.analyzer.NoSuchMethodFailureAnalyzer$NoSuchMethodDescriptor);
    Code:
       0: aload_1
       1: invokevirtual #223                // Method org/springframework/boot/diagnostics/analyzer/NoSuchMethodFailureAnalyzer$NoSuchMethodDescriptor.getClassName:()Ljava/lang/String;
       4: aload_2
       5: invokevirtual #223                // Method org/springframework/boot/diagnostics/analyzer/NoSuchMethodFailureAnalyzer$NoSuchMethodDescriptor.getClassName:()Ljava/lang/String;
       8: invokevirtual #261                // Method java/lang/String.equals:(Ljava/lang/Object;)Z
      11: ifeq          24
      14: aload_2
      15: invokevirtual #223                // Method org/springframework/boot/diagnostics/analyzer/NoSuchMethodFailureAnalyzer$NoSuchMethodDescriptor.getClassName:()Ljava/lang/String;
      18: invokedynamic #262,  0            // InvokeDynamic #1:makeConcatWithConstants:(Ljava/lang/String;)Ljava/lang/String;
      23: areturn
      24: aload_1
      25: invokevirtual #223                // Method org/springframework/boot/diagnostics/analyzer/NoSuchMethodFailureAnalyzer$NoSuchMethodDescriptor.getClassName:()Ljava/lang/String;
      28: aload_2
      29: invokevirtual #223                // Method org/springframework/boot/diagnostics/analyzer/NoSuchMethodFailureAnalyzer$NoSuchMethodDescriptor.getClassName:()Ljava/lang/String;
      32: invokedynamic #263,  0            // InvokeDynamic #2:makeConcatWithConstants:(Ljava/lang/String;Ljava/lang/String;)Ljava/lang/String;
      37: areturn

  protected org.springframework.boot.diagnostics.FailureAnalysis analyze(java.lang.Throwable, java.lang.Throwable);
    Code:
       0: aload_0
       1: aload_1
       2: aload_2
       3: checkcast     #14                 // class java/lang/NoSuchMethodError
       6: invokevirtual #266                // Method analyze:(Ljava/lang/Throwable;Ljava/lang/NoSuchMethodError;)Lorg/springframework/boot/diagnostics/FailureAnalysis;
       9: areturn
}
