Compiled from "NoUniqueBeanDefinitionFailureAnalyzer.java"
class org.springframework.boot.diagnostics.analyzer.NoUniqueBeanDefinitionFailureAnalyzer extends org.springframework.boot.diagnostics.analyzer.AbstractInjectionFailureAnalyzer<org.springframework.beans.factory.NoUniqueBeanDefinitionException> {
  private final org.springframework.beans.factory.config.ConfigurableBeanFactory beanFactory;

  org.springframework.boot.diagnostics.analyzer.NoUniqueBeanDefinitionFailureAnalyzer(org.springframework.beans.factory.BeanFactory);
    Code:
       0: aload_0
       1: invokespecial #1                  // Method org/springframework/boot/diagnostics/analyzer/AbstractInjectionFailureAnalyzer."<init>":()V
       4: ldc           #7                  // class org/springframework/beans/factory/config/ConfigurableBeanFactory
       6: aload_1
       7: invokestatic  #9                  // Method org/springframework/util/Assert.isInstanceOf:(Ljava/lang/Class;Ljava/lang/Object;)V
      10: aload_0
      11: aload_1
      12: checkcast     #7                  // class org/springframework/beans/factory/config/ConfigurableBeanFactory
      15: putfield      #15                 // Field beanFactory:Lorg/springframework/beans/factory/config/ConfigurableBeanFactory;
      18: return

  protected org.springframework.boot.diagnostics.FailureAnalysis analyze(java.lang.Throwable, org.springframework.beans.factory.NoUniqueBeanDefinitionException, java.lang.String);
    Code:
       0: aload_3
       1: ifnonnull     6
       4: aconst_null
       5: areturn
       6: aload_0
       7: aload_2
       8: invokevirtual #21                 // Method extractBeanNames:(Lorg/springframework/beans/factory/NoUniqueBeanDefinitionException;)[Ljava/lang/String;
      11: astore        4
      13: aload         4
      15: ifnonnull     20
      18: aconst_null
      19: areturn
      20: new           #25                 // class java/lang/StringBuilder
      23: dup
      24: invokespecial #27                 // Method java/lang/StringBuilder."<init>":()V
      27: astore        5
      29: aload         5
      31: ldc           #28                 // String %s required a single bean, but %d were found:%n
      33: iconst_2
      34: anewarray     #30                 // class java/lang/Object
      37: dup
      38: iconst_0
      39: aload_3
      40: aastore
      41: dup
      42: iconst_1
      43: aload         4
      45: arraylength
      46: invokestatic  #32                 // Method java/lang/Integer.valueOf:(I)Ljava/lang/Integer;
      49: aastore
      50: invokestatic  #38                 // Method java/lang/String.format:(Ljava/lang/String;[Ljava/lang/Object;)Ljava/lang/String;
      53: invokevirtual #44                 // Method java/lang/StringBuilder.append:(Ljava/lang/String;)Ljava/lang/StringBuilder;
      56: pop
      57: aload         4
      59: astore        6
      61: aload         6
      63: arraylength
      64: istore        7
      66: iconst_0
      67: istore        8
      69: iload         8
      71: iload         7
      73: if_icmpge     97
      76: aload         6
      78: iload         8
      80: aaload
      81: astore        9
      83: aload_0
      84: aload         5
      86: aload         9
      88: invokevirtual #48                 // Method buildMessage:(Ljava/lang/StringBuilder;Ljava/lang/String;)V
      91: iinc          8, 1
      94: goto          69
      97: new           #52                 // class org/springframework/boot/diagnostics/FailureAnalysis
     100: dup
     101: aload         5
     103: invokevirtual #54                 // Method java/lang/StringBuilder.toString:()Ljava/lang/String;
     106: ldc           #58                 // String Consider marking one of the beans as @Primary, updating the consumer to accept multiple beans, or using @Qualifier to identify the bean that should be consumed
     108: aload_2
     109: invokespecial #60                 // Method org/springframework/boot/diagnostics/FailureAnalysis."<init>":(Ljava/lang/String;Ljava/lang/String;Ljava/lang/Throwable;)V
     112: areturn

  private void buildMessage(java.lang.StringBuilder, java.lang.String);
    Code:
       0: aload_0
       1: getfield      #15                 // Field beanFactory:Lorg/springframework/beans/factory/config/ConfigurableBeanFactory;
       4: aload_2
       5: invokeinterface #63,  2           // InterfaceMethod org/springframework/beans/factory/config/ConfigurableBeanFactory.getMergedBeanDefinition:(Ljava/lang/String;)Lorg/springframework/beans/factory/config/BeanDefinition;
      10: astore_3
      11: aload_1
      12: aload_0
      13: aload_2
      14: aload_3
      15: invokevirtual #67                 // Method getDefinitionDescription:(Ljava/lang/String;Lorg/springframework/beans/factory/config/BeanDefinition;)Ljava/lang/String;
      18: invokevirtual #44                 // Method java/lang/StringBuilder.append:(Ljava/lang/String;)Ljava/lang/StringBuilder;
      21: pop
      22: goto          44
      25: astore_3
      26: aload_1
      27: ldc           #73                 // String \t- %s: a programmatically registered singleton
      29: iconst_1
      30: anewarray     #30                 // class java/lang/Object
      33: dup
      34: iconst_0
      35: aload_2
      36: aastore
      37: invokestatic  #38                 // Method java/lang/String.format:(Ljava/lang/String;[Ljava/lang/Object;)Ljava/lang/String;
      40: invokevirtual #44                 // Method java/lang/StringBuilder.append:(Ljava/lang/String;)Ljava/lang/StringBuilder;
      43: pop
      44: return
    Exception table:
       from    to  target type
           0    22    25   Class org/springframework/beans/factory/NoSuchBeanDefinitionException

  private java.lang.String getDefinitionDescription(java.lang.String, org.springframework.beans.factory.config.BeanDefinition);
    Code:
       0: aload_2
       1: invokeinterface #75,  1           // InterfaceMethod org/springframework/beans/factory/config/BeanDefinition.getFactoryMethodName:()Ljava/lang/String;
       6: invokestatic  #80                 // Method org/springframework/util/StringUtils.hasText:(Ljava/lang/String;)Z
       9: ifeq          43
      12: ldc           #86                 // String \t- %s: defined by method \'%s\' in %s%n
      14: iconst_3
      15: anewarray     #30                 // class java/lang/Object
      18: dup
      19: iconst_0
      20: aload_1
      21: aastore
      22: dup
      23: iconst_1
      24: aload_2
      25: invokeinterface #75,  1           // InterfaceMethod org/springframework/beans/factory/config/BeanDefinition.getFactoryMethodName:()Ljava/lang/String;
      30: aastore
      31: dup
      32: iconst_2
      33: aload_0
      34: aload_2
      35: invokevirtual #88                 // Method getResourceDescription:(Lorg/springframework/beans/factory/config/BeanDefinition;)Ljava/lang/String;
      38: aastore
      39: invokestatic  #38                 // Method java/lang/String.format:(Ljava/lang/String;[Ljava/lang/Object;)Ljava/lang/String;
      42: areturn
      43: ldc           #92                 // String \t- %s: defined in %s%n
      45: iconst_2
      46: anewarray     #30                 // class java/lang/Object
      49: dup
      50: iconst_0
      51: aload_1
      52: aastore
      53: dup
      54: iconst_1
      55: aload_0
      56: aload_2
      57: invokevirtual #88                 // Method getResourceDescription:(Lorg/springframework/beans/factory/config/BeanDefinition;)Ljava/lang/String;
      60: aastore
      61: invokestatic  #38                 // Method java/lang/String.format:(Ljava/lang/String;[Ljava/lang/Object;)Ljava/lang/String;
      64: areturn

  private java.lang.String getResourceDescription(org.springframework.beans.factory.config.BeanDefinition);
    Code:
       0: aload_1
       1: invokeinterface #94,  1           // InterfaceMethod org/springframework/beans/factory/config/BeanDefinition.getResourceDescription:()Ljava/lang/String;
       6: astore_2
       7: aload_2
       8: ifnull        15
      11: aload_2
      12: goto          17
      15: ldc           #96                 // String unknown location
      17: areturn

  private java.lang.String[] extractBeanNames(org.springframework.beans.factory.NoUniqueBeanDefinitionException);
    Code:
       0: aload_1
       1: invokevirtual #98                 // Method org/springframework/beans/factory/NoUniqueBeanDefinitionException.getMessage:()Ljava/lang/String;
       4: ldc           #103                // String but found
       6: invokevirtual #105                // Method java/lang/String.contains:(Ljava/lang/CharSequence;)Z
       9: ifeq          37
      12: aload_1
      13: invokevirtual #98                 // Method org/springframework/beans/factory/NoUniqueBeanDefinitionException.getMessage:()Ljava/lang/String;
      16: aload_1
      17: invokevirtual #98                 // Method org/springframework/beans/factory/NoUniqueBeanDefinitionException.getMessage:()Ljava/lang/String;
      20: bipush        58
      22: invokevirtual #109                // Method java/lang/String.lastIndexOf:(I)I
      25: iconst_1
      26: iadd
      27: invokevirtual #113                // Method java/lang/String.substring:(I)Ljava/lang/String;
      30: invokevirtual #117                // Method java/lang/String.trim:()Ljava/lang/String;
      33: invokestatic  #120                // Method org/springframework/util/StringUtils.commaDelimitedListToStringArray:(Ljava/lang/String;)[Ljava/lang/String;
      36: areturn
      37: aconst_null
      38: areturn

  protected org.springframework.boot.diagnostics.FailureAnalysis analyze(java.lang.Throwable, java.lang.Throwable, java.lang.String);
    Code:
       0: aload_0
       1: aload_1
       2: aload_2
       3: checkcast     #99                 // class org/springframework/beans/factory/NoUniqueBeanDefinitionException
       6: aload_3
       7: invokevirtual #124                // Method analyze:(Ljava/lang/Throwable;Lorg/springframework/beans/factory/NoUniqueBeanDefinitionException;Ljava/lang/String;)Lorg/springframework/boot/diagnostics/FailureAnalysis;
      10: areturn
}
