Compiled from "ValidationExceptionFailureAnalyzer.java"
class org.springframework.boot.diagnostics.analyzer.ValidationExceptionFailureAnalyzer extends org.springframework.boot.diagnostics.AbstractFailureAnalyzer<jakarta.validation.ValidationException> {
  private static final java.lang.String JAVAX_MISSING_IMPLEMENTATION_MESSAGE;

  private static final java.lang.String JAKARTA_MISSING_IMPLEMENTATION_MESSAGE;

  org.springframework.boot.diagnostics.analyzer.ValidationExceptionFailureAnalyzer();
    Code:
       0: aload_0
       1: invokespecial #1                  // Method org/springframework/boot/diagnostics/AbstractFailureAnalyzer."<init>":()V
       4: return

  protected org.springframework.boot.diagnostics.FailureAnalysis analyze(java.lang.Throwable, jakarta.validation.ValidationException);
    Code:
       0: aload_2
       1: invokevirtual #7                  // Method jakarta/validation/ValidationException.getMessage:()Ljava/lang/String;
       4: ldc           #15                 // String Unable to create a Configuration, because no Bean Validation provider could be found
       6: invokevirtual #17                 // Method java/lang/String.startsWith:(Ljava/lang/String;)Z
       9: ifne          24
      12: aload_2
      13: invokevirtual #7                  // Method jakarta/validation/ValidationException.getMessage:()Ljava/lang/String;
      16: ldc           #23                 // String Unable to create a Configuration, because no Jakarta Bean Validation provider could be found
      18: invokevirtual #17                 // Method java/lang/String.startsWith:(Ljava/lang/String;)Z
      21: ifeq          37
      24: new           #25                 // class org/springframework/boot/diagnostics/FailureAnalysis
      27: dup
      28: ldc           #27                 // String The Bean Validation API is on the classpath but no implementation could be found
      30: ldc           #29                 // String Add an implementation, such as Hibernate Validator, to the classpath
      32: aload_2
      33: invokespecial #31                 // Method org/springframework/boot/diagnostics/FailureAnalysis."<init>":(Ljava/lang/String;Ljava/lang/String;Ljava/lang/Throwable;)V
      36: areturn
      37: aconst_null
      38: areturn

  protected org.springframework.boot.diagnostics.FailureAnalysis analyze(java.lang.Throwable, java.lang.Throwable);
    Code:
       0: aload_0
       1: aload_1
       2: aload_2
       3: checkcast     #8                  // class jakarta/validation/ValidationException
       6: invokevirtual #34                 // Method analyze:(Ljava/lang/Throwable;Ljakarta/validation/ValidationException;)Lorg/springframework/boot/diagnostics/FailureAnalysis;
       9: areturn
}
