Compiled from "DubboSwaggerApiListingResource.java"
public class org.apache.dubbo.rpc.protocol.rest.integration.swagger.DubboSwaggerApiListingResource extends io.swagger.jaxrs.listing.BaseApiListingResource implements org.apache.dubbo.rpc.protocol.rest.integration.swagger.DubboSwaggerService {
  javax.servlet.ServletContext context;

  public org.apache.dubbo.rpc.protocol.rest.integration.swagger.DubboSwaggerApiListingResource();
    Code:
       0: aload_0
       1: invokespecial #1                  // Method io/swagger/jaxrs/listing/BaseApiListingResource."<init>":()V
       4: return

  public javax.ws.rs.core.Response getListingJson(javax.ws.rs.core.Application, javax.servlet.ServletConfig, javax.ws.rs.core.HttpHeaders, javax.ws.rs.core.UriInfo) throws com.fasterxml.jackson.core.JsonProcessingException;
    Code:
       0: aload_0
       1: aload_1
       2: aload_0
       3: getfield      #2                  // Field context:Ljavax/servlet/ServletContext;
       6: aload_2
       7: aload_3
       8: aload         4
      10: invokevirtual #3                  // Method getListingJsonResponse:(Ljavax/ws/rs/core/Application;Ljavax/servlet/ServletContext;Ljavax/servlet/ServletConfig;Ljavax/ws/rs/core/HttpHeaders;Ljavax/ws/rs/core/UriInfo;)Ljavax/ws/rs/core/Response;
      13: astore        5
      15: aload         5
      17: invokevirtual #4                  // Method javax/ws/rs/core/Response.getHeaders:()Ljavax/ws/rs/core/MultivaluedMap;
      20: ldc           #5                  // String Access-Control-Allow-Origin
      22: ldc           #6                  // String *
      24: invokeinterface #7,  3            // InterfaceMethod javax/ws/rs/core/MultivaluedMap.add:(Ljava/lang/Object;Ljava/lang/Object;)V
      29: aload         5
      31: invokevirtual #4                  // Method javax/ws/rs/core/Response.getHeaders:()Ljavax/ws/rs/core/MultivaluedMap;
      34: ldc           #8                  // String Access-Control-Allow-Headers
      36: ldc           #9                  // String x-requested-with, ssi-token
      38: invokeinterface #7,  3            // InterfaceMethod javax/ws/rs/core/MultivaluedMap.add:(Ljava/lang/Object;Ljava/lang/Object;)V
      43: aload         5
      45: invokevirtual #4                  // Method javax/ws/rs/core/Response.getHeaders:()Ljavax/ws/rs/core/MultivaluedMap;
      48: ldc           #10                 // String Access-Control-Max-Age
      50: ldc           #11                 // String 3600
      52: invokeinterface #7,  3            // InterfaceMethod javax/ws/rs/core/MultivaluedMap.add:(Ljava/lang/Object;Ljava/lang/Object;)V
      57: aload         5
      59: invokevirtual #4                  // Method javax/ws/rs/core/Response.getHeaders:()Ljavax/ws/rs/core/MultivaluedMap;
      62: ldc           #12                 // String Access-Control-Allow-Methods
      64: ldc           #13                 // String GET,POST,PUT,DELETE,OPTIONS
      66: invokeinterface #7,  3            // InterfaceMethod javax/ws/rs/core/MultivaluedMap.add:(Ljava/lang/Object;Ljava/lang/Object;)V
      71: aload         5
      73: areturn
}
