Compiled from "AtomicLongContainer.java"
public class org.apache.dubbo.metrics.model.container.AtomicLongContainer extends org.apache.dubbo.metrics.model.container.LongContainer<java.util.concurrent.atomic.AtomicLong> {
  public org.apache.dubbo.metrics.model.container.AtomicLongContainer(org.apache.dubbo.metrics.model.key.MetricsKeyWrapper);
    Code:
       0: aload_0
       1: aload_1
       2: invokedynamic #1,  0              // InvokeDynamic #0:get:()Ljava/util/function/Supplier;
       7: invokedynamic #2,  0              // InvokeDynamic #1:accept:()Ljava/util/function/BiConsumer;
      12: invokespecial #3                  // Method org/apache/dubbo/metrics/model/container/LongContainer."<init>":(Lorg/apache/dubbo/metrics/model/key/MetricsKeyWrapper;Ljava/util/function/Supplier;Ljava/util/function/BiConsumer;)V
      15: return

  public org.apache.dubbo.metrics.model.container.AtomicLongContainer(org.apache.dubbo.metrics.model.key.MetricsKeyWrapper, java.util.function.BiConsumer<java.lang.Long, java.util.concurrent.atomic.AtomicLong>);
    Code:
       0: aload_0
       1: aload_1
       2: invokedynamic #1,  0              // InvokeDynamic #0:get:()Ljava/util/function/Supplier;
       7: aload_2
       8: invokespecial #3                  // Method org/apache/dubbo/metrics/model/container/LongContainer."<init>":(Lorg/apache/dubbo/metrics/model/key/MetricsKeyWrapper;Ljava/util/function/Supplier;Ljava/util/function/BiConsumer;)V
      11: return

  private static void lambda$new$0(java.lang.Long, java.util.concurrent.atomic.AtomicLong);
    Code:
       0: aload_1
       1: aload_0
       2: invokevirtual #4                  // Method java/lang/Long.longValue:()J
       5: invokevirtual #5                  // Method java/util/concurrent/atomic/AtomicLong.set:(J)V
       8: return
}
