Compiled from "LongContainer.java"
public class org.apache.dubbo.metrics.model.container.LongContainer<N extends java.lang.Number> extends java.util.concurrent.ConcurrentHashMap<java.lang.String, N> {
  private final transient org.apache.dubbo.metrics.model.key.MetricsKeyWrapper metricsKeyWrapper;

  private final transient java.util.function.Function<java.lang.String, N> initFunc;

  private final transient java.util.function.BiConsumer<java.lang.Long, N> consumerFunc;

  private transient java.util.function.Function<java.lang.String, java.lang.Long> valueSupplier;

  public org.apache.dubbo.metrics.model.container.LongContainer(org.apache.dubbo.metrics.model.key.MetricsKeyWrapper, java.util.function.Supplier<N>, java.util.function.BiConsumer<java.lang.Long, N>);
    Code:
       0: aload_0
       1: invokespecial #1                  // Method java/util/concurrent/ConcurrentHashMap."<init>":()V
       4: aload_0
       5: aload_1
       6: putfield      #2                  // Field metricsKeyWrapper:Lorg/apache/dubbo/metrics/model/key/MetricsKeyWrapper;
       9: aload_0
      10: aload_2
      11: invokedynamic #3,  0              // InvokeDynamic #0:apply:(Ljava/util/function/Supplier;)Ljava/util/function/Function;
      16: putfield      #4                  // Field initFunc:Ljava/util/function/Function;
      19: aload_0
      20: aload_3
      21: putfield      #5                  // Field consumerFunc:Ljava/util/function/BiConsumer;
      24: aload_0
      25: aload_0
      26: invokedynamic #6,  0              // InvokeDynamic #1:apply:(Lorg/apache/dubbo/metrics/model/container/LongContainer;)Ljava/util/function/Function;
      31: putfield      #7                  // Field valueSupplier:Ljava/util/function/Function;
      34: return

  public boolean specifyType(java.lang.String);
    Code:
       0: aload_1
       1: aload_0
       2: invokevirtual #8                  // Method getMetricsKeyWrapper:()Lorg/apache/dubbo/metrics/model/key/MetricsKeyWrapper;
       5: invokevirtual #9                  // Method org/apache/dubbo/metrics/model/key/MetricsKeyWrapper.getType:()Ljava/lang/String;
       8: invokevirtual #10                 // Method java/lang/String.equals:(Ljava/lang/Object;)Z
      11: ireturn

  public org.apache.dubbo.metrics.model.key.MetricsKeyWrapper getMetricsKeyWrapper();
    Code:
       0: aload_0
       1: getfield      #2                  // Field metricsKeyWrapper:Lorg/apache/dubbo/metrics/model/key/MetricsKeyWrapper;
       4: areturn

  public boolean isKeyWrapper(org.apache.dubbo.metrics.model.key.MetricsKey, java.lang.String);
    Code:
       0: aload_0
       1: getfield      #2                  // Field metricsKeyWrapper:Lorg/apache/dubbo/metrics/model/key/MetricsKeyWrapper;
       4: aload_1
       5: aload_2
       6: invokevirtual #11                 // Method org/apache/dubbo/metrics/model/key/MetricsKeyWrapper.isKey:(Lorg/apache/dubbo/metrics/model/key/MetricsKey;Ljava/lang/String;)Z
       9: ireturn

  public java.util.function.Function<java.lang.String, N> getInitFunc();
    Code:
       0: aload_0
       1: getfield      #4                  // Field initFunc:Ljava/util/function/Function;
       4: areturn

  public java.util.function.BiConsumer<java.lang.Long, N> getConsumerFunc();
    Code:
       0: aload_0
       1: getfield      #5                  // Field consumerFunc:Ljava/util/function/BiConsumer;
       4: areturn

  public java.util.function.Function<java.lang.String, java.lang.Long> getValueSupplier();
    Code:
       0: aload_0
       1: getfield      #7                  // Field valueSupplier:Ljava/util/function/Function;
       4: areturn

  public void setValueSupplier(java.util.function.Function<java.lang.String, java.lang.Long>);
    Code:
       0: aload_0
       1: aload_1
       2: putfield      #7                  // Field valueSupplier:Ljava/util/function/Function;
       5: return

  public java.lang.String toString();
    Code:
       0: new           #12                 // class java/lang/StringBuilder
       3: dup
       4: invokespecial #13                 // Method java/lang/StringBuilder."<init>":()V
       7: ldc           #14                 // String LongContainer{metricsKeyWrapper=
       9: invokevirtual #15                 // Method java/lang/StringBuilder.append:(Ljava/lang/String;)Ljava/lang/StringBuilder;
      12: aload_0
      13: getfield      #2                  // Field metricsKeyWrapper:Lorg/apache/dubbo/metrics/model/key/MetricsKeyWrapper;
      16: invokevirtual #16                 // Method java/lang/StringBuilder.append:(Ljava/lang/Object;)Ljava/lang/StringBuilder;
      19: bipush        125
      21: invokevirtual #17                 // Method java/lang/StringBuilder.append:(C)Ljava/lang/StringBuilder;
      24: invokevirtual #18                 // Method java/lang/StringBuilder.toString:()Ljava/lang/String;
      27: areturn

  public boolean equals(java.lang.Object);
    Code:
       0: aload_0
       1: aload_1
       2: if_acmpne     7
       5: iconst_1
       6: ireturn
       7: aload_1
       8: ifnull        22
      11: aload_0
      12: invokevirtual #19                 // Method java/lang/Object.getClass:()Ljava/lang/Class;
      15: aload_1
      16: invokevirtual #19                 // Method java/lang/Object.getClass:()Ljava/lang/Class;
      19: if_acmpeq     24
      22: iconst_0
      23: ireturn
      24: aload_0
      25: aload_1
      26: invokespecial #20                 // Method java/util/concurrent/ConcurrentHashMap.equals:(Ljava/lang/Object;)Z
      29: ifne          34
      32: iconst_0
      33: ireturn
      34: aload_1
      35: checkcast     #21                 // class org/apache/dubbo/metrics/model/container/LongContainer
      38: astore_2
      39: aload_0
      40: getfield      #2                  // Field metricsKeyWrapper:Lorg/apache/dubbo/metrics/model/key/MetricsKeyWrapper;
      43: aload_2
      44: getfield      #2                  // Field metricsKeyWrapper:Lorg/apache/dubbo/metrics/model/key/MetricsKeyWrapper;
      47: invokevirtual #22                 // Method org/apache/dubbo/metrics/model/key/MetricsKeyWrapper.equals:(Ljava/lang/Object;)Z
      50: ireturn

  public int hashCode();
    Code:
       0: aload_0
       1: invokespecial #23                 // Method java/util/concurrent/ConcurrentHashMap.hashCode:()I
       4: istore_1
       5: bipush        31
       7: iload_1
       8: imul
       9: aload_0
      10: getfield      #2                  // Field metricsKeyWrapper:Lorg/apache/dubbo/metrics/model/key/MetricsKeyWrapper;
      13: invokevirtual #24                 // Method org/apache/dubbo/metrics/model/key/MetricsKeyWrapper.hashCode:()I
      16: iadd
      17: istore_1
      18: iload_1
      19: ireturn

  private java.lang.Long lambda$new$1(java.lang.String);
    Code:
       0: aload_0
       1: aload_1
       2: invokevirtual #25                 // Method get:(Ljava/lang/Object;)Ljava/lang/Object;
       5: checkcast     #26                 // class java/lang/Number
       8: invokevirtual #27                 // Method java/lang/Number.longValue:()J
      11: invokestatic  #28                 // Method java/lang/Long.valueOf:(J)Ljava/lang/Long;
      14: areturn

  private static java.lang.Number lambda$new$0(java.util.function.Supplier, java.lang.String);
    Code:
       0: aload_0
       1: invokeinterface #29,  1           // InterfaceMethod java/util/function/Supplier.get:()Ljava/lang/Object;
       6: checkcast     #26                 // class java/lang/Number
       9: areturn
}
