Compiled from "ByQuadrantReader.java"
public final class com.google.zxing.multi.ByQuadrantReader implements com.google.zxing.Reader {
  private final com.google.zxing.Reader delegate;

  public com.google.zxing.multi.ByQuadrantReader(com.google.zxing.Reader);
    Code:
       0: aload_0
       1: invokespecial #1                  // Method java/lang/Object."<init>":()V
       4: aload_0
       5: aload_1
       6: putfield      #2                  // Field delegate:Lcom/google/zxing/Reader;
       9: return

  public com.google.zxing.Result decode(com.google.zxing.BinaryBitmap) throws com.google.zxing.NotFoundException, com.google.zxing.ChecksumException, com.google.zxing.FormatException;
    Code:
       0: aload_0
       1: aload_1
       2: aconst_null
       3: invokevirtual #3                  // Method decode:(Lcom/google/zxing/BinaryBitmap;Ljava/util/Map;)Lcom/google/zxing/Result;
       6: areturn

  public com.google.zxing.Result decode(com.google.zxing.BinaryBitmap, java.util.Map<com.google.zxing.DecodeHintType, ?>) throws com.google.zxing.NotFoundException, com.google.zxing.ChecksumException, com.google.zxing.FormatException;
    Code:
       0: aload_1
       1: invokevirtual #4                  // Method com/google/zxing/BinaryBitmap.getWidth:()I
       4: istore_3
       5: aload_1
       6: invokevirtual #5                  // Method com/google/zxing/BinaryBitmap.getHeight:()I
       9: istore        4
      11: iload_3
      12: iconst_2
      13: idiv
      14: istore        5
      16: iload         4
      18: iconst_2
      19: idiv
      20: istore        6
      22: aload_0
      23: getfield      #2                  // Field delegate:Lcom/google/zxing/Reader;
      26: aload_1
      27: iconst_0
      28: iconst_0
      29: iload         5
      31: iload         6
      33: invokevirtual #6                  // Method com/google/zxing/BinaryBitmap.crop:(IIII)Lcom/google/zxing/BinaryBitmap;
      36: aload_2
      37: invokeinterface #7,  3            // InterfaceMethod com/google/zxing/Reader.decode:(Lcom/google/zxing/BinaryBitmap;Ljava/util/Map;)Lcom/google/zxing/Result;
      42: areturn
      43: astore        7
      45: aload_0
      46: getfield      #2                  // Field delegate:Lcom/google/zxing/Reader;
      49: aload_1
      50: iload         5
      52: iconst_0
      53: iload         5
      55: iload         6
      57: invokevirtual #6                  // Method com/google/zxing/BinaryBitmap.crop:(IIII)Lcom/google/zxing/BinaryBitmap;
      60: aload_2
      61: invokeinterface #7,  3            // InterfaceMethod com/google/zxing/Reader.decode:(Lcom/google/zxing/BinaryBitmap;Ljava/util/Map;)Lcom/google/zxing/Result;
      66: astore        7
      68: aload         7
      70: invokevirtual #9                  // Method com/google/zxing/Result.getResultPoints:()[Lcom/google/zxing/ResultPoint;
      73: iload         5
      75: iconst_0
      76: invokestatic  #10                 // Method makeAbsolute:([Lcom/google/zxing/ResultPoint;II)V
      79: aload         7
      81: areturn
      82: astore        7
      84: aload_0
      85: getfield      #2                  // Field delegate:Lcom/google/zxing/Reader;
      88: aload_1
      89: iconst_0
      90: iload         6
      92: iload         5
      94: iload         6
      96: invokevirtual #6                  // Method com/google/zxing/BinaryBitmap.crop:(IIII)Lcom/google/zxing/BinaryBitmap;
      99: aload_2
     100: invokeinterface #7,  3            // InterfaceMethod com/google/zxing/Reader.decode:(Lcom/google/zxing/BinaryBitmap;Ljava/util/Map;)Lcom/google/zxing/Result;
     105: astore        7
     107: aload         7
     109: invokevirtual #9                  // Method com/google/zxing/Result.getResultPoints:()[Lcom/google/zxing/ResultPoint;
     112: iconst_0
     113: iload         6
     115: invokestatic  #10                 // Method makeAbsolute:([Lcom/google/zxing/ResultPoint;II)V
     118: aload         7
     120: areturn
     121: astore        7
     123: aload_0
     124: getfield      #2                  // Field delegate:Lcom/google/zxing/Reader;
     127: aload_1
     128: iload         5
     130: iload         6
     132: iload         5
     134: iload         6
     136: invokevirtual #6                  // Method com/google/zxing/BinaryBitmap.crop:(IIII)Lcom/google/zxing/BinaryBitmap;
     139: aload_2
     140: invokeinterface #7,  3            // InterfaceMethod com/google/zxing/Reader.decode:(Lcom/google/zxing/BinaryBitmap;Ljava/util/Map;)Lcom/google/zxing/Result;
     145: astore        7
     147: aload         7
     149: invokevirtual #9                  // Method com/google/zxing/Result.getResultPoints:()[Lcom/google/zxing/ResultPoint;
     152: iload         5
     154: iload         6
     156: invokestatic  #10                 // Method makeAbsolute:([Lcom/google/zxing/ResultPoint;II)V
     159: aload         7
     161: areturn
     162: astore        7
     164: iload         5
     166: iconst_2
     167: idiv
     168: istore        7
     170: iload         6
     172: iconst_2
     173: idiv
     174: istore        8
     176: aload_1
     177: iload         7
     179: iload         8
     181: iload         5
     183: iload         6
     185: invokevirtual #6                  // Method com/google/zxing/BinaryBitmap.crop:(IIII)Lcom/google/zxing/BinaryBitmap;
     188: astore        9
     190: aload_0
     191: getfield      #2                  // Field delegate:Lcom/google/zxing/Reader;
     194: aload         9
     196: aload_2
     197: invokeinterface #7,  3            // InterfaceMethod com/google/zxing/Reader.decode:(Lcom/google/zxing/BinaryBitmap;Ljava/util/Map;)Lcom/google/zxing/Result;
     202: astore        10
     204: aload         10
     206: invokevirtual #9                  // Method com/google/zxing/Result.getResultPoints:()[Lcom/google/zxing/ResultPoint;
     209: iload         7
     211: iload         8
     213: invokestatic  #10                 // Method makeAbsolute:([Lcom/google/zxing/ResultPoint;II)V
     216: aload         10
     218: areturn
    Exception table:
       from    to  target type
          22    42    43   Class com/google/zxing/NotFoundException
          45    81    82   Class com/google/zxing/NotFoundException
          84   120   121   Class com/google/zxing/NotFoundException
         123   161   162   Class com/google/zxing/NotFoundException

  public void reset();
    Code:
       0: aload_0
       1: getfield      #2                  // Field delegate:Lcom/google/zxing/Reader;
       4: invokeinterface #11,  1           // InterfaceMethod com/google/zxing/Reader.reset:()V
       9: return

  private static void makeAbsolute(com.google.zxing.ResultPoint[], int, int);
    Code:
       0: aload_0
       1: ifnull        54
       4: iconst_0
       5: istore_3
       6: iload_3
       7: aload_0
       8: arraylength
       9: if_icmpge     54
      12: aload_0
      13: iload_3
      14: aaload
      15: astore        4
      17: aload         4
      19: ifnull        48
      22: aload_0
      23: iload_3
      24: new           #12                 // class com/google/zxing/ResultPoint
      27: dup
      28: aload         4
      30: invokevirtual #13                 // Method com/google/zxing/ResultPoint.getX:()F
      33: iload_1
      34: i2f
      35: fadd
      36: aload         4
      38: invokevirtual #14                 // Method com/google/zxing/ResultPoint.getY:()F
      41: iload_2
      42: i2f
      43: fadd
      44: invokespecial #15                 // Method com/google/zxing/ResultPoint."<init>":(FF)V
      47: aastore
      48: iinc          3, 1
      51: goto          6
      54: return
}
