Compiled from "Curator5ZookeeperClient.java"
class org.apache.dubbo.remoting.zookeeper.curator5.Curator5ZookeeperClient$CuratorWatcherImpl implements org.apache.curator.framework.api.CuratorWatcher {
  private org.apache.curator.framework.CuratorFramework client;

  private volatile org.apache.dubbo.remoting.zookeeper.ChildListener childListener;

  private java.lang.String path;

  public org.apache.dubbo.remoting.zookeeper.curator5.Curator5ZookeeperClient$CuratorWatcherImpl(org.apache.curator.framework.CuratorFramework, org.apache.dubbo.remoting.zookeeper.ChildListener, java.lang.String);
    Code:
       0: aload_0
       1: invokespecial #1                  // Method java/lang/Object."<init>":()V
       4: aload_0
       5: aload_1
       6: putfield      #2                  // Field client:Lorg/apache/curator/framework/CuratorFramework;
       9: aload_0
      10: aload_2
      11: putfield      #3                  // Field childListener:Lorg/apache/dubbo/remoting/zookeeper/ChildListener;
      14: aload_0
      15: aload_3
      16: putfield      #4                  // Field path:Ljava/lang/String;
      19: return

  protected org.apache.dubbo.remoting.zookeeper.curator5.Curator5ZookeeperClient$CuratorWatcherImpl();
    Code:
       0: aload_0
       1: invokespecial #1                  // Method java/lang/Object."<init>":()V
       4: return

  public void unwatch();
    Code:
       0: aload_0
       1: aconst_null
       2: putfield      #3                  // Field childListener:Lorg/apache/dubbo/remoting/zookeeper/ChildListener;
       5: return

  public void process(org.apache.zookeeper.WatchedEvent) throws java.lang.Exception;
    Code:
       0: aload_1
       1: invokevirtual #5                  // Method org/apache/zookeeper/WatchedEvent.getType:()Lorg/apache/zookeeper/Watcher$Event$EventType;
       4: getstatic     #6                  // Field org/apache/zookeeper/Watcher$Event$EventType.None:Lorg/apache/zookeeper/Watcher$Event$EventType;
       7: if_acmpne     11
      10: return
      11: aload_0
      12: getfield      #3                  // Field childListener:Lorg/apache/dubbo/remoting/zookeeper/ChildListener;
      15: ifnull        61
      18: aload_0
      19: getfield      #3                  // Field childListener:Lorg/apache/dubbo/remoting/zookeeper/ChildListener;
      22: aload_0
      23: getfield      #4                  // Field path:Ljava/lang/String;
      26: aload_0
      27: getfield      #2                  // Field client:Lorg/apache/curator/framework/CuratorFramework;
      30: invokeinterface #7,  1            // InterfaceMethod org/apache/curator/framework/CuratorFramework.getChildren:()Lorg/apache/curator/framework/api/GetChildrenBuilder;
      35: aload_0
      36: invokeinterface #8,  2            // InterfaceMethod org/apache/curator/framework/api/GetChildrenBuilder.usingWatcher:(Lorg/apache/curator/framework/api/CuratorWatcher;)Ljava/lang/Object;
      41: checkcast     #9                  // class org/apache/curator/framework/api/BackgroundPathable
      44: aload_0
      45: getfield      #4                  // Field path:Ljava/lang/String;
      48: invokeinterface #10,  2           // InterfaceMethod org/apache/curator/framework/api/BackgroundPathable.forPath:(Ljava/lang/String;)Ljava/lang/Object;
      53: checkcast     #11                 // class java/util/List
      56: invokeinterface #12,  3           // InterfaceMethod org/apache/dubbo/remoting/zookeeper/ChildListener.childChanged:(Ljava/lang/String;Ljava/util/List;)V
      61: return
}
