Compiled from "Curator5ZookeeperTransporter.java"
public class org.apache.dubbo.remoting.zookeeper.curator5.Curator5ZookeeperTransporter extends org.apache.dubbo.remoting.zookeeper.AbstractZookeeperTransporter {
  public org.apache.dubbo.remoting.zookeeper.curator5.Curator5ZookeeperTransporter();
    Code:
       0: aload_0
       1: invokespecial #1                  // Method org/apache/dubbo/remoting/zookeeper/AbstractZookeeperTransporter."<init>":()V
       4: return

  public org.apache.dubbo.remoting.zookeeper.ZookeeperClient createZookeeperClient(org.apache.dubbo.common.URL);
    Code:
       0: new           #2                  // class org/apache/dubbo/remoting/zookeeper/curator5/Curator5ZookeeperClient
       3: dup
       4: aload_1
       5: invokespecial #3                  // Method org/apache/dubbo/remoting/zookeeper/curator5/Curator5ZookeeperClient."<init>":(Lorg/apache/dubbo/common/URL;)V
       8: areturn
}
