Compiled from "Curator5ZookeeperClient.java"
class org.apache.dubbo.remoting.zookeeper.curator5.Curator5ZookeeperClient$NodeCacheListenerImpl implements org.apache.curator.framework.recipes.cache.NodeCacheListener {
  private org.apache.curator.framework.CuratorFramework client;

  private volatile org.apache.dubbo.remoting.zookeeper.DataListener dataListener;

  private java.lang.String path;

  protected org.apache.dubbo.remoting.zookeeper.curator5.Curator5ZookeeperClient$NodeCacheListenerImpl();
    Code:
       0: aload_0
       1: invokespecial #2                  // Method java/lang/Object."<init>":()V
       4: return

  public org.apache.dubbo.remoting.zookeeper.curator5.Curator5ZookeeperClient$NodeCacheListenerImpl(org.apache.curator.framework.CuratorFramework, org.apache.dubbo.remoting.zookeeper.DataListener, java.lang.String);
    Code:
       0: aload_0
       1: invokespecial #2                  // Method java/lang/Object."<init>":()V
       4: aload_0
       5: aload_1
       6: putfield      #3                  // Field client:Lorg/apache/curator/framework/CuratorFramework;
       9: aload_0
      10: aload_2
      11: putfield      #1                  // Field dataListener:Lorg/apache/dubbo/remoting/zookeeper/DataListener;
      14: aload_0
      15: aload_3
      16: putfield      #4                  // Field path:Ljava/lang/String;
      19: return

  public void nodeChanged() throws java.lang.Exception;
    Code:
       0: invokestatic  #5                  // Method org/apache/dubbo/remoting/zookeeper/curator5/Curator5ZookeeperClient.access$100:()Ljava/util/Map;
       3: aload_0
       4: getfield      #4                  // Field path:Ljava/lang/String;
       7: invokeinterface #6,  2            // InterfaceMethod java/util/Map.get:(Ljava/lang/Object;)Ljava/lang/Object;
      12: checkcast     #7                  // class org/apache/curator/framework/recipes/cache/NodeCache
      15: invokevirtual #8                  // Method org/apache/curator/framework/recipes/cache/NodeCache.getCurrentData:()Lorg/apache/curator/framework/recipes/cache/ChildData;
      18: astore_1
      19: aconst_null
      20: astore_2
      21: aload_1
      22: ifnonnull     32
      25: getstatic     #9                  // Field org/apache/dubbo/remoting/zookeeper/EventType.NodeDeleted:Lorg/apache/dubbo/remoting/zookeeper/EventType;
      28: astore_3
      29: goto          83
      32: aload_1
      33: invokevirtual #10                 // Method org/apache/curator/framework/recipes/cache/ChildData.getStat:()Lorg/apache/zookeeper/data/Stat;
      36: invokevirtual #11                 // Method org/apache/zookeeper/data/Stat.getVersion:()I
      39: ifne          64
      42: new           #12                 // class java/lang/String
      45: dup
      46: aload_1
      47: invokevirtual #13                 // Method org/apache/curator/framework/recipes/cache/ChildData.getData:()[B
      50: invokestatic  #14                 // Method org/apache/dubbo/remoting/zookeeper/curator5/Curator5ZookeeperClient.access$200:()Ljava/nio/charset/Charset;
      53: invokespecial #15                 // Method java/lang/String."<init>":([BLjava/nio/charset/Charset;)V
      56: astore_2
      57: getstatic     #16                 // Field org/apache/dubbo/remoting/zookeeper/EventType.NodeCreated:Lorg/apache/dubbo/remoting/zookeeper/EventType;
      60: astore_3
      61: goto          83
      64: new           #12                 // class java/lang/String
      67: dup
      68: aload_1
      69: invokevirtual #13                 // Method org/apache/curator/framework/recipes/cache/ChildData.getData:()[B
      72: invokestatic  #14                 // Method org/apache/dubbo/remoting/zookeeper/curator5/Curator5ZookeeperClient.access$200:()Ljava/nio/charset/Charset;
      75: invokespecial #15                 // Method java/lang/String."<init>":([BLjava/nio/charset/Charset;)V
      78: astore_2
      79: getstatic     #17                 // Field org/apache/dubbo/remoting/zookeeper/EventType.NodeDataChanged:Lorg/apache/dubbo/remoting/zookeeper/EventType;
      82: astore_3
      83: aload_0
      84: getfield      #1                  // Field dataListener:Lorg/apache/dubbo/remoting/zookeeper/DataListener;
      87: aload_0
      88: getfield      #4                  // Field path:Ljava/lang/String;
      91: aload_2
      92: aload_3
      93: invokeinterface #18,  4           // InterfaceMethod org/apache/dubbo/remoting/zookeeper/DataListener.dataChanged:(Ljava/lang/String;Ljava/lang/Object;Lorg/apache/dubbo/remoting/zookeeper/EventType;)V
      98: return

  static org.apache.dubbo.remoting.zookeeper.DataListener access$002(org.apache.dubbo.remoting.zookeeper.curator5.Curator5ZookeeperClient$NodeCacheListenerImpl, org.apache.dubbo.remoting.zookeeper.DataListener);
    Code:
       0: aload_0
       1: aload_1
       2: dup_x1
       3: putfield      #1                  // Field dataListener:Lorg/apache/dubbo/remoting/zookeeper/DataListener;
       6: areturn
}
