Compiled from "Curator5ZookeeperClient.java"
class org.apache.dubbo.remoting.zookeeper.curator5.Curator5ZookeeperClient$1 implements org.apache.curator.framework.api.ACLProvider {
  final org.apache.dubbo.remoting.zookeeper.curator5.Curator5ZookeeperClient this$0;

  org.apache.dubbo.remoting.zookeeper.curator5.Curator5ZookeeperClient$1(org.apache.dubbo.remoting.zookeeper.curator5.Curator5ZookeeperClient);
    Code:
       0: aload_0
       1: aload_1
       2: putfield      #1                  // Field this$0:Lorg/apache/dubbo/remoting/zookeeper/curator5/Curator5ZookeeperClient;
       5: aload_0
       6: invokespecial #2                  // Method java/lang/Object."<init>":()V
       9: return

  public java.util.List<org.apache.zookeeper.data.ACL> getDefaultAcl();
    Code:
       0: getstatic     #3                  // Field org/apache/zookeeper/ZooDefs$Ids.CREATOR_ALL_ACL:Ljava/util/ArrayList;
       3: areturn

  public java.util.List<org.apache.zookeeper.data.ACL> getAclForPath(java.lang.String);
    Code:
       0: getstatic     #3                  // Field org/apache/zookeeper/ZooDefs$Ids.CREATOR_ALL_ACL:Ljava/util/ArrayList;
       3: areturn
}
