Compiled from "Predicates.java"
public interface org.apache.dubbo.common.function.Predicates {
  public static final java.util.function.Predicate[] EMPTY_ARRAY;

  public static <T> java.util.function.Predicate<T> alwaysTrue();
    Code:
       0: invokedynamic #1,  0              // InvokeDynamic #0:test:()Ljava/util/function/Predicate;
       5: areturn

  public static <T> java.util.function.Predicate<T> alwaysFalse();
    Code:
       0: invokedynamic #2,  0              // InvokeDynamic #1:test:()Ljava/util/function/Predicate;
       5: areturn

  public static <T> java.util.function.Predicate<T> and(java.util.function.Predicate<T>...);
    Code:
       0: aload_0
       1: invokestatic  #3                  // InterfaceMethod java/util/stream/Stream.of:([Ljava/lang/Object;)Ljava/util/stream/Stream;
       4: invokedynamic #4,  0              // InvokeDynamic #2:apply:()Ljava/util/function/BinaryOperator;
       9: invokeinterface #5,  2            // InterfaceMethod java/util/stream/Stream.reduce:(Ljava/util/function/BinaryOperator;)Ljava/util/Optional;
      14: invokedynamic #6,  0              // InvokeDynamic #3:get:()Ljava/util/function/Supplier;
      19: invokevirtual #7                  // Method java/util/Optional.orElseGet:(Ljava/util/function/Supplier;)Ljava/lang/Object;
      22: checkcast     #8                  // class java/util/function/Predicate
      25: areturn

  public static <T> java.util.function.Predicate<T> or(java.util.function.Predicate<T>...);
    Code:
       0: aload_0
       1: invokestatic  #3                  // InterfaceMethod java/util/stream/Stream.of:([Ljava/lang/Object;)Ljava/util/stream/Stream;
       4: invokedynamic #9,  0              // InvokeDynamic #4:apply:()Ljava/util/function/BinaryOperator;
       9: invokeinterface #5,  2            // InterfaceMethod java/util/stream/Stream.reduce:(Ljava/util/function/BinaryOperator;)Ljava/util/Optional;
      14: invokedynamic #10,  0             // InvokeDynamic #5:test:()Ljava/util/function/Predicate;
      19: invokevirtual #11                 // Method java/util/Optional.orElse:(Ljava/lang/Object;)Ljava/lang/Object;
      22: checkcast     #8                  // class java/util/function/Predicate
      25: areturn

  private static boolean lambda$or$2(java.lang.Object);
    Code:
       0: iconst_1
       1: ireturn

  private static boolean lambda$alwaysFalse$1(java.lang.Object);
    Code:
       0: iconst_0
       1: ireturn

  private static boolean lambda$alwaysTrue$0(java.lang.Object);
    Code:
       0: iconst_1
       1: ireturn

  static {};
    Code:
       0: iconst_0
       1: anewarray     #8                  // class java/util/function/Predicate
       4: putstatic     #12                 // Field EMPTY_ARRAY:[Ljava/util/function/Predicate;
       7: return
}
