Compiled from "ThrowableAction.java"
public interface org.apache.dubbo.common.function.ThrowableAction {
  public abstract void execute() throws java.lang.Throwable;

  public static void execute(org.apache.dubbo.common.function.ThrowableAction) throws java.lang.RuntimeException;
    Code:
       0: aload_0
       1: invokeinterface #1,  1            // InterfaceMethod execute:()V
       6: goto          19
       9: astore_1
      10: new           #3                  // class java/lang/RuntimeException
      13: dup
      14: aload_1
      15: invokespecial #4                  // Method java/lang/RuntimeException."<init>":(Ljava/lang/Throwable;)V
      18: athrow
      19: return
    Exception table:
       from    to  target type
           0     6     9   Class java/lang/Throwable
}
