Compiled from "ThrowableConsumer.java"
public interface org.apache.dubbo.common.function.ThrowableConsumer<T> {
  public abstract void accept(T) throws java.lang.Throwable;

  public default void execute(T) throws java.lang.RuntimeException;
    Code:
       0: aload_0
       1: aload_1
       2: invokeinterface #1,  2            // InterfaceMethod accept:(Ljava/lang/Object;)V
       7: goto          27
      10: astore_2
      11: new           #3                  // class java/lang/RuntimeException
      14: dup
      15: aload_2
      16: invokevirtual #4                  // Method java/lang/Throwable.getMessage:()Ljava/lang/String;
      19: aload_2
      20: invokevirtual #5                  // Method java/lang/Throwable.getCause:()Ljava/lang/Throwable;
      23: invokespecial #6                  // Method java/lang/RuntimeException."<init>":(Ljava/lang/String;Ljava/lang/Throwable;)V
      26: athrow
      27: return
    Exception table:
       from    to  target type
           0     7    10   Class java/lang/Throwable

  public static <T> void execute(T, org.apache.dubbo.common.function.ThrowableConsumer<T>);
    Code:
       0: aload_1
       1: aload_0
       2: invokeinterface #7,  2            // InterfaceMethod execute:(Ljava/lang/Object;)V
       7: return
}
