Compiled from "ThrowableFunction.java"
public interface org.apache.dubbo.common.function.ThrowableFunction<T, R> {
  public abstract R apply(T) throws java.lang.Throwable;

  public default R execute(T) throws java.lang.RuntimeException;
    Code:
       0: aconst_null
       1: astore_2
       2: aload_0
       3: aload_1
       4: invokeinterface #1,  2            // InterfaceMethod apply:(Ljava/lang/Object;)Ljava/lang/Object;
       9: astore_2
      10: goto          23
      13: astore_3
      14: new           #3                  // class java/lang/RuntimeException
      17: dup
      18: aload_3
      19: invokespecial #4                  // Method java/lang/RuntimeException."<init>":(Ljava/lang/Throwable;)V
      22: athrow
      23: aload_2
      24: areturn
    Exception table:
       from    to  target type
           2    10    13   Class java/lang/Throwable

  public static <T, R> R execute(T, org.apache.dubbo.common.function.ThrowableFunction<T, R>);
    Code:
       0: aload_1
       1: aload_0
       2: invokeinterface #5,  2            // InterfaceMethod execute:(Ljava/lang/Object;)Ljava/lang/Object;
       7: areturn
}
