Compiled from "ArgumentConditionMatcherFactory.java"
public class org.apache.dubbo.rpc.cluster.router.condition.matcher.argument.ArgumentConditionMatcherFactory implements org.apache.dubbo.rpc.cluster.router.condition.matcher.ConditionMatcherFactory {
  public org.apache.dubbo.rpc.cluster.router.condition.matcher.argument.ArgumentConditionMatcherFactory();
    Code:
       0: aload_0
       1: invokespecial #1                  // Method java/lang/Object."<init>":()V
       4: return

  public boolean shouldMatch(java.lang.String);
    Code:
       0: aload_1
       1: ldc           #3                  // String arguments
       3: invokevirtual #4                  // Method java/lang/String.startsWith:(Ljava/lang/String;)Z
       6: ireturn

  public org.apache.dubbo.rpc.cluster.router.condition.matcher.ConditionMatcher createMatcher(java.lang.String, org.apache.dubbo.rpc.model.ModuleModel);
    Code:
       0: new           #5                  // class org/apache/dubbo/rpc/cluster/router/condition/matcher/argument/ArgumentConditionMatcher
       3: dup
       4: aload_1
       5: aload_2
       6: invokespecial #6                  // Method org/apache/dubbo/rpc/cluster/router/condition/matcher/argument/ArgumentConditionMatcher."<init>":(Ljava/lang/String;Lorg/apache/dubbo/rpc/model/ModuleModel;)V
       9: areturn
}
