Compiled from "DispatcherType.java"
public final class org.springframework.boot.web.servlet.DispatcherType extends java.lang.Enum<org.springframework.boot.web.servlet.DispatcherType> {
  public static final org.springframework.boot.web.servlet.DispatcherType FORWARD;

  public static final org.springframework.boot.web.servlet.DispatcherType INCLUDE;

  public static final org.springframework.boot.web.servlet.DispatcherType REQUEST;

  public static final org.springframework.boot.web.servlet.DispatcherType ASYNC;

  public static final org.springframework.boot.web.servlet.DispatcherType ERROR;

  private static final org.springframework.boot.web.servlet.DispatcherType[] $VALUES;

  public static org.springframework.boot.web.servlet.DispatcherType[] values();
    Code:
       0: getstatic     #19                 // Field $VALUES:[Lorg/springframework/boot/web/servlet/DispatcherType;
       3: invokevirtual #23                 // Method "[Lorg/springframework/boot/web/servlet/DispatcherType;".clone:()Ljava/lang/Object;
       6: checkcast     #24                 // class "[Lorg/springframework/boot/web/servlet/DispatcherType;"
       9: areturn

  public static org.springframework.boot.web.servlet.DispatcherType valueOf(java.lang.String);
    Code:
       0: ldc           #1                  // class org/springframework/boot/web/servlet/DispatcherType
       2: aload_0
       3: invokestatic  #28                 // Method java/lang/Enum.valueOf:(Ljava/lang/Class;Ljava/lang/String;)Ljava/lang/Enum;
       6: checkcast     #1                  // class org/springframework/boot/web/servlet/DispatcherType
       9: areturn

  private org.springframework.boot.web.servlet.DispatcherType();
    Code:
       0: aload_0
       1: aload_1
       2: iload_2
       3: invokespecial #34                 // Method java/lang/Enum."<init>":(Ljava/lang/String;I)V
       6: return

  private static org.springframework.boot.web.servlet.DispatcherType[] $values();
    Code:
       0: iconst_5
       1: anewarray     #1                  // class org/springframework/boot/web/servlet/DispatcherType
       4: dup
       5: iconst_0
       6: getstatic     #3                  // Field FORWARD:Lorg/springframework/boot/web/servlet/DispatcherType;
       9: aastore
      10: dup
      11: iconst_1
      12: getstatic     #7                  // Field INCLUDE:Lorg/springframework/boot/web/servlet/DispatcherType;
      15: aastore
      16: dup
      17: iconst_2
      18: getstatic     #10                 // Field REQUEST:Lorg/springframework/boot/web/servlet/DispatcherType;
      21: aastore
      22: dup
      23: iconst_3
      24: getstatic     #13                 // Field ASYNC:Lorg/springframework/boot/web/servlet/DispatcherType;
      27: aastore
      28: dup
      29: iconst_4
      30: getstatic     #16                 // Field ERROR:Lorg/springframework/boot/web/servlet/DispatcherType;
      33: aastore
      34: areturn

  static {};
    Code:
       0: new           #1                  // class org/springframework/boot/web/servlet/DispatcherType
       3: dup
       4: ldc           #38                 // String FORWARD
       6: iconst_0
       7: invokespecial #39                 // Method "<init>":(Ljava/lang/String;I)V
      10: putstatic     #3                  // Field FORWARD:Lorg/springframework/boot/web/servlet/DispatcherType;
      13: new           #1                  // class org/springframework/boot/web/servlet/DispatcherType
      16: dup
      17: ldc           #40                 // String INCLUDE
      19: iconst_1
      20: invokespecial #39                 // Method "<init>":(Ljava/lang/String;I)V
      23: putstatic     #7                  // Field INCLUDE:Lorg/springframework/boot/web/servlet/DispatcherType;
      26: new           #1                  // class org/springframework/boot/web/servlet/DispatcherType
      29: dup
      30: ldc           #41                 // String REQUEST
      32: iconst_2
      33: invokespecial #39                 // Method "<init>":(Ljava/lang/String;I)V
      36: putstatic     #10                 // Field REQUEST:Lorg/springframework/boot/web/servlet/DispatcherType;
      39: new           #1                  // class org/springframework/boot/web/servlet/DispatcherType
      42: dup
      43: ldc           #42                 // String ASYNC
      45: iconst_3
      46: invokespecial #39                 // Method "<init>":(Ljava/lang/String;I)V
      49: putstatic     #13                 // Field ASYNC:Lorg/springframework/boot/web/servlet/DispatcherType;
      52: new           #1                  // class org/springframework/boot/web/servlet/DispatcherType
      55: dup
      56: ldc           #43                 // String ERROR
      58: iconst_4
      59: invokespecial #39                 // Method "<init>":(Ljava/lang/String;I)V
      62: putstatic     #16                 // Field ERROR:Lorg/springframework/boot/web/servlet/DispatcherType;
      65: invokestatic  #44                 // Method $values:()[Lorg/springframework/boot/web/servlet/DispatcherType;
      68: putstatic     #19                 // Field $VALUES:[Lorg/springframework/boot/web/servlet/DispatcherType;
      71: return
}
