Compiled from "ServletComponentScanRegistrar.java"
class org.springframework.boot.web.servlet.ServletComponentScanRegistrar implements org.springframework.context.annotation.ImportBeanDefinitionRegistrar {
  private static final java.lang.String BEAN_NAME;

  org.springframework.boot.web.servlet.ServletComponentScanRegistrar();
    Code:
       0: aload_0
       1: invokespecial #1                  // Method java/lang/Object."<init>":()V
       4: return

  public void registerBeanDefinitions(org.springframework.core.type.AnnotationMetadata, org.springframework.beans.factory.support.BeanDefinitionRegistry);
    Code:
       0: aload_0
       1: aload_1
       2: invokevirtual #7                  // Method getPackagesToScan:(Lorg/springframework/core/type/AnnotationMetadata;)Ljava/util/Set;
       5: astore_3
       6: aload_2
       7: ldc           #13                 // String servletComponentRegisteringPostProcessor
       9: invokeinterface #15,  2           // InterfaceMethod org/springframework/beans/factory/support/BeanDefinitionRegistry.containsBeanDefinition:(Ljava/lang/String;)Z
      14: ifeq          26
      17: aload_0
      18: aload_2
      19: aload_3
      20: invokevirtual #21                 // Method updatePostProcessor:(Lorg/springframework/beans/factory/support/BeanDefinitionRegistry;Ljava/util/Set;)V
      23: goto          32
      26: aload_0
      27: aload_2
      28: aload_3
      29: invokevirtual #25                 // Method addPostProcessor:(Lorg/springframework/beans/factory/support/BeanDefinitionRegistry;Ljava/util/Set;)V
      32: return

  private void updatePostProcessor(org.springframework.beans.factory.support.BeanDefinitionRegistry, java.util.Set<java.lang.String>);
    Code:
       0: aload_1
       1: ldc           #13                 // String servletComponentRegisteringPostProcessor
       3: invokeinterface #28,  2           // InterfaceMethod org/springframework/beans/factory/support/BeanDefinitionRegistry.getBeanDefinition:(Ljava/lang/String;)Lorg/springframework/beans/factory/config/BeanDefinition;
       8: checkcast     #32                 // class org/springframework/boot/web/servlet/ServletComponentScanRegistrar$ServletComponentRegisteringPostProcessorBeanDefinition
      11: astore_3
      12: aload_3
      13: aload_2
      14: invokevirtual #34                 // Method org/springframework/boot/web/servlet/ServletComponentScanRegistrar$ServletComponentRegisteringPostProcessorBeanDefinition.addPackageNames:(Ljava/util/Collection;)V
      17: return

  private void addPostProcessor(org.springframework.beans.factory.support.BeanDefinitionRegistry, java.util.Set<java.lang.String>);
    Code:
       0: new           #32                 // class org/springframework/boot/web/servlet/ServletComponentScanRegistrar$ServletComponentRegisteringPostProcessorBeanDefinition
       3: dup
       4: aload_2
       5: invokespecial #38                 // Method org/springframework/boot/web/servlet/ServletComponentScanRegistrar$ServletComponentRegisteringPostProcessorBeanDefinition."<init>":(Ljava/util/Collection;)V
       8: astore_3
       9: aload_1
      10: ldc           #13                 // String servletComponentRegisteringPostProcessor
      12: aload_3
      13: invokeinterface #40,  3           // InterfaceMethod org/springframework/beans/factory/support/BeanDefinitionRegistry.registerBeanDefinition:(Ljava/lang/String;Lorg/springframework/beans/factory/config/BeanDefinition;)V
      18: return

  private java.util.Set<java.lang.String> getPackagesToScan(org.springframework.core.type.AnnotationMetadata);
    Code:
       0: aload_1
       1: ldc           #44                 // class org/springframework/boot/web/servlet/ServletComponentScan
       3: invokevirtual #46                 // Method java/lang/Class.getName:()Ljava/lang/String;
       6: invokeinterface #52,  2           // InterfaceMethod org/springframework/core/type/AnnotationMetadata.getAnnotationAttributes:(Ljava/lang/String;)Ljava/util/Map;
      11: invokestatic  #58                 // Method org/springframework/core/annotation/AnnotationAttributes.fromMap:(Ljava/util/Map;)Lorg/springframework/core/annotation/AnnotationAttributes;
      14: astore_2
      15: aload_2
      16: ldc           #64                 // String basePackages
      18: invokevirtual #66                 // Method org/springframework/core/annotation/AnnotationAttributes.getStringArray:(Ljava/lang/String;)[Ljava/lang/String;
      21: astore_3
      22: aload_2
      23: ldc           #70                 // String basePackageClasses
      25: invokevirtual #72                 // Method org/springframework/core/annotation/AnnotationAttributes.getClassArray:(Ljava/lang/String;)[Ljava/lang/Class;
      28: astore        4
      30: new           #76                 // class java/util/LinkedHashSet
      33: dup
      34: aload_3
      35: invokestatic  #78                 // Method java/util/Arrays.asList:([Ljava/lang/Object;)Ljava/util/List;
      38: invokespecial #84                 // Method java/util/LinkedHashSet."<init>":(Ljava/util/Collection;)V
      41: astore        5
      43: aload         4
      45: astore        6
      47: aload         6
      49: arraylength
      50: istore        7
      52: iconst_0
      53: istore        8
      55: iload         8
      57: iload         7
      59: if_icmpge     88
      62: aload         6
      64: iload         8
      66: aaload
      67: astore        9
      69: aload         5
      71: aload         9
      73: invokestatic  #85                 // Method org/springframework/util/ClassUtils.getPackageName:(Ljava/lang/Class;)Ljava/lang/String;
      76: invokeinterface #91,  2           // InterfaceMethod java/util/Set.add:(Ljava/lang/Object;)Z
      81: pop
      82: iinc          8, 1
      85: goto          55
      88: aload         5
      90: invokeinterface #97,  1           // InterfaceMethod java/util/Set.isEmpty:()Z
      95: ifeq          115
      98: aload         5
     100: aload_1
     101: invokeinterface #101,  1          // InterfaceMethod org/springframework/core/type/AnnotationMetadata.getClassName:()Ljava/lang/String;
     106: invokestatic  #104                // Method org/springframework/util/ClassUtils.getPackageName:(Ljava/lang/String;)Ljava/lang/String;
     109: invokeinterface #91,  2           // InterfaceMethod java/util/Set.add:(Ljava/lang/Object;)Z
     114: pop
     115: aload         5
     117: areturn
}
