Compiled from "ServletContextInitializerBeans.java"
public class org.springframework.boot.web.servlet.ServletContextInitializerBeans extends java.util.AbstractCollection<org.springframework.boot.web.servlet.ServletContextInitializer> {
  private static final java.lang.String DISPATCHER_SERVLET_NAME;

  private static final org.apache.commons.logging.Log logger;

  private final java.util.Set<java.lang.Object> seen;

  private final org.springframework.util.MultiValueMap<java.lang.Class<?>, org.springframework.boot.web.servlet.ServletContextInitializer> initializers;

  private final java.util.List<java.lang.Class<? extends org.springframework.boot.web.servlet.ServletContextInitializer>> initializerTypes;

  private final java.util.List<org.springframework.boot.web.servlet.ServletContextInitializer> sortedList;

  public org.springframework.boot.web.servlet.ServletContextInitializerBeans(org.springframework.beans.factory.ListableBeanFactory, java.lang.Class<? extends org.springframework.boot.web.servlet.ServletContextInitializer>...);
    Code:
       0: aload_0
       1: invokespecial #1                  // Method java/util/AbstractCollection."<init>":()V
       4: aload_0
       5: new           #7                  // class java/util/HashSet
       8: dup
       9: invokespecial #9                  // Method java/util/HashSet."<init>":()V
      12: putfield      #10                 // Field seen:Ljava/util/Set;
      15: aload_0
      16: new           #16                 // class org/springframework/util/LinkedMultiValueMap
      19: dup
      20: invokespecial #18                 // Method org/springframework/util/LinkedMultiValueMap."<init>":()V
      23: putfield      #19                 // Field initializers:Lorg/springframework/util/MultiValueMap;
      26: aload_0
      27: aload_2
      28: arraylength
      29: ifeq          39
      32: aload_2
      33: invokestatic  #23                 // Method java/util/Arrays.asList:([Ljava/lang/Object;)Ljava/util/List;
      36: goto          44
      39: ldc           #29                 // class org/springframework/boot/web/servlet/ServletContextInitializer
      41: invokestatic  #31                 // Method java/util/Collections.singletonList:(Ljava/lang/Object;)Ljava/util/List;
      44: putfield      #37                 // Field initializerTypes:Ljava/util/List;
      47: aload_0
      48: aload_1
      49: invokevirtual #41                 // Method addServletContextInitializerBeans:(Lorg/springframework/beans/factory/ListableBeanFactory;)V
      52: aload_0
      53: aload_1
      54: invokevirtual #45                 // Method addAdaptableBeans:(Lorg/springframework/beans/factory/ListableBeanFactory;)V
      57: aload_0
      58: aload_0
      59: getfield      #19                 // Field initializers:Lorg/springframework/util/MultiValueMap;
      62: invokeinterface #48,  1           // InterfaceMethod org/springframework/util/MultiValueMap.values:()Ljava/util/Collection;
      67: invokeinterface #54,  1           // InterfaceMethod java/util/Collection.stream:()Ljava/util/stream/Stream;
      72: invokedynamic #60,  0             // InvokeDynamic #0:apply:()Ljava/util/function/Function;
      77: invokeinterface #64,  2           // InterfaceMethod java/util/stream/Stream.flatMap:(Ljava/util/function/Function;)Ljava/util/stream/Stream;
      82: invokeinterface #70,  1           // InterfaceMethod java/util/stream/Stream.toList:()Ljava/util/List;
      87: putfield      #74                 // Field sortedList:Ljava/util/List;
      90: aload_0
      91: aload_0
      92: getfield      #19                 // Field initializers:Lorg/springframework/util/MultiValueMap;
      95: invokevirtual #77                 // Method logMappings:(Lorg/springframework/util/MultiValueMap;)V
      98: return

  private void addServletContextInitializerBeans(org.springframework.beans.factory.ListableBeanFactory);
    Code:
       0: aload_0
       1: getfield      #37                 // Field initializerTypes:Ljava/util/List;
       4: invokeinterface #81,  1           // InterfaceMethod java/util/List.iterator:()Ljava/util/Iterator;
       9: astore_2
      10: aload_2
      11: invokeinterface #87,  1           // InterfaceMethod java/util/Iterator.hasNext:()Z
      16: ifeq          95
      19: aload_2
      20: invokeinterface #93,  1           // InterfaceMethod java/util/Iterator.next:()Ljava/lang/Object;
      25: checkcast     #97                 // class java/lang/Class
      28: astore_3
      29: aload_0
      30: aload_1
      31: aload_3
      32: invokevirtual #99                 // Method getOrderedBeansOfType:(Lorg/springframework/beans/factory/ListableBeanFactory;Ljava/lang/Class;)Ljava/util/List;
      35: invokeinterface #81,  1           // InterfaceMethod java/util/List.iterator:()Ljava/util/Iterator;
      40: astore        4
      42: aload         4
      44: invokeinterface #87,  1           // InterfaceMethod java/util/Iterator.hasNext:()Z
      49: ifeq          92
      52: aload         4
      54: invokeinterface #93,  1           // InterfaceMethod java/util/Iterator.next:()Ljava/lang/Object;
      59: checkcast     #103                // class java/util/Map$Entry
      62: astore        5
      64: aload_0
      65: aload         5
      67: invokeinterface #105,  1          // InterfaceMethod java/util/Map$Entry.getKey:()Ljava/lang/Object;
      72: checkcast     #108                // class java/lang/String
      75: aload         5
      77: invokeinterface #110,  1          // InterfaceMethod java/util/Map$Entry.getValue:()Ljava/lang/Object;
      82: checkcast     #29                 // class org/springframework/boot/web/servlet/ServletContextInitializer
      85: aload_1
      86: invokevirtual #113                // Method addServletContextInitializerBean:(Ljava/lang/String;Lorg/springframework/boot/web/servlet/ServletContextInitializer;Lorg/springframework/beans/factory/ListableBeanFactory;)V
      89: goto          42
      92: goto          10
      95: return

  private void addServletContextInitializerBean(java.lang.String, org.springframework.boot.web.servlet.ServletContextInitializer, org.springframework.beans.factory.ListableBeanFactory);
    Code:
       0: aload_2
       1: instanceof    #117                // class org/springframework/boot/web/servlet/ServletRegistrationBean
       4: ifeq          30
       7: aload_2
       8: checkcast     #117                // class org/springframework/boot/web/servlet/ServletRegistrationBean
      11: invokevirtual #119                // Method org/springframework/boot/web/servlet/ServletRegistrationBean.getServlet:()Ljakarta/servlet/Servlet;
      14: astore        4
      16: aload_0
      17: ldc           #123                // class jakarta/servlet/Servlet
      19: aload_1
      20: aload_2
      21: aload_3
      22: aload         4
      24: invokevirtual #125                // Method addServletContextInitializerBean:(Ljava/lang/Class;Ljava/lang/String;Lorg/springframework/boot/web/servlet/ServletContextInitializer;Lorg/springframework/beans/factory/ListableBeanFactory;Ljava/lang/Object;)V
      27: goto          130
      30: aload_2
      31: instanceof    #128                // class org/springframework/boot/web/servlet/FilterRegistrationBean
      34: ifeq          60
      37: aload_2
      38: checkcast     #128                // class org/springframework/boot/web/servlet/FilterRegistrationBean
      41: invokevirtual #130                // Method org/springframework/boot/web/servlet/FilterRegistrationBean.getFilter:()Ljakarta/servlet/Filter;
      44: astore        4
      46: aload_0
      47: ldc           #134                // class jakarta/servlet/Filter
      49: aload_1
      50: aload_2
      51: aload_3
      52: aload         4
      54: invokevirtual #125                // Method addServletContextInitializerBean:(Ljava/lang/Class;Ljava/lang/String;Lorg/springframework/boot/web/servlet/ServletContextInitializer;Lorg/springframework/beans/factory/ListableBeanFactory;Ljava/lang/Object;)V
      57: goto          130
      60: aload_2
      61: instanceof    #136                // class org/springframework/boot/web/servlet/DelegatingFilterProxyRegistrationBean
      64: ifeq          90
      67: aload_2
      68: checkcast     #136                // class org/springframework/boot/web/servlet/DelegatingFilterProxyRegistrationBean
      71: invokevirtual #138                // Method org/springframework/boot/web/servlet/DelegatingFilterProxyRegistrationBean.getTargetBeanName:()Ljava/lang/String;
      74: astore        4
      76: aload_0
      77: ldc           #134                // class jakarta/servlet/Filter
      79: aload_1
      80: aload_2
      81: aload_3
      82: aload         4
      84: invokevirtual #125                // Method addServletContextInitializerBean:(Ljava/lang/Class;Ljava/lang/String;Lorg/springframework/boot/web/servlet/ServletContextInitializer;Lorg/springframework/beans/factory/ListableBeanFactory;Ljava/lang/Object;)V
      87: goto          130
      90: aload_2
      91: instanceof    #142                // class org/springframework/boot/web/servlet/ServletListenerRegistrationBean
      94: ifeq          120
      97: aload_2
      98: checkcast     #142                // class org/springframework/boot/web/servlet/ServletListenerRegistrationBean
     101: invokevirtual #144                // Method org/springframework/boot/web/servlet/ServletListenerRegistrationBean.getListener:()Ljava/util/EventListener;
     104: astore        4
     106: aload_0
     107: ldc           #148                // class java/util/EventListener
     109: aload_1
     110: aload_2
     111: aload_3
     112: aload         4
     114: invokevirtual #125                // Method addServletContextInitializerBean:(Ljava/lang/Class;Ljava/lang/String;Lorg/springframework/boot/web/servlet/ServletContextInitializer;Lorg/springframework/beans/factory/ListableBeanFactory;Ljava/lang/Object;)V
     117: goto          130
     120: aload_0
     121: ldc           #29                 // class org/springframework/boot/web/servlet/ServletContextInitializer
     123: aload_1
     124: aload_2
     125: aload_3
     126: aload_2
     127: invokevirtual #125                // Method addServletContextInitializerBean:(Ljava/lang/Class;Ljava/lang/String;Lorg/springframework/boot/web/servlet/ServletContextInitializer;Lorg/springframework/beans/factory/ListableBeanFactory;Ljava/lang/Object;)V
     130: return

  private void addServletContextInitializerBean(java.lang.Class<?>, java.lang.String, org.springframework.boot.web.servlet.ServletContextInitializer, org.springframework.beans.factory.ListableBeanFactory, java.lang.Object);
    Code:
       0: aload_0
       1: getfield      #19                 // Field initializers:Lorg/springframework/util/MultiValueMap;
       4: aload_1
       5: aload_3
       6: invokeinterface #150,  3          // InterfaceMethod org/springframework/util/MultiValueMap.add:(Ljava/lang/Object;Ljava/lang/Object;)V
      11: aload         5
      13: ifnull        28
      16: aload_0
      17: getfield      #10                 // Field seen:Ljava/util/Set;
      20: aload         5
      22: invokeinterface #154,  2          // InterfaceMethod java/util/Set.add:(Ljava/lang/Object;)Z
      27: pop
      28: getstatic     #159                // Field logger:Lorg/apache/commons/logging/Log;
      31: invokeinterface #163,  1          // InterfaceMethod org/apache/commons/logging/Log.isTraceEnabled:()Z
      36: ifeq          77
      39: aload_0
      40: aload_2
      41: aload         4
      43: invokevirtual #168                // Method getResourceDescription:(Ljava/lang/String;Lorg/springframework/beans/factory/ListableBeanFactory;)Ljava/lang/String;
      46: astore        6
      48: aload_0
      49: aload_3
      50: invokevirtual #172                // Method getOrder:(Ljava/lang/Object;)I
      53: istore        7
      55: getstatic     #159                // Field logger:Lorg/apache/commons/logging/Log;
      58: aload_1
      59: invokevirtual #176                // Method java/lang/Class.getSimpleName:()Ljava/lang/String;
      62: aload_2
      63: iload         7
      65: aload         6
      67: invokedynamic #179,  0            // InvokeDynamic #1:makeConcatWithConstants:(Ljava/lang/String;Ljava/lang/String;ILjava/lang/String;)Ljava/lang/String;
      72: invokeinterface #183,  2          // InterfaceMethod org/apache/commons/logging/Log.trace:(Ljava/lang/Object;)V
      77: return

  private java.lang.String getResourceDescription(java.lang.String, org.springframework.beans.factory.ListableBeanFactory);
    Code:
       0: aload_2
       1: instanceof    #187                // class org/springframework/beans/factory/support/BeanDefinitionRegistry
       4: ifeq          25
       7: aload_2
       8: checkcast     #187                // class org/springframework/beans/factory/support/BeanDefinitionRegistry
      11: astore_3
      12: aload_3
      13: aload_1
      14: invokeinterface #189,  2          // InterfaceMethod org/springframework/beans/factory/support/BeanDefinitionRegistry.getBeanDefinition:(Ljava/lang/String;)Lorg/springframework/beans/factory/config/BeanDefinition;
      19: invokeinterface #193,  1          // InterfaceMethod org/springframework/beans/factory/config/BeanDefinition.getResourceDescription:()Ljava/lang/String;
      24: areturn
      25: ldc           #197                // String unknown
      27: areturn

  protected void addAdaptableBeans(org.springframework.beans.factory.ListableBeanFactory);
    Code:
       0: aload_0
       1: aload_1
       2: invokevirtual #199                // Method getMultipartConfig:(Lorg/springframework/beans/factory/ListableBeanFactory;)Ljakarta/servlet/MultipartConfigElement;
       5: astore_2
       6: aload_0
       7: aload_1
       8: ldc           #123                // class jakarta/servlet/Servlet
      10: new           #203                // class org/springframework/boot/web/servlet/ServletContextInitializerBeans$ServletRegistrationBeanAdapter
      13: dup
      14: aload_2
      15: invokespecial #205                // Method org/springframework/boot/web/servlet/ServletContextInitializerBeans$ServletRegistrationBeanAdapter."<init>":(Ljakarta/servlet/MultipartConfigElement;)V
      18: invokevirtual #208                // Method addAsRegistrationBean:(Lorg/springframework/beans/factory/ListableBeanFactory;Ljava/lang/Class;Lorg/springframework/boot/web/servlet/ServletContextInitializerBeans$RegistrationBeanAdapter;)V
      21: aload_0
      22: aload_1
      23: ldc           #134                // class jakarta/servlet/Filter
      25: new           #212                // class org/springframework/boot/web/servlet/ServletContextInitializerBeans$FilterRegistrationBeanAdapter
      28: dup
      29: invokespecial #214                // Method org/springframework/boot/web/servlet/ServletContextInitializerBeans$FilterRegistrationBeanAdapter."<init>":()V
      32: invokevirtual #208                // Method addAsRegistrationBean:(Lorg/springframework/beans/factory/ListableBeanFactory;Ljava/lang/Class;Lorg/springframework/boot/web/servlet/ServletContextInitializerBeans$RegistrationBeanAdapter;)V
      35: invokestatic  #215                // Method org/springframework/boot/web/servlet/ServletListenerRegistrationBean.getSupportedTypes:()Ljava/util/Set;
      38: invokeinterface #219,  1          // InterfaceMethod java/util/Set.iterator:()Ljava/util/Iterator;
      43: astore_3
      44: aload_3
      45: invokeinterface #87,  1           // InterfaceMethod java/util/Iterator.hasNext:()Z
      50: ifeq          83
      53: aload_3
      54: invokeinterface #93,  1           // InterfaceMethod java/util/Iterator.next:()Ljava/lang/Object;
      59: checkcast     #97                 // class java/lang/Class
      62: astore        4
      64: aload_0
      65: aload_1
      66: ldc           #148                // class java/util/EventListener
      68: aload         4
      70: new           #220                // class org/springframework/boot/web/servlet/ServletContextInitializerBeans$ServletListenerRegistrationBeanAdapter
      73: dup
      74: invokespecial #222                // Method org/springframework/boot/web/servlet/ServletContextInitializerBeans$ServletListenerRegistrationBeanAdapter."<init>":()V
      77: invokevirtual #223                // Method addAsRegistrationBean:(Lorg/springframework/beans/factory/ListableBeanFactory;Ljava/lang/Class;Ljava/lang/Class;Lorg/springframework/boot/web/servlet/ServletContextInitializerBeans$RegistrationBeanAdapter;)V
      80: goto          44
      83: return

  private jakarta.servlet.MultipartConfigElement getMultipartConfig(org.springframework.beans.factory.ListableBeanFactory);
    Code:
       0: aload_0
       1: aload_1
       2: ldc           #226                // class jakarta/servlet/MultipartConfigElement
       4: invokevirtual #99                 // Method getOrderedBeansOfType:(Lorg/springframework/beans/factory/ListableBeanFactory;Ljava/lang/Class;)Ljava/util/List;
       7: astore_2
       8: aload_2
       9: invokeinterface #228,  1          // InterfaceMethod java/util/List.isEmpty:()Z
      14: ifeq          21
      17: aconst_null
      18: goto          39
      21: aload_2
      22: iconst_0
      23: invokeinterface #231,  2          // InterfaceMethod java/util/List.get:(I)Ljava/lang/Object;
      28: checkcast     #103                // class java/util/Map$Entry
      31: invokeinterface #110,  1          // InterfaceMethod java/util/Map$Entry.getValue:()Ljava/lang/Object;
      36: checkcast     #226                // class jakarta/servlet/MultipartConfigElement
      39: areturn

  protected <T> void addAsRegistrationBean(org.springframework.beans.factory.ListableBeanFactory, java.lang.Class<T>, org.springframework.boot.web.servlet.ServletContextInitializerBeans$RegistrationBeanAdapter<T>);
    Code:
       0: aload_0
       1: aload_1
       2: aload_2
       3: aload_2
       4: aload_3
       5: invokevirtual #223                // Method addAsRegistrationBean:(Lorg/springframework/beans/factory/ListableBeanFactory;Ljava/lang/Class;Ljava/lang/Class;Lorg/springframework/boot/web/servlet/ServletContextInitializerBeans$RegistrationBeanAdapter;)V
       8: return

  private <T, B extends T> void addAsRegistrationBean(org.springframework.beans.factory.ListableBeanFactory, java.lang.Class<T>, java.lang.Class<B>, org.springframework.boot.web.servlet.ServletContextInitializerBeans$RegistrationBeanAdapter<T>);
    Code:
       0: aload_0
       1: aload_1
       2: aload_3
       3: aload_0
       4: getfield      #10                 // Field seen:Ljava/util/Set;
       7: invokevirtual #235                // Method getOrderedBeansOfType:(Lorg/springframework/beans/factory/ListableBeanFactory;Ljava/lang/Class;Ljava/util/Set;)Ljava/util/List;
      10: astore        5
      12: aload         5
      14: invokeinterface #81,  1           // InterfaceMethod java/util/List.iterator:()Ljava/util/Iterator;
      19: astore        6
      21: aload         6
      23: invokeinterface #87,  1           // InterfaceMethod java/util/Iterator.hasNext:()Z
      28: ifeq          167
      31: aload         6
      33: invokeinterface #93,  1           // InterfaceMethod java/util/Iterator.next:()Ljava/lang/Object;
      38: checkcast     #103                // class java/util/Map$Entry
      41: astore        7
      43: aload         7
      45: invokeinterface #105,  1          // InterfaceMethod java/util/Map$Entry.getKey:()Ljava/lang/Object;
      50: checkcast     #108                // class java/lang/String
      53: astore        8
      55: aload         7
      57: invokeinterface #110,  1          // InterfaceMethod java/util/Map$Entry.getValue:()Ljava/lang/Object;
      62: astore        9
      64: aload_0
      65: getfield      #10                 // Field seen:Ljava/util/Set;
      68: aload         9
      70: invokeinterface #154,  2          // InterfaceMethod java/util/Set.add:(Ljava/lang/Object;)Z
      75: ifeq          164
      78: aload         4
      80: aload         8
      82: aload         9
      84: aload         5
      86: invokeinterface #238,  1          // InterfaceMethod java/util/List.size:()I
      91: invokeinterface #242,  4          // InterfaceMethod org/springframework/boot/web/servlet/ServletContextInitializerBeans$RegistrationBeanAdapter.createRegistrationBean:(Ljava/lang/String;Ljava/lang/Object;I)Lorg/springframework/boot/web/servlet/RegistrationBean;
      96: astore        10
      98: aload_0
      99: aload         9
     101: invokevirtual #172                // Method getOrder:(Ljava/lang/Object;)I
     104: istore        11
     106: aload         10
     108: iload         11
     110: invokevirtual #248                // Method org/springframework/boot/web/servlet/RegistrationBean.setOrder:(I)V
     113: aload_0
     114: getfield      #19                 // Field initializers:Lorg/springframework/util/MultiValueMap;
     117: aload_2
     118: aload         10
     120: invokeinterface #150,  3          // InterfaceMethod org/springframework/util/MultiValueMap.add:(Ljava/lang/Object;Ljava/lang/Object;)V
     125: getstatic     #159                // Field logger:Lorg/apache/commons/logging/Log;
     128: invokeinterface #163,  1          // InterfaceMethod org/apache/commons/logging/Log.isTraceEnabled:()Z
     133: ifeq          164
     136: getstatic     #159                // Field logger:Lorg/apache/commons/logging/Log;
     139: aload_2
     140: invokevirtual #176                // Method java/lang/Class.getSimpleName:()Ljava/lang/String;
     143: aload         8
     145: iload         11
     147: aload_0
     148: aload         8
     150: aload_1
     151: invokevirtual #168                // Method getResourceDescription:(Ljava/lang/String;Lorg/springframework/beans/factory/ListableBeanFactory;)Ljava/lang/String;
     154: invokedynamic #254,  0            // InvokeDynamic #2:makeConcatWithConstants:(Ljava/lang/String;Ljava/lang/String;ILjava/lang/String;)Ljava/lang/String;
     159: invokeinterface #183,  2          // InterfaceMethod org/apache/commons/logging/Log.trace:(Ljava/lang/Object;)V
     164: goto          21
     167: return

  private int getOrder(java.lang.Object);
    Code:
       0: new           #255                // class org/springframework/boot/web/servlet/ServletContextInitializerBeans$1
       3: dup
       4: aload_0
       5: invokespecial #257                // Method org/springframework/boot/web/servlet/ServletContextInitializerBeans$1."<init>":(Lorg/springframework/boot/web/servlet/ServletContextInitializerBeans;)V
       8: aload_1
       9: invokevirtual #260                // Method org/springframework/boot/web/servlet/ServletContextInitializerBeans$1.getOrder:(Ljava/lang/Object;)I
      12: ireturn

  private <T> java.util.List<java.util.Map$Entry<java.lang.String, T>> getOrderedBeansOfType(org.springframework.beans.factory.ListableBeanFactory, java.lang.Class<T>);
    Code:
       0: aload_0
       1: aload_1
       2: aload_2
       3: invokestatic  #261                // Method java/util/Collections.emptySet:()Ljava/util/Set;
       6: invokevirtual #235                // Method getOrderedBeansOfType:(Lorg/springframework/beans/factory/ListableBeanFactory;Ljava/lang/Class;Ljava/util/Set;)Ljava/util/List;
       9: areturn

  private <T> java.util.List<java.util.Map$Entry<java.lang.String, T>> getOrderedBeansOfType(org.springframework.beans.factory.ListableBeanFactory, java.lang.Class<T>, java.util.Set<?>);
    Code:
       0: aload_1
       1: aload_2
       2: iconst_1
       3: iconst_0
       4: invokeinterface #264,  4          // InterfaceMethod org/springframework/beans/factory/ListableBeanFactory.getBeanNamesForType:(Ljava/lang/Class;ZZ)[Ljava/lang/String;
       9: astore        4
      11: new           #270                // class java/util/LinkedHashMap
      14: dup
      15: invokespecial #272                // Method java/util/LinkedHashMap."<init>":()V
      18: astore        5
      20: aload         4
      22: astore        6
      24: aload         6
      26: arraylength
      27: istore        7
      29: iconst_0
      30: istore        8
      32: iload         8
      34: iload         7
      36: if_icmpge     105
      39: aload         6
      41: iload         8
      43: aaload
      44: astore        9
      46: aload_3
      47: aload         9
      49: invokeinterface #273,  2          // InterfaceMethod java/util/Set.contains:(Ljava/lang/Object;)Z
      54: ifne          99
      57: aload         9
      59: invokestatic  #276                // Method org/springframework/aop/scope/ScopedProxyUtils.isScopedTarget:(Ljava/lang/String;)Z
      62: ifne          99
      65: aload_1
      66: aload         9
      68: aload_2
      69: invokeinterface #282,  3          // InterfaceMethod org/springframework/beans/factory/ListableBeanFactory.getBean:(Ljava/lang/String;Ljava/lang/Class;)Ljava/lang/Object;
      74: astore        10
      76: aload_3
      77: aload         10
      79: invokeinterface #273,  2          // InterfaceMethod java/util/Set.contains:(Ljava/lang/Object;)Z
      84: ifne          99
      87: aload         5
      89: aload         9
      91: aload         10
      93: invokeinterface #286,  3          // InterfaceMethod java/util/Map.put:(Ljava/lang/Object;Ljava/lang/Object;)Ljava/lang/Object;
      98: pop
      99: iinc          8, 1
     102: goto          32
     105: new           #292                // class java/util/ArrayList
     108: dup
     109: aload         5
     111: invokeinterface #294,  1          // InterfaceMethod java/util/Map.entrySet:()Ljava/util/Set;
     116: invokespecial #297                // Method java/util/ArrayList."<init>":(Ljava/util/Collection;)V
     119: astore        6
     121: aload         6
     123: invokedynamic #300,  0            // InvokeDynamic #3:compare:()Ljava/util/Comparator;
     128: invokeinterface #304,  2          // InterfaceMethod java/util/List.sort:(Ljava/util/Comparator;)V
     133: aload         6
     135: areturn

  private void logMappings(org.springframework.util.MultiValueMap<java.lang.Class<?>, org.springframework.boot.web.servlet.ServletContextInitializer>);
    Code:
       0: getstatic     #159                // Field logger:Lorg/apache/commons/logging/Log;
       3: invokeinterface #308,  1          // InterfaceMethod org/apache/commons/logging/Log.isDebugEnabled:()Z
       8: ifeq          35
      11: aload_0
      12: ldc_w         #311                // String filters
      15: aload_1
      16: ldc           #134                // class jakarta/servlet/Filter
      18: ldc           #128                // class org/springframework/boot/web/servlet/FilterRegistrationBean
      20: invokevirtual #313                // Method logMappings:(Ljava/lang/String;Lorg/springframework/util/MultiValueMap;Ljava/lang/Class;Ljava/lang/Class;)V
      23: aload_0
      24: ldc_w         #316                // String servlets
      27: aload_1
      28: ldc           #123                // class jakarta/servlet/Servlet
      30: ldc           #117                // class org/springframework/boot/web/servlet/ServletRegistrationBean
      32: invokevirtual #313                // Method logMappings:(Ljava/lang/String;Lorg/springframework/util/MultiValueMap;Ljava/lang/Class;Ljava/lang/Class;)V
      35: return

  private void logMappings(java.lang.String, org.springframework.util.MultiValueMap<java.lang.Class<?>, org.springframework.boot.web.servlet.ServletContextInitializer>, java.lang.Class<?>, java.lang.Class<? extends org.springframework.boot.web.servlet.RegistrationBean>);
    Code:
       0: new           #292                // class java/util/ArrayList
       3: dup
       4: invokespecial #318                // Method java/util/ArrayList."<init>":()V
       7: astore        5
       9: aload         5
      11: aload_2
      12: aload         4
      14: invokestatic  #319                // Method java/util/Collections.emptyList:()Ljava/util/List;
      17: invokeinterface #322,  3          // InterfaceMethod org/springframework/util/MultiValueMap.getOrDefault:(Ljava/lang/Object;Ljava/lang/Object;)Ljava/lang/Object;
      22: checkcast     #55                 // class java/util/Collection
      25: invokeinterface #325,  2          // InterfaceMethod java/util/List.addAll:(Ljava/util/Collection;)Z
      30: pop
      31: aload         5
      33: aload_2
      34: aload_3
      35: invokestatic  #319                // Method java/util/Collections.emptyList:()Ljava/util/List;
      38: invokeinterface #322,  3          // InterfaceMethod org/springframework/util/MultiValueMap.getOrDefault:(Ljava/lang/Object;Ljava/lang/Object;)Ljava/lang/Object;
      43: checkcast     #55                 // class java/util/Collection
      46: invokeinterface #325,  2          // InterfaceMethod java/util/List.addAll:(Ljava/util/Collection;)Z
      51: pop
      52: aload         5
      54: invokeinterface #329,  1          // InterfaceMethod java/util/List.stream:()Ljava/util/stream/Stream;
      59: invokedynamic #330,  0            // InvokeDynamic #4:apply:()Ljava/util/function/Function;
      64: invokeinterface #331,  2          // InterfaceMethod java/util/stream/Stream.map:(Ljava/util/function/Function;)Ljava/util/stream/Stream;
      69: ldc_w         #334                // String ,
      72: invokestatic  #336                // Method java/util/stream/Collectors.joining:(Ljava/lang/CharSequence;)Ljava/util/stream/Collector;
      75: invokeinterface #342,  2          // InterfaceMethod java/util/stream/Stream.collect:(Ljava/util/stream/Collector;)Ljava/lang/Object;
      80: checkcast     #108                // class java/lang/String
      83: astore        6
      85: getstatic     #159                // Field logger:Lorg/apache/commons/logging/Log;
      88: aload_1
      89: aload         6
      91: invokedynamic #346,  0            // InvokeDynamic #5:makeConcatWithConstants:(Ljava/lang/String;Ljava/lang/String;)Ljava/lang/String;
      96: invokeinterface #349,  2          // InterfaceMethod org/apache/commons/logging/Log.debug:(Ljava/lang/Object;)V
     101: return

  public java.util.Iterator<org.springframework.boot.web.servlet.ServletContextInitializer> iterator();
    Code:
       0: aload_0
       1: getfield      #74                 // Field sortedList:Ljava/util/List;
       4: invokeinterface #81,  1           // InterfaceMethod java/util/List.iterator:()Ljava/util/Iterator;
       9: areturn

  public int size();
    Code:
       0: aload_0
       1: getfield      #74                 // Field sortedList:Ljava/util/List;
       4: invokeinterface #238,  1          // InterfaceMethod java/util/List.size:()I
       9: ireturn

  private static int lambda$getOrderedBeansOfType$1(java.util.Map$Entry, java.util.Map$Entry);
    Code:
       0: getstatic     #352                // Field org/springframework/core/annotation/AnnotationAwareOrderComparator.INSTANCE:Lorg/springframework/core/annotation/AnnotationAwareOrderComparator;
       3: aload_0
       4: invokeinterface #110,  1          // InterfaceMethod java/util/Map$Entry.getValue:()Ljava/lang/Object;
       9: aload_1
      10: invokeinterface #110,  1          // InterfaceMethod java/util/Map$Entry.getValue:()Ljava/lang/Object;
      15: invokevirtual #358                // Method org/springframework/core/annotation/AnnotationAwareOrderComparator.compare:(Ljava/lang/Object;Ljava/lang/Object;)I
      18: ireturn

  private static java.util.stream.Stream lambda$new$0(java.util.List);
    Code:
       0: aload_0
       1: invokeinterface #329,  1          // InterfaceMethod java/util/List.stream:()Ljava/util/stream/Stream;
       6: getstatic     #352                // Field org/springframework/core/annotation/AnnotationAwareOrderComparator.INSTANCE:Lorg/springframework/core/annotation/AnnotationAwareOrderComparator;
       9: invokeinterface #361,  2          // InterfaceMethod java/util/stream/Stream.sorted:(Ljava/util/Comparator;)Ljava/util/stream/Stream;
      14: areturn

  static {};
    Code:
       0: ldc           #11                 // class org/springframework/boot/web/servlet/ServletContextInitializerBeans
       2: invokestatic  #365                // Method org/apache/commons/logging/LogFactory.getLog:(Ljava/lang/Class;)Lorg/apache/commons/logging/Log;
       5: putstatic     #159                // Field logger:Lorg/apache/commons/logging/Log;
       8: return
}
