Compiled from "ServletComponentRegisteringPostProcessor.java"
class org.springframework.boot.web.servlet.ServletComponentRegisteringPostProcessor implements org.springframework.beans.factory.config.BeanFactoryPostProcessor,org.springframework.context.ApplicationContextAware {
  private static final java.util.List<org.springframework.boot.web.servlet.ServletComponentHandler> HANDLERS;

  private final java.util.Set<java.lang.String> packagesToScan;

  private org.springframework.context.ApplicationContext applicationContext;

  org.springframework.boot.web.servlet.ServletComponentRegisteringPostProcessor(java.util.Set<java.lang.String>);
    Code:
       0: aload_0
       1: invokespecial #1                  // Method java/lang/Object."<init>":()V
       4: aload_0
       5: aload_1
       6: putfield      #7                  // Field packagesToScan:Ljava/util/Set;
       9: return

  public void postProcessBeanFactory(org.springframework.beans.factory.config.ConfigurableListableBeanFactory) throws org.springframework.beans.BeansException;
    Code:
       0: aload_0
       1: invokevirtual #13                 // Method isRunningInEmbeddedWebServer:()Z
       4: ifeq          52
       7: aload_0
       8: invokevirtual #17                 // Method createComponentProvider:()Lorg/springframework/context/annotation/ClassPathScanningCandidateComponentProvider;
      11: astore_2
      12: aload_0
      13: getfield      #7                  // Field packagesToScan:Ljava/util/Set;
      16: invokeinterface #21,  1           // InterfaceMethod java/util/Set.iterator:()Ljava/util/Iterator;
      21: astore_3
      22: aload_3
      23: invokeinterface #27,  1           // InterfaceMethod java/util/Iterator.hasNext:()Z
      28: ifeq          52
      31: aload_3
      32: invokeinterface #32,  1           // InterfaceMethod java/util/Iterator.next:()Ljava/lang/Object;
      37: checkcast     #36                 // class java/lang/String
      40: astore        4
      42: aload_0
      43: aload_2
      44: aload         4
      46: invokevirtual #38                 // Method scanPackage:(Lorg/springframework/context/annotation/ClassPathScanningCandidateComponentProvider;Ljava/lang/String;)V
      49: goto          22
      52: return

  private void scanPackage(org.springframework.context.annotation.ClassPathScanningCandidateComponentProvider, java.lang.String);
    Code:
       0: aload_1
       1: aload_2
       2: invokevirtual #42                 // Method org/springframework/context/annotation/ClassPathScanningCandidateComponentProvider.findCandidateComponents:(Ljava/lang/String;)Ljava/util/Set;
       5: invokeinterface #21,  1           // InterfaceMethod java/util/Set.iterator:()Ljava/util/Iterator;
      10: astore_3
      11: aload_3
      12: invokeinterface #27,  1           // InterfaceMethod java/util/Iterator.hasNext:()Z
      17: ifeq          98
      20: aload_3
      21: invokeinterface #32,  1           // InterfaceMethod java/util/Iterator.next:()Ljava/lang/Object;
      26: checkcast     #48                 // class org/springframework/beans/factory/config/BeanDefinition
      29: astore        4
      31: aload         4
      33: instanceof    #50                 // class org/springframework/beans/factory/annotation/AnnotatedBeanDefinition
      36: ifeq          95
      39: aload         4
      41: checkcast     #50                 // class org/springframework/beans/factory/annotation/AnnotatedBeanDefinition
      44: astore        5
      46: getstatic     #52                 // Field HANDLERS:Ljava/util/List;
      49: invokeinterface #56,  1           // InterfaceMethod java/util/List.iterator:()Ljava/util/Iterator;
      54: astore        6
      56: aload         6
      58: invokeinterface #27,  1           // InterfaceMethod java/util/Iterator.hasNext:()Z
      63: ifeq          95
      66: aload         6
      68: invokeinterface #32,  1           // InterfaceMethod java/util/Iterator.next:()Ljava/lang/Object;
      73: checkcast     #59                 // class org/springframework/boot/web/servlet/ServletComponentHandler
      76: astore        7
      78: aload         7
      80: aload         5
      82: aload_0
      83: getfield      #61                 // Field applicationContext:Lorg/springframework/context/ApplicationContext;
      86: checkcast     #65                 // class org/springframework/beans/factory/support/BeanDefinitionRegistry
      89: invokevirtual #67                 // Method org/springframework/boot/web/servlet/ServletComponentHandler.handle:(Lorg/springframework/beans/factory/annotation/AnnotatedBeanDefinition;Lorg/springframework/beans/factory/support/BeanDefinitionRegistry;)V
      92: goto          56
      95: goto          11
      98: return

  private boolean isRunningInEmbeddedWebServer();
    Code:
       0: aload_0
       1: getfield      #61                 // Field applicationContext:Lorg/springframework/context/ApplicationContext;
       4: astore_2
       5: aload_2
       6: instanceof    #71                 // class org/springframework/web/context/WebApplicationContext
       9: ifeq          30
      12: aload_2
      13: checkcast     #71                 // class org/springframework/web/context/WebApplicationContext
      16: astore_1
      17: aload_1
      18: invokeinterface #73,  1           // InterfaceMethod org/springframework/web/context/WebApplicationContext.getServletContext:()Ljakarta/servlet/ServletContext;
      23: ifnonnull     30
      26: iconst_1
      27: goto          31
      30: iconst_0
      31: ireturn

  private org.springframework.context.annotation.ClassPathScanningCandidateComponentProvider createComponentProvider();
    Code:
       0: new           #43                 // class org/springframework/context/annotation/ClassPathScanningCandidateComponentProvider
       3: dup
       4: iconst_0
       5: invokespecial #77                 // Method org/springframework/context/annotation/ClassPathScanningCandidateComponentProvider."<init>":(Z)V
       8: astore_1
       9: aload_1
      10: aload_0
      11: getfield      #61                 // Field applicationContext:Lorg/springframework/context/ApplicationContext;
      14: invokeinterface #80,  1           // InterfaceMethod org/springframework/context/ApplicationContext.getEnvironment:()Lorg/springframework/core/env/Environment;
      19: invokevirtual #86                 // Method org/springframework/context/annotation/ClassPathScanningCandidateComponentProvider.setEnvironment:(Lorg/springframework/core/env/Environment;)V
      22: aload_1
      23: aload_0
      24: getfield      #61                 // Field applicationContext:Lorg/springframework/context/ApplicationContext;
      27: invokevirtual #90                 // Method org/springframework/context/annotation/ClassPathScanningCandidateComponentProvider.setResourceLoader:(Lorg/springframework/core/io/ResourceLoader;)V
      30: getstatic     #52                 // Field HANDLERS:Ljava/util/List;
      33: invokeinterface #56,  1           // InterfaceMethod java/util/List.iterator:()Ljava/util/Iterator;
      38: astore_2
      39: aload_2
      40: invokeinterface #27,  1           // InterfaceMethod java/util/Iterator.hasNext:()Z
      45: ifeq          69
      48: aload_2
      49: invokeinterface #32,  1           // InterfaceMethod java/util/Iterator.next:()Ljava/lang/Object;
      54: checkcast     #59                 // class org/springframework/boot/web/servlet/ServletComponentHandler
      57: astore_3
      58: aload_1
      59: aload_3
      60: invokevirtual #94                 // Method org/springframework/boot/web/servlet/ServletComponentHandler.getTypeFilter:()Lorg/springframework/core/type/filter/TypeFilter;
      63: invokevirtual #98                 // Method org/springframework/context/annotation/ClassPathScanningCandidateComponentProvider.addIncludeFilter:(Lorg/springframework/core/type/filter/TypeFilter;)V
      66: goto          39
      69: aload_1
      70: areturn

  java.util.Set<java.lang.String> getPackagesToScan();
    Code:
       0: aload_0
       1: getfield      #7                  // Field packagesToScan:Ljava/util/Set;
       4: invokestatic  #102                // Method java/util/Collections.unmodifiableSet:(Ljava/util/Set;)Ljava/util/Set;
       7: areturn

  public void setApplicationContext(org.springframework.context.ApplicationContext) throws org.springframework.beans.BeansException;
    Code:
       0: aload_0
       1: aload_1
       2: putfield      #61                 // Field applicationContext:Lorg/springframework/context/ApplicationContext;
       5: return

  static {};
    Code:
       0: new           #108                // class java/util/ArrayList
       3: dup
       4: invokespecial #110                // Method java/util/ArrayList."<init>":()V
       7: astore_0
       8: aload_0
       9: new           #111                // class org/springframework/boot/web/servlet/WebServletHandler
      12: dup
      13: invokespecial #113                // Method org/springframework/boot/web/servlet/WebServletHandler."<init>":()V
      16: invokeinterface #114,  2          // InterfaceMethod java/util/List.add:(Ljava/lang/Object;)Z
      21: pop
      22: aload_0
      23: new           #118                // class org/springframework/boot/web/servlet/WebFilterHandler
      26: dup
      27: invokespecial #120                // Method org/springframework/boot/web/servlet/WebFilterHandler."<init>":()V
      30: invokeinterface #114,  2          // InterfaceMethod java/util/List.add:(Ljava/lang/Object;)Z
      35: pop
      36: aload_0
      37: new           #121                // class org/springframework/boot/web/servlet/WebListenerHandler
      40: dup
      41: invokespecial #123                // Method org/springframework/boot/web/servlet/WebListenerHandler."<init>":()V
      44: invokeinterface #114,  2          // InterfaceMethod java/util/List.add:(Ljava/lang/Object;)Z
      49: pop
      50: aload_0
      51: invokestatic  #124                // Method java/util/Collections.unmodifiableList:(Ljava/util/List;)Ljava/util/List;
      54: putstatic     #52                 // Field HANDLERS:Ljava/util/List;
      57: return
}
