Compiled from "ServletComponentScanRegistrar.java"
final class org.springframework.boot.web.servlet.ServletComponentScanRegistrar$ServletComponentRegisteringPostProcessorBeanDefinition extends org.springframework.beans.factory.support.GenericBeanDefinition {
  private final java.util.Set<java.lang.String> packageNames;

  org.springframework.boot.web.servlet.ServletComponentScanRegistrar$ServletComponentRegisteringPostProcessorBeanDefinition(java.util.Collection<java.lang.String>);
    Code:
       0: aload_0
       1: invokespecial #1                  // Method org/springframework/beans/factory/support/GenericBeanDefinition."<init>":()V
       4: aload_0
       5: new           #7                  // class java/util/LinkedHashSet
       8: dup
       9: invokespecial #9                  // Method java/util/LinkedHashSet."<init>":()V
      12: putfield      #10                 // Field packageNames:Ljava/util/Set;
      15: aload_0
      16: ldc           #16                 // class org/springframework/boot/web/servlet/ServletComponentRegisteringPostProcessor
      18: invokevirtual #18                 // Method setBeanClass:(Ljava/lang/Class;)V
      21: aload_0
      22: iconst_2
      23: invokevirtual #24                 // Method setRole:(I)V
      26: aload_0
      27: aload_1
      28: invokevirtual #28                 // Method addPackageNames:(Ljava/util/Collection;)V
      31: return

  public java.util.function.Supplier<?> getInstanceSupplier();
    Code:
       0: aload_0
       1: invokedynamic #32,  0             // InvokeDynamic #0:get:(Lorg/springframework/boot/web/servlet/ServletComponentScanRegistrar$ServletComponentRegisteringPostProcessorBeanDefinition;)Ljava/util/function/Supplier;
       6: areturn

  private void addPackageNames(java.util.Collection<java.lang.String>);
    Code:
       0: aload_0
       1: getfield      #10                 // Field packageNames:Ljava/util/Set;
       4: aload_1
       5: invokeinterface #36,  2           // InterfaceMethod java/util/Set.addAll:(Ljava/util/Collection;)Z
      10: pop
      11: return

  private java.lang.Object lambda$getInstanceSupplier$0();
    Code:
       0: new           #16                 // class org/springframework/boot/web/servlet/ServletComponentRegisteringPostProcessor
       3: dup
       4: aload_0
       5: getfield      #10                 // Field packageNames:Ljava/util/Set;
       8: invokespecial #42                 // Method org/springframework/boot/web/servlet/ServletComponentRegisteringPostProcessor."<init>":(Ljava/util/Set;)V
      11: areturn
}
