Compiled from "ServletComponentScanRegistrar.java"
class org.springframework.boot.web.servlet.ServletComponentScanRegistrar$ServletComponentScanBeanRegistrationExcludeFilter implements org.springframework.beans.factory.aot.BeanRegistrationExcludeFilter {
  org.springframework.boot.web.servlet.ServletComponentScanRegistrar$ServletComponentScanBeanRegistrationExcludeFilter();
    Code:
       0: aload_0
       1: invokespecial #3                  // Method java/lang/Object."<init>":()V
       4: return

  public boolean isExcludedFromAotProcessing(org.springframework.beans.factory.support.RegisteredBean);
    Code:
       0: ldc           #9                  // String servletComponentRegisteringPostProcessor
       2: aload_1
       3: invokevirtual #11                 // Method org/springframework/beans/factory/support/RegisteredBean.getBeanName:()Ljava/lang/String;
       6: invokevirtual #17                 // Method java/lang/String.equals:(Ljava/lang/Object;)Z
       9: ireturn
}
