Compiled from "WebListenerHandler.java"
class org.springframework.boot.web.servlet.WebListenerHandler extends org.springframework.boot.web.servlet.ServletComponentHandler {
  org.springframework.boot.web.servlet.WebListenerHandler();
    Code:
       0: aload_0
       1: ldc           #1                  // class jakarta/servlet/annotation/WebListener
       3: invokespecial #3                  // Method org/springframework/boot/web/servlet/ServletComponentHandler."<init>":(Ljava/lang/Class;)V
       6: return

  protected void doHandle(java.util.Map<java.lang.String, java.lang.Object>, org.springframework.beans.factory.annotation.AnnotatedBeanDefinition, org.springframework.beans.factory.support.BeanDefinitionRegistry);
    Code:
       0: ldc           #9                  // class org/springframework/boot/web/servlet/WebListenerHandler$ServletComponentWebListenerRegistrar
       2: invokestatic  #11                 // Method org/springframework/beans/factory/support/BeanDefinitionBuilder.rootBeanDefinition:(Ljava/lang/Class;)Lorg/springframework/beans/factory/support/BeanDefinitionBuilder;
       5: astore        4
       7: aload         4
       9: aload_2
      10: invokeinterface #17,  1           // InterfaceMethod org/springframework/beans/factory/annotation/AnnotatedBeanDefinition.getBeanClassName:()Ljava/lang/String;
      15: invokevirtual #23                 // Method org/springframework/beans/factory/support/BeanDefinitionBuilder.addConstructorArgValue:(Ljava/lang/Object;)Lorg/springframework/beans/factory/support/BeanDefinitionBuilder;
      18: pop
      19: aload_3
      20: aload_2
      21: invokeinterface #17,  1           // InterfaceMethod org/springframework/beans/factory/annotation/AnnotatedBeanDefinition.getBeanClassName:()Ljava/lang/String;
      26: invokedynamic #27,  0             // InvokeDynamic #0:makeConcatWithConstants:(Ljava/lang/String;)Ljava/lang/String;
      31: aload         4
      33: invokevirtual #31                 // Method org/springframework/beans/factory/support/BeanDefinitionBuilder.getBeanDefinition:()Lorg/springframework/beans/factory/support/AbstractBeanDefinition;
      36: invokeinterface #35,  3           // InterfaceMethod org/springframework/beans/factory/support/BeanDefinitionRegistry.registerBeanDefinition:(Ljava/lang/String;Lorg/springframework/beans/factory/config/BeanDefinition;)V
      41: return
}
