Compiled from "WebListenerHandler.java"
class org.springframework.boot.web.servlet.WebListenerHandler$ServletComponentWebListenerRegistrar implements org.springframework.boot.web.servlet.WebListenerRegistrar {
  private final java.lang.String listenerClassName;

  org.springframework.boot.web.servlet.WebListenerHandler$ServletComponentWebListenerRegistrar(java.lang.String);
    Code:
       0: aload_0
       1: invokespecial #1                  // Method java/lang/Object."<init>":()V
       4: aload_0
       5: aload_1
       6: putfield      #7                  // Field listenerClassName:Ljava/lang/String;
       9: return

  public void register(org.springframework.boot.web.servlet.WebListenerRegistry);
    Code:
       0: aload_1
       1: iconst_1
       2: anewarray     #13                 // class java/lang/String
       5: dup
       6: iconst_0
       7: aload_0
       8: getfield      #7                  // Field listenerClassName:Ljava/lang/String;
      11: aastore
      12: invokeinterface #15,  2           // InterfaceMethod org/springframework/boot/web/servlet/WebListenerRegistry.addWebListeners:([Ljava/lang/String;)V
      17: return
}
