Compiled from "WebServletHandler.java"
class org.springframework.boot.web.servlet.WebServletHandler extends org.springframework.boot.web.servlet.ServletComponentHandler {
  org.springframework.boot.web.servlet.WebServletHandler();
    Code:
       0: aload_0
       1: ldc           #1                  // class jakarta/servlet/annotation/WebServlet
       3: invokespecial #3                  // Method org/springframework/boot/web/servlet/ServletComponentHandler."<init>":(Ljava/lang/Class;)V
       6: return

  public void doHandle(java.util.Map<java.lang.String, java.lang.Object>, org.springframework.beans.factory.annotation.AnnotatedBeanDefinition, org.springframework.beans.factory.support.BeanDefinitionRegistry);
    Code:
       0: ldc           #9                  // class org/springframework/boot/web/servlet/ServletRegistrationBean
       2: invokestatic  #11                 // Method org/springframework/beans/factory/support/BeanDefinitionBuilder.rootBeanDefinition:(Ljava/lang/Class;)Lorg/springframework/beans/factory/support/BeanDefinitionBuilder;
       5: astore        4
       7: aload         4
       9: ldc           #17                 // String asyncSupported
      11: aload_1
      12: ldc           #17                 // String asyncSupported
      14: invokeinterface #19,  2           // InterfaceMethod java/util/Map.get:(Ljava/lang/Object;)Ljava/lang/Object;
      19: invokevirtual #25                 // Method org/springframework/beans/factory/support/BeanDefinitionBuilder.addPropertyValue:(Ljava/lang/String;Ljava/lang/Object;)Lorg/springframework/beans/factory/support/BeanDefinitionBuilder;
      22: pop
      23: aload         4
      25: ldc           #29                 // String initParameters
      27: aload_0
      28: aload_1
      29: invokevirtual #31                 // Method extractInitParameters:(Ljava/util/Map;)Ljava/util/Map;
      32: invokevirtual #25                 // Method org/springframework/beans/factory/support/BeanDefinitionBuilder.addPropertyValue:(Ljava/lang/String;Ljava/lang/Object;)Lorg/springframework/beans/factory/support/BeanDefinitionBuilder;
      35: pop
      36: aload         4
      38: ldc           #37                 // String loadOnStartup
      40: aload_1
      41: ldc           #37                 // String loadOnStartup
      43: invokeinterface #19,  2           // InterfaceMethod java/util/Map.get:(Ljava/lang/Object;)Ljava/lang/Object;
      48: invokevirtual #25                 // Method org/springframework/beans/factory/support/BeanDefinitionBuilder.addPropertyValue:(Ljava/lang/String;Ljava/lang/Object;)Lorg/springframework/beans/factory/support/BeanDefinitionBuilder;
      51: pop
      52: aload_0
      53: aload_1
      54: aload_2
      55: invokevirtual #39                 // Method determineName:(Ljava/util/Map;Lorg/springframework/beans/factory/config/BeanDefinition;)Ljava/lang/String;
      58: astore        5
      60: aload         4
      62: ldc           #43                 // String name
      64: aload         5
      66: invokevirtual #25                 // Method org/springframework/beans/factory/support/BeanDefinitionBuilder.addPropertyValue:(Ljava/lang/String;Ljava/lang/Object;)Lorg/springframework/beans/factory/support/BeanDefinitionBuilder;
      69: pop
      70: aload         4
      72: ldc           #45                 // String servlet
      74: aload_2
      75: invokevirtual #25                 // Method org/springframework/beans/factory/support/BeanDefinitionBuilder.addPropertyValue:(Ljava/lang/String;Ljava/lang/Object;)Lorg/springframework/beans/factory/support/BeanDefinitionBuilder;
      78: pop
      79: aload         4
      81: ldc           #47                 // String urlMappings
      83: aload_0
      84: aload_1
      85: invokevirtual #49                 // Method extractUrlPatterns:(Ljava/util/Map;)[Ljava/lang/String;
      88: invokevirtual #25                 // Method org/springframework/beans/factory/support/BeanDefinitionBuilder.addPropertyValue:(Ljava/lang/String;Ljava/lang/Object;)Lorg/springframework/beans/factory/support/BeanDefinitionBuilder;
      91: pop
      92: aload         4
      94: ldc           #53                 // String multipartConfig
      96: aload_0
      97: aload_2
      98: invokevirtual #55                 // Method determineMultipartConfig:(Lorg/springframework/beans/factory/annotation/AnnotatedBeanDefinition;)Ljakarta/servlet/MultipartConfigElement;
     101: invokevirtual #25                 // Method org/springframework/beans/factory/support/BeanDefinitionBuilder.addPropertyValue:(Ljava/lang/String;Ljava/lang/Object;)Lorg/springframework/beans/factory/support/BeanDefinitionBuilder;
     104: pop
     105: aload_3
     106: aload         5
     108: aload         4
     110: invokevirtual #59                 // Method org/springframework/beans/factory/support/BeanDefinitionBuilder.getBeanDefinition:()Lorg/springframework/beans/factory/support/AbstractBeanDefinition;
     113: invokeinterface #63,  3           // InterfaceMethod org/springframework/beans/factory/support/BeanDefinitionRegistry.registerBeanDefinition:(Ljava/lang/String;Lorg/springframework/beans/factory/config/BeanDefinition;)V
     118: return

  private java.lang.String determineName(java.util.Map<java.lang.String, java.lang.Object>, org.springframework.beans.factory.config.BeanDefinition);
    Code:
       0: aload_1
       1: ldc           #43                 // String name
       3: invokeinterface #19,  2           // InterfaceMethod java/util/Map.get:(Ljava/lang/Object;)Ljava/lang/Object;
       8: checkcast     #69                 // class java/lang/String
      11: invokestatic  #71                 // Method org/springframework/util/StringUtils.hasText:(Ljava/lang/String;)Z
      14: ifeq          28
      17: aload_1
      18: ldc           #43                 // String name
      20: invokeinterface #19,  2           // InterfaceMethod java/util/Map.get:(Ljava/lang/Object;)Ljava/lang/Object;
      25: goto          34
      28: aload_2
      29: invokeinterface #77,  1           // InterfaceMethod org/springframework/beans/factory/config/BeanDefinition.getBeanClassName:()Ljava/lang/String;
      34: checkcast     #69                 // class java/lang/String
      37: areturn

  private jakarta.servlet.MultipartConfigElement determineMultipartConfig(org.springframework.beans.factory.annotation.AnnotatedBeanDefinition);
    Code:
       0: aload_1
       1: invokeinterface #83,  1           // InterfaceMethod org/springframework/beans/factory/annotation/AnnotatedBeanDefinition.getMetadata:()Lorg/springframework/core/type/AnnotationMetadata;
       6: ldc           #89                 // class jakarta/servlet/annotation/MultipartConfig
       8: invokevirtual #91                 // Method java/lang/Class.getName:()Ljava/lang/String;
      11: invokeinterface #96,  2           // InterfaceMethod org/springframework/core/type/AnnotationMetadata.getAnnotationAttributes:(Ljava/lang/String;)Ljava/util/Map;
      16: astore_2
      17: aload_2
      18: ifnonnull     23
      21: aconst_null
      22: areturn
      23: new           #102                // class jakarta/servlet/MultipartConfigElement
      26: dup
      27: aload_2
      28: ldc           #104                // String location
      30: invokeinterface #19,  2           // InterfaceMethod java/util/Map.get:(Ljava/lang/Object;)Ljava/lang/Object;
      35: checkcast     #69                 // class java/lang/String
      38: aload_2
      39: ldc           #106                // String maxFileSize
      41: invokeinterface #19,  2           // InterfaceMethod java/util/Map.get:(Ljava/lang/Object;)Ljava/lang/Object;
      46: checkcast     #108                // class java/lang/Long
      49: invokevirtual #110                // Method java/lang/Long.longValue:()J
      52: aload_2
      53: ldc           #114                // String maxRequestSize
      55: invokeinterface #19,  2           // InterfaceMethod java/util/Map.get:(Ljava/lang/Object;)Ljava/lang/Object;
      60: checkcast     #108                // class java/lang/Long
      63: invokevirtual #110                // Method java/lang/Long.longValue:()J
      66: aload_2
      67: ldc           #116                // String fileSizeThreshold
      69: invokeinterface #19,  2           // InterfaceMethod java/util/Map.get:(Ljava/lang/Object;)Ljava/lang/Object;
      74: checkcast     #118                // class java/lang/Integer
      77: invokevirtual #120                // Method java/lang/Integer.intValue:()I
      80: invokespecial #124                // Method jakarta/servlet/MultipartConfigElement."<init>":(Ljava/lang/String;JJI)V
      83: areturn
}
