Compiled from "FileCacheStore.java"
public class org.apache.dubbo.common.cache.FileCacheStore$Empty extends org.apache.dubbo.common.cache.FileCacheStore {
  private org.apache.dubbo.common.cache.FileCacheStore$Empty(java.lang.String);
    Code:
       0: aload_0
       1: aload_1
       2: aconst_null
       3: aconst_null
       4: aconst_null
       5: aconst_null
       6: invokespecial #1                  // Method org/apache/dubbo/common/cache/FileCacheStore."<init>":(Ljava/lang/String;Ljava/io/File;Ljava/io/File;Ljava/nio/channels/FileLock;Lorg/apache/dubbo/common/cache/FileCacheStore$1;)V
       9: return

  public static org.apache.dubbo.common.cache.FileCacheStore$Empty getInstance(java.lang.String);
    Code:
       0: new           #2                  // class org/apache/dubbo/common/cache/FileCacheStore$Empty
       3: dup
       4: aload_0
       5: invokespecial #3                  // Method "<init>":(Ljava/lang/String;)V
       8: areturn

  public synchronized java.util.Map<java.lang.String, java.lang.String> loadCache(int) throws java.io.IOException;
    Code:
       0: invokestatic  #4                  // Method java/util/Collections.emptyMap:()Ljava/util/Map;
       3: areturn

  public synchronized void refreshCache(java.util.Map<java.lang.String, java.lang.String>, java.lang.String, long);
    Code:
       0: return
}
