Compiled from "FileCacheStore.java"
public class org.apache.dubbo.common.cache.FileCacheStore$Builder {
  private java.lang.String cacheFilePath;

  private java.io.File cacheFile;

  private java.io.File lockFile;

  private java.nio.channels.FileLock directoryLock;

  private org.apache.dubbo.common.cache.FileCacheStore$Builder();
    Code:
       0: aload_0
       1: invokespecial #2                  // Method java/lang/Object."<init>":()V
       4: return

  public org.apache.dubbo.common.cache.FileCacheStore$Builder cacheFilePath(java.lang.String);
    Code:
       0: aload_0
       1: aload_1
       2: putfield      #3                  // Field cacheFilePath:Ljava/lang/String;
       5: aload_0
       6: areturn

  public org.apache.dubbo.common.cache.FileCacheStore$Builder cacheFile(java.io.File);
    Code:
       0: aload_0
       1: aload_1
       2: putfield      #4                  // Field cacheFile:Ljava/io/File;
       5: aload_0
       6: areturn

  public org.apache.dubbo.common.cache.FileCacheStore$Builder lockFile(java.io.File);
    Code:
       0: aload_0
       1: aload_1
       2: putfield      #5                  // Field lockFile:Ljava/io/File;
       5: aload_0
       6: areturn

  public org.apache.dubbo.common.cache.FileCacheStore$Builder directoryLock(java.nio.channels.FileLock);
    Code:
       0: aload_0
       1: aload_1
       2: putfield      #6                  // Field directoryLock:Ljava/nio/channels/FileLock;
       5: aload_0
       6: areturn

  public org.apache.dubbo.common.cache.FileCacheStore build();
    Code:
       0: new           #7                  // class org/apache/dubbo/common/cache/FileCacheStore
       3: dup
       4: aload_0
       5: getfield      #3                  // Field cacheFilePath:Ljava/lang/String;
       8: aload_0
       9: getfield      #4                  // Field cacheFile:Ljava/io/File;
      12: aload_0
      13: getfield      #5                  // Field lockFile:Ljava/io/File;
      16: aload_0
      17: getfield      #6                  // Field directoryLock:Ljava/nio/channels/FileLock;
      20: aconst_null
      21: invokespecial #8                  // Method org/apache/dubbo/common/cache/FileCacheStore."<init>":(Ljava/lang/String;Ljava/io/File;Ljava/io/File;Ljava/nio/channels/FileLock;Lorg/apache/dubbo/common/cache/FileCacheStore$1;)V
      24: areturn

  org.apache.dubbo.common.cache.FileCacheStore$Builder(org.apache.dubbo.common.cache.FileCacheStore$1);
    Code:
       0: aload_0
       1: invokespecial #1                  // Method "<init>":()V
       4: return
}
