Compiled from "FileCacheStoreFactory.java"
public final class org.apache.dubbo.common.cache.FileCacheStoreFactory {
  private static final org.apache.dubbo.common.logger.ErrorTypeAwareLogger logger;

  private static final java.util.concurrent.ConcurrentMap<java.lang.String, org.apache.dubbo.common.cache.FileCacheStore> cacheMap;

  private static final java.lang.String SUFFIX;

  private static final char ESCAPE_MARK;

  private static final java.util.Set<java.lang.Character> LEGAL_CHARACTERS;

  private org.apache.dubbo.common.cache.FileCacheStoreFactory();
    Code:
       0: aload_0
       1: invokespecial #2                  // Method java/lang/Object."<init>":()V
       4: new           #3                  // class java/lang/UnsupportedOperationException
       7: dup
       8: ldc           #4                  // String No instance of \'FileCacheStoreFactory\' for you!
      10: invokespecial #5                  // Method java/lang/UnsupportedOperationException."<init>":(Ljava/lang/String;)V
      13: athrow

  public static org.apache.dubbo.common.cache.FileCacheStore getInstance(java.lang.String, java.lang.String);
    Code:
       0: aload_0
       1: aload_1
       2: iconst_1
       3: invokestatic  #6                  // Method getInstance:(Ljava/lang/String;Ljava/lang/String;Z)Lorg/apache/dubbo/common/cache/FileCacheStore;
       6: areturn

  public static org.apache.dubbo.common.cache.FileCacheStore getInstance(java.lang.String, java.lang.String, boolean);
    Code:
       0: aload_0
       1: ifnonnull     34
       4: new           #7                  // class java/lang/StringBuilder
       7: dup
       8: invokespecial #8                  // Method java/lang/StringBuilder."<init>":()V
      11: ldc           #9                  // String user.home
      13: invokestatic  #10                 // Method java/lang/System.getProperty:(Ljava/lang/String;)Ljava/lang/String;
      16: invokevirtual #11                 // Method java/lang/StringBuilder.append:(Ljava/lang/String;)Ljava/lang/StringBuilder;
      19: getstatic     #12                 // Field java/io/File.separator:Ljava/lang/String;
      22: invokevirtual #11                 // Method java/lang/StringBuilder.append:(Ljava/lang/String;)Ljava/lang/StringBuilder;
      25: ldc           #13                 // String .dubbo
      27: invokevirtual #11                 // Method java/lang/StringBuilder.append:(Ljava/lang/String;)Ljava/lang/StringBuilder;
      30: invokevirtual #14                 // Method java/lang/StringBuilder.toString:()Ljava/lang/String;
      33: astore_0
      34: aload_0
      35: getstatic     #12                 // Field java/io/File.separator:Ljava/lang/String;
      38: invokevirtual #15                 // Method java/lang/String.endsWith:(Ljava/lang/String;)Z
      41: ifeq          56
      44: aload_0
      45: iconst_0
      46: aload_0
      47: invokevirtual #16                 // Method java/lang/String.length:()I
      50: iconst_1
      51: isub
      52: invokevirtual #17                 // Method java/lang/String.substring:(II)Ljava/lang/String;
      55: astore_0
      56: new           #18                 // class java/io/File
      59: dup
      60: aload_0
      61: invokespecial #19                 // Method java/io/File."<init>":(Ljava/lang/String;)V
      64: astore_3
      65: aload_3
      66: invokevirtual #20                 // Method java/io/File.toPath:()Ljava/nio/file/Path;
      69: astore        4
      71: aload_3
      72: invokevirtual #21                 // Method java/io/File.isDirectory:()Z
      75: ifne          140
      78: aload         4
      80: iconst_0
      81: anewarray     #22                 // class java/nio/file/attribute/FileAttribute
      84: invokestatic  #23                 // Method java/nio/file/Files.createDirectories:(Ljava/nio/file/Path;[Ljava/nio/file/attribute/FileAttribute;)Ljava/nio/file/Path;
      87: pop
      88: goto          140
      91: astore        5
      93: getstatic     #25                 // Field logger:Lorg/apache/dubbo/common/logger/ErrorTypeAwareLogger;
      96: ldc           #26                 // String 0-3
      98: ldc           #27                 // String inaccessible of cache path
     100: ldc           #28                 // String
     102: ldc           #29                 // String Cache store path can\'t be created:
     104: aload         5
     106: invokeinterface #30,  6           // InterfaceMethod org/apache/dubbo/common/logger/ErrorTypeAwareLogger.error:(Ljava/lang/String;Ljava/lang/String;Ljava/lang/String;Ljava/lang/String;Ljava/lang/Throwable;)V
     111: new           #31                 // class java/lang/RuntimeException
     114: dup
     115: new           #7                  // class java/lang/StringBuilder
     118: dup
     119: invokespecial #8                  // Method java/lang/StringBuilder."<init>":()V
     122: ldc           #29                 // String Cache store path can\'t be created:
     124: invokevirtual #11                 // Method java/lang/StringBuilder.append:(Ljava/lang/String;)Ljava/lang/StringBuilder;
     127: aload_3
     128: invokevirtual #32                 // Method java/lang/StringBuilder.append:(Ljava/lang/Object;)Ljava/lang/StringBuilder;
     131: invokevirtual #14                 // Method java/lang/StringBuilder.toString:()Ljava/lang/String;
     134: aload         5
     136: invokespecial #33                 // Method java/lang/RuntimeException."<init>":(Ljava/lang/String;Ljava/lang/Throwable;)V
     139: athrow
     140: aload_1
     141: invokestatic  #34                 // Method safeName:(Ljava/lang/String;)Ljava/lang/String;
     144: astore_1
     145: aload_1
     146: ldc           #36                 // String .dubbo.cache
     148: invokevirtual #15                 // Method java/lang/String.endsWith:(Ljava/lang/String;)Z
     151: ifne          174
     154: new           #7                  // class java/lang/StringBuilder
     157: dup
     158: invokespecial #8                  // Method java/lang/StringBuilder."<init>":()V
     161: aload_1
     162: invokevirtual #11                 // Method java/lang/StringBuilder.append:(Ljava/lang/String;)Ljava/lang/StringBuilder;
     165: ldc           #36                 // String .dubbo.cache
     167: invokevirtual #11                 // Method java/lang/StringBuilder.append:(Ljava/lang/String;)Ljava/lang/StringBuilder;
     170: invokevirtual #14                 // Method java/lang/StringBuilder.toString:()Ljava/lang/String;
     173: astore_1
     174: new           #7                  // class java/lang/StringBuilder
     177: dup
     178: invokespecial #8                  // Method java/lang/StringBuilder."<init>":()V
     181: aload_0
     182: invokevirtual #11                 // Method java/lang/StringBuilder.append:(Ljava/lang/String;)Ljava/lang/StringBuilder;
     185: getstatic     #12                 // Field java/io/File.separator:Ljava/lang/String;
     188: invokevirtual #11                 // Method java/lang/StringBuilder.append:(Ljava/lang/String;)Ljava/lang/StringBuilder;
     191: aload_1
     192: invokevirtual #11                 // Method java/lang/StringBuilder.append:(Ljava/lang/String;)Ljava/lang/StringBuilder;
     195: invokevirtual #14                 // Method java/lang/StringBuilder.toString:()Ljava/lang/String;
     198: astore        5
     200: getstatic     #37                 // Field cacheMap:Ljava/util/concurrent/ConcurrentMap;
     203: aload         5
     205: iload_2
     206: invokedynamic #38,  0             // InvokeDynamic #0:apply:(Z)Ljava/util/function/Function;
     211: invokestatic  #39                 // Method org/apache/dubbo/common/utils/ConcurrentHashMapUtils.computeIfAbsent:(Ljava/util/concurrent/ConcurrentMap;Ljava/lang/Object;Ljava/util/function/Function;)Ljava/lang/Object;
     214: checkcast     #40                 // class org/apache/dubbo/common/cache/FileCacheStore
     217: areturn
    Exception table:
       from    to  target type
          78    88    91   Class java/io/IOException

  private static java.lang.String safeName(java.lang.String);
    Code:
       0: aload_0
       1: invokevirtual #16                 // Method java/lang/String.length:()I
       4: istore_1
       5: new           #7                  // class java/lang/StringBuilder
       8: dup
       9: iload_1
      10: invokespecial #41                 // Method java/lang/StringBuilder."<init>":(I)V
      13: astore_2
      14: iconst_0
      15: istore_3
      16: iload_3
      17: iload_1
      18: if_icmpge     89
      21: aload_0
      22: iload_3
      23: invokevirtual #42                 // Method java/lang/String.charAt:(I)C
      26: istore        4
      28: getstatic     #43                 // Field LEGAL_CHARACTERS:Ljava/util/Set;
      31: iload         4
      33: invokestatic  #44                 // Method java/lang/Character.valueOf:(C)Ljava/lang/Character;
      36: invokeinterface #45,  2           // InterfaceMethod java/util/Set.contains:(Ljava/lang/Object;)Z
      41: ifeq          54
      44: aload_2
      45: iload         4
      47: invokevirtual #46                 // Method java/lang/StringBuilder.append:(C)Ljava/lang/StringBuilder;
      50: pop
      51: goto          83
      54: aload_2
      55: bipush        37
      57: invokevirtual #46                 // Method java/lang/StringBuilder.append:(C)Ljava/lang/StringBuilder;
      60: pop
      61: aload_2
      62: ldc           #47                 // String %04x
      64: iconst_1
      65: anewarray     #48                 // class java/lang/Object
      68: dup
      69: iconst_0
      70: iload         4
      72: invokestatic  #49                 // Method java/lang/Integer.valueOf:(I)Ljava/lang/Integer;
      75: aastore
      76: invokestatic  #50                 // Method java/lang/String.format:(Ljava/lang/String;[Ljava/lang/Object;)Ljava/lang/String;
      79: invokevirtual #11                 // Method java/lang/StringBuilder.append:(Ljava/lang/String;)Ljava/lang/StringBuilder;
      82: pop
      83: iinc          3, 1
      86: goto          16
      89: aload_2
      90: invokevirtual #14                 // Method java/lang/StringBuilder.toString:()Ljava/lang/String;
      93: areturn

  private static org.apache.dubbo.common.cache.FileCacheStore getFile(java.lang.String, boolean);
    Code:
       0: iload_1
       1: ifne          9
       4: aload_0
       5: invokestatic  #51                 // Method org/apache/dubbo/common/cache/FileCacheStore$Empty.getInstance:(Ljava/lang/String;)Lorg/apache/dubbo/common/cache/FileCacheStore$Empty;
       8: areturn
       9: invokestatic  #52                 // Method org/apache/dubbo/common/cache/FileCacheStore.newBuilder:()Lorg/apache/dubbo/common/cache/FileCacheStore$Builder;
      12: astore_2
      13: aload_2
      14: aload_0
      15: invokestatic  #53                 // Method tryFileLock:(Lorg/apache/dubbo/common/cache/FileCacheStore$Builder;Ljava/lang/String;)V
      18: new           #18                 // class java/io/File
      21: dup
      22: aload_0
      23: invokespecial #19                 // Method java/io/File."<init>":(Ljava/lang/String;)V
      26: astore_3
      27: aload_3
      28: invokevirtual #54                 // Method java/io/File.exists:()Z
      31: ifne          50
      34: aload_3
      35: invokevirtual #20                 // Method java/io/File.toPath:()Ljava/nio/file/Path;
      38: astore        4
      40: aload         4
      42: iconst_0
      43: anewarray     #22                 // class java/nio/file/attribute/FileAttribute
      46: invokestatic  #55                 // Method java/nio/file/Files.createFile:(Ljava/nio/file/Path;[Ljava/nio/file/attribute/FileAttribute;)Ljava/nio/file/Path;
      49: pop
      50: aload_2
      51: aload_0
      52: invokevirtual #56                 // Method org/apache/dubbo/common/cache/FileCacheStore$Builder.cacheFilePath:(Ljava/lang/String;)Lorg/apache/dubbo/common/cache/FileCacheStore$Builder;
      55: aload_3
      56: invokevirtual #57                 // Method org/apache/dubbo/common/cache/FileCacheStore$Builder.cacheFile:(Ljava/io/File;)Lorg/apache/dubbo/common/cache/FileCacheStore$Builder;
      59: pop
      60: aload_2
      61: invokevirtual #58                 // Method org/apache/dubbo/common/cache/FileCacheStore$Builder.build:()Lorg/apache/dubbo/common/cache/FileCacheStore;
      64: areturn
      65: astore_2
      66: getstatic     #25                 // Field logger:Lorg/apache/dubbo/common/logger/ErrorTypeAwareLogger;
      69: ldc           #26                 // String 0-3
      71: ldc           #27                 // String inaccessible of cache path
      73: ldc           #28                 // String
      75: new           #7                  // class java/lang/StringBuilder
      78: dup
      79: invokespecial #8                  // Method java/lang/StringBuilder."<init>":()V
      82: ldc           #60                 // String Failed to create file store cache. Local file cache will be disabled. Cache file name:
      84: invokevirtual #11                 // Method java/lang/StringBuilder.append:(Ljava/lang/String;)Ljava/lang/StringBuilder;
      87: aload_0
      88: invokevirtual #11                 // Method java/lang/StringBuilder.append:(Ljava/lang/String;)Ljava/lang/StringBuilder;
      91: invokevirtual #14                 // Method java/lang/StringBuilder.toString:()Ljava/lang/String;
      94: aload_2
      95: invokeinterface #61,  6           // InterfaceMethod org/apache/dubbo/common/logger/ErrorTypeAwareLogger.warn:(Ljava/lang/String;Ljava/lang/String;Ljava/lang/String;Ljava/lang/String;Ljava/lang/Throwable;)V
     100: aload_0
     101: invokestatic  #51                 // Method org/apache/dubbo/common/cache/FileCacheStore$Empty.getInstance:(Ljava/lang/String;)Lorg/apache/dubbo/common/cache/FileCacheStore$Empty;
     104: areturn
    Exception table:
       from    to  target type
           9    64    65   Class java/lang/Throwable

  private static void tryFileLock(org.apache.dubbo.common.cache.FileCacheStore$Builder, java.lang.String) throws org.apache.dubbo.common.cache.FileCacheStoreFactory$PathNotExclusiveException;
    Code:
       0: new           #18                 // class java/io/File
       3: dup
       4: new           #7                  // class java/lang/StringBuilder
       7: dup
       8: invokespecial #8                  // Method java/lang/StringBuilder."<init>":()V
      11: aload_1
      12: invokevirtual #11                 // Method java/lang/StringBuilder.append:(Ljava/lang/String;)Ljava/lang/StringBuilder;
      15: ldc           #62                 // String .lock
      17: invokevirtual #11                 // Method java/lang/StringBuilder.append:(Ljava/lang/String;)Ljava/lang/StringBuilder;
      20: invokevirtual #14                 // Method java/lang/StringBuilder.toString:()Ljava/lang/String;
      23: invokespecial #19                 // Method java/io/File."<init>":(Ljava/lang/String;)V
      26: astore_2
      27: aload_2
      28: invokevirtual #63                 // Method java/io/File.createNewFile:()Z
      31: pop
      32: aload_2
      33: invokevirtual #54                 // Method java/io/File.exists:()Z
      36: ifne          66
      39: new           #64                 // class java/lang/AssertionError
      42: dup
      43: new           #7                  // class java/lang/StringBuilder
      46: dup
      47: invokespecial #8                  // Method java/lang/StringBuilder."<init>":()V
      50: ldc           #65                 // String Failed to create lock file
      52: invokevirtual #11                 // Method java/lang/StringBuilder.append:(Ljava/lang/String;)Ljava/lang/StringBuilder;
      55: aload_2
      56: invokevirtual #32                 // Method java/lang/StringBuilder.append:(Ljava/lang/Object;)Ljava/lang/StringBuilder;
      59: invokevirtual #14                 // Method java/lang/StringBuilder.toString:()Ljava/lang/String;
      62: invokespecial #66                 // Method java/lang/AssertionError."<init>":(Ljava/lang/Object;)V
      65: athrow
      66: new           #67                 // class java/io/RandomAccessFile
      69: dup
      70: aload_2
      71: ldc           #68                 // String rw
      73: invokespecial #69                 // Method java/io/RandomAccessFile."<init>":(Ljava/io/File;Ljava/lang/String;)V
      76: invokevirtual #70                 // Method java/io/RandomAccessFile.getChannel:()Ljava/nio/channels/FileChannel;
      79: astore        4
      81: aload         4
      83: invokevirtual #71                 // Method java/nio/channels/FileChannel.tryLock:()Ljava/nio/channels/FileLock;
      86: astore_3
      87: goto          109
      90: astore        4
      92: aconst_null
      93: astore_3
      94: goto          109
      97: astore        4
      99: new           #31                 // class java/lang/RuntimeException
     102: dup
     103: aload         4
     105: invokespecial #73                 // Method java/lang/RuntimeException."<init>":(Ljava/lang/Throwable;)V
     108: athrow
     109: aload_3
     110: ifnonnull     140
     113: new           #74                 // class org/apache/dubbo/common/cache/FileCacheStoreFactory$PathNotExclusiveException
     116: dup
     117: new           #7                  // class java/lang/StringBuilder
     120: dup
     121: invokespecial #8                  // Method java/lang/StringBuilder."<init>":()V
     124: aload_1
     125: invokevirtual #11                 // Method java/lang/StringBuilder.append:(Ljava/lang/String;)Ljava/lang/StringBuilder;
     128: ldc           #75                 // String  is not exclusive. Maybe multiple Dubbo instances are using the same folder.
     130: invokevirtual #11                 // Method java/lang/StringBuilder.append:(Ljava/lang/String;)Ljava/lang/StringBuilder;
     133: invokevirtual #14                 // Method java/lang/StringBuilder.toString:()Ljava/lang/String;
     136: invokespecial #76                 // Method org/apache/dubbo/common/cache/FileCacheStoreFactory$PathNotExclusiveException."<init>":(Ljava/lang/String;)V
     139: athrow
     140: aload_2
     141: invokevirtual #77                 // Method java/io/File.deleteOnExit:()V
     144: aload_0
     145: aload_3
     146: invokevirtual #78                 // Method org/apache/dubbo/common/cache/FileCacheStore$Builder.directoryLock:(Ljava/nio/channels/FileLock;)Lorg/apache/dubbo/common/cache/FileCacheStore$Builder;
     149: aload_2
     150: invokevirtual #79                 // Method org/apache/dubbo/common/cache/FileCacheStore$Builder.lockFile:(Ljava/io/File;)Lorg/apache/dubbo/common/cache/FileCacheStore$Builder;
     153: pop
     154: return
    Exception table:
       from    to  target type
          27    87    90   Class java/nio/channels/OverlappingFileLockException
          27    87    97   Class java/io/IOException

  static void removeCache(java.lang.String);
    Code:
       0: getstatic     #37                 // Field cacheMap:Ljava/util/concurrent/ConcurrentMap;
       3: aload_0
       4: invokeinterface #80,  2           // InterfaceMethod java/util/concurrent/ConcurrentMap.remove:(Ljava/lang/Object;)Ljava/lang/Object;
       9: pop
      10: return

  static java.util.Map<java.lang.String, org.apache.dubbo.common.cache.FileCacheStore> getCacheMap();
    Code:
       0: getstatic     #37                 // Field cacheMap:Ljava/util/concurrent/ConcurrentMap;
       3: areturn

  private static org.apache.dubbo.common.cache.FileCacheStore lambda$getInstance$0(boolean, java.lang.String);
    Code:
       0: aload_1
       1: iload_0
       2: invokestatic  #81                 // Method getFile:(Ljava/lang/String;Z)Lorg/apache/dubbo/common/cache/FileCacheStore;
       5: areturn

  static {};
    Code:
       0: ldc           #35                 // class org/apache/dubbo/common/cache/FileCacheStoreFactory
       2: invokestatic  #82                 // Method org/apache/dubbo/common/logger/LoggerFactory.getErrorTypeAwareLogger:(Ljava/lang/Class;)Lorg/apache/dubbo/common/logger/ErrorTypeAwareLogger;
       5: putstatic     #25                 // Field logger:Lorg/apache/dubbo/common/logger/ErrorTypeAwareLogger;
       8: new           #83                 // class java/util/concurrent/ConcurrentHashMap
      11: dup
      12: invokespecial #84                 // Method java/util/concurrent/ConcurrentHashMap."<init>":()V
      15: putstatic     #37                 // Field cacheMap:Ljava/util/concurrent/ConcurrentMap;
      18: new           #85                 // class org/apache/dubbo/common/cache/FileCacheStoreFactory$1
      21: dup
      22: invokespecial #86                 // Method org/apache/dubbo/common/cache/FileCacheStoreFactory$1."<init>":()V
      25: invokestatic  #87                 // Method java/util/Collections.unmodifiableSet:(Ljava/util/Set;)Ljava/util/Set;
      28: putstatic     #43                 // Field LEGAL_CHARACTERS:Ljava/util/Set;
      31: return
}
