Compiled from "FileCacheStore.java"
class org.apache.dubbo.common.cache.FileCacheStore$LimitedLengthBufferedWriter extends java.io.BufferedWriter {
  private long remainSize;

  public org.apache.dubbo.common.cache.FileCacheStore$LimitedLengthBufferedWriter(java.io.Writer, long);
    Code:
       0: aload_0
       1: aload_1
       2: invokespecial #1                  // Method java/io/BufferedWriter."<init>":(Ljava/io/Writer;)V
       5: aload_0
       6: lload_2
       7: lconst_0
       8: lcmp
       9: ifne          18
      12: ldc2_w        #3                  // long 9223372036854775807l
      15: goto          19
      18: lload_2
      19: putfield      #5                  // Field remainSize:J
      22: return

  public void write(java.lang.String) throws java.io.IOException;
    Code:
       0: aload_0
       1: dup
       2: getfield      #5                  // Field remainSize:J
       5: aload_1
       6: getstatic     #6                  // Field java/nio/charset/StandardCharsets.UTF_8:Ljava/nio/charset/Charset;
       9: invokevirtual #7                  // Method java/lang/String.getBytes:(Ljava/nio/charset/Charset;)[B
      12: arraylength
      13: i2l
      14: lsub
      15: putfield      #5                  // Field remainSize:J
      18: aload_0
      19: getfield      #5                  // Field remainSize:J
      22: lconst_0
      23: lcmp
      24: ifge          28
      27: return
      28: aload_0
      29: aload_1
      30: invokespecial #8                  // Method java/io/BufferedWriter.write:(Ljava/lang/String;)V
      33: return

  public long getRemainSize();
    Code:
       0: aload_0
       1: getfield      #5                  // Field remainSize:J
       4: lreturn
}
