Compiled from "NettyRequestFacade.java"
public class org.apache.dubbo.rpc.protocol.rest.request.NettyRequestFacade extends org.apache.dubbo.rpc.protocol.rest.request.RequestFacade<io.netty.handler.codec.http.FullHttpRequest> {
  private io.netty.channel.ChannelHandlerContext context;

  public org.apache.dubbo.rpc.protocol.rest.request.NettyRequestFacade(java.lang.Object, io.netty.channel.ChannelHandlerContext);
    Code:
       0: aload_0
       1: aload_1
       2: checkcast     #1                  // class io/netty/handler/codec/http/FullHttpRequest
       5: invokespecial #2                  // Method org/apache/dubbo/rpc/protocol/rest/request/RequestFacade."<init>":(Ljava/lang/Object;)V
       8: aload_0
       9: aload_2
      10: putfield      #3                  // Field context:Lio/netty/channel/ChannelHandlerContext;
      13: return

  protected void initHeaders();
    Code:
       0: aload_0
       1: getfield      #4                  // Field request:Ljava/lang/Object;
       4: checkcast     #1                  // class io/netty/handler/codec/http/FullHttpRequest
       7: invokeinterface #5,  1            // InterfaceMethod io/netty/handler/codec/http/FullHttpRequest.headers:()Lio/netty/handler/codec/http/HttpHeaders;
      12: invokevirtual #6                  // Method io/netty/handler/codec/http/HttpHeaders.iterator:()Ljava/util/Iterator;
      15: astore_1
      16: aload_1
      17: invokeinterface #7,  1            // InterfaceMethod java/util/Iterator.hasNext:()Z
      22: ifeq          102
      25: aload_1
      26: invokeinterface #8,  1            // InterfaceMethod java/util/Iterator.next:()Ljava/lang/Object;
      31: checkcast     #9                  // class java/util/Map$Entry
      34: astore_2
      35: aload_2
      36: invokeinterface #10,  1           // InterfaceMethod java/util/Map$Entry.getKey:()Ljava/lang/Object;
      41: checkcast     #11                 // class java/lang/String
      44: astore_3
      45: aload_0
      46: getfield      #12                 // Field headers:Ljava/util/Map;
      49: aload_3
      50: invokeinterface #13,  2           // InterfaceMethod java/util/Map.get:(Ljava/lang/Object;)Ljava/lang/Object;
      55: checkcast     #14                 // class java/util/ArrayList
      58: astore        4
      60: aload         4
      62: ifnonnull     87
      65: new           #14                 // class java/util/ArrayList
      68: dup
      69: invokespecial #15                 // Method java/util/ArrayList."<init>":()V
      72: astore        4
      74: aload_0
      75: getfield      #12                 // Field headers:Ljava/util/Map;
      78: aload_3
      79: aload         4
      81: invokeinterface #16,  3           // InterfaceMethod java/util/Map.put:(Ljava/lang/Object;Ljava/lang/Object;)Ljava/lang/Object;
      86: pop
      87: aload         4
      89: aload_2
      90: invokeinterface #17,  1           // InterfaceMethod java/util/Map$Entry.getValue:()Ljava/lang/Object;
      95: invokevirtual #18                 // Method java/util/ArrayList.add:(Ljava/lang/Object;)Z
      98: pop
      99: goto          16
     102: return

  public java.lang.String getHeader(java.lang.String);
    Code:
       0: aload_0
       1: getfield      #12                 // Field headers:Ljava/util/Map;
       4: aload_1
       5: invokeinterface #13,  2           // InterfaceMethod java/util/Map.get:(Ljava/lang/Object;)Ljava/lang/Object;
      10: checkcast     #19                 // class java/util/List
      13: astore_2
      14: aload_2
      15: ifnull        27
      18: aload_2
      19: invokeinterface #20,  1           // InterfaceMethod java/util/List.isEmpty:()Z
      24: ifeq          29
      27: aconst_null
      28: areturn
      29: aload_2
      30: iconst_0
      31: invokeinterface #21,  2           // InterfaceMethod java/util/List.get:(I)Ljava/lang/Object;
      36: checkcast     #11                 // class java/lang/String
      39: areturn

  public java.util.Enumeration<java.lang.String> getHeaders(java.lang.String);
    Code:
       0: aload_0
       1: getfield      #12                 // Field headers:Ljava/util/Map;
       4: aload_1
       5: invokeinterface #13,  2           // InterfaceMethod java/util/Map.get:(Ljava/lang/Object;)Ljava/lang/Object;
      10: checkcast     #19                 // class java/util/List
      13: astore_2
      14: aload_2
      15: ifnonnull     26
      18: new           #14                 // class java/util/ArrayList
      21: dup
      22: invokespecial #15                 // Method java/util/ArrayList."<init>":()V
      25: astore_2
      26: aload_2
      27: invokeinterface #22,  1           // InterfaceMethod java/util/List.listIterator:()Ljava/util/ListIterator;
      32: astore_3
      33: new           #23                 // class org/apache/dubbo/rpc/protocol/rest/request/NettyRequestFacade$1
      36: dup
      37: aload_0
      38: aload_3
      39: invokespecial #24                 // Method org/apache/dubbo/rpc/protocol/rest/request/NettyRequestFacade$1."<init>":(Lorg/apache/dubbo/rpc/protocol/rest/request/NettyRequestFacade;Ljava/util/ListIterator;)V
      42: areturn

  public java.util.Enumeration<java.lang.String> getHeaderNames();
    Code:
       0: aload_0
       1: getfield      #12                 // Field headers:Ljava/util/Map;
       4: invokeinterface #25,  1           // InterfaceMethod java/util/Map.keySet:()Ljava/util/Set;
       9: invokeinterface #26,  1           // InterfaceMethod java/util/Set.iterator:()Ljava/util/Iterator;
      14: astore_1
      15: new           #27                 // class org/apache/dubbo/rpc/protocol/rest/request/NettyRequestFacade$2
      18: dup
      19: aload_0
      20: aload_1
      21: invokespecial #28                 // Method org/apache/dubbo/rpc/protocol/rest/request/NettyRequestFacade$2."<init>":(Lorg/apache/dubbo/rpc/protocol/rest/request/NettyRequestFacade;Ljava/util/Iterator;)V
      24: areturn

  public java.lang.String getMethod();
    Code:
       0: aload_0
       1: getfield      #4                  // Field request:Ljava/lang/Object;
       4: checkcast     #1                  // class io/netty/handler/codec/http/FullHttpRequest
       7: invokeinterface #29,  1           // InterfaceMethod io/netty/handler/codec/http/FullHttpRequest.method:()Lio/netty/handler/codec/http/HttpMethod;
      12: invokevirtual #30                 // Method io/netty/handler/codec/http/HttpMethod.name:()Ljava/lang/String;
      15: areturn

  public java.lang.String getPath();
    Code:
       0: aload_0
       1: getfield      #31                 // Field path:Ljava/lang/String;
       4: areturn

  public java.lang.String getContextPath();
    Code:
       0: aconst_null
       1: areturn

  public java.lang.String getRequestURI();
    Code:
       0: aload_0
       1: getfield      #4                  // Field request:Ljava/lang/Object;
       4: checkcast     #1                  // class io/netty/handler/codec/http/FullHttpRequest
       7: invokeinterface #32,  1           // InterfaceMethod io/netty/handler/codec/http/FullHttpRequest.uri:()Ljava/lang/String;
      12: areturn

  public java.lang.String getParameter(java.lang.String);
    Code:
       0: aload_0
       1: getfield      #33                 // Field parameters:Ljava/util/Map;
       4: aload_1
       5: invokeinterface #13,  2           // InterfaceMethod java/util/Map.get:(Ljava/lang/Object;)Ljava/lang/Object;
      10: checkcast     #14                 // class java/util/ArrayList
      13: astore_2
      14: aconst_null
      15: astore_3
      16: aload_2
      17: ifnull        36
      20: aload_2
      21: invokevirtual #34                 // Method java/util/ArrayList.isEmpty:()Z
      24: ifne          36
      27: aload_2
      28: iconst_0
      29: invokevirtual #35                 // Method java/util/ArrayList.get:(I)Ljava/lang/Object;
      32: checkcast     #11                 // class java/lang/String
      35: astore_3
      36: aload_3
      37: areturn

  public java.util.Enumeration<java.lang.String> getParameterNames();
    Code:
       0: aload_0
       1: getfield      #33                 // Field parameters:Ljava/util/Map;
       4: invokeinterface #25,  1           // InterfaceMethod java/util/Map.keySet:()Ljava/util/Set;
       9: invokeinterface #26,  1           // InterfaceMethod java/util/Set.iterator:()Ljava/util/Iterator;
      14: astore_1
      15: new           #36                 // class org/apache/dubbo/rpc/protocol/rest/request/NettyRequestFacade$3
      18: dup
      19: aload_0
      20: aload_1
      21: invokespecial #37                 // Method org/apache/dubbo/rpc/protocol/rest/request/NettyRequestFacade$3."<init>":(Lorg/apache/dubbo/rpc/protocol/rest/request/NettyRequestFacade;Ljava/util/Iterator;)V
      24: areturn

  public java.lang.String[] getParameterValues(java.lang.String);
    Code:
       0: aload_0
       1: getfield      #33                 // Field parameters:Ljava/util/Map;
       4: aload_1
       5: invokeinterface #38,  2           // InterfaceMethod java/util/Map.containsKey:(Ljava/lang/Object;)Z
      10: ifne          15
      13: aconst_null
      14: areturn
      15: aload_0
      16: getfield      #33                 // Field parameters:Ljava/util/Map;
      19: aload_1
      20: invokeinterface #13,  2           // InterfaceMethod java/util/Map.get:(Ljava/lang/Object;)Ljava/lang/Object;
      25: checkcast     #14                 // class java/util/ArrayList
      28: iconst_0
      29: anewarray     #11                 // class java/lang/String
      32: invokevirtual #39                 // Method java/util/ArrayList.toArray:([Ljava/lang/Object;)[Ljava/lang/Object;
      35: checkcast     #40                 // class "[Ljava/lang/String;"
      38: areturn

  public java.util.Map<java.lang.String, java.lang.String[]> getParameterMap();
    Code:
       0: new           #41                 // class java/util/HashMap
       3: dup
       4: invokespecial #42                 // Method java/util/HashMap."<init>":()V
       7: astore_1
       8: aload_0
       9: getfield      #33                 // Field parameters:Ljava/util/Map;
      12: invokeinterface #43,  1           // InterfaceMethod java/util/Map.entrySet:()Ljava/util/Set;
      17: aload_1
      18: invokedynamic #44,  0             // InvokeDynamic #0:accept:(Ljava/util/HashMap;)Ljava/util/function/Consumer;
      23: invokeinterface #45,  2           // InterfaceMethod java/util/Set.forEach:(Ljava/util/function/Consumer;)V
      28: aload_1
      29: areturn

  public java.lang.String getRemoteAddr();
    Code:
       0: aload_0
       1: invokespecial #46                 // Method getChannel:()Lio/netty/channel/socket/nio/NioSocketChannel;
       4: invokevirtual #47                 // Method io/netty/channel/socket/nio/NioSocketChannel.remoteAddress:()Ljava/net/InetSocketAddress;
       7: invokevirtual #48                 // Method java/net/InetSocketAddress.getHostString:()Ljava/lang/String;
      10: areturn

  public java.lang.String getRemoteHost();
    Code:
       0: new           #49                 // class java/lang/StringBuilder
       3: dup
       4: invokespecial #50                 // Method java/lang/StringBuilder."<init>":()V
       7: aload_0
       8: invokevirtual #51                 // Method getRemoteAddr:()Ljava/lang/String;
      11: invokevirtual #52                 // Method java/lang/StringBuilder.append:(Ljava/lang/String;)Ljava/lang/StringBuilder;
      14: ldc           #53                 // String :
      16: invokevirtual #52                 // Method java/lang/StringBuilder.append:(Ljava/lang/String;)Ljava/lang/StringBuilder;
      19: aload_0
      20: invokevirtual #54                 // Method getRemotePort:()I
      23: invokevirtual #55                 // Method java/lang/StringBuilder.append:(I)Ljava/lang/StringBuilder;
      26: invokevirtual #56                 // Method java/lang/StringBuilder.toString:()Ljava/lang/String;
      29: areturn

  public int getRemotePort();
    Code:
       0: aload_0
       1: invokespecial #46                 // Method getChannel:()Lio/netty/channel/socket/nio/NioSocketChannel;
       4: invokevirtual #47                 // Method io/netty/channel/socket/nio/NioSocketChannel.remoteAddress:()Ljava/net/InetSocketAddress;
       7: invokevirtual #57                 // Method java/net/InetSocketAddress.getPort:()I
      10: ireturn

  public java.lang.String getLocalAddr();
    Code:
       0: aload_0
       1: invokespecial #46                 // Method getChannel:()Lio/netty/channel/socket/nio/NioSocketChannel;
       4: invokevirtual #58                 // Method io/netty/channel/socket/nio/NioSocketChannel.localAddress:()Ljava/net/InetSocketAddress;
       7: invokevirtual #48                 // Method java/net/InetSocketAddress.getHostString:()Ljava/lang/String;
      10: areturn

  public java.lang.String getLocalHost();
    Code:
       0: new           #49                 // class java/lang/StringBuilder
       3: dup
       4: invokespecial #50                 // Method java/lang/StringBuilder."<init>":()V
       7: aload_0
       8: invokevirtual #51                 // Method getRemoteAddr:()Ljava/lang/String;
      11: invokevirtual #52                 // Method java/lang/StringBuilder.append:(Ljava/lang/String;)Ljava/lang/StringBuilder;
      14: ldc           #53                 // String :
      16: invokevirtual #52                 // Method java/lang/StringBuilder.append:(Ljava/lang/String;)Ljava/lang/StringBuilder;
      19: aload_0
      20: invokevirtual #59                 // Method getLocalPort:()I
      23: invokevirtual #55                 // Method java/lang/StringBuilder.append:(I)Ljava/lang/StringBuilder;
      26: invokevirtual #56                 // Method java/lang/StringBuilder.toString:()Ljava/lang/String;
      29: areturn

  private io.netty.channel.socket.nio.NioSocketChannel getChannel();
    Code:
       0: aload_0
       1: getfield      #3                  // Field context:Lio/netty/channel/ChannelHandlerContext;
       4: invokeinterface #60,  1           // InterfaceMethod io/netty/channel/ChannelHandlerContext.channel:()Lio/netty/channel/Channel;
       9: checkcast     #61                 // class io/netty/channel/socket/nio/NioSocketChannel
      12: areturn

  public int getLocalPort();
    Code:
       0: aload_0
       1: invokespecial #46                 // Method getChannel:()Lio/netty/channel/socket/nio/NioSocketChannel;
       4: invokevirtual #58                 // Method io/netty/channel/socket/nio/NioSocketChannel.localAddress:()Ljava/net/InetSocketAddress;
       7: invokevirtual #57                 // Method java/net/InetSocketAddress.getPort:()I
      10: ireturn

  public byte[] getInputStream() throws java.io.IOException;
    Code:
       0: aload_0
       1: getfield      #62                 // Field body:[B
       4: areturn

  protected void parseBody();
    Code:
       0: aload_0
       1: getfield      #4                  // Field request:Ljava/lang/Object;
       4: checkcast     #63                 // class io/netty/handler/codec/http/HttpContent
       7: invokeinterface #64,  1           // InterfaceMethod io/netty/handler/codec/http/HttpContent.content:()Lio/netty/buffer/ByteBuf;
      12: astore_1
      13: aload_1
      14: invokevirtual #65                 // Method io/netty/buffer/ByteBuf.readableBytes:()I
      17: ifle          39
      20: aload_0
      21: new           #66                 // class io/netty/buffer/ByteBufInputStream
      24: dup
      25: aload_1
      26: invokespecial #67                 // Method io/netty/buffer/ByteBufInputStream."<init>":(Lio/netty/buffer/ByteBuf;)V
      29: invokestatic  #68                 // Method org/apache/dubbo/common/utils/IOUtils.toByteArray:(Ljava/io/InputStream;)[B
      32: putfield      #62                 // Field body:[B
      35: goto          39
      38: astore_2
      39: return
    Exception table:
       from    to  target type
          20    35    38   Class java/io/IOException

  private static void lambda$getParameterMap$0(java.util.HashMap, java.util.Map$Entry);
    Code:
       0: aload_0
       1: aload_1
       2: invokeinterface #10,  1           // InterfaceMethod java/util/Map$Entry.getKey:()Ljava/lang/Object;
       7: aload_1
       8: invokeinterface #17,  1           // InterfaceMethod java/util/Map$Entry.getValue:()Ljava/lang/Object;
      13: checkcast     #14                 // class java/util/ArrayList
      16: iconst_0
      17: anewarray     #11                 // class java/lang/String
      20: invokevirtual #39                 // Method java/util/ArrayList.toArray:([Ljava/lang/Object;)[Ljava/lang/Object;
      23: invokevirtual #70                 // Method java/util/HashMap.put:(Ljava/lang/Object;Ljava/lang/Object;)Ljava/lang/Object;
      26: pop
      27: return
}
