Compiled from "NettyRequestFacade.java"
class org.apache.dubbo.rpc.protocol.rest.request.NettyRequestFacade$1 implements java.util.Enumeration<java.lang.String> {
  final java.util.ListIterator val$stringListIterator;

  final org.apache.dubbo.rpc.protocol.rest.request.NettyRequestFacade this$0;

  org.apache.dubbo.rpc.protocol.rest.request.NettyRequestFacade$1(org.apache.dubbo.rpc.protocol.rest.request.NettyRequestFacade, java.util.ListIterator);
    Code:
       0: aload_0
       1: aload_1
       2: putfield      #1                  // Field this$0:Lorg/apache/dubbo/rpc/protocol/rest/request/NettyRequestFacade;
       5: aload_0
       6: aload_2
       7: putfield      #2                  // Field val$stringListIterator:Ljava/util/ListIterator;
      10: aload_0
      11: invokespecial #3                  // Method java/lang/Object."<init>":()V
      14: return

  public boolean hasMoreElements();
    Code:
       0: aload_0
       1: getfield      #2                  // Field val$stringListIterator:Ljava/util/ListIterator;
       4: invokeinterface #4,  1            // InterfaceMethod java/util/ListIterator.hasNext:()Z
       9: ireturn

  public java.lang.String nextElement();
    Code:
       0: aload_0
       1: getfield      #2                  // Field val$stringListIterator:Ljava/util/ListIterator;
       4: invokeinterface #5,  1            // InterfaceMethod java/util/ListIterator.next:()Ljava/lang/Object;
       9: checkcast     #6                  // class java/lang/String
      12: areturn

  public java.lang.Object nextElement();
    Code:
       0: aload_0
       1: invokevirtual #7                  // Method nextElement:()Ljava/lang/String;
       4: areturn
}
