Compiled from "Slf4jLoggerAdapter.java"
public class org.apache.dubbo.common.logger.slf4j.Slf4jLoggerAdapter implements org.apache.dubbo.common.logger.LoggerAdapter {
  public static final java.lang.String NAME;

  private org.apache.dubbo.common.logger.Level level;

  private java.io.File file;

  public org.apache.dubbo.common.logger.slf4j.Slf4jLoggerAdapter();
    Code:
       0: aload_0
       1: invokespecial #1                  // Method java/lang/Object."<init>":()V
       4: return

  public org.apache.dubbo.common.logger.Logger getLogger(java.lang.String);
    Code:
       0: new           #2                  // class org/apache/dubbo/common/logger/slf4j/Slf4jLogger
       3: dup
       4: aload_1
       5: invokestatic  #3                  // Method org/slf4j/LoggerFactory.getLogger:(Ljava/lang/String;)Lorg/slf4j/Logger;
       8: invokespecial #4                  // Method org/apache/dubbo/common/logger/slf4j/Slf4jLogger."<init>":(Lorg/slf4j/Logger;)V
      11: areturn

  public org.apache.dubbo.common.logger.Logger getLogger(java.lang.Class<?>);
    Code:
       0: new           #2                  // class org/apache/dubbo/common/logger/slf4j/Slf4jLogger
       3: dup
       4: aload_1
       5: invokestatic  #5                  // Method org/slf4j/LoggerFactory.getLogger:(Ljava/lang/Class;)Lorg/slf4j/Logger;
       8: invokespecial #4                  // Method org/apache/dubbo/common/logger/slf4j/Slf4jLogger."<init>":(Lorg/slf4j/Logger;)V
      11: areturn

  public org.apache.dubbo.common.logger.Level getLevel();
    Code:
       0: aload_0
       1: getfield      #6                  // Field level:Lorg/apache/dubbo/common/logger/Level;
       4: areturn

  public void setLevel(org.apache.dubbo.common.logger.Level);
    Code:
       0: aload_0
       1: aload_1
       2: putfield      #6                  // Field level:Lorg/apache/dubbo/common/logger/Level;
       5: return

  public java.io.File getFile();
    Code:
       0: aload_0
       1: getfield      #7                  // Field file:Ljava/io/File;
       4: areturn

  public void setFile(java.io.File);
    Code:
       0: aload_0
       1: aload_1
       2: putfield      #7                  // Field file:Ljava/io/File;
       5: return

  public boolean isConfigured();
    Code:
       0: ldc           #8                  // String org.slf4j.impl.StaticLoggerBinder
       2: invokestatic  #9                  // Method org/apache/dubbo/common/utils/ClassUtils.forName:(Ljava/lang/String;)Ljava/lang/Class;
       5: pop
       6: iconst_1
       7: ireturn
       8: astore_1
       9: iconst_0
      10: ireturn
    Exception table:
       from    to  target type
           0     7     8   Class java/lang/ClassNotFoundException
}
