Compiled from "Slf4jLogger.java"
public class org.apache.dubbo.common.logger.slf4j.Slf4jLogger implements org.apache.dubbo.common.logger.Logger {
  private static final java.lang.String FQCN;

  private final org.slf4j.Logger logger;

  private final org.slf4j.spi.LocationAwareLogger locationAwareLogger;

  public org.apache.dubbo.common.logger.slf4j.Slf4jLogger(org.slf4j.Logger);
    Code:
       0: aload_0
       1: invokespecial #1                  // Method java/lang/Object."<init>":()V
       4: aload_1
       5: instanceof    #2                  // class org/slf4j/spi/LocationAwareLogger
       8: ifeq          22
      11: aload_0
      12: aload_1
      13: checkcast     #2                  // class org/slf4j/spi/LocationAwareLogger
      16: putfield      #3                  // Field locationAwareLogger:Lorg/slf4j/spi/LocationAwareLogger;
      19: goto          27
      22: aload_0
      23: aconst_null
      24: putfield      #3                  // Field locationAwareLogger:Lorg/slf4j/spi/LocationAwareLogger;
      27: aload_0
      28: aload_1
      29: putfield      #4                  // Field logger:Lorg/slf4j/Logger;
      32: return

  public void trace(java.lang.String);
    Code:
       0: aload_0
       1: getfield      #3                  // Field locationAwareLogger:Lorg/slf4j/spi/LocationAwareLogger;
       4: ifnull        25
       7: aload_0
       8: getfield      #3                  // Field locationAwareLogger:Lorg/slf4j/spi/LocationAwareLogger;
      11: aconst_null
      12: getstatic     #5                  // Field FQCN:Ljava/lang/String;
      15: iconst_0
      16: aload_1
      17: aconst_null
      18: aconst_null
      19: invokeinterface #6,  7            // InterfaceMethod org/slf4j/spi/LocationAwareLogger.log:(Lorg/slf4j/Marker;Ljava/lang/String;ILjava/lang/String;[Ljava/lang/Object;Ljava/lang/Throwable;)V
      24: return
      25: aload_0
      26: getfield      #4                  // Field logger:Lorg/slf4j/Logger;
      29: aload_1
      30: invokeinterface #7,  2            // InterfaceMethod org/slf4j/Logger.trace:(Ljava/lang/String;)V
      35: return

  public void trace(java.lang.Throwable);
    Code:
       0: aload_0
       1: getfield      #3                  // Field locationAwareLogger:Lorg/slf4j/spi/LocationAwareLogger;
       4: ifnull        28
       7: aload_0
       8: getfield      #3                  // Field locationAwareLogger:Lorg/slf4j/spi/LocationAwareLogger;
      11: aconst_null
      12: getstatic     #5                  // Field FQCN:Ljava/lang/String;
      15: iconst_0
      16: aload_1
      17: invokevirtual #8                  // Method java/lang/Throwable.getMessage:()Ljava/lang/String;
      20: aconst_null
      21: aload_1
      22: invokeinterface #6,  7            // InterfaceMethod org/slf4j/spi/LocationAwareLogger.log:(Lorg/slf4j/Marker;Ljava/lang/String;ILjava/lang/String;[Ljava/lang/Object;Ljava/lang/Throwable;)V
      27: return
      28: aload_0
      29: getfield      #4                  // Field logger:Lorg/slf4j/Logger;
      32: aload_1
      33: invokevirtual #8                  // Method java/lang/Throwable.getMessage:()Ljava/lang/String;
      36: aload_1
      37: invokeinterface #9,  3            // InterfaceMethod org/slf4j/Logger.trace:(Ljava/lang/String;Ljava/lang/Throwable;)V
      42: return

  public void trace(java.lang.String, java.lang.Throwable);
    Code:
       0: aload_0
       1: getfield      #3                  // Field locationAwareLogger:Lorg/slf4j/spi/LocationAwareLogger;
       4: ifnull        25
       7: aload_0
       8: getfield      #3                  // Field locationAwareLogger:Lorg/slf4j/spi/LocationAwareLogger;
      11: aconst_null
      12: getstatic     #5                  // Field FQCN:Ljava/lang/String;
      15: iconst_0
      16: aload_1
      17: aconst_null
      18: aload_2
      19: invokeinterface #6,  7            // InterfaceMethod org/slf4j/spi/LocationAwareLogger.log:(Lorg/slf4j/Marker;Ljava/lang/String;ILjava/lang/String;[Ljava/lang/Object;Ljava/lang/Throwable;)V
      24: return
      25: aload_0
      26: getfield      #4                  // Field logger:Lorg/slf4j/Logger;
      29: aload_1
      30: aload_2
      31: invokeinterface #9,  3            // InterfaceMethod org/slf4j/Logger.trace:(Ljava/lang/String;Ljava/lang/Throwable;)V
      36: return

  public void debug(java.lang.String);
    Code:
       0: aload_0
       1: getfield      #3                  // Field locationAwareLogger:Lorg/slf4j/spi/LocationAwareLogger;
       4: ifnull        26
       7: aload_0
       8: getfield      #3                  // Field locationAwareLogger:Lorg/slf4j/spi/LocationAwareLogger;
      11: aconst_null
      12: getstatic     #5                  // Field FQCN:Ljava/lang/String;
      15: bipush        10
      17: aload_1
      18: aconst_null
      19: aconst_null
      20: invokeinterface #6,  7            // InterfaceMethod org/slf4j/spi/LocationAwareLogger.log:(Lorg/slf4j/Marker;Ljava/lang/String;ILjava/lang/String;[Ljava/lang/Object;Ljava/lang/Throwable;)V
      25: return
      26: aload_0
      27: getfield      #4                  // Field logger:Lorg/slf4j/Logger;
      30: aload_1
      31: invokeinterface #10,  2           // InterfaceMethod org/slf4j/Logger.debug:(Ljava/lang/String;)V
      36: return

  public void debug(java.lang.Throwable);
    Code:
       0: aload_0
       1: getfield      #3                  // Field locationAwareLogger:Lorg/slf4j/spi/LocationAwareLogger;
       4: ifnull        29
       7: aload_0
       8: getfield      #3                  // Field locationAwareLogger:Lorg/slf4j/spi/LocationAwareLogger;
      11: aconst_null
      12: getstatic     #5                  // Field FQCN:Ljava/lang/String;
      15: bipush        10
      17: aload_1
      18: invokevirtual #8                  // Method java/lang/Throwable.getMessage:()Ljava/lang/String;
      21: aconst_null
      22: aload_1
      23: invokeinterface #6,  7            // InterfaceMethod org/slf4j/spi/LocationAwareLogger.log:(Lorg/slf4j/Marker;Ljava/lang/String;ILjava/lang/String;[Ljava/lang/Object;Ljava/lang/Throwable;)V
      28: return
      29: aload_0
      30: getfield      #4                  // Field logger:Lorg/slf4j/Logger;
      33: aload_1
      34: invokevirtual #8                  // Method java/lang/Throwable.getMessage:()Ljava/lang/String;
      37: aload_1
      38: invokeinterface #11,  3           // InterfaceMethod org/slf4j/Logger.debug:(Ljava/lang/String;Ljava/lang/Throwable;)V
      43: return

  public void debug(java.lang.String, java.lang.Throwable);
    Code:
       0: aload_0
       1: getfield      #3                  // Field locationAwareLogger:Lorg/slf4j/spi/LocationAwareLogger;
       4: ifnull        26
       7: aload_0
       8: getfield      #3                  // Field locationAwareLogger:Lorg/slf4j/spi/LocationAwareLogger;
      11: aconst_null
      12: getstatic     #5                  // Field FQCN:Ljava/lang/String;
      15: bipush        10
      17: aload_1
      18: aconst_null
      19: aload_2
      20: invokeinterface #6,  7            // InterfaceMethod org/slf4j/spi/LocationAwareLogger.log:(Lorg/slf4j/Marker;Ljava/lang/String;ILjava/lang/String;[Ljava/lang/Object;Ljava/lang/Throwable;)V
      25: return
      26: aload_0
      27: getfield      #4                  // Field logger:Lorg/slf4j/Logger;
      30: aload_1
      31: aload_2
      32: invokeinterface #11,  3           // InterfaceMethod org/slf4j/Logger.debug:(Ljava/lang/String;Ljava/lang/Throwable;)V
      37: return

  public void info(java.lang.String);
    Code:
       0: aload_0
       1: getfield      #3                  // Field locationAwareLogger:Lorg/slf4j/spi/LocationAwareLogger;
       4: ifnull        26
       7: aload_0
       8: getfield      #3                  // Field locationAwareLogger:Lorg/slf4j/spi/LocationAwareLogger;
      11: aconst_null
      12: getstatic     #5                  // Field FQCN:Ljava/lang/String;
      15: bipush        20
      17: aload_1
      18: aconst_null
      19: aconst_null
      20: invokeinterface #6,  7            // InterfaceMethod org/slf4j/spi/LocationAwareLogger.log:(Lorg/slf4j/Marker;Ljava/lang/String;ILjava/lang/String;[Ljava/lang/Object;Ljava/lang/Throwable;)V
      25: return
      26: aload_0
      27: getfield      #4                  // Field logger:Lorg/slf4j/Logger;
      30: aload_1
      31: invokeinterface #12,  2           // InterfaceMethod org/slf4j/Logger.info:(Ljava/lang/String;)V
      36: return

  public void info(java.lang.Throwable);
    Code:
       0: aload_0
       1: getfield      #3                  // Field locationAwareLogger:Lorg/slf4j/spi/LocationAwareLogger;
       4: ifnull        29
       7: aload_0
       8: getfield      #3                  // Field locationAwareLogger:Lorg/slf4j/spi/LocationAwareLogger;
      11: aconst_null
      12: getstatic     #5                  // Field FQCN:Ljava/lang/String;
      15: bipush        20
      17: aload_1
      18: invokevirtual #8                  // Method java/lang/Throwable.getMessage:()Ljava/lang/String;
      21: aconst_null
      22: aload_1
      23: invokeinterface #6,  7            // InterfaceMethod org/slf4j/spi/LocationAwareLogger.log:(Lorg/slf4j/Marker;Ljava/lang/String;ILjava/lang/String;[Ljava/lang/Object;Ljava/lang/Throwable;)V
      28: return
      29: aload_0
      30: getfield      #4                  // Field logger:Lorg/slf4j/Logger;
      33: aload_1
      34: invokevirtual #8                  // Method java/lang/Throwable.getMessage:()Ljava/lang/String;
      37: aload_1
      38: invokeinterface #13,  3           // InterfaceMethod org/slf4j/Logger.info:(Ljava/lang/String;Ljava/lang/Throwable;)V
      43: return

  public void info(java.lang.String, java.lang.Throwable);
    Code:
       0: aload_0
       1: getfield      #3                  // Field locationAwareLogger:Lorg/slf4j/spi/LocationAwareLogger;
       4: ifnull        26
       7: aload_0
       8: getfield      #3                  // Field locationAwareLogger:Lorg/slf4j/spi/LocationAwareLogger;
      11: aconst_null
      12: getstatic     #5                  // Field FQCN:Ljava/lang/String;
      15: bipush        20
      17: aload_1
      18: aconst_null
      19: aload_2
      20: invokeinterface #6,  7            // InterfaceMethod org/slf4j/spi/LocationAwareLogger.log:(Lorg/slf4j/Marker;Ljava/lang/String;ILjava/lang/String;[Ljava/lang/Object;Ljava/lang/Throwable;)V
      25: return
      26: aload_0
      27: getfield      #4                  // Field logger:Lorg/slf4j/Logger;
      30: aload_1
      31: aload_2
      32: invokeinterface #13,  3           // InterfaceMethod org/slf4j/Logger.info:(Ljava/lang/String;Ljava/lang/Throwable;)V
      37: return

  public void warn(java.lang.String);
    Code:
       0: aload_0
       1: getfield      #3                  // Field locationAwareLogger:Lorg/slf4j/spi/LocationAwareLogger;
       4: ifnull        26
       7: aload_0
       8: getfield      #3                  // Field locationAwareLogger:Lorg/slf4j/spi/LocationAwareLogger;
      11: aconst_null
      12: getstatic     #5                  // Field FQCN:Ljava/lang/String;
      15: bipush        30
      17: aload_1
      18: aconst_null
      19: aconst_null
      20: invokeinterface #6,  7            // InterfaceMethod org/slf4j/spi/LocationAwareLogger.log:(Lorg/slf4j/Marker;Ljava/lang/String;ILjava/lang/String;[Ljava/lang/Object;Ljava/lang/Throwable;)V
      25: return
      26: aload_0
      27: getfield      #4                  // Field logger:Lorg/slf4j/Logger;
      30: aload_1
      31: invokeinterface #14,  2           // InterfaceMethod org/slf4j/Logger.warn:(Ljava/lang/String;)V
      36: return

  public void warn(java.lang.Throwable);
    Code:
       0: aload_0
       1: getfield      #3                  // Field locationAwareLogger:Lorg/slf4j/spi/LocationAwareLogger;
       4: ifnull        29
       7: aload_0
       8: getfield      #3                  // Field locationAwareLogger:Lorg/slf4j/spi/LocationAwareLogger;
      11: aconst_null
      12: getstatic     #5                  // Field FQCN:Ljava/lang/String;
      15: bipush        30
      17: aload_1
      18: invokevirtual #8                  // Method java/lang/Throwable.getMessage:()Ljava/lang/String;
      21: aconst_null
      22: aload_1
      23: invokeinterface #6,  7            // InterfaceMethod org/slf4j/spi/LocationAwareLogger.log:(Lorg/slf4j/Marker;Ljava/lang/String;ILjava/lang/String;[Ljava/lang/Object;Ljava/lang/Throwable;)V
      28: return
      29: aload_0
      30: getfield      #4                  // Field logger:Lorg/slf4j/Logger;
      33: aload_1
      34: invokevirtual #8                  // Method java/lang/Throwable.getMessage:()Ljava/lang/String;
      37: aload_1
      38: invokeinterface #15,  3           // InterfaceMethod org/slf4j/Logger.warn:(Ljava/lang/String;Ljava/lang/Throwable;)V
      43: return

  public void warn(java.lang.String, java.lang.Throwable);
    Code:
       0: aload_0
       1: getfield      #3                  // Field locationAwareLogger:Lorg/slf4j/spi/LocationAwareLogger;
       4: ifnull        26
       7: aload_0
       8: getfield      #3                  // Field locationAwareLogger:Lorg/slf4j/spi/LocationAwareLogger;
      11: aconst_null
      12: getstatic     #5                  // Field FQCN:Ljava/lang/String;
      15: bipush        30
      17: aload_1
      18: aconst_null
      19: aload_2
      20: invokeinterface #6,  7            // InterfaceMethod org/slf4j/spi/LocationAwareLogger.log:(Lorg/slf4j/Marker;Ljava/lang/String;ILjava/lang/String;[Ljava/lang/Object;Ljava/lang/Throwable;)V
      25: return
      26: aload_0
      27: getfield      #4                  // Field logger:Lorg/slf4j/Logger;
      30: aload_1
      31: aload_2
      32: invokeinterface #15,  3           // InterfaceMethod org/slf4j/Logger.warn:(Ljava/lang/String;Ljava/lang/Throwable;)V
      37: return

  public void error(java.lang.String);
    Code:
       0: aload_0
       1: getfield      #3                  // Field locationAwareLogger:Lorg/slf4j/spi/LocationAwareLogger;
       4: ifnull        26
       7: aload_0
       8: getfield      #3                  // Field locationAwareLogger:Lorg/slf4j/spi/LocationAwareLogger;
      11: aconst_null
      12: getstatic     #5                  // Field FQCN:Ljava/lang/String;
      15: bipush        40
      17: aload_1
      18: aconst_null
      19: aconst_null
      20: invokeinterface #6,  7            // InterfaceMethod org/slf4j/spi/LocationAwareLogger.log:(Lorg/slf4j/Marker;Ljava/lang/String;ILjava/lang/String;[Ljava/lang/Object;Ljava/lang/Throwable;)V
      25: return
      26: aload_0
      27: getfield      #4                  // Field logger:Lorg/slf4j/Logger;
      30: aload_1
      31: invokeinterface #16,  2           // InterfaceMethod org/slf4j/Logger.error:(Ljava/lang/String;)V
      36: return

  public void error(java.lang.Throwable);
    Code:
       0: aload_0
       1: getfield      #3                  // Field locationAwareLogger:Lorg/slf4j/spi/LocationAwareLogger;
       4: ifnull        29
       7: aload_0
       8: getfield      #3                  // Field locationAwareLogger:Lorg/slf4j/spi/LocationAwareLogger;
      11: aconst_null
      12: getstatic     #5                  // Field FQCN:Ljava/lang/String;
      15: bipush        40
      17: aload_1
      18: invokevirtual #8                  // Method java/lang/Throwable.getMessage:()Ljava/lang/String;
      21: aconst_null
      22: aload_1
      23: invokeinterface #6,  7            // InterfaceMethod org/slf4j/spi/LocationAwareLogger.log:(Lorg/slf4j/Marker;Ljava/lang/String;ILjava/lang/String;[Ljava/lang/Object;Ljava/lang/Throwable;)V
      28: return
      29: aload_0
      30: getfield      #4                  // Field logger:Lorg/slf4j/Logger;
      33: aload_1
      34: invokevirtual #8                  // Method java/lang/Throwable.getMessage:()Ljava/lang/String;
      37: aload_1
      38: invokeinterface #17,  3           // InterfaceMethod org/slf4j/Logger.error:(Ljava/lang/String;Ljava/lang/Throwable;)V
      43: return

  public void error(java.lang.String, java.lang.Throwable);
    Code:
       0: aload_0
       1: getfield      #3                  // Field locationAwareLogger:Lorg/slf4j/spi/LocationAwareLogger;
       4: ifnull        26
       7: aload_0
       8: getfield      #3                  // Field locationAwareLogger:Lorg/slf4j/spi/LocationAwareLogger;
      11: aconst_null
      12: getstatic     #5                  // Field FQCN:Ljava/lang/String;
      15: bipush        40
      17: aload_1
      18: aconst_null
      19: aload_2
      20: invokeinterface #6,  7            // InterfaceMethod org/slf4j/spi/LocationAwareLogger.log:(Lorg/slf4j/Marker;Ljava/lang/String;ILjava/lang/String;[Ljava/lang/Object;Ljava/lang/Throwable;)V
      25: return
      26: aload_0
      27: getfield      #4                  // Field logger:Lorg/slf4j/Logger;
      30: aload_1
      31: aload_2
      32: invokeinterface #17,  3           // InterfaceMethod org/slf4j/Logger.error:(Ljava/lang/String;Ljava/lang/Throwable;)V
      37: return

  public boolean isTraceEnabled();
    Code:
       0: aload_0
       1: getfield      #4                  // Field logger:Lorg/slf4j/Logger;
       4: invokeinterface #18,  1           // InterfaceMethod org/slf4j/Logger.isTraceEnabled:()Z
       9: ireturn

  public boolean isDebugEnabled();
    Code:
       0: aload_0
       1: getfield      #4                  // Field logger:Lorg/slf4j/Logger;
       4: invokeinterface #19,  1           // InterfaceMethod org/slf4j/Logger.isDebugEnabled:()Z
       9: ireturn

  public boolean isInfoEnabled();
    Code:
       0: aload_0
       1: getfield      #4                  // Field logger:Lorg/slf4j/Logger;
       4: invokeinterface #20,  1           // InterfaceMethod org/slf4j/Logger.isInfoEnabled:()Z
       9: ireturn

  public boolean isWarnEnabled();
    Code:
       0: aload_0
       1: getfield      #4                  // Field logger:Lorg/slf4j/Logger;
       4: invokeinterface #21,  1           // InterfaceMethod org/slf4j/Logger.isWarnEnabled:()Z
       9: ireturn

  public boolean isErrorEnabled();
    Code:
       0: aload_0
       1: getfield      #4                  // Field logger:Lorg/slf4j/Logger;
       4: invokeinterface #22,  1           // InterfaceMethod org/slf4j/Logger.isErrorEnabled:()Z
       9: ireturn

  static {};
    Code:
       0: ldc           #23                 // class org/apache/dubbo/common/logger/support/FailsafeLogger
       2: invokevirtual #24                 // Method java/lang/Class.getName:()Ljava/lang/String;
       5: putstatic     #5                  // Field FQCN:Ljava/lang/String;
       8: return
}
