Compiled from "CancelableStreamObserver.java"
public abstract class org.apache.dubbo.rpc.protocol.tri.CancelableStreamObserver<T> implements org.apache.dubbo.common.stream.StreamObserver<T> {
  private org.apache.dubbo.rpc.CancellationContext cancellationContext;

  public org.apache.dubbo.rpc.protocol.tri.CancelableStreamObserver();
    Code:
       0: aload_0
       1: invokespecial #1                  // Method java/lang/Object."<init>":()V
       4: return

  public void setCancellationContext(org.apache.dubbo.rpc.CancellationContext);
    Code:
       0: aload_0
       1: aload_1
       2: putfield      #2                  // Field cancellationContext:Lorg/apache/dubbo/rpc/CancellationContext;
       5: return

  public org.apache.dubbo.rpc.CancellationContext getCancellationContext();
    Code:
       0: aload_0
       1: getfield      #2                  // Field cancellationContext:Lorg/apache/dubbo/rpc/CancellationContext;
       4: areturn

  public void cancel(java.lang.Throwable);
    Code:
       0: aload_0
       1: getfield      #2                  // Field cancellationContext:Lorg/apache/dubbo/rpc/CancellationContext;
       4: aload_1
       5: invokevirtual #3                  // Method org/apache/dubbo/rpc/CancellationContext.cancel:(Ljava/lang/Throwable;)Z
       8: pop
       9: return

  public void beforeStart(org.apache.dubbo.rpc.protocol.tri.observer.ClientCallToObserverAdapter<T>);
    Code:
       0: return

  public void startRequest();
    Code:
       0: return
}
