Compiled from "ClassLoadUtil.java"
public class org.apache.dubbo.rpc.protocol.tri.ClassLoadUtil {
  public org.apache.dubbo.rpc.protocol.tri.ClassLoadUtil();
    Code:
       0: aload_0
       1: invokespecial #1                  // Method java/lang/Object."<init>":()V
       4: return

  public static void switchContextLoader(java.lang.ClassLoader);
    Code:
       0: aload_0
       1: ifnull        21
       4: aload_0
       5: invokestatic  #2                  // Method java/lang/Thread.currentThread:()Ljava/lang/Thread;
       8: invokevirtual #3                  // Method java/lang/Thread.getContextClassLoader:()Ljava/lang/ClassLoader;
      11: if_acmpeq     21
      14: invokestatic  #2                  // Method java/lang/Thread.currentThread:()Ljava/lang/Thread;
      17: aload_0
      18: invokevirtual #4                  // Method java/lang/Thread.setContextClassLoader:(Ljava/lang/ClassLoader;)V
      21: goto          25
      24: astore_1
      25: return
    Exception table:
       from    to  target type
           0    21    24   Class java/lang/SecurityException
}
