Compiled from "DeadlineFuture.java"
class org.apache.dubbo.rpc.protocol.tri.DeadlineFuture$TimeoutCheckTask implements org.apache.dubbo.common.timer.TimerTask {
  final org.apache.dubbo.rpc.protocol.tri.DeadlineFuture this$0;

  private org.apache.dubbo.rpc.protocol.tri.DeadlineFuture$TimeoutCheckTask(org.apache.dubbo.rpc.protocol.tri.DeadlineFuture);
    Code:
       0: aload_0
       1: aload_1
       2: putfield      #2                  // Field this$0:Lorg/apache/dubbo/rpc/protocol/tri/DeadlineFuture;
       5: aload_0
       6: invokespecial #3                  // Method java/lang/Object."<init>":()V
       9: return

  public void run(org.apache.dubbo.common.timer.Timeout);
    Code:
       0: aload_0
       1: getfield      #2                  // Field this$0:Lorg/apache/dubbo/rpc/protocol/tri/DeadlineFuture;
       4: invokevirtual #4                  // Method org/apache/dubbo/rpc/protocol/tri/DeadlineFuture.isDone:()Z
       7: ifeq          11
      10: return
      11: aload_0
      12: getfield      #2                  // Field this$0:Lorg/apache/dubbo/rpc/protocol/tri/DeadlineFuture;
      15: invokevirtual #5                  // Method org/apache/dubbo/rpc/protocol/tri/DeadlineFuture.getExecutor:()Ljava/util/concurrent/Executor;
      18: ifnull        42
      21: aload_0
      22: getfield      #2                  // Field this$0:Lorg/apache/dubbo/rpc/protocol/tri/DeadlineFuture;
      25: invokevirtual #5                  // Method org/apache/dubbo/rpc/protocol/tri/DeadlineFuture.getExecutor:()Ljava/util/concurrent/Executor;
      28: aload_0
      29: invokedynamic #6,  0              // InvokeDynamic #0:run:(Lorg/apache/dubbo/rpc/protocol/tri/DeadlineFuture$TimeoutCheckTask;)Ljava/lang/Runnable;
      34: invokeinterface #7,  2            // InterfaceMethod java/util/concurrent/Executor.execute:(Ljava/lang/Runnable;)V
      39: goto          46
      42: aload_0
      43: invokespecial #8                  // Method notifyTimeout:()V
      46: return

  private void notifyTimeout();
    Code:
       0: getstatic     #9                  // Field org/apache/dubbo/rpc/TriRpcStatus.DEADLINE_EXCEEDED:Lorg/apache/dubbo/rpc/TriRpcStatus;
       3: aload_0
       4: getfield      #2                  // Field this$0:Lorg/apache/dubbo/rpc/protocol/tri/DeadlineFuture;
       7: invokestatic  #10                 // Method org/apache/dubbo/rpc/protocol/tri/DeadlineFuture.access$100:(Lorg/apache/dubbo/rpc/protocol/tri/DeadlineFuture;)Ljava/lang/String;
      10: invokevirtual #11                 // Method org/apache/dubbo/rpc/TriRpcStatus.withDescription:(Ljava/lang/String;)Lorg/apache/dubbo/rpc/TriRpcStatus;
      13: astore_1
      14: new           #12                 // class org/apache/dubbo/rpc/AppResponse
      17: dup
      18: invokespecial #13                 // Method org/apache/dubbo/rpc/AppResponse."<init>":()V
      21: astore_2
      22: aload_2
      23: aload_1
      24: invokevirtual #14                 // Method org/apache/dubbo/rpc/TriRpcStatus.asException:()Lorg/apache/dubbo/rpc/StatusRpcException;
      27: invokevirtual #15                 // Method org/apache/dubbo/rpc/AppResponse.setException:(Ljava/lang/Throwable;)V
      30: aload_0
      31: getfield      #2                  // Field this$0:Lorg/apache/dubbo/rpc/protocol/tri/DeadlineFuture;
      34: aload_1
      35: aload_2
      36: invokestatic  #16                 // Method org/apache/dubbo/rpc/protocol/tri/DeadlineFuture.access$200:(Lorg/apache/dubbo/rpc/protocol/tri/DeadlineFuture;Lorg/apache/dubbo/rpc/TriRpcStatus;Lorg/apache/dubbo/rpc/AppResponse;)V
      39: return

  private void lambda$run$0();
    Code:
       0: aload_0
       1: invokespecial #8                  // Method notifyTimeout:()V
       4: aload_0
       5: getfield      #2                  // Field this$0:Lorg/apache/dubbo/rpc/protocol/tri/DeadlineFuture;
       8: invokevirtual #17                 // Method org/apache/dubbo/rpc/protocol/tri/DeadlineFuture.getTimeoutListeners:()Ljava/util/List;
      11: invokeinterface #18,  1           // InterfaceMethod java/util/List.iterator:()Ljava/util/Iterator;
      16: astore_1
      17: aload_1
      18: invokeinterface #19,  1           // InterfaceMethod java/util/Iterator.hasNext:()Z
      23: ifeq          45
      26: aload_1
      27: invokeinterface #20,  1           // InterfaceMethod java/util/Iterator.next:()Ljava/lang/Object;
      32: checkcast     #21                 // class java/lang/Runnable
      35: astore_2
      36: aload_2
      37: invokeinterface #22,  1           // InterfaceMethod java/lang/Runnable.run:()V
      42: goto          17
      45: return

  org.apache.dubbo.rpc.protocol.tri.DeadlineFuture$TimeoutCheckTask(org.apache.dubbo.rpc.protocol.tri.DeadlineFuture, org.apache.dubbo.rpc.protocol.tri.DeadlineFuture$1);
    Code:
       0: aload_0
       1: aload_1
       2: invokespecial #1                  // Method "<init>":(Lorg/apache/dubbo/rpc/protocol/tri/DeadlineFuture;)V
       5: return
}
