Compiled from "Http2ProtocolDetector.java"
public class org.apache.dubbo.rpc.protocol.tri.Http2ProtocolDetector implements org.apache.dubbo.remoting.api.ProtocolDetector {
  private final org.apache.dubbo.remoting.buffer.ChannelBuffer clientPrefaceString;

  public org.apache.dubbo.rpc.protocol.tri.Http2ProtocolDetector();
    Code:
       0: aload_0
       1: invokespecial #1                  // Method java/lang/Object."<init>":()V
       4: aload_0
       5: new           #2                  // class org/apache/dubbo/remoting/buffer/ByteBufferBackedChannelBuffer
       8: dup
       9: invokestatic  #3                  // Method io/netty/handler/codec/http2/Http2CodecUtil.connectionPrefaceBuf:()Lio/netty/buffer/ByteBuf;
      12: invokevirtual #4                  // Method io/netty/buffer/ByteBuf.nioBuffer:()Ljava/nio/ByteBuffer;
      15: invokespecial #5                  // Method org/apache/dubbo/remoting/buffer/ByteBufferBackedChannelBuffer."<init>":(Ljava/nio/ByteBuffer;)V
      18: putfield      #6                  // Field clientPrefaceString:Lorg/apache/dubbo/remoting/buffer/ChannelBuffer;
      21: return

  public org.apache.dubbo.remoting.api.ProtocolDetector$Result detect(org.apache.dubbo.remoting.buffer.ChannelBuffer);
    Code:
       0: aload_0
       1: getfield      #6                  // Field clientPrefaceString:Lorg/apache/dubbo/remoting/buffer/ChannelBuffer;
       4: invokeinterface #7,  1            // InterfaceMethod org/apache/dubbo/remoting/buffer/ChannelBuffer.readableBytes:()I
       9: istore_2
      10: aload_1
      11: invokeinterface #7,  1            // InterfaceMethod org/apache/dubbo/remoting/buffer/ChannelBuffer.readableBytes:()I
      16: iload_2
      17: invokestatic  #8                  // Method java/lang/Math.min:(II)I
      20: istore_3
      21: iload_3
      22: ifeq          37
      25: aload_1
      26: aload_0
      27: getfield      #6                  // Field clientPrefaceString:Lorg/apache/dubbo/remoting/buffer/ChannelBuffer;
      30: iload_3
      31: invokestatic  #9                  // Method org/apache/dubbo/remoting/buffer/ChannelBuffers.prefixEquals:(Lorg/apache/dubbo/remoting/buffer/ChannelBuffer;Lorg/apache/dubbo/remoting/buffer/ChannelBuffer;I)Z
      34: ifne          41
      37: getstatic     #10                 // Field org/apache/dubbo/remoting/api/ProtocolDetector$Result.UNRECOGNIZED:Lorg/apache/dubbo/remoting/api/ProtocolDetector$Result;
      40: areturn
      41: iload_3
      42: iload_2
      43: if_icmpne     50
      46: getstatic     #11                 // Field org/apache/dubbo/remoting/api/ProtocolDetector$Result.RECOGNIZED:Lorg/apache/dubbo/remoting/api/ProtocolDetector$Result;
      49: areturn
      50: getstatic     #12                 // Field org/apache/dubbo/remoting/api/ProtocolDetector$Result.NEED_MORE_DATA:Lorg/apache/dubbo/remoting/api/ProtocolDetector$Result;
      53: areturn
}
