Compiled from "PbArrayPacker.java"
public class org.apache.dubbo.rpc.protocol.tri.PbArrayPacker implements org.apache.dubbo.rpc.model.Pack {
  private static final org.apache.dubbo.rpc.model.Pack PB_PACK;

  private final boolean singleArgument;

  public org.apache.dubbo.rpc.protocol.tri.PbArrayPacker(boolean);
    Code:
       0: aload_0
       1: invokespecial #1                  // Method java/lang/Object."<init>":()V
       4: aload_0
       5: iload_1
       6: putfield      #2                  // Field singleArgument:Z
       9: return

  public byte[] pack(java.lang.Object) throws java.lang.Exception;
    Code:
       0: aload_0
       1: getfield      #2                  // Field singleArgument:Z
       4: ifne          17
       7: aload_1
       8: checkcast     #3                  // class "[Ljava/lang/Object;"
      11: checkcast     #3                  // class "[Ljava/lang/Object;"
      14: iconst_0
      15: aaload
      16: astore_1
      17: getstatic     #4                  // Field PB_PACK:Lorg/apache/dubbo/rpc/model/Pack;
      20: aload_1
      21: invokeinterface #5,  2            // InterfaceMethod org/apache/dubbo/rpc/model/Pack.pack:(Ljava/lang/Object;)[B
      26: areturn

  private static byte[] lambda$static$0(java.lang.Object) throws java.lang.Exception;
    Code:
       0: aload_0
       1: checkcast     #6                  // class com/google/protobuf/Message
       4: invokeinterface #7,  1            // InterfaceMethod com/google/protobuf/Message.toByteArray:()[B
       9: areturn

  static {};
    Code:
       0: invokedynamic #8,  0              // InvokeDynamic #0:pack:()Lorg/apache/dubbo/rpc/model/Pack;
       5: putstatic     #4                  // Field PB_PACK:Lorg/apache/dubbo/rpc/model/Pack;
       8: return
}
