Compiled from "PbUnpack.java"
public class org.apache.dubbo.rpc.protocol.tri.PbUnpack<T> implements org.apache.dubbo.rpc.model.UnPack {
  private final java.lang.Class<T> clz;

  public org.apache.dubbo.rpc.protocol.tri.PbUnpack(java.lang.Class<T>);
    Code:
       0: aload_0
       1: invokespecial #1                  // Method java/lang/Object."<init>":()V
       4: aload_0
       5: aload_1
       6: putfield      #2                  // Field clz:Ljava/lang/Class;
       9: return

  public java.lang.Object unpack(byte[]) throws java.io.IOException;
    Code:
       0: new           #3                  // class java/io/ByteArrayInputStream
       3: dup
       4: aload_1
       5: invokespecial #4                  // Method java/io/ByteArrayInputStream."<init>":([B)V
       8: astore_2
       9: aload_2
      10: aload_0
      11: getfield      #2                  // Field clz:Ljava/lang/Class;
      14: invokestatic  #5                  // Method org/apache/dubbo/rpc/protocol/tri/SingleProtobufUtils.deserialize:(Ljava/io/InputStream;Ljava/lang/Class;)Ljava/lang/Object;
      17: areturn
}
