Compiled from "ReflectionPackableMethod.java"
class org.apache.dubbo.rpc.protocol.tri.ReflectionPackableMethod$WrapResponsePack implements org.apache.dubbo.rpc.model.Pack {
  private final org.apache.dubbo.common.serialize.MultipleSerialization multipleSerialization;

  private final org.apache.dubbo.common.URL url;

  private final java.lang.Class<?> actualResponseType;

  java.lang.String requestSerialize;

  private org.apache.dubbo.rpc.protocol.tri.ReflectionPackableMethod$WrapResponsePack(org.apache.dubbo.common.serialize.MultipleSerialization, org.apache.dubbo.common.URL, java.lang.String, java.lang.Class<?>);
    Code:
       0: aload_0
       1: invokespecial #2                  // Method java/lang/Object."<init>":()V
       4: aload_0
       5: aload_1
       6: putfield      #3                  // Field multipleSerialization:Lorg/apache/dubbo/common/serialize/MultipleSerialization;
       9: aload_0
      10: aload_2
      11: putfield      #4                  // Field url:Lorg/apache/dubbo/common/URL;
      14: aload_0
      15: aload         4
      17: putfield      #5                  // Field actualResponseType:Ljava/lang/Class;
      20: aload_0
      21: aload_3
      22: putfield      #6                  // Field requestSerialize:Ljava/lang/String;
      25: return

  public byte[] pack(java.lang.Object) throws java.io.IOException;
    Code:
       0: new           #7                  // class java/io/ByteArrayOutputStream
       3: dup
       4: invokespecial #8                  // Method java/io/ByteArrayOutputStream."<init>":()V
       7: astore_2
       8: aload_0
       9: getfield      #3                  // Field multipleSerialization:Lorg/apache/dubbo/common/serialize/MultipleSerialization;
      12: aload_0
      13: getfield      #4                  // Field url:Lorg/apache/dubbo/common/URL;
      16: aload_0
      17: getfield      #6                  // Field requestSerialize:Ljava/lang/String;
      20: aload_0
      21: getfield      #5                  // Field actualResponseType:Ljava/lang/Class;
      24: aload_1
      25: aload_2
      26: invokeinterface #9,  6            // InterfaceMethod org/apache/dubbo/common/serialize/MultipleSerialization.serialize:(Lorg/apache/dubbo/common/URL;Ljava/lang/String;Ljava/lang/Class;Ljava/lang/Object;Ljava/io/OutputStream;)V
      31: invokestatic  #10                 // Method org/apache/dubbo/rpc/protocol/tri/TripleCustomerProtocolWapper$TripleResponseWrapper$Builder.newBuilder:()Lorg/apache/dubbo/rpc/protocol/tri/TripleCustomerProtocolWapper$TripleResponseWrapper$Builder;
      34: aload_0
      35: getfield      #6                  // Field requestSerialize:Ljava/lang/String;
      38: invokevirtual #11                 // Method org/apache/dubbo/rpc/protocol/tri/TripleCustomerProtocolWapper$TripleResponseWrapper$Builder.setSerializeType:(Ljava/lang/String;)Lorg/apache/dubbo/rpc/protocol/tri/TripleCustomerProtocolWapper$TripleResponseWrapper$Builder;
      41: aload_0
      42: getfield      #5                  // Field actualResponseType:Ljava/lang/Class;
      45: invokevirtual #12                 // Method java/lang/Class.getName:()Ljava/lang/String;
      48: invokevirtual #13                 // Method org/apache/dubbo/rpc/protocol/tri/TripleCustomerProtocolWapper$TripleResponseWrapper$Builder.setType:(Ljava/lang/String;)Lorg/apache/dubbo/rpc/protocol/tri/TripleCustomerProtocolWapper$TripleResponseWrapper$Builder;
      51: aload_2
      52: invokevirtual #14                 // Method java/io/ByteArrayOutputStream.toByteArray:()[B
      55: invokevirtual #15                 // Method org/apache/dubbo/rpc/protocol/tri/TripleCustomerProtocolWapper$TripleResponseWrapper$Builder.setData:([B)Lorg/apache/dubbo/rpc/protocol/tri/TripleCustomerProtocolWapper$TripleResponseWrapper$Builder;
      58: invokevirtual #16                 // Method org/apache/dubbo/rpc/protocol/tri/TripleCustomerProtocolWapper$TripleResponseWrapper$Builder.build:()Lorg/apache/dubbo/rpc/protocol/tri/TripleCustomerProtocolWapper$TripleResponseWrapper;
      61: invokevirtual #17                 // Method org/apache/dubbo/rpc/protocol/tri/TripleCustomerProtocolWapper$TripleResponseWrapper.toByteArray:()[B
      64: areturn

  org.apache.dubbo.rpc.protocol.tri.ReflectionPackableMethod$WrapResponsePack(org.apache.dubbo.common.serialize.MultipleSerialization, org.apache.dubbo.common.URL, java.lang.String, java.lang.Class, org.apache.dubbo.rpc.protocol.tri.ReflectionPackableMethod$1);
    Code:
       0: aload_0
       1: aload_1
       2: aload_2
       3: aload_3
       4: aload         4
       6: invokespecial #1                  // Method "<init>":(Lorg/apache/dubbo/common/serialize/MultipleSerialization;Lorg/apache/dubbo/common/URL;Ljava/lang/String;Ljava/lang/Class;)V
       9: return
}
