Compiled from "ReflectionPackableMethod.java"
public class org.apache.dubbo.rpc.protocol.tri.ReflectionPackableMethod implements org.apache.dubbo.rpc.model.PackableMethod {
  private static final java.lang.String GRPC_ASYNC_RETURN_CLASS;

  private static final java.lang.String TRI_ASYNC_RETURN_CLASS;

  private static final java.lang.String REACTOR_RETURN_CLASS;

  private static final java.lang.String RX_RETURN_CLASS;

  private static final java.lang.String GRPC_STREAM_CLASS;

  private static final org.apache.dubbo.rpc.model.Pack PB_PACK;

  private final org.apache.dubbo.rpc.model.Pack requestPack;

  private final org.apache.dubbo.rpc.model.Pack responsePack;

  private final org.apache.dubbo.rpc.model.UnPack requestUnpack;

  private final org.apache.dubbo.rpc.model.UnPack responseUnpack;

  private final boolean needWrapper;

  private final java.util.Collection<java.lang.String> allSerialize;

  public boolean needWrapper();
    Code:
       0: aload_0
       1: getfield      #5                  // Field needWrapper:Z
       4: ireturn

  public org.apache.dubbo.rpc.protocol.tri.ReflectionPackableMethod(org.apache.dubbo.rpc.model.MethodDescriptor, org.apache.dubbo.common.URL, java.lang.String, java.util.Collection<java.lang.String>);
    Code:
       0: aload_0
       1: invokespecial #6                  // Method java/lang/Object."<init>":()V
       4: getstatic     #7                  // Field org/apache/dubbo/rpc/protocol/tri/ReflectionPackableMethod$1.$SwitchMap$org$apache$dubbo$rpc$model$MethodDescriptor$RpcType:[I
       7: aload_1
       8: invokeinterface #8,  1            // InterfaceMethod org/apache/dubbo/rpc/model/MethodDescriptor.getRpcType:()Lorg/apache/dubbo/rpc/model/MethodDescriptor$RpcType;
      13: invokevirtual #9                  // Method org/apache/dubbo/rpc/model/MethodDescriptor$RpcType.ordinal:()I
      16: iaload
      17: tableswitch   { // 1 to 4
                     1: 48
                     2: 48
                     3: 108
                     4: 148
               default: 172
          }
      48: iconst_1
      49: anewarray     #10                 // class java/lang/Class
      52: dup
      53: iconst_0
      54: aload_1
      55: invokeinterface #11,  1           // InterfaceMethod org/apache/dubbo/rpc/model/MethodDescriptor.getMethod:()Ljava/lang/reflect/Method;
      60: invokevirtual #12                 // Method java/lang/reflect/Method.getGenericReturnType:()Ljava/lang/reflect/Type;
      63: checkcast     #13                 // class java/lang/reflect/ParameterizedType
      66: invokeinterface #14,  1           // InterfaceMethod java/lang/reflect/ParameterizedType.getActualTypeArguments:()[Ljava/lang/reflect/Type;
      71: iconst_0
      72: aaload
      73: checkcast     #10                 // class java/lang/Class
      76: aastore
      77: astore        5
      79: aload_1
      80: invokeinterface #11,  1           // InterfaceMethod org/apache/dubbo/rpc/model/MethodDescriptor.getMethod:()Ljava/lang/reflect/Method;
      85: invokevirtual #15                 // Method java/lang/reflect/Method.getGenericParameterTypes:()[Ljava/lang/reflect/Type;
      88: iconst_0
      89: aaload
      90: checkcast     #13                 // class java/lang/reflect/ParameterizedType
      93: invokeinterface #14,  1           // InterfaceMethod java/lang/reflect/ParameterizedType.getActualTypeArguments:()[Ljava/lang/reflect/Type;
      98: iconst_0
      99: aaload
     100: checkcast     #10                 // class java/lang/Class
     103: astore        6
     105: goto          182
     108: aload_1
     109: invokeinterface #11,  1           // InterfaceMethod org/apache/dubbo/rpc/model/MethodDescriptor.getMethod:()Ljava/lang/reflect/Method;
     114: invokevirtual #16                 // Method java/lang/reflect/Method.getParameterTypes:()[Ljava/lang/Class;
     117: astore        5
     119: aload_1
     120: invokeinterface #11,  1           // InterfaceMethod org/apache/dubbo/rpc/model/MethodDescriptor.getMethod:()Ljava/lang/reflect/Method;
     125: invokevirtual #15                 // Method java/lang/reflect/Method.getGenericParameterTypes:()[Ljava/lang/reflect/Type;
     128: iconst_1
     129: aaload
     130: checkcast     #13                 // class java/lang/reflect/ParameterizedType
     133: invokeinterface #14,  1           // InterfaceMethod java/lang/reflect/ParameterizedType.getActualTypeArguments:()[Ljava/lang/reflect/Type;
     138: iconst_0
     139: aaload
     140: checkcast     #10                 // class java/lang/Class
     143: astore        6
     145: goto          182
     148: aload_1
     149: invokeinterface #17,  1           // InterfaceMethod org/apache/dubbo/rpc/model/MethodDescriptor.getParameterClasses:()[Ljava/lang/Class;
     154: astore        5
     156: aload_1
     157: invokeinterface #18,  1           // InterfaceMethod org/apache/dubbo/rpc/model/MethodDescriptor.getReturnTypes:()[Ljava/lang/reflect/Type;
     162: iconst_0
     163: aaload
     164: checkcast     #10                 // class java/lang/Class
     167: astore        6
     169: goto          182
     172: new           #19                 // class java/lang/IllegalStateException
     175: dup
     176: ldc           #20                 // String Can not reach here
     178: invokespecial #21                 // Method java/lang/IllegalStateException."<init>":(Ljava/lang/String;)V
     181: athrow
     182: aload_1
     183: invokeinterface #8,  1            // InterfaceMethod org/apache/dubbo/rpc/model/MethodDescriptor.getRpcType:()Lorg/apache/dubbo/rpc/model/MethodDescriptor$RpcType;
     188: getstatic     #22                 // Field org/apache/dubbo/rpc/model/MethodDescriptor$RpcType.UNARY:Lorg/apache/dubbo/rpc/model/MethodDescriptor$RpcType;
     191: if_acmpeq     198
     194: iconst_1
     195: goto          199
     198: iconst_0
     199: istore        7
     201: aload_0
     202: aload_1
     203: aload         5
     205: aload         6
     207: invokestatic  #23                 // Method needWrap:(Lorg/apache/dubbo/rpc/model/MethodDescriptor;[Ljava/lang/Class;Ljava/lang/Class;)Z
     210: putfield      #5                  // Field needWrapper:Z
     213: aload_0
     214: getfield      #5                  // Field needWrapper:Z
     217: ifne          271
     220: aload_0
     221: new           #24                 // class org/apache/dubbo/rpc/protocol/tri/PbArrayPacker
     224: dup
     225: iload         7
     227: invokespecial #25                 // Method org/apache/dubbo/rpc/protocol/tri/PbArrayPacker."<init>":(Z)V
     230: putfield      #26                 // Field requestPack:Lorg/apache/dubbo/rpc/model/Pack;
     233: aload_0
     234: getstatic     #27                 // Field PB_PACK:Lorg/apache/dubbo/rpc/model/Pack;
     237: putfield      #3                  // Field responsePack:Lorg/apache/dubbo/rpc/model/Pack;
     240: aload_0
     241: new           #28                 // class org/apache/dubbo/rpc/protocol/tri/PbUnpack
     244: dup
     245: aload         5
     247: iconst_0
     248: aaload
     249: invokespecial #29                 // Method org/apache/dubbo/rpc/protocol/tri/PbUnpack."<init>":(Ljava/lang/Class;)V
     252: putfield      #30                 // Field requestUnpack:Lorg/apache/dubbo/rpc/model/UnPack;
     255: aload_0
     256: new           #28                 // class org/apache/dubbo/rpc/protocol/tri/PbUnpack
     259: dup
     260: aload         6
     262: invokespecial #29                 // Method org/apache/dubbo/rpc/protocol/tri/PbUnpack."<init>":(Ljava/lang/Class;)V
     265: putfield      #31                 // Field responseUnpack:Lorg/apache/dubbo/rpc/model/UnPack;
     268: goto          373
     271: aload_2
     272: invokevirtual #32                 // Method org/apache/dubbo/common/URL.getOrDefaultFrameworkModel:()Lorg/apache/dubbo/rpc/model/FrameworkModel;
     275: ldc           #33                 // class org/apache/dubbo/common/serialize/MultipleSerialization
     277: invokevirtual #34                 // Method org/apache/dubbo/rpc/model/FrameworkModel.getExtensionLoader:(Ljava/lang/Class;)Lorg/apache/dubbo/common/extension/ExtensionLoader;
     280: aload_2
     281: ldc           #36                 // String serialize.multiple
     283: ldc           #37                 // String default
     285: invokevirtual #38                 // Method org/apache/dubbo/common/URL.getParameter:(Ljava/lang/String;Ljava/lang/String;)Ljava/lang/String;
     288: invokevirtual #39                 // Method org/apache/dubbo/common/extension/ExtensionLoader.getExtension:(Ljava/lang/String;)Ljava/lang/Object;
     291: checkcast     #33                 // class org/apache/dubbo/common/serialize/MultipleSerialization
     294: astore        8
     296: aload_0
     297: new           #40                 // class org/apache/dubbo/rpc/protocol/tri/ReflectionPackableMethod$WrapRequestPack
     300: dup
     301: aload         8
     303: aload_2
     304: aload_3
     305: aload         5
     307: iload         7
     309: aconst_null
     310: invokespecial #41                 // Method org/apache/dubbo/rpc/protocol/tri/ReflectionPackableMethod$WrapRequestPack."<init>":(Lorg/apache/dubbo/common/serialize/MultipleSerialization;Lorg/apache/dubbo/common/URL;Ljava/lang/String;[Ljava/lang/Class;ZLorg/apache/dubbo/rpc/protocol/tri/ReflectionPackableMethod$1;)V
     313: putfield      #26                 // Field requestPack:Lorg/apache/dubbo/rpc/model/Pack;
     316: aload_0
     317: new           #42                 // class org/apache/dubbo/rpc/protocol/tri/ReflectionPackableMethod$WrapResponseUnpack
     320: dup
     321: aload         8
     323: aload_2
     324: aload         4
     326: aload         6
     328: aconst_null
     329: invokespecial #43                 // Method org/apache/dubbo/rpc/protocol/tri/ReflectionPackableMethod$WrapResponseUnpack."<init>":(Lorg/apache/dubbo/common/serialize/MultipleSerialization;Lorg/apache/dubbo/common/URL;Ljava/util/Collection;Ljava/lang/Class;Lorg/apache/dubbo/rpc/protocol/tri/ReflectionPackableMethod$1;)V
     332: putfield      #31                 // Field responseUnpack:Lorg/apache/dubbo/rpc/model/UnPack;
     335: aload_0
     336: new           #44                 // class org/apache/dubbo/rpc/protocol/tri/ReflectionPackableMethod$WrapResponsePack
     339: dup
     340: aload         8
     342: aload_2
     343: aload_3
     344: aload         6
     346: aconst_null
     347: invokespecial #45                 // Method org/apache/dubbo/rpc/protocol/tri/ReflectionPackableMethod$WrapResponsePack."<init>":(Lorg/apache/dubbo/common/serialize/MultipleSerialization;Lorg/apache/dubbo/common/URL;Ljava/lang/String;Ljava/lang/Class;Lorg/apache/dubbo/rpc/protocol/tri/ReflectionPackableMethod$1;)V
     350: putfield      #3                  // Field responsePack:Lorg/apache/dubbo/rpc/model/Pack;
     353: aload_0
     354: new           #46                 // class org/apache/dubbo/rpc/protocol/tri/ReflectionPackableMethod$WrapRequestUnpack
     357: dup
     358: aload_0
     359: aload         8
     361: aload_2
     362: aload         4
     364: aload         5
     366: aconst_null
     367: invokespecial #47                 // Method org/apache/dubbo/rpc/protocol/tri/ReflectionPackableMethod$WrapRequestUnpack."<init>":(Lorg/apache/dubbo/rpc/protocol/tri/ReflectionPackableMethod;Lorg/apache/dubbo/common/serialize/MultipleSerialization;Lorg/apache/dubbo/common/URL;Ljava/util/Collection;[Ljava/lang/Class;Lorg/apache/dubbo/rpc/protocol/tri/ReflectionPackableMethod$1;)V
     370: putfield      #30                 // Field requestUnpack:Lorg/apache/dubbo/rpc/model/UnPack;
     373: aload_0
     374: aload         4
     376: putfield      #48                 // Field allSerialize:Ljava/util/Collection;
     379: return

  public static org.apache.dubbo.rpc.protocol.tri.ReflectionPackableMethod init(org.apache.dubbo.rpc.model.MethodDescriptor, org.apache.dubbo.common.URL);
    Code:
       0: aload_0
       1: ldc           #49                 // String pack
       3: invokeinterface #50,  2           // InterfaceMethod org/apache/dubbo/rpc/model/MethodDescriptor.getAttribute:(Ljava/lang/String;)Ljava/lang/Object;
       8: astore_2
       9: aload_2
      10: ifnull        18
      13: aload_2
      14: checkcast     #51                 // class org/apache/dubbo/rpc/protocol/tri/ReflectionPackableMethod
      17: areturn
      18: aload_1
      19: invokestatic  #52                 // Method org/apache/dubbo/remoting/utils/UrlUtils.serializationOrDefault:(Lorg/apache/dubbo/common/URL;)Ljava/lang/String;
      22: astore_3
      23: aload_1
      24: invokestatic  #53                 // Method org/apache/dubbo/remoting/utils/UrlUtils.allSerializations:(Lorg/apache/dubbo/common/URL;)Ljava/util/Collection;
      27: astore        4
      29: new           #51                 // class org/apache/dubbo/rpc/protocol/tri/ReflectionPackableMethod
      32: dup
      33: aload_0
      34: aload_1
      35: aload_3
      36: aload         4
      38: invokespecial #54                 // Method "<init>":(Lorg/apache/dubbo/rpc/model/MethodDescriptor;Lorg/apache/dubbo/common/URL;Ljava/lang/String;Ljava/util/Collection;)V
      41: astore        5
      43: aload_0
      44: ldc           #49                 // String pack
      46: aload         5
      48: invokeinterface #55,  3           // InterfaceMethod org/apache/dubbo/rpc/model/MethodDescriptor.addAttribute:(Ljava/lang/String;Ljava/lang/Object;)V
      53: aload         5
      55: areturn

  static boolean isStreamType(java.lang.Class<?>);
    Code:
       0: ldc           #56                 // class org/apache/dubbo/common/stream/StreamObserver
       2: aload_0
       3: invokevirtual #57                 // Method java/lang/Class.isAssignableFrom:(Ljava/lang/Class;)Z
       6: ifne          21
       9: ldc           #58                 // String io.grpc.stub.StreamObserver
      11: aload_0
      12: invokevirtual #59                 // Method java/lang/Class.getName:()Ljava/lang/String;
      15: invokevirtual #60                 // Method java/lang/String.equalsIgnoreCase:(Ljava/lang/String;)Z
      18: ifeq          25
      21: iconst_1
      22: goto          26
      25: iconst_0
      26: ireturn

  static boolean needWrap(org.apache.dubbo.rpc.model.MethodDescriptor, java.lang.Class<?>[], java.lang.Class<?>);
    Code:
       0: aload_0
       1: invokeinterface #61,  1           // InterfaceMethod org/apache/dubbo/rpc/model/MethodDescriptor.getMethodName:()Ljava/lang/String;
       6: astore_3
       7: ldc           #62                 // String $invoke
       9: aload_3
      10: invokevirtual #63                 // Method java/lang/String.equals:(Ljava/lang/Object;)Z
      13: ifne          25
      16: ldc           #64                 // String $invokeAsync
      18: aload_3
      19: invokevirtual #63                 // Method java/lang/String.equals:(Ljava/lang/Object;)Z
      22: ifeq          27
      25: iconst_1
      26: ireturn
      27: ldc           #65                 // String $echo
      29: aload_3
      30: invokevirtual #63                 // Method java/lang/String.equals:(Ljava/lang/Object;)Z
      33: ifeq          38
      36: iconst_1
      37: ireturn
      38: aload_2
      39: invokestatic  #66                 // Method isProtobufClass:(Ljava/lang/Class;)Z
      42: istore        4
      44: aload_1
      45: arraylength
      46: ifne          60
      49: iload         4
      51: ifne          58
      54: iconst_1
      55: goto          59
      58: iconst_0
      59: ireturn
      60: iconst_0
      61: istore        5
      63: iconst_0
      64: istore        6
      66: iconst_0
      67: istore        7
      69: iconst_0
      70: istore        8
      72: iconst_0
      73: istore        9
      75: iload         9
      77: aload_1
      78: arraylength
      79: if_icmpge     134
      82: aload_1
      83: iload         9
      85: aaload
      86: astore        10
      88: aload         10
      90: invokestatic  #66                 // Method isProtobufClass:(Ljava/lang/Class;)Z
      93: ifeq          102
      96: iinc          5, 1
      99: goto          128
     102: aload         10
     104: invokestatic  #67                 // Method isStreamType:(Ljava/lang/Class;)Z
     107: ifeq          125
     110: iload         9
     112: iconst_1
     113: if_icmpne     119
     116: iconst_1
     117: istore        8
     119: iinc          7, 1
     122: goto          128
     125: iinc          6, 1
     128: iinc          9, 1
     131: goto          75
     134: iload         7
     136: iconst_1
     137: if_icmple     167
     140: new           #19                 // class java/lang/IllegalStateException
     143: dup
     144: new           #68                 // class java/lang/StringBuilder
     147: dup
     148: invokespecial #69                 // Method java/lang/StringBuilder."<init>":()V
     151: ldc           #70                 // String method params error: more than one Stream params. method=
     153: invokevirtual #71                 // Method java/lang/StringBuilder.append:(Ljava/lang/String;)Ljava/lang/StringBuilder;
     156: aload_3
     157: invokevirtual #71                 // Method java/lang/StringBuilder.append:(Ljava/lang/String;)Ljava/lang/StringBuilder;
     160: invokevirtual #72                 // Method java/lang/StringBuilder.toString:()Ljava/lang/String;
     163: invokespecial #21                 // Method java/lang/IllegalStateException."<init>":(Ljava/lang/String;)V
     166: athrow
     167: iload         5
     169: iconst_2
     170: if_icmplt     200
     173: new           #19                 // class java/lang/IllegalStateException
     176: dup
     177: new           #68                 // class java/lang/StringBuilder
     180: dup
     181: invokespecial #69                 // Method java/lang/StringBuilder."<init>":()V
     184: ldc           #73                 // String method params error: more than one protobuf params. method=
     186: invokevirtual #71                 // Method java/lang/StringBuilder.append:(Ljava/lang/String;)Ljava/lang/StringBuilder;
     189: aload_3
     190: invokevirtual #71                 // Method java/lang/StringBuilder.append:(Ljava/lang/String;)Ljava/lang/StringBuilder;
     193: invokevirtual #72                 // Method java/lang/StringBuilder.toString:()Ljava/lang/String;
     196: invokespecial #21                 // Method java/lang/IllegalStateException."<init>":(Ljava/lang/String;)V
     199: athrow
     200: iload         7
     202: iconst_1
     203: if_icmpne     274
     206: iload         6
     208: iload         5
     210: iadd
     211: iconst_1
     212: if_icmple     242
     215: new           #19                 // class java/lang/IllegalStateException
     218: dup
     219: new           #68                 // class java/lang/StringBuilder
     222: dup
     223: invokespecial #69                 // Method java/lang/StringBuilder."<init>":()V
     226: ldc           #74                 // String method params error: server stream does not support more than one normal param. method=
     228: invokevirtual #71                 // Method java/lang/StringBuilder.append:(Ljava/lang/String;)Ljava/lang/StringBuilder;
     231: aload_3
     232: invokevirtual #71                 // Method java/lang/StringBuilder.append:(Ljava/lang/String;)Ljava/lang/StringBuilder;
     235: invokevirtual #72                 // Method java/lang/StringBuilder.toString:()Ljava/lang/String;
     238: invokespecial #21                 // Method java/lang/IllegalStateException."<init>":(Ljava/lang/String;)V
     241: athrow
     242: iload         8
     244: ifne          274
     247: new           #19                 // class java/lang/IllegalStateException
     250: dup
     251: new           #68                 // class java/lang/StringBuilder
     254: dup
     255: invokespecial #69                 // Method java/lang/StringBuilder."<init>":()V
     258: ldc           #75                 // String method params error: server stream\'s second param must be StreamObserver. method=
     260: invokevirtual #71                 // Method java/lang/StringBuilder.append:(Ljava/lang/String;)Ljava/lang/StringBuilder;
     263: aload_3
     264: invokevirtual #71                 // Method java/lang/StringBuilder.append:(Ljava/lang/String;)Ljava/lang/StringBuilder;
     267: invokevirtual #72                 // Method java/lang/StringBuilder.toString:()Ljava/lang/String;
     270: invokespecial #21                 // Method java/lang/IllegalStateException."<init>":(Ljava/lang/String;)V
     273: athrow
     274: aload_0
     275: invokeinterface #8,  1            // InterfaceMethod org/apache/dubbo/rpc/model/MethodDescriptor.getRpcType:()Lorg/apache/dubbo/rpc/model/MethodDescriptor$RpcType;
     280: getstatic     #22                 // Field org/apache/dubbo/rpc/model/MethodDescriptor$RpcType.UNARY:Lorg/apache/dubbo/rpc/model/MethodDescriptor$RpcType;
     283: if_acmpeq     399
     286: getstatic     #76                 // Field org/apache/dubbo/rpc/model/MethodDescriptor$RpcType.SERVER_STREAM:Lorg/apache/dubbo/rpc/model/MethodDescriptor$RpcType;
     289: aload_0
     290: invokeinterface #8,  1            // InterfaceMethod org/apache/dubbo/rpc/model/MethodDescriptor.getRpcType:()Lorg/apache/dubbo/rpc/model/MethodDescriptor$RpcType;
     295: if_acmpne     330
     298: iload         8
     300: ifne          330
     303: new           #19                 // class java/lang/IllegalStateException
     306: dup
     307: new           #68                 // class java/lang/StringBuilder
     310: dup
     311: invokespecial #69                 // Method java/lang/StringBuilder."<init>":()V
     314: ldc           #77                 // String method params error:server stream\'s second param must be StreamObserver. method=
     316: invokevirtual #71                 // Method java/lang/StringBuilder.append:(Ljava/lang/String;)Ljava/lang/StringBuilder;
     319: aload_3
     320: invokevirtual #71                 // Method java/lang/StringBuilder.append:(Ljava/lang/String;)Ljava/lang/StringBuilder;
     323: invokevirtual #72                 // Method java/lang/StringBuilder.toString:()Ljava/lang/String;
     326: invokespecial #21                 // Method java/lang/IllegalStateException."<init>":(Ljava/lang/String;)V
     329: athrow
     330: iload         4
     332: ifeq          367
     335: iload         6
     337: ifle          609
     340: new           #19                 // class java/lang/IllegalStateException
     343: dup
     344: new           #68                 // class java/lang/StringBuilder
     347: dup
     348: invokespecial #69                 // Method java/lang/StringBuilder."<init>":()V
     351: ldc           #78                 // String method params error: both normal and protobuf param found. method=
     353: invokevirtual #71                 // Method java/lang/StringBuilder.append:(Ljava/lang/String;)Ljava/lang/StringBuilder;
     356: aload_3
     357: invokevirtual #71                 // Method java/lang/StringBuilder.append:(Ljava/lang/String;)Ljava/lang/StringBuilder;
     360: invokevirtual #72                 // Method java/lang/StringBuilder.toString:()Ljava/lang/String;
     363: invokespecial #21                 // Method java/lang/IllegalStateException."<init>":(Ljava/lang/String;)V
     366: athrow
     367: iload         5
     369: ifle          609
     372: new           #19                 // class java/lang/IllegalStateException
     375: dup
     376: new           #68                 // class java/lang/StringBuilder
     379: dup
     380: invokespecial #69                 // Method java/lang/StringBuilder."<init>":()V
     383: ldc           #79                 // String method params error method=
     385: invokevirtual #71                 // Method java/lang/StringBuilder.append:(Ljava/lang/String;)Ljava/lang/StringBuilder;
     388: aload_3
     389: invokevirtual #71                 // Method java/lang/StringBuilder.append:(Ljava/lang/String;)Ljava/lang/StringBuilder;
     392: invokevirtual #72                 // Method java/lang/StringBuilder.toString:()Ljava/lang/String;
     395: invokespecial #21                 // Method java/lang/IllegalStateException."<init>":(Ljava/lang/String;)V
     398: athrow
     399: iload         7
     401: ifle          431
     404: new           #19                 // class java/lang/IllegalStateException
     407: dup
     408: new           #68                 // class java/lang/StringBuilder
     411: dup
     412: invokespecial #69                 // Method java/lang/StringBuilder."<init>":()V
     415: ldc           #80                 // String method params error: unary method should not contain any StreamObserver. method=
     417: invokevirtual #71                 // Method java/lang/StringBuilder.append:(Ljava/lang/String;)Ljava/lang/StringBuilder;
     420: aload_3
     421: invokevirtual #71                 // Method java/lang/StringBuilder.append:(Ljava/lang/String;)Ljava/lang/StringBuilder;
     424: invokevirtual #72                 // Method java/lang/StringBuilder.toString:()Ljava/lang/String;
     427: invokespecial #21                 // Method java/lang/IllegalStateException."<init>":(Ljava/lang/String;)V
     430: athrow
     431: iload         5
     433: ifle          443
     436: iload         4
     438: ifeq          443
     441: iconst_0
     442: ireturn
     443: aload_2
     444: invokestatic  #81                 // Method isMono:(Ljava/lang/Class;)Z
     447: ifne          457
     450: aload_2
     451: invokestatic  #82                 // Method isRx:(Ljava/lang/Class;)Z
     454: ifeq          459
     457: iconst_0
     458: ireturn
     459: iload         5
     461: ifgt          471
     464: iload         4
     466: ifne          471
     469: iconst_1
     470: ireturn
     471: ldc           #83                 // String com.google.common.util.concurrent.ListenableFuture
     473: aload_2
     474: invokevirtual #59                 // Method java/lang/Class.getName:()Ljava/lang/String;
     477: invokevirtual #60                 // Method java/lang/String.equalsIgnoreCase:(Ljava/lang/String;)Z
     480: ifeq          491
     483: iload         5
     485: iconst_1
     486: if_icmpne     491
     489: iconst_0
     490: ireturn
     491: ldc           #84                 // String java.util.concurrent.CompletableFuture
     493: aload_2
     494: invokevirtual #59                 // Method java/lang/Class.getName:()Ljava/lang/String;
     497: invokevirtual #60                 // Method java/lang/String.equalsIgnoreCase:(Ljava/lang/String;)Z
     500: ifeq          559
     503: aload_0
     504: invokeinterface #11,  1           // InterfaceMethod org/apache/dubbo/rpc/model/MethodDescriptor.getMethod:()Ljava/lang/reflect/Method;
     509: invokevirtual #12                 // Method java/lang/reflect/Method.getGenericReturnType:()Ljava/lang/reflect/Type;
     512: checkcast     #13                 // class java/lang/reflect/ParameterizedType
     515: invokeinterface #14,  1           // InterfaceMethod java/lang/reflect/ParameterizedType.getActualTypeArguments:()[Ljava/lang/reflect/Type;
     520: iconst_0
     521: aaload
     522: checkcast     #10                 // class java/lang/Class
     525: astore        9
     527: aload         9
     529: invokestatic  #66                 // Method isProtobufClass:(Ljava/lang/Class;)Z
     532: istore        10
     534: iload         10
     536: ifeq          547
     539: iload         5
     541: iconst_1
     542: if_icmpne     547
     545: iconst_0
     546: ireturn
     547: iload         10
     549: ifne          559
     552: iload         5
     554: ifne          559
     557: iconst_1
     558: ireturn
     559: aload_2
     560: invokestatic  #85                 // Method checkNeedIgnore:(Ljava/lang/Class;)Z
     563: istore        9
     565: iload         9
     567: ifeq          582
     570: iload         5
     572: iconst_1
     573: if_icmpeq     580
     576: iconst_1
     577: goto          581
     580: iconst_0
     581: ireturn
     582: new           #19                 // class java/lang/IllegalStateException
     585: dup
     586: new           #68                 // class java/lang/StringBuilder
     589: dup
     590: invokespecial #69                 // Method java/lang/StringBuilder."<init>":()V
     593: ldc           #79                 // String method params error method=
     595: invokevirtual #71                 // Method java/lang/StringBuilder.append:(Ljava/lang/String;)Ljava/lang/StringBuilder;
     598: aload_3
     599: invokevirtual #71                 // Method java/lang/StringBuilder.append:(Ljava/lang/String;)Ljava/lang/StringBuilder;
     602: invokevirtual #72                 // Method java/lang/StringBuilder.toString:()Ljava/lang/String;
     605: invokespecial #21                 // Method java/lang/IllegalStateException."<init>":(Ljava/lang/String;)V
     608: athrow
     609: iload         6
     611: ifle          618
     614: iconst_1
     615: goto          619
     618: iconst_0
     619: ireturn

  static boolean checkNeedIgnore(java.lang.Class<?>);
    Code:
       0: ldc           #86                 // class java/util/Iterator
       2: aload_0
       3: invokevirtual #57                 // Method java/lang/Class.isAssignableFrom:(Ljava/lang/Class;)Z
       6: ireturn

  static boolean isMono(java.lang.Class<?>);
    Code:
       0: ldc           #87                 // String reactor.core.publisher.Mono
       2: aload_0
       3: invokevirtual #59                 // Method java/lang/Class.getName:()Ljava/lang/String;
       6: invokevirtual #60                 // Method java/lang/String.equalsIgnoreCase:(Ljava/lang/String;)Z
       9: ireturn

  static boolean isRx(java.lang.Class<?>);
    Code:
       0: ldc           #88                 // String io.reactivex.Single
       2: aload_0
       3: invokevirtual #59                 // Method java/lang/Class.getName:()Ljava/lang/String;
       6: invokevirtual #60                 // Method java/lang/String.equalsIgnoreCase:(Ljava/lang/String;)Z
       9: ireturn

  static boolean isProtobufClass(java.lang.Class<?>);
    Code:
       0: aload_0
       1: ldc           #89                 // class java/lang/Object
       3: if_acmpeq     69
       6: aload_0
       7: ifnull        69
      10: aload_0
      11: invokevirtual #90                 // Method java/lang/Class.getInterfaces:()[Ljava/lang/Class;
      14: astore_1
      15: aload_1
      16: arraylength
      17: ifle          61
      20: aload_1
      21: astore_2
      22: aload_2
      23: arraylength
      24: istore_3
      25: iconst_0
      26: istore        4
      28: iload         4
      30: iload_3
      31: if_icmpge     61
      34: aload_2
      35: iload         4
      37: aaload
      38: astore        5
      40: ldc           #91                 // String com.google.protobuf.Message
      42: aload         5
      44: invokevirtual #59                 // Method java/lang/Class.getName:()Ljava/lang/String;
      47: invokevirtual #60                 // Method java/lang/String.equalsIgnoreCase:(Ljava/lang/String;)Z
      50: ifeq          55
      53: iconst_1
      54: ireturn
      55: iinc          4, 1
      58: goto          28
      61: aload_0
      62: invokevirtual #92                 // Method java/lang/Class.getSuperclass:()Ljava/lang/Class;
      65: astore_0
      66: goto          0
      69: iconst_0
      70: ireturn

  private static java.lang.String convertHessianFromWrapper(java.lang.String);
    Code:
       0: ldc           #94                 // String hessian4
       2: aload_0
       3: invokevirtual #63                 // Method java/lang/String.equals:(Ljava/lang/Object;)Z
       6: ifeq          12
       9: ldc           #95                 // String hessian2
      11: areturn
      12: aload_0
      13: areturn

  public org.apache.dubbo.rpc.model.Pack getRequestPack();
    Code:
       0: aload_0
       1: getfield      #26                 // Field requestPack:Lorg/apache/dubbo/rpc/model/Pack;
       4: areturn

  public org.apache.dubbo.rpc.model.Pack getResponsePack();
    Code:
       0: aload_0
       1: getfield      #3                  // Field responsePack:Lorg/apache/dubbo/rpc/model/Pack;
       4: areturn

  public org.apache.dubbo.rpc.model.UnPack getResponseUnpack();
    Code:
       0: aload_0
       1: getfield      #31                 // Field responseUnpack:Lorg/apache/dubbo/rpc/model/UnPack;
       4: areturn

  public org.apache.dubbo.rpc.model.UnPack getRequestUnpack();
    Code:
       0: aload_0
       1: getfield      #30                 // Field requestUnpack:Lorg/apache/dubbo/rpc/model/UnPack;
       4: areturn

  private static byte[] lambda$static$0(java.lang.Object) throws java.lang.Exception;
    Code:
       0: aload_0
       1: checkcast     #96                 // class com/google/protobuf/Message
       4: invokeinterface #97,  1           // InterfaceMethod com/google/protobuf/Message.toByteArray:()[B
       9: areturn

  static java.lang.String access$400(java.lang.String);
    Code:
       0: aload_0
       1: invokestatic  #4                  // Method convertHessianFromWrapper:(Ljava/lang/String;)Ljava/lang/String;
       4: areturn

  static org.apache.dubbo.rpc.model.Pack access$500(org.apache.dubbo.rpc.protocol.tri.ReflectionPackableMethod);
    Code:
       0: aload_0
       1: getfield      #3                  // Field responsePack:Lorg/apache/dubbo/rpc/model/Pack;
       4: areturn

  static {};
    Code:
       0: invokedynamic #98,  0             // InvokeDynamic #0:pack:()Lorg/apache/dubbo/rpc/model/Pack;
       5: putstatic     #27                 // Field PB_PACK:Lorg/apache/dubbo/rpc/model/Pack;
       8: return
}
