Compiled from "RequestMetadata.java"
public class org.apache.dubbo.rpc.protocol.tri.RequestMetadata {
  public io.netty.util.AsciiString scheme;

  public java.lang.String application;

  public java.lang.String service;

  public java.lang.String version;

  public java.lang.String group;

  public java.lang.String address;

  public java.lang.String acceptEncoding;

  public java.lang.String timeout;

  public org.apache.dubbo.rpc.protocol.tri.compressor.Compressor compressor;

  public org.apache.dubbo.rpc.CancellationContext cancellationContext;

  public org.apache.dubbo.rpc.model.MethodDescriptor method;

  public org.apache.dubbo.rpc.model.PackableMethod packableMethod;

  public java.util.Map<java.lang.String, java.lang.Object> attachments;

  public boolean convertNoLowerHeader;

  public boolean ignoreDefaultVersion;

  public org.apache.dubbo.rpc.protocol.tri.RequestMetadata();
    Code:
       0: aload_0
       1: invokespecial #1                  // Method java/lang/Object."<init>":()V
       4: return

  public io.netty.handler.codec.http2.DefaultHttp2Headers toHeaders();
    Code:
       0: new           #2                  // class io/netty/handler/codec/http2/DefaultHttp2Headers
       3: dup
       4: iconst_0
       5: invokespecial #3                  // Method io/netty/handler/codec/http2/DefaultHttp2Headers."<init>":(Z)V
       8: astore_1
       9: aload_1
      10: aload_0
      11: getfield      #4                  // Field scheme:Lio/netty/util/AsciiString;
      14: invokevirtual #5                  // Method io/netty/handler/codec/http2/DefaultHttp2Headers.scheme:(Ljava/lang/CharSequence;)Lio/netty/handler/codec/http2/Http2Headers;
      17: aload_0
      18: getfield      #6                  // Field address:Ljava/lang/String;
      21: invokeinterface #7,  2            // InterfaceMethod io/netty/handler/codec/http2/Http2Headers.authority:(Ljava/lang/CharSequence;)Lio/netty/handler/codec/http2/Http2Headers;
      26: getstatic     #8                  // Field io/netty/handler/codec/http/HttpMethod.POST:Lio/netty/handler/codec/http/HttpMethod;
      29: invokevirtual #9                  // Method io/netty/handler/codec/http/HttpMethod.asciiName:()Lio/netty/util/AsciiString;
      32: invokeinterface #10,  2           // InterfaceMethod io/netty/handler/codec/http2/Http2Headers.method:(Ljava/lang/CharSequence;)Lio/netty/handler/codec/http2/Http2Headers;
      37: new           #11                 // class java/lang/StringBuilder
      40: dup
      41: invokespecial #12                 // Method java/lang/StringBuilder."<init>":()V
      44: ldc           #13                 // String /
      46: invokevirtual #14                 // Method java/lang/StringBuilder.append:(Ljava/lang/String;)Ljava/lang/StringBuilder;
      49: aload_0
      50: getfield      #15                 // Field service:Ljava/lang/String;
      53: invokevirtual #14                 // Method java/lang/StringBuilder.append:(Ljava/lang/String;)Ljava/lang/StringBuilder;
      56: ldc           #13                 // String /
      58: invokevirtual #14                 // Method java/lang/StringBuilder.append:(Ljava/lang/String;)Ljava/lang/StringBuilder;
      61: aload_0
      62: getfield      #16                 // Field method:Lorg/apache/dubbo/rpc/model/MethodDescriptor;
      65: invokeinterface #17,  1           // InterfaceMethod org/apache/dubbo/rpc/model/MethodDescriptor.getMethodName:()Ljava/lang/String;
      70: invokevirtual #14                 // Method java/lang/StringBuilder.append:(Ljava/lang/String;)Ljava/lang/StringBuilder;
      73: invokevirtual #18                 // Method java/lang/StringBuilder.toString:()Ljava/lang/String;
      76: invokeinterface #19,  2           // InterfaceMethod io/netty/handler/codec/http2/Http2Headers.path:(Ljava/lang/CharSequence;)Lio/netty/handler/codec/http2/Http2Headers;
      81: getstatic     #20                 // Field org/apache/dubbo/rpc/protocol/tri/TripleHeaderEnum.CONTENT_TYPE_KEY:Lorg/apache/dubbo/rpc/protocol/tri/TripleHeaderEnum;
      84: invokevirtual #21                 // Method org/apache/dubbo/rpc/protocol/tri/TripleHeaderEnum.getHeader:()Ljava/lang/String;
      87: ldc           #23                 // String application/grpc+proto
      89: invokeinterface #24,  3           // InterfaceMethod io/netty/handler/codec/http2/Http2Headers.set:(Ljava/lang/Object;Ljava/lang/Object;)Lio/netty/handler/codec/Headers;
      94: checkcast     #25                 // class io/netty/handler/codec/http2/Http2Headers
      97: getstatic     #26                 // Field io/netty/handler/codec/http/HttpHeaderNames.TE:Lio/netty/util/AsciiString;
     100: getstatic     #27                 // Field io/netty/handler/codec/http/HttpHeaderValues.TRAILERS:Lio/netty/util/AsciiString;
     103: invokeinterface #24,  3           // InterfaceMethod io/netty/handler/codec/http2/Http2Headers.set:(Ljava/lang/Object;Ljava/lang/Object;)Lio/netty/handler/codec/Headers;
     108: pop
     109: aload_0
     110: aload_1
     111: getstatic     #28                 // Field org/apache/dubbo/rpc/protocol/tri/TripleHeaderEnum.TIMEOUT:Lorg/apache/dubbo/rpc/protocol/tri/TripleHeaderEnum;
     114: invokevirtual #21                 // Method org/apache/dubbo/rpc/protocol/tri/TripleHeaderEnum.getHeader:()Ljava/lang/String;
     117: aload_0
     118: getfield      #29                 // Field timeout:Ljava/lang/String;
     121: invokespecial #30                 // Method setIfNotNull:(Lio/netty/handler/codec/http2/DefaultHttp2Headers;Ljava/lang/CharSequence;Ljava/lang/CharSequence;)V
     124: aload_0
     125: getfield      #31                 // Field ignoreDefaultVersion:Z
     128: ifeq          143
     131: ldc           #32                 // String 1.0.0
     133: aload_0
     134: getfield      #33                 // Field version:Ljava/lang/String;
     137: invokevirtual #34                 // Method java/lang/String.equals:(Ljava/lang/Object;)Z
     140: ifne          158
     143: aload_0
     144: aload_1
     145: getstatic     #35                 // Field org/apache/dubbo/rpc/protocol/tri/TripleHeaderEnum.SERVICE_VERSION:Lorg/apache/dubbo/rpc/protocol/tri/TripleHeaderEnum;
     148: invokevirtual #21                 // Method org/apache/dubbo/rpc/protocol/tri/TripleHeaderEnum.getHeader:()Ljava/lang/String;
     151: aload_0
     152: getfield      #33                 // Field version:Ljava/lang/String;
     155: invokespecial #30                 // Method setIfNotNull:(Lio/netty/handler/codec/http2/DefaultHttp2Headers;Ljava/lang/CharSequence;Ljava/lang/CharSequence;)V
     158: aload_0
     159: aload_1
     160: getstatic     #36                 // Field org/apache/dubbo/rpc/protocol/tri/TripleHeaderEnum.SERVICE_GROUP:Lorg/apache/dubbo/rpc/protocol/tri/TripleHeaderEnum;
     163: invokevirtual #21                 // Method org/apache/dubbo/rpc/protocol/tri/TripleHeaderEnum.getHeader:()Ljava/lang/String;
     166: aload_0
     167: getfield      #37                 // Field group:Ljava/lang/String;
     170: invokespecial #30                 // Method setIfNotNull:(Lio/netty/handler/codec/http2/DefaultHttp2Headers;Ljava/lang/CharSequence;Ljava/lang/CharSequence;)V
     173: aload_0
     174: aload_1
     175: getstatic     #38                 // Field org/apache/dubbo/rpc/protocol/tri/TripleHeaderEnum.CONSUMER_APP_NAME_KEY:Lorg/apache/dubbo/rpc/protocol/tri/TripleHeaderEnum;
     178: invokevirtual #21                 // Method org/apache/dubbo/rpc/protocol/tri/TripleHeaderEnum.getHeader:()Ljava/lang/String;
     181: aload_0
     182: getfield      #39                 // Field application:Ljava/lang/String;
     185: invokespecial #30                 // Method setIfNotNull:(Lio/netty/handler/codec/http2/DefaultHttp2Headers;Ljava/lang/CharSequence;Ljava/lang/CharSequence;)V
     188: aload_0
     189: aload_1
     190: getstatic     #40                 // Field org/apache/dubbo/rpc/protocol/tri/TripleHeaderEnum.GRPC_ACCEPT_ENCODING:Lorg/apache/dubbo/rpc/protocol/tri/TripleHeaderEnum;
     193: invokevirtual #21                 // Method org/apache/dubbo/rpc/protocol/tri/TripleHeaderEnum.getHeader:()Ljava/lang/String;
     196: aload_0
     197: getfield      #41                 // Field acceptEncoding:Ljava/lang/String;
     200: invokespecial #30                 // Method setIfNotNull:(Lio/netty/handler/codec/http2/DefaultHttp2Headers;Ljava/lang/CharSequence;Ljava/lang/CharSequence;)V
     203: ldc           #43                 // String identity
     205: aload_0
     206: getfield      #44                 // Field compressor:Lorg/apache/dubbo/rpc/protocol/tri/compressor/Compressor;
     209: invokeinterface #45,  1           // InterfaceMethod org/apache/dubbo/rpc/protocol/tri/compressor/Compressor.getMessageEncoding:()Ljava/lang/String;
     214: invokevirtual #34                 // Method java/lang/String.equals:(Ljava/lang/Object;)Z
     217: ifne          240
     220: aload_0
     221: aload_1
     222: getstatic     #46                 // Field org/apache/dubbo/rpc/protocol/tri/TripleHeaderEnum.GRPC_ENCODING:Lorg/apache/dubbo/rpc/protocol/tri/TripleHeaderEnum;
     225: invokevirtual #21                 // Method org/apache/dubbo/rpc/protocol/tri/TripleHeaderEnum.getHeader:()Ljava/lang/String;
     228: aload_0
     229: getfield      #44                 // Field compressor:Lorg/apache/dubbo/rpc/protocol/tri/compressor/Compressor;
     232: invokeinterface #45,  1           // InterfaceMethod org/apache/dubbo/rpc/protocol/tri/compressor/Compressor.getMessageEncoding:()Ljava/lang/String;
     237: invokespecial #30                 // Method setIfNotNull:(Lio/netty/handler/codec/http2/DefaultHttp2Headers;Ljava/lang/CharSequence;Ljava/lang/CharSequence;)V
     240: aload_1
     241: aload_0
     242: getfield      #47                 // Field attachments:Ljava/util/Map;
     245: aload_0
     246: getfield      #48                 // Field convertNoLowerHeader:Z
     249: invokestatic  #49                 // Method org/apache/dubbo/rpc/protocol/tri/stream/StreamUtils.convertAttachment:(Lio/netty/handler/codec/http2/DefaultHttp2Headers;Ljava/util/Map;Z)V
     252: aload_1
     253: areturn

  private void setIfNotNull(io.netty.handler.codec.http2.DefaultHttp2Headers, java.lang.CharSequence, java.lang.CharSequence);
    Code:
       0: aload_3
       1: ifnonnull     5
       4: return
       5: aload_1
       6: aload_2
       7: aload_3
       8: invokevirtual #50                 // Method io/netty/handler/codec/http2/DefaultHttp2Headers.set:(Ljava/lang/Object;Ljava/lang/Object;)Lio/netty/handler/codec/Headers;
      11: pop
      12: return
}
