Compiled from "SingleProtobufUtils.java"
public final class org.apache.dubbo.rpc.protocol.tri.SingleProtobufUtils$SingleMessageMarshaller<T extends com.google.protobuf.MessageLite> {
  private final com.google.protobuf.Parser<T> parser;

  private final T defaultInstance;

  org.apache.dubbo.rpc.protocol.tri.SingleProtobufUtils$SingleMessageMarshaller(java.lang.Class<T>);
    Code:
       0: aload_0
       1: invokespecial #1                  // Method java/lang/Object."<init>":()V
       4: aload_0
       5: aload_1
       6: invokestatic  #2                  // Method org/apache/dubbo/rpc/protocol/tri/SingleProtobufUtils.defaultInst:(Ljava/lang/Class;)Lcom/google/protobuf/Message;
       9: putfield      #3                  // Field defaultInstance:Lcom/google/protobuf/MessageLite;
      12: aload_0
      13: aload_0
      14: getfield      #3                  // Field defaultInstance:Lcom/google/protobuf/MessageLite;
      17: invokeinterface #4,  1            // InterfaceMethod com/google/protobuf/MessageLite.getParserForType:()Lcom/google/protobuf/Parser;
      22: putfield      #5                  // Field parser:Lcom/google/protobuf/Parser;
      25: return

  org.apache.dubbo.rpc.protocol.tri.SingleProtobufUtils$SingleMessageMarshaller(T);
    Code:
       0: aload_0
       1: invokespecial #1                  // Method java/lang/Object."<init>":()V
       4: aload_0
       5: aload_1
       6: putfield      #3                  // Field defaultInstance:Lcom/google/protobuf/MessageLite;
       9: aload_0
      10: aload_1
      11: invokeinterface #4,  1            // InterfaceMethod com/google/protobuf/MessageLite.getParserForType:()Lcom/google/protobuf/Parser;
      16: putfield      #5                  // Field parser:Lcom/google/protobuf/Parser;
      19: return

  public T parse(java.io.InputStream) throws com.google.protobuf.InvalidProtocolBufferException;
    Code:
       0: aload_0
       1: getfield      #5                  // Field parser:Lcom/google/protobuf/Parser;
       4: aload_1
       5: invokestatic  #6                  // Method org/apache/dubbo/rpc/protocol/tri/SingleProtobufUtils.access$000:()Lcom/google/protobuf/ExtensionRegistryLite;
       8: invokeinterface #7,  3            // InterfaceMethod com/google/protobuf/Parser.parseFrom:(Ljava/io/InputStream;Lcom/google/protobuf/ExtensionRegistryLite;)Ljava/lang/Object;
      13: checkcast     #8                  // class com/google/protobuf/MessageLite
      16: areturn
}
