Compiled from "SingleProtobufUtils.java"
public class org.apache.dubbo.rpc.protocol.tri.SingleProtobufUtils {
  private static final java.util.concurrent.ConcurrentHashMap<java.lang.Class<?>, com.google.protobuf.Message> INST_CACHE;

  private static final com.google.protobuf.ExtensionRegistryLite GLOBAL_REGISTRY;

  private static final java.util.concurrent.ConcurrentMap<java.lang.Class<?>, org.apache.dubbo.rpc.protocol.tri.SingleProtobufUtils$SingleMessageMarshaller<?>> MARSHALLER_CACHE;

  public org.apache.dubbo.rpc.protocol.tri.SingleProtobufUtils();
    Code:
       0: aload_0
       1: invokespecial #2                  // Method java/lang/Object."<init>":()V
       4: return

  static boolean isSupported(java.lang.Class<?>);
    Code:
       0: aload_0
       1: ifnonnull     6
       4: iconst_0
       5: ireturn
       6: ldc           #3                  // class com/google/protobuf/MessageLite
       8: aload_0
       9: invokevirtual #4                  // Method java/lang/Class.isAssignableFrom:(Ljava/lang/Class;)Z
      12: ireturn

  public static <T extends com.google.protobuf.MessageLite> void marshaller(T);
    Code:
       0: getstatic     #5                  // Field MARSHALLER_CACHE:Ljava/util/concurrent/ConcurrentMap;
       3: aload_0
       4: invokevirtual #6                  // Method java/lang/Object.getClass:()Ljava/lang/Class;
       7: new           #7                  // class org/apache/dubbo/rpc/protocol/tri/SingleProtobufUtils$SingleMessageMarshaller
      10: dup
      11: aload_0
      12: invokespecial #8                  // Method org/apache/dubbo/rpc/protocol/tri/SingleProtobufUtils$SingleMessageMarshaller."<init>":(Lcom/google/protobuf/MessageLite;)V
      15: invokeinterface #9,  3            // InterfaceMethod java/util/concurrent/ConcurrentMap.put:(Ljava/lang/Object;Ljava/lang/Object;)Ljava/lang/Object;
      20: pop
      21: return

  public static com.google.protobuf.Message defaultInst(java.lang.Class<?>);
    Code:
       0: getstatic     #10                 // Field INST_CACHE:Ljava/util/concurrent/ConcurrentHashMap;
       3: aload_0
       4: invokevirtual #11                 // Method java/util/concurrent/ConcurrentHashMap.get:(Ljava/lang/Object;)Ljava/lang/Object;
       7: checkcast     #12                 // class com/google/protobuf/Message
      10: astore_1
      11: aload_1
      12: ifnull        17
      15: aload_1
      16: areturn
      17: aload_0
      18: ldc           #13                 // String getDefaultInstance
      20: iconst_0
      21: anewarray     #14                 // class java/lang/Class
      24: invokevirtual #15                 // Method java/lang/Class.getMethod:(Ljava/lang/String;[Ljava/lang/Class;)Ljava/lang/reflect/Method;
      27: aconst_null
      28: iconst_0
      29: anewarray     #16                 // class java/lang/Object
      32: invokevirtual #17                 // Method java/lang/reflect/Method.invoke:(Ljava/lang/Object;[Ljava/lang/Object;)Ljava/lang/Object;
      35: checkcast     #12                 // class com/google/protobuf/Message
      38: astore_1
      39: goto          54
      42: astore_2
      43: new           #21                 // class java/lang/RuntimeException
      46: dup
      47: ldc           #22                 // String Create default protobuf instance failed
      49: aload_2
      50: invokespecial #23                 // Method java/lang/RuntimeException."<init>":(Ljava/lang/String;Ljava/lang/Throwable;)V
      53: athrow
      54: getstatic     #10                 // Field INST_CACHE:Ljava/util/concurrent/ConcurrentHashMap;
      57: aload_0
      58: aload_1
      59: invokevirtual #24                 // Method java/util/concurrent/ConcurrentHashMap.put:(Ljava/lang/Object;Ljava/lang/Object;)Ljava/lang/Object;
      62: pop
      63: aload_1
      64: areturn
    Exception table:
       from    to  target type
          17    39    42   Class java/lang/IllegalAccessException
          17    39    42   Class java/lang/reflect/InvocationTargetException
          17    39    42   Class java/lang/NoSuchMethodException

  public static <T> com.google.protobuf.Parser<T> getParser(java.lang.Class<T>);
    Code:
       0: aload_0
       1: invokestatic  #25                 // Method defaultInst:(Ljava/lang/Class;)Lcom/google/protobuf/Message;
       4: astore_1
       5: aload_1
       6: invokeinterface #26,  1           // InterfaceMethod com/google/protobuf/Message.getParserForType:()Lcom/google/protobuf/Parser;
      11: areturn

  public static <T> T deserialize(java.io.InputStream, java.lang.Class<T>) throws java.io.IOException;
    Code:
       0: aload_1
       1: invokestatic  #27                 // Method isSupported:(Ljava/lang/Class;)Z
       4: ifne          37
       7: new           #28                 // class java/lang/IllegalArgumentException
      10: dup
      11: new           #29                 // class java/lang/StringBuilder
      14: dup
      15: invokespecial #30                 // Method java/lang/StringBuilder."<init>":()V
      18: ldc           #31                 // String This serialization only support google protobuf messages, but the actual input type is :
      20: invokevirtual #32                 // Method java/lang/StringBuilder.append:(Ljava/lang/String;)Ljava/lang/StringBuilder;
      23: aload_1
      24: invokevirtual #33                 // Method java/lang/Class.getName:()Ljava/lang/String;
      27: invokevirtual #32                 // Method java/lang/StringBuilder.append:(Ljava/lang/String;)Ljava/lang/StringBuilder;
      30: invokevirtual #34                 // Method java/lang/StringBuilder.toString:()Ljava/lang/String;
      33: invokespecial #35                 // Method java/lang/IllegalArgumentException."<init>":(Ljava/lang/String;)V
      36: athrow
      37: aload_1
      38: invokestatic  #36                 // Method getMarshaller:(Ljava/lang/Class;)Lorg/apache/dubbo/rpc/protocol/tri/SingleProtobufUtils$SingleMessageMarshaller;
      41: aload_0
      42: invokevirtual #37                 // Method org/apache/dubbo/rpc/protocol/tri/SingleProtobufUtils$SingleMessageMarshaller.parse:(Ljava/io/InputStream;)Lcom/google/protobuf/MessageLite;
      45: areturn
      46: astore_2
      47: new           #39                 // class java/io/IOException
      50: dup
      51: aload_2
      52: invokespecial #40                 // Method java/io/IOException."<init>":(Ljava/lang/Throwable;)V
      55: athrow
    Exception table:
       from    to  target type
          37    45    46   Class com/google/protobuf/InvalidProtocolBufferException

  public static void serialize(java.lang.Object, java.io.OutputStream) throws java.io.IOException;
    Code:
       0: aload_0
       1: checkcast     #3                  // class com/google/protobuf/MessageLite
       4: astore_2
       5: aload_2
       6: aload_1
       7: invokeinterface #41,  2           // InterfaceMethod com/google/protobuf/MessageLite.writeTo:(Ljava/io/OutputStream;)V
      12: return

  private static org.apache.dubbo.rpc.protocol.tri.SingleProtobufUtils$SingleMessageMarshaller<?> getMarshaller(java.lang.Class<?>);
    Code:
       0: getstatic     #5                  // Field MARSHALLER_CACHE:Ljava/util/concurrent/ConcurrentMap;
       3: aload_0
       4: invokedynamic #42,  0             // InvokeDynamic #0:apply:()Ljava/util/function/Function;
       9: invokestatic  #43                 // Method org/apache/dubbo/common/utils/ConcurrentHashMapUtils.computeIfAbsent:(Ljava/util/concurrent/ConcurrentMap;Ljava/lang/Object;Ljava/util/function/Function;)Ljava/lang/Object;
      12: checkcast     #7                  // class org/apache/dubbo/rpc/protocol/tri/SingleProtobufUtils$SingleMessageMarshaller
      15: areturn

  private static org.apache.dubbo.rpc.protocol.tri.SingleProtobufUtils$SingleMessageMarshaller lambda$getMarshaller$0(java.lang.Class);
    Code:
       0: new           #7                  // class org/apache/dubbo/rpc/protocol/tri/SingleProtobufUtils$SingleMessageMarshaller
       3: dup
       4: aload_0
       5: invokespecial #44                 // Method org/apache/dubbo/rpc/protocol/tri/SingleProtobufUtils$SingleMessageMarshaller."<init>":(Ljava/lang/Class;)V
       8: areturn

  static com.google.protobuf.ExtensionRegistryLite access$000();
    Code:
       0: getstatic     #1                  // Field GLOBAL_REGISTRY:Lcom/google/protobuf/ExtensionRegistryLite;
       3: areturn

  static {};
    Code:
       0: new           #45                 // class java/util/concurrent/ConcurrentHashMap
       3: dup
       4: invokespecial #46                 // Method java/util/concurrent/ConcurrentHashMap."<init>":()V
       7: putstatic     #10                 // Field INST_CACHE:Ljava/util/concurrent/ConcurrentHashMap;
      10: invokestatic  #47                 // Method com/google/protobuf/ExtensionRegistryLite.getEmptyRegistry:()Lcom/google/protobuf/ExtensionRegistryLite;
      13: putstatic     #1                  // Field GLOBAL_REGISTRY:Lcom/google/protobuf/ExtensionRegistryLite;
      16: new           #45                 // class java/util/concurrent/ConcurrentHashMap
      19: dup
      20: invokespecial #46                 // Method java/util/concurrent/ConcurrentHashMap."<init>":()V
      23: putstatic     #5                  // Field MARSHALLER_CACHE:Ljava/util/concurrent/ConcurrentMap;
      26: invokestatic  #48                 // Method com/google/protobuf/Empty.getDefaultInstance:()Lcom/google/protobuf/Empty;
      29: invokestatic  #49                 // Method marshaller:(Lcom/google/protobuf/MessageLite;)V
      32: invokestatic  #50                 // Method com/google/protobuf/BoolValue.getDefaultInstance:()Lcom/google/protobuf/BoolValue;
      35: invokestatic  #49                 // Method marshaller:(Lcom/google/protobuf/MessageLite;)V
      38: invokestatic  #51                 // Method com/google/protobuf/Int32Value.getDefaultInstance:()Lcom/google/protobuf/Int32Value;
      41: invokestatic  #49                 // Method marshaller:(Lcom/google/protobuf/MessageLite;)V
      44: invokestatic  #52                 // Method com/google/protobuf/Int64Value.getDefaultInstance:()Lcom/google/protobuf/Int64Value;
      47: invokestatic  #49                 // Method marshaller:(Lcom/google/protobuf/MessageLite;)V
      50: invokestatic  #53                 // Method com/google/protobuf/FloatValue.getDefaultInstance:()Lcom/google/protobuf/FloatValue;
      53: invokestatic  #49                 // Method marshaller:(Lcom/google/protobuf/MessageLite;)V
      56: invokestatic  #54                 // Method com/google/protobuf/DoubleValue.getDefaultInstance:()Lcom/google/protobuf/DoubleValue;
      59: invokestatic  #49                 // Method marshaller:(Lcom/google/protobuf/MessageLite;)V
      62: invokestatic  #55                 // Method com/google/protobuf/BytesValue.getDefaultInstance:()Lcom/google/protobuf/BytesValue;
      65: invokestatic  #49                 // Method marshaller:(Lcom/google/protobuf/MessageLite;)V
      68: invokestatic  #56                 // Method com/google/protobuf/StringValue.getDefaultInstance:()Lcom/google/protobuf/StringValue;
      71: invokestatic  #49                 // Method marshaller:(Lcom/google/protobuf/MessageLite;)V
      74: invokestatic  #57                 // Method com/google/protobuf/EnumValue.getDefaultInstance:()Lcom/google/protobuf/EnumValue;
      77: invokestatic  #49                 // Method marshaller:(Lcom/google/protobuf/MessageLite;)V
      80: invokestatic  #58                 // Method com/google/protobuf/ListValue.getDefaultInstance:()Lcom/google/protobuf/ListValue;
      83: invokestatic  #49                 // Method marshaller:(Lcom/google/protobuf/MessageLite;)V
      86: return
}
