Compiled from "TriHttp2RemoteFlowController.java"
final class org.apache.dubbo.rpc.protocol.tri.TriHttp2RemoteFlowController$ListenerWritabilityMonitor extends org.apache.dubbo.rpc.protocol.tri.TriHttp2RemoteFlowController$WritabilityMonitor implements io.netty.handler.codec.http2.Http2StreamVisitor {
  private final io.netty.handler.codec.http2.Http2RemoteFlowController$Listener listener;

  final org.apache.dubbo.rpc.protocol.tri.TriHttp2RemoteFlowController this$0;

  org.apache.dubbo.rpc.protocol.tri.TriHttp2RemoteFlowController$ListenerWritabilityMonitor(org.apache.dubbo.rpc.protocol.tri.TriHttp2RemoteFlowController, io.netty.handler.codec.http2.Http2RemoteFlowController$Listener);
    Code:
       0: aload_0
       1: aload_1
       2: putfield      #1                  // Field this$0:Lorg/apache/dubbo/rpc/protocol/tri/TriHttp2RemoteFlowController;
       5: aload_0
       6: aload_1
       7: aconst_null
       8: invokespecial #2                  // Method org/apache/dubbo/rpc/protocol/tri/TriHttp2RemoteFlowController$WritabilityMonitor."<init>":(Lorg/apache/dubbo/rpc/protocol/tri/TriHttp2RemoteFlowController;Lorg/apache/dubbo/rpc/protocol/tri/TriHttp2RemoteFlowController$1;)V
      11: aload_0
      12: aload_2
      13: putfield      #3                  // Field listener:Lio/netty/handler/codec/http2/Http2RemoteFlowController$Listener;
      16: return

  public boolean visit(io.netty.handler.codec.http2.Http2Stream) throws io.netty.handler.codec.http2.Http2Exception;
    Code:
       0: aload_0
       1: getfield      #1                  // Field this$0:Lorg/apache/dubbo/rpc/protocol/tri/TriHttp2RemoteFlowController;
       4: aload_1
       5: invokestatic  #4                  // Method org/apache/dubbo/rpc/protocol/tri/TriHttp2RemoteFlowController.access$100:(Lorg/apache/dubbo/rpc/protocol/tri/TriHttp2RemoteFlowController;Lio/netty/handler/codec/http2/Http2Stream;)Lorg/apache/dubbo/rpc/protocol/tri/TriHttp2RemoteFlowController$FlowState;
       8: astore_2
       9: aload_0
      10: aload_2
      11: invokevirtual #5                  // Method isWritable:(Lorg/apache/dubbo/rpc/protocol/tri/TriHttp2RemoteFlowController$FlowState;)Z
      14: aload_2
      15: invokevirtual #6                  // Method org/apache/dubbo/rpc/protocol/tri/TriHttp2RemoteFlowController$FlowState.markedWritability:()Z
      18: if_icmpeq     26
      21: aload_0
      22: aload_2
      23: invokespecial #7                  // Method notifyWritabilityChanged:(Lorg/apache/dubbo/rpc/protocol/tri/TriHttp2RemoteFlowController$FlowState;)V
      26: iconst_1
      27: ireturn

  void windowSize(org.apache.dubbo.rpc.protocol.tri.TriHttp2RemoteFlowController$FlowState, int);
    Code:
       0: aload_0
       1: aload_1
       2: iload_2
       3: invokespecial #8                  // Method org/apache/dubbo/rpc/protocol/tri/TriHttp2RemoteFlowController$WritabilityMonitor.windowSize:(Lorg/apache/dubbo/rpc/protocol/tri/TriHttp2RemoteFlowController$FlowState;I)V
       6: aload_0
       7: aload_1
       8: invokespecial #9                  // Method checkStateWritability:(Lorg/apache/dubbo/rpc/protocol/tri/TriHttp2RemoteFlowController$FlowState;)V
      11: goto          26
      14: astore_3
      15: new           #11                 // class java/lang/RuntimeException
      18: dup
      19: ldc           #12                 // String Caught unexpected exception from window
      21: aload_3
      22: invokespecial #13                 // Method java/lang/RuntimeException."<init>":(Ljava/lang/String;Ljava/lang/Throwable;)V
      25: athrow
      26: return
    Exception table:
       from    to  target type
           6    11    14   Class io/netty/handler/codec/http2/Http2Exception

  void incrementWindowSize(org.apache.dubbo.rpc.protocol.tri.TriHttp2RemoteFlowController$FlowState, int) throws io.netty.handler.codec.http2.Http2Exception;
    Code:
       0: aload_0
       1: aload_1
       2: iload_2
       3: invokespecial #14                 // Method org/apache/dubbo/rpc/protocol/tri/TriHttp2RemoteFlowController$WritabilityMonitor.incrementWindowSize:(Lorg/apache/dubbo/rpc/protocol/tri/TriHttp2RemoteFlowController$FlowState;I)V
       6: aload_0
       7: aload_1
       8: invokespecial #9                  // Method checkStateWritability:(Lorg/apache/dubbo/rpc/protocol/tri/TriHttp2RemoteFlowController$FlowState;)V
      11: return

  void initialWindowSize(int) throws io.netty.handler.codec.http2.Http2Exception;
    Code:
       0: aload_0
       1: iload_1
       2: invokespecial #15                 // Method org/apache/dubbo/rpc/protocol/tri/TriHttp2RemoteFlowController$WritabilityMonitor.initialWindowSize:(I)V
       5: aload_0
       6: invokevirtual #16                 // Method isWritableConnection:()Z
       9: ifeq          16
      12: aload_0
      13: invokespecial #17                 // Method checkAllWritabilityChanged:()V
      16: return

  void enqueueFrame(org.apache.dubbo.rpc.protocol.tri.TriHttp2RemoteFlowController$FlowState, io.netty.handler.codec.http2.Http2RemoteFlowController$FlowControlled) throws io.netty.handler.codec.http2.Http2Exception;
    Code:
       0: aload_0
       1: aload_1
       2: aload_2
       3: invokespecial #18                 // Method org/apache/dubbo/rpc/protocol/tri/TriHttp2RemoteFlowController$WritabilityMonitor.enqueueFrame:(Lorg/apache/dubbo/rpc/protocol/tri/TriHttp2RemoteFlowController$FlowState;Lio/netty/handler/codec/http2/Http2RemoteFlowController$FlowControlled;)V
       6: aload_0
       7: aload_1
       8: invokespecial #19                 // Method checkConnectionThenStreamWritabilityChanged:(Lorg/apache/dubbo/rpc/protocol/tri/TriHttp2RemoteFlowController$FlowState;)V
      11: return

  void stateCancelled(org.apache.dubbo.rpc.protocol.tri.TriHttp2RemoteFlowController$FlowState);
    Code:
       0: aload_0
       1: aload_1
       2: invokespecial #19                 // Method checkConnectionThenStreamWritabilityChanged:(Lorg/apache/dubbo/rpc/protocol/tri/TriHttp2RemoteFlowController$FlowState;)V
       5: goto          20
       8: astore_2
       9: new           #11                 // class java/lang/RuntimeException
      12: dup
      13: ldc           #20                 // String Caught unexpected exception from checkAllWritabilityChanged
      15: aload_2
      16: invokespecial #13                 // Method java/lang/RuntimeException."<init>":(Ljava/lang/String;Ljava/lang/Throwable;)V
      19: athrow
      20: return
    Exception table:
       from    to  target type
           0     5     8   Class io/netty/handler/codec/http2/Http2Exception

  void channelWritabilityChange() throws io.netty.handler.codec.http2.Http2Exception;
    Code:
       0: aload_0
       1: getfield      #1                  // Field this$0:Lorg/apache/dubbo/rpc/protocol/tri/TriHttp2RemoteFlowController;
       4: invokestatic  #21                 // Method org/apache/dubbo/rpc/protocol/tri/TriHttp2RemoteFlowController.access$800:(Lorg/apache/dubbo/rpc/protocol/tri/TriHttp2RemoteFlowController;)Lorg/apache/dubbo/rpc/protocol/tri/TriHttp2RemoteFlowController$FlowState;
       7: invokevirtual #6                  // Method org/apache/dubbo/rpc/protocol/tri/TriHttp2RemoteFlowController$FlowState.markedWritability:()Z
      10: aload_0
      11: getfield      #1                  // Field this$0:Lorg/apache/dubbo/rpc/protocol/tri/TriHttp2RemoteFlowController;
      14: invokestatic  #22                 // Method org/apache/dubbo/rpc/protocol/tri/TriHttp2RemoteFlowController.access$1200:(Lorg/apache/dubbo/rpc/protocol/tri/TriHttp2RemoteFlowController;)Z
      17: if_icmpeq     24
      20: aload_0
      21: invokespecial #17                 // Method checkAllWritabilityChanged:()V
      24: return

  private void checkStateWritability(org.apache.dubbo.rpc.protocol.tri.TriHttp2RemoteFlowController$FlowState) throws io.netty.handler.codec.http2.Http2Exception;
    Code:
       0: aload_0
       1: aload_1
       2: invokevirtual #5                  // Method isWritable:(Lorg/apache/dubbo/rpc/protocol/tri/TriHttp2RemoteFlowController$FlowState;)Z
       5: aload_1
       6: invokevirtual #6                  // Method org/apache/dubbo/rpc/protocol/tri/TriHttp2RemoteFlowController$FlowState.markedWritability:()Z
       9: if_icmpeq     35
      12: aload_1
      13: aload_0
      14: getfield      #1                  // Field this$0:Lorg/apache/dubbo/rpc/protocol/tri/TriHttp2RemoteFlowController;
      17: invokestatic  #21                 // Method org/apache/dubbo/rpc/protocol/tri/TriHttp2RemoteFlowController.access$800:(Lorg/apache/dubbo/rpc/protocol/tri/TriHttp2RemoteFlowController;)Lorg/apache/dubbo/rpc/protocol/tri/TriHttp2RemoteFlowController$FlowState;
      20: if_acmpne     30
      23: aload_0
      24: invokespecial #17                 // Method checkAllWritabilityChanged:()V
      27: goto          35
      30: aload_0
      31: aload_1
      32: invokespecial #7                  // Method notifyWritabilityChanged:(Lorg/apache/dubbo/rpc/protocol/tri/TriHttp2RemoteFlowController$FlowState;)V
      35: return

  private void notifyWritabilityChanged(org.apache.dubbo.rpc.protocol.tri.TriHttp2RemoteFlowController$FlowState);
    Code:
       0: aload_1
       1: aload_1
       2: invokevirtual #6                  // Method org/apache/dubbo/rpc/protocol/tri/TriHttp2RemoteFlowController$FlowState.markedWritability:()Z
       5: ifne          12
       8: iconst_1
       9: goto          13
      12: iconst_0
      13: invokevirtual #23                 // Method org/apache/dubbo/rpc/protocol/tri/TriHttp2RemoteFlowController$FlowState.markedWritability:(Z)V
      16: aload_0
      17: getfield      #3                  // Field listener:Lio/netty/handler/codec/http2/Http2RemoteFlowController$Listener;
      20: aload_1
      21: invokestatic  #24                 // Method org/apache/dubbo/rpc/protocol/tri/TriHttp2RemoteFlowController$FlowState.access$1300:(Lorg/apache/dubbo/rpc/protocol/tri/TriHttp2RemoteFlowController$FlowState;)Lio/netty/handler/codec/http2/Http2Stream;
      24: invokeinterface #25,  2           // InterfaceMethod io/netty/handler/codec/http2/Http2RemoteFlowController$Listener.writabilityChanged:(Lio/netty/handler/codec/http2/Http2Stream;)V
      29: goto          44
      32: astore_2
      33: invokestatic  #27                 // Method org/apache/dubbo/rpc/protocol/tri/TriHttp2RemoteFlowController.access$1400:()Lio/netty/util/internal/logging/InternalLogger;
      36: ldc           #28                 // String Caught Throwable from listener.writabilityChanged
      38: aload_2
      39: invokeinterface #29,  3           // InterfaceMethod io/netty/util/internal/logging/InternalLogger.error:(Ljava/lang/String;Ljava/lang/Throwable;)V
      44: return
    Exception table:
       from    to  target type
          16    29    32   Class java/lang/Throwable

  private void checkConnectionThenStreamWritabilityChanged(org.apache.dubbo.rpc.protocol.tri.TriHttp2RemoteFlowController$FlowState) throws io.netty.handler.codec.http2.Http2Exception;
    Code:
       0: aload_0
       1: invokevirtual #16                 // Method isWritableConnection:()Z
       4: aload_0
       5: getfield      #1                  // Field this$0:Lorg/apache/dubbo/rpc/protocol/tri/TriHttp2RemoteFlowController;
       8: invokestatic  #21                 // Method org/apache/dubbo/rpc/protocol/tri/TriHttp2RemoteFlowController.access$800:(Lorg/apache/dubbo/rpc/protocol/tri/TriHttp2RemoteFlowController;)Lorg/apache/dubbo/rpc/protocol/tri/TriHttp2RemoteFlowController$FlowState;
      11: invokevirtual #6                  // Method org/apache/dubbo/rpc/protocol/tri/TriHttp2RemoteFlowController$FlowState.markedWritability:()Z
      14: if_icmpeq     24
      17: aload_0
      18: invokespecial #17                 // Method checkAllWritabilityChanged:()V
      21: goto          88
      24: aload_0
      25: aload_1
      26: invokevirtual #5                  // Method isWritable:(Lorg/apache/dubbo/rpc/protocol/tri/TriHttp2RemoteFlowController$FlowState;)Z
      29: aload_1
      30: invokevirtual #6                  // Method org/apache/dubbo/rpc/protocol/tri/TriHttp2RemoteFlowController$FlowState.markedWritability:()Z
      33: if_icmpeq     44
      36: aload_0
      37: aload_1
      38: invokespecial #7                  // Method notifyWritabilityChanged:(Lorg/apache/dubbo/rpc/protocol/tri/TriHttp2RemoteFlowController$FlowState;)V
      41: goto          88
      44: aload_0
      45: invokevirtual #30                 // Method isOverFlowControl:()Z
      48: ifeq          88
      51: aload_1
      52: invokevirtual #31                 // Method org/apache/dubbo/rpc/protocol/tri/TriHttp2RemoteFlowController$FlowState.stream:()Lio/netty/handler/codec/http2/Http2Stream;
      55: invokeinterface #32,  1           // InterfaceMethod io/netty/handler/codec/http2/Http2Stream.id:()I
      60: getstatic     #33                 // Field io/netty/handler/codec/http2/Http2Error.FLOW_CONTROL_ERROR:Lio/netty/handler/codec/http2/Http2Error;
      63: ldc           #34                 // String TotalPendingBytes size overflow for stream: %d
      65: iconst_1
      66: anewarray     #35                 // class java/lang/Object
      69: dup
      70: iconst_0
      71: aload_1
      72: invokevirtual #31                 // Method org/apache/dubbo/rpc/protocol/tri/TriHttp2RemoteFlowController$FlowState.stream:()Lio/netty/handler/codec/http2/Http2Stream;
      75: invokeinterface #32,  1           // InterfaceMethod io/netty/handler/codec/http2/Http2Stream.id:()I
      80: invokestatic  #36                 // Method java/lang/Integer.valueOf:(I)Ljava/lang/Integer;
      83: aastore
      84: invokestatic  #37                 // Method io/netty/handler/codec/http2/Http2Exception.streamError:(ILio/netty/handler/codec/http2/Http2Error;Ljava/lang/String;[Ljava/lang/Object;)Lio/netty/handler/codec/http2/Http2Exception;
      87: athrow
      88: return

  private void checkAllWritabilityChanged() throws io.netty.handler.codec.http2.Http2Exception;
    Code:
       0: aload_0
       1: getfield      #1                  // Field this$0:Lorg/apache/dubbo/rpc/protocol/tri/TriHttp2RemoteFlowController;
       4: invokestatic  #21                 // Method org/apache/dubbo/rpc/protocol/tri/TriHttp2RemoteFlowController.access$800:(Lorg/apache/dubbo/rpc/protocol/tri/TriHttp2RemoteFlowController;)Lorg/apache/dubbo/rpc/protocol/tri/TriHttp2RemoteFlowController$FlowState;
       7: aload_0
       8: invokevirtual #16                 // Method isWritableConnection:()Z
      11: invokevirtual #23                 // Method org/apache/dubbo/rpc/protocol/tri/TriHttp2RemoteFlowController$FlowState.markedWritability:(Z)V
      14: aload_0
      15: getfield      #1                  // Field this$0:Lorg/apache/dubbo/rpc/protocol/tri/TriHttp2RemoteFlowController;
      18: invokestatic  #38                 // Method org/apache/dubbo/rpc/protocol/tri/TriHttp2RemoteFlowController.access$1100:(Lorg/apache/dubbo/rpc/protocol/tri/TriHttp2RemoteFlowController;)Lio/netty/handler/codec/http2/Http2Connection;
      21: aload_0
      22: invokeinterface #39,  2           // InterfaceMethod io/netty/handler/codec/http2/Http2Connection.forEachActiveStream:(Lio/netty/handler/codec/http2/Http2StreamVisitor;)Lio/netty/handler/codec/http2/Http2Stream;
      27: pop
      28: return
}
