Compiled from "TriHttp2RemoteFlowController.java"
class org.apache.dubbo.rpc.protocol.tri.TriHttp2RemoteFlowController$WritabilityMonitor$1 implements io.netty.handler.codec.http2.Http2StreamVisitor {
  final int val$delta;

  final org.apache.dubbo.rpc.protocol.tri.TriHttp2RemoteFlowController$WritabilityMonitor this$1;

  org.apache.dubbo.rpc.protocol.tri.TriHttp2RemoteFlowController$WritabilityMonitor$1(org.apache.dubbo.rpc.protocol.tri.TriHttp2RemoteFlowController$WritabilityMonitor, int);
    Code:
       0: aload_0
       1: aload_1
       2: putfield      #1                  // Field this$1:Lorg/apache/dubbo/rpc/protocol/tri/TriHttp2RemoteFlowController$WritabilityMonitor;
       5: aload_0
       6: iload_2
       7: putfield      #2                  // Field val$delta:I
      10: aload_0
      11: invokespecial #3                  // Method java/lang/Object."<init>":()V
      14: return

  public boolean visit(io.netty.handler.codec.http2.Http2Stream) throws io.netty.handler.codec.http2.Http2Exception;
    Code:
       0: aload_0
       1: getfield      #1                  // Field this$1:Lorg/apache/dubbo/rpc/protocol/tri/TriHttp2RemoteFlowController$WritabilityMonitor;
       4: getfield      #4                  // Field org/apache/dubbo/rpc/protocol/tri/TriHttp2RemoteFlowController$WritabilityMonitor.this$0:Lorg/apache/dubbo/rpc/protocol/tri/TriHttp2RemoteFlowController;
       7: aload_1
       8: invokestatic  #5                  // Method org/apache/dubbo/rpc/protocol/tri/TriHttp2RemoteFlowController.access$100:(Lorg/apache/dubbo/rpc/protocol/tri/TriHttp2RemoteFlowController;Lio/netty/handler/codec/http2/Http2Stream;)Lorg/apache/dubbo/rpc/protocol/tri/TriHttp2RemoteFlowController$FlowState;
      11: aload_0
      12: getfield      #2                  // Field val$delta:I
      15: invokevirtual #6                  // Method org/apache/dubbo/rpc/protocol/tri/TriHttp2RemoteFlowController$FlowState.incrementStreamWindow:(I)I
      18: pop
      19: iconst_1
      20: ireturn
}
