Compiled from "TriHttp2RemoteFlowController.java"
public class org.apache.dubbo.rpc.protocol.tri.TriHttp2RemoteFlowController implements io.netty.handler.codec.http2.Http2RemoteFlowController {
  private static final io.netty.util.internal.logging.InternalLogger logger;

  private static final int MIN_WRITABLE_CHUNK;

  private final io.netty.handler.codec.http2.Http2Connection connection;

  private final io.netty.handler.codec.http2.Http2Connection$PropertyKey stateKey;

  private final io.netty.handler.codec.http2.StreamByteDistributor streamByteDistributor;

  private final org.apache.dubbo.rpc.protocol.tri.TriHttp2RemoteFlowController$FlowState connectionState;

  private final org.apache.dubbo.common.config.Configuration config;

  private int initialWindowSize;

  private org.apache.dubbo.rpc.protocol.tri.TriHttp2RemoteFlowController$WritabilityMonitor monitor;

  private io.netty.channel.ChannelHandlerContext ctx;

  static final boolean $assertionsDisabled;

  public org.apache.dubbo.rpc.protocol.tri.TriHttp2RemoteFlowController(io.netty.handler.codec.http2.Http2Connection, org.apache.dubbo.rpc.model.ApplicationModel);
    Code:
       0: aload_0
       1: aload_1
       2: aconst_null
       3: checkcast     #16                 // class io/netty/handler/codec/http2/Http2RemoteFlowController$Listener
       6: aload_2
       7: invokespecial #17                 // Method "<init>":(Lio/netty/handler/codec/http2/Http2Connection;Lio/netty/handler/codec/http2/Http2RemoteFlowController$Listener;Lorg/apache/dubbo/rpc/model/ApplicationModel;)V
      10: return

  public org.apache.dubbo.rpc.protocol.tri.TriHttp2RemoteFlowController(io.netty.handler.codec.http2.Http2Connection, io.netty.handler.codec.http2.StreamByteDistributor, org.apache.dubbo.rpc.model.ApplicationModel);
    Code:
       0: aload_0
       1: aload_1
       2: aload_2
       3: aconst_null
       4: aload_3
       5: invokespecial #18                 // Method "<init>":(Lio/netty/handler/codec/http2/Http2Connection;Lio/netty/handler/codec/http2/StreamByteDistributor;Lio/netty/handler/codec/http2/Http2RemoteFlowController$Listener;Lorg/apache/dubbo/rpc/model/ApplicationModel;)V
       8: return

  public org.apache.dubbo.rpc.protocol.tri.TriHttp2RemoteFlowController(io.netty.handler.codec.http2.Http2Connection, io.netty.handler.codec.http2.Http2RemoteFlowController$Listener, org.apache.dubbo.rpc.model.ApplicationModel);
    Code:
       0: aload_0
       1: aload_1
       2: new           #19                 // class io/netty/handler/codec/http2/WeightedFairQueueByteDistributor
       5: dup
       6: aload_1
       7: invokespecial #20                 // Method io/netty/handler/codec/http2/WeightedFairQueueByteDistributor."<init>":(Lio/netty/handler/codec/http2/Http2Connection;)V
      10: aload_2
      11: aload_3
      12: invokespecial #18                 // Method "<init>":(Lio/netty/handler/codec/http2/Http2Connection;Lio/netty/handler/codec/http2/StreamByteDistributor;Lio/netty/handler/codec/http2/Http2RemoteFlowController$Listener;Lorg/apache/dubbo/rpc/model/ApplicationModel;)V
      15: return

  public org.apache.dubbo.rpc.protocol.tri.TriHttp2RemoteFlowController(io.netty.handler.codec.http2.Http2Connection, io.netty.handler.codec.http2.StreamByteDistributor, io.netty.handler.codec.http2.Http2RemoteFlowController$Listener, org.apache.dubbo.rpc.model.ApplicationModel);
    Code:
       0: aload_0
       1: invokespecial #21                 // Method java/lang/Object."<init>":()V
       4: aload_0
       5: aload_1
       6: ldc           #22                 // String connection
       8: invokestatic  #23                 // Method io/netty/util/internal/ObjectUtil.checkNotNull:(Ljava/lang/Object;Ljava/lang/String;)Ljava/lang/Object;
      11: checkcast     #24                 // class io/netty/handler/codec/http2/Http2Connection
      14: putfield      #5                  // Field connection:Lio/netty/handler/codec/http2/Http2Connection;
      17: aload_0
      18: aload_2
      19: ldc           #25                 // String streamWriteDistributor
      21: invokestatic  #23                 // Method io/netty/util/internal/ObjectUtil.checkNotNull:(Ljava/lang/Object;Ljava/lang/String;)Ljava/lang/Object;
      24: checkcast     #26                 // class io/netty/handler/codec/http2/StreamByteDistributor
      27: putfield      #10                 // Field streamByteDistributor:Lio/netty/handler/codec/http2/StreamByteDistributor;
      30: aload_0
      31: aload         4
      33: invokestatic  #27                 // Method org/apache/dubbo/common/config/ConfigurationUtils.getGlobalConfiguration:(Lorg/apache/dubbo/rpc/model/ScopeModel;)Lorg/apache/dubbo/common/config/Configuration;
      36: putfield      #28                 // Field config:Lorg/apache/dubbo/common/config/Configuration;
      39: aload_0
      40: aload_0
      41: getfield      #28                 // Field config:Lorg/apache/dubbo/common/config/Configuration;
      44: ldc           #29                 // String dubbo.rpc.tri.initial-window-size
      46: ldc           #30                 // int 65535
      48: invokeinterface #31,  3           // InterfaceMethod org/apache/dubbo/common/config/Configuration.getInt:(Ljava/lang/String;I)I
      53: putfield      #13                 // Field initialWindowSize:I
      56: aload_0
      57: aload_1
      58: invokeinterface #32,  1           // InterfaceMethod io/netty/handler/codec/http2/Http2Connection.newKey:()Lio/netty/handler/codec/http2/Http2Connection$PropertyKey;
      63: putfield      #15                 // Field stateKey:Lio/netty/handler/codec/http2/Http2Connection$PropertyKey;
      66: aload_0
      67: new           #33                 // class org/apache/dubbo/rpc/protocol/tri/TriHttp2RemoteFlowController$FlowState
      70: dup
      71: aload_0
      72: aload_1
      73: invokeinterface #34,  1           // InterfaceMethod io/netty/handler/codec/http2/Http2Connection.connectionStream:()Lio/netty/handler/codec/http2/Http2Stream;
      78: invokespecial #35                 // Method org/apache/dubbo/rpc/protocol/tri/TriHttp2RemoteFlowController$FlowState."<init>":(Lorg/apache/dubbo/rpc/protocol/tri/TriHttp2RemoteFlowController;Lio/netty/handler/codec/http2/Http2Stream;)V
      81: putfield      #8                  // Field connectionState:Lorg/apache/dubbo/rpc/protocol/tri/TriHttp2RemoteFlowController$FlowState;
      84: aload_1
      85: invokeinterface #34,  1           // InterfaceMethod io/netty/handler/codec/http2/Http2Connection.connectionStream:()Lio/netty/handler/codec/http2/Http2Stream;
      90: aload_0
      91: getfield      #15                 // Field stateKey:Lio/netty/handler/codec/http2/Http2Connection$PropertyKey;
      94: aload_0
      95: getfield      #8                  // Field connectionState:Lorg/apache/dubbo/rpc/protocol/tri/TriHttp2RemoteFlowController$FlowState;
      98: invokeinterface #36,  3           // InterfaceMethod io/netty/handler/codec/http2/Http2Stream.setProperty:(Lio/netty/handler/codec/http2/Http2Connection$PropertyKey;Ljava/lang/Object;)Ljava/lang/Object;
     103: pop
     104: aload_0
     105: aload_3
     106: invokevirtual #37                 // Method listener:(Lio/netty/handler/codec/http2/Http2RemoteFlowController$Listener;)V
     109: aload_0
     110: getfield      #12                 // Field monitor:Lorg/apache/dubbo/rpc/protocol/tri/TriHttp2RemoteFlowController$WritabilityMonitor;
     113: aload_0
     114: getfield      #8                  // Field connectionState:Lorg/apache/dubbo/rpc/protocol/tri/TriHttp2RemoteFlowController$FlowState;
     117: aload_0
     118: getfield      #13                 // Field initialWindowSize:I
     121: invokevirtual #38                 // Method org/apache/dubbo/rpc/protocol/tri/TriHttp2RemoteFlowController$WritabilityMonitor.windowSize:(Lorg/apache/dubbo/rpc/protocol/tri/TriHttp2RemoteFlowController$FlowState;I)V
     124: aload_1
     125: new           #39                 // class org/apache/dubbo/rpc/protocol/tri/TriHttp2RemoteFlowController$1
     128: dup
     129: aload_0
     130: invokespecial #40                 // Method org/apache/dubbo/rpc/protocol/tri/TriHttp2RemoteFlowController$1."<init>":(Lorg/apache/dubbo/rpc/protocol/tri/TriHttp2RemoteFlowController;)V
     133: invokeinterface #41,  2           // InterfaceMethod io/netty/handler/codec/http2/Http2Connection.addListener:(Lio/netty/handler/codec/http2/Http2Connection$Listener;)V
     138: return

  public void channelHandlerContext(io.netty.channel.ChannelHandlerContext) throws io.netty.handler.codec.http2.Http2Exception;
    Code:
       0: aload_0
       1: aload_1
       2: ldc           #42                 // String ctx
       4: invokestatic  #23                 // Method io/netty/util/internal/ObjectUtil.checkNotNull:(Ljava/lang/Object;Ljava/lang/String;)Ljava/lang/Object;
       7: checkcast     #43                 // class io/netty/channel/ChannelHandlerContext
      10: putfield      #11                 // Field ctx:Lio/netty/channel/ChannelHandlerContext;
      13: aload_0
      14: invokevirtual #44                 // Method channelWritabilityChanged:()V
      17: aload_0
      18: invokespecial #4                  // Method isChannelWritable:()Z
      21: ifeq          28
      24: aload_0
      25: invokevirtual #45                 // Method writePendingBytes:()V
      28: return

  public io.netty.channel.ChannelHandlerContext channelHandlerContext();
    Code:
       0: aload_0
       1: getfield      #11                 // Field ctx:Lio/netty/channel/ChannelHandlerContext;
       4: areturn

  public void initialWindowSize(int) throws io.netty.handler.codec.http2.Http2Exception;
    Code:
       0: getstatic     #46                 // Field $assertionsDisabled:Z
       3: ifne          38
       6: aload_0
       7: getfield      #11                 // Field ctx:Lio/netty/channel/ChannelHandlerContext;
      10: ifnull        38
      13: aload_0
      14: getfield      #11                 // Field ctx:Lio/netty/channel/ChannelHandlerContext;
      17: invokeinterface #47,  1           // InterfaceMethod io/netty/channel/ChannelHandlerContext.executor:()Lio/netty/util/concurrent/EventExecutor;
      22: invokeinterface #48,  1           // InterfaceMethod io/netty/util/concurrent/EventExecutor.inEventLoop:()Z
      27: ifne          38
      30: new           #49                 // class java/lang/AssertionError
      33: dup
      34: invokespecial #50                 // Method java/lang/AssertionError."<init>":()V
      37: athrow
      38: aload_0
      39: getfield      #12                 // Field monitor:Lorg/apache/dubbo/rpc/protocol/tri/TriHttp2RemoteFlowController$WritabilityMonitor;
      42: iload_1
      43: invokevirtual #51                 // Method org/apache/dubbo/rpc/protocol/tri/TriHttp2RemoteFlowController$WritabilityMonitor.initialWindowSize:(I)V
      46: return

  public int initialWindowSize();
    Code:
       0: aload_0
       1: getfield      #13                 // Field initialWindowSize:I
       4: ireturn

  public int windowSize(io.netty.handler.codec.http2.Http2Stream);
    Code:
       0: aload_0
       1: aload_1
       2: invokespecial #14                 // Method state:(Lio/netty/handler/codec/http2/Http2Stream;)Lorg/apache/dubbo/rpc/protocol/tri/TriHttp2RemoteFlowController$FlowState;
       5: invokevirtual #52                 // Method org/apache/dubbo/rpc/protocol/tri/TriHttp2RemoteFlowController$FlowState.windowSize:()I
       8: ireturn

  public boolean isWritable(io.netty.handler.codec.http2.Http2Stream);
    Code:
       0: aload_0
       1: getfield      #12                 // Field monitor:Lorg/apache/dubbo/rpc/protocol/tri/TriHttp2RemoteFlowController$WritabilityMonitor;
       4: aload_0
       5: aload_1
       6: invokespecial #14                 // Method state:(Lio/netty/handler/codec/http2/Http2Stream;)Lorg/apache/dubbo/rpc/protocol/tri/TriHttp2RemoteFlowController$FlowState;
       9: invokevirtual #53                 // Method org/apache/dubbo/rpc/protocol/tri/TriHttp2RemoteFlowController$WritabilityMonitor.isWritable:(Lorg/apache/dubbo/rpc/protocol/tri/TriHttp2RemoteFlowController$FlowState;)Z
      12: ireturn

  public void channelWritabilityChanged() throws io.netty.handler.codec.http2.Http2Exception;
    Code:
       0: aload_0
       1: getfield      #12                 // Field monitor:Lorg/apache/dubbo/rpc/protocol/tri/TriHttp2RemoteFlowController$WritabilityMonitor;
       4: invokevirtual #54                 // Method org/apache/dubbo/rpc/protocol/tri/TriHttp2RemoteFlowController$WritabilityMonitor.channelWritabilityChange:()V
       7: return

  public void updateDependencyTree(int, int, short, boolean);
    Code:
       0: getstatic     #46                 // Field $assertionsDisabled:Z
       3: ifne          28
       6: iload_3
       7: iconst_1
       8: if_icmplt     18
      11: iload_3
      12: sipush        256
      15: if_icmple     28
      18: new           #49                 // class java/lang/AssertionError
      21: dup
      22: ldc           #55                 // String Invalid weight
      24: invokespecial #56                 // Method java/lang/AssertionError."<init>":(Ljava/lang/Object;)V
      27: athrow
      28: getstatic     #46                 // Field $assertionsDisabled:Z
      31: ifne          49
      34: iload_1
      35: iload_2
      36: if_icmpne     49
      39: new           #49                 // class java/lang/AssertionError
      42: dup
      43: ldc           #57                 // String A stream cannot depend on itself
      45: invokespecial #56                 // Method java/lang/AssertionError."<init>":(Ljava/lang/Object;)V
      48: athrow
      49: getstatic     #46                 // Field $assertionsDisabled:Z
      52: ifne          73
      55: iload_1
      56: ifle          63
      59: iload_2
      60: ifge          73
      63: new           #49                 // class java/lang/AssertionError
      66: dup
      67: ldc           #58                 // String childStreamId must be > 0. parentStreamId must be >= 0.
      69: invokespecial #56                 // Method java/lang/AssertionError."<init>":(Ljava/lang/Object;)V
      72: athrow
      73: aload_0
      74: getfield      #10                 // Field streamByteDistributor:Lio/netty/handler/codec/http2/StreamByteDistributor;
      77: iload_1
      78: iload_2
      79: iload_3
      80: iload         4
      82: invokeinterface #59,  5           // InterfaceMethod io/netty/handler/codec/http2/StreamByteDistributor.updateDependencyTree:(IISZ)V
      87: return

  private boolean isChannelWritable();
    Code:
       0: aload_0
       1: getfield      #11                 // Field ctx:Lio/netty/channel/ChannelHandlerContext;
       4: ifnull        18
       7: aload_0
       8: invokespecial #6                  // Method isChannelWritable0:()Z
      11: ifeq          18
      14: iconst_1
      15: goto          19
      18: iconst_0
      19: ireturn

  private boolean isChannelWritable0();
    Code:
       0: aload_0
       1: getfield      #11                 // Field ctx:Lio/netty/channel/ChannelHandlerContext;
       4: invokeinterface #60,  1           // InterfaceMethod io/netty/channel/ChannelHandlerContext.channel:()Lio/netty/channel/Channel;
       9: invokeinterface #61,  1           // InterfaceMethod io/netty/channel/Channel.isWritable:()Z
      14: ireturn

  public void listener(io.netty.handler.codec.http2.Http2RemoteFlowController$Listener);
    Code:
       0: aload_0
       1: aload_1
       2: ifnonnull     17
       5: new           #62                 // class org/apache/dubbo/rpc/protocol/tri/TriHttp2RemoteFlowController$WritabilityMonitor
       8: dup
       9: aload_0
      10: aconst_null
      11: invokespecial #63                 // Method org/apache/dubbo/rpc/protocol/tri/TriHttp2RemoteFlowController$WritabilityMonitor."<init>":(Lorg/apache/dubbo/rpc/protocol/tri/TriHttp2RemoteFlowController;Lorg/apache/dubbo/rpc/protocol/tri/TriHttp2RemoteFlowController$1;)V
      14: goto          26
      17: new           #64                 // class org/apache/dubbo/rpc/protocol/tri/TriHttp2RemoteFlowController$ListenerWritabilityMonitor
      20: dup
      21: aload_0
      22: aload_1
      23: invokespecial #65                 // Method org/apache/dubbo/rpc/protocol/tri/TriHttp2RemoteFlowController$ListenerWritabilityMonitor."<init>":(Lorg/apache/dubbo/rpc/protocol/tri/TriHttp2RemoteFlowController;Lio/netty/handler/codec/http2/Http2RemoteFlowController$Listener;)V
      26: putfield      #12                 // Field monitor:Lorg/apache/dubbo/rpc/protocol/tri/TriHttp2RemoteFlowController$WritabilityMonitor;
      29: return

  public void incrementWindowSize(io.netty.handler.codec.http2.Http2Stream, int) throws io.netty.handler.codec.http2.Http2Exception;
    Code:
       0: getstatic     #46                 // Field $assertionsDisabled:Z
       3: ifne          38
       6: aload_0
       7: getfield      #11                 // Field ctx:Lio/netty/channel/ChannelHandlerContext;
      10: ifnull        38
      13: aload_0
      14: getfield      #11                 // Field ctx:Lio/netty/channel/ChannelHandlerContext;
      17: invokeinterface #47,  1           // InterfaceMethod io/netty/channel/ChannelHandlerContext.executor:()Lio/netty/util/concurrent/EventExecutor;
      22: invokeinterface #48,  1           // InterfaceMethod io/netty/util/concurrent/EventExecutor.inEventLoop:()Z
      27: ifne          38
      30: new           #49                 // class java/lang/AssertionError
      33: dup
      34: invokespecial #50                 // Method java/lang/AssertionError."<init>":()V
      37: athrow
      38: aload_0
      39: getfield      #12                 // Field monitor:Lorg/apache/dubbo/rpc/protocol/tri/TriHttp2RemoteFlowController$WritabilityMonitor;
      42: aload_0
      43: aload_1
      44: invokespecial #14                 // Method state:(Lio/netty/handler/codec/http2/Http2Stream;)Lorg/apache/dubbo/rpc/protocol/tri/TriHttp2RemoteFlowController$FlowState;
      47: iload_2
      48: invokevirtual #66                 // Method org/apache/dubbo/rpc/protocol/tri/TriHttp2RemoteFlowController$WritabilityMonitor.incrementWindowSize:(Lorg/apache/dubbo/rpc/protocol/tri/TriHttp2RemoteFlowController$FlowState;I)V
      51: return

  public void addFlowControlled(io.netty.handler.codec.http2.Http2Stream, io.netty.handler.codec.http2.Http2RemoteFlowController$FlowControlled);
    Code:
       0: getstatic     #46                 // Field $assertionsDisabled:Z
       3: ifne          38
       6: aload_0
       7: getfield      #11                 // Field ctx:Lio/netty/channel/ChannelHandlerContext;
      10: ifnull        38
      13: aload_0
      14: getfield      #11                 // Field ctx:Lio/netty/channel/ChannelHandlerContext;
      17: invokeinterface #47,  1           // InterfaceMethod io/netty/channel/ChannelHandlerContext.executor:()Lio/netty/util/concurrent/EventExecutor;
      22: invokeinterface #48,  1           // InterfaceMethod io/netty/util/concurrent/EventExecutor.inEventLoop:()Z
      27: ifne          38
      30: new           #49                 // class java/lang/AssertionError
      33: dup
      34: invokespecial #50                 // Method java/lang/AssertionError."<init>":()V
      37: athrow
      38: aload_2
      39: ldc           #67                 // String frame
      41: invokestatic  #23                 // Method io/netty/util/internal/ObjectUtil.checkNotNull:(Ljava/lang/Object;Ljava/lang/String;)Ljava/lang/Object;
      44: pop
      45: aload_0
      46: getfield      #12                 // Field monitor:Lorg/apache/dubbo/rpc/protocol/tri/TriHttp2RemoteFlowController$WritabilityMonitor;
      49: aload_0
      50: aload_1
      51: invokespecial #14                 // Method state:(Lio/netty/handler/codec/http2/Http2Stream;)Lorg/apache/dubbo/rpc/protocol/tri/TriHttp2RemoteFlowController$FlowState;
      54: aload_2
      55: invokevirtual #68                 // Method org/apache/dubbo/rpc/protocol/tri/TriHttp2RemoteFlowController$WritabilityMonitor.enqueueFrame:(Lorg/apache/dubbo/rpc/protocol/tri/TriHttp2RemoteFlowController$FlowState;Lio/netty/handler/codec/http2/Http2RemoteFlowController$FlowControlled;)V
      58: goto          73
      61: astore_3
      62: aload_2
      63: aload_0
      64: getfield      #11                 // Field ctx:Lio/netty/channel/ChannelHandlerContext;
      67: aload_3
      68: invokeinterface #70,  3           // InterfaceMethod io/netty/handler/codec/http2/Http2RemoteFlowController$FlowControlled.error:(Lio/netty/channel/ChannelHandlerContext;Ljava/lang/Throwable;)V
      73: return
    Exception table:
       from    to  target type
          45    58    61   Class java/lang/Throwable

  public boolean hasFlowControlled(io.netty.handler.codec.http2.Http2Stream);
    Code:
       0: aload_0
       1: aload_1
       2: invokespecial #14                 // Method state:(Lio/netty/handler/codec/http2/Http2Stream;)Lorg/apache/dubbo/rpc/protocol/tri/TriHttp2RemoteFlowController$FlowState;
       5: invokevirtual #71                 // Method org/apache/dubbo/rpc/protocol/tri/TriHttp2RemoteFlowController$FlowState.hasFrame:()Z
       8: ireturn

  private org.apache.dubbo.rpc.protocol.tri.TriHttp2RemoteFlowController$FlowState state(io.netty.handler.codec.http2.Http2Stream);
    Code:
       0: aload_1
       1: aload_0
       2: getfield      #15                 // Field stateKey:Lio/netty/handler/codec/http2/Http2Connection$PropertyKey;
       5: invokeinterface #72,  2           // InterfaceMethod io/netty/handler/codec/http2/Http2Stream.getProperty:(Lio/netty/handler/codec/http2/Http2Connection$PropertyKey;)Ljava/lang/Object;
      10: checkcast     #33                 // class org/apache/dubbo/rpc/protocol/tri/TriHttp2RemoteFlowController$FlowState
      13: areturn

  private int connectionWindowSize();
    Code:
       0: aload_0
       1: getfield      #8                  // Field connectionState:Lorg/apache/dubbo/rpc/protocol/tri/TriHttp2RemoteFlowController$FlowState;
       4: invokevirtual #52                 // Method org/apache/dubbo/rpc/protocol/tri/TriHttp2RemoteFlowController$FlowState.windowSize:()I
       7: ireturn

  private int minUsableChannelBytes();
    Code:
       0: aload_0
       1: getfield      #11                 // Field ctx:Lio/netty/channel/ChannelHandlerContext;
       4: invokeinterface #60,  1           // InterfaceMethod io/netty/channel/ChannelHandlerContext.channel:()Lio/netty/channel/Channel;
       9: invokeinterface #73,  1           // InterfaceMethod io/netty/channel/Channel.config:()Lio/netty/channel/ChannelConfig;
      14: invokeinterface #74,  1           // InterfaceMethod io/netty/channel/ChannelConfig.getWriteBufferLowWaterMark:()I
      19: ldc           #76                 // int 32768
      21: invokestatic  #77                 // Method java/lang/Math.max:(II)I
      24: ireturn

  private int maxUsableChannelBytes();
    Code:
       0: ldc2_w        #79                 // long 2147483647l
       3: aload_0
       4: getfield      #11                 // Field ctx:Lio/netty/channel/ChannelHandlerContext;
       7: invokeinterface #60,  1           // InterfaceMethod io/netty/channel/ChannelHandlerContext.channel:()Lio/netty/channel/Channel;
      12: invokeinterface #81,  1           // InterfaceMethod io/netty/channel/Channel.bytesBeforeUnwritable:()J
      17: invokestatic  #82                 // Method java/lang/Math.min:(JJ)J
      20: l2i
      21: istore_1
      22: iload_1
      23: ifle          37
      26: iload_1
      27: aload_0
      28: invokespecial #83                 // Method minUsableChannelBytes:()I
      31: invokestatic  #77                 // Method java/lang/Math.max:(II)I
      34: goto          38
      37: iconst_0
      38: istore_2
      39: aload_0
      40: getfield      #8                  // Field connectionState:Lorg/apache/dubbo/rpc/protocol/tri/TriHttp2RemoteFlowController$FlowState;
      43: invokevirtual #52                 // Method org/apache/dubbo/rpc/protocol/tri/TriHttp2RemoteFlowController$FlowState.windowSize:()I
      46: iload_2
      47: invokestatic  #84                 // Method java/lang/Math.min:(II)I
      50: ireturn

  private int writableBytes();
    Code:
       0: aload_0
       1: invokespecial #9                  // Method connectionWindowSize:()I
       4: aload_0
       5: invokespecial #85                 // Method maxUsableChannelBytes:()I
       8: invokestatic  #84                 // Method java/lang/Math.min:(II)I
      11: ireturn

  public void writePendingBytes() throws io.netty.handler.codec.http2.Http2Exception;
    Code:
       0: aload_0
       1: getfield      #12                 // Field monitor:Lorg/apache/dubbo/rpc/protocol/tri/TriHttp2RemoteFlowController$WritabilityMonitor;
       4: invokevirtual #86                 // Method org/apache/dubbo/rpc/protocol/tri/TriHttp2RemoteFlowController$WritabilityMonitor.writePendingBytes:()V
       7: return

  static io.netty.handler.codec.http2.Http2Connection$PropertyKey access$000(org.apache.dubbo.rpc.protocol.tri.TriHttp2RemoteFlowController);
    Code:
       0: aload_0
       1: getfield      #15                 // Field stateKey:Lio/netty/handler/codec/http2/Http2Connection$PropertyKey;
       4: areturn

  static org.apache.dubbo.rpc.protocol.tri.TriHttp2RemoteFlowController$FlowState access$100(org.apache.dubbo.rpc.protocol.tri.TriHttp2RemoteFlowController, io.netty.handler.codec.http2.Http2Stream);
    Code:
       0: aload_0
       1: aload_1
       2: invokespecial #14                 // Method state:(Lio/netty/handler/codec/http2/Http2Stream;)Lorg/apache/dubbo/rpc/protocol/tri/TriHttp2RemoteFlowController$FlowState;
       5: areturn

  static int access$200(org.apache.dubbo.rpc.protocol.tri.TriHttp2RemoteFlowController);
    Code:
       0: aload_0
       1: getfield      #13                 // Field initialWindowSize:I
       4: ireturn

  static org.apache.dubbo.rpc.protocol.tri.TriHttp2RemoteFlowController$WritabilityMonitor access$300(org.apache.dubbo.rpc.protocol.tri.TriHttp2RemoteFlowController);
    Code:
       0: aload_0
       1: getfield      #12                 // Field monitor:Lorg/apache/dubbo/rpc/protocol/tri/TriHttp2RemoteFlowController$WritabilityMonitor;
       4: areturn

  static io.netty.channel.ChannelHandlerContext access$500(org.apache.dubbo.rpc.protocol.tri.TriHttp2RemoteFlowController);
    Code:
       0: aload_0
       1: getfield      #11                 // Field ctx:Lio/netty/channel/ChannelHandlerContext;
       4: areturn

  static io.netty.handler.codec.http2.StreamByteDistributor access$600(org.apache.dubbo.rpc.protocol.tri.TriHttp2RemoteFlowController);
    Code:
       0: aload_0
       1: getfield      #10                 // Field streamByteDistributor:Lio/netty/handler/codec/http2/StreamByteDistributor;
       4: areturn

  static int access$700(org.apache.dubbo.rpc.protocol.tri.TriHttp2RemoteFlowController);
    Code:
       0: aload_0
       1: invokespecial #9                  // Method connectionWindowSize:()I
       4: ireturn

  static org.apache.dubbo.rpc.protocol.tri.TriHttp2RemoteFlowController$FlowState access$800(org.apache.dubbo.rpc.protocol.tri.TriHttp2RemoteFlowController);
    Code:
       0: aload_0
       1: getfield      #8                  // Field connectionState:Lorg/apache/dubbo/rpc/protocol/tri/TriHttp2RemoteFlowController$FlowState;
       4: areturn

  static int access$900(org.apache.dubbo.rpc.protocol.tri.TriHttp2RemoteFlowController);
    Code:
       0: aload_0
       1: invokespecial #7                  // Method writableBytes:()I
       4: ireturn

  static boolean access$1000(org.apache.dubbo.rpc.protocol.tri.TriHttp2RemoteFlowController);
    Code:
       0: aload_0
       1: invokespecial #6                  // Method isChannelWritable0:()Z
       4: ireturn

  static int access$202(org.apache.dubbo.rpc.protocol.tri.TriHttp2RemoteFlowController, int);
    Code:
       0: aload_0
       1: iload_1
       2: dup_x1
       3: putfield      #13                 // Field initialWindowSize:I
       6: ireturn

  static io.netty.handler.codec.http2.Http2Connection access$1100(org.apache.dubbo.rpc.protocol.tri.TriHttp2RemoteFlowController);
    Code:
       0: aload_0
       1: getfield      #5                  // Field connection:Lio/netty/handler/codec/http2/Http2Connection;
       4: areturn

  static boolean access$1200(org.apache.dubbo.rpc.protocol.tri.TriHttp2RemoteFlowController);
    Code:
       0: aload_0
       1: invokespecial #4                  // Method isChannelWritable:()Z
       4: ireturn

  static io.netty.util.internal.logging.InternalLogger access$1400();
    Code:
       0: getstatic     #3                  // Field logger:Lio/netty/util/internal/logging/InternalLogger;
       3: areturn

  static {};
    Code:
       0: ldc           #75                 // class org/apache/dubbo/rpc/protocol/tri/TriHttp2RemoteFlowController
       2: invokevirtual #87                 // Method java/lang/Class.desiredAssertionStatus:()Z
       5: ifne          12
       8: iconst_1
       9: goto          13
      12: iconst_0
      13: putstatic     #46                 // Field $assertionsDisabled:Z
      16: ldc           #75                 // class org/apache/dubbo/rpc/protocol/tri/TriHttp2RemoteFlowController
      18: invokestatic  #88                 // Method io/netty/util/internal/logging/InternalLoggerFactory.getInstance:(Ljava/lang/Class;)Lio/netty/util/internal/logging/InternalLogger;
      21: putstatic     #3                  // Field logger:Lio/netty/util/internal/logging/InternalLogger;
      24: return
}
