Compiled from "TripleHttp2Protocol.java"
class org.apache.dubbo.rpc.protocol.tri.TripleHttp2Protocol$1 extends io.netty.channel.ChannelInitializer<io.netty.handler.codec.http2.Http2StreamChannel> {
  final org.apache.dubbo.rpc.executor.ExecutorSupport val$executorSupport;

  final java.util.List val$headFilters;

  final org.apache.dubbo.rpc.protocol.tri.transport.TripleWriteQueue val$writeQueue;

  final org.apache.dubbo.rpc.protocol.tri.TripleHttp2Protocol this$0;

  org.apache.dubbo.rpc.protocol.tri.TripleHttp2Protocol$1(org.apache.dubbo.rpc.protocol.tri.TripleHttp2Protocol, org.apache.dubbo.rpc.executor.ExecutorSupport, java.util.List, org.apache.dubbo.rpc.protocol.tri.transport.TripleWriteQueue);
    Code:
       0: aload_0
       1: aload_1
       2: putfield      #1                  // Field this$0:Lorg/apache/dubbo/rpc/protocol/tri/TripleHttp2Protocol;
       5: aload_0
       6: aload_2
       7: putfield      #2                  // Field val$executorSupport:Lorg/apache/dubbo/rpc/executor/ExecutorSupport;
      10: aload_0
      11: aload_3
      12: putfield      #3                  // Field val$headFilters:Ljava/util/List;
      15: aload_0
      16: aload         4
      18: putfield      #4                  // Field val$writeQueue:Lorg/apache/dubbo/rpc/protocol/tri/transport/TripleWriteQueue;
      21: aload_0
      22: invokespecial #5                  // Method io/netty/channel/ChannelInitializer."<init>":()V
      25: return

  protected void initChannel(io.netty.handler.codec.http2.Http2StreamChannel);
    Code:
       0: aload_1
       1: invokeinterface #6,  1            // InterfaceMethod io/netty/handler/codec/http2/Http2StreamChannel.pipeline:()Lio/netty/channel/ChannelPipeline;
       6: astore_2
       7: aload_2
       8: iconst_1
       9: anewarray     #7                  // class io/netty/channel/ChannelHandler
      12: dup
      13: iconst_0
      14: new           #8                  // class org/apache/dubbo/rpc/protocol/tri/transport/TripleCommandOutBoundHandler
      17: dup
      18: invokespecial #9                  // Method org/apache/dubbo/rpc/protocol/tri/transport/TripleCommandOutBoundHandler."<init>":()V
      21: aastore
      22: invokeinterface #10,  2           // InterfaceMethod io/netty/channel/ChannelPipeline.addLast:([Lio/netty/channel/ChannelHandler;)Lio/netty/channel/ChannelPipeline;
      27: pop
      28: aload_2
      29: iconst_1
      30: anewarray     #7                  // class io/netty/channel/ChannelHandler
      33: dup
      34: iconst_0
      35: new           #11                 // class org/apache/dubbo/rpc/protocol/tri/transport/TripleHttp2FrameServerHandler
      38: dup
      39: aload_0
      40: getfield      #1                  // Field this$0:Lorg/apache/dubbo/rpc/protocol/tri/TripleHttp2Protocol;
      43: invokestatic  #12                 // Method org/apache/dubbo/rpc/protocol/tri/TripleHttp2Protocol.access$000:(Lorg/apache/dubbo/rpc/protocol/tri/TripleHttp2Protocol;)Lorg/apache/dubbo/rpc/model/FrameworkModel;
      46: aload_0
      47: getfield      #2                  // Field val$executorSupport:Lorg/apache/dubbo/rpc/executor/ExecutorSupport;
      50: aload_0
      51: getfield      #3                  // Field val$headFilters:Ljava/util/List;
      54: aload_1
      55: aload_0
      56: getfield      #4                  // Field val$writeQueue:Lorg/apache/dubbo/rpc/protocol/tri/transport/TripleWriteQueue;
      59: invokespecial #13                 // Method org/apache/dubbo/rpc/protocol/tri/transport/TripleHttp2FrameServerHandler."<init>":(Lorg/apache/dubbo/rpc/model/FrameworkModel;Lorg/apache/dubbo/rpc/executor/ExecutorSupport;Ljava/util/List;Lio/netty/handler/codec/http2/Http2StreamChannel;Lorg/apache/dubbo/rpc/protocol/tri/transport/TripleWriteQueue;)V
      62: aastore
      63: invokeinterface #10,  2           // InterfaceMethod io/netty/channel/ChannelPipeline.addLast:([Lio/netty/channel/ChannelHandler;)Lio/netty/channel/ChannelPipeline;
      68: pop
      69: return

  protected void initChannel(io.netty.channel.Channel) throws java.lang.Exception;
    Code:
       0: aload_0
       1: aload_1
       2: checkcast     #14                 // class io/netty/handler/codec/http2/Http2StreamChannel
       5: invokevirtual #15                 // Method initChannel:(Lio/netty/handler/codec/http2/Http2StreamChannel;)V
       8: return
}
