Compiled from "TripleCustomerProtocolWapper.java"
public final class org.apache.dubbo.rpc.protocol.tri.TripleCustomerProtocolWapper$TripleRequestWrapper$Builder {
  private java.lang.String serializeType;

  private final java.util.List<byte[]> args;

  private final java.util.List<java.lang.String> argTypes;

  public org.apache.dubbo.rpc.protocol.tri.TripleCustomerProtocolWapper$TripleRequestWrapper$Builder();
    Code:
       0: aload_0
       1: invokespecial #1                  // Method java/lang/Object."<init>":()V
       4: aload_0
       5: new           #2                  // class java/util/ArrayList
       8: dup
       9: invokespecial #3                  // Method java/util/ArrayList."<init>":()V
      12: putfield      #4                  // Field args:Ljava/util/List;
      15: aload_0
      16: new           #2                  // class java/util/ArrayList
      19: dup
      20: invokespecial #3                  // Method java/util/ArrayList."<init>":()V
      23: putfield      #5                  // Field argTypes:Ljava/util/List;
      26: return

  public org.apache.dubbo.rpc.protocol.tri.TripleCustomerProtocolWapper$TripleRequestWrapper$Builder setSerializeType(java.lang.String);
    Code:
       0: aload_0
       1: aload_1
       2: putfield      #6                  // Field serializeType:Ljava/lang/String;
       5: aload_0
       6: areturn

  public org.apache.dubbo.rpc.protocol.tri.TripleCustomerProtocolWapper$TripleRequestWrapper$Builder addArgTypes(java.lang.String);
    Code:
       0: aload_1
       1: ldc           #7                  // String argsType cannot be empty.
       3: invokestatic  #8                  // Method org/apache/dubbo/common/utils/Assert.notEmptyString:(Ljava/lang/String;Ljava/lang/String;)V
       6: aload_0
       7: getfield      #5                  // Field argTypes:Ljava/util/List;
      10: aload_1
      11: invokeinterface #9,  2            // InterfaceMethod java/util/List.add:(Ljava/lang/Object;)Z
      16: pop
      17: aload_0
      18: areturn

  public org.apache.dubbo.rpc.protocol.tri.TripleCustomerProtocolWapper$TripleRequestWrapper$Builder addArgs(byte[]);
    Code:
       0: aload_0
       1: getfield      #4                  // Field args:Ljava/util/List;
       4: aload_1
       5: invokeinterface #9,  2            // InterfaceMethod java/util/List.add:(Ljava/lang/Object;)Z
      10: pop
      11: aload_0
      12: areturn

  public static org.apache.dubbo.rpc.protocol.tri.TripleCustomerProtocolWapper$TripleRequestWrapper$Builder newBuilder();
    Code:
       0: new           #10                 // class org/apache/dubbo/rpc/protocol/tri/TripleCustomerProtocolWapper$TripleRequestWrapper$Builder
       3: dup
       4: invokespecial #11                 // Method "<init>":()V
       7: areturn

  public org.apache.dubbo.rpc.protocol.tri.TripleCustomerProtocolWapper$TripleRequestWrapper build();
    Code:
       0: aload_0
       1: getfield      #6                  // Field serializeType:Ljava/lang/String;
       4: ldc           #12                 // String serializeType can not be null
       6: invokestatic  #13                 // Method org/apache/dubbo/common/utils/Assert.notNull:(Ljava/lang/Object;Ljava/lang/String;)V
       9: new           #14                 // class org/apache/dubbo/rpc/protocol/tri/TripleCustomerProtocolWapper$TripleRequestWrapper
      12: dup
      13: invokespecial #15                 // Method org/apache/dubbo/rpc/protocol/tri/TripleCustomerProtocolWapper$TripleRequestWrapper."<init>":()V
      16: astore_1
      17: aload_1
      18: aload_0
      19: getfield      #4                  // Field args:Ljava/util/List;
      22: invokestatic  #16                 // Method org/apache/dubbo/rpc/protocol/tri/TripleCustomerProtocolWapper$TripleRequestWrapper.access$302:(Lorg/apache/dubbo/rpc/protocol/tri/TripleCustomerProtocolWapper$TripleRequestWrapper;Ljava/util/List;)Ljava/util/List;
      25: pop
      26: aload_1
      27: aload_0
      28: getfield      #5                  // Field argTypes:Ljava/util/List;
      31: invokestatic  #17                 // Method org/apache/dubbo/rpc/protocol/tri/TripleCustomerProtocolWapper$TripleRequestWrapper.access$402:(Lorg/apache/dubbo/rpc/protocol/tri/TripleCustomerProtocolWapper$TripleRequestWrapper;Ljava/util/List;)Ljava/util/List;
      34: pop
      35: aload_1
      36: aload_0
      37: getfield      #6                  // Field serializeType:Ljava/lang/String;
      40: invokestatic  #18                 // Method org/apache/dubbo/rpc/protocol/tri/TripleCustomerProtocolWapper$TripleRequestWrapper.access$502:(Lorg/apache/dubbo/rpc/protocol/tri/TripleCustomerProtocolWapper$TripleRequestWrapper;Ljava/lang/String;)Ljava/lang/String;
      43: pop
      44: aload_1
      45: areturn
}
