Compiled from "TripleCustomerProtocolWapper.java"
public final class org.apache.dubbo.rpc.protocol.tri.TripleCustomerProtocolWapper$TripleResponseWrapper$Builder {
  private java.lang.String serializeType;

  private byte[] data;

  private java.lang.String type;

  public org.apache.dubbo.rpc.protocol.tri.TripleCustomerProtocolWapper$TripleResponseWrapper$Builder();
    Code:
       0: aload_0
       1: invokespecial #1                  // Method java/lang/Object."<init>":()V
       4: return

  public org.apache.dubbo.rpc.protocol.tri.TripleCustomerProtocolWapper$TripleResponseWrapper$Builder setSerializeType(java.lang.String);
    Code:
       0: aload_0
       1: aload_1
       2: putfield      #2                  // Field serializeType:Ljava/lang/String;
       5: aload_0
       6: areturn

  public org.apache.dubbo.rpc.protocol.tri.TripleCustomerProtocolWapper$TripleResponseWrapper$Builder setData(byte[]);
    Code:
       0: aload_0
       1: aload_1
       2: putfield      #3                  // Field data:[B
       5: aload_0
       6: areturn

  public org.apache.dubbo.rpc.protocol.tri.TripleCustomerProtocolWapper$TripleResponseWrapper$Builder setType(java.lang.String);
    Code:
       0: aload_0
       1: aload_1
       2: putfield      #4                  // Field type:Ljava/lang/String;
       5: aload_0
       6: areturn

  public static org.apache.dubbo.rpc.protocol.tri.TripleCustomerProtocolWapper$TripleResponseWrapper$Builder newBuilder();
    Code:
       0: new           #5                  // class org/apache/dubbo/rpc/protocol/tri/TripleCustomerProtocolWapper$TripleResponseWrapper$Builder
       3: dup
       4: invokespecial #6                  // Method "<init>":()V
       7: areturn

  public org.apache.dubbo.rpc.protocol.tri.TripleCustomerProtocolWapper$TripleResponseWrapper build();
    Code:
       0: aload_0
       1: getfield      #2                  // Field serializeType:Ljava/lang/String;
       4: ldc           #7                  // String serializeType can not be null
       6: invokestatic  #8                  // Method org/apache/dubbo/common/utils/Assert.notNull:(Ljava/lang/Object;Ljava/lang/String;)V
       9: aload_0
      10: getfield      #4                  // Field type:Ljava/lang/String;
      13: ldc           #9                  // String type can not be null
      15: invokestatic  #8                  // Method org/apache/dubbo/common/utils/Assert.notNull:(Ljava/lang/Object;Ljava/lang/String;)V
      18: new           #10                 // class org/apache/dubbo/rpc/protocol/tri/TripleCustomerProtocolWapper$TripleResponseWrapper
      21: dup
      22: invokespecial #11                 // Method org/apache/dubbo/rpc/protocol/tri/TripleCustomerProtocolWapper$TripleResponseWrapper."<init>":()V
      25: astore_1
      26: aload_1
      27: aload_0
      28: getfield      #3                  // Field data:[B
      31: invokestatic  #12                 // Method org/apache/dubbo/rpc/protocol/tri/TripleCustomerProtocolWapper$TripleResponseWrapper.access$002:(Lorg/apache/dubbo/rpc/protocol/tri/TripleCustomerProtocolWapper$TripleResponseWrapper;[B)[B
      34: pop
      35: aload_1
      36: aload_0
      37: getfield      #2                  // Field serializeType:Ljava/lang/String;
      40: invokestatic  #13                 // Method org/apache/dubbo/rpc/protocol/tri/TripleCustomerProtocolWapper$TripleResponseWrapper.access$102:(Lorg/apache/dubbo/rpc/protocol/tri/TripleCustomerProtocolWapper$TripleResponseWrapper;Ljava/lang/String;)Ljava/lang/String;
      43: pop
      44: aload_1
      45: aload_0
      46: getfield      #4                  // Field type:Ljava/lang/String;
      49: invokestatic  #14                 // Method org/apache/dubbo/rpc/protocol/tri/TripleCustomerProtocolWapper$TripleResponseWrapper.access$202:(Lorg/apache/dubbo/rpc/protocol/tri/TripleCustomerProtocolWapper$TripleResponseWrapper;Ljava/lang/String;)Ljava/lang/String;
      52: pop
      53: aload_1
      54: areturn
}
