Compiled from "TripleProtocol.java"
public class org.apache.dubbo.rpc.protocol.tri.TripleProtocol extends org.apache.dubbo.rpc.protocol.AbstractProtocol {
  public static final java.lang.String METHOD_ATTR_PACK;

  private static final org.apache.dubbo.common.logger.Logger logger;

  private final org.apache.dubbo.rpc.PathResolver pathResolver;

  private final org.apache.dubbo.rpc.protocol.tri.service.TriBuiltinService triBuiltinService;

  private final java.lang.String acceptEncodings;

  public static boolean CONVERT_NO_LOWER_HEADER;

  public static boolean IGNORE_1_0_0_VERSION;

  public static boolean RESOLVE_FALLBACK_TO_DEFAULT;

  public org.apache.dubbo.rpc.protocol.tri.TripleProtocol(org.apache.dubbo.rpc.model.FrameworkModel);
    Code:
       0: aload_0
       1: invokespecial #6                  // Method org/apache/dubbo/rpc/protocol/AbstractProtocol."<init>":()V
       4: aload_0
       5: aload_1
       6: putfield      #7                  // Field frameworkModel:Lorg/apache/dubbo/rpc/model/FrameworkModel;
       9: aload_0
      10: new           #8                  // class org/apache/dubbo/rpc/protocol/tri/service/TriBuiltinService
      13: dup
      14: aload_1
      15: invokespecial #9                  // Method org/apache/dubbo/rpc/protocol/tri/service/TriBuiltinService."<init>":(Lorg/apache/dubbo/rpc/model/FrameworkModel;)V
      18: putfield      #4                  // Field triBuiltinService:Lorg/apache/dubbo/rpc/protocol/tri/service/TriBuiltinService;
      21: aload_0
      22: aload_1
      23: ldc           #10                 // class org/apache/dubbo/rpc/PathResolver
      25: invokevirtual #11                 // Method org/apache/dubbo/rpc/model/FrameworkModel.getExtensionLoader:(Ljava/lang/Class;)Lorg/apache/dubbo/common/extension/ExtensionLoader;
      28: invokevirtual #12                 // Method org/apache/dubbo/common/extension/ExtensionLoader.getDefaultExtension:()Ljava/lang/Object;
      31: checkcast     #10                 // class org/apache/dubbo/rpc/PathResolver
      34: putfield      #5                  // Field pathResolver:Lorg/apache/dubbo/rpc/PathResolver;
      37: invokestatic  #13                 // Method org/apache/dubbo/rpc/model/ApplicationModel.defaultModel:()Lorg/apache/dubbo/rpc/model/ApplicationModel;
      40: invokestatic  #14                 // Method org/apache/dubbo/common/config/ConfigurationUtils.getEnvConfiguration:(Lorg/apache/dubbo/rpc/model/ScopeModel;)Lorg/apache/dubbo/common/config/Configuration;
      43: ldc           #15                 // String dubbo.rpc.tri.support-no-lower-header
      45: iconst_1
      46: invokeinterface #16,  3           // InterfaceMethod org/apache/dubbo/common/config/Configuration.getBoolean:(Ljava/lang/String;Z)Z
      51: putstatic     #17                 // Field CONVERT_NO_LOWER_HEADER:Z
      54: invokestatic  #13                 // Method org/apache/dubbo/rpc/model/ApplicationModel.defaultModel:()Lorg/apache/dubbo/rpc/model/ApplicationModel;
      57: invokestatic  #14                 // Method org/apache/dubbo/common/config/ConfigurationUtils.getEnvConfiguration:(Lorg/apache/dubbo/rpc/model/ScopeModel;)Lorg/apache/dubbo/common/config/Configuration;
      60: ldc           #18                 // String dubbo.rpc.tri.ignore-1.0.0-version
      62: iconst_0
      63: invokeinterface #16,  3           // InterfaceMethod org/apache/dubbo/common/config/Configuration.getBoolean:(Ljava/lang/String;Z)Z
      68: putstatic     #19                 // Field IGNORE_1_0_0_VERSION:Z
      71: invokestatic  #13                 // Method org/apache/dubbo/rpc/model/ApplicationModel.defaultModel:()Lorg/apache/dubbo/rpc/model/ApplicationModel;
      74: invokestatic  #14                 // Method org/apache/dubbo/common/config/ConfigurationUtils.getEnvConfiguration:(Lorg/apache/dubbo/rpc/model/ScopeModel;)Lorg/apache/dubbo/common/config/Configuration;
      77: ldc           #20                 // String dubbo.rpc.tri.resolve-fallback-to-default
      79: iconst_0
      80: invokeinterface #16,  3           // InterfaceMethod org/apache/dubbo/common/config/Configuration.getBoolean:(Ljava/lang/String;Z)Z
      85: putstatic     #21                 // Field RESOLVE_FALLBACK_TO_DEFAULT:Z
      88: aload_1
      89: ldc           #22                 // class org/apache/dubbo/rpc/protocol/tri/compressor/DeCompressor
      91: invokevirtual #11                 // Method org/apache/dubbo/rpc/model/FrameworkModel.getExtensionLoader:(Ljava/lang/Class;)Lorg/apache/dubbo/common/extension/ExtensionLoader;
      94: invokevirtual #23                 // Method org/apache/dubbo/common/extension/ExtensionLoader.getSupportedExtensions:()Ljava/util/Set;
      97: astore_2
      98: aload_0
      99: ldc           #24                 // String ,
     101: aload_2
     102: invokestatic  #25                 // Method java/lang/String.join:(Ljava/lang/CharSequence;Ljava/lang/Iterable;)Ljava/lang/String;
     105: putfield      #26                 // Field acceptEncodings:Ljava/lang/String;
     108: return

  public int getDefaultPort();
    Code:
       0: ldc           #27                 // int 50051
       2: ireturn

  public <T> org.apache.dubbo.rpc.Exporter<T> export(org.apache.dubbo.rpc.Invoker<T>) throws org.apache.dubbo.rpc.RpcException;
    Code:
       0: aload_1
       1: invokeinterface #28,  1           // InterfaceMethod org/apache/dubbo/rpc/Invoker.getUrl:()Lorg/apache/dubbo/common/URL;
       6: astore_2
       7: aload_2
       8: invokestatic  #29                 // Method serviceKey:(Lorg/apache/dubbo/common/URL;)Ljava/lang/String;
      11: astore_3
      12: new           #30                 // class org/apache/dubbo/rpc/protocol/tri/TripleProtocol$1
      15: dup
      16: aload_0
      17: aload_1
      18: aload_2
      19: aload_3
      20: invokespecial #31                 // Method org/apache/dubbo/rpc/protocol/tri/TripleProtocol$1."<init>":(Lorg/apache/dubbo/rpc/protocol/tri/TripleProtocol;Lorg/apache/dubbo/rpc/Invoker;Lorg/apache/dubbo/common/URL;Ljava/lang/String;)V
      23: astore        4
      25: aload_0
      26: getfield      #3                  // Field exporterMap:Ljava/util/Map;
      29: aload_3
      30: aload         4
      32: invokeinterface #32,  3           // InterfaceMethod java/util/Map.put:(Ljava/lang/Object;Ljava/lang/Object;)Ljava/lang/Object;
      37: pop
      38: aload_0
      39: getfield      #33                 // Field invokers:Ljava/util/Set;
      42: aload_1
      43: invokeinterface #34,  2           // InterfaceMethod java/util/Set.add:(Ljava/lang/Object;)Z
      48: pop
      49: aload_0
      50: getfield      #5                  // Field pathResolver:Lorg/apache/dubbo/rpc/PathResolver;
      53: aload_2
      54: invokevirtual #35                 // Method org/apache/dubbo/common/URL.getServiceKey:()Ljava/lang/String;
      57: aload_1
      58: invokeinterface #36,  3           // InterfaceMethod org/apache/dubbo/rpc/PathResolver.add:(Ljava/lang/String;Lorg/apache/dubbo/rpc/Invoker;)V
      63: getstatic     #21                 // Field RESOLVE_FALLBACK_TO_DEFAULT:Z
      66: ifeq          91
      69: aload_0
      70: getfield      #5                  // Field pathResolver:Lorg/apache/dubbo/rpc/PathResolver;
      73: aload_2
      74: invokevirtual #37                 // Method org/apache/dubbo/common/URL.getServiceModel:()Lorg/apache/dubbo/rpc/model/ServiceModel;
      77: invokevirtual #38                 // Method org/apache/dubbo/rpc/model/ServiceModel.getServiceModel:()Lorg/apache/dubbo/rpc/model/ServiceDescriptor;
      80: invokeinterface #39,  1           // InterfaceMethod org/apache/dubbo/rpc/model/ServiceDescriptor.getInterfaceName:()Ljava/lang/String;
      85: aload_1
      86: invokeinterface #36,  3           // InterfaceMethod org/apache/dubbo/rpc/PathResolver.add:(Ljava/lang/String;Lorg/apache/dubbo/rpc/Invoker;)V
      91: aload_0
      92: getfield      #4                  // Field triBuiltinService:Lorg/apache/dubbo/rpc/protocol/tri/service/TriBuiltinService;
      95: invokevirtual #40                 // Method org/apache/dubbo/rpc/protocol/tri/service/TriBuiltinService.enable:()Z
      98: ifeq          135
     101: aload_0
     102: getfield      #4                  // Field triBuiltinService:Lorg/apache/dubbo/rpc/protocol/tri/service/TriBuiltinService;
     105: invokevirtual #41                 // Method org/apache/dubbo/rpc/protocol/tri/service/TriBuiltinService.getHealthStatusManager:()Lorg/apache/dubbo/rpc/protocol/tri/service/HealthStatusManager;
     108: aload_2
     109: invokevirtual #35                 // Method org/apache/dubbo/common/URL.getServiceKey:()Ljava/lang/String;
     112: getstatic     #42                 // Field io/grpc/health/v1/HealthCheckResponse$ServingStatus.SERVING:Lio/grpc/health/v1/HealthCheckResponse$ServingStatus;
     115: invokevirtual #43                 // Method org/apache/dubbo/rpc/protocol/tri/service/HealthStatusManager.setStatus:(Ljava/lang/String;Lio/grpc/health/v1/HealthCheckResponse$ServingStatus;)V
     118: aload_0
     119: getfield      #4                  // Field triBuiltinService:Lorg/apache/dubbo/rpc/protocol/tri/service/TriBuiltinService;
     122: invokevirtual #41                 // Method org/apache/dubbo/rpc/protocol/tri/service/TriBuiltinService.getHealthStatusManager:()Lorg/apache/dubbo/rpc/protocol/tri/service/HealthStatusManager;
     125: aload_2
     126: invokevirtual #44                 // Method org/apache/dubbo/common/URL.getServiceInterface:()Ljava/lang/String;
     129: getstatic     #42                 // Field io/grpc/health/v1/HealthCheckResponse$ServingStatus.SERVING:Lio/grpc/health/v1/HealthCheckResponse$ServingStatus;
     132: invokevirtual #43                 // Method org/apache/dubbo/rpc/protocol/tri/service/HealthStatusManager.setStatus:(Ljava/lang/String;Lio/grpc/health/v1/HealthCheckResponse$ServingStatus;)V
     135: aload_2
     136: invokevirtual #45                 // Method org/apache/dubbo/common/URL.getOrDefaultApplicationModel:()Lorg/apache/dubbo/rpc/model/ApplicationModel;
     139: invokestatic  #46                 // InterfaceMethod org/apache/dubbo/common/threadpool/manager/ExecutorRepository.getInstance:(Lorg/apache/dubbo/rpc/model/ApplicationModel;)Lorg/apache/dubbo/common/threadpool/manager/ExecutorRepository;
     142: aload_2
     143: ldc           #47                 // String DubboServerHandler
     145: invokestatic  #48                 // Method org/apache/dubbo/common/utils/ExecutorUtil.setThreadName:(Lorg/apache/dubbo/common/URL;Ljava/lang/String;)Lorg/apache/dubbo/common/URL;
     148: invokeinterface #49,  2           // InterfaceMethod org/apache/dubbo/common/threadpool/manager/ExecutorRepository.createExecutorIfAbsent:(Lorg/apache/dubbo/common/URL;)Ljava/util/concurrent/ExecutorService;
     153: pop
     154: aload_2
     155: new           #50                 // class org/apache/dubbo/remoting/api/pu/DefaultPuHandler
     158: dup
     159: invokespecial #51                 // Method org/apache/dubbo/remoting/api/pu/DefaultPuHandler."<init>":()V
     162: invokestatic  #52                 // Method org/apache/dubbo/remoting/exchange/PortUnificationExchanger.bind:(Lorg/apache/dubbo/common/URL;Lorg/apache/dubbo/remoting/ChannelHandler;)Lorg/apache/dubbo/remoting/RemotingServer;
     165: pop
     166: aload_0
     167: aload_2
     168: invokevirtual #53                 // Method optimizeSerialization:(Lorg/apache/dubbo/common/URL;)V
     171: aload         4
     173: areturn

  public <T> org.apache.dubbo.rpc.Invoker<T> refer(java.lang.Class<T>, org.apache.dubbo.common.URL) throws org.apache.dubbo.rpc.RpcException;
    Code:
       0: aload_0
       1: aload_2
       2: invokevirtual #53                 // Method optimizeSerialization:(Lorg/apache/dubbo/common/URL;)V
       5: aload_0
       6: aload_2
       7: invokevirtual #45                 // Method org/apache/dubbo/common/URL.getOrDefaultApplicationModel:()Lorg/apache/dubbo/rpc/model/ApplicationModel;
      10: aload_2
      11: invokespecial #54                 // Method getOrCreateStreamExecutor:(Lorg/apache/dubbo/rpc/model/ApplicationModel;Lorg/apache/dubbo/common/URL;)Ljava/util/concurrent/ExecutorService;
      14: astore_3
      15: aload_2
      16: new           #50                 // class org/apache/dubbo/remoting/api/pu/DefaultPuHandler
      19: dup
      20: invokespecial #51                 // Method org/apache/dubbo/remoting/api/pu/DefaultPuHandler."<init>":()V
      23: invokestatic  #55                 // Method org/apache/dubbo/remoting/exchange/PortUnificationExchanger.connect:(Lorg/apache/dubbo/common/URL;Lorg/apache/dubbo/remoting/ChannelHandler;)Lorg/apache/dubbo/remoting/api/connection/AbstractConnectionClient;
      26: astore        4
      28: new           #56                 // class org/apache/dubbo/rpc/protocol/tri/TripleInvoker
      31: dup
      32: aload_1
      33: aload_2
      34: aload_0
      35: getfield      #26                 // Field acceptEncodings:Ljava/lang/String;
      38: aload         4
      40: aload_0
      41: getfield      #33                 // Field invokers:Ljava/util/Set;
      44: aload_3
      45: invokespecial #57                 // Method org/apache/dubbo/rpc/protocol/tri/TripleInvoker."<init>":(Ljava/lang/Class;Lorg/apache/dubbo/common/URL;Ljava/lang/String;Lorg/apache/dubbo/remoting/api/connection/AbstractConnectionClient;Ljava/util/Set;Ljava/util/concurrent/ExecutorService;)V
      48: astore        5
      50: aload_0
      51: getfield      #33                 // Field invokers:Ljava/util/Set;
      54: aload         5
      56: invokeinterface #34,  2           // InterfaceMethod java/util/Set.add:(Ljava/lang/Object;)Z
      61: pop
      62: aload         5
      64: areturn

  private java.util.concurrent.ExecutorService getOrCreateStreamExecutor(org.apache.dubbo.rpc.model.ApplicationModel, org.apache.dubbo.common.URL);
    Code:
       0: aload_1
       1: invokestatic  #46                 // InterfaceMethod org/apache/dubbo/common/threadpool/manager/ExecutorRepository.getInstance:(Lorg/apache/dubbo/rpc/model/ApplicationModel;)Lorg/apache/dubbo/common/threadpool/manager/ExecutorRepository;
       4: aload_2
       5: ldc           #47                 // String DubboServerHandler
       7: invokestatic  #48                 // Method org/apache/dubbo/common/utils/ExecutorUtil.setThreadName:(Lorg/apache/dubbo/common/URL;Ljava/lang/String;)Lorg/apache/dubbo/common/URL;
      10: invokeinterface #49,  2           // InterfaceMethod org/apache/dubbo/common/threadpool/manager/ExecutorRepository.createExecutorIfAbsent:(Lorg/apache/dubbo/common/URL;)Ljava/util/concurrent/ExecutorService;
      15: astore_3
      16: aload_3
      17: ldc           #58                 // String No available executor found in %s
      19: iconst_1
      20: anewarray     #59                 // class java/lang/Object
      23: dup
      24: iconst_0
      25: aload_2
      26: aastore
      27: invokestatic  #60                 // Method java/lang/String.format:(Ljava/lang/String;[Ljava/lang/Object;)Ljava/lang/String;
      30: invokestatic  #61                 // Method java/util/Objects.requireNonNull:(Ljava/lang/Object;Ljava/lang/String;)Ljava/lang/Object;
      33: pop
      34: aload_3
      35: areturn

  protected <T> org.apache.dubbo.rpc.Invoker<T> protocolBindingRefer(java.lang.Class<T>, org.apache.dubbo.common.URL) throws org.apache.dubbo.rpc.RpcException;
    Code:
       0: aconst_null
       1: areturn

  public void destroy();
    Code:
       0: getstatic     #62                 // Field logger:Lorg/apache/dubbo/common/logger/Logger;
       3: invokeinterface #63,  1           // InterfaceMethod org/apache/dubbo/common/logger/Logger.isInfoEnabled:()Z
       8: ifeq          49
      11: getstatic     #62                 // Field logger:Lorg/apache/dubbo/common/logger/Logger;
      14: new           #64                 // class java/lang/StringBuilder
      17: dup
      18: invokespecial #65                 // Method java/lang/StringBuilder."<init>":()V
      21: ldc           #66                 // String Destroying protocol [
      23: invokevirtual #67                 // Method java/lang/StringBuilder.append:(Ljava/lang/String;)Ljava/lang/StringBuilder;
      26: aload_0
      27: invokevirtual #68                 // Method java/lang/Object.getClass:()Ljava/lang/Class;
      30: invokevirtual #69                 // Method java/lang/Class.getSimpleName:()Ljava/lang/String;
      33: invokevirtual #67                 // Method java/lang/StringBuilder.append:(Ljava/lang/String;)Ljava/lang/StringBuilder;
      36: ldc           #70                 // String ] ...
      38: invokevirtual #67                 // Method java/lang/StringBuilder.append:(Ljava/lang/String;)Ljava/lang/StringBuilder;
      41: invokevirtual #71                 // Method java/lang/StringBuilder.toString:()Ljava/lang/String;
      44: invokeinterface #72,  2           // InterfaceMethod org/apache/dubbo/common/logger/Logger.info:(Ljava/lang/String;)V
      49: invokestatic  #73                 // Method org/apache/dubbo/remoting/exchange/PortUnificationExchanger.close:()V
      52: aload_0
      53: getfield      #5                  // Field pathResolver:Lorg/apache/dubbo/rpc/PathResolver;
      56: invokeinterface #74,  1           // InterfaceMethod org/apache/dubbo/rpc/PathResolver.destroy:()V
      61: aload_0
      62: invokespecial #75                 // Method org/apache/dubbo/rpc/protocol/AbstractProtocol.destroy:()V
      65: return

  static org.apache.dubbo.rpc.PathResolver access$000(org.apache.dubbo.rpc.protocol.tri.TripleProtocol);
    Code:
       0: aload_0
       1: getfield      #5                  // Field pathResolver:Lorg/apache/dubbo/rpc/PathResolver;
       4: areturn

  static org.apache.dubbo.rpc.protocol.tri.service.TriBuiltinService access$100(org.apache.dubbo.rpc.protocol.tri.TripleProtocol);
    Code:
       0: aload_0
       1: getfield      #4                  // Field triBuiltinService:Lorg/apache/dubbo/rpc/protocol/tri/service/TriBuiltinService;
       4: areturn

  static java.util.Map access$200(org.apache.dubbo.rpc.protocol.tri.TripleProtocol);
    Code:
       0: aload_0
       1: getfield      #3                  // Field exporterMap:Ljava/util/Map;
       4: areturn

  static {};
    Code:
       0: ldc           #76                 // class org/apache/dubbo/rpc/protocol/tri/TripleProtocol
       2: invokestatic  #77                 // Method org/apache/dubbo/common/logger/LoggerFactory.getLogger:(Ljava/lang/Class;)Lorg/apache/dubbo/common/logger/Logger;
       5: putstatic     #62                 // Field logger:Lorg/apache/dubbo/common/logger/Logger;
       8: iconst_0
       9: putstatic     #17                 // Field CONVERT_NO_LOWER_HEADER:Z
      12: iconst_0
      13: putstatic     #19                 // Field IGNORE_1_0_0_VERSION:Z
      16: iconst_0
      17: putstatic     #21                 // Field RESOLVE_FALLBACK_TO_DEFAULT:Z
      20: return
}
