Compiled from "TripleConstant.java"
public class org.apache.dubbo.rpc.protocol.tri.TripleConstant {
  public static final java.lang.String CONTENT_PROTO;

  public static final java.lang.String APPLICATION_GRPC;

  public static final java.lang.String TEXT_PLAIN_UTF8;

  public static final java.lang.String TRI_VERSION;

  public static final java.lang.String SERIALIZATION_KEY;

  public static final java.lang.String TE_KEY;

  public static final java.lang.String HESSIAN4;

  public static final java.lang.String HESSIAN2;

  public static final java.lang.String HEADER_BIN_SUFFIX;

  public static final io.netty.util.AsciiString HTTPS_SCHEME;

  public static final io.netty.util.AsciiString HTTP_SCHEME;

  public org.apache.dubbo.rpc.protocol.tri.TripleConstant();
    Code:
       0: aload_0
       1: invokespecial #1                  // Method java/lang/Object."<init>":()V
       4: return

  static {};
    Code:
       0: ldc           #2                  // String https
       2: invokestatic  #3                  // Method io/netty/util/AsciiString.of:(Ljava/lang/CharSequence;)Lio/netty/util/AsciiString;
       5: putstatic     #4                  // Field HTTPS_SCHEME:Lio/netty/util/AsciiString;
       8: ldc           #5                  // String http
      10: invokestatic  #3                  // Method io/netty/util/AsciiString.of:(Ljava/lang/CharSequence;)Lio/netty/util/AsciiString;
      13: putstatic     #6                  // Field HTTP_SCHEME:Lio/netty/util/AsciiString;
      16: return
}
