Compiled from "TripleHeaderEnum.java"
public final class org.apache.dubbo.rpc.protocol.tri.TripleHeaderEnum extends java.lang.Enum<org.apache.dubbo.rpc.protocol.tri.TripleHeaderEnum> {
  public static final org.apache.dubbo.rpc.protocol.tri.TripleHeaderEnum AUTHORITY_KEY;

  public static final org.apache.dubbo.rpc.protocol.tri.TripleHeaderEnum PATH_KEY;

  public static final org.apache.dubbo.rpc.protocol.tri.TripleHeaderEnum HTTP_STATUS_KEY;

  public static final org.apache.dubbo.rpc.protocol.tri.TripleHeaderEnum STATUS_KEY;

  public static final org.apache.dubbo.rpc.protocol.tri.TripleHeaderEnum MESSAGE_KEY;

  public static final org.apache.dubbo.rpc.protocol.tri.TripleHeaderEnum STATUS_DETAIL_KEY;

  public static final org.apache.dubbo.rpc.protocol.tri.TripleHeaderEnum TIMEOUT;

  public static final org.apache.dubbo.rpc.protocol.tri.TripleHeaderEnum CONTENT_TYPE_KEY;

  public static final org.apache.dubbo.rpc.protocol.tri.TripleHeaderEnum CONTENT_PROTO;

  public static final org.apache.dubbo.rpc.protocol.tri.TripleHeaderEnum APPLICATION_GRPC;

  public static final org.apache.dubbo.rpc.protocol.tri.TripleHeaderEnum GRPC_ENCODING;

  public static final org.apache.dubbo.rpc.protocol.tri.TripleHeaderEnum GRPC_ACCEPT_ENCODING;

  public static final org.apache.dubbo.rpc.protocol.tri.TripleHeaderEnum CONSUMER_APP_NAME_KEY;

  public static final org.apache.dubbo.rpc.protocol.tri.TripleHeaderEnum SERVICE_VERSION;

  public static final org.apache.dubbo.rpc.protocol.tri.TripleHeaderEnum SERVICE_GROUP;

  public static final org.apache.dubbo.rpc.protocol.tri.TripleHeaderEnum TRI_HEADER_CONVERT;

  public static final org.apache.dubbo.rpc.protocol.tri.TripleHeaderEnum TRI_EXCEPTION_CODE;

  static final java.util.Map<java.lang.String, org.apache.dubbo.rpc.protocol.tri.TripleHeaderEnum> enumMap;

  static final java.util.Set<java.lang.String> excludeAttachmentsSet;

  private final java.lang.String header;

  private static final org.apache.dubbo.rpc.protocol.tri.TripleHeaderEnum[] $VALUES;

  public static org.apache.dubbo.rpc.protocol.tri.TripleHeaderEnum[] values();
    Code:
       0: getstatic     #1                  // Field $VALUES:[Lorg/apache/dubbo/rpc/protocol/tri/TripleHeaderEnum;
       3: invokevirtual #2                  // Method "[Lorg/apache/dubbo/rpc/protocol/tri/TripleHeaderEnum;".clone:()Ljava/lang/Object;
       6: checkcast     #3                  // class "[Lorg/apache/dubbo/rpc/protocol/tri/TripleHeaderEnum;"
       9: areturn

  public static org.apache.dubbo.rpc.protocol.tri.TripleHeaderEnum valueOf(java.lang.String);
    Code:
       0: ldc           #4                  // class org/apache/dubbo/rpc/protocol/tri/TripleHeaderEnum
       2: aload_0
       3: invokestatic  #5                  // Method java/lang/Enum.valueOf:(Ljava/lang/Class;Ljava/lang/String;)Ljava/lang/Enum;
       6: checkcast     #4                  // class org/apache/dubbo/rpc/protocol/tri/TripleHeaderEnum
       9: areturn

  private org.apache.dubbo.rpc.protocol.tri.TripleHeaderEnum(java.lang.String);
    Code:
       0: aload_0
       1: aload_1
       2: iload_2
       3: invokespecial #6                  // Method java/lang/Enum."<init>":(Ljava/lang/String;I)V
       6: aload_0
       7: aload_3
       8: putfield      #7                  // Field header:Ljava/lang/String;
      11: return

  public static boolean containsExcludeAttachments(java.lang.String);
    Code:
       0: getstatic     #8                  // Field excludeAttachmentsSet:Ljava/util/Set;
       3: aload_0
       4: invokeinterface #9,  2            // InterfaceMethod java/util/Set.contains:(Ljava/lang/Object;)Z
       9: ifne          24
      12: getstatic     #10                 // Field enumMap:Ljava/util/Map;
      15: aload_0
      16: invokeinterface #11,  2           // InterfaceMethod java/util/Map.containsKey:(Ljava/lang/Object;)Z
      21: ifeq          28
      24: iconst_1
      25: goto          29
      28: iconst_0
      29: ireturn

  public java.lang.String getHeader();
    Code:
       0: aload_0
       1: getfield      #7                  // Field header:Ljava/lang/String;
       4: areturn

  static {};
    Code:
       0: new           #4                  // class org/apache/dubbo/rpc/protocol/tri/TripleHeaderEnum
       3: dup
       4: ldc           #12                 // String AUTHORITY_KEY
       6: iconst_0
       7: ldc           #13                 // String :authority
       9: invokespecial #14                 // Method "<init>":(Ljava/lang/String;ILjava/lang/String;)V
      12: putstatic     #15                 // Field AUTHORITY_KEY:Lorg/apache/dubbo/rpc/protocol/tri/TripleHeaderEnum;
      15: new           #4                  // class org/apache/dubbo/rpc/protocol/tri/TripleHeaderEnum
      18: dup
      19: ldc           #16                 // String PATH_KEY
      21: iconst_1
      22: ldc           #17                 // String :path
      24: invokespecial #14                 // Method "<init>":(Ljava/lang/String;ILjava/lang/String;)V
      27: putstatic     #18                 // Field PATH_KEY:Lorg/apache/dubbo/rpc/protocol/tri/TripleHeaderEnum;
      30: new           #4                  // class org/apache/dubbo/rpc/protocol/tri/TripleHeaderEnum
      33: dup
      34: ldc           #19                 // String HTTP_STATUS_KEY
      36: iconst_2
      37: ldc           #20                 // String http-status
      39: invokespecial #14                 // Method "<init>":(Ljava/lang/String;ILjava/lang/String;)V
      42: putstatic     #21                 // Field HTTP_STATUS_KEY:Lorg/apache/dubbo/rpc/protocol/tri/TripleHeaderEnum;
      45: new           #4                  // class org/apache/dubbo/rpc/protocol/tri/TripleHeaderEnum
      48: dup
      49: ldc           #22                 // String STATUS_KEY
      51: iconst_3
      52: ldc           #23                 // String grpc-status
      54: invokespecial #14                 // Method "<init>":(Ljava/lang/String;ILjava/lang/String;)V
      57: putstatic     #24                 // Field STATUS_KEY:Lorg/apache/dubbo/rpc/protocol/tri/TripleHeaderEnum;
      60: new           #4                  // class org/apache/dubbo/rpc/protocol/tri/TripleHeaderEnum
      63: dup
      64: ldc           #25                 // String MESSAGE_KEY
      66: iconst_4
      67: ldc           #26                 // String grpc-message
      69: invokespecial #14                 // Method "<init>":(Ljava/lang/String;ILjava/lang/String;)V
      72: putstatic     #27                 // Field MESSAGE_KEY:Lorg/apache/dubbo/rpc/protocol/tri/TripleHeaderEnum;
      75: new           #4                  // class org/apache/dubbo/rpc/protocol/tri/TripleHeaderEnum
      78: dup
      79: ldc           #28                 // String STATUS_DETAIL_KEY
      81: iconst_5
      82: ldc           #29                 // String grpc-status-details-bin
      84: invokespecial #14                 // Method "<init>":(Ljava/lang/String;ILjava/lang/String;)V
      87: putstatic     #30                 // Field STATUS_DETAIL_KEY:Lorg/apache/dubbo/rpc/protocol/tri/TripleHeaderEnum;
      90: new           #4                  // class org/apache/dubbo/rpc/protocol/tri/TripleHeaderEnum
      93: dup
      94: ldc           #31                 // String TIMEOUT
      96: bipush        6
      98: ldc           #32                 // String grpc-timeout
     100: invokespecial #14                 // Method "<init>":(Ljava/lang/String;ILjava/lang/String;)V
     103: putstatic     #33                 // Field TIMEOUT:Lorg/apache/dubbo/rpc/protocol/tri/TripleHeaderEnum;
     106: new           #4                  // class org/apache/dubbo/rpc/protocol/tri/TripleHeaderEnum
     109: dup
     110: ldc           #34                 // String CONTENT_TYPE_KEY
     112: bipush        7
     114: ldc           #35                 // String content-type
     116: invokespecial #14                 // Method "<init>":(Ljava/lang/String;ILjava/lang/String;)V
     119: putstatic     #36                 // Field CONTENT_TYPE_KEY:Lorg/apache/dubbo/rpc/protocol/tri/TripleHeaderEnum;
     122: new           #4                  // class org/apache/dubbo/rpc/protocol/tri/TripleHeaderEnum
     125: dup
     126: ldc           #37                 // String CONTENT_PROTO
     128: bipush        8
     130: ldc           #38                 // String application/grpc+proto
     132: invokespecial #14                 // Method "<init>":(Ljava/lang/String;ILjava/lang/String;)V
     135: putstatic     #39                 // Field CONTENT_PROTO:Lorg/apache/dubbo/rpc/protocol/tri/TripleHeaderEnum;
     138: new           #4                  // class org/apache/dubbo/rpc/protocol/tri/TripleHeaderEnum
     141: dup
     142: ldc           #40                 // String APPLICATION_GRPC
     144: bipush        9
     146: ldc           #41                 // String application/grpc
     148: invokespecial #14                 // Method "<init>":(Ljava/lang/String;ILjava/lang/String;)V
     151: putstatic     #42                 // Field APPLICATION_GRPC:Lorg/apache/dubbo/rpc/protocol/tri/TripleHeaderEnum;
     154: new           #4                  // class org/apache/dubbo/rpc/protocol/tri/TripleHeaderEnum
     157: dup
     158: ldc           #43                 // String GRPC_ENCODING
     160: bipush        10
     162: ldc           #44                 // String grpc-encoding
     164: invokespecial #14                 // Method "<init>":(Ljava/lang/String;ILjava/lang/String;)V
     167: putstatic     #45                 // Field GRPC_ENCODING:Lorg/apache/dubbo/rpc/protocol/tri/TripleHeaderEnum;
     170: new           #4                  // class org/apache/dubbo/rpc/protocol/tri/TripleHeaderEnum
     173: dup
     174: ldc           #46                 // String GRPC_ACCEPT_ENCODING
     176: bipush        11
     178: ldc           #47                 // String grpc-accept-encoding
     180: invokespecial #14                 // Method "<init>":(Ljava/lang/String;ILjava/lang/String;)V
     183: putstatic     #48                 // Field GRPC_ACCEPT_ENCODING:Lorg/apache/dubbo/rpc/protocol/tri/TripleHeaderEnum;
     186: new           #4                  // class org/apache/dubbo/rpc/protocol/tri/TripleHeaderEnum
     189: dup
     190: ldc           #49                 // String CONSUMER_APP_NAME_KEY
     192: bipush        12
     194: ldc           #50                 // String tri-consumer-appname
     196: invokespecial #14                 // Method "<init>":(Ljava/lang/String;ILjava/lang/String;)V
     199: putstatic     #51                 // Field CONSUMER_APP_NAME_KEY:Lorg/apache/dubbo/rpc/protocol/tri/TripleHeaderEnum;
     202: new           #4                  // class org/apache/dubbo/rpc/protocol/tri/TripleHeaderEnum
     205: dup
     206: ldc           #52                 // String SERVICE_VERSION
     208: bipush        13
     210: ldc           #53                 // String tri-service-version
     212: invokespecial #14                 // Method "<init>":(Ljava/lang/String;ILjava/lang/String;)V
     215: putstatic     #54                 // Field SERVICE_VERSION:Lorg/apache/dubbo/rpc/protocol/tri/TripleHeaderEnum;
     218: new           #4                  // class org/apache/dubbo/rpc/protocol/tri/TripleHeaderEnum
     221: dup
     222: ldc           #55                 // String SERVICE_GROUP
     224: bipush        14
     226: ldc           #56                 // String tri-service-group
     228: invokespecial #14                 // Method "<init>":(Ljava/lang/String;ILjava/lang/String;)V
     231: putstatic     #57                 // Field SERVICE_GROUP:Lorg/apache/dubbo/rpc/protocol/tri/TripleHeaderEnum;
     234: new           #4                  // class org/apache/dubbo/rpc/protocol/tri/TripleHeaderEnum
     237: dup
     238: ldc           #58                 // String TRI_HEADER_CONVERT
     240: bipush        15
     242: ldc           #59                 // String tri-header-convert
     244: invokespecial #14                 // Method "<init>":(Ljava/lang/String;ILjava/lang/String;)V
     247: putstatic     #60                 // Field TRI_HEADER_CONVERT:Lorg/apache/dubbo/rpc/protocol/tri/TripleHeaderEnum;
     250: new           #4                  // class org/apache/dubbo/rpc/protocol/tri/TripleHeaderEnum
     253: dup
     254: ldc           #61                 // String TRI_EXCEPTION_CODE
     256: bipush        16
     258: ldc           #62                 // String tri-exception-code
     260: invokespecial #14                 // Method "<init>":(Ljava/lang/String;ILjava/lang/String;)V
     263: putstatic     #63                 // Field TRI_EXCEPTION_CODE:Lorg/apache/dubbo/rpc/protocol/tri/TripleHeaderEnum;
     266: bipush        17
     268: anewarray     #4                  // class org/apache/dubbo/rpc/protocol/tri/TripleHeaderEnum
     271: dup
     272: iconst_0
     273: getstatic     #15                 // Field AUTHORITY_KEY:Lorg/apache/dubbo/rpc/protocol/tri/TripleHeaderEnum;
     276: aastore
     277: dup
     278: iconst_1
     279: getstatic     #18                 // Field PATH_KEY:Lorg/apache/dubbo/rpc/protocol/tri/TripleHeaderEnum;
     282: aastore
     283: dup
     284: iconst_2
     285: getstatic     #21                 // Field HTTP_STATUS_KEY:Lorg/apache/dubbo/rpc/protocol/tri/TripleHeaderEnum;
     288: aastore
     289: dup
     290: iconst_3
     291: getstatic     #24                 // Field STATUS_KEY:Lorg/apache/dubbo/rpc/protocol/tri/TripleHeaderEnum;
     294: aastore
     295: dup
     296: iconst_4
     297: getstatic     #27                 // Field MESSAGE_KEY:Lorg/apache/dubbo/rpc/protocol/tri/TripleHeaderEnum;
     300: aastore
     301: dup
     302: iconst_5
     303: getstatic     #30                 // Field STATUS_DETAIL_KEY:Lorg/apache/dubbo/rpc/protocol/tri/TripleHeaderEnum;
     306: aastore
     307: dup
     308: bipush        6
     310: getstatic     #33                 // Field TIMEOUT:Lorg/apache/dubbo/rpc/protocol/tri/TripleHeaderEnum;
     313: aastore
     314: dup
     315: bipush        7
     317: getstatic     #36                 // Field CONTENT_TYPE_KEY:Lorg/apache/dubbo/rpc/protocol/tri/TripleHeaderEnum;
     320: aastore
     321: dup
     322: bipush        8
     324: getstatic     #39                 // Field CONTENT_PROTO:Lorg/apache/dubbo/rpc/protocol/tri/TripleHeaderEnum;
     327: aastore
     328: dup
     329: bipush        9
     331: getstatic     #42                 // Field APPLICATION_GRPC:Lorg/apache/dubbo/rpc/protocol/tri/TripleHeaderEnum;
     334: aastore
     335: dup
     336: bipush        10
     338: getstatic     #45                 // Field GRPC_ENCODING:Lorg/apache/dubbo/rpc/protocol/tri/TripleHeaderEnum;
     341: aastore
     342: dup
     343: bipush        11
     345: getstatic     #48                 // Field GRPC_ACCEPT_ENCODING:Lorg/apache/dubbo/rpc/protocol/tri/TripleHeaderEnum;
     348: aastore
     349: dup
     350: bipush        12
     352: getstatic     #51                 // Field CONSUMER_APP_NAME_KEY:Lorg/apache/dubbo/rpc/protocol/tri/TripleHeaderEnum;
     355: aastore
     356: dup
     357: bipush        13
     359: getstatic     #54                 // Field SERVICE_VERSION:Lorg/apache/dubbo/rpc/protocol/tri/TripleHeaderEnum;
     362: aastore
     363: dup
     364: bipush        14
     366: getstatic     #57                 // Field SERVICE_GROUP:Lorg/apache/dubbo/rpc/protocol/tri/TripleHeaderEnum;
     369: aastore
     370: dup
     371: bipush        15
     373: getstatic     #60                 // Field TRI_HEADER_CONVERT:Lorg/apache/dubbo/rpc/protocol/tri/TripleHeaderEnum;
     376: aastore
     377: dup
     378: bipush        16
     380: getstatic     #63                 // Field TRI_EXCEPTION_CODE:Lorg/apache/dubbo/rpc/protocol/tri/TripleHeaderEnum;
     383: aastore
     384: putstatic     #1                  // Field $VALUES:[Lorg/apache/dubbo/rpc/protocol/tri/TripleHeaderEnum;
     387: new           #64                 // class java/util/HashMap
     390: dup
     391: invokespecial #65                 // Method java/util/HashMap."<init>":()V
     394: putstatic     #10                 // Field enumMap:Ljava/util/Map;
     397: new           #66                 // class java/util/HashSet
     400: dup
     401: invokespecial #67                 // Method java/util/HashSet."<init>":()V
     404: putstatic     #8                  // Field excludeAttachmentsSet:Ljava/util/Set;
     407: invokestatic  #68                 // Method values:()[Lorg/apache/dubbo/rpc/protocol/tri/TripleHeaderEnum;
     410: astore_0
     411: aload_0
     412: arraylength
     413: istore_1
     414: iconst_0
     415: istore_2
     416: iload_2
     417: iload_1
     418: if_icmpge     445
     421: aload_0
     422: iload_2
     423: aaload
     424: astore_3
     425: getstatic     #10                 // Field enumMap:Ljava/util/Map;
     428: aload_3
     429: invokevirtual #69                 // Method getHeader:()Ljava/lang/String;
     432: aload_3
     433: invokeinterface #70,  3           // InterfaceMethod java/util/Map.put:(Ljava/lang/Object;Ljava/lang/Object;)Ljava/lang/Object;
     438: pop
     439: iinc          2, 1
     442: goto          416
     445: getstatic     #8                  // Field excludeAttachmentsSet:Ljava/util/Set;
     448: ldc           #72                 // String group
     450: invokeinterface #73,  2           // InterfaceMethod java/util/Set.add:(Ljava/lang/Object;)Z
     455: pop
     456: getstatic     #8                  // Field excludeAttachmentsSet:Ljava/util/Set;
     459: ldc           #74                 // String interface
     461: invokeinterface #73,  2           // InterfaceMethod java/util/Set.add:(Ljava/lang/Object;)Z
     466: pop
     467: getstatic     #8                  // Field excludeAttachmentsSet:Ljava/util/Set;
     470: ldc           #75                 // String path
     472: invokeinterface #73,  2           // InterfaceMethod java/util/Set.add:(Ljava/lang/Object;)Z
     477: pop
     478: getstatic     #8                  // Field excludeAttachmentsSet:Ljava/util/Set;
     481: ldc           #76                 // String remote.application
     483: invokeinterface #73,  2           // InterfaceMethod java/util/Set.add:(Ljava/lang/Object;)Z
     488: pop
     489: getstatic     #8                  // Field excludeAttachmentsSet:Ljava/util/Set;
     492: ldc           #77                 // String application
     494: invokeinterface #73,  2           // InterfaceMethod java/util/Set.add:(Ljava/lang/Object;)Z
     499: pop
     500: getstatic     #8                  // Field excludeAttachmentsSet:Ljava/util/Set;
     503: ldc           #79                 // String serialization
     505: invokeinterface #73,  2           // InterfaceMethod java/util/Set.add:(Ljava/lang/Object;)Z
     510: pop
     511: getstatic     #8                  // Field excludeAttachmentsSet:Ljava/util/Set;
     514: ldc           #80                 // String te
     516: invokeinterface #73,  2           // InterfaceMethod java/util/Set.add:(Ljava/lang/Object;)Z
     521: pop
     522: invokestatic  #81                 // Method io/netty/handler/codec/http2/Http2Headers$PseudoHeaderName.values:()[Lio/netty/handler/codec/http2/Http2Headers$PseudoHeaderName;
     525: astore_0
     526: aload_0
     527: arraylength
     528: istore_1
     529: iconst_0
     530: istore_2
     531: iload_2
     532: iload_1
     533: if_icmpge     562
     536: aload_0
     537: iload_2
     538: aaload
     539: astore_3
     540: getstatic     #8                  // Field excludeAttachmentsSet:Ljava/util/Set;
     543: aload_3
     544: invokevirtual #82                 // Method io/netty/handler/codec/http2/Http2Headers$PseudoHeaderName.value:()Lio/netty/util/AsciiString;
     547: invokevirtual #83                 // Method io/netty/util/AsciiString.toString:()Ljava/lang/String;
     550: invokeinterface #73,  2           // InterfaceMethod java/util/Set.add:(Ljava/lang/Object;)Z
     555: pop
     556: iinc          2, 1
     559: goto          531
     562: return
}
