Compiled from "TripleHttp2Protocol.java"
public class org.apache.dubbo.rpc.protocol.tri.TripleHttp2Protocol extends org.apache.dubbo.remoting.api.AbstractWireProtocol implements org.apache.dubbo.rpc.model.ScopeModelAware {
  private static final int MIB_1;

  private static final int MIB_8;

  private static final int KIB_32;

  private static final int DEFAULT_MAX_HEADER_LIST_SIZE;

  private static final int DEFAULT_SETTING_HEADER_LIST_SIZE;

  private static final int DEFAULT_MAX_FRAME_SIZE;

  private static final int DEFAULT_WINDOW_INIT_SIZE;

  public static final io.netty.handler.codec.http2.Http2FrameLogger CLIENT_LOGGER;

  public static final io.netty.handler.codec.http2.Http2FrameLogger SERVER_LOGGER;

  private org.apache.dubbo.common.extension.ExtensionLoader<org.apache.dubbo.rpc.HeaderFilter> filtersLoader;

  private org.apache.dubbo.rpc.model.FrameworkModel frameworkModel;

  public org.apache.dubbo.rpc.protocol.tri.TripleHttp2Protocol();
    Code:
       0: aload_0
       1: new           #5                  // class org/apache/dubbo/rpc/protocol/tri/Http2ProtocolDetector
       4: dup
       5: invokespecial #6                  // Method org/apache/dubbo/rpc/protocol/tri/Http2ProtocolDetector."<init>":()V
       8: invokespecial #7                  // Method org/apache/dubbo/remoting/api/AbstractWireProtocol."<init>":(Lorg/apache/dubbo/remoting/api/ProtocolDetector;)V
      11: return

  public void setFrameworkModel(org.apache.dubbo.rpc.model.FrameworkModel);
    Code:
       0: aload_0
       1: aload_1
       2: putfield      #4                  // Field frameworkModel:Lorg/apache/dubbo/rpc/model/FrameworkModel;
       5: aload_0
       6: aload_1
       7: ldc           #8                  // class org/apache/dubbo/rpc/HeaderFilter
       9: invokevirtual #9                  // Method org/apache/dubbo/rpc/model/FrameworkModel.getExtensionLoader:(Ljava/lang/Class;)Lorg/apache/dubbo/common/extension/ExtensionLoader;
      12: putfield      #10                 // Field filtersLoader:Lorg/apache/dubbo/common/extension/ExtensionLoader;
      15: return

  public void close();
    Code:
       0: aload_0
       1: invokespecial #11                 // Method org/apache/dubbo/remoting/api/AbstractWireProtocol.close:()V
       4: return

  public void configServerProtocolHandler(org.apache.dubbo.common.URL, org.apache.dubbo.remoting.api.pu.ChannelOperator);
    Code:
       0: aload_1
       1: invokevirtual #12                 // Method org/apache/dubbo/common/URL.getOrDefaultApplicationModel:()Lorg/apache/dubbo/rpc/model/ApplicationModel;
       4: invokestatic  #13                 // Method org/apache/dubbo/common/config/ConfigurationUtils.getGlobalConfiguration:(Lorg/apache/dubbo/rpc/model/ScopeModel;)Lorg/apache/dubbo/common/config/Configuration;
       7: astore_3
       8: aload_0
       9: getfield      #10                 // Field filtersLoader:Lorg/apache/dubbo/common/extension/ExtensionLoader;
      12: ifnull        30
      15: aload_0
      16: getfield      #10                 // Field filtersLoader:Lorg/apache/dubbo/common/extension/ExtensionLoader;
      19: aload_1
      20: ldc           #14                 // String header.filter
      22: invokevirtual #15                 // Method org/apache/dubbo/common/extension/ExtensionLoader.getActivateExtension:(Lorg/apache/dubbo/common/URL;Ljava/lang/String;)Ljava/util/List;
      25: astore        4
      27: goto          35
      30: invokestatic  #16                 // Method java/util/Collections.emptyList:()Ljava/util/List;
      33: astore        4
      35: invokestatic  #17                 // Method org/apache/dubbo/rpc/protocol/tri/TripleHttp2FrameCodecBuilder.forServer:()Lorg/apache/dubbo/rpc/protocol/tri/TripleHttp2FrameCodecBuilder;
      38: aload_1
      39: invokedynamic #18,  0             // InvokeDynamic #0:accept:(Lorg/apache/dubbo/common/URL;)Ljava/util/function/Consumer;
      44: invokevirtual #19                 // Method org/apache/dubbo/rpc/protocol/tri/TripleHttp2FrameCodecBuilder.customizeConnection:(Ljava/util/function/Consumer;)Lorg/apache/dubbo/rpc/protocol/tri/TripleHttp2FrameCodecBuilder;
      47: ldc2_w        #20                 // long 10000l
      50: invokevirtual #22                 // Method org/apache/dubbo/rpc/protocol/tri/TripleHttp2FrameCodecBuilder.gracefulShutdownTimeoutMillis:(J)Lio/netty/handler/codec/http2/Http2FrameCodecBuilder;
      53: new           #23                 // class io/netty/handler/codec/http2/Http2Settings
      56: dup
      57: invokespecial #24                 // Method io/netty/handler/codec/http2/Http2Settings."<init>":()V
      60: aload_3
      61: ldc           #25                 // String dubbo.rpc.tri.header-table-size
      63: sipush        4096
      66: invokeinterface #26,  3           // InterfaceMethod org/apache/dubbo/common/config/Configuration.getInt:(Ljava/lang/String;I)I
      71: i2l
      72: invokevirtual #27                 // Method io/netty/handler/codec/http2/Http2Settings.headerTableSize:(J)Lio/netty/handler/codec/http2/Http2Settings;
      75: aload_3
      76: ldc           #28                 // String dubbo.rpc.tri.max-concurrent-streams
      78: ldc           #30                 // int 2147483647
      80: invokeinterface #26,  3           // InterfaceMethod org/apache/dubbo/common/config/Configuration.getInt:(Ljava/lang/String;I)I
      85: i2l
      86: invokevirtual #31                 // Method io/netty/handler/codec/http2/Http2Settings.maxConcurrentStreams:(J)Lio/netty/handler/codec/http2/Http2Settings;
      89: aload_3
      90: ldc           #32                 // String dubbo.rpc.tri.initial-window-size
      92: ldc           #33                 // int 8388608
      94: invokeinterface #26,  3           // InterfaceMethod org/apache/dubbo/common/config/Configuration.getInt:(Ljava/lang/String;I)I
      99: invokevirtual #34                 // Method io/netty/handler/codec/http2/Http2Settings.initialWindowSize:(I)Lio/netty/handler/codec/http2/Http2Settings;
     102: aload_3
     103: ldc           #35                 // String dubbo.rpc.tri.max-frame-size
     105: ldc           #33                 // int 8388608
     107: invokeinterface #26,  3           // InterfaceMethod org/apache/dubbo/common/config/Configuration.getInt:(Ljava/lang/String;I)I
     112: invokevirtual #36                 // Method io/netty/handler/codec/http2/Http2Settings.maxFrameSize:(I)Lio/netty/handler/codec/http2/Http2Settings;
     115: aload_3
     116: ldc           #37                 // String dubbo.rpc.tri.max-header-list-size
     118: ldc           #38                 // int 32768
     120: invokeinterface #26,  3           // InterfaceMethod org/apache/dubbo/common/config/Configuration.getInt:(Ljava/lang/String;I)I
     125: i2l
     126: invokevirtual #39                 // Method io/netty/handler/codec/http2/Http2Settings.maxHeaderListSize:(J)Lio/netty/handler/codec/http2/Http2Settings;
     129: invokevirtual #40                 // Method io/netty/handler/codec/http2/Http2FrameCodecBuilder.initialSettings:(Lio/netty/handler/codec/http2/Http2Settings;)Lio/netty/handler/codec/http2/Http2FrameCodecBuilder;
     132: getstatic     #41                 // Field SERVER_LOGGER:Lio/netty/handler/codec/http2/Http2FrameLogger;
     135: invokevirtual #42                 // Method io/netty/handler/codec/http2/Http2FrameCodecBuilder.frameLogger:(Lio/netty/handler/codec/http2/Http2FrameLogger;)Lio/netty/handler/codec/http2/Http2FrameCodecBuilder;
     138: invokevirtual #43                 // Method io/netty/handler/codec/http2/Http2FrameCodecBuilder.build:()Lio/netty/handler/codec/http2/Http2FrameCodec;
     141: astore        5
     143: aload_1
     144: invokevirtual #12                 // Method org/apache/dubbo/common/URL.getOrDefaultApplicationModel:()Lorg/apache/dubbo/rpc/model/ApplicationModel;
     147: invokestatic  #44                 // InterfaceMethod org/apache/dubbo/common/threadpool/manager/ExecutorRepository.getInstance:(Lorg/apache/dubbo/rpc/model/ApplicationModel;)Lorg/apache/dubbo/common/threadpool/manager/ExecutorRepository;
     150: aload_1
     151: invokeinterface #45,  2           // InterfaceMethod org/apache/dubbo/common/threadpool/manager/ExecutorRepository.getExecutorSupport:(Lorg/apache/dubbo/common/URL;)Lorg/apache/dubbo/rpc/executor/ExecutorSupport;
     156: astore        6
     158: aload         5
     160: invokevirtual #46                 // Method io/netty/handler/codec/http2/Http2FrameCodec.connection:()Lio/netty/handler/codec/http2/Http2Connection;
     163: invokeinterface #47,  1           // InterfaceMethod io/netty/handler/codec/http2/Http2Connection.local:()Lio/netty/handler/codec/http2/Http2Connection$Endpoint;
     168: invokeinterface #48,  1           // InterfaceMethod io/netty/handler/codec/http2/Http2Connection$Endpoint.flowController:()Lio/netty/handler/codec/http2/Http2FlowController;
     173: checkcast     #49                 // class io/netty/handler/codec/http2/Http2LocalFlowController
     176: aload         5
     178: invokevirtual #50                 // Method io/netty/handler/codec/http2/Http2FrameCodec.encoder:()Lio/netty/handler/codec/http2/Http2ConnectionEncoder;
     181: invokeinterface #51,  1           // InterfaceMethod io/netty/handler/codec/http2/Http2ConnectionEncoder.frameWriter:()Lio/netty/handler/codec/http2/Http2FrameWriter;
     186: invokeinterface #52,  2           // InterfaceMethod io/netty/handler/codec/http2/Http2LocalFlowController.frameWriter:(Lio/netty/handler/codec/http2/Http2FrameWriter;)Lio/netty/handler/codec/http2/Http2LocalFlowController;
     191: pop
     192: new           #53                 // class org/apache/dubbo/rpc/protocol/tri/transport/TripleWriteQueue
     195: dup
     196: invokespecial #54                 // Method org/apache/dubbo/rpc/protocol/tri/transport/TripleWriteQueue."<init>":()V
     199: astore        7
     201: new           #55                 // class io/netty/handler/codec/http2/Http2MultiplexHandler
     204: dup
     205: new           #56                 // class org/apache/dubbo/rpc/protocol/tri/TripleHttp2Protocol$1
     208: dup
     209: aload_0
     210: aload         6
     212: aload         4
     214: aload         7
     216: invokespecial #57                 // Method org/apache/dubbo/rpc/protocol/tri/TripleHttp2Protocol$1."<init>":(Lorg/apache/dubbo/rpc/protocol/tri/TripleHttp2Protocol;Lorg/apache/dubbo/rpc/executor/ExecutorSupport;Ljava/util/List;Lorg/apache/dubbo/rpc/protocol/tri/transport/TripleWriteQueue;)V
     219: invokespecial #58                 // Method io/netty/handler/codec/http2/Http2MultiplexHandler."<init>":(Lio/netty/channel/ChannelHandler;)V
     222: astore        8
     224: new           #59                 // class java/util/ArrayList
     227: dup
     228: invokespecial #60                 // Method java/util/ArrayList."<init>":()V
     231: astore        9
     233: aload         9
     235: new           #61                 // class org/apache/dubbo/remoting/api/pu/ChannelHandlerPretender
     238: dup
     239: aload         5
     241: invokespecial #62                 // Method org/apache/dubbo/remoting/api/pu/ChannelHandlerPretender."<init>":(Ljava/lang/Object;)V
     244: invokeinterface #63,  2           // InterfaceMethod java/util/List.add:(Ljava/lang/Object;)Z
     249: pop
     250: aload         9
     252: new           #61                 // class org/apache/dubbo/remoting/api/pu/ChannelHandlerPretender
     255: dup
     256: new           #64                 // class io/netty/handler/flush/FlushConsolidationHandler
     259: dup
     260: bipush        64
     262: iconst_1
     263: invokespecial #65                 // Method io/netty/handler/flush/FlushConsolidationHandler."<init>":(IZ)V
     266: invokespecial #62                 // Method org/apache/dubbo/remoting/api/pu/ChannelHandlerPretender."<init>":(Ljava/lang/Object;)V
     269: invokeinterface #63,  2           // InterfaceMethod java/util/List.add:(Ljava/lang/Object;)Z
     274: pop
     275: aload         9
     277: new           #61                 // class org/apache/dubbo/remoting/api/pu/ChannelHandlerPretender
     280: dup
     281: new           #66                 // class org/apache/dubbo/rpc/protocol/tri/transport/TripleServerConnectionHandler
     284: dup
     285: invokespecial #67                 // Method org/apache/dubbo/rpc/protocol/tri/transport/TripleServerConnectionHandler."<init>":()V
     288: invokespecial #62                 // Method org/apache/dubbo/remoting/api/pu/ChannelHandlerPretender."<init>":(Ljava/lang/Object;)V
     291: invokeinterface #63,  2           // InterfaceMethod java/util/List.add:(Ljava/lang/Object;)Z
     296: pop
     297: aload         9
     299: new           #61                 // class org/apache/dubbo/remoting/api/pu/ChannelHandlerPretender
     302: dup
     303: aload         8
     305: invokespecial #62                 // Method org/apache/dubbo/remoting/api/pu/ChannelHandlerPretender."<init>":(Ljava/lang/Object;)V
     308: invokeinterface #63,  2           // InterfaceMethod java/util/List.add:(Ljava/lang/Object;)Z
     313: pop
     314: aload         9
     316: new           #61                 // class org/apache/dubbo/remoting/api/pu/ChannelHandlerPretender
     319: dup
     320: new           #68                 // class org/apache/dubbo/rpc/protocol/tri/transport/TripleTailHandler
     323: dup
     324: invokespecial #69                 // Method org/apache/dubbo/rpc/protocol/tri/transport/TripleTailHandler."<init>":()V
     327: invokespecial #62                 // Method org/apache/dubbo/remoting/api/pu/ChannelHandlerPretender."<init>":(Ljava/lang/Object;)V
     330: invokeinterface #63,  2           // InterfaceMethod java/util/List.add:(Ljava/lang/Object;)Z
     335: pop
     336: aload_2
     337: aload         9
     339: invokeinterface #70,  2           // InterfaceMethod org/apache/dubbo/remoting/api/pu/ChannelOperator.configChannelHandler:(Ljava/util/List;)V
     344: return

  public void configClientPipeline(org.apache.dubbo.common.URL, org.apache.dubbo.remoting.api.pu.ChannelOperator, org.apache.dubbo.remoting.api.ssl.ContextOperator);
    Code:
       0: aload_1
       1: invokevirtual #12                 // Method org/apache/dubbo/common/URL.getOrDefaultApplicationModel:()Lorg/apache/dubbo/rpc/model/ApplicationModel;
       4: invokestatic  #13                 // Method org/apache/dubbo/common/config/ConfigurationUtils.getGlobalConfiguration:(Lorg/apache/dubbo/rpc/model/ScopeModel;)Lorg/apache/dubbo/common/config/Configuration;
       7: astore        4
       9: invokestatic  #71                 // Method org/apache/dubbo/rpc/protocol/tri/TripleHttp2FrameCodecBuilder.forClient:()Lorg/apache/dubbo/rpc/protocol/tri/TripleHttp2FrameCodecBuilder;
      12: aload_1
      13: invokedynamic #72,  0             // InvokeDynamic #1:accept:(Lorg/apache/dubbo/common/URL;)Ljava/util/function/Consumer;
      18: invokevirtual #19                 // Method org/apache/dubbo/rpc/protocol/tri/TripleHttp2FrameCodecBuilder.customizeConnection:(Ljava/util/function/Consumer;)Lorg/apache/dubbo/rpc/protocol/tri/TripleHttp2FrameCodecBuilder;
      21: ldc2_w        #20                 // long 10000l
      24: invokevirtual #22                 // Method org/apache/dubbo/rpc/protocol/tri/TripleHttp2FrameCodecBuilder.gracefulShutdownTimeoutMillis:(J)Lio/netty/handler/codec/http2/Http2FrameCodecBuilder;
      27: new           #23                 // class io/netty/handler/codec/http2/Http2Settings
      30: dup
      31: invokespecial #24                 // Method io/netty/handler/codec/http2/Http2Settings."<init>":()V
      34: aload         4
      36: ldc           #25                 // String dubbo.rpc.tri.header-table-size
      38: sipush        4096
      41: invokeinterface #26,  3           // InterfaceMethod org/apache/dubbo/common/config/Configuration.getInt:(Ljava/lang/String;I)I
      46: i2l
      47: invokevirtual #27                 // Method io/netty/handler/codec/http2/Http2Settings.headerTableSize:(J)Lio/netty/handler/codec/http2/Http2Settings;
      50: aload         4
      52: ldc           #73                 // String dubbo.rpc.tri.enable-push
      54: iconst_0
      55: invokeinterface #74,  3           // InterfaceMethod org/apache/dubbo/common/config/Configuration.getBoolean:(Ljava/lang/String;Z)Z
      60: invokevirtual #75                 // Method io/netty/handler/codec/http2/Http2Settings.pushEnabled:(Z)Lio/netty/handler/codec/http2/Http2Settings;
      63: aload         4
      65: ldc           #28                 // String dubbo.rpc.tri.max-concurrent-streams
      67: ldc           #30                 // int 2147483647
      69: invokeinterface #26,  3           // InterfaceMethod org/apache/dubbo/common/config/Configuration.getInt:(Ljava/lang/String;I)I
      74: i2l
      75: invokevirtual #31                 // Method io/netty/handler/codec/http2/Http2Settings.maxConcurrentStreams:(J)Lio/netty/handler/codec/http2/Http2Settings;
      78: aload         4
      80: ldc           #32                 // String dubbo.rpc.tri.initial-window-size
      82: ldc           #33                 // int 8388608
      84: invokeinterface #26,  3           // InterfaceMethod org/apache/dubbo/common/config/Configuration.getInt:(Ljava/lang/String;I)I
      89: invokevirtual #34                 // Method io/netty/handler/codec/http2/Http2Settings.initialWindowSize:(I)Lio/netty/handler/codec/http2/Http2Settings;
      92: aload         4
      94: ldc           #35                 // String dubbo.rpc.tri.max-frame-size
      96: ldc           #33                 // int 8388608
      98: invokeinterface #26,  3           // InterfaceMethod org/apache/dubbo/common/config/Configuration.getInt:(Ljava/lang/String;I)I
     103: invokevirtual #36                 // Method io/netty/handler/codec/http2/Http2Settings.maxFrameSize:(I)Lio/netty/handler/codec/http2/Http2Settings;
     106: aload         4
     108: ldc           #37                 // String dubbo.rpc.tri.max-header-list-size
     110: ldc           #38                 // int 32768
     112: invokeinterface #26,  3           // InterfaceMethod org/apache/dubbo/common/config/Configuration.getInt:(Ljava/lang/String;I)I
     117: i2l
     118: invokevirtual #39                 // Method io/netty/handler/codec/http2/Http2Settings.maxHeaderListSize:(J)Lio/netty/handler/codec/http2/Http2Settings;
     121: invokevirtual #40                 // Method io/netty/handler/codec/http2/Http2FrameCodecBuilder.initialSettings:(Lio/netty/handler/codec/http2/Http2Settings;)Lio/netty/handler/codec/http2/Http2FrameCodecBuilder;
     124: getstatic     #76                 // Field CLIENT_LOGGER:Lio/netty/handler/codec/http2/Http2FrameLogger;
     127: invokevirtual #42                 // Method io/netty/handler/codec/http2/Http2FrameCodecBuilder.frameLogger:(Lio/netty/handler/codec/http2/Http2FrameLogger;)Lio/netty/handler/codec/http2/Http2FrameCodecBuilder;
     130: invokevirtual #43                 // Method io/netty/handler/codec/http2/Http2FrameCodecBuilder.build:()Lio/netty/handler/codec/http2/Http2FrameCodec;
     133: astore        5
     135: aload         5
     137: invokevirtual #46                 // Method io/netty/handler/codec/http2/Http2FrameCodec.connection:()Lio/netty/handler/codec/http2/Http2Connection;
     140: invokeinterface #47,  1           // InterfaceMethod io/netty/handler/codec/http2/Http2Connection.local:()Lio/netty/handler/codec/http2/Http2Connection$Endpoint;
     145: invokeinterface #48,  1           // InterfaceMethod io/netty/handler/codec/http2/Http2Connection$Endpoint.flowController:()Lio/netty/handler/codec/http2/Http2FlowController;
     150: checkcast     #49                 // class io/netty/handler/codec/http2/Http2LocalFlowController
     153: aload         5
     155: invokevirtual #50                 // Method io/netty/handler/codec/http2/Http2FrameCodec.encoder:()Lio/netty/handler/codec/http2/Http2ConnectionEncoder;
     158: invokeinterface #51,  1           // InterfaceMethod io/netty/handler/codec/http2/Http2ConnectionEncoder.frameWriter:()Lio/netty/handler/codec/http2/Http2FrameWriter;
     163: invokeinterface #52,  2           // InterfaceMethod io/netty/handler/codec/http2/Http2LocalFlowController.frameWriter:(Lio/netty/handler/codec/http2/Http2FrameWriter;)Lio/netty/handler/codec/http2/Http2LocalFlowController;
     168: pop
     169: new           #55                 // class io/netty/handler/codec/http2/Http2MultiplexHandler
     172: dup
     173: new           #77                 // class org/apache/dubbo/rpc/protocol/tri/transport/TripleClientHandler
     176: dup
     177: aload_0
     178: getfield      #4                  // Field frameworkModel:Lorg/apache/dubbo/rpc/model/FrameworkModel;
     181: invokespecial #78                 // Method org/apache/dubbo/rpc/protocol/tri/transport/TripleClientHandler."<init>":(Lorg/apache/dubbo/rpc/model/FrameworkModel;)V
     184: invokespecial #58                 // Method io/netty/handler/codec/http2/Http2MultiplexHandler."<init>":(Lio/netty/channel/ChannelHandler;)V
     187: astore        6
     189: new           #59                 // class java/util/ArrayList
     192: dup
     193: invokespecial #60                 // Method java/util/ArrayList."<init>":()V
     196: astore        7
     198: aload         7
     200: new           #61                 // class org/apache/dubbo/remoting/api/pu/ChannelHandlerPretender
     203: dup
     204: aload         5
     206: invokespecial #62                 // Method org/apache/dubbo/remoting/api/pu/ChannelHandlerPretender."<init>":(Ljava/lang/Object;)V
     209: invokeinterface #63,  2           // InterfaceMethod java/util/List.add:(Ljava/lang/Object;)Z
     214: pop
     215: aload         7
     217: new           #61                 // class org/apache/dubbo/remoting/api/pu/ChannelHandlerPretender
     220: dup
     221: aload         6
     223: invokespecial #62                 // Method org/apache/dubbo/remoting/api/pu/ChannelHandlerPretender."<init>":(Ljava/lang/Object;)V
     226: invokeinterface #63,  2           // InterfaceMethod java/util/List.add:(Ljava/lang/Object;)Z
     231: pop
     232: aload         7
     234: new           #61                 // class org/apache/dubbo/remoting/api/pu/ChannelHandlerPretender
     237: dup
     238: new           #68                 // class org/apache/dubbo/rpc/protocol/tri/transport/TripleTailHandler
     241: dup
     242: invokespecial #69                 // Method org/apache/dubbo/rpc/protocol/tri/transport/TripleTailHandler."<init>":()V
     245: invokespecial #62                 // Method org/apache/dubbo/remoting/api/pu/ChannelHandlerPretender."<init>":(Ljava/lang/Object;)V
     248: invokeinterface #63,  2           // InterfaceMethod java/util/List.add:(Ljava/lang/Object;)Z
     253: pop
     254: aload_2
     255: aload         7
     257: invokeinterface #70,  2           // InterfaceMethod org/apache/dubbo/remoting/api/pu/ChannelOperator.configChannelHandler:(Ljava/util/List;)V
     262: return

  private static void lambda$configClientPipeline$1(org.apache.dubbo.common.URL, io.netty.handler.codec.http2.Http2Connection);
    Code:
       0: aload_1
       1: invokeinterface #79,  1           // InterfaceMethod io/netty/handler/codec/http2/Http2Connection.remote:()Lio/netty/handler/codec/http2/Http2Connection$Endpoint;
       6: new           #80                 // class org/apache/dubbo/rpc/protocol/tri/TriHttp2RemoteFlowController
       9: dup
      10: aload_1
      11: aload_0
      12: invokevirtual #12                 // Method org/apache/dubbo/common/URL.getOrDefaultApplicationModel:()Lorg/apache/dubbo/rpc/model/ApplicationModel;
      15: invokespecial #81                 // Method org/apache/dubbo/rpc/protocol/tri/TriHttp2RemoteFlowController."<init>":(Lio/netty/handler/codec/http2/Http2Connection;Lorg/apache/dubbo/rpc/model/ApplicationModel;)V
      18: invokeinterface #82,  2           // InterfaceMethod io/netty/handler/codec/http2/Http2Connection$Endpoint.flowController:(Lio/netty/handler/codec/http2/Http2FlowController;)V
      23: return

  private static void lambda$configServerProtocolHandler$0(org.apache.dubbo.common.URL, io.netty.handler.codec.http2.Http2Connection);
    Code:
       0: aload_1
       1: invokeinterface #79,  1           // InterfaceMethod io/netty/handler/codec/http2/Http2Connection.remote:()Lio/netty/handler/codec/http2/Http2Connection$Endpoint;
       6: new           #80                 // class org/apache/dubbo/rpc/protocol/tri/TriHttp2RemoteFlowController
       9: dup
      10: aload_1
      11: aload_0
      12: invokevirtual #12                 // Method org/apache/dubbo/common/URL.getOrDefaultApplicationModel:()Lorg/apache/dubbo/rpc/model/ApplicationModel;
      15: invokespecial #81                 // Method org/apache/dubbo/rpc/protocol/tri/TriHttp2RemoteFlowController."<init>":(Lio/netty/handler/codec/http2/Http2Connection;Lorg/apache/dubbo/rpc/model/ApplicationModel;)V
      18: invokeinterface #82,  2           // InterfaceMethod io/netty/handler/codec/http2/Http2Connection$Endpoint.flowController:(Lio/netty/handler/codec/http2/Http2FlowController;)V
      23: return

  static org.apache.dubbo.rpc.model.FrameworkModel access$000(org.apache.dubbo.rpc.protocol.tri.TripleHttp2Protocol);
    Code:
       0: aload_0
       1: getfield      #4                  // Field frameworkModel:Lorg/apache/dubbo/rpc/model/FrameworkModel;
       4: areturn

  static {};
    Code:
       0: new           #83                 // class io/netty/handler/codec/http2/Http2FrameLogger
       3: dup
       4: getstatic     #84                 // Field io/netty/handler/logging/LogLevel.DEBUG:Lio/netty/handler/logging/LogLevel;
       7: ldc           #85                 // String H2_CLIENT
       9: invokespecial #86                 // Method io/netty/handler/codec/http2/Http2FrameLogger."<init>":(Lio/netty/handler/logging/LogLevel;Ljava/lang/String;)V
      12: putstatic     #76                 // Field CLIENT_LOGGER:Lio/netty/handler/codec/http2/Http2FrameLogger;
      15: new           #83                 // class io/netty/handler/codec/http2/Http2FrameLogger
      18: dup
      19: getstatic     #84                 // Field io/netty/handler/logging/LogLevel.DEBUG:Lio/netty/handler/logging/LogLevel;
      22: ldc           #87                 // String H2_SERVER
      24: invokespecial #86                 // Method io/netty/handler/codec/http2/Http2FrameLogger."<init>":(Lio/netty/handler/logging/LogLevel;Ljava/lang/String;)V
      27: putstatic     #41                 // Field SERVER_LOGGER:Lio/netty/handler/codec/http2/Http2FrameLogger;
      30: return
}
