Compiled from "TriplePathResolver.java"
public class org.apache.dubbo.rpc.protocol.tri.TriplePathResolver implements org.apache.dubbo.rpc.PathResolver {
  private final java.util.concurrent.ConcurrentHashMap<java.lang.String, org.apache.dubbo.rpc.Invoker<?>> path2Invoker;

  private final java.util.concurrent.ConcurrentHashMap<java.lang.String, java.lang.Object> nativeStub;

  public org.apache.dubbo.rpc.protocol.tri.TriplePathResolver();
    Code:
       0: aload_0
       1: invokespecial #1                  // Method java/lang/Object."<init>":()V
       4: aload_0
       5: new           #2                  // class java/util/concurrent/ConcurrentHashMap
       8: dup
       9: invokespecial #3                  // Method java/util/concurrent/ConcurrentHashMap."<init>":()V
      12: putfield      #4                  // Field path2Invoker:Ljava/util/concurrent/ConcurrentHashMap;
      15: aload_0
      16: new           #2                  // class java/util/concurrent/ConcurrentHashMap
      19: dup
      20: invokespecial #3                  // Method java/util/concurrent/ConcurrentHashMap."<init>":()V
      23: putfield      #5                  // Field nativeStub:Ljava/util/concurrent/ConcurrentHashMap;
      26: return

  public void add(java.lang.String, org.apache.dubbo.rpc.Invoker<?>);
    Code:
       0: aload_0
       1: getfield      #4                  // Field path2Invoker:Ljava/util/concurrent/ConcurrentHashMap;
       4: aload_1
       5: aload_2
       6: invokevirtual #6                  // Method java/util/concurrent/ConcurrentHashMap.put:(Ljava/lang/Object;Ljava/lang/Object;)Ljava/lang/Object;
       9: pop
      10: return

  public org.apache.dubbo.rpc.Invoker<?> resolve(java.lang.String);
    Code:
       0: aload_0
       1: getfield      #4                  // Field path2Invoker:Ljava/util/concurrent/ConcurrentHashMap;
       4: aload_1
       5: invokevirtual #7                  // Method java/util/concurrent/ConcurrentHashMap.get:(Ljava/lang/Object;)Ljava/lang/Object;
       8: checkcast     #8                  // class org/apache/dubbo/rpc/Invoker
      11: areturn

  public boolean hasNativeStub(java.lang.String);
    Code:
       0: aload_0
       1: getfield      #5                  // Field nativeStub:Ljava/util/concurrent/ConcurrentHashMap;
       4: aload_1
       5: invokevirtual #9                  // Method java/util/concurrent/ConcurrentHashMap.containsKey:(Ljava/lang/Object;)Z
       8: ireturn

  public void addNativeStub(java.lang.String);
    Code:
       0: aload_0
       1: getfield      #5                  // Field nativeStub:Ljava/util/concurrent/ConcurrentHashMap;
       4: aload_1
       5: iconst_0
       6: invokestatic  #10                 // Method java/lang/Integer.valueOf:(I)Ljava/lang/Integer;
       9: invokevirtual #6                  // Method java/util/concurrent/ConcurrentHashMap.put:(Ljava/lang/Object;Ljava/lang/Object;)Ljava/lang/Object;
      12: pop
      13: return

  public void remove(java.lang.String);
    Code:
       0: aload_0
       1: getfield      #4                  // Field path2Invoker:Ljava/util/concurrent/ConcurrentHashMap;
       4: aload_1
       5: invokevirtual #11                 // Method java/util/concurrent/ConcurrentHashMap.remove:(Ljava/lang/Object;)Ljava/lang/Object;
       8: pop
       9: return

  public void destroy();
    Code:
       0: aload_0
       1: getfield      #4                  // Field path2Invoker:Ljava/util/concurrent/ConcurrentHashMap;
       4: invokevirtual #12                 // Method java/util/concurrent/ConcurrentHashMap.clear:()V
       7: return
}
