Compiled from "TripleHttp2FrameCodecBuilder.java"
public class org.apache.dubbo.rpc.protocol.tri.TripleHttp2FrameCodecBuilder extends io.netty.handler.codec.http2.Http2FrameCodecBuilder {
  org.apache.dubbo.rpc.protocol.tri.TripleHttp2FrameCodecBuilder(io.netty.handler.codec.http2.Http2Connection);
    Code:
       0: aload_0
       1: invokespecial #1                  // Method io/netty/handler/codec/http2/Http2FrameCodecBuilder."<init>":()V
       4: aload_0
       5: aload_1
       6: invokevirtual #2                  // Method connection:(Lio/netty/handler/codec/http2/Http2Connection;)Lio/netty/handler/codec/http2/AbstractHttp2ConnectionHandlerBuilder;
       9: pop
      10: return

  public static org.apache.dubbo.rpc.protocol.tri.TripleHttp2FrameCodecBuilder fromConnection(io.netty.handler.codec.http2.Http2Connection);
    Code:
       0: new           #3                  // class org/apache/dubbo/rpc/protocol/tri/TripleHttp2FrameCodecBuilder
       3: dup
       4: aload_0
       5: invokespecial #4                  // Method "<init>":(Lio/netty/handler/codec/http2/Http2Connection;)V
       8: areturn

  public static org.apache.dubbo.rpc.protocol.tri.TripleHttp2FrameCodecBuilder forClient();
    Code:
       0: bipush        100
       2: invokestatic  #6                  // Method forClient:(I)Lorg/apache/dubbo/rpc/protocol/tri/TripleHttp2FrameCodecBuilder;
       5: areturn

  public static org.apache.dubbo.rpc.protocol.tri.TripleHttp2FrameCodecBuilder forClient(int);
    Code:
       0: new           #7                  // class io/netty/handler/codec/http2/DefaultHttp2Connection
       3: dup
       4: iconst_0
       5: iload_0
       6: invokespecial #8                  // Method io/netty/handler/codec/http2/DefaultHttp2Connection."<init>":(ZI)V
       9: invokestatic  #9                  // Method fromConnection:(Lio/netty/handler/codec/http2/Http2Connection;)Lorg/apache/dubbo/rpc/protocol/tri/TripleHttp2FrameCodecBuilder;
      12: areturn

  public static org.apache.dubbo.rpc.protocol.tri.TripleHttp2FrameCodecBuilder forServer();
    Code:
       0: bipush        100
       2: invokestatic  #10                 // Method forServer:(I)Lorg/apache/dubbo/rpc/protocol/tri/TripleHttp2FrameCodecBuilder;
       5: areturn

  public static org.apache.dubbo.rpc.protocol.tri.TripleHttp2FrameCodecBuilder forServer(int);
    Code:
       0: new           #7                  // class io/netty/handler/codec/http2/DefaultHttp2Connection
       3: dup
       4: iconst_1
       5: iload_0
       6: invokespecial #8                  // Method io/netty/handler/codec/http2/DefaultHttp2Connection."<init>":(ZI)V
       9: invokestatic  #9                  // Method fromConnection:(Lio/netty/handler/codec/http2/Http2Connection;)Lorg/apache/dubbo/rpc/protocol/tri/TripleHttp2FrameCodecBuilder;
      12: areturn

  public org.apache.dubbo.rpc.protocol.tri.TripleHttp2FrameCodecBuilder customizeConnection(java.util.function.Consumer<io.netty.handler.codec.http2.Http2Connection>);
    Code:
       0: aload_0
       1: invokevirtual #11                 // Method connection:()Lio/netty/handler/codec/http2/Http2Connection;
       4: astore_2
       5: aload_2
       6: ldc           #12                 // String connection cannot be null.
       8: invokestatic  #13                 // Method org/apache/dubbo/common/utils/Assert.notNull:(Ljava/lang/Object;Ljava/lang/String;)V
      11: aload_1
      12: aload_2
      13: invokeinterface #14,  2           // InterfaceMethod java/util/function/Consumer.accept:(Ljava/lang/Object;)V
      18: aload_0
      19: areturn

  public org.apache.dubbo.rpc.protocol.tri.TripleHttp2FrameCodecBuilder remoteFlowController(io.netty.handler.codec.http2.Http2RemoteFlowController);
    Code:
       0: aload_0
       1: aload_1
       2: invokedynamic #15,  0             // InvokeDynamic #0:accept:(Lio/netty/handler/codec/http2/Http2RemoteFlowController;)Ljava/util/function/Consumer;
       7: invokevirtual #16                 // Method customizeConnection:(Ljava/util/function/Consumer;)Lorg/apache/dubbo/rpc/protocol/tri/TripleHttp2FrameCodecBuilder;
      10: areturn

  public org.apache.dubbo.rpc.protocol.tri.TripleHttp2FrameCodecBuilder localFlowController(io.netty.handler.codec.http2.Http2LocalFlowController);
    Code:
       0: aload_0
       1: aload_1
       2: invokedynamic #17,  0             // InvokeDynamic #1:accept:(Lio/netty/handler/codec/http2/Http2LocalFlowController;)Ljava/util/function/Consumer;
       7: invokevirtual #16                 // Method customizeConnection:(Ljava/util/function/Consumer;)Lorg/apache/dubbo/rpc/protocol/tri/TripleHttp2FrameCodecBuilder;
      10: areturn

  private static void lambda$localFlowController$1(io.netty.handler.codec.http2.Http2LocalFlowController, io.netty.handler.codec.http2.Http2Connection);
    Code:
       0: aload_1
       1: invokeinterface #18,  1           // InterfaceMethod io/netty/handler/codec/http2/Http2Connection.local:()Lio/netty/handler/codec/http2/Http2Connection$Endpoint;
       6: aload_0
       7: invokeinterface #19,  2           // InterfaceMethod io/netty/handler/codec/http2/Http2Connection$Endpoint.flowController:(Lio/netty/handler/codec/http2/Http2FlowController;)V
      12: return

  private static void lambda$remoteFlowController$0(io.netty.handler.codec.http2.Http2RemoteFlowController, io.netty.handler.codec.http2.Http2Connection);
    Code:
       0: aload_1
       1: invokeinterface #20,  1           // InterfaceMethod io/netty/handler/codec/http2/Http2Connection.remote:()Lio/netty/handler/codec/http2/Http2Connection$Endpoint;
       6: aload_0
       7: invokeinterface #19,  2           // InterfaceMethod io/netty/handler/codec/http2/Http2Connection$Endpoint.flowController:(Lio/netty/handler/codec/http2/Http2FlowController;)V
      12: return
}
