Compiled from "AbstractNetwork.java"
class com.google.common.graph.AbstractNetwork$1$1 extends java.util.AbstractSet<com.google.common.graph.EndpointPair<N>> {
  final com.google.common.graph.AbstractNetwork$1 this$1;

  com.google.common.graph.AbstractNetwork$1$1(com.google.common.graph.AbstractNetwork$1);
    Code:
       0: aload_0
       1: aload_1
       2: putfield      #1                  // Field this$1:Lcom/google/common/graph/AbstractNetwork$1;
       5: aload_0
       6: invokespecial #2                  // Method java/util/AbstractSet."<init>":()V
       9: return

  public java.util.Iterator<com.google.common.graph.EndpointPair<N>> iterator();
    Code:
       0: aload_0
       1: getfield      #1                  // Field this$1:Lcom/google/common/graph/AbstractNetwork$1;
       4: getfield      #3                  // Field com/google/common/graph/AbstractNetwork$1.this$0:Lcom/google/common/graph/AbstractNetwork;
       7: invokevirtual #4                  // Method com/google/common/graph/AbstractNetwork.edges:()Ljava/util/Set;
      10: invokeinterface #5,  1            // InterfaceMethod java/util/Set.iterator:()Ljava/util/Iterator;
      15: aload_0
      16: invokedynamic #6,  0              // InvokeDynamic #0:apply:(Lcom/google/common/graph/AbstractNetwork$1$1;)Lcom/google/common/base/Function;
      21: invokestatic  #7                  // Method com/google/common/collect/Iterators.transform:(Ljava/util/Iterator;Lcom/google/common/base/Function;)Ljava/util/Iterator;
      24: areturn

  public int size();
    Code:
       0: aload_0
       1: getfield      #1                  // Field this$1:Lcom/google/common/graph/AbstractNetwork$1;
       4: getfield      #3                  // Field com/google/common/graph/AbstractNetwork$1.this$0:Lcom/google/common/graph/AbstractNetwork;
       7: invokevirtual #4                  // Method com/google/common/graph/AbstractNetwork.edges:()Ljava/util/Set;
      10: invokeinterface #8,  1            // InterfaceMethod java/util/Set.size:()I
      15: ireturn

  public boolean contains(java.lang.Object);
    Code:
       0: aload_1
       1: instanceof    #9                  // class com/google/common/graph/EndpointPair
       4: ifne          9
       7: iconst_0
       8: ireturn
       9: aload_1
      10: checkcast     #9                  // class com/google/common/graph/EndpointPair
      13: astore_2
      14: aload_0
      15: getfield      #1                  // Field this$1:Lcom/google/common/graph/AbstractNetwork$1;
      18: aload_2
      19: invokevirtual #10                 // Method com/google/common/graph/AbstractNetwork$1.isOrderingCompatible:(Lcom/google/common/graph/EndpointPair;)Z
      22: ifeq          71
      25: aload_0
      26: getfield      #1                  // Field this$1:Lcom/google/common/graph/AbstractNetwork$1;
      29: invokevirtual #11                 // Method com/google/common/graph/AbstractNetwork$1.nodes:()Ljava/util/Set;
      32: aload_2
      33: invokevirtual #12                 // Method com/google/common/graph/EndpointPair.nodeU:()Ljava/lang/Object;
      36: invokeinterface #13,  2           // InterfaceMethod java/util/Set.contains:(Ljava/lang/Object;)Z
      41: ifeq          71
      44: aload_0
      45: getfield      #1                  // Field this$1:Lcom/google/common/graph/AbstractNetwork$1;
      48: aload_2
      49: invokevirtual #12                 // Method com/google/common/graph/EndpointPair.nodeU:()Ljava/lang/Object;
      52: invokevirtual #14                 // Method com/google/common/graph/AbstractNetwork$1.successors:(Ljava/lang/Object;)Ljava/util/Set;
      55: aload_2
      56: invokevirtual #15                 // Method com/google/common/graph/EndpointPair.nodeV:()Ljava/lang/Object;
      59: invokeinterface #13,  2           // InterfaceMethod java/util/Set.contains:(Ljava/lang/Object;)Z
      64: ifeq          71
      67: iconst_1
      68: goto          72
      71: iconst_0
      72: ireturn

  private com.google.common.graph.EndpointPair lambda$iterator$0(java.lang.Object);
    Code:
       0: aload_0
       1: getfield      #1                  // Field this$1:Lcom/google/common/graph/AbstractNetwork$1;
       4: getfield      #3                  // Field com/google/common/graph/AbstractNetwork$1.this$0:Lcom/google/common/graph/AbstractNetwork;
       7: aload_1
       8: invokevirtual #16                 // Method com/google/common/graph/AbstractNetwork.incidentNodes:(Ljava/lang/Object;)Lcom/google/common/graph/EndpointPair;
      11: areturn
}
