Compiled from "Graphs.java"
class com.google.common.graph.Graphs$TransposedGraph$1 extends com.google.common.graph.IncidentEdgeSet<N> {
  final com.google.common.graph.Graphs$TransposedGraph this$0;

  com.google.common.graph.Graphs$TransposedGraph$1(com.google.common.graph.Graphs$TransposedGraph, com.google.common.graph.BaseGraph, java.lang.Object);
    Code:
       0: aload_0
       1: aload_1
       2: putfield      #1                  // Field this$0:Lcom/google/common/graph/Graphs$TransposedGraph;
       5: aload_0
       6: aload_2
       7: aload_3
       8: invokespecial #2                  // Method com/google/common/graph/IncidentEdgeSet."<init>":(Lcom/google/common/graph/BaseGraph;Ljava/lang/Object;)V
      11: return

  public java.util.Iterator<com.google.common.graph.EndpointPair<N>> iterator();
    Code:
       0: aload_0
       1: getfield      #1                  // Field this$0:Lcom/google/common/graph/Graphs$TransposedGraph;
       4: invokevirtual #3                  // Method com/google/common/graph/Graphs$TransposedGraph.delegate:()Lcom/google/common/graph/Graph;
       7: aload_0
       8: getfield      #4                  // Field node:Ljava/lang/Object;
      11: invokeinterface #5,  2            // InterfaceMethod com/google/common/graph/Graph.incidentEdges:(Ljava/lang/Object;)Ljava/util/Set;
      16: invokeinterface #6,  1            // InterfaceMethod java/util/Set.iterator:()Ljava/util/Iterator;
      21: aload_0
      22: invokedynamic #7,  0              // InvokeDynamic #0:apply:(Lcom/google/common/graph/Graphs$TransposedGraph$1;)Lcom/google/common/base/Function;
      27: invokestatic  #8                  // Method com/google/common/collect/Iterators.transform:(Ljava/util/Iterator;Lcom/google/common/base/Function;)Ljava/util/Iterator;
      30: areturn

  private com.google.common.graph.EndpointPair lambda$iterator$0(com.google.common.graph.EndpointPair);
    Code:
       0: aload_0
       1: getfield      #1                  // Field this$0:Lcom/google/common/graph/Graphs$TransposedGraph;
       4: invokevirtual #3                  // Method com/google/common/graph/Graphs$TransposedGraph.delegate:()Lcom/google/common/graph/Graph;
       7: aload_1
       8: invokevirtual #9                  // Method com/google/common/graph/EndpointPair.nodeV:()Ljava/lang/Object;
      11: aload_1
      12: invokevirtual #10                 // Method com/google/common/graph/EndpointPair.nodeU:()Ljava/lang/Object;
      15: invokestatic  #11                 // Method com/google/common/graph/EndpointPair.of:(Lcom/google/common/graph/Graph;Ljava/lang/Object;Ljava/lang/Object;)Lcom/google/common/graph/EndpointPair;
      18: areturn
}
