Compiled from "ApplicationContextFactory.java"
public interface org.springframework.boot.ApplicationContextFactory {
  public static final org.springframework.boot.ApplicationContextFactory DEFAULT;

  public default java.lang.Class<? extends org.springframework.core.env.ConfigurableEnvironment> getEnvironmentType(org.springframework.boot.WebApplicationType);
    Code:
       0: aconst_null
       1: areturn

  public default org.springframework.core.env.ConfigurableEnvironment createEnvironment(org.springframework.boot.WebApplicationType);
    Code:
       0: aconst_null
       1: areturn

  public abstract org.springframework.context.ConfigurableApplicationContext create(org.springframework.boot.WebApplicationType);

  public static org.springframework.boot.ApplicationContextFactory ofContextClass(java.lang.Class<? extends org.springframework.context.ConfigurableApplicationContext>);
    Code:
       0: aload_0
       1: invokedynamic #1,  0              // InvokeDynamic #0:get:(Ljava/lang/Class;)Ljava/util/function/Supplier;
       6: invokestatic  #5                  // InterfaceMethod of:(Ljava/util/function/Supplier;)Lorg/springframework/boot/ApplicationContextFactory;
       9: areturn

  public static org.springframework.boot.ApplicationContextFactory of(java.util.function.Supplier<org.springframework.context.ConfigurableApplicationContext>);
    Code:
       0: aload_0
       1: invokedynamic #11,  0             // InvokeDynamic #1:create:(Ljava/util/function/Supplier;)Lorg/springframework/boot/ApplicationContextFactory;
       6: areturn

  private static org.springframework.context.ConfigurableApplicationContext lambda$of$1(java.util.function.Supplier, org.springframework.boot.WebApplicationType);
    Code:
       0: aload_0
       1: invokeinterface #14,  1           // InterfaceMethod java/util/function/Supplier.get:()Ljava/lang/Object;
       6: checkcast     #19                 // class org/springframework/context/ConfigurableApplicationContext
       9: areturn

  private static org.springframework.context.ConfigurableApplicationContext lambda$ofContextClass$0(java.lang.Class);
    Code:
       0: aload_0
       1: invokestatic  #21                 // Method org/springframework/beans/BeanUtils.instantiateClass:(Ljava/lang/Class;)Ljava/lang/Object;
       4: checkcast     #19                 // class org/springframework/context/ConfigurableApplicationContext
       7: areturn

  static {};
    Code:
       0: new           #27                 // class org/springframework/boot/DefaultApplicationContextFactory
       3: dup
       4: invokespecial #29                 // Method org/springframework/boot/DefaultApplicationContextFactory."<init>":()V
       7: putstatic     #33                 // Field DEFAULT:Lorg/springframework/boot/ApplicationContextFactory;
      10: return
}
