Compiled from "Banner.java"
public final class org.springframework.boot.Banner$Mode extends java.lang.Enum<org.springframework.boot.Banner$Mode> {
  public static final org.springframework.boot.Banner$Mode OFF;

  public static final org.springframework.boot.Banner$Mode CONSOLE;

  public static final org.springframework.boot.Banner$Mode LOG;

  private static final org.springframework.boot.Banner$Mode[] $VALUES;

  public static org.springframework.boot.Banner$Mode[] values();
    Code:
       0: getstatic     #13                 // Field $VALUES:[Lorg/springframework/boot/Banner$Mode;
       3: invokevirtual #17                 // Method "[Lorg/springframework/boot/Banner$Mode;".clone:()Ljava/lang/Object;
       6: checkcast     #18                 // class "[Lorg/springframework/boot/Banner$Mode;"
       9: areturn

  public static org.springframework.boot.Banner$Mode valueOf(java.lang.String);
    Code:
       0: ldc           #1                  // class org/springframework/boot/Banner$Mode
       2: aload_0
       3: invokestatic  #22                 // Method java/lang/Enum.valueOf:(Ljava/lang/Class;Ljava/lang/String;)Ljava/lang/Enum;
       6: checkcast     #1                  // class org/springframework/boot/Banner$Mode
       9: areturn

  private org.springframework.boot.Banner$Mode();
    Code:
       0: aload_0
       1: aload_1
       2: iload_2
       3: invokespecial #28                 // Method java/lang/Enum."<init>":(Ljava/lang/String;I)V
       6: return

  private static org.springframework.boot.Banner$Mode[] $values();
    Code:
       0: iconst_3
       1: anewarray     #1                  // class org/springframework/boot/Banner$Mode
       4: dup
       5: iconst_0
       6: getstatic     #3                  // Field OFF:Lorg/springframework/boot/Banner$Mode;
       9: aastore
      10: dup
      11: iconst_1
      12: getstatic     #7                  // Field CONSOLE:Lorg/springframework/boot/Banner$Mode;
      15: aastore
      16: dup
      17: iconst_2
      18: getstatic     #10                 // Field LOG:Lorg/springframework/boot/Banner$Mode;
      21: aastore
      22: areturn

  static {};
    Code:
       0: new           #1                  // class org/springframework/boot/Banner$Mode
       3: dup
       4: ldc           #32                 // String OFF
       6: iconst_0
       7: invokespecial #33                 // Method "<init>":(Ljava/lang/String;I)V
      10: putstatic     #3                  // Field OFF:Lorg/springframework/boot/Banner$Mode;
      13: new           #1                  // class org/springframework/boot/Banner$Mode
      16: dup
      17: ldc           #34                 // String CONSOLE
      19: iconst_1
      20: invokespecial #33                 // Method "<init>":(Ljava/lang/String;I)V
      23: putstatic     #7                  // Field CONSOLE:Lorg/springframework/boot/Banner$Mode;
      26: new           #1                  // class org/springframework/boot/Banner$Mode
      29: dup
      30: ldc           #35                 // String LOG
      32: iconst_2
      33: invokespecial #33                 // Method "<init>":(Ljava/lang/String;I)V
      36: putstatic     #10                 // Field LOG:Lorg/springframework/boot/Banner$Mode;
      39: invokestatic  #36                 // Method $values:()[Lorg/springframework/boot/Banner$Mode;
      42: putstatic     #13                 // Field $VALUES:[Lorg/springframework/boot/Banner$Mode;
      45: return
}
