Compiled from "BootstrapRegistry.java"
class org.springframework.boot.BootstrapRegistry$InstanceSupplier$1 implements org.springframework.boot.BootstrapRegistry$InstanceSupplier<T> {
  final org.springframework.boot.BootstrapRegistry$InstanceSupplier val$parent;

  final org.springframework.boot.BootstrapRegistry$Scope val$scope;

  final org.springframework.boot.BootstrapRegistry$InstanceSupplier this$0;

  org.springframework.boot.BootstrapRegistry$InstanceSupplier$1(org.springframework.boot.BootstrapRegistry$InstanceSupplier, org.springframework.boot.BootstrapRegistry$InstanceSupplier, org.springframework.boot.BootstrapRegistry$Scope);
    Code:
       0: aload_0
       1: aload_1
       2: putfield      #1                  // Field this$0:Lorg/springframework/boot/BootstrapRegistry$InstanceSupplier;
       5: aload_0
       6: aload_2
       7: putfield      #7                  // Field val$parent:Lorg/springframework/boot/BootstrapRegistry$InstanceSupplier;
      10: aload_0
      11: aload_3
      12: putfield      #10                 // Field val$scope:Lorg/springframework/boot/BootstrapRegistry$Scope;
      15: aload_0
      16: invokespecial #14                 // Method java/lang/Object."<init>":()V
      19: return

  public T get(org.springframework.boot.BootstrapContext);
    Code:
       0: aload_0
       1: getfield      #7                  // Field val$parent:Lorg/springframework/boot/BootstrapRegistry$InstanceSupplier;
       4: aload_1
       5: invokeinterface #20,  2           // InterfaceMethod org/springframework/boot/BootstrapRegistry$InstanceSupplier.get:(Lorg/springframework/boot/BootstrapContext;)Ljava/lang/Object;
      10: areturn

  public org.springframework.boot.BootstrapRegistry$Scope getScope();
    Code:
       0: aload_0
       1: getfield      #10                 // Field val$scope:Lorg/springframework/boot/BootstrapRegistry$Scope;
       4: areturn
}
