Compiled from "BootstrapRegistry.java"
public interface org.springframework.boot.BootstrapRegistry$InstanceSupplier<T> {
  public abstract T get(org.springframework.boot.BootstrapContext);

  public default org.springframework.boot.BootstrapRegistry$Scope getScope();
    Code:
       0: getstatic     #1                  // Field org/springframework/boot/BootstrapRegistry$Scope.SINGLETON:Lorg/springframework/boot/BootstrapRegistry$Scope;
       3: areturn

  public default org.springframework.boot.BootstrapRegistry$InstanceSupplier<T> withScope(org.springframework.boot.BootstrapRegistry$Scope);
    Code:
       0: aload_1
       1: ldc           #7                  // String Scope must not be null
       3: invokestatic  #9                  // Method org/springframework/util/Assert.notNull:(Ljava/lang/Object;Ljava/lang/String;)V
       6: aload_0
       7: astore_2
       8: new           #15                 // class org/springframework/boot/BootstrapRegistry$InstanceSupplier$1
      11: dup
      12: aload_0
      13: aload_2
      14: aload_1
      15: invokespecial #17                 // Method org/springframework/boot/BootstrapRegistry$InstanceSupplier$1."<init>":(Lorg/springframework/boot/BootstrapRegistry$InstanceSupplier;Lorg/springframework/boot/BootstrapRegistry$InstanceSupplier;Lorg/springframework/boot/BootstrapRegistry$Scope;)V
      18: areturn

  public static <T> org.springframework.boot.BootstrapRegistry$InstanceSupplier<T> of(T);
    Code:
       0: aload_0
       1: invokedynamic #21,  0             // InvokeDynamic #0:get:(Ljava/lang/Object;)Lorg/springframework/boot/BootstrapRegistry$InstanceSupplier;
       6: areturn

  public static <T> org.springframework.boot.BootstrapRegistry$InstanceSupplier<T> from(java.util.function.Supplier<T>);
    Code:
       0: aload_0
       1: invokedynamic #25,  0             // InvokeDynamic #1:get:(Ljava/util/function/Supplier;)Lorg/springframework/boot/BootstrapRegistry$InstanceSupplier;
       6: areturn

  private static java.lang.Object lambda$from$1(java.util.function.Supplier, org.springframework.boot.BootstrapContext);
    Code:
       0: aload_0
       1: ifnull        13
       4: aload_0
       5: invokeinterface #28,  1           // InterfaceMethod java/util/function/Supplier.get:()Ljava/lang/Object;
      10: goto          14
      13: aconst_null
      14: areturn

  private static java.lang.Object lambda$of$0(java.lang.Object, org.springframework.boot.BootstrapContext);
    Code:
       0: aload_0
       1: areturn
}
