Compiled from "BootstrapContextClosedEvent.java"
public class org.springframework.boot.BootstrapContextClosedEvent extends org.springframework.context.ApplicationEvent {
  private final org.springframework.context.ConfigurableApplicationContext applicationContext;

  org.springframework.boot.BootstrapContextClosedEvent(org.springframework.boot.BootstrapContext, org.springframework.context.ConfigurableApplicationContext);
    Code:
       0: aload_0
       1: aload_1
       2: invokespecial #1                  // Method org/springframework/context/ApplicationEvent."<init>":(Ljava/lang/Object;)V
       5: aload_0
       6: aload_2
       7: putfield      #7                  // Field applicationContext:Lorg/springframework/context/ConfigurableApplicationContext;
      10: return

  public org.springframework.boot.BootstrapContext getBootstrapContext();
    Code:
       0: aload_0
       1: getfield      #13                 // Field source:Ljava/lang/Object;
       4: checkcast     #17                 // class org/springframework/boot/BootstrapContext
       7: areturn

  public org.springframework.context.ConfigurableApplicationContext getApplicationContext();
    Code:
       0: aload_0
       1: getfield      #7                  // Field applicationContext:Lorg/springframework/context/ConfigurableApplicationContext;
       4: areturn
}
