Compiled from "DefaultPropertiesPropertySource.java"
public class org.springframework.boot.DefaultPropertiesPropertySource extends org.springframework.core.env.MapPropertySource {
  public static final java.lang.String NAME;

  public org.springframework.boot.DefaultPropertiesPropertySource(java.util.Map<java.lang.String, java.lang.Object>);
    Code:
       0: aload_0
       1: ldc           #3                  // String defaultProperties
       3: aload_1
       4: invokespecial #5                  // Method org/springframework/core/env/MapPropertySource."<init>":(Ljava/lang/String;Ljava/util/Map;)V
       7: return

  public static boolean hasMatchingName(org.springframework.core.env.PropertySource<?>);
    Code:
       0: aload_0
       1: ifnull        20
       4: aload_0
       5: invokevirtual #11                 // Method org/springframework/core/env/PropertySource.getName:()Ljava/lang/String;
       8: ldc           #3                  // String defaultProperties
      10: invokevirtual #17                 // Method java/lang/String.equals:(Ljava/lang/Object;)Z
      13: ifeq          20
      16: iconst_1
      17: goto          21
      20: iconst_0
      21: ireturn

  public static void ifNotEmpty(java.util.Map<java.lang.String, java.lang.Object>, java.util.function.Consumer<org.springframework.boot.DefaultPropertiesPropertySource>);
    Code:
       0: aload_0
       1: invokestatic  #23                 // Method org/springframework/util/CollectionUtils.isEmpty:(Ljava/util/Map;)Z
       4: ifne          25
       7: aload_1
       8: ifnull        25
      11: aload_1
      12: new           #1                  // class org/springframework/boot/DefaultPropertiesPropertySource
      15: dup
      16: aload_0
      17: invokespecial #29                 // Method "<init>":(Ljava/util/Map;)V
      20: invokeinterface #32,  2           // InterfaceMethod java/util/function/Consumer.accept:(Ljava/lang/Object;)V
      25: return

  public static void addOrMerge(java.util.Map<java.lang.String, java.lang.Object>, org.springframework.core.env.MutablePropertySources);
    Code:
       0: aload_0
       1: invokestatic  #23                 // Method org/springframework/util/CollectionUtils.isEmpty:(Ljava/util/Map;)Z
       4: ifne          61
       7: new           #38                 // class java/util/HashMap
      10: dup
      11: invokespecial #40                 // Method java/util/HashMap."<init>":()V
      14: astore_2
      15: new           #1                  // class org/springframework/boot/DefaultPropertiesPropertySource
      18: dup
      19: aload_2
      20: invokespecial #29                 // Method "<init>":(Ljava/util/Map;)V
      23: astore_3
      24: aload_1
      25: ldc           #3                  // String defaultProperties
      27: invokevirtual #43                 // Method org/springframework/core/env/MutablePropertySources.contains:(Ljava/lang/String;)Z
      30: ifeq          49
      33: aload_0
      34: aload_1
      35: aload_2
      36: invokestatic  #49                 // Method mergeIfPossible:(Ljava/util/Map;Lorg/springframework/core/env/MutablePropertySources;Ljava/util/Map;)V
      39: aload_1
      40: ldc           #3                  // String defaultProperties
      42: aload_3
      43: invokevirtual #53                 // Method org/springframework/core/env/MutablePropertySources.replace:(Ljava/lang/String;Lorg/springframework/core/env/PropertySource;)V
      46: goto          61
      49: aload_2
      50: aload_0
      51: invokeinterface #57,  2           // InterfaceMethod java/util/Map.putAll:(Ljava/util/Map;)V
      56: aload_1
      57: aload_3
      58: invokevirtual #62                 // Method org/springframework/core/env/MutablePropertySources.addLast:(Lorg/springframework/core/env/PropertySource;)V
      61: return

  private static void mergeIfPossible(java.util.Map<java.lang.String, java.lang.Object>, org.springframework.core.env.MutablePropertySources, java.util.Map<java.lang.String, java.lang.Object>);
    Code:
       0: aload_1
       1: ldc           #3                  // String defaultProperties
       3: invokevirtual #66                 // Method org/springframework/core/env/MutablePropertySources.get:(Ljava/lang/String;)Lorg/springframework/core/env/PropertySource;
       6: astore_3
       7: aload_3
       8: ifnull        43
      11: aload_3
      12: invokevirtual #70                 // Method org/springframework/core/env/PropertySource.getSource:()Ljava/lang/Object;
      15: astore        4
      17: aload         4
      19: instanceof    #58                 // class java/util/Map
      22: ifeq          36
      25: aload_2
      26: aload         4
      28: checkcast     #58                 // class java/util/Map
      31: invokeinterface #57,  2           // InterfaceMethod java/util/Map.putAll:(Ljava/util/Map;)V
      36: aload_2
      37: aload_0
      38: invokeinterface #57,  2           // InterfaceMethod java/util/Map.putAll:(Ljava/util/Map;)V
      43: return

  public static void moveToEnd(org.springframework.core.env.ConfigurableEnvironment);
    Code:
       0: aload_0
       1: invokeinterface #74,  1           // InterfaceMethod org/springframework/core/env/ConfigurableEnvironment.getPropertySources:()Lorg/springframework/core/env/MutablePropertySources;
       6: invokestatic  #80                 // Method moveToEnd:(Lorg/springframework/core/env/MutablePropertySources;)V
       9: return

  public static void moveToEnd(org.springframework.core.env.MutablePropertySources);
    Code:
       0: aload_0
       1: ldc           #3                  // String defaultProperties
       3: invokevirtual #84                 // Method org/springframework/core/env/MutablePropertySources.remove:(Ljava/lang/String;)Lorg/springframework/core/env/PropertySource;
       6: astore_1
       7: aload_1
       8: ifnull        16
      11: aload_0
      12: aload_1
      13: invokevirtual #62                 // Method org/springframework/core/env/MutablePropertySources.addLast:(Lorg/springframework/core/env/PropertySource;)V
      16: return
}
