Compiled from "DefaultApplicationArguments.java"
public class org.springframework.boot.DefaultApplicationArguments implements org.springframework.boot.ApplicationArguments {
  private final org.springframework.boot.DefaultApplicationArguments$Source source;

  private final java.lang.String[] args;

  public org.springframework.boot.DefaultApplicationArguments(java.lang.String...);
    Code:
       0: aload_0
       1: invokespecial #1                  // Method java/lang/Object."<init>":()V
       4: aload_1
       5: ldc           #7                  // String Args must not be null
       7: invokestatic  #9                  // Method org/springframework/util/Assert.notNull:(Ljava/lang/Object;Ljava/lang/String;)V
      10: aload_0
      11: new           #15                 // class org/springframework/boot/DefaultApplicationArguments$Source
      14: dup
      15: aload_1
      16: invokespecial #17                 // Method org/springframework/boot/DefaultApplicationArguments$Source."<init>":([Ljava/lang/String;)V
      19: putfield      #20                 // Field source:Lorg/springframework/boot/DefaultApplicationArguments$Source;
      22: aload_0
      23: aload_1
      24: putfield      #26                 // Field args:[Ljava/lang/String;
      27: return

  public java.lang.String[] getSourceArgs();
    Code:
       0: aload_0
       1: getfield      #26                 // Field args:[Ljava/lang/String;
       4: areturn

  public java.util.Set<java.lang.String> getOptionNames();
    Code:
       0: aload_0
       1: getfield      #20                 // Field source:Lorg/springframework/boot/DefaultApplicationArguments$Source;
       4: invokevirtual #30                 // Method org/springframework/boot/DefaultApplicationArguments$Source.getPropertyNames:()[Ljava/lang/String;
       7: astore_1
       8: new           #34                 // class java/util/HashSet
      11: dup
      12: aload_1
      13: invokestatic  #36                 // Method java/util/Arrays.asList:([Ljava/lang/Object;)Ljava/util/List;
      16: invokespecial #42                 // Method java/util/HashSet."<init>":(Ljava/util/Collection;)V
      19: invokestatic  #45                 // Method java/util/Collections.unmodifiableSet:(Ljava/util/Set;)Ljava/util/Set;
      22: areturn

  public boolean containsOption(java.lang.String);
    Code:
       0: aload_0
       1: getfield      #20                 // Field source:Lorg/springframework/boot/DefaultApplicationArguments$Source;
       4: aload_1
       5: invokevirtual #51                 // Method org/springframework/boot/DefaultApplicationArguments$Source.containsProperty:(Ljava/lang/String;)Z
       8: ireturn

  public java.util.List<java.lang.String> getOptionValues(java.lang.String);
    Code:
       0: aload_0
       1: getfield      #20                 // Field source:Lorg/springframework/boot/DefaultApplicationArguments$Source;
       4: aload_1
       5: invokevirtual #55                 // Method org/springframework/boot/DefaultApplicationArguments$Source.getOptionValues:(Ljava/lang/String;)Ljava/util/List;
       8: astore_2
       9: aload_2
      10: ifnull        20
      13: aload_2
      14: invokestatic  #59                 // Method java/util/Collections.unmodifiableList:(Ljava/util/List;)Ljava/util/List;
      17: goto          21
      20: aconst_null
      21: areturn

  public java.util.List<java.lang.String> getNonOptionArgs();
    Code:
       0: aload_0
       1: getfield      #20                 // Field source:Lorg/springframework/boot/DefaultApplicationArguments$Source;
       4: invokevirtual #63                 // Method org/springframework/boot/DefaultApplicationArguments$Source.getNonOptionArgs:()Ljava/util/List;
       7: areturn
}
