Compiled from "DefaultApplicationContextFactory.java"
class org.springframework.boot.DefaultApplicationContextFactory implements org.springframework.boot.ApplicationContextFactory {
  org.springframework.boot.DefaultApplicationContextFactory();
    Code:
       0: aload_0
       1: invokespecial #1                  // Method java/lang/Object."<init>":()V
       4: return

  public java.lang.Class<? extends org.springframework.core.env.ConfigurableEnvironment> getEnvironmentType(org.springframework.boot.WebApplicationType);
    Code:
       0: aload_0
       1: aload_1
       2: invokedynamic #7,  0              // InvokeDynamic #0:apply:()Ljava/util/function/BiFunction;
       7: aconst_null
       8: invokevirtual #11                 // Method getFromSpringFactories:(Lorg/springframework/boot/WebApplicationType;Ljava/util/function/BiFunction;Ljava/util/function/Supplier;)Ljava/lang/Object;
      11: checkcast     #17                 // class java/lang/Class
      14: areturn

  public org.springframework.core.env.ConfigurableEnvironment createEnvironment(org.springframework.boot.WebApplicationType);
    Code:
       0: aload_0
       1: aload_1
       2: invokedynamic #19,  0             // InvokeDynamic #1:apply:()Ljava/util/function/BiFunction;
       7: aconst_null
       8: invokevirtual #11                 // Method getFromSpringFactories:(Lorg/springframework/boot/WebApplicationType;Ljava/util/function/BiFunction;Ljava/util/function/Supplier;)Ljava/lang/Object;
      11: checkcast     #20                 // class org/springframework/core/env/ConfigurableEnvironment
      14: areturn

  public org.springframework.context.ConfigurableApplicationContext create(org.springframework.boot.WebApplicationType);
    Code:
       0: aload_0
       1: aload_1
       2: invokedynamic #22,  0             // InvokeDynamic #2:apply:()Ljava/util/function/BiFunction;
       7: aload_0
       8: invokedynamic #23,  0             // InvokeDynamic #3:get:(Lorg/springframework/boot/DefaultApplicationContextFactory;)Ljava/util/function/Supplier;
      13: invokevirtual #11                 // Method getFromSpringFactories:(Lorg/springframework/boot/WebApplicationType;Ljava/util/function/BiFunction;Ljava/util/function/Supplier;)Ljava/lang/Object;
      16: checkcast     #27                 // class org/springframework/context/ConfigurableApplicationContext
      19: areturn
      20: astore_2
      21: new           #31                 // class java/lang/IllegalStateException
      24: dup
      25: ldc           #33                 // String Unable create a default ApplicationContext instance, you may need a custom ApplicationContextFactory
      27: aload_2
      28: invokespecial #35                 // Method java/lang/IllegalStateException."<init>":(Ljava/lang/String;Ljava/lang/Throwable;)V
      31: athrow
    Exception table:
       from    to  target type
           0    19    20   Class java/lang/Exception

  private org.springframework.context.ConfigurableApplicationContext createDefaultApplicationContext();
    Code:
       0: invokestatic  #38                 // Method org/springframework/aot/AotDetector.useGeneratedArtifacts:()Z
       3: ifne          14
       6: new           #44                 // class org/springframework/context/annotation/AnnotationConfigApplicationContext
       9: dup
      10: invokespecial #46                 // Method org/springframework/context/annotation/AnnotationConfigApplicationContext."<init>":()V
      13: areturn
      14: new           #47                 // class org/springframework/context/support/GenericApplicationContext
      17: dup
      18: invokespecial #49                 // Method org/springframework/context/support/GenericApplicationContext."<init>":()V
      21: areturn

  private <T> T getFromSpringFactories(org.springframework.boot.WebApplicationType, java.util.function.BiFunction<org.springframework.boot.ApplicationContextFactory, org.springframework.boot.WebApplicationType, T>, java.util.function.Supplier<T>);
    Code:
       0: ldc           #50                 // class org/springframework/boot/ApplicationContextFactory
       2: aload_0
       3: invokevirtual #52                 // Method java/lang/Object.getClass:()Ljava/lang/Class;
       6: invokevirtual #56                 // Method java/lang/Class.getClassLoader:()Ljava/lang/ClassLoader;
       9: invokestatic  #60                 // Method org/springframework/core/io/support/SpringFactoriesLoader.loadFactories:(Ljava/lang/Class;Ljava/lang/ClassLoader;)Ljava/util/List;
      12: invokeinterface #66,  1           // InterfaceMethod java/util/List.iterator:()Ljava/util/Iterator;
      17: astore        4
      19: aload         4
      21: invokeinterface #72,  1           // InterfaceMethod java/util/Iterator.hasNext:()Z
      26: ifeq          63
      29: aload         4
      31: invokeinterface #77,  1           // InterfaceMethod java/util/Iterator.next:()Ljava/lang/Object;
      36: checkcast     #50                 // class org/springframework/boot/ApplicationContextFactory
      39: astore        5
      41: aload_2
      42: aload         5
      44: aload_1
      45: invokeinterface #81,  3           // InterfaceMethod java/util/function/BiFunction.apply:(Ljava/lang/Object;Ljava/lang/Object;)Ljava/lang/Object;
      50: astore        6
      52: aload         6
      54: ifnull        60
      57: aload         6
      59: areturn
      60: goto          19
      63: aload_3
      64: ifnull        76
      67: aload_3
      68: invokeinterface #86,  1           // InterfaceMethod java/util/function/Supplier.get:()Ljava/lang/Object;
      73: goto          77
      76: aconst_null
      77: areturn
}
