Compiled from "EnvironmentConverter.java"
final class org.springframework.boot.EnvironmentConverter {
  private static final java.lang.String CONFIGURABLE_WEB_ENVIRONMENT_CLASS;

  private static final java.util.Set<java.lang.String> SERVLET_ENVIRONMENT_SOURCE_NAMES;

  private final java.lang.ClassLoader classLoader;

  org.springframework.boot.EnvironmentConverter(java.lang.ClassLoader);
    Code:
       0: aload_0
       1: invokespecial #1                  // Method java/lang/Object."<init>":()V
       4: aload_0
       5: aload_1
       6: putfield      #7                  // Field classLoader:Ljava/lang/ClassLoader;
       9: return

  org.springframework.core.env.ConfigurableEnvironment convertEnvironmentIfNecessary(org.springframework.core.env.ConfigurableEnvironment, java.lang.Class<? extends org.springframework.core.env.ConfigurableEnvironment>);
    Code:
       0: aload_2
       1: aload_1
       2: invokevirtual #13                 // Method java/lang/Object.getClass:()Ljava/lang/Class;
       5: invokevirtual #17                 // Method java/lang/Object.equals:(Ljava/lang/Object;)Z
       8: ifeq          13
      11: aload_1
      12: areturn
      13: aload_0
      14: aload_1
      15: aload_2
      16: invokevirtual #21                 // Method convertEnvironment:(Lorg/springframework/core/env/ConfigurableEnvironment;Ljava/lang/Class;)Lorg/springframework/core/env/ConfigurableEnvironment;
      19: areturn

  private org.springframework.core.env.ConfigurableEnvironment convertEnvironment(org.springframework.core.env.ConfigurableEnvironment, java.lang.Class<? extends org.springframework.core.env.ConfigurableEnvironment>);
    Code:
       0: aload_0
       1: aload_2
       2: invokevirtual #25                 // Method createEnvironment:(Ljava/lang/Class;)Lorg/springframework/core/env/ConfigurableEnvironment;
       5: astore_3
       6: aload_3
       7: aload_1
       8: invokeinterface #29,  1           // InterfaceMethod org/springframework/core/env/ConfigurableEnvironment.getActiveProfiles:()[Ljava/lang/String;
      13: invokeinterface #35,  2           // InterfaceMethod org/springframework/core/env/ConfigurableEnvironment.setActiveProfiles:([Ljava/lang/String;)V
      18: aload_3
      19: aload_1
      20: invokeinterface #39,  1           // InterfaceMethod org/springframework/core/env/ConfigurableEnvironment.getConversionService:()Lorg/springframework/core/convert/support/ConfigurableConversionService;
      25: invokeinterface #43,  2           // InterfaceMethod org/springframework/core/env/ConfigurableEnvironment.setConversionService:(Lorg/springframework/core/convert/support/ConfigurableConversionService;)V
      30: aload_0
      31: aload_1
      32: aload_3
      33: invokevirtual #47                 // Method copyPropertySources:(Lorg/springframework/core/env/ConfigurableEnvironment;Lorg/springframework/core/env/ConfigurableEnvironment;)V
      36: aload_3
      37: areturn

  private org.springframework.core.env.ConfigurableEnvironment createEnvironment(java.lang.Class<? extends org.springframework.core.env.ConfigurableEnvironment>);
    Code:
       0: aload_1
       1: iconst_0
       2: anewarray     #51                 // class java/lang/Class
       5: invokevirtual #53                 // Method java/lang/Class.getDeclaredConstructor:([Ljava/lang/Class;)Ljava/lang/reflect/Constructor;
       8: astore_2
       9: aload_2
      10: invokestatic  #57                 // Method org/springframework/util/ReflectionUtils.makeAccessible:(Ljava/lang/reflect/Constructor;)V
      13: aload_2
      14: iconst_0
      15: anewarray     #2                  // class java/lang/Object
      18: invokevirtual #63                 // Method java/lang/reflect/Constructor.newInstance:([Ljava/lang/Object;)Ljava/lang/Object;
      21: checkcast     #30                 // class org/springframework/core/env/ConfigurableEnvironment
      24: areturn
      25: astore_2
      26: new           #71                 // class org/springframework/boot/ApplicationEnvironment
      29: dup
      30: invokespecial #73                 // Method org/springframework/boot/ApplicationEnvironment."<init>":()V
      33: areturn
    Exception table:
       from    to  target type
           0    24    25   Class java/lang/Exception

  private void copyPropertySources(org.springframework.core.env.ConfigurableEnvironment, org.springframework.core.env.ConfigurableEnvironment);
    Code:
       0: aload_0
       1: aload_2
       2: invokeinterface #74,  1           // InterfaceMethod org/springframework/core/env/ConfigurableEnvironment.getPropertySources:()Lorg/springframework/core/env/MutablePropertySources;
       7: aload_0
       8: aload_2
       9: invokevirtual #13                 // Method java/lang/Object.getClass:()Ljava/lang/Class;
      12: aload_0
      13: getfield      #7                  // Field classLoader:Ljava/lang/ClassLoader;
      16: invokevirtual #78                 // Method isServletEnvironment:(Ljava/lang/Class;Ljava/lang/ClassLoader;)Z
      19: invokevirtual #82                 // Method removePropertySources:(Lorg/springframework/core/env/MutablePropertySources;Z)V
      22: aload_1
      23: invokeinterface #74,  1           // InterfaceMethod org/springframework/core/env/ConfigurableEnvironment.getPropertySources:()Lorg/springframework/core/env/MutablePropertySources;
      28: invokevirtual #86                 // Method org/springframework/core/env/MutablePropertySources.iterator:()Ljava/util/Iterator;
      31: astore_3
      32: aload_3
      33: invokeinterface #92,  1           // InterfaceMethod java/util/Iterator.hasNext:()Z
      38: ifeq          82
      41: aload_3
      42: invokeinterface #98,  1           // InterfaceMethod java/util/Iterator.next:()Ljava/lang/Object;
      47: checkcast     #102                // class org/springframework/core/env/PropertySource
      50: astore        4
      52: getstatic     #104                // Field SERVLET_ENVIRONMENT_SOURCE_NAMES:Ljava/util/Set;
      55: aload         4
      57: invokevirtual #108                // Method org/springframework/core/env/PropertySource.getName:()Ljava/lang/String;
      60: invokeinterface #112,  2          // InterfaceMethod java/util/Set.contains:(Ljava/lang/Object;)Z
      65: ifne          79
      68: aload_2
      69: invokeinterface #74,  1           // InterfaceMethod org/springframework/core/env/ConfigurableEnvironment.getPropertySources:()Lorg/springframework/core/env/MutablePropertySources;
      74: aload         4
      76: invokevirtual #117                // Method org/springframework/core/env/MutablePropertySources.addLast:(Lorg/springframework/core/env/PropertySource;)V
      79: goto          32
      82: return

  private boolean isServletEnvironment(java.lang.Class<?>, java.lang.ClassLoader);
    Code:
       0: ldc           #121                // String org.springframework.web.context.ConfigurableWebEnvironment
       2: aload_2
       3: invokestatic  #123                // Method org/springframework/util/ClassUtils.forName:(Ljava/lang/String;Ljava/lang/ClassLoader;)Ljava/lang/Class;
       6: astore_3
       7: aload_3
       8: aload_1
       9: invokevirtual #129                // Method java/lang/Class.isAssignableFrom:(Ljava/lang/Class;)Z
      12: ireturn
      13: astore_3
      14: iconst_0
      15: ireturn
    Exception table:
       from    to  target type
           0    12    13   Class java/lang/Throwable

  private void removePropertySources(org.springframework.core.env.MutablePropertySources, boolean);
    Code:
       0: new           #135                // class java/util/HashSet
       3: dup
       4: invokespecial #137                // Method java/util/HashSet."<init>":()V
       7: astore_3
       8: aload_1
       9: invokevirtual #86                 // Method org/springframework/core/env/MutablePropertySources.iterator:()Ljava/util/Iterator;
      12: astore        4
      14: aload         4
      16: invokeinterface #92,  1           // InterfaceMethod java/util/Iterator.hasNext:()Z
      21: ifeq          51
      24: aload         4
      26: invokeinterface #98,  1           // InterfaceMethod java/util/Iterator.next:()Ljava/lang/Object;
      31: checkcast     #102                // class org/springframework/core/env/PropertySource
      34: astore        5
      36: aload_3
      37: aload         5
      39: invokevirtual #108                // Method org/springframework/core/env/PropertySource.getName:()Ljava/lang/String;
      42: invokeinterface #138,  2          // InterfaceMethod java/util/Set.add:(Ljava/lang/Object;)Z
      47: pop
      48: goto          14
      51: aload_3
      52: invokeinterface #141,  1          // InterfaceMethod java/util/Set.iterator:()Ljava/util/Iterator;
      57: astore        4
      59: aload         4
      61: invokeinterface #92,  1           // InterfaceMethod java/util/Iterator.hasNext:()Z
      66: ifeq          108
      69: aload         4
      71: invokeinterface #98,  1           // InterfaceMethod java/util/Iterator.next:()Ljava/lang/Object;
      76: checkcast     #142                // class java/lang/String
      79: astore        5
      81: iload_2
      82: ifeq          98
      85: getstatic     #104                // Field SERVLET_ENVIRONMENT_SOURCE_NAMES:Ljava/util/Set;
      88: aload         5
      90: invokeinterface #112,  2          // InterfaceMethod java/util/Set.contains:(Ljava/lang/Object;)Z
      95: ifne          105
      98: aload_1
      99: aload         5
     101: invokevirtual #144                // Method org/springframework/core/env/MutablePropertySources.remove:(Ljava/lang/String;)Lorg/springframework/core/env/PropertySource;
     104: pop
     105: goto          59
     108: return

  static {};
    Code:
       0: new           #135                // class java/util/HashSet
       3: dup
       4: invokespecial #137                // Method java/util/HashSet."<init>":()V
       7: astore_0
       8: aload_0
       9: ldc           #150                // String servletContextInitParams
      11: invokeinterface #138,  2          // InterfaceMethod java/util/Set.add:(Ljava/lang/Object;)Z
      16: pop
      17: aload_0
      18: ldc           #152                // String servletConfigInitParams
      20: invokeinterface #138,  2          // InterfaceMethod java/util/Set.add:(Ljava/lang/Object;)Z
      25: pop
      26: aload_0
      27: ldc           #154                // String jndiProperties
      29: invokeinterface #138,  2          // InterfaceMethod java/util/Set.add:(Ljava/lang/Object;)Z
      34: pop
      35: aload_0
      36: invokestatic  #156                // Method java/util/Collections.unmodifiableSet:(Ljava/util/Set;)Ljava/util/Set;
      39: putstatic     #104                // Field SERVLET_ENVIRONMENT_SOURCE_NAMES:Ljava/util/Set;
      42: return
}
