Compiled from "ExitCodeGenerators.java"
class org.springframework.boot.ExitCodeGenerators implements java.lang.Iterable<org.springframework.boot.ExitCodeGenerator> {
  private final java.util.List<org.springframework.boot.ExitCodeGenerator> generators;

  org.springframework.boot.ExitCodeGenerators();
    Code:
       0: aload_0
       1: invokespecial #1                  // Method java/lang/Object."<init>":()V
       4: aload_0
       5: new           #7                  // class java/util/ArrayList
       8: dup
       9: invokespecial #9                  // Method java/util/ArrayList."<init>":()V
      12: putfield      #10                 // Field generators:Ljava/util/List;
      15: return

  void addAll(java.lang.Throwable, org.springframework.boot.ExitCodeExceptionMapper...);
    Code:
       0: aload_1
       1: ldc           #16                 // String Exception must not be null
       3: invokestatic  #18                 // Method org/springframework/util/Assert.notNull:(Ljava/lang/Object;Ljava/lang/String;)V
       6: aload_2
       7: ldc           #24                 // String Mappers must not be null
       9: invokestatic  #18                 // Method org/springframework/util/Assert.notNull:(Ljava/lang/Object;Ljava/lang/String;)V
      12: aload_0
      13: aload_1
      14: aload_2
      15: invokestatic  #26                 // Method java/util/Arrays.asList:([Ljava/lang/Object;)Ljava/util/List;
      18: invokevirtual #32                 // Method addAll:(Ljava/lang/Throwable;Ljava/lang/Iterable;)V
      21: return

  void addAll(java.lang.Throwable, java.lang.Iterable<? extends org.springframework.boot.ExitCodeExceptionMapper>);
    Code:
       0: aload_1
       1: ldc           #16                 // String Exception must not be null
       3: invokestatic  #18                 // Method org/springframework/util/Assert.notNull:(Ljava/lang/Object;Ljava/lang/String;)V
       6: aload_2
       7: ldc           #24                 // String Mappers must not be null
       9: invokestatic  #18                 // Method org/springframework/util/Assert.notNull:(Ljava/lang/Object;Ljava/lang/String;)V
      12: aload_2
      13: invokeinterface #36,  1           // InterfaceMethod java/lang/Iterable.iterator:()Ljava/util/Iterator;
      18: astore_3
      19: aload_3
      20: invokeinterface #42,  1           // InterfaceMethod java/util/Iterator.hasNext:()Z
      25: ifeq          49
      28: aload_3
      29: invokeinterface #48,  1           // InterfaceMethod java/util/Iterator.next:()Ljava/lang/Object;
      34: checkcast     #52                 // class org/springframework/boot/ExitCodeExceptionMapper
      37: astore        4
      39: aload_0
      40: aload_1
      41: aload         4
      43: invokevirtual #54                 // Method add:(Ljava/lang/Throwable;Lorg/springframework/boot/ExitCodeExceptionMapper;)V
      46: goto          19
      49: return

  void add(java.lang.Throwable, org.springframework.boot.ExitCodeExceptionMapper);
    Code:
       0: aload_1
       1: ldc           #16                 // String Exception must not be null
       3: invokestatic  #18                 // Method org/springframework/util/Assert.notNull:(Ljava/lang/Object;Ljava/lang/String;)V
       6: aload_2
       7: ldc           #58                 // String Mapper must not be null
       9: invokestatic  #18                 // Method org/springframework/util/Assert.notNull:(Ljava/lang/Object;Ljava/lang/String;)V
      12: aload_0
      13: new           #60                 // class org/springframework/boot/ExitCodeGenerators$MappedExitCodeGenerator
      16: dup
      17: aload_1
      18: aload_2
      19: invokespecial #62                 // Method org/springframework/boot/ExitCodeGenerators$MappedExitCodeGenerator."<init>":(Ljava/lang/Throwable;Lorg/springframework/boot/ExitCodeExceptionMapper;)V
      22: invokevirtual #64                 // Method add:(Lorg/springframework/boot/ExitCodeGenerator;)V
      25: return

  void addAll(org.springframework.boot.ExitCodeGenerator...);
    Code:
       0: aload_1
       1: ldc           #67                 // String Generators must not be null
       3: invokestatic  #18                 // Method org/springframework/util/Assert.notNull:(Ljava/lang/Object;Ljava/lang/String;)V
       6: aload_0
       7: aload_1
       8: invokestatic  #26                 // Method java/util/Arrays.asList:([Ljava/lang/Object;)Ljava/util/List;
      11: invokevirtual #69                 // Method addAll:(Ljava/lang/Iterable;)V
      14: return

  void addAll(java.lang.Iterable<? extends org.springframework.boot.ExitCodeGenerator>);
    Code:
       0: aload_1
       1: ldc           #67                 // String Generators must not be null
       3: invokestatic  #18                 // Method org/springframework/util/Assert.notNull:(Ljava/lang/Object;Ljava/lang/String;)V
       6: aload_1
       7: invokeinterface #36,  1           // InterfaceMethod java/lang/Iterable.iterator:()Ljava/util/Iterator;
      12: astore_2
      13: aload_2
      14: invokeinterface #42,  1           // InterfaceMethod java/util/Iterator.hasNext:()Z
      19: ifeq          40
      22: aload_2
      23: invokeinterface #48,  1           // InterfaceMethod java/util/Iterator.next:()Ljava/lang/Object;
      28: checkcast     #72                 // class org/springframework/boot/ExitCodeGenerator
      31: astore_3
      32: aload_0
      33: aload_3
      34: invokevirtual #64                 // Method add:(Lorg/springframework/boot/ExitCodeGenerator;)V
      37: goto          13
      40: return

  void add(org.springframework.boot.ExitCodeGenerator);
    Code:
       0: aload_1
       1: ldc           #74                 // String Generator must not be null
       3: invokestatic  #18                 // Method org/springframework/util/Assert.notNull:(Ljava/lang/Object;Ljava/lang/String;)V
       6: aload_0
       7: getfield      #10                 // Field generators:Ljava/util/List;
      10: aload_1
      11: invokeinterface #76,  2           // InterfaceMethod java/util/List.add:(Ljava/lang/Object;)Z
      16: pop
      17: aload_0
      18: getfield      #10                 // Field generators:Ljava/util/List;
      21: invokestatic  #81                 // Method org/springframework/core/annotation/AnnotationAwareOrderComparator.sort:(Ljava/util/List;)V
      24: return

  public java.util.Iterator<org.springframework.boot.ExitCodeGenerator> iterator();
    Code:
       0: aload_0
       1: getfield      #10                 // Field generators:Ljava/util/List;
       4: invokeinterface #87,  1           // InterfaceMethod java/util/List.iterator:()Ljava/util/Iterator;
       9: areturn

  int getExitCode();
    Code:
       0: iconst_0
       1: istore_1
       2: aload_0
       3: getfield      #10                 // Field generators:Ljava/util/List;
       6: invokeinterface #87,  1           // InterfaceMethod java/util/List.iterator:()Ljava/util/Iterator;
      11: astore_2
      12: aload_2
      13: invokeinterface #42,  1           // InterfaceMethod java/util/Iterator.hasNext:()Z
      18: ifeq          65
      21: aload_2
      22: invokeinterface #48,  1           // InterfaceMethod java/util/Iterator.next:()Ljava/lang/Object;
      27: checkcast     #72                 // class org/springframework/boot/ExitCodeGenerator
      30: astore_3
      31: aload_3
      32: invokeinterface #88,  1           // InterfaceMethod org/springframework/boot/ExitCodeGenerator.getExitCode:()I
      37: istore        4
      39: iload         4
      41: ifeq          50
      44: iload         4
      46: istore_1
      47: goto          65
      50: goto          62
      53: astore        4
      55: iconst_1
      56: istore_1
      57: aload         4
      59: invokevirtual #94                 // Method java/lang/Exception.printStackTrace:()V
      62: goto          12
      65: iload_1
      66: ireturn
    Exception table:
       from    to  target type
          31    47    53   Class java/lang/Exception
}
