Compiled from "LazyInitializationBeanFactoryPostProcessor.java"
public final class org.springframework.boot.LazyInitializationBeanFactoryPostProcessor implements org.springframework.beans.factory.config.BeanFactoryPostProcessor,org.springframework.core.Ordered {
  public org.springframework.boot.LazyInitializationBeanFactoryPostProcessor();
    Code:
       0: aload_0
       1: invokespecial #1                  // Method java/lang/Object."<init>":()V
       4: return

  public void postProcessBeanFactory(org.springframework.beans.factory.config.ConfigurableListableBeanFactory) throws org.springframework.beans.BeansException;
    Code:
       0: aload_0
       1: aload_1
       2: invokevirtual #7                  // Method getFilters:(Lorg/springframework/beans/factory/config/ConfigurableListableBeanFactory;)Ljava/util/Collection;
       5: astore_2
       6: aload_1
       7: invokeinterface #13,  1           // InterfaceMethod org/springframework/beans/factory/config/ConfigurableListableBeanFactory.getBeanDefinitionNames:()[Ljava/lang/String;
      12: astore_3
      13: aload_3
      14: arraylength
      15: istore        4
      17: iconst_0
      18: istore        5
      20: iload         5
      22: iload         4
      24: if_icmpge     74
      27: aload_3
      28: iload         5
      30: aaload
      31: astore        6
      33: aload_1
      34: aload         6
      36: invokeinterface #19,  2           // InterfaceMethod org/springframework/beans/factory/config/ConfigurableListableBeanFactory.getBeanDefinition:(Ljava/lang/String;)Lorg/springframework/beans/factory/config/BeanDefinition;
      41: astore        7
      43: aload         7
      45: instanceof    #23                 // class org/springframework/beans/factory/support/AbstractBeanDefinition
      48: ifeq          68
      51: aload         7
      53: checkcast     #23                 // class org/springframework/beans/factory/support/AbstractBeanDefinition
      56: astore        8
      58: aload_0
      59: aload_1
      60: aload_2
      61: aload         6
      63: aload         8
      65: invokevirtual #25                 // Method postProcess:(Lorg/springframework/beans/factory/config/ConfigurableListableBeanFactory;Ljava/util/Collection;Ljava/lang/String;Lorg/springframework/beans/factory/support/AbstractBeanDefinition;)V
      68: iinc          5, 1
      71: goto          20
      74: return

  private java.util.Collection<org.springframework.boot.LazyInitializationExcludeFilter> getFilters(org.springframework.beans.factory.config.ConfigurableListableBeanFactory);
    Code:
       0: new           #29                 // class java/util/ArrayList
       3: dup
       4: aload_1
       5: ldc           #31                 // class org/springframework/boot/LazyInitializationExcludeFilter
       7: iconst_0
       8: iconst_0
       9: invokeinterface #33,  4           // InterfaceMethod org/springframework/beans/factory/config/ConfigurableListableBeanFactory.getBeansOfType:(Ljava/lang/Class;ZZ)Ljava/util/Map;
      14: invokeinterface #37,  1           // InterfaceMethod java/util/Map.values:()Ljava/util/Collection;
      19: invokespecial #43                 // Method java/util/ArrayList."<init>":(Ljava/util/Collection;)V
      22: astore_2
      23: aload_2
      24: iconst_1
      25: anewarray     #46                 // class java/lang/Class
      28: dup
      29: iconst_0
      30: ldc           #48                 // class org/springframework/beans/factory/SmartInitializingSingleton
      32: aastore
      33: invokestatic  #50                 // InterfaceMethod org/springframework/boot/LazyInitializationExcludeFilter.forBeanTypes:([Ljava/lang/Class;)Lorg/springframework/boot/LazyInitializationExcludeFilter;
      36: invokevirtual #54                 // Method java/util/ArrayList.add:(Ljava/lang/Object;)Z
      39: pop
      40: aload_2
      41: areturn

  private void postProcess(org.springframework.beans.factory.config.ConfigurableListableBeanFactory, java.util.Collection<org.springframework.boot.LazyInitializationExcludeFilter>, java.lang.String, org.springframework.beans.factory.support.AbstractBeanDefinition);
    Code:
       0: aload         4
       2: invokevirtual #58                 // Method org/springframework/beans/factory/support/AbstractBeanDefinition.getLazyInit:()Ljava/lang/Boolean;
       5: astore        5
       7: aload         5
       9: ifnull        13
      12: return
      13: aload_0
      14: aload_1
      15: aload_3
      16: invokevirtual #62                 // Method getBeanType:(Lorg/springframework/beans/factory/config/ConfigurableListableBeanFactory;Ljava/lang/String;)Ljava/lang/Class;
      19: astore        6
      21: aload_0
      22: aload_2
      23: aload_3
      24: aload         4
      26: aload         6
      28: invokevirtual #66                 // Method isExcluded:(Ljava/util/Collection;Ljava/lang/String;Lorg/springframework/beans/factory/support/AbstractBeanDefinition;Ljava/lang/Class;)Z
      31: ifne          40
      34: aload         4
      36: iconst_1
      37: invokevirtual #70                 // Method org/springframework/beans/factory/support/AbstractBeanDefinition.setLazyInit:(Z)V
      40: return

  private java.lang.Class<?> getBeanType(org.springframework.beans.factory.config.ConfigurableListableBeanFactory, java.lang.String);
    Code:
       0: aload_1
       1: aload_2
       2: iconst_0
       3: invokeinterface #74,  3           // InterfaceMethod org/springframework/beans/factory/config/ConfigurableListableBeanFactory.getType:(Ljava/lang/String;Z)Ljava/lang/Class;
       8: areturn
       9: astore_3
      10: aconst_null
      11: areturn
    Exception table:
       from    to  target type
           0     8     9   Class org/springframework/beans/factory/NoSuchBeanDefinitionException

  private boolean isExcluded(java.util.Collection<org.springframework.boot.LazyInitializationExcludeFilter>, java.lang.String, org.springframework.beans.factory.support.AbstractBeanDefinition, java.lang.Class<?>);
    Code:
       0: aload         4
       2: ifnull        54
       5: aload_1
       6: invokeinterface #80,  1           // InterfaceMethod java/util/Collection.iterator:()Ljava/util/Iterator;
      11: astore        5
      13: aload         5
      15: invokeinterface #86,  1           // InterfaceMethod java/util/Iterator.hasNext:()Z
      20: ifeq          54
      23: aload         5
      25: invokeinterface #92,  1           // InterfaceMethod java/util/Iterator.next:()Ljava/lang/Object;
      30: checkcast     #31                 // class org/springframework/boot/LazyInitializationExcludeFilter
      33: astore        6
      35: aload         6
      37: aload_2
      38: aload_3
      39: aload         4
      41: invokeinterface #96,  4           // InterfaceMethod org/springframework/boot/LazyInitializationExcludeFilter.isExcluded:(Ljava/lang/String;Lorg/springframework/beans/factory/config/BeanDefinition;Ljava/lang/Class;)Z
      46: ifeq          51
      49: iconst_1
      50: ireturn
      51: goto          13
      54: iconst_0
      55: ireturn

  public int getOrder();
    Code:
       0: ldc           #101                // int -2147483648
       2: ireturn
}
