Compiled from "SpringApplicationShutdownHook.java"
class org.springframework.boot.SpringApplicationShutdownHook implements java.lang.Runnable {
  private static final int SLEEP;

  private static final long TIMEOUT;

  private static final org.apache.commons.logging.Log logger;

  private final org.springframework.boot.SpringApplicationShutdownHook$Handlers handlers;

  private final java.util.Set<org.springframework.context.ConfigurableApplicationContext> contexts;

  private final java.util.Set<org.springframework.context.ConfigurableApplicationContext> closedContexts;

  private final org.springframework.boot.SpringApplicationShutdownHook$ApplicationContextClosedListener contextCloseListener;

  private final java.util.concurrent.atomic.AtomicBoolean shutdownHookAdded;

  private boolean inProgress;

  org.springframework.boot.SpringApplicationShutdownHook();
    Code:
       0: aload_0
       1: invokespecial #1                  // Method java/lang/Object."<init>":()V
       4: aload_0
       5: new           #7                  // class org/springframework/boot/SpringApplicationShutdownHook$Handlers
       8: dup
       9: aload_0
      10: invokespecial #9                  // Method org/springframework/boot/SpringApplicationShutdownHook$Handlers."<init>":(Lorg/springframework/boot/SpringApplicationShutdownHook;)V
      13: putfield      #12                 // Field handlers:Lorg/springframework/boot/SpringApplicationShutdownHook$Handlers;
      16: aload_0
      17: new           #18                 // class java/util/LinkedHashSet
      20: dup
      21: invokespecial #20                 // Method java/util/LinkedHashSet."<init>":()V
      24: putfield      #21                 // Field contexts:Ljava/util/Set;
      27: aload_0
      28: new           #25                 // class java/util/WeakHashMap
      31: dup
      32: invokespecial #27                 // Method java/util/WeakHashMap."<init>":()V
      35: invokestatic  #28                 // Method java/util/Collections.newSetFromMap:(Ljava/util/Map;)Ljava/util/Set;
      38: putfield      #34                 // Field closedContexts:Ljava/util/Set;
      41: aload_0
      42: new           #37                 // class org/springframework/boot/SpringApplicationShutdownHook$ApplicationContextClosedListener
      45: dup
      46: aload_0
      47: invokespecial #39                 // Method org/springframework/boot/SpringApplicationShutdownHook$ApplicationContextClosedListener."<init>":(Lorg/springframework/boot/SpringApplicationShutdownHook;)V
      50: putfield      #40                 // Field contextCloseListener:Lorg/springframework/boot/SpringApplicationShutdownHook$ApplicationContextClosedListener;
      53: aload_0
      54: new           #44                 // class java/util/concurrent/atomic/AtomicBoolean
      57: dup
      58: invokespecial #46                 // Method java/util/concurrent/atomic/AtomicBoolean."<init>":()V
      61: putfield      #47                 // Field shutdownHookAdded:Ljava/util/concurrent/atomic/AtomicBoolean;
      64: return

  org.springframework.boot.SpringApplicationShutdownHandlers getHandlers();
    Code:
       0: aload_0
       1: getfield      #12                 // Field handlers:Lorg/springframework/boot/SpringApplicationShutdownHook$Handlers;
       4: areturn

  void registerApplicationContext(org.springframework.context.ConfigurableApplicationContext);
    Code:
       0: aload_0
       1: invokevirtual #51                 // Method addRuntimeShutdownHookIfNecessary:()V
       4: ldc           #13                 // class org/springframework/boot/SpringApplicationShutdownHook
       6: dup
       7: astore_2
       8: monitorenter
       9: aload_0
      10: invokevirtual #54                 // Method assertNotInProgress:()V
      13: aload_1
      14: aload_0
      15: getfield      #40                 // Field contextCloseListener:Lorg/springframework/boot/SpringApplicationShutdownHook$ApplicationContextClosedListener;
      18: invokeinterface #57,  2           // InterfaceMethod org/springframework/context/ConfigurableApplicationContext.addApplicationListener:(Lorg/springframework/context/ApplicationListener;)V
      23: aload_0
      24: getfield      #21                 // Field contexts:Ljava/util/Set;
      27: aload_1
      28: invokeinterface #63,  2           // InterfaceMethod java/util/Set.add:(Ljava/lang/Object;)Z
      33: pop
      34: aload_2
      35: monitorexit
      36: goto          44
      39: astore_3
      40: aload_2
      41: monitorexit
      42: aload_3
      43: athrow
      44: return
    Exception table:
       from    to  target type
           9    36    39   any
          39    42    39   any

  private void addRuntimeShutdownHookIfNecessary();
    Code:
       0: aload_0
       1: getfield      #47                 // Field shutdownHookAdded:Ljava/util/concurrent/atomic/AtomicBoolean;
       4: iconst_0
       5: iconst_1
       6: invokevirtual #69                 // Method java/util/concurrent/atomic/AtomicBoolean.compareAndSet:(ZZ)Z
       9: ifeq          16
      12: aload_0
      13: invokevirtual #73                 // Method addRuntimeShutdownHook:()V
      16: return

  void addRuntimeShutdownHook();
    Code:
       0: invokestatic  #76                 // Method java/lang/Runtime.getRuntime:()Ljava/lang/Runtime;
       3: new           #82                 // class java/lang/Thread
       6: dup
       7: aload_0
       8: ldc           #84                 // String SpringApplicationShutdownHook
      10: invokespecial #86                 // Method java/lang/Thread."<init>":(Ljava/lang/Runnable;Ljava/lang/String;)V
      13: invokevirtual #89                 // Method java/lang/Runtime.addShutdownHook:(Ljava/lang/Thread;)V
      16: return

  void deregisterFailedApplicationContext(org.springframework.context.ConfigurableApplicationContext);
    Code:
       0: ldc           #13                 // class org/springframework/boot/SpringApplicationShutdownHook
       2: dup
       3: astore_2
       4: monitorenter
       5: aload_1
       6: invokeinterface #93,  1           // InterfaceMethod org/springframework/context/ConfigurableApplicationContext.isActive:()Z
      11: ifne          18
      14: iconst_1
      15: goto          19
      18: iconst_0
      19: ldc           #97                 // String Cannot unregister active application context
      21: invokestatic  #99                 // Method org/springframework/util/Assert.state:(ZLjava/lang/String;)V
      24: aload_0
      25: getfield      #21                 // Field contexts:Ljava/util/Set;
      28: aload_1
      29: invokeinterface #105,  2          // InterfaceMethod java/util/Set.remove:(Ljava/lang/Object;)Z
      34: pop
      35: aload_2
      36: monitorexit
      37: goto          45
      40: astore_3
      41: aload_2
      42: monitorexit
      43: aload_3
      44: athrow
      45: return
    Exception table:
       from    to  target type
           5    37    40   any
          40    43    40   any

  public void run();
    Code:
       0: ldc           #13                 // class org/springframework/boot/SpringApplicationShutdownHook
       2: dup
       3: astore        4
       5: monitorenter
       6: aload_0
       7: iconst_1
       8: putfield      #108                // Field inProgress:Z
      11: new           #18                 // class java/util/LinkedHashSet
      14: dup
      15: aload_0
      16: getfield      #21                 // Field contexts:Ljava/util/Set;
      19: invokespecial #112                // Method java/util/LinkedHashSet."<init>":(Ljava/util/Collection;)V
      22: astore_1
      23: new           #18                 // class java/util/LinkedHashSet
      26: dup
      27: aload_0
      28: getfield      #34                 // Field closedContexts:Ljava/util/Set;
      31: invokespecial #112                // Method java/util/LinkedHashSet."<init>":(Ljava/util/Collection;)V
      34: astore_2
      35: new           #18                 // class java/util/LinkedHashSet
      38: dup
      39: aload_0
      40: getfield      #12                 // Field handlers:Lorg/springframework/boot/SpringApplicationShutdownHook$Handlers;
      43: invokevirtual #115                // Method org/springframework/boot/SpringApplicationShutdownHook$Handlers.getActions:()Ljava/util/Set;
      46: invokespecial #112                // Method java/util/LinkedHashSet."<init>":(Ljava/util/Collection;)V
      49: astore_3
      50: aload         4
      52: monitorexit
      53: goto          64
      56: astore        5
      58: aload         4
      60: monitorexit
      61: aload         5
      63: athrow
      64: aload_1
      65: aload_0
      66: invokedynamic #119,  0            // InvokeDynamic #0:accept:(Lorg/springframework/boot/SpringApplicationShutdownHook;)Ljava/util/function/Consumer;
      71: invokeinterface #123,  2          // InterfaceMethod java/util/Set.forEach:(Ljava/util/function/Consumer;)V
      76: aload_2
      77: aload_0
      78: invokedynamic #119,  0            // InvokeDynamic #0:accept:(Lorg/springframework/boot/SpringApplicationShutdownHook;)Ljava/util/function/Consumer;
      83: invokeinterface #123,  2          // InterfaceMethod java/util/Set.forEach:(Ljava/util/function/Consumer;)V
      88: aload_3
      89: invokedynamic #127,  0            // InvokeDynamic #1:accept:()Ljava/util/function/Consumer;
      94: invokeinterface #123,  2          // InterfaceMethod java/util/Set.forEach:(Ljava/util/function/Consumer;)V
      99: return
    Exception table:
       from    to  target type
           6    53    56   any
          56    61    56   any

  boolean isApplicationContextRegistered(org.springframework.context.ConfigurableApplicationContext);
    Code:
       0: ldc           #13                 // class org/springframework/boot/SpringApplicationShutdownHook
       2: dup
       3: astore_2
       4: monitorenter
       5: aload_0
       6: getfield      #21                 // Field contexts:Ljava/util/Set;
       9: aload_1
      10: invokeinterface #130,  2          // InterfaceMethod java/util/Set.contains:(Ljava/lang/Object;)Z
      15: aload_2
      16: monitorexit
      17: ireturn
      18: astore_3
      19: aload_2
      20: monitorexit
      21: aload_3
      22: athrow
    Exception table:
       from    to  target type
           5    17    18   any
          18    21    18   any

  void reset();
    Code:
       0: ldc           #13                 // class org/springframework/boot/SpringApplicationShutdownHook
       2: dup
       3: astore_1
       4: monitorenter
       5: aload_0
       6: getfield      #21                 // Field contexts:Ljava/util/Set;
       9: invokeinterface #133,  1          // InterfaceMethod java/util/Set.clear:()V
      14: aload_0
      15: getfield      #34                 // Field closedContexts:Ljava/util/Set;
      18: invokeinterface #133,  1          // InterfaceMethod java/util/Set.clear:()V
      23: aload_0
      24: getfield      #12                 // Field handlers:Lorg/springframework/boot/SpringApplicationShutdownHook$Handlers;
      27: invokevirtual #115                // Method org/springframework/boot/SpringApplicationShutdownHook$Handlers.getActions:()Ljava/util/Set;
      30: invokeinterface #133,  1          // InterfaceMethod java/util/Set.clear:()V
      35: aload_0
      36: iconst_0
      37: putfield      #108                // Field inProgress:Z
      40: aload_1
      41: monitorexit
      42: goto          50
      45: astore_2
      46: aload_1
      47: monitorexit
      48: aload_2
      49: athrow
      50: return
    Exception table:
       from    to  target type
           5    42    45   any
          45    48    45   any

  private void closeAndWait(org.springframework.context.ConfigurableApplicationContext);
    Code:
       0: aload_1
       1: invokeinterface #93,  1           // InterfaceMethod org/springframework/context/ConfigurableApplicationContext.isActive:()Z
       6: ifne          10
       9: return
      10: aload_1
      11: invokeinterface #136,  1          // InterfaceMethod org/springframework/context/ConfigurableApplicationContext.close:()V
      16: iconst_0
      17: istore_2
      18: aload_1
      19: invokeinterface #93,  1           // InterfaceMethod org/springframework/context/ConfigurableApplicationContext.isActive:()Z
      24: ifeq          56
      27: iload_2
      28: i2l
      29: getstatic     #139                // Field TIMEOUT:J
      32: lcmp
      33: ifle          44
      36: new           #143                // class java/util/concurrent/TimeoutException
      39: dup
      40: invokespecial #145                // Method java/util/concurrent/TimeoutException."<init>":()V
      43: athrow
      44: ldc2_w        #146                // long 50l
      47: invokestatic  #148                // Method java/lang/Thread.sleep:(J)V
      50: iinc          2, 50
      53: goto          18
      56: goto          99
      59: astore_2
      60: invokestatic  #154                // Method java/lang/Thread.currentThread:()Ljava/lang/Thread;
      63: invokevirtual #158                // Method java/lang/Thread.interrupt:()V
      66: getstatic     #161                // Field logger:Lorg/apache/commons/logging/Log;
      69: aload_1
      70: invokedynamic #165,  0            // InvokeDynamic #2:makeConcatWithConstants:(Lorg/springframework/context/ConfigurableApplicationContext;)Ljava/lang/String;
      75: invokeinterface #169,  2          // InterfaceMethod org/apache/commons/logging/Log.warn:(Ljava/lang/Object;)V
      80: goto          99
      83: astore_2
      84: getstatic     #161                // Field logger:Lorg/apache/commons/logging/Log;
      87: aload_1
      88: invokedynamic #175,  0            // InvokeDynamic #3:makeConcatWithConstants:(Lorg/springframework/context/ConfigurableApplicationContext;)Ljava/lang/String;
      93: aload_2
      94: invokeinterface #176,  3          // InterfaceMethod org/apache/commons/logging/Log.warn:(Ljava/lang/Object;Ljava/lang/Throwable;)V
      99: return
    Exception table:
       from    to  target type
          16    56    59   Class java/lang/InterruptedException
          16    56    83   Class java/util/concurrent/TimeoutException

  private void assertNotInProgress();
    Code:
       0: aload_0
       1: getfield      #108                // Field inProgress:Z
       4: ifne          11
       7: iconst_1
       8: goto          12
      11: iconst_0
      12: ldc           #179                // String Shutdown in progress
      14: invokestatic  #99                 // Method org/springframework/util/Assert.state:(ZLjava/lang/String;)V
      17: return

  static {};
    Code:
       0: getstatic     #181                // Field java/util/concurrent/TimeUnit.MINUTES:Ljava/util/concurrent/TimeUnit;
       3: ldc2_w        #187                // long 10l
       6: invokevirtual #189                // Method java/util/concurrent/TimeUnit.toMillis:(J)J
       9: putstatic     #139                // Field TIMEOUT:J
      12: ldc           #13                 // class org/springframework/boot/SpringApplicationShutdownHook
      14: invokestatic  #193                // Method org/apache/commons/logging/LogFactory.getLog:(Ljava/lang/Class;)Lorg/apache/commons/logging/Log;
      17: putstatic     #161                // Field logger:Lorg/apache/commons/logging/Log;
      20: return
}
