Compiled from "SpringApplicationShutdownHook.java"
class org.springframework.boot.SpringApplicationShutdownHook$Handlers implements org.springframework.boot.SpringApplicationShutdownHandlers,java.lang.Runnable {
  private final java.util.Set<java.lang.Runnable> actions;

  final org.springframework.boot.SpringApplicationShutdownHook this$0;

  private org.springframework.boot.SpringApplicationShutdownHook$Handlers(org.springframework.boot.SpringApplicationShutdownHook);
    Code:
       0: aload_0
       1: aload_1
       2: putfield      #1                  // Field this$0:Lorg/springframework/boot/SpringApplicationShutdownHook;
       5: aload_0
       6: invokespecial #7                  // Method java/lang/Object."<init>":()V
       9: aload_0
      10: new           #13                 // class java/util/IdentityHashMap
      13: dup
      14: invokespecial #15                 // Method java/util/IdentityHashMap."<init>":()V
      17: invokestatic  #16                 // Method java/util/Collections.newSetFromMap:(Ljava/util/Map;)Ljava/util/Set;
      20: putfield      #22                 // Field actions:Ljava/util/Set;
      23: return

  public void add(java.lang.Runnable);
    Code:
       0: aload_1
       1: ldc           #26                 // String Action must not be null
       3: invokestatic  #28                 // Method org/springframework/util/Assert.notNull:(Ljava/lang/Object;Ljava/lang/String;)V
       6: aload_0
       7: getfield      #1                  // Field this$0:Lorg/springframework/boot/SpringApplicationShutdownHook;
      10: invokevirtual #34                 // Method org/springframework/boot/SpringApplicationShutdownHook.addRuntimeShutdownHookIfNecessary:()V
      13: ldc           #35                 // class org/springframework/boot/SpringApplicationShutdownHook
      15: dup
      16: astore_2
      17: monitorenter
      18: aload_0
      19: getfield      #1                  // Field this$0:Lorg/springframework/boot/SpringApplicationShutdownHook;
      22: invokevirtual #39                 // Method org/springframework/boot/SpringApplicationShutdownHook.assertNotInProgress:()V
      25: aload_0
      26: getfield      #22                 // Field actions:Ljava/util/Set;
      29: aload_1
      30: invokeinterface #42,  2           // InterfaceMethod java/util/Set.add:(Ljava/lang/Object;)Z
      35: pop
      36: aload_2
      37: monitorexit
      38: goto          46
      41: astore_3
      42: aload_2
      43: monitorexit
      44: aload_3
      45: athrow
      46: return
    Exception table:
       from    to  target type
          18    38    41   any
          41    44    41   any

  public void remove(java.lang.Runnable);
    Code:
       0: aload_1
       1: ldc           #26                 // String Action must not be null
       3: invokestatic  #28                 // Method org/springframework/util/Assert.notNull:(Ljava/lang/Object;Ljava/lang/String;)V
       6: ldc           #35                 // class org/springframework/boot/SpringApplicationShutdownHook
       8: dup
       9: astore_2
      10: monitorenter
      11: aload_0
      12: getfield      #1                  // Field this$0:Lorg/springframework/boot/SpringApplicationShutdownHook;
      15: invokevirtual #39                 // Method org/springframework/boot/SpringApplicationShutdownHook.assertNotInProgress:()V
      18: aload_0
      19: getfield      #22                 // Field actions:Ljava/util/Set;
      22: aload_1
      23: invokeinterface #48,  2           // InterfaceMethod java/util/Set.remove:(Ljava/lang/Object;)Z
      28: pop
      29: aload_2
      30: monitorexit
      31: goto          39
      34: astore_3
      35: aload_2
      36: monitorexit
      37: aload_3
      38: athrow
      39: return
    Exception table:
       from    to  target type
          11    31    34   any
          34    37    34   any

  java.util.Set<java.lang.Runnable> getActions();
    Code:
       0: aload_0
       1: getfield      #22                 // Field actions:Ljava/util/Set;
       4: areturn

  public void run();
    Code:
       0: aload_0
       1: getfield      #1                  // Field this$0:Lorg/springframework/boot/SpringApplicationShutdownHook;
       4: invokevirtual #51                 // Method org/springframework/boot/SpringApplicationShutdownHook.run:()V
       7: aload_0
       8: getfield      #1                  // Field this$0:Lorg/springframework/boot/SpringApplicationShutdownHook;
      11: invokevirtual #54                 // Method org/springframework/boot/SpringApplicationShutdownHook.reset:()V
      14: return
}
