Compiled from "SpringApplication.java"
class org.springframework.boot.SpringApplication$SpringApplicationRuntimeHints extends org.springframework.boot.context.properties.bind.BindableRuntimeHintsRegistrar {
  org.springframework.boot.SpringApplication$SpringApplicationRuntimeHints();
    Code:
       0: aload_0
       1: iconst_1
       2: anewarray     #1                  // class java/lang/Class
       5: dup
       6: iconst_0
       7: ldc           #3                  // class org/springframework/boot/SpringApplication
       9: aastore
      10: invokespecial #5                  // Method org/springframework/boot/context/properties/bind/BindableRuntimeHintsRegistrar."<init>":([Ljava/lang/Class;)V
      13: return
}
