Compiled from "SpringApplicationBannerPrinter.java"
class org.springframework.boot.SpringApplicationBannerPrinter {
  static final java.lang.String BANNER_LOCATION_PROPERTY;

  static final java.lang.String DEFAULT_BANNER_LOCATION;

  private static final org.springframework.boot.Banner DEFAULT_BANNER;

  private final org.springframework.core.io.ResourceLoader resourceLoader;

  private final org.springframework.boot.Banner fallbackBanner;

  org.springframework.boot.SpringApplicationBannerPrinter(org.springframework.core.io.ResourceLoader, org.springframework.boot.Banner);
    Code:
       0: aload_0
       1: invokespecial #1                  // Method java/lang/Object."<init>":()V
       4: aload_0
       5: aload_1
       6: putfield      #7                  // Field resourceLoader:Lorg/springframework/core/io/ResourceLoader;
       9: aload_0
      10: aload_2
      11: putfield      #13                 // Field fallbackBanner:Lorg/springframework/boot/Banner;
      14: return

  org.springframework.boot.Banner print(org.springframework.core.env.Environment, java.lang.Class<?>, org.apache.commons.logging.Log);
    Code:
       0: aload_0
       1: aload_1
       2: invokevirtual #17                 // Method getBanner:(Lorg/springframework/core/env/Environment;)Lorg/springframework/boot/Banner;
       5: astore        4
       7: aload_3
       8: aload_0
       9: aload         4
      11: aload_1
      12: aload_2
      13: invokevirtual #21                 // Method createStringFromBanner:(Lorg/springframework/boot/Banner;Lorg/springframework/core/env/Environment;Ljava/lang/Class;)Ljava/lang/String;
      16: invokeinterface #25,  2           // InterfaceMethod org/apache/commons/logging/Log.info:(Ljava/lang/Object;)V
      21: goto          36
      24: astore        5
      26: aload_3
      27: ldc           #33                 // String Failed to create String for banner
      29: aload         5
      31: invokeinterface #35,  3           // InterfaceMethod org/apache/commons/logging/Log.warn:(Ljava/lang/Object;Ljava/lang/Throwable;)V
      36: new           #39                 // class org/springframework/boot/SpringApplicationBannerPrinter$PrintedBanner
      39: dup
      40: aload         4
      42: aload_2
      43: invokespecial #41                 // Method org/springframework/boot/SpringApplicationBannerPrinter$PrintedBanner."<init>":(Lorg/springframework/boot/Banner;Ljava/lang/Class;)V
      46: areturn
    Exception table:
       from    to  target type
           7    21    24   Class java/io/UnsupportedEncodingException

  org.springframework.boot.Banner print(org.springframework.core.env.Environment, java.lang.Class<?>, java.io.PrintStream);
    Code:
       0: aload_0
       1: aload_1
       2: invokevirtual #17                 // Method getBanner:(Lorg/springframework/core/env/Environment;)Lorg/springframework/boot/Banner;
       5: astore        4
       7: aload         4
       9: aload_1
      10: aload_2
      11: aload_3
      12: invokeinterface #44,  4           // InterfaceMethod org/springframework/boot/Banner.printBanner:(Lorg/springframework/core/env/Environment;Ljava/lang/Class;Ljava/io/PrintStream;)V
      17: new           #39                 // class org/springframework/boot/SpringApplicationBannerPrinter$PrintedBanner
      20: dup
      21: aload         4
      23: aload_2
      24: invokespecial #41                 // Method org/springframework/boot/SpringApplicationBannerPrinter$PrintedBanner."<init>":(Lorg/springframework/boot/Banner;Ljava/lang/Class;)V
      27: areturn

  private org.springframework.boot.Banner getBanner(org.springframework.core.env.Environment);
    Code:
       0: aload_0
       1: aload_1
       2: invokevirtual #50                 // Method getTextBanner:(Lorg/springframework/core/env/Environment;)Lorg/springframework/boot/Banner;
       5: astore_2
       6: aload_2
       7: ifnull        12
      10: aload_2
      11: areturn
      12: aload_0
      13: getfield      #13                 // Field fallbackBanner:Lorg/springframework/boot/Banner;
      16: ifnull        24
      19: aload_0
      20: getfield      #13                 // Field fallbackBanner:Lorg/springframework/boot/Banner;
      23: areturn
      24: getstatic     #53                 // Field DEFAULT_BANNER:Lorg/springframework/boot/Banner;
      27: areturn

  private org.springframework.boot.Banner getTextBanner(org.springframework.core.env.Environment);
    Code:
       0: aload_1
       1: ldc           #56                 // String spring.banner.location
       3: ldc           #58                 // String banner.txt
       5: invokeinterface #60,  3           // InterfaceMethod org/springframework/core/env/Environment.getProperty:(Ljava/lang/String;Ljava/lang/String;)Ljava/lang/String;
      10: astore_2
      11: aload_0
      12: getfield      #7                  // Field resourceLoader:Lorg/springframework/core/io/ResourceLoader;
      15: aload_2
      16: invokeinterface #66,  2           // InterfaceMethod org/springframework/core/io/ResourceLoader.getResource:(Ljava/lang/String;)Lorg/springframework/core/io/Resource;
      21: astore_3
      22: aload_3
      23: invokeinterface #72,  1           // InterfaceMethod org/springframework/core/io/Resource.exists:()Z
      28: ifeq          57
      31: aload_3
      32: invokeinterface #78,  1           // InterfaceMethod org/springframework/core/io/Resource.getURL:()Ljava/net/URL;
      37: invokevirtual #82                 // Method java/net/URL.toExternalForm:()Ljava/lang/String;
      40: ldc           #88                 // String liquibase-core
      42: invokevirtual #90                 // Method java/lang/String.contains:(Ljava/lang/CharSequence;)Z
      45: ifne          57
      48: new           #96                 // class org/springframework/boot/ResourceBanner
      51: dup
      52: aload_3
      53: invokespecial #98                 // Method org/springframework/boot/ResourceBanner."<init>":(Lorg/springframework/core/io/Resource;)V
      56: areturn
      57: goto          62
      60: astore        4
      62: aconst_null
      63: areturn
    Exception table:
       from    to  target type
          22    56    60   Class java/io/IOException

  private java.lang.String createStringFromBanner(org.springframework.boot.Banner, org.springframework.core.env.Environment, java.lang.Class<?>) throws java.io.UnsupportedEncodingException;
    Code:
       0: new           #103                // class java/io/ByteArrayOutputStream
       3: dup
       4: invokespecial #105                // Method java/io/ByteArrayOutputStream."<init>":()V
       7: astore        4
       9: aload_1
      10: aload_2
      11: aload_3
      12: new           #106                // class java/io/PrintStream
      15: dup
      16: aload         4
      18: invokespecial #108                // Method java/io/PrintStream."<init>":(Ljava/io/OutputStream;)V
      21: invokeinterface #44,  4           // InterfaceMethod org/springframework/boot/Banner.printBanner:(Lorg/springframework/core/env/Environment;Ljava/lang/Class;Ljava/io/PrintStream;)V
      26: aload_2
      27: ldc           #111                // String spring.banner.charset
      29: ldc           #113                // String UTF-8
      31: invokeinterface #60,  3           // InterfaceMethod org/springframework/core/env/Environment.getProperty:(Ljava/lang/String;Ljava/lang/String;)Ljava/lang/String;
      36: astore        5
      38: aload         4
      40: aload         5
      42: invokevirtual #115                // Method java/io/ByteArrayOutputStream.toString:(Ljava/lang/String;)Ljava/lang/String;
      45: areturn

  static {};
    Code:
       0: new           #119                // class org/springframework/boot/SpringBootBanner
       3: dup
       4: invokespecial #121                // Method org/springframework/boot/SpringBootBanner."<init>":()V
       7: putstatic     #53                 // Field DEFAULT_BANNER:Lorg/springframework/boot/Banner;
      10: return
}
