Compiled from "SpringApplication.java"
class org.springframework.boot.SpringApplication$PropertySourceOrderingBeanFactoryPostProcessor implements org.springframework.beans.factory.config.BeanFactoryPostProcessor,org.springframework.core.Ordered {
  private final org.springframework.context.ConfigurableApplicationContext context;

  org.springframework.boot.SpringApplication$PropertySourceOrderingBeanFactoryPostProcessor(org.springframework.context.ConfigurableApplicationContext);
    Code:
       0: aload_0
       1: invokespecial #1                  // Method java/lang/Object."<init>":()V
       4: aload_0
       5: aload_1
       6: putfield      #7                  // Field context:Lorg/springframework/context/ConfigurableApplicationContext;
       9: return

  public int getOrder();
    Code:
       0: ldc           #15                 // int -2147483648
       2: ireturn

  public void postProcessBeanFactory(org.springframework.beans.factory.config.ConfigurableListableBeanFactory) throws org.springframework.beans.BeansException;
    Code:
       0: aload_0
       1: getfield      #7                  // Field context:Lorg/springframework/context/ConfigurableApplicationContext;
       4: invokeinterface #16,  1           // InterfaceMethod org/springframework/context/ConfigurableApplicationContext.getEnvironment:()Lorg/springframework/core/env/ConfigurableEnvironment;
       9: invokestatic  #22                 // Method org/springframework/boot/DefaultPropertiesPropertySource.moveToEnd:(Lorg/springframework/core/env/ConfigurableEnvironment;)V
      12: return
}
