Compiled from "SpringApplication.java"
public class org.springframework.boot.SpringApplication$Augmented {
  private final org.springframework.util.function.ThrowingConsumer<java.lang.String[]> main;

  private final java.util.Set<java.lang.Class<?>> sources;

  org.springframework.boot.SpringApplication$Augmented(org.springframework.util.function.ThrowingConsumer<java.lang.String[]>, java.util.Set<java.lang.Class<?>>);
    Code:
       0: aload_0
       1: invokespecial #1                  // Method java/lang/Object."<init>":()V
       4: aload_0
       5: aload_1
       6: putfield      #7                  // Field main:Lorg/springframework/util/function/ThrowingConsumer;
       9: aload_0
      10: aload_2
      11: invokestatic  #13                 // InterfaceMethod java/util/Set.copyOf:(Ljava/util/Collection;)Ljava/util/Set;
      14: putfield      #19                 // Field sources:Ljava/util/Set;
      17: return

  public org.springframework.boot.SpringApplication$Augmented with(java.lang.Class<?>...);
    Code:
       0: new           #23                 // class java/util/LinkedHashSet
       3: dup
       4: aload_0
       5: getfield      #19                 // Field sources:Ljava/util/Set;
       8: invokespecial #25                 // Method java/util/LinkedHashSet."<init>":(Ljava/util/Collection;)V
      11: astore_2
      12: aload_2
      13: aload_1
      14: invokestatic  #28                 // Method java/util/Arrays.asList:([Ljava/lang/Object;)Ljava/util/List;
      17: invokevirtual #34                 // Method java/util/LinkedHashSet.addAll:(Ljava/util/Collection;)Z
      20: pop
      21: new           #8                  // class org/springframework/boot/SpringApplication$Augmented
      24: dup
      25: aload_0
      26: getfield      #7                  // Field main:Lorg/springframework/util/function/ThrowingConsumer;
      29: aload_2
      30: invokespecial #38                 // Method "<init>":(Lorg/springframework/util/function/ThrowingConsumer;Ljava/util/Set;)V
      33: areturn

  public org.springframework.boot.SpringApplication$Running run(java.lang.String...);
    Code:
       0: new           #41                 // class org/springframework/boot/SpringApplication$Augmented$RunListener
       3: dup
       4: invokespecial #43                 // Method org/springframework/boot/SpringApplication$Augmented$RunListener."<init>":()V
       7: astore_2
       8: aload_0
       9: aload_2
      10: invokedynamic #44,  0             // InvokeDynamic #0:getRunListener:(Lorg/springframework/boot/SpringApplication$Augmented;Lorg/springframework/boot/SpringApplication$Augmented$RunListener;)Lorg/springframework/boot/SpringApplicationHook;
      15: astore_3
      16: aload_3
      17: aload_0
      18: aload_1
      19: invokedynamic #48,  0             // InvokeDynamic #1:run:(Lorg/springframework/boot/SpringApplication$Augmented;[Ljava/lang/String;)Ljava/lang/Runnable;
      24: invokestatic  #52                 // Method org/springframework/boot/SpringApplication.withHook:(Lorg/springframework/boot/SpringApplicationHook;Ljava/lang/Runnable;)V
      27: aload_2
      28: areturn

  private void lambda$run$1(java.lang.String[]);
    Code:
       0: aload_0
       1: getfield      #7                  // Field main:Lorg/springframework/util/function/ThrowingConsumer;
       4: aload_1
       5: invokeinterface #58,  2           // InterfaceMethod org/springframework/util/function/ThrowingConsumer.accept:(Ljava/lang/Object;)V
      10: return

  private org.springframework.boot.SpringApplicationRunListener lambda$run$0(org.springframework.boot.SpringApplication$Augmented$RunListener, org.springframework.boot.SpringApplication);
    Code:
       0: aload_2
       1: aload_0
       2: getfield      #19                 // Field sources:Ljava/util/Set;
       5: invokevirtual #64                 // Method org/springframework/boot/SpringApplication.addPrimarySources:(Ljava/util/Collection;)V
       8: aload_1
       9: areturn
}
