Compiled from "SpringApplication.java"
class org.springframework.boot.SpringApplication$Augmented$RunListener implements org.springframework.boot.SpringApplicationRunListener,org.springframework.boot.SpringApplication$Running {
  private final java.util.List<org.springframework.context.ConfigurableApplicationContext> contexts;

  private org.springframework.boot.SpringApplication$Augmented$RunListener();
    Code:
       0: aload_0
       1: invokespecial #1                  // Method java/lang/Object."<init>":()V
       4: aload_0
       5: new           #7                  // class java/util/ArrayList
       8: dup
       9: invokespecial #9                  // Method java/util/ArrayList."<init>":()V
      12: invokestatic  #10                 // Method java/util/Collections.synchronizedList:(Ljava/util/List;)Ljava/util/List;
      15: putfield      #16                 // Field contexts:Ljava/util/List;
      18: return

  public void contextLoaded(org.springframework.context.ConfigurableApplicationContext);
    Code:
       0: aload_0
       1: getfield      #16                 // Field contexts:Ljava/util/List;
       4: aload_1
       5: invokeinterface #22,  2           // InterfaceMethod java/util/List.add:(Ljava/lang/Object;)Z
      10: pop
      11: return

  public org.springframework.context.ConfigurableApplicationContext getApplicationContext();
    Code:
       0: aload_0
       1: getfield      #16                 // Field contexts:Ljava/util/List;
       4: invokeinterface #28,  1           // InterfaceMethod java/util/List.stream:()Ljava/util/stream/Stream;
       9: invokedynamic #32,  0             // InvokeDynamic #0:test:()Ljava/util/function/Predicate;
      14: invokeinterface #36,  2           // InterfaceMethod java/util/stream/Stream.filter:(Ljava/util/function/Predicate;)Ljava/util/stream/Stream;
      19: invokeinterface #42,  1           // InterfaceMethod java/util/stream/Stream.toList:()Ljava/util/List;
      24: astore_1
      25: aload_1
      26: invokeinterface #46,  1           // InterfaceMethod java/util/List.isEmpty:()Z
      31: ifne          38
      34: iconst_1
      35: goto          39
      38: iconst_0
      39: ldc           #50                 // String No root application context located
      41: invokestatic  #52                 // Method org/springframework/util/Assert.state:(ZLjava/lang/String;)V
      44: aload_1
      45: invokeinterface #58,  1           // InterfaceMethod java/util/List.size:()I
      50: iconst_1
      51: if_icmpne     58
      54: iconst_1
      55: goto          59
      58: iconst_0
      59: ldc           #62                 // String No unique root application context located
      61: invokestatic  #52                 // Method org/springframework/util/Assert.state:(ZLjava/lang/String;)V
      64: aload_1
      65: iconst_0
      66: invokeinterface #64,  2           // InterfaceMethod java/util/List.get:(I)Ljava/lang/Object;
      71: checkcast     #68                 // class org/springframework/context/ConfigurableApplicationContext
      74: areturn

  private static boolean lambda$getApplicationContext$0(org.springframework.context.ConfigurableApplicationContext);
    Code:
       0: aload_0
       1: invokeinterface #70,  1           // InterfaceMethod org/springframework/context/ConfigurableApplicationContext.getParent:()Lorg/springframework/context/ApplicationContext;
       6: ifnonnull     13
       9: iconst_1
      10: goto          14
      13: iconst_0
      14: ireturn
}
