Compiled from "SpringApplicationAotProcessor.java"
class org.springframework.boot.SpringApplicationAotProcessor$AotProcessorHook$1 implements org.springframework.boot.SpringApplicationRunListener {
  final org.springframework.boot.SpringApplicationAotProcessor$AotProcessorHook this$0;

  org.springframework.boot.SpringApplicationAotProcessor$AotProcessorHook$1(org.springframework.boot.SpringApplicationAotProcessor$AotProcessorHook);
    Code:
       0: aload_0
       1: aload_1
       2: putfield      #1                  // Field this$0:Lorg/springframework/boot/SpringApplicationAotProcessor$AotProcessorHook;
       5: aload_0
       6: invokespecial #7                  // Method java/lang/Object."<init>":()V
       9: return

  public void contextLoaded(org.springframework.context.ConfigurableApplicationContext);
    Code:
       0: new           #13                 // class org/springframework/boot/SpringApplication$AbandonedRunException
       3: dup
       4: aload_1
       5: invokespecial #15                 // Method org/springframework/boot/SpringApplication$AbandonedRunException."<init>":(Lorg/springframework/context/ConfigurableApplicationContext;)V
       8: athrow
}
