Compiled from "SpringApplicationAotProcessor.java"
public class org.springframework.boot.SpringApplicationAotProcessor extends org.springframework.context.aot.ContextAotProcessor {
  private final java.lang.String[] applicationArgs;

  public org.springframework.boot.SpringApplicationAotProcessor(java.lang.Class<?>, org.springframework.context.aot.AbstractAotProcessor$Settings, java.lang.String[]);
    Code:
       0: aload_0
       1: aload_1
       2: aload_2
       3: invokespecial #1                  // Method org/springframework/context/aot/ContextAotProcessor."<init>":(Ljava/lang/Class;Lorg/springframework/context/aot/AbstractAotProcessor$Settings;)V
       6: aload_0
       7: aload_3
       8: putfield      #7                  // Field applicationArgs:[Ljava/lang/String;
      11: return

  protected org.springframework.context.support.GenericApplicationContext prepareApplicationContext(java.lang.Class<?>);
    Code:
       0: new           #13                 // class org/springframework/boot/SpringApplicationAotProcessor$AotProcessorHook
       3: dup
       4: aload_1
       5: invokespecial #15                 // Method org/springframework/boot/SpringApplicationAotProcessor$AotProcessorHook."<init>":(Ljava/lang/Class;)V
       8: aload_0
       9: aload_1
      10: invokedynamic #18,  0             // InvokeDynamic #0:getWithException:(Lorg/springframework/boot/SpringApplicationAotProcessor;Ljava/lang/Class;)Lorg/springframework/util/function/ThrowingSupplier;
      15: invokevirtual #22                 // Method org/springframework/boot/SpringApplicationAotProcessor$AotProcessorHook.run:(Lorg/springframework/util/function/ThrowingSupplier;)Lorg/springframework/context/support/GenericApplicationContext;
      18: areturn

  public static void main(java.lang.String[]) throws java.lang.Exception;
    Code:
       0: bipush        6
       2: istore_1
       3: aload_0
       4: arraylength
       5: iload_1
       6: if_icmplt     13
       9: iconst_1
      10: goto          14
      13: iconst_0
      14: invokedynamic #26,  0             // InvokeDynamic #1:get:()Ljava/util/function/Supplier;
      19: invokestatic  #30                 // Method org/springframework/util/Assert.isTrue:(ZLjava/util/function/Supplier;)V
      22: aload_0
      23: iconst_0
      24: aaload
      25: invokestatic  #36                 // Method java/lang/Class.forName:(Ljava/lang/String;)Ljava/lang/Class;
      28: astore_2
      29: invokestatic  #42                 // Method org/springframework/context/aot/AbstractAotProcessor$Settings.builder:()Lorg/springframework/context/aot/AbstractAotProcessor$Settings$Builder;
      32: aload_0
      33: iconst_1
      34: aaload
      35: iconst_0
      36: anewarray     #48                 // class java/lang/String
      39: invokestatic  #50                 // Method java/nio/file/Paths.get:(Ljava/lang/String;[Ljava/lang/String;)Ljava/nio/file/Path;
      42: invokevirtual #55                 // Method org/springframework/context/aot/AbstractAotProcessor$Settings$Builder.sourceOutput:(Ljava/nio/file/Path;)Lorg/springframework/context/aot/AbstractAotProcessor$Settings$Builder;
      45: aload_0
      46: iconst_2
      47: aaload
      48: iconst_0
      49: anewarray     #48                 // class java/lang/String
      52: invokestatic  #50                 // Method java/nio/file/Paths.get:(Ljava/lang/String;[Ljava/lang/String;)Ljava/nio/file/Path;
      55: invokevirtual #61                 // Method org/springframework/context/aot/AbstractAotProcessor$Settings$Builder.resourceOutput:(Ljava/nio/file/Path;)Lorg/springframework/context/aot/AbstractAotProcessor$Settings$Builder;
      58: aload_0
      59: iconst_3
      60: aaload
      61: iconst_0
      62: anewarray     #48                 // class java/lang/String
      65: invokestatic  #50                 // Method java/nio/file/Paths.get:(Ljava/lang/String;[Ljava/lang/String;)Ljava/nio/file/Path;
      68: invokevirtual #64                 // Method org/springframework/context/aot/AbstractAotProcessor$Settings$Builder.classOutput:(Ljava/nio/file/Path;)Lorg/springframework/context/aot/AbstractAotProcessor$Settings$Builder;
      71: aload_0
      72: iconst_4
      73: aaload
      74: invokestatic  #67                 // Method org/springframework/util/StringUtils.hasText:(Ljava/lang/String;)Z
      77: ifeq          86
      80: aload_0
      81: iconst_4
      82: aaload
      83: goto          88
      86: ldc           #73                 // String unspecified
      88: invokevirtual #75                 // Method org/springframework/context/aot/AbstractAotProcessor$Settings$Builder.groupId:(Ljava/lang/String;)Lorg/springframework/context/aot/AbstractAotProcessor$Settings$Builder;
      91: aload_0
      92: iconst_5
      93: aaload
      94: invokevirtual #79                 // Method org/springframework/context/aot/AbstractAotProcessor$Settings$Builder.artifactId:(Ljava/lang/String;)Lorg/springframework/context/aot/AbstractAotProcessor$Settings$Builder;
      97: invokevirtual #82                 // Method org/springframework/context/aot/AbstractAotProcessor$Settings$Builder.build:()Lorg/springframework/context/aot/AbstractAotProcessor$Settings;
     100: astore_3
     101: aload_0
     102: arraylength
     103: iload_1
     104: if_icmple     120
     107: aload_0
     108: iload_1
     109: aload_0
     110: arraylength
     111: invokestatic  #86                 // Method java/util/Arrays.copyOfRange:([Ljava/lang/Object;II)[Ljava/lang/Object;
     114: checkcast     #92                 // class "[Ljava/lang/String;"
     117: goto          124
     120: iconst_0
     121: anewarray     #48                 // class java/lang/String
     124: astore        4
     126: new           #8                  // class org/springframework/boot/SpringApplicationAotProcessor
     129: dup
     130: aload_2
     131: aload_3
     132: aload         4
     134: invokespecial #93                 // Method "<init>":(Ljava/lang/Class;Lorg/springframework/context/aot/AbstractAotProcessor$Settings;[Ljava/lang/String;)V
     137: invokevirtual #96                 // Method process:()Ljava/lang/Object;
     140: pop
     141: return

  private static java.lang.String lambda$main$1();
    Code:
       0: ldc           #8                  // class org/springframework/boot/SpringApplicationAotProcessor
       2: invokevirtual #100                // Method java/lang/Class.getName:()Ljava/lang/String;
       5: invokedynamic #104,  0            // InvokeDynamic #2:makeConcatWithConstants:(Ljava/lang/String;)Ljava/lang/String;
      10: areturn

  private java.lang.Object lambda$prepareApplicationContext$0(java.lang.Class) throws java.lang.Exception;
    Code:
       0: aload_1
       1: ldc           #108                // String main
       3: iconst_1
       4: anewarray     #37                 // class java/lang/Class
       7: dup
       8: iconst_0
       9: ldc           #92                 // class "[Ljava/lang/String;"
      11: aastore
      12: invokevirtual #110                // Method java/lang/Class.getMethod:(Ljava/lang/String;[Ljava/lang/Class;)Ljava/lang/reflect/Method;
      15: astore_2
      16: aload_2
      17: aconst_null
      18: iconst_1
      19: anewarray     #114                // class java/lang/Object
      22: dup
      23: iconst_0
      24: aload_0
      25: getfield      #7                  // Field applicationArgs:[Ljava/lang/String;
      28: aastore
      29: invokestatic  #116                // Method org/springframework/util/ReflectionUtils.invokeMethod:(Ljava/lang/reflect/Method;Ljava/lang/Object;[Ljava/lang/Object;)Ljava/lang/Object;
      32: areturn
}
