Compiled from "SpringApplicationExtensions.kt"
public final class org.springframework.boot.SpringApplicationExtensionsKt {
  public static final <T> org.springframework.context.ConfigurableApplicationContext runApplication(java.lang.String...);
    Code:
       0: aload_0
       1: ldc           #9                  // String args
       3: invokestatic  #15                 // Method kotlin/jvm/internal/Intrinsics.checkNotNullParameter:(Ljava/lang/Object;Ljava/lang/String;)V
       6: iconst_0
       7: istore_1
       8: iconst_4
       9: ldc           #17                 // String T
      11: invokestatic  #21                 // Method kotlin/jvm/internal/Intrinsics.reifiedOperationMarker:(ILjava/lang/String;)V
      14: ldc           #4                  // class java/lang/Object
      16: checkcast     #23                 // class java/lang/Class
      19: aload_0
      20: aload_0
      21: arraylength
      22: invokestatic  #29                 // Method java/util/Arrays.copyOf:([Ljava/lang/Object;I)[Ljava/lang/Object;
      25: checkcast     #31                 // class "[Ljava/lang/String;"
      28: invokestatic  #37                 // Method org/springframework/boot/SpringApplication.run:(Ljava/lang/Class;[Ljava/lang/String;)Lorg/springframework/context/ConfigurableApplicationContext;
      31: dup
      32: ldc           #39                 // String run(T::class.java, *args)
      34: invokestatic  #42                 // Method kotlin/jvm/internal/Intrinsics.checkNotNullExpressionValue:(Ljava/lang/Object;Ljava/lang/String;)V
      37: checkcast     #44                 // class org/springframework/context/ConfigurableApplicationContext
      40: areturn

  public static final <T> org.springframework.context.ConfigurableApplicationContext runApplication(java.lang.String[], kotlin.jvm.functions.Function1<? super org.springframework.boot.SpringApplication, kotlin.Unit>);
    Code:
       0: aload_0
       1: ldc           #9                  // String args
       3: invokestatic  #15                 // Method kotlin/jvm/internal/Intrinsics.checkNotNullParameter:(Ljava/lang/Object;Ljava/lang/String;)V
       6: aload_1
       7: ldc           #50                 // String init
       9: invokestatic  #15                 // Method kotlin/jvm/internal/Intrinsics.checkNotNullParameter:(Ljava/lang/Object;Ljava/lang/String;)V
      12: iconst_0
      13: istore_2
      14: new           #33                 // class org/springframework/boot/SpringApplication
      17: dup
      18: iconst_1
      19: anewarray     #23                 // class java/lang/Class
      22: astore_3
      23: aload_3
      24: iconst_0
      25: iconst_4
      26: ldc           #17                 // String T
      28: invokestatic  #21                 // Method kotlin/jvm/internal/Intrinsics.reifiedOperationMarker:(ILjava/lang/String;)V
      31: ldc           #4                  // class java/lang/Object
      33: aastore
      34: aload_3
      35: invokespecial #54                 // Method org/springframework/boot/SpringApplication."<init>":([Ljava/lang/Class;)V
      38: astore_3
      39: aload_1
      40: aload_3
      41: invokeinterface #60,  2           // InterfaceMethod kotlin/jvm/functions/Function1.invoke:(Ljava/lang/Object;)Ljava/lang/Object;
      46: pop
      47: aload_3
      48: checkcast     #33                 // class org/springframework/boot/SpringApplication
      51: aload_0
      52: aload_0
      53: arraylength
      54: invokestatic  #29                 // Method java/util/Arrays.copyOf:([Ljava/lang/Object;I)[Ljava/lang/Object;
      57: checkcast     #31                 // class "[Ljava/lang/String;"
      60: invokevirtual #62                 // Method org/springframework/boot/SpringApplication.run:([Ljava/lang/String;)Lorg/springframework/context/ConfigurableApplicationContext;
      63: dup
      64: ldc           #64                 // String SpringApplication(T::cla¡¦a).apply(init).run(*args)
      66: invokestatic  #42                 // Method kotlin/jvm/internal/Intrinsics.checkNotNullExpressionValue:(Ljava/lang/Object;Ljava/lang/String;)V
      69: checkcast     #44                 // class org/springframework/context/ConfigurableApplicationContext
      72: areturn
}
