Compiled from "SpringApplicationShutdownHook.java"
class org.springframework.boot.SpringApplicationShutdownHook$ApplicationContextClosedListener implements org.springframework.context.ApplicationListener<org.springframework.context.event.ContextClosedEvent> {
  final org.springframework.boot.SpringApplicationShutdownHook this$0;

  private org.springframework.boot.SpringApplicationShutdownHook$ApplicationContextClosedListener(org.springframework.boot.SpringApplicationShutdownHook);
    Code:
       0: aload_0
       1: aload_1
       2: putfield      #1                  // Field this$0:Lorg/springframework/boot/SpringApplicationShutdownHook;
       5: aload_0
       6: invokespecial #7                  // Method java/lang/Object."<init>":()V
       9: return

  public void onApplicationEvent(org.springframework.context.event.ContextClosedEvent);
    Code:
       0: ldc           #13                 // class org/springframework/boot/SpringApplicationShutdownHook
       2: dup
       3: astore_2
       4: monitorenter
       5: aload_1
       6: invokevirtual #15                 // Method org/springframework/context/event/ContextClosedEvent.getApplicationContext:()Lorg/springframework/context/ApplicationContext;
       9: astore_3
      10: aload_0
      11: getfield      #1                  // Field this$0:Lorg/springframework/boot/SpringApplicationShutdownHook;
      14: getfield      #21                 // Field org/springframework/boot/SpringApplicationShutdownHook.contexts:Ljava/util/Set;
      17: aload_3
      18: invokeinterface #25,  2           // InterfaceMethod java/util/Set.remove:(Ljava/lang/Object;)Z
      23: pop
      24: aload_0
      25: getfield      #1                  // Field this$0:Lorg/springframework/boot/SpringApplicationShutdownHook;
      28: getfield      #31                 // Field org/springframework/boot/SpringApplicationShutdownHook.closedContexts:Ljava/util/Set;
      31: aload_3
      32: checkcast     #34                 // class org/springframework/context/ConfigurableApplicationContext
      35: invokeinterface #36,  2           // InterfaceMethod java/util/Set.add:(Ljava/lang/Object;)Z
      40: pop
      41: aload_2
      42: monitorexit
      43: goto          53
      46: astore        4
      48: aload_2
      49: monitorexit
      50: aload         4
      52: athrow
      53: return
    Exception table:
       from    to  target type
           5    43    46   any
          46    50    46   any

  public void onApplicationEvent(org.springframework.context.ApplicationEvent);
    Code:
       0: aload_0
       1: aload_1
       2: checkcast     #16                 // class org/springframework/context/event/ContextClosedEvent
       5: invokevirtual #39                 // Method onApplicationEvent:(Lorg/springframework/context/event/ContextClosedEvent;)V
       8: return
}
