Compiled from "SpringBootExceptionHandler.java"
class org.springframework.boot.SpringBootExceptionHandler implements java.lang.Thread$UncaughtExceptionHandler {
  private static final java.util.Set<java.lang.String> LOG_CONFIGURATION_MESSAGES;

  private static final org.springframework.boot.SpringBootExceptionHandler$LoggedExceptionHandlerThreadLocal handler;

  private final java.lang.Thread$UncaughtExceptionHandler parent;

  private final java.util.List<java.lang.Throwable> loggedExceptions;

  private int exitCode;

  org.springframework.boot.SpringBootExceptionHandler(java.lang.Thread$UncaughtExceptionHandler);
    Code:
       0: aload_0
       1: invokespecial #1                  // Method java/lang/Object."<init>":()V
       4: aload_0
       5: new           #7                  // class java/util/ArrayList
       8: dup
       9: invokespecial #9                  // Method java/util/ArrayList."<init>":()V
      12: putfield      #10                 // Field loggedExceptions:Ljava/util/List;
      15: aload_0
      16: iconst_0
      17: putfield      #16                 // Field exitCode:I
      20: aload_0
      21: aload_1
      22: putfield      #20                 // Field parent:Ljava/lang/Thread$UncaughtExceptionHandler;
      25: return

  void registerLoggedException(java.lang.Throwable);
    Code:
       0: aload_0
       1: getfield      #10                 // Field loggedExceptions:Ljava/util/List;
       4: aload_1
       5: invokeinterface #24,  2           // InterfaceMethod java/util/List.add:(Ljava/lang/Object;)Z
      10: pop
      11: return

  void registerExitCode(int);
    Code:
       0: aload_0
       1: iload_1
       2: putfield      #16                 // Field exitCode:I
       5: return

  public void uncaughtException(java.lang.Thread, java.lang.Throwable);
    Code:
       0: aload_0
       1: aload_2
       2: invokevirtual #30                 // Method isPassedToParent:(Ljava/lang/Throwable;)Z
       5: ifeq          26
       8: aload_0
       9: getfield      #20                 // Field parent:Ljava/lang/Thread$UncaughtExceptionHandler;
      12: ifnull        26
      15: aload_0
      16: getfield      #20                 // Field parent:Ljava/lang/Thread$UncaughtExceptionHandler;
      19: aload_1
      20: aload_2
      21: invokeinterface #34,  3           // InterfaceMethod java/lang/Thread$UncaughtExceptionHandler.uncaughtException:(Ljava/lang/Thread;Ljava/lang/Throwable;)V
      26: aload_0
      27: getfield      #10                 // Field loggedExceptions:Ljava/util/List;
      30: invokeinterface #40,  1           // InterfaceMethod java/util/List.clear:()V
      35: aload_0
      36: getfield      #16                 // Field exitCode:I
      39: ifeq          78
      42: aload_0
      43: getfield      #16                 // Field exitCode:I
      46: invokestatic  #43                 // Method java/lang/System.exit:(I)V
      49: goto          78
      52: astore_3
      53: aload_0
      54: getfield      #10                 // Field loggedExceptions:Ljava/util/List;
      57: invokeinterface #40,  1           // InterfaceMethod java/util/List.clear:()V
      62: aload_0
      63: getfield      #16                 // Field exitCode:I
      66: ifeq          76
      69: aload_0
      70: getfield      #16                 // Field exitCode:I
      73: invokestatic  #43                 // Method java/lang/System.exit:(I)V
      76: aload_3
      77: athrow
      78: return
    Exception table:
       from    to  target type
           0    26    52   any

  private boolean isPassedToParent(java.lang.Throwable);
    Code:
       0: aload_0
       1: aload_1
       2: invokevirtual #49                 // Method isLogConfigurationMessage:(Ljava/lang/Throwable;)Z
       5: ifne          16
       8: aload_0
       9: aload_1
      10: invokevirtual #52                 // Method isRegistered:(Ljava/lang/Throwable;)Z
      13: ifne          20
      16: iconst_1
      17: goto          21
      20: iconst_0
      21: ireturn

  private boolean isLogConfigurationMessage(java.lang.Throwable);
    Code:
       0: aload_1
       1: instanceof    #55                 // class java/lang/reflect/InvocationTargetException
       4: ifeq          16
       7: aload_0
       8: aload_1
       9: invokevirtual #57                 // Method java/lang/Throwable.getCause:()Ljava/lang/Throwable;
      12: invokevirtual #49                 // Method isLogConfigurationMessage:(Ljava/lang/Throwable;)Z
      15: ireturn
      16: aload_1
      17: invokevirtual #63                 // Method java/lang/Throwable.getMessage:()Ljava/lang/String;
      20: astore_2
      21: aload_2
      22: ifnull        68
      25: getstatic     #67                 // Field LOG_CONFIGURATION_MESSAGES:Ljava/util/Set;
      28: invokeinterface #71,  1           // InterfaceMethod java/util/Set.iterator:()Ljava/util/Iterator;
      33: astore_3
      34: aload_3
      35: invokeinterface #77,  1           // InterfaceMethod java/util/Iterator.hasNext:()Z
      40: ifeq          68
      43: aload_3
      44: invokeinterface #83,  1           // InterfaceMethod java/util/Iterator.next:()Ljava/lang/Object;
      49: checkcast     #87                 // class java/lang/String
      52: astore        4
      54: aload_2
      55: aload         4
      57: invokevirtual #89                 // Method java/lang/String.contains:(Ljava/lang/CharSequence;)Z
      60: ifeq          65
      63: iconst_1
      64: ireturn
      65: goto          34
      68: iconst_0
      69: ireturn

  private boolean isRegistered(java.lang.Throwable);
    Code:
       0: aload_0
       1: getfield      #10                 // Field loggedExceptions:Ljava/util/List;
       4: aload_1
       5: invokeinterface #93,  2           // InterfaceMethod java/util/List.contains:(Ljava/lang/Object;)Z
      10: ifeq          15
      13: iconst_1
      14: ireturn
      15: aload_1
      16: instanceof    #55                 // class java/lang/reflect/InvocationTargetException
      19: ifeq          31
      22: aload_0
      23: aload_1
      24: invokevirtual #57                 // Method java/lang/Throwable.getCause:()Ljava/lang/Throwable;
      27: invokevirtual #52                 // Method isRegistered:(Ljava/lang/Throwable;)Z
      30: ireturn
      31: iconst_0
      32: ireturn

  static org.springframework.boot.SpringBootExceptionHandler forCurrentThread();
    Code:
       0: getstatic     #95                 // Field handler:Lorg/springframework/boot/SpringBootExceptionHandler$LoggedExceptionHandlerThreadLocal;
       3: invokevirtual #99                 // Method org/springframework/boot/SpringBootExceptionHandler$LoggedExceptionHandlerThreadLocal.get:()Ljava/lang/Object;
       6: checkcast     #11                 // class org/springframework/boot/SpringBootExceptionHandler
       9: areturn

  static {};
    Code:
       0: new           #104                // class java/util/HashSet
       3: dup
       4: invokespecial #106                // Method java/util/HashSet."<init>":()V
       7: astore_0
       8: aload_0
       9: ldc           #107                // String Logback configuration error detected
      11: invokeinterface #109,  2          // InterfaceMethod java/util/Set.add:(Ljava/lang/Object;)Z
      16: pop
      17: aload_0
      18: invokestatic  #110                // Method java/util/Collections.unmodifiableSet:(Ljava/util/Set;)Ljava/util/Set;
      21: putstatic     #67                 // Field LOG_CONFIGURATION_MESSAGES:Ljava/util/Set;
      24: new           #100                // class org/springframework/boot/SpringBootExceptionHandler$LoggedExceptionHandlerThreadLocal
      27: dup
      28: invokespecial #116                // Method org/springframework/boot/SpringBootExceptionHandler$LoggedExceptionHandlerThreadLocal."<init>":()V
      31: putstatic     #95                 // Field handler:Lorg/springframework/boot/SpringBootExceptionHandler$LoggedExceptionHandlerThreadLocal;
      34: return
}
