Compiled from "SpringApplicationAotProcessor.java"
final class org.springframework.boot.SpringApplicationAotProcessor$AotProcessorHook implements org.springframework.boot.SpringApplicationHook {
  private final java.lang.Class<?> application;

  private org.springframework.boot.SpringApplicationAotProcessor$AotProcessorHook(java.lang.Class<?>);
    Code:
       0: aload_0
       1: invokespecial #1                  // Method java/lang/Object."<init>":()V
       4: aload_0
       5: aload_1
       6: putfield      #7                  // Field application:Ljava/lang/Class;
       9: return

  public org.springframework.boot.SpringApplicationRunListener getRunListener(org.springframework.boot.SpringApplication);
    Code:
       0: new           #13                 // class org/springframework/boot/SpringApplicationAotProcessor$AotProcessorHook$1
       3: dup
       4: aload_0
       5: invokespecial #15                 // Method org/springframework/boot/SpringApplicationAotProcessor$AotProcessorHook$1."<init>":(Lorg/springframework/boot/SpringApplicationAotProcessor$AotProcessorHook;)V
       8: areturn

  private <T> org.springframework.context.support.GenericApplicationContext run(org.springframework.util.function.ThrowingSupplier<T>);
    Code:
       0: aload_0
       1: aload_1
       2: invokestatic  #18                 // Method org/springframework/boot/SpringApplication.withHook:(Lorg/springframework/boot/SpringApplicationHook;Lorg/springframework/util/function/ThrowingSupplier;)Ljava/lang/Object;
       5: pop
       6: goto          32
       9: astore_2
      10: aload_2
      11: invokevirtual #26                 // Method org/springframework/boot/SpringApplication$AbandonedRunException.getApplicationContext:()Lorg/springframework/context/ConfigurableApplicationContext;
      14: astore_3
      15: ldc           #30                 // class org/springframework/context/support/GenericApplicationContext
      17: aload_3
      18: aload_3
      19: invokedynamic #32,  0             // InvokeDynamic #0:get:(Lorg/springframework/context/ApplicationContext;)Ljava/util/function/Supplier;
      24: invokestatic  #36                 // Method org/springframework/util/Assert.isInstanceOf:(Ljava/lang/Class;Ljava/lang/Object;Ljava/util/function/Supplier;)V
      27: aload_3
      28: checkcast     #30                 // class org/springframework/context/support/GenericApplicationContext
      31: areturn
      32: new           #42                 // class java/lang/IllegalStateException
      35: dup
      36: ldc           #44                 // String No application context available after calling main method of \'%s\'. Does it run a SpringApplication?
      38: iconst_1
      39: anewarray     #2                  // class java/lang/Object
      42: dup
      43: iconst_0
      44: aload_0
      45: getfield      #7                  // Field application:Ljava/lang/Class;
      48: invokevirtual #46                 // Method java/lang/Class.getName:()Ljava/lang/String;
      51: aastore
      52: invokevirtual #52                 // Method java/lang/String.formatted:([Ljava/lang/Object;)Ljava/lang/String;
      55: invokespecial #58                 // Method java/lang/IllegalStateException."<init>":(Ljava/lang/String;)V
      58: athrow
    Exception table:
       from    to  target type
           0     6     9   Class org/springframework/boot/SpringApplication$AbandonedRunException

  private static java.lang.String lambda$run$0(org.springframework.context.ApplicationContext);
    Code:
       0: aload_0
       1: invokevirtual #61                 // Method java/lang/Object.getClass:()Ljava/lang/Class;
       4: invokevirtual #46                 // Method java/lang/Class.getName:()Ljava/lang/String;
       7: invokedynamic #65,  0             // InvokeDynamic #1:makeConcatWithConstants:(Ljava/lang/String;)Ljava/lang/String;
      12: areturn
}
