Compiled from "SpringApplicationRunListeners.java"
class org.springframework.boot.SpringApplicationRunListeners {
  private final org.apache.commons.logging.Log log;

  private final java.util.List<org.springframework.boot.SpringApplicationRunListener> listeners;

  private final org.springframework.core.metrics.ApplicationStartup applicationStartup;

  org.springframework.boot.SpringApplicationRunListeners(org.apache.commons.logging.Log, java.util.List<org.springframework.boot.SpringApplicationRunListener>, org.springframework.core.metrics.ApplicationStartup);
    Code:
       0: aload_0
       1: invokespecial #1                  // Method java/lang/Object."<init>":()V
       4: aload_0
       5: aload_1
       6: putfield      #7                  // Field log:Lorg/apache/commons/logging/Log;
       9: aload_0
      10: aload_2
      11: invokestatic  #13                 // InterfaceMethod java/util/List.copyOf:(Ljava/util/Collection;)Ljava/util/List;
      14: putfield      #19                 // Field listeners:Ljava/util/List;
      17: aload_0
      18: aload_3
      19: putfield      #23                 // Field applicationStartup:Lorg/springframework/core/metrics/ApplicationStartup;
      22: return

  void starting(org.springframework.boot.ConfigurableBootstrapContext, java.lang.Class<?>);
    Code:
       0: aload_0
       1: ldc           #27                 // String spring.boot.application.starting
       3: aload_1
       4: invokedynamic #29,  0             // InvokeDynamic #0:accept:(Lorg/springframework/boot/ConfigurableBootstrapContext;)Ljava/util/function/Consumer;
       9: aload_2
      10: invokedynamic #33,  0             // InvokeDynamic #1:accept:(Ljava/lang/Class;)Ljava/util/function/Consumer;
      15: invokevirtual #36                 // Method doWithListeners:(Ljava/lang/String;Ljava/util/function/Consumer;Ljava/util/function/Consumer;)V
      18: return

  void environmentPrepared(org.springframework.boot.ConfigurableBootstrapContext, org.springframework.core.env.ConfigurableEnvironment);
    Code:
       0: aload_0
       1: ldc           #40                 // String spring.boot.application.environment-prepared
       3: aload_1
       4: aload_2
       5: invokedynamic #42,  0             // InvokeDynamic #2:accept:(Lorg/springframework/boot/ConfigurableBootstrapContext;Lorg/springframework/core/env/ConfigurableEnvironment;)Ljava/util/function/Consumer;
      10: invokevirtual #45                 // Method doWithListeners:(Ljava/lang/String;Ljava/util/function/Consumer;)V
      13: return

  void contextPrepared(org.springframework.context.ConfigurableApplicationContext);
    Code:
       0: aload_0
       1: ldc           #48                 // String spring.boot.application.context-prepared
       3: aload_1
       4: invokedynamic #50,  0             // InvokeDynamic #3:accept:(Lorg/springframework/context/ConfigurableApplicationContext;)Ljava/util/function/Consumer;
       9: invokevirtual #45                 // Method doWithListeners:(Ljava/lang/String;Ljava/util/function/Consumer;)V
      12: return

  void contextLoaded(org.springframework.context.ConfigurableApplicationContext);
    Code:
       0: aload_0
       1: ldc           #53                 // String spring.boot.application.context-loaded
       3: aload_1
       4: invokedynamic #55,  0             // InvokeDynamic #4:accept:(Lorg/springframework/context/ConfigurableApplicationContext;)Ljava/util/function/Consumer;
       9: invokevirtual #45                 // Method doWithListeners:(Ljava/lang/String;Ljava/util/function/Consumer;)V
      12: return

  void started(org.springframework.context.ConfigurableApplicationContext, java.time.Duration);
    Code:
       0: aload_0
       1: ldc           #56                 // String spring.boot.application.started
       3: aload_1
       4: aload_2
       5: invokedynamic #58,  0             // InvokeDynamic #5:accept:(Lorg/springframework/context/ConfigurableApplicationContext;Ljava/time/Duration;)Ljava/util/function/Consumer;
      10: invokevirtual #45                 // Method doWithListeners:(Ljava/lang/String;Ljava/util/function/Consumer;)V
      13: return

  void ready(org.springframework.context.ConfigurableApplicationContext, java.time.Duration);
    Code:
       0: aload_0
       1: ldc           #61                 // String spring.boot.application.ready
       3: aload_1
       4: aload_2
       5: invokedynamic #63,  0             // InvokeDynamic #6:accept:(Lorg/springframework/context/ConfigurableApplicationContext;Ljava/time/Duration;)Ljava/util/function/Consumer;
      10: invokevirtual #45                 // Method doWithListeners:(Ljava/lang/String;Ljava/util/function/Consumer;)V
      13: return

  void failed(org.springframework.context.ConfigurableApplicationContext, java.lang.Throwable);
    Code:
       0: aload_0
       1: ldc           #64                 // String spring.boot.application.failed
       3: aload_0
       4: aload_1
       5: aload_2
       6: invokedynamic #66,  0             // InvokeDynamic #7:accept:(Lorg/springframework/boot/SpringApplicationRunListeners;Lorg/springframework/context/ConfigurableApplicationContext;Ljava/lang/Throwable;)Ljava/util/function/Consumer;
      11: aload_2
      12: invokedynamic #69,  0             // InvokeDynamic #8:accept:(Ljava/lang/Throwable;)Ljava/util/function/Consumer;
      17: invokevirtual #36                 // Method doWithListeners:(Ljava/lang/String;Ljava/util/function/Consumer;Ljava/util/function/Consumer;)V
      20: return

  private void callFailedListener(org.springframework.boot.SpringApplicationRunListener, org.springframework.context.ConfigurableApplicationContext, java.lang.Throwable);
    Code:
       0: aload_1
       1: aload_2
       2: aload_3
       3: invokeinterface #72,  3           // InterfaceMethod org/springframework/boot/SpringApplicationRunListener.failed:(Lorg/springframework/context/ConfigurableApplicationContext;Ljava/lang/Throwable;)V
       8: goto          87
      11: astore        4
      13: aload_3
      14: ifnonnull     22
      17: aload         4
      19: invokestatic  #80                 // Method org/springframework/util/ReflectionUtils.rethrowRuntimeException:(Ljava/lang/Throwable;)V
      22: aload_0
      23: getfield      #7                  // Field log:Lorg/apache/commons/logging/Log;
      26: invokeinterface #86,  1           // InterfaceMethod org/apache/commons/logging/Log.isDebugEnabled:()Z
      31: ifeq          50
      34: aload_0
      35: getfield      #7                  // Field log:Lorg/apache/commons/logging/Log;
      38: ldc           #92                 // String Error handling failed
      40: aload         4
      42: invokeinterface #94,  3           // InterfaceMethod org/apache/commons/logging/Log.error:(Ljava/lang/Object;Ljava/lang/Throwable;)V
      47: goto          87
      50: aload         4
      52: invokevirtual #98                 // Method java/lang/Throwable.getMessage:()Ljava/lang/String;
      55: astore        5
      57: aload         5
      59: ifnull        67
      62: aload         5
      64: goto          69
      67: ldc           #102                // String no error message
      69: astore        5
      71: aload_0
      72: getfield      #7                  // Field log:Lorg/apache/commons/logging/Log;
      75: aload         5
      77: invokedynamic #104,  0            // InvokeDynamic #9:makeConcatWithConstants:(Ljava/lang/String;)Ljava/lang/String;
      82: invokeinterface #108,  2          // InterfaceMethod org/apache/commons/logging/Log.warn:(Ljava/lang/Object;)V
      87: return
    Exception table:
       from    to  target type
           0     8    11   Class java/lang/Throwable

  private void doWithListeners(java.lang.String, java.util.function.Consumer<org.springframework.boot.SpringApplicationRunListener>);
    Code:
       0: aload_0
       1: aload_1
       2: aload_2
       3: aconst_null
       4: invokevirtual #36                 // Method doWithListeners:(Ljava/lang/String;Ljava/util/function/Consumer;Ljava/util/function/Consumer;)V
       7: return

  private void doWithListeners(java.lang.String, java.util.function.Consumer<org.springframework.boot.SpringApplicationRunListener>, java.util.function.Consumer<org.springframework.core.metrics.StartupStep>);
    Code:
       0: aload_0
       1: getfield      #23                 // Field applicationStartup:Lorg/springframework/core/metrics/ApplicationStartup;
       4: aload_1
       5: invokeinterface #112,  2          // InterfaceMethod org/springframework/core/metrics/ApplicationStartup.start:(Ljava/lang/String;)Lorg/springframework/core/metrics/StartupStep;
      10: astore        4
      12: aload_0
      13: getfield      #19                 // Field listeners:Ljava/util/List;
      16: aload_2
      17: invokeinterface #118,  2          // InterfaceMethod java/util/List.forEach:(Ljava/util/function/Consumer;)V
      22: aload_3
      23: ifnull        34
      26: aload_3
      27: aload         4
      29: invokeinterface #122,  2          // InterfaceMethod java/util/function/Consumer.accept:(Ljava/lang/Object;)V
      34: aload         4
      36: invokeinterface #126,  1          // InterfaceMethod org/springframework/core/metrics/StartupStep.end:()V
      41: return

  private static void lambda$failed$8(java.lang.Throwable, org.springframework.core.metrics.StartupStep);
    Code:
       0: aload_1
       1: ldc           #131                // String exception
       3: aload_0
       4: invokevirtual #133                // Method java/lang/Object.getClass:()Ljava/lang/Class;
       7: invokevirtual #137                // Method java/lang/Class.toString:()Ljava/lang/String;
      10: invokeinterface #142,  3          // InterfaceMethod org/springframework/core/metrics/StartupStep.tag:(Ljava/lang/String;Ljava/lang/String;)Lorg/springframework/core/metrics/StartupStep;
      15: pop
      16: aload_1
      17: ldc           #146                // String message
      19: aload_0
      20: invokevirtual #98                 // Method java/lang/Throwable.getMessage:()Ljava/lang/String;
      23: invokeinterface #142,  3          // InterfaceMethod org/springframework/core/metrics/StartupStep.tag:(Ljava/lang/String;Ljava/lang/String;)Lorg/springframework/core/metrics/StartupStep;
      28: pop
      29: return

  private void lambda$failed$7(org.springframework.context.ConfigurableApplicationContext, java.lang.Throwable, org.springframework.boot.SpringApplicationRunListener);
    Code:
       0: aload_0
       1: aload_3
       2: aload_1
       3: aload_2
       4: invokevirtual #148                // Method callFailedListener:(Lorg/springframework/boot/SpringApplicationRunListener;Lorg/springframework/context/ConfigurableApplicationContext;Ljava/lang/Throwable;)V
       7: return

  private static void lambda$ready$6(org.springframework.context.ConfigurableApplicationContext, java.time.Duration, org.springframework.boot.SpringApplicationRunListener);
    Code:
       0: aload_2
       1: aload_0
       2: aload_1
       3: invokeinterface #152,  3          // InterfaceMethod org/springframework/boot/SpringApplicationRunListener.ready:(Lorg/springframework/context/ConfigurableApplicationContext;Ljava/time/Duration;)V
       8: return

  private static void lambda$started$5(org.springframework.context.ConfigurableApplicationContext, java.time.Duration, org.springframework.boot.SpringApplicationRunListener);
    Code:
       0: aload_2
       1: aload_0
       2: aload_1
       3: invokeinterface #156,  3          // InterfaceMethod org/springframework/boot/SpringApplicationRunListener.started:(Lorg/springframework/context/ConfigurableApplicationContext;Ljava/time/Duration;)V
       8: return

  private static void lambda$contextLoaded$4(org.springframework.context.ConfigurableApplicationContext, org.springframework.boot.SpringApplicationRunListener);
    Code:
       0: aload_1
       1: aload_0
       2: invokeinterface #159,  2          // InterfaceMethod org/springframework/boot/SpringApplicationRunListener.contextLoaded:(Lorg/springframework/context/ConfigurableApplicationContext;)V
       7: return

  private static void lambda$contextPrepared$3(org.springframework.context.ConfigurableApplicationContext, org.springframework.boot.SpringApplicationRunListener);
    Code:
       0: aload_1
       1: aload_0
       2: invokeinterface #163,  2          // InterfaceMethod org/springframework/boot/SpringApplicationRunListener.contextPrepared:(Lorg/springframework/context/ConfigurableApplicationContext;)V
       7: return

  private static void lambda$environmentPrepared$2(org.springframework.boot.ConfigurableBootstrapContext, org.springframework.core.env.ConfigurableEnvironment, org.springframework.boot.SpringApplicationRunListener);
    Code:
       0: aload_2
       1: aload_0
       2: aload_1
       3: invokeinterface #166,  3          // InterfaceMethod org/springframework/boot/SpringApplicationRunListener.environmentPrepared:(Lorg/springframework/boot/ConfigurableBootstrapContext;Lorg/springframework/core/env/ConfigurableEnvironment;)V
       8: return

  private static void lambda$starting$1(java.lang.Class, org.springframework.core.metrics.StartupStep);
    Code:
       0: aload_0
       1: ifnull        17
       4: aload_1
       5: ldc           #170                // String mainApplicationClass
       7: aload_0
       8: invokevirtual #172                // Method java/lang/Class.getName:()Ljava/lang/String;
      11: invokeinterface #142,  3          // InterfaceMethod org/springframework/core/metrics/StartupStep.tag:(Ljava/lang/String;Ljava/lang/String;)Lorg/springframework/core/metrics/StartupStep;
      16: pop
      17: return

  private static void lambda$starting$0(org.springframework.boot.ConfigurableBootstrapContext, org.springframework.boot.SpringApplicationRunListener);
    Code:
       0: aload_1
       1: aload_0
       2: invokeinterface #175,  2          // InterfaceMethod org/springframework/boot/SpringApplicationRunListener.starting:(Lorg/springframework/boot/ConfigurableBootstrapContext;)V
       7: return
}
