Compiled from "SpringApplicationBannerPrinter.java"
class org.springframework.boot.SpringApplicationBannerPrinter$SpringApplicationBannerPrinterRuntimeHints implements org.springframework.aot.hint.RuntimeHintsRegistrar {
  org.springframework.boot.SpringApplicationBannerPrinter$SpringApplicationBannerPrinterRuntimeHints();
    Code:
       0: aload_0
       1: invokespecial #3                  // Method java/lang/Object."<init>":()V
       4: return

  public void registerHints(org.springframework.aot.hint.RuntimeHints, java.lang.ClassLoader);
    Code:
       0: aload_1
       1: invokevirtual #9                  // Method org/springframework/aot/hint/RuntimeHints.resources:()Lorg/springframework/aot/hint/ResourceHints;
       4: ldc           #15                 // String banner.txt
       6: invokevirtual #17                 // Method org/springframework/aot/hint/ResourceHints.registerPattern:(Ljava/lang/String;)Lorg/springframework/aot/hint/ResourceHints;
       9: pop
      10: return
}
