Compiled from "SpringApplication.java"
public class org.springframework.boot.SpringApplication$AbandonedRunException extends java.lang.RuntimeException {
  private final org.springframework.context.ConfigurableApplicationContext applicationContext;

  public org.springframework.boot.SpringApplication$AbandonedRunException();
    Code:
       0: aload_0
       1: aconst_null
       2: invokespecial #1                  // Method "<init>":(Lorg/springframework/context/ConfigurableApplicationContext;)V
       5: return

  public org.springframework.boot.SpringApplication$AbandonedRunException(org.springframework.context.ConfigurableApplicationContext);
    Code:
       0: aload_0
       1: invokespecial #7                  // Method java/lang/RuntimeException."<init>":()V
       4: aload_0
       5: aload_1
       6: putfield      #12                 // Field applicationContext:Lorg/springframework/context/ConfigurableApplicationContext;
       9: return

  public org.springframework.context.ConfigurableApplicationContext getApplicationContext();
    Code:
       0: aload_0
       1: getfield      #12                 // Field applicationContext:Lorg/springframework/context/ConfigurableApplicationContext;
       4: areturn
}
