Compiled from "WebApplicationType.java"
public final class org.springframework.boot.WebApplicationType extends java.lang.Enum<org.springframework.boot.WebApplicationType> {
  public static final org.springframework.boot.WebApplicationType NONE;

  public static final org.springframework.boot.WebApplicationType SERVLET;

  public static final org.springframework.boot.WebApplicationType REACTIVE;

  private static final java.lang.String[] SERVLET_INDICATOR_CLASSES;

  private static final java.lang.String WEBMVC_INDICATOR_CLASS;

  private static final java.lang.String WEBFLUX_INDICATOR_CLASS;

  private static final java.lang.String JERSEY_INDICATOR_CLASS;

  private static final org.springframework.boot.WebApplicationType[] $VALUES;

  public static org.springframework.boot.WebApplicationType[] values();
    Code:
       0: getstatic     #13                 // Field $VALUES:[Lorg/springframework/boot/WebApplicationType;
       3: invokevirtual #17                 // Method "[Lorg/springframework/boot/WebApplicationType;".clone:()Ljava/lang/Object;
       6: checkcast     #18                 // class "[Lorg/springframework/boot/WebApplicationType;"
       9: areturn

  public static org.springframework.boot.WebApplicationType valueOf(java.lang.String);
    Code:
       0: ldc           #1                  // class org/springframework/boot/WebApplicationType
       2: aload_0
       3: invokestatic  #22                 // Method java/lang/Enum.valueOf:(Ljava/lang/Class;Ljava/lang/String;)Ljava/lang/Enum;
       6: checkcast     #1                  // class org/springframework/boot/WebApplicationType
       9: areturn

  private org.springframework.boot.WebApplicationType();
    Code:
       0: aload_0
       1: aload_1
       2: iload_2
       3: invokespecial #28                 // Method java/lang/Enum."<init>":(Ljava/lang/String;I)V
       6: return

  static org.springframework.boot.WebApplicationType deduceFromClasspath();
    Code:
       0: ldc           #32                 // String org.springframework.web.reactive.DispatcherHandler
       2: aconst_null
       3: invokestatic  #34                 // Method org/springframework/util/ClassUtils.isPresent:(Ljava/lang/String;Ljava/lang/ClassLoader;)Z
       6: ifeq          31
       9: ldc           #40                 // String org.springframework.web.servlet.DispatcherServlet
      11: aconst_null
      12: invokestatic  #34                 // Method org/springframework/util/ClassUtils.isPresent:(Ljava/lang/String;Ljava/lang/ClassLoader;)Z
      15: ifne          31
      18: ldc           #42                 // String org.glassfish.jersey.servlet.ServletContainer
      20: aconst_null
      21: invokestatic  #34                 // Method org/springframework/util/ClassUtils.isPresent:(Ljava/lang/String;Ljava/lang/ClassLoader;)Z
      24: ifne          31
      27: getstatic     #10                 // Field REACTIVE:Lorg/springframework/boot/WebApplicationType;
      30: areturn
      31: getstatic     #44                 // Field SERVLET_INDICATOR_CLASSES:[Ljava/lang/String;
      34: astore_0
      35: aload_0
      36: arraylength
      37: istore_1
      38: iconst_0
      39: istore_2
      40: iload_2
      41: iload_1
      42: if_icmpge     67
      45: aload_0
      46: iload_2
      47: aaload
      48: astore_3
      49: aload_3
      50: aconst_null
      51: invokestatic  #34                 // Method org/springframework/util/ClassUtils.isPresent:(Ljava/lang/String;Ljava/lang/ClassLoader;)Z
      54: ifne          61
      57: getstatic     #3                  // Field NONE:Lorg/springframework/boot/WebApplicationType;
      60: areturn
      61: iinc          2, 1
      64: goto          40
      67: getstatic     #7                  // Field SERVLET:Lorg/springframework/boot/WebApplicationType;
      70: areturn

  private static org.springframework.boot.WebApplicationType[] $values();
    Code:
       0: iconst_3
       1: anewarray     #1                  // class org/springframework/boot/WebApplicationType
       4: dup
       5: iconst_0
       6: getstatic     #3                  // Field NONE:Lorg/springframework/boot/WebApplicationType;
       9: aastore
      10: dup
      11: iconst_1
      12: getstatic     #7                  // Field SERVLET:Lorg/springframework/boot/WebApplicationType;
      15: aastore
      16: dup
      17: iconst_2
      18: getstatic     #10                 // Field REACTIVE:Lorg/springframework/boot/WebApplicationType;
      21: aastore
      22: areturn

  static {};
    Code:
       0: new           #1                  // class org/springframework/boot/WebApplicationType
       3: dup
       4: ldc           #48                 // String NONE
       6: iconst_0
       7: invokespecial #49                 // Method "<init>":(Ljava/lang/String;I)V
      10: putstatic     #3                  // Field NONE:Lorg/springframework/boot/WebApplicationType;
      13: new           #1                  // class org/springframework/boot/WebApplicationType
      16: dup
      17: ldc           #50                 // String SERVLET
      19: iconst_1
      20: invokespecial #49                 // Method "<init>":(Ljava/lang/String;I)V
      23: putstatic     #7                  // Field SERVLET:Lorg/springframework/boot/WebApplicationType;
      26: new           #1                  // class org/springframework/boot/WebApplicationType
      29: dup
      30: ldc           #51                 // String REACTIVE
      32: iconst_2
      33: invokespecial #49                 // Method "<init>":(Ljava/lang/String;I)V
      36: putstatic     #10                 // Field REACTIVE:Lorg/springframework/boot/WebApplicationType;
      39: invokestatic  #52                 // Method $values:()[Lorg/springframework/boot/WebApplicationType;
      42: putstatic     #13                 // Field $VALUES:[Lorg/springframework/boot/WebApplicationType;
      45: iconst_2
      46: anewarray     #56                 // class java/lang/String
      49: dup
      50: iconst_0
      51: ldc           #58                 // String jakarta.servlet.Servlet
      53: aastore
      54: dup
      55: iconst_1
      56: ldc           #60                 // String org.springframework.web.context.ConfigurableWebApplicationContext
      58: aastore
      59: putstatic     #44                 // Field SERVLET_INDICATOR_CLASSES:[Ljava/lang/String;
      62: return
}
