Compiled from "WebApplicationType.java"
class org.springframework.boot.WebApplicationType$WebApplicationTypeRuntimeHints implements org.springframework.aot.hint.RuntimeHintsRegistrar {
  org.springframework.boot.WebApplicationType$WebApplicationTypeRuntimeHints();
    Code:
       0: aload_0
       1: invokespecial #3                  // Method java/lang/Object."<init>":()V
       4: return

  public void registerHints(org.springframework.aot.hint.RuntimeHints, java.lang.ClassLoader);
    Code:
       0: getstatic     #9                  // Field org/springframework/boot/WebApplicationType.SERVLET_INDICATOR_CLASSES:[Ljava/lang/String;
       3: astore_3
       4: aload_3
       5: arraylength
       6: istore        4
       8: iconst_0
       9: istore        5
      11: iload         5
      13: iload         4
      15: if_icmpge     38
      18: aload_3
      19: iload         5
      21: aaload
      22: astore        6
      24: aload_0
      25: aload         6
      27: aload_2
      28: aload_1
      29: invokevirtual #13                 // Method registerTypeIfPresent:(Ljava/lang/String;Ljava/lang/ClassLoader;Lorg/springframework/aot/hint/RuntimeHints;)V
      32: iinc          5, 1
      35: goto          11
      38: aload_0
      39: ldc           #19                 // String org.glassfish.jersey.servlet.ServletContainer
      41: aload_2
      42: aload_1
      43: invokevirtual #13                 // Method registerTypeIfPresent:(Ljava/lang/String;Ljava/lang/ClassLoader;Lorg/springframework/aot/hint/RuntimeHints;)V
      46: aload_0
      47: ldc           #21                 // String org.springframework.web.reactive.DispatcherHandler
      49: aload_2
      50: aload_1
      51: invokevirtual #13                 // Method registerTypeIfPresent:(Ljava/lang/String;Ljava/lang/ClassLoader;Lorg/springframework/aot/hint/RuntimeHints;)V
      54: aload_0
      55: ldc           #23                 // String org.springframework.web.servlet.DispatcherServlet
      57: aload_2
      58: aload_1
      59: invokevirtual #13                 // Method registerTypeIfPresent:(Ljava/lang/String;Ljava/lang/ClassLoader;Lorg/springframework/aot/hint/RuntimeHints;)V
      62: return

  private void registerTypeIfPresent(java.lang.String, java.lang.ClassLoader, org.springframework.aot.hint.RuntimeHints);
    Code:
       0: aload_1
       1: aload_2
       2: invokestatic  #25                 // Method org/springframework/util/ClassUtils.isPresent:(Ljava/lang/String;Ljava/lang/ClassLoader;)Z
       5: ifeq          24
       8: aload_3
       9: invokevirtual #31                 // Method org/springframework/aot/hint/RuntimeHints.reflection:()Lorg/springframework/aot/hint/ReflectionHints;
      12: aload_1
      13: invokestatic  #37                 // InterfaceMethod org/springframework/aot/hint/TypeReference.of:(Ljava/lang/String;)Lorg/springframework/aot/hint/TypeReference;
      16: iconst_0
      17: anewarray     #43                 // class org/springframework/aot/hint/MemberCategory
      20: invokevirtual #45                 // Method org/springframework/aot/hint/ReflectionHints.registerType:(Lorg/springframework/aot/hint/TypeReference;[Lorg/springframework/aot/hint/MemberCategory;)Lorg/springframework/aot/hint/ReflectionHints;
      23: pop
      24: return
}
