Compiled from "AbstractAnnotationBeanPostProcessor.java"
public class org.apache.dubbo.config.spring.beans.factory.annotation.AbstractAnnotationBeanPostProcessor$AnnotatedMethodElement extends org.apache.dubbo.config.spring.beans.factory.annotation.AbstractAnnotationBeanPostProcessor$AnnotatedInjectElement {
  protected final java.lang.reflect.Method method;

  final org.apache.dubbo.config.spring.beans.factory.annotation.AbstractAnnotationBeanPostProcessor this$0;

  protected org.apache.dubbo.config.spring.beans.factory.annotation.AbstractAnnotationBeanPostProcessor$AnnotatedMethodElement(org.apache.dubbo.config.spring.beans.factory.annotation.AbstractAnnotationBeanPostProcessor, java.lang.reflect.Method, java.beans.PropertyDescriptor, org.springframework.core.annotation.AnnotationAttributes);
    Code:
       0: aload_0
       1: aload_1
       2: putfield      #1                  // Field this$0:Lorg/apache/dubbo/config/spring/beans/factory/annotation/AbstractAnnotationBeanPostProcessor;
       5: aload_0
       6: aload_1
       7: aload_2
       8: aload_3
       9: aload         4
      11: invokespecial #2                  // Method org/apache/dubbo/config/spring/beans/factory/annotation/AbstractAnnotationBeanPostProcessor$AnnotatedInjectElement."<init>":(Lorg/apache/dubbo/config/spring/beans/factory/annotation/AbstractAnnotationBeanPostProcessor;Ljava/lang/reflect/Member;Ljava/beans/PropertyDescriptor;Lorg/springframework/core/annotation/AnnotationAttributes;)V
      14: aload_0
      15: aload_2
      16: putfield      #3                  // Field method:Ljava/lang/reflect/Method;
      19: return
}
