Compiled from "AbstractAnnotationBeanPostProcessor.java"
public class org.apache.dubbo.config.spring.beans.factory.annotation.AbstractAnnotationBeanPostProcessor$AnnotatedFieldElement extends org.apache.dubbo.config.spring.beans.factory.annotation.AbstractAnnotationBeanPostProcessor$AnnotatedInjectElement {
  protected final java.lang.reflect.Field field;

  final org.apache.dubbo.config.spring.beans.factory.annotation.AbstractAnnotationBeanPostProcessor this$0;

  protected org.apache.dubbo.config.spring.beans.factory.annotation.AbstractAnnotationBeanPostProcessor$AnnotatedFieldElement(org.apache.dubbo.config.spring.beans.factory.annotation.AbstractAnnotationBeanPostProcessor, java.lang.reflect.Field, org.springframework.core.annotation.AnnotationAttributes);
    Code:
       0: aload_0
       1: aload_1
       2: putfield      #1                  // Field this$0:Lorg/apache/dubbo/config/spring/beans/factory/annotation/AbstractAnnotationBeanPostProcessor;
       5: aload_0
       6: aload_1
       7: aload_2
       8: aconst_null
       9: aload_3
      10: invokespecial #2                  // Method org/apache/dubbo/config/spring/beans/factory/annotation/AbstractAnnotationBeanPostProcessor$AnnotatedInjectElement."<init>":(Lorg/apache/dubbo/config/spring/beans/factory/annotation/AbstractAnnotationBeanPostProcessor;Ljava/lang/reflect/Member;Ljava/beans/PropertyDescriptor;Lorg/springframework/core/annotation/AnnotationAttributes;)V
      13: aload_0
      14: aload_2
      15: putfield      #3                  // Field field:Ljava/lang/reflect/Field;
      18: return

  public java.lang.String getPropertyName();
    Code:
       0: aload_0
       1: invokespecial #4                  // Method org/apache/dubbo/config/spring/beans/factory/annotation/AbstractAnnotationBeanPostProcessor$AnnotatedInjectElement.getPropertyName:()Ljava/lang/String;
       4: areturn

  public java.lang.Class getInjectedType() throws java.lang.ClassNotFoundException;
    Code:
       0: aload_0
       1: invokespecial #5                  // Method org/apache/dubbo/config/spring/beans/factory/annotation/AbstractAnnotationBeanPostProcessor$AnnotatedInjectElement.getInjectedType:()Ljava/lang/Class;
       4: areturn
}
