Compiled from "AbstractAnnotationBeanPostProcessor.java"
public abstract class org.apache.dubbo.config.spring.beans.factory.annotation.AbstractAnnotationBeanPostProcessor implements org.springframework.beans.factory.config.InstantiationAwareBeanPostProcessor,org.springframework.beans.factory.support.MergedBeanDefinitionPostProcessor,org.springframework.beans.factory.BeanFactoryAware,org.springframework.beans.factory.BeanClassLoaderAware,org.springframework.context.EnvironmentAware,org.springframework.beans.factory.DisposableBean {
  private static final int CACHE_SIZE;

  private final org.apache.dubbo.common.logger.ErrorTypeAwareLogger logger;

  private final java.lang.Class<? extends java.lang.annotation.Annotation>[] annotationTypes;

  private final java.util.concurrent.ConcurrentMap<java.lang.String, org.apache.dubbo.config.spring.beans.factory.annotation.AbstractAnnotationBeanPostProcessor$AnnotatedInjectionMetadata> injectionMetadataCache;

  private org.springframework.beans.factory.config.ConfigurableListableBeanFactory beanFactory;

  private org.springframework.core.env.Environment environment;

  private java.lang.ClassLoader classLoader;

  private int order;

  public org.apache.dubbo.config.spring.beans.factory.annotation.AbstractAnnotationBeanPostProcessor(java.lang.Class<? extends java.lang.annotation.Annotation>...);
    Code:
       0: aload_0
       1: invokespecial #3                  // Method java/lang/Object."<init>":()V
       4: aload_0
       5: aload_0
       6: invokevirtual #4                  // Method java/lang/Object.getClass:()Ljava/lang/Class;
       9: invokestatic  #5                  // Method org/apache/dubbo/common/logger/LoggerFactory.getErrorTypeAwareLogger:(Ljava/lang/Class;)Lorg/apache/dubbo/common/logger/ErrorTypeAwareLogger;
      12: putfield      #6                  // Field logger:Lorg/apache/dubbo/common/logger/ErrorTypeAwareLogger;
      15: aload_0
      16: new           #7                  // class java/util/concurrent/ConcurrentHashMap
      19: dup
      20: getstatic     #8                  // Field CACHE_SIZE:I
      23: invokespecial #9                  // Method java/util/concurrent/ConcurrentHashMap."<init>":(I)V
      26: putfield      #10                 // Field injectionMetadataCache:Ljava/util/concurrent/ConcurrentMap;
      29: aload_0
      30: ldc           #12                 // int 2147483647
      32: putfield      #13                 // Field order:I
      35: aload_1
      36: ldc           #14                 // String The argument of annotations\' types must not empty
      38: invokestatic  #15                 // Method org/springframework/util/Assert.notEmpty:([Ljava/lang/Object;Ljava/lang/String;)V
      41: aload_0
      42: aload_1
      43: putfield      #16                 // Field annotationTypes:[Ljava/lang/Class;
      46: return

  private static <T> java.util.Collection<T> combine(java.util.Collection<? extends T>...);
    Code:
       0: new           #17                 // class java/util/ArrayList
       3: dup
       4: invokespecial #18                 // Method java/util/ArrayList."<init>":()V
       7: astore_1
       8: aload_0
       9: astore_2
      10: aload_2
      11: arraylength
      12: istore_3
      13: iconst_0
      14: istore        4
      16: iload         4
      18: iload_3
      19: if_icmpge     43
      22: aload_2
      23: iload         4
      25: aaload
      26: astore        5
      28: aload_1
      29: aload         5
      31: invokeinterface #19,  2           // InterfaceMethod java/util/List.addAll:(Ljava/util/Collection;)Z
      36: pop
      37: iinc          4, 1
      40: goto          16
      43: aload_1
      44: areturn

  public final java.lang.Class<? extends java.lang.annotation.Annotation> getAnnotationType();
    Code:
       0: aload_0
       1: getfield      #16                 // Field annotationTypes:[Ljava/lang/Class;
       4: iconst_0
       5: aaload
       6: areturn

  protected final java.lang.Class<? extends java.lang.annotation.Annotation>[] getAnnotationTypes();
    Code:
       0: aload_0
       1: getfield      #16                 // Field annotationTypes:[Ljava/lang/Class;
       4: areturn

  public void setBeanFactory(org.springframework.beans.factory.BeanFactory) throws org.springframework.beans.BeansException;
    Code:
       0: ldc           #20                 // class org/springframework/beans/factory/config/ConfigurableListableBeanFactory
       2: aload_1
       3: ldc           #21                 // String AnnotationInjectedBeanPostProcessor requires a ConfigurableListableBeanFactory
       5: invokestatic  #22                 // Method org/springframework/util/Assert.isInstanceOf:(Ljava/lang/Class;Ljava/lang/Object;Ljava/lang/String;)V
       8: aload_0
       9: aload_1
      10: checkcast     #20                 // class org/springframework/beans/factory/config/ConfigurableListableBeanFactory
      13: putfield      #23                 // Field beanFactory:Lorg/springframework/beans/factory/config/ConfigurableListableBeanFactory;
      16: return

  private java.util.List<org.apache.dubbo.config.spring.beans.factory.annotation.AbstractAnnotationBeanPostProcessor$AnnotatedFieldElement> findFieldAnnotationMetadata(java.lang.Class<?>);
    Code:
       0: new           #24                 // class java/util/LinkedList
       3: dup
       4: invokespecial #25                 // Method java/util/LinkedList."<init>":()V
       7: astore_2
       8: aload_1
       9: aload_0
      10: aload_2
      11: invokedynamic #26,  0             // InvokeDynamic #0:doWith:(Lorg/apache/dubbo/config/spring/beans/factory/annotation/AbstractAnnotationBeanPostProcessor;Ljava/util/List;)Lorg/springframework/util/ReflectionUtils$FieldCallback;
      16: invokestatic  #27                 // Method org/springframework/util/ReflectionUtils.doWithFields:(Ljava/lang/Class;Lorg/springframework/util/ReflectionUtils$FieldCallback;)V
      19: aload_2
      20: areturn

  private java.util.List<org.apache.dubbo.config.spring.beans.factory.annotation.AbstractAnnotationBeanPostProcessor$AnnotatedMethodElement> findAnnotatedMethodMetadata(java.lang.Class<?>);
    Code:
       0: new           #24                 // class java/util/LinkedList
       3: dup
       4: invokespecial #25                 // Method java/util/LinkedList."<init>":()V
       7: astore_2
       8: aload_1
       9: aload_0
      10: aload_1
      11: aload_2
      12: invokedynamic #28,  0             // InvokeDynamic #1:doWith:(Lorg/apache/dubbo/config/spring/beans/factory/annotation/AbstractAnnotationBeanPostProcessor;Ljava/lang/Class;Ljava/util/List;)Lorg/springframework/util/ReflectionUtils$MethodCallback;
      17: invokestatic  #29                 // Method org/springframework/util/ReflectionUtils.doWithMethods:(Ljava/lang/Class;Lorg/springframework/util/ReflectionUtils$MethodCallback;)V
      20: aload_2
      21: areturn

  private org.apache.dubbo.config.spring.beans.factory.annotation.AbstractAnnotationBeanPostProcessor$AnnotatedInjectionMetadata buildAnnotatedMetadata(java.lang.Class<?>);
    Code:
       0: aload_0
       1: aload_1
       2: invokespecial #30                 // Method findFieldAnnotationMetadata:(Ljava/lang/Class;)Ljava/util/List;
       5: astore_2
       6: aload_0
       7: aload_1
       8: invokespecial #31                 // Method findAnnotatedMethodMetadata:(Ljava/lang/Class;)Ljava/util/List;
      11: astore_3
      12: new           #32                 // class org/apache/dubbo/config/spring/beans/factory/annotation/AbstractAnnotationBeanPostProcessor$AnnotatedInjectionMetadata
      15: dup
      16: aload_1
      17: aload_2
      18: aload_3
      19: invokespecial #33                 // Method org/apache/dubbo/config/spring/beans/factory/annotation/AbstractAnnotationBeanPostProcessor$AnnotatedInjectionMetadata."<init>":(Ljava/lang/Class;Ljava/util/Collection;Ljava/util/Collection;)V
      22: areturn

  protected org.apache.dubbo.config.spring.beans.factory.annotation.AbstractAnnotationBeanPostProcessor$AnnotatedInjectionMetadata findInjectionMetadata(java.lang.String, java.lang.Class<?>, org.springframework.beans.PropertyValues);
    Code:
       0: aload_1
       1: invokestatic  #34                 // Method org/springframework/util/StringUtils.hasLength:(Ljava/lang/String;)Z
       4: ifeq          11
       7: aload_1
       8: goto          15
      11: aload_2
      12: invokevirtual #35                 // Method java/lang/Class.getName:()Ljava/lang/String;
      15: astore        4
      17: aload_0
      18: getfield      #10                 // Field injectionMetadataCache:Ljava/util/concurrent/ConcurrentMap;
      21: aload         4
      23: invokeinterface #36,  2           // InterfaceMethod java/util/concurrent/ConcurrentMap.get:(Ljava/lang/Object;)Ljava/lang/Object;
      28: checkcast     #32                 // class org/apache/dubbo/config/spring/beans/factory/annotation/AbstractAnnotationBeanPostProcessor$AnnotatedInjectionMetadata
      31: astore        5
      33: aload_0
      34: aload         5
      36: aload_2
      37: invokespecial #37                 // Method needsRefreshInjectionMetadata:(Lorg/apache/dubbo/config/spring/beans/factory/annotation/AbstractAnnotationBeanPostProcessor$AnnotatedInjectionMetadata;Ljava/lang/Class;)Z
      40: ifeq          165
      43: aload_0
      44: getfield      #10                 // Field injectionMetadataCache:Ljava/util/concurrent/ConcurrentMap;
      47: dup
      48: astore        6
      50: monitorenter
      51: aload_0
      52: getfield      #10                 // Field injectionMetadataCache:Ljava/util/concurrent/ConcurrentMap;
      55: aload         4
      57: invokeinterface #36,  2           // InterfaceMethod java/util/concurrent/ConcurrentMap.get:(Ljava/lang/Object;)Ljava/lang/Object;
      62: checkcast     #32                 // class org/apache/dubbo/config/spring/beans/factory/annotation/AbstractAnnotationBeanPostProcessor$AnnotatedInjectionMetadata
      65: astore        5
      67: aload_0
      68: aload         5
      70: aload_2
      71: invokespecial #37                 // Method needsRefreshInjectionMetadata:(Lorg/apache/dubbo/config/spring/beans/factory/annotation/AbstractAnnotationBeanPostProcessor$AnnotatedInjectionMetadata;Ljava/lang/Class;)Z
      74: ifeq          151
      77: aload         5
      79: ifnull        88
      82: aload         5
      84: aload_3
      85: invokevirtual #38                 // Method org/apache/dubbo/config/spring/beans/factory/annotation/AbstractAnnotationBeanPostProcessor$AnnotatedInjectionMetadata.clear:(Lorg/springframework/beans/PropertyValues;)V
      88: aload_0
      89: aload_2
      90: invokespecial #39                 // Method buildAnnotatedMetadata:(Ljava/lang/Class;)Lorg/apache/dubbo/config/spring/beans/factory/annotation/AbstractAnnotationBeanPostProcessor$AnnotatedInjectionMetadata;
      93: astore        5
      95: aload_0
      96: getfield      #10                 // Field injectionMetadataCache:Ljava/util/concurrent/ConcurrentMap;
      99: aload         4
     101: aload         5
     103: invokeinterface #40,  3           // InterfaceMethod java/util/concurrent/ConcurrentMap.put:(Ljava/lang/Object;Ljava/lang/Object;)Ljava/lang/Object;
     108: pop
     109: goto          151
     112: astore        7
     114: new           #42                 // class java/lang/IllegalStateException
     117: dup
     118: new           #43                 // class java/lang/StringBuilder
     121: dup
     122: invokespecial #44                 // Method java/lang/StringBuilder."<init>":()V
     125: ldc           #45                 // String Failed to introspect object class [
     127: invokevirtual #46                 // Method java/lang/StringBuilder.append:(Ljava/lang/String;)Ljava/lang/StringBuilder;
     130: aload_2
     131: invokevirtual #35                 // Method java/lang/Class.getName:()Ljava/lang/String;
     134: invokevirtual #46                 // Method java/lang/StringBuilder.append:(Ljava/lang/String;)Ljava/lang/StringBuilder;
     137: ldc           #47                 // String ] for annotation metadata: could not find class that it depends on
     139: invokevirtual #46                 // Method java/lang/StringBuilder.append:(Ljava/lang/String;)Ljava/lang/StringBuilder;
     142: invokevirtual #48                 // Method java/lang/StringBuilder.toString:()Ljava/lang/String;
     145: aload         7
     147: invokespecial #49                 // Method java/lang/IllegalStateException."<init>":(Ljava/lang/String;Ljava/lang/Throwable;)V
     150: athrow
     151: aload         6
     153: monitorexit
     154: goto          165
     157: astore        8
     159: aload         6
     161: monitorexit
     162: aload         8
     164: athrow
     165: aload         5
     167: areturn
    Exception table:
       from    to  target type
          88   109   112   Class java/lang/NoClassDefFoundError
          51   154   157   any
         157   162   157   any

  private boolean needsRefreshInjectionMetadata(org.apache.dubbo.config.spring.beans.factory.annotation.AbstractAnnotationBeanPostProcessor$AnnotatedInjectionMetadata, java.lang.Class<?>);
    Code:
       0: aload_1
       1: ifnull        12
       4: aload_1
       5: aload_2
       6: invokevirtual #50                 // Method org/apache/dubbo/config/spring/beans/factory/annotation/AbstractAnnotationBeanPostProcessor$AnnotatedInjectionMetadata.needsRefresh:(Ljava/lang/Class;)Z
       9: ifeq          16
      12: iconst_1
      13: goto          17
      16: iconst_0
      17: ireturn

  public void destroy() throws java.lang.Exception;
    Code:
       0: aload_0
       1: getfield      #10                 // Field injectionMetadataCache:Ljava/util/concurrent/ConcurrentMap;
       4: invokeinterface #51,  1           // InterfaceMethod java/util/concurrent/ConcurrentMap.clear:()V
       9: aload_0
      10: getfield      #6                  // Field logger:Lorg/apache/dubbo/common/logger/ErrorTypeAwareLogger;
      13: invokeinterface #52,  1           // InterfaceMethod org/apache/dubbo/common/logger/ErrorTypeAwareLogger.isInfoEnabled:()Z
      18: ifeq          52
      21: aload_0
      22: getfield      #6                  // Field logger:Lorg/apache/dubbo/common/logger/ErrorTypeAwareLogger;
      25: new           #43                 // class java/lang/StringBuilder
      28: dup
      29: invokespecial #44                 // Method java/lang/StringBuilder."<init>":()V
      32: aload_0
      33: invokevirtual #4                  // Method java/lang/Object.getClass:()Ljava/lang/Class;
      36: invokevirtual #53                 // Method java/lang/StringBuilder.append:(Ljava/lang/Object;)Ljava/lang/StringBuilder;
      39: ldc           #54                 // String  was destroying!
      41: invokevirtual #46                 // Method java/lang/StringBuilder.append:(Ljava/lang/String;)Ljava/lang/StringBuilder;
      44: invokevirtual #48                 // Method java/lang/StringBuilder.toString:()Ljava/lang/String;
      47: invokeinterface #55,  2           // InterfaceMethod org/apache/dubbo/common/logger/ErrorTypeAwareLogger.info:(Ljava/lang/String;)V
      52: return

  public void setBeanClassLoader(java.lang.ClassLoader);
    Code:
       0: aload_0
       1: aload_1
       2: putfield      #56                 // Field classLoader:Ljava/lang/ClassLoader;
       5: return

  public void setEnvironment(org.springframework.core.env.Environment);
    Code:
       0: aload_0
       1: aload_1
       2: putfield      #57                 // Field environment:Lorg/springframework/core/env/Environment;
       5: return

  protected org.springframework.core.env.Environment getEnvironment();
    Code:
       0: aload_0
       1: getfield      #57                 // Field environment:Lorg/springframework/core/env/Environment;
       4: areturn

  protected java.lang.ClassLoader getClassLoader();
    Code:
       0: aload_0
       1: getfield      #56                 // Field classLoader:Ljava/lang/ClassLoader;
       4: areturn

  protected org.springframework.beans.factory.config.ConfigurableListableBeanFactory getBeanFactory();
    Code:
       0: aload_0
       1: getfield      #23                 // Field beanFactory:Lorg/springframework/beans/factory/config/ConfigurableListableBeanFactory;
       4: areturn

  protected java.lang.Object getInjectedObject(org.springframework.core.annotation.AnnotationAttributes, java.lang.Object, java.lang.String, java.lang.Class<?>, org.apache.dubbo.config.spring.beans.factory.annotation.AbstractAnnotationBeanPostProcessor$AnnotatedInjectElement) throws java.lang.Exception;
    Code:
       0: aload_0
       1: aload_1
       2: aload_2
       3: aload_3
       4: aload         4
       6: aload         5
       8: invokevirtual #58                 // Method doGetInjectedBean:(Lorg/springframework/core/annotation/AnnotationAttributes;Ljava/lang/Object;Ljava/lang/String;Ljava/lang/Class;Lorg/apache/dubbo/config/spring/beans/factory/annotation/AbstractAnnotationBeanPostProcessor$AnnotatedInjectElement;)Ljava/lang/Object;
      11: areturn

  protected void prepareInjection(org.apache.dubbo.config.spring.beans.factory.annotation.AbstractAnnotationBeanPostProcessor$AnnotatedInjectionMetadata) throws java.lang.Exception;
    Code:
       0: return

  protected abstract java.lang.Object doGetInjectedBean(org.springframework.core.annotation.AnnotationAttributes, java.lang.Object, java.lang.String, java.lang.Class<?>, org.apache.dubbo.config.spring.beans.factory.annotation.AbstractAnnotationBeanPostProcessor$AnnotatedInjectElement) throws java.lang.Exception;

  public java.lang.Object postProcessBeforeInstantiation(java.lang.Class<?>, java.lang.String) throws org.springframework.beans.BeansException;
    Code:
       0: aconst_null
       1: areturn

  public boolean postProcessAfterInstantiation(java.lang.Object, java.lang.String) throws org.springframework.beans.BeansException;
    Code:
       0: iconst_1
       1: ireturn

  public java.lang.Object postProcessBeforeInitialization(java.lang.Object, java.lang.String) throws org.springframework.beans.BeansException;
    Code:
       0: aload_1
       1: areturn

  public java.lang.Object postProcessAfterInitialization(java.lang.Object, java.lang.String) throws org.springframework.beans.BeansException;
    Code:
       0: aload_1
       1: areturn

  private void lambda$findAnnotatedMethodMetadata$1(java.lang.Class, java.util.List, java.lang.reflect.Method) throws java.lang.IllegalArgumentException, java.lang.IllegalAccessException;
    Code:
       0: aload_3
       1: invokestatic  #59                 // Method org/springframework/core/BridgeMethodResolver.findBridgedMethod:(Ljava/lang/reflect/Method;)Ljava/lang/reflect/Method;
       4: astore        4
       6: aload_3
       7: aload         4
       9: invokestatic  #60                 // Method org/springframework/core/BridgeMethodResolver.isVisibilityBridgeMethodPair:(Ljava/lang/reflect/Method;Ljava/lang/reflect/Method;)Z
      12: ifne          16
      15: return
      16: aload_3
      17: ldc           #61                 // class org/springframework/context/annotation/Bean
      19: invokevirtual #62                 // Method java/lang/reflect/Method.getAnnotation:(Ljava/lang/Class;)Ljava/lang/annotation/Annotation;
      22: ifnull        26
      25: return
      26: aload_0
      27: invokevirtual #63                 // Method getAnnotationTypes:()[Ljava/lang/Class;
      30: astore        5
      32: aload         5
      34: arraylength
      35: istore        6
      37: iconst_0
      38: istore        7
      40: iload         7
      42: iload         6
      44: if_icmpge     223
      47: aload         5
      49: iload         7
      51: aaload
      52: astore        8
      54: aload         4
      56: aload         8
      58: aload_0
      59: invokevirtual #64                 // Method getEnvironment:()Lorg/springframework/core/env/Environment;
      62: iconst_1
      63: iconst_1
      64: iconst_0
      65: anewarray     #65                 // class java/lang/String
      68: invokestatic  #66                 // Method com/alibaba/spring/util/AnnotationUtils.getAnnotationAttributes:(Ljava/lang/reflect/AnnotatedElement;Ljava/lang/Class;Lorg/springframework/core/env/PropertyResolver;ZZ[Ljava/lang/String;)Lorg/springframework/core/annotation/AnnotationAttributes;
      71: astore        9
      73: aload         9
      75: ifnull        217
      78: aload_3
      79: aload_3
      80: aload_1
      81: invokestatic  #67                 // Method org/springframework/util/ClassUtils.getMostSpecificMethod:(Ljava/lang/reflect/Method;Ljava/lang/Class;)Ljava/lang/reflect/Method;
      84: invokevirtual #68                 // Method java/lang/reflect/Method.equals:(Ljava/lang/Object;)Z
      87: ifeq          217
      90: aload_3
      91: invokevirtual #69                 // Method java/lang/reflect/Method.getModifiers:()I
      94: invokestatic  #70                 // Method java/lang/reflect/Modifier.isStatic:(I)Z
      97: ifeq          140
     100: new           #42                 // class java/lang/IllegalStateException
     103: dup
     104: new           #43                 // class java/lang/StringBuilder
     107: dup
     108: invokespecial #44                 // Method java/lang/StringBuilder."<init>":()V
     111: ldc           #71                 // String When using @
     113: invokevirtual #46                 // Method java/lang/StringBuilder.append:(Ljava/lang/String;)Ljava/lang/StringBuilder;
     116: aload         8
     118: invokevirtual #35                 // Method java/lang/Class.getName:()Ljava/lang/String;
     121: invokevirtual #46                 // Method java/lang/StringBuilder.append:(Ljava/lang/String;)Ljava/lang/StringBuilder;
     124: ldc           #72                 // String  to inject interface proxy, it is not supported on static methods:
     126: invokevirtual #46                 // Method java/lang/StringBuilder.append:(Ljava/lang/String;)Ljava/lang/StringBuilder;
     129: aload_3
     130: invokevirtual #53                 // Method java/lang/StringBuilder.append:(Ljava/lang/Object;)Ljava/lang/StringBuilder;
     133: invokevirtual #48                 // Method java/lang/StringBuilder.toString:()Ljava/lang/String;
     136: invokespecial #73                 // Method java/lang/IllegalStateException."<init>":(Ljava/lang/String;)V
     139: athrow
     140: aload_3
     141: invokevirtual #74                 // Method java/lang/reflect/Method.getParameterTypes:()[Ljava/lang/Class;
     144: arraylength
     145: iconst_1
     146: if_icmpeq     189
     149: new           #42                 // class java/lang/IllegalStateException
     152: dup
     153: new           #43                 // class java/lang/StringBuilder
     156: dup
     157: invokespecial #44                 // Method java/lang/StringBuilder."<init>":()V
     160: ldc           #71                 // String When using @
     162: invokevirtual #46                 // Method java/lang/StringBuilder.append:(Ljava/lang/String;)Ljava/lang/StringBuilder;
     165: aload         8
     167: invokevirtual #35                 // Method java/lang/Class.getName:()Ljava/lang/String;
     170: invokevirtual #46                 // Method java/lang/StringBuilder.append:(Ljava/lang/String;)Ljava/lang/StringBuilder;
     173: ldc           #75                 // String  to inject interface proxy, the method must have only one parameter:
     175: invokevirtual #46                 // Method java/lang/StringBuilder.append:(Ljava/lang/String;)Ljava/lang/StringBuilder;
     178: aload_3
     179: invokevirtual #53                 // Method java/lang/StringBuilder.append:(Ljava/lang/Object;)Ljava/lang/StringBuilder;
     182: invokevirtual #48                 // Method java/lang/StringBuilder.toString:()Ljava/lang/String;
     185: invokespecial #73                 // Method java/lang/IllegalStateException."<init>":(Ljava/lang/String;)V
     188: athrow
     189: aload         4
     191: aload_1
     192: invokestatic  #76                 // Method org/springframework/beans/BeanUtils.findPropertyForMethod:(Ljava/lang/reflect/Method;Ljava/lang/Class;)Ljava/beans/PropertyDescriptor;
     195: astore        10
     197: aload_2
     198: new           #77                 // class org/apache/dubbo/config/spring/beans/factory/annotation/AbstractAnnotationBeanPostProcessor$AnnotatedMethodElement
     201: dup
     202: aload_0
     203: aload_3
     204: aload         10
     206: aload         9
     208: invokespecial #78                 // Method org/apache/dubbo/config/spring/beans/factory/annotation/AbstractAnnotationBeanPostProcessor$AnnotatedMethodElement."<init>":(Lorg/apache/dubbo/config/spring/beans/factory/annotation/AbstractAnnotationBeanPostProcessor;Ljava/lang/reflect/Method;Ljava/beans/PropertyDescriptor;Lorg/springframework/core/annotation/AnnotationAttributes;)V
     211: invokeinterface #79,  2           // InterfaceMethod java/util/List.add:(Ljava/lang/Object;)Z
     216: pop
     217: iinc          7, 1
     220: goto          40
     223: return

  private void lambda$findFieldAnnotationMetadata$0(java.util.List, java.lang.reflect.Field) throws java.lang.IllegalArgumentException, java.lang.IllegalAccessException;
    Code:
       0: aload_0
       1: invokevirtual #63                 // Method getAnnotationTypes:()[Ljava/lang/Class;
       4: astore_3
       5: aload_3
       6: arraylength
       7: istore        4
       9: iconst_0
      10: istore        5
      12: iload         5
      14: iload         4
      16: if_icmpge     142
      19: aload_3
      20: iload         5
      22: aaload
      23: astore        6
      25: aload_2
      26: aload         6
      28: aload_0
      29: invokevirtual #64                 // Method getEnvironment:()Lorg/springframework/core/env/Environment;
      32: iconst_1
      33: iconst_1
      34: iconst_0
      35: anewarray     #65                 // class java/lang/String
      38: invokestatic  #66                 // Method com/alibaba/spring/util/AnnotationUtils.getAnnotationAttributes:(Ljava/lang/reflect/AnnotatedElement;Ljava/lang/Class;Lorg/springframework/core/env/PropertyResolver;ZZ[Ljava/lang/String;)Lorg/springframework/core/annotation/AnnotationAttributes;
      41: astore        7
      43: aload         7
      45: ifnull        136
      48: aload_2
      49: invokevirtual #80                 // Method java/lang/reflect/Field.getModifiers:()I
      52: invokestatic  #70                 // Method java/lang/reflect/Modifier.isStatic:(I)Z
      55: ifeq          118
      58: aload_0
      59: getfield      #6                  // Field logger:Lorg/apache/dubbo/common/logger/ErrorTypeAwareLogger;
      62: invokeinterface #81,  1           // InterfaceMethod org/apache/dubbo/common/logger/ErrorTypeAwareLogger.isWarnEnabled:()Z
      67: ifeq          117
      70: aload_0
      71: getfield      #6                  // Field logger:Lorg/apache/dubbo/common/logger/ErrorTypeAwareLogger;
      74: ldc           #82                 // String 5-39
      76: ldc           #83                 // String
      78: ldc           #83                 // String
      80: new           #43                 // class java/lang/StringBuilder
      83: dup
      84: invokespecial #44                 // Method java/lang/StringBuilder."<init>":()V
      87: ldc           #84                 // String @
      89: invokevirtual #46                 // Method java/lang/StringBuilder.append:(Ljava/lang/String;)Ljava/lang/StringBuilder;
      92: aload         6
      94: invokevirtual #35                 // Method java/lang/Class.getName:()Ljava/lang/String;
      97: invokevirtual #46                 // Method java/lang/StringBuilder.append:(Ljava/lang/String;)Ljava/lang/StringBuilder;
     100: ldc           #85                 // String  is not supported on static fields:
     102: invokevirtual #46                 // Method java/lang/StringBuilder.append:(Ljava/lang/String;)Ljava/lang/StringBuilder;
     105: aload_2
     106: invokevirtual #53                 // Method java/lang/StringBuilder.append:(Ljava/lang/Object;)Ljava/lang/StringBuilder;
     109: invokevirtual #48                 // Method java/lang/StringBuilder.toString:()Ljava/lang/String;
     112: invokeinterface #86,  5           // InterfaceMethod org/apache/dubbo/common/logger/ErrorTypeAwareLogger.warn:(Ljava/lang/String;Ljava/lang/String;Ljava/lang/String;Ljava/lang/String;)V
     117: return
     118: aload_1
     119: new           #87                 // class org/apache/dubbo/config/spring/beans/factory/annotation/AbstractAnnotationBeanPostProcessor$AnnotatedFieldElement
     122: dup
     123: aload_0
     124: aload_2
     125: aload         7
     127: invokespecial #88                 // Method org/apache/dubbo/config/spring/beans/factory/annotation/AbstractAnnotationBeanPostProcessor$AnnotatedFieldElement."<init>":(Lorg/apache/dubbo/config/spring/beans/factory/annotation/AbstractAnnotationBeanPostProcessor;Ljava/lang/reflect/Field;Lorg/springframework/core/annotation/AnnotationAttributes;)V
     130: invokeinterface #79,  2           // InterfaceMethod java/util/List.add:(Ljava/lang/Object;)Z
     135: pop
     136: iinc          5, 1
     139: goto          12
     142: return

  static java.util.Collection access$000(java.util.Collection[]);
    Code:
       0: aload_0
       1: invokestatic  #2                  // Method combine:([Ljava/util/Collection;)Ljava/util/Collection;
       4: areturn

  static {};
    Code:
       0: ldc           #83                 // String
       2: bipush        32
       4: invokestatic  #89                 // Method java/lang/Integer.getInteger:(Ljava/lang/String;I)Ljava/lang/Integer;
       7: invokevirtual #90                 // Method java/lang/Integer.intValue:()I
      10: putstatic     #8                  // Field CACHE_SIZE:I
      13: return
}
