Compiled from "AbstractAnnotationBeanPostProcessor.java"
public class org.apache.dubbo.config.spring.beans.factory.annotation.AbstractAnnotationBeanPostProcessor$AnnotatedInjectElement extends org.springframework.beans.factory.annotation.InjectionMetadata$InjectedElement {
  protected final org.springframework.core.annotation.AnnotationAttributes attributes;

  protected volatile java.lang.Object injectedObject;

  private java.lang.Class<?> injectedType;

  final org.apache.dubbo.config.spring.beans.factory.annotation.AbstractAnnotationBeanPostProcessor this$0;

  protected org.apache.dubbo.config.spring.beans.factory.annotation.AbstractAnnotationBeanPostProcessor$AnnotatedInjectElement(org.apache.dubbo.config.spring.beans.factory.annotation.AbstractAnnotationBeanPostProcessor, java.lang.reflect.Member, java.beans.PropertyDescriptor, org.springframework.core.annotation.AnnotationAttributes);
    Code:
       0: aload_0
       1: aload_1
       2: putfield      #1                  // Field this$0:Lorg/apache/dubbo/config/spring/beans/factory/annotation/AbstractAnnotationBeanPostProcessor;
       5: aload_0
       6: aload_2
       7: aload_3
       8: invokespecial #2                  // Method org/springframework/beans/factory/annotation/InjectionMetadata$InjectedElement."<init>":(Ljava/lang/reflect/Member;Ljava/beans/PropertyDescriptor;)V
      11: aload_0
      12: aload         4
      14: putfield      #3                  // Field attributes:Lorg/springframework/core/annotation/AnnotationAttributes;
      17: return

  protected void inject(java.lang.Object, java.lang.String, org.springframework.beans.PropertyValues) throws java.lang.Throwable;
    Code:
       0: aload_0
       1: getfield      #1                  // Field this$0:Lorg/apache/dubbo/config/spring/beans/factory/annotation/AbstractAnnotationBeanPostProcessor;
       4: aload_0
       5: getfield      #3                  // Field attributes:Lorg/springframework/core/annotation/AnnotationAttributes;
       8: aload_1
       9: aload_2
      10: aload_0
      11: invokevirtual #4                  // Method getInjectedType:()Ljava/lang/Class;
      14: aload_0
      15: invokevirtual #5                  // Method org/apache/dubbo/config/spring/beans/factory/annotation/AbstractAnnotationBeanPostProcessor.getInjectedObject:(Lorg/springframework/core/annotation/AnnotationAttributes;Ljava/lang/Object;Ljava/lang/String;Ljava/lang/Class;Lorg/apache/dubbo/config/spring/beans/factory/annotation/AbstractAnnotationBeanPostProcessor$AnnotatedInjectElement;)Ljava/lang/Object;
      18: astore        4
      20: aload_0
      21: getfield      #6                  // Field member:Ljava/lang/reflect/Member;
      24: instanceof    #7                  // class java/lang/reflect/Field
      27: ifeq          55
      30: aload_0
      31: getfield      #6                  // Field member:Ljava/lang/reflect/Member;
      34: checkcast     #7                  // class java/lang/reflect/Field
      37: astore        5
      39: aload         5
      41: invokestatic  #8                  // Method org/springframework/util/ReflectionUtils.makeAccessible:(Ljava/lang/reflect/Field;)V
      44: aload         5
      46: aload_1
      47: aload         4
      49: invokevirtual #9                  // Method java/lang/reflect/Field.set:(Ljava/lang/Object;Ljava/lang/Object;)V
      52: goto          95
      55: aload_0
      56: getfield      #6                  // Field member:Ljava/lang/reflect/Member;
      59: instanceof    #10                 // class java/lang/reflect/Method
      62: ifeq          95
      65: aload_0
      66: getfield      #6                  // Field member:Ljava/lang/reflect/Member;
      69: checkcast     #10                 // class java/lang/reflect/Method
      72: astore        5
      74: aload         5
      76: invokestatic  #11                 // Method org/springframework/util/ReflectionUtils.makeAccessible:(Ljava/lang/reflect/Method;)V
      79: aload         5
      81: aload_1
      82: iconst_1
      83: anewarray     #12                 // class java/lang/Object
      86: dup
      87: iconst_0
      88: aload         4
      90: aastore
      91: invokevirtual #13                 // Method java/lang/reflect/Method.invoke:(Ljava/lang/Object;[Ljava/lang/Object;)Ljava/lang/Object;
      94: pop
      95: return

  public java.lang.Class<?> getInjectedType() throws java.lang.ClassNotFoundException;
    Code:
       0: aload_0
       1: getfield      #14                 // Field injectedType:Ljava/lang/Class;
       4: ifnonnull     85
       7: aload_0
       8: getfield      #15                 // Field isField:Z
      11: ifeq          31
      14: aload_0
      15: aload_0
      16: getfield      #6                  // Field member:Ljava/lang/reflect/Member;
      19: checkcast     #7                  // class java/lang/reflect/Field
      22: invokevirtual #16                 // Method java/lang/reflect/Field.getType:()Ljava/lang/Class;
      25: putfield      #14                 // Field injectedType:Ljava/lang/Class;
      28: goto          85
      31: aload_0
      32: getfield      #17                 // Field pd:Ljava/beans/PropertyDescriptor;
      35: ifnull        46
      38: aload_0
      39: getfield      #17                 // Field pd:Ljava/beans/PropertyDescriptor;
      42: invokevirtual #18                 // Method java/beans/PropertyDescriptor.getPropertyType:()Ljava/lang/Class;
      45: areturn
      46: aload_0
      47: getfield      #6                  // Field member:Ljava/lang/reflect/Member;
      50: checkcast     #10                 // class java/lang/reflect/Method
      53: astore_1
      54: aload_1
      55: invokevirtual #19                 // Method java/lang/reflect/Method.getParameterTypes:()[Ljava/lang/Class;
      58: arraylength
      59: ifle          75
      62: aload_0
      63: aload_1
      64: invokevirtual #19                 // Method java/lang/reflect/Method.getParameterTypes:()[Ljava/lang/Class;
      67: iconst_0
      68: aaload
      69: putfield      #14                 // Field injectedType:Ljava/lang/Class;
      72: goto          85
      75: new           #20                 // class java/lang/IllegalStateException
      78: dup
      79: ldc           #21                 // String get injected type failed
      81: invokespecial #22                 // Method java/lang/IllegalStateException."<init>":(Ljava/lang/String;)V
      84: athrow
      85: aload_0
      86: getfield      #14                 // Field injectedType:Ljava/lang/Class;
      89: areturn

  public java.lang.String getPropertyName();
    Code:
       0: aload_0
       1: getfield      #6                  // Field member:Ljava/lang/reflect/Member;
       4: instanceof    #7                  // class java/lang/reflect/Field
       7: ifeq          23
      10: aload_0
      11: getfield      #6                  // Field member:Ljava/lang/reflect/Member;
      14: checkcast     #7                  // class java/lang/reflect/Field
      17: astore_1
      18: aload_1
      19: invokevirtual #23                 // Method java/lang/reflect/Field.getName:()Ljava/lang/String;
      22: areturn
      23: aload_0
      24: getfield      #17                 // Field pd:Ljava/beans/PropertyDescriptor;
      27: ifnull        38
      30: aload_0
      31: getfield      #17                 // Field pd:Ljava/beans/PropertyDescriptor;
      34: invokevirtual #24                 // Method java/beans/PropertyDescriptor.getName:()Ljava/lang/String;
      37: areturn
      38: aload_0
      39: getfield      #6                  // Field member:Ljava/lang/reflect/Member;
      42: checkcast     #10                 // class java/lang/reflect/Method
      45: astore_1
      46: aload_1
      47: invokevirtual #25                 // Method java/lang/reflect/Method.getName:()Ljava/lang/String;
      50: areturn
}
