Compiled from "AbstractAnnotationBeanPostProcessor.java"
public class org.apache.dubbo.config.spring.beans.factory.annotation.AbstractAnnotationBeanPostProcessor$AnnotatedInjectionMetadata extends org.springframework.beans.factory.annotation.InjectionMetadata {
  private java.lang.Class<?> targetClass;

  private final java.util.Collection<org.apache.dubbo.config.spring.beans.factory.annotation.AbstractAnnotationBeanPostProcessor$AnnotatedFieldElement> fieldElements;

  private final java.util.Collection<org.apache.dubbo.config.spring.beans.factory.annotation.AbstractAnnotationBeanPostProcessor$AnnotatedMethodElement> methodElements;

  public org.apache.dubbo.config.spring.beans.factory.annotation.AbstractAnnotationBeanPostProcessor$AnnotatedInjectionMetadata(java.lang.Class<?>, java.util.Collection<org.apache.dubbo.config.spring.beans.factory.annotation.AbstractAnnotationBeanPostProcessor$AnnotatedFieldElement>, java.util.Collection<org.apache.dubbo.config.spring.beans.factory.annotation.AbstractAnnotationBeanPostProcessor$AnnotatedMethodElement>);
    Code:
       0: aload_0
       1: aload_1
       2: iconst_2
       3: anewarray     #1                  // class java/util/Collection
       6: dup
       7: iconst_0
       8: aload_2
       9: aastore
      10: dup
      11: iconst_1
      12: aload_3
      13: aastore
      14: invokestatic  #2                  // Method org/apache/dubbo/config/spring/beans/factory/annotation/AbstractAnnotationBeanPostProcessor.access$000:([Ljava/util/Collection;)Ljava/util/Collection;
      17: invokespecial #3                  // Method org/springframework/beans/factory/annotation/InjectionMetadata."<init>":(Ljava/lang/Class;Ljava/util/Collection;)V
      20: aload_0
      21: aload_1
      22: putfield      #4                  // Field targetClass:Ljava/lang/Class;
      25: aload_0
      26: aload_2
      27: putfield      #5                  // Field fieldElements:Ljava/util/Collection;
      30: aload_0
      31: aload_3
      32: putfield      #6                  // Field methodElements:Ljava/util/Collection;
      35: return

  public java.util.Collection<org.apache.dubbo.config.spring.beans.factory.annotation.AbstractAnnotationBeanPostProcessor$AnnotatedFieldElement> getFieldElements();
    Code:
       0: aload_0
       1: getfield      #5                  // Field fieldElements:Ljava/util/Collection;
       4: areturn

  public java.util.Collection<org.apache.dubbo.config.spring.beans.factory.annotation.AbstractAnnotationBeanPostProcessor$AnnotatedMethodElement> getMethodElements();
    Code:
       0: aload_0
       1: getfield      #6                  // Field methodElements:Ljava/util/Collection;
       4: areturn

  protected boolean needsRefresh(java.lang.Class<?>);
    Code:
       0: aload_0
       1: getfield      #4                  // Field targetClass:Ljava/lang/Class;
       4: aload_1
       5: if_acmpne     10
       8: iconst_0
       9: ireturn
      10: aload_0
      11: getfield      #4                  // Field targetClass:Ljava/lang/Class;
      14: aload_1
      15: invokevirtual #7                  // Method java/lang/Class.isAssignableFrom:(Ljava/lang/Class;)Z
      18: ifeq          35
      21: aload_1
      22: invokevirtual #8                  // Method java/lang/Class.getName:()Ljava/lang/String;
      25: ldc           #9                  // String $$EnhancerBySpringCGLIB$$
      27: invokevirtual #10                 // Method java/lang/String.contains:(Ljava/lang/CharSequence;)Z
      30: ifeq          35
      33: iconst_0
      34: ireturn
      35: iconst_1
      36: ireturn
}
