Compiled from "AnnotationPropertyValuesAdapter.java"
public class org.apache.dubbo.config.spring.beans.factory.annotation.AnnotationPropertyValuesAdapter implements org.springframework.beans.PropertyValues {
  private final org.springframework.beans.PropertyValues delegate;

  public org.apache.dubbo.config.spring.beans.factory.annotation.AnnotationPropertyValuesAdapter(java.util.Map<java.lang.String, java.lang.Object>, org.springframework.core.env.PropertyResolver, java.lang.String...);
    Code:
       0: aload_0
       1: invokespecial #1                  // Method java/lang/Object."<init>":()V
       4: aload_0
       5: new           #2                  // class org/springframework/beans/MutablePropertyValues
       8: dup
       9: aload_1
      10: aload_2
      11: aload_3
      12: invokestatic  #3                  // Method com/alibaba/spring/util/AnnotationUtils.getAttributes:(Ljava/util/Map;Lorg/springframework/core/env/PropertyResolver;[Ljava/lang/String;)Ljava/util/Map;
      15: invokespecial #4                  // Method org/springframework/beans/MutablePropertyValues."<init>":(Ljava/util/Map;)V
      18: putfield      #5                  // Field delegate:Lorg/springframework/beans/PropertyValues;
      21: return

  public org.apache.dubbo.config.spring.beans.factory.annotation.AnnotationPropertyValuesAdapter(java.lang.annotation.Annotation, org.springframework.core.env.PropertyResolver, boolean, java.lang.String...);
    Code:
       0: aload_0
       1: invokespecial #1                  // Method java/lang/Object."<init>":()V
       4: aload_0
       5: new           #2                  // class org/springframework/beans/MutablePropertyValues
       8: dup
       9: aload_1
      10: aload_2
      11: iload_3
      12: aload         4
      14: invokestatic  #6                  // Method com/alibaba/spring/util/AnnotationUtils.getAttributes:(Ljava/lang/annotation/Annotation;Lorg/springframework/core/env/PropertyResolver;Z[Ljava/lang/String;)Ljava/util/Map;
      17: invokespecial #4                  // Method org/springframework/beans/MutablePropertyValues."<init>":(Ljava/util/Map;)V
      20: putfield      #5                  // Field delegate:Lorg/springframework/beans/PropertyValues;
      23: return

  public org.apache.dubbo.config.spring.beans.factory.annotation.AnnotationPropertyValuesAdapter(java.lang.annotation.Annotation, org.springframework.core.env.PropertyResolver, java.lang.String...);
    Code:
       0: aload_0
       1: aload_1
       2: aload_2
       3: iconst_1
       4: aload_3
       5: invokespecial #7                  // Method "<init>":(Ljava/lang/annotation/Annotation;Lorg/springframework/core/env/PropertyResolver;Z[Ljava/lang/String;)V
       8: return

  public org.springframework.beans.PropertyValue[] getPropertyValues();
    Code:
       0: aload_0
       1: getfield      #5                  // Field delegate:Lorg/springframework/beans/PropertyValues;
       4: invokeinterface #8,  1            // InterfaceMethod org/springframework/beans/PropertyValues.getPropertyValues:()[Lorg/springframework/beans/PropertyValue;
       9: areturn

  public org.springframework.beans.PropertyValue getPropertyValue(java.lang.String);
    Code:
       0: aload_0
       1: getfield      #5                  // Field delegate:Lorg/springframework/beans/PropertyValues;
       4: aload_1
       5: invokeinterface #9,  2            // InterfaceMethod org/springframework/beans/PropertyValues.getPropertyValue:(Ljava/lang/String;)Lorg/springframework/beans/PropertyValue;
      10: areturn

  public org.springframework.beans.PropertyValues changesSince(org.springframework.beans.PropertyValues);
    Code:
       0: aload_0
       1: getfield      #5                  // Field delegate:Lorg/springframework/beans/PropertyValues;
       4: aload_1
       5: invokeinterface #10,  2           // InterfaceMethod org/springframework/beans/PropertyValues.changesSince:(Lorg/springframework/beans/PropertyValues;)Lorg/springframework/beans/PropertyValues;
      10: areturn

  public boolean contains(java.lang.String);
    Code:
       0: aload_0
       1: getfield      #5                  // Field delegate:Lorg/springframework/beans/PropertyValues;
       4: aload_1
       5: invokeinterface #11,  2           // InterfaceMethod org/springframework/beans/PropertyValues.contains:(Ljava/lang/String;)Z
      10: ireturn

  public boolean isEmpty();
    Code:
       0: aload_0
       1: getfield      #5                  // Field delegate:Lorg/springframework/beans/PropertyValues;
       4: invokeinterface #12,  1           // InterfaceMethod org/springframework/beans/PropertyValues.isEmpty:()Z
       9: ireturn
}
