Compiled from "DubboConfigAliasPostProcessor.java"
public class org.apache.dubbo.config.spring.beans.factory.annotation.DubboConfigAliasPostProcessor implements org.springframework.beans.factory.support.BeanDefinitionRegistryPostProcessor,org.springframework.beans.factory.config.BeanPostProcessor {
  public static final java.lang.String BEAN_NAME;

  private org.springframework.beans.factory.support.BeanDefinitionRegistry registry;

  public org.apache.dubbo.config.spring.beans.factory.annotation.DubboConfigAliasPostProcessor();
    Code:
       0: aload_0
       1: invokespecial #1                  // Method java/lang/Object."<init>":()V
       4: return

  public void postProcessBeanDefinitionRegistry(org.springframework.beans.factory.support.BeanDefinitionRegistry) throws org.springframework.beans.BeansException;
    Code:
       0: aload_0
       1: aload_1
       2: putfield      #2                  // Field registry:Lorg/springframework/beans/factory/support/BeanDefinitionRegistry;
       5: return

  public void postProcessBeanFactory(org.springframework.beans.factory.config.ConfigurableListableBeanFactory) throws org.springframework.beans.BeansException;
    Code:
       0: return

  public java.lang.Object postProcessBeforeInitialization(java.lang.Object, java.lang.String) throws org.springframework.beans.BeansException;
    Code:
       0: aload_1
       1: areturn

  public java.lang.Object postProcessAfterInitialization(java.lang.Object, java.lang.String) throws org.springframework.beans.BeansException;
    Code:
       0: aload_1
       1: instanceof    #3                  // class org/apache/dubbo/config/AbstractConfig
       4: ifeq          53
       7: aload_1
       8: checkcast     #3                  // class org/apache/dubbo/config/AbstractConfig
      11: invokevirtual #4                  // Method org/apache/dubbo/config/AbstractConfig.getId:()Ljava/lang/String;
      14: astore_3
      15: aload_3
      16: invokestatic  #5                  // Method org/springframework/util/StringUtils.hasText:(Ljava/lang/String;)Z
      19: ifeq          53
      22: aload_3
      23: aload_2
      24: invokestatic  #6                  // Method org/springframework/util/ObjectUtils.nullSafeEquals:(Ljava/lang/Object;Ljava/lang/Object;)Z
      27: ifne          53
      30: aload_0
      31: getfield      #2                  // Field registry:Lorg/springframework/beans/factory/support/BeanDefinitionRegistry;
      34: aload_2
      35: aload_3
      36: invokestatic  #7                  // Method com/alibaba/spring/util/BeanRegistrar.hasAlias:(Lorg/springframework/core/AliasRegistry;Ljava/lang/String;Ljava/lang/String;)Z
      39: ifne          53
      42: aload_0
      43: getfield      #2                  // Field registry:Lorg/springframework/beans/factory/support/BeanDefinitionRegistry;
      46: aload_2
      47: aload_3
      48: invokeinterface #8,  3            // InterfaceMethod org/springframework/beans/factory/support/BeanDefinitionRegistry.registerAlias:(Ljava/lang/String;Ljava/lang/String;)V
      53: aload_1
      54: areturn
}
