Compiled from "ServiceAnnotationPostProcessor.java"
public class org.apache.dubbo.config.spring.beans.factory.annotation.ServiceAnnotationPostProcessor implements org.springframework.beans.factory.support.BeanDefinitionRegistryPostProcessor,org.springframework.context.EnvironmentAware,org.springframework.context.ResourceLoaderAware,org.springframework.beans.factory.BeanClassLoaderAware,org.springframework.context.ApplicationContextAware,org.springframework.beans.factory.InitializingBean {
  public static final java.lang.String BEAN_NAME;

  private static final java.util.List<java.lang.Class<? extends java.lang.annotation.Annotation>> serviceAnnotationTypes;

  private final org.apache.dubbo.common.logger.ErrorTypeAwareLogger logger;

  protected final java.util.Set<java.lang.String> packagesToScan;

  private java.util.Set<java.lang.String> resolvedPackagesToScan;

  private org.springframework.core.env.Environment environment;

  private org.springframework.core.io.ResourceLoader resourceLoader;

  private java.lang.ClassLoader classLoader;

  private org.springframework.beans.factory.support.BeanDefinitionRegistry registry;

  private org.apache.dubbo.config.spring.beans.factory.annotation.ServicePackagesHolder servicePackagesHolder;

  private volatile boolean scanned;

  public org.apache.dubbo.config.spring.beans.factory.annotation.ServiceAnnotationPostProcessor(java.lang.String...);
    Code:
       0: aload_0
       1: aload_1
       2: invokestatic  #4                  // Method java/util/Arrays.asList:([Ljava/lang/Object;)Ljava/util/List;
       5: invokespecial #5                  // Method "<init>":(Ljava/util/Collection;)V
       8: return

  public org.apache.dubbo.config.spring.beans.factory.annotation.ServiceAnnotationPostProcessor(java.util.Collection<java.lang.String>);
    Code:
       0: aload_0
       1: new           #6                  // class java/util/LinkedHashSet
       4: dup
       5: aload_1
       6: invokespecial #7                  // Method java/util/LinkedHashSet."<init>":(Ljava/util/Collection;)V
       9: invokespecial #8                  // Method "<init>":(Ljava/util/Set;)V
      12: return

  public org.apache.dubbo.config.spring.beans.factory.annotation.ServiceAnnotationPostProcessor(java.util.Set<java.lang.String>);
    Code:
       0: aload_0
       1: invokespecial #9                  // Method java/lang/Object."<init>":()V
       4: aload_0
       5: aload_0
       6: invokevirtual #10                 // Method java/lang/Object.getClass:()Ljava/lang/Class;
       9: invokestatic  #11                 // Method org/apache/dubbo/common/logger/LoggerFactory.getErrorTypeAwareLogger:(Ljava/lang/Class;)Lorg/apache/dubbo/common/logger/ErrorTypeAwareLogger;
      12: putfield      #12                 // Field logger:Lorg/apache/dubbo/common/logger/ErrorTypeAwareLogger;
      15: aload_0
      16: iconst_0
      17: putfield      #13                 // Field scanned:Z
      20: aload_0
      21: aload_1
      22: putfield      #14                 // Field packagesToScan:Ljava/util/Set;
      25: return

  public void afterPropertiesSet() throws java.lang.Exception;
    Code:
       0: aload_0
       1: aload_0
       2: aload_0
       3: getfield      #14                 // Field packagesToScan:Ljava/util/Set;
       6: invokespecial #15                 // Method resolvePackagesToScan:(Ljava/util/Set;)Ljava/util/Set;
       9: putfield      #16                 // Field resolvedPackagesToScan:Ljava/util/Set;
      12: return

  public void postProcessBeanDefinitionRegistry(org.springframework.beans.factory.support.BeanDefinitionRegistry) throws org.springframework.beans.BeansException;
    Code:
       0: aload_0
       1: aload_1
       2: putfield      #17                 // Field registry:Lorg/springframework/beans/factory/support/BeanDefinitionRegistry;
       5: aload_0
       6: aload_0
       7: getfield      #16                 // Field resolvedPackagesToScan:Ljava/util/Set;
      10: aload_1
      11: invokespecial #18                 // Method scanServiceBeans:(Ljava/util/Set;Lorg/springframework/beans/factory/support/BeanDefinitionRegistry;)V
      14: return

  public void postProcessBeanFactory(org.springframework.beans.factory.config.ConfigurableListableBeanFactory) throws org.springframework.beans.BeansException;
    Code:
       0: aload_0
       1: getfield      #17                 // Field registry:Lorg/springframework/beans/factory/support/BeanDefinitionRegistry;
       4: ifnonnull     15
       7: aload_0
       8: aload_1
       9: checkcast     #19                 // class org/springframework/beans/factory/support/BeanDefinitionRegistry
      12: putfield      #17                 // Field registry:Lorg/springframework/beans/factory/support/BeanDefinitionRegistry;
      15: aload_1
      16: invokeinterface #20,  1           // InterfaceMethod org/springframework/beans/factory/config/ConfigurableListableBeanFactory.getBeanDefinitionNames:()[Ljava/lang/String;
      21: astore_2
      22: aload_2
      23: astore_3
      24: aload_3
      25: arraylength
      26: istore        4
      28: iconst_0
      29: istore        5
      31: iload         5
      33: iload         4
      35: if_icmpge     86
      38: aload_3
      39: iload         5
      41: aaload
      42: astore        6
      44: aload_1
      45: aload         6
      47: invokeinterface #21,  2           // InterfaceMethod org/springframework/beans/factory/config/ConfigurableListableBeanFactory.getBeanDefinition:(Ljava/lang/String;)Lorg/springframework/beans/factory/config/BeanDefinition;
      52: astore        7
      54: aload_0
      55: aload         7
      57: invokespecial #22                 // Method getServiceAnnotationAttributes:(Lorg/springframework/beans/factory/config/BeanDefinition;)Ljava/util/Map;
      60: astore        8
      62: aload         8
      64: ifnull        80
      67: aload_0
      68: aload         6
      70: aload         7
      72: checkcast     #23                 // class org/springframework/beans/factory/annotation/AnnotatedBeanDefinition
      75: aload         8
      77: invokespecial #24                 // Method processAnnotatedBeanDefinition:(Ljava/lang/String;Lorg/springframework/beans/factory/annotation/AnnotatedBeanDefinition;Ljava/util/Map;)V
      80: iinc          5, 1
      83: goto          31
      86: aload_0
      87: getfield      #13                 // Field scanned:Z
      90: ifne          105
      93: aload_0
      94: aload_0
      95: getfield      #16                 // Field resolvedPackagesToScan:Ljava/util/Set;
      98: aload_0
      99: getfield      #17                 // Field registry:Lorg/springframework/beans/factory/support/BeanDefinitionRegistry;
     102: invokespecial #18                 // Method scanServiceBeans:(Ljava/util/Set;Lorg/springframework/beans/factory/support/BeanDefinitionRegistry;)V
     105: return

  private void scanServiceBeans(java.util.Set<java.lang.String>, org.springframework.beans.factory.support.BeanDefinitionRegistry);
    Code:
       0: aload_0
       1: iconst_1
       2: putfield      #13                 // Field scanned:Z
       5: aload_1
       6: invokestatic  #25                 // Method org/springframework/util/CollectionUtils.isEmpty:(Ljava/util/Collection;)Z
       9: ifeq          42
      12: aload_0
      13: getfield      #12                 // Field logger:Lorg/apache/dubbo/common/logger/ErrorTypeAwareLogger;
      16: invokeinterface #26,  1           // InterfaceMethod org/apache/dubbo/common/logger/ErrorTypeAwareLogger.isWarnEnabled:()Z
      21: ifeq          41
      24: aload_0
      25: getfield      #12                 // Field logger:Lorg/apache/dubbo/common/logger/ErrorTypeAwareLogger;
      28: ldc           #27                 // String 5-29
      30: ldc           #28                 // String
      32: ldc           #28                 // String
      34: ldc           #29                 // String packagesToScan is empty , ServiceBean registry will be ignored!
      36: invokeinterface #30,  5           // InterfaceMethod org/apache/dubbo/common/logger/ErrorTypeAwareLogger.warn:(Ljava/lang/String;Ljava/lang/String;Ljava/lang/String;Ljava/lang/String;)V
      41: return
      42: new           #31                 // class org/apache/dubbo/config/spring/context/annotation/DubboClassPathBeanDefinitionScanner
      45: dup
      46: aload_2
      47: aload_0
      48: getfield      #32                 // Field environment:Lorg/springframework/core/env/Environment;
      51: aload_0
      52: getfield      #33                 // Field resourceLoader:Lorg/springframework/core/io/ResourceLoader;
      55: invokespecial #34                 // Method org/apache/dubbo/config/spring/context/annotation/DubboClassPathBeanDefinitionScanner."<init>":(Lorg/springframework/beans/factory/support/BeanDefinitionRegistry;Lorg/springframework/core/env/Environment;Lorg/springframework/core/io/ResourceLoader;)V
      58: astore_3
      59: aload_0
      60: aload_2
      61: invokespecial #35                 // Method resolveBeanNameGenerator:(Lorg/springframework/beans/factory/support/BeanDefinitionRegistry;)Lorg/springframework/beans/factory/support/BeanNameGenerator;
      64: astore        4
      66: aload_3
      67: aload         4
      69: invokevirtual #36                 // Method org/apache/dubbo/config/spring/context/annotation/DubboClassPathBeanDefinitionScanner.setBeanNameGenerator:(Lorg/springframework/beans/factory/support/BeanNameGenerator;)V
      72: getstatic     #37                 // Field serviceAnnotationTypes:Ljava/util/List;
      75: invokeinterface #38,  1           // InterfaceMethod java/util/List.iterator:()Ljava/util/Iterator;
      80: astore        5
      82: aload         5
      84: invokeinterface #39,  1           // InterfaceMethod java/util/Iterator.hasNext:()Z
      89: ifeq          120
      92: aload         5
      94: invokeinterface #40,  1           // InterfaceMethod java/util/Iterator.next:()Ljava/lang/Object;
      99: checkcast     #41                 // class java/lang/Class
     102: astore        6
     104: aload_3
     105: new           #42                 // class org/springframework/core/type/filter/AnnotationTypeFilter
     108: dup
     109: aload         6
     111: invokespecial #43                 // Method org/springframework/core/type/filter/AnnotationTypeFilter."<init>":(Ljava/lang/Class;)V
     114: invokevirtual #44                 // Method org/apache/dubbo/config/spring/context/annotation/DubboClassPathBeanDefinitionScanner.addIncludeFilter:(Lorg/springframework/core/type/filter/TypeFilter;)V
     117: goto          82
     120: new           #45                 // class org/apache/dubbo/config/spring/beans/factory/annotation/ServiceAnnotationPostProcessor$ScanExcludeFilter
     123: dup
     124: aload_0
     125: aconst_null
     126: invokespecial #46                 // Method org/apache/dubbo/config/spring/beans/factory/annotation/ServiceAnnotationPostProcessor$ScanExcludeFilter."<init>":(Lorg/apache/dubbo/config/spring/beans/factory/annotation/ServiceAnnotationPostProcessor;Lorg/apache/dubbo/config/spring/beans/factory/annotation/ServiceAnnotationPostProcessor$1;)V
     129: astore        5
     131: aload_3
     132: aload         5
     134: invokevirtual #47                 // Method org/apache/dubbo/config/spring/context/annotation/DubboClassPathBeanDefinitionScanner.addExcludeFilter:(Lorg/springframework/core/type/filter/TypeFilter;)V
     137: aload_1
     138: invokeinterface #48,  1           // InterfaceMethod java/util/Set.iterator:()Ljava/util/Iterator;
     143: astore        6
     145: aload         6
     147: invokeinterface #39,  1           // InterfaceMethod java/util/Iterator.hasNext:()Z
     152: ifeq          523
     155: aload         6
     157: invokeinterface #40,  1           // InterfaceMethod java/util/Iterator.next:()Ljava/lang/Object;
     162: checkcast     #49                 // class java/lang/String
     165: astore        7
     167: aload_0
     168: getfield      #3                  // Field servicePackagesHolder:Lorg/apache/dubbo/config/spring/beans/factory/annotation/ServicePackagesHolder;
     171: aload         7
     173: invokevirtual #50                 // Method org/apache/dubbo/config/spring/beans/factory/annotation/ServicePackagesHolder.isPackageScanned:(Ljava/lang/String;)Z
     176: ifeq          223
     179: aload_0
     180: getfield      #12                 // Field logger:Lorg/apache/dubbo/common/logger/ErrorTypeAwareLogger;
     183: invokeinterface #51,  1           // InterfaceMethod org/apache/dubbo/common/logger/ErrorTypeAwareLogger.isInfoEnabled:()Z
     188: ifeq          145
     191: aload_0
     192: getfield      #12                 // Field logger:Lorg/apache/dubbo/common/logger/ErrorTypeAwareLogger;
     195: new           #52                 // class java/lang/StringBuilder
     198: dup
     199: invokespecial #53                 // Method java/lang/StringBuilder."<init>":()V
     202: ldc           #54                 // String Ignore package who has already bean scanned:
     204: invokevirtual #55                 // Method java/lang/StringBuilder.append:(Ljava/lang/String;)Ljava/lang/StringBuilder;
     207: aload         7
     209: invokevirtual #55                 // Method java/lang/StringBuilder.append:(Ljava/lang/String;)Ljava/lang/StringBuilder;
     212: invokevirtual #56                 // Method java/lang/StringBuilder.toString:()Ljava/lang/String;
     215: invokeinterface #57,  2           // InterfaceMethod org/apache/dubbo/common/logger/ErrorTypeAwareLogger.info:(Ljava/lang/String;)V
     220: goto          145
     223: aload_3
     224: iconst_1
     225: anewarray     #49                 // class java/lang/String
     228: dup
     229: iconst_0
     230: aload         7
     232: aastore
     233: invokevirtual #58                 // Method org/apache/dubbo/config/spring/context/annotation/DubboClassPathBeanDefinitionScanner.scan:([Ljava/lang/String;)I
     236: pop
     237: aload_0
     238: aload_3
     239: aload         7
     241: aload_2
     242: aload         4
     244: invokespecial #59                 // Method findServiceBeanDefinitionHolders:(Lorg/springframework/context/annotation/ClassPathBeanDefinitionScanner;Ljava/lang/String;Lorg/springframework/beans/factory/support/BeanDefinitionRegistry;Lorg/springframework/beans/factory/support/BeanNameGenerator;)Ljava/util/Set;
     247: astore        8
     249: aload         8
     251: invokestatic  #25                 // Method org/springframework/util/CollectionUtils.isEmpty:(Ljava/util/Collection;)Z
     254: ifne          451
     257: aload_0
     258: getfield      #12                 // Field logger:Lorg/apache/dubbo/common/logger/ErrorTypeAwareLogger;
     261: invokeinterface #51,  1           // InterfaceMethod org/apache/dubbo/common/logger/ErrorTypeAwareLogger.isInfoEnabled:()Z
     266: ifeq          391
     269: new           #60                 // class java/util/ArrayList
     272: dup
     273: aload         8
     275: invokeinterface #61,  1           // InterfaceMethod java/util/Set.size:()I
     280: invokespecial #62                 // Method java/util/ArrayList."<init>":(I)V
     283: astore        9
     285: aload         8
     287: invokeinterface #48,  1           // InterfaceMethod java/util/Set.iterator:()Ljava/util/Iterator;
     292: astore        10
     294: aload         10
     296: invokeinterface #39,  1           // InterfaceMethod java/util/Iterator.hasNext:()Z
     301: ifeq          337
     304: aload         10
     306: invokeinterface #40,  1           // InterfaceMethod java/util/Iterator.next:()Ljava/lang/Object;
     311: checkcast     #63                 // class org/springframework/beans/factory/config/BeanDefinitionHolder
     314: astore        11
     316: aload         9
     318: aload         11
     320: invokevirtual #64                 // Method org/springframework/beans/factory/config/BeanDefinitionHolder.getBeanDefinition:()Lorg/springframework/beans/factory/config/BeanDefinition;
     323: invokeinterface #65,  1           // InterfaceMethod org/springframework/beans/factory/config/BeanDefinition.getBeanClassName:()Ljava/lang/String;
     328: invokeinterface #66,  2           // InterfaceMethod java/util/List.add:(Ljava/lang/Object;)Z
     333: pop
     334: goto          294
     337: aload_0
     338: getfield      #12                 // Field logger:Lorg/apache/dubbo/common/logger/ErrorTypeAwareLogger;
     341: new           #52                 // class java/lang/StringBuilder
     344: dup
     345: invokespecial #53                 // Method java/lang/StringBuilder."<init>":()V
     348: ldc           #67                 // String Found
     350: invokevirtual #55                 // Method java/lang/StringBuilder.append:(Ljava/lang/String;)Ljava/lang/StringBuilder;
     353: aload         8
     355: invokeinterface #61,  1           // InterfaceMethod java/util/Set.size:()I
     360: invokevirtual #68                 // Method java/lang/StringBuilder.append:(I)Ljava/lang/StringBuilder;
     363: ldc           #69                 // String  classes annotated by Dubbo @Service under package [
     365: invokevirtual #55                 // Method java/lang/StringBuilder.append:(Ljava/lang/String;)Ljava/lang/StringBuilder;
     368: aload         7
     370: invokevirtual #55                 // Method java/lang/StringBuilder.append:(Ljava/lang/String;)Ljava/lang/StringBuilder;
     373: ldc           #70                 // String ]:
     375: invokevirtual #55                 // Method java/lang/StringBuilder.append:(Ljava/lang/String;)Ljava/lang/StringBuilder;
     378: aload         9
     380: invokevirtual #71                 // Method java/lang/StringBuilder.append:(Ljava/lang/Object;)Ljava/lang/StringBuilder;
     383: invokevirtual #56                 // Method java/lang/StringBuilder.toString:()Ljava/lang/String;
     386: invokeinterface #57,  2           // InterfaceMethod org/apache/dubbo/common/logger/ErrorTypeAwareLogger.info:(Ljava/lang/String;)V
     391: aload         8
     393: invokeinterface #48,  1           // InterfaceMethod java/util/Set.iterator:()Ljava/util/Iterator;
     398: astore        9
     400: aload         9
     402: invokeinterface #39,  1           // InterfaceMethod java/util/Iterator.hasNext:()Z
     407: ifeq          448
     410: aload         9
     412: invokeinterface #40,  1           // InterfaceMethod java/util/Iterator.next:()Ljava/lang/Object;
     417: checkcast     #63                 // class org/springframework/beans/factory/config/BeanDefinitionHolder
     420: astore        10
     422: aload_0
     423: aload         10
     425: invokespecial #72                 // Method processScannedBeanDefinition:(Lorg/springframework/beans/factory/config/BeanDefinitionHolder;)V
     428: aload_0
     429: getfield      #3                  // Field servicePackagesHolder:Lorg/apache/dubbo/config/spring/beans/factory/annotation/ServicePackagesHolder;
     432: aload         10
     434: invokevirtual #64                 // Method org/springframework/beans/factory/config/BeanDefinitionHolder.getBeanDefinition:()Lorg/springframework/beans/factory/config/BeanDefinition;
     437: invokeinterface #65,  1           // InterfaceMethod org/springframework/beans/factory/config/BeanDefinition.getBeanClassName:()Ljava/lang/String;
     442: invokevirtual #73                 // Method org/apache/dubbo/config/spring/beans/factory/annotation/ServicePackagesHolder.addScannedClass:(Ljava/lang/String;)V
     445: goto          400
     448: goto          511
     451: aload_0
     452: getfield      #12                 // Field logger:Lorg/apache/dubbo/common/logger/ErrorTypeAwareLogger;
     455: invokeinterface #26,  1           // InterfaceMethod org/apache/dubbo/common/logger/ErrorTypeAwareLogger.isWarnEnabled:()Z
     460: ifeq          511
     463: aload_0
     464: getfield      #12                 // Field logger:Lorg/apache/dubbo/common/logger/ErrorTypeAwareLogger;
     467: ldc           #74                 // String 5-28
     469: ldc           #75                 // String No annotations were found on the class
     471: ldc           #28                 // String
     473: new           #52                 // class java/lang/StringBuilder
     476: dup
     477: invokespecial #53                 // Method java/lang/StringBuilder."<init>":()V
     480: ldc           #76                 // String No class annotated by Dubbo @Service was found under package [
     482: invokevirtual #55                 // Method java/lang/StringBuilder.append:(Ljava/lang/String;)Ljava/lang/StringBuilder;
     485: aload         7
     487: invokevirtual #55                 // Method java/lang/StringBuilder.append:(Ljava/lang/String;)Ljava/lang/StringBuilder;
     490: ldc           #77                 // String ], ignore re-scanned classes:
     492: invokevirtual #55                 // Method java/lang/StringBuilder.append:(Ljava/lang/String;)Ljava/lang/StringBuilder;
     495: aload         5
     497: invokevirtual #78                 // Method org/apache/dubbo/config/spring/beans/factory/annotation/ServiceAnnotationPostProcessor$ScanExcludeFilter.getExcludedCount:()I
     500: invokevirtual #68                 // Method java/lang/StringBuilder.append:(I)Ljava/lang/StringBuilder;
     503: invokevirtual #56                 // Method java/lang/StringBuilder.toString:()Ljava/lang/String;
     506: invokeinterface #30,  5           // InterfaceMethod org/apache/dubbo/common/logger/ErrorTypeAwareLogger.warn:(Ljava/lang/String;Ljava/lang/String;Ljava/lang/String;Ljava/lang/String;)V
     511: aload_0
     512: getfield      #3                  // Field servicePackagesHolder:Lorg/apache/dubbo/config/spring/beans/factory/annotation/ServicePackagesHolder;
     515: aload         7
     517: invokevirtual #79                 // Method org/apache/dubbo/config/spring/beans/factory/annotation/ServicePackagesHolder.addScannedPackage:(Ljava/lang/String;)V
     520: goto          145
     523: return

  private org.springframework.beans.factory.support.BeanNameGenerator resolveBeanNameGenerator(org.springframework.beans.factory.support.BeanDefinitionRegistry);
    Code:
       0: aconst_null
       1: astore_2
       2: aload_1
       3: instanceof    #80                 // class org/springframework/beans/factory/config/SingletonBeanRegistry
       6: ifeq          31
       9: ldc           #80                 // class org/springframework/beans/factory/config/SingletonBeanRegistry
      11: aload_1
      12: invokevirtual #81                 // Method java/lang/Class.cast:(Ljava/lang/Object;)Ljava/lang/Object;
      15: checkcast     #80                 // class org/springframework/beans/factory/config/SingletonBeanRegistry
      18: astore_3
      19: aload_3
      20: ldc           #82                 // String org.springframework.context.annotation.internalConfigurationBeanNameGenerator
      22: invokeinterface #83,  2           // InterfaceMethod org/springframework/beans/factory/config/SingletonBeanRegistry.getSingleton:(Ljava/lang/String;)Ljava/lang/Object;
      27: checkcast     #84                 // class org/springframework/beans/factory/support/BeanNameGenerator
      30: astore_2
      31: aload_2
      32: ifnonnull     103
      35: aload_0
      36: getfield      #12                 // Field logger:Lorg/apache/dubbo/common/logger/ErrorTypeAwareLogger;
      39: invokeinterface #51,  1           // InterfaceMethod org/apache/dubbo/common/logger/ErrorTypeAwareLogger.isInfoEnabled:()Z
      44: ifeq          95
      47: aload_0
      48: getfield      #12                 // Field logger:Lorg/apache/dubbo/common/logger/ErrorTypeAwareLogger;
      51: ldc           #85                 // String BeanNameGenerator bean can\'t be found in BeanFactory with name [org.springframework.context.annotation.internalConfigurationBeanNameGenerator]
      53: invokeinterface #57,  2           // InterfaceMethod org/apache/dubbo/common/logger/ErrorTypeAwareLogger.info:(Ljava/lang/String;)V
      58: aload_0
      59: getfield      #12                 // Field logger:Lorg/apache/dubbo/common/logger/ErrorTypeAwareLogger;
      62: new           #52                 // class java/lang/StringBuilder
      65: dup
      66: invokespecial #53                 // Method java/lang/StringBuilder."<init>":()V
      69: ldc           #86                 // String BeanNameGenerator will be a instance of
      71: invokevirtual #55                 // Method java/lang/StringBuilder.append:(Ljava/lang/String;)Ljava/lang/StringBuilder;
      74: ldc           #87                 // class org/springframework/context/annotation/AnnotationBeanNameGenerator
      76: invokevirtual #88                 // Method java/lang/Class.getName:()Ljava/lang/String;
      79: invokevirtual #55                 // Method java/lang/StringBuilder.append:(Ljava/lang/String;)Ljava/lang/StringBuilder;
      82: ldc           #89                 // String  , it maybe a potential problem on bean name generation.
      84: invokevirtual #55                 // Method java/lang/StringBuilder.append:(Ljava/lang/String;)Ljava/lang/StringBuilder;
      87: invokevirtual #56                 // Method java/lang/StringBuilder.toString:()Ljava/lang/String;
      90: invokeinterface #57,  2           // InterfaceMethod org/apache/dubbo/common/logger/ErrorTypeAwareLogger.info:(Ljava/lang/String;)V
      95: new           #87                 // class org/springframework/context/annotation/AnnotationBeanNameGenerator
      98: dup
      99: invokespecial #90                 // Method org/springframework/context/annotation/AnnotationBeanNameGenerator."<init>":()V
     102: astore_2
     103: aload_2
     104: areturn

  private java.util.Set<org.springframework.beans.factory.config.BeanDefinitionHolder> findServiceBeanDefinitionHolders(org.springframework.context.annotation.ClassPathBeanDefinitionScanner, java.lang.String, org.springframework.beans.factory.support.BeanDefinitionRegistry, org.springframework.beans.factory.support.BeanNameGenerator);
    Code:
       0: aload_1
       1: aload_2
       2: invokevirtual #91                 // Method org/springframework/context/annotation/ClassPathBeanDefinitionScanner.findCandidateComponents:(Ljava/lang/String;)Ljava/util/Set;
       5: astore        5
       7: new           #6                  // class java/util/LinkedHashSet
      10: dup
      11: aload         5
      13: invokeinterface #61,  1           // InterfaceMethod java/util/Set.size:()I
      18: invokespecial #92                 // Method java/util/LinkedHashSet."<init>":(I)V
      21: astore        6
      23: aload         5
      25: invokeinterface #48,  1           // InterfaceMethod java/util/Set.iterator:()Ljava/util/Iterator;
      30: astore        7
      32: aload         7
      34: invokeinterface #39,  1           // InterfaceMethod java/util/Iterator.hasNext:()Z
      39: ifeq          92
      42: aload         7
      44: invokeinterface #40,  1           // InterfaceMethod java/util/Iterator.next:()Ljava/lang/Object;
      49: checkcast     #93                 // class org/springframework/beans/factory/config/BeanDefinition
      52: astore        8
      54: aload         4
      56: aload         8
      58: aload_3
      59: invokeinterface #94,  3           // InterfaceMethod org/springframework/beans/factory/support/BeanNameGenerator.generateBeanName:(Lorg/springframework/beans/factory/config/BeanDefinition;Lorg/springframework/beans/factory/support/BeanDefinitionRegistry;)Ljava/lang/String;
      64: astore        9
      66: new           #63                 // class org/springframework/beans/factory/config/BeanDefinitionHolder
      69: dup
      70: aload         8
      72: aload         9
      74: invokespecial #95                 // Method org/springframework/beans/factory/config/BeanDefinitionHolder."<init>":(Lorg/springframework/beans/factory/config/BeanDefinition;Ljava/lang/String;)V
      77: astore        10
      79: aload         6
      81: aload         10
      83: invokeinterface #96,  2           // InterfaceMethod java/util/Set.add:(Ljava/lang/Object;)Z
      88: pop
      89: goto          32
      92: aload         6
      94: areturn

  private void processScannedBeanDefinition(org.springframework.beans.factory.config.BeanDefinitionHolder);
    Code:
       0: aload_0
       1: aload_1
       2: invokespecial #97                 // Method resolveClass:(Lorg/springframework/beans/factory/config/BeanDefinitionHolder;)Ljava/lang/Class;
       5: astore_2
       6: aload_0
       7: aload_2
       8: invokespecial #98                 // Method findServiceAnnotation:(Ljava/lang/Class;)Ljava/lang/annotation/Annotation;
      11: astore_3
      12: aload_3
      13: iconst_1
      14: iconst_0
      15: anewarray     #49                 // class java/lang/String
      18: invokestatic  #99                 // Method com/alibaba/spring/util/AnnotationUtils.getAttributes:(Ljava/lang/annotation/Annotation;Z[Ljava/lang/String;)Ljava/util/Map;
      21: astore        4
      23: aload         4
      25: aload_2
      26: invokestatic  #100                // Method org/apache/dubbo/config/spring/util/DubboAnnotationUtils.resolveInterfaceName:(Ljava/util/Map;Ljava/lang/Class;)Ljava/lang/String;
      29: astore        5
      31: aload_1
      32: invokevirtual #101                // Method org/springframework/beans/factory/config/BeanDefinitionHolder.getBeanName:()Ljava/lang/String;
      35: astore        6
      37: aload_0
      38: aload         4
      40: aload         5
      42: invokespecial #102                // Method generateServiceBeanName:(Ljava/util/Map;Ljava/lang/String;)Ljava/lang/String;
      45: astore        7
      47: aload_0
      48: aload         4
      50: aload         5
      52: aload         6
      54: invokespecial #103                // Method buildServiceBeanDefinition:(Ljava/util/Map;Ljava/lang/String;Ljava/lang/String;)Lorg/springframework/beans/factory/support/AbstractBeanDefinition;
      57: astore        8
      59: aload_0
      60: aload         7
      62: aload         8
      64: aload         5
      66: invokespecial #104                // Method registerServiceBeanDefinition:(Ljava/lang/String;Lorg/springframework/beans/factory/support/AbstractBeanDefinition;Ljava/lang/String;)V
      69: return

  private java.lang.annotation.Annotation findServiceAnnotation(java.lang.Class<?>);
    Code:
       0: getstatic     #37                 // Field serviceAnnotationTypes:Ljava/util/List;
       3: invokeinterface #105,  1          // InterfaceMethod java/util/List.stream:()Ljava/util/stream/Stream;
       8: aload_1
       9: invokedynamic #106,  0            // InvokeDynamic #0:apply:(Ljava/lang/Class;)Ljava/util/function/Function;
      14: invokeinterface #107,  2          // InterfaceMethod java/util/stream/Stream.map:(Ljava/util/function/Function;)Ljava/util/stream/Stream;
      19: invokedynamic #108,  0            // InvokeDynamic #1:test:()Ljava/util/function/Predicate;
      24: invokeinterface #109,  2          // InterfaceMethod java/util/stream/Stream.filter:(Ljava/util/function/Predicate;)Ljava/util/stream/Stream;
      29: invokeinterface #110,  1          // InterfaceMethod java/util/stream/Stream.findFirst:()Ljava/util/Optional;
      34: aconst_null
      35: invokevirtual #111                // Method java/util/Optional.orElse:(Ljava/lang/Object;)Ljava/lang/Object;
      38: checkcast     #112                // class java/lang/annotation/Annotation
      41: areturn

  private java.lang.String generateServiceBeanName(java.util.Map<java.lang.String, java.lang.Object>, java.lang.String);
    Code:
       0: aload_2
       1: aload_0
       2: getfield      #32                 // Field environment:Lorg/springframework/core/env/Environment;
       5: invokestatic  #113                // Method org/apache/dubbo/config/spring/beans/factory/annotation/ServiceBeanNameBuilder.create:(Ljava/lang/String;Lorg/springframework/core/env/Environment;)Lorg/apache/dubbo/config/spring/beans/factory/annotation/ServiceBeanNameBuilder;
       8: aload_1
       9: ldc           #114                // String group
      11: invokeinterface #115,  2          // InterfaceMethod java/util/Map.get:(Ljava/lang/Object;)Ljava/lang/Object;
      16: checkcast     #49                 // class java/lang/String
      19: invokevirtual #116                // Method org/apache/dubbo/config/spring/beans/factory/annotation/ServiceBeanNameBuilder.group:(Ljava/lang/String;)Lorg/apache/dubbo/config/spring/beans/factory/annotation/ServiceBeanNameBuilder;
      22: aload_1
      23: ldc           #117                // String version
      25: invokeinterface #115,  2          // InterfaceMethod java/util/Map.get:(Ljava/lang/Object;)Ljava/lang/Object;
      30: checkcast     #49                 // class java/lang/String
      33: invokevirtual #118                // Method org/apache/dubbo/config/spring/beans/factory/annotation/ServiceBeanNameBuilder.version:(Ljava/lang/String;)Lorg/apache/dubbo/config/spring/beans/factory/annotation/ServiceBeanNameBuilder;
      36: astore_3
      37: aload_3
      38: invokevirtual #119                // Method org/apache/dubbo/config/spring/beans/factory/annotation/ServiceBeanNameBuilder.build:()Ljava/lang/String;
      41: areturn

  private java.lang.Class<?> resolveClass(org.springframework.beans.factory.config.BeanDefinitionHolder);
    Code:
       0: aload_1
       1: invokevirtual #64                 // Method org/springframework/beans/factory/config/BeanDefinitionHolder.getBeanDefinition:()Lorg/springframework/beans/factory/config/BeanDefinition;
       4: astore_2
       5: aload_0
       6: aload_2
       7: invokespecial #120                // Method resolveClass:(Lorg/springframework/beans/factory/config/BeanDefinition;)Ljava/lang/Class;
      10: areturn

  private java.lang.Class<?> resolveClass(org.springframework.beans.factory.config.BeanDefinition);
    Code:
       0: aload_1
       1: invokeinterface #65,  1           // InterfaceMethod org/springframework/beans/factory/config/BeanDefinition.getBeanClassName:()Ljava/lang/String;
       6: astore_2
       7: aload_2
       8: aload_0
       9: getfield      #121                // Field classLoader:Ljava/lang/ClassLoader;
      12: invokestatic  #122                // Method org/springframework/util/ClassUtils.resolveClassName:(Ljava/lang/String;Ljava/lang/ClassLoader;)Ljava/lang/Class;
      15: areturn

  private java.util.Set<java.lang.String> resolvePackagesToScan(java.util.Set<java.lang.String>);
    Code:
       0: new           #6                  // class java/util/LinkedHashSet
       3: dup
       4: aload_1
       5: invokeinterface #61,  1           // InterfaceMethod java/util/Set.size:()I
      10: invokespecial #92                 // Method java/util/LinkedHashSet."<init>":(I)V
      13: astore_2
      14: aload_1
      15: invokeinterface #48,  1           // InterfaceMethod java/util/Set.iterator:()Ljava/util/Iterator;
      20: astore_3
      21: aload_3
      22: invokeinterface #39,  1           // InterfaceMethod java/util/Iterator.hasNext:()Z
      27: ifeq          77
      30: aload_3
      31: invokeinterface #40,  1           // InterfaceMethod java/util/Iterator.next:()Ljava/lang/Object;
      36: checkcast     #49                 // class java/lang/String
      39: astore        4
      41: aload         4
      43: invokestatic  #123                // Method org/apache/dubbo/common/utils/StringUtils.hasText:(Ljava/lang/CharSequence;)Z
      46: ifeq          74
      49: aload_0
      50: getfield      #32                 // Field environment:Lorg/springframework/core/env/Environment;
      53: aload         4
      55: invokevirtual #124                // Method java/lang/String.trim:()Ljava/lang/String;
      58: invokeinterface #125,  2          // InterfaceMethod org/springframework/core/env/Environment.resolvePlaceholders:(Ljava/lang/String;)Ljava/lang/String;
      63: astore        5
      65: aload_2
      66: aload         5
      68: invokeinterface #96,  2           // InterfaceMethod java/util/Set.add:(Ljava/lang/Object;)Z
      73: pop
      74: goto          21
      77: aload_2
      78: areturn

  private org.springframework.beans.factory.support.AbstractBeanDefinition buildServiceBeanDefinition(java.util.Map<java.lang.String, java.lang.Object>, java.lang.String, java.lang.String);
    Code:
       0: ldc           #126                // class org/apache/dubbo/config/spring/ServiceBean
       2: invokestatic  #127                // Method org/springframework/beans/factory/support/BeanDefinitionBuilder.rootBeanDefinition:(Ljava/lang/Class;)Lorg/springframework/beans/factory/support/BeanDefinitionBuilder;
       5: astore        4
       7: aload         4
       9: invokevirtual #128                // Method org/springframework/beans/factory/support/BeanDefinitionBuilder.getBeanDefinition:()Lorg/springframework/beans/factory/support/AbstractBeanDefinition;
      12: astore        5
      14: aload         5
      16: invokevirtual #129                // Method org/springframework/beans/factory/support/AbstractBeanDefinition.getPropertyValues:()Lorg/springframework/beans/MutablePropertyValues;
      19: astore        6
      21: bipush        10
      23: anewarray     #49                 // class java/lang/String
      26: dup
      27: iconst_0
      28: ldc           #130                // String provider
      30: aastore
      31: dup
      32: iconst_1
      33: ldc           #131                // String monitor
      35: aastore
      36: dup
      37: iconst_2
      38: ldc           #132                // String application
      40: aastore
      41: dup
      42: iconst_3
      43: ldc           #133                // String module
      45: aastore
      46: dup
      47: iconst_4
      48: ldc           #134                // String registry
      50: aastore
      51: dup
      52: iconst_5
      53: ldc           #135                // String protocol
      55: aastore
      56: dup
      57: bipush        6
      59: ldc           #136                // String methods
      61: aastore
      62: dup
      63: bipush        7
      65: ldc           #137                // String interfaceName
      67: aastore
      68: dup
      69: bipush        8
      71: ldc           #138                // String parameters
      73: aastore
      74: dup
      75: bipush        9
      77: ldc           #139                // String executor
      79: aastore
      80: invokestatic  #140                // Method com/alibaba/spring/util/ObjectUtils.of:([Ljava/lang/Object;)[Ljava/lang/Object;
      83: checkcast     #141                // class "[Ljava/lang/String;"
      86: astore        7
      88: aload         6
      90: new           #142                // class org/apache/dubbo/config/spring/beans/factory/annotation/AnnotationPropertyValuesAdapter
      93: dup
      94: aload_1
      95: aload_0
      96: getfield      #32                 // Field environment:Lorg/springframework/core/env/Environment;
      99: aload         7
     101: invokespecial #143                // Method org/apache/dubbo/config/spring/beans/factory/annotation/AnnotationPropertyValuesAdapter."<init>":(Ljava/util/Map;Lorg/springframework/core/env/PropertyResolver;[Ljava/lang/String;)V
     104: invokevirtual #144                // Method org/springframework/beans/MutablePropertyValues.addPropertyValues:(Lorg/springframework/beans/PropertyValues;)Lorg/springframework/beans/MutablePropertyValues;
     107: pop
     108: aload_0
     109: aload         4
     111: ldc           #145                // String ref
     113: aload_3
     114: invokespecial #146                // Method addPropertyReference:(Lorg/springframework/beans/factory/support/BeanDefinitionBuilder;Ljava/lang/String;Ljava/lang/String;)V
     117: aload         4
     119: ldc           #147                // String interface
     121: aload_2
     122: invokevirtual #148                // Method org/springframework/beans/factory/support/BeanDefinitionBuilder.addPropertyValue:(Ljava/lang/String;Ljava/lang/Object;)Lorg/springframework/beans/factory/support/BeanDefinitionBuilder;
     125: pop
     126: aload         4
     128: ldc           #138                // String parameters
     130: aload_1
     131: ldc           #138                // String parameters
     133: invokeinterface #115,  2          // InterfaceMethod java/util/Map.get:(Ljava/lang/Object;)Ljava/lang/Object;
     138: checkcast     #141                // class "[Ljava/lang/String;"
     141: checkcast     #141                // class "[Ljava/lang/String;"
     144: invokestatic  #149                // Method org/apache/dubbo/config/spring/util/DubboAnnotationUtils.convertParameters:([Ljava/lang/String;)Ljava/util/Map;
     147: invokevirtual #148                // Method org/springframework/beans/factory/support/BeanDefinitionBuilder.addPropertyValue:(Ljava/lang/String;Ljava/lang/Object;)Lorg/springframework/beans/factory/support/BeanDefinitionBuilder;
     150: pop
     151: aload_0
     152: aload_1
     153: ldc           #136                // String methods
     155: invokeinterface #115,  2          // InterfaceMethod java/util/Map.get:(Ljava/lang/Object;)Ljava/lang/Object;
     160: invokespecial #150                // Method convertMethodConfigs:(Ljava/lang/Object;)Ljava/util/List;
     163: astore        8
     165: aload         8
     167: invokeinterface #151,  1          // InterfaceMethod java/util/List.isEmpty:()Z
     172: ifne          185
     175: aload         4
     177: ldc           #136                // String methods
     179: aload         8
     181: invokevirtual #148                // Method org/springframework/beans/factory/support/BeanDefinitionBuilder.addPropertyValue:(Ljava/lang/String;Ljava/lang/Object;)Lorg/springframework/beans/factory/support/BeanDefinitionBuilder;
     184: pop
     185: aload_1
     186: ldc           #130                // String provider
     188: invokeinterface #115,  2          // InterfaceMethod java/util/Map.get:(Ljava/lang/Object;)Ljava/lang/Object;
     193: checkcast     #49                 // class java/lang/String
     196: astore        9
     198: aload         9
     200: invokestatic  #123                // Method org/apache/dubbo/common/utils/StringUtils.hasText:(Ljava/lang/CharSequence;)Z
     203: ifeq          216
     206: aload_0
     207: aload         4
     209: ldc           #152                // String providerIds
     211: aload         9
     213: invokespecial #153                // Method addPropertyValue:(Lorg/springframework/beans/factory/support/BeanDefinitionBuilder;Ljava/lang/String;Ljava/lang/String;)V
     216: aload_1
     217: ldc           #134                // String registry
     219: invokeinterface #115,  2          // InterfaceMethod java/util/Map.get:(Ljava/lang/Object;)Ljava/lang/Object;
     224: checkcast     #141                // class "[Ljava/lang/String;"
     227: checkcast     #141                // class "[Ljava/lang/String;"
     230: astore        10
     232: aload         10
     234: ifnull        265
     237: aload         10
     239: arraylength
     240: ifle          265
     243: aload_0
     244: aload         10
     246: invokespecial #154                // Method resolveStringArray:([Ljava/lang/String;)[Ljava/lang/String;
     249: pop
     250: aload         4
     252: ldc           #155                // String registryIds
     254: aload         10
     256: bipush        44
     258: invokestatic  #156                // Method org/apache/dubbo/common/utils/StringUtils.join:([Ljava/lang/String;C)Ljava/lang/String;
     261: invokevirtual #148                // Method org/springframework/beans/factory/support/BeanDefinitionBuilder.addPropertyValue:(Ljava/lang/String;Ljava/lang/Object;)Lorg/springframework/beans/factory/support/BeanDefinitionBuilder;
     264: pop
     265: aload_1
     266: ldc           #135                // String protocol
     268: invokeinterface #115,  2          // InterfaceMethod java/util/Map.get:(Ljava/lang/Object;)Ljava/lang/Object;
     273: checkcast     #141                // class "[Ljava/lang/String;"
     276: checkcast     #141                // class "[Ljava/lang/String;"
     279: astore        11
     281: aload         11
     283: ifnull        314
     286: aload         11
     288: arraylength
     289: ifle          314
     292: aload_0
     293: aload         11
     295: invokespecial #154                // Method resolveStringArray:([Ljava/lang/String;)[Ljava/lang/String;
     298: pop
     299: aload         4
     301: ldc           #157                // String protocolIds
     303: aload         11
     305: bipush        44
     307: invokestatic  #156                // Method org/apache/dubbo/common/utils/StringUtils.join:([Ljava/lang/String;C)Ljava/lang/String;
     310: invokevirtual #148                // Method org/springframework/beans/factory/support/BeanDefinitionBuilder.addPropertyValue:(Ljava/lang/String;Ljava/lang/Object;)Lorg/springframework/beans/factory/support/BeanDefinitionBuilder;
     313: pop
     314: aload_1
     315: ldc           #131                // String monitor
     317: invokeinterface #115,  2          // InterfaceMethod java/util/Map.get:(Ljava/lang/Object;)Ljava/lang/Object;
     322: checkcast     #49                 // class java/lang/String
     325: astore        12
     327: aload         12
     329: invokestatic  #123                // Method org/apache/dubbo/common/utils/StringUtils.hasText:(Ljava/lang/CharSequence;)Z
     332: ifeq          345
     335: aload_0
     336: aload         4
     338: ldc           #131                // String monitor
     340: aload         12
     342: invokespecial #146                // Method addPropertyReference:(Lorg/springframework/beans/factory/support/BeanDefinitionBuilder;Ljava/lang/String;Ljava/lang/String;)V
     345: aload_1
     346: ldc           #133                // String module
     348: invokeinterface #115,  2          // InterfaceMethod java/util/Map.get:(Ljava/lang/Object;)Ljava/lang/Object;
     353: checkcast     #49                 // class java/lang/String
     356: astore        13
     358: aload         13
     360: invokestatic  #123                // Method org/apache/dubbo/common/utils/StringUtils.hasText:(Ljava/lang/CharSequence;)Z
     363: ifeq          376
     366: aload_0
     367: aload         4
     369: ldc           #133                // String module
     371: aload         13
     373: invokespecial #146                // Method addPropertyReference:(Lorg/springframework/beans/factory/support/BeanDefinitionBuilder;Ljava/lang/String;Ljava/lang/String;)V
     376: aload_1
     377: ldc           #139                // String executor
     379: invokeinterface #115,  2          // InterfaceMethod java/util/Map.get:(Ljava/lang/Object;)Ljava/lang/Object;
     384: checkcast     #49                 // class java/lang/String
     387: astore        14
     389: aload         14
     391: invokestatic  #123                // Method org/apache/dubbo/common/utils/StringUtils.hasText:(Ljava/lang/CharSequence;)Z
     394: ifeq          407
     397: aload_0
     398: aload         4
     400: ldc           #139                // String executor
     402: aload         14
     404: invokespecial #146                // Method addPropertyReference:(Lorg/springframework/beans/factory/support/BeanDefinitionBuilder;Ljava/lang/String;Ljava/lang/String;)V
     407: aload         4
     409: invokevirtual #128                // Method org/springframework/beans/factory/support/BeanDefinitionBuilder.getBeanDefinition:()Lorg/springframework/beans/factory/support/AbstractBeanDefinition;
     412: areturn

  private java.lang.String[] resolveStringArray(java.lang.String[]);
    Code:
       0: aload_1
       1: ifnonnull     6
       4: aconst_null
       5: areturn
       6: iconst_0
       7: istore_2
       8: iload_2
       9: aload_1
      10: arraylength
      11: if_icmpge     35
      14: aload_1
      15: iload_2
      16: aload_0
      17: getfield      #32                 // Field environment:Lorg/springframework/core/env/Environment;
      20: aload_1
      21: iload_2
      22: aaload
      23: invokeinterface #125,  2          // InterfaceMethod org/springframework/core/env/Environment.resolvePlaceholders:(Ljava/lang/String;)Ljava/lang/String;
      28: aastore
      29: iinc          2, 1
      32: goto          8
      35: aload_1
      36: areturn

  private java.util.List convertMethodConfigs(java.lang.Object);
    Code:
       0: aload_1
       1: ifnonnull     8
       4: getstatic     #158                // Field java/util/Collections.EMPTY_LIST:Ljava/util/List;
       7: areturn
       8: aload_1
       9: checkcast     #159                // class "[Lorg/apache/dubbo/config/annotation/Method;"
      12: checkcast     #159                // class "[Lorg/apache/dubbo/config/annotation/Method;"
      15: invokestatic  #160                // Method org/apache/dubbo/config/MethodConfig.constructMethodConfig:([Lorg/apache/dubbo/config/annotation/Method;)Ljava/util/List;
      18: areturn

  private void addPropertyReference(org.springframework.beans.factory.support.BeanDefinitionBuilder, java.lang.String, java.lang.String);
    Code:
       0: aload_0
       1: getfield      #32                 // Field environment:Lorg/springframework/core/env/Environment;
       4: aload_3
       5: invokeinterface #125,  2          // InterfaceMethod org/springframework/core/env/Environment.resolvePlaceholders:(Ljava/lang/String;)Ljava/lang/String;
      10: astore        4
      12: aload_1
      13: aload_2
      14: aload         4
      16: invokevirtual #161                // Method org/springframework/beans/factory/support/BeanDefinitionBuilder.addPropertyReference:(Ljava/lang/String;Ljava/lang/String;)Lorg/springframework/beans/factory/support/BeanDefinitionBuilder;
      19: pop
      20: return

  private void addPropertyValue(org.springframework.beans.factory.support.BeanDefinitionBuilder, java.lang.String, java.lang.String);
    Code:
       0: aload_0
       1: getfield      #32                 // Field environment:Lorg/springframework/core/env/Environment;
       4: aload_3
       5: invokeinterface #125,  2          // InterfaceMethod org/springframework/core/env/Environment.resolvePlaceholders:(Ljava/lang/String;)Ljava/lang/String;
      10: astore        4
      12: aload_1
      13: aload_2
      14: aload         4
      16: invokevirtual #148                // Method org/springframework/beans/factory/support/BeanDefinitionBuilder.addPropertyValue:(Ljava/lang/String;Ljava/lang/Object;)Lorg/springframework/beans/factory/support/BeanDefinitionBuilder;
      19: pop
      20: return

  private java.util.Map<java.lang.String, java.lang.Object> getServiceAnnotationAttributes(org.springframework.beans.factory.config.BeanDefinition);
    Code:
       0: aload_1
       1: instanceof    #23                 // class org/springframework/beans/factory/annotation/AnnotatedBeanDefinition
       4: ifeq          91
       7: aload_1
       8: checkcast     #23                 // class org/springframework/beans/factory/annotation/AnnotatedBeanDefinition
      11: astore_2
      12: aload_2
      13: invokestatic  #162                // Method org/apache/dubbo/config/spring/util/SpringCompatUtils.getFactoryMethodMetadata:(Lorg/springframework/beans/factory/annotation/AnnotatedBeanDefinition;)Lorg/springframework/core/type/MethodMetadata;
      16: astore_3
      17: aload_3
      18: ifnull        91
      21: getstatic     #37                 // Field serviceAnnotationTypes:Ljava/util/List;
      24: invokeinterface #38,  1           // InterfaceMethod java/util/List.iterator:()Ljava/util/Iterator;
      29: astore        4
      31: aload         4
      33: invokeinterface #39,  1           // InterfaceMethod java/util/Iterator.hasNext:()Z
      38: ifeq          91
      41: aload         4
      43: invokeinterface #40,  1           // InterfaceMethod java/util/Iterator.next:()Ljava/lang/Object;
      48: checkcast     #41                 // class java/lang/Class
      51: astore        5
      53: aload_3
      54: aload         5
      56: invokevirtual #88                 // Method java/lang/Class.getName:()Ljava/lang/String;
      59: invokeinterface #163,  2          // InterfaceMethod org/springframework/core/type/MethodMetadata.isAnnotated:(Ljava/lang/String;)Z
      64: ifeq          88
      67: aload_3
      68: aload         5
      70: invokevirtual #88                 // Method java/lang/Class.getName:()Ljava/lang/String;
      73: invokeinterface #164,  2          // InterfaceMethod org/springframework/core/type/MethodMetadata.getAnnotationAttributes:(Ljava/lang/String;)Ljava/util/Map;
      78: astore        6
      80: aload         5
      82: aload         6
      84: invokestatic  #165                // InterfaceMethod org/apache/dubbo/common/utils/AnnotationUtils.filterDefaultValues:(Ljava/lang/Class;Ljava/util/Map;)Ljava/util/Map;
      87: areturn
      88: goto          31
      91: aconst_null
      92: areturn

  private void processAnnotatedBeanDefinition(java.lang.String, org.springframework.beans.factory.annotation.AnnotatedBeanDefinition, java.util.Map<java.lang.String, java.lang.Object>);
    Code:
       0: new           #166                // class java/util/LinkedHashMap
       3: dup
       4: aload_3
       5: invokespecial #167                // Method java/util/LinkedHashMap."<init>":(Ljava/util/Map;)V
       8: astore        4
      10: aload_2
      11: invokestatic  #168                // Method org/apache/dubbo/config/spring/util/SpringCompatUtils.getFactoryMethodReturnType:(Lorg/springframework/beans/factory/annotation/AnnotatedBeanDefinition;)Ljava/lang/String;
      14: astore        5
      16: aload         5
      18: aload_0
      19: getfield      #121                // Field classLoader:Ljava/lang/ClassLoader;
      22: invokestatic  #122                // Method org/springframework/util/ClassUtils.resolveClassName:(Ljava/lang/String;Ljava/lang/ClassLoader;)Ljava/lang/Class;
      25: astore        6
      27: aload         4
      29: aload         6
      31: invokestatic  #100                // Method org/apache/dubbo/config/spring/util/DubboAnnotationUtils.resolveInterfaceName:(Ljava/util/Map;Ljava/lang/Class;)Ljava/lang/String;
      34: astore        7
      36: aload_0
      37: aload         4
      39: aload         7
      41: invokespecial #102                // Method generateServiceBeanName:(Ljava/util/Map;Ljava/lang/String;)Ljava/lang/String;
      44: astore        8
      46: aload_0
      47: aload         4
      49: aload         7
      51: aload_1
      52: invokespecial #103                // Method buildServiceBeanDefinition:(Ljava/util/Map;Ljava/lang/String;Ljava/lang/String;)Lorg/springframework/beans/factory/support/AbstractBeanDefinition;
      55: astore        9
      57: aload         9
      59: invokevirtual #129                // Method org/springframework/beans/factory/support/AbstractBeanDefinition.getPropertyValues:()Lorg/springframework/beans/MutablePropertyValues;
      62: ldc           #170                // String id
      64: aload         8
      66: invokevirtual #171                // Method org/springframework/beans/MutablePropertyValues.add:(Ljava/lang/String;Ljava/lang/Object;)Lorg/springframework/beans/MutablePropertyValues;
      69: pop
      70: aload_0
      71: aload         8
      73: aload         9
      75: aload         7
      77: invokespecial #104                // Method registerServiceBeanDefinition:(Ljava/lang/String;Lorg/springframework/beans/factory/support/AbstractBeanDefinition;Ljava/lang/String;)V
      80: return

  private void registerServiceBeanDefinition(java.lang.String, org.springframework.beans.factory.support.AbstractBeanDefinition, java.lang.String);
    Code:
       0: aload_0
       1: getfield      #17                 // Field registry:Lorg/springframework/beans/factory/support/BeanDefinitionRegistry;
       4: aload_1
       5: invokeinterface #172,  2          // InterfaceMethod org/springframework/beans/factory/support/BeanDefinitionRegistry.containsBeanDefinition:(Ljava/lang/String;)Z
      10: ifeq          121
      13: aload_0
      14: getfield      #17                 // Field registry:Lorg/springframework/beans/factory/support/BeanDefinitionRegistry;
      17: aload_1
      18: invokeinterface #173,  2          // InterfaceMethod org/springframework/beans/factory/support/BeanDefinitionRegistry.getBeanDefinition:(Ljava/lang/String;)Lorg/springframework/beans/factory/config/BeanDefinition;
      23: astore        4
      25: aload         4
      27: aload_2
      28: invokevirtual #174                // Method java/lang/Object.equals:(Ljava/lang/Object;)Z
      31: ifeq          35
      34: return
      35: new           #52                 // class java/lang/StringBuilder
      38: dup
      39: invokespecial #53                 // Method java/lang/StringBuilder."<init>":()V
      42: ldc           #175                // String Found duplicated BeanDefinition of service interface [
      44: invokevirtual #55                 // Method java/lang/StringBuilder.append:(Ljava/lang/String;)Ljava/lang/StringBuilder;
      47: aload_3
      48: invokevirtual #55                 // Method java/lang/StringBuilder.append:(Ljava/lang/String;)Ljava/lang/StringBuilder;
      51: ldc           #176                // String ] with bean name [
      53: invokevirtual #55                 // Method java/lang/StringBuilder.append:(Ljava/lang/String;)Ljava/lang/StringBuilder;
      56: aload_1
      57: invokevirtual #55                 // Method java/lang/StringBuilder.append:(Ljava/lang/String;)Ljava/lang/StringBuilder;
      60: ldc           #177                // String ], existing definition [
      62: invokevirtual #55                 // Method java/lang/StringBuilder.append:(Ljava/lang/String;)Ljava/lang/StringBuilder;
      65: aload         4
      67: invokevirtual #71                 // Method java/lang/StringBuilder.append:(Ljava/lang/Object;)Ljava/lang/StringBuilder;
      70: ldc           #178                // String ], new definition [
      72: invokevirtual #55                 // Method java/lang/StringBuilder.append:(Ljava/lang/String;)Ljava/lang/StringBuilder;
      75: aload_2
      76: invokevirtual #71                 // Method java/lang/StringBuilder.append:(Ljava/lang/Object;)Ljava/lang/StringBuilder;
      79: ldc           #179                // String ]
      81: invokevirtual #55                 // Method java/lang/StringBuilder.append:(Ljava/lang/String;)Ljava/lang/StringBuilder;
      84: invokevirtual #56                 // Method java/lang/StringBuilder.toString:()Ljava/lang/String;
      87: astore        5
      89: aload_0
      90: getfield      #12                 // Field logger:Lorg/apache/dubbo/common/logger/ErrorTypeAwareLogger;
      93: ldc           #180                // String 5-30
      95: ldc           #28                 // String
      97: ldc           #28                 // String
      99: aload         5
     101: invokeinterface #181,  5          // InterfaceMethod org/apache/dubbo/common/logger/ErrorTypeAwareLogger.error:(Ljava/lang/String;Ljava/lang/String;Ljava/lang/String;Ljava/lang/String;)V
     106: new           #182                // class org/springframework/beans/factory/BeanDefinitionStoreException
     109: dup
     110: aload_2
     111: invokevirtual #183                // Method org/springframework/beans/factory/support/AbstractBeanDefinition.getResourceDescription:()Ljava/lang/String;
     114: aload_1
     115: aload         5
     117: invokespecial #184                // Method org/springframework/beans/factory/BeanDefinitionStoreException."<init>":(Ljava/lang/String;Ljava/lang/String;Ljava/lang/String;)V
     120: athrow
     121: aload_0
     122: getfield      #17                 // Field registry:Lorg/springframework/beans/factory/support/BeanDefinitionRegistry;
     125: aload_1
     126: aload_2
     127: invokeinterface #185,  3          // InterfaceMethod org/springframework/beans/factory/support/BeanDefinitionRegistry.registerBeanDefinition:(Ljava/lang/String;Lorg/springframework/beans/factory/config/BeanDefinition;)V
     132: aload_0
     133: getfield      #12                 // Field logger:Lorg/apache/dubbo/common/logger/ErrorTypeAwareLogger;
     136: invokeinterface #51,  1           // InterfaceMethod org/apache/dubbo/common/logger/ErrorTypeAwareLogger.isInfoEnabled:()Z
     141: ifeq          181
     144: aload_0
     145: getfield      #12                 // Field logger:Lorg/apache/dubbo/common/logger/ErrorTypeAwareLogger;
     148: new           #52                 // class java/lang/StringBuilder
     151: dup
     152: invokespecial #53                 // Method java/lang/StringBuilder."<init>":()V
     155: ldc           #186                // String Register ServiceBean[
     157: invokevirtual #55                 // Method java/lang/StringBuilder.append:(Ljava/lang/String;)Ljava/lang/StringBuilder;
     160: aload_1
     161: invokevirtual #55                 // Method java/lang/StringBuilder.append:(Ljava/lang/String;)Ljava/lang/StringBuilder;
     164: ldc           #70                 // String ]:
     166: invokevirtual #55                 // Method java/lang/StringBuilder.append:(Ljava/lang/String;)Ljava/lang/StringBuilder;
     169: aload_2
     170: invokevirtual #71                 // Method java/lang/StringBuilder.append:(Ljava/lang/Object;)Ljava/lang/StringBuilder;
     173: invokevirtual #56                 // Method java/lang/StringBuilder.toString:()Ljava/lang/String;
     176: invokeinterface #57,  2           // InterfaceMethod org/apache/dubbo/common/logger/ErrorTypeAwareLogger.info:(Ljava/lang/String;)V
     181: return

  public void setEnvironment(org.springframework.core.env.Environment);
    Code:
       0: aload_0
       1: aload_1
       2: putfield      #32                 // Field environment:Lorg/springframework/core/env/Environment;
       5: return

  public void setResourceLoader(org.springframework.core.io.ResourceLoader);
    Code:
       0: aload_0
       1: aload_1
       2: putfield      #33                 // Field resourceLoader:Lorg/springframework/core/io/ResourceLoader;
       5: return

  public void setBeanClassLoader(java.lang.ClassLoader);
    Code:
       0: aload_0
       1: aload_1
       2: putfield      #121                // Field classLoader:Ljava/lang/ClassLoader;
       5: return

  public void setApplicationContext(org.springframework.context.ApplicationContext) throws org.springframework.beans.BeansException;
    Code:
       0: aload_0
       1: aload_1
       2: ldc           #188                // String dubboServicePackagesHolder
       4: ldc           #187                // class org/apache/dubbo/config/spring/beans/factory/annotation/ServicePackagesHolder
       6: invokeinterface #189,  3          // InterfaceMethod org/springframework/context/ApplicationContext.getBean:(Ljava/lang/String;Ljava/lang/Class;)Ljava/lang/Object;
      11: checkcast     #187                // class org/apache/dubbo/config/spring/beans/factory/annotation/ServicePackagesHolder
      14: putfield      #3                  // Field servicePackagesHolder:Lorg/apache/dubbo/config/spring/beans/factory/annotation/ServicePackagesHolder;
      17: return

  private static java.lang.annotation.Annotation lambda$findServiceAnnotation$0(java.lang.Class, java.lang.Class);
    Code:
       0: ldc           #190                // String org.springframework.core.annotation.AnnotatedElementUtils
       2: invokestatic  #191                // Method java/lang/Thread.currentThread:()Ljava/lang/Thread;
       5: invokevirtual #192                // Method java/lang/Thread.getContextClassLoader:()Ljava/lang/ClassLoader;
       8: invokestatic  #193                // Method org/apache/dubbo/common/utils/ClassUtils.isPresent:(Ljava/lang/String;Ljava/lang/ClassLoader;)Z
      11: ifeq          32
      14: ldc           #194                // class org/springframework/core/annotation/AnnotatedElementUtils
      16: ldc           #195                // String findMergedAnnotation
      18: invokestatic  #196                // Method org/apache/dubbo/common/utils/ReflectUtils.hasMethod:(Ljava/lang/Class;Ljava/lang/String;)Z
      21: ifeq          32
      24: aload_0
      25: aload_1
      26: invokestatic  #197                // Method org/springframework/core/annotation/AnnotatedElementUtils.findMergedAnnotation:(Ljava/lang/reflect/AnnotatedElement;Ljava/lang/Class;)Ljava/lang/annotation/Annotation;
      29: goto          37
      32: aload_0
      33: aload_1
      34: invokestatic  #198                // InterfaceMethod org/apache/dubbo/common/utils/AnnotationUtils.findAnnotation:(Ljava/lang/reflect/AnnotatedElement;Ljava/lang/Class;)Ljava/lang/annotation/Annotation;
      37: areturn

  static org.apache.dubbo.config.spring.beans.factory.annotation.ServicePackagesHolder access$100(org.apache.dubbo.config.spring.beans.factory.annotation.ServiceAnnotationPostProcessor);
    Code:
       0: aload_0
       1: getfield      #3                  // Field servicePackagesHolder:Lorg/apache/dubbo/config/spring/beans/factory/annotation/ServicePackagesHolder;
       4: areturn

  static {};
    Code:
       0: iconst_3
       1: anewarray     #41                 // class java/lang/Class
       4: dup
       5: iconst_0
       6: ldc           #199                // class org/apache/dubbo/config/annotation/DubboService
       8: aastore
       9: dup
      10: iconst_1
      11: ldc           #200                // class org/apache/dubbo/config/annotation/Service
      13: aastore
      14: dup
      15: iconst_2
      16: ldc           #201                // class com/alibaba/dubbo/config/annotation/Service
      18: aastore
      19: invokestatic  #4                  // Method java/util/Arrays.asList:([Ljava/lang/Object;)Ljava/util/List;
      22: putstatic     #37                 // Field serviceAnnotationTypes:Ljava/util/List;
      25: return
}
