Compiled from "ServiceAnnotationPostProcessor.java"
class org.apache.dubbo.config.spring.beans.factory.annotation.ServiceAnnotationPostProcessor$ScanExcludeFilter implements org.springframework.core.type.filter.TypeFilter {
  private int excludedCount;

  final org.apache.dubbo.config.spring.beans.factory.annotation.ServiceAnnotationPostProcessor this$0;

  private org.apache.dubbo.config.spring.beans.factory.annotation.ServiceAnnotationPostProcessor$ScanExcludeFilter(org.apache.dubbo.config.spring.beans.factory.annotation.ServiceAnnotationPostProcessor);
    Code:
       0: aload_0
       1: aload_1
       2: putfield      #2                  // Field this$0:Lorg/apache/dubbo/config/spring/beans/factory/annotation/ServiceAnnotationPostProcessor;
       5: aload_0
       6: invokespecial #3                  // Method java/lang/Object."<init>":()V
       9: return

  public boolean match(org.springframework.core.type.classreading.MetadataReader, org.springframework.core.type.classreading.MetadataReaderFactory) throws java.io.IOException;
    Code:
       0: aload_1
       1: invokeinterface #4,  1            // InterfaceMethod org/springframework/core/type/classreading/MetadataReader.getClassMetadata:()Lorg/springframework/core/type/ClassMetadata;
       6: invokeinterface #5,  1            // InterfaceMethod org/springframework/core/type/ClassMetadata.getClassName:()Ljava/lang/String;
      11: astore_3
      12: aload_0
      13: getfield      #2                  // Field this$0:Lorg/apache/dubbo/config/spring/beans/factory/annotation/ServiceAnnotationPostProcessor;
      16: invokestatic  #6                  // Method org/apache/dubbo/config/spring/beans/factory/annotation/ServiceAnnotationPostProcessor.access$100:(Lorg/apache/dubbo/config/spring/beans/factory/annotation/ServiceAnnotationPostProcessor;)Lorg/apache/dubbo/config/spring/beans/factory/annotation/ServicePackagesHolder;
      19: aload_3
      20: invokevirtual #7                  // Method org/apache/dubbo/config/spring/beans/factory/annotation/ServicePackagesHolder.isClassScanned:(Ljava/lang/String;)Z
      23: istore        4
      25: iload         4
      27: ifeq          40
      30: aload_0
      31: dup
      32: getfield      #8                  // Field excludedCount:I
      35: iconst_1
      36: iadd
      37: putfield      #8                  // Field excludedCount:I
      40: iload         4
      42: ireturn

  public int getExcludedCount();
    Code:
       0: aload_0
       1: getfield      #8                  // Field excludedCount:I
       4: ireturn

  org.apache.dubbo.config.spring.beans.factory.annotation.ServiceAnnotationPostProcessor$ScanExcludeFilter(org.apache.dubbo.config.spring.beans.factory.annotation.ServiceAnnotationPostProcessor, org.apache.dubbo.config.spring.beans.factory.annotation.ServiceAnnotationPostProcessor$1);
    Code:
       0: aload_0
       1: aload_1
       2: invokespecial #1                  // Method "<init>":(Lorg/apache/dubbo/config/spring/beans/factory/annotation/ServiceAnnotationPostProcessor;)V
       5: return
}
