Compiled from "ServiceBeanNameBuilder.java"
public class org.apache.dubbo.config.spring.beans.factory.annotation.ServiceBeanNameBuilder {
  private static final java.lang.String SEPARATOR;

  private final java.lang.String interfaceClassName;

  private final org.springframework.core.env.Environment environment;

  private java.lang.String version;

  private java.lang.String group;

  private org.apache.dubbo.config.spring.beans.factory.annotation.ServiceBeanNameBuilder(java.lang.Class<?>, org.springframework.core.env.Environment);
    Code:
       0: aload_0
       1: aload_1
       2: invokevirtual #1                  // Method java/lang/Class.getName:()Ljava/lang/String;
       5: aload_2
       6: invokespecial #2                  // Method "<init>":(Ljava/lang/String;Lorg/springframework/core/env/Environment;)V
       9: return

  private org.apache.dubbo.config.spring.beans.factory.annotation.ServiceBeanNameBuilder(java.lang.String, org.springframework.core.env.Environment);
    Code:
       0: aload_0
       1: invokespecial #3                  // Method java/lang/Object."<init>":()V
       4: aload_0
       5: aload_1
       6: putfield      #4                  // Field interfaceClassName:Ljava/lang/String;
       9: aload_0
      10: aload_2
      11: putfield      #5                  // Field environment:Lorg/springframework/core/env/Environment;
      14: return

  private org.apache.dubbo.config.spring.beans.factory.annotation.ServiceBeanNameBuilder(org.springframework.core.annotation.AnnotationAttributes, java.lang.Class<?>, org.springframework.core.env.Environment);
    Code:
       0: aload_0
       1: aload_1
       2: aload_2
       3: invokestatic  #6                  // Method org/apache/dubbo/config/spring/util/DubboAnnotationUtils.resolveInterfaceName:(Ljava/util/Map;Ljava/lang/Class;)Ljava/lang/String;
       6: aload_3
       7: invokespecial #2                  // Method "<init>":(Ljava/lang/String;Lorg/springframework/core/env/Environment;)V
      10: aload_0
      11: aload_1
      12: ldc           #7                  // String group
      14: invokestatic  #8                  // Method com/alibaba/spring/util/AnnotationUtils.getAttribute:(Ljava/util/Map;Ljava/lang/String;)Ljava/lang/Object;
      17: checkcast     #9                  // class java/lang/String
      20: invokevirtual #10                 // Method group:(Ljava/lang/String;)Lorg/apache/dubbo/config/spring/beans/factory/annotation/ServiceBeanNameBuilder;
      23: pop
      24: aload_0
      25: aload_1
      26: ldc           #11                 // String version
      28: invokestatic  #8                  // Method com/alibaba/spring/util/AnnotationUtils.getAttribute:(Ljava/util/Map;Ljava/lang/String;)Ljava/lang/Object;
      31: checkcast     #9                  // class java/lang/String
      34: invokevirtual #12                 // Method version:(Ljava/lang/String;)Lorg/apache/dubbo/config/spring/beans/factory/annotation/ServiceBeanNameBuilder;
      37: pop
      38: return

  public static org.apache.dubbo.config.spring.beans.factory.annotation.ServiceBeanNameBuilder create(org.springframework.core.annotation.AnnotationAttributes, java.lang.Class<?>, org.springframework.core.env.Environment);
    Code:
       0: new           #13                 // class org/apache/dubbo/config/spring/beans/factory/annotation/ServiceBeanNameBuilder
       3: dup
       4: aload_0
       5: aload_1
       6: aload_2
       7: invokespecial #14                 // Method "<init>":(Lorg/springframework/core/annotation/AnnotationAttributes;Ljava/lang/Class;Lorg/springframework/core/env/Environment;)V
      10: areturn

  public static org.apache.dubbo.config.spring.beans.factory.annotation.ServiceBeanNameBuilder create(java.lang.Class<?>, org.springframework.core.env.Environment);
    Code:
       0: new           #13                 // class org/apache/dubbo/config/spring/beans/factory/annotation/ServiceBeanNameBuilder
       3: dup
       4: aload_0
       5: aload_1
       6: invokespecial #15                 // Method "<init>":(Ljava/lang/Class;Lorg/springframework/core/env/Environment;)V
       9: areturn

  public static org.apache.dubbo.config.spring.beans.factory.annotation.ServiceBeanNameBuilder create(java.lang.String, org.springframework.core.env.Environment);
    Code:
       0: new           #13                 // class org/apache/dubbo/config/spring/beans/factory/annotation/ServiceBeanNameBuilder
       3: dup
       4: aload_0
       5: aload_1
       6: invokespecial #2                  // Method "<init>":(Ljava/lang/String;Lorg/springframework/core/env/Environment;)V
       9: areturn

  public static org.apache.dubbo.config.spring.beans.factory.annotation.ServiceBeanNameBuilder create(org.apache.dubbo.config.annotation.Service, java.lang.Class<?>, org.springframework.core.env.Environment);
    Code:
       0: aload_0
       1: iconst_0
       2: iconst_0
       3: invokestatic  #16                 // Method org/springframework/core/annotation/AnnotationUtils.getAnnotationAttributes:(Ljava/lang/annotation/Annotation;ZZ)Lorg/springframework/core/annotation/AnnotationAttributes;
       6: aload_1
       7: aload_2
       8: invokestatic  #17                 // Method create:(Lorg/springframework/core/annotation/AnnotationAttributes;Ljava/lang/Class;Lorg/springframework/core/env/Environment;)Lorg/apache/dubbo/config/spring/beans/factory/annotation/ServiceBeanNameBuilder;
      11: areturn

  public static org.apache.dubbo.config.spring.beans.factory.annotation.ServiceBeanNameBuilder create(org.apache.dubbo.config.annotation.Reference, java.lang.Class<?>, org.springframework.core.env.Environment);
    Code:
       0: aload_0
       1: iconst_0
       2: iconst_0
       3: invokestatic  #16                 // Method org/springframework/core/annotation/AnnotationUtils.getAnnotationAttributes:(Ljava/lang/annotation/Annotation;ZZ)Lorg/springframework/core/annotation/AnnotationAttributes;
       6: aload_1
       7: aload_2
       8: invokestatic  #17                 // Method create:(Lorg/springframework/core/annotation/AnnotationAttributes;Ljava/lang/Class;Lorg/springframework/core/env/Environment;)Lorg/apache/dubbo/config/spring/beans/factory/annotation/ServiceBeanNameBuilder;
      11: areturn

  private static void append(java.lang.StringBuilder, java.lang.String);
    Code:
       0: aload_0
       1: ldc           #18                 // String :
       3: invokevirtual #19                 // Method java/lang/StringBuilder.append:(Ljava/lang/String;)Ljava/lang/StringBuilder;
       6: pop
       7: aload_1
       8: invokestatic  #20                 // Method org/springframework/util/StringUtils.hasText:(Ljava/lang/String;)Z
      11: ifeq          20
      14: aload_0
      15: aload_1
      16: invokevirtual #19                 // Method java/lang/StringBuilder.append:(Ljava/lang/String;)Ljava/lang/StringBuilder;
      19: pop
      20: return

  public org.apache.dubbo.config.spring.beans.factory.annotation.ServiceBeanNameBuilder group(java.lang.String);
    Code:
       0: aload_0
       1: aload_1
       2: putfield      #21                 // Field group:Ljava/lang/String;
       5: aload_0
       6: areturn

  public org.apache.dubbo.config.spring.beans.factory.annotation.ServiceBeanNameBuilder version(java.lang.String);
    Code:
       0: aload_0
       1: aload_1
       2: putfield      #22                 // Field version:Ljava/lang/String;
       5: aload_0
       6: areturn

  public java.lang.String build();
    Code:
       0: new           #23                 // class java/lang/StringBuilder
       3: dup
       4: ldc           #24                 // String ServiceBean
       6: invokespecial #25                 // Method java/lang/StringBuilder."<init>":(Ljava/lang/String;)V
       9: astore_1
      10: aload_1
      11: aload_0
      12: getfield      #4                  // Field interfaceClassName:Ljava/lang/String;
      15: invokestatic  #26                 // Method append:(Ljava/lang/StringBuilder;Ljava/lang/String;)V
      18: aload_1
      19: aload_0
      20: getfield      #22                 // Field version:Ljava/lang/String;
      23: invokestatic  #26                 // Method append:(Ljava/lang/StringBuilder;Ljava/lang/String;)V
      26: aload_1
      27: aload_0
      28: getfield      #21                 // Field group:Ljava/lang/String;
      31: invokestatic  #26                 // Method append:(Ljava/lang/StringBuilder;Ljava/lang/String;)V
      34: aload_1
      35: invokevirtual #27                 // Method java/lang/StringBuilder.toString:()Ljava/lang/String;
      38: astore_2
      39: aload_0
      40: getfield      #5                  // Field environment:Lorg/springframework/core/env/Environment;
      43: aload_2
      44: invokeinterface #28,  2           // InterfaceMethod org/springframework/core/env/Environment.resolvePlaceholders:(Ljava/lang/String;)Ljava/lang/String;
      49: areturn
}
