Compiled from "MetadataServiceNameMapping.java"
public class org.apache.dubbo.registry.client.metadata.MetadataServiceNameMapping extends org.apache.dubbo.metadata.AbstractServiceNameMapping {
  private final org.apache.dubbo.common.logger.ErrorTypeAwareLogger logger;

  private static final java.util.List<java.lang.String> IGNORED_SERVICE_INTERFACES;

  private final int casRetryTimes;

  private final int casRetryWaitTime;

  protected org.apache.dubbo.metadata.report.MetadataReportInstance metadataReportInstance;

  public org.apache.dubbo.registry.client.metadata.MetadataServiceNameMapping(org.apache.dubbo.rpc.model.ApplicationModel);
    Code:
       0: aload_0
       1: aload_1
       2: invokespecial #4                  // Method org/apache/dubbo/metadata/AbstractServiceNameMapping."<init>":(Lorg/apache/dubbo/rpc/model/ApplicationModel;)V
       5: aload_0
       6: aload_0
       7: invokevirtual #5                  // Method java/lang/Object.getClass:()Ljava/lang/Class;
      10: invokestatic  #6                  // Method org/apache/dubbo/common/logger/LoggerFactory.getErrorTypeAwareLogger:(Ljava/lang/Class;)Lorg/apache/dubbo/common/logger/ErrorTypeAwareLogger;
      13: putfield      #7                  // Field logger:Lorg/apache/dubbo/common/logger/ErrorTypeAwareLogger;
      16: aload_0
      17: aload_1
      18: invokevirtual #8                  // Method org/apache/dubbo/rpc/model/ApplicationModel.getBeanFactory:()Lorg/apache/dubbo/common/beans/factory/ScopeBeanFactory;
      21: ldc           #9                  // class org/apache/dubbo/metadata/report/MetadataReportInstance
      23: invokevirtual #10                 // Method org/apache/dubbo/common/beans/factory/ScopeBeanFactory.getBean:(Ljava/lang/Class;)Ljava/lang/Object;
      26: checkcast     #9                  // class org/apache/dubbo/metadata/report/MetadataReportInstance
      29: putfield      #11                 // Field metadataReportInstance:Lorg/apache/dubbo/metadata/report/MetadataReportInstance;
      32: aload_0
      33: aload_1
      34: invokestatic  #12                 // Method org/apache/dubbo/common/config/ConfigurationUtils.getGlobalConfiguration:(Lorg/apache/dubbo/rpc/model/ScopeModel;)Lorg/apache/dubbo/common/config/Configuration;
      37: ldc           #13                 // String dubbo.metadata-report.cas-retry-times
      39: bipush        10
      41: invokeinterface #14,  3           // InterfaceMethod org/apache/dubbo/common/config/Configuration.getInt:(Ljava/lang/String;I)I
      46: putfield      #15                 // Field casRetryTimes:I
      49: aload_0
      50: aload_1
      51: invokestatic  #12                 // Method org/apache/dubbo/common/config/ConfigurationUtils.getGlobalConfiguration:(Lorg/apache/dubbo/rpc/model/ScopeModel;)Lorg/apache/dubbo/common/config/Configuration;
      54: ldc           #16                 // String dubbo.metadata-report.cas-retry-wait-time
      56: bipush        100
      58: invokeinterface #14,  3           // InterfaceMethod org/apache/dubbo/common/config/Configuration.getInt:(Ljava/lang/String;I)I
      63: putfield      #17                 // Field casRetryWaitTime:I
      66: return

  public boolean hasValidMetadataCenter();
    Code:
       0: aload_0
       1: getfield      #18                 // Field applicationModel:Lorg/apache/dubbo/rpc/model/ApplicationModel;
       4: invokevirtual #19                 // Method org/apache/dubbo/rpc/model/ApplicationModel.getApplicationConfigManager:()Lorg/apache/dubbo/config/context/ConfigManager;
       7: invokevirtual #20                 // Method org/apache/dubbo/config/context/ConfigManager.getMetadataConfigs:()Ljava/util/Collection;
      10: invokestatic  #21                 // Method org/apache/dubbo/common/utils/CollectionUtils.isEmpty:(Ljava/util/Collection;)Z
      13: ifne          20
      16: iconst_1
      17: goto          21
      20: iconst_0
      21: ireturn

  public boolean map(org.apache.dubbo.common.URL);
    Code:
       0: aload_0
       1: getfield      #18                 // Field applicationModel:Lorg/apache/dubbo/rpc/model/ApplicationModel;
       4: invokevirtual #19                 // Method org/apache/dubbo/rpc/model/ApplicationModel.getApplicationConfigManager:()Lorg/apache/dubbo/config/context/ConfigManager;
       7: invokevirtual #20                 // Method org/apache/dubbo/config/context/ConfigManager.getMetadataConfigs:()Ljava/util/Collection;
      10: invokestatic  #21                 // Method org/apache/dubbo/common/utils/CollectionUtils.isEmpty:(Ljava/util/Collection;)Z
      13: ifeq          35
      16: aload_0
      17: getfield      #7                  // Field logger:Lorg/apache/dubbo/common/logger/ErrorTypeAwareLogger;
      20: ldc           #22                 // String 0-2
      22: ldc           #23                 // String
      24: ldc           #23                 // String
      26: ldc           #24                 // String No valid metadata config center found for mapping report.
      28: invokeinterface #25,  5           // InterfaceMethod org/apache/dubbo/common/logger/ErrorTypeAwareLogger.warn:(Ljava/lang/String;Ljava/lang/String;Ljava/lang/String;Ljava/lang/String;)V
      33: iconst_0
      34: ireturn
      35: aload_1
      36: invokevirtual #26                 // Method org/apache/dubbo/common/URL.getServiceInterface:()Ljava/lang/String;
      39: astore_2
      40: getstatic     #27                 // Field IGNORED_SERVICE_INTERFACES:Ljava/util/List;
      43: aload_2
      44: invokeinterface #28,  2           // InterfaceMethod java/util/List.contains:(Ljava/lang/Object;)Z
      49: ifeq          54
      52: iconst_1
      53: ireturn
      54: iconst_1
      55: istore_3
      56: aload_0
      57: getfield      #11                 // Field metadataReportInstance:Lorg/apache/dubbo/metadata/report/MetadataReportInstance;
      60: iconst_1
      61: invokevirtual #29                 // Method org/apache/dubbo/metadata/report/MetadataReportInstance.getMetadataReports:(Z)Ljava/util/Map;
      64: invokeinterface #30,  1           // InterfaceMethod java/util/Map.entrySet:()Ljava/util/Set;
      69: invokeinterface #31,  1           // InterfaceMethod java/util/Set.iterator:()Ljava/util/Iterator;
      74: astore        4
      76: aload         4
      78: invokeinterface #32,  1           // InterfaceMethod java/util/Iterator.hasNext:()Z
      83: ifeq          465
      86: aload         4
      88: invokeinterface #33,  1           // InterfaceMethod java/util/Iterator.next:()Ljava/lang/Object;
      93: checkcast     #34                 // class java/util/Map$Entry
      96: astore        5
      98: aload         5
     100: invokeinterface #35,  1           // InterfaceMethod java/util/Map$Entry.getValue:()Ljava/lang/Object;
     105: checkcast     #36                 // class org/apache/dubbo/metadata/report/MetadataReport
     108: astore        6
     110: aload_0
     111: getfield      #18                 // Field applicationModel:Lorg/apache/dubbo/rpc/model/ApplicationModel;
     114: invokevirtual #37                 // Method org/apache/dubbo/rpc/model/ApplicationModel.getApplicationName:()Ljava/lang/String;
     117: astore        7
     119: aload         6
     121: aload_2
     122: aload         7
     124: aload_1
     125: invokeinterface #38,  4           // InterfaceMethod org/apache/dubbo/metadata/report/MetadataReport.registerServiceAppMapping:(Ljava/lang/String;Ljava/lang/String;Lorg/apache/dubbo/common/URL;)Z
     130: ifeq          136
     133: goto          76
     136: iconst_0
     137: istore        8
     139: iconst_1
     140: istore        9
     142: aload         7
     144: astore        10
     146: aload         6
     148: aload_2
     149: ldc           #40                 // String mapping
     151: invokeinterface #41,  3           // InterfaceMethod org/apache/dubbo/metadata/report/MetadataReport.getConfigItem:(Ljava/lang/String;Ljava/lang/String;)Lorg/apache/dubbo/common/config/configcenter/ConfigItem;
     156: astore        11
     158: aload         11
     160: invokevirtual #42                 // Method org/apache/dubbo/common/config/configcenter/ConfigItem.getContent:()Ljava/lang/String;
     163: astore        12
     165: aload         12
     167: invokestatic  #43                 // Method org/apache/dubbo/common/utils/StringUtils.isNotEmpty:(Ljava/lang/String;)Z
     170: ifeq          271
     173: aload         12
     175: ldc           #44                 // String ,
     177: invokevirtual #45                 // Method java/lang/String.split:(Ljava/lang/String;)[Ljava/lang/String;
     180: astore        13
     182: aload         13
     184: arraylength
     185: ifle          236
     188: aload         13
     190: astore        14
     192: aload         14
     194: arraylength
     195: istore        15
     197: iconst_0
     198: istore        16
     200: iload         16
     202: iload         15
     204: if_icmpge     236
     207: aload         14
     209: iload         16
     211: aaload
     212: astore        17
     214: aload         17
     216: aload         7
     218: invokevirtual #46                 // Method java/lang/String.equals:(Ljava/lang/Object;)Z
     221: ifeq          230
     224: iconst_1
     225: istore        8
     227: goto          236
     230: iinc          16, 1
     233: goto          200
     236: iload         8
     238: ifeq          244
     241: goto          411
     244: new           #47                 // class java/lang/StringBuilder
     247: dup
     248: invokespecial #48                 // Method java/lang/StringBuilder."<init>":()V
     251: aload         12
     253: invokevirtual #49                 // Method java/lang/StringBuilder.append:(Ljava/lang/String;)Ljava/lang/StringBuilder;
     256: ldc           #44                 // String ,
     258: invokevirtual #49                 // Method java/lang/StringBuilder.append:(Ljava/lang/String;)Ljava/lang/StringBuilder;
     261: aload         7
     263: invokevirtual #49                 // Method java/lang/StringBuilder.append:(Ljava/lang/String;)Ljava/lang/StringBuilder;
     266: invokevirtual #50                 // Method java/lang/StringBuilder.toString:()Ljava/lang/String;
     269: astore        10
     271: aload         6
     273: aload_2
     274: ldc           #40                 // String mapping
     276: aload         10
     278: aload         11
     280: invokevirtual #51                 // Method org/apache/dubbo/common/config/configcenter/ConfigItem.getTicket:()Ljava/lang/Object;
     283: invokeinterface #52,  5           // InterfaceMethod org/apache/dubbo/metadata/report/MetadataReport.registerServiceAppMapping:(Ljava/lang/String;Ljava/lang/String;Ljava/lang/String;Ljava/lang/Object;)Z
     288: istore        8
     290: iload         8
     292: ifne          394
     295: invokestatic  #53                 // Method java/util/concurrent/ThreadLocalRandom.current:()Ljava/util/concurrent/ThreadLocalRandom;
     298: aload_0
     299: getfield      #17                 // Field casRetryWaitTime:I
     302: invokevirtual #54                 // Method java/util/concurrent/ThreadLocalRandom.nextInt:(I)I
     305: istore        13
     307: aload_0
     308: getfield      #7                  // Field logger:Lorg/apache/dubbo/common/logger/ErrorTypeAwareLogger;
     311: new           #47                 // class java/lang/StringBuilder
     314: dup
     315: invokespecial #48                 // Method java/lang/StringBuilder."<init>":()V
     318: ldc           #55                 // String Failed to publish service name mapping to metadata center by cas operation. Times:
     320: invokevirtual #49                 // Method java/lang/StringBuilder.append:(Ljava/lang/String;)Ljava/lang/StringBuilder;
     323: iload         9
     325: invokevirtual #56                 // Method java/lang/StringBuilder.append:(I)Ljava/lang/StringBuilder;
     328: ldc           #57                 // String . Next retry delay:
     330: invokevirtual #49                 // Method java/lang/StringBuilder.append:(Ljava/lang/String;)Ljava/lang/StringBuilder;
     333: iload         13
     335: invokevirtual #56                 // Method java/lang/StringBuilder.append:(I)Ljava/lang/StringBuilder;
     338: ldc           #58                 // String . Service Interface:
     340: invokevirtual #49                 // Method java/lang/StringBuilder.append:(Ljava/lang/String;)Ljava/lang/StringBuilder;
     343: aload_2
     344: invokevirtual #49                 // Method java/lang/StringBuilder.append:(Ljava/lang/String;)Ljava/lang/StringBuilder;
     347: ldc           #59                 // String . Origin Content:
     349: invokevirtual #49                 // Method java/lang/StringBuilder.append:(Ljava/lang/String;)Ljava/lang/StringBuilder;
     352: aload         12
     354: invokevirtual #49                 // Method java/lang/StringBuilder.append:(Ljava/lang/String;)Ljava/lang/StringBuilder;
     357: ldc           #60                 // String . Ticket:
     359: invokevirtual #49                 // Method java/lang/StringBuilder.append:(Ljava/lang/String;)Ljava/lang/StringBuilder;
     362: aload         11
     364: invokevirtual #51                 // Method org/apache/dubbo/common/config/configcenter/ConfigItem.getTicket:()Ljava/lang/Object;
     367: invokevirtual #61                 // Method java/lang/StringBuilder.append:(Ljava/lang/Object;)Ljava/lang/StringBuilder;
     370: ldc           #62                 // String . Excepted context:
     372: invokevirtual #49                 // Method java/lang/StringBuilder.append:(Ljava/lang/String;)Ljava/lang/StringBuilder;
     375: aload         10
     377: invokevirtual #49                 // Method java/lang/StringBuilder.append:(Ljava/lang/String;)Ljava/lang/StringBuilder;
     380: invokevirtual #50                 // Method java/lang/StringBuilder.toString:()Ljava/lang/String;
     383: invokeinterface #63,  2           // InterfaceMethod org/apache/dubbo/common/logger/ErrorTypeAwareLogger.info:(Ljava/lang/String;)V
     388: iload         13
     390: i2l
     391: invokestatic  #64                 // Method java/lang/Thread.sleep:(J)V
     394: iload         8
     396: ifne          411
     399: iload         9
     401: iinc          9, 1
     404: aload_0
     405: getfield      #15                 // Field casRetryTimes:I
     408: if_icmple     146
     411: iload         8
     413: ifne          418
     416: iconst_0
     417: istore_3
     418: goto          462
     421: astore        8
     423: iconst_0
     424: istore_3
     425: aload_0
     426: getfield      #7                  // Field logger:Lorg/apache/dubbo/common/logger/ErrorTypeAwareLogger;
     429: ldc           #66                 // String 99-0
     431: ldc           #67                 // String unknown error in registry module
     433: ldc           #23                 // String
     435: new           #47                 // class java/lang/StringBuilder
     438: dup
     439: invokespecial #48                 // Method java/lang/StringBuilder."<init>":()V
     442: ldc           #68                 // String Failed registering mapping to remote.
     444: invokevirtual #49                 // Method java/lang/StringBuilder.append:(Ljava/lang/String;)Ljava/lang/StringBuilder;
     447: aload         6
     449: invokevirtual #61                 // Method java/lang/StringBuilder.append:(Ljava/lang/Object;)Ljava/lang/StringBuilder;
     452: invokevirtual #50                 // Method java/lang/StringBuilder.toString:()Ljava/lang/String;
     455: aload         8
     457: invokeinterface #69,  6           // InterfaceMethod org/apache/dubbo/common/logger/ErrorTypeAwareLogger.warn:(Ljava/lang/String;Ljava/lang/String;Ljava/lang/String;Ljava/lang/String;Ljava/lang/Throwable;)V
     462: goto          76
     465: iload_3
     466: ireturn
    Exception table:
       from    to  target type
         119   133   421   Class java/lang/Exception
         136   418   421   Class java/lang/Exception

  public java.util.Set<java.lang.String> get(org.apache.dubbo.common.URL);
    Code:
       0: aload_1
       1: invokevirtual #26                 // Method org/apache/dubbo/common/URL.getServiceInterface:()Ljava/lang/String;
       4: astore_2
       5: aload_0
       6: aload_1
       7: invokevirtual #70                 // Method getRegistryCluster:(Lorg/apache/dubbo/common/URL;)Ljava/lang/String;
      10: astore_3
      11: aload_0
      12: getfield      #11                 // Field metadataReportInstance:Lorg/apache/dubbo/metadata/report/MetadataReportInstance;
      15: aload_3
      16: invokevirtual #71                 // Method org/apache/dubbo/metadata/report/MetadataReportInstance.getMetadataReport:(Ljava/lang/String;)Lorg/apache/dubbo/metadata/report/MetadataReport;
      19: astore        4
      21: aload         4
      23: ifnonnull     30
      26: invokestatic  #72                 // Method java/util/Collections.emptySet:()Ljava/util/Set;
      29: areturn
      30: aload         4
      32: aload_2
      33: aload_1
      34: invokeinterface #73,  3           // InterfaceMethod org/apache/dubbo/metadata/report/MetadataReport.getServiceAppMapping:(Ljava/lang/String;Lorg/apache/dubbo/common/URL;)Ljava/util/Set;
      39: areturn

  public java.util.Set<java.lang.String> getAndListen(org.apache.dubbo.common.URL, org.apache.dubbo.metadata.MappingListener);
    Code:
       0: aload_1
       1: invokevirtual #26                 // Method org/apache/dubbo/common/URL.getServiceInterface:()Ljava/lang/String;
       4: astore_3
       5: aload_0
       6: aload_1
       7: invokevirtual #70                 // Method getRegistryCluster:(Lorg/apache/dubbo/common/URL;)Ljava/lang/String;
      10: astore        4
      12: aload_0
      13: getfield      #11                 // Field metadataReportInstance:Lorg/apache/dubbo/metadata/report/MetadataReportInstance;
      16: aload         4
      18: invokevirtual #71                 // Method org/apache/dubbo/metadata/report/MetadataReportInstance.getMetadataReport:(Ljava/lang/String;)Lorg/apache/dubbo/metadata/report/MetadataReport;
      21: astore        5
      23: aload         5
      25: ifnonnull     32
      28: invokestatic  #72                 // Method java/util/Collections.emptySet:()Ljava/util/Set;
      31: areturn
      32: aload         5
      34: aload_3
      35: aload_2
      36: aload_1
      37: invokeinterface #74,  4           // InterfaceMethod org/apache/dubbo/metadata/report/MetadataReport.getServiceAppMapping:(Ljava/lang/String;Lorg/apache/dubbo/metadata/MappingListener;Lorg/apache/dubbo/common/URL;)Ljava/util/Set;
      42: areturn

  protected void removeListener(org.apache.dubbo.common.URL, org.apache.dubbo.metadata.MappingListener);
    Code:
       0: aload_1
       1: invokevirtual #26                 // Method org/apache/dubbo/common/URL.getServiceInterface:()Ljava/lang/String;
       4: astore_3
       5: aload_0
       6: aload_1
       7: invokevirtual #70                 // Method getRegistryCluster:(Lorg/apache/dubbo/common/URL;)Ljava/lang/String;
      10: astore        4
      12: aload_0
      13: getfield      #11                 // Field metadataReportInstance:Lorg/apache/dubbo/metadata/report/MetadataReportInstance;
      16: aload         4
      18: invokevirtual #71                 // Method org/apache/dubbo/metadata/report/MetadataReportInstance.getMetadataReport:(Ljava/lang/String;)Lorg/apache/dubbo/metadata/report/MetadataReport;
      21: astore        5
      23: aload         5
      25: ifnonnull     29
      28: return
      29: aload         5
      31: aload_3
      32: aload_2
      33: invokeinterface #75,  3           // InterfaceMethod org/apache/dubbo/metadata/report/MetadataReport.removeServiceAppMappingListener:(Ljava/lang/String;Lorg/apache/dubbo/metadata/MappingListener;)V
      38: return

  protected java.lang.String getRegistryCluster(org.apache.dubbo.common.URL);
    Code:
       0: aload_1
       1: invokestatic  #76                 // InterfaceMethod org/apache/dubbo/registry/client/RegistryClusterIdentifier.getExtension:(Lorg/apache/dubbo/common/URL;)Lorg/apache/dubbo/registry/client/RegistryClusterIdentifier;
       4: aload_1
       5: invokeinterface #77,  2           // InterfaceMethod org/apache/dubbo/registry/client/RegistryClusterIdentifier.providerKey:(Lorg/apache/dubbo/common/URL;)Ljava/lang/String;
      10: astore_2
      11: aload_2
      12: ifnonnull     18
      15: ldc           #78                 // String default
      17: astore_2
      18: aload_2
      19: ldc           #44                 // String ,
      21: invokevirtual #79                 // Method java/lang/String.indexOf:(Ljava/lang/String;)I
      24: istore_3
      25: iload_3
      26: ifle          36
      29: aload_2
      30: iconst_0
      31: iload_3
      32: invokevirtual #80                 // Method java/lang/String.substring:(II)Ljava/lang/String;
      35: astore_2
      36: aload_2
      37: areturn

  static {};
    Code:
       0: ldc           #81                 // class org/apache/dubbo/metadata/MetadataService
       2: invokevirtual #82                 // Method java/lang/Class.getName:()Ljava/lang/String;
       5: invokestatic  #83                 // Method java/util/Collections.singletonList:(Ljava/lang/Object;)Ljava/util/List;
       8: putstatic     #27                 // Field IGNORED_SERVICE_INTERFACES:Ljava/util/List;
      11: return
}
