Compiled from "MetadataServiceDelegation.java"
public class org.apache.dubbo.registry.client.metadata.MetadataServiceDelegation implements org.apache.dubbo.metadata.MetadataService,org.apache.dubbo.common.resource.Disposable {
  org.apache.dubbo.common.logger.ErrorTypeAwareLogger logger;

  private final org.apache.dubbo.rpc.model.ApplicationModel applicationModel;

  private final org.apache.dubbo.registry.support.RegistryManager registryManager;

  private java.util.concurrent.ConcurrentMap<java.lang.String, org.apache.dubbo.metadata.InstanceMetadataChangedListener> instanceMetadataChangedListenerMap;

  private org.apache.dubbo.common.URL url;

  private java.lang.String instanceMetadata;

  public org.apache.dubbo.registry.client.metadata.MetadataServiceDelegation(org.apache.dubbo.rpc.model.ApplicationModel);
    Code:
       0: aload_0
       1: invokespecial #3                  // Method java/lang/Object."<init>":()V
       4: aload_0
       5: aload_0
       6: invokevirtual #4                  // Method java/lang/Object.getClass:()Ljava/lang/Class;
       9: invokestatic  #5                  // Method org/apache/dubbo/common/logger/LoggerFactory.getErrorTypeAwareLogger:(Ljava/lang/Class;)Lorg/apache/dubbo/common/logger/ErrorTypeAwareLogger;
      12: putfield      #6                  // Field logger:Lorg/apache/dubbo/common/logger/ErrorTypeAwareLogger;
      15: aload_0
      16: new           #7                  // class java/util/concurrent/ConcurrentHashMap
      19: dup
      20: invokespecial #8                  // Method java/util/concurrent/ConcurrentHashMap."<init>":()V
      23: putfield      #9                  // Field instanceMetadataChangedListenerMap:Ljava/util/concurrent/ConcurrentMap;
      26: aload_0
      27: aload_1
      28: putfield      #10                 // Field applicationModel:Lorg/apache/dubbo/rpc/model/ApplicationModel;
      31: aload_0
      32: aload_1
      33: invokestatic  #11                 // Method org/apache/dubbo/registry/support/RegistryManager.getInstance:(Lorg/apache/dubbo/rpc/model/ApplicationModel;)Lorg/apache/dubbo/registry/support/RegistryManager;
      36: putfield      #12                 // Field registryManager:Lorg/apache/dubbo/registry/support/RegistryManager;
      39: return

  public java.lang.String serviceName();
    Code:
       0: aload_0
       1: getfield      #10                 // Field applicationModel:Lorg/apache/dubbo/rpc/model/ApplicationModel;
       4: invokestatic  #13                 // Method org/apache/dubbo/rpc/model/ApplicationModel.ofNullable:(Lorg/apache/dubbo/rpc/model/ApplicationModel;)Lorg/apache/dubbo/rpc/model/ApplicationModel;
       7: invokevirtual #14                 // Method org/apache/dubbo/rpc/model/ApplicationModel.getApplicationName:()Ljava/lang/String;
      10: areturn

  public org.apache.dubbo.common.URL getMetadataURL();
    Code:
       0: aload_0
       1: getfield      #15                 // Field url:Lorg/apache/dubbo/common/URL;
       4: areturn

  public void setMetadataURL(org.apache.dubbo.common.URL);
    Code:
       0: aload_0
       1: aload_1
       2: putfield      #15                 // Field url:Lorg/apache/dubbo/common/URL;
       5: return

  public java.util.SortedSet<java.lang.String> getSubscribedURLs();
    Code:
       0: aload_0
       1: invokespecial #16                 // Method getAllUnmodifiableSubscribedURLs:()Ljava/util/SortedSet;
       4: areturn

  private java.util.SortedSet<java.lang.String> getAllUnmodifiableServiceURLs();
    Code:
       0: new           #17                 // class java/util/TreeSet
       3: dup
       4: getstatic     #18                 // Field org/apache/dubbo/registry/client/metadata/MetadataServiceDelegation$URLComparator.INSTANCE:Lorg/apache/dubbo/registry/client/metadata/MetadataServiceDelegation$URLComparator;
       7: invokespecial #19                 // Method java/util/TreeSet."<init>":(Ljava/util/Comparator;)V
      10: astore_1
      11: aload_0
      12: getfield      #12                 // Field registryManager:Lorg/apache/dubbo/registry/support/RegistryManager;
      15: invokevirtual #20                 // Method org/apache/dubbo/registry/support/RegistryManager.getServiceDiscoveries:()Ljava/util/List;
      18: astore_2
      19: aload_2
      20: invokeinterface #21,  1           // InterfaceMethod java/util/List.iterator:()Ljava/util/Iterator;
      25: astore_3
      26: aload_3
      27: invokeinterface #22,  1           // InterfaceMethod java/util/Iterator.hasNext:()Z
      32: ifeq          188
      35: aload_3
      36: invokeinterface #23,  1           // InterfaceMethod java/util/Iterator.next:()Ljava/lang/Object;
      41: checkcast     #24                 // class org/apache/dubbo/registry/client/ServiceDiscovery
      44: astore        4
      46: aload         4
      48: invokeinterface #25,  1           // InterfaceMethod org/apache/dubbo/registry/client/ServiceDiscovery.getLocalMetadata:()Lorg/apache/dubbo/metadata/MetadataInfo;
      53: astore        5
      55: aload         5
      57: invokevirtual #26                 // Method org/apache/dubbo/metadata/MetadataInfo.getExportedServiceURLs:()Ljava/util/concurrent/ConcurrentNavigableMap;
      60: astore        6
      62: aload         6
      64: ifnonnull     70
      67: goto          26
      70: aload         6
      72: invokeinterface #27,  1           // InterfaceMethod java/util/Map.entrySet:()Ljava/util/Set;
      77: invokeinterface #28,  1           // InterfaceMethod java/util/Set.iterator:()Ljava/util/Iterator;
      82: astore        7
      84: aload         7
      86: invokeinterface #22,  1           // InterfaceMethod java/util/Iterator.hasNext:()Z
      91: ifeq          185
      94: aload         7
      96: invokeinterface #23,  1           // InterfaceMethod java/util/Iterator.next:()Ljava/lang/Object;
     101: checkcast     #29                 // class java/util/Map$Entry
     104: astore        8
     106: aload         8
     108: invokeinterface #30,  1           // InterfaceMethod java/util/Map$Entry.getValue:()Ljava/lang/Object;
     113: checkcast     #31                 // class java/util/SortedSet
     116: astore        9
     118: aload         9
     120: ifnull        182
     123: aload         9
     125: invokeinterface #32,  1           // InterfaceMethod java/util/SortedSet.iterator:()Ljava/util/Iterator;
     130: astore        10
     132: aload         10
     134: invokeinterface #22,  1           // InterfaceMethod java/util/Iterator.hasNext:()Z
     139: ifeq          182
     142: aload         10
     144: invokeinterface #23,  1           // InterfaceMethod java/util/Iterator.next:()Ljava/lang/Object;
     149: checkcast     #33                 // class org/apache/dubbo/common/URL
     152: astore        11
     154: ldc           #34                 // class org/apache/dubbo/metadata/MetadataService
     156: invokevirtual #35                 // Method java/lang/Class.getName:()Ljava/lang/String;
     159: aload         11
     161: invokevirtual #36                 // Method org/apache/dubbo/common/URL.getServiceInterface:()Ljava/lang/String;
     164: invokevirtual #37                 // Method java/lang/String.equals:(Ljava/lang/Object;)Z
     167: ifne          179
     170: aload_1
     171: aload         11
     173: invokeinterface #38,  2           // InterfaceMethod java/util/SortedSet.add:(Ljava/lang/Object;)Z
     178: pop
     179: goto          132
     182: goto          84
     185: goto          26
     188: aload_1
     189: invokestatic  #39                 // InterfaceMethod org/apache/dubbo/metadata/MetadataService.toSortedStrings:(Ljava/lang/Iterable;)Ljava/util/SortedSet;
     192: areturn

  private java.util.SortedSet<java.lang.String> getAllUnmodifiableSubscribedURLs();
    Code:
       0: new           #17                 // class java/util/TreeSet
       3: dup
       4: getstatic     #18                 // Field org/apache/dubbo/registry/client/metadata/MetadataServiceDelegation$URLComparator.INSTANCE:Lorg/apache/dubbo/registry/client/metadata/MetadataServiceDelegation$URLComparator;
       7: invokespecial #19                 // Method java/util/TreeSet."<init>":(Ljava/util/Comparator;)V
      10: astore_1
      11: aload_0
      12: getfield      #12                 // Field registryManager:Lorg/apache/dubbo/registry/support/RegistryManager;
      15: invokevirtual #20                 // Method org/apache/dubbo/registry/support/RegistryManager.getServiceDiscoveries:()Ljava/util/List;
      18: astore_2
      19: aload_2
      20: invokeinterface #21,  1           // InterfaceMethod java/util/List.iterator:()Ljava/util/Iterator;
      25: astore_3
      26: aload_3
      27: invokeinterface #22,  1           // InterfaceMethod java/util/Iterator.hasNext:()Z
      32: ifeq          188
      35: aload_3
      36: invokeinterface #23,  1           // InterfaceMethod java/util/Iterator.next:()Ljava/lang/Object;
      41: checkcast     #24                 // class org/apache/dubbo/registry/client/ServiceDiscovery
      44: astore        4
      46: aload         4
      48: invokeinterface #25,  1           // InterfaceMethod org/apache/dubbo/registry/client/ServiceDiscovery.getLocalMetadata:()Lorg/apache/dubbo/metadata/MetadataInfo;
      53: astore        5
      55: aload         5
      57: invokevirtual #40                 // Method org/apache/dubbo/metadata/MetadataInfo.getSubscribedServiceURLs:()Ljava/util/concurrent/ConcurrentNavigableMap;
      60: astore        6
      62: aload         6
      64: ifnonnull     70
      67: goto          26
      70: aload         6
      72: invokeinterface #27,  1           // InterfaceMethod java/util/Map.entrySet:()Ljava/util/Set;
      77: invokeinterface #28,  1           // InterfaceMethod java/util/Set.iterator:()Ljava/util/Iterator;
      82: astore        7
      84: aload         7
      86: invokeinterface #22,  1           // InterfaceMethod java/util/Iterator.hasNext:()Z
      91: ifeq          185
      94: aload         7
      96: invokeinterface #23,  1           // InterfaceMethod java/util/Iterator.next:()Ljava/lang/Object;
     101: checkcast     #29                 // class java/util/Map$Entry
     104: astore        8
     106: aload         8
     108: invokeinterface #30,  1           // InterfaceMethod java/util/Map$Entry.getValue:()Ljava/lang/Object;
     113: checkcast     #31                 // class java/util/SortedSet
     116: astore        9
     118: aload         9
     120: ifnull        182
     123: aload         9
     125: invokeinterface #32,  1           // InterfaceMethod java/util/SortedSet.iterator:()Ljava/util/Iterator;
     130: astore        10
     132: aload         10
     134: invokeinterface #22,  1           // InterfaceMethod java/util/Iterator.hasNext:()Z
     139: ifeq          182
     142: aload         10
     144: invokeinterface #23,  1           // InterfaceMethod java/util/Iterator.next:()Ljava/lang/Object;
     149: checkcast     #33                 // class org/apache/dubbo/common/URL
     152: astore        11
     154: ldc           #34                 // class org/apache/dubbo/metadata/MetadataService
     156: invokevirtual #35                 // Method java/lang/Class.getName:()Ljava/lang/String;
     159: aload         11
     161: invokevirtual #36                 // Method org/apache/dubbo/common/URL.getServiceInterface:()Ljava/lang/String;
     164: invokevirtual #37                 // Method java/lang/String.equals:(Ljava/lang/Object;)Z
     167: ifne          179
     170: aload_1
     171: aload         11
     173: invokeinterface #38,  2           // InterfaceMethod java/util/SortedSet.add:(Ljava/lang/Object;)Z
     178: pop
     179: goto          132
     182: goto          84
     185: goto          26
     188: aload_1
     189: invokestatic  #39                 // InterfaceMethod org/apache/dubbo/metadata/MetadataService.toSortedStrings:(Ljava/lang/Iterable;)Ljava/util/SortedSet;
     192: areturn

  public java.util.SortedSet<java.lang.String> getExportedURLs(java.lang.String, java.lang.String, java.lang.String, java.lang.String);
    Code:
       0: ldc           #41                 // String *
       2: aload_1
       3: invokevirtual #37                 // Method java/lang/String.equals:(Ljava/lang/Object;)Z
       6: ifeq          14
       9: aload_0
      10: invokespecial #42                 // Method getAllUnmodifiableServiceURLs:()Ljava/util/SortedSet;
      13: areturn
      14: aload_1
      15: aload_2
      16: aload_3
      17: invokestatic  #43                 // Method org/apache/dubbo/common/URL.buildKey:(Ljava/lang/String;Ljava/lang/String;Ljava/lang/String;)Ljava/lang/String;
      20: astore        5
      22: aload_0
      23: aload_0
      24: invokespecial #44                 // Method getAllServiceURLs:()Ljava/util/Map;
      27: aload         5
      29: aload         4
      31: invokespecial #45                 // Method getServiceURLs:(Ljava/util/Map;Ljava/lang/String;Ljava/lang/String;)Ljava/util/SortedSet;
      34: invokestatic  #46                 // Method java/util/Collections.unmodifiableSortedSet:(Ljava/util/SortedSet;)Ljava/util/SortedSet;
      37: areturn

  private java.util.Map<java.lang.String, java.util.SortedSet<org.apache.dubbo.common.URL>> getAllServiceURLs();
    Code:
       0: aload_0
       1: getfield      #12                 // Field registryManager:Lorg/apache/dubbo/registry/support/RegistryManager;
       4: invokevirtual #20                 // Method org/apache/dubbo/registry/support/RegistryManager.getServiceDiscoveries:()Ljava/util/List;
       7: astore_1
       8: new           #47                 // class java/util/HashMap
      11: dup
      12: invokespecial #48                 // Method java/util/HashMap."<init>":()V
      15: astore_2
      16: aload_1
      17: invokeinterface #21,  1           // InterfaceMethod java/util/List.iterator:()Ljava/util/Iterator;
      22: astore_3
      23: aload_3
      24: invokeinterface #22,  1           // InterfaceMethod java/util/Iterator.hasNext:()Z
      29: ifeq          70
      32: aload_3
      33: invokeinterface #23,  1           // InterfaceMethod java/util/Iterator.next:()Ljava/lang/Object;
      38: checkcast     #24                 // class org/apache/dubbo/registry/client/ServiceDiscovery
      41: astore        4
      43: aload         4
      45: invokeinterface #25,  1           // InterfaceMethod org/apache/dubbo/registry/client/ServiceDiscovery.getLocalMetadata:()Lorg/apache/dubbo/metadata/MetadataInfo;
      50: astore        5
      52: aload         5
      54: invokevirtual #26                 // Method org/apache/dubbo/metadata/MetadataInfo.getExportedServiceURLs:()Ljava/util/concurrent/ConcurrentNavigableMap;
      57: astore        6
      59: aload_2
      60: aload         6
      62: invokeinterface #49,  2           // InterfaceMethod java/util/Map.putAll:(Ljava/util/Map;)V
      67: goto          23
      70: aload_2
      71: areturn

  public java.util.Set<org.apache.dubbo.common.URL> getExportedServiceURLs();
    Code:
       0: new           #50                 // class java/util/HashSet
       3: dup
       4: invokespecial #51                 // Method java/util/HashSet."<init>":()V
       7: astore_1
       8: aload_0
       9: getfield      #12                 // Field registryManager:Lorg/apache/dubbo/registry/support/RegistryManager;
      12: invokevirtual #52                 // Method org/apache/dubbo/registry/support/RegistryManager.getRegistries:()Ljava/util/Collection;
      15: pop
      16: aload_0
      17: invokespecial #44                 // Method getAllServiceURLs:()Ljava/util/Map;
      20: invokeinterface #27,  1           // InterfaceMethod java/util/Map.entrySet:()Ljava/util/Set;
      25: invokeinterface #28,  1           // InterfaceMethod java/util/Set.iterator:()Ljava/util/Iterator;
      30: astore_2
      31: aload_2
      32: invokeinterface #22,  1           // InterfaceMethod java/util/Iterator.hasNext:()Z
      37: ifeq          69
      40: aload_2
      41: invokeinterface #23,  1           // InterfaceMethod java/util/Iterator.next:()Ljava/lang/Object;
      46: checkcast     #29                 // class java/util/Map$Entry
      49: astore_3
      50: aload_1
      51: aload_3
      52: invokeinterface #30,  1           // InterfaceMethod java/util/Map$Entry.getValue:()Ljava/lang/Object;
      57: checkcast     #53                 // class java/util/Collection
      60: invokeinterface #54,  2           // InterfaceMethod java/util/Set.addAll:(Ljava/util/Collection;)Z
      65: pop
      66: goto          31
      69: aload_1
      70: areturn

  public java.lang.String getServiceDefinition(java.lang.String, java.lang.String, java.lang.String);
    Code:
       0: ldc           #55                 // String
       2: areturn

  public java.lang.String getServiceDefinition(java.lang.String);
    Code:
       0: ldc           #55                 // String
       2: areturn

  public org.apache.dubbo.metadata.MetadataInfo getMetadataInfo(java.lang.String);
    Code:
       0: aload_1
       1: invokestatic  #56                 // Method org/apache/dubbo/common/utils/StringUtils.isEmpty:(Ljava/lang/String;)Z
       4: ifeq          9
       7: aconst_null
       8: areturn
       9: aload_0
      10: getfield      #12                 // Field registryManager:Lorg/apache/dubbo/registry/support/RegistryManager;
      13: invokevirtual #20                 // Method org/apache/dubbo/registry/support/RegistryManager.getServiceDiscoveries:()Ljava/util/List;
      16: invokeinterface #21,  1           // InterfaceMethod java/util/List.iterator:()Ljava/util/Iterator;
      21: astore_2
      22: aload_2
      23: invokeinterface #22,  1           // InterfaceMethod java/util/Iterator.hasNext:()Z
      28: ifeq          73
      31: aload_2
      32: invokeinterface #23,  1           // InterfaceMethod java/util/Iterator.next:()Ljava/lang/Object;
      37: checkcast     #24                 // class org/apache/dubbo/registry/client/ServiceDiscovery
      40: astore_3
      41: aload_3
      42: aload_1
      43: invokeinterface #57,  2           // InterfaceMethod org/apache/dubbo/registry/client/ServiceDiscovery.getLocalMetadata:(Ljava/lang/String;)Lorg/apache/dubbo/metadata/MetadataInfo;
      48: astore        4
      50: aload         4
      52: ifnull        70
      55: aload_1
      56: aload         4
      58: invokevirtual #58                 // Method org/apache/dubbo/metadata/MetadataInfo.getRevision:()Ljava/lang/String;
      61: invokevirtual #37                 // Method java/lang/String.equals:(Ljava/lang/Object;)Z
      64: ifeq          70
      67: aload         4
      69: areturn
      70: goto          22
      73: aload_0
      74: getfield      #6                  // Field logger:Lorg/apache/dubbo/common/logger/ErrorTypeAwareLogger;
      77: invokeinterface #59,  1           // InterfaceMethod org/apache/dubbo/common/logger/ErrorTypeAwareLogger.isWarnEnabled:()Z
      82: ifeq          119
      85: aload_0
      86: getfield      #6                  // Field logger:Lorg/apache/dubbo/common/logger/ErrorTypeAwareLogger;
      89: ldc           #60                 // String 1-39
      91: ldc           #55                 // String
      93: ldc           #55                 // String
      95: new           #61                 // class java/lang/StringBuilder
      98: dup
      99: invokespecial #62                 // Method java/lang/StringBuilder."<init>":()V
     102: ldc           #63                 // String metadata not found for revision:
     104: invokevirtual #64                 // Method java/lang/StringBuilder.append:(Ljava/lang/String;)Ljava/lang/StringBuilder;
     107: aload_1
     108: invokevirtual #64                 // Method java/lang/StringBuilder.append:(Ljava/lang/String;)Ljava/lang/StringBuilder;
     111: invokevirtual #65                 // Method java/lang/StringBuilder.toString:()Ljava/lang/String;
     114: invokeinterface #66,  5           // InterfaceMethod org/apache/dubbo/common/logger/ErrorTypeAwareLogger.warn:(Ljava/lang/String;Ljava/lang/String;Ljava/lang/String;Ljava/lang/String;)V
     119: aconst_null
     120: areturn

  public java.util.List<org.apache.dubbo.metadata.MetadataInfo> getMetadataInfos();
    Code:
       0: new           #67                 // class java/util/ArrayList
       3: dup
       4: invokespecial #68                 // Method java/util/ArrayList."<init>":()V
       7: astore_1
       8: aload_0
       9: getfield      #12                 // Field registryManager:Lorg/apache/dubbo/registry/support/RegistryManager;
      12: invokevirtual #20                 // Method org/apache/dubbo/registry/support/RegistryManager.getServiceDiscoveries:()Ljava/util/List;
      15: invokeinterface #21,  1           // InterfaceMethod java/util/List.iterator:()Ljava/util/Iterator;
      20: astore_2
      21: aload_2
      22: invokeinterface #22,  1           // InterfaceMethod java/util/Iterator.hasNext:()Z
      27: ifeq          56
      30: aload_2
      31: invokeinterface #23,  1           // InterfaceMethod java/util/Iterator.next:()Ljava/lang/Object;
      36: checkcast     #24                 // class org/apache/dubbo/registry/client/ServiceDiscovery
      39: astore_3
      40: aload_1
      41: aload_3
      42: invokeinterface #25,  1           // InterfaceMethod org/apache/dubbo/registry/client/ServiceDiscovery.getLocalMetadata:()Lorg/apache/dubbo/metadata/MetadataInfo;
      47: invokeinterface #69,  2           // InterfaceMethod java/util/List.add:(Ljava/lang/Object;)Z
      52: pop
      53: goto          21
      56: aload_1
      57: areturn

  public void exportInstanceMetadata(java.lang.String);
    Code:
       0: aload_0
       1: aload_1
       2: putfield      #70                 // Field instanceMetadata:Ljava/lang/String;
       5: return

  public java.util.Map<java.lang.String, org.apache.dubbo.metadata.InstanceMetadataChangedListener> getInstanceMetadataChangedListenerMap();
    Code:
       0: aload_0
       1: getfield      #9                  // Field instanceMetadataChangedListenerMap:Ljava/util/concurrent/ConcurrentMap;
       4: areturn

  public java.lang.String getAndListenInstanceMetadata(java.lang.String, org.apache.dubbo.metadata.InstanceMetadataChangedListener);
    Code:
       0: aload_0
       1: getfield      #9                  // Field instanceMetadataChangedListenerMap:Ljava/util/concurrent/ConcurrentMap;
       4: aload_1
       5: aload_2
       6: invokeinterface #71,  3           // InterfaceMethod java/util/concurrent/ConcurrentMap.put:(Ljava/lang/Object;Ljava/lang/Object;)Ljava/lang/Object;
      11: pop
      12: aload_0
      13: getfield      #70                 // Field instanceMetadata:Ljava/lang/String;
      16: areturn

  private java.util.SortedSet<java.lang.String> getServiceURLs(java.util.Map<java.lang.String, java.util.SortedSet<org.apache.dubbo.common.URL>>, java.lang.String, java.lang.String);
    Code:
       0: aload_1
       1: aload_2
       2: invokeinterface #72,  2           // InterfaceMethod java/util/Map.get:(Ljava/lang/Object;)Ljava/lang/Object;
       7: checkcast     #31                 // class java/util/SortedSet
      10: astore        4
      12: aload         4
      14: invokestatic  #73                 // Method org/apache/dubbo/common/utils/CollectionUtils.isEmpty:(Ljava/util/Collection;)Z
      17: ifeq          24
      20: invokestatic  #74                 // Method java/util/Collections.emptySortedSet:()Ljava/util/SortedSet;
      23: areturn
      24: aload         4
      26: invokeinterface #75,  1           // InterfaceMethod java/util/SortedSet.stream:()Ljava/util/stream/Stream;
      31: aload_0
      32: aload_3
      33: invokedynamic #76,  0             // InvokeDynamic #0:test:(Lorg/apache/dubbo/registry/client/metadata/MetadataServiceDelegation;Ljava/lang/String;)Ljava/util/function/Predicate;
      38: invokeinterface #77,  2           // InterfaceMethod java/util/stream/Stream.filter:(Ljava/util/function/Predicate;)Ljava/util/stream/Stream;
      43: invokestatic  #78                 // InterfaceMethod org/apache/dubbo/metadata/MetadataService.toSortedStrings:(Ljava/util/stream/Stream;)Ljava/util/SortedSet;
      46: areturn

  private boolean isAcceptableProtocol(java.lang.String, org.apache.dubbo.common.URL);
    Code:
       0: aload_1
       1: ifnull        28
       4: aload_1
       5: aload_2
       6: ldc           #79                 // String protocol
       8: invokevirtual #80                 // Method org/apache/dubbo/common/URL.getParameter:(Ljava/lang/String;)Ljava/lang/String;
      11: invokevirtual #37                 // Method java/lang/String.equals:(Ljava/lang/Object;)Z
      14: ifne          28
      17: aload_1
      18: aload_2
      19: invokevirtual #81                 // Method org/apache/dubbo/common/URL.getProtocol:()Ljava/lang/String;
      22: invokevirtual #37                 // Method java/lang/String.equals:(Ljava/lang/Object;)Z
      25: ifeq          32
      28: iconst_1
      29: goto          33
      32: iconst_0
      33: ireturn

  public void destroy();
    Code:
       0: return

  private boolean lambda$getServiceURLs$0(java.lang.String, org.apache.dubbo.common.URL);
    Code:
       0: aload_0
       1: aload_1
       2: aload_2
       3: invokespecial #82                 // Method isAcceptableProtocol:(Ljava/lang/String;Lorg/apache/dubbo/common/URL;)Z
       6: ireturn
}
