Compiled from "MetadataUtils.java"
public class org.apache.dubbo.registry.client.metadata.MetadataUtils {
  public static final org.apache.dubbo.common.logger.ErrorTypeAwareLogger logger;

  public org.apache.dubbo.registry.client.metadata.MetadataUtils();
    Code:
       0: aload_0
       1: invokespecial #5                  // Method java/lang/Object."<init>":()V
       4: return

  public static void publishServiceDefinition(org.apache.dubbo.common.URL, org.apache.dubbo.rpc.model.ServiceDescriptor, org.apache.dubbo.rpc.model.ApplicationModel);
    Code:
       0: aload_2
       1: invokestatic  #6                  // Method getMetadataReports:(Lorg/apache/dubbo/rpc/model/ApplicationModel;)Ljava/util/Map;
       4: invokeinterface #7,  1            // InterfaceMethod java/util/Map.size:()I
       9: ifne          31
      12: ldc           #8                  // String Remote Metadata Report Server is not provided or unavailable, will stop registering service definition to remote center!
      14: astore_3
      15: getstatic     #9                  // Field logger:Lorg/apache/dubbo/common/logger/ErrorTypeAwareLogger;
      18: ldc           #10                 // String 1-39
      20: ldc           #11                 // String
      22: ldc           #11                 // String
      24: aload_3
      25: invokeinterface #12,  5           // InterfaceMethod org/apache/dubbo/common/logger/ErrorTypeAwareLogger.warn:(Ljava/lang/String;Ljava/lang/String;Ljava/lang/String;Ljava/lang/String;)V
      30: return
      31: aload_0
      32: invokevirtual #13                 // Method org/apache/dubbo/common/URL.getSide:()Ljava/lang/String;
      35: astore_3
      36: ldc           #14                 // String provider
      38: aload_3
      39: invokevirtual #15                 // Method java/lang/String.equalsIgnoreCase:(Ljava/lang/String;)Z
      42: ifeq          246
      45: aload_0
      46: invokevirtual #16                 // Method org/apache/dubbo/common/URL.getServiceKey:()Ljava/lang/String;
      49: astore        4
      51: aload_1
      52: aload         4
      54: invokeinterface #17,  2           // InterfaceMethod org/apache/dubbo/rpc/model/ServiceDescriptor.getFullServiceDefinition:(Ljava/lang/String;)Lorg/apache/dubbo/metadata/definition/model/FullServiceDefinition;
      59: astore        5
      61: aload         4
      63: invokestatic  #18                 // Method org/apache/dubbo/common/utils/StringUtils.isNotEmpty:(Ljava/lang/String;)Z
      66: ifeq          243
      69: aload         5
      71: ifnull        243
      74: aload         5
      76: aload_0
      77: invokevirtual #19                 // Method org/apache/dubbo/common/URL.getParameters:()Ljava/util/Map;
      80: invokevirtual #20                 // Method org/apache/dubbo/metadata/definition/model/FullServiceDefinition.setParameters:(Ljava/util/Map;)V
      83: aload_2
      84: invokestatic  #6                  // Method getMetadataReports:(Lorg/apache/dubbo/rpc/model/ApplicationModel;)Ljava/util/Map;
      87: invokeinterface #21,  1           // InterfaceMethod java/util/Map.entrySet:()Ljava/util/Set;
      92: invokeinterface #22,  1           // InterfaceMethod java/util/Set.iterator:()Ljava/util/Iterator;
      97: astore        6
      99: aload         6
     101: invokeinterface #23,  1           // InterfaceMethod java/util/Iterator.hasNext:()Z
     106: ifeq          243
     109: aload         6
     111: invokeinterface #24,  1           // InterfaceMethod java/util/Iterator.next:()Ljava/lang/Object;
     116: checkcast     #25                 // class java/util/Map$Entry
     119: astore        7
     121: aload         7
     123: invokeinterface #26,  1           // InterfaceMethod java/util/Map$Entry.getValue:()Ljava/lang/Object;
     128: checkcast     #27                 // class org/apache/dubbo/metadata/report/MetadataReport
     131: astore        8
     133: aload         8
     135: invokeinterface #28,  1           // InterfaceMethod org/apache/dubbo/metadata/report/MetadataReport.shouldReportDefinition:()Z
     140: ifne          182
     143: getstatic     #9                  // Field logger:Lorg/apache/dubbo/common/logger/ErrorTypeAwareLogger;
     146: new           #29                 // class java/lang/StringBuilder
     149: dup
     150: invokespecial #30                 // Method java/lang/StringBuilder."<init>":()V
     153: ldc           #31                 // String Report of service definition is disabled for
     155: invokevirtual #32                 // Method java/lang/StringBuilder.append:(Ljava/lang/String;)Ljava/lang/StringBuilder;
     158: aload         7
     160: invokeinterface #33,  1           // InterfaceMethod java/util/Map$Entry.getKey:()Ljava/lang/Object;
     165: checkcast     #34                 // class java/lang/String
     168: invokevirtual #32                 // Method java/lang/StringBuilder.append:(Ljava/lang/String;)Ljava/lang/StringBuilder;
     171: invokevirtual #35                 // Method java/lang/StringBuilder.toString:()Ljava/lang/String;
     174: invokeinterface #36,  2           // InterfaceMethod org/apache/dubbo/common/logger/ErrorTypeAwareLogger.info:(Ljava/lang/String;)V
     179: goto          99
     182: aload         8
     184: new           #37                 // class org/apache/dubbo/metadata/report/identifier/MetadataIdentifier
     187: dup
     188: aload_0
     189: invokevirtual #38                 // Method org/apache/dubbo/common/URL.getServiceInterface:()Ljava/lang/String;
     192: aload_0
     193: invokevirtual #39                 // Method org/apache/dubbo/common/URL.getVersion:()Ljava/lang/String;
     196: ifnonnull     204
     199: ldc           #11                 // String
     201: goto          208
     204: aload_0
     205: invokevirtual #39                 // Method org/apache/dubbo/common/URL.getVersion:()Ljava/lang/String;
     208: aload_0
     209: invokevirtual #40                 // Method org/apache/dubbo/common/URL.getGroup:()Ljava/lang/String;
     212: ifnonnull     220
     215: ldc           #11                 // String
     217: goto          224
     220: aload_0
     221: invokevirtual #40                 // Method org/apache/dubbo/common/URL.getGroup:()Ljava/lang/String;
     224: ldc           #14                 // String provider
     226: aload_2
     227: invokevirtual #41                 // Method org/apache/dubbo/rpc/model/ApplicationModel.getApplicationName:()Ljava/lang/String;
     230: invokespecial #42                 // Method org/apache/dubbo/metadata/report/identifier/MetadataIdentifier."<init>":(Ljava/lang/String;Ljava/lang/String;Ljava/lang/String;Ljava/lang/String;Ljava/lang/String;)V
     233: aload         5
     235: invokeinterface #43,  3           // InterfaceMethod org/apache/dubbo/metadata/report/MetadataReport.storeProviderMetadata:(Lorg/apache/dubbo/metadata/report/identifier/MetadataIdentifier;Lorg/apache/dubbo/metadata/definition/model/ServiceDefinition;)V
     240: goto          99
     243: goto          408
     246: aload_2
     247: invokestatic  #6                  // Method getMetadataReports:(Lorg/apache/dubbo/rpc/model/ApplicationModel;)Ljava/util/Map;
     250: invokeinterface #21,  1           // InterfaceMethod java/util/Map.entrySet:()Ljava/util/Set;
     255: invokeinterface #22,  1           // InterfaceMethod java/util/Set.iterator:()Ljava/util/Iterator;
     260: astore        4
     262: aload         4
     264: invokeinterface #23,  1           // InterfaceMethod java/util/Iterator.hasNext:()Z
     269: ifeq          408
     272: aload         4
     274: invokeinterface #24,  1           // InterfaceMethod java/util/Iterator.next:()Ljava/lang/Object;
     279: checkcast     #25                 // class java/util/Map$Entry
     282: astore        5
     284: aload         5
     286: invokeinterface #26,  1           // InterfaceMethod java/util/Map$Entry.getValue:()Ljava/lang/Object;
     291: checkcast     #27                 // class org/apache/dubbo/metadata/report/MetadataReport
     294: astore        6
     296: aload         6
     298: invokeinterface #28,  1           // InterfaceMethod org/apache/dubbo/metadata/report/MetadataReport.shouldReportDefinition:()Z
     303: ifne          345
     306: getstatic     #9                  // Field logger:Lorg/apache/dubbo/common/logger/ErrorTypeAwareLogger;
     309: new           #29                 // class java/lang/StringBuilder
     312: dup
     313: invokespecial #30                 // Method java/lang/StringBuilder."<init>":()V
     316: ldc           #31                 // String Report of service definition is disabled for
     318: invokevirtual #32                 // Method java/lang/StringBuilder.append:(Ljava/lang/String;)Ljava/lang/StringBuilder;
     321: aload         5
     323: invokeinterface #33,  1           // InterfaceMethod java/util/Map$Entry.getKey:()Ljava/lang/Object;
     328: checkcast     #34                 // class java/lang/String
     331: invokevirtual #32                 // Method java/lang/StringBuilder.append:(Ljava/lang/String;)Ljava/lang/StringBuilder;
     334: invokevirtual #35                 // Method java/lang/StringBuilder.toString:()Ljava/lang/String;
     337: invokeinterface #36,  2           // InterfaceMethod org/apache/dubbo/common/logger/ErrorTypeAwareLogger.info:(Ljava/lang/String;)V
     342: goto          262
     345: aload         6
     347: new           #37                 // class org/apache/dubbo/metadata/report/identifier/MetadataIdentifier
     350: dup
     351: aload_0
     352: invokevirtual #38                 // Method org/apache/dubbo/common/URL.getServiceInterface:()Ljava/lang/String;
     355: aload_0
     356: invokevirtual #39                 // Method org/apache/dubbo/common/URL.getVersion:()Ljava/lang/String;
     359: ifnonnull     367
     362: ldc           #11                 // String
     364: goto          371
     367: aload_0
     368: invokevirtual #39                 // Method org/apache/dubbo/common/URL.getVersion:()Ljava/lang/String;
     371: aload_0
     372: invokevirtual #40                 // Method org/apache/dubbo/common/URL.getGroup:()Ljava/lang/String;
     375: ifnonnull     383
     378: ldc           #11                 // String
     380: goto          387
     383: aload_0
     384: invokevirtual #40                 // Method org/apache/dubbo/common/URL.getGroup:()Ljava/lang/String;
     387: ldc           #44                 // String consumer
     389: aload_2
     390: invokevirtual #41                 // Method org/apache/dubbo/rpc/model/ApplicationModel.getApplicationName:()Ljava/lang/String;
     393: invokespecial #42                 // Method org/apache/dubbo/metadata/report/identifier/MetadataIdentifier."<init>":(Ljava/lang/String;Ljava/lang/String;Ljava/lang/String;Ljava/lang/String;Ljava/lang/String;)V
     396: aload_0
     397: invokevirtual #19                 // Method org/apache/dubbo/common/URL.getParameters:()Ljava/util/Map;
     400: invokeinterface #45,  3           // InterfaceMethod org/apache/dubbo/metadata/report/MetadataReport.storeConsumerMetadata:(Lorg/apache/dubbo/metadata/report/identifier/MetadataIdentifier;Ljava/util/Map;)V
     405: goto          262
     408: goto          429
     411: astore_3
     412: getstatic     #9                  // Field logger:Lorg/apache/dubbo/common/logger/ErrorTypeAwareLogger;
     415: ldc           #47                 // String 1-11
     417: ldc           #11                 // String
     419: ldc           #11                 // String
     421: ldc           #48                 // String publish service definition metadata error.
     423: aload_3
     424: invokeinterface #49,  6           // InterfaceMethod org/apache/dubbo/common/logger/ErrorTypeAwareLogger.error:(Ljava/lang/String;Ljava/lang/String;Ljava/lang/String;Ljava/lang/String;Ljava/lang/Throwable;)V
     429: return
    Exception table:
       from    to  target type
          31   408   411   Class java/lang/Exception

  public static org.apache.dubbo.registry.client.metadata.MetadataUtils$ProxyHolder referProxy(org.apache.dubbo.registry.client.ServiceInstance);
    Code:
       0: aload_0
       1: invokeinterface #50,  1           // InterfaceMethod org/apache/dubbo/registry/client/ServiceInstance.getApplicationModel:()Lorg/apache/dubbo/rpc/model/ApplicationModel;
       6: ldc           #51                 // class org/apache/dubbo/registry/client/metadata/MetadataServiceURLBuilder
       8: invokevirtual #52                 // Method org/apache/dubbo/rpc/model/ApplicationModel.getExtensionLoader:(Ljava/lang/Class;)Lorg/apache/dubbo/common/extension/ExtensionLoader;
      11: astore_2
      12: aload_0
      13: invokeinterface #53,  1           // InterfaceMethod org/apache/dubbo/registry/client/ServiceInstance.getMetadata:()Ljava/util/Map;
      18: astore_3
      19: aload_3
      20: ldc           #54                 // String dubbo.metadata-service.urls
      22: invokeinterface #55,  2           // InterfaceMethod java/util/Map.get:(Ljava/lang/Object;)Ljava/lang/Object;
      27: checkcast     #34                 // class java/lang/String
      30: astore        4
      32: aload_3
      33: invokeinterface #56,  1           // InterfaceMethod java/util/Map.isEmpty:()Z
      38: ifne          49
      41: aload         4
      43: invokestatic  #57                 // Method org/apache/dubbo/common/utils/StringUtils.isEmpty:(Ljava/lang/String;)Z
      46: ifeq          62
      49: aload_2
      50: ldc           #59                 // String standard
      52: invokevirtual #60                 // Method org/apache/dubbo/common/extension/ExtensionLoader.getExtension:(Ljava/lang/String;)Ljava/lang/Object;
      55: checkcast     #51                 // class org/apache/dubbo/registry/client/metadata/MetadataServiceURLBuilder
      58: astore_1
      59: goto          72
      62: aload_2
      63: ldc           #62                 // String spring-cloud
      65: invokevirtual #60                 // Method org/apache/dubbo/common/extension/ExtensionLoader.getExtension:(Ljava/lang/String;)Ljava/lang/Object;
      68: checkcast     #51                 // class org/apache/dubbo/registry/client/metadata/MetadataServiceURLBuilder
      71: astore_1
      72: aload_1
      73: aload_0
      74: invokeinterface #63,  2           // InterfaceMethod org/apache/dubbo/registry/client/metadata/MetadataServiceURLBuilder.build:(Lorg/apache/dubbo/registry/client/ServiceInstance;)Ljava/util/List;
      79: astore        5
      81: aload         5
      83: invokestatic  #64                 // Method org/apache/dubbo/common/utils/CollectionUtils.isEmpty:(Ljava/util/Collection;)Z
      86: ifeq          121
      89: new           #65                 // class java/lang/IllegalStateException
      92: dup
      93: new           #29                 // class java/lang/StringBuilder
      96: dup
      97: invokespecial #30                 // Method java/lang/StringBuilder."<init>":()V
     100: ldc           #66                 // String Introspection service discovery mode is enabled
     102: invokevirtual #32                 // Method java/lang/StringBuilder.append:(Ljava/lang/String;)Ljava/lang/StringBuilder;
     105: aload_0
     106: invokevirtual #67                 // Method java/lang/StringBuilder.append:(Ljava/lang/Object;)Ljava/lang/StringBuilder;
     109: ldc           #68                 // String , but no metadata service can build from it.
     111: invokevirtual #32                 // Method java/lang/StringBuilder.append:(Ljava/lang/String;)Ljava/lang/StringBuilder;
     114: invokevirtual #35                 // Method java/lang/StringBuilder.toString:()Ljava/lang/String;
     117: invokespecial #69                 // Method java/lang/IllegalStateException."<init>":(Ljava/lang/String;)V
     120: athrow
     121: aload         5
     123: iconst_0
     124: invokeinterface #70,  2           // InterfaceMethod java/util/List.get:(I)Ljava/lang/Object;
     129: checkcast     #71                 // class org/apache/dubbo/common/URL
     132: astore        6
     134: aload_0
     135: invokeinterface #50,  1           // InterfaceMethod org/apache/dubbo/registry/client/ServiceInstance.getApplicationModel:()Lorg/apache/dubbo/rpc/model/ApplicationModel;
     140: astore        7
     142: aload         7
     144: invokevirtual #72                 // Method org/apache/dubbo/rpc/model/ApplicationModel.getInternalModule:()Lorg/apache/dubbo/rpc/model/ModuleModel;
     147: astore        8
     149: aload         7
     151: invokevirtual #72                 // Method org/apache/dubbo/rpc/model/ApplicationModel.getInternalModule:()Lorg/apache/dubbo/rpc/model/ModuleModel;
     154: ldc           #73                 // class org/apache/dubbo/metadata/MetadataService
     156: aload         6
     158: invokevirtual #74                 // Method org/apache/dubbo/rpc/model/ModuleModel.registerInternalConsumer:(Ljava/lang/Class;Lorg/apache/dubbo/common/URL;)Lorg/apache/dubbo/rpc/model/ConsumerModel;
     161: astore        9
     163: aload         7
     165: ldc           #75                 // class org/apache/dubbo/rpc/Protocol
     167: invokevirtual #52                 // Method org/apache/dubbo/rpc/model/ApplicationModel.getExtensionLoader:(Ljava/lang/Class;)Lorg/apache/dubbo/common/extension/ExtensionLoader;
     170: aload         6
     172: invokevirtual #76                 // Method org/apache/dubbo/common/URL.getProtocol:()Ljava/lang/String;
     175: iconst_0
     176: invokevirtual #77                 // Method org/apache/dubbo/common/extension/ExtensionLoader.getExtension:(Ljava/lang/String;Z)Ljava/lang/Object;
     179: checkcast     #75                 // class org/apache/dubbo/rpc/Protocol
     182: astore        10
     184: aload         6
     186: aload         9
     188: invokevirtual #78                 // Method org/apache/dubbo/common/URL.setServiceModel:(Lorg/apache/dubbo/rpc/model/ServiceModel;)Lorg/apache/dubbo/common/URL;
     191: astore        6
     193: aload         10
     195: ldc           #73                 // class org/apache/dubbo/metadata/MetadataService
     197: aload         6
     199: invokeinterface #79,  3           // InterfaceMethod org/apache/dubbo/rpc/Protocol.refer:(Ljava/lang/Class;Lorg/apache/dubbo/common/URL;)Lorg/apache/dubbo/rpc/Invoker;
     204: astore        11
     206: aload         7
     208: ldc           #80                 // class org/apache/dubbo/rpc/ProxyFactory
     210: invokevirtual #52                 // Method org/apache/dubbo/rpc/model/ApplicationModel.getExtensionLoader:(Ljava/lang/Class;)Lorg/apache/dubbo/common/extension/ExtensionLoader;
     213: invokevirtual #81                 // Method org/apache/dubbo/common/extension/ExtensionLoader.getAdaptiveExtension:()Ljava/lang/Object;
     216: checkcast     #80                 // class org/apache/dubbo/rpc/ProxyFactory
     219: astore        12
     221: aload         12
     223: aload         11
     225: invokeinterface #82,  2           // InterfaceMethod org/apache/dubbo/rpc/ProxyFactory.getProxy:(Lorg/apache/dubbo/rpc/Invoker;)Ljava/lang/Object;
     230: checkcast     #73                 // class org/apache/dubbo/metadata/MetadataService
     233: astore        13
     235: aload         9
     237: invokevirtual #83                 // Method org/apache/dubbo/rpc/model/ConsumerModel.getServiceMetadata:()Lorg/apache/dubbo/rpc/model/ServiceMetadata;
     240: aload         13
     242: invokevirtual #84                 // Method org/apache/dubbo/rpc/model/ServiceMetadata.setTarget:(Ljava/lang/Object;)V
     245: aload         9
     247: invokevirtual #83                 // Method org/apache/dubbo/rpc/model/ConsumerModel.getServiceMetadata:()Lorg/apache/dubbo/rpc/model/ServiceMetadata;
     250: ldc           #85                 // String refClass
     252: aload         13
     254: invokevirtual #86                 // Method org/apache/dubbo/rpc/model/ServiceMetadata.addAttribute:(Ljava/lang/String;Ljava/lang/Object;)V
     257: aload         9
     259: aload         13
     261: invokevirtual #87                 // Method org/apache/dubbo/rpc/model/ConsumerModel.setProxyObject:(Ljava/lang/Object;)V
     264: aload         9
     266: invokevirtual #88                 // Method org/apache/dubbo/rpc/model/ConsumerModel.initMethodModels:()V
     269: new           #89                 // class org/apache/dubbo/registry/client/metadata/MetadataUtils$ProxyHolder
     272: dup
     273: aload         9
     275: aload         13
     277: aload         8
     279: invokespecial #90                 // Method org/apache/dubbo/registry/client/metadata/MetadataUtils$ProxyHolder."<init>":(Lorg/apache/dubbo/rpc/model/ConsumerModel;Lorg/apache/dubbo/metadata/MetadataService;Lorg/apache/dubbo/rpc/model/ModuleModel;)V
     282: areturn

  public static org.apache.dubbo.metadata.MetadataInfo getRemoteMetadata(java.lang.String, java.util.List<org.apache.dubbo.registry.client.ServiceInstance>, org.apache.dubbo.metadata.report.MetadataReport);
    Code:
       0: aload_1
       1: invokestatic  #91                 // Method selectInstance:(Ljava/util/List;)Lorg/apache/dubbo/registry/client/ServiceInstance;
       4: astore_3
       5: aload_3
       6: invokestatic  #92                 // Method org/apache/dubbo/registry/client/metadata/ServiceInstanceMetadataUtils.getMetadataStorageType:(Lorg/apache/dubbo/registry/client/ServiceInstance;)Ljava/lang/String;
       9: astore        4
      11: getstatic     #9                  // Field logger:Lorg/apache/dubbo/common/logger/ErrorTypeAwareLogger;
      14: invokeinterface #93,  1           // InterfaceMethod org/apache/dubbo/common/logger/ErrorTypeAwareLogger.isDebugEnabled:()Z
      19: ifeq          64
      22: getstatic     #9                  // Field logger:Lorg/apache/dubbo/common/logger/ErrorTypeAwareLogger;
      25: new           #29                 // class java/lang/StringBuilder
      28: dup
      29: invokespecial #30                 // Method java/lang/StringBuilder."<init>":()V
      32: ldc           #94                 // String Instance
      34: invokevirtual #32                 // Method java/lang/StringBuilder.append:(Ljava/lang/String;)Ljava/lang/StringBuilder;
      37: aload_3
      38: invokeinterface #95,  1           // InterfaceMethod org/apache/dubbo/registry/client/ServiceInstance.getAddress:()Ljava/lang/String;
      43: invokevirtual #32                 // Method java/lang/StringBuilder.append:(Ljava/lang/String;)Ljava/lang/StringBuilder;
      46: ldc           #96                 // String  is using metadata type
      48: invokevirtual #32                 // Method java/lang/StringBuilder.append:(Ljava/lang/String;)Ljava/lang/StringBuilder;
      51: aload         4
      53: invokevirtual #32                 // Method java/lang/StringBuilder.append:(Ljava/lang/String;)Ljava/lang/StringBuilder;
      56: invokevirtual #35                 // Method java/lang/StringBuilder.toString:()Ljava/lang/String;
      59: invokeinterface #97,  2           // InterfaceMethod org/apache/dubbo/common/logger/ErrorTypeAwareLogger.debug:(Ljava/lang/String;)V
      64: ldc           #98                 // String remote
      66: aload         4
      68: invokevirtual #99                 // Method java/lang/String.equals:(Ljava/lang/Object;)Z
      71: ifeq          85
      74: aload_0
      75: aload_3
      76: aload_2
      77: invokestatic  #100                // Method getMetadata:(Ljava/lang/String;Lorg/apache/dubbo/registry/client/ServiceInstance;Lorg/apache/dubbo/metadata/report/MetadataReport;)Lorg/apache/dubbo/metadata/MetadataInfo;
      80: astore        5
      82: goto          128
      85: aconst_null
      86: astore        6
      88: aload_3
      89: invokestatic  #101                // Method referProxy:(Lorg/apache/dubbo/registry/client/ServiceInstance;)Lorg/apache/dubbo/registry/client/metadata/MetadataUtils$ProxyHolder;
      92: astore        6
      94: aload         6
      96: invokevirtual #102                // Method org/apache/dubbo/registry/client/metadata/MetadataUtils$ProxyHolder.getProxy:()Lorg/apache/dubbo/metadata/MetadataService;
      99: aload_3
     100: invokestatic  #103                // Method org/apache/dubbo/registry/client/metadata/ServiceInstanceMetadataUtils.getExportedServicesRevision:(Lorg/apache/dubbo/registry/client/ServiceInstance;)Ljava/lang/String;
     103: invokeinterface #104,  2          // InterfaceMethod org/apache/dubbo/metadata/MetadataService.getMetadataInfo:(Ljava/lang/String;)Lorg/apache/dubbo/metadata/MetadataInfo;
     108: astore        5
     110: aload         6
     112: invokestatic  #105                // Method destroyProxy:(Lorg/apache/dubbo/registry/client/metadata/MetadataUtils$ProxyHolder;)V
     115: goto          128
     118: astore        7
     120: aload         6
     122: invokestatic  #105                // Method destroyProxy:(Lorg/apache/dubbo/registry/client/metadata/MetadataUtils$ProxyHolder;)V
     125: aload         7
     127: athrow
     128: goto          195
     131: astore        6
     133: getstatic     #9                  // Field logger:Lorg/apache/dubbo/common/logger/ErrorTypeAwareLogger;
     136: ldc           #10                 // String 1-39
     138: ldc           #11                 // String
     140: ldc           #11                 // String
     142: new           #29                 // class java/lang/StringBuilder
     145: dup
     146: invokespecial #30                 // Method java/lang/StringBuilder."<init>":()V
     149: ldc           #106                // String Failed to get app metadata for revision
     151: invokevirtual #32                 // Method java/lang/StringBuilder.append:(Ljava/lang/String;)Ljava/lang/StringBuilder;
     154: aload_0
     155: invokevirtual #32                 // Method java/lang/StringBuilder.append:(Ljava/lang/String;)Ljava/lang/StringBuilder;
     158: ldc           #107                // String  for type
     160: invokevirtual #32                 // Method java/lang/StringBuilder.append:(Ljava/lang/String;)Ljava/lang/StringBuilder;
     163: aload         4
     165: invokevirtual #32                 // Method java/lang/StringBuilder.append:(Ljava/lang/String;)Ljava/lang/StringBuilder;
     168: ldc           #108                // String  from instance
     170: invokevirtual #32                 // Method java/lang/StringBuilder.append:(Ljava/lang/String;)Ljava/lang/StringBuilder;
     173: aload_3
     174: invokeinterface #95,  1           // InterfaceMethod org/apache/dubbo/registry/client/ServiceInstance.getAddress:()Ljava/lang/String;
     179: invokevirtual #32                 // Method java/lang/StringBuilder.append:(Ljava/lang/String;)Ljava/lang/StringBuilder;
     182: invokevirtual #35                 // Method java/lang/StringBuilder.toString:()Ljava/lang/String;
     185: aload         6
     187: invokeinterface #49,  6           // InterfaceMethod org/apache/dubbo/common/logger/ErrorTypeAwareLogger.error:(Ljava/lang/String;Ljava/lang/String;Ljava/lang/String;Ljava/lang/String;Ljava/lang/Throwable;)V
     192: aconst_null
     193: astore        5
     195: aload         5
     197: ifnonnull     205
     200: getstatic     #109                // Field org/apache/dubbo/metadata/MetadataInfo.EMPTY:Lorg/apache/dubbo/metadata/MetadataInfo;
     203: astore        5
     205: aload         5
     207: areturn
    Exception table:
       from    to  target type
          88   110   118   any
         118   120   118   any
          11   128   131   Class java/lang/Exception

  public static void destroyProxy(org.apache.dubbo.registry.client.metadata.MetadataUtils$ProxyHolder);
    Code:
       0: aload_0
       1: ifnull        8
       4: aload_0
       5: invokevirtual #110                // Method org/apache/dubbo/registry/client/metadata/MetadataUtils$ProxyHolder.destroy:()V
       8: return

  public static org.apache.dubbo.metadata.MetadataInfo getMetadata(java.lang.String, org.apache.dubbo.registry.client.ServiceInstance, org.apache.dubbo.metadata.report.MetadataReport);
    Code:
       0: new           #111                // class org/apache/dubbo/metadata/report/identifier/SubscriberMetadataIdentifier
       3: dup
       4: aload_1
       5: invokeinterface #112,  1          // InterfaceMethod org/apache/dubbo/registry/client/ServiceInstance.getServiceName:()Ljava/lang/String;
      10: aload_0
      11: invokespecial #113                // Method org/apache/dubbo/metadata/report/identifier/SubscriberMetadataIdentifier."<init>":(Ljava/lang/String;Ljava/lang/String;)V
      14: astore_3
      15: aload_2
      16: ifnonnull     29
      19: new           #65                 // class java/lang/IllegalStateException
      22: dup
      23: ldc           #114                // String No valid remote metadata report specified.
      25: invokespecial #69                 // Method java/lang/IllegalStateException."<init>":(Ljava/lang/String;)V
      28: athrow
      29: aload_1
      30: invokeinterface #115,  1          // InterfaceMethod org/apache/dubbo/registry/client/ServiceInstance.getRegistryCluster:()Ljava/lang/String;
      35: astore        4
      37: new           #116                // class java/util/HashMap
      40: dup
      41: aload_1
      42: invokeinterface #117,  1          // InterfaceMethod org/apache/dubbo/registry/client/ServiceInstance.getExtendParams:()Ljava/util/Map;
      47: invokespecial #118                // Method java/util/HashMap."<init>":(Ljava/util/Map;)V
      50: astore        5
      52: aload         4
      54: ifnull        89
      57: aload         4
      59: aload         5
      61: ldc           #119                // String REGISTRY_CLUSTER
      63: invokeinterface #55,  2           // InterfaceMethod java/util/Map.get:(Ljava/lang/Object;)Ljava/lang/Object;
      68: checkcast     #34                 // class java/lang/String
      71: invokevirtual #15                 // Method java/lang/String.equalsIgnoreCase:(Ljava/lang/String;)Z
      74: ifne          89
      77: aload         5
      79: ldc           #119                // String REGISTRY_CLUSTER
      81: aload         4
      83: invokeinterface #120,  3          // InterfaceMethod java/util/Map.put:(Ljava/lang/Object;Ljava/lang/Object;)Ljava/lang/Object;
      88: pop
      89: aload_2
      90: aload_3
      91: aload         5
      93: invokeinterface #121,  3          // InterfaceMethod org/apache/dubbo/metadata/report/MetadataReport.getAppMetadata:(Lorg/apache/dubbo/metadata/report/identifier/SubscriberMetadataIdentifier;Ljava/util/Map;)Lorg/apache/dubbo/metadata/MetadataInfo;
      98: areturn

  private static java.util.Map<java.lang.String, org.apache.dubbo.metadata.report.MetadataReport> getMetadataReports(org.apache.dubbo.rpc.model.ApplicationModel);
    Code:
       0: aload_0
       1: invokevirtual #122                // Method org/apache/dubbo/rpc/model/ApplicationModel.getBeanFactory:()Lorg/apache/dubbo/common/beans/factory/ScopeBeanFactory;
       4: ldc           #123                // class org/apache/dubbo/metadata/report/MetadataReportInstance
       6: invokevirtual #124                // Method org/apache/dubbo/common/beans/factory/ScopeBeanFactory.getBean:(Ljava/lang/Class;)Ljava/lang/Object;
       9: checkcast     #123                // class org/apache/dubbo/metadata/report/MetadataReportInstance
      12: iconst_0
      13: invokevirtual #125                // Method org/apache/dubbo/metadata/report/MetadataReportInstance.getMetadataReports:(Z)Ljava/util/Map;
      16: areturn

  private static org.apache.dubbo.registry.client.ServiceInstance selectInstance(java.util.List<org.apache.dubbo.registry.client.ServiceInstance>);
    Code:
       0: aload_0
       1: invokeinterface #126,  1          // InterfaceMethod java/util/List.size:()I
       6: iconst_1
       7: if_icmpne     21
      10: aload_0
      11: iconst_0
      12: invokeinterface #70,  2           // InterfaceMethod java/util/List.get:(I)Ljava/lang/Object;
      17: checkcast     #127                // class org/apache/dubbo/registry/client/ServiceInstance
      20: areturn
      21: aload_0
      22: invokestatic  #128                // Method java/util/concurrent/ThreadLocalRandom.current:()Ljava/util/concurrent/ThreadLocalRandom;
      25: iconst_0
      26: aload_0
      27: invokeinterface #126,  1          // InterfaceMethod java/util/List.size:()I
      32: invokevirtual #129                // Method java/util/concurrent/ThreadLocalRandom.nextInt:(II)I
      35: invokeinterface #70,  2           // InterfaceMethod java/util/List.get:(I)Ljava/lang/Object;
      40: checkcast     #127                // class org/apache/dubbo/registry/client/ServiceInstance
      43: areturn

  static {};
    Code:
       0: ldc           #130                // class org/apache/dubbo/registry/client/metadata/MetadataUtils
       2: invokestatic  #131                // Method org/apache/dubbo/common/logger/LoggerFactory.getErrorTypeAwareLogger:(Ljava/lang/Class;)Lorg/apache/dubbo/common/logger/ErrorTypeAwareLogger;
       5: putstatic     #9                  // Field logger:Lorg/apache/dubbo/common/logger/ErrorTypeAwareLogger;
       8: return
}
