Compiled from "MetadataUtils.java"
public class org.apache.dubbo.registry.client.metadata.MetadataUtils$ProxyHolder {
  private final org.apache.dubbo.rpc.model.ConsumerModel consumerModel;

  private final org.apache.dubbo.metadata.MetadataService proxy;

  private final org.apache.dubbo.rpc.model.ModuleModel internalModel;

  public org.apache.dubbo.registry.client.metadata.MetadataUtils$ProxyHolder(org.apache.dubbo.rpc.model.ConsumerModel, org.apache.dubbo.metadata.MetadataService, org.apache.dubbo.rpc.model.ModuleModel);
    Code:
       0: aload_0
       1: invokespecial #1                  // Method java/lang/Object."<init>":()V
       4: aload_0
       5: aload_1
       6: putfield      #2                  // Field consumerModel:Lorg/apache/dubbo/rpc/model/ConsumerModel;
       9: aload_0
      10: aload_2
      11: putfield      #3                  // Field proxy:Lorg/apache/dubbo/metadata/MetadataService;
      14: aload_0
      15: aload_3
      16: putfield      #4                  // Field internalModel:Lorg/apache/dubbo/rpc/model/ModuleModel;
      19: return

  public void destroy();
    Code:
       0: aload_0
       1: getfield      #3                  // Field proxy:Lorg/apache/dubbo/metadata/MetadataService;
       4: instanceof    #5                  // class org/apache/dubbo/rpc/service/Destroyable
       7: ifeq          22
      10: aload_0
      11: getfield      #3                  // Field proxy:Lorg/apache/dubbo/metadata/MetadataService;
      14: checkcast     #5                  // class org/apache/dubbo/rpc/service/Destroyable
      17: invokeinterface #6,  1            // InterfaceMethod org/apache/dubbo/rpc/service/Destroyable.$destroy:()V
      22: aload_0
      23: getfield      #4                  // Field internalModel:Lorg/apache/dubbo/rpc/model/ModuleModel;
      26: invokevirtual #7                  // Method org/apache/dubbo/rpc/model/ModuleModel.getServiceRepository:()Lorg/apache/dubbo/rpc/model/ModuleServiceRepository;
      29: aload_0
      30: getfield      #2                  // Field consumerModel:Lorg/apache/dubbo/rpc/model/ConsumerModel;
      33: invokevirtual #8                  // Method org/apache/dubbo/rpc/model/ModuleServiceRepository.unregisterConsumer:(Lorg/apache/dubbo/rpc/model/ConsumerModel;)V
      36: return

  public org.apache.dubbo.rpc.model.ConsumerModel getConsumerModel();
    Code:
       0: aload_0
       1: getfield      #2                  // Field consumerModel:Lorg/apache/dubbo/rpc/model/ConsumerModel;
       4: areturn

  public org.apache.dubbo.metadata.MetadataService getProxy();
    Code:
       0: aload_0
       1: getfield      #3                  // Field proxy:Lorg/apache/dubbo/metadata/MetadataService;
       4: areturn

  public org.apache.dubbo.rpc.model.ModuleModel getInternalModel();
    Code:
       0: aload_0
       1: getfield      #4                  // Field internalModel:Lorg/apache/dubbo/rpc/model/ModuleModel;
       4: areturn
}
