Compiled from "MetadataServiceDelegation.java"
class org.apache.dubbo.registry.client.metadata.MetadataServiceDelegation$URLComparator implements java.util.Comparator<org.apache.dubbo.common.URL> {
  public static final org.apache.dubbo.registry.client.metadata.MetadataServiceDelegation$URLComparator INSTANCE;

  org.apache.dubbo.registry.client.metadata.MetadataServiceDelegation$URLComparator();
    Code:
       0: aload_0
       1: invokespecial #1                  // Method java/lang/Object."<init>":()V
       4: return

  public int compare(org.apache.dubbo.common.URL, org.apache.dubbo.common.URL);
    Code:
       0: aload_1
       1: invokevirtual #2                  // Method org/apache/dubbo/common/URL.toFullString:()Ljava/lang/String;
       4: aload_2
       5: invokevirtual #2                  // Method org/apache/dubbo/common/URL.toFullString:()Ljava/lang/String;
       8: invokevirtual #3                  // Method java/lang/String.compareTo:(Ljava/lang/String;)I
      11: ireturn

  public int compare(java.lang.Object, java.lang.Object);
    Code:
       0: aload_0
       1: aload_1
       2: checkcast     #4                  // class org/apache/dubbo/common/URL
       5: aload_2
       6: checkcast     #4                  // class org/apache/dubbo/common/URL
       9: invokevirtual #5                  // Method compare:(Lorg/apache/dubbo/common/URL;Lorg/apache/dubbo/common/URL;)I
      12: ireturn

  static {};
    Code:
       0: new           #6                  // class org/apache/dubbo/registry/client/metadata/MetadataServiceDelegation$URLComparator
       3: dup
       4: invokespecial #7                  // Method "<init>":()V
       7: putstatic     #8                  // Field INSTANCE:Lorg/apache/dubbo/registry/client/metadata/MetadataServiceDelegation$URLComparator;
      10: return
}
