Compiled from "ServiceInstanceMetadataCustomizer.java"
public class org.apache.dubbo.registry.client.metadata.ServiceInstanceMetadataCustomizer implements org.apache.dubbo.registry.client.ServiceInstanceCustomizer {
  public org.apache.dubbo.registry.client.metadata.ServiceInstanceMetadataCustomizer();
    Code:
       0: aload_0
       1: invokespecial #2                  // Method java/lang/Object."<init>":()V
       4: return

  public void customize(org.apache.dubbo.registry.client.ServiceInstance, org.apache.dubbo.rpc.model.ApplicationModel);
    Code:
       0: aload_1
       1: invokeinterface #3,  1            // InterfaceMethod org/apache/dubbo/registry/client/ServiceInstance.getServiceMetadata:()Lorg/apache/dubbo/metadata/MetadataInfo;
       6: astore_3
       7: aload_3
       8: ifnull        21
      11: aload_3
      12: invokevirtual #4                  // Method org/apache/dubbo/metadata/MetadataInfo.getServices:()Ljava/util/Map;
      15: invokestatic  #5                  // Method org/apache/dubbo/common/utils/CollectionUtils.isEmptyMap:(Ljava/util/Map;)Z
      18: ifeq          22
      21: return
      22: invokestatic  #6                  // Method java/util/Collections.emptyMap:()Ljava/util/Map;
      25: astore        4
      27: aload_2
      28: ldc           #7                  // class org/apache/dubbo/common/infra/InfraAdapter
      30: invokevirtual #8                  // Method org/apache/dubbo/rpc/model/ApplicationModel.getExtensionLoader:(Ljava/lang/Class;)Lorg/apache/dubbo/common/extension/ExtensionLoader;
      33: invokevirtual #9                  // Method org/apache/dubbo/common/extension/ExtensionLoader.getSupportedExtensionInstances:()Ljava/util/Set;
      36: astore        5
      38: aload         5
      40: invokestatic  #10                 // Method org/apache/dubbo/common/utils/CollectionUtils.isNotEmpty:(Ljava/util/Collection;)Z
      43: ifeq          114
      46: new           #11                 // class java/util/HashMap
      49: dup
      50: invokespecial #12                 // Method java/util/HashMap."<init>":()V
      53: astore        6
      55: aload         6
      57: ldc           #13                 // String application
      59: aload_2
      60: invokevirtual #14                 // Method org/apache/dubbo/rpc/model/ApplicationModel.getApplicationName:()Ljava/lang/String;
      63: invokeinterface #15,  3           // InterfaceMethod java/util/Map.put:(Ljava/lang/Object;Ljava/lang/Object;)Ljava/lang/Object;
      68: pop
      69: aload         5
      71: invokeinterface #16,  1           // InterfaceMethod java/util/Set.iterator:()Ljava/util/Iterator;
      76: astore        7
      78: aload         7
      80: invokeinterface #17,  1           // InterfaceMethod java/util/Iterator.hasNext:()Z
      85: ifeq          114
      88: aload         7
      90: invokeinterface #18,  1           // InterfaceMethod java/util/Iterator.next:()Ljava/lang/Object;
      95: checkcast     #7                  // class org/apache/dubbo/common/infra/InfraAdapter
      98: astore        8
     100: aload         8
     102: aload         6
     104: invokeinterface #19,  2           // InterfaceMethod org/apache/dubbo/common/infra/InfraAdapter.getExtraAttributes:(Ljava/util/Map;)Ljava/util/Map;
     109: astore        4
     111: goto          78
     114: aload_1
     115: invokeinterface #20,  1           // InterfaceMethod org/apache/dubbo/registry/client/ServiceInstance.getMetadata:()Ljava/util/Map;
     120: aload         4
     122: invokeinterface #21,  2           // InterfaceMethod java/util/Map.putAll:(Ljava/util/Map;)V
     127: aload_3
     128: invokevirtual #22                 // Method org/apache/dubbo/metadata/MetadataInfo.getInstanceParams:()Ljava/util/Map;
     131: invokestatic  #23                 // Method org/apache/dubbo/common/utils/CollectionUtils.isNotEmptyMap:(Ljava/util/Map;)Z
     134: ifeq          152
     137: aload_1
     138: invokeinterface #20,  1           // InterfaceMethod org/apache/dubbo/registry/client/ServiceInstance.getMetadata:()Ljava/util/Map;
     143: aload_3
     144: invokevirtual #22                 // Method org/apache/dubbo/metadata/MetadataInfo.getInstanceParams:()Ljava/util/Map;
     147: invokeinterface #21,  2           // InterfaceMethod java/util/Map.putAll:(Ljava/util/Map;)V
     152: return
}
