Compiled from "SpringCloudServiceInstanceNotificationCustomizer.java"
public class org.apache.dubbo.registry.client.metadata.SpringCloudServiceInstanceNotificationCustomizer implements org.apache.dubbo.registry.client.metadata.ServiceInstanceNotificationCustomizer {
  public org.apache.dubbo.registry.client.metadata.SpringCloudServiceInstanceNotificationCustomizer();
    Code:
       0: aload_0
       1: invokespecial #1                  // Method java/lang/Object."<init>":()V
       4: return

  public void customize(java.util.List<org.apache.dubbo.registry.client.ServiceInstance>);
    Code:
       0: aload_1
       1: invokeinterface #2,  1            // InterfaceMethod java/util/List.isEmpty:()Z
       6: ifeq          10
       9: return
      10: aload_1
      11: invokeinterface #3,  1            // InterfaceMethod java/util/List.stream:()Ljava/util/stream/Stream;
      16: invokedynamic #4,  0              // InvokeDynamic #0:test:()Ljava/util/function/Predicate;
      21: invokeinterface #5,  2            // InterfaceMethod java/util/stream/Stream.allMatch:(Ljava/util/function/Predicate;)Z
      26: ifne          30
      29: return
      30: aload_1
      31: invokeinterface #6,  1            // InterfaceMethod java/util/List.iterator:()Ljava/util/Iterator;
      36: astore_2
      37: aload_2
      38: invokeinterface #7,  1            // InterfaceMethod java/util/Iterator.hasNext:()Z
      43: ifeq          186
      46: aload_2
      47: invokeinterface #8,  1            // InterfaceMethod java/util/Iterator.next:()Ljava/lang/Object;
      52: checkcast     #9                  // class org/apache/dubbo/registry/client/ServiceInstance
      55: astore_3
      56: new           #10                 // class org/apache/dubbo/metadata/MetadataInfo$ServiceInfo
      59: dup
      60: ldc           #11                 // String *
      62: ldc           #11                 // String *
      64: ldc           #11                 // String *
      66: ldc           #12                 // String rest
      68: aload_3
      69: invokeinterface #13,  1           // InterfaceMethod org/apache/dubbo/registry/client/ServiceInstance.getPort:()I
      74: ldc           #11                 // String *
      76: new           #14                 // class java/util/HashMap
      79: dup
      80: invokespecial #15                 // Method java/util/HashMap."<init>":()V
      83: invokespecial #16                 // Method org/apache/dubbo/metadata/MetadataInfo$ServiceInfo."<init>":(Ljava/lang/String;Ljava/lang/String;Ljava/lang/String;Ljava/lang/String;ILjava/lang/String;Ljava/util/Map;)V
      86: astore        4
      88: new           #17                 // class java/lang/StringBuilder
      91: dup
      92: invokespecial #18                 // Method java/lang/StringBuilder."<init>":()V
      95: ldc           #19                 // String SPRING_CLOUD-
      97: invokevirtual #20                 // Method java/lang/StringBuilder.append:(Ljava/lang/String;)Ljava/lang/StringBuilder;
     100: aload_3
     101: invokeinterface #21,  1           // InterfaceMethod org/apache/dubbo/registry/client/ServiceInstance.getServiceName:()Ljava/lang/String;
     106: invokevirtual #20                 // Method java/lang/StringBuilder.append:(Ljava/lang/String;)Ljava/lang/StringBuilder;
     109: ldc           #22                 // String -
     111: invokevirtual #20                 // Method java/lang/StringBuilder.append:(Ljava/lang/String;)Ljava/lang/StringBuilder;
     114: aload_3
     115: invokeinterface #23,  1           // InterfaceMethod org/apache/dubbo/registry/client/ServiceInstance.getAddress:()Ljava/lang/String;
     120: invokevirtual #20                 // Method java/lang/StringBuilder.append:(Ljava/lang/String;)Ljava/lang/StringBuilder;
     123: ldc           #22                 // String -
     125: invokevirtual #20                 // Method java/lang/StringBuilder.append:(Ljava/lang/String;)Ljava/lang/StringBuilder;
     128: aload_3
     129: invokeinterface #13,  1           // InterfaceMethod org/apache/dubbo/registry/client/ServiceInstance.getPort:()I
     134: invokevirtual #24                 // Method java/lang/StringBuilder.append:(I)Ljava/lang/StringBuilder;
     137: invokevirtual #25                 // Method java/lang/StringBuilder.toString:()Ljava/lang/String;
     140: astore        5
     142: new           #26                 // class org/apache/dubbo/registry/client/metadata/SpringCloudServiceInstanceNotificationCustomizer$1
     145: dup
     146: aload_0
     147: aload_3
     148: invokeinterface #21,  1           // InterfaceMethod org/apache/dubbo/registry/client/ServiceInstance.getServiceName:()Ljava/lang/String;
     153: aload         5
     155: new           #27                 // class java/util/concurrent/ConcurrentHashMap
     158: dup
     159: ldc           #11                 // String *
     161: aload         4
     163: invokestatic  #28                 // Method java/util/Collections.singletonMap:(Ljava/lang/Object;Ljava/lang/Object;)Ljava/util/Map;
     166: invokespecial #29                 // Method java/util/concurrent/ConcurrentHashMap."<init>":(Ljava/util/Map;)V
     169: aload_3
     170: invokespecial #30                 // Method org/apache/dubbo/registry/client/metadata/SpringCloudServiceInstanceNotificationCustomizer$1."<init>":(Lorg/apache/dubbo/registry/client/metadata/SpringCloudServiceInstanceNotificationCustomizer;Ljava/lang/String;Ljava/lang/String;Ljava/util/Map;Lorg/apache/dubbo/registry/client/ServiceInstance;)V
     173: astore        6
     175: aload_3
     176: aload         6
     178: invokeinterface #31,  2           // InterfaceMethod org/apache/dubbo/registry/client/ServiceInstance.setServiceMetadata:(Lorg/apache/dubbo/metadata/MetadataInfo;)V
     183: goto          37
     186: return

  private static boolean lambda$customize$0(org.apache.dubbo.registry.client.ServiceInstance);
    Code:
       0: ldc           #32                 // String SPRING_CLOUD
       2: aload_0
       3: ldc           #33                 // String preserved.register.source
       5: invokeinterface #34,  2           // InterfaceMethod org/apache/dubbo/registry/client/ServiceInstance.getMetadata:(Ljava/lang/String;)Ljava/lang/String;
      10: invokevirtual #35                 // Method java/lang/String.equals:(Ljava/lang/Object;)Z
      13: ireturn
}
