Compiled from "SpringCloudMetadataServiceURLBuilder.java"
public class org.apache.dubbo.registry.client.metadata.SpringCloudMetadataServiceURLBuilder implements org.apache.dubbo.registry.client.metadata.MetadataServiceURLBuilder {
  public static final java.lang.String NAME;

  public org.apache.dubbo.registry.client.metadata.SpringCloudMetadataServiceURLBuilder();
    Code:
       0: aload_0
       1: invokespecial #2                  // Method java/lang/Object."<init>":()V
       4: return

  public java.util.List<org.apache.dubbo.common.URL> build(org.apache.dubbo.registry.client.ServiceInstance);
    Code:
       0: aload_1
       1: invokeinterface #3,  1            // InterfaceMethod org/apache/dubbo/registry/client/ServiceInstance.getMetadata:()Ljava/util/Map;
       6: astore_2
       7: aload_2
       8: ldc           #4                  // String dubbo.metadata-service.urls
      10: invokeinterface #5,  2            // InterfaceMethod java/util/Map.get:(Ljava/lang/Object;)Ljava/lang/Object;
      15: checkcast     #6                  // class java/lang/String
      18: astore_3
      19: aload_3
      20: invokestatic  #7                  // Method org/apache/dubbo/common/utils/StringUtils.isBlank:(Ljava/lang/CharSequence;)Z
      23: ifeq          30
      26: invokestatic  #8                  // Method java/util/Collections.emptyList:()Ljava/util/List;
      29: areturn
      30: aload_3
      31: ldc           #6                  // class java/lang/String
      33: invokestatic  #9                  // Method org/apache/dubbo/common/utils/JsonUtils.toJavaList:(Ljava/lang/String;Ljava/lang/Class;)Ljava/util/List;
      36: astore        4
      38: aload         4
      40: invokeinterface #10,  1           // InterfaceMethod java/util/List.stream:()Ljava/util/stream/Stream;
      45: invokedynamic #11,  0             // InvokeDynamic #0:apply:()Ljava/util/function/Function;
      50: invokeinterface #12,  2           // InterfaceMethod java/util/stream/Stream.map:(Ljava/util/function/Function;)Ljava/util/stream/Stream;
      55: invokestatic  #13                 // Method java/util/stream/Collectors.toList:()Ljava/util/stream/Collector;
      58: invokeinterface #14,  2           // InterfaceMethod java/util/stream/Stream.collect:(Ljava/util/stream/Collector;)Ljava/lang/Object;
      63: checkcast     #15                 // class java/util/List
      66: areturn
}
