Compiled from "ClassGenerator.java"
public final class org.apache.dubbo.common.bytecode.ClassGenerator {
  private static final java.util.concurrent.atomic.AtomicLong CLASS_NAME_COUNTER;

  private static final java.lang.String SIMPLE_NAME_TAG;

  private static final java.util.Map<java.lang.ClassLoader, javassist.ClassPool> POOL_MAP;

  private javassist.ClassPool mPool;

  private javassist.CtClass mCtc;

  private java.lang.String mClassName;

  private java.lang.String mSuperClass;

  private java.util.Set<java.lang.String> mInterfaces;

  private java.util.List<java.lang.String> mFields;

  private java.util.List<java.lang.String> mConstructors;

  private java.util.List<java.lang.String> mMethods;

  private java.lang.ClassLoader mClassLoader;

  private java.util.Map<java.lang.String, java.lang.reflect.Method> mCopyMethods;

  private java.util.Map<java.lang.String, java.lang.reflect.Constructor<?>> mCopyConstructors;

  private boolean mDefaultConstructor;

  private org.apache.dubbo.common.bytecode.ClassGenerator();
    Code:
       0: aload_0
       1: invokespecial #1                  // Method java/lang/Object."<init>":()V
       4: aload_0
       5: iconst_0
       6: putfield      #2                  // Field mDefaultConstructor:Z
       9: return

  private org.apache.dubbo.common.bytecode.ClassGenerator(java.lang.ClassLoader, javassist.ClassPool);
    Code:
       0: aload_0
       1: invokespecial #1                  // Method java/lang/Object."<init>":()V
       4: aload_0
       5: iconst_0
       6: putfield      #2                  // Field mDefaultConstructor:Z
       9: aload_0
      10: aload_1
      11: putfield      #3                  // Field mClassLoader:Ljava/lang/ClassLoader;
      14: aload_0
      15: aload_2
      16: putfield      #4                  // Field mPool:Ljavassist/ClassPool;
      19: return

  public static org.apache.dubbo.common.bytecode.ClassGenerator newInstance();
    Code:
       0: new           #5                  // class org/apache/dubbo/common/bytecode/ClassGenerator
       3: dup
       4: invokestatic  #6                  // Method java/lang/Thread.currentThread:()Ljava/lang/Thread;
       7: invokevirtual #7                  // Method java/lang/Thread.getContextClassLoader:()Ljava/lang/ClassLoader;
      10: invokestatic  #6                  // Method java/lang/Thread.currentThread:()Ljava/lang/Thread;
      13: invokevirtual #7                  // Method java/lang/Thread.getContextClassLoader:()Ljava/lang/ClassLoader;
      16: invokestatic  #8                  // Method getClassPool:(Ljava/lang/ClassLoader;)Ljavassist/ClassPool;
      19: invokespecial #9                  // Method "<init>":(Ljava/lang/ClassLoader;Ljavassist/ClassPool;)V
      22: areturn

  public static org.apache.dubbo.common.bytecode.ClassGenerator newInstance(java.lang.ClassLoader);
    Code:
       0: new           #5                  // class org/apache/dubbo/common/bytecode/ClassGenerator
       3: dup
       4: aload_0
       5: aload_0
       6: invokestatic  #8                  // Method getClassPool:(Ljava/lang/ClassLoader;)Ljavassist/ClassPool;
       9: invokespecial #9                  // Method "<init>":(Ljava/lang/ClassLoader;Ljavassist/ClassPool;)V
      12: areturn

  public static boolean isDynamicClass(java.lang.Class<?>);
    Code:
       0: ldc           #10                 // class org/apache/dubbo/common/bytecode/ClassGenerator$DC
       2: aload_0
       3: invokevirtual #11                 // Method java/lang/Class.isAssignableFrom:(Ljava/lang/Class;)Z
       6: ireturn

  public static javassist.ClassPool getClassPool(java.lang.ClassLoader);
    Code:
       0: aload_0
       1: ifnonnull     8
       4: invokestatic  #12                 // Method javassist/ClassPool.getDefault:()Ljavassist/ClassPool;
       7: areturn
       8: getstatic     #13                 // Field POOL_MAP:Ljava/util/Map;
      11: aload_0
      12: invokeinterface #14,  2           // InterfaceMethod java/util/Map.get:(Ljava/lang/Object;)Ljava/lang/Object;
      17: checkcast     #15                 // class javassist/ClassPool
      20: astore_1
      21: aload_1
      22: ifnonnull     70
      25: new           #15                 // class javassist/ClassPool
      28: dup
      29: iconst_1
      30: invokespecial #16                 // Method javassist/ClassPool."<init>":(Z)V
      33: astore_1
      34: aload_1
      35: new           #17                 // class javassist/LoaderClassPath
      38: dup
      39: aload_0
      40: invokespecial #18                 // Method javassist/LoaderClassPath."<init>":(Ljava/lang/ClassLoader;)V
      43: invokevirtual #19                 // Method javassist/ClassPool.insertClassPath:(Ljavassist/ClassPath;)Ljavassist/ClassPath;
      46: pop
      47: aload_1
      48: new           #20                 // class org/apache/dubbo/common/bytecode/DubboLoaderClassPath
      51: dup
      52: invokespecial #21                 // Method org/apache/dubbo/common/bytecode/DubboLoaderClassPath."<init>":()V
      55: invokevirtual #19                 // Method javassist/ClassPool.insertClassPath:(Ljavassist/ClassPath;)Ljavassist/ClassPath;
      58: pop
      59: getstatic     #13                 // Field POOL_MAP:Ljava/util/Map;
      62: aload_0
      63: aload_1
      64: invokeinterface #22,  3           // InterfaceMethod java/util/Map.put:(Ljava/lang/Object;Ljava/lang/Object;)Ljava/lang/Object;
      69: pop
      70: aload_1
      71: areturn

  private static java.lang.String modifier(int);
    Code:
       0: new           #23                 // class java/lang/StringBuilder
       3: dup
       4: invokespecial #24                 // Method java/lang/StringBuilder."<init>":()V
       7: astore_1
       8: iload_0
       9: invokestatic  #25                 // Method java/lang/reflect/Modifier.isPublic:(I)Z
      12: ifeq          25
      15: aload_1
      16: ldc           #26                 // String public
      18: invokevirtual #27                 // Method java/lang/StringBuilder.append:(Ljava/lang/String;)Ljava/lang/StringBuilder;
      21: pop
      22: goto          56
      25: iload_0
      26: invokestatic  #28                 // Method java/lang/reflect/Modifier.isProtected:(I)Z
      29: ifeq          42
      32: aload_1
      33: ldc           #29                 // String protected
      35: invokevirtual #27                 // Method java/lang/StringBuilder.append:(Ljava/lang/String;)Ljava/lang/StringBuilder;
      38: pop
      39: goto          56
      42: iload_0
      43: invokestatic  #30                 // Method java/lang/reflect/Modifier.isPrivate:(I)Z
      46: ifeq          56
      49: aload_1
      50: ldc           #31                 // String private
      52: invokevirtual #27                 // Method java/lang/StringBuilder.append:(Ljava/lang/String;)Ljava/lang/StringBuilder;
      55: pop
      56: iload_0
      57: invokestatic  #32                 // Method java/lang/reflect/Modifier.isStatic:(I)Z
      60: ifeq          70
      63: aload_1
      64: ldc           #33                 // String  static
      66: invokevirtual #27                 // Method java/lang/StringBuilder.append:(Ljava/lang/String;)Ljava/lang/StringBuilder;
      69: pop
      70: iload_0
      71: invokestatic  #34                 // Method java/lang/reflect/Modifier.isVolatile:(I)Z
      74: ifeq          84
      77: aload_1
      78: ldc           #35                 // String  volatile
      80: invokevirtual #27                 // Method java/lang/StringBuilder.append:(Ljava/lang/String;)Ljava/lang/StringBuilder;
      83: pop
      84: aload_1
      85: invokevirtual #36                 // Method java/lang/StringBuilder.toString:()Ljava/lang/String;
      88: areturn

  public java.lang.String getClassName();
    Code:
       0: aload_0
       1: getfield      #37                 // Field mClassName:Ljava/lang/String;
       4: areturn

  public org.apache.dubbo.common.bytecode.ClassGenerator setClassName(java.lang.String);
    Code:
       0: aload_0
       1: aload_1
       2: putfield      #37                 // Field mClassName:Ljava/lang/String;
       5: aload_0
       6: areturn

  public org.apache.dubbo.common.bytecode.ClassGenerator addInterface(java.lang.String);
    Code:
       0: aload_0
       1: getfield      #38                 // Field mInterfaces:Ljava/util/Set;
       4: ifnonnull     18
       7: aload_0
       8: new           #39                 // class java/util/HashSet
      11: dup
      12: invokespecial #40                 // Method java/util/HashSet."<init>":()V
      15: putfield      #38                 // Field mInterfaces:Ljava/util/Set;
      18: aload_0
      19: getfield      #38                 // Field mInterfaces:Ljava/util/Set;
      22: aload_1
      23: invokeinterface #41,  2           // InterfaceMethod java/util/Set.add:(Ljava/lang/Object;)Z
      28: pop
      29: aload_0
      30: areturn

  public org.apache.dubbo.common.bytecode.ClassGenerator addInterface(java.lang.Class<?>);
    Code:
       0: aload_0
       1: aload_1
       2: invokevirtual #42                 // Method java/lang/Class.getName:()Ljava/lang/String;
       5: invokevirtual #43                 // Method addInterface:(Ljava/lang/String;)Lorg/apache/dubbo/common/bytecode/ClassGenerator;
       8: areturn

  public org.apache.dubbo.common.bytecode.ClassGenerator setSuperClass(java.lang.String);
    Code:
       0: aload_0
       1: aload_1
       2: putfield      #44                 // Field mSuperClass:Ljava/lang/String;
       5: aload_0
       6: areturn

  public org.apache.dubbo.common.bytecode.ClassGenerator setSuperClass(java.lang.Class<?>);
    Code:
       0: aload_0
       1: aload_1
       2: invokevirtual #42                 // Method java/lang/Class.getName:()Ljava/lang/String;
       5: putfield      #44                 // Field mSuperClass:Ljava/lang/String;
       8: aload_0
       9: areturn

  public org.apache.dubbo.common.bytecode.ClassGenerator addField(java.lang.String);
    Code:
       0: aload_0
       1: getfield      #45                 // Field mFields:Ljava/util/List;
       4: ifnonnull     18
       7: aload_0
       8: new           #46                 // class java/util/ArrayList
      11: dup
      12: invokespecial #47                 // Method java/util/ArrayList."<init>":()V
      15: putfield      #45                 // Field mFields:Ljava/util/List;
      18: aload_0
      19: getfield      #45                 // Field mFields:Ljava/util/List;
      22: aload_1
      23: invokeinterface #48,  2           // InterfaceMethod java/util/List.add:(Ljava/lang/Object;)Z
      28: pop
      29: aload_0
      30: areturn

  public org.apache.dubbo.common.bytecode.ClassGenerator addField(java.lang.String, int, java.lang.Class<?>);
    Code:
       0: aload_0
       1: aload_1
       2: iload_2
       3: aload_3
       4: aconst_null
       5: invokevirtual #49                 // Method addField:(Ljava/lang/String;ILjava/lang/Class;Ljava/lang/String;)Lorg/apache/dubbo/common/bytecode/ClassGenerator;
       8: areturn

  public org.apache.dubbo.common.bytecode.ClassGenerator addField(java.lang.String, int, java.lang.Class<?>, java.lang.String);
    Code:
       0: new           #23                 // class java/lang/StringBuilder
       3: dup
       4: invokespecial #24                 // Method java/lang/StringBuilder."<init>":()V
       7: astore        5
       9: aload         5
      11: iload_2
      12: invokestatic  #50                 // Method modifier:(I)Ljava/lang/String;
      15: invokevirtual #27                 // Method java/lang/StringBuilder.append:(Ljava/lang/String;)Ljava/lang/StringBuilder;
      18: bipush        32
      20: invokevirtual #51                 // Method java/lang/StringBuilder.append:(C)Ljava/lang/StringBuilder;
      23: aload_3
      24: invokestatic  #52                 // Method org/apache/dubbo/common/utils/ReflectUtils.getName:(Ljava/lang/Class;)Ljava/lang/String;
      27: invokevirtual #27                 // Method java/lang/StringBuilder.append:(Ljava/lang/String;)Ljava/lang/StringBuilder;
      30: bipush        32
      32: invokevirtual #51                 // Method java/lang/StringBuilder.append:(C)Ljava/lang/StringBuilder;
      35: pop
      36: aload         5
      38: aload_1
      39: invokevirtual #27                 // Method java/lang/StringBuilder.append:(Ljava/lang/String;)Ljava/lang/StringBuilder;
      42: pop
      43: aload         4
      45: invokestatic  #53                 // Method org/apache/dubbo/common/utils/StringUtils.isNotEmpty:(Ljava/lang/String;)Z
      48: ifeq          67
      51: aload         5
      53: bipush        61
      55: invokevirtual #51                 // Method java/lang/StringBuilder.append:(C)Ljava/lang/StringBuilder;
      58: pop
      59: aload         5
      61: aload         4
      63: invokevirtual #27                 // Method java/lang/StringBuilder.append:(Ljava/lang/String;)Ljava/lang/StringBuilder;
      66: pop
      67: aload         5
      69: bipush        59
      71: invokevirtual #51                 // Method java/lang/StringBuilder.append:(C)Ljava/lang/StringBuilder;
      74: pop
      75: aload_0
      76: aload         5
      78: invokevirtual #36                 // Method java/lang/StringBuilder.toString:()Ljava/lang/String;
      81: invokevirtual #54                 // Method addField:(Ljava/lang/String;)Lorg/apache/dubbo/common/bytecode/ClassGenerator;
      84: areturn

  public org.apache.dubbo.common.bytecode.ClassGenerator addMethod(java.lang.String);
    Code:
       0: aload_0
       1: getfield      #55                 // Field mMethods:Ljava/util/List;
       4: ifnonnull     18
       7: aload_0
       8: new           #46                 // class java/util/ArrayList
      11: dup
      12: invokespecial #47                 // Method java/util/ArrayList."<init>":()V
      15: putfield      #55                 // Field mMethods:Ljava/util/List;
      18: aload_0
      19: getfield      #55                 // Field mMethods:Ljava/util/List;
      22: aload_1
      23: invokeinterface #48,  2           // InterfaceMethod java/util/List.add:(Ljava/lang/Object;)Z
      28: pop
      29: aload_0
      30: areturn

  public org.apache.dubbo.common.bytecode.ClassGenerator addMethod(java.lang.String, int, java.lang.Class<?>, java.lang.Class<?>[], java.lang.String);
    Code:
       0: aload_0
       1: aload_1
       2: iload_2
       3: aload_3
       4: aload         4
       6: aconst_null
       7: aload         5
       9: invokevirtual #56                 // Method addMethod:(Ljava/lang/String;ILjava/lang/Class;[Ljava/lang/Class;[Ljava/lang/Class;Ljava/lang/String;)Lorg/apache/dubbo/common/bytecode/ClassGenerator;
      12: areturn

  public org.apache.dubbo.common.bytecode.ClassGenerator addMethod(java.lang.String, int, java.lang.Class<?>, java.lang.Class<?>[], java.lang.Class<?>[], java.lang.String);
    Code:
       0: new           #23                 // class java/lang/StringBuilder
       3: dup
       4: invokespecial #24                 // Method java/lang/StringBuilder."<init>":()V
       7: astore        7
       9: aload         7
      11: iload_2
      12: invokestatic  #50                 // Method modifier:(I)Ljava/lang/String;
      15: invokevirtual #27                 // Method java/lang/StringBuilder.append:(Ljava/lang/String;)Ljava/lang/StringBuilder;
      18: bipush        32
      20: invokevirtual #51                 // Method java/lang/StringBuilder.append:(C)Ljava/lang/StringBuilder;
      23: aload_3
      24: invokestatic  #52                 // Method org/apache/dubbo/common/utils/ReflectUtils.getName:(Ljava/lang/Class;)Ljava/lang/String;
      27: invokevirtual #27                 // Method java/lang/StringBuilder.append:(Ljava/lang/String;)Ljava/lang/StringBuilder;
      30: bipush        32
      32: invokevirtual #51                 // Method java/lang/StringBuilder.append:(C)Ljava/lang/StringBuilder;
      35: aload_1
      36: invokevirtual #27                 // Method java/lang/StringBuilder.append:(Ljava/lang/String;)Ljava/lang/StringBuilder;
      39: pop
      40: aload         7
      42: bipush        40
      44: invokevirtual #51                 // Method java/lang/StringBuilder.append:(C)Ljava/lang/StringBuilder;
      47: pop
      48: aload         4
      50: invokestatic  #57                 // Method org/apache/dubbo/common/utils/ArrayUtils.isNotEmpty:([Ljava/lang/Object;)Z
      53: ifeq          113
      56: iconst_0
      57: istore        8
      59: iload         8
      61: aload         4
      63: arraylength
      64: if_icmpge     113
      67: iload         8
      69: ifle          80
      72: aload         7
      74: bipush        44
      76: invokevirtual #51                 // Method java/lang/StringBuilder.append:(C)Ljava/lang/StringBuilder;
      79: pop
      80: aload         7
      82: aload         4
      84: iload         8
      86: aaload
      87: invokestatic  #52                 // Method org/apache/dubbo/common/utils/ReflectUtils.getName:(Ljava/lang/Class;)Ljava/lang/String;
      90: invokevirtual #27                 // Method java/lang/StringBuilder.append:(Ljava/lang/String;)Ljava/lang/StringBuilder;
      93: pop
      94: aload         7
      96: ldc           #58                 // String  arg
      98: invokevirtual #27                 // Method java/lang/StringBuilder.append:(Ljava/lang/String;)Ljava/lang/StringBuilder;
     101: iload         8
     103: invokevirtual #59                 // Method java/lang/StringBuilder.append:(I)Ljava/lang/StringBuilder;
     106: pop
     107: iinc          8, 1
     110: goto          59
     113: aload         7
     115: bipush        41
     117: invokevirtual #51                 // Method java/lang/StringBuilder.append:(C)Ljava/lang/StringBuilder;
     120: pop
     121: aload         5
     123: invokestatic  #57                 // Method org/apache/dubbo/common/utils/ArrayUtils.isNotEmpty:([Ljava/lang/Object;)Z
     126: ifeq          181
     129: aload         7
     131: ldc           #60                 // String  throws
     133: invokevirtual #27                 // Method java/lang/StringBuilder.append:(Ljava/lang/String;)Ljava/lang/StringBuilder;
     136: pop
     137: iconst_0
     138: istore        8
     140: iload         8
     142: aload         5
     144: arraylength
     145: if_icmpge     181
     148: iload         8
     150: ifle          161
     153: aload         7
     155: bipush        44
     157: invokevirtual #51                 // Method java/lang/StringBuilder.append:(C)Ljava/lang/StringBuilder;
     160: pop
     161: aload         7
     163: aload         5
     165: iload         8
     167: aaload
     168: invokestatic  #52                 // Method org/apache/dubbo/common/utils/ReflectUtils.getName:(Ljava/lang/Class;)Ljava/lang/String;
     171: invokevirtual #27                 // Method java/lang/StringBuilder.append:(Ljava/lang/String;)Ljava/lang/StringBuilder;
     174: pop
     175: iinc          8, 1
     178: goto          140
     181: aload         7
     183: bipush        123
     185: invokevirtual #51                 // Method java/lang/StringBuilder.append:(C)Ljava/lang/StringBuilder;
     188: aload         6
     190: invokevirtual #27                 // Method java/lang/StringBuilder.append:(Ljava/lang/String;)Ljava/lang/StringBuilder;
     193: bipush        125
     195: invokevirtual #51                 // Method java/lang/StringBuilder.append:(C)Ljava/lang/StringBuilder;
     198: pop
     199: aload_0
     200: aload         7
     202: invokevirtual #36                 // Method java/lang/StringBuilder.toString:()Ljava/lang/String;
     205: invokevirtual #61                 // Method addMethod:(Ljava/lang/String;)Lorg/apache/dubbo/common/bytecode/ClassGenerator;
     208: areturn

  public org.apache.dubbo.common.bytecode.ClassGenerator addMethod(java.lang.reflect.Method);
    Code:
       0: aload_0
       1: aload_1
       2: invokevirtual #62                 // Method java/lang/reflect/Method.getName:()Ljava/lang/String;
       5: aload_1
       6: invokevirtual #63                 // Method addMethod:(Ljava/lang/String;Ljava/lang/reflect/Method;)Lorg/apache/dubbo/common/bytecode/ClassGenerator;
       9: pop
      10: aload_0
      11: areturn

  public org.apache.dubbo.common.bytecode.ClassGenerator addMethod(java.lang.String, java.lang.reflect.Method);
    Code:
       0: new           #23                 // class java/lang/StringBuilder
       3: dup
       4: invokespecial #24                 // Method java/lang/StringBuilder."<init>":()V
       7: aload_1
       8: invokevirtual #27                 // Method java/lang/StringBuilder.append:(Ljava/lang/String;)Ljava/lang/StringBuilder;
      11: aload_2
      12: invokestatic  #64                 // Method org/apache/dubbo/common/utils/ReflectUtils.getDescWithoutMethodName:(Ljava/lang/reflect/Method;)Ljava/lang/String;
      15: invokevirtual #27                 // Method java/lang/StringBuilder.append:(Ljava/lang/String;)Ljava/lang/StringBuilder;
      18: invokevirtual #36                 // Method java/lang/StringBuilder.toString:()Ljava/lang/String;
      21: astore_3
      22: aload_0
      23: new           #23                 // class java/lang/StringBuilder
      26: dup
      27: invokespecial #24                 // Method java/lang/StringBuilder."<init>":()V
      30: bipush        58
      32: invokevirtual #51                 // Method java/lang/StringBuilder.append:(C)Ljava/lang/StringBuilder;
      35: aload_3
      36: invokevirtual #27                 // Method java/lang/StringBuilder.append:(Ljava/lang/String;)Ljava/lang/StringBuilder;
      39: invokevirtual #36                 // Method java/lang/StringBuilder.toString:()Ljava/lang/String;
      42: invokevirtual #61                 // Method addMethod:(Ljava/lang/String;)Lorg/apache/dubbo/common/bytecode/ClassGenerator;
      45: pop
      46: aload_0
      47: getfield      #65                 // Field mCopyMethods:Ljava/util/Map;
      50: ifnonnull     66
      53: aload_0
      54: new           #66                 // class java/util/concurrent/ConcurrentHashMap
      57: dup
      58: bipush        8
      60: invokespecial #67                 // Method java/util/concurrent/ConcurrentHashMap."<init>":(I)V
      63: putfield      #65                 // Field mCopyMethods:Ljava/util/Map;
      66: aload_0
      67: getfield      #65                 // Field mCopyMethods:Ljava/util/Map;
      70: aload_3
      71: aload_2
      72: invokeinterface #22,  3           // InterfaceMethod java/util/Map.put:(Ljava/lang/Object;Ljava/lang/Object;)Ljava/lang/Object;
      77: pop
      78: aload_0
      79: areturn

  public org.apache.dubbo.common.bytecode.ClassGenerator addConstructor(java.lang.String);
    Code:
       0: aload_0
       1: getfield      #68                 // Field mConstructors:Ljava/util/List;
       4: ifnonnull     18
       7: aload_0
       8: new           #69                 // class java/util/LinkedList
      11: dup
      12: invokespecial #70                 // Method java/util/LinkedList."<init>":()V
      15: putfield      #68                 // Field mConstructors:Ljava/util/List;
      18: aload_0
      19: getfield      #68                 // Field mConstructors:Ljava/util/List;
      22: aload_1
      23: invokeinterface #48,  2           // InterfaceMethod java/util/List.add:(Ljava/lang/Object;)Z
      28: pop
      29: aload_0
      30: areturn

  public org.apache.dubbo.common.bytecode.ClassGenerator addConstructor(int, java.lang.Class<?>[], java.lang.String);
    Code:
       0: aload_0
       1: iload_1
       2: aload_2
       3: aconst_null
       4: aload_3
       5: invokevirtual #71                 // Method addConstructor:(I[Ljava/lang/Class;[Ljava/lang/Class;Ljava/lang/String;)Lorg/apache/dubbo/common/bytecode/ClassGenerator;
       8: areturn

  public org.apache.dubbo.common.bytecode.ClassGenerator addConstructor(int, java.lang.Class<?>[], java.lang.Class<?>[], java.lang.String);
    Code:
       0: new           #23                 // class java/lang/StringBuilder
       3: dup
       4: invokespecial #24                 // Method java/lang/StringBuilder."<init>":()V
       7: astore        5
       9: aload         5
      11: iload_1
      12: invokestatic  #50                 // Method modifier:(I)Ljava/lang/String;
      15: invokevirtual #27                 // Method java/lang/StringBuilder.append:(Ljava/lang/String;)Ljava/lang/StringBuilder;
      18: bipush        32
      20: invokevirtual #51                 // Method java/lang/StringBuilder.append:(C)Ljava/lang/StringBuilder;
      23: ldc           #72                 // String <init>
      25: invokevirtual #27                 // Method java/lang/StringBuilder.append:(Ljava/lang/String;)Ljava/lang/StringBuilder;
      28: pop
      29: aload         5
      31: bipush        40
      33: invokevirtual #51                 // Method java/lang/StringBuilder.append:(C)Ljava/lang/StringBuilder;
      36: pop
      37: iconst_0
      38: istore        6
      40: iload         6
      42: aload_2
      43: arraylength
      44: if_icmpge     92
      47: iload         6
      49: ifle          60
      52: aload         5
      54: bipush        44
      56: invokevirtual #51                 // Method java/lang/StringBuilder.append:(C)Ljava/lang/StringBuilder;
      59: pop
      60: aload         5
      62: aload_2
      63: iload         6
      65: aaload
      66: invokestatic  #52                 // Method org/apache/dubbo/common/utils/ReflectUtils.getName:(Ljava/lang/Class;)Ljava/lang/String;
      69: invokevirtual #27                 // Method java/lang/StringBuilder.append:(Ljava/lang/String;)Ljava/lang/StringBuilder;
      72: pop
      73: aload         5
      75: ldc           #58                 // String  arg
      77: invokevirtual #27                 // Method java/lang/StringBuilder.append:(Ljava/lang/String;)Ljava/lang/StringBuilder;
      80: iload         6
      82: invokevirtual #59                 // Method java/lang/StringBuilder.append:(I)Ljava/lang/StringBuilder;
      85: pop
      86: iinc          6, 1
      89: goto          40
      92: aload         5
      94: bipush        41
      96: invokevirtual #51                 // Method java/lang/StringBuilder.append:(C)Ljava/lang/StringBuilder;
      99: pop
     100: aload_3
     101: invokestatic  #57                 // Method org/apache/dubbo/common/utils/ArrayUtils.isNotEmpty:([Ljava/lang/Object;)Z
     104: ifeq          157
     107: aload         5
     109: ldc           #60                 // String  throws
     111: invokevirtual #27                 // Method java/lang/StringBuilder.append:(Ljava/lang/String;)Ljava/lang/StringBuilder;
     114: pop
     115: iconst_0
     116: istore        6
     118: iload         6
     120: aload_3
     121: arraylength
     122: if_icmpge     157
     125: iload         6
     127: ifle          138
     130: aload         5
     132: bipush        44
     134: invokevirtual #51                 // Method java/lang/StringBuilder.append:(C)Ljava/lang/StringBuilder;
     137: pop
     138: aload         5
     140: aload_3
     141: iload         6
     143: aaload
     144: invokestatic  #52                 // Method org/apache/dubbo/common/utils/ReflectUtils.getName:(Ljava/lang/Class;)Ljava/lang/String;
     147: invokevirtual #27                 // Method java/lang/StringBuilder.append:(Ljava/lang/String;)Ljava/lang/StringBuilder;
     150: pop
     151: iinc          6, 1
     154: goto          118
     157: aload         5
     159: bipush        123
     161: invokevirtual #51                 // Method java/lang/StringBuilder.append:(C)Ljava/lang/StringBuilder;
     164: aload         4
     166: invokevirtual #27                 // Method java/lang/StringBuilder.append:(Ljava/lang/String;)Ljava/lang/StringBuilder;
     169: bipush        125
     171: invokevirtual #51                 // Method java/lang/StringBuilder.append:(C)Ljava/lang/StringBuilder;
     174: pop
     175: aload_0
     176: aload         5
     178: invokevirtual #36                 // Method java/lang/StringBuilder.toString:()Ljava/lang/String;
     181: invokevirtual #73                 // Method addConstructor:(Ljava/lang/String;)Lorg/apache/dubbo/common/bytecode/ClassGenerator;
     184: areturn

  public org.apache.dubbo.common.bytecode.ClassGenerator addConstructor(java.lang.reflect.Constructor<?>);
    Code:
       0: aload_1
       1: invokestatic  #74                 // Method org/apache/dubbo/common/utils/ReflectUtils.getDesc:(Ljava/lang/reflect/Constructor;)Ljava/lang/String;
       4: astore_2
       5: aload_0
       6: new           #23                 // class java/lang/StringBuilder
       9: dup
      10: invokespecial #24                 // Method java/lang/StringBuilder."<init>":()V
      13: ldc           #75                 // String :
      15: invokevirtual #27                 // Method java/lang/StringBuilder.append:(Ljava/lang/String;)Ljava/lang/StringBuilder;
      18: aload_2
      19: invokevirtual #27                 // Method java/lang/StringBuilder.append:(Ljava/lang/String;)Ljava/lang/StringBuilder;
      22: invokevirtual #36                 // Method java/lang/StringBuilder.toString:()Ljava/lang/String;
      25: invokevirtual #73                 // Method addConstructor:(Ljava/lang/String;)Lorg/apache/dubbo/common/bytecode/ClassGenerator;
      28: pop
      29: aload_0
      30: getfield      #76                 // Field mCopyConstructors:Ljava/util/Map;
      33: ifnonnull     48
      36: aload_0
      37: new           #66                 // class java/util/concurrent/ConcurrentHashMap
      40: dup
      41: iconst_4
      42: invokespecial #67                 // Method java/util/concurrent/ConcurrentHashMap."<init>":(I)V
      45: putfield      #76                 // Field mCopyConstructors:Ljava/util/Map;
      48: aload_0
      49: getfield      #76                 // Field mCopyConstructors:Ljava/util/Map;
      52: aload_2
      53: aload_1
      54: invokeinterface #22,  3           // InterfaceMethod java/util/Map.put:(Ljava/lang/Object;Ljava/lang/Object;)Ljava/lang/Object;
      59: pop
      60: aload_0
      61: areturn

  public org.apache.dubbo.common.bytecode.ClassGenerator addDefaultConstructor();
    Code:
       0: aload_0
       1: iconst_1
       2: putfield      #2                  // Field mDefaultConstructor:Z
       5: aload_0
       6: areturn

  public javassist.ClassPool getClassPool();
    Code:
       0: aload_0
       1: getfield      #4                  // Field mPool:Ljavassist/ClassPool;
       4: areturn

  public java.lang.Class<?> toClass(java.lang.Class<?>);
    Code:
       0: aload_0
       1: aload_1
       2: aload_0
       3: getfield      #3                  // Field mClassLoader:Ljava/lang/ClassLoader;
       6: aload_0
       7: invokevirtual #77                 // Method java/lang/Object.getClass:()Ljava/lang/Class;
      10: invokevirtual #78                 // Method java/lang/Class.getProtectionDomain:()Ljava/security/ProtectionDomain;
      13: invokevirtual #79                 // Method toClass:(Ljava/lang/Class;Ljava/lang/ClassLoader;Ljava/security/ProtectionDomain;)Ljava/lang/Class;
      16: areturn

  public java.lang.Class<?> toClass(java.lang.Class<?>, java.lang.ClassLoader, java.security.ProtectionDomain);
    Code:
       0: aload_0
       1: getfield      #80                 // Field mCtc:Ljavassist/CtClass;
       4: ifnull        14
       7: aload_0
       8: getfield      #80                 // Field mCtc:Ljavassist/CtClass;
      11: invokevirtual #81                 // Method javassist/CtClass.detach:()V
      14: getstatic     #82                 // Field CLASS_NAME_COUNTER:Ljava/util/concurrent/atomic/AtomicLong;
      17: invokevirtual #83                 // Method java/util/concurrent/atomic/AtomicLong.getAndIncrement:()J
      20: lstore        4
      22: aload_0
      23: getfield      #44                 // Field mSuperClass:Ljava/lang/String;
      26: ifnonnull     33
      29: aconst_null
      30: goto          44
      33: aload_0
      34: getfield      #4                  // Field mPool:Ljavassist/ClassPool;
      37: aload_0
      38: getfield      #44                 // Field mSuperClass:Ljava/lang/String;
      41: invokevirtual #84                 // Method javassist/ClassPool.get:(Ljava/lang/String;)Ljavassist/CtClass;
      44: astore        6
      46: aload_0
      47: getfield      #37                 // Field mClassName:Ljava/lang/String;
      50: ifnonnull     123
      53: aload_0
      54: new           #23                 // class java/lang/StringBuilder
      57: dup
      58: invokespecial #24                 // Method java/lang/StringBuilder."<init>":()V
      61: aload_0
      62: getfield      #44                 // Field mSuperClass:Ljava/lang/String;
      65: ifnull        79
      68: aload         6
      70: invokevirtual #85                 // Method javassist/CtClass.getModifiers:()I
      73: invokestatic  #86                 // Method javassist/Modifier.isPublic:(I)Z
      76: ifeq          87
      79: ldc           #5                  // class org/apache/dubbo/common/bytecode/ClassGenerator
      81: invokevirtual #42                 // Method java/lang/Class.getName:()Ljava/lang/String;
      84: goto          109
      87: new           #23                 // class java/lang/StringBuilder
      90: dup
      91: invokespecial #24                 // Method java/lang/StringBuilder."<init>":()V
      94: aload_0
      95: getfield      #44                 // Field mSuperClass:Ljava/lang/String;
      98: invokevirtual #27                 // Method java/lang/StringBuilder.append:(Ljava/lang/String;)Ljava/lang/StringBuilder;
     101: ldc           #87                 // String $sc
     103: invokevirtual #27                 // Method java/lang/StringBuilder.append:(Ljava/lang/String;)Ljava/lang/StringBuilder;
     106: invokevirtual #36                 // Method java/lang/StringBuilder.toString:()Ljava/lang/String;
     109: invokevirtual #27                 // Method java/lang/StringBuilder.append:(Ljava/lang/String;)Ljava/lang/StringBuilder;
     112: lload         4
     114: invokevirtual #88                 // Method java/lang/StringBuilder.append:(J)Ljava/lang/StringBuilder;
     117: invokevirtual #36                 // Method java/lang/StringBuilder.toString:()Ljava/lang/String;
     120: putfield      #37                 // Field mClassName:Ljava/lang/String;
     123: aload_0
     124: aload_0
     125: getfield      #4                  // Field mPool:Ljavassist/ClassPool;
     128: aload_0
     129: getfield      #37                 // Field mClassName:Ljava/lang/String;
     132: invokevirtual #89                 // Method javassist/ClassPool.makeClass:(Ljava/lang/String;)Ljavassist/CtClass;
     135: putfield      #80                 // Field mCtc:Ljavassist/CtClass;
     138: aload_0
     139: getfield      #44                 // Field mSuperClass:Ljava/lang/String;
     142: ifnull        154
     145: aload_0
     146: getfield      #80                 // Field mCtc:Ljavassist/CtClass;
     149: aload         6
     151: invokevirtual #90                 // Method javassist/CtClass.setSuperclass:(Ljavassist/CtClass;)V
     154: aload_0
     155: getfield      #80                 // Field mCtc:Ljavassist/CtClass;
     158: aload_0
     159: getfield      #4                  // Field mPool:Ljavassist/ClassPool;
     162: ldc           #10                 // class org/apache/dubbo/common/bytecode/ClassGenerator$DC
     164: invokevirtual #42                 // Method java/lang/Class.getName:()Ljava/lang/String;
     167: invokevirtual #84                 // Method javassist/ClassPool.get:(Ljava/lang/String;)Ljavassist/CtClass;
     170: invokevirtual #91                 // Method javassist/CtClass.addInterface:(Ljavassist/CtClass;)V
     173: aload_0
     174: getfield      #38                 // Field mInterfaces:Ljava/util/Set;
     177: ifnull        232
     180: aload_0
     181: getfield      #38                 // Field mInterfaces:Ljava/util/Set;
     184: invokeinterface #92,  1           // InterfaceMethod java/util/Set.iterator:()Ljava/util/Iterator;
     189: astore        7
     191: aload         7
     193: invokeinterface #93,  1           // InterfaceMethod java/util/Iterator.hasNext:()Z
     198: ifeq          232
     201: aload         7
     203: invokeinterface #94,  1           // InterfaceMethod java/util/Iterator.next:()Ljava/lang/Object;
     208: checkcast     #95                 // class java/lang/String
     211: astore        8
     213: aload_0
     214: getfield      #80                 // Field mCtc:Ljavassist/CtClass;
     217: aload_0
     218: getfield      #4                  // Field mPool:Ljavassist/ClassPool;
     221: aload         8
     223: invokevirtual #84                 // Method javassist/ClassPool.get:(Ljava/lang/String;)Ljavassist/CtClass;
     226: invokevirtual #91                 // Method javassist/CtClass.addInterface:(Ljavassist/CtClass;)V
     229: goto          191
     232: aload_0
     233: getfield      #45                 // Field mFields:Ljava/util/List;
     236: ifnull        291
     239: aload_0
     240: getfield      #45                 // Field mFields:Ljava/util/List;
     243: invokeinterface #96,  1           // InterfaceMethod java/util/List.iterator:()Ljava/util/Iterator;
     248: astore        7
     250: aload         7
     252: invokeinterface #93,  1           // InterfaceMethod java/util/Iterator.hasNext:()Z
     257: ifeq          291
     260: aload         7
     262: invokeinterface #94,  1           // InterfaceMethod java/util/Iterator.next:()Ljava/lang/Object;
     267: checkcast     #95                 // class java/lang/String
     270: astore        8
     272: aload_0
     273: getfield      #80                 // Field mCtc:Ljavassist/CtClass;
     276: aload         8
     278: aload_0
     279: getfield      #80                 // Field mCtc:Ljavassist/CtClass;
     282: invokestatic  #97                 // Method javassist/CtField.make:(Ljava/lang/String;Ljavassist/CtClass;)Ljavassist/CtField;
     285: invokevirtual #98                 // Method javassist/CtClass.addField:(Ljavassist/CtField;)V
     288: goto          250
     291: aload_0
     292: getfield      #55                 // Field mMethods:Ljava/util/List;
     295: ifnull        414
     298: aload_0
     299: getfield      #55                 // Field mMethods:Ljava/util/List;
     302: invokeinterface #96,  1           // InterfaceMethod java/util/List.iterator:()Ljava/util/Iterator;
     307: astore        7
     309: aload         7
     311: invokeinterface #93,  1           // InterfaceMethod java/util/Iterator.hasNext:()Z
     316: ifeq          414
     319: aload         7
     321: invokeinterface #94,  1           // InterfaceMethod java/util/Iterator.next:()Ljava/lang/Object;
     326: checkcast     #95                 // class java/lang/String
     329: astore        8
     331: aload         8
     333: iconst_0
     334: invokevirtual #99                 // Method java/lang/String.charAt:(I)C
     337: bipush        58
     339: if_icmpne     395
     342: aload_0
     343: getfield      #80                 // Field mCtc:Ljavassist/CtClass;
     346: aload_0
     347: aload_0
     348: getfield      #65                 // Field mCopyMethods:Ljava/util/Map;
     351: aload         8
     353: iconst_1
     354: invokevirtual #100                // Method java/lang/String.substring:(I)Ljava/lang/String;
     357: invokeinterface #14,  2           // InterfaceMethod java/util/Map.get:(Ljava/lang/Object;)Ljava/lang/Object;
     362: checkcast     #101                // class java/lang/reflect/Method
     365: invokespecial #102                // Method getCtMethod:(Ljava/lang/reflect/Method;)Ljavassist/CtMethod;
     368: aload         8
     370: iconst_1
     371: aload         8
     373: bipush        40
     375: invokevirtual #103                // Method java/lang/String.indexOf:(I)I
     378: invokevirtual #104                // Method java/lang/String.substring:(II)Ljava/lang/String;
     381: aload_0
     382: getfield      #80                 // Field mCtc:Ljavassist/CtClass;
     385: aconst_null
     386: invokestatic  #105                // Method javassist/CtNewMethod.copy:(Ljavassist/CtMethod;Ljava/lang/String;Ljavassist/CtClass;Ljavassist/ClassMap;)Ljavassist/CtMethod;
     389: invokevirtual #106                // Method javassist/CtClass.addMethod:(Ljavassist/CtMethod;)V
     392: goto          411
     395: aload_0
     396: getfield      #80                 // Field mCtc:Ljavassist/CtClass;
     399: aload         8
     401: aload_0
     402: getfield      #80                 // Field mCtc:Ljavassist/CtClass;
     405: invokestatic  #107                // Method javassist/CtNewMethod.make:(Ljava/lang/String;Ljavassist/CtClass;)Ljavassist/CtMethod;
     408: invokevirtual #106                // Method javassist/CtClass.addMethod:(Ljavassist/CtMethod;)V
     411: goto          309
     414: aload_0
     415: getfield      #2                  // Field mDefaultConstructor:Z
     418: ifeq          435
     421: aload_0
     422: getfield      #80                 // Field mCtc:Ljavassist/CtClass;
     425: aload_0
     426: getfield      #80                 // Field mCtc:Ljavassist/CtClass;
     429: invokestatic  #108                // Method javassist/CtNewConstructor.defaultConstructor:(Ljavassist/CtClass;)Ljavassist/CtConstructor;
     432: invokevirtual #109                // Method javassist/CtClass.addConstructor:(Ljavassist/CtConstructor;)V
     435: aload_0
     436: getfield      #68                 // Field mConstructors:Ljava/util/List;
     439: ifnull        572
     442: aload_0
     443: getfield      #68                 // Field mConstructors:Ljava/util/List;
     446: invokeinterface #96,  1           // InterfaceMethod java/util/List.iterator:()Ljava/util/Iterator;
     451: astore        7
     453: aload         7
     455: invokeinterface #93,  1           // InterfaceMethod java/util/Iterator.hasNext:()Z
     460: ifeq          572
     463: aload         7
     465: invokeinterface #94,  1           // InterfaceMethod java/util/Iterator.next:()Ljava/lang/Object;
     470: checkcast     #95                 // class java/lang/String
     473: astore        8
     475: aload         8
     477: iconst_0
     478: invokevirtual #99                 // Method java/lang/String.charAt:(I)C
     481: bipush        58
     483: if_icmpne     526
     486: aload_0
     487: getfield      #80                 // Field mCtc:Ljavassist/CtClass;
     490: aload_0
     491: aload_0
     492: getfield      #76                 // Field mCopyConstructors:Ljava/util/Map;
     495: aload         8
     497: iconst_1
     498: invokevirtual #100                // Method java/lang/String.substring:(I)Ljava/lang/String;
     501: invokeinterface #14,  2           // InterfaceMethod java/util/Map.get:(Ljava/lang/Object;)Ljava/lang/Object;
     506: checkcast     #110                // class java/lang/reflect/Constructor
     509: invokespecial #111                // Method getCtConstructor:(Ljava/lang/reflect/Constructor;)Ljavassist/CtConstructor;
     512: aload_0
     513: getfield      #80                 // Field mCtc:Ljavassist/CtClass;
     516: aconst_null
     517: invokestatic  #112                // Method javassist/CtNewConstructor.copy:(Ljavassist/CtConstructor;Ljavassist/CtClass;Ljavassist/ClassMap;)Ljavassist/CtConstructor;
     520: invokevirtual #109                // Method javassist/CtClass.addConstructor:(Ljavassist/CtConstructor;)V
     523: goto          569
     526: aload_0
     527: getfield      #80                 // Field mCtc:Ljavassist/CtClass;
     530: invokevirtual #113                // Method javassist/CtClass.getSimpleName:()Ljava/lang/String;
     533: ldc           #114                // String \\$+
     535: invokevirtual #115                // Method java/lang/String.split:(Ljava/lang/String;)[Ljava/lang/String;
     538: astore        9
     540: aload_0
     541: getfield      #80                 // Field mCtc:Ljavassist/CtClass;
     544: aload         8
     546: ldc           #72                 // String <init>
     548: aload         9
     550: aload         9
     552: arraylength
     553: iconst_1
     554: isub
     555: aaload
     556: invokevirtual #116                // Method java/lang/String.replaceFirst:(Ljava/lang/String;Ljava/lang/String;)Ljava/lang/String;
     559: aload_0
     560: getfield      #80                 // Field mCtc:Ljavassist/CtClass;
     563: invokestatic  #117                // Method javassist/CtNewConstructor.make:(Ljava/lang/String;Ljavassist/CtClass;)Ljavassist/CtConstructor;
     566: invokevirtual #109                // Method javassist/CtClass.addConstructor:(Ljavassist/CtConstructor;)V
     569: goto          453
     572: aload_0
     573: getfield      #4                  // Field mPool:Ljavassist/ClassPool;
     576: aload_0
     577: getfield      #80                 // Field mCtc:Ljavassist/CtClass;
     580: aload_1
     581: aload_2
     582: aload_3
     583: invokevirtual #118                // Method javassist/ClassPool.toClass:(Ljavassist/CtClass;Ljava/lang/Class;Ljava/lang/ClassLoader;Ljava/security/ProtectionDomain;)Ljava/lang/Class;
     586: areturn
     587: astore        7
     589: aload         7
     591: instanceof    #120                // class javassist/CannotCompileException
     594: ifne          611
     597: aload_0
     598: getfield      #4                  // Field mPool:Ljavassist/ClassPool;
     601: aload_0
     602: getfield      #80                 // Field mCtc:Ljavassist/CtClass;
     605: aload_2
     606: aload_3
     607: invokevirtual #121                // Method javassist/ClassPool.toClass:(Ljavassist/CtClass;Ljava/lang/ClassLoader;Ljava/security/ProtectionDomain;)Ljava/lang/Class;
     610: areturn
     611: aload         7
     613: athrow
     614: astore        6
     616: aload         6
     618: athrow
     619: astore        6
     621: new           #122                // class java/lang/RuntimeException
     624: dup
     625: aload         6
     627: invokevirtual #124                // Method java/lang/Exception.getMessage:()Ljava/lang/String;
     630: aload         6
     632: invokespecial #125                // Method java/lang/RuntimeException."<init>":(Ljava/lang/String;Ljava/lang/Throwable;)V
     635: athrow
    Exception table:
       from    to  target type
         572   586   587   Class java/lang/Throwable
          22   586   614   Class java/lang/RuntimeException
         587   610   614   Class java/lang/RuntimeException
         611   614   614   Class java/lang/RuntimeException
          22   586   619   Class javassist/NotFoundException
          22   586   619   Class javassist/CannotCompileException
         587   610   619   Class javassist/NotFoundException
         587   610   619   Class javassist/CannotCompileException
         611   614   619   Class javassist/NotFoundException
         611   614   619   Class javassist/CannotCompileException

  public void release();
    Code:
       0: aload_0
       1: getfield      #80                 // Field mCtc:Ljavassist/CtClass;
       4: ifnull        14
       7: aload_0
       8: getfield      #80                 // Field mCtc:Ljavassist/CtClass;
      11: invokevirtual #81                 // Method javassist/CtClass.detach:()V
      14: aload_0
      15: getfield      #38                 // Field mInterfaces:Ljava/util/Set;
      18: ifnull        30
      21: aload_0
      22: getfield      #38                 // Field mInterfaces:Ljava/util/Set;
      25: invokeinterface #126,  1          // InterfaceMethod java/util/Set.clear:()V
      30: aload_0
      31: getfield      #45                 // Field mFields:Ljava/util/List;
      34: ifnull        46
      37: aload_0
      38: getfield      #45                 // Field mFields:Ljava/util/List;
      41: invokeinterface #127,  1          // InterfaceMethod java/util/List.clear:()V
      46: aload_0
      47: getfield      #55                 // Field mMethods:Ljava/util/List;
      50: ifnull        62
      53: aload_0
      54: getfield      #55                 // Field mMethods:Ljava/util/List;
      57: invokeinterface #127,  1          // InterfaceMethod java/util/List.clear:()V
      62: aload_0
      63: getfield      #68                 // Field mConstructors:Ljava/util/List;
      66: ifnull        78
      69: aload_0
      70: getfield      #68                 // Field mConstructors:Ljava/util/List;
      73: invokeinterface #127,  1          // InterfaceMethod java/util/List.clear:()V
      78: aload_0
      79: getfield      #65                 // Field mCopyMethods:Ljava/util/Map;
      82: ifnull        94
      85: aload_0
      86: getfield      #65                 // Field mCopyMethods:Ljava/util/Map;
      89: invokeinterface #128,  1          // InterfaceMethod java/util/Map.clear:()V
      94: aload_0
      95: getfield      #76                 // Field mCopyConstructors:Ljava/util/Map;
      98: ifnull        110
     101: aload_0
     102: getfield      #76                 // Field mCopyConstructors:Ljava/util/Map;
     105: invokeinterface #128,  1          // InterfaceMethod java/util/Map.clear:()V
     110: return

  private javassist.CtClass getCtClass(java.lang.Class<?>) throws javassist.NotFoundException;
    Code:
       0: aload_0
       1: getfield      #4                  // Field mPool:Ljavassist/ClassPool;
       4: aload_1
       5: invokevirtual #42                 // Method java/lang/Class.getName:()Ljava/lang/String;
       8: invokevirtual #84                 // Method javassist/ClassPool.get:(Ljava/lang/String;)Ljavassist/CtClass;
      11: areturn

  private javassist.CtMethod getCtMethod(java.lang.reflect.Method) throws javassist.NotFoundException;
    Code:
       0: aload_0
       1: aload_1
       2: invokevirtual #129                // Method java/lang/reflect/Method.getDeclaringClass:()Ljava/lang/Class;
       5: invokespecial #130                // Method getCtClass:(Ljava/lang/Class;)Ljavassist/CtClass;
       8: aload_1
       9: invokevirtual #62                 // Method java/lang/reflect/Method.getName:()Ljava/lang/String;
      12: aload_1
      13: invokestatic  #64                 // Method org/apache/dubbo/common/utils/ReflectUtils.getDescWithoutMethodName:(Ljava/lang/reflect/Method;)Ljava/lang/String;
      16: invokevirtual #131                // Method javassist/CtClass.getMethod:(Ljava/lang/String;Ljava/lang/String;)Ljavassist/CtMethod;
      19: areturn

  private javassist.CtConstructor getCtConstructor(java.lang.reflect.Constructor<?>) throws javassist.NotFoundException;
    Code:
       0: aload_0
       1: aload_1
       2: invokevirtual #132                // Method java/lang/reflect/Constructor.getDeclaringClass:()Ljava/lang/Class;
       5: invokespecial #130                // Method getCtClass:(Ljava/lang/Class;)Ljavassist/CtClass;
       8: aload_1
       9: invokestatic  #74                 // Method org/apache/dubbo/common/utils/ReflectUtils.getDesc:(Ljava/lang/reflect/Constructor;)Ljava/lang/String;
      12: invokevirtual #133                // Method javassist/CtClass.getConstructor:(Ljava/lang/String;)Ljavassist/CtConstructor;
      15: areturn

  static {};
    Code:
       0: new           #134                // class java/util/concurrent/atomic/AtomicLong
       3: dup
       4: lconst_0
       5: invokespecial #135                // Method java/util/concurrent/atomic/AtomicLong."<init>":(J)V
       8: putstatic     #82                 // Field CLASS_NAME_COUNTER:Ljava/util/concurrent/atomic/AtomicLong;
      11: new           #66                 // class java/util/concurrent/ConcurrentHashMap
      14: dup
      15: invokespecial #136                // Method java/util/concurrent/ConcurrentHashMap."<init>":()V
      18: putstatic     #13                 // Field POOL_MAP:Ljava/util/Map;
      21: return
}
