Compiled from "DubboLoaderClassPath.java"
public class org.apache.dubbo.common.bytecode.DubboLoaderClassPath extends javassist.LoaderClassPath {
  public org.apache.dubbo.common.bytecode.DubboLoaderClassPath();
    Code:
       0: aload_0
       1: ldc           #1                  // class org/apache/dubbo/common/bytecode/DubboLoaderClassPath
       3: invokevirtual #2                  // Method java/lang/Class.getClassLoader:()Ljava/lang/ClassLoader;
       6: invokespecial #3                  // Method javassist/LoaderClassPath."<init>":(Ljava/lang/ClassLoader;)V
       9: return

  public java.io.InputStream openClassfile(java.lang.String) throws javassist.NotFoundException;
    Code:
       0: aload_1
       1: ldc           #4                  // String org.apache.dubbo
       3: invokevirtual #5                  // Method java/lang/String.startsWith:(Ljava/lang/String;)Z
       6: ifne          29
       9: aload_1
      10: ldc           #6                  // String grpc.health
      12: invokevirtual #5                  // Method java/lang/String.startsWith:(Ljava/lang/String;)Z
      15: ifne          29
      18: aload_1
      19: ldc           #7                  // String com.google
      21: invokevirtual #5                  // Method java/lang/String.startsWith:(Ljava/lang/String;)Z
      24: ifne          29
      27: aconst_null
      28: areturn
      29: aload_0
      30: aload_1
      31: invokespecial #8                  // Method javassist/LoaderClassPath.openClassfile:(Ljava/lang/String;)Ljava/io/InputStream;
      34: areturn

  public java.net.URL find(java.lang.String);
    Code:
       0: aload_1
       1: ldc           #4                  // String org.apache.dubbo
       3: invokevirtual #5                  // Method java/lang/String.startsWith:(Ljava/lang/String;)Z
       6: ifne          11
       9: aconst_null
      10: areturn
      11: aload_0
      12: aload_1
      13: invokespecial #9                  // Method javassist/LoaderClassPath.find:(Ljava/lang/String;)Ljava/net/URL;
      16: areturn
}
