Compiled from "Mixin.java"
public abstract class org.apache.dubbo.common.bytecode.Mixin {
  private static final java.lang.String PACKAGE_NAME;

  private static final java.util.concurrent.atomic.AtomicLong MIXIN_CLASS_COUNTER;

  protected org.apache.dubbo.common.bytecode.Mixin();
    Code:
       0: aload_0
       1: invokespecial #1                  // Method java/lang/Object."<init>":()V
       4: return

  public static org.apache.dubbo.common.bytecode.Mixin mixin(java.lang.Class<?>[], java.lang.Class<?>);
    Code:
       0: aload_0
       1: iconst_1
       2: anewarray     #2                  // class java/lang/Class
       5: dup
       6: iconst_0
       7: aload_1
       8: aastore
       9: invokestatic  #3                  // Method mixin:([Ljava/lang/Class;[Ljava/lang/Class;)Lorg/apache/dubbo/common/bytecode/Mixin;
      12: areturn

  public static org.apache.dubbo.common.bytecode.Mixin mixin(java.lang.Class<?>[], java.lang.Class<?>, java.lang.ClassLoader);
    Code:
       0: aload_0
       1: iconst_1
       2: anewarray     #2                  // class java/lang/Class
       5: dup
       6: iconst_0
       7: aload_1
       8: aastore
       9: aload_2
      10: invokestatic  #4                  // Method mixin:([Ljava/lang/Class;[Ljava/lang/Class;Ljava/lang/ClassLoader;)Lorg/apache/dubbo/common/bytecode/Mixin;
      13: areturn

  public static org.apache.dubbo.common.bytecode.Mixin mixin(java.lang.Class<?>[], java.lang.Class<?>[]);
    Code:
       0: aload_0
       1: aload_1
       2: ldc           #5                  // class org/apache/dubbo/common/bytecode/Mixin
       4: invokestatic  #6                  // Method org/apache/dubbo/common/utils/ClassUtils.getCallerClassLoader:(Ljava/lang/Class;)Ljava/lang/ClassLoader;
       7: invokestatic  #4                  // Method mixin:([Ljava/lang/Class;[Ljava/lang/Class;Ljava/lang/ClassLoader;)Lorg/apache/dubbo/common/bytecode/Mixin;
      10: areturn

  public static org.apache.dubbo.common.bytecode.Mixin mixin(java.lang.Class<?>[], java.lang.Class<?>[], java.lang.ClassLoader);
    Code:
       0: aload_0
       1: invokestatic  #7                  // Method assertInterfaceArray:([Ljava/lang/Class;)V
       4: getstatic     #8                  // Field MIXIN_CLASS_COUNTER:Ljava/util/concurrent/atomic/AtomicLong;
       7: invokevirtual #9                  // Method java/util/concurrent/atomic/AtomicLong.getAndIncrement:()J
      10: lstore_3
      11: aconst_null
      12: astore        5
      14: aconst_null
      15: astore        6
      17: aconst_null
      18: astore        7
      20: aload_2
      21: invokestatic  #10                 // Method org/apache/dubbo/common/bytecode/ClassGenerator.newInstance:(Ljava/lang/ClassLoader;)Lorg/apache/dubbo/common/bytecode/ClassGenerator;
      24: astore        6
      26: new           #11                 // class java/lang/StringBuilder
      29: dup
      30: invokespecial #12                 // Method java/lang/StringBuilder."<init>":()V
      33: astore        8
      35: iconst_0
      36: istore        9
      38: iload         9
      40: aload_1
      41: arraylength
      42: if_icmpge     227
      45: aload_1
      46: iload         9
      48: aaload
      49: invokevirtual #13                 // Method java/lang/Class.getModifiers:()I
      52: invokestatic  #14                 // Method java/lang/reflect/Modifier.isPublic:(I)Z
      55: ifne          102
      58: aload_1
      59: iload         9
      61: aaload
      62: invokevirtual #15                 // Method java/lang/Class.getPackage:()Ljava/lang/Package;
      65: invokevirtual #16                 // Method java/lang/Package.getName:()Ljava/lang/String;
      68: astore        10
      70: aload         5
      72: ifnonnull     82
      75: aload         10
      77: astore        5
      79: goto          102
      82: aload         5
      84: aload         10
      86: invokevirtual #17                 // Method java/lang/String.equals:(Ljava/lang/Object;)Z
      89: ifne          102
      92: new           #18                 // class java/lang/IllegalArgumentException
      95: dup
      96: ldc           #19                 // String non-public interfaces class from different packages
      98: invokespecial #20                 // Method java/lang/IllegalArgumentException."<init>":(Ljava/lang/String;)V
     101: athrow
     102: aload         6
     104: new           #11                 // class java/lang/StringBuilder
     107: dup
     108: invokespecial #12                 // Method java/lang/StringBuilder."<init>":()V
     111: ldc           #21                 // String private
     113: invokevirtual #22                 // Method java/lang/StringBuilder.append:(Ljava/lang/String;)Ljava/lang/StringBuilder;
     116: aload_1
     117: iload         9
     119: aaload
     120: invokevirtual #23                 // Method java/lang/Class.getName:()Ljava/lang/String;
     123: invokevirtual #22                 // Method java/lang/StringBuilder.append:(Ljava/lang/String;)Ljava/lang/StringBuilder;
     126: ldc           #24                 // String  d
     128: invokevirtual #22                 // Method java/lang/StringBuilder.append:(Ljava/lang/String;)Ljava/lang/StringBuilder;
     131: iload         9
     133: invokevirtual #25                 // Method java/lang/StringBuilder.append:(I)Ljava/lang/StringBuilder;
     136: ldc           #26                 // String ;
     138: invokevirtual #22                 // Method java/lang/StringBuilder.append:(Ljava/lang/String;)Ljava/lang/StringBuilder;
     141: invokevirtual #27                 // Method java/lang/StringBuilder.toString:()Ljava/lang/String;
     144: invokevirtual #28                 // Method org/apache/dubbo/common/bytecode/ClassGenerator.addField:(Ljava/lang/String;)Lorg/apache/dubbo/common/bytecode/ClassGenerator;
     147: pop
     148: aload         8
     150: bipush        100
     152: invokevirtual #29                 // Method java/lang/StringBuilder.append:(C)Ljava/lang/StringBuilder;
     155: iload         9
     157: invokevirtual #25                 // Method java/lang/StringBuilder.append:(I)Ljava/lang/StringBuilder;
     160: ldc           #30                 // String  = (
     162: invokevirtual #22                 // Method java/lang/StringBuilder.append:(Ljava/lang/String;)Ljava/lang/StringBuilder;
     165: aload_1
     166: iload         9
     168: aaload
     169: invokevirtual #23                 // Method java/lang/Class.getName:()Ljava/lang/String;
     172: invokevirtual #22                 // Method java/lang/StringBuilder.append:(Ljava/lang/String;)Ljava/lang/StringBuilder;
     175: ldc           #31                 // String )$1[
     177: invokevirtual #22                 // Method java/lang/StringBuilder.append:(Ljava/lang/String;)Ljava/lang/StringBuilder;
     180: iload         9
     182: invokevirtual #25                 // Method java/lang/StringBuilder.append:(I)Ljava/lang/StringBuilder;
     185: ldc           #32                 // String ];\n
     187: invokevirtual #22                 // Method java/lang/StringBuilder.append:(Ljava/lang/String;)Ljava/lang/StringBuilder;
     190: pop
     191: ldc           #33                 // class org/apache/dubbo/common/bytecode/Mixin$MixinAware
     193: aload_1
     194: iload         9
     196: aaload
     197: invokevirtual #34                 // Method java/lang/Class.isAssignableFrom:(Ljava/lang/Class;)Z
     200: ifeq          221
     203: aload         8
     205: bipush        100
     207: invokevirtual #29                 // Method java/lang/StringBuilder.append:(C)Ljava/lang/StringBuilder;
     210: iload         9
     212: invokevirtual #25                 // Method java/lang/StringBuilder.append:(I)Ljava/lang/StringBuilder;
     215: ldc           #35                 // String .setMixinInstance(this);\n
     217: invokevirtual #22                 // Method java/lang/StringBuilder.append:(Ljava/lang/String;)Ljava/lang/StringBuilder;
     220: pop
     221: iinc          9, 1
     224: goto          38
     227: aload         6
     229: iconst_1
     230: iconst_1
     231: anewarray     #2                  // class java/lang/Class
     234: dup
     235: iconst_0
     236: ldc           #37                 // class "[Ljava/lang/Object;"
     238: aastore
     239: aload         8
     241: invokevirtual #27                 // Method java/lang/StringBuilder.toString:()Ljava/lang/String;
     244: invokevirtual #38                 // Method org/apache/dubbo/common/bytecode/ClassGenerator.addConstructor:(I[Ljava/lang/Class;Ljava/lang/String;)Lorg/apache/dubbo/common/bytecode/ClassGenerator;
     247: pop
     248: aconst_null
     249: astore        9
     251: new           #39                 // class java/util/HashSet
     254: dup
     255: invokespecial #40                 // Method java/util/HashSet."<init>":()V
     258: astore        10
     260: iconst_0
     261: istore        11
     263: iload         11
     265: aload_0
     266: arraylength
     267: if_icmpge     631
     270: aload_0
     271: iload         11
     273: aaload
     274: invokevirtual #13                 // Method java/lang/Class.getModifiers:()I
     277: invokestatic  #14                 // Method java/lang/reflect/Modifier.isPublic:(I)Z
     280: ifne          333
     283: aload_0
     284: iload         11
     286: aaload
     287: invokevirtual #15                 // Method java/lang/Class.getPackage:()Ljava/lang/Package;
     290: invokevirtual #16                 // Method java/lang/Package.getName:()Ljava/lang/String;
     293: astore        12
     295: aload         5
     297: ifnonnull     313
     300: aload         12
     302: astore        5
     304: aload_0
     305: iload         11
     307: aaload
     308: astore        9
     310: goto          333
     313: aload         5
     315: aload         12
     317: invokevirtual #17                 // Method java/lang/String.equals:(Ljava/lang/Object;)Z
     320: ifne          333
     323: new           #18                 // class java/lang/IllegalArgumentException
     326: dup
     327: ldc           #41                 // String non-public delegate class from different packages
     329: invokespecial #20                 // Method java/lang/IllegalArgumentException."<init>":(Ljava/lang/String;)V
     332: athrow
     333: aload         6
     335: aload_0
     336: iload         11
     338: aaload
     339: invokevirtual #42                 // Method org/apache/dubbo/common/bytecode/ClassGenerator.addInterface:(Ljava/lang/Class;)Lorg/apache/dubbo/common/bytecode/ClassGenerator;
     342: pop
     343: aload_0
     344: iload         11
     346: aaload
     347: invokevirtual #43                 // Method java/lang/Class.getMethods:()[Ljava/lang/reflect/Method;
     350: astore        12
     352: aload         12
     354: arraylength
     355: istore        13
     357: iconst_0
     358: istore        14
     360: iload         14
     362: iload         13
     364: if_icmpge     625
     367: aload         12
     369: iload         14
     371: aaload
     372: astore        15
     374: ldc           #44                 // String java.lang.Object
     376: aload         15
     378: invokevirtual #45                 // Method java/lang/reflect/Method.getDeclaringClass:()Ljava/lang/Class;
     381: invokevirtual #23                 // Method java/lang/Class.getName:()Ljava/lang/String;
     384: invokevirtual #17                 // Method java/lang/String.equals:(Ljava/lang/Object;)Z
     387: ifeq          393
     390: goto          619
     393: aload         15
     395: invokestatic  #46                 // Method org/apache/dubbo/common/utils/ReflectUtils.getDesc:(Ljava/lang/reflect/Method;)Ljava/lang/String;
     398: astore        16
     400: aload         10
     402: aload         16
     404: invokeinterface #47,  2           // InterfaceMethod java/util/Set.contains:(Ljava/lang/Object;)Z
     409: ifeq          415
     412: goto          619
     415: aload         10
     417: aload         16
     419: invokeinterface #48,  2           // InterfaceMethod java/util/Set.add:(Ljava/lang/Object;)Z
     424: pop
     425: aload_1
     426: aload         16
     428: invokestatic  #49                 // Method findMethod:([Ljava/lang/Class;Ljava/lang/String;)I
     431: istore        17
     433: iload         17
     435: ifge          471
     438: new           #50                 // class java/lang/RuntimeException
     441: dup
     442: new           #11                 // class java/lang/StringBuilder
     445: dup
     446: invokespecial #12                 // Method java/lang/StringBuilder."<init>":()V
     449: ldc           #51                 // String Missing method [
     451: invokevirtual #22                 // Method java/lang/StringBuilder.append:(Ljava/lang/String;)Ljava/lang/StringBuilder;
     454: aload         16
     456: invokevirtual #22                 // Method java/lang/StringBuilder.append:(Ljava/lang/String;)Ljava/lang/StringBuilder;
     459: ldc           #52                 // String ] implement.
     461: invokevirtual #22                 // Method java/lang/StringBuilder.append:(Ljava/lang/String;)Ljava/lang/StringBuilder;
     464: invokevirtual #27                 // Method java/lang/StringBuilder.toString:()Ljava/lang/String;
     467: invokespecial #53                 // Method java/lang/RuntimeException."<init>":(Ljava/lang/String;)V
     470: athrow
     471: aload         15
     473: invokevirtual #54                 // Method java/lang/reflect/Method.getReturnType:()Ljava/lang/Class;
     476: astore        18
     478: aload         15
     480: invokevirtual #55                 // Method java/lang/reflect/Method.getName:()Ljava/lang/String;
     483: astore        19
     485: getstatic     #56                 // Field java/lang/Void.TYPE:Ljava/lang/Class;
     488: aload         18
     490: invokevirtual #57                 // Method java/lang/Object.equals:(Ljava/lang/Object;)Z
     493: ifeq          559
     496: aload         6
     498: aload         19
     500: aload         15
     502: invokevirtual #58                 // Method java/lang/reflect/Method.getModifiers:()I
     505: aload         18
     507: aload         15
     509: invokevirtual #59                 // Method java/lang/reflect/Method.getParameterTypes:()[Ljava/lang/Class;
     512: aload         15
     514: invokevirtual #60                 // Method java/lang/reflect/Method.getExceptionTypes:()[Ljava/lang/Class;
     517: new           #11                 // class java/lang/StringBuilder
     520: dup
     521: invokespecial #12                 // Method java/lang/StringBuilder."<init>":()V
     524: ldc           #61                 // String d
     526: invokevirtual #22                 // Method java/lang/StringBuilder.append:(Ljava/lang/String;)Ljava/lang/StringBuilder;
     529: iload         17
     531: invokevirtual #25                 // Method java/lang/StringBuilder.append:(I)Ljava/lang/StringBuilder;
     534: ldc           #62                 // String .
     536: invokevirtual #22                 // Method java/lang/StringBuilder.append:(Ljava/lang/String;)Ljava/lang/StringBuilder;
     539: aload         19
     541: invokevirtual #22                 // Method java/lang/StringBuilder.append:(Ljava/lang/String;)Ljava/lang/StringBuilder;
     544: ldc           #63                 // String ($$);
     546: invokevirtual #22                 // Method java/lang/StringBuilder.append:(Ljava/lang/String;)Ljava/lang/StringBuilder;
     549: invokevirtual #27                 // Method java/lang/StringBuilder.toString:()Ljava/lang/String;
     552: invokevirtual #64                 // Method org/apache/dubbo/common/bytecode/ClassGenerator.addMethod:(Ljava/lang/String;ILjava/lang/Class;[Ljava/lang/Class;[Ljava/lang/Class;Ljava/lang/String;)Lorg/apache/dubbo/common/bytecode/ClassGenerator;
     555: pop
     556: goto          619
     559: aload         6
     561: aload         19
     563: aload         15
     565: invokevirtual #58                 // Method java/lang/reflect/Method.getModifiers:()I
     568: aload         18
     570: aload         15
     572: invokevirtual #59                 // Method java/lang/reflect/Method.getParameterTypes:()[Ljava/lang/Class;
     575: aload         15
     577: invokevirtual #60                 // Method java/lang/reflect/Method.getExceptionTypes:()[Ljava/lang/Class;
     580: new           #11                 // class java/lang/StringBuilder
     583: dup
     584: invokespecial #12                 // Method java/lang/StringBuilder."<init>":()V
     587: ldc           #65                 // String return ($r)d
     589: invokevirtual #22                 // Method java/lang/StringBuilder.append:(Ljava/lang/String;)Ljava/lang/StringBuilder;
     592: iload         17
     594: invokevirtual #25                 // Method java/lang/StringBuilder.append:(I)Ljava/lang/StringBuilder;
     597: ldc           #62                 // String .
     599: invokevirtual #22                 // Method java/lang/StringBuilder.append:(Ljava/lang/String;)Ljava/lang/StringBuilder;
     602: aload         19
     604: invokevirtual #22                 // Method java/lang/StringBuilder.append:(Ljava/lang/String;)Ljava/lang/StringBuilder;
     607: ldc           #63                 // String ($$);
     609: invokevirtual #22                 // Method java/lang/StringBuilder.append:(Ljava/lang/String;)Ljava/lang/StringBuilder;
     612: invokevirtual #27                 // Method java/lang/StringBuilder.toString:()Ljava/lang/String;
     615: invokevirtual #64                 // Method org/apache/dubbo/common/bytecode/ClassGenerator.addMethod:(Ljava/lang/String;ILjava/lang/Class;[Ljava/lang/Class;[Ljava/lang/Class;Ljava/lang/String;)Lorg/apache/dubbo/common/bytecode/ClassGenerator;
     618: pop
     619: iinc          14, 1
     622: goto          360
     625: iinc          11, 1
     628: goto          263
     631: aload         5
     633: ifnonnull     645
     636: getstatic     #66                 // Field PACKAGE_NAME:Ljava/lang/String;
     639: astore        5
     641: ldc           #5                  // class org/apache/dubbo/common/bytecode/Mixin
     643: astore        9
     645: new           #11                 // class java/lang/StringBuilder
     648: dup
     649: invokespecial #12                 // Method java/lang/StringBuilder."<init>":()V
     652: aload         5
     654: invokevirtual #22                 // Method java/lang/StringBuilder.append:(Ljava/lang/String;)Ljava/lang/StringBuilder;
     657: ldc           #67                 // String .mixin
     659: invokevirtual #22                 // Method java/lang/StringBuilder.append:(Ljava/lang/String;)Ljava/lang/StringBuilder;
     662: lload_3
     663: invokevirtual #68                 // Method java/lang/StringBuilder.append:(J)Ljava/lang/StringBuilder;
     666: invokevirtual #27                 // Method java/lang/StringBuilder.toString:()Ljava/lang/String;
     669: astore        11
     671: aload         6
     673: aload         11
     675: invokevirtual #69                 // Method org/apache/dubbo/common/bytecode/ClassGenerator.setClassName:(Ljava/lang/String;)Lorg/apache/dubbo/common/bytecode/ClassGenerator;
     678: pop
     679: aload         6
     681: aload         9
     683: invokevirtual #70                 // Method org/apache/dubbo/common/bytecode/ClassGenerator.toClass:(Ljava/lang/Class;)Ljava/lang/Class;
     686: pop
     687: new           #11                 // class java/lang/StringBuilder
     690: dup
     691: invokespecial #12                 // Method java/lang/StringBuilder."<init>":()V
     694: ldc           #5                  // class org/apache/dubbo/common/bytecode/Mixin
     696: invokevirtual #23                 // Method java/lang/Class.getName:()Ljava/lang/String;
     699: invokevirtual #22                 // Method java/lang/StringBuilder.append:(Ljava/lang/String;)Ljava/lang/StringBuilder;
     702: lload_3
     703: invokevirtual #68                 // Method java/lang/StringBuilder.append:(J)Ljava/lang/StringBuilder;
     706: invokevirtual #27                 // Method java/lang/StringBuilder.toString:()Ljava/lang/String;
     709: astore        12
     711: aload_2
     712: invokestatic  #10                 // Method org/apache/dubbo/common/bytecode/ClassGenerator.newInstance:(Ljava/lang/ClassLoader;)Lorg/apache/dubbo/common/bytecode/ClassGenerator;
     715: astore        7
     717: aload         7
     719: aload         12
     721: invokevirtual #69                 // Method org/apache/dubbo/common/bytecode/ClassGenerator.setClassName:(Ljava/lang/String;)Lorg/apache/dubbo/common/bytecode/ClassGenerator;
     724: pop
     725: aload         7
     727: invokevirtual #71                 // Method org/apache/dubbo/common/bytecode/ClassGenerator.addDefaultConstructor:()Lorg/apache/dubbo/common/bytecode/ClassGenerator;
     730: pop
     731: aload         7
     733: ldc           #5                  // class org/apache/dubbo/common/bytecode/Mixin
     735: invokevirtual #23                 // Method java/lang/Class.getName:()Ljava/lang/String;
     738: invokevirtual #72                 // Method org/apache/dubbo/common/bytecode/ClassGenerator.setSuperClass:(Ljava/lang/String;)Lorg/apache/dubbo/common/bytecode/ClassGenerator;
     741: pop
     742: aload         7
     744: new           #11                 // class java/lang/StringBuilder
     747: dup
     748: invokespecial #12                 // Method java/lang/StringBuilder."<init>":()V
     751: ldc           #73                 // String public Object newInstance(Object[] delegates){ return new
     753: invokevirtual #22                 // Method java/lang/StringBuilder.append:(Ljava/lang/String;)Ljava/lang/StringBuilder;
     756: aload         11
     758: invokevirtual #22                 // Method java/lang/StringBuilder.append:(Ljava/lang/String;)Ljava/lang/StringBuilder;
     761: ldc           #74                 // String ($1); }
     763: invokevirtual #22                 // Method java/lang/StringBuilder.append:(Ljava/lang/String;)Ljava/lang/StringBuilder;
     766: invokevirtual #27                 // Method java/lang/StringBuilder.toString:()Ljava/lang/String;
     769: invokevirtual #75                 // Method org/apache/dubbo/common/bytecode/ClassGenerator.addMethod:(Ljava/lang/String;)Lorg/apache/dubbo/common/bytecode/ClassGenerator;
     772: pop
     773: aload         7
     775: ldc           #5                  // class org/apache/dubbo/common/bytecode/Mixin
     777: invokevirtual #70                 // Method org/apache/dubbo/common/bytecode/ClassGenerator.toClass:(Ljava/lang/Class;)Ljava/lang/Class;
     780: astore        13
     782: aload         13
     784: iconst_0
     785: anewarray     #2                  // class java/lang/Class
     788: invokevirtual #76                 // Method java/lang/Class.getDeclaredConstructor:([Ljava/lang/Class;)Ljava/lang/reflect/Constructor;
     791: iconst_0
     792: anewarray     #77                 // class java/lang/Object
     795: invokevirtual #78                 // Method java/lang/reflect/Constructor.newInstance:([Ljava/lang/Object;)Ljava/lang/Object;
     798: checkcast     #5                  // class org/apache/dubbo/common/bytecode/Mixin
     801: astore        14
     803: aload         6
     805: ifnull        813
     808: aload         6
     810: invokevirtual #79                 // Method org/apache/dubbo/common/bytecode/ClassGenerator.release:()V
     813: aload         7
     815: ifnull        823
     818: aload         7
     820: invokevirtual #79                 // Method org/apache/dubbo/common/bytecode/ClassGenerator.release:()V
     823: aload         14
     825: areturn
     826: astore        8
     828: aload         8
     830: athrow
     831: astore        8
     833: new           #50                 // class java/lang/RuntimeException
     836: dup
     837: aload         8
     839: invokevirtual #81                 // Method java/lang/Exception.getMessage:()Ljava/lang/String;
     842: aload         8
     844: invokespecial #82                 // Method java/lang/RuntimeException."<init>":(Ljava/lang/String;Ljava/lang/Throwable;)V
     847: athrow
     848: astore        20
     850: aload         6
     852: ifnull        860
     855: aload         6
     857: invokevirtual #79                 // Method org/apache/dubbo/common/bytecode/ClassGenerator.release:()V
     860: aload         7
     862: ifnull        870
     865: aload         7
     867: invokevirtual #79                 // Method org/apache/dubbo/common/bytecode/ClassGenerator.release:()V
     870: aload         20
     872: athrow
    Exception table:
       from    to  target type
          20   803   826   Class java/lang/RuntimeException
          20   803   831   Class java/lang/Exception
          20   803   848   any
         826   850   848   any

  private static int findMethod(java.lang.Class<?>[], java.lang.String);
    Code:
       0: iconst_0
       1: istore        4
       3: iload         4
       5: aload_0
       6: arraylength
       7: if_icmpge     72
      10: aload_0
      11: iload         4
      13: aaload
      14: astore_2
      15: aload_2
      16: invokevirtual #43                 // Method java/lang/Class.getMethods:()[Ljava/lang/reflect/Method;
      19: astore_3
      20: aload_3
      21: astore        5
      23: aload         5
      25: arraylength
      26: istore        6
      28: iconst_0
      29: istore        7
      31: iload         7
      33: iload         6
      35: if_icmpge     66
      38: aload         5
      40: iload         7
      42: aaload
      43: astore        8
      45: aload_1
      46: aload         8
      48: invokestatic  #46                 // Method org/apache/dubbo/common/utils/ReflectUtils.getDesc:(Ljava/lang/reflect/Method;)Ljava/lang/String;
      51: invokevirtual #17                 // Method java/lang/String.equals:(Ljava/lang/Object;)Z
      54: ifeq          60
      57: iload         4
      59: ireturn
      60: iinc          7, 1
      63: goto          31
      66: iinc          4, 1
      69: goto          3
      72: iconst_m1
      73: ireturn

  private static void assertInterfaceArray(java.lang.Class<?>[]);
    Code:
       0: iconst_0
       1: istore_1
       2: iload_1
       3: aload_0
       4: arraylength
       5: if_icmpge     60
       8: aload_0
       9: iload_1
      10: aaload
      11: invokevirtual #83                 // Method java/lang/Class.isInterface:()Z
      14: ifne          54
      17: new           #50                 // class java/lang/RuntimeException
      20: dup
      21: new           #11                 // class java/lang/StringBuilder
      24: dup
      25: invokespecial #12                 // Method java/lang/StringBuilder."<init>":()V
      28: ldc           #84                 // String Class
      30: invokevirtual #22                 // Method java/lang/StringBuilder.append:(Ljava/lang/String;)Ljava/lang/StringBuilder;
      33: aload_0
      34: iload_1
      35: aaload
      36: invokevirtual #23                 // Method java/lang/Class.getName:()Ljava/lang/String;
      39: invokevirtual #22                 // Method java/lang/StringBuilder.append:(Ljava/lang/String;)Ljava/lang/StringBuilder;
      42: ldc           #85                 // String  is not a interface.
      44: invokevirtual #22                 // Method java/lang/StringBuilder.append:(Ljava/lang/String;)Ljava/lang/StringBuilder;
      47: invokevirtual #27                 // Method java/lang/StringBuilder.toString:()Ljava/lang/String;
      50: invokespecial #53                 // Method java/lang/RuntimeException."<init>":(Ljava/lang/String;)V
      53: athrow
      54: iinc          1, 1
      57: goto          2
      60: return

  public abstract java.lang.Object newInstance(java.lang.Object[]);

  static {};
    Code:
       0: ldc           #5                  // class org/apache/dubbo/common/bytecode/Mixin
       2: invokevirtual #15                 // Method java/lang/Class.getPackage:()Ljava/lang/Package;
       5: invokevirtual #16                 // Method java/lang/Package.getName:()Ljava/lang/String;
       8: putstatic     #66                 // Field PACKAGE_NAME:Ljava/lang/String;
      11: new           #86                 // class java/util/concurrent/atomic/AtomicLong
      14: dup
      15: lconst_0
      16: invokespecial #87                 // Method java/util/concurrent/atomic/AtomicLong."<init>":(J)V
      19: putstatic     #8                  // Field MIXIN_CLASS_COUNTER:Ljava/util/concurrent/atomic/AtomicLong;
      22: return
}
