Compiled from "Proxy.java"
public class org.apache.dubbo.common.bytecode.Proxy {
  public static final java.lang.reflect.InvocationHandler THROW_UNSUPPORTED_INVOKER;

  private static final java.util.concurrent.atomic.AtomicLong PROXY_CLASS_COUNTER;

  private static final java.util.Map<java.lang.ClassLoader, java.util.Map<java.lang.String, org.apache.dubbo.common.bytecode.Proxy>> PROXY_CACHE_MAP;

  private final java.lang.Class<?> classToCreate;

  protected org.apache.dubbo.common.bytecode.Proxy(java.lang.Class<?>);
    Code:
       0: aload_0
       1: invokespecial #2                  // Method java/lang/Object."<init>":()V
       4: aload_0
       5: aload_1
       6: putfield      #3                  // Field classToCreate:Ljava/lang/Class;
       9: return

  public static org.apache.dubbo.common.bytecode.Proxy getProxy(java.lang.Class<?>...);
    Code:
       0: aload_0
       1: arraylength
       2: ldc           #4                  // int 65535
       4: if_icmple     17
       7: new           #5                  // class java/lang/IllegalArgumentException
      10: dup
      11: ldc           #6                  // String interface limit exceeded
      13: invokespecial #7                  // Method java/lang/IllegalArgumentException."<init>":(Ljava/lang/String;)V
      16: athrow
      17: aload_0
      18: iconst_0
      19: aaload
      20: invokevirtual #8                  // Method java/lang/Class.getClassLoader:()Ljava/lang/ClassLoader;
      23: astore_1
      24: aload_0
      25: iconst_0
      26: aaload
      27: invokevirtual #9                  // Method java/lang/Class.getProtectionDomain:()Ljava/security/ProtectionDomain;
      30: astore_2
      31: aload_1
      32: aload_0
      33: invokestatic  #10                 // Method buildInterfacesKey:(Ljava/lang/ClassLoader;[Ljava/lang/Class;)Ljava/lang/String;
      36: astore_3
      37: getstatic     #11                 // Field PROXY_CACHE_MAP:Ljava/util/Map;
      40: dup
      41: astore        5
      43: monitorenter
      44: getstatic     #11                 // Field PROXY_CACHE_MAP:Ljava/util/Map;
      47: aload_1
      48: invokedynamic #12,  0             // InvokeDynamic #0:apply:()Ljava/util/function/Function;
      53: invokeinterface #13,  3           // InterfaceMethod java/util/Map.computeIfAbsent:(Ljava/lang/Object;Ljava/util/function/Function;)Ljava/lang/Object;
      58: checkcast     #14                 // class java/util/Map
      61: astore        4
      63: aload         5
      65: monitorexit
      66: goto          77
      69: astore        6
      71: aload         5
      73: monitorexit
      74: aload         6
      76: athrow
      77: aload         4
      79: aload_3
      80: invokeinterface #15,  2           // InterfaceMethod java/util/Map.get:(Ljava/lang/Object;)Ljava/lang/Object;
      85: checkcast     #16                 // class org/apache/dubbo/common/bytecode/Proxy
      88: astore        5
      90: aload         5
      92: ifnonnull     160
      95: aload_0
      96: iconst_0
      97: aaload
      98: dup
      99: astore        6
     101: monitorenter
     102: aload         4
     104: aload_3
     105: invokeinterface #15,  2           // InterfaceMethod java/util/Map.get:(Ljava/lang/Object;)Ljava/lang/Object;
     110: checkcast     #16                 // class org/apache/dubbo/common/bytecode/Proxy
     113: astore        5
     115: aload         5
     117: ifnonnull     146
     120: new           #16                 // class org/apache/dubbo/common/bytecode/Proxy
     123: dup
     124: aload_1
     125: aload_0
     126: aload_2
     127: invokestatic  #17                 // Method buildProxyClass:(Ljava/lang/ClassLoader;[Ljava/lang/Class;Ljava/security/ProtectionDomain;)Ljava/lang/Class;
     130: invokespecial #18                 // Method "<init>":(Ljava/lang/Class;)V
     133: astore        5
     135: aload         4
     137: aload_3
     138: aload         5
     140: invokeinterface #19,  3           // InterfaceMethod java/util/Map.put:(Ljava/lang/Object;Ljava/lang/Object;)Ljava/lang/Object;
     145: pop
     146: aload         6
     148: monitorexit
     149: goto          160
     152: astore        7
     154: aload         6
     156: monitorexit
     157: aload         7
     159: athrow
     160: aload         5
     162: areturn
    Exception table:
       from    to  target type
          44    66    69   any
          69    74    69   any
         102   149   152   any
         152   157   152   any

  private static java.lang.String buildInterfacesKey(java.lang.ClassLoader, java.lang.Class<?>[]);
    Code:
       0: new           #20                 // class java/lang/StringBuilder
       3: dup
       4: invokespecial #21                 // Method java/lang/StringBuilder."<init>":()V
       7: astore_2
       8: aload_1
       9: astore_3
      10: aload_3
      11: arraylength
      12: istore        4
      14: iconst_0
      15: istore        5
      17: iload         5
      19: iload         4
      21: if_icmpge     143
      24: aload_3
      25: iload         5
      27: aaload
      28: astore        6
      30: aload         6
      32: invokevirtual #22                 // Method java/lang/Class.getName:()Ljava/lang/String;
      35: astore        7
      37: aload         6
      39: invokevirtual #23                 // Method java/lang/Class.isInterface:()Z
      42: ifne          73
      45: new           #24                 // class java/lang/RuntimeException
      48: dup
      49: new           #20                 // class java/lang/StringBuilder
      52: dup
      53: invokespecial #21                 // Method java/lang/StringBuilder."<init>":()V
      56: aload         7
      58: invokevirtual #25                 // Method java/lang/StringBuilder.append:(Ljava/lang/String;)Ljava/lang/StringBuilder;
      61: ldc           #26                 // String  is not a interface.
      63: invokevirtual #25                 // Method java/lang/StringBuilder.append:(Ljava/lang/String;)Ljava/lang/StringBuilder;
      66: invokevirtual #27                 // Method java/lang/StringBuilder.toString:()Ljava/lang/String;
      69: invokespecial #28                 // Method java/lang/RuntimeException."<init>":(Ljava/lang/String;)V
      72: athrow
      73: aconst_null
      74: astore        8
      76: aload         7
      78: iconst_0
      79: aload_0
      80: invokestatic  #29                 // Method java/lang/Class.forName:(Ljava/lang/String;ZLjava/lang/ClassLoader;)Ljava/lang/Class;
      83: astore        8
      85: goto          90
      88: astore        9
      90: aload         8
      92: aload         6
      94: if_acmpeq     125
      97: new           #5                  // class java/lang/IllegalArgumentException
     100: dup
     101: new           #20                 // class java/lang/StringBuilder
     104: dup
     105: invokespecial #21                 // Method java/lang/StringBuilder."<init>":()V
     108: aload         6
     110: invokevirtual #31                 // Method java/lang/StringBuilder.append:(Ljava/lang/Object;)Ljava/lang/StringBuilder;
     113: ldc           #32                 // String  is not visible from class loader
     115: invokevirtual #25                 // Method java/lang/StringBuilder.append:(Ljava/lang/String;)Ljava/lang/StringBuilder;
     118: invokevirtual #27                 // Method java/lang/StringBuilder.toString:()Ljava/lang/String;
     121: invokespecial #7                  // Method java/lang/IllegalArgumentException."<init>":(Ljava/lang/String;)V
     124: athrow
     125: aload_2
     126: aload         7
     128: invokevirtual #25                 // Method java/lang/StringBuilder.append:(Ljava/lang/String;)Ljava/lang/StringBuilder;
     131: bipush        59
     133: invokevirtual #33                 // Method java/lang/StringBuilder.append:(C)Ljava/lang/StringBuilder;
     136: pop
     137: iinc          5, 1
     140: goto          17
     143: aload_2
     144: invokevirtual #27                 // Method java/lang/StringBuilder.toString:()Ljava/lang/String;
     147: areturn
    Exception table:
       from    to  target type
          76    85    88   Class java/lang/ClassNotFoundException

  private static java.lang.Class<?> buildProxyClass(java.lang.ClassLoader, java.lang.Class<?>[], java.security.ProtectionDomain);
    Code:
       0: aconst_null
       1: astore_3
       2: aload_0
       3: invokestatic  #34                 // Method org/apache/dubbo/common/bytecode/ClassGenerator.newInstance:(Ljava/lang/ClassLoader;)Lorg/apache/dubbo/common/bytecode/ClassGenerator;
       6: astore_3
       7: new           #35                 // class java/util/HashSet
      10: dup
      11: invokespecial #36                 // Method java/util/HashSet."<init>":()V
      14: astore        4
      16: new           #37                 // class java/util/ArrayList
      19: dup
      20: invokespecial #38                 // Method java/util/ArrayList."<init>":()V
      23: astore        5
      25: aload_1
      26: iconst_0
      27: aaload
      28: invokevirtual #39                 // Method java/lang/Class.getPackage:()Ljava/lang/Package;
      31: invokevirtual #40                 // Method java/lang/Package.getName:()Ljava/lang/String;
      34: astore        6
      36: aload_1
      37: iconst_0
      38: aaload
      39: astore        7
      41: aload_1
      42: astore        8
      44: aload         8
      46: arraylength
      47: istore        9
      49: iconst_0
      50: istore        10
      52: iload         10
      54: iload         9
      56: if_icmpge     381
      59: aload         8
      61: iload         10
      63: aaload
      64: astore        11
      66: aload         11
      68: invokevirtual #39                 // Method java/lang/Class.getPackage:()Ljava/lang/Package;
      71: invokevirtual #40                 // Method java/lang/Package.getName:()Ljava/lang/String;
      74: astore        12
      76: aload         11
      78: invokevirtual #41                 // Method java/lang/Class.getModifiers:()I
      81: invokestatic  #42                 // Method java/lang/reflect/Modifier.isPublic:(I)Z
      84: ifne          107
      87: aload         6
      89: aload         12
      91: invokevirtual #43                 // Method java/lang/String.equals:(Ljava/lang/Object;)Z
      94: ifne          107
      97: new           #5                  // class java/lang/IllegalArgumentException
     100: dup
     101: ldc           #44                 // String non-public interfaces from different packages
     103: invokespecial #7                  // Method java/lang/IllegalArgumentException."<init>":(Ljava/lang/String;)V
     106: athrow
     107: aload_3
     108: aload         11
     110: invokevirtual #45                 // Method org/apache/dubbo/common/bytecode/ClassGenerator.addInterface:(Ljava/lang/Class;)Lorg/apache/dubbo/common/bytecode/ClassGenerator;
     113: pop
     114: aload         11
     116: invokevirtual #46                 // Method java/lang/Class.getMethods:()[Ljava/lang/reflect/Method;
     119: astore        13
     121: aload         13
     123: arraylength
     124: istore        14
     126: iconst_0
     127: istore        15
     129: iload         15
     131: iload         14
     133: if_icmpge     375
     136: aload         13
     138: iload         15
     140: aaload
     141: astore        16
     143: aload         16
     145: invokestatic  #47                 // Method org/apache/dubbo/common/utils/ReflectUtils.getDesc:(Ljava/lang/reflect/Method;)Ljava/lang/String;
     148: astore        17
     150: aload         4
     152: aload         17
     154: invokeinterface #48,  2           // InterfaceMethod java/util/Set.contains:(Ljava/lang/Object;)Z
     159: ifne          369
     162: aload         16
     164: invokevirtual #49                 // Method java/lang/reflect/Method.getModifiers:()I
     167: invokestatic  #50                 // Method java/lang/reflect/Modifier.isStatic:(I)Z
     170: ifeq          176
     173: goto          369
     176: aload         4
     178: aload         17
     180: invokeinterface #51,  2           // InterfaceMethod java/util/Set.add:(Ljava/lang/Object;)Z
     185: pop
     186: aload         5
     188: invokeinterface #52,  1           // InterfaceMethod java/util/List.size:()I
     193: istore        18
     195: aload         16
     197: invokevirtual #53                 // Method java/lang/reflect/Method.getReturnType:()Ljava/lang/Class;
     200: astore        19
     202: aload         16
     204: invokevirtual #54                 // Method java/lang/reflect/Method.getParameterTypes:()[Ljava/lang/Class;
     207: astore        20
     209: new           #20                 // class java/lang/StringBuilder
     212: dup
     213: ldc           #55                 // String Object[] args = new Object[
     215: invokespecial #56                 // Method java/lang/StringBuilder."<init>":(Ljava/lang/String;)V
     218: aload         20
     220: arraylength
     221: invokevirtual #57                 // Method java/lang/StringBuilder.append:(I)Ljava/lang/StringBuilder;
     224: ldc           #58                 // String ];
     226: invokevirtual #25                 // Method java/lang/StringBuilder.append:(Ljava/lang/String;)Ljava/lang/StringBuilder;
     229: astore        21
     231: iconst_0
     232: istore        22
     234: iload         22
     236: aload         20
     238: arraylength
     239: if_icmpge     278
     242: aload         21
     244: ldc           #59                 // String  args[
     246: invokevirtual #25                 // Method java/lang/StringBuilder.append:(Ljava/lang/String;)Ljava/lang/StringBuilder;
     249: iload         22
     251: invokevirtual #57                 // Method java/lang/StringBuilder.append:(I)Ljava/lang/StringBuilder;
     254: ldc           #60                 // String ] = ($w)$
     256: invokevirtual #25                 // Method java/lang/StringBuilder.append:(Ljava/lang/String;)Ljava/lang/StringBuilder;
     259: iload         22
     261: iconst_1
     262: iadd
     263: invokevirtual #57                 // Method java/lang/StringBuilder.append:(I)Ljava/lang/StringBuilder;
     266: bipush        59
     268: invokevirtual #33                 // Method java/lang/StringBuilder.append:(C)Ljava/lang/StringBuilder;
     271: pop
     272: iinc          22, 1
     275: goto          234
     278: aload         21
     280: ldc           #61                 // String  Object ret = handler.invoke(this, methods[
     282: invokevirtual #25                 // Method java/lang/StringBuilder.append:(Ljava/lang/String;)Ljava/lang/StringBuilder;
     285: iload         18
     287: invokevirtual #57                 // Method java/lang/StringBuilder.append:(I)Ljava/lang/StringBuilder;
     290: ldc           #62                 // String ], args);
     292: invokevirtual #25                 // Method java/lang/StringBuilder.append:(Ljava/lang/String;)Ljava/lang/StringBuilder;
     295: pop
     296: getstatic     #63                 // Field java/lang/Void.TYPE:Ljava/lang/Class;
     299: aload         19
     301: invokevirtual #64                 // Method java/lang/Object.equals:(Ljava/lang/Object;)Z
     304: ifne          330
     307: aload         21
     309: ldc           #65                 // String  return
     311: invokevirtual #25                 // Method java/lang/StringBuilder.append:(Ljava/lang/String;)Ljava/lang/StringBuilder;
     314: aload         19
     316: ldc           #66                 // String ret
     318: invokestatic  #67                 // Method asArgument:(Ljava/lang/Class;Ljava/lang/String;)Ljava/lang/String;
     321: invokevirtual #25                 // Method java/lang/StringBuilder.append:(Ljava/lang/String;)Ljava/lang/StringBuilder;
     324: bipush        59
     326: invokevirtual #33                 // Method java/lang/StringBuilder.append:(C)Ljava/lang/StringBuilder;
     329: pop
     330: aload         5
     332: aload         16
     334: invokeinterface #68,  2           // InterfaceMethod java/util/List.add:(Ljava/lang/Object;)Z
     339: pop
     340: aload_3
     341: aload         16
     343: invokevirtual #69                 // Method java/lang/reflect/Method.getName:()Ljava/lang/String;
     346: aload         16
     348: invokevirtual #49                 // Method java/lang/reflect/Method.getModifiers:()I
     351: aload         19
     353: aload         20
     355: aload         16
     357: invokevirtual #70                 // Method java/lang/reflect/Method.getExceptionTypes:()[Ljava/lang/Class;
     360: aload         21
     362: invokevirtual #27                 // Method java/lang/StringBuilder.toString:()Ljava/lang/String;
     365: invokevirtual #71                 // Method org/apache/dubbo/common/bytecode/ClassGenerator.addMethod:(Ljava/lang/String;ILjava/lang/Class;[Ljava/lang/Class;[Ljava/lang/Class;Ljava/lang/String;)Lorg/apache/dubbo/common/bytecode/ClassGenerator;
     368: pop
     369: iinc          15, 1
     372: goto          129
     375: iinc          10, 1
     378: goto          52
     381: new           #20                 // class java/lang/StringBuilder
     384: dup
     385: invokespecial #21                 // Method java/lang/StringBuilder."<init>":()V
     388: aload         7
     390: invokevirtual #22                 // Method java/lang/Class.getName:()Ljava/lang/String;
     393: invokevirtual #25                 // Method java/lang/StringBuilder.append:(Ljava/lang/String;)Ljava/lang/StringBuilder;
     396: ldc           #72                 // String DubboProxy
     398: invokevirtual #25                 // Method java/lang/StringBuilder.append:(Ljava/lang/String;)Ljava/lang/StringBuilder;
     401: getstatic     #73                 // Field PROXY_CLASS_COUNTER:Ljava/util/concurrent/atomic/AtomicLong;
     404: invokevirtual #74                 // Method java/util/concurrent/atomic/AtomicLong.getAndIncrement:()J
     407: invokevirtual #75                 // Method java/lang/StringBuilder.append:(J)Ljava/lang/StringBuilder;
     410: invokevirtual #27                 // Method java/lang/StringBuilder.toString:()Ljava/lang/String;
     413: astore        8
     415: aload_3
     416: aload         8
     418: invokevirtual #76                 // Method org/apache/dubbo/common/bytecode/ClassGenerator.setClassName:(Ljava/lang/String;)Lorg/apache/dubbo/common/bytecode/ClassGenerator;
     421: pop
     422: aload_3
     423: ldc           #77                 // String public static java.lang.reflect.Method[] methods;
     425: invokevirtual #78                 // Method org/apache/dubbo/common/bytecode/ClassGenerator.addField:(Ljava/lang/String;)Lorg/apache/dubbo/common/bytecode/ClassGenerator;
     428: pop
     429: aload_3
     430: new           #20                 // class java/lang/StringBuilder
     433: dup
     434: invokespecial #21                 // Method java/lang/StringBuilder."<init>":()V
     437: ldc           #79                 // String private
     439: invokevirtual #25                 // Method java/lang/StringBuilder.append:(Ljava/lang/String;)Ljava/lang/StringBuilder;
     442: ldc           #80                 // class java/lang/reflect/InvocationHandler
     444: invokevirtual #22                 // Method java/lang/Class.getName:()Ljava/lang/String;
     447: invokevirtual #25                 // Method java/lang/StringBuilder.append:(Ljava/lang/String;)Ljava/lang/StringBuilder;
     450: ldc           #81                 // String  handler;
     452: invokevirtual #25                 // Method java/lang/StringBuilder.append:(Ljava/lang/String;)Ljava/lang/StringBuilder;
     455: invokevirtual #27                 // Method java/lang/StringBuilder.toString:()Ljava/lang/String;
     458: invokevirtual #78                 // Method org/apache/dubbo/common/bytecode/ClassGenerator.addField:(Ljava/lang/String;)Lorg/apache/dubbo/common/bytecode/ClassGenerator;
     461: pop
     462: aload_3
     463: iconst_1
     464: iconst_1
     465: anewarray     #83                 // class java/lang/Class
     468: dup
     469: iconst_0
     470: ldc           #80                 // class java/lang/reflect/InvocationHandler
     472: aastore
     473: iconst_0
     474: anewarray     #83                 // class java/lang/Class
     477: ldc           #84                 // String handler=$1;
     479: invokevirtual #85                 // Method org/apache/dubbo/common/bytecode/ClassGenerator.addConstructor:(I[Ljava/lang/Class;[Ljava/lang/Class;Ljava/lang/String;)Lorg/apache/dubbo/common/bytecode/ClassGenerator;
     482: pop
     483: aload_3
     484: invokevirtual #86                 // Method org/apache/dubbo/common/bytecode/ClassGenerator.addDefaultConstructor:()Lorg/apache/dubbo/common/bytecode/ClassGenerator;
     487: pop
     488: aload_3
     489: aload         7
     491: aload_0
     492: aload_2
     493: invokevirtual #87                 // Method org/apache/dubbo/common/bytecode/ClassGenerator.toClass:(Ljava/lang/Class;Ljava/lang/ClassLoader;Ljava/security/ProtectionDomain;)Ljava/lang/Class;
     496: astore        9
     498: aload         9
     500: ldc           #88                 // String methods
     502: invokevirtual #89                 // Method java/lang/Class.getField:(Ljava/lang/String;)Ljava/lang/reflect/Field;
     505: aconst_null
     506: aload         5
     508: iconst_0
     509: anewarray     #90                 // class java/lang/reflect/Method
     512: invokeinterface #91,  2           // InterfaceMethod java/util/List.toArray:([Ljava/lang/Object;)[Ljava/lang/Object;
     517: invokevirtual #92                 // Method java/lang/reflect/Field.set:(Ljava/lang/Object;Ljava/lang/Object;)V
     520: aload         9
     522: astore        10
     524: aload_3
     525: ifnull        532
     528: aload_3
     529: invokevirtual #93                 // Method org/apache/dubbo/common/bytecode/ClassGenerator.release:()V
     532: aload         10
     534: areturn
     535: astore        4
     537: aload         4
     539: athrow
     540: astore        4
     542: new           #24                 // class java/lang/RuntimeException
     545: dup
     546: aload         4
     548: invokevirtual #95                 // Method java/lang/Exception.getMessage:()Ljava/lang/String;
     551: aload         4
     553: invokespecial #96                 // Method java/lang/RuntimeException."<init>":(Ljava/lang/String;Ljava/lang/Throwable;)V
     556: athrow
     557: astore        23
     559: aload_3
     560: ifnull        567
     563: aload_3
     564: invokevirtual #93                 // Method org/apache/dubbo/common/bytecode/ClassGenerator.release:()V
     567: aload         23
     569: athrow
    Exception table:
       from    to  target type
           2   524   535   Class java/lang/RuntimeException
           2   524   540   Class java/lang/Exception
           2   524   557   any
         535   559   557   any

  private static java.lang.String asArgument(java.lang.Class<?>, java.lang.String);
    Code:
       0: aload_0
       1: invokevirtual #97                 // Method java/lang/Class.isPrimitive:()Z
       4: ifeq          322
       7: getstatic     #98                 // Field java/lang/Boolean.TYPE:Ljava/lang/Class;
      10: aload_0
      11: if_acmpne     43
      14: new           #20                 // class java/lang/StringBuilder
      17: dup
      18: invokespecial #21                 // Method java/lang/StringBuilder."<init>":()V
      21: aload_1
      22: invokevirtual #25                 // Method java/lang/StringBuilder.append:(Ljava/lang/String;)Ljava/lang/StringBuilder;
      25: ldc           #99                 // String ==null?false:((Boolean)
      27: invokevirtual #25                 // Method java/lang/StringBuilder.append:(Ljava/lang/String;)Ljava/lang/StringBuilder;
      30: aload_1
      31: invokevirtual #25                 // Method java/lang/StringBuilder.append:(Ljava/lang/String;)Ljava/lang/StringBuilder;
      34: ldc           #100                // String ).booleanValue()
      36: invokevirtual #25                 // Method java/lang/StringBuilder.append:(Ljava/lang/String;)Ljava/lang/StringBuilder;
      39: invokevirtual #27                 // Method java/lang/StringBuilder.toString:()Ljava/lang/String;
      42: areturn
      43: getstatic     #101                // Field java/lang/Byte.TYPE:Ljava/lang/Class;
      46: aload_0
      47: if_acmpne     79
      50: new           #20                 // class java/lang/StringBuilder
      53: dup
      54: invokespecial #21                 // Method java/lang/StringBuilder."<init>":()V
      57: aload_1
      58: invokevirtual #25                 // Method java/lang/StringBuilder.append:(Ljava/lang/String;)Ljava/lang/StringBuilder;
      61: ldc           #102                // String ==null?(byte)0:((Byte)
      63: invokevirtual #25                 // Method java/lang/StringBuilder.append:(Ljava/lang/String;)Ljava/lang/StringBuilder;
      66: aload_1
      67: invokevirtual #25                 // Method java/lang/StringBuilder.append:(Ljava/lang/String;)Ljava/lang/StringBuilder;
      70: ldc           #103                // String ).byteValue()
      72: invokevirtual #25                 // Method java/lang/StringBuilder.append:(Ljava/lang/String;)Ljava/lang/StringBuilder;
      75: invokevirtual #27                 // Method java/lang/StringBuilder.toString:()Ljava/lang/String;
      78: areturn
      79: getstatic     #104                // Field java/lang/Character.TYPE:Ljava/lang/Class;
      82: aload_0
      83: if_acmpne     115
      86: new           #20                 // class java/lang/StringBuilder
      89: dup
      90: invokespecial #21                 // Method java/lang/StringBuilder."<init>":()V
      93: aload_1
      94: invokevirtual #25                 // Method java/lang/StringBuilder.append:(Ljava/lang/String;)Ljava/lang/StringBuilder;
      97: ldc           #105                // String ==null?(char)0:((Character)
      99: invokevirtual #25                 // Method java/lang/StringBuilder.append:(Ljava/lang/String;)Ljava/lang/StringBuilder;
     102: aload_1
     103: invokevirtual #25                 // Method java/lang/StringBuilder.append:(Ljava/lang/String;)Ljava/lang/StringBuilder;
     106: ldc           #106                // String ).charValue()
     108: invokevirtual #25                 // Method java/lang/StringBuilder.append:(Ljava/lang/String;)Ljava/lang/StringBuilder;
     111: invokevirtual #27                 // Method java/lang/StringBuilder.toString:()Ljava/lang/String;
     114: areturn
     115: getstatic     #107                // Field java/lang/Double.TYPE:Ljava/lang/Class;
     118: aload_0
     119: if_acmpne     151
     122: new           #20                 // class java/lang/StringBuilder
     125: dup
     126: invokespecial #21                 // Method java/lang/StringBuilder."<init>":()V
     129: aload_1
     130: invokevirtual #25                 // Method java/lang/StringBuilder.append:(Ljava/lang/String;)Ljava/lang/StringBuilder;
     133: ldc           #108                // String ==null?(double)0:((Double)
     135: invokevirtual #25                 // Method java/lang/StringBuilder.append:(Ljava/lang/String;)Ljava/lang/StringBuilder;
     138: aload_1
     139: invokevirtual #25                 // Method java/lang/StringBuilder.append:(Ljava/lang/String;)Ljava/lang/StringBuilder;
     142: ldc           #109                // String ).doubleValue()
     144: invokevirtual #25                 // Method java/lang/StringBuilder.append:(Ljava/lang/String;)Ljava/lang/StringBuilder;
     147: invokevirtual #27                 // Method java/lang/StringBuilder.toString:()Ljava/lang/String;
     150: areturn
     151: getstatic     #110                // Field java/lang/Float.TYPE:Ljava/lang/Class;
     154: aload_0
     155: if_acmpne     187
     158: new           #20                 // class java/lang/StringBuilder
     161: dup
     162: invokespecial #21                 // Method java/lang/StringBuilder."<init>":()V
     165: aload_1
     166: invokevirtual #25                 // Method java/lang/StringBuilder.append:(Ljava/lang/String;)Ljava/lang/StringBuilder;
     169: ldc           #111                // String ==null?(float)0:((Float)
     171: invokevirtual #25                 // Method java/lang/StringBuilder.append:(Ljava/lang/String;)Ljava/lang/StringBuilder;
     174: aload_1
     175: invokevirtual #25                 // Method java/lang/StringBuilder.append:(Ljava/lang/String;)Ljava/lang/StringBuilder;
     178: ldc           #112                // String ).floatValue()
     180: invokevirtual #25                 // Method java/lang/StringBuilder.append:(Ljava/lang/String;)Ljava/lang/StringBuilder;
     183: invokevirtual #27                 // Method java/lang/StringBuilder.toString:()Ljava/lang/String;
     186: areturn
     187: getstatic     #113                // Field java/lang/Integer.TYPE:Ljava/lang/Class;
     190: aload_0
     191: if_acmpne     223
     194: new           #20                 // class java/lang/StringBuilder
     197: dup
     198: invokespecial #21                 // Method java/lang/StringBuilder."<init>":()V
     201: aload_1
     202: invokevirtual #25                 // Method java/lang/StringBuilder.append:(Ljava/lang/String;)Ljava/lang/StringBuilder;
     205: ldc           #114                // String ==null?(int)0:((Integer)
     207: invokevirtual #25                 // Method java/lang/StringBuilder.append:(Ljava/lang/String;)Ljava/lang/StringBuilder;
     210: aload_1
     211: invokevirtual #25                 // Method java/lang/StringBuilder.append:(Ljava/lang/String;)Ljava/lang/StringBuilder;
     214: ldc           #115                // String ).intValue()
     216: invokevirtual #25                 // Method java/lang/StringBuilder.append:(Ljava/lang/String;)Ljava/lang/StringBuilder;
     219: invokevirtual #27                 // Method java/lang/StringBuilder.toString:()Ljava/lang/String;
     222: areturn
     223: getstatic     #116                // Field java/lang/Long.TYPE:Ljava/lang/Class;
     226: aload_0
     227: if_acmpne     259
     230: new           #20                 // class java/lang/StringBuilder
     233: dup
     234: invokespecial #21                 // Method java/lang/StringBuilder."<init>":()V
     237: aload_1
     238: invokevirtual #25                 // Method java/lang/StringBuilder.append:(Ljava/lang/String;)Ljava/lang/StringBuilder;
     241: ldc           #117                // String ==null?(long)0:((Long)
     243: invokevirtual #25                 // Method java/lang/StringBuilder.append:(Ljava/lang/String;)Ljava/lang/StringBuilder;
     246: aload_1
     247: invokevirtual #25                 // Method java/lang/StringBuilder.append:(Ljava/lang/String;)Ljava/lang/StringBuilder;
     250: ldc           #118                // String ).longValue()
     252: invokevirtual #25                 // Method java/lang/StringBuilder.append:(Ljava/lang/String;)Ljava/lang/StringBuilder;
     255: invokevirtual #27                 // Method java/lang/StringBuilder.toString:()Ljava/lang/String;
     258: areturn
     259: getstatic     #119                // Field java/lang/Short.TYPE:Ljava/lang/Class;
     262: aload_0
     263: if_acmpne     295
     266: new           #20                 // class java/lang/StringBuilder
     269: dup
     270: invokespecial #21                 // Method java/lang/StringBuilder."<init>":()V
     273: aload_1
     274: invokevirtual #25                 // Method java/lang/StringBuilder.append:(Ljava/lang/String;)Ljava/lang/StringBuilder;
     277: ldc           #120                // String ==null?(short)0:((Short)
     279: invokevirtual #25                 // Method java/lang/StringBuilder.append:(Ljava/lang/String;)Ljava/lang/StringBuilder;
     282: aload_1
     283: invokevirtual #25                 // Method java/lang/StringBuilder.append:(Ljava/lang/String;)Ljava/lang/StringBuilder;
     286: ldc           #121                // String ).shortValue()
     288: invokevirtual #25                 // Method java/lang/StringBuilder.append:(Ljava/lang/String;)Ljava/lang/StringBuilder;
     291: invokevirtual #27                 // Method java/lang/StringBuilder.toString:()Ljava/lang/String;
     294: areturn
     295: new           #24                 // class java/lang/RuntimeException
     298: dup
     299: new           #20                 // class java/lang/StringBuilder
     302: dup
     303: invokespecial #21                 // Method java/lang/StringBuilder."<init>":()V
     306: aload_1
     307: invokevirtual #25                 // Method java/lang/StringBuilder.append:(Ljava/lang/String;)Ljava/lang/StringBuilder;
     310: ldc           #122                // String  is unknown primitive type.
     312: invokevirtual #25                 // Method java/lang/StringBuilder.append:(Ljava/lang/String;)Ljava/lang/StringBuilder;
     315: invokevirtual #27                 // Method java/lang/StringBuilder.toString:()Ljava/lang/String;
     318: invokespecial #28                 // Method java/lang/RuntimeException."<init>":(Ljava/lang/String;)V
     321: athrow
     322: new           #20                 // class java/lang/StringBuilder
     325: dup
     326: invokespecial #21                 // Method java/lang/StringBuilder."<init>":()V
     329: ldc           #123                // String (
     331: invokevirtual #25                 // Method java/lang/StringBuilder.append:(Ljava/lang/String;)Ljava/lang/StringBuilder;
     334: aload_0
     335: invokestatic  #124                // Method org/apache/dubbo/common/utils/ReflectUtils.getName:(Ljava/lang/Class;)Ljava/lang/String;
     338: invokevirtual #25                 // Method java/lang/StringBuilder.append:(Ljava/lang/String;)Ljava/lang/StringBuilder;
     341: ldc           #125                // String )
     343: invokevirtual #25                 // Method java/lang/StringBuilder.append:(Ljava/lang/String;)Ljava/lang/StringBuilder;
     346: aload_1
     347: invokevirtual #25                 // Method java/lang/StringBuilder.append:(Ljava/lang/String;)Ljava/lang/StringBuilder;
     350: invokevirtual #27                 // Method java/lang/StringBuilder.toString:()Ljava/lang/String;
     353: areturn

  public java.lang.Object newInstance();
    Code:
       0: aload_0
       1: getstatic     #126                // Field THROW_UNSUPPORTED_INVOKER:Ljava/lang/reflect/InvocationHandler;
       4: invokevirtual #127                // Method newInstance:(Ljava/lang/reflect/InvocationHandler;)Ljava/lang/Object;
       7: areturn

  public java.lang.Object newInstance(java.lang.reflect.InvocationHandler);
    Code:
       0: aload_0
       1: getfield      #3                  // Field classToCreate:Ljava/lang/Class;
       4: iconst_1
       5: anewarray     #83                 // class java/lang/Class
       8: dup
       9: iconst_0
      10: ldc           #80                 // class java/lang/reflect/InvocationHandler
      12: aastore
      13: invokevirtual #128                // Method java/lang/Class.getDeclaredConstructor:([Ljava/lang/Class;)Ljava/lang/reflect/Constructor;
      16: astore_2
      17: aload_2
      18: iconst_1
      19: anewarray     #129                // class java/lang/Object
      22: dup
      23: iconst_0
      24: aload_1
      25: aastore
      26: invokevirtual #130                // Method java/lang/reflect/Constructor.newInstance:([Ljava/lang/Object;)Ljava/lang/Object;
      29: areturn
      30: astore_3
      31: new           #24                 // class java/lang/RuntimeException
      34: dup
      35: aload_3
      36: invokespecial #132                // Method java/lang/RuntimeException."<init>":(Ljava/lang/Throwable;)V
      39: athrow
    Exception table:
       from    to  target type
           0    29    30   Class java/lang/ReflectiveOperationException

  public java.lang.Class<?> getClassToCreate();
    Code:
       0: aload_0
       1: getfield      #3                  // Field classToCreate:Ljava/lang/Class;
       4: areturn

  private static java.util.Map lambda$getProxy$0(java.lang.ClassLoader);
    Code:
       0: new           #133                // class java/util/concurrent/ConcurrentHashMap
       3: dup
       4: invokespecial #134                // Method java/util/concurrent/ConcurrentHashMap."<init>":()V
       7: areturn

  static {};
    Code:
       0: new           #135                // class org/apache/dubbo/common/bytecode/Proxy$1
       3: dup
       4: invokespecial #136                // Method org/apache/dubbo/common/bytecode/Proxy$1."<init>":()V
       7: putstatic     #126                // Field THROW_UNSUPPORTED_INVOKER:Ljava/lang/reflect/InvocationHandler;
      10: new           #137                // class java/util/concurrent/atomic/AtomicLong
      13: dup
      14: lconst_0
      15: invokespecial #138                // Method java/util/concurrent/atomic/AtomicLong."<init>":(J)V
      18: putstatic     #73                 // Field PROXY_CLASS_COUNTER:Ljava/util/concurrent/atomic/AtomicLong;
      21: new           #139                // class java/util/WeakHashMap
      24: dup
      25: invokespecial #140                // Method java/util/WeakHashMap."<init>":()V
      28: putstatic     #11                 // Field PROXY_CACHE_MAP:Ljava/util/Map;
      31: return
}
