Compiled from "Proxy.java"
final class org.apache.dubbo.common.bytecode.Proxy$1 implements java.lang.reflect.InvocationHandler {
  org.apache.dubbo.common.bytecode.Proxy$1();
    Code:
       0: aload_0
       1: invokespecial #1                  // Method java/lang/Object."<init>":()V
       4: return

  public java.lang.Object invoke(java.lang.Object, java.lang.reflect.Method, java.lang.Object[]);
    Code:
       0: new           #2                  // class java/lang/UnsupportedOperationException
       3: dup
       4: new           #3                  // class java/lang/StringBuilder
       7: dup
       8: invokespecial #4                  // Method java/lang/StringBuilder."<init>":()V
      11: ldc           #5                  // String Method [
      13: invokevirtual #6                  // Method java/lang/StringBuilder.append:(Ljava/lang/String;)Ljava/lang/StringBuilder;
      16: aload_2
      17: invokestatic  #7                  // Method org/apache/dubbo/common/utils/ReflectUtils.getName:(Ljava/lang/reflect/Method;)Ljava/lang/String;
      20: invokevirtual #6                  // Method java/lang/StringBuilder.append:(Ljava/lang/String;)Ljava/lang/StringBuilder;
      23: ldc           #8                  // String ] unimplemented.
      25: invokevirtual #6                  // Method java/lang/StringBuilder.append:(Ljava/lang/String;)Ljava/lang/StringBuilder;
      28: invokevirtual #9                  // Method java/lang/StringBuilder.toString:()Ljava/lang/String;
      31: invokespecial #10                 // Method java/lang/UnsupportedOperationException."<init>":(Ljava/lang/String;)V
      34: athrow
}
