Compiled from "Wrapper.java"
final class org.apache.dubbo.common.bytecode.Wrapper$1 extends org.apache.dubbo.common.bytecode.Wrapper {
  org.apache.dubbo.common.bytecode.Wrapper$1();
    Code:
       0: aload_0
       1: invokespecial #1                  // Method org/apache/dubbo/common/bytecode/Wrapper."<init>":()V
       4: return

  public java.lang.String[] getMethodNames();
    Code:
       0: invokestatic  #2                  // Method org/apache/dubbo/common/bytecode/Wrapper.access$000:()[Ljava/lang/String;
       3: areturn

  public java.lang.String[] getDeclaredMethodNames();
    Code:
       0: invokestatic  #2                  // Method org/apache/dubbo/common/bytecode/Wrapper.access$000:()[Ljava/lang/String;
       3: areturn

  public java.lang.String[] getPropertyNames();
    Code:
       0: invokestatic  #3                  // Method org/apache/dubbo/common/bytecode/Wrapper.access$100:()[Ljava/lang/String;
       3: areturn

  public java.lang.Class<?> getPropertyType(java.lang.String);
    Code:
       0: aconst_null
       1: areturn

  public java.lang.Object getPropertyValue(java.lang.Object, java.lang.String) throws org.apache.dubbo.common.bytecode.NoSuchPropertyException;
    Code:
       0: new           #4                  // class org/apache/dubbo/common/bytecode/NoSuchPropertyException
       3: dup
       4: new           #5                  // class java/lang/StringBuilder
       7: dup
       8: invokespecial #6                  // Method java/lang/StringBuilder."<init>":()V
      11: ldc           #7                  // String Property [
      13: invokevirtual #8                  // Method java/lang/StringBuilder.append:(Ljava/lang/String;)Ljava/lang/StringBuilder;
      16: aload_2
      17: invokevirtual #8                  // Method java/lang/StringBuilder.append:(Ljava/lang/String;)Ljava/lang/StringBuilder;
      20: ldc           #9                  // String ] not found.
      22: invokevirtual #8                  // Method java/lang/StringBuilder.append:(Ljava/lang/String;)Ljava/lang/StringBuilder;
      25: invokevirtual #10                 // Method java/lang/StringBuilder.toString:()Ljava/lang/String;
      28: invokespecial #11                 // Method org/apache/dubbo/common/bytecode/NoSuchPropertyException."<init>":(Ljava/lang/String;)V
      31: athrow

  public void setPropertyValue(java.lang.Object, java.lang.String, java.lang.Object) throws org.apache.dubbo.common.bytecode.NoSuchPropertyException;
    Code:
       0: new           #4                  // class org/apache/dubbo/common/bytecode/NoSuchPropertyException
       3: dup
       4: new           #5                  // class java/lang/StringBuilder
       7: dup
       8: invokespecial #6                  // Method java/lang/StringBuilder."<init>":()V
      11: ldc           #7                  // String Property [
      13: invokevirtual #8                  // Method java/lang/StringBuilder.append:(Ljava/lang/String;)Ljava/lang/StringBuilder;
      16: aload_2
      17: invokevirtual #8                  // Method java/lang/StringBuilder.append:(Ljava/lang/String;)Ljava/lang/StringBuilder;
      20: ldc           #9                  // String ] not found.
      22: invokevirtual #8                  // Method java/lang/StringBuilder.append:(Ljava/lang/String;)Ljava/lang/StringBuilder;
      25: invokevirtual #10                 // Method java/lang/StringBuilder.toString:()Ljava/lang/String;
      28: invokespecial #11                 // Method org/apache/dubbo/common/bytecode/NoSuchPropertyException."<init>":(Ljava/lang/String;)V
      31: athrow

  public boolean hasProperty(java.lang.String);
    Code:
       0: iconst_0
       1: ireturn

  public java.lang.Object invokeMethod(java.lang.Object, java.lang.String, java.lang.Class<?>[], java.lang.Object[]) throws org.apache.dubbo.common.bytecode.NoSuchMethodException;
    Code:
       0: ldc           #12                 // String getClass
       2: aload_2
       3: invokevirtual #13                 // Method java/lang/String.equals:(Ljava/lang/Object;)Z
       6: ifeq          14
       9: aload_1
      10: invokevirtual #14                 // Method java/lang/Object.getClass:()Ljava/lang/Class;
      13: areturn
      14: ldc           #15                 // String hashCode
      16: aload_2
      17: invokevirtual #13                 // Method java/lang/String.equals:(Ljava/lang/Object;)Z
      20: ifeq          31
      23: aload_1
      24: invokevirtual #16                 // Method java/lang/Object.hashCode:()I
      27: invokestatic  #17                 // Method java/lang/Integer.valueOf:(I)Ljava/lang/Integer;
      30: areturn
      31: ldc           #18                 // String toString
      33: aload_2
      34: invokevirtual #13                 // Method java/lang/String.equals:(Ljava/lang/Object;)Z
      37: ifeq          45
      40: aload_1
      41: invokevirtual #19                 // Method java/lang/Object.toString:()Ljava/lang/String;
      44: areturn
      45: ldc           #20                 // String equals
      47: aload_2
      48: invokevirtual #13                 // Method java/lang/String.equals:(Ljava/lang/Object;)Z
      51: ifeq          105
      54: aload         4
      56: arraylength
      57: iconst_1
      58: if_icmpne     73
      61: aload_1
      62: aload         4
      64: iconst_0
      65: aaload
      66: invokevirtual #21                 // Method java/lang/Object.equals:(Ljava/lang/Object;)Z
      69: invokestatic  #22                 // Method java/lang/Boolean.valueOf:(Z)Ljava/lang/Boolean;
      72: areturn
      73: new           #23                 // class java/lang/IllegalArgumentException
      76: dup
      77: new           #5                  // class java/lang/StringBuilder
      80: dup
      81: invokespecial #6                  // Method java/lang/StringBuilder."<init>":()V
      84: ldc           #24                 // String Invoke method [
      86: invokevirtual #8                  // Method java/lang/StringBuilder.append:(Ljava/lang/String;)Ljava/lang/StringBuilder;
      89: aload_2
      90: invokevirtual #8                  // Method java/lang/StringBuilder.append:(Ljava/lang/String;)Ljava/lang/StringBuilder;
      93: ldc           #25                 // String ] argument number error.
      95: invokevirtual #8                  // Method java/lang/StringBuilder.append:(Ljava/lang/String;)Ljava/lang/StringBuilder;
      98: invokevirtual #10                 // Method java/lang/StringBuilder.toString:()Ljava/lang/String;
     101: invokespecial #26                 // Method java/lang/IllegalArgumentException."<init>":(Ljava/lang/String;)V
     104: athrow
     105: new           #27                 // class org/apache/dubbo/common/bytecode/NoSuchMethodException
     108: dup
     109: new           #5                  // class java/lang/StringBuilder
     112: dup
     113: invokespecial #6                  // Method java/lang/StringBuilder."<init>":()V
     116: ldc           #28                 // String Method [
     118: invokevirtual #8                  // Method java/lang/StringBuilder.append:(Ljava/lang/String;)Ljava/lang/StringBuilder;
     121: aload_2
     122: invokevirtual #8                  // Method java/lang/StringBuilder.append:(Ljava/lang/String;)Ljava/lang/StringBuilder;
     125: ldc           #9                  // String ] not found.
     127: invokevirtual #8                  // Method java/lang/StringBuilder.append:(Ljava/lang/String;)Ljava/lang/StringBuilder;
     130: invokevirtual #10                 // Method java/lang/StringBuilder.toString:()Ljava/lang/String;
     133: invokespecial #29                 // Method org/apache/dubbo/common/bytecode/NoSuchMethodException."<init>":(Ljava/lang/String;)V
     136: athrow
}
