Compiled from "NettyServer.java"
class org.apache.dubbo.rpc.protocol.rest.netty.NettyServer$1 extends io.netty.channel.ChannelInitializer<io.netty.channel.socket.SocketChannel> {
  final org.apache.dubbo.common.URL val$url;

  final org.apache.dubbo.rpc.protocol.rest.netty.NettyServer this$0;

  org.apache.dubbo.rpc.protocol.rest.netty.NettyServer$1(org.apache.dubbo.rpc.protocol.rest.netty.NettyServer, org.apache.dubbo.common.URL);
    Code:
       0: aload_0
       1: aload_1
       2: putfield      #1                  // Field this$0:Lorg/apache/dubbo/rpc/protocol/rest/netty/NettyServer;
       5: aload_0
       6: aload_2
       7: putfield      #2                  // Field val$url:Lorg/apache/dubbo/common/URL;
      10: aload_0
      11: invokespecial #3                  // Method io/netty/channel/ChannelInitializer."<init>":()V
      14: return

  public void initChannel(io.netty.channel.socket.SocketChannel) throws java.lang.Exception;
    Code:
       0: aload_1
       1: invokeinterface #4,  1            // InterfaceMethod io/netty/channel/socket/SocketChannel.pipeline:()Lio/netty/channel/ChannelPipeline;
       6: astore_2
       7: aload_0
       8: getfield      #2                  // Field val$url:Lorg/apache/dubbo/common/URL;
      11: ldc           #6                  // String idle.timeout
      13: iconst_m1
      14: invokevirtual #7                  // Method org/apache/dubbo/common/URL.getParameter:(Ljava/lang/String;I)I
      17: istore_3
      18: iload_3
      19: ifle          46
      22: aload_2
      23: iconst_1
      24: anewarray     #8                  // class io/netty/channel/ChannelHandler
      27: dup
      28: iconst_0
      29: new           #9                  // class io/netty/handler/timeout/IdleStateHandler
      32: dup
      33: iconst_0
      34: iconst_0
      35: iload_3
      36: invokespecial #10                 // Method io/netty/handler/timeout/IdleStateHandler."<init>":(III)V
      39: aastore
      40: invokeinterface #11,  2           // InterfaceMethod io/netty/channel/ChannelPipeline.addLast:([Lio/netty/channel/ChannelHandler;)Lio/netty/channel/ChannelPipeline;
      45: pop
      46: aload_2
      47: aload_0
      48: getfield      #1                  // Field this$0:Lorg/apache/dubbo/rpc/protocol/rest/netty/NettyServer;
      51: invokestatic  #12                 // Method org/apache/dubbo/rpc/protocol/rest/netty/NettyServer.access$000:(Lorg/apache/dubbo/rpc/protocol/rest/netty/NettyServer;)Ljava/util/List;
      54: aload_0
      55: getfield      #1                  // Field this$0:Lorg/apache/dubbo/rpc/protocol/rest/netty/NettyServer;
      58: invokestatic  #12                 // Method org/apache/dubbo/rpc/protocol/rest/netty/NettyServer.access$000:(Lorg/apache/dubbo/rpc/protocol/rest/netty/NettyServer;)Ljava/util/List;
      61: invokeinterface #13,  1           // InterfaceMethod java/util/List.size:()I
      66: anewarray     #8                  // class io/netty/channel/ChannelHandler
      69: invokeinterface #14,  2           // InterfaceMethod java/util/List.toArray:([Ljava/lang/Object;)[Ljava/lang/Object;
      74: checkcast     #15                 // class "[Lio/netty/channel/ChannelHandler;"
      77: invokeinterface #11,  2           // InterfaceMethod io/netty/channel/ChannelPipeline.addLast:([Lio/netty/channel/ChannelHandler;)Lio/netty/channel/ChannelPipeline;
      82: pop
      83: aload_0
      84: getfield      #1                  // Field this$0:Lorg/apache/dubbo/rpc/protocol/rest/netty/NettyServer;
      87: invokestatic  #16                 // Method org/apache/dubbo/rpc/protocol/rest/netty/NettyServer.access$100:(Lorg/apache/dubbo/rpc/protocol/rest/netty/NettyServer;)Lorg/apache/dubbo/rpc/protocol/rest/netty/UnSharedHandlerCreator;
      90: aload_0
      91: getfield      #2                  // Field val$url:Lorg/apache/dubbo/common/URL;
      94: invokeinterface #17,  2           // InterfaceMethod org/apache/dubbo/rpc/protocol/rest/netty/UnSharedHandlerCreator.getUnSharedHandlers:(Lorg/apache/dubbo/common/URL;)Ljava/util/List;
      99: astore        4
     101: aload         4
     103: invokeinterface #18,  1           // InterfaceMethod java/util/List.iterator:()Ljava/util/Iterator;
     108: astore        5
     110: aload         5
     112: invokeinterface #19,  1           // InterfaceMethod java/util/Iterator.hasNext:()Z
     117: ifeq          151
     120: aload         5
     122: invokeinterface #20,  1           // InterfaceMethod java/util/Iterator.next:()Ljava/lang/Object;
     127: checkcast     #8                  // class io/netty/channel/ChannelHandler
     130: astore        6
     132: aload_2
     133: iconst_1
     134: anewarray     #8                  // class io/netty/channel/ChannelHandler
     137: dup
     138: iconst_0
     139: aload         6
     141: aastore
     142: invokeinterface #11,  2           // InterfaceMethod io/netty/channel/ChannelPipeline.addLast:([Lio/netty/channel/ChannelHandler;)Lio/netty/channel/ChannelPipeline;
     147: pop
     148: goto          110
     151: return

  public void initChannel(io.netty.channel.Channel) throws java.lang.Exception;
    Code:
       0: aload_0
       1: aload_1
       2: checkcast     #21                 // class io/netty/channel/socket/SocketChannel
       5: invokevirtual #22                 // Method initChannel:(Lio/netty/channel/socket/SocketChannel;)V
       8: return
}
