Compiled from "RestHttpRequestDecoder.java"
public class org.apache.dubbo.rpc.protocol.rest.netty.RestHttpRequestDecoder extends io.netty.handler.codec.MessageToMessageDecoder<io.netty.handler.codec.http.FullHttpRequest> {
  private final org.apache.dubbo.common.logger.ErrorTypeAwareLogger logger;

  private final org.apache.dubbo.rpc.protocol.rest.handler.NettyHttpHandler handler;

  private final java.util.concurrent.Executor executor;

  public org.apache.dubbo.rpc.protocol.rest.netty.RestHttpRequestDecoder(org.apache.dubbo.rpc.protocol.rest.handler.NettyHttpHandler, org.apache.dubbo.common.URL);
    Code:
       0: aload_0
       1: invokespecial #1                  // Method io/netty/handler/codec/MessageToMessageDecoder."<init>":()V
       4: aload_0
       5: aload_0
       6: invokevirtual #2                  // Method java/lang/Object.getClass:()Ljava/lang/Class;
       9: invokestatic  #3                  // Method org/apache/dubbo/common/logger/LoggerFactory.getErrorTypeAwareLogger:(Ljava/lang/Class;)Lorg/apache/dubbo/common/logger/ErrorTypeAwareLogger;
      12: putfield      #4                  // Field logger:Lorg/apache/dubbo/common/logger/ErrorTypeAwareLogger;
      15: aload_0
      16: aload_1
      17: putfield      #5                  // Field handler:Lorg/apache/dubbo/rpc/protocol/rest/handler/NettyHttpHandler;
      20: aload_0
      21: aload_2
      22: invokevirtual #6                  // Method org/apache/dubbo/common/URL.getOrDefaultFrameworkModel:()Lorg/apache/dubbo/rpc/model/FrameworkModel;
      25: ldc           #7                  // class org/apache/dubbo/common/threadpool/ThreadPool
      27: invokevirtual #8                  // Method org/apache/dubbo/rpc/model/FrameworkModel.getExtensionLoader:(Ljava/lang/Class;)Lorg/apache/dubbo/common/extension/ExtensionLoader;
      30: invokevirtual #9                  // Method org/apache/dubbo/common/extension/ExtensionLoader.getAdaptiveExtension:()Ljava/lang/Object;
      33: checkcast     #7                  // class org/apache/dubbo/common/threadpool/ThreadPool
      36: aload_2
      37: invokeinterface #10,  2           // InterfaceMethod org/apache/dubbo/common/threadpool/ThreadPool.getExecutor:(Lorg/apache/dubbo/common/URL;)Ljava/util/concurrent/Executor;
      42: putfield      #11                 // Field executor:Ljava/util/concurrent/Executor;
      45: return

  protected void decode(io.netty.channel.ChannelHandlerContext, io.netty.handler.codec.http.FullHttpRequest, java.util.List<java.lang.Object>) throws java.lang.Exception;
    Code:
       0: aload_2
       1: invokestatic  #12                 // Method io/netty/handler/codec/http/HttpHeaders.isKeepAlive:(Lio/netty/handler/codec/http/HttpMessage;)Z
       4: istore        4
       6: new           #13                 // class org/apache/dubbo/rpc/protocol/rest/netty/NettyHttpResponse
       9: dup
      10: aload_1
      11: iload         4
      13: invokespecial #14                 // Method org/apache/dubbo/rpc/protocol/rest/netty/NettyHttpResponse."<init>":(Lio/netty/channel/ChannelHandlerContext;Z)V
      16: astore        5
      18: new           #15                 // class org/apache/dubbo/rpc/protocol/rest/request/NettyRequestFacade
      21: dup
      22: aload_2
      23: aload_1
      24: invokespecial #16                 // Method org/apache/dubbo/rpc/protocol/rest/request/NettyRequestFacade."<init>":(Ljava/lang/Object;Lio/netty/channel/ChannelHandlerContext;)V
      27: astore        6
      29: aload_0
      30: getfield      #11                 // Field executor:Ljava/util/concurrent/Executor;
      33: aload_0
      34: aload         6
      36: aload         5
      38: invokedynamic #17,  0             // InvokeDynamic #0:run:(Lorg/apache/dubbo/rpc/protocol/rest/netty/RestHttpRequestDecoder;Lorg/apache/dubbo/rpc/protocol/rest/request/NettyRequestFacade;Lorg/apache/dubbo/rpc/protocol/rest/netty/NettyHttpResponse;)Ljava/lang/Runnable;
      43: invokeinterface #18,  2           // InterfaceMethod java/util/concurrent/Executor.execute:(Ljava/lang/Runnable;)V
      48: return

  protected void decode(io.netty.channel.ChannelHandlerContext, java.lang.Object, java.util.List) throws java.lang.Exception;
    Code:
       0: aload_0
       1: aload_1
       2: aload_2
       3: checkcast     #19                 // class io/netty/handler/codec/http/FullHttpRequest
       6: aload_3
       7: invokevirtual #20                 // Method decode:(Lio/netty/channel/ChannelHandlerContext;Lio/netty/handler/codec/http/FullHttpRequest;Ljava/util/List;)V
      10: return

  private void lambda$decode$0(org.apache.dubbo.rpc.protocol.rest.request.NettyRequestFacade, org.apache.dubbo.rpc.protocol.rest.netty.NettyHttpResponse);
    Code:
       0: aload_0
       1: getfield      #5                  // Field handler:Lorg/apache/dubbo/rpc/protocol/rest/handler/NettyHttpHandler;
       4: aload_1
       5: aload_2
       6: invokevirtual #21                 // Method org/apache/dubbo/rpc/protocol/rest/handler/NettyHttpHandler.handle:(Lorg/apache/dubbo/rpc/protocol/rest/request/NettyRequestFacade;Lorg/apache/dubbo/rpc/protocol/rest/netty/NettyHttpResponse;)V
       9: aload_2
      10: getstatic     #22                 // Field org/apache/dubbo/rpc/protocol/rest/RestHeaderEnum.CONNECTION:Lorg/apache/dubbo/rpc/protocol/rest/RestHeaderEnum;
      13: invokevirtual #23                 // Method org/apache/dubbo/rpc/protocol/rest/RestHeaderEnum.getHeader:()Ljava/lang/String;
      16: ldc           #24                 // String close
      18: invokevirtual #25                 // Method org/apache/dubbo/rpc/protocol/rest/netty/NettyHttpResponse.addOutputHeaders:(Ljava/lang/String;Ljava/lang/String;)V
      21: aload_2
      22: invokevirtual #26                 // Method org/apache/dubbo/rpc/protocol/rest/netty/NettyHttpResponse.finish:()V
      25: goto          185
      28: astore_3
      29: aload_0
      30: getfield      #4                  // Field logger:Lorg/apache/dubbo/common/logger/ErrorTypeAwareLogger;
      33: ldc           #28                 // String
      35: aload_3
      36: invokevirtual #29                 // Method java/io/IOException.getCause:()Ljava/lang/Throwable;
      39: invokevirtual #30                 // Method java/lang/Throwable.getMessage:()Ljava/lang/String;
      42: ldc           #31                 // String dubbo rest rest http response flush error
      44: aload_3
      45: invokevirtual #32                 // Method java/io/IOException.getMessage:()Ljava/lang/String;
      48: aload_3
      49: invokeinterface #33,  6           // InterfaceMethod org/apache/dubbo/common/logger/ErrorTypeAwareLogger.error:(Ljava/lang/String;Ljava/lang/String;Ljava/lang/String;Ljava/lang/String;Ljava/lang/Throwable;)V
      54: goto          185
      57: astore_3
      58: aload_0
      59: getfield      #4                  // Field logger:Lorg/apache/dubbo/common/logger/ErrorTypeAwareLogger;
      62: ldc           #28                 // String
      64: aload_3
      65: invokevirtual #29                 // Method java/io/IOException.getCause:()Ljava/lang/Throwable;
      68: invokevirtual #30                 // Method java/lang/Throwable.getMessage:()Ljava/lang/String;
      71: ldc           #34                 // String dubbo rest rest http request handler error
      73: aload_3
      74: invokevirtual #32                 // Method java/io/IOException.getMessage:()Ljava/lang/String;
      77: aload_3
      78: invokeinterface #33,  6           // InterfaceMethod org/apache/dubbo/common/logger/ErrorTypeAwareLogger.error:(Ljava/lang/String;Ljava/lang/String;Ljava/lang/String;Ljava/lang/String;Ljava/lang/Throwable;)V
      83: aload_2
      84: getstatic     #22                 // Field org/apache/dubbo/rpc/protocol/rest/RestHeaderEnum.CONNECTION:Lorg/apache/dubbo/rpc/protocol/rest/RestHeaderEnum;
      87: invokevirtual #23                 // Method org/apache/dubbo/rpc/protocol/rest/RestHeaderEnum.getHeader:()Ljava/lang/String;
      90: ldc           #24                 // String close
      92: invokevirtual #25                 // Method org/apache/dubbo/rpc/protocol/rest/netty/NettyHttpResponse.addOutputHeaders:(Ljava/lang/String;Ljava/lang/String;)V
      95: aload_2
      96: invokevirtual #26                 // Method org/apache/dubbo/rpc/protocol/rest/netty/NettyHttpResponse.finish:()V
      99: goto          185
     102: astore_3
     103: aload_0
     104: getfield      #4                  // Field logger:Lorg/apache/dubbo/common/logger/ErrorTypeAwareLogger;
     107: ldc           #28                 // String
     109: aload_3
     110: invokevirtual #29                 // Method java/io/IOException.getCause:()Ljava/lang/Throwable;
     113: invokevirtual #30                 // Method java/lang/Throwable.getMessage:()Ljava/lang/String;
     116: ldc           #31                 // String dubbo rest rest http response flush error
     118: aload_3
     119: invokevirtual #32                 // Method java/io/IOException.getMessage:()Ljava/lang/String;
     122: aload_3
     123: invokeinterface #33,  6           // InterfaceMethod org/apache/dubbo/common/logger/ErrorTypeAwareLogger.error:(Ljava/lang/String;Ljava/lang/String;Ljava/lang/String;Ljava/lang/String;Ljava/lang/Throwable;)V
     128: goto          185
     131: astore        4
     133: aload_2
     134: getstatic     #22                 // Field org/apache/dubbo/rpc/protocol/rest/RestHeaderEnum.CONNECTION:Lorg/apache/dubbo/rpc/protocol/rest/RestHeaderEnum;
     137: invokevirtual #23                 // Method org/apache/dubbo/rpc/protocol/rest/RestHeaderEnum.getHeader:()Ljava/lang/String;
     140: ldc           #24                 // String close
     142: invokevirtual #25                 // Method org/apache/dubbo/rpc/protocol/rest/netty/NettyHttpResponse.addOutputHeaders:(Ljava/lang/String;Ljava/lang/String;)V
     145: aload_2
     146: invokevirtual #26                 // Method org/apache/dubbo/rpc/protocol/rest/netty/NettyHttpResponse.finish:()V
     149: goto          182
     152: astore        5
     154: aload_0
     155: getfield      #4                  // Field logger:Lorg/apache/dubbo/common/logger/ErrorTypeAwareLogger;
     158: ldc           #28                 // String
     160: aload         5
     162: invokevirtual #29                 // Method java/io/IOException.getCause:()Ljava/lang/Throwable;
     165: invokevirtual #30                 // Method java/lang/Throwable.getMessage:()Ljava/lang/String;
     168: ldc           #31                 // String dubbo rest rest http response flush error
     170: aload         5
     172: invokevirtual #32                 // Method java/io/IOException.getMessage:()Ljava/lang/String;
     175: aload         5
     177: invokeinterface #33,  6           // InterfaceMethod org/apache/dubbo/common/logger/ErrorTypeAwareLogger.error:(Ljava/lang/String;Ljava/lang/String;Ljava/lang/String;Ljava/lang/String;Ljava/lang/Throwable;)V
     182: aload         4
     184: athrow
     185: return
    Exception table:
       from    to  target type
           9    25    28   Class java/io/IOException
           0     9    57   Class java/io/IOException
          83    99   102   Class java/io/IOException
           0     9   131   any
          57    83   131   any
         133   149   152   Class java/io/IOException
         131   133   131   any
}
