Compiled from "Configurator.java"
public interface com.alibaba.dubbo.rpc.cluster.Configurator extends org.apache.dubbo.rpc.cluster.Configurator {
  public abstract com.alibaba.dubbo.common.URL getUrl();

  public abstract com.alibaba.dubbo.common.URL configure(com.alibaba.dubbo.common.URL);

  public default org.apache.dubbo.common.URL configure(org.apache.dubbo.common.URL);
    Code:
       0: aload_0
       1: new           #1                  // class com/alibaba/dubbo/common/URL
       4: dup
       5: aload_1
       6: invokespecial #2                  // Method com/alibaba/dubbo/common/URL."<init>":(Lorg/apache/dubbo/common/URL;)V
       9: invokeinterface #3,  2            // InterfaceMethod configure:(Lcom/alibaba/dubbo/common/URL;)Lcom/alibaba/dubbo/common/URL;
      14: areturn

  public default org.apache.dubbo.common.URL getUrl();
    Code:
       0: aload_0
       1: invokeinterface #4,  1            // InterfaceMethod getUrl:()Lcom/alibaba/dubbo/common/URL;
       6: areturn
}
