Compiled from "Directory.java"
public interface com.alibaba.dubbo.rpc.cluster.Directory<T> extends org.apache.dubbo.rpc.cluster.Directory<T> {
  public abstract com.alibaba.dubbo.common.URL getUrl();

  public abstract java.util.List<com.alibaba.dubbo.rpc.Invoker<T>> list(com.alibaba.dubbo.rpc.Invocation) throws com.alibaba.dubbo.rpc.RpcException;

  public default java.util.List<org.apache.dubbo.rpc.Invoker<T>> list(org.apache.dubbo.rpc.Invocation) throws org.apache.dubbo.rpc.RpcException;
    Code:
       0: aload_0
       1: new           #1                  // class com/alibaba/dubbo/rpc/Invocation$CompatibleInvocation
       4: dup
       5: aload_1
       6: invokespecial #2                  // Method com/alibaba/dubbo/rpc/Invocation$CompatibleInvocation."<init>":(Lorg/apache/dubbo/rpc/Invocation;)V
       9: invokeinterface #3,  2            // InterfaceMethod list:(Lcom/alibaba/dubbo/rpc/Invocation;)Ljava/util/List;
      14: astore_2
      15: aload_2
      16: invokeinterface #4,  1            // InterfaceMethod java/util/List.stream:()Ljava/util/stream/Stream;
      21: invokedynamic #5,  0              // InvokeDynamic #0:apply:()Ljava/util/function/Function;
      26: invokeinterface #6,  2            // InterfaceMethod java/util/stream/Stream.map:(Ljava/util/function/Function;)Ljava/util/stream/Stream;
      31: invokestatic  #7                  // Method java/util/stream/Collectors.toList:()Ljava/util/stream/Collector;
      34: invokeinterface #8,  2            // InterfaceMethod java/util/stream/Stream.collect:(Ljava/util/stream/Collector;)Ljava/lang/Object;
      39: checkcast     #9                  // class java/util/List
      42: areturn

  public default org.apache.dubbo.common.URL getUrl();
    Code:
       0: aload_0
       1: invokeinterface #10,  1           // InterfaceMethod getUrl:()Lcom/alibaba/dubbo/common/URL;
       6: areturn
}
