Compiled from "Router.java"
public interface com.alibaba.dubbo.rpc.cluster.Router extends org.apache.dubbo.rpc.cluster.Router {
  public abstract com.alibaba.dubbo.common.URL getUrl();

  public abstract <T> java.util.List<com.alibaba.dubbo.rpc.Invoker<T>> route(java.util.List<com.alibaba.dubbo.rpc.Invoker<T>>, com.alibaba.dubbo.common.URL, com.alibaba.dubbo.rpc.Invocation) throws com.alibaba.dubbo.rpc.RpcException;

  public abstract int compareTo(com.alibaba.dubbo.rpc.cluster.Router);

  public default <T> java.util.List<org.apache.dubbo.rpc.Invoker<T>> route(java.util.List<org.apache.dubbo.rpc.Invoker<T>>, org.apache.dubbo.common.URL, org.apache.dubbo.rpc.Invocation) throws org.apache.dubbo.rpc.RpcException;
    Code:
       0: aload_1
       1: invokeinterface #1,  1            // InterfaceMethod java/util/List.stream:()Ljava/util/stream/Stream;
       6: invokedynamic #2,  0              // InvokeDynamic #0:apply:()Ljava/util/function/Function;
      11: invokeinterface #3,  2            // InterfaceMethod java/util/stream/Stream.map:(Ljava/util/function/Function;)Ljava/util/stream/Stream;
      16: invokestatic  #4                  // Method java/util/stream/Collectors.toList:()Ljava/util/stream/Collector;
      19: invokeinterface #5,  2            // InterfaceMethod java/util/stream/Stream.collect:(Ljava/util/stream/Collector;)Ljava/lang/Object;
      24: checkcast     #6                  // class java/util/List
      27: astore        4
      29: aload_0
      30: aload         4
      32: new           #7                  // class com/alibaba/dubbo/common/URL
      35: dup
      36: aload_2
      37: invokespecial #8                  // Method com/alibaba/dubbo/common/URL."<init>":(Lorg/apache/dubbo/common/URL;)V
      40: new           #9                  // class com/alibaba/dubbo/rpc/Invocation$CompatibleInvocation
      43: dup
      44: aload_3
      45: invokespecial #10                 // Method com/alibaba/dubbo/rpc/Invocation$CompatibleInvocation."<init>":(Lorg/apache/dubbo/rpc/Invocation;)V
      48: invokeinterface #11,  4           // InterfaceMethod route:(Ljava/util/List;Lcom/alibaba/dubbo/common/URL;Lcom/alibaba/dubbo/rpc/Invocation;)Ljava/util/List;
      53: astore        5
      55: aload         5
      57: invokeinterface #1,  1            // InterfaceMethod java/util/List.stream:()Ljava/util/stream/Stream;
      62: invokedynamic #12,  0             // InvokeDynamic #1:apply:()Ljava/util/function/Function;
      67: invokeinterface #3,  2            // InterfaceMethod java/util/stream/Stream.map:(Ljava/util/function/Function;)Ljava/util/stream/Stream;
      72: invokestatic  #4                  // Method java/util/stream/Collectors.toList:()Ljava/util/stream/Collector;
      75: invokeinterface #5,  2            // InterfaceMethod java/util/stream/Stream.collect:(Ljava/util/stream/Collector;)Ljava/lang/Object;
      80: checkcast     #6                  // class java/util/List
      83: areturn

  public default boolean isRuntime();
    Code:
       0: iconst_1
       1: ireturn

  public default boolean isForce();
    Code:
       0: iconst_0
       1: ireturn

  public default int getPriority();
    Code:
       0: iconst_1
       1: ireturn

  public default int compareTo(org.apache.dubbo.rpc.cluster.Router);
    Code:
       0: aload_1
       1: instanceof    #13                 // class com/alibaba/dubbo/rpc/cluster/Router
       4: ifne          9
       7: iconst_1
       8: ireturn
       9: aload_0
      10: aload_1
      11: checkcast     #13                 // class com/alibaba/dubbo/rpc/cluster/Router
      14: invokeinterface #14,  2           // InterfaceMethod compareTo:(Lcom/alibaba/dubbo/rpc/cluster/Router;)I
      19: ireturn

  public default org.apache.dubbo.common.URL getUrl();
    Code:
       0: aload_0
       1: invokeinterface #15,  1           // InterfaceMethod getUrl:()Lcom/alibaba/dubbo/common/URL;
       6: areturn

  public default int compareTo(java.lang.Object);
    Code:
       0: aload_0
       1: aload_1
       2: checkcast     #16                 // class org/apache/dubbo/rpc/cluster/Router
       5: invokeinterface #17,  2           // InterfaceMethod compareTo:(Lorg/apache/dubbo/rpc/cluster/Router;)I
      10: ireturn

  private static org.apache.dubbo.rpc.Invoker lambda$route$1(com.alibaba.dubbo.rpc.Invoker);
    Code:
       0: aload_0
       1: invokeinterface #18,  1           // InterfaceMethod com/alibaba/dubbo/rpc/Invoker.getOriginal:()Lorg/apache/dubbo/rpc/Invoker;
       6: areturn

  private static com.alibaba.dubbo.rpc.Invoker$CompatibleInvoker lambda$route$0(org.apache.dubbo.rpc.Invoker);
    Code:
       0: new           #19                 // class com/alibaba/dubbo/rpc/Invoker$CompatibleInvoker
       3: dup
       4: aload_0
       5: invokespecial #20                 // Method com/alibaba/dubbo/rpc/Invoker$CompatibleInvoker."<init>":(Lorg/apache/dubbo/rpc/Invoker;)V
       8: areturn
}
