Compiled from "RuleConverter.java"
public interface com.alibaba.dubbo.rpc.cluster.RuleConverter extends org.apache.dubbo.rpc.cluster.RuleConverter {
  public abstract java.util.List<com.alibaba.dubbo.common.URL> convert(com.alibaba.dubbo.common.URL, java.lang.Object);

  public default java.util.List<org.apache.dubbo.common.URL> convert(org.apache.dubbo.common.URL, java.lang.Object);
    Code:
       0: aload_0
       1: new           #1                  // class com/alibaba/dubbo/common/URL
       4: dup
       5: aload_1
       6: invokespecial #2                  // Method com/alibaba/dubbo/common/URL."<init>":(Lorg/apache/dubbo/common/URL;)V
       9: aload_2
      10: invokeinterface #3,  3            // InterfaceMethod convert:(Lcom/alibaba/dubbo/common/URL;Ljava/lang/Object;)Ljava/util/List;
      15: invokeinterface #4,  1            // InterfaceMethod java/util/List.stream:()Ljava/util/stream/Stream;
      20: invokedynamic #5,  0              // InvokeDynamic #0:apply:()Ljava/util/function/Function;
      25: invokeinterface #6,  2            // InterfaceMethod java/util/stream/Stream.map:(Ljava/util/function/Function;)Ljava/util/stream/Stream;
      30: invokestatic  #7                  // Method java/util/stream/Collectors.toList:()Ljava/util/stream/Collector;
      33: invokeinterface #8,  2            // InterfaceMethod java/util/stream/Stream.collect:(Ljava/util/stream/Collector;)Ljava/lang/Object;
      38: checkcast     #9                  // class java/util/List
      41: areturn

  private static org.apache.dubbo.common.URL lambda$convert$0(com.alibaba.dubbo.common.URL);
    Code:
       0: aload_0
       1: invokevirtual #10                 // Method com/alibaba/dubbo/common/URL.getOriginalURL:()Lorg/apache/dubbo/common/URL;
       4: areturn
}
