Compiled from "FileStateRouterFactory.java"
public class org.apache.dubbo.rpc.cluster.router.file.FileStateRouterFactory implements org.apache.dubbo.rpc.cluster.router.state.StateRouterFactory {
  public static final java.lang.String NAME;

  private org.apache.dubbo.rpc.cluster.router.state.StateRouterFactory routerFactory;

  public org.apache.dubbo.rpc.cluster.router.file.FileStateRouterFactory();
    Code:
       0: aload_0
       1: invokespecial #2                  // Method java/lang/Object."<init>":()V
       4: return

  public void setRouterFactory(org.apache.dubbo.rpc.cluster.router.state.StateRouterFactory);
    Code:
       0: aload_0
       1: aload_1
       2: putfield      #3                  // Field routerFactory:Lorg/apache/dubbo/rpc/cluster/router/state/StateRouterFactory;
       5: return

  public <T> org.apache.dubbo.rpc.cluster.router.state.StateRouter<T> getRouter(java.lang.Class<T>, org.apache.dubbo.common.URL);
    Code:
       0: aload_2
       1: ldc           #4                  // String router
       3: ldc           #6                  // String script
       5: invokevirtual #7                  // Method org/apache/dubbo/common/URL.getParameter:(Ljava/lang/String;Ljava/lang/String;)Ljava/lang/String;
       8: astore_3
       9: aconst_null
      10: astore        4
      12: aload_2
      13: invokevirtual #8                  // Method org/apache/dubbo/common/URL.getPath:()Ljava/lang/String;
      16: astore        5
      18: aload         5
      20: ifnull        48
      23: aload         5
      25: bipush        46
      27: invokevirtual #9                  // Method java/lang/String.lastIndexOf:(I)I
      30: istore        6
      32: iload         6
      34: ifle          48
      37: aload         5
      39: iload         6
      41: iconst_1
      42: iadd
      43: invokevirtual #10                 // Method java/lang/String.substring:(I)Ljava/lang/String;
      46: astore        4
      48: new           #11                 // class java/io/FileReader
      51: dup
      52: aload_2
      53: invokevirtual #12                 // Method org/apache/dubbo/common/URL.getAbsolutePath:()Ljava/lang/String;
      56: invokespecial #13                 // Method java/io/FileReader."<init>":(Ljava/lang/String;)V
      59: invokestatic  #14                 // Method org/apache/dubbo/common/utils/IOUtils.read:(Ljava/io/Reader;)Ljava/lang/String;
      62: astore        6
      64: aload_2
      65: ldc           #15                 // String runtime
      67: iconst_0
      68: invokevirtual #16                 // Method org/apache/dubbo/common/URL.getParameter:(Ljava/lang/String;Z)Z
      71: istore        7
      73: aload_2
      74: invokestatic  #17                 // Method org/apache/dubbo/common/URLBuilder.from:(Lorg/apache/dubbo/common/URL;)Lorg/apache/dubbo/common/URLBuilder;
      77: aload_3
      78: invokevirtual #18                 // Method org/apache/dubbo/common/URLBuilder.setProtocol:(Ljava/lang/String;)Lorg/apache/dubbo/common/URLBuilder;
      81: ldc           #19                 // String type
      83: aload         4
      85: invokevirtual #20                 // Method org/apache/dubbo/common/URLBuilder.addParameter:(Ljava/lang/String;Ljava/lang/String;)Lorg/apache/dubbo/common/URLBuilder;
      88: ldc           #15                 // String runtime
      90: iload         7
      92: invokevirtual #21                 // Method org/apache/dubbo/common/URLBuilder.addParameter:(Ljava/lang/String;Z)Lorg/apache/dubbo/common/URLBuilder;
      95: ldc           #22                 // String rule
      97: aload         6
      99: invokevirtual #23                 // Method org/apache/dubbo/common/URLBuilder.addParameterAndEncoded:(Ljava/lang/String;Ljava/lang/String;)Lorg/apache/dubbo/common/URLBuilder;
     102: invokevirtual #24                 // Method org/apache/dubbo/common/URLBuilder.build:()Lorg/apache/dubbo/common/url/component/ServiceConfigURL;
     105: astore        8
     107: aload_0
     108: getfield      #3                  // Field routerFactory:Lorg/apache/dubbo/rpc/cluster/router/state/StateRouterFactory;
     111: aload_1
     112: aload         8
     114: invokeinterface #25,  3           // InterfaceMethod org/apache/dubbo/rpc/cluster/router/state/StateRouterFactory.getRouter:(Ljava/lang/Class;Lorg/apache/dubbo/common/URL;)Lorg/apache/dubbo/rpc/cluster/router/state/StateRouter;
     119: areturn
     120: astore_3
     121: new           #27                 // class java/lang/IllegalStateException
     124: dup
     125: aload_3
     126: invokevirtual #28                 // Method java/io/IOException.getMessage:()Ljava/lang/String;
     129: aload_3
     130: invokespecial #29                 // Method java/lang/IllegalStateException."<init>":(Ljava/lang/String;Ljava/lang/Throwable;)V
     133: athrow
    Exception table:
       from    to  target type
           0   119   120   Class java/io/IOException
}
