Compiled from "ConsumerClassLoaderFilter.java"
public class org.apache.dubbo.rpc.cluster.filter.support.ConsumerClassLoaderFilter implements org.apache.dubbo.rpc.cluster.filter.ClusterFilter {
  public org.apache.dubbo.rpc.cluster.filter.support.ConsumerClassLoaderFilter();
    Code:
       0: aload_0
       1: invokespecial #1                  // Method java/lang/Object."<init>":()V
       4: return

  public org.apache.dubbo.rpc.Result invoke(org.apache.dubbo.rpc.Invoker<?>, org.apache.dubbo.rpc.Invocation) throws org.apache.dubbo.rpc.RpcException;
    Code:
       0: invokestatic  #2                  // Method java/lang/Thread.currentThread:()Ljava/lang/Thread;
       3: invokevirtual #3                  // Method java/lang/Thread.getContextClassLoader:()Ljava/lang/ClassLoader;
       6: astore_3
       7: aload_2
       8: invokeinterface #4,  1            // InterfaceMethod org/apache/dubbo/rpc/Invocation.getServiceModel:()Lorg/apache/dubbo/rpc/model/ServiceModel;
      13: invokestatic  #5                  // Method java/util/Optional.ofNullable:(Ljava/lang/Object;)Ljava/util/Optional;
      16: invokedynamic #6,  0              // InvokeDynamic #0:apply:()Ljava/util/function/Function;
      21: invokevirtual #7                  // Method java/util/Optional.map:(Ljava/util/function/Function;)Ljava/util/Optional;
      24: invokestatic  #2                  // Method java/lang/Thread.currentThread:()Ljava/lang/Thread;
      27: dup
      28: invokevirtual #8                  // Method java/lang/Object.getClass:()Ljava/lang/Class;
      31: pop
      32: invokedynamic #9,  0              // InvokeDynamic #1:accept:(Ljava/lang/Thread;)Ljava/util/function/Consumer;
      37: invokevirtual #10                 // Method java/util/Optional.ifPresent:(Ljava/util/function/Consumer;)V
      40: aload_1
      41: aload_2
      42: invokeinterface #11,  2           // InterfaceMethod org/apache/dubbo/rpc/Invoker.invoke:(Lorg/apache/dubbo/rpc/Invocation;)Lorg/apache/dubbo/rpc/Result;
      47: astore        4
      49: invokestatic  #2                  // Method java/lang/Thread.currentThread:()Ljava/lang/Thread;
      52: aload_3
      53: invokevirtual #12                 // Method java/lang/Thread.setContextClassLoader:(Ljava/lang/ClassLoader;)V
      56: aload         4
      58: areturn
      59: astore        5
      61: invokestatic  #2                  // Method java/lang/Thread.currentThread:()Ljava/lang/Thread;
      64: aload_3
      65: invokevirtual #12                 // Method java/lang/Thread.setContextClassLoader:(Ljava/lang/ClassLoader;)V
      68: aload         5
      70: athrow
    Exception table:
       from    to  target type
           7    49    59   any
          59    61    59   any
}
