Compiled from "ConsumerContextFilter.java"
public class org.apache.dubbo.rpc.cluster.filter.support.ConsumerContextFilter implements org.apache.dubbo.rpc.cluster.filter.ClusterFilter,org.apache.dubbo.rpc.BaseFilter$Listener {
  private java.util.Set<org.apache.dubbo.rpc.PenetrateAttachmentSelector> supportedSelectors;

  public org.apache.dubbo.rpc.cluster.filter.support.ConsumerContextFilter(org.apache.dubbo.rpc.model.ApplicationModel);
    Code:
       0: aload_0
       1: invokespecial #2                  // Method java/lang/Object."<init>":()V
       4: aload_1
       5: ldc           #3                  // class org/apache/dubbo/rpc/PenetrateAttachmentSelector
       7: invokevirtual #4                  // Method org/apache/dubbo/rpc/model/ApplicationModel.getExtensionLoader:(Ljava/lang/Class;)Lorg/apache/dubbo/common/extension/ExtensionLoader;
      10: astore_2
      11: aload_0
      12: aload_2
      13: invokevirtual #5                  // Method org/apache/dubbo/common/extension/ExtensionLoader.getSupportedExtensionInstances:()Ljava/util/Set;
      16: putfield      #6                  // Field supportedSelectors:Ljava/util/Set;
      19: return

  public org.apache.dubbo.rpc.Result invoke(org.apache.dubbo.rpc.Invoker<?>, org.apache.dubbo.rpc.Invocation) throws org.apache.dubbo.rpc.RpcException;
    Code:
       0: invokestatic  #7                  // Method org/apache/dubbo/rpc/RpcContext.storeServiceContext:()Lorg/apache/dubbo/rpc/RpcContext$RestoreServiceContext;
       3: astore_3
       4: invokestatic  #8                  // Method org/apache/dubbo/rpc/RpcContext.getServiceContext:()Lorg/apache/dubbo/rpc/RpcServiceContext;
       7: aload_1
       8: invokevirtual #9                  // Method org/apache/dubbo/rpc/RpcServiceContext.setInvoker:(Lorg/apache/dubbo/rpc/Invoker;)Lorg/apache/dubbo/rpc/RpcServiceContext;
      11: aload_2
      12: invokevirtual #10                 // Method org/apache/dubbo/rpc/RpcServiceContext.setInvocation:(Lorg/apache/dubbo/rpc/Invocation;)Lorg/apache/dubbo/rpc/RpcServiceContext;
      15: invokestatic  #11                 // Method org/apache/dubbo/common/utils/NetUtils.getLocalHost:()Ljava/lang/String;
      18: iconst_0
      19: invokevirtual #12                 // Method org/apache/dubbo/rpc/RpcServiceContext.setLocalAddress:(Ljava/lang/String;I)Lorg/apache/dubbo/rpc/RpcServiceContext;
      22: pop
      23: invokestatic  #13                 // Method org/apache/dubbo/rpc/RpcContext.getClientAttachment:()Lorg/apache/dubbo/rpc/RpcContextAttachment;
      26: astore        4
      28: aload         4
      30: ldc           #14                 // String remote.application
      32: aload_1
      33: invokeinterface #15,  1           // InterfaceMethod org/apache/dubbo/rpc/Invoker.getUrl:()Lorg/apache/dubbo/common/URL;
      38: invokevirtual #16                 // Method org/apache/dubbo/common/URL.getApplication:()Ljava/lang/String;
      41: invokevirtual #17                 // Method org/apache/dubbo/rpc/RpcContext.setAttachment:(Ljava/lang/String;Ljava/lang/String;)Lorg/apache/dubbo/rpc/RpcContext;
      44: pop
      45: aload_2
      46: instanceof    #18                 // class org/apache/dubbo/rpc/RpcInvocation
      49: ifeq          60
      52: aload_2
      53: checkcast     #18                 // class org/apache/dubbo/rpc/RpcInvocation
      56: aload_1
      57: invokevirtual #19                 // Method org/apache/dubbo/rpc/RpcInvocation.setInvoker:(Lorg/apache/dubbo/rpc/Invoker;)V
      60: aload_0
      61: getfield      #6                  // Field supportedSelectors:Ljava/util/Set;
      64: invokestatic  #20                 // Method org/apache/dubbo/common/utils/CollectionUtils.isNotEmpty:(Ljava/util/Collection;)Z
      67: ifeq          142
      70: aload_0
      71: getfield      #6                  // Field supportedSelectors:Ljava/util/Set;
      74: invokeinterface #21,  1           // InterfaceMethod java/util/Set.iterator:()Ljava/util/Iterator;
      79: astore        5
      81: aload         5
      83: invokeinterface #22,  1           // InterfaceMethod java/util/Iterator.hasNext:()Z
      88: ifeq          139
      91: aload         5
      93: invokeinterface #23,  1           // InterfaceMethod java/util/Iterator.next:()Ljava/lang/Object;
      98: checkcast     #3                  // class org/apache/dubbo/rpc/PenetrateAttachmentSelector
     101: astore        6
     103: aload         6
     105: aload_2
     106: invokestatic  #13                 // Method org/apache/dubbo/rpc/RpcContext.getClientAttachment:()Lorg/apache/dubbo/rpc/RpcContextAttachment;
     109: invokestatic  #24                 // Method org/apache/dubbo/rpc/RpcContext.getServerAttachment:()Lorg/apache/dubbo/rpc/RpcContextAttachment;
     112: invokeinterface #25,  4           // InterfaceMethod org/apache/dubbo/rpc/PenetrateAttachmentSelector.select:(Lorg/apache/dubbo/rpc/Invocation;Lorg/apache/dubbo/rpc/RpcContextAttachment;Lorg/apache/dubbo/rpc/RpcContextAttachment;)Ljava/util/Map;
     117: astore        7
     119: aload         7
     121: invokestatic  #26                 // Method org/apache/dubbo/common/utils/CollectionUtils.isNotEmptyMap:(Ljava/util/Map;)Z
     124: ifeq          136
     127: aload_2
     128: checkcast     #18                 // class org/apache/dubbo/rpc/RpcInvocation
     131: aload         7
     133: invokevirtual #27                 // Method org/apache/dubbo/rpc/RpcInvocation.addObjectAttachments:(Ljava/util/Map;)V
     136: goto          81
     139: goto          155
     142: aload_2
     143: checkcast     #18                 // class org/apache/dubbo/rpc/RpcInvocation
     146: invokestatic  #24                 // Method org/apache/dubbo/rpc/RpcContext.getServerAttachment:()Lorg/apache/dubbo/rpc/RpcContextAttachment;
     149: invokevirtual #28                 // Method org/apache/dubbo/rpc/RpcContextAttachment.getObjectAttachments:()Ljava/util/Map;
     152: invokevirtual #27                 // Method org/apache/dubbo/rpc/RpcInvocation.addObjectAttachments:(Ljava/util/Map;)V
     155: invokestatic  #13                 // Method org/apache/dubbo/rpc/RpcContext.getClientAttachment:()Lorg/apache/dubbo/rpc/RpcContextAttachment;
     158: invokevirtual #28                 // Method org/apache/dubbo/rpc/RpcContextAttachment.getObjectAttachments:()Ljava/util/Map;
     161: astore        5
     163: aload         5
     165: invokestatic  #26                 // Method org/apache/dubbo/common/utils/CollectionUtils.isNotEmptyMap:(Ljava/util/Map;)Z
     168: ifeq          180
     171: aload_2
     172: checkcast     #18                 // class org/apache/dubbo/rpc/RpcInvocation
     175: aload         5
     177: invokevirtual #27                 // Method org/apache/dubbo/rpc/RpcInvocation.addObjectAttachments:(Ljava/util/Map;)V
     180: invokestatic  #24                 // Method org/apache/dubbo/rpc/RpcContext.getServerAttachment:()Lorg/apache/dubbo/rpc/RpcContextAttachment;
     183: ldc           #29                 // String timeout-countdown
     185: invokevirtual #30                 // Method org/apache/dubbo/rpc/RpcContextAttachment.getObjectAttachment:(Ljava/lang/String;)Ljava/lang/Object;
     188: astore        6
     190: aload         6
     192: ifnull        308
     195: aload_2
     196: invokestatic  #31                 // Method org/apache/dubbo/rpc/support/RpcUtils.getMethodName:(Lorg/apache/dubbo/rpc/Invocation;)Ljava/lang/String;
     199: astore        7
     201: aload_1
     202: invokeinterface #15,  1           // InterfaceMethod org/apache/dubbo/rpc/Invoker.getUrl:()Lorg/apache/dubbo/common/URL;
     207: aload         7
     209: ldc           #32                 // String enable-timeout-countdown
     211: iconst_1
     212: invokevirtual #33                 // Method org/apache/dubbo/common/URL.getMethodParameter:(Ljava/lang/String;Ljava/lang/String;Z)Z
     215: ifeq          308
     218: aload         4
     220: ldc           #29                 // String timeout-countdown
     222: aload         6
     224: invokevirtual #34                 // Method org/apache/dubbo/rpc/RpcContext.setObjectAttachment:(Ljava/lang/String;Ljava/lang/Object;)Lorg/apache/dubbo/rpc/RpcContext;
     227: pop
     228: aload         6
     230: checkcast     #35                 // class org/apache/dubbo/rpc/TimeoutCountDown
     233: astore        8
     235: aload         8
     237: invokevirtual #36                 // Method org/apache/dubbo/rpc/TimeoutCountDown.isExpired:()Z
     240: ifeq          308
     243: new           #37                 // class org/apache/dubbo/rpc/RpcException
     246: dup
     247: bipush        8
     249: new           #38                 // class java/lang/StringBuilder
     252: dup
     253: invokespecial #39                 // Method java/lang/StringBuilder."<init>":()V
     256: ldc           #40                 // String No time left for making the following call:
     258: invokevirtual #41                 // Method java/lang/StringBuilder.append:(Ljava/lang/String;)Ljava/lang/StringBuilder;
     261: aload_2
     262: invokeinterface #42,  1           // InterfaceMethod org/apache/dubbo/rpc/Invocation.getServiceName:()Ljava/lang/String;
     267: invokevirtual #41                 // Method java/lang/StringBuilder.append:(Ljava/lang/String;)Ljava/lang/StringBuilder;
     270: ldc           #43                 // String .
     272: invokevirtual #41                 // Method java/lang/StringBuilder.append:(Ljava/lang/String;)Ljava/lang/StringBuilder;
     275: aload_2
     276: invokeinterface #44,  1           // InterfaceMethod org/apache/dubbo/rpc/Invocation.getMethodName:()Ljava/lang/String;
     281: invokevirtual #41                 // Method java/lang/StringBuilder.append:(Ljava/lang/String;)Ljava/lang/StringBuilder;
     284: ldc           #45                 // String , terminate directly.
     286: invokevirtual #41                 // Method java/lang/StringBuilder.append:(Ljava/lang/String;)Ljava/lang/StringBuilder;
     289: invokevirtual #46                 // Method java/lang/StringBuilder.toString:()Ljava/lang/String;
     292: invokespecial #47                 // Method org/apache/dubbo/rpc/RpcException."<init>":(ILjava/lang/String;)V
     295: aload_2
     296: invokestatic  #48                 // Method org/apache/dubbo/rpc/AsyncRpcResult.newDefaultAsyncResult:(Ljava/lang/Throwable;Lorg/apache/dubbo/rpc/Invocation;)Lorg/apache/dubbo/rpc/AsyncRpcResult;
     299: astore        9
     301: aload_3
     302: invokestatic  #49                 // Method org/apache/dubbo/rpc/RpcContext.restoreServiceContext:(Lorg/apache/dubbo/rpc/RpcContext$RestoreServiceContext;)V
     305: aload         9
     307: areturn
     308: invokestatic  #50                 // Method org/apache/dubbo/rpc/RpcContext.removeClientResponseContext:()V
     311: aload_1
     312: aload_2
     313: invokeinterface #51,  2           // InterfaceMethod org/apache/dubbo/rpc/Invoker.invoke:(Lorg/apache/dubbo/rpc/Invocation;)Lorg/apache/dubbo/rpc/Result;
     318: astore        7
     320: aload_3
     321: invokestatic  #49                 // Method org/apache/dubbo/rpc/RpcContext.restoreServiceContext:(Lorg/apache/dubbo/rpc/RpcContext$RestoreServiceContext;)V
     324: aload         7
     326: areturn
     327: astore        10
     329: aload_3
     330: invokestatic  #49                 // Method org/apache/dubbo/rpc/RpcContext.restoreServiceContext:(Lorg/apache/dubbo/rpc/RpcContext$RestoreServiceContext;)V
     333: aload         10
     335: athrow
    Exception table:
       from    to  target type
           4   301   327   any
         308   320   327   any
         327   329   327   any

  public void onResponse(org.apache.dubbo.rpc.Result, org.apache.dubbo.rpc.Invoker<?>, org.apache.dubbo.rpc.Invocation);
    Code:
       0: aload_1
       1: invokeinterface #52,  1           // InterfaceMethod org/apache/dubbo/rpc/Result.getObjectAttachments:()Ljava/util/Map;
       6: astore        4
       8: invokestatic  #53                 // Method org/apache/dubbo/rpc/RpcContext.getClientResponseContext:()Lorg/apache/dubbo/rpc/RpcContextAttachment;
      11: aload         4
      13: invokevirtual #54                 // Method org/apache/dubbo/rpc/RpcContextAttachment.setObjectAttachments:(Ljava/util/Map;)Lorg/apache/dubbo/rpc/RpcContextAttachment;
      16: pop
      17: aload_0
      18: aload_3
      19: invokespecial #55                 // Method removeContext:(Lorg/apache/dubbo/rpc/Invocation;)V
      22: return

  public void onError(java.lang.Throwable, org.apache.dubbo.rpc.Invoker<?>, org.apache.dubbo.rpc.Invocation);
    Code:
       0: aload_0
       1: aload_3
       2: invokespecial #55                 // Method removeContext:(Lorg/apache/dubbo/rpc/Invocation;)V
       5: return

  private void removeContext(org.apache.dubbo.rpc.Invocation);
    Code:
       0: invokestatic  #56                 // Method org/apache/dubbo/rpc/RpcContext.removeClientAttachment:()V
       3: aload_1
       4: instanceof    #18                 // class org/apache/dubbo/rpc/RpcInvocation
       7: ifeq          45
      10: aload_1
      11: checkcast     #18                 // class org/apache/dubbo/rpc/RpcInvocation
      14: astore_2
      15: aload_2
      16: invokevirtual #57                 // Method org/apache/dubbo/rpc/RpcInvocation.getInvokeMode:()Lorg/apache/dubbo/rpc/InvokeMode;
      19: ifnull        45
      22: aload_2
      23: invokevirtual #57                 // Method org/apache/dubbo/rpc/RpcInvocation.getInvokeMode:()Lorg/apache/dubbo/rpc/InvokeMode;
      26: getstatic     #58                 // Field org/apache/dubbo/rpc/InvokeMode.ASYNC:Lorg/apache/dubbo/rpc/InvokeMode;
      29: if_acmpeq     42
      32: aload_2
      33: invokevirtual #57                 // Method org/apache/dubbo/rpc/RpcInvocation.getInvokeMode:()Lorg/apache/dubbo/rpc/InvokeMode;
      36: getstatic     #59                 // Field org/apache/dubbo/rpc/InvokeMode.FUTURE:Lorg/apache/dubbo/rpc/InvokeMode;
      39: if_acmpne     45
      42: invokestatic  #60                 // Method org/apache/dubbo/rpc/RpcContext.removeServiceContext:()V
      45: return
}
