Compiled from "ObservationSenderFilter.java"
public class org.apache.dubbo.rpc.cluster.filter.support.ObservationSenderFilter implements org.apache.dubbo.rpc.cluster.filter.ClusterFilter,org.apache.dubbo.rpc.BaseFilter$Listener,org.apache.dubbo.rpc.model.ScopeModelAware {
  private io.micrometer.observation.ObservationRegistry observationRegistry;

  private org.apache.dubbo.metrics.observation.DubboClientObservationConvention clientObservationConvention;

  public org.apache.dubbo.rpc.cluster.filter.support.ObservationSenderFilter(org.apache.dubbo.rpc.model.ApplicationModel);
    Code:
       0: aload_0
       1: invokespecial #1                  // Method java/lang/Object."<init>":()V
       4: aload_1
       5: invokevirtual #2                  // Method org/apache/dubbo/rpc/model/ApplicationModel.getApplicationConfigManager:()Lorg/apache/dubbo/config/context/ConfigManager;
       8: invokevirtual #3                  // Method org/apache/dubbo/config/context/ConfigManager.getTracing:()Ljava/util/Optional;
      11: aload_0
      12: aload_1
      13: invokedynamic #4,  0              // InvokeDynamic #0:accept:(Lorg/apache/dubbo/rpc/cluster/filter/support/ObservationSenderFilter;Lorg/apache/dubbo/rpc/model/ApplicationModel;)Ljava/util/function/Consumer;
      18: invokevirtual #5                  // Method java/util/Optional.ifPresent:(Ljava/util/function/Consumer;)V
      21: return

  public org.apache.dubbo.rpc.Result invoke(org.apache.dubbo.rpc.Invoker<?>, org.apache.dubbo.rpc.Invocation) throws org.apache.dubbo.rpc.RpcException;
    Code:
       0: aload_0
       1: getfield      #6                  // Field observationRegistry:Lio/micrometer/observation/ObservationRegistry;
       4: ifnonnull     15
       7: aload_1
       8: aload_2
       9: invokeinterface #7,  2            // InterfaceMethod org/apache/dubbo/rpc/Invoker.invoke:(Lorg/apache/dubbo/rpc/Invocation;)Lorg/apache/dubbo/rpc/Result;
      14: areturn
      15: new           #8                  // class org/apache/dubbo/metrics/observation/DubboClientContext
      18: dup
      19: aload_1
      20: aload_2
      21: invokespecial #9                  // Method org/apache/dubbo/metrics/observation/DubboClientContext."<init>":(Lorg/apache/dubbo/rpc/Invoker;Lorg/apache/dubbo/rpc/Invocation;)V
      24: astore_3
      25: getstatic     #10                 // Field org/apache/dubbo/metrics/observation/DubboObservationDocumentation.CLIENT:Lorg/apache/dubbo/metrics/observation/DubboObservationDocumentation;
      28: aload_0
      29: getfield      #11                 // Field clientObservationConvention:Lorg/apache/dubbo/metrics/observation/DubboClientObservationConvention;
      32: invokestatic  #12                 // Method org/apache/dubbo/metrics/observation/DefaultDubboClientObservationConvention.getInstance:()Lorg/apache/dubbo/metrics/observation/DubboClientObservationConvention;
      35: aload_3
      36: invokedynamic #13,  0             // InvokeDynamic #1:get:(Lorg/apache/dubbo/metrics/observation/DubboClientContext;)Ljava/util/function/Supplier;
      41: aload_0
      42: getfield      #6                  // Field observationRegistry:Lio/micrometer/observation/ObservationRegistry;
      45: invokevirtual #14                 // Method org/apache/dubbo/metrics/observation/DubboObservationDocumentation.observation:(Lio/micrometer/observation/ObservationConvention;Lio/micrometer/observation/ObservationConvention;Ljava/util/function/Supplier;Lio/micrometer/observation/ObservationRegistry;)Lio/micrometer/observation/Observation;
      48: astore        4
      50: aload_2
      51: ldc           #15                 // class io/micrometer/observation/Observation
      53: aload         4
      55: invokeinterface #16,  1           // InterfaceMethod io/micrometer/observation/Observation.start:()Lio/micrometer/observation/Observation;
      60: invokeinterface #17,  3           // InterfaceMethod org/apache/dubbo/rpc/Invocation.put:(Ljava/lang/Object;Ljava/lang/Object;)Ljava/lang/Object;
      65: pop
      66: aload         4
      68: aload_1
      69: aload_2
      70: invokedynamic #18,  0             // InvokeDynamic #2:get:(Lorg/apache/dubbo/rpc/Invoker;Lorg/apache/dubbo/rpc/Invocation;)Ljava/util/function/Supplier;
      75: invokeinterface #19,  2           // InterfaceMethod io/micrometer/observation/Observation.scoped:(Ljava/util/function/Supplier;)Ljava/lang/Object;
      80: checkcast     #20                 // class org/apache/dubbo/rpc/Result
      83: areturn

  public void onResponse(org.apache.dubbo.rpc.Result, org.apache.dubbo.rpc.Invoker<?>, org.apache.dubbo.rpc.Invocation);
    Code:
       0: aload_0
       1: aload_3
       2: invokespecial #21                 // Method getObservation:(Lorg/apache/dubbo/rpc/Invocation;)Lio/micrometer/observation/Observation;
       5: astore        4
       7: aload         4
       9: ifnonnull     13
      12: return
      13: aload         4
      15: invokeinterface #22,  1           // InterfaceMethod io/micrometer/observation/Observation.stop:()V
      20: return

  public void onError(java.lang.Throwable, org.apache.dubbo.rpc.Invoker<?>, org.apache.dubbo.rpc.Invocation);
    Code:
       0: aload_0
       1: aload_3
       2: invokespecial #21                 // Method getObservation:(Lorg/apache/dubbo/rpc/Invocation;)Lio/micrometer/observation/Observation;
       5: astore        4
       7: aload         4
       9: ifnonnull     13
      12: return
      13: aload         4
      15: aload_1
      16: invokeinterface #23,  2           // InterfaceMethod io/micrometer/observation/Observation.error:(Ljava/lang/Throwable;)Lio/micrometer/observation/Observation;
      21: pop
      22: aload         4
      24: invokeinterface #22,  1           // InterfaceMethod io/micrometer/observation/Observation.stop:()V
      29: return

  private io.micrometer.observation.Observation getObservation(org.apache.dubbo.rpc.Invocation);
    Code:
       0: aload_1
       1: ldc           #15                 // class io/micrometer/observation/Observation
       3: invokeinterface #24,  2           // InterfaceMethod org/apache/dubbo/rpc/Invocation.get:(Ljava/lang/Object;)Ljava/lang/Object;
       8: checkcast     #15                 // class io/micrometer/observation/Observation
      11: areturn

  private static org.apache.dubbo.rpc.Result lambda$invoke$2(org.apache.dubbo.rpc.Invoker, org.apache.dubbo.rpc.Invocation);
    Code:
       0: aload_0
       1: aload_1
       2: invokeinterface #7,  2            // InterfaceMethod org/apache/dubbo/rpc/Invoker.invoke:(Lorg/apache/dubbo/rpc/Invocation;)Lorg/apache/dubbo/rpc/Result;
       7: areturn

  private static org.apache.dubbo.metrics.observation.DubboClientContext lambda$invoke$1(org.apache.dubbo.metrics.observation.DubboClientContext);
    Code:
       0: aload_0
       1: areturn

  private void lambda$new$0(org.apache.dubbo.rpc.model.ApplicationModel, org.apache.dubbo.config.TracingConfig);
    Code:
       0: getstatic     #25                 // Field java/lang/Boolean.TRUE:Ljava/lang/Boolean;
       3: aload_2
       4: invokevirtual #26                 // Method org/apache/dubbo/config/TracingConfig.getEnabled:()Ljava/lang/Boolean;
       7: invokevirtual #27                 // Method java/lang/Boolean.equals:(Ljava/lang/Object;)Z
      10: ifeq          45
      13: aload_0
      14: aload_1
      15: invokevirtual #28                 // Method org/apache/dubbo/rpc/model/ApplicationModel.getBeanFactory:()Lorg/apache/dubbo/common/beans/factory/ScopeBeanFactory;
      18: ldc           #29                 // class io/micrometer/observation/ObservationRegistry
      20: invokevirtual #30                 // Method org/apache/dubbo/common/beans/factory/ScopeBeanFactory.getBean:(Ljava/lang/Class;)Ljava/lang/Object;
      23: checkcast     #29                 // class io/micrometer/observation/ObservationRegistry
      26: putfield      #6                  // Field observationRegistry:Lio/micrometer/observation/ObservationRegistry;
      29: aload_0
      30: aload_1
      31: invokevirtual #28                 // Method org/apache/dubbo/rpc/model/ApplicationModel.getBeanFactory:()Lorg/apache/dubbo/common/beans/factory/ScopeBeanFactory;
      34: ldc           #31                 // class org/apache/dubbo/metrics/observation/DubboClientObservationConvention
      36: invokevirtual #30                 // Method org/apache/dubbo/common/beans/factory/ScopeBeanFactory.getBean:(Ljava/lang/Class;)Ljava/lang/Object;
      39: checkcast     #31                 // class org/apache/dubbo/metrics/observation/DubboClientObservationConvention
      42: putfield      #11                 // Field clientObservationConvention:Lorg/apache/dubbo/metrics/observation/DubboClientObservationConvention;
      45: return
}
