Compiled from "AbsentConfiguratorFactory.java"
public class org.apache.dubbo.rpc.cluster.configurator.absent.AbsentConfiguratorFactory implements org.apache.dubbo.rpc.cluster.ConfiguratorFactory {
  public org.apache.dubbo.rpc.cluster.configurator.absent.AbsentConfiguratorFactory();
    Code:
       0: aload_0
       1: invokespecial #1                  // Method java/lang/Object."<init>":()V
       4: return

  public org.apache.dubbo.rpc.cluster.Configurator getConfigurator(org.apache.dubbo.common.URL);
    Code:
       0: new           #2                  // class org/apache/dubbo/rpc/cluster/configurator/absent/AbsentConfigurator
       3: dup
       4: aload_1
       5: invokespecial #3                  // Method org/apache/dubbo/rpc/cluster/configurator/absent/AbsentConfigurator."<init>":(Lorg/apache/dubbo/common/URL;)V
       8: areturn
}
