Compiled from "AbsentConfigurator.java"
public class org.apache.dubbo.rpc.cluster.configurator.absent.AbsentConfigurator extends org.apache.dubbo.rpc.cluster.configurator.AbstractConfigurator {
  public org.apache.dubbo.rpc.cluster.configurator.absent.AbsentConfigurator(org.apache.dubbo.common.URL);
    Code:
       0: aload_0
       1: aload_1
       2: invokespecial #1                  // Method org/apache/dubbo/rpc/cluster/configurator/AbstractConfigurator."<init>":(Lorg/apache/dubbo/common/URL;)V
       5: return

  public org.apache.dubbo.common.URL doConfigure(org.apache.dubbo.common.URL, org.apache.dubbo.common.URL);
    Code:
       0: aload_1
       1: aload_2
       2: invokevirtual #2                  // Method org/apache/dubbo/common/URL.getParameters:()Ljava/util/Map;
       5: invokevirtual #3                  // Method org/apache/dubbo/common/URL.addParametersIfAbsent:(Ljava/util/Map;)Lorg/apache/dubbo/common/URL;
       8: areturn
}
