Compiled from "BackpressureOverflowStrategy.java"
public final class io.reactivex.rxjava3.core.BackpressureOverflowStrategy extends java.lang.Enum<io.reactivex.rxjava3.core.BackpressureOverflowStrategy> {
  public static final io.reactivex.rxjava3.core.BackpressureOverflowStrategy ERROR;

  public static final io.reactivex.rxjava3.core.BackpressureOverflowStrategy DROP_OLDEST;

  public static final io.reactivex.rxjava3.core.BackpressureOverflowStrategy DROP_LATEST;

  private static final io.reactivex.rxjava3.core.BackpressureOverflowStrategy[] $VALUES;

  public static io.reactivex.rxjava3.core.BackpressureOverflowStrategy[] values();
    Code:
       0: getstatic     #1                  // Field $VALUES:[Lio/reactivex/rxjava3/core/BackpressureOverflowStrategy;
       3: invokevirtual #2                  // Method "[Lio/reactivex/rxjava3/core/BackpressureOverflowStrategy;".clone:()Ljava/lang/Object;
       6: checkcast     #3                  // class "[Lio/reactivex/rxjava3/core/BackpressureOverflowStrategy;"
       9: areturn

  public static io.reactivex.rxjava3.core.BackpressureOverflowStrategy valueOf(java.lang.String);
    Code:
       0: ldc           #4                  // class io/reactivex/rxjava3/core/BackpressureOverflowStrategy
       2: aload_0
       3: invokestatic  #5                  // Method java/lang/Enum.valueOf:(Ljava/lang/Class;Ljava/lang/String;)Ljava/lang/Enum;
       6: checkcast     #4                  // class io/reactivex/rxjava3/core/BackpressureOverflowStrategy
       9: areturn

  private io.reactivex.rxjava3.core.BackpressureOverflowStrategy();
    Code:
       0: aload_0
       1: aload_1
       2: iload_2
       3: invokespecial #6                  // Method java/lang/Enum."<init>":(Ljava/lang/String;I)V
       6: return

  static {};
    Code:
       0: new           #4                  // class io/reactivex/rxjava3/core/BackpressureOverflowStrategy
       3: dup
       4: ldc           #7                  // String ERROR
       6: iconst_0
       7: invokespecial #8                  // Method "<init>":(Ljava/lang/String;I)V
      10: putstatic     #9                  // Field ERROR:Lio/reactivex/rxjava3/core/BackpressureOverflowStrategy;
      13: new           #4                  // class io/reactivex/rxjava3/core/BackpressureOverflowStrategy
      16: dup
      17: ldc           #10                 // String DROP_OLDEST
      19: iconst_1
      20: invokespecial #8                  // Method "<init>":(Ljava/lang/String;I)V
      23: putstatic     #11                 // Field DROP_OLDEST:Lio/reactivex/rxjava3/core/BackpressureOverflowStrategy;
      26: new           #4                  // class io/reactivex/rxjava3/core/BackpressureOverflowStrategy
      29: dup
      30: ldc           #12                 // String DROP_LATEST
      32: iconst_2
      33: invokespecial #8                  // Method "<init>":(Ljava/lang/String;I)V
      36: putstatic     #13                 // Field DROP_LATEST:Lio/reactivex/rxjava3/core/BackpressureOverflowStrategy;
      39: iconst_3
      40: anewarray     #4                  // class io/reactivex/rxjava3/core/BackpressureOverflowStrategy
      43: dup
      44: iconst_0
      45: getstatic     #9                  // Field ERROR:Lio/reactivex/rxjava3/core/BackpressureOverflowStrategy;
      48: aastore
      49: dup
      50: iconst_1
      51: getstatic     #11                 // Field DROP_OLDEST:Lio/reactivex/rxjava3/core/BackpressureOverflowStrategy;
      54: aastore
      55: dup
      56: iconst_2
      57: getstatic     #13                 // Field DROP_LATEST:Lio/reactivex/rxjava3/core/BackpressureOverflowStrategy;
      60: aastore
      61: putstatic     #1                  // Field $VALUES:[Lio/reactivex/rxjava3/core/BackpressureOverflowStrategy;
      64: return
}
