Compiled from "Completable.java"
public abstract class io.reactivex.rxjava3.core.Completable implements io.reactivex.rxjava3.core.CompletableSource {
  public io.reactivex.rxjava3.core.Completable();
    Code:
       0: aload_0
       1: invokespecial #1                  // Method java/lang/Object."<init>":()V
       4: return

  public static io.reactivex.rxjava3.core.Completable ambArray(io.reactivex.rxjava3.core.CompletableSource...);
    Code:
       0: aload_0
       1: ldc           #2                  // String sources is null
       3: invokestatic  #3                  // Method java/util/Objects.requireNonNull:(Ljava/lang/Object;Ljava/lang/String;)Ljava/lang/Object;
       6: pop
       7: aload_0
       8: arraylength
       9: ifne          16
      12: invokestatic  #4                  // Method complete:()Lio/reactivex/rxjava3/core/Completable;
      15: areturn
      16: aload_0
      17: arraylength
      18: iconst_1
      19: if_icmpne     29
      22: aload_0
      23: iconst_0
      24: aaload
      25: invokestatic  #5                  // Method wrap:(Lio/reactivex/rxjava3/core/CompletableSource;)Lio/reactivex/rxjava3/core/Completable;
      28: areturn
      29: new           #6                  // class io/reactivex/rxjava3/internal/operators/completable/CompletableAmb
      32: dup
      33: aload_0
      34: aconst_null
      35: invokespecial #7                  // Method io/reactivex/rxjava3/internal/operators/completable/CompletableAmb."<init>":([Lio/reactivex/rxjava3/core/CompletableSource;Ljava/lang/Iterable;)V
      38: invokestatic  #8                  // Method io/reactivex/rxjava3/plugins/RxJavaPlugins.onAssembly:(Lio/reactivex/rxjava3/core/Completable;)Lio/reactivex/rxjava3/core/Completable;
      41: areturn

  public static io.reactivex.rxjava3.core.Completable amb(java.lang.Iterable<? extends io.reactivex.rxjava3.core.CompletableSource>);
    Code:
       0: aload_0
       1: ldc           #2                  // String sources is null
       3: invokestatic  #3                  // Method java/util/Objects.requireNonNull:(Ljava/lang/Object;Ljava/lang/String;)Ljava/lang/Object;
       6: pop
       7: new           #6                  // class io/reactivex/rxjava3/internal/operators/completable/CompletableAmb
      10: dup
      11: aconst_null
      12: aload_0
      13: invokespecial #7                  // Method io/reactivex/rxjava3/internal/operators/completable/CompletableAmb."<init>":([Lio/reactivex/rxjava3/core/CompletableSource;Ljava/lang/Iterable;)V
      16: invokestatic  #8                  // Method io/reactivex/rxjava3/plugins/RxJavaPlugins.onAssembly:(Lio/reactivex/rxjava3/core/Completable;)Lio/reactivex/rxjava3/core/Completable;
      19: areturn

  public static io.reactivex.rxjava3.core.Completable complete();
    Code:
       0: getstatic     #9                  // Field io/reactivex/rxjava3/internal/operators/completable/CompletableEmpty.INSTANCE:Lio/reactivex/rxjava3/core/Completable;
       3: invokestatic  #8                  // Method io/reactivex/rxjava3/plugins/RxJavaPlugins.onAssembly:(Lio/reactivex/rxjava3/core/Completable;)Lio/reactivex/rxjava3/core/Completable;
       6: areturn

  public static io.reactivex.rxjava3.core.Completable concatArray(io.reactivex.rxjava3.core.CompletableSource...);
    Code:
       0: aload_0
       1: ldc           #2                  // String sources is null
       3: invokestatic  #3                  // Method java/util/Objects.requireNonNull:(Ljava/lang/Object;Ljava/lang/String;)Ljava/lang/Object;
       6: pop
       7: aload_0
       8: arraylength
       9: ifne          16
      12: invokestatic  #4                  // Method complete:()Lio/reactivex/rxjava3/core/Completable;
      15: areturn
      16: aload_0
      17: arraylength
      18: iconst_1
      19: if_icmpne     29
      22: aload_0
      23: iconst_0
      24: aaload
      25: invokestatic  #5                  // Method wrap:(Lio/reactivex/rxjava3/core/CompletableSource;)Lio/reactivex/rxjava3/core/Completable;
      28: areturn
      29: new           #10                 // class io/reactivex/rxjava3/internal/operators/completable/CompletableConcatArray
      32: dup
      33: aload_0
      34: invokespecial #11                 // Method io/reactivex/rxjava3/internal/operators/completable/CompletableConcatArray."<init>":([Lio/reactivex/rxjava3/core/CompletableSource;)V
      37: invokestatic  #8                  // Method io/reactivex/rxjava3/plugins/RxJavaPlugins.onAssembly:(Lio/reactivex/rxjava3/core/Completable;)Lio/reactivex/rxjava3/core/Completable;
      40: areturn

  public static io.reactivex.rxjava3.core.Completable concatArrayDelayError(io.reactivex.rxjava3.core.CompletableSource...);
    Code:
       0: aload_0
       1: invokestatic  #12                 // Method io/reactivex/rxjava3/core/Flowable.fromArray:([Ljava/lang/Object;)Lio/reactivex/rxjava3/core/Flowable;
       4: invokestatic  #13                 // Method io/reactivex/rxjava3/internal/functions/Functions.identity:()Lio/reactivex/rxjava3/functions/Function;
       7: iconst_1
       8: iconst_2
       9: invokevirtual #14                 // Method io/reactivex/rxjava3/core/Flowable.concatMapCompletableDelayError:(Lio/reactivex/rxjava3/functions/Function;ZI)Lio/reactivex/rxjava3/core/Completable;
      12: areturn

  public static io.reactivex.rxjava3.core.Completable concat(java.lang.Iterable<? extends io.reactivex.rxjava3.core.CompletableSource>);
    Code:
       0: aload_0
       1: ldc           #2                  // String sources is null
       3: invokestatic  #3                  // Method java/util/Objects.requireNonNull:(Ljava/lang/Object;Ljava/lang/String;)Ljava/lang/Object;
       6: pop
       7: new           #15                 // class io/reactivex/rxjava3/internal/operators/completable/CompletableConcatIterable
      10: dup
      11: aload_0
      12: invokespecial #16                 // Method io/reactivex/rxjava3/internal/operators/completable/CompletableConcatIterable."<init>":(Ljava/lang/Iterable;)V
      15: invokestatic  #8                  // Method io/reactivex/rxjava3/plugins/RxJavaPlugins.onAssembly:(Lio/reactivex/rxjava3/core/Completable;)Lio/reactivex/rxjava3/core/Completable;
      18: areturn

  public static io.reactivex.rxjava3.core.Completable concat(org.reactivestreams.Publisher<? extends io.reactivex.rxjava3.core.CompletableSource>);
    Code:
       0: aload_0
       1: iconst_2
       2: invokestatic  #17                 // Method concat:(Lorg/reactivestreams/Publisher;I)Lio/reactivex/rxjava3/core/Completable;
       5: areturn

  public static io.reactivex.rxjava3.core.Completable concat(org.reactivestreams.Publisher<? extends io.reactivex.rxjava3.core.CompletableSource>, int);
    Code:
       0: aload_0
       1: ldc           #2                  // String sources is null
       3: invokestatic  #3                  // Method java/util/Objects.requireNonNull:(Ljava/lang/Object;Ljava/lang/String;)Ljava/lang/Object;
       6: pop
       7: iload_1
       8: ldc           #18                 // String prefetch
      10: invokestatic  #19                 // Method io/reactivex/rxjava3/internal/functions/ObjectHelper.verifyPositive:(ILjava/lang/String;)I
      13: pop
      14: new           #20                 // class io/reactivex/rxjava3/internal/operators/completable/CompletableConcat
      17: dup
      18: aload_0
      19: iload_1
      20: invokespecial #21                 // Method io/reactivex/rxjava3/internal/operators/completable/CompletableConcat."<init>":(Lorg/reactivestreams/Publisher;I)V
      23: invokestatic  #8                  // Method io/reactivex/rxjava3/plugins/RxJavaPlugins.onAssembly:(Lio/reactivex/rxjava3/core/Completable;)Lio/reactivex/rxjava3/core/Completable;
      26: areturn

  public static io.reactivex.rxjava3.core.Completable concatDelayError(java.lang.Iterable<? extends io.reactivex.rxjava3.core.CompletableSource>);
    Code:
       0: aload_0
       1: invokestatic  #22                 // Method io/reactivex/rxjava3/core/Flowable.fromIterable:(Ljava/lang/Iterable;)Lio/reactivex/rxjava3/core/Flowable;
       4: invokestatic  #23                 // Method io/reactivex/rxjava3/internal/functions/Functions.identity:()Lio/reactivex/rxjava3/functions/Function;
       7: invokevirtual #24                 // Method io/reactivex/rxjava3/core/Flowable.concatMapCompletableDelayError:(Lio/reactivex/rxjava3/functions/Function;)Lio/reactivex/rxjava3/core/Completable;
      10: areturn

  public static io.reactivex.rxjava3.core.Completable concatDelayError(org.reactivestreams.Publisher<? extends io.reactivex.rxjava3.core.CompletableSource>);
    Code:
       0: aload_0
       1: iconst_2
       2: invokestatic  #25                 // Method concatDelayError:(Lorg/reactivestreams/Publisher;I)Lio/reactivex/rxjava3/core/Completable;
       5: areturn

  public static io.reactivex.rxjava3.core.Completable concatDelayError(org.reactivestreams.Publisher<? extends io.reactivex.rxjava3.core.CompletableSource>, int);
    Code:
       0: aload_0
       1: invokestatic  #26                 // Method io/reactivex/rxjava3/core/Flowable.fromPublisher:(Lorg/reactivestreams/Publisher;)Lio/reactivex/rxjava3/core/Flowable;
       4: invokestatic  #27                 // Method io/reactivex/rxjava3/internal/functions/Functions.identity:()Lio/reactivex/rxjava3/functions/Function;
       7: iconst_1
       8: iload_1
       9: invokevirtual #14                 // Method io/reactivex/rxjava3/core/Flowable.concatMapCompletableDelayError:(Lio/reactivex/rxjava3/functions/Function;ZI)Lio/reactivex/rxjava3/core/Completable;
      12: areturn

  public static io.reactivex.rxjava3.core.Completable create(io.reactivex.rxjava3.core.CompletableOnSubscribe);
    Code:
       0: aload_0
       1: ldc           #28                 // String source is null
       3: invokestatic  #3                  // Method java/util/Objects.requireNonNull:(Ljava/lang/Object;Ljava/lang/String;)Ljava/lang/Object;
       6: pop
       7: new           #29                 // class io/reactivex/rxjava3/internal/operators/completable/CompletableCreate
      10: dup
      11: aload_0
      12: invokespecial #30                 // Method io/reactivex/rxjava3/internal/operators/completable/CompletableCreate."<init>":(Lio/reactivex/rxjava3/core/CompletableOnSubscribe;)V
      15: invokestatic  #8                  // Method io/reactivex/rxjava3/plugins/RxJavaPlugins.onAssembly:(Lio/reactivex/rxjava3/core/Completable;)Lio/reactivex/rxjava3/core/Completable;
      18: areturn

  public static io.reactivex.rxjava3.core.Single<java.lang.Boolean> sequenceEqual(io.reactivex.rxjava3.core.CompletableSource, io.reactivex.rxjava3.core.CompletableSource);
    Code:
       0: aload_0
       1: ldc           #31                 // String source1 is null
       3: invokestatic  #3                  // Method java/util/Objects.requireNonNull:(Ljava/lang/Object;Ljava/lang/String;)Ljava/lang/Object;
       6: pop
       7: aload_1
       8: ldc           #32                 // String source2 is null
      10: invokestatic  #3                  // Method java/util/Objects.requireNonNull:(Ljava/lang/Object;Ljava/lang/String;)Ljava/lang/Object;
      13: pop
      14: iconst_2
      15: anewarray     #33                 // class io/reactivex/rxjava3/core/CompletableSource
      18: dup
      19: iconst_0
      20: aload_0
      21: aastore
      22: dup
      23: iconst_1
      24: aload_1
      25: aastore
      26: invokestatic  #34                 // Method mergeArrayDelayError:([Lio/reactivex/rxjava3/core/CompletableSource;)Lio/reactivex/rxjava3/core/Completable;
      29: iconst_1
      30: invokestatic  #35                 // Method java/lang/Boolean.valueOf:(Z)Ljava/lang/Boolean;
      33: invokestatic  #36                 // Method io/reactivex/rxjava3/core/Single.just:(Ljava/lang/Object;)Lio/reactivex/rxjava3/core/Single;
      36: invokevirtual #37                 // Method andThen:(Lio/reactivex/rxjava3/core/SingleSource;)Lio/reactivex/rxjava3/core/Single;
      39: areturn

  public static io.reactivex.rxjava3.core.Completable unsafeCreate(io.reactivex.rxjava3.core.CompletableSource);
    Code:
       0: aload_0
       1: ldc           #38                 // String onSubscribe is null
       3: invokestatic  #3                  // Method java/util/Objects.requireNonNull:(Ljava/lang/Object;Ljava/lang/String;)Ljava/lang/Object;
       6: pop
       7: aload_0
       8: instanceof    #39                 // class io/reactivex/rxjava3/core/Completable
      11: ifeq          24
      14: new           #40                 // class java/lang/IllegalArgumentException
      17: dup
      18: ldc           #41                 // String Use of unsafeCreate(Completable)!
      20: invokespecial #42                 // Method java/lang/IllegalArgumentException."<init>":(Ljava/lang/String;)V
      23: athrow
      24: new           #43                 // class io/reactivex/rxjava3/internal/operators/completable/CompletableFromUnsafeSource
      27: dup
      28: aload_0
      29: invokespecial #44                 // Method io/reactivex/rxjava3/internal/operators/completable/CompletableFromUnsafeSource."<init>":(Lio/reactivex/rxjava3/core/CompletableSource;)V
      32: invokestatic  #8                  // Method io/reactivex/rxjava3/plugins/RxJavaPlugins.onAssembly:(Lio/reactivex/rxjava3/core/Completable;)Lio/reactivex/rxjava3/core/Completable;
      35: areturn

  public static io.reactivex.rxjava3.core.Completable defer(io.reactivex.rxjava3.functions.Supplier<? extends io.reactivex.rxjava3.core.CompletableSource>);
    Code:
       0: aload_0
       1: ldc           #45                 // String supplier is null
       3: invokestatic  #3                  // Method java/util/Objects.requireNonNull:(Ljava/lang/Object;Ljava/lang/String;)Ljava/lang/Object;
       6: pop
       7: new           #46                 // class io/reactivex/rxjava3/internal/operators/completable/CompletableDefer
      10: dup
      11: aload_0
      12: invokespecial #47                 // Method io/reactivex/rxjava3/internal/operators/completable/CompletableDefer."<init>":(Lio/reactivex/rxjava3/functions/Supplier;)V
      15: invokestatic  #8                  // Method io/reactivex/rxjava3/plugins/RxJavaPlugins.onAssembly:(Lio/reactivex/rxjava3/core/Completable;)Lio/reactivex/rxjava3/core/Completable;
      18: areturn

  public static io.reactivex.rxjava3.core.Completable error(io.reactivex.rxjava3.functions.Supplier<? extends java.lang.Throwable>);
    Code:
       0: aload_0
       1: ldc           #45                 // String supplier is null
       3: invokestatic  #3                  // Method java/util/Objects.requireNonNull:(Ljava/lang/Object;Ljava/lang/String;)Ljava/lang/Object;
       6: pop
       7: new           #48                 // class io/reactivex/rxjava3/internal/operators/completable/CompletableErrorSupplier
      10: dup
      11: aload_0
      12: invokespecial #49                 // Method io/reactivex/rxjava3/internal/operators/completable/CompletableErrorSupplier."<init>":(Lio/reactivex/rxjava3/functions/Supplier;)V
      15: invokestatic  #8                  // Method io/reactivex/rxjava3/plugins/RxJavaPlugins.onAssembly:(Lio/reactivex/rxjava3/core/Completable;)Lio/reactivex/rxjava3/core/Completable;
      18: areturn

  public static io.reactivex.rxjava3.core.Completable error(java.lang.Throwable);
    Code:
       0: aload_0
       1: ldc           #50                 // String throwable is null
       3: invokestatic  #3                  // Method java/util/Objects.requireNonNull:(Ljava/lang/Object;Ljava/lang/String;)Ljava/lang/Object;
       6: pop
       7: new           #51                 // class io/reactivex/rxjava3/internal/operators/completable/CompletableError
      10: dup
      11: aload_0
      12: invokespecial #52                 // Method io/reactivex/rxjava3/internal/operators/completable/CompletableError."<init>":(Ljava/lang/Throwable;)V
      15: invokestatic  #8                  // Method io/reactivex/rxjava3/plugins/RxJavaPlugins.onAssembly:(Lio/reactivex/rxjava3/core/Completable;)Lio/reactivex/rxjava3/core/Completable;
      18: areturn

  public static io.reactivex.rxjava3.core.Completable fromAction(io.reactivex.rxjava3.functions.Action);
    Code:
       0: aload_0
       1: ldc           #53                 // String action is null
       3: invokestatic  #3                  // Method java/util/Objects.requireNonNull:(Ljava/lang/Object;Ljava/lang/String;)Ljava/lang/Object;
       6: pop
       7: new           #54                 // class io/reactivex/rxjava3/internal/operators/completable/CompletableFromAction
      10: dup
      11: aload_0
      12: invokespecial #55                 // Method io/reactivex/rxjava3/internal/operators/completable/CompletableFromAction."<init>":(Lio/reactivex/rxjava3/functions/Action;)V
      15: invokestatic  #8                  // Method io/reactivex/rxjava3/plugins/RxJavaPlugins.onAssembly:(Lio/reactivex/rxjava3/core/Completable;)Lio/reactivex/rxjava3/core/Completable;
      18: areturn

  public static io.reactivex.rxjava3.core.Completable fromCallable(java.util.concurrent.Callable<?>);
    Code:
       0: aload_0
       1: ldc           #56                 // String callable is null
       3: invokestatic  #3                  // Method java/util/Objects.requireNonNull:(Ljava/lang/Object;Ljava/lang/String;)Ljava/lang/Object;
       6: pop
       7: new           #57                 // class io/reactivex/rxjava3/internal/operators/completable/CompletableFromCallable
      10: dup
      11: aload_0
      12: invokespecial #58                 // Method io/reactivex/rxjava3/internal/operators/completable/CompletableFromCallable."<init>":(Ljava/util/concurrent/Callable;)V
      15: invokestatic  #8                  // Method io/reactivex/rxjava3/plugins/RxJavaPlugins.onAssembly:(Lio/reactivex/rxjava3/core/Completable;)Lio/reactivex/rxjava3/core/Completable;
      18: areturn

  public static io.reactivex.rxjava3.core.Completable fromFuture(java.util.concurrent.Future<?>);
    Code:
       0: aload_0
       1: ldc           #59                 // String future is null
       3: invokestatic  #3                  // Method java/util/Objects.requireNonNull:(Ljava/lang/Object;Ljava/lang/String;)Ljava/lang/Object;
       6: pop
       7: aload_0
       8: invokestatic  #60                 // Method io/reactivex/rxjava3/internal/functions/Functions.futureAction:(Ljava/util/concurrent/Future;)Lio/reactivex/rxjava3/functions/Action;
      11: invokestatic  #61                 // Method fromAction:(Lio/reactivex/rxjava3/functions/Action;)Lio/reactivex/rxjava3/core/Completable;
      14: areturn

  public static <T> io.reactivex.rxjava3.core.Completable fromMaybe(io.reactivex.rxjava3.core.MaybeSource<T>);
    Code:
       0: aload_0
       1: ldc           #62                 // String maybe is null
       3: invokestatic  #3                  // Method java/util/Objects.requireNonNull:(Ljava/lang/Object;Ljava/lang/String;)Ljava/lang/Object;
       6: pop
       7: new           #63                 // class io/reactivex/rxjava3/internal/operators/maybe/MaybeIgnoreElementCompletable
      10: dup
      11: aload_0
      12: invokespecial #64                 // Method io/reactivex/rxjava3/internal/operators/maybe/MaybeIgnoreElementCompletable."<init>":(Lio/reactivex/rxjava3/core/MaybeSource;)V
      15: invokestatic  #8                  // Method io/reactivex/rxjava3/plugins/RxJavaPlugins.onAssembly:(Lio/reactivex/rxjava3/core/Completable;)Lio/reactivex/rxjava3/core/Completable;
      18: areturn

  public static io.reactivex.rxjava3.core.Completable fromRunnable(java.lang.Runnable);
    Code:
       0: aload_0
       1: ldc           #65                 // String run is null
       3: invokestatic  #3                  // Method java/util/Objects.requireNonNull:(Ljava/lang/Object;Ljava/lang/String;)Ljava/lang/Object;
       6: pop
       7: new           #66                 // class io/reactivex/rxjava3/internal/operators/completable/CompletableFromRunnable
      10: dup
      11: aload_0
      12: invokespecial #67                 // Method io/reactivex/rxjava3/internal/operators/completable/CompletableFromRunnable."<init>":(Ljava/lang/Runnable;)V
      15: invokestatic  #8                  // Method io/reactivex/rxjava3/plugins/RxJavaPlugins.onAssembly:(Lio/reactivex/rxjava3/core/Completable;)Lio/reactivex/rxjava3/core/Completable;
      18: areturn

  public static <T> io.reactivex.rxjava3.core.Completable fromObservable(io.reactivex.rxjava3.core.ObservableSource<T>);
    Code:
       0: aload_0
       1: ldc           #68                 // String observable is null
       3: invokestatic  #3                  // Method java/util/Objects.requireNonNull:(Ljava/lang/Object;Ljava/lang/String;)Ljava/lang/Object;
       6: pop
       7: new           #69                 // class io/reactivex/rxjava3/internal/operators/completable/CompletableFromObservable
      10: dup
      11: aload_0
      12: invokespecial #70                 // Method io/reactivex/rxjava3/internal/operators/completable/CompletableFromObservable."<init>":(Lio/reactivex/rxjava3/core/ObservableSource;)V
      15: invokestatic  #8                  // Method io/reactivex/rxjava3/plugins/RxJavaPlugins.onAssembly:(Lio/reactivex/rxjava3/core/Completable;)Lio/reactivex/rxjava3/core/Completable;
      18: areturn

  public static <T> io.reactivex.rxjava3.core.Completable fromPublisher(org.reactivestreams.Publisher<T>);
    Code:
       0: aload_0
       1: ldc           #71                 // String publisher is null
       3: invokestatic  #3                  // Method java/util/Objects.requireNonNull:(Ljava/lang/Object;Ljava/lang/String;)Ljava/lang/Object;
       6: pop
       7: new           #72                 // class io/reactivex/rxjava3/internal/operators/completable/CompletableFromPublisher
      10: dup
      11: aload_0
      12: invokespecial #73                 // Method io/reactivex/rxjava3/internal/operators/completable/CompletableFromPublisher."<init>":(Lorg/reactivestreams/Publisher;)V
      15: invokestatic  #8                  // Method io/reactivex/rxjava3/plugins/RxJavaPlugins.onAssembly:(Lio/reactivex/rxjava3/core/Completable;)Lio/reactivex/rxjava3/core/Completable;
      18: areturn

  public static <T> io.reactivex.rxjava3.core.Completable fromSingle(io.reactivex.rxjava3.core.SingleSource<T>);
    Code:
       0: aload_0
       1: ldc           #74                 // String single is null
       3: invokestatic  #3                  // Method java/util/Objects.requireNonNull:(Ljava/lang/Object;Ljava/lang/String;)Ljava/lang/Object;
       6: pop
       7: new           #75                 // class io/reactivex/rxjava3/internal/operators/completable/CompletableFromSingle
      10: dup
      11: aload_0
      12: invokespecial #76                 // Method io/reactivex/rxjava3/internal/operators/completable/CompletableFromSingle."<init>":(Lio/reactivex/rxjava3/core/SingleSource;)V
      15: invokestatic  #8                  // Method io/reactivex/rxjava3/plugins/RxJavaPlugins.onAssembly:(Lio/reactivex/rxjava3/core/Completable;)Lio/reactivex/rxjava3/core/Completable;
      18: areturn

  public static io.reactivex.rxjava3.core.Completable fromSupplier(io.reactivex.rxjava3.functions.Supplier<?>);
    Code:
       0: aload_0
       1: ldc           #45                 // String supplier is null
       3: invokestatic  #3                  // Method java/util/Objects.requireNonNull:(Ljava/lang/Object;Ljava/lang/String;)Ljava/lang/Object;
       6: pop
       7: new           #77                 // class io/reactivex/rxjava3/internal/operators/completable/CompletableFromSupplier
      10: dup
      11: aload_0
      12: invokespecial #78                 // Method io/reactivex/rxjava3/internal/operators/completable/CompletableFromSupplier."<init>":(Lio/reactivex/rxjava3/functions/Supplier;)V
      15: invokestatic  #8                  // Method io/reactivex/rxjava3/plugins/RxJavaPlugins.onAssembly:(Lio/reactivex/rxjava3/core/Completable;)Lio/reactivex/rxjava3/core/Completable;
      18: areturn

  public static io.reactivex.rxjava3.core.Completable mergeArray(io.reactivex.rxjava3.core.CompletableSource...);
    Code:
       0: aload_0
       1: ldc           #2                  // String sources is null
       3: invokestatic  #3                  // Method java/util/Objects.requireNonNull:(Ljava/lang/Object;Ljava/lang/String;)Ljava/lang/Object;
       6: pop
       7: aload_0
       8: arraylength
       9: ifne          16
      12: invokestatic  #4                  // Method complete:()Lio/reactivex/rxjava3/core/Completable;
      15: areturn
      16: aload_0
      17: arraylength
      18: iconst_1
      19: if_icmpne     29
      22: aload_0
      23: iconst_0
      24: aaload
      25: invokestatic  #5                  // Method wrap:(Lio/reactivex/rxjava3/core/CompletableSource;)Lio/reactivex/rxjava3/core/Completable;
      28: areturn
      29: new           #79                 // class io/reactivex/rxjava3/internal/operators/completable/CompletableMergeArray
      32: dup
      33: aload_0
      34: invokespecial #80                 // Method io/reactivex/rxjava3/internal/operators/completable/CompletableMergeArray."<init>":([Lio/reactivex/rxjava3/core/CompletableSource;)V
      37: invokestatic  #8                  // Method io/reactivex/rxjava3/plugins/RxJavaPlugins.onAssembly:(Lio/reactivex/rxjava3/core/Completable;)Lio/reactivex/rxjava3/core/Completable;
      40: areturn

  public static io.reactivex.rxjava3.core.Completable merge(java.lang.Iterable<? extends io.reactivex.rxjava3.core.CompletableSource>);
    Code:
       0: aload_0
       1: ldc           #2                  // String sources is null
       3: invokestatic  #3                  // Method java/util/Objects.requireNonNull:(Ljava/lang/Object;Ljava/lang/String;)Ljava/lang/Object;
       6: pop
       7: new           #81                 // class io/reactivex/rxjava3/internal/operators/completable/CompletableMergeIterable
      10: dup
      11: aload_0
      12: invokespecial #82                 // Method io/reactivex/rxjava3/internal/operators/completable/CompletableMergeIterable."<init>":(Ljava/lang/Iterable;)V
      15: invokestatic  #8                  // Method io/reactivex/rxjava3/plugins/RxJavaPlugins.onAssembly:(Lio/reactivex/rxjava3/core/Completable;)Lio/reactivex/rxjava3/core/Completable;
      18: areturn

  public static io.reactivex.rxjava3.core.Completable merge(org.reactivestreams.Publisher<? extends io.reactivex.rxjava3.core.CompletableSource>);
    Code:
       0: aload_0
       1: ldc           #84                 // int 2147483647
       3: iconst_0
       4: invokestatic  #85                 // Method merge0:(Lorg/reactivestreams/Publisher;IZ)Lio/reactivex/rxjava3/core/Completable;
       7: areturn

  public static io.reactivex.rxjava3.core.Completable merge(org.reactivestreams.Publisher<? extends io.reactivex.rxjava3.core.CompletableSource>, int);
    Code:
       0: aload_0
       1: iload_1
       2: iconst_0
       3: invokestatic  #85                 // Method merge0:(Lorg/reactivestreams/Publisher;IZ)Lio/reactivex/rxjava3/core/Completable;
       6: areturn

  private static io.reactivex.rxjava3.core.Completable merge0(org.reactivestreams.Publisher<? extends io.reactivex.rxjava3.core.CompletableSource>, int, boolean);
    Code:
       0: aload_0
       1: ldc           #2                  // String sources is null
       3: invokestatic  #3                  // Method java/util/Objects.requireNonNull:(Ljava/lang/Object;Ljava/lang/String;)Ljava/lang/Object;
       6: pop
       7: iload_1
       8: ldc           #86                 // String maxConcurrency
      10: invokestatic  #19                 // Method io/reactivex/rxjava3/internal/functions/ObjectHelper.verifyPositive:(ILjava/lang/String;)I
      13: pop
      14: new           #87                 // class io/reactivex/rxjava3/internal/operators/completable/CompletableMerge
      17: dup
      18: aload_0
      19: iload_1
      20: iload_2
      21: invokespecial #88                 // Method io/reactivex/rxjava3/internal/operators/completable/CompletableMerge."<init>":(Lorg/reactivestreams/Publisher;IZ)V
      24: invokestatic  #8                  // Method io/reactivex/rxjava3/plugins/RxJavaPlugins.onAssembly:(Lio/reactivex/rxjava3/core/Completable;)Lio/reactivex/rxjava3/core/Completable;
      27: areturn

  public static io.reactivex.rxjava3.core.Completable mergeArrayDelayError(io.reactivex.rxjava3.core.CompletableSource...);
    Code:
       0: aload_0
       1: ldc           #2                  // String sources is null
       3: invokestatic  #3                  // Method java/util/Objects.requireNonNull:(Ljava/lang/Object;Ljava/lang/String;)Ljava/lang/Object;
       6: pop
       7: new           #89                 // class io/reactivex/rxjava3/internal/operators/completable/CompletableMergeArrayDelayError
      10: dup
      11: aload_0
      12: invokespecial #90                 // Method io/reactivex/rxjava3/internal/operators/completable/CompletableMergeArrayDelayError."<init>":([Lio/reactivex/rxjava3/core/CompletableSource;)V
      15: invokestatic  #8                  // Method io/reactivex/rxjava3/plugins/RxJavaPlugins.onAssembly:(Lio/reactivex/rxjava3/core/Completable;)Lio/reactivex/rxjava3/core/Completable;
      18: areturn

  public static io.reactivex.rxjava3.core.Completable mergeDelayError(java.lang.Iterable<? extends io.reactivex.rxjava3.core.CompletableSource>);
    Code:
       0: aload_0
       1: ldc           #2                  // String sources is null
       3: invokestatic  #3                  // Method java/util/Objects.requireNonNull:(Ljava/lang/Object;Ljava/lang/String;)Ljava/lang/Object;
       6: pop
       7: new           #91                 // class io/reactivex/rxjava3/internal/operators/completable/CompletableMergeDelayErrorIterable
      10: dup
      11: aload_0
      12: invokespecial #92                 // Method io/reactivex/rxjava3/internal/operators/completable/CompletableMergeDelayErrorIterable."<init>":(Ljava/lang/Iterable;)V
      15: invokestatic  #8                  // Method io/reactivex/rxjava3/plugins/RxJavaPlugins.onAssembly:(Lio/reactivex/rxjava3/core/Completable;)Lio/reactivex/rxjava3/core/Completable;
      18: areturn

  public static io.reactivex.rxjava3.core.Completable mergeDelayError(org.reactivestreams.Publisher<? extends io.reactivex.rxjava3.core.CompletableSource>);
    Code:
       0: aload_0
       1: ldc           #84                 // int 2147483647
       3: iconst_1
       4: invokestatic  #85                 // Method merge0:(Lorg/reactivestreams/Publisher;IZ)Lio/reactivex/rxjava3/core/Completable;
       7: areturn

  public static io.reactivex.rxjava3.core.Completable mergeDelayError(org.reactivestreams.Publisher<? extends io.reactivex.rxjava3.core.CompletableSource>, int);
    Code:
       0: aload_0
       1: iload_1
       2: iconst_1
       3: invokestatic  #85                 // Method merge0:(Lorg/reactivestreams/Publisher;IZ)Lio/reactivex/rxjava3/core/Completable;
       6: areturn

  public static io.reactivex.rxjava3.core.Completable never();
    Code:
       0: getstatic     #93                 // Field io/reactivex/rxjava3/internal/operators/completable/CompletableNever.INSTANCE:Lio/reactivex/rxjava3/core/Completable;
       3: invokestatic  #8                  // Method io/reactivex/rxjava3/plugins/RxJavaPlugins.onAssembly:(Lio/reactivex/rxjava3/core/Completable;)Lio/reactivex/rxjava3/core/Completable;
       6: areturn

  public static io.reactivex.rxjava3.core.Completable timer(long, java.util.concurrent.TimeUnit);
    Code:
       0: lload_0
       1: aload_2
       2: invokestatic  #94                 // Method io/reactivex/rxjava3/schedulers/Schedulers.computation:()Lio/reactivex/rxjava3/core/Scheduler;
       5: invokestatic  #95                 // Method timer:(JLjava/util/concurrent/TimeUnit;Lio/reactivex/rxjava3/core/Scheduler;)Lio/reactivex/rxjava3/core/Completable;
       8: areturn

  public static io.reactivex.rxjava3.core.Completable timer(long, java.util.concurrent.TimeUnit, io.reactivex.rxjava3.core.Scheduler);
    Code:
       0: aload_2
       1: ldc           #96                 // String unit is null
       3: invokestatic  #3                  // Method java/util/Objects.requireNonNull:(Ljava/lang/Object;Ljava/lang/String;)Ljava/lang/Object;
       6: pop
       7: aload_3
       8: ldc           #97                 // String scheduler is null
      10: invokestatic  #3                  // Method java/util/Objects.requireNonNull:(Ljava/lang/Object;Ljava/lang/String;)Ljava/lang/Object;
      13: pop
      14: new           #98                 // class io/reactivex/rxjava3/internal/operators/completable/CompletableTimer
      17: dup
      18: lload_0
      19: aload_2
      20: aload_3
      21: invokespecial #99                 // Method io/reactivex/rxjava3/internal/operators/completable/CompletableTimer."<init>":(JLjava/util/concurrent/TimeUnit;Lio/reactivex/rxjava3/core/Scheduler;)V
      24: invokestatic  #8                  // Method io/reactivex/rxjava3/plugins/RxJavaPlugins.onAssembly:(Lio/reactivex/rxjava3/core/Completable;)Lio/reactivex/rxjava3/core/Completable;
      27: areturn

  private static java.lang.NullPointerException toNpe(java.lang.Throwable);
    Code:
       0: new           #100                // class java/lang/NullPointerException
       3: dup
       4: ldc           #101                // String Actually not, but can\'t pass out an exception otherwise...
       6: invokespecial #102                // Method java/lang/NullPointerException."<init>":(Ljava/lang/String;)V
       9: astore_1
      10: aload_1
      11: aload_0
      12: invokevirtual #103                // Method java/lang/NullPointerException.initCause:(Ljava/lang/Throwable;)Ljava/lang/Throwable;
      15: pop
      16: aload_1
      17: areturn

  public static io.reactivex.rxjava3.core.Completable switchOnNext(org.reactivestreams.Publisher<? extends io.reactivex.rxjava3.core.CompletableSource>);
    Code:
       0: aload_0
       1: ldc           #2                  // String sources is null
       3: invokestatic  #3                  // Method java/util/Objects.requireNonNull:(Ljava/lang/Object;Ljava/lang/String;)Ljava/lang/Object;
       6: pop
       7: new           #104                // class io/reactivex/rxjava3/internal/operators/mixed/FlowableSwitchMapCompletablePublisher
      10: dup
      11: aload_0
      12: invokestatic  #105                // Method io/reactivex/rxjava3/internal/functions/Functions.identity:()Lio/reactivex/rxjava3/functions/Function;
      15: iconst_0
      16: invokespecial #106                // Method io/reactivex/rxjava3/internal/operators/mixed/FlowableSwitchMapCompletablePublisher."<init>":(Lorg/reactivestreams/Publisher;Lio/reactivex/rxjava3/functions/Function;Z)V
      19: invokestatic  #8                  // Method io/reactivex/rxjava3/plugins/RxJavaPlugins.onAssembly:(Lio/reactivex/rxjava3/core/Completable;)Lio/reactivex/rxjava3/core/Completable;
      22: areturn

  public static io.reactivex.rxjava3.core.Completable switchOnNextDelayError(org.reactivestreams.Publisher<? extends io.reactivex.rxjava3.core.CompletableSource>);
    Code:
       0: aload_0
       1: ldc           #2                  // String sources is null
       3: invokestatic  #3                  // Method java/util/Objects.requireNonNull:(Ljava/lang/Object;Ljava/lang/String;)Ljava/lang/Object;
       6: pop
       7: new           #104                // class io/reactivex/rxjava3/internal/operators/mixed/FlowableSwitchMapCompletablePublisher
      10: dup
      11: aload_0
      12: invokestatic  #107                // Method io/reactivex/rxjava3/internal/functions/Functions.identity:()Lio/reactivex/rxjava3/functions/Function;
      15: iconst_1
      16: invokespecial #106                // Method io/reactivex/rxjava3/internal/operators/mixed/FlowableSwitchMapCompletablePublisher."<init>":(Lorg/reactivestreams/Publisher;Lio/reactivex/rxjava3/functions/Function;Z)V
      19: invokestatic  #8                  // Method io/reactivex/rxjava3/plugins/RxJavaPlugins.onAssembly:(Lio/reactivex/rxjava3/core/Completable;)Lio/reactivex/rxjava3/core/Completable;
      22: areturn

  public static <R> io.reactivex.rxjava3.core.Completable using(io.reactivex.rxjava3.functions.Supplier<R>, io.reactivex.rxjava3.functions.Function<? super R, ? extends io.reactivex.rxjava3.core.CompletableSource>, io.reactivex.rxjava3.functions.Consumer<? super R>);
    Code:
       0: aload_0
       1: aload_1
       2: aload_2
       3: iconst_1
       4: invokestatic  #108                // Method using:(Lio/reactivex/rxjava3/functions/Supplier;Lio/reactivex/rxjava3/functions/Function;Lio/reactivex/rxjava3/functions/Consumer;Z)Lio/reactivex/rxjava3/core/Completable;
       7: areturn

  public static <R> io.reactivex.rxjava3.core.Completable using(io.reactivex.rxjava3.functions.Supplier<R>, io.reactivex.rxjava3.functions.Function<? super R, ? extends io.reactivex.rxjava3.core.CompletableSource>, io.reactivex.rxjava3.functions.Consumer<? super R>, boolean);
    Code:
       0: aload_0
       1: ldc           #109                // String resourceSupplier is null
       3: invokestatic  #3                  // Method java/util/Objects.requireNonNull:(Ljava/lang/Object;Ljava/lang/String;)Ljava/lang/Object;
       6: pop
       7: aload_1
       8: ldc           #110                // String sourceSupplier is null
      10: invokestatic  #3                  // Method java/util/Objects.requireNonNull:(Ljava/lang/Object;Ljava/lang/String;)Ljava/lang/Object;
      13: pop
      14: aload_2
      15: ldc           #111                // String resourceCleanup is null
      17: invokestatic  #3                  // Method java/util/Objects.requireNonNull:(Ljava/lang/Object;Ljava/lang/String;)Ljava/lang/Object;
      20: pop
      21: new           #112                // class io/reactivex/rxjava3/internal/operators/completable/CompletableUsing
      24: dup
      25: aload_0
      26: aload_1
      27: aload_2
      28: iload_3
      29: invokespecial #113                // Method io/reactivex/rxjava3/internal/operators/completable/CompletableUsing."<init>":(Lio/reactivex/rxjava3/functions/Supplier;Lio/reactivex/rxjava3/functions/Function;Lio/reactivex/rxjava3/functions/Consumer;Z)V
      32: invokestatic  #8                  // Method io/reactivex/rxjava3/plugins/RxJavaPlugins.onAssembly:(Lio/reactivex/rxjava3/core/Completable;)Lio/reactivex/rxjava3/core/Completable;
      35: areturn

  public static io.reactivex.rxjava3.core.Completable wrap(io.reactivex.rxjava3.core.CompletableSource);
    Code:
       0: aload_0
       1: ldc           #28                 // String source is null
       3: invokestatic  #3                  // Method java/util/Objects.requireNonNull:(Ljava/lang/Object;Ljava/lang/String;)Ljava/lang/Object;
       6: pop
       7: aload_0
       8: instanceof    #39                 // class io/reactivex/rxjava3/core/Completable
      11: ifeq          22
      14: aload_0
      15: checkcast     #39                 // class io/reactivex/rxjava3/core/Completable
      18: invokestatic  #8                  // Method io/reactivex/rxjava3/plugins/RxJavaPlugins.onAssembly:(Lio/reactivex/rxjava3/core/Completable;)Lio/reactivex/rxjava3/core/Completable;
      21: areturn
      22: new           #43                 // class io/reactivex/rxjava3/internal/operators/completable/CompletableFromUnsafeSource
      25: dup
      26: aload_0
      27: invokespecial #44                 // Method io/reactivex/rxjava3/internal/operators/completable/CompletableFromUnsafeSource."<init>":(Lio/reactivex/rxjava3/core/CompletableSource;)V
      30: invokestatic  #8                  // Method io/reactivex/rxjava3/plugins/RxJavaPlugins.onAssembly:(Lio/reactivex/rxjava3/core/Completable;)Lio/reactivex/rxjava3/core/Completable;
      33: areturn

  public final io.reactivex.rxjava3.core.Completable ambWith(io.reactivex.rxjava3.core.CompletableSource);
    Code:
       0: aload_1
       1: ldc           #114                // String other is null
       3: invokestatic  #3                  // Method java/util/Objects.requireNonNull:(Ljava/lang/Object;Ljava/lang/String;)Ljava/lang/Object;
       6: pop
       7: iconst_2
       8: anewarray     #115                // class io/reactivex/rxjava3/core/CompletableSource
      11: dup
      12: iconst_0
      13: aload_0
      14: aastore
      15: dup
      16: iconst_1
      17: aload_1
      18: aastore
      19: invokestatic  #116                // Method ambArray:([Lio/reactivex/rxjava3/core/CompletableSource;)Lio/reactivex/rxjava3/core/Completable;
      22: areturn

  public final <T> io.reactivex.rxjava3.core.Observable<T> andThen(io.reactivex.rxjava3.core.ObservableSource<T>);
    Code:
       0: aload_1
       1: ldc           #117                // String next is null
       3: invokestatic  #3                  // Method java/util/Objects.requireNonNull:(Ljava/lang/Object;Ljava/lang/String;)Ljava/lang/Object;
       6: pop
       7: new           #118                // class io/reactivex/rxjava3/internal/operators/mixed/CompletableAndThenObservable
      10: dup
      11: aload_0
      12: aload_1
      13: invokespecial #119                // Method io/reactivex/rxjava3/internal/operators/mixed/CompletableAndThenObservable."<init>":(Lio/reactivex/rxjava3/core/CompletableSource;Lio/reactivex/rxjava3/core/ObservableSource;)V
      16: invokestatic  #120                // Method io/reactivex/rxjava3/plugins/RxJavaPlugins.onAssembly:(Lio/reactivex/rxjava3/core/Observable;)Lio/reactivex/rxjava3/core/Observable;
      19: areturn

  public final <T> io.reactivex.rxjava3.core.Flowable<T> andThen(org.reactivestreams.Publisher<T>);
    Code:
       0: aload_1
       1: ldc           #117                // String next is null
       3: invokestatic  #3                  // Method java/util/Objects.requireNonNull:(Ljava/lang/Object;Ljava/lang/String;)Ljava/lang/Object;
       6: pop
       7: new           #121                // class io/reactivex/rxjava3/internal/operators/mixed/CompletableAndThenPublisher
      10: dup
      11: aload_0
      12: aload_1
      13: invokespecial #122                // Method io/reactivex/rxjava3/internal/operators/mixed/CompletableAndThenPublisher."<init>":(Lio/reactivex/rxjava3/core/CompletableSource;Lorg/reactivestreams/Publisher;)V
      16: invokestatic  #123                // Method io/reactivex/rxjava3/plugins/RxJavaPlugins.onAssembly:(Lio/reactivex/rxjava3/core/Flowable;)Lio/reactivex/rxjava3/core/Flowable;
      19: areturn

  public final <T> io.reactivex.rxjava3.core.Single<T> andThen(io.reactivex.rxjava3.core.SingleSource<T>);
    Code:
       0: aload_1
       1: ldc           #117                // String next is null
       3: invokestatic  #3                  // Method java/util/Objects.requireNonNull:(Ljava/lang/Object;Ljava/lang/String;)Ljava/lang/Object;
       6: pop
       7: new           #124                // class io/reactivex/rxjava3/internal/operators/single/SingleDelayWithCompletable
      10: dup
      11: aload_1
      12: aload_0
      13: invokespecial #125                // Method io/reactivex/rxjava3/internal/operators/single/SingleDelayWithCompletable."<init>":(Lio/reactivex/rxjava3/core/SingleSource;Lio/reactivex/rxjava3/core/CompletableSource;)V
      16: invokestatic  #126                // Method io/reactivex/rxjava3/plugins/RxJavaPlugins.onAssembly:(Lio/reactivex/rxjava3/core/Single;)Lio/reactivex/rxjava3/core/Single;
      19: areturn

  public final <T> io.reactivex.rxjava3.core.Maybe<T> andThen(io.reactivex.rxjava3.core.MaybeSource<T>);
    Code:
       0: aload_1
       1: ldc           #117                // String next is null
       3: invokestatic  #3                  // Method java/util/Objects.requireNonNull:(Ljava/lang/Object;Ljava/lang/String;)Ljava/lang/Object;
       6: pop
       7: new           #127                // class io/reactivex/rxjava3/internal/operators/maybe/MaybeDelayWithCompletable
      10: dup
      11: aload_1
      12: aload_0
      13: invokespecial #128                // Method io/reactivex/rxjava3/internal/operators/maybe/MaybeDelayWithCompletable."<init>":(Lio/reactivex/rxjava3/core/MaybeSource;Lio/reactivex/rxjava3/core/CompletableSource;)V
      16: invokestatic  #129                // Method io/reactivex/rxjava3/plugins/RxJavaPlugins.onAssembly:(Lio/reactivex/rxjava3/core/Maybe;)Lio/reactivex/rxjava3/core/Maybe;
      19: areturn

  public final io.reactivex.rxjava3.core.Completable andThen(io.reactivex.rxjava3.core.CompletableSource);
    Code:
       0: aload_1
       1: ldc           #117                // String next is null
       3: invokestatic  #3                  // Method java/util/Objects.requireNonNull:(Ljava/lang/Object;Ljava/lang/String;)Ljava/lang/Object;
       6: pop
       7: new           #130                // class io/reactivex/rxjava3/internal/operators/completable/CompletableAndThenCompletable
      10: dup
      11: aload_0
      12: aload_1
      13: invokespecial #131                // Method io/reactivex/rxjava3/internal/operators/completable/CompletableAndThenCompletable."<init>":(Lio/reactivex/rxjava3/core/CompletableSource;Lio/reactivex/rxjava3/core/CompletableSource;)V
      16: invokestatic  #8                  // Method io/reactivex/rxjava3/plugins/RxJavaPlugins.onAssembly:(Lio/reactivex/rxjava3/core/Completable;)Lio/reactivex/rxjava3/core/Completable;
      19: areturn

  public final void blockingAwait();
    Code:
       0: new           #132                // class io/reactivex/rxjava3/internal/observers/BlockingMultiObserver
       3: dup
       4: invokespecial #133                // Method io/reactivex/rxjava3/internal/observers/BlockingMultiObserver."<init>":()V
       7: astore_1
       8: aload_0
       9: aload_1
      10: invokevirtual #134                // Method subscribe:(Lio/reactivex/rxjava3/core/CompletableObserver;)V
      13: aload_1
      14: invokevirtual #135                // Method io/reactivex/rxjava3/internal/observers/BlockingMultiObserver.blockingGet:()Ljava/lang/Object;
      17: pop
      18: return

  public final boolean blockingAwait(long, java.util.concurrent.TimeUnit);
    Code:
       0: aload_3
       1: ldc           #96                 // String unit is null
       3: invokestatic  #3                  // Method java/util/Objects.requireNonNull:(Ljava/lang/Object;Ljava/lang/String;)Ljava/lang/Object;
       6: pop
       7: new           #132                // class io/reactivex/rxjava3/internal/observers/BlockingMultiObserver
      10: dup
      11: invokespecial #133                // Method io/reactivex/rxjava3/internal/observers/BlockingMultiObserver."<init>":()V
      14: astore        4
      16: aload_0
      17: aload         4
      19: invokevirtual #134                // Method subscribe:(Lio/reactivex/rxjava3/core/CompletableObserver;)V
      22: aload         4
      24: lload_1
      25: aload_3
      26: invokevirtual #136                // Method io/reactivex/rxjava3/internal/observers/BlockingMultiObserver.blockingAwait:(JLjava/util/concurrent/TimeUnit;)Z
      29: ireturn

  public final void blockingSubscribe();
    Code:
       0: aload_0
       1: getstatic     #137                // Field io/reactivex/rxjava3/internal/functions/Functions.EMPTY_ACTION:Lio/reactivex/rxjava3/functions/Action;
       4: getstatic     #138                // Field io/reactivex/rxjava3/internal/functions/Functions.ERROR_CONSUMER:Lio/reactivex/rxjava3/functions/Consumer;
       7: invokevirtual #139                // Method blockingSubscribe:(Lio/reactivex/rxjava3/functions/Action;Lio/reactivex/rxjava3/functions/Consumer;)V
      10: return

  public final void blockingSubscribe(io.reactivex.rxjava3.functions.Action);
    Code:
       0: aload_0
       1: aload_1
       2: getstatic     #138                // Field io/reactivex/rxjava3/internal/functions/Functions.ERROR_CONSUMER:Lio/reactivex/rxjava3/functions/Consumer;
       5: invokevirtual #139                // Method blockingSubscribe:(Lio/reactivex/rxjava3/functions/Action;Lio/reactivex/rxjava3/functions/Consumer;)V
       8: return

  public final void blockingSubscribe(io.reactivex.rxjava3.functions.Action, io.reactivex.rxjava3.functions.Consumer<? super java.lang.Throwable>);
    Code:
       0: aload_1
       1: ldc           #140                // String onComplete is null
       3: invokestatic  #3                  // Method java/util/Objects.requireNonNull:(Ljava/lang/Object;Ljava/lang/String;)Ljava/lang/Object;
       6: pop
       7: aload_2
       8: ldc           #141                // String onError is null
      10: invokestatic  #3                  // Method java/util/Objects.requireNonNull:(Ljava/lang/Object;Ljava/lang/String;)Ljava/lang/Object;
      13: pop
      14: new           #132                // class io/reactivex/rxjava3/internal/observers/BlockingMultiObserver
      17: dup
      18: invokespecial #133                // Method io/reactivex/rxjava3/internal/observers/BlockingMultiObserver."<init>":()V
      21: astore_3
      22: aload_0
      23: aload_3
      24: invokevirtual #134                // Method subscribe:(Lio/reactivex/rxjava3/core/CompletableObserver;)V
      27: aload_3
      28: invokestatic  #142                // Method io/reactivex/rxjava3/internal/functions/Functions.emptyConsumer:()Lio/reactivex/rxjava3/functions/Consumer;
      31: aload_2
      32: aload_1
      33: invokevirtual #143                // Method io/reactivex/rxjava3/internal/observers/BlockingMultiObserver.blockingConsume:(Lio/reactivex/rxjava3/functions/Consumer;Lio/reactivex/rxjava3/functions/Consumer;Lio/reactivex/rxjava3/functions/Action;)V
      36: return

  public final void blockingSubscribe(io.reactivex.rxjava3.core.CompletableObserver);
    Code:
       0: aload_1
       1: ldc           #144                // String observer is null
       3: invokestatic  #3                  // Method java/util/Objects.requireNonNull:(Ljava/lang/Object;Ljava/lang/String;)Ljava/lang/Object;
       6: pop
       7: new           #145                // class io/reactivex/rxjava3/internal/observers/BlockingDisposableMultiObserver
      10: dup
      11: invokespecial #146                // Method io/reactivex/rxjava3/internal/observers/BlockingDisposableMultiObserver."<init>":()V
      14: astore_2
      15: aload_1
      16: aload_2
      17: invokeinterface #147,  2          // InterfaceMethod io/reactivex/rxjava3/core/CompletableObserver.onSubscribe:(Lio/reactivex/rxjava3/disposables/Disposable;)V
      22: aload_0
      23: aload_2
      24: invokevirtual #134                // Method subscribe:(Lio/reactivex/rxjava3/core/CompletableObserver;)V
      27: aload_2
      28: aload_1
      29: invokevirtual #148                // Method io/reactivex/rxjava3/internal/observers/BlockingDisposableMultiObserver.blockingConsume:(Lio/reactivex/rxjava3/core/CompletableObserver;)V
      32: return

  public final io.reactivex.rxjava3.core.Completable cache();
    Code:
       0: new           #149                // class io/reactivex/rxjava3/internal/operators/completable/CompletableCache
       3: dup
       4: aload_0
       5: invokespecial #150                // Method io/reactivex/rxjava3/internal/operators/completable/CompletableCache."<init>":(Lio/reactivex/rxjava3/core/CompletableSource;)V
       8: invokestatic  #8                  // Method io/reactivex/rxjava3/plugins/RxJavaPlugins.onAssembly:(Lio/reactivex/rxjava3/core/Completable;)Lio/reactivex/rxjava3/core/Completable;
      11: areturn

  public final io.reactivex.rxjava3.core.Completable compose(io.reactivex.rxjava3.core.CompletableTransformer);
    Code:
       0: aload_1
       1: ldc           #151                // String transformer is null
       3: invokestatic  #3                  // Method java/util/Objects.requireNonNull:(Ljava/lang/Object;Ljava/lang/String;)Ljava/lang/Object;
       6: checkcast     #152                // class io/reactivex/rxjava3/core/CompletableTransformer
       9: aload_0
      10: invokeinterface #153,  2          // InterfaceMethod io/reactivex/rxjava3/core/CompletableTransformer.apply:(Lio/reactivex/rxjava3/core/Completable;)Lio/reactivex/rxjava3/core/CompletableSource;
      15: invokestatic  #5                  // Method wrap:(Lio/reactivex/rxjava3/core/CompletableSource;)Lio/reactivex/rxjava3/core/Completable;
      18: areturn

  public final io.reactivex.rxjava3.core.Completable concatWith(io.reactivex.rxjava3.core.CompletableSource);
    Code:
       0: aload_1
       1: ldc           #114                // String other is null
       3: invokestatic  #3                  // Method java/util/Objects.requireNonNull:(Ljava/lang/Object;Ljava/lang/String;)Ljava/lang/Object;
       6: pop
       7: new           #130                // class io/reactivex/rxjava3/internal/operators/completable/CompletableAndThenCompletable
      10: dup
      11: aload_0
      12: aload_1
      13: invokespecial #131                // Method io/reactivex/rxjava3/internal/operators/completable/CompletableAndThenCompletable."<init>":(Lio/reactivex/rxjava3/core/CompletableSource;Lio/reactivex/rxjava3/core/CompletableSource;)V
      16: invokestatic  #8                  // Method io/reactivex/rxjava3/plugins/RxJavaPlugins.onAssembly:(Lio/reactivex/rxjava3/core/Completable;)Lio/reactivex/rxjava3/core/Completable;
      19: areturn

  public final io.reactivex.rxjava3.core.Completable delay(long, java.util.concurrent.TimeUnit);
    Code:
       0: aload_0
       1: lload_1
       2: aload_3
       3: invokestatic  #94                 // Method io/reactivex/rxjava3/schedulers/Schedulers.computation:()Lio/reactivex/rxjava3/core/Scheduler;
       6: iconst_0
       7: invokevirtual #154                // Method delay:(JLjava/util/concurrent/TimeUnit;Lio/reactivex/rxjava3/core/Scheduler;Z)Lio/reactivex/rxjava3/core/Completable;
      10: areturn

  public final io.reactivex.rxjava3.core.Completable delay(long, java.util.concurrent.TimeUnit, io.reactivex.rxjava3.core.Scheduler);
    Code:
       0: aload_0
       1: lload_1
       2: aload_3
       3: aload         4
       5: iconst_0
       6: invokevirtual #154                // Method delay:(JLjava/util/concurrent/TimeUnit;Lio/reactivex/rxjava3/core/Scheduler;Z)Lio/reactivex/rxjava3/core/Completable;
       9: areturn

  public final io.reactivex.rxjava3.core.Completable delay(long, java.util.concurrent.TimeUnit, io.reactivex.rxjava3.core.Scheduler, boolean);
    Code:
       0: aload_3
       1: ldc           #96                 // String unit is null
       3: invokestatic  #3                  // Method java/util/Objects.requireNonNull:(Ljava/lang/Object;Ljava/lang/String;)Ljava/lang/Object;
       6: pop
       7: aload         4
       9: ldc           #97                 // String scheduler is null
      11: invokestatic  #3                  // Method java/util/Objects.requireNonNull:(Ljava/lang/Object;Ljava/lang/String;)Ljava/lang/Object;
      14: pop
      15: new           #155                // class io/reactivex/rxjava3/internal/operators/completable/CompletableDelay
      18: dup
      19: aload_0
      20: lload_1
      21: aload_3
      22: aload         4
      24: iload         5
      26: invokespecial #156                // Method io/reactivex/rxjava3/internal/operators/completable/CompletableDelay."<init>":(Lio/reactivex/rxjava3/core/CompletableSource;JLjava/util/concurrent/TimeUnit;Lio/reactivex/rxjava3/core/Scheduler;Z)V
      29: invokestatic  #8                  // Method io/reactivex/rxjava3/plugins/RxJavaPlugins.onAssembly:(Lio/reactivex/rxjava3/core/Completable;)Lio/reactivex/rxjava3/core/Completable;
      32: areturn

  public final io.reactivex.rxjava3.core.Completable delaySubscription(long, java.util.concurrent.TimeUnit);
    Code:
       0: aload_0
       1: lload_1
       2: aload_3
       3: invokestatic  #94                 // Method io/reactivex/rxjava3/schedulers/Schedulers.computation:()Lio/reactivex/rxjava3/core/Scheduler;
       6: invokevirtual #157                // Method delaySubscription:(JLjava/util/concurrent/TimeUnit;Lio/reactivex/rxjava3/core/Scheduler;)Lio/reactivex/rxjava3/core/Completable;
       9: areturn

  public final io.reactivex.rxjava3.core.Completable delaySubscription(long, java.util.concurrent.TimeUnit, io.reactivex.rxjava3.core.Scheduler);
    Code:
       0: lload_1
       1: aload_3
       2: aload         4
       4: invokestatic  #95                 // Method timer:(JLjava/util/concurrent/TimeUnit;Lio/reactivex/rxjava3/core/Scheduler;)Lio/reactivex/rxjava3/core/Completable;
       7: aload_0
       8: invokevirtual #158                // Method andThen:(Lio/reactivex/rxjava3/core/CompletableSource;)Lio/reactivex/rxjava3/core/Completable;
      11: areturn

  public final io.reactivex.rxjava3.core.Completable doOnComplete(io.reactivex.rxjava3.functions.Action);
    Code:
       0: aload_0
       1: invokestatic  #142                // Method io/reactivex/rxjava3/internal/functions/Functions.emptyConsumer:()Lio/reactivex/rxjava3/functions/Consumer;
       4: invokestatic  #142                // Method io/reactivex/rxjava3/internal/functions/Functions.emptyConsumer:()Lio/reactivex/rxjava3/functions/Consumer;
       7: aload_1
       8: getstatic     #137                // Field io/reactivex/rxjava3/internal/functions/Functions.EMPTY_ACTION:Lio/reactivex/rxjava3/functions/Action;
      11: getstatic     #137                // Field io/reactivex/rxjava3/internal/functions/Functions.EMPTY_ACTION:Lio/reactivex/rxjava3/functions/Action;
      14: getstatic     #137                // Field io/reactivex/rxjava3/internal/functions/Functions.EMPTY_ACTION:Lio/reactivex/rxjava3/functions/Action;
      17: invokespecial #159                // Method doOnLifecycle:(Lio/reactivex/rxjava3/functions/Consumer;Lio/reactivex/rxjava3/functions/Consumer;Lio/reactivex/rxjava3/functions/Action;Lio/reactivex/rxjava3/functions/Action;Lio/reactivex/rxjava3/functions/Action;Lio/reactivex/rxjava3/functions/Action;)Lio/reactivex/rxjava3/core/Completable;
      20: areturn

  public final io.reactivex.rxjava3.core.Completable doOnDispose(io.reactivex.rxjava3.functions.Action);
    Code:
       0: aload_0
       1: invokestatic  #142                // Method io/reactivex/rxjava3/internal/functions/Functions.emptyConsumer:()Lio/reactivex/rxjava3/functions/Consumer;
       4: invokestatic  #142                // Method io/reactivex/rxjava3/internal/functions/Functions.emptyConsumer:()Lio/reactivex/rxjava3/functions/Consumer;
       7: getstatic     #137                // Field io/reactivex/rxjava3/internal/functions/Functions.EMPTY_ACTION:Lio/reactivex/rxjava3/functions/Action;
      10: getstatic     #137                // Field io/reactivex/rxjava3/internal/functions/Functions.EMPTY_ACTION:Lio/reactivex/rxjava3/functions/Action;
      13: getstatic     #137                // Field io/reactivex/rxjava3/internal/functions/Functions.EMPTY_ACTION:Lio/reactivex/rxjava3/functions/Action;
      16: aload_1
      17: invokespecial #159                // Method doOnLifecycle:(Lio/reactivex/rxjava3/functions/Consumer;Lio/reactivex/rxjava3/functions/Consumer;Lio/reactivex/rxjava3/functions/Action;Lio/reactivex/rxjava3/functions/Action;Lio/reactivex/rxjava3/functions/Action;Lio/reactivex/rxjava3/functions/Action;)Lio/reactivex/rxjava3/core/Completable;
      20: areturn

  public final io.reactivex.rxjava3.core.Completable doOnError(io.reactivex.rxjava3.functions.Consumer<? super java.lang.Throwable>);
    Code:
       0: aload_0
       1: invokestatic  #142                // Method io/reactivex/rxjava3/internal/functions/Functions.emptyConsumer:()Lio/reactivex/rxjava3/functions/Consumer;
       4: aload_1
       5: getstatic     #137                // Field io/reactivex/rxjava3/internal/functions/Functions.EMPTY_ACTION:Lio/reactivex/rxjava3/functions/Action;
       8: getstatic     #137                // Field io/reactivex/rxjava3/internal/functions/Functions.EMPTY_ACTION:Lio/reactivex/rxjava3/functions/Action;
      11: getstatic     #137                // Field io/reactivex/rxjava3/internal/functions/Functions.EMPTY_ACTION:Lio/reactivex/rxjava3/functions/Action;
      14: getstatic     #137                // Field io/reactivex/rxjava3/internal/functions/Functions.EMPTY_ACTION:Lio/reactivex/rxjava3/functions/Action;
      17: invokespecial #159                // Method doOnLifecycle:(Lio/reactivex/rxjava3/functions/Consumer;Lio/reactivex/rxjava3/functions/Consumer;Lio/reactivex/rxjava3/functions/Action;Lio/reactivex/rxjava3/functions/Action;Lio/reactivex/rxjava3/functions/Action;Lio/reactivex/rxjava3/functions/Action;)Lio/reactivex/rxjava3/core/Completable;
      20: areturn

  public final io.reactivex.rxjava3.core.Completable doOnEvent(io.reactivex.rxjava3.functions.Consumer<? super java.lang.Throwable>);
    Code:
       0: aload_1
       1: ldc           #160                // String onEvent is null
       3: invokestatic  #3                  // Method java/util/Objects.requireNonNull:(Ljava/lang/Object;Ljava/lang/String;)Ljava/lang/Object;
       6: pop
       7: new           #161                // class io/reactivex/rxjava3/internal/operators/completable/CompletableDoOnEvent
      10: dup
      11: aload_0
      12: aload_1
      13: invokespecial #162                // Method io/reactivex/rxjava3/internal/operators/completable/CompletableDoOnEvent."<init>":(Lio/reactivex/rxjava3/core/CompletableSource;Lio/reactivex/rxjava3/functions/Consumer;)V
      16: invokestatic  #8                  // Method io/reactivex/rxjava3/plugins/RxJavaPlugins.onAssembly:(Lio/reactivex/rxjava3/core/Completable;)Lio/reactivex/rxjava3/core/Completable;
      19: areturn

  public final io.reactivex.rxjava3.core.Completable doOnLifecycle(io.reactivex.rxjava3.functions.Consumer<? super io.reactivex.rxjava3.disposables.Disposable>, io.reactivex.rxjava3.functions.Action);
    Code:
       0: aload_0
       1: aload_1
       2: invokestatic  #142                // Method io/reactivex/rxjava3/internal/functions/Functions.emptyConsumer:()Lio/reactivex/rxjava3/functions/Consumer;
       5: getstatic     #137                // Field io/reactivex/rxjava3/internal/functions/Functions.EMPTY_ACTION:Lio/reactivex/rxjava3/functions/Action;
       8: getstatic     #137                // Field io/reactivex/rxjava3/internal/functions/Functions.EMPTY_ACTION:Lio/reactivex/rxjava3/functions/Action;
      11: getstatic     #137                // Field io/reactivex/rxjava3/internal/functions/Functions.EMPTY_ACTION:Lio/reactivex/rxjava3/functions/Action;
      14: aload_2
      15: invokespecial #159                // Method doOnLifecycle:(Lio/reactivex/rxjava3/functions/Consumer;Lio/reactivex/rxjava3/functions/Consumer;Lio/reactivex/rxjava3/functions/Action;Lio/reactivex/rxjava3/functions/Action;Lio/reactivex/rxjava3/functions/Action;Lio/reactivex/rxjava3/functions/Action;)Lio/reactivex/rxjava3/core/Completable;
      18: areturn

  private io.reactivex.rxjava3.core.Completable doOnLifecycle(io.reactivex.rxjava3.functions.Consumer<? super io.reactivex.rxjava3.disposables.Disposable>, io.reactivex.rxjava3.functions.Consumer<? super java.lang.Throwable>, io.reactivex.rxjava3.functions.Action, io.reactivex.rxjava3.functions.Action, io.reactivex.rxjava3.functions.Action, io.reactivex.rxjava3.functions.Action);
    Code:
       0: aload_1
       1: ldc           #38                 // String onSubscribe is null
       3: invokestatic  #3                  // Method java/util/Objects.requireNonNull:(Ljava/lang/Object;Ljava/lang/String;)Ljava/lang/Object;
       6: pop
       7: aload_2
       8: ldc           #141                // String onError is null
      10: invokestatic  #3                  // Method java/util/Objects.requireNonNull:(Ljava/lang/Object;Ljava/lang/String;)Ljava/lang/Object;
      13: pop
      14: aload_3
      15: ldc           #140                // String onComplete is null
      17: invokestatic  #3                  // Method java/util/Objects.requireNonNull:(Ljava/lang/Object;Ljava/lang/String;)Ljava/lang/Object;
      20: pop
      21: aload         4
      23: ldc           #163                // String onTerminate is null
      25: invokestatic  #3                  // Method java/util/Objects.requireNonNull:(Ljava/lang/Object;Ljava/lang/String;)Ljava/lang/Object;
      28: pop
      29: aload         5
      31: ldc           #164                // String onAfterTerminate is null
      33: invokestatic  #3                  // Method java/util/Objects.requireNonNull:(Ljava/lang/Object;Ljava/lang/String;)Ljava/lang/Object;
      36: pop
      37: aload         6
      39: ldc           #165                // String onDispose is null
      41: invokestatic  #3                  // Method java/util/Objects.requireNonNull:(Ljava/lang/Object;Ljava/lang/String;)Ljava/lang/Object;
      44: pop
      45: new           #166                // class io/reactivex/rxjava3/internal/operators/completable/CompletablePeek
      48: dup
      49: aload_0
      50: aload_1
      51: aload_2
      52: aload_3
      53: aload         4
      55: aload         5
      57: aload         6
      59: invokespecial #167                // Method io/reactivex/rxjava3/internal/operators/completable/CompletablePeek."<init>":(Lio/reactivex/rxjava3/core/CompletableSource;Lio/reactivex/rxjava3/functions/Consumer;Lio/reactivex/rxjava3/functions/Consumer;Lio/reactivex/rxjava3/functions/Action;Lio/reactivex/rxjava3/functions/Action;Lio/reactivex/rxjava3/functions/Action;Lio/reactivex/rxjava3/functions/Action;)V
      62: invokestatic  #8                  // Method io/reactivex/rxjava3/plugins/RxJavaPlugins.onAssembly:(Lio/reactivex/rxjava3/core/Completable;)Lio/reactivex/rxjava3/core/Completable;
      65: areturn

  public final io.reactivex.rxjava3.core.Completable doOnSubscribe(io.reactivex.rxjava3.functions.Consumer<? super io.reactivex.rxjava3.disposables.Disposable>);
    Code:
       0: aload_0
       1: aload_1
       2: invokestatic  #142                // Method io/reactivex/rxjava3/internal/functions/Functions.emptyConsumer:()Lio/reactivex/rxjava3/functions/Consumer;
       5: getstatic     #137                // Field io/reactivex/rxjava3/internal/functions/Functions.EMPTY_ACTION:Lio/reactivex/rxjava3/functions/Action;
       8: getstatic     #137                // Field io/reactivex/rxjava3/internal/functions/Functions.EMPTY_ACTION:Lio/reactivex/rxjava3/functions/Action;
      11: getstatic     #137                // Field io/reactivex/rxjava3/internal/functions/Functions.EMPTY_ACTION:Lio/reactivex/rxjava3/functions/Action;
      14: getstatic     #137                // Field io/reactivex/rxjava3/internal/functions/Functions.EMPTY_ACTION:Lio/reactivex/rxjava3/functions/Action;
      17: invokespecial #159                // Method doOnLifecycle:(Lio/reactivex/rxjava3/functions/Consumer;Lio/reactivex/rxjava3/functions/Consumer;Lio/reactivex/rxjava3/functions/Action;Lio/reactivex/rxjava3/functions/Action;Lio/reactivex/rxjava3/functions/Action;Lio/reactivex/rxjava3/functions/Action;)Lio/reactivex/rxjava3/core/Completable;
      20: areturn

  public final io.reactivex.rxjava3.core.Completable doOnTerminate(io.reactivex.rxjava3.functions.Action);
    Code:
       0: aload_0
       1: invokestatic  #142                // Method io/reactivex/rxjava3/internal/functions/Functions.emptyConsumer:()Lio/reactivex/rxjava3/functions/Consumer;
       4: invokestatic  #142                // Method io/reactivex/rxjava3/internal/functions/Functions.emptyConsumer:()Lio/reactivex/rxjava3/functions/Consumer;
       7: getstatic     #137                // Field io/reactivex/rxjava3/internal/functions/Functions.EMPTY_ACTION:Lio/reactivex/rxjava3/functions/Action;
      10: aload_1
      11: getstatic     #137                // Field io/reactivex/rxjava3/internal/functions/Functions.EMPTY_ACTION:Lio/reactivex/rxjava3/functions/Action;
      14: getstatic     #137                // Field io/reactivex/rxjava3/internal/functions/Functions.EMPTY_ACTION:Lio/reactivex/rxjava3/functions/Action;
      17: invokespecial #159                // Method doOnLifecycle:(Lio/reactivex/rxjava3/functions/Consumer;Lio/reactivex/rxjava3/functions/Consumer;Lio/reactivex/rxjava3/functions/Action;Lio/reactivex/rxjava3/functions/Action;Lio/reactivex/rxjava3/functions/Action;Lio/reactivex/rxjava3/functions/Action;)Lio/reactivex/rxjava3/core/Completable;
      20: areturn

  public final io.reactivex.rxjava3.core.Completable doAfterTerminate(io.reactivex.rxjava3.functions.Action);
    Code:
       0: aload_0
       1: invokestatic  #142                // Method io/reactivex/rxjava3/internal/functions/Functions.emptyConsumer:()Lio/reactivex/rxjava3/functions/Consumer;
       4: invokestatic  #142                // Method io/reactivex/rxjava3/internal/functions/Functions.emptyConsumer:()Lio/reactivex/rxjava3/functions/Consumer;
       7: getstatic     #137                // Field io/reactivex/rxjava3/internal/functions/Functions.EMPTY_ACTION:Lio/reactivex/rxjava3/functions/Action;
      10: getstatic     #137                // Field io/reactivex/rxjava3/internal/functions/Functions.EMPTY_ACTION:Lio/reactivex/rxjava3/functions/Action;
      13: aload_1
      14: getstatic     #137                // Field io/reactivex/rxjava3/internal/functions/Functions.EMPTY_ACTION:Lio/reactivex/rxjava3/functions/Action;
      17: invokespecial #159                // Method doOnLifecycle:(Lio/reactivex/rxjava3/functions/Consumer;Lio/reactivex/rxjava3/functions/Consumer;Lio/reactivex/rxjava3/functions/Action;Lio/reactivex/rxjava3/functions/Action;Lio/reactivex/rxjava3/functions/Action;Lio/reactivex/rxjava3/functions/Action;)Lio/reactivex/rxjava3/core/Completable;
      20: areturn

  public final io.reactivex.rxjava3.core.Completable doFinally(io.reactivex.rxjava3.functions.Action);
    Code:
       0: aload_1
       1: ldc           #168                // String onFinally is null
       3: invokestatic  #3                  // Method java/util/Objects.requireNonNull:(Ljava/lang/Object;Ljava/lang/String;)Ljava/lang/Object;
       6: pop
       7: new           #169                // class io/reactivex/rxjava3/internal/operators/completable/CompletableDoFinally
      10: dup
      11: aload_0
      12: aload_1
      13: invokespecial #170                // Method io/reactivex/rxjava3/internal/operators/completable/CompletableDoFinally."<init>":(Lio/reactivex/rxjava3/core/CompletableSource;Lio/reactivex/rxjava3/functions/Action;)V
      16: invokestatic  #8                  // Method io/reactivex/rxjava3/plugins/RxJavaPlugins.onAssembly:(Lio/reactivex/rxjava3/core/Completable;)Lio/reactivex/rxjava3/core/Completable;
      19: areturn

  public final io.reactivex.rxjava3.core.Completable lift(io.reactivex.rxjava3.core.CompletableOperator);
    Code:
       0: aload_1
       1: ldc           #171                // String onLift is null
       3: invokestatic  #3                  // Method java/util/Objects.requireNonNull:(Ljava/lang/Object;Ljava/lang/String;)Ljava/lang/Object;
       6: pop
       7: new           #172                // class io/reactivex/rxjava3/internal/operators/completable/CompletableLift
      10: dup
      11: aload_0
      12: aload_1
      13: invokespecial #173                // Method io/reactivex/rxjava3/internal/operators/completable/CompletableLift."<init>":(Lio/reactivex/rxjava3/core/CompletableSource;Lio/reactivex/rxjava3/core/CompletableOperator;)V
      16: invokestatic  #8                  // Method io/reactivex/rxjava3/plugins/RxJavaPlugins.onAssembly:(Lio/reactivex/rxjava3/core/Completable;)Lio/reactivex/rxjava3/core/Completable;
      19: areturn

  public final <T> io.reactivex.rxjava3.core.Single<io.reactivex.rxjava3.core.Notification<T>> materialize();
    Code:
       0: new           #174                // class io/reactivex/rxjava3/internal/operators/completable/CompletableMaterialize
       3: dup
       4: aload_0
       5: invokespecial #175                // Method io/reactivex/rxjava3/internal/operators/completable/CompletableMaterialize."<init>":(Lio/reactivex/rxjava3/core/Completable;)V
       8: invokestatic  #176                // Method io/reactivex/rxjava3/plugins/RxJavaPlugins.onAssembly:(Lio/reactivex/rxjava3/core/Single;)Lio/reactivex/rxjava3/core/Single;
      11: areturn

  public final io.reactivex.rxjava3.core.Completable mergeWith(io.reactivex.rxjava3.core.CompletableSource);
    Code:
       0: aload_1
       1: ldc           #114                // String other is null
       3: invokestatic  #3                  // Method java/util/Objects.requireNonNull:(Ljava/lang/Object;Ljava/lang/String;)Ljava/lang/Object;
       6: pop
       7: iconst_2
       8: anewarray     #177                // class io/reactivex/rxjava3/core/CompletableSource
      11: dup
      12: iconst_0
      13: aload_0
      14: aastore
      15: dup
      16: iconst_1
      17: aload_1
      18: aastore
      19: invokestatic  #178                // Method mergeArray:([Lio/reactivex/rxjava3/core/CompletableSource;)Lio/reactivex/rxjava3/core/Completable;
      22: areturn

  public final io.reactivex.rxjava3.core.Completable observeOn(io.reactivex.rxjava3.core.Scheduler);
    Code:
       0: aload_1
       1: ldc           #97                 // String scheduler is null
       3: invokestatic  #3                  // Method java/util/Objects.requireNonNull:(Ljava/lang/Object;Ljava/lang/String;)Ljava/lang/Object;
       6: pop
       7: new           #179                // class io/reactivex/rxjava3/internal/operators/completable/CompletableObserveOn
      10: dup
      11: aload_0
      12: aload_1
      13: invokespecial #180                // Method io/reactivex/rxjava3/internal/operators/completable/CompletableObserveOn."<init>":(Lio/reactivex/rxjava3/core/CompletableSource;Lio/reactivex/rxjava3/core/Scheduler;)V
      16: invokestatic  #8                  // Method io/reactivex/rxjava3/plugins/RxJavaPlugins.onAssembly:(Lio/reactivex/rxjava3/core/Completable;)Lio/reactivex/rxjava3/core/Completable;
      19: areturn

  public final io.reactivex.rxjava3.core.Completable onErrorComplete();
    Code:
       0: aload_0
       1: invokestatic  #181                // Method io/reactivex/rxjava3/internal/functions/Functions.alwaysTrue:()Lio/reactivex/rxjava3/functions/Predicate;
       4: invokevirtual #182                // Method onErrorComplete:(Lio/reactivex/rxjava3/functions/Predicate;)Lio/reactivex/rxjava3/core/Completable;
       7: areturn

  public final io.reactivex.rxjava3.core.Completable onErrorComplete(io.reactivex.rxjava3.functions.Predicate<? super java.lang.Throwable>);
    Code:
       0: aload_1
       1: ldc           #183                // String predicate is null
       3: invokestatic  #3                  // Method java/util/Objects.requireNonNull:(Ljava/lang/Object;Ljava/lang/String;)Ljava/lang/Object;
       6: pop
       7: new           #184                // class io/reactivex/rxjava3/internal/operators/completable/CompletableOnErrorComplete
      10: dup
      11: aload_0
      12: aload_1
      13: invokespecial #185                // Method io/reactivex/rxjava3/internal/operators/completable/CompletableOnErrorComplete."<init>":(Lio/reactivex/rxjava3/core/CompletableSource;Lio/reactivex/rxjava3/functions/Predicate;)V
      16: invokestatic  #8                  // Method io/reactivex/rxjava3/plugins/RxJavaPlugins.onAssembly:(Lio/reactivex/rxjava3/core/Completable;)Lio/reactivex/rxjava3/core/Completable;
      19: areturn

  public final io.reactivex.rxjava3.core.Completable onErrorResumeNext(io.reactivex.rxjava3.functions.Function<? super java.lang.Throwable, ? extends io.reactivex.rxjava3.core.CompletableSource>);
    Code:
       0: aload_1
       1: ldc           #186                // String fallbackSupplier is null
       3: invokestatic  #3                  // Method java/util/Objects.requireNonNull:(Ljava/lang/Object;Ljava/lang/String;)Ljava/lang/Object;
       6: pop
       7: new           #187                // class io/reactivex/rxjava3/internal/operators/completable/CompletableResumeNext
      10: dup
      11: aload_0
      12: aload_1
      13: invokespecial #188                // Method io/reactivex/rxjava3/internal/operators/completable/CompletableResumeNext."<init>":(Lio/reactivex/rxjava3/core/CompletableSource;Lio/reactivex/rxjava3/functions/Function;)V
      16: invokestatic  #8                  // Method io/reactivex/rxjava3/plugins/RxJavaPlugins.onAssembly:(Lio/reactivex/rxjava3/core/Completable;)Lio/reactivex/rxjava3/core/Completable;
      19: areturn

  public final io.reactivex.rxjava3.core.Completable onErrorResumeWith(io.reactivex.rxjava3.core.CompletableSource);
    Code:
       0: aload_1
       1: ldc           #189                // String fallback is null
       3: invokestatic  #3                  // Method java/util/Objects.requireNonNull:(Ljava/lang/Object;Ljava/lang/String;)Ljava/lang/Object;
       6: pop
       7: aload_0
       8: aload_1
       9: invokestatic  #190                // Method io/reactivex/rxjava3/internal/functions/Functions.justFunction:(Ljava/lang/Object;)Lio/reactivex/rxjava3/functions/Function;
      12: invokevirtual #191                // Method onErrorResumeNext:(Lio/reactivex/rxjava3/functions/Function;)Lio/reactivex/rxjava3/core/Completable;
      15: areturn

  public final <T> io.reactivex.rxjava3.core.Maybe<T> onErrorReturn(io.reactivex.rxjava3.functions.Function<? super java.lang.Throwable, ? extends T>);
    Code:
       0: aload_1
       1: ldc           #192                // String itemSupplier is null
       3: invokestatic  #3                  // Method java/util/Objects.requireNonNull:(Ljava/lang/Object;Ljava/lang/String;)Ljava/lang/Object;
       6: pop
       7: new           #193                // class io/reactivex/rxjava3/internal/operators/completable/CompletableOnErrorReturn
      10: dup
      11: aload_0
      12: aload_1
      13: invokespecial #194                // Method io/reactivex/rxjava3/internal/operators/completable/CompletableOnErrorReturn."<init>":(Lio/reactivex/rxjava3/core/CompletableSource;Lio/reactivex/rxjava3/functions/Function;)V
      16: invokestatic  #195                // Method io/reactivex/rxjava3/plugins/RxJavaPlugins.onAssembly:(Lio/reactivex/rxjava3/core/Maybe;)Lio/reactivex/rxjava3/core/Maybe;
      19: areturn

  public final <T> io.reactivex.rxjava3.core.Maybe<T> onErrorReturnItem(T);
    Code:
       0: aload_1
       1: ldc           #196                // String item is null
       3: invokestatic  #3                  // Method java/util/Objects.requireNonNull:(Ljava/lang/Object;Ljava/lang/String;)Ljava/lang/Object;
       6: pop
       7: aload_0
       8: aload_1
       9: invokestatic  #197                // Method io/reactivex/rxjava3/internal/functions/Functions.justFunction:(Ljava/lang/Object;)Lio/reactivex/rxjava3/functions/Function;
      12: invokevirtual #198                // Method onErrorReturn:(Lio/reactivex/rxjava3/functions/Function;)Lio/reactivex/rxjava3/core/Maybe;
      15: areturn

  public final io.reactivex.rxjava3.core.Completable onTerminateDetach();
    Code:
       0: new           #199                // class io/reactivex/rxjava3/internal/operators/completable/CompletableDetach
       3: dup
       4: aload_0
       5: invokespecial #200                // Method io/reactivex/rxjava3/internal/operators/completable/CompletableDetach."<init>":(Lio/reactivex/rxjava3/core/CompletableSource;)V
       8: invokestatic  #8                  // Method io/reactivex/rxjava3/plugins/RxJavaPlugins.onAssembly:(Lio/reactivex/rxjava3/core/Completable;)Lio/reactivex/rxjava3/core/Completable;
      11: areturn

  public final io.reactivex.rxjava3.core.Completable repeat();
    Code:
       0: aload_0
       1: invokevirtual #201                // Method toFlowable:()Lio/reactivex/rxjava3/core/Flowable;
       4: invokevirtual #202                // Method io/reactivex/rxjava3/core/Flowable.repeat:()Lio/reactivex/rxjava3/core/Flowable;
       7: invokestatic  #203                // Method fromPublisher:(Lorg/reactivestreams/Publisher;)Lio/reactivex/rxjava3/core/Completable;
      10: areturn

  public final io.reactivex.rxjava3.core.Completable repeat(long);
    Code:
       0: aload_0
       1: invokevirtual #204                // Method toFlowable:()Lio/reactivex/rxjava3/core/Flowable;
       4: lload_1
       5: invokevirtual #205                // Method io/reactivex/rxjava3/core/Flowable.repeat:(J)Lio/reactivex/rxjava3/core/Flowable;
       8: invokestatic  #206                // Method fromPublisher:(Lorg/reactivestreams/Publisher;)Lio/reactivex/rxjava3/core/Completable;
      11: areturn

  public final io.reactivex.rxjava3.core.Completable repeatUntil(io.reactivex.rxjava3.functions.BooleanSupplier);
    Code:
       0: aload_0
       1: invokevirtual #207                // Method toFlowable:()Lio/reactivex/rxjava3/core/Flowable;
       4: aload_1
       5: invokevirtual #208                // Method io/reactivex/rxjava3/core/Flowable.repeatUntil:(Lio/reactivex/rxjava3/functions/BooleanSupplier;)Lio/reactivex/rxjava3/core/Flowable;
       8: invokestatic  #209                // Method fromPublisher:(Lorg/reactivestreams/Publisher;)Lio/reactivex/rxjava3/core/Completable;
      11: areturn

  public final io.reactivex.rxjava3.core.Completable repeatWhen(io.reactivex.rxjava3.functions.Function<? super io.reactivex.rxjava3.core.Flowable<java.lang.Object>, ? extends org.reactivestreams.Publisher<?>>);
    Code:
       0: aload_0
       1: invokevirtual #210                // Method toFlowable:()Lio/reactivex/rxjava3/core/Flowable;
       4: aload_1
       5: invokevirtual #211                // Method io/reactivex/rxjava3/core/Flowable.repeatWhen:(Lio/reactivex/rxjava3/functions/Function;)Lio/reactivex/rxjava3/core/Flowable;
       8: invokestatic  #212                // Method fromPublisher:(Lorg/reactivestreams/Publisher;)Lio/reactivex/rxjava3/core/Completable;
      11: areturn

  public final io.reactivex.rxjava3.core.Completable retry();
    Code:
       0: aload_0
       1: invokevirtual #213                // Method toFlowable:()Lio/reactivex/rxjava3/core/Flowable;
       4: invokevirtual #214                // Method io/reactivex/rxjava3/core/Flowable.retry:()Lio/reactivex/rxjava3/core/Flowable;
       7: invokestatic  #215                // Method fromPublisher:(Lorg/reactivestreams/Publisher;)Lio/reactivex/rxjava3/core/Completable;
      10: areturn

  public final io.reactivex.rxjava3.core.Completable retry(io.reactivex.rxjava3.functions.BiPredicate<? super java.lang.Integer, ? super java.lang.Throwable>);
    Code:
       0: aload_0
       1: invokevirtual #216                // Method toFlowable:()Lio/reactivex/rxjava3/core/Flowable;
       4: aload_1
       5: invokevirtual #217                // Method io/reactivex/rxjava3/core/Flowable.retry:(Lio/reactivex/rxjava3/functions/BiPredicate;)Lio/reactivex/rxjava3/core/Flowable;
       8: invokestatic  #218                // Method fromPublisher:(Lorg/reactivestreams/Publisher;)Lio/reactivex/rxjava3/core/Completable;
      11: areturn

  public final io.reactivex.rxjava3.core.Completable retry(long);
    Code:
       0: aload_0
       1: invokevirtual #219                // Method toFlowable:()Lio/reactivex/rxjava3/core/Flowable;
       4: lload_1
       5: invokevirtual #220                // Method io/reactivex/rxjava3/core/Flowable.retry:(J)Lio/reactivex/rxjava3/core/Flowable;
       8: invokestatic  #221                // Method fromPublisher:(Lorg/reactivestreams/Publisher;)Lio/reactivex/rxjava3/core/Completable;
      11: areturn

  public final io.reactivex.rxjava3.core.Completable retry(long, io.reactivex.rxjava3.functions.Predicate<? super java.lang.Throwable>);
    Code:
       0: aload_0
       1: invokevirtual #222                // Method toFlowable:()Lio/reactivex/rxjava3/core/Flowable;
       4: lload_1
       5: aload_3
       6: invokevirtual #223                // Method io/reactivex/rxjava3/core/Flowable.retry:(JLio/reactivex/rxjava3/functions/Predicate;)Lio/reactivex/rxjava3/core/Flowable;
       9: invokestatic  #224                // Method fromPublisher:(Lorg/reactivestreams/Publisher;)Lio/reactivex/rxjava3/core/Completable;
      12: areturn

  public final io.reactivex.rxjava3.core.Completable retry(io.reactivex.rxjava3.functions.Predicate<? super java.lang.Throwable>);
    Code:
       0: aload_0
       1: invokevirtual #225                // Method toFlowable:()Lio/reactivex/rxjava3/core/Flowable;
       4: aload_1
       5: invokevirtual #226                // Method io/reactivex/rxjava3/core/Flowable.retry:(Lio/reactivex/rxjava3/functions/Predicate;)Lio/reactivex/rxjava3/core/Flowable;
       8: invokestatic  #227                // Method fromPublisher:(Lorg/reactivestreams/Publisher;)Lio/reactivex/rxjava3/core/Completable;
      11: areturn

  public final io.reactivex.rxjava3.core.Completable retryUntil(io.reactivex.rxjava3.functions.BooleanSupplier);
    Code:
       0: aload_1
       1: ldc           #228                // String stop is null
       3: invokestatic  #3                  // Method java/util/Objects.requireNonNull:(Ljava/lang/Object;Ljava/lang/String;)Ljava/lang/Object;
       6: pop
       7: aload_0
       8: ldc2_w        #230                // long 9223372036854775807l
      11: aload_1
      12: invokestatic  #232                // Method io/reactivex/rxjava3/internal/functions/Functions.predicateReverseFor:(Lio/reactivex/rxjava3/functions/BooleanSupplier;)Lio/reactivex/rxjava3/functions/Predicate;
      15: invokevirtual #233                // Method retry:(JLio/reactivex/rxjava3/functions/Predicate;)Lio/reactivex/rxjava3/core/Completable;
      18: areturn

  public final io.reactivex.rxjava3.core.Completable retryWhen(io.reactivex.rxjava3.functions.Function<? super io.reactivex.rxjava3.core.Flowable<java.lang.Throwable>, ? extends org.reactivestreams.Publisher<?>>);
    Code:
       0: aload_0
       1: invokevirtual #234                // Method toFlowable:()Lio/reactivex/rxjava3/core/Flowable;
       4: aload_1
       5: invokevirtual #235                // Method io/reactivex/rxjava3/core/Flowable.retryWhen:(Lio/reactivex/rxjava3/functions/Function;)Lio/reactivex/rxjava3/core/Flowable;
       8: invokestatic  #236                // Method fromPublisher:(Lorg/reactivestreams/Publisher;)Lio/reactivex/rxjava3/core/Completable;
      11: areturn

  public final void safeSubscribe(io.reactivex.rxjava3.core.CompletableObserver);
    Code:
       0: aload_1
       1: ldc           #144                // String observer is null
       3: invokestatic  #3                  // Method java/util/Objects.requireNonNull:(Ljava/lang/Object;Ljava/lang/String;)Ljava/lang/Object;
       6: pop
       7: aload_0
       8: new           #237                // class io/reactivex/rxjava3/internal/observers/SafeCompletableObserver
      11: dup
      12: aload_1
      13: invokespecial #238                // Method io/reactivex/rxjava3/internal/observers/SafeCompletableObserver."<init>":(Lio/reactivex/rxjava3/core/CompletableObserver;)V
      16: invokevirtual #134                // Method subscribe:(Lio/reactivex/rxjava3/core/CompletableObserver;)V
      19: return

  public final io.reactivex.rxjava3.core.Completable startWith(io.reactivex.rxjava3.core.CompletableSource);
    Code:
       0: aload_1
       1: ldc           #114                // String other is null
       3: invokestatic  #3                  // Method java/util/Objects.requireNonNull:(Ljava/lang/Object;Ljava/lang/String;)Ljava/lang/Object;
       6: pop
       7: iconst_2
       8: anewarray     #239                // class io/reactivex/rxjava3/core/CompletableSource
      11: dup
      12: iconst_0
      13: aload_1
      14: aastore
      15: dup
      16: iconst_1
      17: aload_0
      18: aastore
      19: invokestatic  #240                // Method concatArray:([Lio/reactivex/rxjava3/core/CompletableSource;)Lio/reactivex/rxjava3/core/Completable;
      22: areturn

  public final <T> io.reactivex.rxjava3.core.Flowable<T> startWith(io.reactivex.rxjava3.core.SingleSource<T>);
    Code:
       0: aload_1
       1: ldc           #114                // String other is null
       3: invokestatic  #3                  // Method java/util/Objects.requireNonNull:(Ljava/lang/Object;Ljava/lang/String;)Ljava/lang/Object;
       6: pop
       7: aload_1
       8: invokestatic  #241                // Method io/reactivex/rxjava3/core/Single.wrap:(Lio/reactivex/rxjava3/core/SingleSource;)Lio/reactivex/rxjava3/core/Single;
      11: invokevirtual #242                // Method io/reactivex/rxjava3/core/Single.toFlowable:()Lio/reactivex/rxjava3/core/Flowable;
      14: aload_0
      15: invokevirtual #243                // Method toFlowable:()Lio/reactivex/rxjava3/core/Flowable;
      18: invokestatic  #244                // Method io/reactivex/rxjava3/core/Flowable.concat:(Lorg/reactivestreams/Publisher;Lorg/reactivestreams/Publisher;)Lio/reactivex/rxjava3/core/Flowable;
      21: areturn

  public final <T> io.reactivex.rxjava3.core.Flowable<T> startWith(io.reactivex.rxjava3.core.MaybeSource<T>);
    Code:
       0: aload_1
       1: ldc           #114                // String other is null
       3: invokestatic  #3                  // Method java/util/Objects.requireNonNull:(Ljava/lang/Object;Ljava/lang/String;)Ljava/lang/Object;
       6: pop
       7: aload_1
       8: invokestatic  #245                // Method io/reactivex/rxjava3/core/Maybe.wrap:(Lio/reactivex/rxjava3/core/MaybeSource;)Lio/reactivex/rxjava3/core/Maybe;
      11: invokevirtual #246                // Method io/reactivex/rxjava3/core/Maybe.toFlowable:()Lio/reactivex/rxjava3/core/Flowable;
      14: aload_0
      15: invokevirtual #247                // Method toFlowable:()Lio/reactivex/rxjava3/core/Flowable;
      18: invokestatic  #248                // Method io/reactivex/rxjava3/core/Flowable.concat:(Lorg/reactivestreams/Publisher;Lorg/reactivestreams/Publisher;)Lio/reactivex/rxjava3/core/Flowable;
      21: areturn

  public final <T> io.reactivex.rxjava3.core.Observable<T> startWith(io.reactivex.rxjava3.core.ObservableSource<T>);
    Code:
       0: aload_1
       1: ldc           #114                // String other is null
       3: invokestatic  #3                  // Method java/util/Objects.requireNonNull:(Ljava/lang/Object;Ljava/lang/String;)Ljava/lang/Object;
       6: pop
       7: aload_1
       8: invokestatic  #249                // Method io/reactivex/rxjava3/core/Observable.wrap:(Lio/reactivex/rxjava3/core/ObservableSource;)Lio/reactivex/rxjava3/core/Observable;
      11: aload_0
      12: invokevirtual #250                // Method toObservable:()Lio/reactivex/rxjava3/core/Observable;
      15: invokevirtual #251                // Method io/reactivex/rxjava3/core/Observable.concatWith:(Lio/reactivex/rxjava3/core/ObservableSource;)Lio/reactivex/rxjava3/core/Observable;
      18: areturn

  public final <T> io.reactivex.rxjava3.core.Flowable<T> startWith(org.reactivestreams.Publisher<T>);
    Code:
       0: aload_1
       1: ldc           #114                // String other is null
       3: invokestatic  #3                  // Method java/util/Objects.requireNonNull:(Ljava/lang/Object;Ljava/lang/String;)Ljava/lang/Object;
       6: pop
       7: aload_0
       8: invokevirtual #252                // Method toFlowable:()Lio/reactivex/rxjava3/core/Flowable;
      11: aload_1
      12: invokevirtual #253                // Method io/reactivex/rxjava3/core/Flowable.startWith:(Lorg/reactivestreams/Publisher;)Lio/reactivex/rxjava3/core/Flowable;
      15: areturn

  public final io.reactivex.rxjava3.core.Completable hide();
    Code:
       0: new           #254                // class io/reactivex/rxjava3/internal/operators/completable/CompletableHide
       3: dup
       4: aload_0
       5: invokespecial #255                // Method io/reactivex/rxjava3/internal/operators/completable/CompletableHide."<init>":(Lio/reactivex/rxjava3/core/CompletableSource;)V
       8: invokestatic  #8                  // Method io/reactivex/rxjava3/plugins/RxJavaPlugins.onAssembly:(Lio/reactivex/rxjava3/core/Completable;)Lio/reactivex/rxjava3/core/Completable;
      11: areturn

  public final io.reactivex.rxjava3.disposables.Disposable subscribe();
    Code:
       0: new           #256                // class io/reactivex/rxjava3/internal/observers/EmptyCompletableObserver
       3: dup
       4: invokespecial #257                // Method io/reactivex/rxjava3/internal/observers/EmptyCompletableObserver."<init>":()V
       7: astore_1
       8: aload_0
       9: aload_1
      10: invokevirtual #134                // Method subscribe:(Lio/reactivex/rxjava3/core/CompletableObserver;)V
      13: aload_1
      14: areturn

  public final void subscribe(io.reactivex.rxjava3.core.CompletableObserver);
    Code:
       0: aload_1
       1: ldc           #144                // String observer is null
       3: invokestatic  #3                  // Method java/util/Objects.requireNonNull:(Ljava/lang/Object;Ljava/lang/String;)Ljava/lang/Object;
       6: pop
       7: aload_0
       8: aload_1
       9: invokestatic  #258                // Method io/reactivex/rxjava3/plugins/RxJavaPlugins.onSubscribe:(Lio/reactivex/rxjava3/core/Completable;Lio/reactivex/rxjava3/core/CompletableObserver;)Lio/reactivex/rxjava3/core/CompletableObserver;
      12: astore_1
      13: aload_1
      14: ldc_w         #259                // String The RxJavaPlugins.onSubscribe hook returned a null CompletableObserver. Please check the handler provided to RxJavaPlugins.setOnCompletableSubscribe for invalid null returns. Further reading: https://github.com/ReactiveX/RxJava/wiki/Plugins
      17: invokestatic  #3                  // Method java/util/Objects.requireNonNull:(Ljava/lang/Object;Ljava/lang/String;)Ljava/lang/Object;
      20: pop
      21: aload_0
      22: aload_1
      23: invokevirtual #260                // Method subscribeActual:(Lio/reactivex/rxjava3/core/CompletableObserver;)V
      26: goto          46
      29: astore_2
      30: aload_2
      31: athrow
      32: astore_2
      33: aload_2
      34: invokestatic  #262                // Method io/reactivex/rxjava3/exceptions/Exceptions.throwIfFatal:(Ljava/lang/Throwable;)V
      37: aload_2
      38: invokestatic  #263                // Method io/reactivex/rxjava3/plugins/RxJavaPlugins.onError:(Ljava/lang/Throwable;)V
      41: aload_2
      42: invokestatic  #264                // Method toNpe:(Ljava/lang/Throwable;)Ljava/lang/NullPointerException;
      45: athrow
      46: return
    Exception table:
       from    to  target type
           7    26    29   Class java/lang/NullPointerException
           7    26    32   Class java/lang/Throwable

  protected abstract void subscribeActual(io.reactivex.rxjava3.core.CompletableObserver);

  public final <E extends io.reactivex.rxjava3.core.CompletableObserver> E subscribeWith(E);
    Code:
       0: aload_0
       1: aload_1
       2: invokevirtual #134                // Method subscribe:(Lio/reactivex/rxjava3/core/CompletableObserver;)V
       5: aload_1
       6: areturn

  public final io.reactivex.rxjava3.disposables.Disposable subscribe(io.reactivex.rxjava3.functions.Action, io.reactivex.rxjava3.functions.Consumer<? super java.lang.Throwable>);
    Code:
       0: aload_2
       1: ldc           #141                // String onError is null
       3: invokestatic  #3                  // Method java/util/Objects.requireNonNull:(Ljava/lang/Object;Ljava/lang/String;)Ljava/lang/Object;
       6: pop
       7: aload_1
       8: ldc           #140                // String onComplete is null
      10: invokestatic  #3                  // Method java/util/Objects.requireNonNull:(Ljava/lang/Object;Ljava/lang/String;)Ljava/lang/Object;
      13: pop
      14: new           #265                // class io/reactivex/rxjava3/internal/observers/CallbackCompletableObserver
      17: dup
      18: aload_2
      19: aload_1
      20: invokespecial #266                // Method io/reactivex/rxjava3/internal/observers/CallbackCompletableObserver."<init>":(Lio/reactivex/rxjava3/functions/Consumer;Lio/reactivex/rxjava3/functions/Action;)V
      23: astore_3
      24: aload_0
      25: aload_3
      26: invokevirtual #134                // Method subscribe:(Lio/reactivex/rxjava3/core/CompletableObserver;)V
      29: aload_3
      30: areturn

  public final io.reactivex.rxjava3.disposables.Disposable subscribe(io.reactivex.rxjava3.functions.Action, io.reactivex.rxjava3.functions.Consumer<? super java.lang.Throwable>, io.reactivex.rxjava3.disposables.DisposableContainer);
    Code:
       0: aload_1
       1: ldc           #140                // String onComplete is null
       3: invokestatic  #3                  // Method java/util/Objects.requireNonNull:(Ljava/lang/Object;Ljava/lang/String;)Ljava/lang/Object;
       6: pop
       7: aload_2
       8: ldc           #141                // String onError is null
      10: invokestatic  #3                  // Method java/util/Objects.requireNonNull:(Ljava/lang/Object;Ljava/lang/String;)Ljava/lang/Object;
      13: pop
      14: aload_3
      15: ldc_w         #267                // String container is null
      18: invokestatic  #3                  // Method java/util/Objects.requireNonNull:(Ljava/lang/Object;Ljava/lang/String;)Ljava/lang/Object;
      21: pop
      22: new           #268                // class io/reactivex/rxjava3/internal/observers/DisposableAutoReleaseMultiObserver
      25: dup
      26: aload_3
      27: invokestatic  #142                // Method io/reactivex/rxjava3/internal/functions/Functions.emptyConsumer:()Lio/reactivex/rxjava3/functions/Consumer;
      30: aload_2
      31: aload_1
      32: invokespecial #269                // Method io/reactivex/rxjava3/internal/observers/DisposableAutoReleaseMultiObserver."<init>":(Lio/reactivex/rxjava3/disposables/DisposableContainer;Lio/reactivex/rxjava3/functions/Consumer;Lio/reactivex/rxjava3/functions/Consumer;Lio/reactivex/rxjava3/functions/Action;)V
      35: astore        4
      37: aload_3
      38: aload         4
      40: invokeinterface #270,  2          // InterfaceMethod io/reactivex/rxjava3/disposables/DisposableContainer.add:(Lio/reactivex/rxjava3/disposables/Disposable;)Z
      45: pop
      46: aload_0
      47: aload         4
      49: invokevirtual #134                // Method subscribe:(Lio/reactivex/rxjava3/core/CompletableObserver;)V
      52: aload         4
      54: areturn

  public final io.reactivex.rxjava3.disposables.Disposable subscribe(io.reactivex.rxjava3.functions.Action);
    Code:
       0: aload_0
       1: aload_1
       2: getstatic     #271                // Field io/reactivex/rxjava3/internal/functions/Functions.ON_ERROR_MISSING:Lio/reactivex/rxjava3/functions/Consumer;
       5: invokevirtual #272                // Method subscribe:(Lio/reactivex/rxjava3/functions/Action;Lio/reactivex/rxjava3/functions/Consumer;)Lio/reactivex/rxjava3/disposables/Disposable;
       8: areturn

  public final io.reactivex.rxjava3.core.Completable subscribeOn(io.reactivex.rxjava3.core.Scheduler);
    Code:
       0: aload_1
       1: ldc           #97                 // String scheduler is null
       3: invokestatic  #3                  // Method java/util/Objects.requireNonNull:(Ljava/lang/Object;Ljava/lang/String;)Ljava/lang/Object;
       6: pop
       7: new           #273                // class io/reactivex/rxjava3/internal/operators/completable/CompletableSubscribeOn
      10: dup
      11: aload_0
      12: aload_1
      13: invokespecial #274                // Method io/reactivex/rxjava3/internal/operators/completable/CompletableSubscribeOn."<init>":(Lio/reactivex/rxjava3/core/CompletableSource;Lio/reactivex/rxjava3/core/Scheduler;)V
      16: invokestatic  #8                  // Method io/reactivex/rxjava3/plugins/RxJavaPlugins.onAssembly:(Lio/reactivex/rxjava3/core/Completable;)Lio/reactivex/rxjava3/core/Completable;
      19: areturn

  public final io.reactivex.rxjava3.core.Completable takeUntil(io.reactivex.rxjava3.core.CompletableSource);
    Code:
       0: aload_1
       1: ldc           #114                // String other is null
       3: invokestatic  #3                  // Method java/util/Objects.requireNonNull:(Ljava/lang/Object;Ljava/lang/String;)Ljava/lang/Object;
       6: pop
       7: new           #275                // class io/reactivex/rxjava3/internal/operators/completable/CompletableTakeUntilCompletable
      10: dup
      11: aload_0
      12: aload_1
      13: invokespecial #276                // Method io/reactivex/rxjava3/internal/operators/completable/CompletableTakeUntilCompletable."<init>":(Lio/reactivex/rxjava3/core/Completable;Lio/reactivex/rxjava3/core/CompletableSource;)V
      16: invokestatic  #8                  // Method io/reactivex/rxjava3/plugins/RxJavaPlugins.onAssembly:(Lio/reactivex/rxjava3/core/Completable;)Lio/reactivex/rxjava3/core/Completable;
      19: areturn

  public final io.reactivex.rxjava3.core.Completable timeout(long, java.util.concurrent.TimeUnit);
    Code:
       0: aload_0
       1: lload_1
       2: aload_3
       3: invokestatic  #94                 // Method io/reactivex/rxjava3/schedulers/Schedulers.computation:()Lio/reactivex/rxjava3/core/Scheduler;
       6: aconst_null
       7: invokespecial #277                // Method timeout0:(JLjava/util/concurrent/TimeUnit;Lio/reactivex/rxjava3/core/Scheduler;Lio/reactivex/rxjava3/core/CompletableSource;)Lio/reactivex/rxjava3/core/Completable;
      10: areturn

  public final io.reactivex.rxjava3.core.Completable timeout(long, java.util.concurrent.TimeUnit, io.reactivex.rxjava3.core.CompletableSource);
    Code:
       0: aload         4
       2: ldc           #189                // String fallback is null
       4: invokestatic  #3                  // Method java/util/Objects.requireNonNull:(Ljava/lang/Object;Ljava/lang/String;)Ljava/lang/Object;
       7: pop
       8: aload_0
       9: lload_1
      10: aload_3
      11: invokestatic  #94                 // Method io/reactivex/rxjava3/schedulers/Schedulers.computation:()Lio/reactivex/rxjava3/core/Scheduler;
      14: aload         4
      16: invokespecial #277                // Method timeout0:(JLjava/util/concurrent/TimeUnit;Lio/reactivex/rxjava3/core/Scheduler;Lio/reactivex/rxjava3/core/CompletableSource;)Lio/reactivex/rxjava3/core/Completable;
      19: areturn

  public final io.reactivex.rxjava3.core.Completable timeout(long, java.util.concurrent.TimeUnit, io.reactivex.rxjava3.core.Scheduler);
    Code:
       0: aload_0
       1: lload_1
       2: aload_3
       3: aload         4
       5: aconst_null
       6: invokespecial #277                // Method timeout0:(JLjava/util/concurrent/TimeUnit;Lio/reactivex/rxjava3/core/Scheduler;Lio/reactivex/rxjava3/core/CompletableSource;)Lio/reactivex/rxjava3/core/Completable;
       9: areturn

  public final io.reactivex.rxjava3.core.Completable timeout(long, java.util.concurrent.TimeUnit, io.reactivex.rxjava3.core.Scheduler, io.reactivex.rxjava3.core.CompletableSource);
    Code:
       0: aload         5
       2: ldc           #189                // String fallback is null
       4: invokestatic  #3                  // Method java/util/Objects.requireNonNull:(Ljava/lang/Object;Ljava/lang/String;)Ljava/lang/Object;
       7: pop
       8: aload_0
       9: lload_1
      10: aload_3
      11: aload         4
      13: aload         5
      15: invokespecial #277                // Method timeout0:(JLjava/util/concurrent/TimeUnit;Lio/reactivex/rxjava3/core/Scheduler;Lio/reactivex/rxjava3/core/CompletableSource;)Lio/reactivex/rxjava3/core/Completable;
      18: areturn

  private io.reactivex.rxjava3.core.Completable timeout0(long, java.util.concurrent.TimeUnit, io.reactivex.rxjava3.core.Scheduler, io.reactivex.rxjava3.core.CompletableSource);
    Code:
       0: aload_3
       1: ldc           #96                 // String unit is null
       3: invokestatic  #3                  // Method java/util/Objects.requireNonNull:(Ljava/lang/Object;Ljava/lang/String;)Ljava/lang/Object;
       6: pop
       7: aload         4
       9: ldc           #97                 // String scheduler is null
      11: invokestatic  #3                  // Method java/util/Objects.requireNonNull:(Ljava/lang/Object;Ljava/lang/String;)Ljava/lang/Object;
      14: pop
      15: new           #278                // class io/reactivex/rxjava3/internal/operators/completable/CompletableTimeout
      18: dup
      19: aload_0
      20: lload_1
      21: aload_3
      22: aload         4
      24: aload         5
      26: invokespecial #279                // Method io/reactivex/rxjava3/internal/operators/completable/CompletableTimeout."<init>":(Lio/reactivex/rxjava3/core/CompletableSource;JLjava/util/concurrent/TimeUnit;Lio/reactivex/rxjava3/core/Scheduler;Lio/reactivex/rxjava3/core/CompletableSource;)V
      29: invokestatic  #8                  // Method io/reactivex/rxjava3/plugins/RxJavaPlugins.onAssembly:(Lio/reactivex/rxjava3/core/Completable;)Lio/reactivex/rxjava3/core/Completable;
      32: areturn

  public final <R> R to(io.reactivex.rxjava3.core.CompletableConverter<? extends R>);
    Code:
       0: aload_1
       1: ldc_w         #280                // String converter is null
       4: invokestatic  #3                  // Method java/util/Objects.requireNonNull:(Ljava/lang/Object;Ljava/lang/String;)Ljava/lang/Object;
       7: checkcast     #281                // class io/reactivex/rxjava3/core/CompletableConverter
      10: aload_0
      11: invokeinterface #282,  2          // InterfaceMethod io/reactivex/rxjava3/core/CompletableConverter.apply:(Lio/reactivex/rxjava3/core/Completable;)Ljava/lang/Object;
      16: areturn

  public final <T> io.reactivex.rxjava3.core.Flowable<T> toFlowable();
    Code:
       0: aload_0
       1: instanceof    #283                // class io/reactivex/rxjava3/internal/fuseable/FuseToFlowable
       4: ifeq          17
       7: aload_0
       8: checkcast     #283                // class io/reactivex/rxjava3/internal/fuseable/FuseToFlowable
      11: invokeinterface #284,  1          // InterfaceMethod io/reactivex/rxjava3/internal/fuseable/FuseToFlowable.fuseToFlowable:()Lio/reactivex/rxjava3/core/Flowable;
      16: areturn
      17: new           #285                // class io/reactivex/rxjava3/internal/operators/completable/CompletableToFlowable
      20: dup
      21: aload_0
      22: invokespecial #286                // Method io/reactivex/rxjava3/internal/operators/completable/CompletableToFlowable."<init>":(Lio/reactivex/rxjava3/core/CompletableSource;)V
      25: invokestatic  #287                // Method io/reactivex/rxjava3/plugins/RxJavaPlugins.onAssembly:(Lio/reactivex/rxjava3/core/Flowable;)Lio/reactivex/rxjava3/core/Flowable;
      28: areturn

  public final java.util.concurrent.Future<java.lang.Void> toFuture();
    Code:
       0: aload_0
       1: new           #288                // class io/reactivex/rxjava3/internal/observers/FutureMultiObserver
       4: dup
       5: invokespecial #289                // Method io/reactivex/rxjava3/internal/observers/FutureMultiObserver."<init>":()V
       8: invokevirtual #290                // Method subscribeWith:(Lio/reactivex/rxjava3/core/CompletableObserver;)Lio/reactivex/rxjava3/core/CompletableObserver;
      11: checkcast     #291                // class java/util/concurrent/Future
      14: areturn

  public final <T> io.reactivex.rxjava3.core.Maybe<T> toMaybe();
    Code:
       0: aload_0
       1: instanceof    #292                // class io/reactivex/rxjava3/internal/fuseable/FuseToMaybe
       4: ifeq          17
       7: aload_0
       8: checkcast     #292                // class io/reactivex/rxjava3/internal/fuseable/FuseToMaybe
      11: invokeinterface #293,  1          // InterfaceMethod io/reactivex/rxjava3/internal/fuseable/FuseToMaybe.fuseToMaybe:()Lio/reactivex/rxjava3/core/Maybe;
      16: areturn
      17: new           #294                // class io/reactivex/rxjava3/internal/operators/maybe/MaybeFromCompletable
      20: dup
      21: aload_0
      22: invokespecial #295                // Method io/reactivex/rxjava3/internal/operators/maybe/MaybeFromCompletable."<init>":(Lio/reactivex/rxjava3/core/CompletableSource;)V
      25: invokestatic  #296                // Method io/reactivex/rxjava3/plugins/RxJavaPlugins.onAssembly:(Lio/reactivex/rxjava3/core/Maybe;)Lio/reactivex/rxjava3/core/Maybe;
      28: areturn

  public final <T> io.reactivex.rxjava3.core.Observable<T> toObservable();
    Code:
       0: aload_0
       1: instanceof    #297                // class io/reactivex/rxjava3/internal/fuseable/FuseToObservable
       4: ifeq          17
       7: aload_0
       8: checkcast     #297                // class io/reactivex/rxjava3/internal/fuseable/FuseToObservable
      11: invokeinterface #298,  1          // InterfaceMethod io/reactivex/rxjava3/internal/fuseable/FuseToObservable.fuseToObservable:()Lio/reactivex/rxjava3/core/Observable;
      16: areturn
      17: new           #299                // class io/reactivex/rxjava3/internal/operators/completable/CompletableToObservable
      20: dup
      21: aload_0
      22: invokespecial #300                // Method io/reactivex/rxjava3/internal/operators/completable/CompletableToObservable."<init>":(Lio/reactivex/rxjava3/core/CompletableSource;)V
      25: invokestatic  #301                // Method io/reactivex/rxjava3/plugins/RxJavaPlugins.onAssembly:(Lio/reactivex/rxjava3/core/Observable;)Lio/reactivex/rxjava3/core/Observable;
      28: areturn

  public final <T> io.reactivex.rxjava3.core.Single<T> toSingle(io.reactivex.rxjava3.functions.Supplier<? extends T>);
    Code:
       0: aload_1
       1: ldc_w         #302                // String completionValueSupplier is null
       4: invokestatic  #3                  // Method java/util/Objects.requireNonNull:(Ljava/lang/Object;Ljava/lang/String;)Ljava/lang/Object;
       7: pop
       8: new           #303                // class io/reactivex/rxjava3/internal/operators/completable/CompletableToSingle
      11: dup
      12: aload_0
      13: aload_1
      14: aconst_null
      15: invokespecial #304                // Method io/reactivex/rxjava3/internal/operators/completable/CompletableToSingle."<init>":(Lio/reactivex/rxjava3/core/CompletableSource;Lio/reactivex/rxjava3/functions/Supplier;Ljava/lang/Object;)V
      18: invokestatic  #305                // Method io/reactivex/rxjava3/plugins/RxJavaPlugins.onAssembly:(Lio/reactivex/rxjava3/core/Single;)Lio/reactivex/rxjava3/core/Single;
      21: areturn

  public final <T> io.reactivex.rxjava3.core.Single<T> toSingleDefault(T);
    Code:
       0: aload_1
       1: ldc_w         #306                // String completionValue is null
       4: invokestatic  #3                  // Method java/util/Objects.requireNonNull:(Ljava/lang/Object;Ljava/lang/String;)Ljava/lang/Object;
       7: pop
       8: new           #303                // class io/reactivex/rxjava3/internal/operators/completable/CompletableToSingle
      11: dup
      12: aload_0
      13: aconst_null
      14: aload_1
      15: invokespecial #304                // Method io/reactivex/rxjava3/internal/operators/completable/CompletableToSingle."<init>":(Lio/reactivex/rxjava3/core/CompletableSource;Lio/reactivex/rxjava3/functions/Supplier;Ljava/lang/Object;)V
      18: invokestatic  #307                // Method io/reactivex/rxjava3/plugins/RxJavaPlugins.onAssembly:(Lio/reactivex/rxjava3/core/Single;)Lio/reactivex/rxjava3/core/Single;
      21: areturn

  public final io.reactivex.rxjava3.core.Completable unsubscribeOn(io.reactivex.rxjava3.core.Scheduler);
    Code:
       0: aload_1
       1: ldc           #97                 // String scheduler is null
       3: invokestatic  #3                  // Method java/util/Objects.requireNonNull:(Ljava/lang/Object;Ljava/lang/String;)Ljava/lang/Object;
       6: pop
       7: new           #308                // class io/reactivex/rxjava3/internal/operators/completable/CompletableDisposeOn
      10: dup
      11: aload_0
      12: aload_1
      13: invokespecial #309                // Method io/reactivex/rxjava3/internal/operators/completable/CompletableDisposeOn."<init>":(Lio/reactivex/rxjava3/core/CompletableSource;Lio/reactivex/rxjava3/core/Scheduler;)V
      16: invokestatic  #8                  // Method io/reactivex/rxjava3/plugins/RxJavaPlugins.onAssembly:(Lio/reactivex/rxjava3/core/Completable;)Lio/reactivex/rxjava3/core/Completable;
      19: areturn

  public final io.reactivex.rxjava3.observers.TestObserver<java.lang.Void> test();
    Code:
       0: new           #310                // class io/reactivex/rxjava3/observers/TestObserver
       3: dup
       4: invokespecial #311                // Method io/reactivex/rxjava3/observers/TestObserver."<init>":()V
       7: astore_1
       8: aload_0
       9: aload_1
      10: invokevirtual #134                // Method subscribe:(Lio/reactivex/rxjava3/core/CompletableObserver;)V
      13: aload_1
      14: areturn

  public final io.reactivex.rxjava3.observers.TestObserver<java.lang.Void> test(boolean);
    Code:
       0: new           #310                // class io/reactivex/rxjava3/observers/TestObserver
       3: dup
       4: invokespecial #311                // Method io/reactivex/rxjava3/observers/TestObserver."<init>":()V
       7: astore_2
       8: iload_1
       9: ifeq          16
      12: aload_2
      13: invokevirtual #312                // Method io/reactivex/rxjava3/observers/TestObserver.dispose:()V
      16: aload_0
      17: aload_2
      18: invokevirtual #134                // Method subscribe:(Lio/reactivex/rxjava3/core/CompletableObserver;)V
      21: aload_2
      22: areturn

  public static io.reactivex.rxjava3.core.Completable fromCompletionStage(java.util.concurrent.CompletionStage<?>);
    Code:
       0: aload_0
       1: ldc_w         #313                // String stage is null
       4: invokestatic  #3                  // Method java/util/Objects.requireNonNull:(Ljava/lang/Object;Ljava/lang/String;)Ljava/lang/Object;
       7: pop
       8: new           #314                // class io/reactivex/rxjava3/internal/jdk8/CompletableFromCompletionStage
      11: dup
      12: aload_0
      13: invokespecial #315                // Method io/reactivex/rxjava3/internal/jdk8/CompletableFromCompletionStage."<init>":(Ljava/util/concurrent/CompletionStage;)V
      16: invokestatic  #8                  // Method io/reactivex/rxjava3/plugins/RxJavaPlugins.onAssembly:(Lio/reactivex/rxjava3/core/Completable;)Lio/reactivex/rxjava3/core/Completable;
      19: areturn

  public final <T> java.util.concurrent.CompletionStage<T> toCompletionStage(T);
    Code:
       0: aload_0
       1: new           #316                // class io/reactivex/rxjava3/internal/jdk8/CompletionStageConsumer
       4: dup
       5: iconst_1
       6: aload_1
       7: invokespecial #317                // Method io/reactivex/rxjava3/internal/jdk8/CompletionStageConsumer."<init>":(ZLjava/lang/Object;)V
      10: invokevirtual #290                // Method subscribeWith:(Lio/reactivex/rxjava3/core/CompletableObserver;)Lio/reactivex/rxjava3/core/CompletableObserver;
      13: checkcast     #318                // class java/util/concurrent/CompletionStage
      16: areturn
}
