Compiled from "Maybe.java"
public abstract class io.reactivex.rxjava3.core.Maybe<T> implements io.reactivex.rxjava3.core.MaybeSource<T> {
  public io.reactivex.rxjava3.core.Maybe();
    Code:
       0: aload_0
       1: invokespecial #1                  // Method java/lang/Object."<init>":()V
       4: return

  public static <T> io.reactivex.rxjava3.core.Maybe<T> amb(java.lang.Iterable<? extends io.reactivex.rxjava3.core.MaybeSource<? extends T>>);
    Code:
       0: aload_0
       1: ldc           #2                  // String sources is null
       3: invokestatic  #3                  // Method java/util/Objects.requireNonNull:(Ljava/lang/Object;Ljava/lang/String;)Ljava/lang/Object;
       6: pop
       7: new           #4                  // class io/reactivex/rxjava3/internal/operators/maybe/MaybeAmb
      10: dup
      11: aconst_null
      12: aload_0
      13: invokespecial #5                  // Method io/reactivex/rxjava3/internal/operators/maybe/MaybeAmb."<init>":([Lio/reactivex/rxjava3/core/MaybeSource;Ljava/lang/Iterable;)V
      16: invokestatic  #6                  // Method io/reactivex/rxjava3/plugins/RxJavaPlugins.onAssembly:(Lio/reactivex/rxjava3/core/Maybe;)Lio/reactivex/rxjava3/core/Maybe;
      19: areturn

  public static <T> io.reactivex.rxjava3.core.Maybe<T> ambArray(io.reactivex.rxjava3.core.MaybeSource<? extends T>...);
    Code:
       0: aload_0
       1: ldc           #2                  // String sources is null
       3: invokestatic  #3                  // Method java/util/Objects.requireNonNull:(Ljava/lang/Object;Ljava/lang/String;)Ljava/lang/Object;
       6: pop
       7: aload_0
       8: arraylength
       9: ifne          16
      12: invokestatic  #7                  // Method empty:()Lio/reactivex/rxjava3/core/Maybe;
      15: areturn
      16: aload_0
      17: arraylength
      18: iconst_1
      19: if_icmpne     31
      22: aload_0
      23: iconst_0
      24: aaload
      25: astore_1
      26: aload_1
      27: invokestatic  #8                  // Method wrap:(Lio/reactivex/rxjava3/core/MaybeSource;)Lio/reactivex/rxjava3/core/Maybe;
      30: areturn
      31: new           #4                  // class io/reactivex/rxjava3/internal/operators/maybe/MaybeAmb
      34: dup
      35: aload_0
      36: aconst_null
      37: invokespecial #5                  // Method io/reactivex/rxjava3/internal/operators/maybe/MaybeAmb."<init>":([Lio/reactivex/rxjava3/core/MaybeSource;Ljava/lang/Iterable;)V
      40: invokestatic  #9                  // Method io/reactivex/rxjava3/plugins/RxJavaPlugins.onAssembly:(Lio/reactivex/rxjava3/core/Maybe;)Lio/reactivex/rxjava3/core/Maybe;
      43: areturn

  public static <T> io.reactivex.rxjava3.core.Flowable<T> concat(java.lang.Iterable<? extends io.reactivex.rxjava3.core.MaybeSource<? extends T>>);
    Code:
       0: aload_0
       1: ldc           #2                  // String sources is null
       3: invokestatic  #3                  // Method java/util/Objects.requireNonNull:(Ljava/lang/Object;Ljava/lang/String;)Ljava/lang/Object;
       6: pop
       7: new           #10                 // class io/reactivex/rxjava3/internal/operators/maybe/MaybeConcatIterable
      10: dup
      11: aload_0
      12: invokespecial #11                 // Method io/reactivex/rxjava3/internal/operators/maybe/MaybeConcatIterable."<init>":(Ljava/lang/Iterable;)V
      15: invokestatic  #12                 // Method io/reactivex/rxjava3/plugins/RxJavaPlugins.onAssembly:(Lio/reactivex/rxjava3/core/Flowable;)Lio/reactivex/rxjava3/core/Flowable;
      18: areturn

  public static <T> io.reactivex.rxjava3.core.Flowable<T> concat(io.reactivex.rxjava3.core.MaybeSource<? extends T>, io.reactivex.rxjava3.core.MaybeSource<? extends T>);
    Code:
       0: aload_0
       1: ldc           #13                 // String source1 is null
       3: invokestatic  #3                  // Method java/util/Objects.requireNonNull:(Ljava/lang/Object;Ljava/lang/String;)Ljava/lang/Object;
       6: pop
       7: aload_1
       8: ldc           #14                 // String source2 is null
      10: invokestatic  #3                  // Method java/util/Objects.requireNonNull:(Ljava/lang/Object;Ljava/lang/String;)Ljava/lang/Object;
      13: pop
      14: iconst_2
      15: anewarray     #15                 // class io/reactivex/rxjava3/core/MaybeSource
      18: dup
      19: iconst_0
      20: aload_0
      21: aastore
      22: dup
      23: iconst_1
      24: aload_1
      25: aastore
      26: invokestatic  #16                 // Method concatArray:([Lio/reactivex/rxjava3/core/MaybeSource;)Lio/reactivex/rxjava3/core/Flowable;
      29: areturn

  public static <T> io.reactivex.rxjava3.core.Flowable<T> concat(io.reactivex.rxjava3.core.MaybeSource<? extends T>, io.reactivex.rxjava3.core.MaybeSource<? extends T>, io.reactivex.rxjava3.core.MaybeSource<? extends T>);
    Code:
       0: aload_0
       1: ldc           #13                 // String source1 is null
       3: invokestatic  #3                  // Method java/util/Objects.requireNonNull:(Ljava/lang/Object;Ljava/lang/String;)Ljava/lang/Object;
       6: pop
       7: aload_1
       8: ldc           #14                 // String source2 is null
      10: invokestatic  #3                  // Method java/util/Objects.requireNonNull:(Ljava/lang/Object;Ljava/lang/String;)Ljava/lang/Object;
      13: pop
      14: aload_2
      15: ldc           #17                 // String source3 is null
      17: invokestatic  #3                  // Method java/util/Objects.requireNonNull:(Ljava/lang/Object;Ljava/lang/String;)Ljava/lang/Object;
      20: pop
      21: iconst_3
      22: anewarray     #15                 // class io/reactivex/rxjava3/core/MaybeSource
      25: dup
      26: iconst_0
      27: aload_0
      28: aastore
      29: dup
      30: iconst_1
      31: aload_1
      32: aastore
      33: dup
      34: iconst_2
      35: aload_2
      36: aastore
      37: invokestatic  #18                 // Method concatArray:([Lio/reactivex/rxjava3/core/MaybeSource;)Lio/reactivex/rxjava3/core/Flowable;
      40: areturn

  public static <T> io.reactivex.rxjava3.core.Flowable<T> concat(io.reactivex.rxjava3.core.MaybeSource<? extends T>, io.reactivex.rxjava3.core.MaybeSource<? extends T>, io.reactivex.rxjava3.core.MaybeSource<? extends T>, io.reactivex.rxjava3.core.MaybeSource<? extends T>);
    Code:
       0: aload_0
       1: ldc           #13                 // String source1 is null
       3: invokestatic  #3                  // Method java/util/Objects.requireNonNull:(Ljava/lang/Object;Ljava/lang/String;)Ljava/lang/Object;
       6: pop
       7: aload_1
       8: ldc           #14                 // String source2 is null
      10: invokestatic  #3                  // Method java/util/Objects.requireNonNull:(Ljava/lang/Object;Ljava/lang/String;)Ljava/lang/Object;
      13: pop
      14: aload_2
      15: ldc           #17                 // String source3 is null
      17: invokestatic  #3                  // Method java/util/Objects.requireNonNull:(Ljava/lang/Object;Ljava/lang/String;)Ljava/lang/Object;
      20: pop
      21: aload_3
      22: ldc           #19                 // String source4 is null
      24: invokestatic  #3                  // Method java/util/Objects.requireNonNull:(Ljava/lang/Object;Ljava/lang/String;)Ljava/lang/Object;
      27: pop
      28: iconst_4
      29: anewarray     #15                 // class io/reactivex/rxjava3/core/MaybeSource
      32: dup
      33: iconst_0
      34: aload_0
      35: aastore
      36: dup
      37: iconst_1
      38: aload_1
      39: aastore
      40: dup
      41: iconst_2
      42: aload_2
      43: aastore
      44: dup
      45: iconst_3
      46: aload_3
      47: aastore
      48: invokestatic  #20                 // Method concatArray:([Lio/reactivex/rxjava3/core/MaybeSource;)Lio/reactivex/rxjava3/core/Flowable;
      51: areturn

  public static <T> io.reactivex.rxjava3.core.Flowable<T> concat(org.reactivestreams.Publisher<? extends io.reactivex.rxjava3.core.MaybeSource<? extends T>>);
    Code:
       0: aload_0
       1: iconst_2
       2: invokestatic  #21                 // Method concat:(Lorg/reactivestreams/Publisher;I)Lio/reactivex/rxjava3/core/Flowable;
       5: areturn

  public static <T> io.reactivex.rxjava3.core.Flowable<T> concat(org.reactivestreams.Publisher<? extends io.reactivex.rxjava3.core.MaybeSource<? extends T>>, int);
    Code:
       0: aload_0
       1: ldc           #2                  // String sources is null
       3: invokestatic  #3                  // Method java/util/Objects.requireNonNull:(Ljava/lang/Object;Ljava/lang/String;)Ljava/lang/Object;
       6: pop
       7: iload_1
       8: ldc           #22                 // String prefetch
      10: invokestatic  #23                 // Method io/reactivex/rxjava3/internal/functions/ObjectHelper.verifyPositive:(ILjava/lang/String;)I
      13: pop
      14: new           #24                 // class io/reactivex/rxjava3/internal/operators/mixed/FlowableConcatMapMaybePublisher
      17: dup
      18: aload_0
      19: invokestatic  #25                 // Method io/reactivex/rxjava3/internal/functions/Functions.identity:()Lio/reactivex/rxjava3/functions/Function;
      22: getstatic     #26                 // Field io/reactivex/rxjava3/internal/util/ErrorMode.IMMEDIATE:Lio/reactivex/rxjava3/internal/util/ErrorMode;
      25: iload_1
      26: invokespecial #27                 // Method io/reactivex/rxjava3/internal/operators/mixed/FlowableConcatMapMaybePublisher."<init>":(Lorg/reactivestreams/Publisher;Lio/reactivex/rxjava3/functions/Function;Lio/reactivex/rxjava3/internal/util/ErrorMode;I)V
      29: invokestatic  #28                 // Method io/reactivex/rxjava3/plugins/RxJavaPlugins.onAssembly:(Lio/reactivex/rxjava3/core/Flowable;)Lio/reactivex/rxjava3/core/Flowable;
      32: areturn

  public static <T> io.reactivex.rxjava3.core.Flowable<T> concatArray(io.reactivex.rxjava3.core.MaybeSource<? extends T>...);
    Code:
       0: aload_0
       1: ldc           #2                  // String sources is null
       3: invokestatic  #3                  // Method java/util/Objects.requireNonNull:(Ljava/lang/Object;Ljava/lang/String;)Ljava/lang/Object;
       6: pop
       7: aload_0
       8: arraylength
       9: ifne          16
      12: invokestatic  #29                 // Method io/reactivex/rxjava3/core/Flowable.empty:()Lio/reactivex/rxjava3/core/Flowable;
      15: areturn
      16: aload_0
      17: arraylength
      18: iconst_1
      19: if_icmpne     38
      22: aload_0
      23: iconst_0
      24: aaload
      25: astore_1
      26: new           #30                 // class io/reactivex/rxjava3/internal/operators/maybe/MaybeToFlowable
      29: dup
      30: aload_1
      31: invokespecial #31                 // Method io/reactivex/rxjava3/internal/operators/maybe/MaybeToFlowable."<init>":(Lio/reactivex/rxjava3/core/MaybeSource;)V
      34: invokestatic  #32                 // Method io/reactivex/rxjava3/plugins/RxJavaPlugins.onAssembly:(Lio/reactivex/rxjava3/core/Flowable;)Lio/reactivex/rxjava3/core/Flowable;
      37: areturn
      38: new           #33                 // class io/reactivex/rxjava3/internal/operators/maybe/MaybeConcatArray
      41: dup
      42: aload_0
      43: invokespecial #34                 // Method io/reactivex/rxjava3/internal/operators/maybe/MaybeConcatArray."<init>":([Lio/reactivex/rxjava3/core/MaybeSource;)V
      46: invokestatic  #35                 // Method io/reactivex/rxjava3/plugins/RxJavaPlugins.onAssembly:(Lio/reactivex/rxjava3/core/Flowable;)Lio/reactivex/rxjava3/core/Flowable;
      49: areturn

  public static <T> io.reactivex.rxjava3.core.Flowable<T> concatArrayDelayError(io.reactivex.rxjava3.core.MaybeSource<? extends T>...);
    Code:
       0: aload_0
       1: ldc           #2                  // String sources is null
       3: invokestatic  #3                  // Method java/util/Objects.requireNonNull:(Ljava/lang/Object;Ljava/lang/String;)Ljava/lang/Object;
       6: pop
       7: aload_0
       8: arraylength
       9: ifne          16
      12: invokestatic  #36                 // Method io/reactivex/rxjava3/core/Flowable.empty:()Lio/reactivex/rxjava3/core/Flowable;
      15: areturn
      16: aload_0
      17: arraylength
      18: iconst_1
      19: if_icmpne     38
      22: aload_0
      23: iconst_0
      24: aaload
      25: astore_1
      26: new           #30                 // class io/reactivex/rxjava3/internal/operators/maybe/MaybeToFlowable
      29: dup
      30: aload_1
      31: invokespecial #31                 // Method io/reactivex/rxjava3/internal/operators/maybe/MaybeToFlowable."<init>":(Lio/reactivex/rxjava3/core/MaybeSource;)V
      34: invokestatic  #37                 // Method io/reactivex/rxjava3/plugins/RxJavaPlugins.onAssembly:(Lio/reactivex/rxjava3/core/Flowable;)Lio/reactivex/rxjava3/core/Flowable;
      37: areturn
      38: new           #38                 // class io/reactivex/rxjava3/internal/operators/maybe/MaybeConcatArrayDelayError
      41: dup
      42: aload_0
      43: invokespecial #39                 // Method io/reactivex/rxjava3/internal/operators/maybe/MaybeConcatArrayDelayError."<init>":([Lio/reactivex/rxjava3/core/MaybeSource;)V
      46: invokestatic  #40                 // Method io/reactivex/rxjava3/plugins/RxJavaPlugins.onAssembly:(Lio/reactivex/rxjava3/core/Flowable;)Lio/reactivex/rxjava3/core/Flowable;
      49: areturn

  public static <T> io.reactivex.rxjava3.core.Flowable<T> concatArrayEager(io.reactivex.rxjava3.core.MaybeSource<? extends T>...);
    Code:
       0: aload_0
       1: invokestatic  #41                 // Method io/reactivex/rxjava3/core/Flowable.fromArray:([Ljava/lang/Object;)Lio/reactivex/rxjava3/core/Flowable;
       4: invokestatic  #42                 // Method io/reactivex/rxjava3/internal/operators/maybe/MaybeToPublisher.instance:()Lio/reactivex/rxjava3/functions/Function;
       7: invokevirtual #43                 // Method io/reactivex/rxjava3/core/Flowable.concatMapEager:(Lio/reactivex/rxjava3/functions/Function;)Lio/reactivex/rxjava3/core/Flowable;
      10: areturn

  public static <T> io.reactivex.rxjava3.core.Flowable<T> concatArrayEagerDelayError(io.reactivex.rxjava3.core.MaybeSource<? extends T>...);
    Code:
       0: aload_0
       1: invokestatic  #44                 // Method io/reactivex/rxjava3/core/Flowable.fromArray:([Ljava/lang/Object;)Lio/reactivex/rxjava3/core/Flowable;
       4: invokestatic  #42                 // Method io/reactivex/rxjava3/internal/operators/maybe/MaybeToPublisher.instance:()Lio/reactivex/rxjava3/functions/Function;
       7: iconst_1
       8: invokevirtual #45                 // Method io/reactivex/rxjava3/core/Flowable.concatMapEagerDelayError:(Lio/reactivex/rxjava3/functions/Function;Z)Lio/reactivex/rxjava3/core/Flowable;
      11: areturn

  public static <T> io.reactivex.rxjava3.core.Flowable<T> concatDelayError(java.lang.Iterable<? extends io.reactivex.rxjava3.core.MaybeSource<? extends T>>);
    Code:
       0: aload_0
       1: invokestatic  #46                 // Method io/reactivex/rxjava3/core/Flowable.fromIterable:(Ljava/lang/Iterable;)Lio/reactivex/rxjava3/core/Flowable;
       4: invokestatic  #47                 // Method io/reactivex/rxjava3/internal/functions/Functions.identity:()Lio/reactivex/rxjava3/functions/Function;
       7: invokevirtual #48                 // Method io/reactivex/rxjava3/core/Flowable.concatMapMaybeDelayError:(Lio/reactivex/rxjava3/functions/Function;)Lio/reactivex/rxjava3/core/Flowable;
      10: areturn

  public static <T> io.reactivex.rxjava3.core.Flowable<T> concatDelayError(org.reactivestreams.Publisher<? extends io.reactivex.rxjava3.core.MaybeSource<? extends T>>);
    Code:
       0: aload_0
       1: invokestatic  #49                 // Method io/reactivex/rxjava3/core/Flowable.fromPublisher:(Lorg/reactivestreams/Publisher;)Lio/reactivex/rxjava3/core/Flowable;
       4: invokestatic  #50                 // Method io/reactivex/rxjava3/internal/functions/Functions.identity:()Lio/reactivex/rxjava3/functions/Function;
       7: invokevirtual #51                 // Method io/reactivex/rxjava3/core/Flowable.concatMapMaybeDelayError:(Lio/reactivex/rxjava3/functions/Function;)Lio/reactivex/rxjava3/core/Flowable;
      10: areturn

  public static <T> io.reactivex.rxjava3.core.Flowable<T> concatDelayError(org.reactivestreams.Publisher<? extends io.reactivex.rxjava3.core.MaybeSource<? extends T>>, int);
    Code:
       0: aload_0
       1: invokestatic  #52                 // Method io/reactivex/rxjava3/core/Flowable.fromPublisher:(Lorg/reactivestreams/Publisher;)Lio/reactivex/rxjava3/core/Flowable;
       4: invokestatic  #53                 // Method io/reactivex/rxjava3/internal/functions/Functions.identity:()Lio/reactivex/rxjava3/functions/Function;
       7: iconst_1
       8: iload_1
       9: invokevirtual #54                 // Method io/reactivex/rxjava3/core/Flowable.concatMapMaybeDelayError:(Lio/reactivex/rxjava3/functions/Function;ZI)Lio/reactivex/rxjava3/core/Flowable;
      12: areturn

  public static <T> io.reactivex.rxjava3.core.Flowable<T> concatEager(java.lang.Iterable<? extends io.reactivex.rxjava3.core.MaybeSource<? extends T>>);
    Code:
       0: aload_0
       1: invokestatic  #55                 // Method io/reactivex/rxjava3/core/Flowable.fromIterable:(Ljava/lang/Iterable;)Lio/reactivex/rxjava3/core/Flowable;
       4: invokestatic  #42                 // Method io/reactivex/rxjava3/internal/operators/maybe/MaybeToPublisher.instance:()Lio/reactivex/rxjava3/functions/Function;
       7: iconst_0
       8: invokevirtual #56                 // Method io/reactivex/rxjava3/core/Flowable.concatMapEagerDelayError:(Lio/reactivex/rxjava3/functions/Function;Z)Lio/reactivex/rxjava3/core/Flowable;
      11: areturn

  public static <T> io.reactivex.rxjava3.core.Flowable<T> concatEager(java.lang.Iterable<? extends io.reactivex.rxjava3.core.MaybeSource<? extends T>>, int);
    Code:
       0: aload_0
       1: invokestatic  #57                 // Method io/reactivex/rxjava3/core/Flowable.fromIterable:(Ljava/lang/Iterable;)Lio/reactivex/rxjava3/core/Flowable;
       4: invokestatic  #42                 // Method io/reactivex/rxjava3/internal/operators/maybe/MaybeToPublisher.instance:()Lio/reactivex/rxjava3/functions/Function;
       7: iconst_0
       8: iload_1
       9: iconst_1
      10: invokevirtual #58                 // Method io/reactivex/rxjava3/core/Flowable.concatMapEagerDelayError:(Lio/reactivex/rxjava3/functions/Function;ZII)Lio/reactivex/rxjava3/core/Flowable;
      13: areturn

  public static <T> io.reactivex.rxjava3.core.Flowable<T> concatEager(org.reactivestreams.Publisher<? extends io.reactivex.rxjava3.core.MaybeSource<? extends T>>);
    Code:
       0: aload_0
       1: invokestatic  #59                 // Method io/reactivex/rxjava3/core/Flowable.fromPublisher:(Lorg/reactivestreams/Publisher;)Lio/reactivex/rxjava3/core/Flowable;
       4: invokestatic  #42                 // Method io/reactivex/rxjava3/internal/operators/maybe/MaybeToPublisher.instance:()Lio/reactivex/rxjava3/functions/Function;
       7: invokevirtual #60                 // Method io/reactivex/rxjava3/core/Flowable.concatMapEager:(Lio/reactivex/rxjava3/functions/Function;)Lio/reactivex/rxjava3/core/Flowable;
      10: areturn

  public static <T> io.reactivex.rxjava3.core.Flowable<T> concatEager(org.reactivestreams.Publisher<? extends io.reactivex.rxjava3.core.MaybeSource<? extends T>>, int);
    Code:
       0: aload_0
       1: invokestatic  #61                 // Method io/reactivex/rxjava3/core/Flowable.fromPublisher:(Lorg/reactivestreams/Publisher;)Lio/reactivex/rxjava3/core/Flowable;
       4: invokestatic  #42                 // Method io/reactivex/rxjava3/internal/operators/maybe/MaybeToPublisher.instance:()Lio/reactivex/rxjava3/functions/Function;
       7: iload_1
       8: iconst_1
       9: invokevirtual #62                 // Method io/reactivex/rxjava3/core/Flowable.concatMapEager:(Lio/reactivex/rxjava3/functions/Function;II)Lio/reactivex/rxjava3/core/Flowable;
      12: areturn

  public static <T> io.reactivex.rxjava3.core.Flowable<T> concatEagerDelayError(java.lang.Iterable<? extends io.reactivex.rxjava3.core.MaybeSource<? extends T>>);
    Code:
       0: aload_0
       1: invokestatic  #63                 // Method io/reactivex/rxjava3/core/Flowable.fromIterable:(Ljava/lang/Iterable;)Lio/reactivex/rxjava3/core/Flowable;
       4: invokestatic  #42                 // Method io/reactivex/rxjava3/internal/operators/maybe/MaybeToPublisher.instance:()Lio/reactivex/rxjava3/functions/Function;
       7: iconst_1
       8: invokevirtual #64                 // Method io/reactivex/rxjava3/core/Flowable.concatMapEagerDelayError:(Lio/reactivex/rxjava3/functions/Function;Z)Lio/reactivex/rxjava3/core/Flowable;
      11: areturn

  public static <T> io.reactivex.rxjava3.core.Flowable<T> concatEagerDelayError(java.lang.Iterable<? extends io.reactivex.rxjava3.core.MaybeSource<? extends T>>, int);
    Code:
       0: aload_0
       1: invokestatic  #65                 // Method io/reactivex/rxjava3/core/Flowable.fromIterable:(Ljava/lang/Iterable;)Lio/reactivex/rxjava3/core/Flowable;
       4: invokestatic  #42                 // Method io/reactivex/rxjava3/internal/operators/maybe/MaybeToPublisher.instance:()Lio/reactivex/rxjava3/functions/Function;
       7: iconst_1
       8: iload_1
       9: iconst_1
      10: invokevirtual #66                 // Method io/reactivex/rxjava3/core/Flowable.concatMapEagerDelayError:(Lio/reactivex/rxjava3/functions/Function;ZII)Lio/reactivex/rxjava3/core/Flowable;
      13: areturn

  public static <T> io.reactivex.rxjava3.core.Flowable<T> concatEagerDelayError(org.reactivestreams.Publisher<? extends io.reactivex.rxjava3.core.MaybeSource<? extends T>>);
    Code:
       0: aload_0
       1: invokestatic  #67                 // Method io/reactivex/rxjava3/core/Flowable.fromPublisher:(Lorg/reactivestreams/Publisher;)Lio/reactivex/rxjava3/core/Flowable;
       4: invokestatic  #42                 // Method io/reactivex/rxjava3/internal/operators/maybe/MaybeToPublisher.instance:()Lio/reactivex/rxjava3/functions/Function;
       7: iconst_1
       8: invokevirtual #68                 // Method io/reactivex/rxjava3/core/Flowable.concatMapEagerDelayError:(Lio/reactivex/rxjava3/functions/Function;Z)Lio/reactivex/rxjava3/core/Flowable;
      11: areturn

  public static <T> io.reactivex.rxjava3.core.Flowable<T> concatEagerDelayError(org.reactivestreams.Publisher<? extends io.reactivex.rxjava3.core.MaybeSource<? extends T>>, int);
    Code:
       0: aload_0
       1: invokestatic  #69                 // Method io/reactivex/rxjava3/core/Flowable.fromPublisher:(Lorg/reactivestreams/Publisher;)Lio/reactivex/rxjava3/core/Flowable;
       4: invokestatic  #42                 // Method io/reactivex/rxjava3/internal/operators/maybe/MaybeToPublisher.instance:()Lio/reactivex/rxjava3/functions/Function;
       7: iconst_1
       8: iload_1
       9: iconst_1
      10: invokevirtual #70                 // Method io/reactivex/rxjava3/core/Flowable.concatMapEagerDelayError:(Lio/reactivex/rxjava3/functions/Function;ZII)Lio/reactivex/rxjava3/core/Flowable;
      13: areturn

  public static <T> io.reactivex.rxjava3.core.Maybe<T> create(io.reactivex.rxjava3.core.MaybeOnSubscribe<T>);
    Code:
       0: aload_0
       1: ldc           #71                 // String onSubscribe is null
       3: invokestatic  #3                  // Method java/util/Objects.requireNonNull:(Ljava/lang/Object;Ljava/lang/String;)Ljava/lang/Object;
       6: pop
       7: new           #72                 // class io/reactivex/rxjava3/internal/operators/maybe/MaybeCreate
      10: dup
      11: aload_0
      12: invokespecial #73                 // Method io/reactivex/rxjava3/internal/operators/maybe/MaybeCreate."<init>":(Lio/reactivex/rxjava3/core/MaybeOnSubscribe;)V
      15: invokestatic  #74                 // Method io/reactivex/rxjava3/plugins/RxJavaPlugins.onAssembly:(Lio/reactivex/rxjava3/core/Maybe;)Lio/reactivex/rxjava3/core/Maybe;
      18: areturn

  public static <T> io.reactivex.rxjava3.core.Maybe<T> defer(io.reactivex.rxjava3.functions.Supplier<? extends io.reactivex.rxjava3.core.MaybeSource<? extends T>>);
    Code:
       0: aload_0
       1: ldc           #75                 // String supplier is null
       3: invokestatic  #3                  // Method java/util/Objects.requireNonNull:(Ljava/lang/Object;Ljava/lang/String;)Ljava/lang/Object;
       6: pop
       7: new           #76                 // class io/reactivex/rxjava3/internal/operators/maybe/MaybeDefer
      10: dup
      11: aload_0
      12: invokespecial #77                 // Method io/reactivex/rxjava3/internal/operators/maybe/MaybeDefer."<init>":(Lio/reactivex/rxjava3/functions/Supplier;)V
      15: invokestatic  #78                 // Method io/reactivex/rxjava3/plugins/RxJavaPlugins.onAssembly:(Lio/reactivex/rxjava3/core/Maybe;)Lio/reactivex/rxjava3/core/Maybe;
      18: areturn

  public static <T> io.reactivex.rxjava3.core.Maybe<T> empty();
    Code:
       0: getstatic     #79                 // Field io/reactivex/rxjava3/internal/operators/maybe/MaybeEmpty.INSTANCE:Lio/reactivex/rxjava3/internal/operators/maybe/MaybeEmpty;
       3: invokestatic  #80                 // Method io/reactivex/rxjava3/plugins/RxJavaPlugins.onAssembly:(Lio/reactivex/rxjava3/core/Maybe;)Lio/reactivex/rxjava3/core/Maybe;
       6: areturn

  public static <T> io.reactivex.rxjava3.core.Maybe<T> error(java.lang.Throwable);
    Code:
       0: aload_0
       1: ldc           #81                 // String throwable is null
       3: invokestatic  #3                  // Method java/util/Objects.requireNonNull:(Ljava/lang/Object;Ljava/lang/String;)Ljava/lang/Object;
       6: pop
       7: new           #82                 // class io/reactivex/rxjava3/internal/operators/maybe/MaybeError
      10: dup
      11: aload_0
      12: invokespecial #83                 // Method io/reactivex/rxjava3/internal/operators/maybe/MaybeError."<init>":(Ljava/lang/Throwable;)V
      15: invokestatic  #84                 // Method io/reactivex/rxjava3/plugins/RxJavaPlugins.onAssembly:(Lio/reactivex/rxjava3/core/Maybe;)Lio/reactivex/rxjava3/core/Maybe;
      18: areturn

  public static <T> io.reactivex.rxjava3.core.Maybe<T> error(io.reactivex.rxjava3.functions.Supplier<? extends java.lang.Throwable>);
    Code:
       0: aload_0
       1: ldc           #75                 // String supplier is null
       3: invokestatic  #3                  // Method java/util/Objects.requireNonNull:(Ljava/lang/Object;Ljava/lang/String;)Ljava/lang/Object;
       6: pop
       7: new           #85                 // class io/reactivex/rxjava3/internal/operators/maybe/MaybeErrorCallable
      10: dup
      11: aload_0
      12: invokespecial #86                 // Method io/reactivex/rxjava3/internal/operators/maybe/MaybeErrorCallable."<init>":(Lio/reactivex/rxjava3/functions/Supplier;)V
      15: invokestatic  #87                 // Method io/reactivex/rxjava3/plugins/RxJavaPlugins.onAssembly:(Lio/reactivex/rxjava3/core/Maybe;)Lio/reactivex/rxjava3/core/Maybe;
      18: areturn

  public static <T> io.reactivex.rxjava3.core.Maybe<T> fromAction(io.reactivex.rxjava3.functions.Action);
    Code:
       0: aload_0
       1: ldc           #88                 // String action is null
       3: invokestatic  #3                  // Method java/util/Objects.requireNonNull:(Ljava/lang/Object;Ljava/lang/String;)Ljava/lang/Object;
       6: pop
       7: new           #89                 // class io/reactivex/rxjava3/internal/operators/maybe/MaybeFromAction
      10: dup
      11: aload_0
      12: invokespecial #90                 // Method io/reactivex/rxjava3/internal/operators/maybe/MaybeFromAction."<init>":(Lio/reactivex/rxjava3/functions/Action;)V
      15: invokestatic  #91                 // Method io/reactivex/rxjava3/plugins/RxJavaPlugins.onAssembly:(Lio/reactivex/rxjava3/core/Maybe;)Lio/reactivex/rxjava3/core/Maybe;
      18: areturn

  public static <T> io.reactivex.rxjava3.core.Maybe<T> fromCompletable(io.reactivex.rxjava3.core.CompletableSource);
    Code:
       0: aload_0
       1: ldc           #92                 // String completableSource is null
       3: invokestatic  #3                  // Method java/util/Objects.requireNonNull:(Ljava/lang/Object;Ljava/lang/String;)Ljava/lang/Object;
       6: pop
       7: new           #93                 // class io/reactivex/rxjava3/internal/operators/maybe/MaybeFromCompletable
      10: dup
      11: aload_0
      12: invokespecial #94                 // Method io/reactivex/rxjava3/internal/operators/maybe/MaybeFromCompletable."<init>":(Lio/reactivex/rxjava3/core/CompletableSource;)V
      15: invokestatic  #95                 // Method io/reactivex/rxjava3/plugins/RxJavaPlugins.onAssembly:(Lio/reactivex/rxjava3/core/Maybe;)Lio/reactivex/rxjava3/core/Maybe;
      18: areturn

  public static <T> io.reactivex.rxjava3.core.Maybe<T> fromSingle(io.reactivex.rxjava3.core.SingleSource<T>);
    Code:
       0: aload_0
       1: ldc           #96                 // String single is null
       3: invokestatic  #3                  // Method java/util/Objects.requireNonNull:(Ljava/lang/Object;Ljava/lang/String;)Ljava/lang/Object;
       6: pop
       7: new           #97                 // class io/reactivex/rxjava3/internal/operators/maybe/MaybeFromSingle
      10: dup
      11: aload_0
      12: invokespecial #98                 // Method io/reactivex/rxjava3/internal/operators/maybe/MaybeFromSingle."<init>":(Lio/reactivex/rxjava3/core/SingleSource;)V
      15: invokestatic  #99                 // Method io/reactivex/rxjava3/plugins/RxJavaPlugins.onAssembly:(Lio/reactivex/rxjava3/core/Maybe;)Lio/reactivex/rxjava3/core/Maybe;
      18: areturn

  public static <T> io.reactivex.rxjava3.core.Maybe<T> fromCallable(java.util.concurrent.Callable<? extends T>);
    Code:
       0: aload_0
       1: ldc           #100                // String callable is null
       3: invokestatic  #3                  // Method java/util/Objects.requireNonNull:(Ljava/lang/Object;Ljava/lang/String;)Ljava/lang/Object;
       6: pop
       7: new           #101                // class io/reactivex/rxjava3/internal/operators/maybe/MaybeFromCallable
      10: dup
      11: aload_0
      12: invokespecial #102                // Method io/reactivex/rxjava3/internal/operators/maybe/MaybeFromCallable."<init>":(Ljava/util/concurrent/Callable;)V
      15: invokestatic  #103                // Method io/reactivex/rxjava3/plugins/RxJavaPlugins.onAssembly:(Lio/reactivex/rxjava3/core/Maybe;)Lio/reactivex/rxjava3/core/Maybe;
      18: areturn

  public static <T> io.reactivex.rxjava3.core.Maybe<T> fromFuture(java.util.concurrent.Future<? extends T>);
    Code:
       0: aload_0
       1: ldc           #104                // String future is null
       3: invokestatic  #3                  // Method java/util/Objects.requireNonNull:(Ljava/lang/Object;Ljava/lang/String;)Ljava/lang/Object;
       6: pop
       7: new           #105                // class io/reactivex/rxjava3/internal/operators/maybe/MaybeFromFuture
      10: dup
      11: aload_0
      12: lconst_0
      13: aconst_null
      14: invokespecial #106                // Method io/reactivex/rxjava3/internal/operators/maybe/MaybeFromFuture."<init>":(Ljava/util/concurrent/Future;JLjava/util/concurrent/TimeUnit;)V
      17: invokestatic  #107                // Method io/reactivex/rxjava3/plugins/RxJavaPlugins.onAssembly:(Lio/reactivex/rxjava3/core/Maybe;)Lio/reactivex/rxjava3/core/Maybe;
      20: areturn

  public static <T> io.reactivex.rxjava3.core.Maybe<T> fromFuture(java.util.concurrent.Future<? extends T>, long, java.util.concurrent.TimeUnit);
    Code:
       0: aload_0
       1: ldc           #104                // String future is null
       3: invokestatic  #3                  // Method java/util/Objects.requireNonNull:(Ljava/lang/Object;Ljava/lang/String;)Ljava/lang/Object;
       6: pop
       7: aload_3
       8: ldc           #108                // String unit is null
      10: invokestatic  #3                  // Method java/util/Objects.requireNonNull:(Ljava/lang/Object;Ljava/lang/String;)Ljava/lang/Object;
      13: pop
      14: new           #105                // class io/reactivex/rxjava3/internal/operators/maybe/MaybeFromFuture
      17: dup
      18: aload_0
      19: lload_1
      20: aload_3
      21: invokespecial #106                // Method io/reactivex/rxjava3/internal/operators/maybe/MaybeFromFuture."<init>":(Ljava/util/concurrent/Future;JLjava/util/concurrent/TimeUnit;)V
      24: invokestatic  #109                // Method io/reactivex/rxjava3/plugins/RxJavaPlugins.onAssembly:(Lio/reactivex/rxjava3/core/Maybe;)Lio/reactivex/rxjava3/core/Maybe;
      27: areturn

  public static <T> io.reactivex.rxjava3.core.Maybe<T> fromObservable(io.reactivex.rxjava3.core.ObservableSource<T>);
    Code:
       0: aload_0
       1: ldc           #110                // String source is null
       3: invokestatic  #3                  // Method java/util/Objects.requireNonNull:(Ljava/lang/Object;Ljava/lang/String;)Ljava/lang/Object;
       6: pop
       7: new           #111                // class io/reactivex/rxjava3/internal/operators/observable/ObservableElementAtMaybe
      10: dup
      11: aload_0
      12: lconst_0
      13: invokespecial #112                // Method io/reactivex/rxjava3/internal/operators/observable/ObservableElementAtMaybe."<init>":(Lio/reactivex/rxjava3/core/ObservableSource;J)V
      16: invokestatic  #113                // Method io/reactivex/rxjava3/plugins/RxJavaPlugins.onAssembly:(Lio/reactivex/rxjava3/core/Maybe;)Lio/reactivex/rxjava3/core/Maybe;
      19: areturn

  public static <T> io.reactivex.rxjava3.core.Maybe<T> fromPublisher(org.reactivestreams.Publisher<T>);
    Code:
       0: aload_0
       1: ldc           #110                // String source is null
       3: invokestatic  #3                  // Method java/util/Objects.requireNonNull:(Ljava/lang/Object;Ljava/lang/String;)Ljava/lang/Object;
       6: pop
       7: new           #114                // class io/reactivex/rxjava3/internal/operators/flowable/FlowableElementAtMaybePublisher
      10: dup
      11: aload_0
      12: lconst_0
      13: invokespecial #115                // Method io/reactivex/rxjava3/internal/operators/flowable/FlowableElementAtMaybePublisher."<init>":(Lorg/reactivestreams/Publisher;J)V
      16: invokestatic  #116                // Method io/reactivex/rxjava3/plugins/RxJavaPlugins.onAssembly:(Lio/reactivex/rxjava3/core/Maybe;)Lio/reactivex/rxjava3/core/Maybe;
      19: areturn

  public static <T> io.reactivex.rxjava3.core.Maybe<T> fromRunnable(java.lang.Runnable);
    Code:
       0: aload_0
       1: ldc           #117                // String run is null
       3: invokestatic  #3                  // Method java/util/Objects.requireNonNull:(Ljava/lang/Object;Ljava/lang/String;)Ljava/lang/Object;
       6: pop
       7: new           #118                // class io/reactivex/rxjava3/internal/operators/maybe/MaybeFromRunnable
      10: dup
      11: aload_0
      12: invokespecial #119                // Method io/reactivex/rxjava3/internal/operators/maybe/MaybeFromRunnable."<init>":(Ljava/lang/Runnable;)V
      15: invokestatic  #120                // Method io/reactivex/rxjava3/plugins/RxJavaPlugins.onAssembly:(Lio/reactivex/rxjava3/core/Maybe;)Lio/reactivex/rxjava3/core/Maybe;
      18: areturn

  public static <T> io.reactivex.rxjava3.core.Maybe<T> fromSupplier(io.reactivex.rxjava3.functions.Supplier<? extends T>);
    Code:
       0: aload_0
       1: ldc           #75                 // String supplier is null
       3: invokestatic  #3                  // Method java/util/Objects.requireNonNull:(Ljava/lang/Object;Ljava/lang/String;)Ljava/lang/Object;
       6: pop
       7: new           #121                // class io/reactivex/rxjava3/internal/operators/maybe/MaybeFromSupplier
      10: dup
      11: aload_0
      12: invokespecial #122                // Method io/reactivex/rxjava3/internal/operators/maybe/MaybeFromSupplier."<init>":(Lio/reactivex/rxjava3/functions/Supplier;)V
      15: invokestatic  #123                // Method io/reactivex/rxjava3/plugins/RxJavaPlugins.onAssembly:(Lio/reactivex/rxjava3/core/Maybe;)Lio/reactivex/rxjava3/core/Maybe;
      18: areturn

  public static <T> io.reactivex.rxjava3.core.Maybe<T> just(T);
    Code:
       0: aload_0
       1: ldc           #124                // String item is null
       3: invokestatic  #3                  // Method java/util/Objects.requireNonNull:(Ljava/lang/Object;Ljava/lang/String;)Ljava/lang/Object;
       6: pop
       7: new           #125                // class io/reactivex/rxjava3/internal/operators/maybe/MaybeJust
      10: dup
      11: aload_0
      12: invokespecial #126                // Method io/reactivex/rxjava3/internal/operators/maybe/MaybeJust."<init>":(Ljava/lang/Object;)V
      15: invokestatic  #127                // Method io/reactivex/rxjava3/plugins/RxJavaPlugins.onAssembly:(Lio/reactivex/rxjava3/core/Maybe;)Lio/reactivex/rxjava3/core/Maybe;
      18: areturn

  public static <T> io.reactivex.rxjava3.core.Flowable<T> merge(java.lang.Iterable<? extends io.reactivex.rxjava3.core.MaybeSource<? extends T>>);
    Code:
       0: aload_0
       1: invokestatic  #128                // Method io/reactivex/rxjava3/core/Flowable.fromIterable:(Ljava/lang/Iterable;)Lio/reactivex/rxjava3/core/Flowable;
       4: invokestatic  #129                // Method io/reactivex/rxjava3/internal/functions/Functions.identity:()Lio/reactivex/rxjava3/functions/Function;
       7: iconst_0
       8: ldc           #131                // int 2147483647
      10: invokevirtual #132                // Method io/reactivex/rxjava3/core/Flowable.flatMapMaybe:(Lio/reactivex/rxjava3/functions/Function;ZI)Lio/reactivex/rxjava3/core/Flowable;
      13: areturn

  public static <T> io.reactivex.rxjava3.core.Flowable<T> merge(org.reactivestreams.Publisher<? extends io.reactivex.rxjava3.core.MaybeSource<? extends T>>);
    Code:
       0: aload_0
       1: ldc           #131                // int 2147483647
       3: invokestatic  #133                // Method merge:(Lorg/reactivestreams/Publisher;I)Lio/reactivex/rxjava3/core/Flowable;
       6: areturn

  public static <T> io.reactivex.rxjava3.core.Flowable<T> merge(org.reactivestreams.Publisher<? extends io.reactivex.rxjava3.core.MaybeSource<? extends T>>, int);
    Code:
       0: aload_0
       1: ldc           #2                  // String sources is null
       3: invokestatic  #3                  // Method java/util/Objects.requireNonNull:(Ljava/lang/Object;Ljava/lang/String;)Ljava/lang/Object;
       6: pop
       7: iload_1
       8: ldc           #134                // String maxConcurrency
      10: invokestatic  #23                 // Method io/reactivex/rxjava3/internal/functions/ObjectHelper.verifyPositive:(ILjava/lang/String;)I
      13: pop
      14: new           #135                // class io/reactivex/rxjava3/internal/operators/flowable/FlowableFlatMapMaybePublisher
      17: dup
      18: aload_0
      19: invokestatic  #136                // Method io/reactivex/rxjava3/internal/functions/Functions.identity:()Lio/reactivex/rxjava3/functions/Function;
      22: iconst_0
      23: iload_1
      24: invokespecial #137                // Method io/reactivex/rxjava3/internal/operators/flowable/FlowableFlatMapMaybePublisher."<init>":(Lorg/reactivestreams/Publisher;Lio/reactivex/rxjava3/functions/Function;ZI)V
      27: invokestatic  #138                // Method io/reactivex/rxjava3/plugins/RxJavaPlugins.onAssembly:(Lio/reactivex/rxjava3/core/Flowable;)Lio/reactivex/rxjava3/core/Flowable;
      30: areturn

  public static <T> io.reactivex.rxjava3.core.Maybe<T> merge(io.reactivex.rxjava3.core.MaybeSource<? extends io.reactivex.rxjava3.core.MaybeSource<? extends T>>);
    Code:
       0: aload_0
       1: ldc           #110                // String source is null
       3: invokestatic  #3                  // Method java/util/Objects.requireNonNull:(Ljava/lang/Object;Ljava/lang/String;)Ljava/lang/Object;
       6: pop
       7: new           #139                // class io/reactivex/rxjava3/internal/operators/maybe/MaybeFlatten
      10: dup
      11: aload_0
      12: invokestatic  #140                // Method io/reactivex/rxjava3/internal/functions/Functions.identity:()Lio/reactivex/rxjava3/functions/Function;
      15: invokespecial #141                // Method io/reactivex/rxjava3/internal/operators/maybe/MaybeFlatten."<init>":(Lio/reactivex/rxjava3/core/MaybeSource;Lio/reactivex/rxjava3/functions/Function;)V
      18: invokestatic  #142                // Method io/reactivex/rxjava3/plugins/RxJavaPlugins.onAssembly:(Lio/reactivex/rxjava3/core/Maybe;)Lio/reactivex/rxjava3/core/Maybe;
      21: areturn

  public static <T> io.reactivex.rxjava3.core.Flowable<T> merge(io.reactivex.rxjava3.core.MaybeSource<? extends T>, io.reactivex.rxjava3.core.MaybeSource<? extends T>);
    Code:
       0: aload_0
       1: ldc           #13                 // String source1 is null
       3: invokestatic  #3                  // Method java/util/Objects.requireNonNull:(Ljava/lang/Object;Ljava/lang/String;)Ljava/lang/Object;
       6: pop
       7: aload_1
       8: ldc           #14                 // String source2 is null
      10: invokestatic  #3                  // Method java/util/Objects.requireNonNull:(Ljava/lang/Object;Ljava/lang/String;)Ljava/lang/Object;
      13: pop
      14: iconst_2
      15: anewarray     #15                 // class io/reactivex/rxjava3/core/MaybeSource
      18: dup
      19: iconst_0
      20: aload_0
      21: aastore
      22: dup
      23: iconst_1
      24: aload_1
      25: aastore
      26: invokestatic  #143                // Method mergeArray:([Lio/reactivex/rxjava3/core/MaybeSource;)Lio/reactivex/rxjava3/core/Flowable;
      29: areturn

  public static <T> io.reactivex.rxjava3.core.Flowable<T> merge(io.reactivex.rxjava3.core.MaybeSource<? extends T>, io.reactivex.rxjava3.core.MaybeSource<? extends T>, io.reactivex.rxjava3.core.MaybeSource<? extends T>);
    Code:
       0: aload_0
       1: ldc           #13                 // String source1 is null
       3: invokestatic  #3                  // Method java/util/Objects.requireNonNull:(Ljava/lang/Object;Ljava/lang/String;)Ljava/lang/Object;
       6: pop
       7: aload_1
       8: ldc           #14                 // String source2 is null
      10: invokestatic  #3                  // Method java/util/Objects.requireNonNull:(Ljava/lang/Object;Ljava/lang/String;)Ljava/lang/Object;
      13: pop
      14: aload_2
      15: ldc           #17                 // String source3 is null
      17: invokestatic  #3                  // Method java/util/Objects.requireNonNull:(Ljava/lang/Object;Ljava/lang/String;)Ljava/lang/Object;
      20: pop
      21: iconst_3
      22: anewarray     #15                 // class io/reactivex/rxjava3/core/MaybeSource
      25: dup
      26: iconst_0
      27: aload_0
      28: aastore
      29: dup
      30: iconst_1
      31: aload_1
      32: aastore
      33: dup
      34: iconst_2
      35: aload_2
      36: aastore
      37: invokestatic  #144                // Method mergeArray:([Lio/reactivex/rxjava3/core/MaybeSource;)Lio/reactivex/rxjava3/core/Flowable;
      40: areturn

  public static <T> io.reactivex.rxjava3.core.Flowable<T> merge(io.reactivex.rxjava3.core.MaybeSource<? extends T>, io.reactivex.rxjava3.core.MaybeSource<? extends T>, io.reactivex.rxjava3.core.MaybeSource<? extends T>, io.reactivex.rxjava3.core.MaybeSource<? extends T>);
    Code:
       0: aload_0
       1: ldc           #13                 // String source1 is null
       3: invokestatic  #3                  // Method java/util/Objects.requireNonNull:(Ljava/lang/Object;Ljava/lang/String;)Ljava/lang/Object;
       6: pop
       7: aload_1
       8: ldc           #14                 // String source2 is null
      10: invokestatic  #3                  // Method java/util/Objects.requireNonNull:(Ljava/lang/Object;Ljava/lang/String;)Ljava/lang/Object;
      13: pop
      14: aload_2
      15: ldc           #17                 // String source3 is null
      17: invokestatic  #3                  // Method java/util/Objects.requireNonNull:(Ljava/lang/Object;Ljava/lang/String;)Ljava/lang/Object;
      20: pop
      21: aload_3
      22: ldc           #19                 // String source4 is null
      24: invokestatic  #3                  // Method java/util/Objects.requireNonNull:(Ljava/lang/Object;Ljava/lang/String;)Ljava/lang/Object;
      27: pop
      28: iconst_4
      29: anewarray     #15                 // class io/reactivex/rxjava3/core/MaybeSource
      32: dup
      33: iconst_0
      34: aload_0
      35: aastore
      36: dup
      37: iconst_1
      38: aload_1
      39: aastore
      40: dup
      41: iconst_2
      42: aload_2
      43: aastore
      44: dup
      45: iconst_3
      46: aload_3
      47: aastore
      48: invokestatic  #145                // Method mergeArray:([Lio/reactivex/rxjava3/core/MaybeSource;)Lio/reactivex/rxjava3/core/Flowable;
      51: areturn

  public static <T> io.reactivex.rxjava3.core.Flowable<T> mergeArray(io.reactivex.rxjava3.core.MaybeSource<? extends T>...);
    Code:
       0: aload_0
       1: ldc           #2                  // String sources is null
       3: invokestatic  #3                  // Method java/util/Objects.requireNonNull:(Ljava/lang/Object;Ljava/lang/String;)Ljava/lang/Object;
       6: pop
       7: aload_0
       8: arraylength
       9: ifne          16
      12: invokestatic  #146                // Method io/reactivex/rxjava3/core/Flowable.empty:()Lio/reactivex/rxjava3/core/Flowable;
      15: areturn
      16: aload_0
      17: arraylength
      18: iconst_1
      19: if_icmpne     38
      22: aload_0
      23: iconst_0
      24: aaload
      25: astore_1
      26: new           #30                 // class io/reactivex/rxjava3/internal/operators/maybe/MaybeToFlowable
      29: dup
      30: aload_1
      31: invokespecial #31                 // Method io/reactivex/rxjava3/internal/operators/maybe/MaybeToFlowable."<init>":(Lio/reactivex/rxjava3/core/MaybeSource;)V
      34: invokestatic  #147                // Method io/reactivex/rxjava3/plugins/RxJavaPlugins.onAssembly:(Lio/reactivex/rxjava3/core/Flowable;)Lio/reactivex/rxjava3/core/Flowable;
      37: areturn
      38: new           #148                // class io/reactivex/rxjava3/internal/operators/maybe/MaybeMergeArray
      41: dup
      42: aload_0
      43: invokespecial #149                // Method io/reactivex/rxjava3/internal/operators/maybe/MaybeMergeArray."<init>":([Lio/reactivex/rxjava3/core/MaybeSource;)V
      46: invokestatic  #150                // Method io/reactivex/rxjava3/plugins/RxJavaPlugins.onAssembly:(Lio/reactivex/rxjava3/core/Flowable;)Lio/reactivex/rxjava3/core/Flowable;
      49: areturn

  public static <T> io.reactivex.rxjava3.core.Flowable<T> mergeArrayDelayError(io.reactivex.rxjava3.core.MaybeSource<? extends T>...);
    Code:
       0: aload_0
       1: ldc           #2                  // String sources is null
       3: invokestatic  #3                  // Method java/util/Objects.requireNonNull:(Ljava/lang/Object;Ljava/lang/String;)Ljava/lang/Object;
       6: pop
       7: aload_0
       8: invokestatic  #151                // Method io/reactivex/rxjava3/core/Flowable.fromArray:([Ljava/lang/Object;)Lio/reactivex/rxjava3/core/Flowable;
      11: invokestatic  #152                // Method io/reactivex/rxjava3/internal/functions/Functions.identity:()Lio/reactivex/rxjava3/functions/Function;
      14: iconst_1
      15: iconst_1
      16: aload_0
      17: arraylength
      18: invokestatic  #153                // Method java/lang/Math.max:(II)I
      21: invokevirtual #154                // Method io/reactivex/rxjava3/core/Flowable.flatMapMaybe:(Lio/reactivex/rxjava3/functions/Function;ZI)Lio/reactivex/rxjava3/core/Flowable;
      24: areturn

  public static <T> io.reactivex.rxjava3.core.Flowable<T> mergeDelayError(java.lang.Iterable<? extends io.reactivex.rxjava3.core.MaybeSource<? extends T>>);
    Code:
       0: aload_0
       1: invokestatic  #155                // Method io/reactivex/rxjava3/core/Flowable.fromIterable:(Ljava/lang/Iterable;)Lio/reactivex/rxjava3/core/Flowable;
       4: invokestatic  #156                // Method io/reactivex/rxjava3/internal/functions/Functions.identity:()Lio/reactivex/rxjava3/functions/Function;
       7: iconst_1
       8: ldc           #131                // int 2147483647
      10: invokevirtual #157                // Method io/reactivex/rxjava3/core/Flowable.flatMapMaybe:(Lio/reactivex/rxjava3/functions/Function;ZI)Lio/reactivex/rxjava3/core/Flowable;
      13: areturn

  public static <T> io.reactivex.rxjava3.core.Flowable<T> mergeDelayError(org.reactivestreams.Publisher<? extends io.reactivex.rxjava3.core.MaybeSource<? extends T>>);
    Code:
       0: aload_0
       1: ldc           #131                // int 2147483647
       3: invokestatic  #158                // Method mergeDelayError:(Lorg/reactivestreams/Publisher;I)Lio/reactivex/rxjava3/core/Flowable;
       6: areturn

  public static <T> io.reactivex.rxjava3.core.Flowable<T> mergeDelayError(org.reactivestreams.Publisher<? extends io.reactivex.rxjava3.core.MaybeSource<? extends T>>, int);
    Code:
       0: aload_0
       1: ldc           #2                  // String sources is null
       3: invokestatic  #3                  // Method java/util/Objects.requireNonNull:(Ljava/lang/Object;Ljava/lang/String;)Ljava/lang/Object;
       6: pop
       7: iload_1
       8: ldc           #134                // String maxConcurrency
      10: invokestatic  #23                 // Method io/reactivex/rxjava3/internal/functions/ObjectHelper.verifyPositive:(ILjava/lang/String;)I
      13: pop
      14: new           #135                // class io/reactivex/rxjava3/internal/operators/flowable/FlowableFlatMapMaybePublisher
      17: dup
      18: aload_0
      19: invokestatic  #159                // Method io/reactivex/rxjava3/internal/functions/Functions.identity:()Lio/reactivex/rxjava3/functions/Function;
      22: iconst_1
      23: iload_1
      24: invokespecial #137                // Method io/reactivex/rxjava3/internal/operators/flowable/FlowableFlatMapMaybePublisher."<init>":(Lorg/reactivestreams/Publisher;Lio/reactivex/rxjava3/functions/Function;ZI)V
      27: invokestatic  #160                // Method io/reactivex/rxjava3/plugins/RxJavaPlugins.onAssembly:(Lio/reactivex/rxjava3/core/Flowable;)Lio/reactivex/rxjava3/core/Flowable;
      30: areturn

  public static <T> io.reactivex.rxjava3.core.Flowable<T> mergeDelayError(io.reactivex.rxjava3.core.MaybeSource<? extends T>, io.reactivex.rxjava3.core.MaybeSource<? extends T>);
    Code:
       0: aload_0
       1: ldc           #13                 // String source1 is null
       3: invokestatic  #3                  // Method java/util/Objects.requireNonNull:(Ljava/lang/Object;Ljava/lang/String;)Ljava/lang/Object;
       6: pop
       7: aload_1
       8: ldc           #14                 // String source2 is null
      10: invokestatic  #3                  // Method java/util/Objects.requireNonNull:(Ljava/lang/Object;Ljava/lang/String;)Ljava/lang/Object;
      13: pop
      14: iconst_2
      15: anewarray     #15                 // class io/reactivex/rxjava3/core/MaybeSource
      18: dup
      19: iconst_0
      20: aload_0
      21: aastore
      22: dup
      23: iconst_1
      24: aload_1
      25: aastore
      26: invokestatic  #161                // Method mergeArrayDelayError:([Lio/reactivex/rxjava3/core/MaybeSource;)Lio/reactivex/rxjava3/core/Flowable;
      29: areturn

  public static <T> io.reactivex.rxjava3.core.Flowable<T> mergeDelayError(io.reactivex.rxjava3.core.MaybeSource<? extends T>, io.reactivex.rxjava3.core.MaybeSource<? extends T>, io.reactivex.rxjava3.core.MaybeSource<? extends T>);
    Code:
       0: aload_0
       1: ldc           #13                 // String source1 is null
       3: invokestatic  #3                  // Method java/util/Objects.requireNonNull:(Ljava/lang/Object;Ljava/lang/String;)Ljava/lang/Object;
       6: pop
       7: aload_1
       8: ldc           #14                 // String source2 is null
      10: invokestatic  #3                  // Method java/util/Objects.requireNonNull:(Ljava/lang/Object;Ljava/lang/String;)Ljava/lang/Object;
      13: pop
      14: aload_2
      15: ldc           #17                 // String source3 is null
      17: invokestatic  #3                  // Method java/util/Objects.requireNonNull:(Ljava/lang/Object;Ljava/lang/String;)Ljava/lang/Object;
      20: pop
      21: iconst_3
      22: anewarray     #15                 // class io/reactivex/rxjava3/core/MaybeSource
      25: dup
      26: iconst_0
      27: aload_0
      28: aastore
      29: dup
      30: iconst_1
      31: aload_1
      32: aastore
      33: dup
      34: iconst_2
      35: aload_2
      36: aastore
      37: invokestatic  #162                // Method mergeArrayDelayError:([Lio/reactivex/rxjava3/core/MaybeSource;)Lio/reactivex/rxjava3/core/Flowable;
      40: areturn

  public static <T> io.reactivex.rxjava3.core.Flowable<T> mergeDelayError(io.reactivex.rxjava3.core.MaybeSource<? extends T>, io.reactivex.rxjava3.core.MaybeSource<? extends T>, io.reactivex.rxjava3.core.MaybeSource<? extends T>, io.reactivex.rxjava3.core.MaybeSource<? extends T>);
    Code:
       0: aload_0
       1: ldc           #13                 // String source1 is null
       3: invokestatic  #3                  // Method java/util/Objects.requireNonNull:(Ljava/lang/Object;Ljava/lang/String;)Ljava/lang/Object;
       6: pop
       7: aload_1
       8: ldc           #14                 // String source2 is null
      10: invokestatic  #3                  // Method java/util/Objects.requireNonNull:(Ljava/lang/Object;Ljava/lang/String;)Ljava/lang/Object;
      13: pop
      14: aload_2
      15: ldc           #17                 // String source3 is null
      17: invokestatic  #3                  // Method java/util/Objects.requireNonNull:(Ljava/lang/Object;Ljava/lang/String;)Ljava/lang/Object;
      20: pop
      21: aload_3
      22: ldc           #19                 // String source4 is null
      24: invokestatic  #3                  // Method java/util/Objects.requireNonNull:(Ljava/lang/Object;Ljava/lang/String;)Ljava/lang/Object;
      27: pop
      28: iconst_4
      29: anewarray     #15                 // class io/reactivex/rxjava3/core/MaybeSource
      32: dup
      33: iconst_0
      34: aload_0
      35: aastore
      36: dup
      37: iconst_1
      38: aload_1
      39: aastore
      40: dup
      41: iconst_2
      42: aload_2
      43: aastore
      44: dup
      45: iconst_3
      46: aload_3
      47: aastore
      48: invokestatic  #163                // Method mergeArrayDelayError:([Lio/reactivex/rxjava3/core/MaybeSource;)Lio/reactivex/rxjava3/core/Flowable;
      51: areturn

  public static <T> io.reactivex.rxjava3.core.Maybe<T> never();
    Code:
       0: getstatic     #164                // Field io/reactivex/rxjava3/internal/operators/maybe/MaybeNever.INSTANCE:Lio/reactivex/rxjava3/internal/operators/maybe/MaybeNever;
       3: invokestatic  #165                // Method io/reactivex/rxjava3/plugins/RxJavaPlugins.onAssembly:(Lio/reactivex/rxjava3/core/Maybe;)Lio/reactivex/rxjava3/core/Maybe;
       6: areturn

  public static <T> io.reactivex.rxjava3.core.Single<java.lang.Boolean> sequenceEqual(io.reactivex.rxjava3.core.MaybeSource<? extends T>, io.reactivex.rxjava3.core.MaybeSource<? extends T>);
    Code:
       0: aload_0
       1: aload_1
       2: invokestatic  #166                // Method io/reactivex/rxjava3/internal/functions/ObjectHelper.equalsPredicate:()Lio/reactivex/rxjava3/functions/BiPredicate;
       5: invokestatic  #167                // Method sequenceEqual:(Lio/reactivex/rxjava3/core/MaybeSource;Lio/reactivex/rxjava3/core/MaybeSource;Lio/reactivex/rxjava3/functions/BiPredicate;)Lio/reactivex/rxjava3/core/Single;
       8: areturn

  public static <T> io.reactivex.rxjava3.core.Single<java.lang.Boolean> sequenceEqual(io.reactivex.rxjava3.core.MaybeSource<? extends T>, io.reactivex.rxjava3.core.MaybeSource<? extends T>, io.reactivex.rxjava3.functions.BiPredicate<? super T, ? super T>);
    Code:
       0: aload_0
       1: ldc           #13                 // String source1 is null
       3: invokestatic  #3                  // Method java/util/Objects.requireNonNull:(Ljava/lang/Object;Ljava/lang/String;)Ljava/lang/Object;
       6: pop
       7: aload_1
       8: ldc           #14                 // String source2 is null
      10: invokestatic  #3                  // Method java/util/Objects.requireNonNull:(Ljava/lang/Object;Ljava/lang/String;)Ljava/lang/Object;
      13: pop
      14: aload_2
      15: ldc           #168                // String isEqual is null
      17: invokestatic  #3                  // Method java/util/Objects.requireNonNull:(Ljava/lang/Object;Ljava/lang/String;)Ljava/lang/Object;
      20: pop
      21: new           #169                // class io/reactivex/rxjava3/internal/operators/maybe/MaybeEqualSingle
      24: dup
      25: aload_0
      26: aload_1
      27: aload_2
      28: invokespecial #170                // Method io/reactivex/rxjava3/internal/operators/maybe/MaybeEqualSingle."<init>":(Lio/reactivex/rxjava3/core/MaybeSource;Lio/reactivex/rxjava3/core/MaybeSource;Lio/reactivex/rxjava3/functions/BiPredicate;)V
      31: invokestatic  #171                // Method io/reactivex/rxjava3/plugins/RxJavaPlugins.onAssembly:(Lio/reactivex/rxjava3/core/Single;)Lio/reactivex/rxjava3/core/Single;
      34: areturn

  public static <T> io.reactivex.rxjava3.core.Flowable<T> switchOnNext(org.reactivestreams.Publisher<? extends io.reactivex.rxjava3.core.MaybeSource<? extends T>>);
    Code:
       0: aload_0
       1: ldc           #2                  // String sources is null
       3: invokestatic  #3                  // Method java/util/Objects.requireNonNull:(Ljava/lang/Object;Ljava/lang/String;)Ljava/lang/Object;
       6: pop
       7: new           #172                // class io/reactivex/rxjava3/internal/operators/mixed/FlowableSwitchMapMaybePublisher
      10: dup
      11: aload_0
      12: invokestatic  #173                // Method io/reactivex/rxjava3/internal/functions/Functions.identity:()Lio/reactivex/rxjava3/functions/Function;
      15: iconst_0
      16: invokespecial #174                // Method io/reactivex/rxjava3/internal/operators/mixed/FlowableSwitchMapMaybePublisher."<init>":(Lorg/reactivestreams/Publisher;Lio/reactivex/rxjava3/functions/Function;Z)V
      19: invokestatic  #175                // Method io/reactivex/rxjava3/plugins/RxJavaPlugins.onAssembly:(Lio/reactivex/rxjava3/core/Flowable;)Lio/reactivex/rxjava3/core/Flowable;
      22: areturn

  public static <T> io.reactivex.rxjava3.core.Flowable<T> switchOnNextDelayError(org.reactivestreams.Publisher<? extends io.reactivex.rxjava3.core.MaybeSource<? extends T>>);
    Code:
       0: aload_0
       1: ldc           #2                  // String sources is null
       3: invokestatic  #3                  // Method java/util/Objects.requireNonNull:(Ljava/lang/Object;Ljava/lang/String;)Ljava/lang/Object;
       6: pop
       7: new           #172                // class io/reactivex/rxjava3/internal/operators/mixed/FlowableSwitchMapMaybePublisher
      10: dup
      11: aload_0
      12: invokestatic  #176                // Method io/reactivex/rxjava3/internal/functions/Functions.identity:()Lio/reactivex/rxjava3/functions/Function;
      15: iconst_1
      16: invokespecial #174                // Method io/reactivex/rxjava3/internal/operators/mixed/FlowableSwitchMapMaybePublisher."<init>":(Lorg/reactivestreams/Publisher;Lio/reactivex/rxjava3/functions/Function;Z)V
      19: invokestatic  #177                // Method io/reactivex/rxjava3/plugins/RxJavaPlugins.onAssembly:(Lio/reactivex/rxjava3/core/Flowable;)Lio/reactivex/rxjava3/core/Flowable;
      22: areturn

  public static io.reactivex.rxjava3.core.Maybe<java.lang.Long> timer(long, java.util.concurrent.TimeUnit);
    Code:
       0: lload_0
       1: aload_2
       2: invokestatic  #178                // Method io/reactivex/rxjava3/schedulers/Schedulers.computation:()Lio/reactivex/rxjava3/core/Scheduler;
       5: invokestatic  #179                // Method timer:(JLjava/util/concurrent/TimeUnit;Lio/reactivex/rxjava3/core/Scheduler;)Lio/reactivex/rxjava3/core/Maybe;
       8: areturn

  public static io.reactivex.rxjava3.core.Maybe<java.lang.Long> timer(long, java.util.concurrent.TimeUnit, io.reactivex.rxjava3.core.Scheduler);
    Code:
       0: aload_2
       1: ldc           #108                // String unit is null
       3: invokestatic  #3                  // Method java/util/Objects.requireNonNull:(Ljava/lang/Object;Ljava/lang/String;)Ljava/lang/Object;
       6: pop
       7: aload_3
       8: ldc           #180                // String scheduler is null
      10: invokestatic  #3                  // Method java/util/Objects.requireNonNull:(Ljava/lang/Object;Ljava/lang/String;)Ljava/lang/Object;
      13: pop
      14: new           #181                // class io/reactivex/rxjava3/internal/operators/maybe/MaybeTimer
      17: dup
      18: lconst_0
      19: lload_0
      20: invokestatic  #182                // Method java/lang/Math.max:(JJ)J
      23: aload_2
      24: aload_3
      25: invokespecial #183                // Method io/reactivex/rxjava3/internal/operators/maybe/MaybeTimer."<init>":(JLjava/util/concurrent/TimeUnit;Lio/reactivex/rxjava3/core/Scheduler;)V
      28: invokestatic  #184                // Method io/reactivex/rxjava3/plugins/RxJavaPlugins.onAssembly:(Lio/reactivex/rxjava3/core/Maybe;)Lio/reactivex/rxjava3/core/Maybe;
      31: areturn

  public static <T> io.reactivex.rxjava3.core.Maybe<T> unsafeCreate(io.reactivex.rxjava3.core.MaybeSource<T>);
    Code:
       0: aload_0
       1: instanceof    #185                // class io/reactivex/rxjava3/core/Maybe
       4: ifeq          17
       7: new           #186                // class java/lang/IllegalArgumentException
      10: dup
      11: ldc           #187                // String unsafeCreate(Maybe) should be upgraded
      13: invokespecial #188                // Method java/lang/IllegalArgumentException."<init>":(Ljava/lang/String;)V
      16: athrow
      17: aload_0
      18: ldc           #71                 // String onSubscribe is null
      20: invokestatic  #3                  // Method java/util/Objects.requireNonNull:(Ljava/lang/Object;Ljava/lang/String;)Ljava/lang/Object;
      23: pop
      24: new           #189                // class io/reactivex/rxjava3/internal/operators/maybe/MaybeUnsafeCreate
      27: dup
      28: aload_0
      29: invokespecial #190                // Method io/reactivex/rxjava3/internal/operators/maybe/MaybeUnsafeCreate."<init>":(Lio/reactivex/rxjava3/core/MaybeSource;)V
      32: invokestatic  #191                // Method io/reactivex/rxjava3/plugins/RxJavaPlugins.onAssembly:(Lio/reactivex/rxjava3/core/Maybe;)Lio/reactivex/rxjava3/core/Maybe;
      35: areturn

  public static <T, D> io.reactivex.rxjava3.core.Maybe<T> using(io.reactivex.rxjava3.functions.Supplier<? extends D>, io.reactivex.rxjava3.functions.Function<? super D, ? extends io.reactivex.rxjava3.core.MaybeSource<? extends T>>, io.reactivex.rxjava3.functions.Consumer<? super D>);
    Code:
       0: aload_0
       1: aload_1
       2: aload_2
       3: iconst_1
       4: invokestatic  #192                // Method using:(Lio/reactivex/rxjava3/functions/Supplier;Lio/reactivex/rxjava3/functions/Function;Lio/reactivex/rxjava3/functions/Consumer;Z)Lio/reactivex/rxjava3/core/Maybe;
       7: areturn

  public static <T, D> io.reactivex.rxjava3.core.Maybe<T> using(io.reactivex.rxjava3.functions.Supplier<? extends D>, io.reactivex.rxjava3.functions.Function<? super D, ? extends io.reactivex.rxjava3.core.MaybeSource<? extends T>>, io.reactivex.rxjava3.functions.Consumer<? super D>, boolean);
    Code:
       0: aload_0
       1: ldc           #193                // String resourceSupplier is null
       3: invokestatic  #3                  // Method java/util/Objects.requireNonNull:(Ljava/lang/Object;Ljava/lang/String;)Ljava/lang/Object;
       6: pop
       7: aload_1
       8: ldc           #194                // String sourceSupplier is null
      10: invokestatic  #3                  // Method java/util/Objects.requireNonNull:(Ljava/lang/Object;Ljava/lang/String;)Ljava/lang/Object;
      13: pop
      14: aload_2
      15: ldc           #195                // String resourceCleanup is null
      17: invokestatic  #3                  // Method java/util/Objects.requireNonNull:(Ljava/lang/Object;Ljava/lang/String;)Ljava/lang/Object;
      20: pop
      21: new           #196                // class io/reactivex/rxjava3/internal/operators/maybe/MaybeUsing
      24: dup
      25: aload_0
      26: aload_1
      27: aload_2
      28: iload_3
      29: invokespecial #197                // Method io/reactivex/rxjava3/internal/operators/maybe/MaybeUsing."<init>":(Lio/reactivex/rxjava3/functions/Supplier;Lio/reactivex/rxjava3/functions/Function;Lio/reactivex/rxjava3/functions/Consumer;Z)V
      32: invokestatic  #198                // Method io/reactivex/rxjava3/plugins/RxJavaPlugins.onAssembly:(Lio/reactivex/rxjava3/core/Maybe;)Lio/reactivex/rxjava3/core/Maybe;
      35: areturn

  public static <T> io.reactivex.rxjava3.core.Maybe<T> wrap(io.reactivex.rxjava3.core.MaybeSource<T>);
    Code:
       0: aload_0
       1: instanceof    #185                // class io/reactivex/rxjava3/core/Maybe
       4: ifeq          15
       7: aload_0
       8: checkcast     #185                // class io/reactivex/rxjava3/core/Maybe
      11: invokestatic  #199                // Method io/reactivex/rxjava3/plugins/RxJavaPlugins.onAssembly:(Lio/reactivex/rxjava3/core/Maybe;)Lio/reactivex/rxjava3/core/Maybe;
      14: areturn
      15: aload_0
      16: ldc           #110                // String source is null
      18: invokestatic  #3                  // Method java/util/Objects.requireNonNull:(Ljava/lang/Object;Ljava/lang/String;)Ljava/lang/Object;
      21: pop
      22: new           #189                // class io/reactivex/rxjava3/internal/operators/maybe/MaybeUnsafeCreate
      25: dup
      26: aload_0
      27: invokespecial #190                // Method io/reactivex/rxjava3/internal/operators/maybe/MaybeUnsafeCreate."<init>":(Lio/reactivex/rxjava3/core/MaybeSource;)V
      30: invokestatic  #200                // Method io/reactivex/rxjava3/plugins/RxJavaPlugins.onAssembly:(Lio/reactivex/rxjava3/core/Maybe;)Lio/reactivex/rxjava3/core/Maybe;
      33: areturn

  public static <T, R> io.reactivex.rxjava3.core.Maybe<R> zip(java.lang.Iterable<? extends io.reactivex.rxjava3.core.MaybeSource<? extends T>>, io.reactivex.rxjava3.functions.Function<? super java.lang.Object[], ? extends R>);
    Code:
       0: aload_1
       1: ldc           #201                // String zipper is null
       3: invokestatic  #3                  // Method java/util/Objects.requireNonNull:(Ljava/lang/Object;Ljava/lang/String;)Ljava/lang/Object;
       6: pop
       7: aload_0
       8: ldc           #2                  // String sources is null
      10: invokestatic  #3                  // Method java/util/Objects.requireNonNull:(Ljava/lang/Object;Ljava/lang/String;)Ljava/lang/Object;
      13: pop
      14: new           #202                // class io/reactivex/rxjava3/internal/operators/maybe/MaybeZipIterable
      17: dup
      18: aload_0
      19: aload_1
      20: invokespecial #203                // Method io/reactivex/rxjava3/internal/operators/maybe/MaybeZipIterable."<init>":(Ljava/lang/Iterable;Lio/reactivex/rxjava3/functions/Function;)V
      23: invokestatic  #204                // Method io/reactivex/rxjava3/plugins/RxJavaPlugins.onAssembly:(Lio/reactivex/rxjava3/core/Maybe;)Lio/reactivex/rxjava3/core/Maybe;
      26: areturn

  public static <T1, T2, R> io.reactivex.rxjava3.core.Maybe<R> zip(io.reactivex.rxjava3.core.MaybeSource<? extends T1>, io.reactivex.rxjava3.core.MaybeSource<? extends T2>, io.reactivex.rxjava3.functions.BiFunction<? super T1, ? super T2, ? extends R>);
    Code:
       0: aload_0
       1: ldc           #13                 // String source1 is null
       3: invokestatic  #3                  // Method java/util/Objects.requireNonNull:(Ljava/lang/Object;Ljava/lang/String;)Ljava/lang/Object;
       6: pop
       7: aload_1
       8: ldc           #14                 // String source2 is null
      10: invokestatic  #3                  // Method java/util/Objects.requireNonNull:(Ljava/lang/Object;Ljava/lang/String;)Ljava/lang/Object;
      13: pop
      14: aload_2
      15: ldc           #201                // String zipper is null
      17: invokestatic  #3                  // Method java/util/Objects.requireNonNull:(Ljava/lang/Object;Ljava/lang/String;)Ljava/lang/Object;
      20: pop
      21: aload_2
      22: invokestatic  #205                // Method io/reactivex/rxjava3/internal/functions/Functions.toFunction:(Lio/reactivex/rxjava3/functions/BiFunction;)Lio/reactivex/rxjava3/functions/Function;
      25: iconst_2
      26: anewarray     #15                 // class io/reactivex/rxjava3/core/MaybeSource
      29: dup
      30: iconst_0
      31: aload_0
      32: aastore
      33: dup
      34: iconst_1
      35: aload_1
      36: aastore
      37: invokestatic  #206                // Method zipArray:(Lio/reactivex/rxjava3/functions/Function;[Lio/reactivex/rxjava3/core/MaybeSource;)Lio/reactivex/rxjava3/core/Maybe;
      40: areturn

  public static <T1, T2, T3, R> io.reactivex.rxjava3.core.Maybe<R> zip(io.reactivex.rxjava3.core.MaybeSource<? extends T1>, io.reactivex.rxjava3.core.MaybeSource<? extends T2>, io.reactivex.rxjava3.core.MaybeSource<? extends T3>, io.reactivex.rxjava3.functions.Function3<? super T1, ? super T2, ? super T3, ? extends R>);
    Code:
       0: aload_0
       1: ldc           #13                 // String source1 is null
       3: invokestatic  #3                  // Method java/util/Objects.requireNonNull:(Ljava/lang/Object;Ljava/lang/String;)Ljava/lang/Object;
       6: pop
       7: aload_1
       8: ldc           #14                 // String source2 is null
      10: invokestatic  #3                  // Method java/util/Objects.requireNonNull:(Ljava/lang/Object;Ljava/lang/String;)Ljava/lang/Object;
      13: pop
      14: aload_2
      15: ldc           #17                 // String source3 is null
      17: invokestatic  #3                  // Method java/util/Objects.requireNonNull:(Ljava/lang/Object;Ljava/lang/String;)Ljava/lang/Object;
      20: pop
      21: aload_3
      22: ldc           #201                // String zipper is null
      24: invokestatic  #3                  // Method java/util/Objects.requireNonNull:(Ljava/lang/Object;Ljava/lang/String;)Ljava/lang/Object;
      27: pop
      28: aload_3
      29: invokestatic  #207                // Method io/reactivex/rxjava3/internal/functions/Functions.toFunction:(Lio/reactivex/rxjava3/functions/Function3;)Lio/reactivex/rxjava3/functions/Function;
      32: iconst_3
      33: anewarray     #15                 // class io/reactivex/rxjava3/core/MaybeSource
      36: dup
      37: iconst_0
      38: aload_0
      39: aastore
      40: dup
      41: iconst_1
      42: aload_1
      43: aastore
      44: dup
      45: iconst_2
      46: aload_2
      47: aastore
      48: invokestatic  #208                // Method zipArray:(Lio/reactivex/rxjava3/functions/Function;[Lio/reactivex/rxjava3/core/MaybeSource;)Lio/reactivex/rxjava3/core/Maybe;
      51: areturn

  public static <T1, T2, T3, T4, R> io.reactivex.rxjava3.core.Maybe<R> zip(io.reactivex.rxjava3.core.MaybeSource<? extends T1>, io.reactivex.rxjava3.core.MaybeSource<? extends T2>, io.reactivex.rxjava3.core.MaybeSource<? extends T3>, io.reactivex.rxjava3.core.MaybeSource<? extends T4>, io.reactivex.rxjava3.functions.Function4<? super T1, ? super T2, ? super T3, ? super T4, ? extends R>);
    Code:
       0: aload_0
       1: ldc           #13                 // String source1 is null
       3: invokestatic  #3                  // Method java/util/Objects.requireNonNull:(Ljava/lang/Object;Ljava/lang/String;)Ljava/lang/Object;
       6: pop
       7: aload_1
       8: ldc           #14                 // String source2 is null
      10: invokestatic  #3                  // Method java/util/Objects.requireNonNull:(Ljava/lang/Object;Ljava/lang/String;)Ljava/lang/Object;
      13: pop
      14: aload_2
      15: ldc           #17                 // String source3 is null
      17: invokestatic  #3                  // Method java/util/Objects.requireNonNull:(Ljava/lang/Object;Ljava/lang/String;)Ljava/lang/Object;
      20: pop
      21: aload_3
      22: ldc           #19                 // String source4 is null
      24: invokestatic  #3                  // Method java/util/Objects.requireNonNull:(Ljava/lang/Object;Ljava/lang/String;)Ljava/lang/Object;
      27: pop
      28: aload         4
      30: ldc           #201                // String zipper is null
      32: invokestatic  #3                  // Method java/util/Objects.requireNonNull:(Ljava/lang/Object;Ljava/lang/String;)Ljava/lang/Object;
      35: pop
      36: aload         4
      38: invokestatic  #209                // Method io/reactivex/rxjava3/internal/functions/Functions.toFunction:(Lio/reactivex/rxjava3/functions/Function4;)Lio/reactivex/rxjava3/functions/Function;
      41: iconst_4
      42: anewarray     #15                 // class io/reactivex/rxjava3/core/MaybeSource
      45: dup
      46: iconst_0
      47: aload_0
      48: aastore
      49: dup
      50: iconst_1
      51: aload_1
      52: aastore
      53: dup
      54: iconst_2
      55: aload_2
      56: aastore
      57: dup
      58: iconst_3
      59: aload_3
      60: aastore
      61: invokestatic  #210                // Method zipArray:(Lio/reactivex/rxjava3/functions/Function;[Lio/reactivex/rxjava3/core/MaybeSource;)Lio/reactivex/rxjava3/core/Maybe;
      64: areturn

  public static <T1, T2, T3, T4, T5, R> io.reactivex.rxjava3.core.Maybe<R> zip(io.reactivex.rxjava3.core.MaybeSource<? extends T1>, io.reactivex.rxjava3.core.MaybeSource<? extends T2>, io.reactivex.rxjava3.core.MaybeSource<? extends T3>, io.reactivex.rxjava3.core.MaybeSource<? extends T4>, io.reactivex.rxjava3.core.MaybeSource<? extends T5>, io.reactivex.rxjava3.functions.Function5<? super T1, ? super T2, ? super T3, ? super T4, ? super T5, ? extends R>);
    Code:
       0: aload_0
       1: ldc           #13                 // String source1 is null
       3: invokestatic  #3                  // Method java/util/Objects.requireNonNull:(Ljava/lang/Object;Ljava/lang/String;)Ljava/lang/Object;
       6: pop
       7: aload_1
       8: ldc           #14                 // String source2 is null
      10: invokestatic  #3                  // Method java/util/Objects.requireNonNull:(Ljava/lang/Object;Ljava/lang/String;)Ljava/lang/Object;
      13: pop
      14: aload_2
      15: ldc           #17                 // String source3 is null
      17: invokestatic  #3                  // Method java/util/Objects.requireNonNull:(Ljava/lang/Object;Ljava/lang/String;)Ljava/lang/Object;
      20: pop
      21: aload_3
      22: ldc           #19                 // String source4 is null
      24: invokestatic  #3                  // Method java/util/Objects.requireNonNull:(Ljava/lang/Object;Ljava/lang/String;)Ljava/lang/Object;
      27: pop
      28: aload         4
      30: ldc           #211                // String source5 is null
      32: invokestatic  #3                  // Method java/util/Objects.requireNonNull:(Ljava/lang/Object;Ljava/lang/String;)Ljava/lang/Object;
      35: pop
      36: aload         5
      38: ldc           #201                // String zipper is null
      40: invokestatic  #3                  // Method java/util/Objects.requireNonNull:(Ljava/lang/Object;Ljava/lang/String;)Ljava/lang/Object;
      43: pop
      44: aload         5
      46: invokestatic  #212                // Method io/reactivex/rxjava3/internal/functions/Functions.toFunction:(Lio/reactivex/rxjava3/functions/Function5;)Lio/reactivex/rxjava3/functions/Function;
      49: iconst_5
      50: anewarray     #15                 // class io/reactivex/rxjava3/core/MaybeSource
      53: dup
      54: iconst_0
      55: aload_0
      56: aastore
      57: dup
      58: iconst_1
      59: aload_1
      60: aastore
      61: dup
      62: iconst_2
      63: aload_2
      64: aastore
      65: dup
      66: iconst_3
      67: aload_3
      68: aastore
      69: dup
      70: iconst_4
      71: aload         4
      73: aastore
      74: invokestatic  #213                // Method zipArray:(Lio/reactivex/rxjava3/functions/Function;[Lio/reactivex/rxjava3/core/MaybeSource;)Lio/reactivex/rxjava3/core/Maybe;
      77: areturn

  public static <T1, T2, T3, T4, T5, T6, R> io.reactivex.rxjava3.core.Maybe<R> zip(io.reactivex.rxjava3.core.MaybeSource<? extends T1>, io.reactivex.rxjava3.core.MaybeSource<? extends T2>, io.reactivex.rxjava3.core.MaybeSource<? extends T3>, io.reactivex.rxjava3.core.MaybeSource<? extends T4>, io.reactivex.rxjava3.core.MaybeSource<? extends T5>, io.reactivex.rxjava3.core.MaybeSource<? extends T6>, io.reactivex.rxjava3.functions.Function6<? super T1, ? super T2, ? super T3, ? super T4, ? super T5, ? super T6, ? extends R>);
    Code:
       0: aload_0
       1: ldc           #13                 // String source1 is null
       3: invokestatic  #3                  // Method java/util/Objects.requireNonNull:(Ljava/lang/Object;Ljava/lang/String;)Ljava/lang/Object;
       6: pop
       7: aload_1
       8: ldc           #14                 // String source2 is null
      10: invokestatic  #3                  // Method java/util/Objects.requireNonNull:(Ljava/lang/Object;Ljava/lang/String;)Ljava/lang/Object;
      13: pop
      14: aload_2
      15: ldc           #17                 // String source3 is null
      17: invokestatic  #3                  // Method java/util/Objects.requireNonNull:(Ljava/lang/Object;Ljava/lang/String;)Ljava/lang/Object;
      20: pop
      21: aload_3
      22: ldc           #19                 // String source4 is null
      24: invokestatic  #3                  // Method java/util/Objects.requireNonNull:(Ljava/lang/Object;Ljava/lang/String;)Ljava/lang/Object;
      27: pop
      28: aload         4
      30: ldc           #211                // String source5 is null
      32: invokestatic  #3                  // Method java/util/Objects.requireNonNull:(Ljava/lang/Object;Ljava/lang/String;)Ljava/lang/Object;
      35: pop
      36: aload         5
      38: ldc           #214                // String source6 is null
      40: invokestatic  #3                  // Method java/util/Objects.requireNonNull:(Ljava/lang/Object;Ljava/lang/String;)Ljava/lang/Object;
      43: pop
      44: aload         6
      46: ldc           #201                // String zipper is null
      48: invokestatic  #3                  // Method java/util/Objects.requireNonNull:(Ljava/lang/Object;Ljava/lang/String;)Ljava/lang/Object;
      51: pop
      52: aload         6
      54: invokestatic  #215                // Method io/reactivex/rxjava3/internal/functions/Functions.toFunction:(Lio/reactivex/rxjava3/functions/Function6;)Lio/reactivex/rxjava3/functions/Function;
      57: bipush        6
      59: anewarray     #15                 // class io/reactivex/rxjava3/core/MaybeSource
      62: dup
      63: iconst_0
      64: aload_0
      65: aastore
      66: dup
      67: iconst_1
      68: aload_1
      69: aastore
      70: dup
      71: iconst_2
      72: aload_2
      73: aastore
      74: dup
      75: iconst_3
      76: aload_3
      77: aastore
      78: dup
      79: iconst_4
      80: aload         4
      82: aastore
      83: dup
      84: iconst_5
      85: aload         5
      87: aastore
      88: invokestatic  #216                // Method zipArray:(Lio/reactivex/rxjava3/functions/Function;[Lio/reactivex/rxjava3/core/MaybeSource;)Lio/reactivex/rxjava3/core/Maybe;
      91: areturn

  public static <T1, T2, T3, T4, T5, T6, T7, R> io.reactivex.rxjava3.core.Maybe<R> zip(io.reactivex.rxjava3.core.MaybeSource<? extends T1>, io.reactivex.rxjava3.core.MaybeSource<? extends T2>, io.reactivex.rxjava3.core.MaybeSource<? extends T3>, io.reactivex.rxjava3.core.MaybeSource<? extends T4>, io.reactivex.rxjava3.core.MaybeSource<? extends T5>, io.reactivex.rxjava3.core.MaybeSource<? extends T6>, io.reactivex.rxjava3.core.MaybeSource<? extends T7>, io.reactivex.rxjava3.functions.Function7<? super T1, ? super T2, ? super T3, ? super T4, ? super T5, ? super T6, ? super T7, ? extends R>);
    Code:
       0: aload_0
       1: ldc           #13                 // String source1 is null
       3: invokestatic  #3                  // Method java/util/Objects.requireNonNull:(Ljava/lang/Object;Ljava/lang/String;)Ljava/lang/Object;
       6: pop
       7: aload_1
       8: ldc           #14                 // String source2 is null
      10: invokestatic  #3                  // Method java/util/Objects.requireNonNull:(Ljava/lang/Object;Ljava/lang/String;)Ljava/lang/Object;
      13: pop
      14: aload_2
      15: ldc           #17                 // String source3 is null
      17: invokestatic  #3                  // Method java/util/Objects.requireNonNull:(Ljava/lang/Object;Ljava/lang/String;)Ljava/lang/Object;
      20: pop
      21: aload_3
      22: ldc           #19                 // String source4 is null
      24: invokestatic  #3                  // Method java/util/Objects.requireNonNull:(Ljava/lang/Object;Ljava/lang/String;)Ljava/lang/Object;
      27: pop
      28: aload         4
      30: ldc           #211                // String source5 is null
      32: invokestatic  #3                  // Method java/util/Objects.requireNonNull:(Ljava/lang/Object;Ljava/lang/String;)Ljava/lang/Object;
      35: pop
      36: aload         5
      38: ldc           #214                // String source6 is null
      40: invokestatic  #3                  // Method java/util/Objects.requireNonNull:(Ljava/lang/Object;Ljava/lang/String;)Ljava/lang/Object;
      43: pop
      44: aload         6
      46: ldc           #217                // String source7 is null
      48: invokestatic  #3                  // Method java/util/Objects.requireNonNull:(Ljava/lang/Object;Ljava/lang/String;)Ljava/lang/Object;
      51: pop
      52: aload         7
      54: ldc           #201                // String zipper is null
      56: invokestatic  #3                  // Method java/util/Objects.requireNonNull:(Ljava/lang/Object;Ljava/lang/String;)Ljava/lang/Object;
      59: pop
      60: aload         7
      62: invokestatic  #218                // Method io/reactivex/rxjava3/internal/functions/Functions.toFunction:(Lio/reactivex/rxjava3/functions/Function7;)Lio/reactivex/rxjava3/functions/Function;
      65: bipush        7
      67: anewarray     #15                 // class io/reactivex/rxjava3/core/MaybeSource
      70: dup
      71: iconst_0
      72: aload_0
      73: aastore
      74: dup
      75: iconst_1
      76: aload_1
      77: aastore
      78: dup
      79: iconst_2
      80: aload_2
      81: aastore
      82: dup
      83: iconst_3
      84: aload_3
      85: aastore
      86: dup
      87: iconst_4
      88: aload         4
      90: aastore
      91: dup
      92: iconst_5
      93: aload         5
      95: aastore
      96: dup
      97: bipush        6
      99: aload         6
     101: aastore
     102: invokestatic  #219                // Method zipArray:(Lio/reactivex/rxjava3/functions/Function;[Lio/reactivex/rxjava3/core/MaybeSource;)Lio/reactivex/rxjava3/core/Maybe;
     105: areturn

  public static <T1, T2, T3, T4, T5, T6, T7, T8, R> io.reactivex.rxjava3.core.Maybe<R> zip(io.reactivex.rxjava3.core.MaybeSource<? extends T1>, io.reactivex.rxjava3.core.MaybeSource<? extends T2>, io.reactivex.rxjava3.core.MaybeSource<? extends T3>, io.reactivex.rxjava3.core.MaybeSource<? extends T4>, io.reactivex.rxjava3.core.MaybeSource<? extends T5>, io.reactivex.rxjava3.core.MaybeSource<? extends T6>, io.reactivex.rxjava3.core.MaybeSource<? extends T7>, io.reactivex.rxjava3.core.MaybeSource<? extends T8>, io.reactivex.rxjava3.functions.Function8<? super T1, ? super T2, ? super T3, ? super T4, ? super T5, ? super T6, ? super T7, ? super T8, ? extends R>);
    Code:
       0: aload_0
       1: ldc           #13                 // String source1 is null
       3: invokestatic  #3                  // Method java/util/Objects.requireNonNull:(Ljava/lang/Object;Ljava/lang/String;)Ljava/lang/Object;
       6: pop
       7: aload_1
       8: ldc           #14                 // String source2 is null
      10: invokestatic  #3                  // Method java/util/Objects.requireNonNull:(Ljava/lang/Object;Ljava/lang/String;)Ljava/lang/Object;
      13: pop
      14: aload_2
      15: ldc           #17                 // String source3 is null
      17: invokestatic  #3                  // Method java/util/Objects.requireNonNull:(Ljava/lang/Object;Ljava/lang/String;)Ljava/lang/Object;
      20: pop
      21: aload_3
      22: ldc           #19                 // String source4 is null
      24: invokestatic  #3                  // Method java/util/Objects.requireNonNull:(Ljava/lang/Object;Ljava/lang/String;)Ljava/lang/Object;
      27: pop
      28: aload         4
      30: ldc           #211                // String source5 is null
      32: invokestatic  #3                  // Method java/util/Objects.requireNonNull:(Ljava/lang/Object;Ljava/lang/String;)Ljava/lang/Object;
      35: pop
      36: aload         5
      38: ldc           #214                // String source6 is null
      40: invokestatic  #3                  // Method java/util/Objects.requireNonNull:(Ljava/lang/Object;Ljava/lang/String;)Ljava/lang/Object;
      43: pop
      44: aload         6
      46: ldc           #217                // String source7 is null
      48: invokestatic  #3                  // Method java/util/Objects.requireNonNull:(Ljava/lang/Object;Ljava/lang/String;)Ljava/lang/Object;
      51: pop
      52: aload         7
      54: ldc           #220                // String source8 is null
      56: invokestatic  #3                  // Method java/util/Objects.requireNonNull:(Ljava/lang/Object;Ljava/lang/String;)Ljava/lang/Object;
      59: pop
      60: aload         8
      62: ldc           #201                // String zipper is null
      64: invokestatic  #3                  // Method java/util/Objects.requireNonNull:(Ljava/lang/Object;Ljava/lang/String;)Ljava/lang/Object;
      67: pop
      68: aload         8
      70: invokestatic  #221                // Method io/reactivex/rxjava3/internal/functions/Functions.toFunction:(Lio/reactivex/rxjava3/functions/Function8;)Lio/reactivex/rxjava3/functions/Function;
      73: bipush        8
      75: anewarray     #15                 // class io/reactivex/rxjava3/core/MaybeSource
      78: dup
      79: iconst_0
      80: aload_0
      81: aastore
      82: dup
      83: iconst_1
      84: aload_1
      85: aastore
      86: dup
      87: iconst_2
      88: aload_2
      89: aastore
      90: dup
      91: iconst_3
      92: aload_3
      93: aastore
      94: dup
      95: iconst_4
      96: aload         4
      98: aastore
      99: dup
     100: iconst_5
     101: aload         5
     103: aastore
     104: dup
     105: bipush        6
     107: aload         6
     109: aastore
     110: dup
     111: bipush        7
     113: aload         7
     115: aastore
     116: invokestatic  #222                // Method zipArray:(Lio/reactivex/rxjava3/functions/Function;[Lio/reactivex/rxjava3/core/MaybeSource;)Lio/reactivex/rxjava3/core/Maybe;
     119: areturn

  public static <T1, T2, T3, T4, T5, T6, T7, T8, T9, R> io.reactivex.rxjava3.core.Maybe<R> zip(io.reactivex.rxjava3.core.MaybeSource<? extends T1>, io.reactivex.rxjava3.core.MaybeSource<? extends T2>, io.reactivex.rxjava3.core.MaybeSource<? extends T3>, io.reactivex.rxjava3.core.MaybeSource<? extends T4>, io.reactivex.rxjava3.core.MaybeSource<? extends T5>, io.reactivex.rxjava3.core.MaybeSource<? extends T6>, io.reactivex.rxjava3.core.MaybeSource<? extends T7>, io.reactivex.rxjava3.core.MaybeSource<? extends T8>, io.reactivex.rxjava3.core.MaybeSource<? extends T9>, io.reactivex.rxjava3.functions.Function9<? super T1, ? super T2, ? super T3, ? super T4, ? super T5, ? super T6, ? super T7, ? super T8, ? super T9, ? extends R>);
    Code:
       0: aload_0
       1: ldc           #13                 // String source1 is null
       3: invokestatic  #3                  // Method java/util/Objects.requireNonNull:(Ljava/lang/Object;Ljava/lang/String;)Ljava/lang/Object;
       6: pop
       7: aload_1
       8: ldc           #14                 // String source2 is null
      10: invokestatic  #3                  // Method java/util/Objects.requireNonNull:(Ljava/lang/Object;Ljava/lang/String;)Ljava/lang/Object;
      13: pop
      14: aload_2
      15: ldc           #17                 // String source3 is null
      17: invokestatic  #3                  // Method java/util/Objects.requireNonNull:(Ljava/lang/Object;Ljava/lang/String;)Ljava/lang/Object;
      20: pop
      21: aload_3
      22: ldc           #19                 // String source4 is null
      24: invokestatic  #3                  // Method java/util/Objects.requireNonNull:(Ljava/lang/Object;Ljava/lang/String;)Ljava/lang/Object;
      27: pop
      28: aload         4
      30: ldc           #211                // String source5 is null
      32: invokestatic  #3                  // Method java/util/Objects.requireNonNull:(Ljava/lang/Object;Ljava/lang/String;)Ljava/lang/Object;
      35: pop
      36: aload         5
      38: ldc           #214                // String source6 is null
      40: invokestatic  #3                  // Method java/util/Objects.requireNonNull:(Ljava/lang/Object;Ljava/lang/String;)Ljava/lang/Object;
      43: pop
      44: aload         6
      46: ldc           #217                // String source7 is null
      48: invokestatic  #3                  // Method java/util/Objects.requireNonNull:(Ljava/lang/Object;Ljava/lang/String;)Ljava/lang/Object;
      51: pop
      52: aload         7
      54: ldc           #220                // String source8 is null
      56: invokestatic  #3                  // Method java/util/Objects.requireNonNull:(Ljava/lang/Object;Ljava/lang/String;)Ljava/lang/Object;
      59: pop
      60: aload         8
      62: ldc           #223                // String source9 is null
      64: invokestatic  #3                  // Method java/util/Objects.requireNonNull:(Ljava/lang/Object;Ljava/lang/String;)Ljava/lang/Object;
      67: pop
      68: aload         9
      70: ldc           #201                // String zipper is null
      72: invokestatic  #3                  // Method java/util/Objects.requireNonNull:(Ljava/lang/Object;Ljava/lang/String;)Ljava/lang/Object;
      75: pop
      76: aload         9
      78: invokestatic  #224                // Method io/reactivex/rxjava3/internal/functions/Functions.toFunction:(Lio/reactivex/rxjava3/functions/Function9;)Lio/reactivex/rxjava3/functions/Function;
      81: bipush        9
      83: anewarray     #15                 // class io/reactivex/rxjava3/core/MaybeSource
      86: dup
      87: iconst_0
      88: aload_0
      89: aastore
      90: dup
      91: iconst_1
      92: aload_1
      93: aastore
      94: dup
      95: iconst_2
      96: aload_2
      97: aastore
      98: dup
      99: iconst_3
     100: aload_3
     101: aastore
     102: dup
     103: iconst_4
     104: aload         4
     106: aastore
     107: dup
     108: iconst_5
     109: aload         5
     111: aastore
     112: dup
     113: bipush        6
     115: aload         6
     117: aastore
     118: dup
     119: bipush        7
     121: aload         7
     123: aastore
     124: dup
     125: bipush        8
     127: aload         8
     129: aastore
     130: invokestatic  #225                // Method zipArray:(Lio/reactivex/rxjava3/functions/Function;[Lio/reactivex/rxjava3/core/MaybeSource;)Lio/reactivex/rxjava3/core/Maybe;
     133: areturn

  public static <T, R> io.reactivex.rxjava3.core.Maybe<R> zipArray(io.reactivex.rxjava3.functions.Function<? super java.lang.Object[], ? extends R>, io.reactivex.rxjava3.core.MaybeSource<? extends T>...);
    Code:
       0: aload_1
       1: ldc           #2                  // String sources is null
       3: invokestatic  #3                  // Method java/util/Objects.requireNonNull:(Ljava/lang/Object;Ljava/lang/String;)Ljava/lang/Object;
       6: pop
       7: aload_1
       8: arraylength
       9: ifne          16
      12: invokestatic  #226                // Method empty:()Lio/reactivex/rxjava3/core/Maybe;
      15: areturn
      16: aload_0
      17: ldc           #201                // String zipper is null
      19: invokestatic  #3                  // Method java/util/Objects.requireNonNull:(Ljava/lang/Object;Ljava/lang/String;)Ljava/lang/Object;
      22: pop
      23: new           #227                // class io/reactivex/rxjava3/internal/operators/maybe/MaybeZipArray
      26: dup
      27: aload_1
      28: aload_0
      29: invokespecial #228                // Method io/reactivex/rxjava3/internal/operators/maybe/MaybeZipArray."<init>":([Lio/reactivex/rxjava3/core/MaybeSource;Lio/reactivex/rxjava3/functions/Function;)V
      32: invokestatic  #229                // Method io/reactivex/rxjava3/plugins/RxJavaPlugins.onAssembly:(Lio/reactivex/rxjava3/core/Maybe;)Lio/reactivex/rxjava3/core/Maybe;
      35: areturn

  public final io.reactivex.rxjava3.core.Maybe<T> ambWith(io.reactivex.rxjava3.core.MaybeSource<? extends T>);
    Code:
       0: aload_1
       1: ldc           #230                // String other is null
       3: invokestatic  #3                  // Method java/util/Objects.requireNonNull:(Ljava/lang/Object;Ljava/lang/String;)Ljava/lang/Object;
       6: pop
       7: iconst_2
       8: anewarray     #15                 // class io/reactivex/rxjava3/core/MaybeSource
      11: dup
      12: iconst_0
      13: aload_0
      14: aastore
      15: dup
      16: iconst_1
      17: aload_1
      18: aastore
      19: invokestatic  #231                // Method ambArray:([Lio/reactivex/rxjava3/core/MaybeSource;)Lio/reactivex/rxjava3/core/Maybe;
      22: areturn

  public final T blockingGet();
    Code:
       0: new           #232                // class io/reactivex/rxjava3/internal/observers/BlockingMultiObserver
       3: dup
       4: invokespecial #233                // Method io/reactivex/rxjava3/internal/observers/BlockingMultiObserver."<init>":()V
       7: astore_1
       8: aload_0
       9: aload_1
      10: invokevirtual #234                // Method subscribe:(Lio/reactivex/rxjava3/core/MaybeObserver;)V
      13: aload_1
      14: invokevirtual #235                // Method io/reactivex/rxjava3/internal/observers/BlockingMultiObserver.blockingGet:()Ljava/lang/Object;
      17: areturn

  public final T blockingGet(T);
    Code:
       0: aload_1
       1: ldc           #236                // String defaultValue is null
       3: invokestatic  #3                  // Method java/util/Objects.requireNonNull:(Ljava/lang/Object;Ljava/lang/String;)Ljava/lang/Object;
       6: pop
       7: new           #232                // class io/reactivex/rxjava3/internal/observers/BlockingMultiObserver
      10: dup
      11: invokespecial #233                // Method io/reactivex/rxjava3/internal/observers/BlockingMultiObserver."<init>":()V
      14: astore_2
      15: aload_0
      16: aload_2
      17: invokevirtual #234                // Method subscribe:(Lio/reactivex/rxjava3/core/MaybeObserver;)V
      20: aload_2
      21: aload_1
      22: invokevirtual #237                // Method io/reactivex/rxjava3/internal/observers/BlockingMultiObserver.blockingGet:(Ljava/lang/Object;)Ljava/lang/Object;
      25: areturn

  public final void blockingSubscribe();
    Code:
       0: aload_0
       1: invokestatic  #238                // Method io/reactivex/rxjava3/internal/functions/Functions.emptyConsumer:()Lio/reactivex/rxjava3/functions/Consumer;
       4: getstatic     #239                // Field io/reactivex/rxjava3/internal/functions/Functions.ERROR_CONSUMER:Lio/reactivex/rxjava3/functions/Consumer;
       7: getstatic     #240                // Field io/reactivex/rxjava3/internal/functions/Functions.EMPTY_ACTION:Lio/reactivex/rxjava3/functions/Action;
      10: invokevirtual #241                // Method blockingSubscribe:(Lio/reactivex/rxjava3/functions/Consumer;Lio/reactivex/rxjava3/functions/Consumer;Lio/reactivex/rxjava3/functions/Action;)V
      13: return

  public final void blockingSubscribe(io.reactivex.rxjava3.functions.Consumer<? super T>);
    Code:
       0: aload_0
       1: aload_1
       2: getstatic     #239                // Field io/reactivex/rxjava3/internal/functions/Functions.ERROR_CONSUMER:Lio/reactivex/rxjava3/functions/Consumer;
       5: getstatic     #240                // Field io/reactivex/rxjava3/internal/functions/Functions.EMPTY_ACTION:Lio/reactivex/rxjava3/functions/Action;
       8: invokevirtual #241                // Method blockingSubscribe:(Lio/reactivex/rxjava3/functions/Consumer;Lio/reactivex/rxjava3/functions/Consumer;Lio/reactivex/rxjava3/functions/Action;)V
      11: return

  public final void blockingSubscribe(io.reactivex.rxjava3.functions.Consumer<? super T>, io.reactivex.rxjava3.functions.Consumer<? super java.lang.Throwable>);
    Code:
       0: aload_0
       1: aload_1
       2: aload_2
       3: getstatic     #240                // Field io/reactivex/rxjava3/internal/functions/Functions.EMPTY_ACTION:Lio/reactivex/rxjava3/functions/Action;
       6: invokevirtual #241                // Method blockingSubscribe:(Lio/reactivex/rxjava3/functions/Consumer;Lio/reactivex/rxjava3/functions/Consumer;Lio/reactivex/rxjava3/functions/Action;)V
       9: return

  public final void blockingSubscribe(io.reactivex.rxjava3.functions.Consumer<? super T>, io.reactivex.rxjava3.functions.Consumer<? super java.lang.Throwable>, io.reactivex.rxjava3.functions.Action);
    Code:
       0: aload_1
       1: ldc           #242                // String onSuccess is null
       3: invokestatic  #3                  // Method java/util/Objects.requireNonNull:(Ljava/lang/Object;Ljava/lang/String;)Ljava/lang/Object;
       6: pop
       7: aload_2
       8: ldc           #243                // String onError is null
      10: invokestatic  #3                  // Method java/util/Objects.requireNonNull:(Ljava/lang/Object;Ljava/lang/String;)Ljava/lang/Object;
      13: pop
      14: aload_3
      15: ldc           #244                // String onComplete is null
      17: invokestatic  #3                  // Method java/util/Objects.requireNonNull:(Ljava/lang/Object;Ljava/lang/String;)Ljava/lang/Object;
      20: pop
      21: new           #232                // class io/reactivex/rxjava3/internal/observers/BlockingMultiObserver
      24: dup
      25: invokespecial #233                // Method io/reactivex/rxjava3/internal/observers/BlockingMultiObserver."<init>":()V
      28: astore        4
      30: aload_0
      31: aload         4
      33: invokevirtual #234                // Method subscribe:(Lio/reactivex/rxjava3/core/MaybeObserver;)V
      36: aload         4
      38: aload_1
      39: aload_2
      40: aload_3
      41: invokevirtual #245                // Method io/reactivex/rxjava3/internal/observers/BlockingMultiObserver.blockingConsume:(Lio/reactivex/rxjava3/functions/Consumer;Lio/reactivex/rxjava3/functions/Consumer;Lio/reactivex/rxjava3/functions/Action;)V
      44: return

  public final void blockingSubscribe(io.reactivex.rxjava3.core.MaybeObserver<? super T>);
    Code:
       0: aload_1
       1: ldc           #246                // String observer is null
       3: invokestatic  #3                  // Method java/util/Objects.requireNonNull:(Ljava/lang/Object;Ljava/lang/String;)Ljava/lang/Object;
       6: pop
       7: new           #247                // class io/reactivex/rxjava3/internal/observers/BlockingDisposableMultiObserver
      10: dup
      11: invokespecial #248                // Method io/reactivex/rxjava3/internal/observers/BlockingDisposableMultiObserver."<init>":()V
      14: astore_2
      15: aload_1
      16: aload_2
      17: invokeinterface #249,  2          // InterfaceMethod io/reactivex/rxjava3/core/MaybeObserver.onSubscribe:(Lio/reactivex/rxjava3/disposables/Disposable;)V
      22: aload_0
      23: aload_2
      24: invokevirtual #234                // Method subscribe:(Lio/reactivex/rxjava3/core/MaybeObserver;)V
      27: aload_2
      28: aload_1
      29: invokevirtual #250                // Method io/reactivex/rxjava3/internal/observers/BlockingDisposableMultiObserver.blockingConsume:(Lio/reactivex/rxjava3/core/MaybeObserver;)V
      32: return

  public final io.reactivex.rxjava3.core.Maybe<T> cache();
    Code:
       0: new           #251                // class io/reactivex/rxjava3/internal/operators/maybe/MaybeCache
       3: dup
       4: aload_0
       5: invokespecial #252                // Method io/reactivex/rxjava3/internal/operators/maybe/MaybeCache."<init>":(Lio/reactivex/rxjava3/core/MaybeSource;)V
       8: invokestatic  #253                // Method io/reactivex/rxjava3/plugins/RxJavaPlugins.onAssembly:(Lio/reactivex/rxjava3/core/Maybe;)Lio/reactivex/rxjava3/core/Maybe;
      11: areturn

  public final <U> io.reactivex.rxjava3.core.Maybe<U> cast(java.lang.Class<? extends U>);
    Code:
       0: aload_1
       1: ldc           #254                // String clazz is null
       3: invokestatic  #3                  // Method java/util/Objects.requireNonNull:(Ljava/lang/Object;Ljava/lang/String;)Ljava/lang/Object;
       6: pop
       7: aload_0
       8: aload_1
       9: invokestatic  #255                // Method io/reactivex/rxjava3/internal/functions/Functions.castFunction:(Ljava/lang/Class;)Lio/reactivex/rxjava3/functions/Function;
      12: invokevirtual #256                // Method map:(Lio/reactivex/rxjava3/functions/Function;)Lio/reactivex/rxjava3/core/Maybe;
      15: areturn

  public final <R> io.reactivex.rxjava3.core.Maybe<R> compose(io.reactivex.rxjava3.core.MaybeTransformer<? super T, ? extends R>);
    Code:
       0: aload_1
       1: ldc_w         #257                // String transformer is null
       4: invokestatic  #3                  // Method java/util/Objects.requireNonNull:(Ljava/lang/Object;Ljava/lang/String;)Ljava/lang/Object;
       7: checkcast     #258                // class io/reactivex/rxjava3/core/MaybeTransformer
      10: aload_0
      11: invokeinterface #259,  2          // InterfaceMethod io/reactivex/rxjava3/core/MaybeTransformer.apply:(Lio/reactivex/rxjava3/core/Maybe;)Lio/reactivex/rxjava3/core/MaybeSource;
      16: invokestatic  #260                // Method wrap:(Lio/reactivex/rxjava3/core/MaybeSource;)Lio/reactivex/rxjava3/core/Maybe;
      19: areturn

  public final <R> io.reactivex.rxjava3.core.Maybe<R> concatMap(io.reactivex.rxjava3.functions.Function<? super T, ? extends io.reactivex.rxjava3.core.MaybeSource<? extends R>>);
    Code:
       0: aload_0
       1: aload_1
       2: invokevirtual #261                // Method flatMap:(Lio/reactivex/rxjava3/functions/Function;)Lio/reactivex/rxjava3/core/Maybe;
       5: areturn

  public final io.reactivex.rxjava3.core.Completable concatMapCompletable(io.reactivex.rxjava3.functions.Function<? super T, ? extends io.reactivex.rxjava3.core.CompletableSource>);
    Code:
       0: aload_0
       1: aload_1
       2: invokevirtual #262                // Method flatMapCompletable:(Lio/reactivex/rxjava3/functions/Function;)Lio/reactivex/rxjava3/core/Completable;
       5: areturn

  public final <R> io.reactivex.rxjava3.core.Maybe<R> concatMapSingle(io.reactivex.rxjava3.functions.Function<? super T, ? extends io.reactivex.rxjava3.core.SingleSource<? extends R>>);
    Code:
       0: aload_0
       1: aload_1
       2: invokevirtual #263                // Method flatMapSingle:(Lio/reactivex/rxjava3/functions/Function;)Lio/reactivex/rxjava3/core/Maybe;
       5: areturn

  public final io.reactivex.rxjava3.core.Flowable<T> concatWith(io.reactivex.rxjava3.core.MaybeSource<? extends T>);
    Code:
       0: aload_1
       1: ldc           #230                // String other is null
       3: invokestatic  #3                  // Method java/util/Objects.requireNonNull:(Ljava/lang/Object;Ljava/lang/String;)Ljava/lang/Object;
       6: pop
       7: aload_0
       8: aload_1
       9: invokestatic  #264                // Method concat:(Lio/reactivex/rxjava3/core/MaybeSource;Lio/reactivex/rxjava3/core/MaybeSource;)Lio/reactivex/rxjava3/core/Flowable;
      12: areturn

  public final io.reactivex.rxjava3.core.Single<java.lang.Boolean> contains(java.lang.Object);
    Code:
       0: aload_1
       1: ldc           #124                // String item is null
       3: invokestatic  #3                  // Method java/util/Objects.requireNonNull:(Ljava/lang/Object;Ljava/lang/String;)Ljava/lang/Object;
       6: pop
       7: new           #265                // class io/reactivex/rxjava3/internal/operators/maybe/MaybeContains
      10: dup
      11: aload_0
      12: aload_1
      13: invokespecial #266                // Method io/reactivex/rxjava3/internal/operators/maybe/MaybeContains."<init>":(Lio/reactivex/rxjava3/core/MaybeSource;Ljava/lang/Object;)V
      16: invokestatic  #267                // Method io/reactivex/rxjava3/plugins/RxJavaPlugins.onAssembly:(Lio/reactivex/rxjava3/core/Single;)Lio/reactivex/rxjava3/core/Single;
      19: areturn

  public final io.reactivex.rxjava3.core.Single<java.lang.Long> count();
    Code:
       0: new           #268                // class io/reactivex/rxjava3/internal/operators/maybe/MaybeCount
       3: dup
       4: aload_0
       5: invokespecial #269                // Method io/reactivex/rxjava3/internal/operators/maybe/MaybeCount."<init>":(Lio/reactivex/rxjava3/core/MaybeSource;)V
       8: invokestatic  #270                // Method io/reactivex/rxjava3/plugins/RxJavaPlugins.onAssembly:(Lio/reactivex/rxjava3/core/Single;)Lio/reactivex/rxjava3/core/Single;
      11: areturn

  public final io.reactivex.rxjava3.core.Single<T> defaultIfEmpty(T);
    Code:
       0: aload_1
       1: ldc_w         #271                // String defaultItem is null
       4: invokestatic  #3                  // Method java/util/Objects.requireNonNull:(Ljava/lang/Object;Ljava/lang/String;)Ljava/lang/Object;
       7: pop
       8: new           #272                // class io/reactivex/rxjava3/internal/operators/maybe/MaybeToSingle
      11: dup
      12: aload_0
      13: aload_1
      14: invokespecial #273                // Method io/reactivex/rxjava3/internal/operators/maybe/MaybeToSingle."<init>":(Lio/reactivex/rxjava3/core/MaybeSource;Ljava/lang/Object;)V
      17: invokestatic  #274                // Method io/reactivex/rxjava3/plugins/RxJavaPlugins.onAssembly:(Lio/reactivex/rxjava3/core/Single;)Lio/reactivex/rxjava3/core/Single;
      20: areturn

  public final <R> io.reactivex.rxjava3.core.Maybe<R> dematerialize(io.reactivex.rxjava3.functions.Function<? super T, io.reactivex.rxjava3.core.Notification<R>>);
    Code:
       0: aload_1
       1: ldc_w         #275                // String selector is null
       4: invokestatic  #3                  // Method java/util/Objects.requireNonNull:(Ljava/lang/Object;Ljava/lang/String;)Ljava/lang/Object;
       7: pop
       8: new           #276                // class io/reactivex/rxjava3/internal/operators/maybe/MaybeDematerialize
      11: dup
      12: aload_0
      13: aload_1
      14: invokespecial #277                // Method io/reactivex/rxjava3/internal/operators/maybe/MaybeDematerialize."<init>":(Lio/reactivex/rxjava3/core/Maybe;Lio/reactivex/rxjava3/functions/Function;)V
      17: invokestatic  #278                // Method io/reactivex/rxjava3/plugins/RxJavaPlugins.onAssembly:(Lio/reactivex/rxjava3/core/Maybe;)Lio/reactivex/rxjava3/core/Maybe;
      20: areturn

  public final io.reactivex.rxjava3.core.Maybe<T> delay(long, java.util.concurrent.TimeUnit);
    Code:
       0: aload_0
       1: lload_1
       2: aload_3
       3: invokestatic  #178                // Method io/reactivex/rxjava3/schedulers/Schedulers.computation:()Lio/reactivex/rxjava3/core/Scheduler;
       6: iconst_0
       7: invokevirtual #279                // Method delay:(JLjava/util/concurrent/TimeUnit;Lio/reactivex/rxjava3/core/Scheduler;Z)Lio/reactivex/rxjava3/core/Maybe;
      10: areturn

  public final io.reactivex.rxjava3.core.Maybe<T> delay(long, java.util.concurrent.TimeUnit, boolean);
    Code:
       0: aload_0
       1: lload_1
       2: aload_3
       3: invokestatic  #178                // Method io/reactivex/rxjava3/schedulers/Schedulers.computation:()Lio/reactivex/rxjava3/core/Scheduler;
       6: iload         4
       8: invokevirtual #279                // Method delay:(JLjava/util/concurrent/TimeUnit;Lio/reactivex/rxjava3/core/Scheduler;Z)Lio/reactivex/rxjava3/core/Maybe;
      11: areturn

  public final io.reactivex.rxjava3.core.Maybe<T> delay(long, java.util.concurrent.TimeUnit, io.reactivex.rxjava3.core.Scheduler);
    Code:
       0: aload_0
       1: lload_1
       2: aload_3
       3: aload         4
       5: iconst_0
       6: invokevirtual #279                // Method delay:(JLjava/util/concurrent/TimeUnit;Lio/reactivex/rxjava3/core/Scheduler;Z)Lio/reactivex/rxjava3/core/Maybe;
       9: areturn

  public final io.reactivex.rxjava3.core.Maybe<T> delay(long, java.util.concurrent.TimeUnit, io.reactivex.rxjava3.core.Scheduler, boolean);
    Code:
       0: aload_3
       1: ldc           #108                // String unit is null
       3: invokestatic  #3                  // Method java/util/Objects.requireNonNull:(Ljava/lang/Object;Ljava/lang/String;)Ljava/lang/Object;
       6: pop
       7: aload         4
       9: ldc           #180                // String scheduler is null
      11: invokestatic  #3                  // Method java/util/Objects.requireNonNull:(Ljava/lang/Object;Ljava/lang/String;)Ljava/lang/Object;
      14: pop
      15: new           #280                // class io/reactivex/rxjava3/internal/operators/maybe/MaybeDelay
      18: dup
      19: aload_0
      20: lconst_0
      21: lload_1
      22: invokestatic  #182                // Method java/lang/Math.max:(JJ)J
      25: aload_3
      26: aload         4
      28: iload         5
      30: invokespecial #281                // Method io/reactivex/rxjava3/internal/operators/maybe/MaybeDelay."<init>":(Lio/reactivex/rxjava3/core/MaybeSource;JLjava/util/concurrent/TimeUnit;Lio/reactivex/rxjava3/core/Scheduler;Z)V
      33: invokestatic  #282                // Method io/reactivex/rxjava3/plugins/RxJavaPlugins.onAssembly:(Lio/reactivex/rxjava3/core/Maybe;)Lio/reactivex/rxjava3/core/Maybe;
      36: areturn

  public final <U> io.reactivex.rxjava3.core.Maybe<T> delay(org.reactivestreams.Publisher<U>);
    Code:
       0: aload_1
       1: ldc_w         #283                // String delayIndicator is null
       4: invokestatic  #3                  // Method java/util/Objects.requireNonNull:(Ljava/lang/Object;Ljava/lang/String;)Ljava/lang/Object;
       7: pop
       8: new           #284                // class io/reactivex/rxjava3/internal/operators/maybe/MaybeDelayOtherPublisher
      11: dup
      12: aload_0
      13: aload_1
      14: invokespecial #285                // Method io/reactivex/rxjava3/internal/operators/maybe/MaybeDelayOtherPublisher."<init>":(Lio/reactivex/rxjava3/core/MaybeSource;Lorg/reactivestreams/Publisher;)V
      17: invokestatic  #286                // Method io/reactivex/rxjava3/plugins/RxJavaPlugins.onAssembly:(Lio/reactivex/rxjava3/core/Maybe;)Lio/reactivex/rxjava3/core/Maybe;
      20: areturn

  public final <U> io.reactivex.rxjava3.core.Maybe<T> delaySubscription(org.reactivestreams.Publisher<U>);
    Code:
       0: aload_1
       1: ldc_w         #287                // String subscriptionIndicator is null
       4: invokestatic  #3                  // Method java/util/Objects.requireNonNull:(Ljava/lang/Object;Ljava/lang/String;)Ljava/lang/Object;
       7: pop
       8: new           #288                // class io/reactivex/rxjava3/internal/operators/maybe/MaybeDelaySubscriptionOtherPublisher
      11: dup
      12: aload_0
      13: aload_1
      14: invokespecial #289                // Method io/reactivex/rxjava3/internal/operators/maybe/MaybeDelaySubscriptionOtherPublisher."<init>":(Lio/reactivex/rxjava3/core/MaybeSource;Lorg/reactivestreams/Publisher;)V
      17: invokestatic  #290                // Method io/reactivex/rxjava3/plugins/RxJavaPlugins.onAssembly:(Lio/reactivex/rxjava3/core/Maybe;)Lio/reactivex/rxjava3/core/Maybe;
      20: areturn

  public final io.reactivex.rxjava3.core.Maybe<T> delaySubscription(long, java.util.concurrent.TimeUnit);
    Code:
       0: aload_0
       1: lload_1
       2: aload_3
       3: invokestatic  #178                // Method io/reactivex/rxjava3/schedulers/Schedulers.computation:()Lio/reactivex/rxjava3/core/Scheduler;
       6: invokevirtual #291                // Method delaySubscription:(JLjava/util/concurrent/TimeUnit;Lio/reactivex/rxjava3/core/Scheduler;)Lio/reactivex/rxjava3/core/Maybe;
       9: areturn

  public final io.reactivex.rxjava3.core.Maybe<T> delaySubscription(long, java.util.concurrent.TimeUnit, io.reactivex.rxjava3.core.Scheduler);
    Code:
       0: aload_0
       1: lload_1
       2: aload_3
       3: aload         4
       5: invokestatic  #292                // Method io/reactivex/rxjava3/core/Flowable.timer:(JLjava/util/concurrent/TimeUnit;Lio/reactivex/rxjava3/core/Scheduler;)Lio/reactivex/rxjava3/core/Flowable;
       8: invokevirtual #293                // Method delaySubscription:(Lorg/reactivestreams/Publisher;)Lio/reactivex/rxjava3/core/Maybe;
      11: areturn

  public final io.reactivex.rxjava3.core.Maybe<T> doAfterSuccess(io.reactivex.rxjava3.functions.Consumer<? super T>);
    Code:
       0: aload_1
       1: ldc_w         #294                // String onAfterSuccess is null
       4: invokestatic  #3                  // Method java/util/Objects.requireNonNull:(Ljava/lang/Object;Ljava/lang/String;)Ljava/lang/Object;
       7: pop
       8: new           #295                // class io/reactivex/rxjava3/internal/operators/maybe/MaybeDoAfterSuccess
      11: dup
      12: aload_0
      13: aload_1
      14: invokespecial #296                // Method io/reactivex/rxjava3/internal/operators/maybe/MaybeDoAfterSuccess."<init>":(Lio/reactivex/rxjava3/core/MaybeSource;Lio/reactivex/rxjava3/functions/Consumer;)V
      17: invokestatic  #297                // Method io/reactivex/rxjava3/plugins/RxJavaPlugins.onAssembly:(Lio/reactivex/rxjava3/core/Maybe;)Lio/reactivex/rxjava3/core/Maybe;
      20: areturn

  public final io.reactivex.rxjava3.core.Maybe<T> doAfterTerminate(io.reactivex.rxjava3.functions.Action);
    Code:
       0: new           #298                // class io/reactivex/rxjava3/internal/operators/maybe/MaybePeek
       3: dup
       4: aload_0
       5: invokestatic  #238                // Method io/reactivex/rxjava3/internal/functions/Functions.emptyConsumer:()Lio/reactivex/rxjava3/functions/Consumer;
       8: invokestatic  #238                // Method io/reactivex/rxjava3/internal/functions/Functions.emptyConsumer:()Lio/reactivex/rxjava3/functions/Consumer;
      11: invokestatic  #238                // Method io/reactivex/rxjava3/internal/functions/Functions.emptyConsumer:()Lio/reactivex/rxjava3/functions/Consumer;
      14: getstatic     #240                // Field io/reactivex/rxjava3/internal/functions/Functions.EMPTY_ACTION:Lio/reactivex/rxjava3/functions/Action;
      17: aload_1
      18: ldc_w         #299                // String onAfterTerminate is null
      21: invokestatic  #3                  // Method java/util/Objects.requireNonNull:(Ljava/lang/Object;Ljava/lang/String;)Ljava/lang/Object;
      24: checkcast     #300                // class io/reactivex/rxjava3/functions/Action
      27: getstatic     #240                // Field io/reactivex/rxjava3/internal/functions/Functions.EMPTY_ACTION:Lio/reactivex/rxjava3/functions/Action;
      30: invokespecial #301                // Method io/reactivex/rxjava3/internal/operators/maybe/MaybePeek."<init>":(Lio/reactivex/rxjava3/core/MaybeSource;Lio/reactivex/rxjava3/functions/Consumer;Lio/reactivex/rxjava3/functions/Consumer;Lio/reactivex/rxjava3/functions/Consumer;Lio/reactivex/rxjava3/functions/Action;Lio/reactivex/rxjava3/functions/Action;Lio/reactivex/rxjava3/functions/Action;)V
      33: invokestatic  #302                // Method io/reactivex/rxjava3/plugins/RxJavaPlugins.onAssembly:(Lio/reactivex/rxjava3/core/Maybe;)Lio/reactivex/rxjava3/core/Maybe;
      36: areturn

  public final io.reactivex.rxjava3.core.Maybe<T> doFinally(io.reactivex.rxjava3.functions.Action);
    Code:
       0: aload_1
       1: ldc_w         #303                // String onFinally is null
       4: invokestatic  #3                  // Method java/util/Objects.requireNonNull:(Ljava/lang/Object;Ljava/lang/String;)Ljava/lang/Object;
       7: pop
       8: new           #304                // class io/reactivex/rxjava3/internal/operators/maybe/MaybeDoFinally
      11: dup
      12: aload_0
      13: aload_1
      14: invokespecial #305                // Method io/reactivex/rxjava3/internal/operators/maybe/MaybeDoFinally."<init>":(Lio/reactivex/rxjava3/core/MaybeSource;Lio/reactivex/rxjava3/functions/Action;)V
      17: invokestatic  #306                // Method io/reactivex/rxjava3/plugins/RxJavaPlugins.onAssembly:(Lio/reactivex/rxjava3/core/Maybe;)Lio/reactivex/rxjava3/core/Maybe;
      20: areturn

  public final io.reactivex.rxjava3.core.Maybe<T> doOnDispose(io.reactivex.rxjava3.functions.Action);
    Code:
       0: new           #298                // class io/reactivex/rxjava3/internal/operators/maybe/MaybePeek
       3: dup
       4: aload_0
       5: invokestatic  #238                // Method io/reactivex/rxjava3/internal/functions/Functions.emptyConsumer:()Lio/reactivex/rxjava3/functions/Consumer;
       8: invokestatic  #238                // Method io/reactivex/rxjava3/internal/functions/Functions.emptyConsumer:()Lio/reactivex/rxjava3/functions/Consumer;
      11: invokestatic  #238                // Method io/reactivex/rxjava3/internal/functions/Functions.emptyConsumer:()Lio/reactivex/rxjava3/functions/Consumer;
      14: getstatic     #240                // Field io/reactivex/rxjava3/internal/functions/Functions.EMPTY_ACTION:Lio/reactivex/rxjava3/functions/Action;
      17: getstatic     #240                // Field io/reactivex/rxjava3/internal/functions/Functions.EMPTY_ACTION:Lio/reactivex/rxjava3/functions/Action;
      20: aload_1
      21: ldc_w         #307                // String onDispose is null
      24: invokestatic  #3                  // Method java/util/Objects.requireNonNull:(Ljava/lang/Object;Ljava/lang/String;)Ljava/lang/Object;
      27: checkcast     #300                // class io/reactivex/rxjava3/functions/Action
      30: invokespecial #301                // Method io/reactivex/rxjava3/internal/operators/maybe/MaybePeek."<init>":(Lio/reactivex/rxjava3/core/MaybeSource;Lio/reactivex/rxjava3/functions/Consumer;Lio/reactivex/rxjava3/functions/Consumer;Lio/reactivex/rxjava3/functions/Consumer;Lio/reactivex/rxjava3/functions/Action;Lio/reactivex/rxjava3/functions/Action;Lio/reactivex/rxjava3/functions/Action;)V
      33: invokestatic  #308                // Method io/reactivex/rxjava3/plugins/RxJavaPlugins.onAssembly:(Lio/reactivex/rxjava3/core/Maybe;)Lio/reactivex/rxjava3/core/Maybe;
      36: areturn

  public final io.reactivex.rxjava3.core.Maybe<T> doOnComplete(io.reactivex.rxjava3.functions.Action);
    Code:
       0: new           #298                // class io/reactivex/rxjava3/internal/operators/maybe/MaybePeek
       3: dup
       4: aload_0
       5: invokestatic  #238                // Method io/reactivex/rxjava3/internal/functions/Functions.emptyConsumer:()Lio/reactivex/rxjava3/functions/Consumer;
       8: invokestatic  #238                // Method io/reactivex/rxjava3/internal/functions/Functions.emptyConsumer:()Lio/reactivex/rxjava3/functions/Consumer;
      11: invokestatic  #238                // Method io/reactivex/rxjava3/internal/functions/Functions.emptyConsumer:()Lio/reactivex/rxjava3/functions/Consumer;
      14: aload_1
      15: ldc           #244                // String onComplete is null
      17: invokestatic  #3                  // Method java/util/Objects.requireNonNull:(Ljava/lang/Object;Ljava/lang/String;)Ljava/lang/Object;
      20: checkcast     #300                // class io/reactivex/rxjava3/functions/Action
      23: getstatic     #240                // Field io/reactivex/rxjava3/internal/functions/Functions.EMPTY_ACTION:Lio/reactivex/rxjava3/functions/Action;
      26: getstatic     #240                // Field io/reactivex/rxjava3/internal/functions/Functions.EMPTY_ACTION:Lio/reactivex/rxjava3/functions/Action;
      29: invokespecial #301                // Method io/reactivex/rxjava3/internal/operators/maybe/MaybePeek."<init>":(Lio/reactivex/rxjava3/core/MaybeSource;Lio/reactivex/rxjava3/functions/Consumer;Lio/reactivex/rxjava3/functions/Consumer;Lio/reactivex/rxjava3/functions/Consumer;Lio/reactivex/rxjava3/functions/Action;Lio/reactivex/rxjava3/functions/Action;Lio/reactivex/rxjava3/functions/Action;)V
      32: invokestatic  #309                // Method io/reactivex/rxjava3/plugins/RxJavaPlugins.onAssembly:(Lio/reactivex/rxjava3/core/Maybe;)Lio/reactivex/rxjava3/core/Maybe;
      35: areturn

  public final io.reactivex.rxjava3.core.Maybe<T> doOnError(io.reactivex.rxjava3.functions.Consumer<? super java.lang.Throwable>);
    Code:
       0: new           #298                // class io/reactivex/rxjava3/internal/operators/maybe/MaybePeek
       3: dup
       4: aload_0
       5: invokestatic  #238                // Method io/reactivex/rxjava3/internal/functions/Functions.emptyConsumer:()Lio/reactivex/rxjava3/functions/Consumer;
       8: invokestatic  #238                // Method io/reactivex/rxjava3/internal/functions/Functions.emptyConsumer:()Lio/reactivex/rxjava3/functions/Consumer;
      11: aload_1
      12: ldc           #243                // String onError is null
      14: invokestatic  #3                  // Method java/util/Objects.requireNonNull:(Ljava/lang/Object;Ljava/lang/String;)Ljava/lang/Object;
      17: checkcast     #310                // class io/reactivex/rxjava3/functions/Consumer
      20: getstatic     #240                // Field io/reactivex/rxjava3/internal/functions/Functions.EMPTY_ACTION:Lio/reactivex/rxjava3/functions/Action;
      23: getstatic     #240                // Field io/reactivex/rxjava3/internal/functions/Functions.EMPTY_ACTION:Lio/reactivex/rxjava3/functions/Action;
      26: getstatic     #240                // Field io/reactivex/rxjava3/internal/functions/Functions.EMPTY_ACTION:Lio/reactivex/rxjava3/functions/Action;
      29: invokespecial #301                // Method io/reactivex/rxjava3/internal/operators/maybe/MaybePeek."<init>":(Lio/reactivex/rxjava3/core/MaybeSource;Lio/reactivex/rxjava3/functions/Consumer;Lio/reactivex/rxjava3/functions/Consumer;Lio/reactivex/rxjava3/functions/Consumer;Lio/reactivex/rxjava3/functions/Action;Lio/reactivex/rxjava3/functions/Action;Lio/reactivex/rxjava3/functions/Action;)V
      32: invokestatic  #311                // Method io/reactivex/rxjava3/plugins/RxJavaPlugins.onAssembly:(Lio/reactivex/rxjava3/core/Maybe;)Lio/reactivex/rxjava3/core/Maybe;
      35: areturn

  public final io.reactivex.rxjava3.core.Maybe<T> doOnEvent(io.reactivex.rxjava3.functions.BiConsumer<? super T, ? super java.lang.Throwable>);
    Code:
       0: aload_1
       1: ldc_w         #312                // String onEvent is null
       4: invokestatic  #3                  // Method java/util/Objects.requireNonNull:(Ljava/lang/Object;Ljava/lang/String;)Ljava/lang/Object;
       7: pop
       8: new           #313                // class io/reactivex/rxjava3/internal/operators/maybe/MaybeDoOnEvent
      11: dup
      12: aload_0
      13: aload_1
      14: invokespecial #314                // Method io/reactivex/rxjava3/internal/operators/maybe/MaybeDoOnEvent."<init>":(Lio/reactivex/rxjava3/core/MaybeSource;Lio/reactivex/rxjava3/functions/BiConsumer;)V
      17: invokestatic  #315                // Method io/reactivex/rxjava3/plugins/RxJavaPlugins.onAssembly:(Lio/reactivex/rxjava3/core/Maybe;)Lio/reactivex/rxjava3/core/Maybe;
      20: areturn

  public final io.reactivex.rxjava3.core.Maybe<T> doOnLifecycle(io.reactivex.rxjava3.functions.Consumer<? super io.reactivex.rxjava3.disposables.Disposable>, io.reactivex.rxjava3.functions.Action);
    Code:
       0: aload_1
       1: ldc           #71                 // String onSubscribe is null
       3: invokestatic  #3                  // Method java/util/Objects.requireNonNull:(Ljava/lang/Object;Ljava/lang/String;)Ljava/lang/Object;
       6: pop
       7: aload_2
       8: ldc_w         #307                // String onDispose is null
      11: invokestatic  #3                  // Method java/util/Objects.requireNonNull:(Ljava/lang/Object;Ljava/lang/String;)Ljava/lang/Object;
      14: pop
      15: new           #316                // class io/reactivex/rxjava3/internal/operators/maybe/MaybeDoOnLifecycle
      18: dup
      19: aload_0
      20: aload_1
      21: aload_2
      22: invokespecial #317                // Method io/reactivex/rxjava3/internal/operators/maybe/MaybeDoOnLifecycle."<init>":(Lio/reactivex/rxjava3/core/Maybe;Lio/reactivex/rxjava3/functions/Consumer;Lio/reactivex/rxjava3/functions/Action;)V
      25: invokestatic  #318                // Method io/reactivex/rxjava3/plugins/RxJavaPlugins.onAssembly:(Lio/reactivex/rxjava3/core/Maybe;)Lio/reactivex/rxjava3/core/Maybe;
      28: areturn

  public final io.reactivex.rxjava3.core.Maybe<T> doOnSubscribe(io.reactivex.rxjava3.functions.Consumer<? super io.reactivex.rxjava3.disposables.Disposable>);
    Code:
       0: new           #298                // class io/reactivex/rxjava3/internal/operators/maybe/MaybePeek
       3: dup
       4: aload_0
       5: aload_1
       6: ldc           #71                 // String onSubscribe is null
       8: invokestatic  #3                  // Method java/util/Objects.requireNonNull:(Ljava/lang/Object;Ljava/lang/String;)Ljava/lang/Object;
      11: checkcast     #310                // class io/reactivex/rxjava3/functions/Consumer
      14: invokestatic  #238                // Method io/reactivex/rxjava3/internal/functions/Functions.emptyConsumer:()Lio/reactivex/rxjava3/functions/Consumer;
      17: invokestatic  #238                // Method io/reactivex/rxjava3/internal/functions/Functions.emptyConsumer:()Lio/reactivex/rxjava3/functions/Consumer;
      20: getstatic     #240                // Field io/reactivex/rxjava3/internal/functions/Functions.EMPTY_ACTION:Lio/reactivex/rxjava3/functions/Action;
      23: getstatic     #240                // Field io/reactivex/rxjava3/internal/functions/Functions.EMPTY_ACTION:Lio/reactivex/rxjava3/functions/Action;
      26: getstatic     #240                // Field io/reactivex/rxjava3/internal/functions/Functions.EMPTY_ACTION:Lio/reactivex/rxjava3/functions/Action;
      29: invokespecial #301                // Method io/reactivex/rxjava3/internal/operators/maybe/MaybePeek."<init>":(Lio/reactivex/rxjava3/core/MaybeSource;Lio/reactivex/rxjava3/functions/Consumer;Lio/reactivex/rxjava3/functions/Consumer;Lio/reactivex/rxjava3/functions/Consumer;Lio/reactivex/rxjava3/functions/Action;Lio/reactivex/rxjava3/functions/Action;Lio/reactivex/rxjava3/functions/Action;)V
      32: invokestatic  #319                // Method io/reactivex/rxjava3/plugins/RxJavaPlugins.onAssembly:(Lio/reactivex/rxjava3/core/Maybe;)Lio/reactivex/rxjava3/core/Maybe;
      35: areturn

  public final io.reactivex.rxjava3.core.Maybe<T> doOnTerminate(io.reactivex.rxjava3.functions.Action);
    Code:
       0: aload_1
       1: ldc_w         #320                // String onTerminate is null
       4: invokestatic  #3                  // Method java/util/Objects.requireNonNull:(Ljava/lang/Object;Ljava/lang/String;)Ljava/lang/Object;
       7: pop
       8: new           #321                // class io/reactivex/rxjava3/internal/operators/maybe/MaybeDoOnTerminate
      11: dup
      12: aload_0
      13: aload_1
      14: invokespecial #322                // Method io/reactivex/rxjava3/internal/operators/maybe/MaybeDoOnTerminate."<init>":(Lio/reactivex/rxjava3/core/MaybeSource;Lio/reactivex/rxjava3/functions/Action;)V
      17: invokestatic  #323                // Method io/reactivex/rxjava3/plugins/RxJavaPlugins.onAssembly:(Lio/reactivex/rxjava3/core/Maybe;)Lio/reactivex/rxjava3/core/Maybe;
      20: areturn

  public final io.reactivex.rxjava3.core.Maybe<T> doOnSuccess(io.reactivex.rxjava3.functions.Consumer<? super T>);
    Code:
       0: new           #298                // class io/reactivex/rxjava3/internal/operators/maybe/MaybePeek
       3: dup
       4: aload_0
       5: invokestatic  #238                // Method io/reactivex/rxjava3/internal/functions/Functions.emptyConsumer:()Lio/reactivex/rxjava3/functions/Consumer;
       8: aload_1
       9: ldc           #242                // String onSuccess is null
      11: invokestatic  #3                  // Method java/util/Objects.requireNonNull:(Ljava/lang/Object;Ljava/lang/String;)Ljava/lang/Object;
      14: checkcast     #310                // class io/reactivex/rxjava3/functions/Consumer
      17: invokestatic  #238                // Method io/reactivex/rxjava3/internal/functions/Functions.emptyConsumer:()Lio/reactivex/rxjava3/functions/Consumer;
      20: getstatic     #240                // Field io/reactivex/rxjava3/internal/functions/Functions.EMPTY_ACTION:Lio/reactivex/rxjava3/functions/Action;
      23: getstatic     #240                // Field io/reactivex/rxjava3/internal/functions/Functions.EMPTY_ACTION:Lio/reactivex/rxjava3/functions/Action;
      26: getstatic     #240                // Field io/reactivex/rxjava3/internal/functions/Functions.EMPTY_ACTION:Lio/reactivex/rxjava3/functions/Action;
      29: invokespecial #301                // Method io/reactivex/rxjava3/internal/operators/maybe/MaybePeek."<init>":(Lio/reactivex/rxjava3/core/MaybeSource;Lio/reactivex/rxjava3/functions/Consumer;Lio/reactivex/rxjava3/functions/Consumer;Lio/reactivex/rxjava3/functions/Consumer;Lio/reactivex/rxjava3/functions/Action;Lio/reactivex/rxjava3/functions/Action;Lio/reactivex/rxjava3/functions/Action;)V
      32: invokestatic  #324                // Method io/reactivex/rxjava3/plugins/RxJavaPlugins.onAssembly:(Lio/reactivex/rxjava3/core/Maybe;)Lio/reactivex/rxjava3/core/Maybe;
      35: areturn

  public final io.reactivex.rxjava3.core.Maybe<T> filter(io.reactivex.rxjava3.functions.Predicate<? super T>);
    Code:
       0: aload_1
       1: ldc_w         #325                // String predicate is null
       4: invokestatic  #3                  // Method java/util/Objects.requireNonNull:(Ljava/lang/Object;Ljava/lang/String;)Ljava/lang/Object;
       7: pop
       8: new           #326                // class io/reactivex/rxjava3/internal/operators/maybe/MaybeFilter
      11: dup
      12: aload_0
      13: aload_1
      14: invokespecial #327                // Method io/reactivex/rxjava3/internal/operators/maybe/MaybeFilter."<init>":(Lio/reactivex/rxjava3/core/MaybeSource;Lio/reactivex/rxjava3/functions/Predicate;)V
      17: invokestatic  #328                // Method io/reactivex/rxjava3/plugins/RxJavaPlugins.onAssembly:(Lio/reactivex/rxjava3/core/Maybe;)Lio/reactivex/rxjava3/core/Maybe;
      20: areturn

  public final <R> io.reactivex.rxjava3.core.Maybe<R> flatMap(io.reactivex.rxjava3.functions.Function<? super T, ? extends io.reactivex.rxjava3.core.MaybeSource<? extends R>>);
    Code:
       0: aload_1
       1: ldc_w         #329                // String mapper is null
       4: invokestatic  #3                  // Method java/util/Objects.requireNonNull:(Ljava/lang/Object;Ljava/lang/String;)Ljava/lang/Object;
       7: pop
       8: new           #139                // class io/reactivex/rxjava3/internal/operators/maybe/MaybeFlatten
      11: dup
      12: aload_0
      13: aload_1
      14: invokespecial #141                // Method io/reactivex/rxjava3/internal/operators/maybe/MaybeFlatten."<init>":(Lio/reactivex/rxjava3/core/MaybeSource;Lio/reactivex/rxjava3/functions/Function;)V
      17: invokestatic  #330                // Method io/reactivex/rxjava3/plugins/RxJavaPlugins.onAssembly:(Lio/reactivex/rxjava3/core/Maybe;)Lio/reactivex/rxjava3/core/Maybe;
      20: areturn

  public final <R> io.reactivex.rxjava3.core.Maybe<R> flatMap(io.reactivex.rxjava3.functions.Function<? super T, ? extends io.reactivex.rxjava3.core.MaybeSource<? extends R>>, io.reactivex.rxjava3.functions.Function<? super java.lang.Throwable, ? extends io.reactivex.rxjava3.core.MaybeSource<? extends R>>, io.reactivex.rxjava3.functions.Supplier<? extends io.reactivex.rxjava3.core.MaybeSource<? extends R>>);
    Code:
       0: aload_1
       1: ldc_w         #331                // String onSuccessMapper is null
       4: invokestatic  #3                  // Method java/util/Objects.requireNonNull:(Ljava/lang/Object;Ljava/lang/String;)Ljava/lang/Object;
       7: pop
       8: aload_2
       9: ldc_w         #332                // String onErrorMapper is null
      12: invokestatic  #3                  // Method java/util/Objects.requireNonNull:(Ljava/lang/Object;Ljava/lang/String;)Ljava/lang/Object;
      15: pop
      16: aload_3
      17: ldc_w         #333                // String onCompleteSupplier is null
      20: invokestatic  #3                  // Method java/util/Objects.requireNonNull:(Ljava/lang/Object;Ljava/lang/String;)Ljava/lang/Object;
      23: pop
      24: new           #334                // class io/reactivex/rxjava3/internal/operators/maybe/MaybeFlatMapNotification
      27: dup
      28: aload_0
      29: aload_1
      30: aload_2
      31: aload_3
      32: invokespecial #335                // Method io/reactivex/rxjava3/internal/operators/maybe/MaybeFlatMapNotification."<init>":(Lio/reactivex/rxjava3/core/MaybeSource;Lio/reactivex/rxjava3/functions/Function;Lio/reactivex/rxjava3/functions/Function;Lio/reactivex/rxjava3/functions/Supplier;)V
      35: invokestatic  #336                // Method io/reactivex/rxjava3/plugins/RxJavaPlugins.onAssembly:(Lio/reactivex/rxjava3/core/Maybe;)Lio/reactivex/rxjava3/core/Maybe;
      38: areturn

  public final <U, R> io.reactivex.rxjava3.core.Maybe<R> flatMap(io.reactivex.rxjava3.functions.Function<? super T, ? extends io.reactivex.rxjava3.core.MaybeSource<? extends U>>, io.reactivex.rxjava3.functions.BiFunction<? super T, ? super U, ? extends R>);
    Code:
       0: aload_1
       1: ldc_w         #329                // String mapper is null
       4: invokestatic  #3                  // Method java/util/Objects.requireNonNull:(Ljava/lang/Object;Ljava/lang/String;)Ljava/lang/Object;
       7: pop
       8: aload_2
       9: ldc_w         #337                // String combiner is null
      12: invokestatic  #3                  // Method java/util/Objects.requireNonNull:(Ljava/lang/Object;Ljava/lang/String;)Ljava/lang/Object;
      15: pop
      16: new           #338                // class io/reactivex/rxjava3/internal/operators/maybe/MaybeFlatMapBiSelector
      19: dup
      20: aload_0
      21: aload_1
      22: aload_2
      23: invokespecial #339                // Method io/reactivex/rxjava3/internal/operators/maybe/MaybeFlatMapBiSelector."<init>":(Lio/reactivex/rxjava3/core/MaybeSource;Lio/reactivex/rxjava3/functions/Function;Lio/reactivex/rxjava3/functions/BiFunction;)V
      26: invokestatic  #340                // Method io/reactivex/rxjava3/plugins/RxJavaPlugins.onAssembly:(Lio/reactivex/rxjava3/core/Maybe;)Lio/reactivex/rxjava3/core/Maybe;
      29: areturn

  public final <U> io.reactivex.rxjava3.core.Flowable<U> flattenAsFlowable(io.reactivex.rxjava3.functions.Function<? super T, ? extends java.lang.Iterable<? extends U>>);
    Code:
       0: aload_1
       1: ldc_w         #329                // String mapper is null
       4: invokestatic  #3                  // Method java/util/Objects.requireNonNull:(Ljava/lang/Object;Ljava/lang/String;)Ljava/lang/Object;
       7: pop
       8: new           #341                // class io/reactivex/rxjava3/internal/operators/maybe/MaybeFlatMapIterableFlowable
      11: dup
      12: aload_0
      13: aload_1
      14: invokespecial #342                // Method io/reactivex/rxjava3/internal/operators/maybe/MaybeFlatMapIterableFlowable."<init>":(Lio/reactivex/rxjava3/core/MaybeSource;Lio/reactivex/rxjava3/functions/Function;)V
      17: invokestatic  #343                // Method io/reactivex/rxjava3/plugins/RxJavaPlugins.onAssembly:(Lio/reactivex/rxjava3/core/Flowable;)Lio/reactivex/rxjava3/core/Flowable;
      20: areturn

  public final <U> io.reactivex.rxjava3.core.Observable<U> flattenAsObservable(io.reactivex.rxjava3.functions.Function<? super T, ? extends java.lang.Iterable<? extends U>>);
    Code:
       0: aload_1
       1: ldc_w         #329                // String mapper is null
       4: invokestatic  #3                  // Method java/util/Objects.requireNonNull:(Ljava/lang/Object;Ljava/lang/String;)Ljava/lang/Object;
       7: pop
       8: new           #344                // class io/reactivex/rxjava3/internal/operators/maybe/MaybeFlatMapIterableObservable
      11: dup
      12: aload_0
      13: aload_1
      14: invokespecial #345                // Method io/reactivex/rxjava3/internal/operators/maybe/MaybeFlatMapIterableObservable."<init>":(Lio/reactivex/rxjava3/core/MaybeSource;Lio/reactivex/rxjava3/functions/Function;)V
      17: invokestatic  #346                // Method io/reactivex/rxjava3/plugins/RxJavaPlugins.onAssembly:(Lio/reactivex/rxjava3/core/Observable;)Lio/reactivex/rxjava3/core/Observable;
      20: areturn

  public final <R> io.reactivex.rxjava3.core.Observable<R> flatMapObservable(io.reactivex.rxjava3.functions.Function<? super T, ? extends io.reactivex.rxjava3.core.ObservableSource<? extends R>>);
    Code:
       0: aload_1
       1: ldc_w         #329                // String mapper is null
       4: invokestatic  #3                  // Method java/util/Objects.requireNonNull:(Ljava/lang/Object;Ljava/lang/String;)Ljava/lang/Object;
       7: pop
       8: new           #347                // class io/reactivex/rxjava3/internal/operators/mixed/MaybeFlatMapObservable
      11: dup
      12: aload_0
      13: aload_1
      14: invokespecial #348                // Method io/reactivex/rxjava3/internal/operators/mixed/MaybeFlatMapObservable."<init>":(Lio/reactivex/rxjava3/core/MaybeSource;Lio/reactivex/rxjava3/functions/Function;)V
      17: invokestatic  #349                // Method io/reactivex/rxjava3/plugins/RxJavaPlugins.onAssembly:(Lio/reactivex/rxjava3/core/Observable;)Lio/reactivex/rxjava3/core/Observable;
      20: areturn

  public final <R> io.reactivex.rxjava3.core.Flowable<R> flatMapPublisher(io.reactivex.rxjava3.functions.Function<? super T, ? extends org.reactivestreams.Publisher<? extends R>>);
    Code:
       0: aload_1
       1: ldc_w         #329                // String mapper is null
       4: invokestatic  #3                  // Method java/util/Objects.requireNonNull:(Ljava/lang/Object;Ljava/lang/String;)Ljava/lang/Object;
       7: pop
       8: new           #350                // class io/reactivex/rxjava3/internal/operators/mixed/MaybeFlatMapPublisher
      11: dup
      12: aload_0
      13: aload_1
      14: invokespecial #351                // Method io/reactivex/rxjava3/internal/operators/mixed/MaybeFlatMapPublisher."<init>":(Lio/reactivex/rxjava3/core/MaybeSource;Lio/reactivex/rxjava3/functions/Function;)V
      17: invokestatic  #352                // Method io/reactivex/rxjava3/plugins/RxJavaPlugins.onAssembly:(Lio/reactivex/rxjava3/core/Flowable;)Lio/reactivex/rxjava3/core/Flowable;
      20: areturn

  public final <R> io.reactivex.rxjava3.core.Maybe<R> flatMapSingle(io.reactivex.rxjava3.functions.Function<? super T, ? extends io.reactivex.rxjava3.core.SingleSource<? extends R>>);
    Code:
       0: aload_1
       1: ldc_w         #329                // String mapper is null
       4: invokestatic  #3                  // Method java/util/Objects.requireNonNull:(Ljava/lang/Object;Ljava/lang/String;)Ljava/lang/Object;
       7: pop
       8: new           #353                // class io/reactivex/rxjava3/internal/operators/maybe/MaybeFlatMapSingle
      11: dup
      12: aload_0
      13: aload_1
      14: invokespecial #354                // Method io/reactivex/rxjava3/internal/operators/maybe/MaybeFlatMapSingle."<init>":(Lio/reactivex/rxjava3/core/MaybeSource;Lio/reactivex/rxjava3/functions/Function;)V
      17: invokestatic  #355                // Method io/reactivex/rxjava3/plugins/RxJavaPlugins.onAssembly:(Lio/reactivex/rxjava3/core/Maybe;)Lio/reactivex/rxjava3/core/Maybe;
      20: areturn

  public final io.reactivex.rxjava3.core.Completable flatMapCompletable(io.reactivex.rxjava3.functions.Function<? super T, ? extends io.reactivex.rxjava3.core.CompletableSource>);
    Code:
       0: aload_1
       1: ldc_w         #329                // String mapper is null
       4: invokestatic  #3                  // Method java/util/Objects.requireNonNull:(Ljava/lang/Object;Ljava/lang/String;)Ljava/lang/Object;
       7: pop
       8: new           #356                // class io/reactivex/rxjava3/internal/operators/maybe/MaybeFlatMapCompletable
      11: dup
      12: aload_0
      13: aload_1
      14: invokespecial #357                // Method io/reactivex/rxjava3/internal/operators/maybe/MaybeFlatMapCompletable."<init>":(Lio/reactivex/rxjava3/core/MaybeSource;Lio/reactivex/rxjava3/functions/Function;)V
      17: invokestatic  #358                // Method io/reactivex/rxjava3/plugins/RxJavaPlugins.onAssembly:(Lio/reactivex/rxjava3/core/Completable;)Lio/reactivex/rxjava3/core/Completable;
      20: areturn

  public final io.reactivex.rxjava3.core.Maybe<T> hide();
    Code:
       0: new           #359                // class io/reactivex/rxjava3/internal/operators/maybe/MaybeHide
       3: dup
       4: aload_0
       5: invokespecial #360                // Method io/reactivex/rxjava3/internal/operators/maybe/MaybeHide."<init>":(Lio/reactivex/rxjava3/core/MaybeSource;)V
       8: invokestatic  #361                // Method io/reactivex/rxjava3/plugins/RxJavaPlugins.onAssembly:(Lio/reactivex/rxjava3/core/Maybe;)Lio/reactivex/rxjava3/core/Maybe;
      11: areturn

  public final io.reactivex.rxjava3.core.Completable ignoreElement();
    Code:
       0: new           #362                // class io/reactivex/rxjava3/internal/operators/maybe/MaybeIgnoreElementCompletable
       3: dup
       4: aload_0
       5: invokespecial #363                // Method io/reactivex/rxjava3/internal/operators/maybe/MaybeIgnoreElementCompletable."<init>":(Lio/reactivex/rxjava3/core/MaybeSource;)V
       8: invokestatic  #358                // Method io/reactivex/rxjava3/plugins/RxJavaPlugins.onAssembly:(Lio/reactivex/rxjava3/core/Completable;)Lio/reactivex/rxjava3/core/Completable;
      11: areturn

  public final io.reactivex.rxjava3.core.Single<java.lang.Boolean> isEmpty();
    Code:
       0: new           #364                // class io/reactivex/rxjava3/internal/operators/maybe/MaybeIsEmptySingle
       3: dup
       4: aload_0
       5: invokespecial #365                // Method io/reactivex/rxjava3/internal/operators/maybe/MaybeIsEmptySingle."<init>":(Lio/reactivex/rxjava3/core/MaybeSource;)V
       8: invokestatic  #366                // Method io/reactivex/rxjava3/plugins/RxJavaPlugins.onAssembly:(Lio/reactivex/rxjava3/core/Single;)Lio/reactivex/rxjava3/core/Single;
      11: areturn

  public final <R> io.reactivex.rxjava3.core.Maybe<R> lift(io.reactivex.rxjava3.core.MaybeOperator<? extends R, ? super T>);
    Code:
       0: aload_1
       1: ldc_w         #367                // String lift is null
       4: invokestatic  #3                  // Method java/util/Objects.requireNonNull:(Ljava/lang/Object;Ljava/lang/String;)Ljava/lang/Object;
       7: pop
       8: new           #368                // class io/reactivex/rxjava3/internal/operators/maybe/MaybeLift
      11: dup
      12: aload_0
      13: aload_1
      14: invokespecial #369                // Method io/reactivex/rxjava3/internal/operators/maybe/MaybeLift."<init>":(Lio/reactivex/rxjava3/core/MaybeSource;Lio/reactivex/rxjava3/core/MaybeOperator;)V
      17: invokestatic  #370                // Method io/reactivex/rxjava3/plugins/RxJavaPlugins.onAssembly:(Lio/reactivex/rxjava3/core/Maybe;)Lio/reactivex/rxjava3/core/Maybe;
      20: areturn

  public final <R> io.reactivex.rxjava3.core.Maybe<R> map(io.reactivex.rxjava3.functions.Function<? super T, ? extends R>);
    Code:
       0: aload_1
       1: ldc_w         #329                // String mapper is null
       4: invokestatic  #3                  // Method java/util/Objects.requireNonNull:(Ljava/lang/Object;Ljava/lang/String;)Ljava/lang/Object;
       7: pop
       8: new           #371                // class io/reactivex/rxjava3/internal/operators/maybe/MaybeMap
      11: dup
      12: aload_0
      13: aload_1
      14: invokespecial #372                // Method io/reactivex/rxjava3/internal/operators/maybe/MaybeMap."<init>":(Lio/reactivex/rxjava3/core/MaybeSource;Lio/reactivex/rxjava3/functions/Function;)V
      17: invokestatic  #373                // Method io/reactivex/rxjava3/plugins/RxJavaPlugins.onAssembly:(Lio/reactivex/rxjava3/core/Maybe;)Lio/reactivex/rxjava3/core/Maybe;
      20: areturn

  public final io.reactivex.rxjava3.core.Single<io.reactivex.rxjava3.core.Notification<T>> materialize();
    Code:
       0: new           #374                // class io/reactivex/rxjava3/internal/operators/maybe/MaybeMaterialize
       3: dup
       4: aload_0
       5: invokespecial #375                // Method io/reactivex/rxjava3/internal/operators/maybe/MaybeMaterialize."<init>":(Lio/reactivex/rxjava3/core/Maybe;)V
       8: invokestatic  #376                // Method io/reactivex/rxjava3/plugins/RxJavaPlugins.onAssembly:(Lio/reactivex/rxjava3/core/Single;)Lio/reactivex/rxjava3/core/Single;
      11: areturn

  public final io.reactivex.rxjava3.core.Flowable<T> mergeWith(io.reactivex.rxjava3.core.MaybeSource<? extends T>);
    Code:
       0: aload_1
       1: ldc           #230                // String other is null
       3: invokestatic  #3                  // Method java/util/Objects.requireNonNull:(Ljava/lang/Object;Ljava/lang/String;)Ljava/lang/Object;
       6: pop
       7: aload_0
       8: aload_1
       9: invokestatic  #377                // Method merge:(Lio/reactivex/rxjava3/core/MaybeSource;Lio/reactivex/rxjava3/core/MaybeSource;)Lio/reactivex/rxjava3/core/Flowable;
      12: areturn

  public final io.reactivex.rxjava3.core.Maybe<T> observeOn(io.reactivex.rxjava3.core.Scheduler);
    Code:
       0: aload_1
       1: ldc           #180                // String scheduler is null
       3: invokestatic  #3                  // Method java/util/Objects.requireNonNull:(Ljava/lang/Object;Ljava/lang/String;)Ljava/lang/Object;
       6: pop
       7: new           #378                // class io/reactivex/rxjava3/internal/operators/maybe/MaybeObserveOn
      10: dup
      11: aload_0
      12: aload_1
      13: invokespecial #379                // Method io/reactivex/rxjava3/internal/operators/maybe/MaybeObserveOn."<init>":(Lio/reactivex/rxjava3/core/MaybeSource;Lio/reactivex/rxjava3/core/Scheduler;)V
      16: invokestatic  #380                // Method io/reactivex/rxjava3/plugins/RxJavaPlugins.onAssembly:(Lio/reactivex/rxjava3/core/Maybe;)Lio/reactivex/rxjava3/core/Maybe;
      19: areturn

  public final <U> io.reactivex.rxjava3.core.Maybe<U> ofType(java.lang.Class<U>);
    Code:
       0: aload_1
       1: ldc           #254                // String clazz is null
       3: invokestatic  #3                  // Method java/util/Objects.requireNonNull:(Ljava/lang/Object;Ljava/lang/String;)Ljava/lang/Object;
       6: pop
       7: aload_0
       8: aload_1
       9: invokestatic  #381                // Method io/reactivex/rxjava3/internal/functions/Functions.isInstanceOf:(Ljava/lang/Class;)Lio/reactivex/rxjava3/functions/Predicate;
      12: invokevirtual #382                // Method filter:(Lio/reactivex/rxjava3/functions/Predicate;)Lio/reactivex/rxjava3/core/Maybe;
      15: aload_1
      16: invokevirtual #383                // Method cast:(Ljava/lang/Class;)Lio/reactivex/rxjava3/core/Maybe;
      19: areturn

  public final <R> R to(io.reactivex.rxjava3.core.MaybeConverter<T, ? extends R>);
    Code:
       0: aload_1
       1: ldc_w         #384                // String converter is null
       4: invokestatic  #3                  // Method java/util/Objects.requireNonNull:(Ljava/lang/Object;Ljava/lang/String;)Ljava/lang/Object;
       7: checkcast     #385                // class io/reactivex/rxjava3/core/MaybeConverter
      10: aload_0
      11: invokeinterface #386,  2          // InterfaceMethod io/reactivex/rxjava3/core/MaybeConverter.apply:(Lio/reactivex/rxjava3/core/Maybe;)Ljava/lang/Object;
      16: areturn

  public final io.reactivex.rxjava3.core.Flowable<T> toFlowable();
    Code:
       0: aload_0
       1: instanceof    #387                // class io/reactivex/rxjava3/internal/fuseable/FuseToFlowable
       4: ifeq          17
       7: aload_0
       8: checkcast     #387                // class io/reactivex/rxjava3/internal/fuseable/FuseToFlowable
      11: invokeinterface #388,  1          // InterfaceMethod io/reactivex/rxjava3/internal/fuseable/FuseToFlowable.fuseToFlowable:()Lio/reactivex/rxjava3/core/Flowable;
      16: areturn
      17: new           #30                 // class io/reactivex/rxjava3/internal/operators/maybe/MaybeToFlowable
      20: dup
      21: aload_0
      22: invokespecial #31                 // Method io/reactivex/rxjava3/internal/operators/maybe/MaybeToFlowable."<init>":(Lio/reactivex/rxjava3/core/MaybeSource;)V
      25: invokestatic  #389                // Method io/reactivex/rxjava3/plugins/RxJavaPlugins.onAssembly:(Lio/reactivex/rxjava3/core/Flowable;)Lio/reactivex/rxjava3/core/Flowable;
      28: areturn

  public final java.util.concurrent.Future<T> toFuture();
    Code:
       0: aload_0
       1: new           #390                // class io/reactivex/rxjava3/internal/observers/FutureMultiObserver
       4: dup
       5: invokespecial #391                // Method io/reactivex/rxjava3/internal/observers/FutureMultiObserver."<init>":()V
       8: invokevirtual #392                // Method subscribeWith:(Lio/reactivex/rxjava3/core/MaybeObserver;)Lio/reactivex/rxjava3/core/MaybeObserver;
      11: checkcast     #393                // class java/util/concurrent/Future
      14: areturn

  public final io.reactivex.rxjava3.core.Observable<T> toObservable();
    Code:
       0: aload_0
       1: instanceof    #394                // class io/reactivex/rxjava3/internal/fuseable/FuseToObservable
       4: ifeq          17
       7: aload_0
       8: checkcast     #394                // class io/reactivex/rxjava3/internal/fuseable/FuseToObservable
      11: invokeinterface #395,  1          // InterfaceMethod io/reactivex/rxjava3/internal/fuseable/FuseToObservable.fuseToObservable:()Lio/reactivex/rxjava3/core/Observable;
      16: areturn
      17: new           #396                // class io/reactivex/rxjava3/internal/operators/maybe/MaybeToObservable
      20: dup
      21: aload_0
      22: invokespecial #397                // Method io/reactivex/rxjava3/internal/operators/maybe/MaybeToObservable."<init>":(Lio/reactivex/rxjava3/core/MaybeSource;)V
      25: invokestatic  #398                // Method io/reactivex/rxjava3/plugins/RxJavaPlugins.onAssembly:(Lio/reactivex/rxjava3/core/Observable;)Lio/reactivex/rxjava3/core/Observable;
      28: areturn

  public final io.reactivex.rxjava3.core.Single<T> toSingle();
    Code:
       0: new           #272                // class io/reactivex/rxjava3/internal/operators/maybe/MaybeToSingle
       3: dup
       4: aload_0
       5: aconst_null
       6: invokespecial #273                // Method io/reactivex/rxjava3/internal/operators/maybe/MaybeToSingle."<init>":(Lio/reactivex/rxjava3/core/MaybeSource;Ljava/lang/Object;)V
       9: invokestatic  #399                // Method io/reactivex/rxjava3/plugins/RxJavaPlugins.onAssembly:(Lio/reactivex/rxjava3/core/Single;)Lio/reactivex/rxjava3/core/Single;
      12: areturn

  public final io.reactivex.rxjava3.core.Maybe<T> onErrorComplete();
    Code:
       0: aload_0
       1: invokestatic  #400                // Method io/reactivex/rxjava3/internal/functions/Functions.alwaysTrue:()Lio/reactivex/rxjava3/functions/Predicate;
       4: invokevirtual #401                // Method onErrorComplete:(Lio/reactivex/rxjava3/functions/Predicate;)Lio/reactivex/rxjava3/core/Maybe;
       7: areturn

  public final io.reactivex.rxjava3.core.Maybe<T> onErrorComplete(io.reactivex.rxjava3.functions.Predicate<? super java.lang.Throwable>);
    Code:
       0: aload_1
       1: ldc_w         #325                // String predicate is null
       4: invokestatic  #3                  // Method java/util/Objects.requireNonNull:(Ljava/lang/Object;Ljava/lang/String;)Ljava/lang/Object;
       7: pop
       8: new           #402                // class io/reactivex/rxjava3/internal/operators/maybe/MaybeOnErrorComplete
      11: dup
      12: aload_0
      13: aload_1
      14: invokespecial #403                // Method io/reactivex/rxjava3/internal/operators/maybe/MaybeOnErrorComplete."<init>":(Lio/reactivex/rxjava3/core/MaybeSource;Lio/reactivex/rxjava3/functions/Predicate;)V
      17: invokestatic  #404                // Method io/reactivex/rxjava3/plugins/RxJavaPlugins.onAssembly:(Lio/reactivex/rxjava3/core/Maybe;)Lio/reactivex/rxjava3/core/Maybe;
      20: areturn

  public final io.reactivex.rxjava3.core.Maybe<T> onErrorResumeWith(io.reactivex.rxjava3.core.MaybeSource<? extends T>);
    Code:
       0: aload_1
       1: ldc_w         #405                // String fallback is null
       4: invokestatic  #3                  // Method java/util/Objects.requireNonNull:(Ljava/lang/Object;Ljava/lang/String;)Ljava/lang/Object;
       7: pop
       8: aload_0
       9: aload_1
      10: invokestatic  #406                // Method io/reactivex/rxjava3/internal/functions/Functions.justFunction:(Ljava/lang/Object;)Lio/reactivex/rxjava3/functions/Function;
      13: invokevirtual #407                // Method onErrorResumeNext:(Lio/reactivex/rxjava3/functions/Function;)Lio/reactivex/rxjava3/core/Maybe;
      16: areturn

  public final io.reactivex.rxjava3.core.Maybe<T> onErrorResumeNext(io.reactivex.rxjava3.functions.Function<? super java.lang.Throwable, ? extends io.reactivex.rxjava3.core.MaybeSource<? extends T>>);
    Code:
       0: aload_1
       1: ldc_w         #408                // String fallbackSupplier is null
       4: invokestatic  #3                  // Method java/util/Objects.requireNonNull:(Ljava/lang/Object;Ljava/lang/String;)Ljava/lang/Object;
       7: pop
       8: new           #409                // class io/reactivex/rxjava3/internal/operators/maybe/MaybeOnErrorNext
      11: dup
      12: aload_0
      13: aload_1
      14: invokespecial #410                // Method io/reactivex/rxjava3/internal/operators/maybe/MaybeOnErrorNext."<init>":(Lio/reactivex/rxjava3/core/MaybeSource;Lio/reactivex/rxjava3/functions/Function;)V
      17: invokestatic  #411                // Method io/reactivex/rxjava3/plugins/RxJavaPlugins.onAssembly:(Lio/reactivex/rxjava3/core/Maybe;)Lio/reactivex/rxjava3/core/Maybe;
      20: areturn

  public final io.reactivex.rxjava3.core.Maybe<T> onErrorReturn(io.reactivex.rxjava3.functions.Function<? super java.lang.Throwable, ? extends T>);
    Code:
       0: aload_1
       1: ldc_w         #412                // String itemSupplier is null
       4: invokestatic  #3                  // Method java/util/Objects.requireNonNull:(Ljava/lang/Object;Ljava/lang/String;)Ljava/lang/Object;
       7: pop
       8: new           #413                // class io/reactivex/rxjava3/internal/operators/maybe/MaybeOnErrorReturn
      11: dup
      12: aload_0
      13: aload_1
      14: invokespecial #414                // Method io/reactivex/rxjava3/internal/operators/maybe/MaybeOnErrorReturn."<init>":(Lio/reactivex/rxjava3/core/MaybeSource;Lio/reactivex/rxjava3/functions/Function;)V
      17: invokestatic  #415                // Method io/reactivex/rxjava3/plugins/RxJavaPlugins.onAssembly:(Lio/reactivex/rxjava3/core/Maybe;)Lio/reactivex/rxjava3/core/Maybe;
      20: areturn

  public final io.reactivex.rxjava3.core.Maybe<T> onErrorReturnItem(T);
    Code:
       0: aload_1
       1: ldc           #124                // String item is null
       3: invokestatic  #3                  // Method java/util/Objects.requireNonNull:(Ljava/lang/Object;Ljava/lang/String;)Ljava/lang/Object;
       6: pop
       7: aload_0
       8: aload_1
       9: invokestatic  #416                // Method io/reactivex/rxjava3/internal/functions/Functions.justFunction:(Ljava/lang/Object;)Lio/reactivex/rxjava3/functions/Function;
      12: invokevirtual #417                // Method onErrorReturn:(Lio/reactivex/rxjava3/functions/Function;)Lio/reactivex/rxjava3/core/Maybe;
      15: areturn

  public final io.reactivex.rxjava3.core.Maybe<T> onTerminateDetach();
    Code:
       0: new           #418                // class io/reactivex/rxjava3/internal/operators/maybe/MaybeDetach
       3: dup
       4: aload_0
       5: invokespecial #419                // Method io/reactivex/rxjava3/internal/operators/maybe/MaybeDetach."<init>":(Lio/reactivex/rxjava3/core/MaybeSource;)V
       8: invokestatic  #420                // Method io/reactivex/rxjava3/plugins/RxJavaPlugins.onAssembly:(Lio/reactivex/rxjava3/core/Maybe;)Lio/reactivex/rxjava3/core/Maybe;
      11: areturn

  public final io.reactivex.rxjava3.core.Flowable<T> repeat();
    Code:
       0: aload_0
       1: ldc2_w        #422                // long 9223372036854775807l
       4: invokevirtual #424                // Method repeat:(J)Lio/reactivex/rxjava3/core/Flowable;
       7: areturn

  public final io.reactivex.rxjava3.core.Flowable<T> repeat(long);
    Code:
       0: aload_0
       1: invokevirtual #425                // Method toFlowable:()Lio/reactivex/rxjava3/core/Flowable;
       4: lload_1
       5: invokevirtual #426                // Method io/reactivex/rxjava3/core/Flowable.repeat:(J)Lio/reactivex/rxjava3/core/Flowable;
       8: areturn

  public final io.reactivex.rxjava3.core.Flowable<T> repeatUntil(io.reactivex.rxjava3.functions.BooleanSupplier);
    Code:
       0: aload_0
       1: invokevirtual #425                // Method toFlowable:()Lio/reactivex/rxjava3/core/Flowable;
       4: aload_1
       5: invokevirtual #427                // Method io/reactivex/rxjava3/core/Flowable.repeatUntil:(Lio/reactivex/rxjava3/functions/BooleanSupplier;)Lio/reactivex/rxjava3/core/Flowable;
       8: areturn

  public final io.reactivex.rxjava3.core.Flowable<T> repeatWhen(io.reactivex.rxjava3.functions.Function<? super io.reactivex.rxjava3.core.Flowable<java.lang.Object>, ? extends org.reactivestreams.Publisher<?>>);
    Code:
       0: aload_0
       1: invokevirtual #425                // Method toFlowable:()Lio/reactivex/rxjava3/core/Flowable;
       4: aload_1
       5: invokevirtual #428                // Method io/reactivex/rxjava3/core/Flowable.repeatWhen:(Lio/reactivex/rxjava3/functions/Function;)Lio/reactivex/rxjava3/core/Flowable;
       8: areturn

  public final io.reactivex.rxjava3.core.Maybe<T> retry();
    Code:
       0: aload_0
       1: ldc2_w        #422                // long 9223372036854775807l
       4: invokestatic  #429                // Method io/reactivex/rxjava3/internal/functions/Functions.alwaysTrue:()Lio/reactivex/rxjava3/functions/Predicate;
       7: invokevirtual #430                // Method retry:(JLio/reactivex/rxjava3/functions/Predicate;)Lio/reactivex/rxjava3/core/Maybe;
      10: areturn

  public final io.reactivex.rxjava3.core.Maybe<T> retry(io.reactivex.rxjava3.functions.BiPredicate<? super java.lang.Integer, ? super java.lang.Throwable>);
    Code:
       0: aload_0
       1: invokevirtual #425                // Method toFlowable:()Lio/reactivex/rxjava3/core/Flowable;
       4: aload_1
       5: invokevirtual #431                // Method io/reactivex/rxjava3/core/Flowable.retry:(Lio/reactivex/rxjava3/functions/BiPredicate;)Lio/reactivex/rxjava3/core/Flowable;
       8: invokevirtual #432                // Method io/reactivex/rxjava3/core/Flowable.singleElement:()Lio/reactivex/rxjava3/core/Maybe;
      11: areturn

  public final io.reactivex.rxjava3.core.Maybe<T> retry(long);
    Code:
       0: aload_0
       1: lload_1
       2: invokestatic  #433                // Method io/reactivex/rxjava3/internal/functions/Functions.alwaysTrue:()Lio/reactivex/rxjava3/functions/Predicate;
       5: invokevirtual #430                // Method retry:(JLio/reactivex/rxjava3/functions/Predicate;)Lio/reactivex/rxjava3/core/Maybe;
       8: areturn

  public final io.reactivex.rxjava3.core.Maybe<T> retry(long, io.reactivex.rxjava3.functions.Predicate<? super java.lang.Throwable>);
    Code:
       0: aload_0
       1: invokevirtual #425                // Method toFlowable:()Lio/reactivex/rxjava3/core/Flowable;
       4: lload_1
       5: aload_3
       6: invokevirtual #434                // Method io/reactivex/rxjava3/core/Flowable.retry:(JLio/reactivex/rxjava3/functions/Predicate;)Lio/reactivex/rxjava3/core/Flowable;
       9: invokevirtual #432                // Method io/reactivex/rxjava3/core/Flowable.singleElement:()Lio/reactivex/rxjava3/core/Maybe;
      12: areturn

  public final io.reactivex.rxjava3.core.Maybe<T> retry(io.reactivex.rxjava3.functions.Predicate<? super java.lang.Throwable>);
    Code:
       0: aload_0
       1: ldc2_w        #422                // long 9223372036854775807l
       4: aload_1
       5: invokevirtual #430                // Method retry:(JLio/reactivex/rxjava3/functions/Predicate;)Lio/reactivex/rxjava3/core/Maybe;
       8: areturn

  public final io.reactivex.rxjava3.core.Maybe<T> retryUntil(io.reactivex.rxjava3.functions.BooleanSupplier);
    Code:
       0: aload_1
       1: ldc_w         #435                // String stop is null
       4: invokestatic  #3                  // Method java/util/Objects.requireNonNull:(Ljava/lang/Object;Ljava/lang/String;)Ljava/lang/Object;
       7: pop
       8: aload_0
       9: ldc2_w        #422                // long 9223372036854775807l
      12: aload_1
      13: invokestatic  #436                // Method io/reactivex/rxjava3/internal/functions/Functions.predicateReverseFor:(Lio/reactivex/rxjava3/functions/BooleanSupplier;)Lio/reactivex/rxjava3/functions/Predicate;
      16: invokevirtual #430                // Method retry:(JLio/reactivex/rxjava3/functions/Predicate;)Lio/reactivex/rxjava3/core/Maybe;
      19: areturn

  public final io.reactivex.rxjava3.core.Maybe<T> retryWhen(io.reactivex.rxjava3.functions.Function<? super io.reactivex.rxjava3.core.Flowable<java.lang.Throwable>, ? extends org.reactivestreams.Publisher<?>>);
    Code:
       0: aload_0
       1: invokevirtual #425                // Method toFlowable:()Lio/reactivex/rxjava3/core/Flowable;
       4: aload_1
       5: invokevirtual #437                // Method io/reactivex/rxjava3/core/Flowable.retryWhen:(Lio/reactivex/rxjava3/functions/Function;)Lio/reactivex/rxjava3/core/Flowable;
       8: invokevirtual #432                // Method io/reactivex/rxjava3/core/Flowable.singleElement:()Lio/reactivex/rxjava3/core/Maybe;
      11: areturn

  public final void safeSubscribe(io.reactivex.rxjava3.core.MaybeObserver<? super T>);
    Code:
       0: aload_1
       1: ldc           #246                // String observer is null
       3: invokestatic  #3                  // Method java/util/Objects.requireNonNull:(Ljava/lang/Object;Ljava/lang/String;)Ljava/lang/Object;
       6: pop
       7: aload_0
       8: new           #438                // class io/reactivex/rxjava3/internal/observers/SafeMaybeObserver
      11: dup
      12: aload_1
      13: invokespecial #439                // Method io/reactivex/rxjava3/internal/observers/SafeMaybeObserver."<init>":(Lio/reactivex/rxjava3/core/MaybeObserver;)V
      16: invokevirtual #234                // Method subscribe:(Lio/reactivex/rxjava3/core/MaybeObserver;)V
      19: return

  public final io.reactivex.rxjava3.core.Flowable<T> startWith(io.reactivex.rxjava3.core.CompletableSource);
    Code:
       0: aload_1
       1: ldc           #230                // String other is null
       3: invokestatic  #3                  // Method java/util/Objects.requireNonNull:(Ljava/lang/Object;Ljava/lang/String;)Ljava/lang/Object;
       6: pop
       7: aload_1
       8: invokestatic  #440                // Method io/reactivex/rxjava3/core/Completable.wrap:(Lio/reactivex/rxjava3/core/CompletableSource;)Lio/reactivex/rxjava3/core/Completable;
      11: invokevirtual #441                // Method io/reactivex/rxjava3/core/Completable.toFlowable:()Lio/reactivex/rxjava3/core/Flowable;
      14: aload_0
      15: invokevirtual #425                // Method toFlowable:()Lio/reactivex/rxjava3/core/Flowable;
      18: invokestatic  #442                // Method io/reactivex/rxjava3/core/Flowable.concat:(Lorg/reactivestreams/Publisher;Lorg/reactivestreams/Publisher;)Lio/reactivex/rxjava3/core/Flowable;
      21: areturn

  public final io.reactivex.rxjava3.core.Flowable<T> startWith(io.reactivex.rxjava3.core.SingleSource<T>);
    Code:
       0: aload_1
       1: ldc           #230                // String other is null
       3: invokestatic  #3                  // Method java/util/Objects.requireNonNull:(Ljava/lang/Object;Ljava/lang/String;)Ljava/lang/Object;
       6: pop
       7: aload_1
       8: invokestatic  #443                // Method io/reactivex/rxjava3/core/Single.wrap:(Lio/reactivex/rxjava3/core/SingleSource;)Lio/reactivex/rxjava3/core/Single;
      11: invokevirtual #444                // Method io/reactivex/rxjava3/core/Single.toFlowable:()Lio/reactivex/rxjava3/core/Flowable;
      14: aload_0
      15: invokevirtual #425                // Method toFlowable:()Lio/reactivex/rxjava3/core/Flowable;
      18: invokestatic  #445                // Method io/reactivex/rxjava3/core/Flowable.concat:(Lorg/reactivestreams/Publisher;Lorg/reactivestreams/Publisher;)Lio/reactivex/rxjava3/core/Flowable;
      21: areturn

  public final io.reactivex.rxjava3.core.Flowable<T> startWith(io.reactivex.rxjava3.core.MaybeSource<T>);
    Code:
       0: aload_1
       1: ldc           #230                // String other is null
       3: invokestatic  #3                  // Method java/util/Objects.requireNonNull:(Ljava/lang/Object;Ljava/lang/String;)Ljava/lang/Object;
       6: pop
       7: aload_1
       8: invokestatic  #446                // Method wrap:(Lio/reactivex/rxjava3/core/MaybeSource;)Lio/reactivex/rxjava3/core/Maybe;
      11: invokevirtual #425                // Method toFlowable:()Lio/reactivex/rxjava3/core/Flowable;
      14: aload_0
      15: invokevirtual #425                // Method toFlowable:()Lio/reactivex/rxjava3/core/Flowable;
      18: invokestatic  #447                // Method io/reactivex/rxjava3/core/Flowable.concat:(Lorg/reactivestreams/Publisher;Lorg/reactivestreams/Publisher;)Lio/reactivex/rxjava3/core/Flowable;
      21: areturn

  public final io.reactivex.rxjava3.core.Observable<T> startWith(io.reactivex.rxjava3.core.ObservableSource<T>);
    Code:
       0: aload_1
       1: ldc           #230                // String other is null
       3: invokestatic  #3                  // Method java/util/Objects.requireNonNull:(Ljava/lang/Object;Ljava/lang/String;)Ljava/lang/Object;
       6: pop
       7: aload_1
       8: invokestatic  #448                // Method io/reactivex/rxjava3/core/Observable.wrap:(Lio/reactivex/rxjava3/core/ObservableSource;)Lio/reactivex/rxjava3/core/Observable;
      11: aload_0
      12: invokevirtual #449                // Method toObservable:()Lio/reactivex/rxjava3/core/Observable;
      15: invokevirtual #450                // Method io/reactivex/rxjava3/core/Observable.concatWith:(Lio/reactivex/rxjava3/core/ObservableSource;)Lio/reactivex/rxjava3/core/Observable;
      18: areturn

  public final io.reactivex.rxjava3.core.Flowable<T> startWith(org.reactivestreams.Publisher<T>);
    Code:
       0: aload_1
       1: ldc           #230                // String other is null
       3: invokestatic  #3                  // Method java/util/Objects.requireNonNull:(Ljava/lang/Object;Ljava/lang/String;)Ljava/lang/Object;
       6: pop
       7: aload_0
       8: invokevirtual #425                // Method toFlowable:()Lio/reactivex/rxjava3/core/Flowable;
      11: aload_1
      12: invokevirtual #451                // Method io/reactivex/rxjava3/core/Flowable.startWith:(Lorg/reactivestreams/Publisher;)Lio/reactivex/rxjava3/core/Flowable;
      15: areturn

  public final io.reactivex.rxjava3.disposables.Disposable subscribe();
    Code:
       0: aload_0
       1: invokestatic  #238                // Method io/reactivex/rxjava3/internal/functions/Functions.emptyConsumer:()Lio/reactivex/rxjava3/functions/Consumer;
       4: getstatic     #452                // Field io/reactivex/rxjava3/internal/functions/Functions.ON_ERROR_MISSING:Lio/reactivex/rxjava3/functions/Consumer;
       7: getstatic     #240                // Field io/reactivex/rxjava3/internal/functions/Functions.EMPTY_ACTION:Lio/reactivex/rxjava3/functions/Action;
      10: invokevirtual #453                // Method subscribe:(Lio/reactivex/rxjava3/functions/Consumer;Lio/reactivex/rxjava3/functions/Consumer;Lio/reactivex/rxjava3/functions/Action;)Lio/reactivex/rxjava3/disposables/Disposable;
      13: areturn

  public final io.reactivex.rxjava3.disposables.Disposable subscribe(io.reactivex.rxjava3.functions.Consumer<? super T>);
    Code:
       0: aload_0
       1: aload_1
       2: getstatic     #452                // Field io/reactivex/rxjava3/internal/functions/Functions.ON_ERROR_MISSING:Lio/reactivex/rxjava3/functions/Consumer;
       5: getstatic     #240                // Field io/reactivex/rxjava3/internal/functions/Functions.EMPTY_ACTION:Lio/reactivex/rxjava3/functions/Action;
       8: invokevirtual #453                // Method subscribe:(Lio/reactivex/rxjava3/functions/Consumer;Lio/reactivex/rxjava3/functions/Consumer;Lio/reactivex/rxjava3/functions/Action;)Lio/reactivex/rxjava3/disposables/Disposable;
      11: areturn

  public final io.reactivex.rxjava3.disposables.Disposable subscribe(io.reactivex.rxjava3.functions.Consumer<? super T>, io.reactivex.rxjava3.functions.Consumer<? super java.lang.Throwable>);
    Code:
       0: aload_0
       1: aload_1
       2: aload_2
       3: getstatic     #240                // Field io/reactivex/rxjava3/internal/functions/Functions.EMPTY_ACTION:Lio/reactivex/rxjava3/functions/Action;
       6: invokevirtual #453                // Method subscribe:(Lio/reactivex/rxjava3/functions/Consumer;Lio/reactivex/rxjava3/functions/Consumer;Lio/reactivex/rxjava3/functions/Action;)Lio/reactivex/rxjava3/disposables/Disposable;
       9: areturn

  public final io.reactivex.rxjava3.disposables.Disposable subscribe(io.reactivex.rxjava3.functions.Consumer<? super T>, io.reactivex.rxjava3.functions.Consumer<? super java.lang.Throwable>, io.reactivex.rxjava3.functions.Action);
    Code:
       0: aload_1
       1: ldc           #242                // String onSuccess is null
       3: invokestatic  #3                  // Method java/util/Objects.requireNonNull:(Ljava/lang/Object;Ljava/lang/String;)Ljava/lang/Object;
       6: pop
       7: aload_2
       8: ldc           #243                // String onError is null
      10: invokestatic  #3                  // Method java/util/Objects.requireNonNull:(Ljava/lang/Object;Ljava/lang/String;)Ljava/lang/Object;
      13: pop
      14: aload_3
      15: ldc           #244                // String onComplete is null
      17: invokestatic  #3                  // Method java/util/Objects.requireNonNull:(Ljava/lang/Object;Ljava/lang/String;)Ljava/lang/Object;
      20: pop
      21: aload_0
      22: new           #454                // class io/reactivex/rxjava3/internal/operators/maybe/MaybeCallbackObserver
      25: dup
      26: aload_1
      27: aload_2
      28: aload_3
      29: invokespecial #455                // Method io/reactivex/rxjava3/internal/operators/maybe/MaybeCallbackObserver."<init>":(Lio/reactivex/rxjava3/functions/Consumer;Lio/reactivex/rxjava3/functions/Consumer;Lio/reactivex/rxjava3/functions/Action;)V
      32: invokevirtual #392                // Method subscribeWith:(Lio/reactivex/rxjava3/core/MaybeObserver;)Lio/reactivex/rxjava3/core/MaybeObserver;
      35: checkcast     #456                // class io/reactivex/rxjava3/disposables/Disposable
      38: areturn

  public final io.reactivex.rxjava3.disposables.Disposable subscribe(io.reactivex.rxjava3.functions.Consumer<? super T>, io.reactivex.rxjava3.functions.Consumer<? super java.lang.Throwable>, io.reactivex.rxjava3.functions.Action, io.reactivex.rxjava3.disposables.DisposableContainer);
    Code:
       0: aload_1
       1: ldc           #242                // String onSuccess is null
       3: invokestatic  #3                  // Method java/util/Objects.requireNonNull:(Ljava/lang/Object;Ljava/lang/String;)Ljava/lang/Object;
       6: pop
       7: aload_2
       8: ldc           #243                // String onError is null
      10: invokestatic  #3                  // Method java/util/Objects.requireNonNull:(Ljava/lang/Object;Ljava/lang/String;)Ljava/lang/Object;
      13: pop
      14: aload_3
      15: ldc           #244                // String onComplete is null
      17: invokestatic  #3                  // Method java/util/Objects.requireNonNull:(Ljava/lang/Object;Ljava/lang/String;)Ljava/lang/Object;
      20: pop
      21: aload         4
      23: ldc_w         #457                // String container is null
      26: invokestatic  #3                  // Method java/util/Objects.requireNonNull:(Ljava/lang/Object;Ljava/lang/String;)Ljava/lang/Object;
      29: pop
      30: new           #458                // class io/reactivex/rxjava3/internal/observers/DisposableAutoReleaseMultiObserver
      33: dup
      34: aload         4
      36: aload_1
      37: aload_2
      38: aload_3
      39: invokespecial #459                // Method io/reactivex/rxjava3/internal/observers/DisposableAutoReleaseMultiObserver."<init>":(Lio/reactivex/rxjava3/disposables/DisposableContainer;Lio/reactivex/rxjava3/functions/Consumer;Lio/reactivex/rxjava3/functions/Consumer;Lio/reactivex/rxjava3/functions/Action;)V
      42: astore        5
      44: aload         4
      46: aload         5
      48: invokeinterface #460,  2          // InterfaceMethod io/reactivex/rxjava3/disposables/DisposableContainer.add:(Lio/reactivex/rxjava3/disposables/Disposable;)Z
      53: pop
      54: aload_0
      55: aload         5
      57: invokevirtual #234                // Method subscribe:(Lio/reactivex/rxjava3/core/MaybeObserver;)V
      60: aload         5
      62: areturn

  public final void subscribe(io.reactivex.rxjava3.core.MaybeObserver<? super T>);
    Code:
       0: aload_1
       1: ldc           #246                // String observer is null
       3: invokestatic  #3                  // Method java/util/Objects.requireNonNull:(Ljava/lang/Object;Ljava/lang/String;)Ljava/lang/Object;
       6: pop
       7: aload_0
       8: aload_1
       9: invokestatic  #461                // Method io/reactivex/rxjava3/plugins/RxJavaPlugins.onSubscribe:(Lio/reactivex/rxjava3/core/Maybe;Lio/reactivex/rxjava3/core/MaybeObserver;)Lio/reactivex/rxjava3/core/MaybeObserver;
      12: astore_1
      13: aload_1
      14: ldc_w         #462                // String The RxJavaPlugins.onSubscribe hook returned a null MaybeObserver. Please check the handler provided to RxJavaPlugins.setOnMaybeSubscribe for invalid null returns. Further reading: https://github.com/ReactiveX/RxJava/wiki/Plugins
      17: invokestatic  #3                  // Method java/util/Objects.requireNonNull:(Ljava/lang/Object;Ljava/lang/String;)Ljava/lang/Object;
      20: pop
      21: aload_0
      22: aload_1
      23: invokevirtual #463                // Method subscribeActual:(Lio/reactivex/rxjava3/core/MaybeObserver;)V
      26: goto          56
      29: astore_2
      30: aload_2
      31: athrow
      32: astore_2
      33: aload_2
      34: invokestatic  #466                // Method io/reactivex/rxjava3/exceptions/Exceptions.throwIfFatal:(Ljava/lang/Throwable;)V
      37: new           #464                // class java/lang/NullPointerException
      40: dup
      41: ldc_w         #467                // String subscribeActual failed
      44: invokespecial #468                // Method java/lang/NullPointerException."<init>":(Ljava/lang/String;)V
      47: astore_3
      48: aload_3
      49: aload_2
      50: invokevirtual #469                // Method java/lang/NullPointerException.initCause:(Ljava/lang/Throwable;)Ljava/lang/Throwable;
      53: pop
      54: aload_3
      55: athrow
      56: return
    Exception table:
       from    to  target type
          21    26    29   Class java/lang/NullPointerException
          21    26    32   Class java/lang/Throwable

  protected abstract void subscribeActual(io.reactivex.rxjava3.core.MaybeObserver<? super T>);

  public final io.reactivex.rxjava3.core.Maybe<T> subscribeOn(io.reactivex.rxjava3.core.Scheduler);
    Code:
       0: aload_1
       1: ldc           #180                // String scheduler is null
       3: invokestatic  #3                  // Method java/util/Objects.requireNonNull:(Ljava/lang/Object;Ljava/lang/String;)Ljava/lang/Object;
       6: pop
       7: new           #470                // class io/reactivex/rxjava3/internal/operators/maybe/MaybeSubscribeOn
      10: dup
      11: aload_0
      12: aload_1
      13: invokespecial #471                // Method io/reactivex/rxjava3/internal/operators/maybe/MaybeSubscribeOn."<init>":(Lio/reactivex/rxjava3/core/MaybeSource;Lio/reactivex/rxjava3/core/Scheduler;)V
      16: invokestatic  #472                // Method io/reactivex/rxjava3/plugins/RxJavaPlugins.onAssembly:(Lio/reactivex/rxjava3/core/Maybe;)Lio/reactivex/rxjava3/core/Maybe;
      19: areturn

  public final <E extends io.reactivex.rxjava3.core.MaybeObserver<? super T>> E subscribeWith(E);
    Code:
       0: aload_0
       1: aload_1
       2: invokevirtual #234                // Method subscribe:(Lio/reactivex/rxjava3/core/MaybeObserver;)V
       5: aload_1
       6: areturn

  public final io.reactivex.rxjava3.core.Maybe<T> switchIfEmpty(io.reactivex.rxjava3.core.MaybeSource<? extends T>);
    Code:
       0: aload_1
       1: ldc           #230                // String other is null
       3: invokestatic  #3                  // Method java/util/Objects.requireNonNull:(Ljava/lang/Object;Ljava/lang/String;)Ljava/lang/Object;
       6: pop
       7: new           #473                // class io/reactivex/rxjava3/internal/operators/maybe/MaybeSwitchIfEmpty
      10: dup
      11: aload_0
      12: aload_1
      13: invokespecial #474                // Method io/reactivex/rxjava3/internal/operators/maybe/MaybeSwitchIfEmpty."<init>":(Lio/reactivex/rxjava3/core/MaybeSource;Lio/reactivex/rxjava3/core/MaybeSource;)V
      16: invokestatic  #475                // Method io/reactivex/rxjava3/plugins/RxJavaPlugins.onAssembly:(Lio/reactivex/rxjava3/core/Maybe;)Lio/reactivex/rxjava3/core/Maybe;
      19: areturn

  public final io.reactivex.rxjava3.core.Single<T> switchIfEmpty(io.reactivex.rxjava3.core.SingleSource<? extends T>);
    Code:
       0: aload_1
       1: ldc           #230                // String other is null
       3: invokestatic  #3                  // Method java/util/Objects.requireNonNull:(Ljava/lang/Object;Ljava/lang/String;)Ljava/lang/Object;
       6: pop
       7: new           #476                // class io/reactivex/rxjava3/internal/operators/maybe/MaybeSwitchIfEmptySingle
      10: dup
      11: aload_0
      12: aload_1
      13: invokespecial #477                // Method io/reactivex/rxjava3/internal/operators/maybe/MaybeSwitchIfEmptySingle."<init>":(Lio/reactivex/rxjava3/core/MaybeSource;Lio/reactivex/rxjava3/core/SingleSource;)V
      16: invokestatic  #478                // Method io/reactivex/rxjava3/plugins/RxJavaPlugins.onAssembly:(Lio/reactivex/rxjava3/core/Single;)Lio/reactivex/rxjava3/core/Single;
      19: areturn

  public final <U> io.reactivex.rxjava3.core.Maybe<T> takeUntil(io.reactivex.rxjava3.core.MaybeSource<U>);
    Code:
       0: aload_1
       1: ldc           #230                // String other is null
       3: invokestatic  #3                  // Method java/util/Objects.requireNonNull:(Ljava/lang/Object;Ljava/lang/String;)Ljava/lang/Object;
       6: pop
       7: new           #479                // class io/reactivex/rxjava3/internal/operators/maybe/MaybeTakeUntilMaybe
      10: dup
      11: aload_0
      12: aload_1
      13: invokespecial #480                // Method io/reactivex/rxjava3/internal/operators/maybe/MaybeTakeUntilMaybe."<init>":(Lio/reactivex/rxjava3/core/MaybeSource;Lio/reactivex/rxjava3/core/MaybeSource;)V
      16: invokestatic  #481                // Method io/reactivex/rxjava3/plugins/RxJavaPlugins.onAssembly:(Lio/reactivex/rxjava3/core/Maybe;)Lio/reactivex/rxjava3/core/Maybe;
      19: areturn

  public final <U> io.reactivex.rxjava3.core.Maybe<T> takeUntil(org.reactivestreams.Publisher<U>);
    Code:
       0: aload_1
       1: ldc           #230                // String other is null
       3: invokestatic  #3                  // Method java/util/Objects.requireNonNull:(Ljava/lang/Object;Ljava/lang/String;)Ljava/lang/Object;
       6: pop
       7: new           #482                // class io/reactivex/rxjava3/internal/operators/maybe/MaybeTakeUntilPublisher
      10: dup
      11: aload_0
      12: aload_1
      13: invokespecial #483                // Method io/reactivex/rxjava3/internal/operators/maybe/MaybeTakeUntilPublisher."<init>":(Lio/reactivex/rxjava3/core/MaybeSource;Lorg/reactivestreams/Publisher;)V
      16: invokestatic  #484                // Method io/reactivex/rxjava3/plugins/RxJavaPlugins.onAssembly:(Lio/reactivex/rxjava3/core/Maybe;)Lio/reactivex/rxjava3/core/Maybe;
      19: areturn

  public final io.reactivex.rxjava3.core.Maybe<io.reactivex.rxjava3.schedulers.Timed<T>> timeInterval();
    Code:
       0: aload_0
       1: getstatic     #485                // Field java/util/concurrent/TimeUnit.MILLISECONDS:Ljava/util/concurrent/TimeUnit;
       4: invokestatic  #178                // Method io/reactivex/rxjava3/schedulers/Schedulers.computation:()Lio/reactivex/rxjava3/core/Scheduler;
       7: invokevirtual #486                // Method timeInterval:(Ljava/util/concurrent/TimeUnit;Lio/reactivex/rxjava3/core/Scheduler;)Lio/reactivex/rxjava3/core/Maybe;
      10: areturn

  public final io.reactivex.rxjava3.core.Maybe<io.reactivex.rxjava3.schedulers.Timed<T>> timeInterval(io.reactivex.rxjava3.core.Scheduler);
    Code:
       0: aload_0
       1: getstatic     #485                // Field java/util/concurrent/TimeUnit.MILLISECONDS:Ljava/util/concurrent/TimeUnit;
       4: aload_1
       5: invokevirtual #486                // Method timeInterval:(Ljava/util/concurrent/TimeUnit;Lio/reactivex/rxjava3/core/Scheduler;)Lio/reactivex/rxjava3/core/Maybe;
       8: areturn

  public final io.reactivex.rxjava3.core.Maybe<io.reactivex.rxjava3.schedulers.Timed<T>> timeInterval(java.util.concurrent.TimeUnit);
    Code:
       0: aload_0
       1: aload_1
       2: invokestatic  #178                // Method io/reactivex/rxjava3/schedulers/Schedulers.computation:()Lio/reactivex/rxjava3/core/Scheduler;
       5: invokevirtual #486                // Method timeInterval:(Ljava/util/concurrent/TimeUnit;Lio/reactivex/rxjava3/core/Scheduler;)Lio/reactivex/rxjava3/core/Maybe;
       8: areturn

  public final io.reactivex.rxjava3.core.Maybe<io.reactivex.rxjava3.schedulers.Timed<T>> timeInterval(java.util.concurrent.TimeUnit, io.reactivex.rxjava3.core.Scheduler);
    Code:
       0: aload_1
       1: ldc           #108                // String unit is null
       3: invokestatic  #3                  // Method java/util/Objects.requireNonNull:(Ljava/lang/Object;Ljava/lang/String;)Ljava/lang/Object;
       6: pop
       7: aload_2
       8: ldc           #180                // String scheduler is null
      10: invokestatic  #3                  // Method java/util/Objects.requireNonNull:(Ljava/lang/Object;Ljava/lang/String;)Ljava/lang/Object;
      13: pop
      14: new           #487                // class io/reactivex/rxjava3/internal/operators/maybe/MaybeTimeInterval
      17: dup
      18: aload_0
      19: aload_1
      20: aload_2
      21: iconst_1
      22: invokespecial #488                // Method io/reactivex/rxjava3/internal/operators/maybe/MaybeTimeInterval."<init>":(Lio/reactivex/rxjava3/core/MaybeSource;Ljava/util/concurrent/TimeUnit;Lio/reactivex/rxjava3/core/Scheduler;Z)V
      25: invokestatic  #489                // Method io/reactivex/rxjava3/plugins/RxJavaPlugins.onAssembly:(Lio/reactivex/rxjava3/core/Maybe;)Lio/reactivex/rxjava3/core/Maybe;
      28: areturn

  public final io.reactivex.rxjava3.core.Maybe<io.reactivex.rxjava3.schedulers.Timed<T>> timestamp();
    Code:
       0: aload_0
       1: getstatic     #485                // Field java/util/concurrent/TimeUnit.MILLISECONDS:Ljava/util/concurrent/TimeUnit;
       4: invokestatic  #178                // Method io/reactivex/rxjava3/schedulers/Schedulers.computation:()Lio/reactivex/rxjava3/core/Scheduler;
       7: invokevirtual #490                // Method timestamp:(Ljava/util/concurrent/TimeUnit;Lio/reactivex/rxjava3/core/Scheduler;)Lio/reactivex/rxjava3/core/Maybe;
      10: areturn

  public final io.reactivex.rxjava3.core.Maybe<io.reactivex.rxjava3.schedulers.Timed<T>> timestamp(io.reactivex.rxjava3.core.Scheduler);
    Code:
       0: aload_0
       1: getstatic     #485                // Field java/util/concurrent/TimeUnit.MILLISECONDS:Ljava/util/concurrent/TimeUnit;
       4: aload_1
       5: invokevirtual #490                // Method timestamp:(Ljava/util/concurrent/TimeUnit;Lio/reactivex/rxjava3/core/Scheduler;)Lio/reactivex/rxjava3/core/Maybe;
       8: areturn

  public final io.reactivex.rxjava3.core.Maybe<io.reactivex.rxjava3.schedulers.Timed<T>> timestamp(java.util.concurrent.TimeUnit);
    Code:
       0: aload_0
       1: aload_1
       2: invokestatic  #178                // Method io/reactivex/rxjava3/schedulers/Schedulers.computation:()Lio/reactivex/rxjava3/core/Scheduler;
       5: invokevirtual #490                // Method timestamp:(Ljava/util/concurrent/TimeUnit;Lio/reactivex/rxjava3/core/Scheduler;)Lio/reactivex/rxjava3/core/Maybe;
       8: areturn

  public final io.reactivex.rxjava3.core.Maybe<io.reactivex.rxjava3.schedulers.Timed<T>> timestamp(java.util.concurrent.TimeUnit, io.reactivex.rxjava3.core.Scheduler);
    Code:
       0: aload_1
       1: ldc           #108                // String unit is null
       3: invokestatic  #3                  // Method java/util/Objects.requireNonNull:(Ljava/lang/Object;Ljava/lang/String;)Ljava/lang/Object;
       6: pop
       7: aload_2
       8: ldc           #180                // String scheduler is null
      10: invokestatic  #3                  // Method java/util/Objects.requireNonNull:(Ljava/lang/Object;Ljava/lang/String;)Ljava/lang/Object;
      13: pop
      14: new           #487                // class io/reactivex/rxjava3/internal/operators/maybe/MaybeTimeInterval
      17: dup
      18: aload_0
      19: aload_1
      20: aload_2
      21: iconst_0
      22: invokespecial #488                // Method io/reactivex/rxjava3/internal/operators/maybe/MaybeTimeInterval."<init>":(Lio/reactivex/rxjava3/core/MaybeSource;Ljava/util/concurrent/TimeUnit;Lio/reactivex/rxjava3/core/Scheduler;Z)V
      25: invokestatic  #491                // Method io/reactivex/rxjava3/plugins/RxJavaPlugins.onAssembly:(Lio/reactivex/rxjava3/core/Maybe;)Lio/reactivex/rxjava3/core/Maybe;
      28: areturn

  public final io.reactivex.rxjava3.core.Maybe<T> timeout(long, java.util.concurrent.TimeUnit);
    Code:
       0: aload_0
       1: lload_1
       2: aload_3
       3: invokestatic  #178                // Method io/reactivex/rxjava3/schedulers/Schedulers.computation:()Lio/reactivex/rxjava3/core/Scheduler;
       6: invokevirtual #492                // Method timeout:(JLjava/util/concurrent/TimeUnit;Lio/reactivex/rxjava3/core/Scheduler;)Lio/reactivex/rxjava3/core/Maybe;
       9: areturn

  public final io.reactivex.rxjava3.core.Maybe<T> timeout(long, java.util.concurrent.TimeUnit, io.reactivex.rxjava3.core.MaybeSource<? extends T>);
    Code:
       0: aload         4
       2: ldc_w         #405                // String fallback is null
       5: invokestatic  #3                  // Method java/util/Objects.requireNonNull:(Ljava/lang/Object;Ljava/lang/String;)Ljava/lang/Object;
       8: pop
       9: aload_0
      10: lload_1
      11: aload_3
      12: invokestatic  #178                // Method io/reactivex/rxjava3/schedulers/Schedulers.computation:()Lio/reactivex/rxjava3/core/Scheduler;
      15: aload         4
      17: invokevirtual #493                // Method timeout:(JLjava/util/concurrent/TimeUnit;Lio/reactivex/rxjava3/core/Scheduler;Lio/reactivex/rxjava3/core/MaybeSource;)Lio/reactivex/rxjava3/core/Maybe;
      20: areturn

  public final io.reactivex.rxjava3.core.Maybe<T> timeout(long, java.util.concurrent.TimeUnit, io.reactivex.rxjava3.core.Scheduler, io.reactivex.rxjava3.core.MaybeSource<? extends T>);
    Code:
       0: aload         5
       2: ldc_w         #405                // String fallback is null
       5: invokestatic  #3                  // Method java/util/Objects.requireNonNull:(Ljava/lang/Object;Ljava/lang/String;)Ljava/lang/Object;
       8: pop
       9: aload_0
      10: lload_1
      11: aload_3
      12: aload         4
      14: invokestatic  #179                // Method timer:(JLjava/util/concurrent/TimeUnit;Lio/reactivex/rxjava3/core/Scheduler;)Lio/reactivex/rxjava3/core/Maybe;
      17: aload         5
      19: invokevirtual #494                // Method timeout:(Lio/reactivex/rxjava3/core/MaybeSource;Lio/reactivex/rxjava3/core/MaybeSource;)Lio/reactivex/rxjava3/core/Maybe;
      22: areturn

  public final io.reactivex.rxjava3.core.Maybe<T> timeout(long, java.util.concurrent.TimeUnit, io.reactivex.rxjava3.core.Scheduler);
    Code:
       0: aload_0
       1: lload_1
       2: aload_3
       3: aload         4
       5: invokestatic  #179                // Method timer:(JLjava/util/concurrent/TimeUnit;Lio/reactivex/rxjava3/core/Scheduler;)Lio/reactivex/rxjava3/core/Maybe;
       8: invokevirtual #495                // Method timeout:(Lio/reactivex/rxjava3/core/MaybeSource;)Lio/reactivex/rxjava3/core/Maybe;
      11: areturn

  public final <U> io.reactivex.rxjava3.core.Maybe<T> timeout(io.reactivex.rxjava3.core.MaybeSource<U>);
    Code:
       0: aload_1
       1: ldc_w         #496                // String timeoutIndicator is null
       4: invokestatic  #3                  // Method java/util/Objects.requireNonNull:(Ljava/lang/Object;Ljava/lang/String;)Ljava/lang/Object;
       7: pop
       8: new           #497                // class io/reactivex/rxjava3/internal/operators/maybe/MaybeTimeoutMaybe
      11: dup
      12: aload_0
      13: aload_1
      14: aconst_null
      15: invokespecial #498                // Method io/reactivex/rxjava3/internal/operators/maybe/MaybeTimeoutMaybe."<init>":(Lio/reactivex/rxjava3/core/MaybeSource;Lio/reactivex/rxjava3/core/MaybeSource;Lio/reactivex/rxjava3/core/MaybeSource;)V
      18: invokestatic  #499                // Method io/reactivex/rxjava3/plugins/RxJavaPlugins.onAssembly:(Lio/reactivex/rxjava3/core/Maybe;)Lio/reactivex/rxjava3/core/Maybe;
      21: areturn

  public final <U> io.reactivex.rxjava3.core.Maybe<T> timeout(io.reactivex.rxjava3.core.MaybeSource<U>, io.reactivex.rxjava3.core.MaybeSource<? extends T>);
    Code:
       0: aload_1
       1: ldc_w         #496                // String timeoutIndicator is null
       4: invokestatic  #3                  // Method java/util/Objects.requireNonNull:(Ljava/lang/Object;Ljava/lang/String;)Ljava/lang/Object;
       7: pop
       8: aload_2
       9: ldc_w         #405                // String fallback is null
      12: invokestatic  #3                  // Method java/util/Objects.requireNonNull:(Ljava/lang/Object;Ljava/lang/String;)Ljava/lang/Object;
      15: pop
      16: new           #497                // class io/reactivex/rxjava3/internal/operators/maybe/MaybeTimeoutMaybe
      19: dup
      20: aload_0
      21: aload_1
      22: aload_2
      23: invokespecial #498                // Method io/reactivex/rxjava3/internal/operators/maybe/MaybeTimeoutMaybe."<init>":(Lio/reactivex/rxjava3/core/MaybeSource;Lio/reactivex/rxjava3/core/MaybeSource;Lio/reactivex/rxjava3/core/MaybeSource;)V
      26: invokestatic  #500                // Method io/reactivex/rxjava3/plugins/RxJavaPlugins.onAssembly:(Lio/reactivex/rxjava3/core/Maybe;)Lio/reactivex/rxjava3/core/Maybe;
      29: areturn

  public final <U> io.reactivex.rxjava3.core.Maybe<T> timeout(org.reactivestreams.Publisher<U>);
    Code:
       0: aload_1
       1: ldc_w         #496                // String timeoutIndicator is null
       4: invokestatic  #3                  // Method java/util/Objects.requireNonNull:(Ljava/lang/Object;Ljava/lang/String;)Ljava/lang/Object;
       7: pop
       8: new           #501                // class io/reactivex/rxjava3/internal/operators/maybe/MaybeTimeoutPublisher
      11: dup
      12: aload_0
      13: aload_1
      14: aconst_null
      15: invokespecial #502                // Method io/reactivex/rxjava3/internal/operators/maybe/MaybeTimeoutPublisher."<init>":(Lio/reactivex/rxjava3/core/MaybeSource;Lorg/reactivestreams/Publisher;Lio/reactivex/rxjava3/core/MaybeSource;)V
      18: invokestatic  #503                // Method io/reactivex/rxjava3/plugins/RxJavaPlugins.onAssembly:(Lio/reactivex/rxjava3/core/Maybe;)Lio/reactivex/rxjava3/core/Maybe;
      21: areturn

  public final <U> io.reactivex.rxjava3.core.Maybe<T> timeout(org.reactivestreams.Publisher<U>, io.reactivex.rxjava3.core.MaybeSource<? extends T>);
    Code:
       0: aload_1
       1: ldc_w         #496                // String timeoutIndicator is null
       4: invokestatic  #3                  // Method java/util/Objects.requireNonNull:(Ljava/lang/Object;Ljava/lang/String;)Ljava/lang/Object;
       7: pop
       8: aload_2
       9: ldc_w         #405                // String fallback is null
      12: invokestatic  #3                  // Method java/util/Objects.requireNonNull:(Ljava/lang/Object;Ljava/lang/String;)Ljava/lang/Object;
      15: pop
      16: new           #501                // class io/reactivex/rxjava3/internal/operators/maybe/MaybeTimeoutPublisher
      19: dup
      20: aload_0
      21: aload_1
      22: aload_2
      23: invokespecial #502                // Method io/reactivex/rxjava3/internal/operators/maybe/MaybeTimeoutPublisher."<init>":(Lio/reactivex/rxjava3/core/MaybeSource;Lorg/reactivestreams/Publisher;Lio/reactivex/rxjava3/core/MaybeSource;)V
      26: invokestatic  #504                // Method io/reactivex/rxjava3/plugins/RxJavaPlugins.onAssembly:(Lio/reactivex/rxjava3/core/Maybe;)Lio/reactivex/rxjava3/core/Maybe;
      29: areturn

  public final io.reactivex.rxjava3.core.Maybe<T> unsubscribeOn(io.reactivex.rxjava3.core.Scheduler);
    Code:
       0: aload_1
       1: ldc           #180                // String scheduler is null
       3: invokestatic  #3                  // Method java/util/Objects.requireNonNull:(Ljava/lang/Object;Ljava/lang/String;)Ljava/lang/Object;
       6: pop
       7: new           #505                // class io/reactivex/rxjava3/internal/operators/maybe/MaybeUnsubscribeOn
      10: dup
      11: aload_0
      12: aload_1
      13: invokespecial #506                // Method io/reactivex/rxjava3/internal/operators/maybe/MaybeUnsubscribeOn."<init>":(Lio/reactivex/rxjava3/core/MaybeSource;Lio/reactivex/rxjava3/core/Scheduler;)V
      16: invokestatic  #507                // Method io/reactivex/rxjava3/plugins/RxJavaPlugins.onAssembly:(Lio/reactivex/rxjava3/core/Maybe;)Lio/reactivex/rxjava3/core/Maybe;
      19: areturn

  public final <U, R> io.reactivex.rxjava3.core.Maybe<R> zipWith(io.reactivex.rxjava3.core.MaybeSource<? extends U>, io.reactivex.rxjava3.functions.BiFunction<? super T, ? super U, ? extends R>);
    Code:
       0: aload_1
       1: ldc           #230                // String other is null
       3: invokestatic  #3                  // Method java/util/Objects.requireNonNull:(Ljava/lang/Object;Ljava/lang/String;)Ljava/lang/Object;
       6: pop
       7: aload_0
       8: aload_1
       9: aload_2
      10: invokestatic  #508                // Method zip:(Lio/reactivex/rxjava3/core/MaybeSource;Lio/reactivex/rxjava3/core/MaybeSource;Lio/reactivex/rxjava3/functions/BiFunction;)Lio/reactivex/rxjava3/core/Maybe;
      13: areturn

  public final io.reactivex.rxjava3.observers.TestObserver<T> test();
    Code:
       0: new           #509                // class io/reactivex/rxjava3/observers/TestObserver
       3: dup
       4: invokespecial #510                // Method io/reactivex/rxjava3/observers/TestObserver."<init>":()V
       7: astore_1
       8: aload_0
       9: aload_1
      10: invokevirtual #234                // Method subscribe:(Lio/reactivex/rxjava3/core/MaybeObserver;)V
      13: aload_1
      14: areturn

  public final io.reactivex.rxjava3.observers.TestObserver<T> test(boolean);
    Code:
       0: new           #509                // class io/reactivex/rxjava3/observers/TestObserver
       3: dup
       4: invokespecial #510                // Method io/reactivex/rxjava3/observers/TestObserver."<init>":()V
       7: astore_2
       8: iload_1
       9: ifeq          16
      12: aload_2
      13: invokevirtual #511                // Method io/reactivex/rxjava3/observers/TestObserver.dispose:()V
      16: aload_0
      17: aload_2
      18: invokevirtual #234                // Method subscribe:(Lio/reactivex/rxjava3/core/MaybeObserver;)V
      21: aload_2
      22: areturn

  public static <T> io.reactivex.rxjava3.core.Maybe<T> fromOptional(java.util.Optional<T>);
    Code:
       0: aload_0
       1: ldc_w         #512                // String optional is null
       4: invokestatic  #3                  // Method java/util/Objects.requireNonNull:(Ljava/lang/Object;Ljava/lang/String;)Ljava/lang/Object;
       7: pop
       8: aload_0
       9: invokedynamic #513,  0            // InvokeDynamic #0:apply:()Ljava/util/function/Function;
      14: invokevirtual #514                // Method java/util/Optional.map:(Ljava/util/function/Function;)Ljava/util/Optional;
      17: invokedynamic #515,  0            // InvokeDynamic #1:get:()Ljava/util/function/Supplier;
      22: invokevirtual #516                // Method java/util/Optional.orElseGet:(Ljava/util/function/Supplier;)Ljava/lang/Object;
      25: checkcast     #517                // class io/reactivex/rxjava3/core/Maybe
      28: areturn

  public static <T> io.reactivex.rxjava3.core.Maybe<T> fromCompletionStage(java.util.concurrent.CompletionStage<T>);
    Code:
       0: aload_0
       1: ldc_w         #518                // String stage is null
       4: invokestatic  #3                  // Method java/util/Objects.requireNonNull:(Ljava/lang/Object;Ljava/lang/String;)Ljava/lang/Object;
       7: pop
       8: new           #519                // class io/reactivex/rxjava3/internal/jdk8/MaybeFromCompletionStage
      11: dup
      12: aload_0
      13: invokespecial #520                // Method io/reactivex/rxjava3/internal/jdk8/MaybeFromCompletionStage."<init>":(Ljava/util/concurrent/CompletionStage;)V
      16: invokestatic  #521                // Method io/reactivex/rxjava3/plugins/RxJavaPlugins.onAssembly:(Lio/reactivex/rxjava3/core/Maybe;)Lio/reactivex/rxjava3/core/Maybe;
      19: areturn

  public final <R> io.reactivex.rxjava3.core.Maybe<R> mapOptional(io.reactivex.rxjava3.functions.Function<? super T, java.util.Optional<? extends R>>);
    Code:
       0: aload_1
       1: ldc_w         #329                // String mapper is null
       4: invokestatic  #3                  // Method java/util/Objects.requireNonNull:(Ljava/lang/Object;Ljava/lang/String;)Ljava/lang/Object;
       7: pop
       8: new           #522                // class io/reactivex/rxjava3/internal/jdk8/MaybeMapOptional
      11: dup
      12: aload_0
      13: aload_1
      14: invokespecial #523                // Method io/reactivex/rxjava3/internal/jdk8/MaybeMapOptional."<init>":(Lio/reactivex/rxjava3/core/Maybe;Lio/reactivex/rxjava3/functions/Function;)V
      17: invokestatic  #524                // Method io/reactivex/rxjava3/plugins/RxJavaPlugins.onAssembly:(Lio/reactivex/rxjava3/core/Maybe;)Lio/reactivex/rxjava3/core/Maybe;
      20: areturn

  public final java.util.concurrent.CompletionStage<T> toCompletionStage();
    Code:
       0: aload_0
       1: new           #525                // class io/reactivex/rxjava3/internal/jdk8/CompletionStageConsumer
       4: dup
       5: iconst_0
       6: aconst_null
       7: invokespecial #526                // Method io/reactivex/rxjava3/internal/jdk8/CompletionStageConsumer."<init>":(ZLjava/lang/Object;)V
      10: invokevirtual #392                // Method subscribeWith:(Lio/reactivex/rxjava3/core/MaybeObserver;)Lio/reactivex/rxjava3/core/MaybeObserver;
      13: checkcast     #527                // class java/util/concurrent/CompletionStage
      16: areturn

  public final java.util.concurrent.CompletionStage<T> toCompletionStage(T);
    Code:
       0: aload_0
       1: new           #525                // class io/reactivex/rxjava3/internal/jdk8/CompletionStageConsumer
       4: dup
       5: iconst_1
       6: aload_1
       7: invokespecial #526                // Method io/reactivex/rxjava3/internal/jdk8/CompletionStageConsumer."<init>":(ZLjava/lang/Object;)V
      10: invokevirtual #392                // Method subscribeWith:(Lio/reactivex/rxjava3/core/MaybeObserver;)Lio/reactivex/rxjava3/core/MaybeObserver;
      13: checkcast     #528                // class java/util/concurrent/CompletionStage
      16: areturn

  public final <R> io.reactivex.rxjava3.core.Flowable<R> flattenStreamAsFlowable(io.reactivex.rxjava3.functions.Function<? super T, ? extends java.util.stream.Stream<? extends R>>);
    Code:
       0: aload_1
       1: ldc_w         #329                // String mapper is null
       4: invokestatic  #3                  // Method java/util/Objects.requireNonNull:(Ljava/lang/Object;Ljava/lang/String;)Ljava/lang/Object;
       7: pop
       8: new           #529                // class io/reactivex/rxjava3/internal/jdk8/MaybeFlattenStreamAsFlowable
      11: dup
      12: aload_0
      13: aload_1
      14: invokespecial #530                // Method io/reactivex/rxjava3/internal/jdk8/MaybeFlattenStreamAsFlowable."<init>":(Lio/reactivex/rxjava3/core/Maybe;Lio/reactivex/rxjava3/functions/Function;)V
      17: invokestatic  #531                // Method io/reactivex/rxjava3/plugins/RxJavaPlugins.onAssembly:(Lio/reactivex/rxjava3/core/Flowable;)Lio/reactivex/rxjava3/core/Flowable;
      20: areturn

  public final <R> io.reactivex.rxjava3.core.Observable<R> flattenStreamAsObservable(io.reactivex.rxjava3.functions.Function<? super T, ? extends java.util.stream.Stream<? extends R>>);
    Code:
       0: aload_1
       1: ldc_w         #329                // String mapper is null
       4: invokestatic  #3                  // Method java/util/Objects.requireNonNull:(Ljava/lang/Object;Ljava/lang/String;)Ljava/lang/Object;
       7: pop
       8: new           #532                // class io/reactivex/rxjava3/internal/jdk8/MaybeFlattenStreamAsObservable
      11: dup
      12: aload_0
      13: aload_1
      14: invokespecial #533                // Method io/reactivex/rxjava3/internal/jdk8/MaybeFlattenStreamAsObservable."<init>":(Lio/reactivex/rxjava3/core/Maybe;Lio/reactivex/rxjava3/functions/Function;)V
      17: invokestatic  #534                // Method io/reactivex/rxjava3/plugins/RxJavaPlugins.onAssembly:(Lio/reactivex/rxjava3/core/Observable;)Lio/reactivex/rxjava3/core/Observable;
      20: areturn
}
