Compiled from "Notification.java"
public final class io.reactivex.rxjava3.core.Notification<T> {
  final java.lang.Object value;

  static final io.reactivex.rxjava3.core.Notification<java.lang.Object> COMPLETE;

  private io.reactivex.rxjava3.core.Notification(java.lang.Object);
    Code:
       0: aload_0
       1: invokespecial #1                  // Method java/lang/Object."<init>":()V
       4: aload_0
       5: aload_1
       6: putfield      #2                  // Field value:Ljava/lang/Object;
       9: return

  public boolean isOnComplete();
    Code:
       0: aload_0
       1: getfield      #2                  // Field value:Ljava/lang/Object;
       4: ifnonnull     11
       7: iconst_1
       8: goto          12
      11: iconst_0
      12: ireturn

  public boolean isOnError();
    Code:
       0: aload_0
       1: getfield      #2                  // Field value:Ljava/lang/Object;
       4: invokestatic  #3                  // Method io/reactivex/rxjava3/internal/util/NotificationLite.isError:(Ljava/lang/Object;)Z
       7: ireturn

  public boolean isOnNext();
    Code:
       0: aload_0
       1: getfield      #2                  // Field value:Ljava/lang/Object;
       4: astore_1
       5: aload_1
       6: ifnull        20
       9: aload_1
      10: invokestatic  #3                  // Method io/reactivex/rxjava3/internal/util/NotificationLite.isError:(Ljava/lang/Object;)Z
      13: ifne          20
      16: iconst_1
      17: goto          21
      20: iconst_0
      21: ireturn

  public T getValue();
    Code:
       0: aload_0
       1: getfield      #2                  // Field value:Ljava/lang/Object;
       4: astore_1
       5: aload_1
       6: ifnull        21
       9: aload_1
      10: invokestatic  #3                  // Method io/reactivex/rxjava3/internal/util/NotificationLite.isError:(Ljava/lang/Object;)Z
      13: ifne          21
      16: aload_0
      17: getfield      #2                  // Field value:Ljava/lang/Object;
      20: areturn
      21: aconst_null
      22: areturn

  public java.lang.Throwable getError();
    Code:
       0: aload_0
       1: getfield      #2                  // Field value:Ljava/lang/Object;
       4: astore_1
       5: aload_1
       6: invokestatic  #3                  // Method io/reactivex/rxjava3/internal/util/NotificationLite.isError:(Ljava/lang/Object;)Z
       9: ifeq          17
      12: aload_1
      13: invokestatic  #4                  // Method io/reactivex/rxjava3/internal/util/NotificationLite.getError:(Ljava/lang/Object;)Ljava/lang/Throwable;
      16: areturn
      17: aconst_null
      18: areturn

  public boolean equals(java.lang.Object);
    Code:
       0: aload_1
       1: instanceof    #5                  // class io/reactivex/rxjava3/core/Notification
       4: ifeq          24
       7: aload_1
       8: checkcast     #5                  // class io/reactivex/rxjava3/core/Notification
      11: astore_2
      12: aload_0
      13: getfield      #2                  // Field value:Ljava/lang/Object;
      16: aload_2
      17: getfield      #2                  // Field value:Ljava/lang/Object;
      20: invokestatic  #6                  // Method java/util/Objects.equals:(Ljava/lang/Object;Ljava/lang/Object;)Z
      23: ireturn
      24: iconst_0
      25: ireturn

  public int hashCode();
    Code:
       0: aload_0
       1: getfield      #2                  // Field value:Ljava/lang/Object;
       4: astore_1
       5: aload_1
       6: ifnull        16
       9: aload_1
      10: invokevirtual #7                  // Method java/lang/Object.hashCode:()I
      13: goto          17
      16: iconst_0
      17: ireturn

  public java.lang.String toString();
    Code:
       0: aload_0
       1: getfield      #2                  // Field value:Ljava/lang/Object;
       4: astore_1
       5: aload_1
       6: ifnonnull     12
       9: ldc           #8                  // String OnCompleteNotification
      11: areturn
      12: aload_1
      13: invokestatic  #3                  // Method io/reactivex/rxjava3/internal/util/NotificationLite.isError:(Ljava/lang/Object;)Z
      16: ifeq          47
      19: new           #9                  // class java/lang/StringBuilder
      22: dup
      23: invokespecial #10                 // Method java/lang/StringBuilder."<init>":()V
      26: ldc           #11                 // String OnErrorNotification[
      28: invokevirtual #12                 // Method java/lang/StringBuilder.append:(Ljava/lang/String;)Ljava/lang/StringBuilder;
      31: aload_1
      32: invokestatic  #4                  // Method io/reactivex/rxjava3/internal/util/NotificationLite.getError:(Ljava/lang/Object;)Ljava/lang/Throwable;
      35: invokevirtual #13                 // Method java/lang/StringBuilder.append:(Ljava/lang/Object;)Ljava/lang/StringBuilder;
      38: ldc           #14                 // String ]
      40: invokevirtual #12                 // Method java/lang/StringBuilder.append:(Ljava/lang/String;)Ljava/lang/StringBuilder;
      43: invokevirtual #15                 // Method java/lang/StringBuilder.toString:()Ljava/lang/String;
      46: areturn
      47: new           #9                  // class java/lang/StringBuilder
      50: dup
      51: invokespecial #10                 // Method java/lang/StringBuilder."<init>":()V
      54: ldc           #16                 // String OnNextNotification[
      56: invokevirtual #12                 // Method java/lang/StringBuilder.append:(Ljava/lang/String;)Ljava/lang/StringBuilder;
      59: aload_0
      60: getfield      #2                  // Field value:Ljava/lang/Object;
      63: invokevirtual #13                 // Method java/lang/StringBuilder.append:(Ljava/lang/Object;)Ljava/lang/StringBuilder;
      66: ldc           #14                 // String ]
      68: invokevirtual #12                 // Method java/lang/StringBuilder.append:(Ljava/lang/String;)Ljava/lang/StringBuilder;
      71: invokevirtual #15                 // Method java/lang/StringBuilder.toString:()Ljava/lang/String;
      74: areturn

  public static <T> io.reactivex.rxjava3.core.Notification<T> createOnNext(T);
    Code:
       0: aload_0
       1: ldc           #17                 // String value is null
       3: invokestatic  #18                 // Method java/util/Objects.requireNonNull:(Ljava/lang/Object;Ljava/lang/String;)Ljava/lang/Object;
       6: pop
       7: new           #5                  // class io/reactivex/rxjava3/core/Notification
      10: dup
      11: aload_0
      12: invokespecial #19                 // Method "<init>":(Ljava/lang/Object;)V
      15: areturn

  public static <T> io.reactivex.rxjava3.core.Notification<T> createOnError(java.lang.Throwable);
    Code:
       0: aload_0
       1: ldc           #20                 // String error is null
       3: invokestatic  #18                 // Method java/util/Objects.requireNonNull:(Ljava/lang/Object;Ljava/lang/String;)Ljava/lang/Object;
       6: pop
       7: new           #5                  // class io/reactivex/rxjava3/core/Notification
      10: dup
      11: aload_0
      12: invokestatic  #21                 // Method io/reactivex/rxjava3/internal/util/NotificationLite.error:(Ljava/lang/Throwable;)Ljava/lang/Object;
      15: invokespecial #19                 // Method "<init>":(Ljava/lang/Object;)V
      18: areturn

  public static <T> io.reactivex.rxjava3.core.Notification<T> createOnComplete();
    Code:
       0: getstatic     #22                 // Field COMPLETE:Lio/reactivex/rxjava3/core/Notification;
       3: areturn

  static {};
    Code:
       0: new           #5                  // class io/reactivex/rxjava3/core/Notification
       3: dup
       4: aconst_null
       5: invokespecial #19                 // Method "<init>":(Ljava/lang/Object;)V
       8: putstatic     #22                 // Field COMPLETE:Lio/reactivex/rxjava3/core/Notification;
      11: return
}
