Compiled from "Scheduler.java"
public abstract class io.reactivex.rxjava3.core.Scheduler$Worker implements io.reactivex.rxjava3.disposables.Disposable {
  public io.reactivex.rxjava3.core.Scheduler$Worker();
    Code:
       0: aload_0
       1: invokespecial #1                  // Method java/lang/Object."<init>":()V
       4: return

  public io.reactivex.rxjava3.disposables.Disposable schedule(java.lang.Runnable);
    Code:
       0: aload_0
       1: aload_1
       2: lconst_0
       3: getstatic     #2                  // Field java/util/concurrent/TimeUnit.NANOSECONDS:Ljava/util/concurrent/TimeUnit;
       6: invokevirtual #3                  // Method schedule:(Ljava/lang/Runnable;JLjava/util/concurrent/TimeUnit;)Lio/reactivex/rxjava3/disposables/Disposable;
       9: areturn

  public abstract io.reactivex.rxjava3.disposables.Disposable schedule(java.lang.Runnable, long, java.util.concurrent.TimeUnit);

  public io.reactivex.rxjava3.disposables.Disposable schedulePeriodically(java.lang.Runnable, long, long, java.util.concurrent.TimeUnit);
    Code:
       0: new           #4                  // class io/reactivex/rxjava3/internal/disposables/SequentialDisposable
       3: dup
       4: invokespecial #5                  // Method io/reactivex/rxjava3/internal/disposables/SequentialDisposable."<init>":()V
       7: astore        7
       9: new           #4                  // class io/reactivex/rxjava3/internal/disposables/SequentialDisposable
      12: dup
      13: aload         7
      15: invokespecial #6                  // Method io/reactivex/rxjava3/internal/disposables/SequentialDisposable."<init>":(Lio/reactivex/rxjava3/disposables/Disposable;)V
      18: astore        8
      20: aload_1
      21: invokestatic  #7                  // Method io/reactivex/rxjava3/plugins/RxJavaPlugins.onSchedule:(Ljava/lang/Runnable;)Ljava/lang/Runnable;
      24: astore        9
      26: aload         6
      28: lload         4
      30: invokevirtual #8                  // Method java/util/concurrent/TimeUnit.toNanos:(J)J
      33: lstore        10
      35: aload_0
      36: getstatic     #2                  // Field java/util/concurrent/TimeUnit.NANOSECONDS:Ljava/util/concurrent/TimeUnit;
      39: invokevirtual #9                  // Method now:(Ljava/util/concurrent/TimeUnit;)J
      42: lstore        12
      44: lload         12
      46: aload         6
      48: lload_2
      49: invokevirtual #8                  // Method java/util/concurrent/TimeUnit.toNanos:(J)J
      52: ladd
      53: lstore        14
      55: aload_0
      56: new           #10                 // class io/reactivex/rxjava3/core/Scheduler$Worker$PeriodicTask
      59: dup
      60: aload_0
      61: lload         14
      63: aload         9
      65: lload         12
      67: aload         8
      69: lload         10
      71: invokespecial #11                 // Method io/reactivex/rxjava3/core/Scheduler$Worker$PeriodicTask."<init>":(Lio/reactivex/rxjava3/core/Scheduler$Worker;JLjava/lang/Runnable;JLio/reactivex/rxjava3/internal/disposables/SequentialDisposable;J)V
      74: lload_2
      75: aload         6
      77: invokevirtual #3                  // Method schedule:(Ljava/lang/Runnable;JLjava/util/concurrent/TimeUnit;)Lio/reactivex/rxjava3/disposables/Disposable;
      80: astore        16
      82: aload         16
      84: getstatic     #12                 // Field io/reactivex/rxjava3/internal/disposables/EmptyDisposable.INSTANCE:Lio/reactivex/rxjava3/internal/disposables/EmptyDisposable;
      87: if_acmpne     93
      90: aload         16
      92: areturn
      93: aload         7
      95: aload         16
      97: invokevirtual #13                 // Method io/reactivex/rxjava3/internal/disposables/SequentialDisposable.replace:(Lio/reactivex/rxjava3/disposables/Disposable;)Z
     100: pop
     101: aload         8
     103: areturn

  public long now(java.util.concurrent.TimeUnit);
    Code:
       0: aload_1
       1: invokestatic  #14                 // Method io/reactivex/rxjava3/core/Scheduler.computeNow:(Ljava/util/concurrent/TimeUnit;)J
       4: lreturn
}
