Compiled from "Scheduler.java"
final class io.reactivex.rxjava3.core.Scheduler$Worker$PeriodicTask implements java.lang.Runnable,io.reactivex.rxjava3.schedulers.SchedulerRunnableIntrospection {
  final java.lang.Runnable decoratedRun;

  final io.reactivex.rxjava3.internal.disposables.SequentialDisposable sd;

  final long periodInNanoseconds;

  long count;

  long lastNowNanoseconds;

  long startInNanoseconds;

  final io.reactivex.rxjava3.core.Scheduler$Worker this$0;

  io.reactivex.rxjava3.core.Scheduler$Worker$PeriodicTask(io.reactivex.rxjava3.core.Scheduler$Worker, long, java.lang.Runnable, long, io.reactivex.rxjava3.internal.disposables.SequentialDisposable, long);
    Code:
       0: aload_0
       1: aload_1
       2: putfield      #1                  // Field this$0:Lio/reactivex/rxjava3/core/Scheduler$Worker;
       5: aload_0
       6: invokespecial #2                  // Method java/lang/Object."<init>":()V
       9: aload_0
      10: aload         4
      12: putfield      #3                  // Field decoratedRun:Ljava/lang/Runnable;
      15: aload_0
      16: aload         7
      18: putfield      #4                  // Field sd:Lio/reactivex/rxjava3/internal/disposables/SequentialDisposable;
      21: aload_0
      22: lload         8
      24: putfield      #5                  // Field periodInNanoseconds:J
      27: aload_0
      28: lload         5
      30: putfield      #6                  // Field lastNowNanoseconds:J
      33: aload_0
      34: lload_2
      35: putfield      #7                  // Field startInNanoseconds:J
      38: return

  public void run();
    Code:
       0: aload_0
       1: getfield      #3                  // Field decoratedRun:Ljava/lang/Runnable;
       4: invokeinterface #8,  1            // InterfaceMethod java/lang/Runnable.run:()V
       9: aload_0
      10: getfield      #4                  // Field sd:Lio/reactivex/rxjava3/internal/disposables/SequentialDisposable;
      13: invokevirtual #9                  // Method io/reactivex/rxjava3/internal/disposables/SequentialDisposable.isDisposed:()Z
      16: ifne          146
      19: aload_0
      20: getfield      #1                  // Field this$0:Lio/reactivex/rxjava3/core/Scheduler$Worker;
      23: getstatic     #10                 // Field java/util/concurrent/TimeUnit.NANOSECONDS:Ljava/util/concurrent/TimeUnit;
      26: invokevirtual #11                 // Method io/reactivex/rxjava3/core/Scheduler$Worker.now:(Ljava/util/concurrent/TimeUnit;)J
      29: lstore_3
      30: lload_3
      31: getstatic     #12                 // Field io/reactivex/rxjava3/core/Scheduler.CLOCK_DRIFT_TOLERANCE_NANOSECONDS:J
      34: ladd
      35: aload_0
      36: getfield      #6                  // Field lastNowNanoseconds:J
      39: lcmp
      40: iflt          61
      43: lload_3
      44: aload_0
      45: getfield      #6                  // Field lastNowNanoseconds:J
      48: aload_0
      49: getfield      #5                  // Field periodInNanoseconds:J
      52: ladd
      53: getstatic     #12                 // Field io/reactivex/rxjava3/core/Scheduler.CLOCK_DRIFT_TOLERANCE_NANOSECONDS:J
      56: ladd
      57: lcmp
      58: iflt          93
      61: lload_3
      62: aload_0
      63: getfield      #5                  // Field periodInNanoseconds:J
      66: ladd
      67: lstore_1
      68: aload_0
      69: lload_1
      70: aload_0
      71: getfield      #5                  // Field periodInNanoseconds:J
      74: aload_0
      75: dup
      76: getfield      #13                 // Field count:J
      79: lconst_1
      80: ladd
      81: dup2_x1
      82: putfield      #13                 // Field count:J
      85: lmul
      86: lsub
      87: putfield      #7                  // Field startInNanoseconds:J
      90: goto          115
      93: aload_0
      94: getfield      #7                  // Field startInNanoseconds:J
      97: aload_0
      98: dup
      99: getfield      #13                 // Field count:J
     102: lconst_1
     103: ladd
     104: dup2_x1
     105: putfield      #13                 // Field count:J
     108: aload_0
     109: getfield      #5                  // Field periodInNanoseconds:J
     112: lmul
     113: ladd
     114: lstore_1
     115: aload_0
     116: lload_3
     117: putfield      #6                  // Field lastNowNanoseconds:J
     120: lload_1
     121: lload_3
     122: lsub
     123: lstore        5
     125: aload_0
     126: getfield      #4                  // Field sd:Lio/reactivex/rxjava3/internal/disposables/SequentialDisposable;
     129: aload_0
     130: getfield      #1                  // Field this$0:Lio/reactivex/rxjava3/core/Scheduler$Worker;
     133: aload_0
     134: lload         5
     136: getstatic     #10                 // Field java/util/concurrent/TimeUnit.NANOSECONDS:Ljava/util/concurrent/TimeUnit;
     139: invokevirtual #14                 // Method io/reactivex/rxjava3/core/Scheduler$Worker.schedule:(Ljava/lang/Runnable;JLjava/util/concurrent/TimeUnit;)Lio/reactivex/rxjava3/disposables/Disposable;
     142: invokevirtual #15                 // Method io/reactivex/rxjava3/internal/disposables/SequentialDisposable.replace:(Lio/reactivex/rxjava3/disposables/Disposable;)Z
     145: pop
     146: return

  public java.lang.Runnable getWrappedRunnable();
    Code:
       0: aload_0
       1: getfield      #3                  // Field decoratedRun:Ljava/lang/Runnable;
       4: areturn
}
