Compiled from "Single.java"
public abstract class io.reactivex.rxjava3.core.Single<T> implements io.reactivex.rxjava3.core.SingleSource<T> {
  public io.reactivex.rxjava3.core.Single();
    Code:
       0: aload_0
       1: invokespecial #1                  // Method java/lang/Object."<init>":()V
       4: return

  public static <T> io.reactivex.rxjava3.core.Single<T> amb(java.lang.Iterable<? extends io.reactivex.rxjava3.core.SingleSource<? extends T>>);
    Code:
       0: aload_0
       1: ldc           #2                  // String sources is null
       3: invokestatic  #3                  // Method java/util/Objects.requireNonNull:(Ljava/lang/Object;Ljava/lang/String;)Ljava/lang/Object;
       6: pop
       7: new           #4                  // class io/reactivex/rxjava3/internal/operators/single/SingleAmb
      10: dup
      11: aconst_null
      12: aload_0
      13: invokespecial #5                  // Method io/reactivex/rxjava3/internal/operators/single/SingleAmb."<init>":([Lio/reactivex/rxjava3/core/SingleSource;Ljava/lang/Iterable;)V
      16: invokestatic  #6                  // Method io/reactivex/rxjava3/plugins/RxJavaPlugins.onAssembly:(Lio/reactivex/rxjava3/core/Single;)Lio/reactivex/rxjava3/core/Single;
      19: areturn

  public static <T> io.reactivex.rxjava3.core.Single<T> ambArray(io.reactivex.rxjava3.core.SingleSource<? extends T>...);
    Code:
       0: aload_0
       1: ldc           #2                  // String sources is null
       3: invokestatic  #3                  // Method java/util/Objects.requireNonNull:(Ljava/lang/Object;Ljava/lang/String;)Ljava/lang/Object;
       6: pop
       7: aload_0
       8: arraylength
       9: ifne          19
      12: invokestatic  #7                  // Method io/reactivex/rxjava3/internal/operators/single/SingleInternalHelper.emptyThrower:()Lio/reactivex/rxjava3/functions/Supplier;
      15: invokestatic  #8                  // Method error:(Lio/reactivex/rxjava3/functions/Supplier;)Lio/reactivex/rxjava3/core/Single;
      18: areturn
      19: aload_0
      20: arraylength
      21: iconst_1
      22: if_icmpne     34
      25: aload_0
      26: iconst_0
      27: aaload
      28: astore_1
      29: aload_1
      30: invokestatic  #9                  // Method wrap:(Lio/reactivex/rxjava3/core/SingleSource;)Lio/reactivex/rxjava3/core/Single;
      33: areturn
      34: new           #4                  // class io/reactivex/rxjava3/internal/operators/single/SingleAmb
      37: dup
      38: aload_0
      39: aconst_null
      40: invokespecial #5                  // Method io/reactivex/rxjava3/internal/operators/single/SingleAmb."<init>":([Lio/reactivex/rxjava3/core/SingleSource;Ljava/lang/Iterable;)V
      43: invokestatic  #10                 // Method io/reactivex/rxjava3/plugins/RxJavaPlugins.onAssembly:(Lio/reactivex/rxjava3/core/Single;)Lio/reactivex/rxjava3/core/Single;
      46: areturn

  public static <T> io.reactivex.rxjava3.core.Flowable<T> concat(java.lang.Iterable<? extends io.reactivex.rxjava3.core.SingleSource<? extends T>>);
    Code:
       0: aload_0
       1: invokestatic  #11                 // Method io/reactivex/rxjava3/core/Flowable.fromIterable:(Ljava/lang/Iterable;)Lio/reactivex/rxjava3/core/Flowable;
       4: invokestatic  #12                 // Method io/reactivex/rxjava3/internal/functions/Functions.identity:()Lio/reactivex/rxjava3/functions/Function;
       7: iconst_0
       8: invokevirtual #13                 // Method io/reactivex/rxjava3/core/Flowable.concatMapSingleDelayError:(Lio/reactivex/rxjava3/functions/Function;Z)Lio/reactivex/rxjava3/core/Flowable;
      11: areturn

  public static <T> io.reactivex.rxjava3.core.Observable<T> concat(io.reactivex.rxjava3.core.ObservableSource<? extends io.reactivex.rxjava3.core.SingleSource<? extends T>>);
    Code:
       0: aload_0
       1: ldc           #2                  // String sources is null
       3: invokestatic  #3                  // Method java/util/Objects.requireNonNull:(Ljava/lang/Object;Ljava/lang/String;)Ljava/lang/Object;
       6: pop
       7: new           #14                 // class io/reactivex/rxjava3/internal/operators/mixed/ObservableConcatMapSingle
      10: dup
      11: aload_0
      12: invokestatic  #15                 // Method io/reactivex/rxjava3/internal/functions/Functions.identity:()Lio/reactivex/rxjava3/functions/Function;
      15: getstatic     #16                 // Field io/reactivex/rxjava3/internal/util/ErrorMode.IMMEDIATE:Lio/reactivex/rxjava3/internal/util/ErrorMode;
      18: iconst_2
      19: invokespecial #17                 // Method io/reactivex/rxjava3/internal/operators/mixed/ObservableConcatMapSingle."<init>":(Lio/reactivex/rxjava3/core/ObservableSource;Lio/reactivex/rxjava3/functions/Function;Lio/reactivex/rxjava3/internal/util/ErrorMode;I)V
      22: invokestatic  #18                 // Method io/reactivex/rxjava3/plugins/RxJavaPlugins.onAssembly:(Lio/reactivex/rxjava3/core/Observable;)Lio/reactivex/rxjava3/core/Observable;
      25: areturn

  public static <T> io.reactivex.rxjava3.core.Flowable<T> concat(org.reactivestreams.Publisher<? extends io.reactivex.rxjava3.core.SingleSource<? extends T>>);
    Code:
       0: aload_0
       1: iconst_2
       2: invokestatic  #19                 // Method concat:(Lorg/reactivestreams/Publisher;I)Lio/reactivex/rxjava3/core/Flowable;
       5: areturn

  public static <T> io.reactivex.rxjava3.core.Flowable<T> concat(org.reactivestreams.Publisher<? extends io.reactivex.rxjava3.core.SingleSource<? extends T>>, int);
    Code:
       0: aload_0
       1: ldc           #2                  // String sources is null
       3: invokestatic  #3                  // Method java/util/Objects.requireNonNull:(Ljava/lang/Object;Ljava/lang/String;)Ljava/lang/Object;
       6: pop
       7: iload_1
       8: ldc           #20                 // String prefetch
      10: invokestatic  #21                 // Method io/reactivex/rxjava3/internal/functions/ObjectHelper.verifyPositive:(ILjava/lang/String;)I
      13: pop
      14: new           #22                 // class io/reactivex/rxjava3/internal/operators/mixed/FlowableConcatMapSinglePublisher
      17: dup
      18: aload_0
      19: invokestatic  #23                 // Method io/reactivex/rxjava3/internal/functions/Functions.identity:()Lio/reactivex/rxjava3/functions/Function;
      22: getstatic     #16                 // Field io/reactivex/rxjava3/internal/util/ErrorMode.IMMEDIATE:Lio/reactivex/rxjava3/internal/util/ErrorMode;
      25: iload_1
      26: invokespecial #24                 // Method io/reactivex/rxjava3/internal/operators/mixed/FlowableConcatMapSinglePublisher."<init>":(Lorg/reactivestreams/Publisher;Lio/reactivex/rxjava3/functions/Function;Lio/reactivex/rxjava3/internal/util/ErrorMode;I)V
      29: invokestatic  #25                 // Method io/reactivex/rxjava3/plugins/RxJavaPlugins.onAssembly:(Lio/reactivex/rxjava3/core/Flowable;)Lio/reactivex/rxjava3/core/Flowable;
      32: areturn

  public static <T> io.reactivex.rxjava3.core.Flowable<T> concat(io.reactivex.rxjava3.core.SingleSource<? extends T>, io.reactivex.rxjava3.core.SingleSource<? extends T>);
    Code:
       0: aload_0
       1: ldc           #26                 // String source1 is null
       3: invokestatic  #3                  // Method java/util/Objects.requireNonNull:(Ljava/lang/Object;Ljava/lang/String;)Ljava/lang/Object;
       6: pop
       7: aload_1
       8: ldc           #27                 // String source2 is null
      10: invokestatic  #3                  // Method java/util/Objects.requireNonNull:(Ljava/lang/Object;Ljava/lang/String;)Ljava/lang/Object;
      13: pop
      14: iconst_2
      15: anewarray     #28                 // class io/reactivex/rxjava3/core/SingleSource
      18: dup
      19: iconst_0
      20: aload_0
      21: aastore
      22: dup
      23: iconst_1
      24: aload_1
      25: aastore
      26: invokestatic  #29                 // Method io/reactivex/rxjava3/core/Flowable.fromArray:([Ljava/lang/Object;)Lio/reactivex/rxjava3/core/Flowable;
      29: invokestatic  #30                 // Method io/reactivex/rxjava3/internal/functions/Functions.identity:()Lio/reactivex/rxjava3/functions/Function;
      32: iconst_0
      33: invokevirtual #31                 // Method io/reactivex/rxjava3/core/Flowable.concatMapSingleDelayError:(Lio/reactivex/rxjava3/functions/Function;Z)Lio/reactivex/rxjava3/core/Flowable;
      36: areturn

  public static <T> io.reactivex.rxjava3.core.Flowable<T> concat(io.reactivex.rxjava3.core.SingleSource<? extends T>, io.reactivex.rxjava3.core.SingleSource<? extends T>, io.reactivex.rxjava3.core.SingleSource<? extends T>);
    Code:
       0: aload_0
       1: ldc           #26                 // String source1 is null
       3: invokestatic  #3                  // Method java/util/Objects.requireNonNull:(Ljava/lang/Object;Ljava/lang/String;)Ljava/lang/Object;
       6: pop
       7: aload_1
       8: ldc           #27                 // String source2 is null
      10: invokestatic  #3                  // Method java/util/Objects.requireNonNull:(Ljava/lang/Object;Ljava/lang/String;)Ljava/lang/Object;
      13: pop
      14: aload_2
      15: ldc           #32                 // String source3 is null
      17: invokestatic  #3                  // Method java/util/Objects.requireNonNull:(Ljava/lang/Object;Ljava/lang/String;)Ljava/lang/Object;
      20: pop
      21: iconst_3
      22: anewarray     #28                 // class io/reactivex/rxjava3/core/SingleSource
      25: dup
      26: iconst_0
      27: aload_0
      28: aastore
      29: dup
      30: iconst_1
      31: aload_1
      32: aastore
      33: dup
      34: iconst_2
      35: aload_2
      36: aastore
      37: invokestatic  #33                 // Method io/reactivex/rxjava3/core/Flowable.fromArray:([Ljava/lang/Object;)Lio/reactivex/rxjava3/core/Flowable;
      40: invokestatic  #34                 // Method io/reactivex/rxjava3/internal/functions/Functions.identity:()Lio/reactivex/rxjava3/functions/Function;
      43: iconst_0
      44: invokevirtual #35                 // Method io/reactivex/rxjava3/core/Flowable.concatMapSingleDelayError:(Lio/reactivex/rxjava3/functions/Function;Z)Lio/reactivex/rxjava3/core/Flowable;
      47: areturn

  public static <T> io.reactivex.rxjava3.core.Flowable<T> concat(io.reactivex.rxjava3.core.SingleSource<? extends T>, io.reactivex.rxjava3.core.SingleSource<? extends T>, io.reactivex.rxjava3.core.SingleSource<? extends T>, io.reactivex.rxjava3.core.SingleSource<? extends T>);
    Code:
       0: aload_0
       1: ldc           #26                 // String source1 is null
       3: invokestatic  #3                  // Method java/util/Objects.requireNonNull:(Ljava/lang/Object;Ljava/lang/String;)Ljava/lang/Object;
       6: pop
       7: aload_1
       8: ldc           #27                 // String source2 is null
      10: invokestatic  #3                  // Method java/util/Objects.requireNonNull:(Ljava/lang/Object;Ljava/lang/String;)Ljava/lang/Object;
      13: pop
      14: aload_2
      15: ldc           #32                 // String source3 is null
      17: invokestatic  #3                  // Method java/util/Objects.requireNonNull:(Ljava/lang/Object;Ljava/lang/String;)Ljava/lang/Object;
      20: pop
      21: aload_3
      22: ldc           #36                 // String source4 is null
      24: invokestatic  #3                  // Method java/util/Objects.requireNonNull:(Ljava/lang/Object;Ljava/lang/String;)Ljava/lang/Object;
      27: pop
      28: iconst_4
      29: anewarray     #28                 // class io/reactivex/rxjava3/core/SingleSource
      32: dup
      33: iconst_0
      34: aload_0
      35: aastore
      36: dup
      37: iconst_1
      38: aload_1
      39: aastore
      40: dup
      41: iconst_2
      42: aload_2
      43: aastore
      44: dup
      45: iconst_3
      46: aload_3
      47: aastore
      48: invokestatic  #37                 // Method io/reactivex/rxjava3/core/Flowable.fromArray:([Ljava/lang/Object;)Lio/reactivex/rxjava3/core/Flowable;
      51: invokestatic  #38                 // Method io/reactivex/rxjava3/internal/functions/Functions.identity:()Lio/reactivex/rxjava3/functions/Function;
      54: iconst_0
      55: invokevirtual #39                 // Method io/reactivex/rxjava3/core/Flowable.concatMapSingleDelayError:(Lio/reactivex/rxjava3/functions/Function;Z)Lio/reactivex/rxjava3/core/Flowable;
      58: areturn

  public static <T> io.reactivex.rxjava3.core.Flowable<T> concatArray(io.reactivex.rxjava3.core.SingleSource<? extends T>...);
    Code:
       0: aload_0
       1: invokestatic  #40                 // Method io/reactivex/rxjava3/core/Flowable.fromArray:([Ljava/lang/Object;)Lio/reactivex/rxjava3/core/Flowable;
       4: invokestatic  #41                 // Method io/reactivex/rxjava3/internal/functions/Functions.identity:()Lio/reactivex/rxjava3/functions/Function;
       7: iconst_0
       8: invokevirtual #42                 // Method io/reactivex/rxjava3/core/Flowable.concatMapSingleDelayError:(Lio/reactivex/rxjava3/functions/Function;Z)Lio/reactivex/rxjava3/core/Flowable;
      11: areturn

  public static <T> io.reactivex.rxjava3.core.Flowable<T> concatArrayDelayError(io.reactivex.rxjava3.core.SingleSource<? extends T>...);
    Code:
       0: aload_0
       1: invokestatic  #43                 // Method io/reactivex/rxjava3/core/Flowable.fromArray:([Ljava/lang/Object;)Lio/reactivex/rxjava3/core/Flowable;
       4: invokestatic  #44                 // Method io/reactivex/rxjava3/internal/functions/Functions.identity:()Lio/reactivex/rxjava3/functions/Function;
       7: iconst_1
       8: invokevirtual #45                 // Method io/reactivex/rxjava3/core/Flowable.concatMapSingleDelayError:(Lio/reactivex/rxjava3/functions/Function;Z)Lio/reactivex/rxjava3/core/Flowable;
      11: areturn

  public static <T> io.reactivex.rxjava3.core.Flowable<T> concatArrayEager(io.reactivex.rxjava3.core.SingleSource<? extends T>...);
    Code:
       0: aload_0
       1: invokestatic  #46                 // Method io/reactivex/rxjava3/core/Flowable.fromArray:([Ljava/lang/Object;)Lio/reactivex/rxjava3/core/Flowable;
       4: invokestatic  #47                 // Method io/reactivex/rxjava3/internal/operators/single/SingleInternalHelper.toFlowable:()Lio/reactivex/rxjava3/functions/Function;
       7: invokevirtual #48                 // Method io/reactivex/rxjava3/core/Flowable.concatMapEager:(Lio/reactivex/rxjava3/functions/Function;)Lio/reactivex/rxjava3/core/Flowable;
      10: areturn

  public static <T> io.reactivex.rxjava3.core.Flowable<T> concatArrayEagerDelayError(io.reactivex.rxjava3.core.SingleSource<? extends T>...);
    Code:
       0: aload_0
       1: invokestatic  #49                 // Method io/reactivex/rxjava3/core/Flowable.fromArray:([Ljava/lang/Object;)Lio/reactivex/rxjava3/core/Flowable;
       4: invokestatic  #47                 // Method io/reactivex/rxjava3/internal/operators/single/SingleInternalHelper.toFlowable:()Lio/reactivex/rxjava3/functions/Function;
       7: iconst_1
       8: invokevirtual #50                 // Method io/reactivex/rxjava3/core/Flowable.concatMapEagerDelayError:(Lio/reactivex/rxjava3/functions/Function;Z)Lio/reactivex/rxjava3/core/Flowable;
      11: areturn

  public static <T> io.reactivex.rxjava3.core.Flowable<T> concatDelayError(java.lang.Iterable<? extends io.reactivex.rxjava3.core.SingleSource<? extends T>>);
    Code:
       0: aload_0
       1: invokestatic  #51                 // Method io/reactivex/rxjava3/core/Flowable.fromIterable:(Ljava/lang/Iterable;)Lio/reactivex/rxjava3/core/Flowable;
       4: invokestatic  #52                 // Method io/reactivex/rxjava3/internal/functions/Functions.identity:()Lio/reactivex/rxjava3/functions/Function;
       7: invokevirtual #53                 // Method io/reactivex/rxjava3/core/Flowable.concatMapSingleDelayError:(Lio/reactivex/rxjava3/functions/Function;)Lio/reactivex/rxjava3/core/Flowable;
      10: areturn

  public static <T> io.reactivex.rxjava3.core.Flowable<T> concatDelayError(org.reactivestreams.Publisher<? extends io.reactivex.rxjava3.core.SingleSource<? extends T>>);
    Code:
       0: aload_0
       1: invokestatic  #54                 // Method io/reactivex/rxjava3/core/Flowable.fromPublisher:(Lorg/reactivestreams/Publisher;)Lio/reactivex/rxjava3/core/Flowable;
       4: invokestatic  #55                 // Method io/reactivex/rxjava3/internal/functions/Functions.identity:()Lio/reactivex/rxjava3/functions/Function;
       7: invokevirtual #56                 // Method io/reactivex/rxjava3/core/Flowable.concatMapSingleDelayError:(Lio/reactivex/rxjava3/functions/Function;)Lio/reactivex/rxjava3/core/Flowable;
      10: areturn

  public static <T> io.reactivex.rxjava3.core.Flowable<T> concatDelayError(org.reactivestreams.Publisher<? extends io.reactivex.rxjava3.core.SingleSource<? extends T>>, int);
    Code:
       0: aload_0
       1: invokestatic  #57                 // Method io/reactivex/rxjava3/core/Flowable.fromPublisher:(Lorg/reactivestreams/Publisher;)Lio/reactivex/rxjava3/core/Flowable;
       4: invokestatic  #58                 // Method io/reactivex/rxjava3/internal/functions/Functions.identity:()Lio/reactivex/rxjava3/functions/Function;
       7: iconst_1
       8: iload_1
       9: invokevirtual #59                 // Method io/reactivex/rxjava3/core/Flowable.concatMapSingleDelayError:(Lio/reactivex/rxjava3/functions/Function;ZI)Lio/reactivex/rxjava3/core/Flowable;
      12: areturn

  public static <T> io.reactivex.rxjava3.core.Flowable<T> concatEager(java.lang.Iterable<? extends io.reactivex.rxjava3.core.SingleSource<? extends T>>);
    Code:
       0: aload_0
       1: invokestatic  #60                 // Method io/reactivex/rxjava3/core/Flowable.fromIterable:(Ljava/lang/Iterable;)Lio/reactivex/rxjava3/core/Flowable;
       4: invokestatic  #47                 // Method io/reactivex/rxjava3/internal/operators/single/SingleInternalHelper.toFlowable:()Lio/reactivex/rxjava3/functions/Function;
       7: iconst_0
       8: invokevirtual #61                 // Method io/reactivex/rxjava3/core/Flowable.concatMapEagerDelayError:(Lio/reactivex/rxjava3/functions/Function;Z)Lio/reactivex/rxjava3/core/Flowable;
      11: areturn

  public static <T> io.reactivex.rxjava3.core.Flowable<T> concatEager(java.lang.Iterable<? extends io.reactivex.rxjava3.core.SingleSource<? extends T>>, int);
    Code:
       0: aload_0
       1: invokestatic  #62                 // Method io/reactivex/rxjava3/core/Flowable.fromIterable:(Ljava/lang/Iterable;)Lio/reactivex/rxjava3/core/Flowable;
       4: invokestatic  #47                 // Method io/reactivex/rxjava3/internal/operators/single/SingleInternalHelper.toFlowable:()Lio/reactivex/rxjava3/functions/Function;
       7: iconst_0
       8: iload_1
       9: iconst_1
      10: invokevirtual #63                 // Method io/reactivex/rxjava3/core/Flowable.concatMapEagerDelayError:(Lio/reactivex/rxjava3/functions/Function;ZII)Lio/reactivex/rxjava3/core/Flowable;
      13: areturn

  public static <T> io.reactivex.rxjava3.core.Flowable<T> concatEager(org.reactivestreams.Publisher<? extends io.reactivex.rxjava3.core.SingleSource<? extends T>>);
    Code:
       0: aload_0
       1: invokestatic  #64                 // Method io/reactivex/rxjava3/core/Flowable.fromPublisher:(Lorg/reactivestreams/Publisher;)Lio/reactivex/rxjava3/core/Flowable;
       4: invokestatic  #47                 // Method io/reactivex/rxjava3/internal/operators/single/SingleInternalHelper.toFlowable:()Lio/reactivex/rxjava3/functions/Function;
       7: invokevirtual #65                 // Method io/reactivex/rxjava3/core/Flowable.concatMapEager:(Lio/reactivex/rxjava3/functions/Function;)Lio/reactivex/rxjava3/core/Flowable;
      10: areturn

  public static <T> io.reactivex.rxjava3.core.Flowable<T> concatEager(org.reactivestreams.Publisher<? extends io.reactivex.rxjava3.core.SingleSource<? extends T>>, int);
    Code:
       0: aload_0
       1: invokestatic  #66                 // Method io/reactivex/rxjava3/core/Flowable.fromPublisher:(Lorg/reactivestreams/Publisher;)Lio/reactivex/rxjava3/core/Flowable;
       4: invokestatic  #47                 // Method io/reactivex/rxjava3/internal/operators/single/SingleInternalHelper.toFlowable:()Lio/reactivex/rxjava3/functions/Function;
       7: iload_1
       8: iconst_1
       9: invokevirtual #67                 // Method io/reactivex/rxjava3/core/Flowable.concatMapEager:(Lio/reactivex/rxjava3/functions/Function;II)Lio/reactivex/rxjava3/core/Flowable;
      12: areturn

  public static <T> io.reactivex.rxjava3.core.Flowable<T> concatEagerDelayError(java.lang.Iterable<? extends io.reactivex.rxjava3.core.SingleSource<? extends T>>);
    Code:
       0: aload_0
       1: invokestatic  #68                 // Method io/reactivex/rxjava3/core/Flowable.fromIterable:(Ljava/lang/Iterable;)Lio/reactivex/rxjava3/core/Flowable;
       4: invokestatic  #47                 // Method io/reactivex/rxjava3/internal/operators/single/SingleInternalHelper.toFlowable:()Lio/reactivex/rxjava3/functions/Function;
       7: iconst_1
       8: invokevirtual #69                 // Method io/reactivex/rxjava3/core/Flowable.concatMapEagerDelayError:(Lio/reactivex/rxjava3/functions/Function;Z)Lio/reactivex/rxjava3/core/Flowable;
      11: areturn

  public static <T> io.reactivex.rxjava3.core.Flowable<T> concatEagerDelayError(java.lang.Iterable<? extends io.reactivex.rxjava3.core.SingleSource<? extends T>>, int);
    Code:
       0: aload_0
       1: invokestatic  #70                 // Method io/reactivex/rxjava3/core/Flowable.fromIterable:(Ljava/lang/Iterable;)Lio/reactivex/rxjava3/core/Flowable;
       4: invokestatic  #47                 // Method io/reactivex/rxjava3/internal/operators/single/SingleInternalHelper.toFlowable:()Lio/reactivex/rxjava3/functions/Function;
       7: iconst_1
       8: iload_1
       9: iconst_1
      10: invokevirtual #71                 // Method io/reactivex/rxjava3/core/Flowable.concatMapEagerDelayError:(Lio/reactivex/rxjava3/functions/Function;ZII)Lio/reactivex/rxjava3/core/Flowable;
      13: areturn

  public static <T> io.reactivex.rxjava3.core.Flowable<T> concatEagerDelayError(org.reactivestreams.Publisher<? extends io.reactivex.rxjava3.core.SingleSource<? extends T>>);
    Code:
       0: aload_0
       1: invokestatic  #72                 // Method io/reactivex/rxjava3/core/Flowable.fromPublisher:(Lorg/reactivestreams/Publisher;)Lio/reactivex/rxjava3/core/Flowable;
       4: invokestatic  #47                 // Method io/reactivex/rxjava3/internal/operators/single/SingleInternalHelper.toFlowable:()Lio/reactivex/rxjava3/functions/Function;
       7: iconst_1
       8: invokevirtual #73                 // Method io/reactivex/rxjava3/core/Flowable.concatMapEagerDelayError:(Lio/reactivex/rxjava3/functions/Function;Z)Lio/reactivex/rxjava3/core/Flowable;
      11: areturn

  public static <T> io.reactivex.rxjava3.core.Flowable<T> concatEagerDelayError(org.reactivestreams.Publisher<? extends io.reactivex.rxjava3.core.SingleSource<? extends T>>, int);
    Code:
       0: aload_0
       1: invokestatic  #74                 // Method io/reactivex/rxjava3/core/Flowable.fromPublisher:(Lorg/reactivestreams/Publisher;)Lio/reactivex/rxjava3/core/Flowable;
       4: invokestatic  #47                 // Method io/reactivex/rxjava3/internal/operators/single/SingleInternalHelper.toFlowable:()Lio/reactivex/rxjava3/functions/Function;
       7: iconst_1
       8: iload_1
       9: iconst_1
      10: invokevirtual #75                 // Method io/reactivex/rxjava3/core/Flowable.concatMapEagerDelayError:(Lio/reactivex/rxjava3/functions/Function;ZII)Lio/reactivex/rxjava3/core/Flowable;
      13: areturn

  public static <T> io.reactivex.rxjava3.core.Single<T> create(io.reactivex.rxjava3.core.SingleOnSubscribe<T>);
    Code:
       0: aload_0
       1: ldc           #76                 // String source is null
       3: invokestatic  #3                  // Method java/util/Objects.requireNonNull:(Ljava/lang/Object;Ljava/lang/String;)Ljava/lang/Object;
       6: pop
       7: new           #77                 // class io/reactivex/rxjava3/internal/operators/single/SingleCreate
      10: dup
      11: aload_0
      12: invokespecial #78                 // Method io/reactivex/rxjava3/internal/operators/single/SingleCreate."<init>":(Lio/reactivex/rxjava3/core/SingleOnSubscribe;)V
      15: invokestatic  #79                 // Method io/reactivex/rxjava3/plugins/RxJavaPlugins.onAssembly:(Lio/reactivex/rxjava3/core/Single;)Lio/reactivex/rxjava3/core/Single;
      18: areturn

  public static <T> io.reactivex.rxjava3.core.Single<T> defer(io.reactivex.rxjava3.functions.Supplier<? extends io.reactivex.rxjava3.core.SingleSource<? extends T>>);
    Code:
       0: aload_0
       1: ldc           #80                 // String supplier is null
       3: invokestatic  #3                  // Method java/util/Objects.requireNonNull:(Ljava/lang/Object;Ljava/lang/String;)Ljava/lang/Object;
       6: pop
       7: new           #81                 // class io/reactivex/rxjava3/internal/operators/single/SingleDefer
      10: dup
      11: aload_0
      12: invokespecial #82                 // Method io/reactivex/rxjava3/internal/operators/single/SingleDefer."<init>":(Lio/reactivex/rxjava3/functions/Supplier;)V
      15: invokestatic  #83                 // Method io/reactivex/rxjava3/plugins/RxJavaPlugins.onAssembly:(Lio/reactivex/rxjava3/core/Single;)Lio/reactivex/rxjava3/core/Single;
      18: areturn

  public static <T> io.reactivex.rxjava3.core.Single<T> error(io.reactivex.rxjava3.functions.Supplier<? extends java.lang.Throwable>);
    Code:
       0: aload_0
       1: ldc           #80                 // String supplier is null
       3: invokestatic  #3                  // Method java/util/Objects.requireNonNull:(Ljava/lang/Object;Ljava/lang/String;)Ljava/lang/Object;
       6: pop
       7: new           #84                 // class io/reactivex/rxjava3/internal/operators/single/SingleError
      10: dup
      11: aload_0
      12: invokespecial #85                 // Method io/reactivex/rxjava3/internal/operators/single/SingleError."<init>":(Lio/reactivex/rxjava3/functions/Supplier;)V
      15: invokestatic  #86                 // Method io/reactivex/rxjava3/plugins/RxJavaPlugins.onAssembly:(Lio/reactivex/rxjava3/core/Single;)Lio/reactivex/rxjava3/core/Single;
      18: areturn

  public static <T> io.reactivex.rxjava3.core.Single<T> error(java.lang.Throwable);
    Code:
       0: aload_0
       1: ldc           #87                 // String throwable is null
       3: invokestatic  #3                  // Method java/util/Objects.requireNonNull:(Ljava/lang/Object;Ljava/lang/String;)Ljava/lang/Object;
       6: pop
       7: aload_0
       8: invokestatic  #88                 // Method io/reactivex/rxjava3/internal/functions/Functions.justSupplier:(Ljava/lang/Object;)Lio/reactivex/rxjava3/functions/Supplier;
      11: invokestatic  #89                 // Method error:(Lio/reactivex/rxjava3/functions/Supplier;)Lio/reactivex/rxjava3/core/Single;
      14: areturn

  public static <T> io.reactivex.rxjava3.core.Single<T> fromCallable(java.util.concurrent.Callable<? extends T>);
    Code:
       0: aload_0
       1: ldc           #90                 // String callable is null
       3: invokestatic  #3                  // Method java/util/Objects.requireNonNull:(Ljava/lang/Object;Ljava/lang/String;)Ljava/lang/Object;
       6: pop
       7: new           #91                 // class io/reactivex/rxjava3/internal/operators/single/SingleFromCallable
      10: dup
      11: aload_0
      12: invokespecial #92                 // Method io/reactivex/rxjava3/internal/operators/single/SingleFromCallable."<init>":(Ljava/util/concurrent/Callable;)V
      15: invokestatic  #93                 // Method io/reactivex/rxjava3/plugins/RxJavaPlugins.onAssembly:(Lio/reactivex/rxjava3/core/Single;)Lio/reactivex/rxjava3/core/Single;
      18: areturn

  public static <T> io.reactivex.rxjava3.core.Single<T> fromFuture(java.util.concurrent.Future<? extends T>);
    Code:
       0: aload_0
       1: invokestatic  #94                 // Method io/reactivex/rxjava3/core/Flowable.fromFuture:(Ljava/util/concurrent/Future;)Lio/reactivex/rxjava3/core/Flowable;
       4: invokestatic  #95                 // Method toSingle:(Lio/reactivex/rxjava3/core/Flowable;)Lio/reactivex/rxjava3/core/Single;
       7: areturn

  public static <T> io.reactivex.rxjava3.core.Single<T> fromFuture(java.util.concurrent.Future<? extends T>, long, java.util.concurrent.TimeUnit);
    Code:
       0: aload_0
       1: lload_1
       2: aload_3
       3: invokestatic  #96                 // Method io/reactivex/rxjava3/core/Flowable.fromFuture:(Ljava/util/concurrent/Future;JLjava/util/concurrent/TimeUnit;)Lio/reactivex/rxjava3/core/Flowable;
       6: invokestatic  #97                 // Method toSingle:(Lio/reactivex/rxjava3/core/Flowable;)Lio/reactivex/rxjava3/core/Single;
       9: areturn

  public static <T> io.reactivex.rxjava3.core.Single<T> fromMaybe(io.reactivex.rxjava3.core.MaybeSource<T>);
    Code:
       0: aload_0
       1: ldc           #98                 // String maybe is null
       3: invokestatic  #3                  // Method java/util/Objects.requireNonNull:(Ljava/lang/Object;Ljava/lang/String;)Ljava/lang/Object;
       6: pop
       7: new           #99                 // class io/reactivex/rxjava3/internal/operators/maybe/MaybeToSingle
      10: dup
      11: aload_0
      12: aconst_null
      13: invokespecial #100                // Method io/reactivex/rxjava3/internal/operators/maybe/MaybeToSingle."<init>":(Lio/reactivex/rxjava3/core/MaybeSource;Ljava/lang/Object;)V
      16: invokestatic  #101                // Method io/reactivex/rxjava3/plugins/RxJavaPlugins.onAssembly:(Lio/reactivex/rxjava3/core/Single;)Lio/reactivex/rxjava3/core/Single;
      19: areturn

  public static <T> io.reactivex.rxjava3.core.Single<T> fromMaybe(io.reactivex.rxjava3.core.MaybeSource<T>, T);
    Code:
       0: aload_0
       1: ldc           #98                 // String maybe is null
       3: invokestatic  #3                  // Method java/util/Objects.requireNonNull:(Ljava/lang/Object;Ljava/lang/String;)Ljava/lang/Object;
       6: pop
       7: aload_1
       8: ldc           #102                // String defaultItem is null
      10: invokestatic  #3                  // Method java/util/Objects.requireNonNull:(Ljava/lang/Object;Ljava/lang/String;)Ljava/lang/Object;
      13: pop
      14: new           #99                 // class io/reactivex/rxjava3/internal/operators/maybe/MaybeToSingle
      17: dup
      18: aload_0
      19: aload_1
      20: invokespecial #100                // Method io/reactivex/rxjava3/internal/operators/maybe/MaybeToSingle."<init>":(Lio/reactivex/rxjava3/core/MaybeSource;Ljava/lang/Object;)V
      23: invokestatic  #103                // Method io/reactivex/rxjava3/plugins/RxJavaPlugins.onAssembly:(Lio/reactivex/rxjava3/core/Single;)Lio/reactivex/rxjava3/core/Single;
      26: areturn

  public static <T> io.reactivex.rxjava3.core.Single<T> fromPublisher(org.reactivestreams.Publisher<? extends T>);
    Code:
       0: aload_0
       1: ldc           #104                // String publisher is null
       3: invokestatic  #3                  // Method java/util/Objects.requireNonNull:(Ljava/lang/Object;Ljava/lang/String;)Ljava/lang/Object;
       6: pop
       7: new           #105                // class io/reactivex/rxjava3/internal/operators/single/SingleFromPublisher
      10: dup
      11: aload_0
      12: invokespecial #106                // Method io/reactivex/rxjava3/internal/operators/single/SingleFromPublisher."<init>":(Lorg/reactivestreams/Publisher;)V
      15: invokestatic  #107                // Method io/reactivex/rxjava3/plugins/RxJavaPlugins.onAssembly:(Lio/reactivex/rxjava3/core/Single;)Lio/reactivex/rxjava3/core/Single;
      18: areturn

  public static <T> io.reactivex.rxjava3.core.Single<T> fromObservable(io.reactivex.rxjava3.core.ObservableSource<? extends T>);
    Code:
       0: aload_0
       1: ldc           #108                // String observable is null
       3: invokestatic  #3                  // Method java/util/Objects.requireNonNull:(Ljava/lang/Object;Ljava/lang/String;)Ljava/lang/Object;
       6: pop
       7: new           #109                // class io/reactivex/rxjava3/internal/operators/observable/ObservableSingleSingle
      10: dup
      11: aload_0
      12: aconst_null
      13: invokespecial #110                // Method io/reactivex/rxjava3/internal/operators/observable/ObservableSingleSingle."<init>":(Lio/reactivex/rxjava3/core/ObservableSource;Ljava/lang/Object;)V
      16: invokestatic  #111                // Method io/reactivex/rxjava3/plugins/RxJavaPlugins.onAssembly:(Lio/reactivex/rxjava3/core/Single;)Lio/reactivex/rxjava3/core/Single;
      19: areturn

  public static <T> io.reactivex.rxjava3.core.Single<T> fromSupplier(io.reactivex.rxjava3.functions.Supplier<? extends T>);
    Code:
       0: aload_0
       1: ldc           #80                 // String supplier is null
       3: invokestatic  #3                  // Method java/util/Objects.requireNonNull:(Ljava/lang/Object;Ljava/lang/String;)Ljava/lang/Object;
       6: pop
       7: new           #112                // class io/reactivex/rxjava3/internal/operators/single/SingleFromSupplier
      10: dup
      11: aload_0
      12: invokespecial #113                // Method io/reactivex/rxjava3/internal/operators/single/SingleFromSupplier."<init>":(Lio/reactivex/rxjava3/functions/Supplier;)V
      15: invokestatic  #114                // Method io/reactivex/rxjava3/plugins/RxJavaPlugins.onAssembly:(Lio/reactivex/rxjava3/core/Single;)Lio/reactivex/rxjava3/core/Single;
      18: areturn

  public static <T> io.reactivex.rxjava3.core.Single<T> just(T);
    Code:
       0: aload_0
       1: ldc           #115                // String item is null
       3: invokestatic  #3                  // Method java/util/Objects.requireNonNull:(Ljava/lang/Object;Ljava/lang/String;)Ljava/lang/Object;
       6: pop
       7: new           #116                // class io/reactivex/rxjava3/internal/operators/single/SingleJust
      10: dup
      11: aload_0
      12: invokespecial #117                // Method io/reactivex/rxjava3/internal/operators/single/SingleJust."<init>":(Ljava/lang/Object;)V
      15: invokestatic  #118                // Method io/reactivex/rxjava3/plugins/RxJavaPlugins.onAssembly:(Lio/reactivex/rxjava3/core/Single;)Lio/reactivex/rxjava3/core/Single;
      18: areturn

  public static <T> io.reactivex.rxjava3.core.Flowable<T> merge(java.lang.Iterable<? extends io.reactivex.rxjava3.core.SingleSource<? extends T>>);
    Code:
       0: aload_0
       1: invokestatic  #119                // Method io/reactivex/rxjava3/core/Flowable.fromIterable:(Ljava/lang/Iterable;)Lio/reactivex/rxjava3/core/Flowable;
       4: invokestatic  #120                // Method io/reactivex/rxjava3/internal/functions/Functions.identity:()Lio/reactivex/rxjava3/functions/Function;
       7: invokevirtual #121                // Method io/reactivex/rxjava3/core/Flowable.flatMapSingle:(Lio/reactivex/rxjava3/functions/Function;)Lio/reactivex/rxjava3/core/Flowable;
      10: areturn

  public static <T> io.reactivex.rxjava3.core.Flowable<T> merge(org.reactivestreams.Publisher<? extends io.reactivex.rxjava3.core.SingleSource<? extends T>>);
    Code:
       0: aload_0
       1: ldc           #2                  // String sources is null
       3: invokestatic  #3                  // Method java/util/Objects.requireNonNull:(Ljava/lang/Object;Ljava/lang/String;)Ljava/lang/Object;
       6: pop
       7: new           #122                // class io/reactivex/rxjava3/internal/operators/flowable/FlowableFlatMapSinglePublisher
      10: dup
      11: aload_0
      12: invokestatic  #123                // Method io/reactivex/rxjava3/internal/functions/Functions.identity:()Lio/reactivex/rxjava3/functions/Function;
      15: iconst_0
      16: ldc           #125                // int 2147483647
      18: invokespecial #126                // Method io/reactivex/rxjava3/internal/operators/flowable/FlowableFlatMapSinglePublisher."<init>":(Lorg/reactivestreams/Publisher;Lio/reactivex/rxjava3/functions/Function;ZI)V
      21: invokestatic  #127                // Method io/reactivex/rxjava3/plugins/RxJavaPlugins.onAssembly:(Lio/reactivex/rxjava3/core/Flowable;)Lio/reactivex/rxjava3/core/Flowable;
      24: areturn

  public static <T> io.reactivex.rxjava3.core.Single<T> merge(io.reactivex.rxjava3.core.SingleSource<? extends io.reactivex.rxjava3.core.SingleSource<? extends T>>);
    Code:
       0: aload_0
       1: ldc           #76                 // String source is null
       3: invokestatic  #3                  // Method java/util/Objects.requireNonNull:(Ljava/lang/Object;Ljava/lang/String;)Ljava/lang/Object;
       6: pop
       7: new           #128                // class io/reactivex/rxjava3/internal/operators/single/SingleFlatMap
      10: dup
      11: aload_0
      12: invokestatic  #129                // Method io/reactivex/rxjava3/internal/functions/Functions.identity:()Lio/reactivex/rxjava3/functions/Function;
      15: invokespecial #130                // Method io/reactivex/rxjava3/internal/operators/single/SingleFlatMap."<init>":(Lio/reactivex/rxjava3/core/SingleSource;Lio/reactivex/rxjava3/functions/Function;)V
      18: invokestatic  #131                // Method io/reactivex/rxjava3/plugins/RxJavaPlugins.onAssembly:(Lio/reactivex/rxjava3/core/Single;)Lio/reactivex/rxjava3/core/Single;
      21: areturn

  public static <T> io.reactivex.rxjava3.core.Flowable<T> merge(io.reactivex.rxjava3.core.SingleSource<? extends T>, io.reactivex.rxjava3.core.SingleSource<? extends T>);
    Code:
       0: aload_0
       1: ldc           #26                 // String source1 is null
       3: invokestatic  #3                  // Method java/util/Objects.requireNonNull:(Ljava/lang/Object;Ljava/lang/String;)Ljava/lang/Object;
       6: pop
       7: aload_1
       8: ldc           #27                 // String source2 is null
      10: invokestatic  #3                  // Method java/util/Objects.requireNonNull:(Ljava/lang/Object;Ljava/lang/String;)Ljava/lang/Object;
      13: pop
      14: iconst_2
      15: anewarray     #28                 // class io/reactivex/rxjava3/core/SingleSource
      18: dup
      19: iconst_0
      20: aload_0
      21: aastore
      22: dup
      23: iconst_1
      24: aload_1
      25: aastore
      26: invokestatic  #132                // Method io/reactivex/rxjava3/core/Flowable.fromArray:([Ljava/lang/Object;)Lio/reactivex/rxjava3/core/Flowable;
      29: invokestatic  #133                // Method io/reactivex/rxjava3/internal/functions/Functions.identity:()Lio/reactivex/rxjava3/functions/Function;
      32: iconst_0
      33: ldc           #125                // int 2147483647
      35: invokevirtual #134                // Method io/reactivex/rxjava3/core/Flowable.flatMapSingle:(Lio/reactivex/rxjava3/functions/Function;ZI)Lio/reactivex/rxjava3/core/Flowable;
      38: areturn

  public static <T> io.reactivex.rxjava3.core.Flowable<T> merge(io.reactivex.rxjava3.core.SingleSource<? extends T>, io.reactivex.rxjava3.core.SingleSource<? extends T>, io.reactivex.rxjava3.core.SingleSource<? extends T>);
    Code:
       0: aload_0
       1: ldc           #26                 // String source1 is null
       3: invokestatic  #3                  // Method java/util/Objects.requireNonNull:(Ljava/lang/Object;Ljava/lang/String;)Ljava/lang/Object;
       6: pop
       7: aload_1
       8: ldc           #27                 // String source2 is null
      10: invokestatic  #3                  // Method java/util/Objects.requireNonNull:(Ljava/lang/Object;Ljava/lang/String;)Ljava/lang/Object;
      13: pop
      14: aload_2
      15: ldc           #32                 // String source3 is null
      17: invokestatic  #3                  // Method java/util/Objects.requireNonNull:(Ljava/lang/Object;Ljava/lang/String;)Ljava/lang/Object;
      20: pop
      21: iconst_3
      22: anewarray     #28                 // class io/reactivex/rxjava3/core/SingleSource
      25: dup
      26: iconst_0
      27: aload_0
      28: aastore
      29: dup
      30: iconst_1
      31: aload_1
      32: aastore
      33: dup
      34: iconst_2
      35: aload_2
      36: aastore
      37: invokestatic  #135                // Method io/reactivex/rxjava3/core/Flowable.fromArray:([Ljava/lang/Object;)Lio/reactivex/rxjava3/core/Flowable;
      40: invokestatic  #136                // Method io/reactivex/rxjava3/internal/functions/Functions.identity:()Lio/reactivex/rxjava3/functions/Function;
      43: iconst_0
      44: ldc           #125                // int 2147483647
      46: invokevirtual #137                // Method io/reactivex/rxjava3/core/Flowable.flatMapSingle:(Lio/reactivex/rxjava3/functions/Function;ZI)Lio/reactivex/rxjava3/core/Flowable;
      49: areturn

  public static <T> io.reactivex.rxjava3.core.Flowable<T> merge(io.reactivex.rxjava3.core.SingleSource<? extends T>, io.reactivex.rxjava3.core.SingleSource<? extends T>, io.reactivex.rxjava3.core.SingleSource<? extends T>, io.reactivex.rxjava3.core.SingleSource<? extends T>);
    Code:
       0: aload_0
       1: ldc           #26                 // String source1 is null
       3: invokestatic  #3                  // Method java/util/Objects.requireNonNull:(Ljava/lang/Object;Ljava/lang/String;)Ljava/lang/Object;
       6: pop
       7: aload_1
       8: ldc           #27                 // String source2 is null
      10: invokestatic  #3                  // Method java/util/Objects.requireNonNull:(Ljava/lang/Object;Ljava/lang/String;)Ljava/lang/Object;
      13: pop
      14: aload_2
      15: ldc           #32                 // String source3 is null
      17: invokestatic  #3                  // Method java/util/Objects.requireNonNull:(Ljava/lang/Object;Ljava/lang/String;)Ljava/lang/Object;
      20: pop
      21: aload_3
      22: ldc           #36                 // String source4 is null
      24: invokestatic  #3                  // Method java/util/Objects.requireNonNull:(Ljava/lang/Object;Ljava/lang/String;)Ljava/lang/Object;
      27: pop
      28: iconst_4
      29: anewarray     #28                 // class io/reactivex/rxjava3/core/SingleSource
      32: dup
      33: iconst_0
      34: aload_0
      35: aastore
      36: dup
      37: iconst_1
      38: aload_1
      39: aastore
      40: dup
      41: iconst_2
      42: aload_2
      43: aastore
      44: dup
      45: iconst_3
      46: aload_3
      47: aastore
      48: invokestatic  #138                // Method io/reactivex/rxjava3/core/Flowable.fromArray:([Ljava/lang/Object;)Lio/reactivex/rxjava3/core/Flowable;
      51: invokestatic  #139                // Method io/reactivex/rxjava3/internal/functions/Functions.identity:()Lio/reactivex/rxjava3/functions/Function;
      54: iconst_0
      55: ldc           #125                // int 2147483647
      57: invokevirtual #140                // Method io/reactivex/rxjava3/core/Flowable.flatMapSingle:(Lio/reactivex/rxjava3/functions/Function;ZI)Lio/reactivex/rxjava3/core/Flowable;
      60: areturn

  public static <T> io.reactivex.rxjava3.core.Flowable<T> mergeArray(io.reactivex.rxjava3.core.SingleSource<? extends T>...);
    Code:
       0: aload_0
       1: invokestatic  #141                // Method io/reactivex/rxjava3/core/Flowable.fromArray:([Ljava/lang/Object;)Lio/reactivex/rxjava3/core/Flowable;
       4: invokestatic  #142                // Method io/reactivex/rxjava3/internal/functions/Functions.identity:()Lio/reactivex/rxjava3/functions/Function;
       7: iconst_0
       8: iconst_1
       9: aload_0
      10: arraylength
      11: invokestatic  #143                // Method java/lang/Math.max:(II)I
      14: invokevirtual #144                // Method io/reactivex/rxjava3/core/Flowable.flatMapSingle:(Lio/reactivex/rxjava3/functions/Function;ZI)Lio/reactivex/rxjava3/core/Flowable;
      17: areturn

  public static <T> io.reactivex.rxjava3.core.Flowable<T> mergeArrayDelayError(io.reactivex.rxjava3.core.SingleSource<? extends T>...);
    Code:
       0: aload_0
       1: invokestatic  #145                // Method io/reactivex/rxjava3/core/Flowable.fromArray:([Ljava/lang/Object;)Lio/reactivex/rxjava3/core/Flowable;
       4: invokestatic  #146                // Method io/reactivex/rxjava3/internal/functions/Functions.identity:()Lio/reactivex/rxjava3/functions/Function;
       7: iconst_1
       8: iconst_1
       9: aload_0
      10: arraylength
      11: invokestatic  #143                // Method java/lang/Math.max:(II)I
      14: invokevirtual #147                // Method io/reactivex/rxjava3/core/Flowable.flatMapSingle:(Lio/reactivex/rxjava3/functions/Function;ZI)Lio/reactivex/rxjava3/core/Flowable;
      17: areturn

  public static <T> io.reactivex.rxjava3.core.Flowable<T> mergeDelayError(java.lang.Iterable<? extends io.reactivex.rxjava3.core.SingleSource<? extends T>>);
    Code:
       0: aload_0
       1: invokestatic  #148                // Method io/reactivex/rxjava3/core/Flowable.fromIterable:(Ljava/lang/Iterable;)Lio/reactivex/rxjava3/core/Flowable;
       4: invokestatic  #149                // Method io/reactivex/rxjava3/internal/functions/Functions.identity:()Lio/reactivex/rxjava3/functions/Function;
       7: iconst_1
       8: ldc           #125                // int 2147483647
      10: invokevirtual #150                // Method io/reactivex/rxjava3/core/Flowable.flatMapSingle:(Lio/reactivex/rxjava3/functions/Function;ZI)Lio/reactivex/rxjava3/core/Flowable;
      13: areturn

  public static <T> io.reactivex.rxjava3.core.Flowable<T> mergeDelayError(org.reactivestreams.Publisher<? extends io.reactivex.rxjava3.core.SingleSource<? extends T>>);
    Code:
       0: aload_0
       1: ldc           #2                  // String sources is null
       3: invokestatic  #3                  // Method java/util/Objects.requireNonNull:(Ljava/lang/Object;Ljava/lang/String;)Ljava/lang/Object;
       6: pop
       7: new           #122                // class io/reactivex/rxjava3/internal/operators/flowable/FlowableFlatMapSinglePublisher
      10: dup
      11: aload_0
      12: invokestatic  #151                // Method io/reactivex/rxjava3/internal/functions/Functions.identity:()Lio/reactivex/rxjava3/functions/Function;
      15: iconst_1
      16: ldc           #125                // int 2147483647
      18: invokespecial #126                // Method io/reactivex/rxjava3/internal/operators/flowable/FlowableFlatMapSinglePublisher."<init>":(Lorg/reactivestreams/Publisher;Lio/reactivex/rxjava3/functions/Function;ZI)V
      21: invokestatic  #152                // Method io/reactivex/rxjava3/plugins/RxJavaPlugins.onAssembly:(Lio/reactivex/rxjava3/core/Flowable;)Lio/reactivex/rxjava3/core/Flowable;
      24: areturn

  public static <T> io.reactivex.rxjava3.core.Flowable<T> mergeDelayError(io.reactivex.rxjava3.core.SingleSource<? extends T>, io.reactivex.rxjava3.core.SingleSource<? extends T>);
    Code:
       0: aload_0
       1: ldc           #26                 // String source1 is null
       3: invokestatic  #3                  // Method java/util/Objects.requireNonNull:(Ljava/lang/Object;Ljava/lang/String;)Ljava/lang/Object;
       6: pop
       7: aload_1
       8: ldc           #27                 // String source2 is null
      10: invokestatic  #3                  // Method java/util/Objects.requireNonNull:(Ljava/lang/Object;Ljava/lang/String;)Ljava/lang/Object;
      13: pop
      14: iconst_2
      15: anewarray     #28                 // class io/reactivex/rxjava3/core/SingleSource
      18: dup
      19: iconst_0
      20: aload_0
      21: aastore
      22: dup
      23: iconst_1
      24: aload_1
      25: aastore
      26: invokestatic  #153                // Method io/reactivex/rxjava3/core/Flowable.fromArray:([Ljava/lang/Object;)Lio/reactivex/rxjava3/core/Flowable;
      29: invokestatic  #154                // Method io/reactivex/rxjava3/internal/functions/Functions.identity:()Lio/reactivex/rxjava3/functions/Function;
      32: iconst_1
      33: ldc           #125                // int 2147483647
      35: invokevirtual #155                // Method io/reactivex/rxjava3/core/Flowable.flatMapSingle:(Lio/reactivex/rxjava3/functions/Function;ZI)Lio/reactivex/rxjava3/core/Flowable;
      38: areturn

  public static <T> io.reactivex.rxjava3.core.Flowable<T> mergeDelayError(io.reactivex.rxjava3.core.SingleSource<? extends T>, io.reactivex.rxjava3.core.SingleSource<? extends T>, io.reactivex.rxjava3.core.SingleSource<? extends T>);
    Code:
       0: aload_0
       1: ldc           #26                 // String source1 is null
       3: invokestatic  #3                  // Method java/util/Objects.requireNonNull:(Ljava/lang/Object;Ljava/lang/String;)Ljava/lang/Object;
       6: pop
       7: aload_1
       8: ldc           #27                 // String source2 is null
      10: invokestatic  #3                  // Method java/util/Objects.requireNonNull:(Ljava/lang/Object;Ljava/lang/String;)Ljava/lang/Object;
      13: pop
      14: aload_2
      15: ldc           #32                 // String source3 is null
      17: invokestatic  #3                  // Method java/util/Objects.requireNonNull:(Ljava/lang/Object;Ljava/lang/String;)Ljava/lang/Object;
      20: pop
      21: iconst_3
      22: anewarray     #28                 // class io/reactivex/rxjava3/core/SingleSource
      25: dup
      26: iconst_0
      27: aload_0
      28: aastore
      29: dup
      30: iconst_1
      31: aload_1
      32: aastore
      33: dup
      34: iconst_2
      35: aload_2
      36: aastore
      37: invokestatic  #156                // Method io/reactivex/rxjava3/core/Flowable.fromArray:([Ljava/lang/Object;)Lio/reactivex/rxjava3/core/Flowable;
      40: invokestatic  #157                // Method io/reactivex/rxjava3/internal/functions/Functions.identity:()Lio/reactivex/rxjava3/functions/Function;
      43: iconst_1
      44: ldc           #125                // int 2147483647
      46: invokevirtual #158                // Method io/reactivex/rxjava3/core/Flowable.flatMapSingle:(Lio/reactivex/rxjava3/functions/Function;ZI)Lio/reactivex/rxjava3/core/Flowable;
      49: areturn

  public static <T> io.reactivex.rxjava3.core.Flowable<T> mergeDelayError(io.reactivex.rxjava3.core.SingleSource<? extends T>, io.reactivex.rxjava3.core.SingleSource<? extends T>, io.reactivex.rxjava3.core.SingleSource<? extends T>, io.reactivex.rxjava3.core.SingleSource<? extends T>);
    Code:
       0: aload_0
       1: ldc           #26                 // String source1 is null
       3: invokestatic  #3                  // Method java/util/Objects.requireNonNull:(Ljava/lang/Object;Ljava/lang/String;)Ljava/lang/Object;
       6: pop
       7: aload_1
       8: ldc           #27                 // String source2 is null
      10: invokestatic  #3                  // Method java/util/Objects.requireNonNull:(Ljava/lang/Object;Ljava/lang/String;)Ljava/lang/Object;
      13: pop
      14: aload_2
      15: ldc           #32                 // String source3 is null
      17: invokestatic  #3                  // Method java/util/Objects.requireNonNull:(Ljava/lang/Object;Ljava/lang/String;)Ljava/lang/Object;
      20: pop
      21: aload_3
      22: ldc           #36                 // String source4 is null
      24: invokestatic  #3                  // Method java/util/Objects.requireNonNull:(Ljava/lang/Object;Ljava/lang/String;)Ljava/lang/Object;
      27: pop
      28: iconst_4
      29: anewarray     #28                 // class io/reactivex/rxjava3/core/SingleSource
      32: dup
      33: iconst_0
      34: aload_0
      35: aastore
      36: dup
      37: iconst_1
      38: aload_1
      39: aastore
      40: dup
      41: iconst_2
      42: aload_2
      43: aastore
      44: dup
      45: iconst_3
      46: aload_3
      47: aastore
      48: invokestatic  #159                // Method io/reactivex/rxjava3/core/Flowable.fromArray:([Ljava/lang/Object;)Lio/reactivex/rxjava3/core/Flowable;
      51: invokestatic  #160                // Method io/reactivex/rxjava3/internal/functions/Functions.identity:()Lio/reactivex/rxjava3/functions/Function;
      54: iconst_1
      55: ldc           #125                // int 2147483647
      57: invokevirtual #161                // Method io/reactivex/rxjava3/core/Flowable.flatMapSingle:(Lio/reactivex/rxjava3/functions/Function;ZI)Lio/reactivex/rxjava3/core/Flowable;
      60: areturn

  public static <T> io.reactivex.rxjava3.core.Single<T> never();
    Code:
       0: getstatic     #162                // Field io/reactivex/rxjava3/internal/operators/single/SingleNever.INSTANCE:Lio/reactivex/rxjava3/core/Single;
       3: invokestatic  #163                // Method io/reactivex/rxjava3/plugins/RxJavaPlugins.onAssembly:(Lio/reactivex/rxjava3/core/Single;)Lio/reactivex/rxjava3/core/Single;
       6: areturn

  public static io.reactivex.rxjava3.core.Single<java.lang.Long> timer(long, java.util.concurrent.TimeUnit);
    Code:
       0: lload_0
       1: aload_2
       2: invokestatic  #164                // Method io/reactivex/rxjava3/schedulers/Schedulers.computation:()Lio/reactivex/rxjava3/core/Scheduler;
       5: invokestatic  #165                // Method timer:(JLjava/util/concurrent/TimeUnit;Lio/reactivex/rxjava3/core/Scheduler;)Lio/reactivex/rxjava3/core/Single;
       8: areturn

  public static io.reactivex.rxjava3.core.Single<java.lang.Long> timer(long, java.util.concurrent.TimeUnit, io.reactivex.rxjava3.core.Scheduler);
    Code:
       0: aload_2
       1: ldc           #166                // String unit is null
       3: invokestatic  #3                  // Method java/util/Objects.requireNonNull:(Ljava/lang/Object;Ljava/lang/String;)Ljava/lang/Object;
       6: pop
       7: aload_3
       8: ldc           #167                // String scheduler is null
      10: invokestatic  #3                  // Method java/util/Objects.requireNonNull:(Ljava/lang/Object;Ljava/lang/String;)Ljava/lang/Object;
      13: pop
      14: new           #168                // class io/reactivex/rxjava3/internal/operators/single/SingleTimer
      17: dup
      18: lload_0
      19: aload_2
      20: aload_3
      21: invokespecial #169                // Method io/reactivex/rxjava3/internal/operators/single/SingleTimer."<init>":(JLjava/util/concurrent/TimeUnit;Lio/reactivex/rxjava3/core/Scheduler;)V
      24: invokestatic  #170                // Method io/reactivex/rxjava3/plugins/RxJavaPlugins.onAssembly:(Lio/reactivex/rxjava3/core/Single;)Lio/reactivex/rxjava3/core/Single;
      27: areturn

  public static <T> io.reactivex.rxjava3.core.Single<java.lang.Boolean> sequenceEqual(io.reactivex.rxjava3.core.SingleSource<? extends T>, io.reactivex.rxjava3.core.SingleSource<? extends T>);
    Code:
       0: aload_0
       1: ldc           #26                 // String source1 is null
       3: invokestatic  #3                  // Method java/util/Objects.requireNonNull:(Ljava/lang/Object;Ljava/lang/String;)Ljava/lang/Object;
       6: pop
       7: aload_1
       8: ldc           #27                 // String source2 is null
      10: invokestatic  #3                  // Method java/util/Objects.requireNonNull:(Ljava/lang/Object;Ljava/lang/String;)Ljava/lang/Object;
      13: pop
      14: new           #171                // class io/reactivex/rxjava3/internal/operators/single/SingleEquals
      17: dup
      18: aload_0
      19: aload_1
      20: invokespecial #172                // Method io/reactivex/rxjava3/internal/operators/single/SingleEquals."<init>":(Lio/reactivex/rxjava3/core/SingleSource;Lio/reactivex/rxjava3/core/SingleSource;)V
      23: invokestatic  #173                // Method io/reactivex/rxjava3/plugins/RxJavaPlugins.onAssembly:(Lio/reactivex/rxjava3/core/Single;)Lio/reactivex/rxjava3/core/Single;
      26: areturn

  public static <T> io.reactivex.rxjava3.core.Flowable<T> switchOnNext(org.reactivestreams.Publisher<? extends io.reactivex.rxjava3.core.SingleSource<? extends T>>);
    Code:
       0: aload_0
       1: ldc           #2                  // String sources is null
       3: invokestatic  #3                  // Method java/util/Objects.requireNonNull:(Ljava/lang/Object;Ljava/lang/String;)Ljava/lang/Object;
       6: pop
       7: new           #174                // class io/reactivex/rxjava3/internal/operators/mixed/FlowableSwitchMapSinglePublisher
      10: dup
      11: aload_0
      12: invokestatic  #175                // Method io/reactivex/rxjava3/internal/functions/Functions.identity:()Lio/reactivex/rxjava3/functions/Function;
      15: iconst_0
      16: invokespecial #176                // Method io/reactivex/rxjava3/internal/operators/mixed/FlowableSwitchMapSinglePublisher."<init>":(Lorg/reactivestreams/Publisher;Lio/reactivex/rxjava3/functions/Function;Z)V
      19: invokestatic  #177                // Method io/reactivex/rxjava3/plugins/RxJavaPlugins.onAssembly:(Lio/reactivex/rxjava3/core/Flowable;)Lio/reactivex/rxjava3/core/Flowable;
      22: areturn

  public static <T> io.reactivex.rxjava3.core.Flowable<T> switchOnNextDelayError(org.reactivestreams.Publisher<? extends io.reactivex.rxjava3.core.SingleSource<? extends T>>);
    Code:
       0: aload_0
       1: ldc           #2                  // String sources is null
       3: invokestatic  #3                  // Method java/util/Objects.requireNonNull:(Ljava/lang/Object;Ljava/lang/String;)Ljava/lang/Object;
       6: pop
       7: new           #174                // class io/reactivex/rxjava3/internal/operators/mixed/FlowableSwitchMapSinglePublisher
      10: dup
      11: aload_0
      12: invokestatic  #178                // Method io/reactivex/rxjava3/internal/functions/Functions.identity:()Lio/reactivex/rxjava3/functions/Function;
      15: iconst_1
      16: invokespecial #176                // Method io/reactivex/rxjava3/internal/operators/mixed/FlowableSwitchMapSinglePublisher."<init>":(Lorg/reactivestreams/Publisher;Lio/reactivex/rxjava3/functions/Function;Z)V
      19: invokestatic  #179                // Method io/reactivex/rxjava3/plugins/RxJavaPlugins.onAssembly:(Lio/reactivex/rxjava3/core/Flowable;)Lio/reactivex/rxjava3/core/Flowable;
      22: areturn

  public static <T> io.reactivex.rxjava3.core.Single<T> unsafeCreate(io.reactivex.rxjava3.core.SingleSource<T>);
    Code:
       0: aload_0
       1: ldc           #180                // String onSubscribe is null
       3: invokestatic  #3                  // Method java/util/Objects.requireNonNull:(Ljava/lang/Object;Ljava/lang/String;)Ljava/lang/Object;
       6: pop
       7: aload_0
       8: instanceof    #181                // class io/reactivex/rxjava3/core/Single
      11: ifeq          24
      14: new           #182                // class java/lang/IllegalArgumentException
      17: dup
      18: ldc           #183                // String unsafeCreate(Single) should be upgraded
      20: invokespecial #184                // Method java/lang/IllegalArgumentException."<init>":(Ljava/lang/String;)V
      23: athrow
      24: new           #185                // class io/reactivex/rxjava3/internal/operators/single/SingleFromUnsafeSource
      27: dup
      28: aload_0
      29: invokespecial #186                // Method io/reactivex/rxjava3/internal/operators/single/SingleFromUnsafeSource."<init>":(Lio/reactivex/rxjava3/core/SingleSource;)V
      32: invokestatic  #187                // Method io/reactivex/rxjava3/plugins/RxJavaPlugins.onAssembly:(Lio/reactivex/rxjava3/core/Single;)Lio/reactivex/rxjava3/core/Single;
      35: areturn

  public static <T, U> io.reactivex.rxjava3.core.Single<T> using(io.reactivex.rxjava3.functions.Supplier<U>, io.reactivex.rxjava3.functions.Function<? super U, ? extends io.reactivex.rxjava3.core.SingleSource<? extends T>>, io.reactivex.rxjava3.functions.Consumer<? super U>);
    Code:
       0: aload_0
       1: aload_1
       2: aload_2
       3: iconst_1
       4: invokestatic  #188                // Method using:(Lio/reactivex/rxjava3/functions/Supplier;Lio/reactivex/rxjava3/functions/Function;Lio/reactivex/rxjava3/functions/Consumer;Z)Lio/reactivex/rxjava3/core/Single;
       7: areturn

  public static <T, U> io.reactivex.rxjava3.core.Single<T> using(io.reactivex.rxjava3.functions.Supplier<U>, io.reactivex.rxjava3.functions.Function<? super U, ? extends io.reactivex.rxjava3.core.SingleSource<? extends T>>, io.reactivex.rxjava3.functions.Consumer<? super U>, boolean);
    Code:
       0: aload_0
       1: ldc           #189                // String resourceSupplier is null
       3: invokestatic  #3                  // Method java/util/Objects.requireNonNull:(Ljava/lang/Object;Ljava/lang/String;)Ljava/lang/Object;
       6: pop
       7: aload_1
       8: ldc           #190                // String sourceSupplier is null
      10: invokestatic  #3                  // Method java/util/Objects.requireNonNull:(Ljava/lang/Object;Ljava/lang/String;)Ljava/lang/Object;
      13: pop
      14: aload_2
      15: ldc           #191                // String resourceCleanup is null
      17: invokestatic  #3                  // Method java/util/Objects.requireNonNull:(Ljava/lang/Object;Ljava/lang/String;)Ljava/lang/Object;
      20: pop
      21: new           #192                // class io/reactivex/rxjava3/internal/operators/single/SingleUsing
      24: dup
      25: aload_0
      26: aload_1
      27: aload_2
      28: iload_3
      29: invokespecial #193                // Method io/reactivex/rxjava3/internal/operators/single/SingleUsing."<init>":(Lio/reactivex/rxjava3/functions/Supplier;Lio/reactivex/rxjava3/functions/Function;Lio/reactivex/rxjava3/functions/Consumer;Z)V
      32: invokestatic  #194                // Method io/reactivex/rxjava3/plugins/RxJavaPlugins.onAssembly:(Lio/reactivex/rxjava3/core/Single;)Lio/reactivex/rxjava3/core/Single;
      35: areturn

  public static <T> io.reactivex.rxjava3.core.Single<T> wrap(io.reactivex.rxjava3.core.SingleSource<T>);
    Code:
       0: aload_0
       1: ldc           #76                 // String source is null
       3: invokestatic  #3                  // Method java/util/Objects.requireNonNull:(Ljava/lang/Object;Ljava/lang/String;)Ljava/lang/Object;
       6: pop
       7: aload_0
       8: instanceof    #181                // class io/reactivex/rxjava3/core/Single
      11: ifeq          22
      14: aload_0
      15: checkcast     #181                // class io/reactivex/rxjava3/core/Single
      18: invokestatic  #195                // Method io/reactivex/rxjava3/plugins/RxJavaPlugins.onAssembly:(Lio/reactivex/rxjava3/core/Single;)Lio/reactivex/rxjava3/core/Single;
      21: areturn
      22: new           #185                // class io/reactivex/rxjava3/internal/operators/single/SingleFromUnsafeSource
      25: dup
      26: aload_0
      27: invokespecial #186                // Method io/reactivex/rxjava3/internal/operators/single/SingleFromUnsafeSource."<init>":(Lio/reactivex/rxjava3/core/SingleSource;)V
      30: invokestatic  #196                // Method io/reactivex/rxjava3/plugins/RxJavaPlugins.onAssembly:(Lio/reactivex/rxjava3/core/Single;)Lio/reactivex/rxjava3/core/Single;
      33: areturn

  public static <T, R> io.reactivex.rxjava3.core.Single<R> zip(java.lang.Iterable<? extends io.reactivex.rxjava3.core.SingleSource<? extends T>>, io.reactivex.rxjava3.functions.Function<? super java.lang.Object[], ? extends R>);
    Code:
       0: aload_1
       1: ldc           #197                // String zipper is null
       3: invokestatic  #3                  // Method java/util/Objects.requireNonNull:(Ljava/lang/Object;Ljava/lang/String;)Ljava/lang/Object;
       6: pop
       7: aload_0
       8: ldc           #2                  // String sources is null
      10: invokestatic  #3                  // Method java/util/Objects.requireNonNull:(Ljava/lang/Object;Ljava/lang/String;)Ljava/lang/Object;
      13: pop
      14: new           #198                // class io/reactivex/rxjava3/internal/operators/single/SingleZipIterable
      17: dup
      18: aload_0
      19: aload_1
      20: invokespecial #199                // Method io/reactivex/rxjava3/internal/operators/single/SingleZipIterable."<init>":(Ljava/lang/Iterable;Lio/reactivex/rxjava3/functions/Function;)V
      23: invokestatic  #200                // Method io/reactivex/rxjava3/plugins/RxJavaPlugins.onAssembly:(Lio/reactivex/rxjava3/core/Single;)Lio/reactivex/rxjava3/core/Single;
      26: areturn

  public static <T1, T2, R> io.reactivex.rxjava3.core.Single<R> zip(io.reactivex.rxjava3.core.SingleSource<? extends T1>, io.reactivex.rxjava3.core.SingleSource<? extends T2>, io.reactivex.rxjava3.functions.BiFunction<? super T1, ? super T2, ? extends R>);
    Code:
       0: aload_0
       1: ldc           #26                 // String source1 is null
       3: invokestatic  #3                  // Method java/util/Objects.requireNonNull:(Ljava/lang/Object;Ljava/lang/String;)Ljava/lang/Object;
       6: pop
       7: aload_1
       8: ldc           #27                 // String source2 is null
      10: invokestatic  #3                  // Method java/util/Objects.requireNonNull:(Ljava/lang/Object;Ljava/lang/String;)Ljava/lang/Object;
      13: pop
      14: aload_2
      15: ldc           #197                // String zipper is null
      17: invokestatic  #3                  // Method java/util/Objects.requireNonNull:(Ljava/lang/Object;Ljava/lang/String;)Ljava/lang/Object;
      20: pop
      21: aload_2
      22: invokestatic  #201                // Method io/reactivex/rxjava3/internal/functions/Functions.toFunction:(Lio/reactivex/rxjava3/functions/BiFunction;)Lio/reactivex/rxjava3/functions/Function;
      25: iconst_2
      26: anewarray     #28                 // class io/reactivex/rxjava3/core/SingleSource
      29: dup
      30: iconst_0
      31: aload_0
      32: aastore
      33: dup
      34: iconst_1
      35: aload_1
      36: aastore
      37: invokestatic  #202                // Method zipArray:(Lio/reactivex/rxjava3/functions/Function;[Lio/reactivex/rxjava3/core/SingleSource;)Lio/reactivex/rxjava3/core/Single;
      40: areturn

  public static <T1, T2, T3, R> io.reactivex.rxjava3.core.Single<R> zip(io.reactivex.rxjava3.core.SingleSource<? extends T1>, io.reactivex.rxjava3.core.SingleSource<? extends T2>, io.reactivex.rxjava3.core.SingleSource<? extends T3>, io.reactivex.rxjava3.functions.Function3<? super T1, ? super T2, ? super T3, ? extends R>);
    Code:
       0: aload_0
       1: ldc           #26                 // String source1 is null
       3: invokestatic  #3                  // Method java/util/Objects.requireNonNull:(Ljava/lang/Object;Ljava/lang/String;)Ljava/lang/Object;
       6: pop
       7: aload_1
       8: ldc           #27                 // String source2 is null
      10: invokestatic  #3                  // Method java/util/Objects.requireNonNull:(Ljava/lang/Object;Ljava/lang/String;)Ljava/lang/Object;
      13: pop
      14: aload_2
      15: ldc           #32                 // String source3 is null
      17: invokestatic  #3                  // Method java/util/Objects.requireNonNull:(Ljava/lang/Object;Ljava/lang/String;)Ljava/lang/Object;
      20: pop
      21: aload_3
      22: ldc           #197                // String zipper is null
      24: invokestatic  #3                  // Method java/util/Objects.requireNonNull:(Ljava/lang/Object;Ljava/lang/String;)Ljava/lang/Object;
      27: pop
      28: aload_3
      29: invokestatic  #203                // Method io/reactivex/rxjava3/internal/functions/Functions.toFunction:(Lio/reactivex/rxjava3/functions/Function3;)Lio/reactivex/rxjava3/functions/Function;
      32: iconst_3
      33: anewarray     #28                 // class io/reactivex/rxjava3/core/SingleSource
      36: dup
      37: iconst_0
      38: aload_0
      39: aastore
      40: dup
      41: iconst_1
      42: aload_1
      43: aastore
      44: dup
      45: iconst_2
      46: aload_2
      47: aastore
      48: invokestatic  #204                // Method zipArray:(Lio/reactivex/rxjava3/functions/Function;[Lio/reactivex/rxjava3/core/SingleSource;)Lio/reactivex/rxjava3/core/Single;
      51: areturn

  public static <T1, T2, T3, T4, R> io.reactivex.rxjava3.core.Single<R> zip(io.reactivex.rxjava3.core.SingleSource<? extends T1>, io.reactivex.rxjava3.core.SingleSource<? extends T2>, io.reactivex.rxjava3.core.SingleSource<? extends T3>, io.reactivex.rxjava3.core.SingleSource<? extends T4>, io.reactivex.rxjava3.functions.Function4<? super T1, ? super T2, ? super T3, ? super T4, ? extends R>);
    Code:
       0: aload_0
       1: ldc           #26                 // String source1 is null
       3: invokestatic  #3                  // Method java/util/Objects.requireNonNull:(Ljava/lang/Object;Ljava/lang/String;)Ljava/lang/Object;
       6: pop
       7: aload_1
       8: ldc           #27                 // String source2 is null
      10: invokestatic  #3                  // Method java/util/Objects.requireNonNull:(Ljava/lang/Object;Ljava/lang/String;)Ljava/lang/Object;
      13: pop
      14: aload_2
      15: ldc           #32                 // String source3 is null
      17: invokestatic  #3                  // Method java/util/Objects.requireNonNull:(Ljava/lang/Object;Ljava/lang/String;)Ljava/lang/Object;
      20: pop
      21: aload_3
      22: ldc           #36                 // String source4 is null
      24: invokestatic  #3                  // Method java/util/Objects.requireNonNull:(Ljava/lang/Object;Ljava/lang/String;)Ljava/lang/Object;
      27: pop
      28: aload         4
      30: ldc           #197                // String zipper is null
      32: invokestatic  #3                  // Method java/util/Objects.requireNonNull:(Ljava/lang/Object;Ljava/lang/String;)Ljava/lang/Object;
      35: pop
      36: aload         4
      38: invokestatic  #205                // Method io/reactivex/rxjava3/internal/functions/Functions.toFunction:(Lio/reactivex/rxjava3/functions/Function4;)Lio/reactivex/rxjava3/functions/Function;
      41: iconst_4
      42: anewarray     #28                 // class io/reactivex/rxjava3/core/SingleSource
      45: dup
      46: iconst_0
      47: aload_0
      48: aastore
      49: dup
      50: iconst_1
      51: aload_1
      52: aastore
      53: dup
      54: iconst_2
      55: aload_2
      56: aastore
      57: dup
      58: iconst_3
      59: aload_3
      60: aastore
      61: invokestatic  #206                // Method zipArray:(Lio/reactivex/rxjava3/functions/Function;[Lio/reactivex/rxjava3/core/SingleSource;)Lio/reactivex/rxjava3/core/Single;
      64: areturn

  public static <T1, T2, T3, T4, T5, R> io.reactivex.rxjava3.core.Single<R> zip(io.reactivex.rxjava3.core.SingleSource<? extends T1>, io.reactivex.rxjava3.core.SingleSource<? extends T2>, io.reactivex.rxjava3.core.SingleSource<? extends T3>, io.reactivex.rxjava3.core.SingleSource<? extends T4>, io.reactivex.rxjava3.core.SingleSource<? extends T5>, io.reactivex.rxjava3.functions.Function5<? super T1, ? super T2, ? super T3, ? super T4, ? super T5, ? extends R>);
    Code:
       0: aload_0
       1: ldc           #26                 // String source1 is null
       3: invokestatic  #3                  // Method java/util/Objects.requireNonNull:(Ljava/lang/Object;Ljava/lang/String;)Ljava/lang/Object;
       6: pop
       7: aload_1
       8: ldc           #27                 // String source2 is null
      10: invokestatic  #3                  // Method java/util/Objects.requireNonNull:(Ljava/lang/Object;Ljava/lang/String;)Ljava/lang/Object;
      13: pop
      14: aload_2
      15: ldc           #32                 // String source3 is null
      17: invokestatic  #3                  // Method java/util/Objects.requireNonNull:(Ljava/lang/Object;Ljava/lang/String;)Ljava/lang/Object;
      20: pop
      21: aload_3
      22: ldc           #36                 // String source4 is null
      24: invokestatic  #3                  // Method java/util/Objects.requireNonNull:(Ljava/lang/Object;Ljava/lang/String;)Ljava/lang/Object;
      27: pop
      28: aload         4
      30: ldc           #207                // String source5 is null
      32: invokestatic  #3                  // Method java/util/Objects.requireNonNull:(Ljava/lang/Object;Ljava/lang/String;)Ljava/lang/Object;
      35: pop
      36: aload         5
      38: ldc           #197                // String zipper is null
      40: invokestatic  #3                  // Method java/util/Objects.requireNonNull:(Ljava/lang/Object;Ljava/lang/String;)Ljava/lang/Object;
      43: pop
      44: aload         5
      46: invokestatic  #208                // Method io/reactivex/rxjava3/internal/functions/Functions.toFunction:(Lio/reactivex/rxjava3/functions/Function5;)Lio/reactivex/rxjava3/functions/Function;
      49: iconst_5
      50: anewarray     #28                 // class io/reactivex/rxjava3/core/SingleSource
      53: dup
      54: iconst_0
      55: aload_0
      56: aastore
      57: dup
      58: iconst_1
      59: aload_1
      60: aastore
      61: dup
      62: iconst_2
      63: aload_2
      64: aastore
      65: dup
      66: iconst_3
      67: aload_3
      68: aastore
      69: dup
      70: iconst_4
      71: aload         4
      73: aastore
      74: invokestatic  #209                // Method zipArray:(Lio/reactivex/rxjava3/functions/Function;[Lio/reactivex/rxjava3/core/SingleSource;)Lio/reactivex/rxjava3/core/Single;
      77: areturn

  public static <T1, T2, T3, T4, T5, T6, R> io.reactivex.rxjava3.core.Single<R> zip(io.reactivex.rxjava3.core.SingleSource<? extends T1>, io.reactivex.rxjava3.core.SingleSource<? extends T2>, io.reactivex.rxjava3.core.SingleSource<? extends T3>, io.reactivex.rxjava3.core.SingleSource<? extends T4>, io.reactivex.rxjava3.core.SingleSource<? extends T5>, io.reactivex.rxjava3.core.SingleSource<? extends T6>, io.reactivex.rxjava3.functions.Function6<? super T1, ? super T2, ? super T3, ? super T4, ? super T5, ? super T6, ? extends R>);
    Code:
       0: aload_0
       1: ldc           #26                 // String source1 is null
       3: invokestatic  #3                  // Method java/util/Objects.requireNonNull:(Ljava/lang/Object;Ljava/lang/String;)Ljava/lang/Object;
       6: pop
       7: aload_1
       8: ldc           #27                 // String source2 is null
      10: invokestatic  #3                  // Method java/util/Objects.requireNonNull:(Ljava/lang/Object;Ljava/lang/String;)Ljava/lang/Object;
      13: pop
      14: aload_2
      15: ldc           #32                 // String source3 is null
      17: invokestatic  #3                  // Method java/util/Objects.requireNonNull:(Ljava/lang/Object;Ljava/lang/String;)Ljava/lang/Object;
      20: pop
      21: aload_3
      22: ldc           #36                 // String source4 is null
      24: invokestatic  #3                  // Method java/util/Objects.requireNonNull:(Ljava/lang/Object;Ljava/lang/String;)Ljava/lang/Object;
      27: pop
      28: aload         4
      30: ldc           #207                // String source5 is null
      32: invokestatic  #3                  // Method java/util/Objects.requireNonNull:(Ljava/lang/Object;Ljava/lang/String;)Ljava/lang/Object;
      35: pop
      36: aload         5
      38: ldc           #210                // String source6 is null
      40: invokestatic  #3                  // Method java/util/Objects.requireNonNull:(Ljava/lang/Object;Ljava/lang/String;)Ljava/lang/Object;
      43: pop
      44: aload         6
      46: ldc           #197                // String zipper is null
      48: invokestatic  #3                  // Method java/util/Objects.requireNonNull:(Ljava/lang/Object;Ljava/lang/String;)Ljava/lang/Object;
      51: pop
      52: aload         6
      54: invokestatic  #211                // Method io/reactivex/rxjava3/internal/functions/Functions.toFunction:(Lio/reactivex/rxjava3/functions/Function6;)Lio/reactivex/rxjava3/functions/Function;
      57: bipush        6
      59: anewarray     #28                 // class io/reactivex/rxjava3/core/SingleSource
      62: dup
      63: iconst_0
      64: aload_0
      65: aastore
      66: dup
      67: iconst_1
      68: aload_1
      69: aastore
      70: dup
      71: iconst_2
      72: aload_2
      73: aastore
      74: dup
      75: iconst_3
      76: aload_3
      77: aastore
      78: dup
      79: iconst_4
      80: aload         4
      82: aastore
      83: dup
      84: iconst_5
      85: aload         5
      87: aastore
      88: invokestatic  #212                // Method zipArray:(Lio/reactivex/rxjava3/functions/Function;[Lio/reactivex/rxjava3/core/SingleSource;)Lio/reactivex/rxjava3/core/Single;
      91: areturn

  public static <T1, T2, T3, T4, T5, T6, T7, R> io.reactivex.rxjava3.core.Single<R> zip(io.reactivex.rxjava3.core.SingleSource<? extends T1>, io.reactivex.rxjava3.core.SingleSource<? extends T2>, io.reactivex.rxjava3.core.SingleSource<? extends T3>, io.reactivex.rxjava3.core.SingleSource<? extends T4>, io.reactivex.rxjava3.core.SingleSource<? extends T5>, io.reactivex.rxjava3.core.SingleSource<? extends T6>, io.reactivex.rxjava3.core.SingleSource<? extends T7>, io.reactivex.rxjava3.functions.Function7<? super T1, ? super T2, ? super T3, ? super T4, ? super T5, ? super T6, ? super T7, ? extends R>);
    Code:
       0: aload_0
       1: ldc           #26                 // String source1 is null
       3: invokestatic  #3                  // Method java/util/Objects.requireNonNull:(Ljava/lang/Object;Ljava/lang/String;)Ljava/lang/Object;
       6: pop
       7: aload_1
       8: ldc           #27                 // String source2 is null
      10: invokestatic  #3                  // Method java/util/Objects.requireNonNull:(Ljava/lang/Object;Ljava/lang/String;)Ljava/lang/Object;
      13: pop
      14: aload_2
      15: ldc           #32                 // String source3 is null
      17: invokestatic  #3                  // Method java/util/Objects.requireNonNull:(Ljava/lang/Object;Ljava/lang/String;)Ljava/lang/Object;
      20: pop
      21: aload_3
      22: ldc           #36                 // String source4 is null
      24: invokestatic  #3                  // Method java/util/Objects.requireNonNull:(Ljava/lang/Object;Ljava/lang/String;)Ljava/lang/Object;
      27: pop
      28: aload         4
      30: ldc           #207                // String source5 is null
      32: invokestatic  #3                  // Method java/util/Objects.requireNonNull:(Ljava/lang/Object;Ljava/lang/String;)Ljava/lang/Object;
      35: pop
      36: aload         5
      38: ldc           #210                // String source6 is null
      40: invokestatic  #3                  // Method java/util/Objects.requireNonNull:(Ljava/lang/Object;Ljava/lang/String;)Ljava/lang/Object;
      43: pop
      44: aload         6
      46: ldc           #213                // String source7 is null
      48: invokestatic  #3                  // Method java/util/Objects.requireNonNull:(Ljava/lang/Object;Ljava/lang/String;)Ljava/lang/Object;
      51: pop
      52: aload         7
      54: ldc           #197                // String zipper is null
      56: invokestatic  #3                  // Method java/util/Objects.requireNonNull:(Ljava/lang/Object;Ljava/lang/String;)Ljava/lang/Object;
      59: pop
      60: aload         7
      62: invokestatic  #214                // Method io/reactivex/rxjava3/internal/functions/Functions.toFunction:(Lio/reactivex/rxjava3/functions/Function7;)Lio/reactivex/rxjava3/functions/Function;
      65: bipush        7
      67: anewarray     #28                 // class io/reactivex/rxjava3/core/SingleSource
      70: dup
      71: iconst_0
      72: aload_0
      73: aastore
      74: dup
      75: iconst_1
      76: aload_1
      77: aastore
      78: dup
      79: iconst_2
      80: aload_2
      81: aastore
      82: dup
      83: iconst_3
      84: aload_3
      85: aastore
      86: dup
      87: iconst_4
      88: aload         4
      90: aastore
      91: dup
      92: iconst_5
      93: aload         5
      95: aastore
      96: dup
      97: bipush        6
      99: aload         6
     101: aastore
     102: invokestatic  #215                // Method zipArray:(Lio/reactivex/rxjava3/functions/Function;[Lio/reactivex/rxjava3/core/SingleSource;)Lio/reactivex/rxjava3/core/Single;
     105: areturn

  public static <T1, T2, T3, T4, T5, T6, T7, T8, R> io.reactivex.rxjava3.core.Single<R> zip(io.reactivex.rxjava3.core.SingleSource<? extends T1>, io.reactivex.rxjava3.core.SingleSource<? extends T2>, io.reactivex.rxjava3.core.SingleSource<? extends T3>, io.reactivex.rxjava3.core.SingleSource<? extends T4>, io.reactivex.rxjava3.core.SingleSource<? extends T5>, io.reactivex.rxjava3.core.SingleSource<? extends T6>, io.reactivex.rxjava3.core.SingleSource<? extends T7>, io.reactivex.rxjava3.core.SingleSource<? extends T8>, io.reactivex.rxjava3.functions.Function8<? super T1, ? super T2, ? super T3, ? super T4, ? super T5, ? super T6, ? super T7, ? super T8, ? extends R>);
    Code:
       0: aload_0
       1: ldc           #26                 // String source1 is null
       3: invokestatic  #3                  // Method java/util/Objects.requireNonNull:(Ljava/lang/Object;Ljava/lang/String;)Ljava/lang/Object;
       6: pop
       7: aload_1
       8: ldc           #27                 // String source2 is null
      10: invokestatic  #3                  // Method java/util/Objects.requireNonNull:(Ljava/lang/Object;Ljava/lang/String;)Ljava/lang/Object;
      13: pop
      14: aload_2
      15: ldc           #32                 // String source3 is null
      17: invokestatic  #3                  // Method java/util/Objects.requireNonNull:(Ljava/lang/Object;Ljava/lang/String;)Ljava/lang/Object;
      20: pop
      21: aload_3
      22: ldc           #36                 // String source4 is null
      24: invokestatic  #3                  // Method java/util/Objects.requireNonNull:(Ljava/lang/Object;Ljava/lang/String;)Ljava/lang/Object;
      27: pop
      28: aload         4
      30: ldc           #207                // String source5 is null
      32: invokestatic  #3                  // Method java/util/Objects.requireNonNull:(Ljava/lang/Object;Ljava/lang/String;)Ljava/lang/Object;
      35: pop
      36: aload         5
      38: ldc           #210                // String source6 is null
      40: invokestatic  #3                  // Method java/util/Objects.requireNonNull:(Ljava/lang/Object;Ljava/lang/String;)Ljava/lang/Object;
      43: pop
      44: aload         6
      46: ldc           #213                // String source7 is null
      48: invokestatic  #3                  // Method java/util/Objects.requireNonNull:(Ljava/lang/Object;Ljava/lang/String;)Ljava/lang/Object;
      51: pop
      52: aload         7
      54: ldc           #216                // String source8 is null
      56: invokestatic  #3                  // Method java/util/Objects.requireNonNull:(Ljava/lang/Object;Ljava/lang/String;)Ljava/lang/Object;
      59: pop
      60: aload         8
      62: ldc           #197                // String zipper is null
      64: invokestatic  #3                  // Method java/util/Objects.requireNonNull:(Ljava/lang/Object;Ljava/lang/String;)Ljava/lang/Object;
      67: pop
      68: aload         8
      70: invokestatic  #217                // Method io/reactivex/rxjava3/internal/functions/Functions.toFunction:(Lio/reactivex/rxjava3/functions/Function8;)Lio/reactivex/rxjava3/functions/Function;
      73: bipush        8
      75: anewarray     #28                 // class io/reactivex/rxjava3/core/SingleSource
      78: dup
      79: iconst_0
      80: aload_0
      81: aastore
      82: dup
      83: iconst_1
      84: aload_1
      85: aastore
      86: dup
      87: iconst_2
      88: aload_2
      89: aastore
      90: dup
      91: iconst_3
      92: aload_3
      93: aastore
      94: dup
      95: iconst_4
      96: aload         4
      98: aastore
      99: dup
     100: iconst_5
     101: aload         5
     103: aastore
     104: dup
     105: bipush        6
     107: aload         6
     109: aastore
     110: dup
     111: bipush        7
     113: aload         7
     115: aastore
     116: invokestatic  #218                // Method zipArray:(Lio/reactivex/rxjava3/functions/Function;[Lio/reactivex/rxjava3/core/SingleSource;)Lio/reactivex/rxjava3/core/Single;
     119: areturn

  public static <T1, T2, T3, T4, T5, T6, T7, T8, T9, R> io.reactivex.rxjava3.core.Single<R> zip(io.reactivex.rxjava3.core.SingleSource<? extends T1>, io.reactivex.rxjava3.core.SingleSource<? extends T2>, io.reactivex.rxjava3.core.SingleSource<? extends T3>, io.reactivex.rxjava3.core.SingleSource<? extends T4>, io.reactivex.rxjava3.core.SingleSource<? extends T5>, io.reactivex.rxjava3.core.SingleSource<? extends T6>, io.reactivex.rxjava3.core.SingleSource<? extends T7>, io.reactivex.rxjava3.core.SingleSource<? extends T8>, io.reactivex.rxjava3.core.SingleSource<? extends T9>, io.reactivex.rxjava3.functions.Function9<? super T1, ? super T2, ? super T3, ? super T4, ? super T5, ? super T6, ? super T7, ? super T8, ? super T9, ? extends R>);
    Code:
       0: aload_0
       1: ldc           #26                 // String source1 is null
       3: invokestatic  #3                  // Method java/util/Objects.requireNonNull:(Ljava/lang/Object;Ljava/lang/String;)Ljava/lang/Object;
       6: pop
       7: aload_1
       8: ldc           #27                 // String source2 is null
      10: invokestatic  #3                  // Method java/util/Objects.requireNonNull:(Ljava/lang/Object;Ljava/lang/String;)Ljava/lang/Object;
      13: pop
      14: aload_2
      15: ldc           #32                 // String source3 is null
      17: invokestatic  #3                  // Method java/util/Objects.requireNonNull:(Ljava/lang/Object;Ljava/lang/String;)Ljava/lang/Object;
      20: pop
      21: aload_3
      22: ldc           #36                 // String source4 is null
      24: invokestatic  #3                  // Method java/util/Objects.requireNonNull:(Ljava/lang/Object;Ljava/lang/String;)Ljava/lang/Object;
      27: pop
      28: aload         4
      30: ldc           #207                // String source5 is null
      32: invokestatic  #3                  // Method java/util/Objects.requireNonNull:(Ljava/lang/Object;Ljava/lang/String;)Ljava/lang/Object;
      35: pop
      36: aload         5
      38: ldc           #210                // String source6 is null
      40: invokestatic  #3                  // Method java/util/Objects.requireNonNull:(Ljava/lang/Object;Ljava/lang/String;)Ljava/lang/Object;
      43: pop
      44: aload         6
      46: ldc           #213                // String source7 is null
      48: invokestatic  #3                  // Method java/util/Objects.requireNonNull:(Ljava/lang/Object;Ljava/lang/String;)Ljava/lang/Object;
      51: pop
      52: aload         7
      54: ldc           #216                // String source8 is null
      56: invokestatic  #3                  // Method java/util/Objects.requireNonNull:(Ljava/lang/Object;Ljava/lang/String;)Ljava/lang/Object;
      59: pop
      60: aload         8
      62: ldc           #219                // String source9 is null
      64: invokestatic  #3                  // Method java/util/Objects.requireNonNull:(Ljava/lang/Object;Ljava/lang/String;)Ljava/lang/Object;
      67: pop
      68: aload         9
      70: ldc           #197                // String zipper is null
      72: invokestatic  #3                  // Method java/util/Objects.requireNonNull:(Ljava/lang/Object;Ljava/lang/String;)Ljava/lang/Object;
      75: pop
      76: aload         9
      78: invokestatic  #220                // Method io/reactivex/rxjava3/internal/functions/Functions.toFunction:(Lio/reactivex/rxjava3/functions/Function9;)Lio/reactivex/rxjava3/functions/Function;
      81: bipush        9
      83: anewarray     #28                 // class io/reactivex/rxjava3/core/SingleSource
      86: dup
      87: iconst_0
      88: aload_0
      89: aastore
      90: dup
      91: iconst_1
      92: aload_1
      93: aastore
      94: dup
      95: iconst_2
      96: aload_2
      97: aastore
      98: dup
      99: iconst_3
     100: aload_3
     101: aastore
     102: dup
     103: iconst_4
     104: aload         4
     106: aastore
     107: dup
     108: iconst_5
     109: aload         5
     111: aastore
     112: dup
     113: bipush        6
     115: aload         6
     117: aastore
     118: dup
     119: bipush        7
     121: aload         7
     123: aastore
     124: dup
     125: bipush        8
     127: aload         8
     129: aastore
     130: invokestatic  #221                // Method zipArray:(Lio/reactivex/rxjava3/functions/Function;[Lio/reactivex/rxjava3/core/SingleSource;)Lio/reactivex/rxjava3/core/Single;
     133: areturn

  public static <T, R> io.reactivex.rxjava3.core.Single<R> zipArray(io.reactivex.rxjava3.functions.Function<? super java.lang.Object[], ? extends R>, io.reactivex.rxjava3.core.SingleSource<? extends T>...);
    Code:
       0: aload_0
       1: ldc           #197                // String zipper is null
       3: invokestatic  #3                  // Method java/util/Objects.requireNonNull:(Ljava/lang/Object;Ljava/lang/String;)Ljava/lang/Object;
       6: pop
       7: aload_1
       8: ldc           #2                  // String sources is null
      10: invokestatic  #3                  // Method java/util/Objects.requireNonNull:(Ljava/lang/Object;Ljava/lang/String;)Ljava/lang/Object;
      13: pop
      14: aload_1
      15: arraylength
      16: ifne          30
      19: new           #222                // class java/util/NoSuchElementException
      22: dup
      23: invokespecial #223                // Method java/util/NoSuchElementException."<init>":()V
      26: invokestatic  #224                // Method error:(Ljava/lang/Throwable;)Lio/reactivex/rxjava3/core/Single;
      29: areturn
      30: new           #225                // class io/reactivex/rxjava3/internal/operators/single/SingleZipArray
      33: dup
      34: aload_1
      35: aload_0
      36: invokespecial #226                // Method io/reactivex/rxjava3/internal/operators/single/SingleZipArray."<init>":([Lio/reactivex/rxjava3/core/SingleSource;Lio/reactivex/rxjava3/functions/Function;)V
      39: invokestatic  #227                // Method io/reactivex/rxjava3/plugins/RxJavaPlugins.onAssembly:(Lio/reactivex/rxjava3/core/Single;)Lio/reactivex/rxjava3/core/Single;
      42: areturn

  public final io.reactivex.rxjava3.core.Single<T> ambWith(io.reactivex.rxjava3.core.SingleSource<? extends T>);
    Code:
       0: aload_1
       1: ldc           #228                // String other is null
       3: invokestatic  #3                  // Method java/util/Objects.requireNonNull:(Ljava/lang/Object;Ljava/lang/String;)Ljava/lang/Object;
       6: pop
       7: iconst_2
       8: anewarray     #28                 // class io/reactivex/rxjava3/core/SingleSource
      11: dup
      12: iconst_0
      13: aload_0
      14: aastore
      15: dup
      16: iconst_1
      17: aload_1
      18: aastore
      19: invokestatic  #229                // Method ambArray:([Lio/reactivex/rxjava3/core/SingleSource;)Lio/reactivex/rxjava3/core/Single;
      22: areturn

  public final io.reactivex.rxjava3.core.Single<T> hide();
    Code:
       0: new           #230                // class io/reactivex/rxjava3/internal/operators/single/SingleHide
       3: dup
       4: aload_0
       5: invokespecial #231                // Method io/reactivex/rxjava3/internal/operators/single/SingleHide."<init>":(Lio/reactivex/rxjava3/core/SingleSource;)V
       8: invokestatic  #232                // Method io/reactivex/rxjava3/plugins/RxJavaPlugins.onAssembly:(Lio/reactivex/rxjava3/core/Single;)Lio/reactivex/rxjava3/core/Single;
      11: areturn

  public final <R> io.reactivex.rxjava3.core.Single<R> compose(io.reactivex.rxjava3.core.SingleTransformer<? super T, ? extends R>);
    Code:
       0: aload_1
       1: ldc           #233                // String transformer is null
       3: invokestatic  #3                  // Method java/util/Objects.requireNonNull:(Ljava/lang/Object;Ljava/lang/String;)Ljava/lang/Object;
       6: checkcast     #234                // class io/reactivex/rxjava3/core/SingleTransformer
       9: aload_0
      10: invokeinterface #235,  2          // InterfaceMethod io/reactivex/rxjava3/core/SingleTransformer.apply:(Lio/reactivex/rxjava3/core/Single;)Lio/reactivex/rxjava3/core/SingleSource;
      15: invokestatic  #236                // Method wrap:(Lio/reactivex/rxjava3/core/SingleSource;)Lio/reactivex/rxjava3/core/Single;
      18: areturn

  public final io.reactivex.rxjava3.core.Single<T> cache();
    Code:
       0: new           #237                // class io/reactivex/rxjava3/internal/operators/single/SingleCache
       3: dup
       4: aload_0
       5: invokespecial #238                // Method io/reactivex/rxjava3/internal/operators/single/SingleCache."<init>":(Lio/reactivex/rxjava3/core/SingleSource;)V
       8: invokestatic  #239                // Method io/reactivex/rxjava3/plugins/RxJavaPlugins.onAssembly:(Lio/reactivex/rxjava3/core/Single;)Lio/reactivex/rxjava3/core/Single;
      11: areturn

  public final <U> io.reactivex.rxjava3.core.Single<U> cast(java.lang.Class<? extends U>);
    Code:
       0: aload_1
       1: ldc           #240                // String clazz is null
       3: invokestatic  #3                  // Method java/util/Objects.requireNonNull:(Ljava/lang/Object;Ljava/lang/String;)Ljava/lang/Object;
       6: pop
       7: aload_0
       8: aload_1
       9: invokestatic  #241                // Method io/reactivex/rxjava3/internal/functions/Functions.castFunction:(Ljava/lang/Class;)Lio/reactivex/rxjava3/functions/Function;
      12: invokevirtual #242                // Method map:(Lio/reactivex/rxjava3/functions/Function;)Lio/reactivex/rxjava3/core/Single;
      15: areturn

  public final <R> io.reactivex.rxjava3.core.Single<R> concatMap(io.reactivex.rxjava3.functions.Function<? super T, ? extends io.reactivex.rxjava3.core.SingleSource<? extends R>>);
    Code:
       0: aload_1
       1: ldc           #243                // String mapper is null
       3: invokestatic  #3                  // Method java/util/Objects.requireNonNull:(Ljava/lang/Object;Ljava/lang/String;)Ljava/lang/Object;
       6: pop
       7: new           #128                // class io/reactivex/rxjava3/internal/operators/single/SingleFlatMap
      10: dup
      11: aload_0
      12: aload_1
      13: invokespecial #130                // Method io/reactivex/rxjava3/internal/operators/single/SingleFlatMap."<init>":(Lio/reactivex/rxjava3/core/SingleSource;Lio/reactivex/rxjava3/functions/Function;)V
      16: invokestatic  #244                // Method io/reactivex/rxjava3/plugins/RxJavaPlugins.onAssembly:(Lio/reactivex/rxjava3/core/Single;)Lio/reactivex/rxjava3/core/Single;
      19: areturn

  public final io.reactivex.rxjava3.core.Completable concatMapCompletable(io.reactivex.rxjava3.functions.Function<? super T, ? extends io.reactivex.rxjava3.core.CompletableSource>);
    Code:
       0: aload_0
       1: aload_1
       2: invokevirtual #245                // Method flatMapCompletable:(Lio/reactivex/rxjava3/functions/Function;)Lio/reactivex/rxjava3/core/Completable;
       5: areturn

  public final <R> io.reactivex.rxjava3.core.Maybe<R> concatMapMaybe(io.reactivex.rxjava3.functions.Function<? super T, ? extends io.reactivex.rxjava3.core.MaybeSource<? extends R>>);
    Code:
       0: aload_0
       1: aload_1
       2: invokevirtual #246                // Method flatMapMaybe:(Lio/reactivex/rxjava3/functions/Function;)Lio/reactivex/rxjava3/core/Maybe;
       5: areturn

  public final io.reactivex.rxjava3.core.Flowable<T> concatWith(io.reactivex.rxjava3.core.SingleSource<? extends T>);
    Code:
       0: aload_0
       1: aload_1
       2: invokestatic  #247                // Method concat:(Lio/reactivex/rxjava3/core/SingleSource;Lio/reactivex/rxjava3/core/SingleSource;)Lio/reactivex/rxjava3/core/Flowable;
       5: areturn

  public final io.reactivex.rxjava3.core.Single<T> delay(long, java.util.concurrent.TimeUnit);
    Code:
       0: aload_0
       1: lload_1
       2: aload_3
       3: invokestatic  #164                // Method io/reactivex/rxjava3/schedulers/Schedulers.computation:()Lio/reactivex/rxjava3/core/Scheduler;
       6: iconst_0
       7: invokevirtual #248                // Method delay:(JLjava/util/concurrent/TimeUnit;Lio/reactivex/rxjava3/core/Scheduler;Z)Lio/reactivex/rxjava3/core/Single;
      10: areturn

  public final io.reactivex.rxjava3.core.Single<T> delay(long, java.util.concurrent.TimeUnit, boolean);
    Code:
       0: aload_0
       1: lload_1
       2: aload_3
       3: invokestatic  #164                // Method io/reactivex/rxjava3/schedulers/Schedulers.computation:()Lio/reactivex/rxjava3/core/Scheduler;
       6: iload         4
       8: invokevirtual #248                // Method delay:(JLjava/util/concurrent/TimeUnit;Lio/reactivex/rxjava3/core/Scheduler;Z)Lio/reactivex/rxjava3/core/Single;
      11: areturn

  public final io.reactivex.rxjava3.core.Single<T> delay(long, java.util.concurrent.TimeUnit, io.reactivex.rxjava3.core.Scheduler);
    Code:
       0: aload_0
       1: lload_1
       2: aload_3
       3: aload         4
       5: iconst_0
       6: invokevirtual #248                // Method delay:(JLjava/util/concurrent/TimeUnit;Lio/reactivex/rxjava3/core/Scheduler;Z)Lio/reactivex/rxjava3/core/Single;
       9: areturn

  public final io.reactivex.rxjava3.core.Single<T> delay(long, java.util.concurrent.TimeUnit, io.reactivex.rxjava3.core.Scheduler, boolean);
    Code:
       0: aload_3
       1: ldc           #166                // String unit is null
       3: invokestatic  #3                  // Method java/util/Objects.requireNonNull:(Ljava/lang/Object;Ljava/lang/String;)Ljava/lang/Object;
       6: pop
       7: aload         4
       9: ldc           #167                // String scheduler is null
      11: invokestatic  #3                  // Method java/util/Objects.requireNonNull:(Ljava/lang/Object;Ljava/lang/String;)Ljava/lang/Object;
      14: pop
      15: new           #249                // class io/reactivex/rxjava3/internal/operators/single/SingleDelay
      18: dup
      19: aload_0
      20: lload_1
      21: aload_3
      22: aload         4
      24: iload         5
      26: invokespecial #250                // Method io/reactivex/rxjava3/internal/operators/single/SingleDelay."<init>":(Lio/reactivex/rxjava3/core/SingleSource;JLjava/util/concurrent/TimeUnit;Lio/reactivex/rxjava3/core/Scheduler;Z)V
      29: invokestatic  #251                // Method io/reactivex/rxjava3/plugins/RxJavaPlugins.onAssembly:(Lio/reactivex/rxjava3/core/Single;)Lio/reactivex/rxjava3/core/Single;
      32: areturn

  public final io.reactivex.rxjava3.core.Single<T> delaySubscription(io.reactivex.rxjava3.core.CompletableSource);
    Code:
       0: aload_1
       1: ldc           #252                // String subscriptionIndicator is null
       3: invokestatic  #3                  // Method java/util/Objects.requireNonNull:(Ljava/lang/Object;Ljava/lang/String;)Ljava/lang/Object;
       6: pop
       7: new           #253                // class io/reactivex/rxjava3/internal/operators/single/SingleDelayWithCompletable
      10: dup
      11: aload_0
      12: aload_1
      13: invokespecial #254                // Method io/reactivex/rxjava3/internal/operators/single/SingleDelayWithCompletable."<init>":(Lio/reactivex/rxjava3/core/SingleSource;Lio/reactivex/rxjava3/core/CompletableSource;)V
      16: invokestatic  #255                // Method io/reactivex/rxjava3/plugins/RxJavaPlugins.onAssembly:(Lio/reactivex/rxjava3/core/Single;)Lio/reactivex/rxjava3/core/Single;
      19: areturn

  public final <U> io.reactivex.rxjava3.core.Single<T> delaySubscription(io.reactivex.rxjava3.core.SingleSource<U>);
    Code:
       0: aload_1
       1: ldc           #252                // String subscriptionIndicator is null
       3: invokestatic  #3                  // Method java/util/Objects.requireNonNull:(Ljava/lang/Object;Ljava/lang/String;)Ljava/lang/Object;
       6: pop
       7: new           #256                // class io/reactivex/rxjava3/internal/operators/single/SingleDelayWithSingle
      10: dup
      11: aload_0
      12: aload_1
      13: invokespecial #257                // Method io/reactivex/rxjava3/internal/operators/single/SingleDelayWithSingle."<init>":(Lio/reactivex/rxjava3/core/SingleSource;Lio/reactivex/rxjava3/core/SingleSource;)V
      16: invokestatic  #258                // Method io/reactivex/rxjava3/plugins/RxJavaPlugins.onAssembly:(Lio/reactivex/rxjava3/core/Single;)Lio/reactivex/rxjava3/core/Single;
      19: areturn

  public final <U> io.reactivex.rxjava3.core.Single<T> delaySubscription(io.reactivex.rxjava3.core.ObservableSource<U>);
    Code:
       0: aload_1
       1: ldc           #252                // String subscriptionIndicator is null
       3: invokestatic  #3                  // Method java/util/Objects.requireNonNull:(Ljava/lang/Object;Ljava/lang/String;)Ljava/lang/Object;
       6: pop
       7: new           #259                // class io/reactivex/rxjava3/internal/operators/single/SingleDelayWithObservable
      10: dup
      11: aload_0
      12: aload_1
      13: invokespecial #260                // Method io/reactivex/rxjava3/internal/operators/single/SingleDelayWithObservable."<init>":(Lio/reactivex/rxjava3/core/SingleSource;Lio/reactivex/rxjava3/core/ObservableSource;)V
      16: invokestatic  #261                // Method io/reactivex/rxjava3/plugins/RxJavaPlugins.onAssembly:(Lio/reactivex/rxjava3/core/Single;)Lio/reactivex/rxjava3/core/Single;
      19: areturn

  public final <U> io.reactivex.rxjava3.core.Single<T> delaySubscription(org.reactivestreams.Publisher<U>);
    Code:
       0: aload_1
       1: ldc           #252                // String subscriptionIndicator is null
       3: invokestatic  #3                  // Method java/util/Objects.requireNonNull:(Ljava/lang/Object;Ljava/lang/String;)Ljava/lang/Object;
       6: pop
       7: new           #262                // class io/reactivex/rxjava3/internal/operators/single/SingleDelayWithPublisher
      10: dup
      11: aload_0
      12: aload_1
      13: invokespecial #263                // Method io/reactivex/rxjava3/internal/operators/single/SingleDelayWithPublisher."<init>":(Lio/reactivex/rxjava3/core/SingleSource;Lorg/reactivestreams/Publisher;)V
      16: invokestatic  #264                // Method io/reactivex/rxjava3/plugins/RxJavaPlugins.onAssembly:(Lio/reactivex/rxjava3/core/Single;)Lio/reactivex/rxjava3/core/Single;
      19: areturn

  public final io.reactivex.rxjava3.core.Single<T> delaySubscription(long, java.util.concurrent.TimeUnit);
    Code:
       0: aload_0
       1: lload_1
       2: aload_3
       3: invokestatic  #164                // Method io/reactivex/rxjava3/schedulers/Schedulers.computation:()Lio/reactivex/rxjava3/core/Scheduler;
       6: invokevirtual #265                // Method delaySubscription:(JLjava/util/concurrent/TimeUnit;Lio/reactivex/rxjava3/core/Scheduler;)Lio/reactivex/rxjava3/core/Single;
       9: areturn

  public final io.reactivex.rxjava3.core.Single<T> delaySubscription(long, java.util.concurrent.TimeUnit, io.reactivex.rxjava3.core.Scheduler);
    Code:
       0: aload_0
       1: lload_1
       2: aload_3
       3: aload         4
       5: invokestatic  #266                // Method io/reactivex/rxjava3/core/Observable.timer:(JLjava/util/concurrent/TimeUnit;Lio/reactivex/rxjava3/core/Scheduler;)Lio/reactivex/rxjava3/core/Observable;
       8: invokevirtual #267                // Method delaySubscription:(Lio/reactivex/rxjava3/core/ObservableSource;)Lio/reactivex/rxjava3/core/Single;
      11: areturn

  public final <R> io.reactivex.rxjava3.core.Maybe<R> dematerialize(io.reactivex.rxjava3.functions.Function<? super T, io.reactivex.rxjava3.core.Notification<R>>);
    Code:
       0: aload_1
       1: ldc_w         #268                // String selector is null
       4: invokestatic  #3                  // Method java/util/Objects.requireNonNull:(Ljava/lang/Object;Ljava/lang/String;)Ljava/lang/Object;
       7: pop
       8: new           #269                // class io/reactivex/rxjava3/internal/operators/single/SingleDematerialize
      11: dup
      12: aload_0
      13: aload_1
      14: invokespecial #270                // Method io/reactivex/rxjava3/internal/operators/single/SingleDematerialize."<init>":(Lio/reactivex/rxjava3/core/Single;Lio/reactivex/rxjava3/functions/Function;)V
      17: invokestatic  #271                // Method io/reactivex/rxjava3/plugins/RxJavaPlugins.onAssembly:(Lio/reactivex/rxjava3/core/Maybe;)Lio/reactivex/rxjava3/core/Maybe;
      20: areturn

  public final io.reactivex.rxjava3.core.Single<T> doAfterSuccess(io.reactivex.rxjava3.functions.Consumer<? super T>);
    Code:
       0: aload_1
       1: ldc_w         #272                // String onAfterSuccess is null
       4: invokestatic  #3                  // Method java/util/Objects.requireNonNull:(Ljava/lang/Object;Ljava/lang/String;)Ljava/lang/Object;
       7: pop
       8: new           #273                // class io/reactivex/rxjava3/internal/operators/single/SingleDoAfterSuccess
      11: dup
      12: aload_0
      13: aload_1
      14: invokespecial #274                // Method io/reactivex/rxjava3/internal/operators/single/SingleDoAfterSuccess."<init>":(Lio/reactivex/rxjava3/core/SingleSource;Lio/reactivex/rxjava3/functions/Consumer;)V
      17: invokestatic  #275                // Method io/reactivex/rxjava3/plugins/RxJavaPlugins.onAssembly:(Lio/reactivex/rxjava3/core/Single;)Lio/reactivex/rxjava3/core/Single;
      20: areturn

  public final io.reactivex.rxjava3.core.Single<T> doAfterTerminate(io.reactivex.rxjava3.functions.Action);
    Code:
       0: aload_1
       1: ldc_w         #276                // String onAfterTerminate is null
       4: invokestatic  #3                  // Method java/util/Objects.requireNonNull:(Ljava/lang/Object;Ljava/lang/String;)Ljava/lang/Object;
       7: pop
       8: new           #277                // class io/reactivex/rxjava3/internal/operators/single/SingleDoAfterTerminate
      11: dup
      12: aload_0
      13: aload_1
      14: invokespecial #278                // Method io/reactivex/rxjava3/internal/operators/single/SingleDoAfterTerminate."<init>":(Lio/reactivex/rxjava3/core/SingleSource;Lio/reactivex/rxjava3/functions/Action;)V
      17: invokestatic  #279                // Method io/reactivex/rxjava3/plugins/RxJavaPlugins.onAssembly:(Lio/reactivex/rxjava3/core/Single;)Lio/reactivex/rxjava3/core/Single;
      20: areturn

  public final io.reactivex.rxjava3.core.Single<T> doFinally(io.reactivex.rxjava3.functions.Action);
    Code:
       0: aload_1
       1: ldc_w         #280                // String onFinally is null
       4: invokestatic  #3                  // Method java/util/Objects.requireNonNull:(Ljava/lang/Object;Ljava/lang/String;)Ljava/lang/Object;
       7: pop
       8: new           #281                // class io/reactivex/rxjava3/internal/operators/single/SingleDoFinally
      11: dup
      12: aload_0
      13: aload_1
      14: invokespecial #282                // Method io/reactivex/rxjava3/internal/operators/single/SingleDoFinally."<init>":(Lio/reactivex/rxjava3/core/SingleSource;Lio/reactivex/rxjava3/functions/Action;)V
      17: invokestatic  #283                // Method io/reactivex/rxjava3/plugins/RxJavaPlugins.onAssembly:(Lio/reactivex/rxjava3/core/Single;)Lio/reactivex/rxjava3/core/Single;
      20: areturn

  public final io.reactivex.rxjava3.core.Single<T> doOnLifecycle(io.reactivex.rxjava3.functions.Consumer<? super io.reactivex.rxjava3.disposables.Disposable>, io.reactivex.rxjava3.functions.Action);
    Code:
       0: aload_1
       1: ldc           #180                // String onSubscribe is null
       3: invokestatic  #3                  // Method java/util/Objects.requireNonNull:(Ljava/lang/Object;Ljava/lang/String;)Ljava/lang/Object;
       6: pop
       7: aload_2
       8: ldc_w         #284                // String onDispose is null
      11: invokestatic  #3                  // Method java/util/Objects.requireNonNull:(Ljava/lang/Object;Ljava/lang/String;)Ljava/lang/Object;
      14: pop
      15: new           #285                // class io/reactivex/rxjava3/internal/operators/single/SingleDoOnLifecycle
      18: dup
      19: aload_0
      20: aload_1
      21: aload_2
      22: invokespecial #286                // Method io/reactivex/rxjava3/internal/operators/single/SingleDoOnLifecycle."<init>":(Lio/reactivex/rxjava3/core/Single;Lio/reactivex/rxjava3/functions/Consumer;Lio/reactivex/rxjava3/functions/Action;)V
      25: invokestatic  #287                // Method io/reactivex/rxjava3/plugins/RxJavaPlugins.onAssembly:(Lio/reactivex/rxjava3/core/Single;)Lio/reactivex/rxjava3/core/Single;
      28: areturn

  public final io.reactivex.rxjava3.core.Single<T> doOnSubscribe(io.reactivex.rxjava3.functions.Consumer<? super io.reactivex.rxjava3.disposables.Disposable>);
    Code:
       0: aload_1
       1: ldc           #180                // String onSubscribe is null
       3: invokestatic  #3                  // Method java/util/Objects.requireNonNull:(Ljava/lang/Object;Ljava/lang/String;)Ljava/lang/Object;
       6: pop
       7: new           #288                // class io/reactivex/rxjava3/internal/operators/single/SingleDoOnSubscribe
      10: dup
      11: aload_0
      12: aload_1
      13: invokespecial #289                // Method io/reactivex/rxjava3/internal/operators/single/SingleDoOnSubscribe."<init>":(Lio/reactivex/rxjava3/core/SingleSource;Lio/reactivex/rxjava3/functions/Consumer;)V
      16: invokestatic  #290                // Method io/reactivex/rxjava3/plugins/RxJavaPlugins.onAssembly:(Lio/reactivex/rxjava3/core/Single;)Lio/reactivex/rxjava3/core/Single;
      19: areturn

  public final io.reactivex.rxjava3.core.Single<T> doOnTerminate(io.reactivex.rxjava3.functions.Action);
    Code:
       0: aload_1
       1: ldc_w         #291                // String onTerminate is null
       4: invokestatic  #3                  // Method java/util/Objects.requireNonNull:(Ljava/lang/Object;Ljava/lang/String;)Ljava/lang/Object;
       7: pop
       8: new           #292                // class io/reactivex/rxjava3/internal/operators/single/SingleDoOnTerminate
      11: dup
      12: aload_0
      13: aload_1
      14: invokespecial #293                // Method io/reactivex/rxjava3/internal/operators/single/SingleDoOnTerminate."<init>":(Lio/reactivex/rxjava3/core/SingleSource;Lio/reactivex/rxjava3/functions/Action;)V
      17: invokestatic  #294                // Method io/reactivex/rxjava3/plugins/RxJavaPlugins.onAssembly:(Lio/reactivex/rxjava3/core/Single;)Lio/reactivex/rxjava3/core/Single;
      20: areturn

  public final io.reactivex.rxjava3.core.Single<T> doOnSuccess(io.reactivex.rxjava3.functions.Consumer<? super T>);
    Code:
       0: aload_1
       1: ldc_w         #295                // String onSuccess is null
       4: invokestatic  #3                  // Method java/util/Objects.requireNonNull:(Ljava/lang/Object;Ljava/lang/String;)Ljava/lang/Object;
       7: pop
       8: new           #296                // class io/reactivex/rxjava3/internal/operators/single/SingleDoOnSuccess
      11: dup
      12: aload_0
      13: aload_1
      14: invokespecial #297                // Method io/reactivex/rxjava3/internal/operators/single/SingleDoOnSuccess."<init>":(Lio/reactivex/rxjava3/core/SingleSource;Lio/reactivex/rxjava3/functions/Consumer;)V
      17: invokestatic  #298                // Method io/reactivex/rxjava3/plugins/RxJavaPlugins.onAssembly:(Lio/reactivex/rxjava3/core/Single;)Lio/reactivex/rxjava3/core/Single;
      20: areturn

  public final io.reactivex.rxjava3.core.Single<T> doOnEvent(io.reactivex.rxjava3.functions.BiConsumer<? super T, ? super java.lang.Throwable>);
    Code:
       0: aload_1
       1: ldc_w         #299                // String onEvent is null
       4: invokestatic  #3                  // Method java/util/Objects.requireNonNull:(Ljava/lang/Object;Ljava/lang/String;)Ljava/lang/Object;
       7: pop
       8: new           #300                // class io/reactivex/rxjava3/internal/operators/single/SingleDoOnEvent
      11: dup
      12: aload_0
      13: aload_1
      14: invokespecial #301                // Method io/reactivex/rxjava3/internal/operators/single/SingleDoOnEvent."<init>":(Lio/reactivex/rxjava3/core/SingleSource;Lio/reactivex/rxjava3/functions/BiConsumer;)V
      17: invokestatic  #302                // Method io/reactivex/rxjava3/plugins/RxJavaPlugins.onAssembly:(Lio/reactivex/rxjava3/core/Single;)Lio/reactivex/rxjava3/core/Single;
      20: areturn

  public final io.reactivex.rxjava3.core.Single<T> doOnError(io.reactivex.rxjava3.functions.Consumer<? super java.lang.Throwable>);
    Code:
       0: aload_1
       1: ldc_w         #303                // String onError is null
       4: invokestatic  #3                  // Method java/util/Objects.requireNonNull:(Ljava/lang/Object;Ljava/lang/String;)Ljava/lang/Object;
       7: pop
       8: new           #304                // class io/reactivex/rxjava3/internal/operators/single/SingleDoOnError
      11: dup
      12: aload_0
      13: aload_1
      14: invokespecial #305                // Method io/reactivex/rxjava3/internal/operators/single/SingleDoOnError."<init>":(Lio/reactivex/rxjava3/core/SingleSource;Lio/reactivex/rxjava3/functions/Consumer;)V
      17: invokestatic  #306                // Method io/reactivex/rxjava3/plugins/RxJavaPlugins.onAssembly:(Lio/reactivex/rxjava3/core/Single;)Lio/reactivex/rxjava3/core/Single;
      20: areturn

  public final io.reactivex.rxjava3.core.Single<T> doOnDispose(io.reactivex.rxjava3.functions.Action);
    Code:
       0: aload_1
       1: ldc_w         #284                // String onDispose is null
       4: invokestatic  #3                  // Method java/util/Objects.requireNonNull:(Ljava/lang/Object;Ljava/lang/String;)Ljava/lang/Object;
       7: pop
       8: new           #307                // class io/reactivex/rxjava3/internal/operators/single/SingleDoOnDispose
      11: dup
      12: aload_0
      13: aload_1
      14: invokespecial #308                // Method io/reactivex/rxjava3/internal/operators/single/SingleDoOnDispose."<init>":(Lio/reactivex/rxjava3/core/SingleSource;Lio/reactivex/rxjava3/functions/Action;)V
      17: invokestatic  #309                // Method io/reactivex/rxjava3/plugins/RxJavaPlugins.onAssembly:(Lio/reactivex/rxjava3/core/Single;)Lio/reactivex/rxjava3/core/Single;
      20: areturn

  public final io.reactivex.rxjava3.core.Maybe<T> filter(io.reactivex.rxjava3.functions.Predicate<? super T>);
    Code:
       0: aload_1
       1: ldc_w         #310                // String predicate is null
       4: invokestatic  #3                  // Method java/util/Objects.requireNonNull:(Ljava/lang/Object;Ljava/lang/String;)Ljava/lang/Object;
       7: pop
       8: new           #311                // class io/reactivex/rxjava3/internal/operators/maybe/MaybeFilterSingle
      11: dup
      12: aload_0
      13: aload_1
      14: invokespecial #312                // Method io/reactivex/rxjava3/internal/operators/maybe/MaybeFilterSingle."<init>":(Lio/reactivex/rxjava3/core/SingleSource;Lio/reactivex/rxjava3/functions/Predicate;)V
      17: invokestatic  #313                // Method io/reactivex/rxjava3/plugins/RxJavaPlugins.onAssembly:(Lio/reactivex/rxjava3/core/Maybe;)Lio/reactivex/rxjava3/core/Maybe;
      20: areturn

  public final <R> io.reactivex.rxjava3.core.Single<R> flatMap(io.reactivex.rxjava3.functions.Function<? super T, ? extends io.reactivex.rxjava3.core.SingleSource<? extends R>>);
    Code:
       0: aload_1
       1: ldc           #243                // String mapper is null
       3: invokestatic  #3                  // Method java/util/Objects.requireNonNull:(Ljava/lang/Object;Ljava/lang/String;)Ljava/lang/Object;
       6: pop
       7: new           #128                // class io/reactivex/rxjava3/internal/operators/single/SingleFlatMap
      10: dup
      11: aload_0
      12: aload_1
      13: invokespecial #130                // Method io/reactivex/rxjava3/internal/operators/single/SingleFlatMap."<init>":(Lio/reactivex/rxjava3/core/SingleSource;Lio/reactivex/rxjava3/functions/Function;)V
      16: invokestatic  #314                // Method io/reactivex/rxjava3/plugins/RxJavaPlugins.onAssembly:(Lio/reactivex/rxjava3/core/Single;)Lio/reactivex/rxjava3/core/Single;
      19: areturn

  public final <U, R> io.reactivex.rxjava3.core.Single<R> flatMap(io.reactivex.rxjava3.functions.Function<? super T, ? extends io.reactivex.rxjava3.core.SingleSource<? extends U>>, io.reactivex.rxjava3.functions.BiFunction<? super T, ? super U, ? extends R>);
    Code:
       0: aload_1
       1: ldc           #243                // String mapper is null
       3: invokestatic  #3                  // Method java/util/Objects.requireNonNull:(Ljava/lang/Object;Ljava/lang/String;)Ljava/lang/Object;
       6: pop
       7: aload_2
       8: ldc_w         #315                // String combiner is null
      11: invokestatic  #3                  // Method java/util/Objects.requireNonNull:(Ljava/lang/Object;Ljava/lang/String;)Ljava/lang/Object;
      14: pop
      15: new           #316                // class io/reactivex/rxjava3/internal/operators/single/SingleFlatMapBiSelector
      18: dup
      19: aload_0
      20: aload_1
      21: aload_2
      22: invokespecial #317                // Method io/reactivex/rxjava3/internal/operators/single/SingleFlatMapBiSelector."<init>":(Lio/reactivex/rxjava3/core/SingleSource;Lio/reactivex/rxjava3/functions/Function;Lio/reactivex/rxjava3/functions/BiFunction;)V
      25: invokestatic  #318                // Method io/reactivex/rxjava3/plugins/RxJavaPlugins.onAssembly:(Lio/reactivex/rxjava3/core/Single;)Lio/reactivex/rxjava3/core/Single;
      28: areturn

  public final <R> io.reactivex.rxjava3.core.Single<R> flatMap(io.reactivex.rxjava3.functions.Function<? super T, ? extends io.reactivex.rxjava3.core.SingleSource<? extends R>>, io.reactivex.rxjava3.functions.Function<? super java.lang.Throwable, ? extends io.reactivex.rxjava3.core.SingleSource<? extends R>>);
    Code:
       0: aload_1
       1: ldc_w         #319                // String onSuccessMapper is null
       4: invokestatic  #3                  // Method java/util/Objects.requireNonNull:(Ljava/lang/Object;Ljava/lang/String;)Ljava/lang/Object;
       7: pop
       8: aload_2
       9: ldc_w         #320                // String onErrorMapper is null
      12: invokestatic  #3                  // Method java/util/Objects.requireNonNull:(Ljava/lang/Object;Ljava/lang/String;)Ljava/lang/Object;
      15: pop
      16: new           #321                // class io/reactivex/rxjava3/internal/operators/single/SingleFlatMapNotification
      19: dup
      20: aload_0
      21: aload_1
      22: aload_2
      23: invokespecial #322                // Method io/reactivex/rxjava3/internal/operators/single/SingleFlatMapNotification."<init>":(Lio/reactivex/rxjava3/core/SingleSource;Lio/reactivex/rxjava3/functions/Function;Lio/reactivex/rxjava3/functions/Function;)V
      26: invokestatic  #323                // Method io/reactivex/rxjava3/plugins/RxJavaPlugins.onAssembly:(Lio/reactivex/rxjava3/core/Single;)Lio/reactivex/rxjava3/core/Single;
      29: areturn

  public final <R> io.reactivex.rxjava3.core.Maybe<R> flatMapMaybe(io.reactivex.rxjava3.functions.Function<? super T, ? extends io.reactivex.rxjava3.core.MaybeSource<? extends R>>);
    Code:
       0: aload_1
       1: ldc           #243                // String mapper is null
       3: invokestatic  #3                  // Method java/util/Objects.requireNonNull:(Ljava/lang/Object;Ljava/lang/String;)Ljava/lang/Object;
       6: pop
       7: new           #324                // class io/reactivex/rxjava3/internal/operators/single/SingleFlatMapMaybe
      10: dup
      11: aload_0
      12: aload_1
      13: invokespecial #325                // Method io/reactivex/rxjava3/internal/operators/single/SingleFlatMapMaybe."<init>":(Lio/reactivex/rxjava3/core/SingleSource;Lio/reactivex/rxjava3/functions/Function;)V
      16: invokestatic  #326                // Method io/reactivex/rxjava3/plugins/RxJavaPlugins.onAssembly:(Lio/reactivex/rxjava3/core/Maybe;)Lio/reactivex/rxjava3/core/Maybe;
      19: areturn

  public final <R> io.reactivex.rxjava3.core.Flowable<R> flatMapPublisher(io.reactivex.rxjava3.functions.Function<? super T, ? extends org.reactivestreams.Publisher<? extends R>>);
    Code:
       0: aload_1
       1: ldc           #243                // String mapper is null
       3: invokestatic  #3                  // Method java/util/Objects.requireNonNull:(Ljava/lang/Object;Ljava/lang/String;)Ljava/lang/Object;
       6: pop
       7: new           #327                // class io/reactivex/rxjava3/internal/operators/single/SingleFlatMapPublisher
      10: dup
      11: aload_0
      12: aload_1
      13: invokespecial #328                // Method io/reactivex/rxjava3/internal/operators/single/SingleFlatMapPublisher."<init>":(Lio/reactivex/rxjava3/core/SingleSource;Lio/reactivex/rxjava3/functions/Function;)V
      16: invokestatic  #329                // Method io/reactivex/rxjava3/plugins/RxJavaPlugins.onAssembly:(Lio/reactivex/rxjava3/core/Flowable;)Lio/reactivex/rxjava3/core/Flowable;
      19: areturn

  public final <U> io.reactivex.rxjava3.core.Flowable<U> flattenAsFlowable(io.reactivex.rxjava3.functions.Function<? super T, ? extends java.lang.Iterable<? extends U>>);
    Code:
       0: aload_1
       1: ldc           #243                // String mapper is null
       3: invokestatic  #3                  // Method java/util/Objects.requireNonNull:(Ljava/lang/Object;Ljava/lang/String;)Ljava/lang/Object;
       6: pop
       7: new           #330                // class io/reactivex/rxjava3/internal/operators/single/SingleFlatMapIterableFlowable
      10: dup
      11: aload_0
      12: aload_1
      13: invokespecial #331                // Method io/reactivex/rxjava3/internal/operators/single/SingleFlatMapIterableFlowable."<init>":(Lio/reactivex/rxjava3/core/SingleSource;Lio/reactivex/rxjava3/functions/Function;)V
      16: invokestatic  #332                // Method io/reactivex/rxjava3/plugins/RxJavaPlugins.onAssembly:(Lio/reactivex/rxjava3/core/Flowable;)Lio/reactivex/rxjava3/core/Flowable;
      19: areturn

  public final <U> io.reactivex.rxjava3.core.Observable<U> flattenAsObservable(io.reactivex.rxjava3.functions.Function<? super T, ? extends java.lang.Iterable<? extends U>>);
    Code:
       0: aload_1
       1: ldc           #243                // String mapper is null
       3: invokestatic  #3                  // Method java/util/Objects.requireNonNull:(Ljava/lang/Object;Ljava/lang/String;)Ljava/lang/Object;
       6: pop
       7: new           #333                // class io/reactivex/rxjava3/internal/operators/single/SingleFlatMapIterableObservable
      10: dup
      11: aload_0
      12: aload_1
      13: invokespecial #334                // Method io/reactivex/rxjava3/internal/operators/single/SingleFlatMapIterableObservable."<init>":(Lio/reactivex/rxjava3/core/SingleSource;Lio/reactivex/rxjava3/functions/Function;)V
      16: invokestatic  #335                // Method io/reactivex/rxjava3/plugins/RxJavaPlugins.onAssembly:(Lio/reactivex/rxjava3/core/Observable;)Lio/reactivex/rxjava3/core/Observable;
      19: areturn

  public final <R> io.reactivex.rxjava3.core.Observable<R> flatMapObservable(io.reactivex.rxjava3.functions.Function<? super T, ? extends io.reactivex.rxjava3.core.ObservableSource<? extends R>>);
    Code:
       0: aload_1
       1: ldc           #243                // String mapper is null
       3: invokestatic  #3                  // Method java/util/Objects.requireNonNull:(Ljava/lang/Object;Ljava/lang/String;)Ljava/lang/Object;
       6: pop
       7: new           #336                // class io/reactivex/rxjava3/internal/operators/mixed/SingleFlatMapObservable
      10: dup
      11: aload_0
      12: aload_1
      13: invokespecial #337                // Method io/reactivex/rxjava3/internal/operators/mixed/SingleFlatMapObservable."<init>":(Lio/reactivex/rxjava3/core/SingleSource;Lio/reactivex/rxjava3/functions/Function;)V
      16: invokestatic  #338                // Method io/reactivex/rxjava3/plugins/RxJavaPlugins.onAssembly:(Lio/reactivex/rxjava3/core/Observable;)Lio/reactivex/rxjava3/core/Observable;
      19: areturn

  public final io.reactivex.rxjava3.core.Completable flatMapCompletable(io.reactivex.rxjava3.functions.Function<? super T, ? extends io.reactivex.rxjava3.core.CompletableSource>);
    Code:
       0: aload_1
       1: ldc           #243                // String mapper is null
       3: invokestatic  #3                  // Method java/util/Objects.requireNonNull:(Ljava/lang/Object;Ljava/lang/String;)Ljava/lang/Object;
       6: pop
       7: new           #339                // class io/reactivex/rxjava3/internal/operators/single/SingleFlatMapCompletable
      10: dup
      11: aload_0
      12: aload_1
      13: invokespecial #340                // Method io/reactivex/rxjava3/internal/operators/single/SingleFlatMapCompletable."<init>":(Lio/reactivex/rxjava3/core/SingleSource;Lio/reactivex/rxjava3/functions/Function;)V
      16: invokestatic  #341                // Method io/reactivex/rxjava3/plugins/RxJavaPlugins.onAssembly:(Lio/reactivex/rxjava3/core/Completable;)Lio/reactivex/rxjava3/core/Completable;
      19: areturn

  public final T blockingGet();
    Code:
       0: new           #342                // class io/reactivex/rxjava3/internal/observers/BlockingMultiObserver
       3: dup
       4: invokespecial #343                // Method io/reactivex/rxjava3/internal/observers/BlockingMultiObserver."<init>":()V
       7: astore_1
       8: aload_0
       9: aload_1
      10: invokevirtual #344                // Method subscribe:(Lio/reactivex/rxjava3/core/SingleObserver;)V
      13: aload_1
      14: invokevirtual #345                // Method io/reactivex/rxjava3/internal/observers/BlockingMultiObserver.blockingGet:()Ljava/lang/Object;
      17: areturn

  public final void blockingSubscribe();
    Code:
       0: aload_0
       1: invokestatic  #346                // Method io/reactivex/rxjava3/internal/functions/Functions.emptyConsumer:()Lio/reactivex/rxjava3/functions/Consumer;
       4: getstatic     #347                // Field io/reactivex/rxjava3/internal/functions/Functions.ERROR_CONSUMER:Lio/reactivex/rxjava3/functions/Consumer;
       7: invokevirtual #348                // Method blockingSubscribe:(Lio/reactivex/rxjava3/functions/Consumer;Lio/reactivex/rxjava3/functions/Consumer;)V
      10: return

  public final void blockingSubscribe(io.reactivex.rxjava3.functions.Consumer<? super T>);
    Code:
       0: aload_0
       1: aload_1
       2: getstatic     #347                // Field io/reactivex/rxjava3/internal/functions/Functions.ERROR_CONSUMER:Lio/reactivex/rxjava3/functions/Consumer;
       5: invokevirtual #348                // Method blockingSubscribe:(Lio/reactivex/rxjava3/functions/Consumer;Lio/reactivex/rxjava3/functions/Consumer;)V
       8: return

  public final void blockingSubscribe(io.reactivex.rxjava3.functions.Consumer<? super T>, io.reactivex.rxjava3.functions.Consumer<? super java.lang.Throwable>);
    Code:
       0: aload_1
       1: ldc_w         #295                // String onSuccess is null
       4: invokestatic  #3                  // Method java/util/Objects.requireNonNull:(Ljava/lang/Object;Ljava/lang/String;)Ljava/lang/Object;
       7: pop
       8: aload_2
       9: ldc_w         #303                // String onError is null
      12: invokestatic  #3                  // Method java/util/Objects.requireNonNull:(Ljava/lang/Object;Ljava/lang/String;)Ljava/lang/Object;
      15: pop
      16: new           #342                // class io/reactivex/rxjava3/internal/observers/BlockingMultiObserver
      19: dup
      20: invokespecial #343                // Method io/reactivex/rxjava3/internal/observers/BlockingMultiObserver."<init>":()V
      23: astore_3
      24: aload_0
      25: aload_3
      26: invokevirtual #344                // Method subscribe:(Lio/reactivex/rxjava3/core/SingleObserver;)V
      29: aload_3
      30: aload_1
      31: aload_2
      32: getstatic     #349                // Field io/reactivex/rxjava3/internal/functions/Functions.EMPTY_ACTION:Lio/reactivex/rxjava3/functions/Action;
      35: invokevirtual #350                // Method io/reactivex/rxjava3/internal/observers/BlockingMultiObserver.blockingConsume:(Lio/reactivex/rxjava3/functions/Consumer;Lio/reactivex/rxjava3/functions/Consumer;Lio/reactivex/rxjava3/functions/Action;)V
      38: return

  public final void blockingSubscribe(io.reactivex.rxjava3.core.SingleObserver<? super T>);
    Code:
       0: aload_1
       1: ldc_w         #351                // String observer is null
       4: invokestatic  #3                  // Method java/util/Objects.requireNonNull:(Ljava/lang/Object;Ljava/lang/String;)Ljava/lang/Object;
       7: pop
       8: new           #352                // class io/reactivex/rxjava3/internal/observers/BlockingDisposableMultiObserver
      11: dup
      12: invokespecial #353                // Method io/reactivex/rxjava3/internal/observers/BlockingDisposableMultiObserver."<init>":()V
      15: astore_2
      16: aload_1
      17: aload_2
      18: invokeinterface #354,  2          // InterfaceMethod io/reactivex/rxjava3/core/SingleObserver.onSubscribe:(Lio/reactivex/rxjava3/disposables/Disposable;)V
      23: aload_0
      24: aload_2
      25: invokevirtual #344                // Method subscribe:(Lio/reactivex/rxjava3/core/SingleObserver;)V
      28: aload_2
      29: aload_1
      30: invokevirtual #355                // Method io/reactivex/rxjava3/internal/observers/BlockingDisposableMultiObserver.blockingConsume:(Lio/reactivex/rxjava3/core/SingleObserver;)V
      33: return

  public final <R> io.reactivex.rxjava3.core.Single<R> lift(io.reactivex.rxjava3.core.SingleOperator<? extends R, ? super T>);
    Code:
       0: aload_1
       1: ldc_w         #356                // String lift is null
       4: invokestatic  #3                  // Method java/util/Objects.requireNonNull:(Ljava/lang/Object;Ljava/lang/String;)Ljava/lang/Object;
       7: pop
       8: new           #357                // class io/reactivex/rxjava3/internal/operators/single/SingleLift
      11: dup
      12: aload_0
      13: aload_1
      14: invokespecial #358                // Method io/reactivex/rxjava3/internal/operators/single/SingleLift."<init>":(Lio/reactivex/rxjava3/core/SingleSource;Lio/reactivex/rxjava3/core/SingleOperator;)V
      17: invokestatic  #359                // Method io/reactivex/rxjava3/plugins/RxJavaPlugins.onAssembly:(Lio/reactivex/rxjava3/core/Single;)Lio/reactivex/rxjava3/core/Single;
      20: areturn

  public final <R> io.reactivex.rxjava3.core.Single<R> map(io.reactivex.rxjava3.functions.Function<? super T, ? extends R>);
    Code:
       0: aload_1
       1: ldc           #243                // String mapper is null
       3: invokestatic  #3                  // Method java/util/Objects.requireNonNull:(Ljava/lang/Object;Ljava/lang/String;)Ljava/lang/Object;
       6: pop
       7: new           #360                // class io/reactivex/rxjava3/internal/operators/single/SingleMap
      10: dup
      11: aload_0
      12: aload_1
      13: invokespecial #361                // Method io/reactivex/rxjava3/internal/operators/single/SingleMap."<init>":(Lio/reactivex/rxjava3/core/SingleSource;Lio/reactivex/rxjava3/functions/Function;)V
      16: invokestatic  #362                // Method io/reactivex/rxjava3/plugins/RxJavaPlugins.onAssembly:(Lio/reactivex/rxjava3/core/Single;)Lio/reactivex/rxjava3/core/Single;
      19: areturn

  public final io.reactivex.rxjava3.core.Single<io.reactivex.rxjava3.core.Notification<T>> materialize();
    Code:
       0: new           #363                // class io/reactivex/rxjava3/internal/operators/single/SingleMaterialize
       3: dup
       4: aload_0
       5: invokespecial #364                // Method io/reactivex/rxjava3/internal/operators/single/SingleMaterialize."<init>":(Lio/reactivex/rxjava3/core/Single;)V
       8: invokestatic  #365                // Method io/reactivex/rxjava3/plugins/RxJavaPlugins.onAssembly:(Lio/reactivex/rxjava3/core/Single;)Lio/reactivex/rxjava3/core/Single;
      11: areturn

  public final io.reactivex.rxjava3.core.Single<java.lang.Boolean> contains(java.lang.Object);
    Code:
       0: aload_0
       1: aload_1
       2: invokestatic  #366                // Method io/reactivex/rxjava3/internal/functions/ObjectHelper.equalsPredicate:()Lio/reactivex/rxjava3/functions/BiPredicate;
       5: invokevirtual #367                // Method contains:(Ljava/lang/Object;Lio/reactivex/rxjava3/functions/BiPredicate;)Lio/reactivex/rxjava3/core/Single;
       8: areturn

  public final io.reactivex.rxjava3.core.Single<java.lang.Boolean> contains(java.lang.Object, io.reactivex.rxjava3.functions.BiPredicate<java.lang.Object, java.lang.Object>);
    Code:
       0: aload_1
       1: ldc           #115                // String item is null
       3: invokestatic  #3                  // Method java/util/Objects.requireNonNull:(Ljava/lang/Object;Ljava/lang/String;)Ljava/lang/Object;
       6: pop
       7: aload_2
       8: ldc_w         #368                // String comparer is null
      11: invokestatic  #3                  // Method java/util/Objects.requireNonNull:(Ljava/lang/Object;Ljava/lang/String;)Ljava/lang/Object;
      14: pop
      15: new           #369                // class io/reactivex/rxjava3/internal/operators/single/SingleContains
      18: dup
      19: aload_0
      20: aload_1
      21: aload_2
      22: invokespecial #370                // Method io/reactivex/rxjava3/internal/operators/single/SingleContains."<init>":(Lio/reactivex/rxjava3/core/SingleSource;Ljava/lang/Object;Lio/reactivex/rxjava3/functions/BiPredicate;)V
      25: invokestatic  #371                // Method io/reactivex/rxjava3/plugins/RxJavaPlugins.onAssembly:(Lio/reactivex/rxjava3/core/Single;)Lio/reactivex/rxjava3/core/Single;
      28: areturn

  public final io.reactivex.rxjava3.core.Flowable<T> mergeWith(io.reactivex.rxjava3.core.SingleSource<? extends T>);
    Code:
       0: aload_0
       1: aload_1
       2: invokestatic  #372                // Method merge:(Lio/reactivex/rxjava3/core/SingleSource;Lio/reactivex/rxjava3/core/SingleSource;)Lio/reactivex/rxjava3/core/Flowable;
       5: areturn

  public final <U> io.reactivex.rxjava3.core.Maybe<U> ofType(java.lang.Class<U>);
    Code:
       0: aload_1
       1: ldc           #240                // String clazz is null
       3: invokestatic  #3                  // Method java/util/Objects.requireNonNull:(Ljava/lang/Object;Ljava/lang/String;)Ljava/lang/Object;
       6: pop
       7: aload_0
       8: aload_1
       9: invokestatic  #373                // Method io/reactivex/rxjava3/internal/functions/Functions.isInstanceOf:(Ljava/lang/Class;)Lio/reactivex/rxjava3/functions/Predicate;
      12: invokevirtual #374                // Method filter:(Lio/reactivex/rxjava3/functions/Predicate;)Lio/reactivex/rxjava3/core/Maybe;
      15: aload_1
      16: invokevirtual #375                // Method io/reactivex/rxjava3/core/Maybe.cast:(Ljava/lang/Class;)Lio/reactivex/rxjava3/core/Maybe;
      19: areturn

  public final io.reactivex.rxjava3.core.Single<T> observeOn(io.reactivex.rxjava3.core.Scheduler);
    Code:
       0: aload_1
       1: ldc           #167                // String scheduler is null
       3: invokestatic  #3                  // Method java/util/Objects.requireNonNull:(Ljava/lang/Object;Ljava/lang/String;)Ljava/lang/Object;
       6: pop
       7: new           #376                // class io/reactivex/rxjava3/internal/operators/single/SingleObserveOn
      10: dup
      11: aload_0
      12: aload_1
      13: invokespecial #377                // Method io/reactivex/rxjava3/internal/operators/single/SingleObserveOn."<init>":(Lio/reactivex/rxjava3/core/SingleSource;Lio/reactivex/rxjava3/core/Scheduler;)V
      16: invokestatic  #378                // Method io/reactivex/rxjava3/plugins/RxJavaPlugins.onAssembly:(Lio/reactivex/rxjava3/core/Single;)Lio/reactivex/rxjava3/core/Single;
      19: areturn

  public final io.reactivex.rxjava3.core.Single<T> onErrorReturn(io.reactivex.rxjava3.functions.Function<java.lang.Throwable, ? extends T>);
    Code:
       0: aload_1
       1: ldc_w         #379                // String itemSupplier is null
       4: invokestatic  #3                  // Method java/util/Objects.requireNonNull:(Ljava/lang/Object;Ljava/lang/String;)Ljava/lang/Object;
       7: pop
       8: new           #380                // class io/reactivex/rxjava3/internal/operators/single/SingleOnErrorReturn
      11: dup
      12: aload_0
      13: aload_1
      14: aconst_null
      15: invokespecial #381                // Method io/reactivex/rxjava3/internal/operators/single/SingleOnErrorReturn."<init>":(Lio/reactivex/rxjava3/core/SingleSource;Lio/reactivex/rxjava3/functions/Function;Ljava/lang/Object;)V
      18: invokestatic  #382                // Method io/reactivex/rxjava3/plugins/RxJavaPlugins.onAssembly:(Lio/reactivex/rxjava3/core/Single;)Lio/reactivex/rxjava3/core/Single;
      21: areturn

  public final io.reactivex.rxjava3.core.Single<T> onErrorReturnItem(T);
    Code:
       0: aload_1
       1: ldc           #115                // String item is null
       3: invokestatic  #3                  // Method java/util/Objects.requireNonNull:(Ljava/lang/Object;Ljava/lang/String;)Ljava/lang/Object;
       6: pop
       7: new           #380                // class io/reactivex/rxjava3/internal/operators/single/SingleOnErrorReturn
      10: dup
      11: aload_0
      12: aconst_null
      13: aload_1
      14: invokespecial #381                // Method io/reactivex/rxjava3/internal/operators/single/SingleOnErrorReturn."<init>":(Lio/reactivex/rxjava3/core/SingleSource;Lio/reactivex/rxjava3/functions/Function;Ljava/lang/Object;)V
      17: invokestatic  #383                // Method io/reactivex/rxjava3/plugins/RxJavaPlugins.onAssembly:(Lio/reactivex/rxjava3/core/Single;)Lio/reactivex/rxjava3/core/Single;
      20: areturn

  public final io.reactivex.rxjava3.core.Single<T> onErrorResumeWith(io.reactivex.rxjava3.core.SingleSource<? extends T>);
    Code:
       0: aload_1
       1: ldc_w         #384                // String fallback is null
       4: invokestatic  #3                  // Method java/util/Objects.requireNonNull:(Ljava/lang/Object;Ljava/lang/String;)Ljava/lang/Object;
       7: pop
       8: aload_0
       9: aload_1
      10: invokestatic  #385                // Method io/reactivex/rxjava3/internal/functions/Functions.justFunction:(Ljava/lang/Object;)Lio/reactivex/rxjava3/functions/Function;
      13: invokevirtual #386                // Method onErrorResumeNext:(Lio/reactivex/rxjava3/functions/Function;)Lio/reactivex/rxjava3/core/Single;
      16: areturn

  public final io.reactivex.rxjava3.core.Maybe<T> onErrorComplete();
    Code:
       0: aload_0
       1: invokestatic  #387                // Method io/reactivex/rxjava3/internal/functions/Functions.alwaysTrue:()Lio/reactivex/rxjava3/functions/Predicate;
       4: invokevirtual #388                // Method onErrorComplete:(Lio/reactivex/rxjava3/functions/Predicate;)Lio/reactivex/rxjava3/core/Maybe;
       7: areturn

  public final io.reactivex.rxjava3.core.Maybe<T> onErrorComplete(io.reactivex.rxjava3.functions.Predicate<? super java.lang.Throwable>);
    Code:
       0: aload_1
       1: ldc_w         #310                // String predicate is null
       4: invokestatic  #3                  // Method java/util/Objects.requireNonNull:(Ljava/lang/Object;Ljava/lang/String;)Ljava/lang/Object;
       7: pop
       8: new           #389                // class io/reactivex/rxjava3/internal/operators/single/SingleOnErrorComplete
      11: dup
      12: aload_0
      13: aload_1
      14: invokespecial #390                // Method io/reactivex/rxjava3/internal/operators/single/SingleOnErrorComplete."<init>":(Lio/reactivex/rxjava3/core/Single;Lio/reactivex/rxjava3/functions/Predicate;)V
      17: invokestatic  #391                // Method io/reactivex/rxjava3/plugins/RxJavaPlugins.onAssembly:(Lio/reactivex/rxjava3/core/Maybe;)Lio/reactivex/rxjava3/core/Maybe;
      20: areturn

  public final io.reactivex.rxjava3.core.Single<T> onErrorResumeNext(io.reactivex.rxjava3.functions.Function<? super java.lang.Throwable, ? extends io.reactivex.rxjava3.core.SingleSource<? extends T>>);
    Code:
       0: aload_1
       1: ldc_w         #392                // String fallbackSupplier is null
       4: invokestatic  #3                  // Method java/util/Objects.requireNonNull:(Ljava/lang/Object;Ljava/lang/String;)Ljava/lang/Object;
       7: pop
       8: new           #393                // class io/reactivex/rxjava3/internal/operators/single/SingleResumeNext
      11: dup
      12: aload_0
      13: aload_1
      14: invokespecial #394                // Method io/reactivex/rxjava3/internal/operators/single/SingleResumeNext."<init>":(Lio/reactivex/rxjava3/core/SingleSource;Lio/reactivex/rxjava3/functions/Function;)V
      17: invokestatic  #395                // Method io/reactivex/rxjava3/plugins/RxJavaPlugins.onAssembly:(Lio/reactivex/rxjava3/core/Single;)Lio/reactivex/rxjava3/core/Single;
      20: areturn

  public final io.reactivex.rxjava3.core.Single<T> onTerminateDetach();
    Code:
       0: new           #396                // class io/reactivex/rxjava3/internal/operators/single/SingleDetach
       3: dup
       4: aload_0
       5: invokespecial #397                // Method io/reactivex/rxjava3/internal/operators/single/SingleDetach."<init>":(Lio/reactivex/rxjava3/core/SingleSource;)V
       8: invokestatic  #398                // Method io/reactivex/rxjava3/plugins/RxJavaPlugins.onAssembly:(Lio/reactivex/rxjava3/core/Single;)Lio/reactivex/rxjava3/core/Single;
      11: areturn

  public final io.reactivex.rxjava3.core.Flowable<T> repeat();
    Code:
       0: aload_0
       1: invokevirtual #399                // Method toFlowable:()Lio/reactivex/rxjava3/core/Flowable;
       4: invokevirtual #400                // Method io/reactivex/rxjava3/core/Flowable.repeat:()Lio/reactivex/rxjava3/core/Flowable;
       7: areturn

  public final io.reactivex.rxjava3.core.Flowable<T> repeat(long);
    Code:
       0: aload_0
       1: invokevirtual #399                // Method toFlowable:()Lio/reactivex/rxjava3/core/Flowable;
       4: lload_1
       5: invokevirtual #401                // Method io/reactivex/rxjava3/core/Flowable.repeat:(J)Lio/reactivex/rxjava3/core/Flowable;
       8: areturn

  public final io.reactivex.rxjava3.core.Flowable<T> repeatWhen(io.reactivex.rxjava3.functions.Function<? super io.reactivex.rxjava3.core.Flowable<java.lang.Object>, ? extends org.reactivestreams.Publisher<?>>);
    Code:
       0: aload_0
       1: invokevirtual #399                // Method toFlowable:()Lio/reactivex/rxjava3/core/Flowable;
       4: aload_1
       5: invokevirtual #402                // Method io/reactivex/rxjava3/core/Flowable.repeatWhen:(Lio/reactivex/rxjava3/functions/Function;)Lio/reactivex/rxjava3/core/Flowable;
       8: areturn

  public final io.reactivex.rxjava3.core.Flowable<T> repeatUntil(io.reactivex.rxjava3.functions.BooleanSupplier);
    Code:
       0: aload_0
       1: invokevirtual #399                // Method toFlowable:()Lio/reactivex/rxjava3/core/Flowable;
       4: aload_1
       5: invokevirtual #403                // Method io/reactivex/rxjava3/core/Flowable.repeatUntil:(Lio/reactivex/rxjava3/functions/BooleanSupplier;)Lio/reactivex/rxjava3/core/Flowable;
       8: areturn

  public final io.reactivex.rxjava3.core.Single<T> retry();
    Code:
       0: aload_0
       1: invokevirtual #399                // Method toFlowable:()Lio/reactivex/rxjava3/core/Flowable;
       4: invokevirtual #404                // Method io/reactivex/rxjava3/core/Flowable.retry:()Lio/reactivex/rxjava3/core/Flowable;
       7: invokestatic  #405                // Method toSingle:(Lio/reactivex/rxjava3/core/Flowable;)Lio/reactivex/rxjava3/core/Single;
      10: areturn

  public final io.reactivex.rxjava3.core.Single<T> retry(long);
    Code:
       0: aload_0
       1: invokevirtual #399                // Method toFlowable:()Lio/reactivex/rxjava3/core/Flowable;
       4: lload_1
       5: invokevirtual #406                // Method io/reactivex/rxjava3/core/Flowable.retry:(J)Lio/reactivex/rxjava3/core/Flowable;
       8: invokestatic  #407                // Method toSingle:(Lio/reactivex/rxjava3/core/Flowable;)Lio/reactivex/rxjava3/core/Single;
      11: areturn

  public final io.reactivex.rxjava3.core.Single<T> retry(io.reactivex.rxjava3.functions.BiPredicate<? super java.lang.Integer, ? super java.lang.Throwable>);
    Code:
       0: aload_0
       1: invokevirtual #399                // Method toFlowable:()Lio/reactivex/rxjava3/core/Flowable;
       4: aload_1
       5: invokevirtual #408                // Method io/reactivex/rxjava3/core/Flowable.retry:(Lio/reactivex/rxjava3/functions/BiPredicate;)Lio/reactivex/rxjava3/core/Flowable;
       8: invokestatic  #409                // Method toSingle:(Lio/reactivex/rxjava3/core/Flowable;)Lio/reactivex/rxjava3/core/Single;
      11: areturn

  public final io.reactivex.rxjava3.core.Single<T> retry(long, io.reactivex.rxjava3.functions.Predicate<? super java.lang.Throwable>);
    Code:
       0: aload_0
       1: invokevirtual #399                // Method toFlowable:()Lio/reactivex/rxjava3/core/Flowable;
       4: lload_1
       5: aload_3
       6: invokevirtual #410                // Method io/reactivex/rxjava3/core/Flowable.retry:(JLio/reactivex/rxjava3/functions/Predicate;)Lio/reactivex/rxjava3/core/Flowable;
       9: invokestatic  #411                // Method toSingle:(Lio/reactivex/rxjava3/core/Flowable;)Lio/reactivex/rxjava3/core/Single;
      12: areturn

  public final io.reactivex.rxjava3.core.Single<T> retry(io.reactivex.rxjava3.functions.Predicate<? super java.lang.Throwable>);
    Code:
       0: aload_0
       1: invokevirtual #399                // Method toFlowable:()Lio/reactivex/rxjava3/core/Flowable;
       4: aload_1
       5: invokevirtual #412                // Method io/reactivex/rxjava3/core/Flowable.retry:(Lio/reactivex/rxjava3/functions/Predicate;)Lio/reactivex/rxjava3/core/Flowable;
       8: invokestatic  #413                // Method toSingle:(Lio/reactivex/rxjava3/core/Flowable;)Lio/reactivex/rxjava3/core/Single;
      11: areturn

  public final io.reactivex.rxjava3.core.Single<T> retryUntil(io.reactivex.rxjava3.functions.BooleanSupplier);
    Code:
       0: aload_1
       1: ldc_w         #414                // String stop is null
       4: invokestatic  #3                  // Method java/util/Objects.requireNonNull:(Ljava/lang/Object;Ljava/lang/String;)Ljava/lang/Object;
       7: pop
       8: aload_0
       9: ldc2_w        #416                // long 9223372036854775807l
      12: aload_1
      13: invokestatic  #418                // Method io/reactivex/rxjava3/internal/functions/Functions.predicateReverseFor:(Lio/reactivex/rxjava3/functions/BooleanSupplier;)Lio/reactivex/rxjava3/functions/Predicate;
      16: invokevirtual #419                // Method retry:(JLio/reactivex/rxjava3/functions/Predicate;)Lio/reactivex/rxjava3/core/Single;
      19: areturn

  public final io.reactivex.rxjava3.core.Single<T> retryWhen(io.reactivex.rxjava3.functions.Function<? super io.reactivex.rxjava3.core.Flowable<java.lang.Throwable>, ? extends org.reactivestreams.Publisher<?>>);
    Code:
       0: aload_0
       1: invokevirtual #399                // Method toFlowable:()Lio/reactivex/rxjava3/core/Flowable;
       4: aload_1
       5: invokevirtual #420                // Method io/reactivex/rxjava3/core/Flowable.retryWhen:(Lio/reactivex/rxjava3/functions/Function;)Lio/reactivex/rxjava3/core/Flowable;
       8: invokestatic  #421                // Method toSingle:(Lio/reactivex/rxjava3/core/Flowable;)Lio/reactivex/rxjava3/core/Single;
      11: areturn

  public final void safeSubscribe(io.reactivex.rxjava3.core.SingleObserver<? super T>);
    Code:
       0: aload_1
       1: ldc_w         #351                // String observer is null
       4: invokestatic  #3                  // Method java/util/Objects.requireNonNull:(Ljava/lang/Object;Ljava/lang/String;)Ljava/lang/Object;
       7: pop
       8: aload_0
       9: new           #422                // class io/reactivex/rxjava3/internal/observers/SafeSingleObserver
      12: dup
      13: aload_1
      14: invokespecial #423                // Method io/reactivex/rxjava3/internal/observers/SafeSingleObserver."<init>":(Lio/reactivex/rxjava3/core/SingleObserver;)V
      17: invokevirtual #344                // Method subscribe:(Lio/reactivex/rxjava3/core/SingleObserver;)V
      20: return

  public final io.reactivex.rxjava3.core.Flowable<T> startWith(io.reactivex.rxjava3.core.CompletableSource);
    Code:
       0: aload_1
       1: ldc           #228                // String other is null
       3: invokestatic  #3                  // Method java/util/Objects.requireNonNull:(Ljava/lang/Object;Ljava/lang/String;)Ljava/lang/Object;
       6: pop
       7: aload_1
       8: invokestatic  #424                // Method io/reactivex/rxjava3/core/Completable.wrap:(Lio/reactivex/rxjava3/core/CompletableSource;)Lio/reactivex/rxjava3/core/Completable;
      11: invokevirtual #425                // Method io/reactivex/rxjava3/core/Completable.toFlowable:()Lio/reactivex/rxjava3/core/Flowable;
      14: aload_0
      15: invokevirtual #399                // Method toFlowable:()Lio/reactivex/rxjava3/core/Flowable;
      18: invokestatic  #426                // Method io/reactivex/rxjava3/core/Flowable.concat:(Lorg/reactivestreams/Publisher;Lorg/reactivestreams/Publisher;)Lio/reactivex/rxjava3/core/Flowable;
      21: areturn

  public final io.reactivex.rxjava3.core.Flowable<T> startWith(io.reactivex.rxjava3.core.SingleSource<T>);
    Code:
       0: aload_1
       1: ldc           #228                // String other is null
       3: invokestatic  #3                  // Method java/util/Objects.requireNonNull:(Ljava/lang/Object;Ljava/lang/String;)Ljava/lang/Object;
       6: pop
       7: aload_1
       8: invokestatic  #427                // Method wrap:(Lio/reactivex/rxjava3/core/SingleSource;)Lio/reactivex/rxjava3/core/Single;
      11: invokevirtual #399                // Method toFlowable:()Lio/reactivex/rxjava3/core/Flowable;
      14: aload_0
      15: invokevirtual #399                // Method toFlowable:()Lio/reactivex/rxjava3/core/Flowable;
      18: invokestatic  #428                // Method io/reactivex/rxjava3/core/Flowable.concat:(Lorg/reactivestreams/Publisher;Lorg/reactivestreams/Publisher;)Lio/reactivex/rxjava3/core/Flowable;
      21: areturn

  public final io.reactivex.rxjava3.core.Flowable<T> startWith(io.reactivex.rxjava3.core.MaybeSource<T>);
    Code:
       0: aload_1
       1: ldc           #228                // String other is null
       3: invokestatic  #3                  // Method java/util/Objects.requireNonNull:(Ljava/lang/Object;Ljava/lang/String;)Ljava/lang/Object;
       6: pop
       7: aload_1
       8: invokestatic  #429                // Method io/reactivex/rxjava3/core/Maybe.wrap:(Lio/reactivex/rxjava3/core/MaybeSource;)Lio/reactivex/rxjava3/core/Maybe;
      11: invokevirtual #430                // Method io/reactivex/rxjava3/core/Maybe.toFlowable:()Lio/reactivex/rxjava3/core/Flowable;
      14: aload_0
      15: invokevirtual #399                // Method toFlowable:()Lio/reactivex/rxjava3/core/Flowable;
      18: invokestatic  #431                // Method io/reactivex/rxjava3/core/Flowable.concat:(Lorg/reactivestreams/Publisher;Lorg/reactivestreams/Publisher;)Lio/reactivex/rxjava3/core/Flowable;
      21: areturn

  public final io.reactivex.rxjava3.core.Observable<T> startWith(io.reactivex.rxjava3.core.ObservableSource<T>);
    Code:
       0: aload_1
       1: ldc           #228                // String other is null
       3: invokestatic  #3                  // Method java/util/Objects.requireNonNull:(Ljava/lang/Object;Ljava/lang/String;)Ljava/lang/Object;
       6: pop
       7: aload_1
       8: invokestatic  #432                // Method io/reactivex/rxjava3/core/Observable.wrap:(Lio/reactivex/rxjava3/core/ObservableSource;)Lio/reactivex/rxjava3/core/Observable;
      11: aload_0
      12: invokevirtual #433                // Method toObservable:()Lio/reactivex/rxjava3/core/Observable;
      15: invokevirtual #434                // Method io/reactivex/rxjava3/core/Observable.concatWith:(Lio/reactivex/rxjava3/core/ObservableSource;)Lio/reactivex/rxjava3/core/Observable;
      18: areturn

  public final io.reactivex.rxjava3.core.Flowable<T> startWith(org.reactivestreams.Publisher<T>);
    Code:
       0: aload_1
       1: ldc           #228                // String other is null
       3: invokestatic  #3                  // Method java/util/Objects.requireNonNull:(Ljava/lang/Object;Ljava/lang/String;)Ljava/lang/Object;
       6: pop
       7: aload_0
       8: invokevirtual #399                // Method toFlowable:()Lio/reactivex/rxjava3/core/Flowable;
      11: aload_1
      12: invokevirtual #435                // Method io/reactivex/rxjava3/core/Flowable.startWith:(Lorg/reactivestreams/Publisher;)Lio/reactivex/rxjava3/core/Flowable;
      15: areturn

  public final io.reactivex.rxjava3.disposables.Disposable subscribe();
    Code:
       0: aload_0
       1: invokestatic  #346                // Method io/reactivex/rxjava3/internal/functions/Functions.emptyConsumer:()Lio/reactivex/rxjava3/functions/Consumer;
       4: getstatic     #436                // Field io/reactivex/rxjava3/internal/functions/Functions.ON_ERROR_MISSING:Lio/reactivex/rxjava3/functions/Consumer;
       7: invokevirtual #437                // Method subscribe:(Lio/reactivex/rxjava3/functions/Consumer;Lio/reactivex/rxjava3/functions/Consumer;)Lio/reactivex/rxjava3/disposables/Disposable;
      10: areturn

  public final io.reactivex.rxjava3.disposables.Disposable subscribe(io.reactivex.rxjava3.functions.BiConsumer<? super T, ? super java.lang.Throwable>);
    Code:
       0: aload_1
       1: ldc_w         #438                // String onCallback is null
       4: invokestatic  #3                  // Method java/util/Objects.requireNonNull:(Ljava/lang/Object;Ljava/lang/String;)Ljava/lang/Object;
       7: pop
       8: new           #439                // class io/reactivex/rxjava3/internal/observers/BiConsumerSingleObserver
      11: dup
      12: aload_1
      13: invokespecial #440                // Method io/reactivex/rxjava3/internal/observers/BiConsumerSingleObserver."<init>":(Lio/reactivex/rxjava3/functions/BiConsumer;)V
      16: astore_2
      17: aload_0
      18: aload_2
      19: invokevirtual #344                // Method subscribe:(Lio/reactivex/rxjava3/core/SingleObserver;)V
      22: aload_2
      23: areturn

  public final io.reactivex.rxjava3.disposables.Disposable subscribe(io.reactivex.rxjava3.functions.Consumer<? super T>);
    Code:
       0: aload_0
       1: aload_1
       2: getstatic     #436                // Field io/reactivex/rxjava3/internal/functions/Functions.ON_ERROR_MISSING:Lio/reactivex/rxjava3/functions/Consumer;
       5: invokevirtual #437                // Method subscribe:(Lio/reactivex/rxjava3/functions/Consumer;Lio/reactivex/rxjava3/functions/Consumer;)Lio/reactivex/rxjava3/disposables/Disposable;
       8: areturn

  public final io.reactivex.rxjava3.disposables.Disposable subscribe(io.reactivex.rxjava3.functions.Consumer<? super T>, io.reactivex.rxjava3.functions.Consumer<? super java.lang.Throwable>);
    Code:
       0: aload_1
       1: ldc_w         #295                // String onSuccess is null
       4: invokestatic  #3                  // Method java/util/Objects.requireNonNull:(Ljava/lang/Object;Ljava/lang/String;)Ljava/lang/Object;
       7: pop
       8: aload_2
       9: ldc_w         #303                // String onError is null
      12: invokestatic  #3                  // Method java/util/Objects.requireNonNull:(Ljava/lang/Object;Ljava/lang/String;)Ljava/lang/Object;
      15: pop
      16: new           #441                // class io/reactivex/rxjava3/internal/observers/ConsumerSingleObserver
      19: dup
      20: aload_1
      21: aload_2
      22: invokespecial #442                // Method io/reactivex/rxjava3/internal/observers/ConsumerSingleObserver."<init>":(Lio/reactivex/rxjava3/functions/Consumer;Lio/reactivex/rxjava3/functions/Consumer;)V
      25: astore_3
      26: aload_0
      27: aload_3
      28: invokevirtual #344                // Method subscribe:(Lio/reactivex/rxjava3/core/SingleObserver;)V
      31: aload_3
      32: areturn

  public final io.reactivex.rxjava3.disposables.Disposable subscribe(io.reactivex.rxjava3.functions.Consumer<? super T>, io.reactivex.rxjava3.functions.Consumer<? super java.lang.Throwable>, io.reactivex.rxjava3.disposables.DisposableContainer);
    Code:
       0: aload_1
       1: ldc_w         #295                // String onSuccess is null
       4: invokestatic  #3                  // Method java/util/Objects.requireNonNull:(Ljava/lang/Object;Ljava/lang/String;)Ljava/lang/Object;
       7: pop
       8: aload_2
       9: ldc_w         #303                // String onError is null
      12: invokestatic  #3                  // Method java/util/Objects.requireNonNull:(Ljava/lang/Object;Ljava/lang/String;)Ljava/lang/Object;
      15: pop
      16: aload_3
      17: ldc_w         #443                // String container is null
      20: invokestatic  #3                  // Method java/util/Objects.requireNonNull:(Ljava/lang/Object;Ljava/lang/String;)Ljava/lang/Object;
      23: pop
      24: new           #444                // class io/reactivex/rxjava3/internal/observers/DisposableAutoReleaseMultiObserver
      27: dup
      28: aload_3
      29: aload_1
      30: aload_2
      31: getstatic     #349                // Field io/reactivex/rxjava3/internal/functions/Functions.EMPTY_ACTION:Lio/reactivex/rxjava3/functions/Action;
      34: invokespecial #445                // Method io/reactivex/rxjava3/internal/observers/DisposableAutoReleaseMultiObserver."<init>":(Lio/reactivex/rxjava3/disposables/DisposableContainer;Lio/reactivex/rxjava3/functions/Consumer;Lio/reactivex/rxjava3/functions/Consumer;Lio/reactivex/rxjava3/functions/Action;)V
      37: astore        4
      39: aload_3
      40: aload         4
      42: invokeinterface #446,  2          // InterfaceMethod io/reactivex/rxjava3/disposables/DisposableContainer.add:(Lio/reactivex/rxjava3/disposables/Disposable;)Z
      47: pop
      48: aload_0
      49: aload         4
      51: invokevirtual #344                // Method subscribe:(Lio/reactivex/rxjava3/core/SingleObserver;)V
      54: aload         4
      56: areturn

  public final void subscribe(io.reactivex.rxjava3.core.SingleObserver<? super T>);
    Code:
       0: aload_1
       1: ldc_w         #351                // String observer is null
       4: invokestatic  #3                  // Method java/util/Objects.requireNonNull:(Ljava/lang/Object;Ljava/lang/String;)Ljava/lang/Object;
       7: pop
       8: aload_0
       9: aload_1
      10: invokestatic  #447                // Method io/reactivex/rxjava3/plugins/RxJavaPlugins.onSubscribe:(Lio/reactivex/rxjava3/core/Single;Lio/reactivex/rxjava3/core/SingleObserver;)Lio/reactivex/rxjava3/core/SingleObserver;
      13: astore_1
      14: aload_1
      15: ldc_w         #448                // String The RxJavaPlugins.onSubscribe hook returned a null SingleObserver. Please check the handler provided to RxJavaPlugins.setOnSingleSubscribe for invalid null returns. Further reading: https://github.com/ReactiveX/RxJava/wiki/Plugins
      18: invokestatic  #3                  // Method java/util/Objects.requireNonNull:(Ljava/lang/Object;Ljava/lang/String;)Ljava/lang/Object;
      21: pop
      22: aload_0
      23: aload_1
      24: invokevirtual #449                // Method subscribeActual:(Lio/reactivex/rxjava3/core/SingleObserver;)V
      27: goto          57
      30: astore_2
      31: aload_2
      32: athrow
      33: astore_2
      34: aload_2
      35: invokestatic  #452                // Method io/reactivex/rxjava3/exceptions/Exceptions.throwIfFatal:(Ljava/lang/Throwable;)V
      38: new           #450                // class java/lang/NullPointerException
      41: dup
      42: ldc_w         #453                // String subscribeActual failed
      45: invokespecial #454                // Method java/lang/NullPointerException."<init>":(Ljava/lang/String;)V
      48: astore_3
      49: aload_3
      50: aload_2
      51: invokevirtual #455                // Method java/lang/NullPointerException.initCause:(Ljava/lang/Throwable;)Ljava/lang/Throwable;
      54: pop
      55: aload_3
      56: athrow
      57: return
    Exception table:
       from    to  target type
          22    27    30   Class java/lang/NullPointerException
          22    27    33   Class java/lang/Throwable

  protected abstract void subscribeActual(io.reactivex.rxjava3.core.SingleObserver<? super T>);

  public final <E extends io.reactivex.rxjava3.core.SingleObserver<? super T>> E subscribeWith(E);
    Code:
       0: aload_0
       1: aload_1
       2: invokevirtual #344                // Method subscribe:(Lio/reactivex/rxjava3/core/SingleObserver;)V
       5: aload_1
       6: areturn

  public final io.reactivex.rxjava3.core.Single<T> subscribeOn(io.reactivex.rxjava3.core.Scheduler);
    Code:
       0: aload_1
       1: ldc           #167                // String scheduler is null
       3: invokestatic  #3                  // Method java/util/Objects.requireNonNull:(Ljava/lang/Object;Ljava/lang/String;)Ljava/lang/Object;
       6: pop
       7: new           #456                // class io/reactivex/rxjava3/internal/operators/single/SingleSubscribeOn
      10: dup
      11: aload_0
      12: aload_1
      13: invokespecial #457                // Method io/reactivex/rxjava3/internal/operators/single/SingleSubscribeOn."<init>":(Lio/reactivex/rxjava3/core/SingleSource;Lio/reactivex/rxjava3/core/Scheduler;)V
      16: invokestatic  #458                // Method io/reactivex/rxjava3/plugins/RxJavaPlugins.onAssembly:(Lio/reactivex/rxjava3/core/Single;)Lio/reactivex/rxjava3/core/Single;
      19: areturn

  public final io.reactivex.rxjava3.core.Single<io.reactivex.rxjava3.schedulers.Timed<T>> timeInterval();
    Code:
       0: aload_0
       1: getstatic     #459                // Field java/util/concurrent/TimeUnit.MILLISECONDS:Ljava/util/concurrent/TimeUnit;
       4: invokestatic  #164                // Method io/reactivex/rxjava3/schedulers/Schedulers.computation:()Lio/reactivex/rxjava3/core/Scheduler;
       7: invokevirtual #460                // Method timeInterval:(Ljava/util/concurrent/TimeUnit;Lio/reactivex/rxjava3/core/Scheduler;)Lio/reactivex/rxjava3/core/Single;
      10: areturn

  public final io.reactivex.rxjava3.core.Single<io.reactivex.rxjava3.schedulers.Timed<T>> timeInterval(io.reactivex.rxjava3.core.Scheduler);
    Code:
       0: aload_0
       1: getstatic     #459                // Field java/util/concurrent/TimeUnit.MILLISECONDS:Ljava/util/concurrent/TimeUnit;
       4: aload_1
       5: invokevirtual #460                // Method timeInterval:(Ljava/util/concurrent/TimeUnit;Lio/reactivex/rxjava3/core/Scheduler;)Lio/reactivex/rxjava3/core/Single;
       8: areturn

  public final io.reactivex.rxjava3.core.Single<io.reactivex.rxjava3.schedulers.Timed<T>> timeInterval(java.util.concurrent.TimeUnit);
    Code:
       0: aload_0
       1: aload_1
       2: invokestatic  #164                // Method io/reactivex/rxjava3/schedulers/Schedulers.computation:()Lio/reactivex/rxjava3/core/Scheduler;
       5: invokevirtual #460                // Method timeInterval:(Ljava/util/concurrent/TimeUnit;Lio/reactivex/rxjava3/core/Scheduler;)Lio/reactivex/rxjava3/core/Single;
       8: areturn

  public final io.reactivex.rxjava3.core.Single<io.reactivex.rxjava3.schedulers.Timed<T>> timeInterval(java.util.concurrent.TimeUnit, io.reactivex.rxjava3.core.Scheduler);
    Code:
       0: aload_1
       1: ldc           #166                // String unit is null
       3: invokestatic  #3                  // Method java/util/Objects.requireNonNull:(Ljava/lang/Object;Ljava/lang/String;)Ljava/lang/Object;
       6: pop
       7: aload_2
       8: ldc           #167                // String scheduler is null
      10: invokestatic  #3                  // Method java/util/Objects.requireNonNull:(Ljava/lang/Object;Ljava/lang/String;)Ljava/lang/Object;
      13: pop
      14: new           #461                // class io/reactivex/rxjava3/internal/operators/single/SingleTimeInterval
      17: dup
      18: aload_0
      19: aload_1
      20: aload_2
      21: iconst_1
      22: invokespecial #462                // Method io/reactivex/rxjava3/internal/operators/single/SingleTimeInterval."<init>":(Lio/reactivex/rxjava3/core/SingleSource;Ljava/util/concurrent/TimeUnit;Lio/reactivex/rxjava3/core/Scheduler;Z)V
      25: invokestatic  #463                // Method io/reactivex/rxjava3/plugins/RxJavaPlugins.onAssembly:(Lio/reactivex/rxjava3/core/Single;)Lio/reactivex/rxjava3/core/Single;
      28: areturn

  public final io.reactivex.rxjava3.core.Single<io.reactivex.rxjava3.schedulers.Timed<T>> timestamp();
    Code:
       0: aload_0
       1: getstatic     #459                // Field java/util/concurrent/TimeUnit.MILLISECONDS:Ljava/util/concurrent/TimeUnit;
       4: invokestatic  #164                // Method io/reactivex/rxjava3/schedulers/Schedulers.computation:()Lio/reactivex/rxjava3/core/Scheduler;
       7: invokevirtual #464                // Method timestamp:(Ljava/util/concurrent/TimeUnit;Lio/reactivex/rxjava3/core/Scheduler;)Lio/reactivex/rxjava3/core/Single;
      10: areturn

  public final io.reactivex.rxjava3.core.Single<io.reactivex.rxjava3.schedulers.Timed<T>> timestamp(io.reactivex.rxjava3.core.Scheduler);
    Code:
       0: aload_0
       1: getstatic     #459                // Field java/util/concurrent/TimeUnit.MILLISECONDS:Ljava/util/concurrent/TimeUnit;
       4: aload_1
       5: invokevirtual #464                // Method timestamp:(Ljava/util/concurrent/TimeUnit;Lio/reactivex/rxjava3/core/Scheduler;)Lio/reactivex/rxjava3/core/Single;
       8: areturn

  public final io.reactivex.rxjava3.core.Single<io.reactivex.rxjava3.schedulers.Timed<T>> timestamp(java.util.concurrent.TimeUnit);
    Code:
       0: aload_0
       1: aload_1
       2: invokestatic  #164                // Method io/reactivex/rxjava3/schedulers/Schedulers.computation:()Lio/reactivex/rxjava3/core/Scheduler;
       5: invokevirtual #464                // Method timestamp:(Ljava/util/concurrent/TimeUnit;Lio/reactivex/rxjava3/core/Scheduler;)Lio/reactivex/rxjava3/core/Single;
       8: areturn

  public final io.reactivex.rxjava3.core.Single<io.reactivex.rxjava3.schedulers.Timed<T>> timestamp(java.util.concurrent.TimeUnit, io.reactivex.rxjava3.core.Scheduler);
    Code:
       0: aload_1
       1: ldc           #166                // String unit is null
       3: invokestatic  #3                  // Method java/util/Objects.requireNonNull:(Ljava/lang/Object;Ljava/lang/String;)Ljava/lang/Object;
       6: pop
       7: aload_2
       8: ldc           #167                // String scheduler is null
      10: invokestatic  #3                  // Method java/util/Objects.requireNonNull:(Ljava/lang/Object;Ljava/lang/String;)Ljava/lang/Object;
      13: pop
      14: new           #461                // class io/reactivex/rxjava3/internal/operators/single/SingleTimeInterval
      17: dup
      18: aload_0
      19: aload_1
      20: aload_2
      21: iconst_0
      22: invokespecial #462                // Method io/reactivex/rxjava3/internal/operators/single/SingleTimeInterval."<init>":(Lio/reactivex/rxjava3/core/SingleSource;Ljava/util/concurrent/TimeUnit;Lio/reactivex/rxjava3/core/Scheduler;Z)V
      25: invokestatic  #465                // Method io/reactivex/rxjava3/plugins/RxJavaPlugins.onAssembly:(Lio/reactivex/rxjava3/core/Single;)Lio/reactivex/rxjava3/core/Single;
      28: areturn

  public final io.reactivex.rxjava3.core.Single<T> takeUntil(io.reactivex.rxjava3.core.CompletableSource);
    Code:
       0: aload_1
       1: ldc           #228                // String other is null
       3: invokestatic  #3                  // Method java/util/Objects.requireNonNull:(Ljava/lang/Object;Ljava/lang/String;)Ljava/lang/Object;
       6: pop
       7: aload_0
       8: new           #466                // class io/reactivex/rxjava3/internal/operators/completable/CompletableToFlowable
      11: dup
      12: aload_1
      13: invokespecial #467                // Method io/reactivex/rxjava3/internal/operators/completable/CompletableToFlowable."<init>":(Lio/reactivex/rxjava3/core/CompletableSource;)V
      16: invokevirtual #468                // Method takeUntil:(Lorg/reactivestreams/Publisher;)Lio/reactivex/rxjava3/core/Single;
      19: areturn

  public final <E> io.reactivex.rxjava3.core.Single<T> takeUntil(org.reactivestreams.Publisher<E>);
    Code:
       0: aload_1
       1: ldc           #228                // String other is null
       3: invokestatic  #3                  // Method java/util/Objects.requireNonNull:(Ljava/lang/Object;Ljava/lang/String;)Ljava/lang/Object;
       6: pop
       7: new           #469                // class io/reactivex/rxjava3/internal/operators/single/SingleTakeUntil
      10: dup
      11: aload_0
      12: aload_1
      13: invokespecial #470                // Method io/reactivex/rxjava3/internal/operators/single/SingleTakeUntil."<init>":(Lio/reactivex/rxjava3/core/SingleSource;Lorg/reactivestreams/Publisher;)V
      16: invokestatic  #471                // Method io/reactivex/rxjava3/plugins/RxJavaPlugins.onAssembly:(Lio/reactivex/rxjava3/core/Single;)Lio/reactivex/rxjava3/core/Single;
      19: areturn

  public final <E> io.reactivex.rxjava3.core.Single<T> takeUntil(io.reactivex.rxjava3.core.SingleSource<? extends E>);
    Code:
       0: aload_1
       1: ldc           #228                // String other is null
       3: invokestatic  #3                  // Method java/util/Objects.requireNonNull:(Ljava/lang/Object;Ljava/lang/String;)Ljava/lang/Object;
       6: pop
       7: aload_0
       8: new           #472                // class io/reactivex/rxjava3/internal/operators/single/SingleToFlowable
      11: dup
      12: aload_1
      13: invokespecial #473                // Method io/reactivex/rxjava3/internal/operators/single/SingleToFlowable."<init>":(Lio/reactivex/rxjava3/core/SingleSource;)V
      16: invokevirtual #474                // Method takeUntil:(Lorg/reactivestreams/Publisher;)Lio/reactivex/rxjava3/core/Single;
      19: areturn

  public final io.reactivex.rxjava3.core.Single<T> timeout(long, java.util.concurrent.TimeUnit);
    Code:
       0: aload_0
       1: lload_1
       2: aload_3
       3: invokestatic  #164                // Method io/reactivex/rxjava3/schedulers/Schedulers.computation:()Lio/reactivex/rxjava3/core/Scheduler;
       6: aconst_null
       7: invokespecial #475                // Method timeout0:(JLjava/util/concurrent/TimeUnit;Lio/reactivex/rxjava3/core/Scheduler;Lio/reactivex/rxjava3/core/SingleSource;)Lio/reactivex/rxjava3/core/Single;
      10: areturn

  public final io.reactivex.rxjava3.core.Single<T> timeout(long, java.util.concurrent.TimeUnit, io.reactivex.rxjava3.core.Scheduler);
    Code:
       0: aload_0
       1: lload_1
       2: aload_3
       3: aload         4
       5: aconst_null
       6: invokespecial #475                // Method timeout0:(JLjava/util/concurrent/TimeUnit;Lio/reactivex/rxjava3/core/Scheduler;Lio/reactivex/rxjava3/core/SingleSource;)Lio/reactivex/rxjava3/core/Single;
       9: areturn

  public final io.reactivex.rxjava3.core.Single<T> timeout(long, java.util.concurrent.TimeUnit, io.reactivex.rxjava3.core.Scheduler, io.reactivex.rxjava3.core.SingleSource<? extends T>);
    Code:
       0: aload         5
       2: ldc_w         #384                // String fallback is null
       5: invokestatic  #3                  // Method java/util/Objects.requireNonNull:(Ljava/lang/Object;Ljava/lang/String;)Ljava/lang/Object;
       8: pop
       9: aload_0
      10: lload_1
      11: aload_3
      12: aload         4
      14: aload         5
      16: invokespecial #475                // Method timeout0:(JLjava/util/concurrent/TimeUnit;Lio/reactivex/rxjava3/core/Scheduler;Lio/reactivex/rxjava3/core/SingleSource;)Lio/reactivex/rxjava3/core/Single;
      19: areturn

  public final io.reactivex.rxjava3.core.Single<T> timeout(long, java.util.concurrent.TimeUnit, io.reactivex.rxjava3.core.SingleSource<? extends T>);
    Code:
       0: aload         4
       2: ldc_w         #384                // String fallback is null
       5: invokestatic  #3                  // Method java/util/Objects.requireNonNull:(Ljava/lang/Object;Ljava/lang/String;)Ljava/lang/Object;
       8: pop
       9: aload_0
      10: lload_1
      11: aload_3
      12: invokestatic  #164                // Method io/reactivex/rxjava3/schedulers/Schedulers.computation:()Lio/reactivex/rxjava3/core/Scheduler;
      15: aload         4
      17: invokespecial #475                // Method timeout0:(JLjava/util/concurrent/TimeUnit;Lio/reactivex/rxjava3/core/Scheduler;Lio/reactivex/rxjava3/core/SingleSource;)Lio/reactivex/rxjava3/core/Single;
      20: areturn

  private io.reactivex.rxjava3.core.Single<T> timeout0(long, java.util.concurrent.TimeUnit, io.reactivex.rxjava3.core.Scheduler, io.reactivex.rxjava3.core.SingleSource<? extends T>);
    Code:
       0: aload_3
       1: ldc           #166                // String unit is null
       3: invokestatic  #3                  // Method java/util/Objects.requireNonNull:(Ljava/lang/Object;Ljava/lang/String;)Ljava/lang/Object;
       6: pop
       7: aload         4
       9: ldc           #167                // String scheduler is null
      11: invokestatic  #3                  // Method java/util/Objects.requireNonNull:(Ljava/lang/Object;Ljava/lang/String;)Ljava/lang/Object;
      14: pop
      15: new           #476                // class io/reactivex/rxjava3/internal/operators/single/SingleTimeout
      18: dup
      19: aload_0
      20: lload_1
      21: aload_3
      22: aload         4
      24: aload         5
      26: invokespecial #477                // Method io/reactivex/rxjava3/internal/operators/single/SingleTimeout."<init>":(Lio/reactivex/rxjava3/core/SingleSource;JLjava/util/concurrent/TimeUnit;Lio/reactivex/rxjava3/core/Scheduler;Lio/reactivex/rxjava3/core/SingleSource;)V
      29: invokestatic  #478                // Method io/reactivex/rxjava3/plugins/RxJavaPlugins.onAssembly:(Lio/reactivex/rxjava3/core/Single;)Lio/reactivex/rxjava3/core/Single;
      32: areturn

  public final <R> R to(io.reactivex.rxjava3.core.SingleConverter<T, ? extends R>);
    Code:
       0: aload_1
       1: ldc_w         #479                // String converter is null
       4: invokestatic  #3                  // Method java/util/Objects.requireNonNull:(Ljava/lang/Object;Ljava/lang/String;)Ljava/lang/Object;
       7: checkcast     #480                // class io/reactivex/rxjava3/core/SingleConverter
      10: aload_0
      11: invokeinterface #481,  2          // InterfaceMethod io/reactivex/rxjava3/core/SingleConverter.apply:(Lio/reactivex/rxjava3/core/Single;)Ljava/lang/Object;
      16: areturn

  public final io.reactivex.rxjava3.core.Completable ignoreElement();
    Code:
       0: new           #482                // class io/reactivex/rxjava3/internal/operators/completable/CompletableFromSingle
       3: dup
       4: aload_0
       5: invokespecial #483                // Method io/reactivex/rxjava3/internal/operators/completable/CompletableFromSingle."<init>":(Lio/reactivex/rxjava3/core/SingleSource;)V
       8: invokestatic  #341                // Method io/reactivex/rxjava3/plugins/RxJavaPlugins.onAssembly:(Lio/reactivex/rxjava3/core/Completable;)Lio/reactivex/rxjava3/core/Completable;
      11: areturn

  public final io.reactivex.rxjava3.core.Flowable<T> toFlowable();
    Code:
       0: aload_0
       1: instanceof    #484                // class io/reactivex/rxjava3/internal/fuseable/FuseToFlowable
       4: ifeq          17
       7: aload_0
       8: checkcast     #484                // class io/reactivex/rxjava3/internal/fuseable/FuseToFlowable
      11: invokeinterface #485,  1          // InterfaceMethod io/reactivex/rxjava3/internal/fuseable/FuseToFlowable.fuseToFlowable:()Lio/reactivex/rxjava3/core/Flowable;
      16: areturn
      17: new           #472                // class io/reactivex/rxjava3/internal/operators/single/SingleToFlowable
      20: dup
      21: aload_0
      22: invokespecial #473                // Method io/reactivex/rxjava3/internal/operators/single/SingleToFlowable."<init>":(Lio/reactivex/rxjava3/core/SingleSource;)V
      25: invokestatic  #486                // Method io/reactivex/rxjava3/plugins/RxJavaPlugins.onAssembly:(Lio/reactivex/rxjava3/core/Flowable;)Lio/reactivex/rxjava3/core/Flowable;
      28: areturn

  public final java.util.concurrent.Future<T> toFuture();
    Code:
       0: aload_0
       1: new           #487                // class io/reactivex/rxjava3/internal/observers/FutureMultiObserver
       4: dup
       5: invokespecial #488                // Method io/reactivex/rxjava3/internal/observers/FutureMultiObserver."<init>":()V
       8: invokevirtual #489                // Method subscribeWith:(Lio/reactivex/rxjava3/core/SingleObserver;)Lio/reactivex/rxjava3/core/SingleObserver;
      11: checkcast     #490                // class java/util/concurrent/Future
      14: areturn

  public final io.reactivex.rxjava3.core.Maybe<T> toMaybe();
    Code:
       0: aload_0
       1: instanceof    #491                // class io/reactivex/rxjava3/internal/fuseable/FuseToMaybe
       4: ifeq          17
       7: aload_0
       8: checkcast     #491                // class io/reactivex/rxjava3/internal/fuseable/FuseToMaybe
      11: invokeinterface #492,  1          // InterfaceMethod io/reactivex/rxjava3/internal/fuseable/FuseToMaybe.fuseToMaybe:()Lio/reactivex/rxjava3/core/Maybe;
      16: areturn
      17: new           #493                // class io/reactivex/rxjava3/internal/operators/maybe/MaybeFromSingle
      20: dup
      21: aload_0
      22: invokespecial #494                // Method io/reactivex/rxjava3/internal/operators/maybe/MaybeFromSingle."<init>":(Lio/reactivex/rxjava3/core/SingleSource;)V
      25: invokestatic  #495                // Method io/reactivex/rxjava3/plugins/RxJavaPlugins.onAssembly:(Lio/reactivex/rxjava3/core/Maybe;)Lio/reactivex/rxjava3/core/Maybe;
      28: areturn

  public final io.reactivex.rxjava3.core.Observable<T> toObservable();
    Code:
       0: aload_0
       1: instanceof    #496                // class io/reactivex/rxjava3/internal/fuseable/FuseToObservable
       4: ifeq          17
       7: aload_0
       8: checkcast     #496                // class io/reactivex/rxjava3/internal/fuseable/FuseToObservable
      11: invokeinterface #497,  1          // InterfaceMethod io/reactivex/rxjava3/internal/fuseable/FuseToObservable.fuseToObservable:()Lio/reactivex/rxjava3/core/Observable;
      16: areturn
      17: new           #498                // class io/reactivex/rxjava3/internal/operators/single/SingleToObservable
      20: dup
      21: aload_0
      22: invokespecial #499                // Method io/reactivex/rxjava3/internal/operators/single/SingleToObservable."<init>":(Lio/reactivex/rxjava3/core/SingleSource;)V
      25: invokestatic  #500                // Method io/reactivex/rxjava3/plugins/RxJavaPlugins.onAssembly:(Lio/reactivex/rxjava3/core/Observable;)Lio/reactivex/rxjava3/core/Observable;
      28: areturn

  public final io.reactivex.rxjava3.core.Single<T> unsubscribeOn(io.reactivex.rxjava3.core.Scheduler);
    Code:
       0: aload_1
       1: ldc           #167                // String scheduler is null
       3: invokestatic  #3                  // Method java/util/Objects.requireNonNull:(Ljava/lang/Object;Ljava/lang/String;)Ljava/lang/Object;
       6: pop
       7: new           #501                // class io/reactivex/rxjava3/internal/operators/single/SingleUnsubscribeOn
      10: dup
      11: aload_0
      12: aload_1
      13: invokespecial #502                // Method io/reactivex/rxjava3/internal/operators/single/SingleUnsubscribeOn."<init>":(Lio/reactivex/rxjava3/core/SingleSource;Lio/reactivex/rxjava3/core/Scheduler;)V
      16: invokestatic  #503                // Method io/reactivex/rxjava3/plugins/RxJavaPlugins.onAssembly:(Lio/reactivex/rxjava3/core/Single;)Lio/reactivex/rxjava3/core/Single;
      19: areturn

  public final <U, R> io.reactivex.rxjava3.core.Single<R> zipWith(io.reactivex.rxjava3.core.SingleSource<U>, io.reactivex.rxjava3.functions.BiFunction<? super T, ? super U, ? extends R>);
    Code:
       0: aload_0
       1: aload_1
       2: aload_2
       3: invokestatic  #504                // Method zip:(Lio/reactivex/rxjava3/core/SingleSource;Lio/reactivex/rxjava3/core/SingleSource;Lio/reactivex/rxjava3/functions/BiFunction;)Lio/reactivex/rxjava3/core/Single;
       6: areturn

  public final io.reactivex.rxjava3.observers.TestObserver<T> test();
    Code:
       0: new           #505                // class io/reactivex/rxjava3/observers/TestObserver
       3: dup
       4: invokespecial #506                // Method io/reactivex/rxjava3/observers/TestObserver."<init>":()V
       7: astore_1
       8: aload_0
       9: aload_1
      10: invokevirtual #344                // Method subscribe:(Lio/reactivex/rxjava3/core/SingleObserver;)V
      13: aload_1
      14: areturn

  public final io.reactivex.rxjava3.observers.TestObserver<T> test(boolean);
    Code:
       0: new           #505                // class io/reactivex/rxjava3/observers/TestObserver
       3: dup
       4: invokespecial #506                // Method io/reactivex/rxjava3/observers/TestObserver."<init>":()V
       7: astore_2
       8: iload_1
       9: ifeq          16
      12: aload_2
      13: invokevirtual #507                // Method io/reactivex/rxjava3/observers/TestObserver.dispose:()V
      16: aload_0
      17: aload_2
      18: invokevirtual #344                // Method subscribe:(Lio/reactivex/rxjava3/core/SingleObserver;)V
      21: aload_2
      22: areturn

  private static <T> io.reactivex.rxjava3.core.Single<T> toSingle(io.reactivex.rxjava3.core.Flowable<T>);
    Code:
       0: new           #508                // class io/reactivex/rxjava3/internal/operators/flowable/FlowableSingleSingle
       3: dup
       4: aload_0
       5: aconst_null
       6: invokespecial #509                // Method io/reactivex/rxjava3/internal/operators/flowable/FlowableSingleSingle."<init>":(Lio/reactivex/rxjava3/core/Flowable;Ljava/lang/Object;)V
       9: invokestatic  #510                // Method io/reactivex/rxjava3/plugins/RxJavaPlugins.onAssembly:(Lio/reactivex/rxjava3/core/Single;)Lio/reactivex/rxjava3/core/Single;
      12: areturn

  public static <T> io.reactivex.rxjava3.core.Single<T> fromCompletionStage(java.util.concurrent.CompletionStage<T>);
    Code:
       0: aload_0
       1: ldc_w         #511                // String stage is null
       4: invokestatic  #3                  // Method java/util/Objects.requireNonNull:(Ljava/lang/Object;Ljava/lang/String;)Ljava/lang/Object;
       7: pop
       8: new           #512                // class io/reactivex/rxjava3/internal/jdk8/SingleFromCompletionStage
      11: dup
      12: aload_0
      13: invokespecial #513                // Method io/reactivex/rxjava3/internal/jdk8/SingleFromCompletionStage."<init>":(Ljava/util/concurrent/CompletionStage;)V
      16: invokestatic  #514                // Method io/reactivex/rxjava3/plugins/RxJavaPlugins.onAssembly:(Lio/reactivex/rxjava3/core/Single;)Lio/reactivex/rxjava3/core/Single;
      19: areturn

  public final <R> io.reactivex.rxjava3.core.Maybe<R> mapOptional(io.reactivex.rxjava3.functions.Function<? super T, java.util.Optional<? extends R>>);
    Code:
       0: aload_1
       1: ldc           #243                // String mapper is null
       3: invokestatic  #3                  // Method java/util/Objects.requireNonNull:(Ljava/lang/Object;Ljava/lang/String;)Ljava/lang/Object;
       6: pop
       7: new           #515                // class io/reactivex/rxjava3/internal/jdk8/SingleMapOptional
      10: dup
      11: aload_0
      12: aload_1
      13: invokespecial #516                // Method io/reactivex/rxjava3/internal/jdk8/SingleMapOptional."<init>":(Lio/reactivex/rxjava3/core/Single;Lio/reactivex/rxjava3/functions/Function;)V
      16: invokestatic  #517                // Method io/reactivex/rxjava3/plugins/RxJavaPlugins.onAssembly:(Lio/reactivex/rxjava3/core/Maybe;)Lio/reactivex/rxjava3/core/Maybe;
      19: areturn

  public final java.util.concurrent.CompletionStage<T> toCompletionStage();
    Code:
       0: aload_0
       1: new           #518                // class io/reactivex/rxjava3/internal/jdk8/CompletionStageConsumer
       4: dup
       5: iconst_0
       6: aconst_null
       7: invokespecial #519                // Method io/reactivex/rxjava3/internal/jdk8/CompletionStageConsumer."<init>":(ZLjava/lang/Object;)V
      10: invokevirtual #489                // Method subscribeWith:(Lio/reactivex/rxjava3/core/SingleObserver;)Lio/reactivex/rxjava3/core/SingleObserver;
      13: checkcast     #520                // class java/util/concurrent/CompletionStage
      16: areturn

  public final <R> io.reactivex.rxjava3.core.Flowable<R> flattenStreamAsFlowable(io.reactivex.rxjava3.functions.Function<? super T, ? extends java.util.stream.Stream<? extends R>>);
    Code:
       0: aload_1
       1: ldc           #243                // String mapper is null
       3: invokestatic  #3                  // Method java/util/Objects.requireNonNull:(Ljava/lang/Object;Ljava/lang/String;)Ljava/lang/Object;
       6: pop
       7: new           #521                // class io/reactivex/rxjava3/internal/jdk8/SingleFlattenStreamAsFlowable
      10: dup
      11: aload_0
      12: aload_1
      13: invokespecial #522                // Method io/reactivex/rxjava3/internal/jdk8/SingleFlattenStreamAsFlowable."<init>":(Lio/reactivex/rxjava3/core/Single;Lio/reactivex/rxjava3/functions/Function;)V
      16: invokestatic  #523                // Method io/reactivex/rxjava3/plugins/RxJavaPlugins.onAssembly:(Lio/reactivex/rxjava3/core/Flowable;)Lio/reactivex/rxjava3/core/Flowable;
      19: areturn

  public final <R> io.reactivex.rxjava3.core.Observable<R> flattenStreamAsObservable(io.reactivex.rxjava3.functions.Function<? super T, ? extends java.util.stream.Stream<? extends R>>);
    Code:
       0: aload_1
       1: ldc           #243                // String mapper is null
       3: invokestatic  #3                  // Method java/util/Objects.requireNonNull:(Ljava/lang/Object;Ljava/lang/String;)Ljava/lang/Object;
       6: pop
       7: new           #524                // class io/reactivex/rxjava3/internal/jdk8/SingleFlattenStreamAsObservable
      10: dup
      11: aload_0
      12: aload_1
      13: invokespecial #525                // Method io/reactivex/rxjava3/internal/jdk8/SingleFlattenStreamAsObservable."<init>":(Lio/reactivex/rxjava3/core/Single;Lio/reactivex/rxjava3/functions/Function;)V
      16: invokestatic  #526                // Method io/reactivex/rxjava3/plugins/RxJavaPlugins.onAssembly:(Lio/reactivex/rxjava3/core/Observable;)Lio/reactivex/rxjava3/core/Observable;
      19: areturn
}
