Compiled from "MessageInterpolatorFactory.java"
public class org.springframework.boot.validation.MessageInterpolatorFactory implements org.springframework.beans.factory.ObjectFactory<jakarta.validation.MessageInterpolator> {
  private static final java.util.Set<java.lang.String> FALLBACKS;

  private final org.springframework.context.MessageSource messageSource;

  public org.springframework.boot.validation.MessageInterpolatorFactory();
    Code:
       0: aload_0
       1: aconst_null
       2: invokespecial #1                  // Method "<init>":(Lorg/springframework/context/MessageSource;)V
       5: return

  public org.springframework.boot.validation.MessageInterpolatorFactory(org.springframework.context.MessageSource);
    Code:
       0: aload_0
       1: invokespecial #7                  // Method java/lang/Object."<init>":()V
       4: aload_0
       5: aload_1
       6: putfield      #12                 // Field messageSource:Lorg/springframework/context/MessageSource;
       9: return

  public jakarta.validation.MessageInterpolator getObject() throws org.springframework.beans.BeansException;
    Code:
       0: aload_0
       1: invokevirtual #16                 // Method getMessageInterpolator:()Ljakarta/validation/MessageInterpolator;
       4: astore_1
       5: aload_0
       6: getfield      #12                 // Field messageSource:Lorg/springframework/context/MessageSource;
       9: ifnull        25
      12: new           #20                 // class org/springframework/boot/validation/MessageSourceMessageInterpolator
      15: dup
      16: aload_0
      17: getfield      #12                 // Field messageSource:Lorg/springframework/context/MessageSource;
      20: aload_1
      21: invokespecial #22                 // Method org/springframework/boot/validation/MessageSourceMessageInterpolator."<init>":(Lorg/springframework/context/MessageSource;Ljakarta/validation/MessageInterpolator;)V
      24: areturn
      25: aload_1
      26: areturn

  private jakarta.validation.MessageInterpolator getMessageInterpolator();
    Code:
       0: invokestatic  #25                 // Method jakarta/validation/Validation.byDefaultProvider:()Ljakarta/validation/bootstrap/GenericBootstrap;
       3: invokeinterface #31,  1           // InterfaceMethod jakarta/validation/bootstrap/GenericBootstrap.configure:()Ljakarta/validation/Configuration;
       8: invokeinterface #37,  1           // InterfaceMethod jakarta/validation/Configuration.getDefaultMessageInterpolator:()Ljakarta/validation/MessageInterpolator;
      13: areturn
      14: astore_1
      15: aload_0
      16: invokevirtual #44                 // Method getFallback:()Ljakarta/validation/MessageInterpolator;
      19: astore_2
      20: aload_2
      21: ifnull        26
      24: aload_2
      25: areturn
      26: aload_1
      27: athrow
    Exception table:
       from    to  target type
           0    13    14   Class jakarta/validation/ValidationException

  private jakarta.validation.MessageInterpolator getFallback();
    Code:
       0: getstatic     #47                 // Field FALLBACKS:Ljava/util/Set;
       3: invokeinterface #51,  1           // InterfaceMethod java/util/Set.iterator:()Ljava/util/Iterator;
       8: astore_1
       9: aload_1
      10: invokeinterface #57,  1           // InterfaceMethod java/util/Iterator.hasNext:()Z
      15: ifeq          38
      18: aload_1
      19: invokeinterface #63,  1           // InterfaceMethod java/util/Iterator.next:()Ljava/lang/Object;
      24: checkcast     #67                 // class java/lang/String
      27: astore_2
      28: aload_0
      29: aload_2
      30: invokevirtual #69                 // Method getFallback:(Ljava/lang/String;)Ljakarta/validation/MessageInterpolator;
      33: areturn
      34: astore_3
      35: goto          9
      38: aconst_null
      39: areturn
    Exception table:
       from    to  target type
          28    33    34   Class java/lang/Exception

  private jakarta.validation.MessageInterpolator getFallback(java.lang.String);
    Code:
       0: aload_1
       1: aconst_null
       2: invokestatic  #74                 // Method org/springframework/util/ClassUtils.resolveClassName:(Ljava/lang/String;Ljava/lang/ClassLoader;)Ljava/lang/Class;
       5: astore_2
       6: aload_2
       7: invokestatic  #80                 // Method org/springframework/beans/BeanUtils.instantiateClass:(Ljava/lang/Class;)Ljava/lang/Object;
      10: astore_3
      11: aload_3
      12: checkcast     #86                 // class jakarta/validation/MessageInterpolator
      15: areturn

  public java.lang.Object getObject() throws org.springframework.beans.BeansException;
    Code:
       0: aload_0
       1: invokevirtual #88                 // Method getObject:()Ljakarta/validation/MessageInterpolator;
       4: areturn

  static {};
    Code:
       0: new           #91                 // class java/util/LinkedHashSet
       3: dup
       4: invokespecial #93                 // Method java/util/LinkedHashSet."<init>":()V
       7: astore_0
       8: aload_0
       9: ldc           #94                 // String org.hibernate.validator.messageinterpolation.ParameterMessageInterpolator
      11: invokeinterface #96,  2           // InterfaceMethod java/util/Set.add:(Ljava/lang/Object;)Z
      16: pop
      17: aload_0
      18: invokestatic  #100                // Method java/util/Collections.unmodifiableSet:(Ljava/util/Set;)Ljava/util/Set;
      21: putstatic     #47                 // Field FALLBACKS:Ljava/util/Set;
      24: return
}
