Compiled from "MessageSourceMessageInterpolator.java"
class org.springframework.boot.validation.MessageSourceMessageInterpolator implements jakarta.validation.MessageInterpolator {
  private static final char PREFIX;

  private static final char SUFFIX;

  private static final char ESCAPE;

  private final org.springframework.context.MessageSource messageSource;

  private final jakarta.validation.MessageInterpolator messageInterpolator;

  org.springframework.boot.validation.MessageSourceMessageInterpolator(org.springframework.context.MessageSource, jakarta.validation.MessageInterpolator);
    Code:
       0: aload_0
       1: invokespecial #1                  // Method java/lang/Object."<init>":()V
       4: aload_0
       5: aload_1
       6: putfield      #7                  // Field messageSource:Lorg/springframework/context/MessageSource;
       9: aload_0
      10: aload_2
      11: putfield      #13                 // Field messageInterpolator:Ljakarta/validation/MessageInterpolator;
      14: return

  public java.lang.String interpolate(java.lang.String, jakarta.validation.MessageInterpolator$Context);
    Code:
       0: aload_0
       1: aload_1
       2: aload_2
       3: invokestatic  #17                 // Method org/springframework/context/i18n/LocaleContextHolder.getLocale:()Ljava/util/Locale;
       6: invokevirtual #23                 // Method interpolate:(Ljava/lang/String;Ljakarta/validation/MessageInterpolator$Context;Ljava/util/Locale;)Ljava/lang/String;
       9: areturn

  public java.lang.String interpolate(java.lang.String, jakarta.validation.MessageInterpolator$Context, java.util.Locale);
    Code:
       0: aload_0
       1: aload_1
       2: aload_3
       3: invokevirtual #27                 // Method replaceParameters:(Ljava/lang/String;Ljava/util/Locale;)Ljava/lang/String;
       6: astore        4
       8: aload_0
       9: getfield      #13                 // Field messageInterpolator:Ljakarta/validation/MessageInterpolator;
      12: aload         4
      14: aload_2
      15: aload_3
      16: invokeinterface #31,  4           // InterfaceMethod jakarta/validation/MessageInterpolator.interpolate:(Ljava/lang/String;Ljakarta/validation/MessageInterpolator$Context;Ljava/util/Locale;)Ljava/lang/String;
      21: areturn

  private java.lang.String replaceParameters(java.lang.String, java.util.Locale);
    Code:
       0: aload_0
       1: aload_1
       2: aload_2
       3: new           #34                 // class java/util/LinkedHashSet
       6: dup
       7: iconst_4
       8: invokespecial #36                 // Method java/util/LinkedHashSet."<init>":(I)V
      11: invokevirtual #39                 // Method replaceParameters:(Ljava/lang/String;Ljava/util/Locale;Ljava/util/Set;)Ljava/lang/String;
      14: areturn

  private java.lang.String replaceParameters(java.lang.String, java.util.Locale, java.util.Set<java.lang.String>);
    Code:
       0: new           #42                 // class java/lang/StringBuilder
       3: dup
       4: aload_1
       5: invokespecial #44                 // Method java/lang/StringBuilder."<init>":(Ljava/lang/String;)V
       8: astore        4
      10: iconst_0
      11: istore        5
      13: iconst_m1
      14: istore        6
      16: iconst_m1
      17: istore        7
      19: iconst_0
      20: istore        8
      22: iload         8
      24: aload         4
      26: invokevirtual #47                 // Method java/lang/StringBuilder.length:()I
      29: if_icmpge     221
      32: aload         4
      34: iload         8
      36: invokevirtual #51                 // Method java/lang/StringBuilder.charAt:(I)C
      39: bipush        92
      41: if_icmpne     50
      44: iinc          8, 1
      47: goto          102
      50: aload         4
      52: iload         8
      54: invokevirtual #51                 // Method java/lang/StringBuilder.charAt:(I)C
      57: bipush        123
      59: if_icmpne     78
      62: iload         6
      64: iconst_m1
      65: if_icmpne     72
      68: iload         8
      70: istore        6
      72: iinc          5, 1
      75: goto          102
      78: aload         4
      80: iload         8
      82: invokevirtual #51                 // Method java/lang/StringBuilder.charAt:(I)C
      85: bipush        125
      87: if_icmpne     102
      90: iload         5
      92: ifle          98
      95: iinc          5, -1
      98: iload         8
     100: istore        7
     102: iload         5
     104: ifne          215
     107: iload         6
     109: iload         7
     111: if_icmpge     215
     114: aload         4
     116: iload         6
     118: iconst_1
     119: iadd
     120: iload         7
     122: invokevirtual #55                 // Method java/lang/StringBuilder.substring:(II)Ljava/lang/String;
     125: astore        9
     127: aload_3
     128: aload         9
     130: invokeinterface #59,  2           // InterfaceMethod java/util/Set.add:(Ljava/lang/Object;)Z
     135: ifne          159
     138: new           #65                 // class java/lang/IllegalArgumentException
     141: dup
     142: ldc           #67                 // String  ->
     144: aload_3
     145: invokestatic  #69                 // Method java/lang/String.join:(Ljava/lang/CharSequence;Ljava/lang/Iterable;)Ljava/lang/String;
     148: aload         9
     150: invokedynamic #75,  0             // InvokeDynamic #0:makeConcatWithConstants:(Ljava/lang/String;Ljava/lang/String;)Ljava/lang/String;
     155: invokespecial #79                 // Method java/lang/IllegalArgumentException."<init>":(Ljava/lang/String;)V
     158: athrow
     159: aload_0
     160: aload         9
     162: aload_2
     163: aload_3
     164: invokevirtual #80                 // Method replaceParameter:(Ljava/lang/String;Ljava/util/Locale;Ljava/util/Set;)Ljava/lang/String;
     167: astore        10
     169: aload         10
     171: ifnull        200
     174: aload         4
     176: iload         6
     178: iload         7
     180: iconst_1
     181: iadd
     182: aload         10
     184: invokevirtual #83                 // Method java/lang/StringBuilder.replace:(IILjava/lang/String;)Ljava/lang/StringBuilder;
     187: pop
     188: iload         6
     190: aload         10
     192: invokevirtual #87                 // Method java/lang/String.length:()I
     195: iadd
     196: iconst_1
     197: isub
     198: istore        8
     200: aload_3
     201: aload         9
     203: invokeinterface #88,  2           // InterfaceMethod java/util/Set.remove:(Ljava/lang/Object;)Z
     208: pop
     209: iconst_m1
     210: istore        6
     212: iconst_m1
     213: istore        7
     215: iinc          8, 1
     218: goto          22
     221: aload         4
     223: invokevirtual #91                 // Method java/lang/StringBuilder.toString:()Ljava/lang/String;
     226: areturn

  private java.lang.String replaceParameter(java.lang.String, java.util.Locale, java.util.Set<java.lang.String>);
    Code:
       0: aload_0
       1: aload_1
       2: aload_2
       3: aload_3
       4: invokevirtual #39                 // Method replaceParameters:(Ljava/lang/String;Ljava/util/Locale;Ljava/util/Set;)Ljava/lang/String;
       7: astore_1
       8: aload_0
       9: getfield      #7                  // Field messageSource:Lorg/springframework/context/MessageSource;
      12: aload_1
      13: aconst_null
      14: aconst_null
      15: aload_2
      16: invokeinterface #95,  5           // InterfaceMethod org/springframework/context/MessageSource.getMessage:(Ljava/lang/String;[Ljava/lang/Object;Ljava/lang/String;Ljava/util/Locale;)Ljava/lang/String;
      21: astore        4
      23: aload         4
      25: ifnull        49
      28: aload_0
      29: aload         4
      31: aload_1
      32: invokevirtual #101                // Method isUsingCodeAsDefaultMessage:(Ljava/lang/String;Ljava/lang/String;)Z
      35: ifne          49
      38: aload_0
      39: aload         4
      41: aload_2
      42: aload_3
      43: invokevirtual #39                 // Method replaceParameters:(Ljava/lang/String;Ljava/util/Locale;Ljava/util/Set;)Ljava/lang/String;
      46: goto          50
      49: aconst_null
      50: areturn

  private boolean isUsingCodeAsDefaultMessage(java.lang.String, java.lang.String);
    Code:
       0: aload_1
       1: aload_2
       2: invokevirtual #105                // Method java/lang/String.equals:(Ljava/lang/Object;)Z
       5: ireturn
}
