Compiled from "AbstractRegistry.java"
public abstract class org.apache.dubbo.registry.support.AbstractRegistry implements org.apache.dubbo.registry.Registry {
  private static final char URL_SEPARATOR;

  private static final java.lang.String URL_SPLIT;

  private static final int MAX_RETRY_TIMES_SAVE_PROPERTIES;

  private static final long DEFAULT_INTERVAL_SAVE_PROPERTIES;

  protected final org.apache.dubbo.common.logger.ErrorTypeAwareLogger logger;

  private final java.util.Properties properties;

  private final java.util.concurrent.ScheduledExecutorService registryCacheExecutor;

  private final java.util.concurrent.atomic.AtomicLong lastCacheChanged;

  private final java.util.concurrent.atomic.AtomicInteger savePropertiesRetryTimes;

  private final java.util.Set<org.apache.dubbo.common.URL> registered;

  private final java.util.concurrent.ConcurrentMap<org.apache.dubbo.common.URL, java.util.Set<org.apache.dubbo.registry.NotifyListener>> subscribed;

  private final java.util.concurrent.ConcurrentMap<org.apache.dubbo.common.URL, java.util.Map<java.lang.String, java.util.List<org.apache.dubbo.common.URL>>> notified;

  private boolean syncSaveFile;

  private org.apache.dubbo.common.URL registryUrl;

  private java.io.File file;

  private final boolean localCacheEnabled;

  protected org.apache.dubbo.registry.support.RegistryManager registryManager;

  protected org.apache.dubbo.rpc.model.ApplicationModel applicationModel;

  private static final java.lang.String CAUSE_MULTI_DUBBO_USING_SAME_FILE;

  protected org.apache.dubbo.registry.support.AbstractRegistry(org.apache.dubbo.common.URL);
    Code:
       0: aload_0
       1: invokespecial #5                  // Method java/lang/Object."<init>":()V
       4: aload_0
       5: aload_0
       6: invokevirtual #6                  // Method java/lang/Object.getClass:()Ljava/lang/Class;
       9: invokestatic  #7                  // Method org/apache/dubbo/common/logger/LoggerFactory.getErrorTypeAwareLogger:(Ljava/lang/Class;)Lorg/apache/dubbo/common/logger/ErrorTypeAwareLogger;
      12: putfield      #8                  // Field logger:Lorg/apache/dubbo/common/logger/ErrorTypeAwareLogger;
      15: aload_0
      16: new           #9                  // class java/util/Properties
      19: dup
      20: invokespecial #10                 // Method java/util/Properties."<init>":()V
      23: putfield      #11                 // Field properties:Ljava/util/Properties;
      26: aload_0
      27: new           #12                 // class java/util/concurrent/atomic/AtomicLong
      30: dup
      31: invokespecial #13                 // Method java/util/concurrent/atomic/AtomicLong."<init>":()V
      34: putfield      #14                 // Field lastCacheChanged:Ljava/util/concurrent/atomic/AtomicLong;
      37: aload_0
      38: new           #15                 // class java/util/concurrent/atomic/AtomicInteger
      41: dup
      42: invokespecial #16                 // Method java/util/concurrent/atomic/AtomicInteger."<init>":()V
      45: putfield      #17                 // Field savePropertiesRetryTimes:Ljava/util/concurrent/atomic/AtomicInteger;
      48: aload_0
      49: new           #18                 // class org/apache/dubbo/common/utils/ConcurrentHashSet
      52: dup
      53: invokespecial #19                 // Method org/apache/dubbo/common/utils/ConcurrentHashSet."<init>":()V
      56: putfield      #20                 // Field registered:Ljava/util/Set;
      59: aload_0
      60: new           #21                 // class java/util/concurrent/ConcurrentHashMap
      63: dup
      64: invokespecial #22                 // Method java/util/concurrent/ConcurrentHashMap."<init>":()V
      67: putfield      #23                 // Field subscribed:Ljava/util/concurrent/ConcurrentMap;
      70: aload_0
      71: new           #21                 // class java/util/concurrent/ConcurrentHashMap
      74: dup
      75: invokespecial #22                 // Method java/util/concurrent/ConcurrentHashMap."<init>":()V
      78: putfield      #24                 // Field notified:Ljava/util/concurrent/ConcurrentMap;
      81: aload_0
      82: aload_1
      83: invokevirtual #25                 // Method setUrl:(Lorg/apache/dubbo/common/URL;)V
      86: aload_0
      87: aload_1
      88: invokevirtual #26                 // Method org/apache/dubbo/common/URL.getOrDefaultApplicationModel:()Lorg/apache/dubbo/rpc/model/ApplicationModel;
      91: invokevirtual #27                 // Method org/apache/dubbo/rpc/model/ApplicationModel.getBeanFactory:()Lorg/apache/dubbo/common/beans/factory/ScopeBeanFactory;
      94: ldc           #28                 // class org/apache/dubbo/registry/support/RegistryManager
      96: invokevirtual #29                 // Method org/apache/dubbo/common/beans/factory/ScopeBeanFactory.getBean:(Ljava/lang/Class;)Ljava/lang/Object;
      99: checkcast     #28                 // class org/apache/dubbo/registry/support/RegistryManager
     102: putfield      #30                 // Field registryManager:Lorg/apache/dubbo/registry/support/RegistryManager;
     105: aload_0
     106: aload_1
     107: ldc           #31                 // String file-cache
     109: iconst_1
     110: invokevirtual #32                 // Method org/apache/dubbo/common/URL.getParameter:(Ljava/lang/String;Z)Z
     113: putfield      #33                 // Field localCacheEnabled:Z
     116: aload_0
     117: aload_1
     118: invokevirtual #34                 // Method org/apache/dubbo/common/URL.getOrDefaultFrameworkModel:()Lorg/apache/dubbo/rpc/model/FrameworkModel;
     121: invokevirtual #35                 // Method org/apache/dubbo/rpc/model/FrameworkModel.getBeanFactory:()Lorg/apache/dubbo/common/beans/factory/ScopeBeanFactory;
     124: ldc           #36                 // class org/apache/dubbo/common/threadpool/manager/FrameworkExecutorRepository
     126: invokevirtual #29                 // Method org/apache/dubbo/common/beans/factory/ScopeBeanFactory.getBean:(Ljava/lang/Class;)Ljava/lang/Object;
     129: checkcast     #36                 // class org/apache/dubbo/common/threadpool/manager/FrameworkExecutorRepository
     132: invokevirtual #37                 // Method org/apache/dubbo/common/threadpool/manager/FrameworkExecutorRepository.getSharedScheduledExecutor:()Ljava/util/concurrent/ScheduledExecutorService;
     135: putfield      #38                 // Field registryCacheExecutor:Ljava/util/concurrent/ScheduledExecutorService;
     138: aload_0
     139: getfield      #33                 // Field localCacheEnabled:Z
     142: ifeq          371
     145: aload_0
     146: aload_1
     147: ldc           #39                 // String save.file
     149: iconst_0
     150: invokevirtual #32                 // Method org/apache/dubbo/common/URL.getParameter:(Ljava/lang/String;Z)Z
     153: putfield      #40                 // Field syncSaveFile:Z
     156: new           #41                 // class java/lang/StringBuilder
     159: dup
     160: invokespecial #42                 // Method java/lang/StringBuilder."<init>":()V
     163: ldc           #43                 // String user.home
     165: invokestatic  #44                 // Method java/lang/System.getProperty:(Ljava/lang/String;)Ljava/lang/String;
     168: invokevirtual #45                 // Method java/lang/StringBuilder.append:(Ljava/lang/String;)Ljava/lang/StringBuilder;
     171: ldc           #46                 // String /.dubbo/dubbo-registry-
     173: invokevirtual #45                 // Method java/lang/StringBuilder.append:(Ljava/lang/String;)Ljava/lang/StringBuilder;
     176: aload_1
     177: invokevirtual #47                 // Method org/apache/dubbo/common/URL.getApplication:()Ljava/lang/String;
     180: invokevirtual #45                 // Method java/lang/StringBuilder.append:(Ljava/lang/String;)Ljava/lang/StringBuilder;
     183: ldc           #48                 // String -
     185: invokevirtual #45                 // Method java/lang/StringBuilder.append:(Ljava/lang/String;)Ljava/lang/StringBuilder;
     188: aload_1
     189: invokevirtual #49                 // Method org/apache/dubbo/common/URL.getAddress:()Ljava/lang/String;
     192: ldc           #50                 // String :
     194: ldc           #48                 // String -
     196: invokevirtual #51                 // Method java/lang/String.replaceAll:(Ljava/lang/String;Ljava/lang/String;)Ljava/lang/String;
     199: invokevirtual #45                 // Method java/lang/StringBuilder.append:(Ljava/lang/String;)Ljava/lang/StringBuilder;
     202: ldc           #52                 // String .cache
     204: invokevirtual #45                 // Method java/lang/StringBuilder.append:(Ljava/lang/String;)Ljava/lang/StringBuilder;
     207: invokevirtual #53                 // Method java/lang/StringBuilder.toString:()Ljava/lang/String;
     210: astore_2
     211: aload_1
     212: ldc           #54                 // String file
     214: aload_2
     215: invokevirtual #55                 // Method org/apache/dubbo/common/URL.getParameter:(Ljava/lang/String;Ljava/lang/String;)Ljava/lang/String;
     218: astore_3
     219: aconst_null
     220: astore        4
     222: aload_3
     223: invokestatic  #56                 // Method org/apache/dubbo/common/utils/ConfigUtils.isNotEmpty:(Ljava/lang/String;)Z
     226: ifeq          353
     229: new           #57                 // class java/io/File
     232: dup
     233: aload_3
     234: invokespecial #58                 // Method java/io/File."<init>":(Ljava/lang/String;)V
     237: astore        4
     239: aload         4
     241: invokevirtual #59                 // Method java/io/File.exists:()Z
     244: ifne          353
     247: aload         4
     249: invokevirtual #60                 // Method java/io/File.getParentFile:()Ljava/io/File;
     252: ifnull        353
     255: aload         4
     257: invokevirtual #60                 // Method java/io/File.getParentFile:()Ljava/io/File;
     260: invokevirtual #59                 // Method java/io/File.exists:()Z
     263: ifne          353
     266: aload         4
     268: invokevirtual #60                 // Method java/io/File.getParentFile:()Ljava/io/File;
     271: invokevirtual #61                 // Method java/io/File.mkdirs:()Z
     274: ifne          353
     277: new           #62                 // class java/lang/IllegalArgumentException
     280: dup
     281: new           #41                 // class java/lang/StringBuilder
     284: dup
     285: invokespecial #42                 // Method java/lang/StringBuilder."<init>":()V
     288: ldc           #63                 // String Invalid registry cache file
     290: invokevirtual #45                 // Method java/lang/StringBuilder.append:(Ljava/lang/String;)Ljava/lang/StringBuilder;
     293: aload         4
     295: invokevirtual #64                 // Method java/lang/StringBuilder.append:(Ljava/lang/Object;)Ljava/lang/StringBuilder;
     298: ldc           #65                 // String , cause: Failed to create directory
     300: invokevirtual #45                 // Method java/lang/StringBuilder.append:(Ljava/lang/String;)Ljava/lang/StringBuilder;
     303: aload         4
     305: invokevirtual #60                 // Method java/io/File.getParentFile:()Ljava/io/File;
     308: invokevirtual #64                 // Method java/lang/StringBuilder.append:(Ljava/lang/Object;)Ljava/lang/StringBuilder;
     311: ldc           #66                 // String !
     313: invokevirtual #45                 // Method java/lang/StringBuilder.append:(Ljava/lang/String;)Ljava/lang/StringBuilder;
     316: invokevirtual #53                 // Method java/lang/StringBuilder.toString:()Ljava/lang/String;
     319: invokespecial #67                 // Method java/lang/IllegalArgumentException."<init>":(Ljava/lang/String;)V
     322: astore        5
     324: aload_0
     325: getfield      #8                  // Field logger:Lorg/apache/dubbo/common/logger/ErrorTypeAwareLogger;
     328: ifnull        350
     331: aload_0
     332: getfield      #8                  // Field logger:Lorg/apache/dubbo/common/logger/ErrorTypeAwareLogger;
     335: ldc           #68                 // String 1-9
     337: ldc           #69                 // String cache directory inaccessible
     339: ldc           #70                 // String Try adjusting permission of the directory.
     341: ldc           #71                 // String failed to create directory
     343: aload         5
     345: invokeinterface #72,  6           // InterfaceMethod org/apache/dubbo/common/logger/ErrorTypeAwareLogger.error:(Ljava/lang/String;Ljava/lang/String;Ljava/lang/String;Ljava/lang/String;Ljava/lang/Throwable;)V
     350: aload         5
     352: athrow
     353: aload_0
     354: aload         4
     356: putfield      #73                 // Field file:Ljava/io/File;
     359: aload_0
     360: invokespecial #74                 // Method loadProperties:()V
     363: aload_0
     364: aload_1
     365: invokevirtual #75                 // Method org/apache/dubbo/common/URL.getBackupUrls:()Ljava/util/List;
     368: invokevirtual #76                 // Method notify:(Ljava/util/List;)V
     371: return

  protected static java.util.List<org.apache.dubbo.common.URL> filterEmpty(org.apache.dubbo.common.URL, java.util.List<org.apache.dubbo.common.URL>);
    Code:
       0: aload_1
       1: invokestatic  #77                 // Method org/apache/dubbo/common/utils/CollectionUtils.isEmpty:(Ljava/util/Collection;)Z
       4: ifeq          31
       7: new           #78                 // class java/util/ArrayList
      10: dup
      11: iconst_1
      12: invokespecial #79                 // Method java/util/ArrayList."<init>":(I)V
      15: astore_2
      16: aload_2
      17: aload_0
      18: ldc           #80                 // String empty
      20: invokevirtual #81                 // Method org/apache/dubbo/common/URL.setProtocol:(Ljava/lang/String;)Lorg/apache/dubbo/common/URL;
      23: invokeinterface #82,  2           // InterfaceMethod java/util/List.add:(Ljava/lang/Object;)Z
      28: pop
      29: aload_2
      30: areturn
      31: aload_1
      32: areturn

  public org.apache.dubbo.common.URL getUrl();
    Code:
       0: aload_0
       1: getfield      #83                 // Field registryUrl:Lorg/apache/dubbo/common/URL;
       4: areturn

  protected void setUrl(org.apache.dubbo.common.URL);
    Code:
       0: aload_1
       1: ifnonnull     14
       4: new           #62                 // class java/lang/IllegalArgumentException
       7: dup
       8: ldc           #84                 // String registry url == null
      10: invokespecial #67                 // Method java/lang/IllegalArgumentException."<init>":(Ljava/lang/String;)V
      13: athrow
      14: aload_0
      15: aload_1
      16: putfield      #83                 // Field registryUrl:Lorg/apache/dubbo/common/URL;
      19: return

  public java.util.Set<org.apache.dubbo.common.URL> getRegistered();
    Code:
       0: aload_0
       1: getfield      #20                 // Field registered:Ljava/util/Set;
       4: invokestatic  #85                 // Method java/util/Collections.unmodifiableSet:(Ljava/util/Set;)Ljava/util/Set;
       7: areturn

  public java.util.Map<org.apache.dubbo.common.URL, java.util.Set<org.apache.dubbo.registry.NotifyListener>> getSubscribed();
    Code:
       0: aload_0
       1: getfield      #23                 // Field subscribed:Ljava/util/concurrent/ConcurrentMap;
       4: invokestatic  #86                 // Method java/util/Collections.unmodifiableMap:(Ljava/util/Map;)Ljava/util/Map;
       7: areturn

  public java.util.Map<org.apache.dubbo.common.URL, java.util.Map<java.lang.String, java.util.List<org.apache.dubbo.common.URL>>> getNotified();
    Code:
       0: aload_0
       1: getfield      #24                 // Field notified:Ljava/util/concurrent/ConcurrentMap;
       4: invokestatic  #86                 // Method java/util/Collections.unmodifiableMap:(Ljava/util/Map;)Ljava/util/Map;
       7: areturn

  public java.io.File getCacheFile();
    Code:
       0: aload_0
       1: getfield      #73                 // Field file:Ljava/io/File;
       4: areturn

  public java.util.Properties getCacheProperties();
    Code:
       0: aload_0
       1: getfield      #11                 // Field properties:Ljava/util/Properties;
       4: areturn

  public java.util.concurrent.atomic.AtomicLong getLastCacheChanged();
    Code:
       0: aload_0
       1: getfield      #14                 // Field lastCacheChanged:Ljava/util/concurrent/atomic/AtomicLong;
       4: areturn

  public void doSaveProperties(long);
    Code:
       0: lload_1
       1: aload_0
       2: getfield      #14                 // Field lastCacheChanged:Ljava/util/concurrent/atomic/AtomicLong;
       5: invokevirtual #87                 // Method java/util/concurrent/atomic/AtomicLong.get:()J
       8: lcmp
       9: ifge          13
      12: return
      13: aload_0
      14: getfield      #73                 // Field file:Ljava/io/File;
      17: ifnonnull     21
      20: return
      21: aconst_null
      22: astore_3
      23: new           #57                 // class java/io/File
      26: dup
      27: new           #41                 // class java/lang/StringBuilder
      30: dup
      31: invokespecial #42                 // Method java/lang/StringBuilder."<init>":()V
      34: aload_0
      35: getfield      #73                 // Field file:Ljava/io/File;
      38: invokevirtual #88                 // Method java/io/File.getAbsolutePath:()Ljava/lang/String;
      41: invokevirtual #45                 // Method java/lang/StringBuilder.append:(Ljava/lang/String;)Ljava/lang/StringBuilder;
      44: ldc           #89                 // String .lock
      46: invokevirtual #45                 // Method java/lang/StringBuilder.append:(Ljava/lang/String;)Ljava/lang/StringBuilder;
      49: invokevirtual #53                 // Method java/lang/StringBuilder.toString:()Ljava/lang/String;
      52: invokespecial #58                 // Method java/io/File."<init>":(Ljava/lang/String;)V
      55: astore_3
      56: aload_3
      57: invokevirtual #59                 // Method java/io/File.exists:()Z
      60: ifne          68
      63: aload_3
      64: invokevirtual #90                 // Method java/io/File.createNewFile:()Z
      67: pop
      68: new           #91                 // class java/io/RandomAccessFile
      71: dup
      72: aload_3
      73: ldc           #92                 // String rw
      75: invokespecial #93                 // Method java/io/RandomAccessFile."<init>":(Ljava/io/File;Ljava/lang/String;)V
      78: astore        4
      80: aconst_null
      81: astore        5
      83: aload         4
      85: invokevirtual #94                 // Method java/io/RandomAccessFile.getChannel:()Ljava/nio/channels/FileChannel;
      88: astore        6
      90: aconst_null
      91: astore        7
      93: aload         6
      95: invokevirtual #95                 // Method java/nio/channels/FileChannel.tryLock:()Ljava/nio/channels/FileLock;
      98: astore        8
     100: aload         8
     102: ifnonnull     166
     105: new           #96                 // class java/io/IOException
     108: dup
     109: new           #41                 // class java/lang/StringBuilder
     112: dup
     113: invokespecial #42                 // Method java/lang/StringBuilder."<init>":()V
     116: ldc           #97                 // String Can not lock the registry cache file
     118: invokevirtual #45                 // Method java/lang/StringBuilder.append:(Ljava/lang/String;)Ljava/lang/StringBuilder;
     121: aload_0
     122: getfield      #73                 // Field file:Ljava/io/File;
     125: invokevirtual #88                 // Method java/io/File.getAbsolutePath:()Ljava/lang/String;
     128: invokevirtual #45                 // Method java/lang/StringBuilder.append:(Ljava/lang/String;)Ljava/lang/StringBuilder;
     131: ldc           #98                 // String , ignore and retry later, maybe multi java process use the file, please config: dubbo.registry.file=xxx.properties
     133: invokevirtual #45                 // Method java/lang/StringBuilder.append:(Ljava/lang/String;)Ljava/lang/StringBuilder;
     136: invokevirtual #53                 // Method java/lang/StringBuilder.toString:()Ljava/lang/String;
     139: invokespecial #99                 // Method java/io/IOException."<init>":(Ljava/lang/String;)V
     142: astore        9
     144: aload_0
     145: getfield      #8                  // Field logger:Lorg/apache/dubbo/common/logger/ErrorTypeAwareLogger;
     148: ldc           #68                 // String 1-9
     150: ldc           #101                // String multiple Dubbo instance are using the same file
     152: ldc           #102                // String
     154: ldc           #103                // String Adjust dubbo.registry.file.
     156: aload         9
     158: invokeinterface #104,  6          // InterfaceMethod org/apache/dubbo/common/logger/ErrorTypeAwareLogger.warn:(Ljava/lang/String;Ljava/lang/String;Ljava/lang/String;Ljava/lang/String;Ljava/lang/Throwable;)V
     163: aload         9
     165: athrow
     166: aload_0
     167: getfield      #73                 // Field file:Ljava/io/File;
     170: invokevirtual #59                 // Method java/io/File.exists:()Z
     173: ifne          184
     176: aload_0
     177: getfield      #73                 // Field file:Ljava/io/File;
     180: invokevirtual #90                 // Method java/io/File.createNewFile:()Z
     183: pop
     184: aload_0
     185: getfield      #40                 // Field syncSaveFile:Z
     188: ifeq          200
     191: aload_0
     192: getfield      #11                 // Field properties:Ljava/util/Properties;
     195: astore        9
     197: goto          278
     200: new           #9                  // class java/util/Properties
     203: dup
     204: invokespecial #10                 // Method java/util/Properties."<init>":()V
     207: astore        9
     209: aload_0
     210: getfield      #11                 // Field properties:Ljava/util/Properties;
     213: invokevirtual #105                // Method java/util/Properties.entrySet:()Ljava/util/Set;
     216: astore        10
     218: aload         10
     220: invokeinterface #106,  1          // InterfaceMethod java/util/Set.iterator:()Ljava/util/Iterator;
     225: astore        11
     227: aload         11
     229: invokeinterface #107,  1          // InterfaceMethod java/util/Iterator.hasNext:()Z
     234: ifeq          278
     237: aload         11
     239: invokeinterface #108,  1          // InterfaceMethod java/util/Iterator.next:()Ljava/lang/Object;
     244: checkcast     #109                // class java/util/Map$Entry
     247: astore        12
     249: aload         9
     251: aload         12
     253: invokeinterface #110,  1          // InterfaceMethod java/util/Map$Entry.getKey:()Ljava/lang/Object;
     258: checkcast     #111                // class java/lang/String
     261: aload         12
     263: invokeinterface #112,  1          // InterfaceMethod java/util/Map$Entry.getValue:()Ljava/lang/Object;
     268: checkcast     #111                // class java/lang/String
     271: invokevirtual #113                // Method java/util/Properties.setProperty:(Ljava/lang/String;Ljava/lang/String;)Ljava/lang/Object;
     274: pop
     275: goto          227
     278: new           #114                // class java/io/FileOutputStream
     281: dup
     282: aload_0
     283: getfield      #73                 // Field file:Ljava/io/File;
     286: invokespecial #115                // Method java/io/FileOutputStream."<init>":(Ljava/io/File;)V
     289: astore        10
     291: aconst_null
     292: astore        11
     294: aload         9
     296: aload         10
     298: ldc           #116                // String Dubbo Registry Cache
     300: invokevirtual #117                // Method java/util/Properties.store:(Ljava/io/OutputStream;Ljava/lang/String;)V
     303: aload         10
     305: ifnull        390
     308: aload         11
     310: ifnull        333
     313: aload         10
     315: invokevirtual #118                // Method java/io/FileOutputStream.close:()V
     318: goto          390
     321: astore        12
     323: aload         11
     325: aload         12
     327: invokevirtual #120                // Method java/lang/Throwable.addSuppressed:(Ljava/lang/Throwable;)V
     330: goto          390
     333: aload         10
     335: invokevirtual #118                // Method java/io/FileOutputStream.close:()V
     338: goto          390
     341: astore        12
     343: aload         12
     345: astore        11
     347: aload         12
     349: athrow
     350: astore        13
     352: aload         10
     354: ifnull        387
     357: aload         11
     359: ifnull        382
     362: aload         10
     364: invokevirtual #118                // Method java/io/FileOutputStream.close:()V
     367: goto          387
     370: astore        14
     372: aload         11
     374: aload         14
     376: invokevirtual #120                // Method java/lang/Throwable.addSuppressed:(Ljava/lang/Throwable;)V
     379: goto          387
     382: aload         10
     384: invokevirtual #118                // Method java/io/FileOutputStream.close:()V
     387: aload         13
     389: athrow
     390: aload         8
     392: invokevirtual #121                // Method java/nio/channels/FileLock.release:()V
     395: goto          408
     398: astore        15
     400: aload         8
     402: invokevirtual #121                // Method java/nio/channels/FileLock.release:()V
     405: aload         15
     407: athrow
     408: aload         6
     410: ifnull        495
     413: aload         7
     415: ifnull        438
     418: aload         6
     420: invokevirtual #122                // Method java/nio/channels/FileChannel.close:()V
     423: goto          495
     426: astore        8
     428: aload         7
     430: aload         8
     432: invokevirtual #120                // Method java/lang/Throwable.addSuppressed:(Ljava/lang/Throwable;)V
     435: goto          495
     438: aload         6
     440: invokevirtual #122                // Method java/nio/channels/FileChannel.close:()V
     443: goto          495
     446: astore        8
     448: aload         8
     450: astore        7
     452: aload         8
     454: athrow
     455: astore        16
     457: aload         6
     459: ifnull        492
     462: aload         7
     464: ifnull        487
     467: aload         6
     469: invokevirtual #122                // Method java/nio/channels/FileChannel.close:()V
     472: goto          492
     475: astore        17
     477: aload         7
     479: aload         17
     481: invokevirtual #120                // Method java/lang/Throwable.addSuppressed:(Ljava/lang/Throwable;)V
     484: goto          492
     487: aload         6
     489: invokevirtual #122                // Method java/nio/channels/FileChannel.close:()V
     492: aload         16
     494: athrow
     495: aload         4
     497: ifnull        582
     500: aload         5
     502: ifnull        525
     505: aload         4
     507: invokevirtual #123                // Method java/io/RandomAccessFile.close:()V
     510: goto          582
     513: astore        6
     515: aload         5
     517: aload         6
     519: invokevirtual #120                // Method java/lang/Throwable.addSuppressed:(Ljava/lang/Throwable;)V
     522: goto          582
     525: aload         4
     527: invokevirtual #123                // Method java/io/RandomAccessFile.close:()V
     530: goto          582
     533: astore        6
     535: aload         6
     537: astore        5
     539: aload         6
     541: athrow
     542: astore        18
     544: aload         4
     546: ifnull        579
     549: aload         5
     551: ifnull        574
     554: aload         4
     556: invokevirtual #123                // Method java/io/RandomAccessFile.close:()V
     559: goto          579
     562: astore        19
     564: aload         5
     566: aload         19
     568: invokevirtual #120                // Method java/lang/Throwable.addSuppressed:(Ljava/lang/Throwable;)V
     571: goto          579
     574: aload         4
     576: invokevirtual #123                // Method java/io/RandomAccessFile.close:()V
     579: aload         18
     581: athrow
     582: aload_3
     583: ifnull        1009
     586: aload_3
     587: invokevirtual #124                // Method java/io/File.delete:()Z
     590: ifne          1009
     593: aload_0
     594: getfield      #8                  // Field logger:Lorg/apache/dubbo/common/logger/ErrorTypeAwareLogger;
     597: ldc           #125                // String 1-10
     599: ldc           #102                // String
     601: ldc           #102                // String
     603: ldc           #126                // String Failed to delete lock file [%s]
     605: iconst_1
     606: anewarray     #127                // class java/lang/Object
     609: dup
     610: iconst_0
     611: aload_3
     612: invokevirtual #128                // Method java/io/File.getName:()Ljava/lang/String;
     615: aastore
     616: invokestatic  #129                // Method java/lang/String.format:(Ljava/lang/String;[Ljava/lang/Object;)Ljava/lang/String;
     619: invokeinterface #130,  5          // InterfaceMethod org/apache/dubbo/common/logger/ErrorTypeAwareLogger.warn:(Ljava/lang/String;Ljava/lang/String;Ljava/lang/String;Ljava/lang/String;)V
     624: goto          1009
     627: astore        4
     629: aload_0
     630: getfield      #17                 // Field savePropertiesRetryTimes:Ljava/util/concurrent/atomic/AtomicInteger;
     633: invokevirtual #131                // Method java/util/concurrent/atomic/AtomicInteger.incrementAndGet:()I
     636: pop
     637: aload_0
     638: getfield      #17                 // Field savePropertiesRetryTimes:Ljava/util/concurrent/atomic/AtomicInteger;
     641: invokevirtual #132                // Method java/util/concurrent/atomic/AtomicInteger.get:()I
     644: iconst_3
     645: if_icmplt     784
     648: aload         4
     650: instanceof    #133                // class java/nio/channels/OverlappingFileLockException
     653: ifeq          693
     656: aload_0
     657: getfield      #8                  // Field logger:Lorg/apache/dubbo/common/logger/ErrorTypeAwareLogger;
     660: new           #41                 // class java/lang/StringBuilder
     663: dup
     664: invokespecial #42                 // Method java/lang/StringBuilder."<init>":()V
     667: ldc           #134                // String Failed to save registry cache file for file overlapping lock exception, file name
     669: invokevirtual #45                 // Method java/lang/StringBuilder.append:(Ljava/lang/String;)Ljava/lang/StringBuilder;
     672: aload_0
     673: getfield      #73                 // Field file:Ljava/io/File;
     676: invokevirtual #128                // Method java/io/File.getName:()Ljava/lang/String;
     679: invokevirtual #45                 // Method java/lang/StringBuilder.append:(Ljava/lang/String;)Ljava/lang/StringBuilder;
     682: invokevirtual #53                 // Method java/lang/StringBuilder.toString:()Ljava/lang/String;
     685: invokeinterface #135,  2          // InterfaceMethod org/apache/dubbo/common/logger/ErrorTypeAwareLogger.info:(Ljava/lang/String;)V
     690: goto          733
     693: aload_0
     694: getfield      #8                  // Field logger:Lorg/apache/dubbo/common/logger/ErrorTypeAwareLogger;
     697: ldc           #68                 // String 1-9
     699: ldc           #101                // String multiple Dubbo instance are using the same file
     701: ldc           #102                // String
     703: new           #41                 // class java/lang/StringBuilder
     706: dup
     707: invokespecial #42                 // Method java/lang/StringBuilder."<init>":()V
     710: ldc           #136                // String Failed to save registry cache file after retrying 3 times, cause:
     712: invokevirtual #45                 // Method java/lang/StringBuilder.append:(Ljava/lang/String;)Ljava/lang/StringBuilder;
     715: aload         4
     717: invokevirtual #137                // Method java/lang/Throwable.getMessage:()Ljava/lang/String;
     720: invokevirtual #45                 // Method java/lang/StringBuilder.append:(Ljava/lang/String;)Ljava/lang/StringBuilder;
     723: invokevirtual #53                 // Method java/lang/StringBuilder.toString:()Ljava/lang/String;
     726: aload         4
     728: invokeinterface #104,  6          // InterfaceMethod org/apache/dubbo/common/logger/ErrorTypeAwareLogger.warn:(Ljava/lang/String;Ljava/lang/String;Ljava/lang/String;Ljava/lang/String;Ljava/lang/Throwable;)V
     733: aload_0
     734: getfield      #17                 // Field savePropertiesRetryTimes:Ljava/util/concurrent/atomic/AtomicInteger;
     737: iconst_0
     738: invokevirtual #138                // Method java/util/concurrent/atomic/AtomicInteger.set:(I)V
     741: aload_3
     742: ifnull        783
     745: aload_3
     746: invokevirtual #124                // Method java/io/File.delete:()Z
     749: ifne          783
     752: aload_0
     753: getfield      #8                  // Field logger:Lorg/apache/dubbo/common/logger/ErrorTypeAwareLogger;
     756: ldc           #125                // String 1-10
     758: ldc           #102                // String
     760: ldc           #102                // String
     762: ldc           #126                // String Failed to delete lock file [%s]
     764: iconst_1
     765: anewarray     #127                // class java/lang/Object
     768: dup
     769: iconst_0
     770: aload_3
     771: invokevirtual #128                // Method java/io/File.getName:()Ljava/lang/String;
     774: aastore
     775: invokestatic  #129                // Method java/lang/String.format:(Ljava/lang/String;[Ljava/lang/Object;)Ljava/lang/String;
     778: invokeinterface #130,  5          // InterfaceMethod org/apache/dubbo/common/logger/ErrorTypeAwareLogger.warn:(Ljava/lang/String;Ljava/lang/String;Ljava/lang/String;Ljava/lang/String;)V
     783: return
     784: lload_1
     785: aload_0
     786: getfield      #14                 // Field lastCacheChanged:Ljava/util/concurrent/atomic/AtomicLong;
     789: invokevirtual #87                 // Method java/util/concurrent/atomic/AtomicLong.get:()J
     792: lcmp
     793: ifge          847
     796: aload_0
     797: getfield      #17                 // Field savePropertiesRetryTimes:Ljava/util/concurrent/atomic/AtomicInteger;
     800: iconst_0
     801: invokevirtual #138                // Method java/util/concurrent/atomic/AtomicInteger.set:(I)V
     804: aload_3
     805: ifnull        846
     808: aload_3
     809: invokevirtual #124                // Method java/io/File.delete:()Z
     812: ifne          846
     815: aload_0
     816: getfield      #8                  // Field logger:Lorg/apache/dubbo/common/logger/ErrorTypeAwareLogger;
     819: ldc           #125                // String 1-10
     821: ldc           #102                // String
     823: ldc           #102                // String
     825: ldc           #126                // String Failed to delete lock file [%s]
     827: iconst_1
     828: anewarray     #127                // class java/lang/Object
     831: dup
     832: iconst_0
     833: aload_3
     834: invokevirtual #128                // Method java/io/File.getName:()Ljava/lang/String;
     837: aastore
     838: invokestatic  #129                // Method java/lang/String.format:(Ljava/lang/String;[Ljava/lang/Object;)Ljava/lang/String;
     841: invokeinterface #130,  5          // InterfaceMethod org/apache/dubbo/common/logger/ErrorTypeAwareLogger.warn:(Ljava/lang/String;Ljava/lang/String;Ljava/lang/String;Ljava/lang/String;)V
     846: return
     847: aload_0
     848: getfield      #38                 // Field registryCacheExecutor:Ljava/util/concurrent/ScheduledExecutorService;
     851: aload_0
     852: invokedynamic #139,  0            // InvokeDynamic #0:run:(Lorg/apache/dubbo/registry/support/AbstractRegistry;)Ljava/lang/Runnable;
     857: ldc2_w        #140                // long 500l
     860: getstatic     #142                // Field java/util/concurrent/TimeUnit.MILLISECONDS:Ljava/util/concurrent/TimeUnit;
     863: invokeinterface #143,  5          // InterfaceMethod java/util/concurrent/ScheduledExecutorService.schedule:(Ljava/lang/Runnable;JLjava/util/concurrent/TimeUnit;)Ljava/util/concurrent/ScheduledFuture;
     868: pop
     869: aload         4
     871: instanceof    #133                // class java/nio/channels/OverlappingFileLockException
     874: ifne          917
     877: aload_0
     878: getfield      #8                  // Field logger:Lorg/apache/dubbo/common/logger/ErrorTypeAwareLogger;
     881: ldc           #68                 // String 1-9
     883: ldc           #101                // String multiple Dubbo instance are using the same file
     885: ldc           #144                // String However, the retrying count limit is not exceeded. Dubbo will still try.
     887: new           #41                 // class java/lang/StringBuilder
     890: dup
     891: invokespecial #42                 // Method java/lang/StringBuilder."<init>":()V
     894: ldc           #145                // String Failed to save registry cache file, will retry, cause:
     896: invokevirtual #45                 // Method java/lang/StringBuilder.append:(Ljava/lang/String;)Ljava/lang/StringBuilder;
     899: aload         4
     901: invokevirtual #137                // Method java/lang/Throwable.getMessage:()Ljava/lang/String;
     904: invokevirtual #45                 // Method java/lang/StringBuilder.append:(Ljava/lang/String;)Ljava/lang/StringBuilder;
     907: invokevirtual #53                 // Method java/lang/StringBuilder.toString:()Ljava/lang/String;
     910: aload         4
     912: invokeinterface #104,  6          // InterfaceMethod org/apache/dubbo/common/logger/ErrorTypeAwareLogger.warn:(Ljava/lang/String;Ljava/lang/String;Ljava/lang/String;Ljava/lang/String;Ljava/lang/Throwable;)V
     917: aload_3
     918: ifnull        1009
     921: aload_3
     922: invokevirtual #124                // Method java/io/File.delete:()Z
     925: ifne          1009
     928: aload_0
     929: getfield      #8                  // Field logger:Lorg/apache/dubbo/common/logger/ErrorTypeAwareLogger;
     932: ldc           #125                // String 1-10
     934: ldc           #102                // String
     936: ldc           #102                // String
     938: ldc           #126                // String Failed to delete lock file [%s]
     940: iconst_1
     941: anewarray     #127                // class java/lang/Object
     944: dup
     945: iconst_0
     946: aload_3
     947: invokevirtual #128                // Method java/io/File.getName:()Ljava/lang/String;
     950: aastore
     951: invokestatic  #129                // Method java/lang/String.format:(Ljava/lang/String;[Ljava/lang/Object;)Ljava/lang/String;
     954: invokeinterface #130,  5          // InterfaceMethod org/apache/dubbo/common/logger/ErrorTypeAwareLogger.warn:(Ljava/lang/String;Ljava/lang/String;Ljava/lang/String;Ljava/lang/String;)V
     959: goto          1009
     962: astore        20
     964: aload_3
     965: ifnull        1006
     968: aload_3
     969: invokevirtual #124                // Method java/io/File.delete:()Z
     972: ifne          1006
     975: aload_0
     976: getfield      #8                  // Field logger:Lorg/apache/dubbo/common/logger/ErrorTypeAwareLogger;
     979: ldc           #125                // String 1-10
     981: ldc           #102                // String
     983: ldc           #102                // String
     985: ldc           #126                // String Failed to delete lock file [%s]
     987: iconst_1
     988: anewarray     #127                // class java/lang/Object
     991: dup
     992: iconst_0
     993: aload_3
     994: invokevirtual #128                // Method java/io/File.getName:()Ljava/lang/String;
     997: aastore
     998: invokestatic  #129                // Method java/lang/String.format:(Ljava/lang/String;[Ljava/lang/Object;)Ljava/lang/String;
    1001: invokeinterface #130,  5          // InterfaceMethod org/apache/dubbo/common/logger/ErrorTypeAwareLogger.warn:(Ljava/lang/String;Ljava/lang/String;Ljava/lang/String;Ljava/lang/String;)V
    1006: aload         20
    1008: athrow
    1009: return
    Exception table:
       from    to  target type
         313   318   321   Class java/lang/Throwable
         294   303   341   Class java/lang/Throwable
         294   303   350   any
         362   367   370   Class java/lang/Throwable
         341   352   350   any
         166   390   398   any
         398   400   398   any
         418   423   426   Class java/lang/Throwable
          93   408   446   Class java/lang/Throwable
          93   408   455   any
         467   472   475   Class java/lang/Throwable
         446   457   455   any
         505   510   513   Class java/lang/Throwable
          83   495   533   Class java/lang/Throwable
          83   495   542   any
         554   559   562   Class java/lang/Throwable
         533   544   542   any
          23   582   627   Class java/lang/Throwable
          23   582   962   any
         627   741   962   any
         784   804   962   any
         847   917   962   any
         962   964   962   any

  private void loadProperties();
    Code:
       0: aload_0
       1: getfield      #73                 // Field file:Ljava/io/File;
       4: ifnull        17
       7: aload_0
       8: getfield      #73                 // Field file:Ljava/io/File;
      11: invokevirtual #59                 // Method java/io/File.exists:()Z
      14: ifne          18
      17: return
      18: aload_0
      19: getfield      #73                 // Field file:Ljava/io/File;
      22: invokevirtual #146                // Method java/io/File.toPath:()Ljava/nio/file/Path;
      25: iconst_0
      26: anewarray     #147                // class java/nio/file/OpenOption
      29: invokestatic  #148                // Method java/nio/file/Files.newInputStream:(Ljava/nio/file/Path;[Ljava/nio/file/OpenOption;)Ljava/io/InputStream;
      32: astore_1
      33: aconst_null
      34: astore_2
      35: aload_0
      36: getfield      #11                 // Field properties:Ljava/util/Properties;
      39: aload_1
      40: invokevirtual #149                // Method java/util/Properties.load:(Ljava/io/InputStream;)V
      43: aload_0
      44: getfield      #8                  // Field logger:Lorg/apache/dubbo/common/logger/ErrorTypeAwareLogger;
      47: invokeinterface #150,  1          // InterfaceMethod org/apache/dubbo/common/logger/ErrorTypeAwareLogger.isInfoEnabled:()Z
      52: ifeq          86
      55: aload_0
      56: getfield      #8                  // Field logger:Lorg/apache/dubbo/common/logger/ErrorTypeAwareLogger;
      59: new           #41                 // class java/lang/StringBuilder
      62: dup
      63: invokespecial #42                 // Method java/lang/StringBuilder."<init>":()V
      66: ldc           #151                // String Loaded registry cache file
      68: invokevirtual #45                 // Method java/lang/StringBuilder.append:(Ljava/lang/String;)Ljava/lang/StringBuilder;
      71: aload_0
      72: getfield      #73                 // Field file:Ljava/io/File;
      75: invokevirtual #64                 // Method java/lang/StringBuilder.append:(Ljava/lang/Object;)Ljava/lang/StringBuilder;
      78: invokevirtual #53                 // Method java/lang/StringBuilder.toString:()Ljava/lang/String;
      81: invokeinterface #135,  2          // InterfaceMethod org/apache/dubbo/common/logger/ErrorTypeAwareLogger.info:(Ljava/lang/String;)V
      86: aload_1
      87: ifnull        157
      90: aload_2
      91: ifnull        110
      94: aload_1
      95: invokevirtual #152                // Method java/io/InputStream.close:()V
      98: goto          157
     101: astore_3
     102: aload_2
     103: aload_3
     104: invokevirtual #120                // Method java/lang/Throwable.addSuppressed:(Ljava/lang/Throwable;)V
     107: goto          157
     110: aload_1
     111: invokevirtual #152                // Method java/io/InputStream.close:()V
     114: goto          157
     117: astore_3
     118: aload_3
     119: astore_2
     120: aload_3
     121: athrow
     122: astore        4
     124: aload_1
     125: ifnull        154
     128: aload_2
     129: ifnull        150
     132: aload_1
     133: invokevirtual #152                // Method java/io/InputStream.close:()V
     136: goto          154
     139: astore        5
     141: aload_2
     142: aload         5
     144: invokevirtual #120                // Method java/lang/Throwable.addSuppressed:(Ljava/lang/Throwable;)V
     147: goto          154
     150: aload_1
     151: invokevirtual #152                // Method java/io/InputStream.close:()V
     154: aload         4
     156: athrow
     157: goto          223
     160: astore_1
     161: aload_0
     162: getfield      #8                  // Field logger:Lorg/apache/dubbo/common/logger/ErrorTypeAwareLogger;
     165: ldc           #68                 // String 1-9
     167: ldc           #101                // String multiple Dubbo instance are using the same file
     169: ldc           #102                // String
     171: aload_1
     172: invokevirtual #153                // Method java/io/IOException.getMessage:()Ljava/lang/String;
     175: aload_1
     176: invokeinterface #104,  6          // InterfaceMethod org/apache/dubbo/common/logger/ErrorTypeAwareLogger.warn:(Ljava/lang/String;Ljava/lang/String;Ljava/lang/String;Ljava/lang/String;Ljava/lang/Throwable;)V
     181: goto          223
     184: astore_1
     185: aload_0
     186: getfield      #8                  // Field logger:Lorg/apache/dubbo/common/logger/ErrorTypeAwareLogger;
     189: ldc           #68                 // String 1-9
     191: ldc           #101                // String multiple Dubbo instance are using the same file
     193: ldc           #102                // String
     195: new           #41                 // class java/lang/StringBuilder
     198: dup
     199: invokespecial #42                 // Method java/lang/StringBuilder."<init>":()V
     202: ldc           #154                // String Failed to load registry cache file
     204: invokevirtual #45                 // Method java/lang/StringBuilder.append:(Ljava/lang/String;)Ljava/lang/StringBuilder;
     207: aload_0
     208: getfield      #73                 // Field file:Ljava/io/File;
     211: invokevirtual #64                 // Method java/lang/StringBuilder.append:(Ljava/lang/Object;)Ljava/lang/StringBuilder;
     214: invokevirtual #53                 // Method java/lang/StringBuilder.toString:()Ljava/lang/String;
     217: aload_1
     218: invokeinterface #104,  6          // InterfaceMethod org/apache/dubbo/common/logger/ErrorTypeAwareLogger.warn:(Ljava/lang/String;Ljava/lang/String;Ljava/lang/String;Ljava/lang/String;Ljava/lang/Throwable;)V
     223: return
    Exception table:
       from    to  target type
          94    98   101   Class java/lang/Throwable
          35    86   117   Class java/lang/Throwable
          35    86   122   any
         132   136   139   Class java/lang/Throwable
         117   124   122   any
          18   157   160   Class java/io/IOException
          18   157   184   Class java/lang/Throwable

  public java.util.List<org.apache.dubbo.common.URL> getCacheUrls(org.apache.dubbo.common.URL);
    Code:
       0: aload_0
       1: getfield      #24                 // Field notified:Ljava/util/concurrent/ConcurrentMap;
       4: aload_1
       5: invokeinterface #155,  2          // InterfaceMethod java/util/concurrent/ConcurrentMap.get:(Ljava/lang/Object;)Ljava/lang/Object;
      10: checkcast     #156                // class java/util/Map
      13: astore_2
      14: aload_2
      15: invokestatic  #157                // Method org/apache/dubbo/common/utils/CollectionUtils.isNotEmptyMap:(Ljava/util/Map;)Z
      18: ifeq          56
      21: aload_2
      22: invokeinterface #158,  1          // InterfaceMethod java/util/Map.values:()Ljava/util/Collection;
      27: invokeinterface #159,  1          // InterfaceMethod java/util/Collection.stream:()Ljava/util/stream/Stream;
      32: invokedynamic #160,  0            // InvokeDynamic #1:apply:()Ljava/util/function/Function;
      37: invokeinterface #161,  2          // InterfaceMethod java/util/stream/Stream.flatMap:(Ljava/util/function/Function;)Ljava/util/stream/Stream;
      42: invokestatic  #162                // Method java/util/stream/Collectors.toList:()Ljava/util/stream/Collector;
      45: invokeinterface #163,  2          // InterfaceMethod java/util/stream/Stream.collect:(Ljava/util/stream/Collector;)Ljava/lang/Object;
      50: checkcast     #164                // class java/util/List
      53: astore_3
      54: aload_3
      55: areturn
      56: aload_0
      57: getfield      #11                 // Field properties:Ljava/util/Properties;
      60: invokevirtual #105                // Method java/util/Properties.entrySet:()Ljava/util/Set;
      63: invokeinterface #106,  1          // InterfaceMethod java/util/Set.iterator:()Ljava/util/Iterator;
      68: astore_3
      69: aload_3
      70: invokeinterface #107,  1          // InterfaceMethod java/util/Iterator.hasNext:()Z
      75: ifeq          236
      78: aload_3
      79: invokeinterface #108,  1          // InterfaceMethod java/util/Iterator.next:()Ljava/lang/Object;
      84: checkcast     #109                // class java/util/Map$Entry
      87: astore        4
      89: aload         4
      91: invokeinterface #110,  1          // InterfaceMethod java/util/Map$Entry.getKey:()Ljava/lang/Object;
      96: checkcast     #111                // class java/lang/String
      99: astore        5
     101: aload         4
     103: invokeinterface #112,  1          // InterfaceMethod java/util/Map$Entry.getValue:()Ljava/lang/Object;
     108: checkcast     #111                // class java/lang/String
     111: astore        6
     113: aload         5
     115: invokestatic  #165                // Method org/apache/dubbo/common/utils/StringUtils.isNotEmpty:(Ljava/lang/String;)Z
     118: ifeq          233
     121: aload         5
     123: aload_1
     124: invokevirtual #166                // Method org/apache/dubbo/common/URL.getServiceKey:()Ljava/lang/String;
     127: invokevirtual #167                // Method java/lang/String.equals:(Ljava/lang/Object;)Z
     130: ifeq          233
     133: aload         5
     135: iconst_0
     136: invokevirtual #168                // Method java/lang/String.charAt:(I)C
     139: invokestatic  #169                // Method java/lang/Character.isLetter:(C)Z
     142: ifne          156
     145: aload         5
     147: iconst_0
     148: invokevirtual #168                // Method java/lang/String.charAt:(I)C
     151: bipush        95
     153: if_icmpne     233
     156: aload         6
     158: invokestatic  #165                // Method org/apache/dubbo/common/utils/StringUtils.isNotEmpty:(Ljava/lang/String;)Z
     161: ifeq          233
     164: aload         6
     166: invokevirtual #170                // Method java/lang/String.trim:()Ljava/lang/String;
     169: ldc           #171                // String \\s+
     171: invokevirtual #172                // Method java/lang/String.split:(Ljava/lang/String;)[Ljava/lang/String;
     174: astore        7
     176: new           #78                 // class java/util/ArrayList
     179: dup
     180: invokespecial #173                // Method java/util/ArrayList."<init>":()V
     183: astore        8
     185: aload         7
     187: astore        9
     189: aload         9
     191: arraylength
     192: istore        10
     194: iconst_0
     195: istore        11
     197: iload         11
     199: iload         10
     201: if_icmpge     230
     204: aload         9
     206: iload         11
     208: aaload
     209: astore        12
     211: aload         8
     213: aload         12
     215: invokestatic  #174                // Method org/apache/dubbo/common/URL.valueOf:(Ljava/lang/String;)Lorg/apache/dubbo/common/URL;
     218: invokeinterface #82,  2           // InterfaceMethod java/util/List.add:(Ljava/lang/Object;)Z
     223: pop
     224: iinc          11, 1
     227: goto          197
     230: aload         8
     232: areturn
     233: goto          69
     236: aconst_null
     237: areturn

  public java.util.List<org.apache.dubbo.common.URL> lookup(org.apache.dubbo.common.URL);
    Code:
       0: new           #78                 // class java/util/ArrayList
       3: dup
       4: invokespecial #173                // Method java/util/ArrayList."<init>":()V
       7: astore_2
       8: aload_0
       9: invokevirtual #175                // Method getNotified:()Ljava/util/Map;
      12: aload_1
      13: invokeinterface #176,  2          // InterfaceMethod java/util/Map.get:(Ljava/lang/Object;)Ljava/lang/Object;
      18: checkcast     #156                // class java/util/Map
      21: astore_3
      22: aload_3
      23: invokestatic  #157                // Method org/apache/dubbo/common/utils/CollectionUtils.isNotEmptyMap:(Ljava/util/Map;)Z
      26: ifeq          126
      29: aload_3
      30: invokeinterface #158,  1          // InterfaceMethod java/util/Map.values:()Ljava/util/Collection;
      35: invokeinterface #177,  1          // InterfaceMethod java/util/Collection.iterator:()Ljava/util/Iterator;
      40: astore        4
      42: aload         4
      44: invokeinterface #107,  1          // InterfaceMethod java/util/Iterator.hasNext:()Z
      49: ifeq          123
      52: aload         4
      54: invokeinterface #108,  1          // InterfaceMethod java/util/Iterator.next:()Ljava/lang/Object;
      59: checkcast     #164                // class java/util/List
      62: astore        5
      64: aload         5
      66: invokeinterface #178,  1          // InterfaceMethod java/util/List.iterator:()Ljava/util/Iterator;
      71: astore        6
      73: aload         6
      75: invokeinterface #107,  1          // InterfaceMethod java/util/Iterator.hasNext:()Z
      80: ifeq          120
      83: aload         6
      85: invokeinterface #108,  1          // InterfaceMethod java/util/Iterator.next:()Ljava/lang/Object;
      90: checkcast     #179                // class org/apache/dubbo/common/URL
      93: astore        7
      95: ldc           #80                 // String empty
      97: aload         7
      99: invokevirtual #180                // Method org/apache/dubbo/common/URL.getProtocol:()Ljava/lang/String;
     102: invokevirtual #167                // Method java/lang/String.equals:(Ljava/lang/Object;)Z
     105: ifne          117
     108: aload_2
     109: aload         7
     111: invokeinterface #82,  2           // InterfaceMethod java/util/List.add:(Ljava/lang/Object;)Z
     116: pop
     117: goto          73
     120: goto          42
     123: goto          230
     126: new           #181                // class java/util/concurrent/atomic/AtomicReference
     129: dup
     130: invokespecial #182                // Method java/util/concurrent/atomic/AtomicReference."<init>":()V
     133: astore        4
     135: aload         4
     137: dup
     138: invokevirtual #6                  // Method java/lang/Object.getClass:()Ljava/lang/Class;
     141: pop
     142: invokedynamic #183,  0            // InvokeDynamic #2:notify:(Ljava/util/concurrent/atomic/AtomicReference;)Lorg/apache/dubbo/registry/NotifyListener;
     147: astore        5
     149: aload_0
     150: aload_1
     151: aload         5
     153: invokevirtual #184                // Method subscribe:(Lorg/apache/dubbo/common/URL;Lorg/apache/dubbo/registry/NotifyListener;)V
     156: aload         4
     158: invokevirtual #185                // Method java/util/concurrent/atomic/AtomicReference.get:()Ljava/lang/Object;
     161: checkcast     #164                // class java/util/List
     164: astore        6
     166: aload         6
     168: invokestatic  #186                // Method org/apache/dubbo/common/utils/CollectionUtils.isNotEmpty:(Ljava/util/Collection;)Z
     171: ifeq          230
     174: aload         6
     176: invokeinterface #178,  1          // InterfaceMethod java/util/List.iterator:()Ljava/util/Iterator;
     181: astore        7
     183: aload         7
     185: invokeinterface #107,  1          // InterfaceMethod java/util/Iterator.hasNext:()Z
     190: ifeq          230
     193: aload         7
     195: invokeinterface #108,  1          // InterfaceMethod java/util/Iterator.next:()Ljava/lang/Object;
     200: checkcast     #179                // class org/apache/dubbo/common/URL
     203: astore        8
     205: ldc           #80                 // String empty
     207: aload         8
     209: invokevirtual #180                // Method org/apache/dubbo/common/URL.getProtocol:()Ljava/lang/String;
     212: invokevirtual #167                // Method java/lang/String.equals:(Ljava/lang/Object;)Z
     215: ifne          227
     218: aload_2
     219: aload         8
     221: invokeinterface #82,  2           // InterfaceMethod java/util/List.add:(Ljava/lang/Object;)Z
     226: pop
     227: goto          183
     230: aload_2
     231: areturn

  public void register(org.apache.dubbo.common.URL);
    Code:
       0: aload_1
       1: ifnonnull     14
       4: new           #62                 // class java/lang/IllegalArgumentException
       7: dup
       8: ldc           #187                // String register url == null
      10: invokespecial #67                 // Method java/lang/IllegalArgumentException."<init>":(Ljava/lang/String;)V
      13: athrow
      14: aload_1
      15: invokevirtual #188                // Method org/apache/dubbo/common/URL.getPort:()I
      18: ifeq          61
      21: aload_0
      22: getfield      #8                  // Field logger:Lorg/apache/dubbo/common/logger/ErrorTypeAwareLogger;
      25: invokeinterface #150,  1          // InterfaceMethod org/apache/dubbo/common/logger/ErrorTypeAwareLogger.isInfoEnabled:()Z
      30: ifeq          61
      33: aload_0
      34: getfield      #8                  // Field logger:Lorg/apache/dubbo/common/logger/ErrorTypeAwareLogger;
      37: new           #41                 // class java/lang/StringBuilder
      40: dup
      41: invokespecial #42                 // Method java/lang/StringBuilder."<init>":()V
      44: ldc           #189                // String Register:
      46: invokevirtual #45                 // Method java/lang/StringBuilder.append:(Ljava/lang/String;)Ljava/lang/StringBuilder;
      49: aload_1
      50: invokevirtual #64                 // Method java/lang/StringBuilder.append:(Ljava/lang/Object;)Ljava/lang/StringBuilder;
      53: invokevirtual #53                 // Method java/lang/StringBuilder.toString:()Ljava/lang/String;
      56: invokeinterface #135,  2          // InterfaceMethod org/apache/dubbo/common/logger/ErrorTypeAwareLogger.info:(Ljava/lang/String;)V
      61: aload_0
      62: getfield      #20                 // Field registered:Ljava/util/Set;
      65: aload_1
      66: invokeinterface #190,  2          // InterfaceMethod java/util/Set.add:(Ljava/lang/Object;)Z
      71: pop
      72: return

  public void unregister(org.apache.dubbo.common.URL);
    Code:
       0: aload_1
       1: ifnonnull     14
       4: new           #62                 // class java/lang/IllegalArgumentException
       7: dup
       8: ldc           #191                // String unregister url == null
      10: invokespecial #67                 // Method java/lang/IllegalArgumentException."<init>":(Ljava/lang/String;)V
      13: athrow
      14: aload_1
      15: invokevirtual #188                // Method org/apache/dubbo/common/URL.getPort:()I
      18: ifeq          61
      21: aload_0
      22: getfield      #8                  // Field logger:Lorg/apache/dubbo/common/logger/ErrorTypeAwareLogger;
      25: invokeinterface #150,  1          // InterfaceMethod org/apache/dubbo/common/logger/ErrorTypeAwareLogger.isInfoEnabled:()Z
      30: ifeq          61
      33: aload_0
      34: getfield      #8                  // Field logger:Lorg/apache/dubbo/common/logger/ErrorTypeAwareLogger;
      37: new           #41                 // class java/lang/StringBuilder
      40: dup
      41: invokespecial #42                 // Method java/lang/StringBuilder."<init>":()V
      44: ldc           #192                // String Unregister:
      46: invokevirtual #45                 // Method java/lang/StringBuilder.append:(Ljava/lang/String;)Ljava/lang/StringBuilder;
      49: aload_1
      50: invokevirtual #64                 // Method java/lang/StringBuilder.append:(Ljava/lang/Object;)Ljava/lang/StringBuilder;
      53: invokevirtual #53                 // Method java/lang/StringBuilder.toString:()Ljava/lang/String;
      56: invokeinterface #135,  2          // InterfaceMethod org/apache/dubbo/common/logger/ErrorTypeAwareLogger.info:(Ljava/lang/String;)V
      61: aload_0
      62: getfield      #20                 // Field registered:Ljava/util/Set;
      65: aload_1
      66: invokeinterface #193,  2          // InterfaceMethod java/util/Set.remove:(Ljava/lang/Object;)Z
      71: pop
      72: return

  public void subscribe(org.apache.dubbo.common.URL, org.apache.dubbo.registry.NotifyListener);
    Code:
       0: aload_1
       1: ifnonnull     14
       4: new           #62                 // class java/lang/IllegalArgumentException
       7: dup
       8: ldc           #194                // String subscribe url == null
      10: invokespecial #67                 // Method java/lang/IllegalArgumentException."<init>":(Ljava/lang/String;)V
      13: athrow
      14: aload_2
      15: ifnonnull     28
      18: new           #62                 // class java/lang/IllegalArgumentException
      21: dup
      22: ldc           #195                // String subscribe listener == null
      24: invokespecial #67                 // Method java/lang/IllegalArgumentException."<init>":(Ljava/lang/String;)V
      27: athrow
      28: aload_0
      29: getfield      #8                  // Field logger:Lorg/apache/dubbo/common/logger/ErrorTypeAwareLogger;
      32: invokeinterface #150,  1          // InterfaceMethod org/apache/dubbo/common/logger/ErrorTypeAwareLogger.isInfoEnabled:()Z
      37: ifeq          68
      40: aload_0
      41: getfield      #8                  // Field logger:Lorg/apache/dubbo/common/logger/ErrorTypeAwareLogger;
      44: new           #41                 // class java/lang/StringBuilder
      47: dup
      48: invokespecial #42                 // Method java/lang/StringBuilder."<init>":()V
      51: ldc           #196                // String Subscribe:
      53: invokevirtual #45                 // Method java/lang/StringBuilder.append:(Ljava/lang/String;)Ljava/lang/StringBuilder;
      56: aload_1
      57: invokevirtual #64                 // Method java/lang/StringBuilder.append:(Ljava/lang/Object;)Ljava/lang/StringBuilder;
      60: invokevirtual #53                 // Method java/lang/StringBuilder.toString:()Ljava/lang/String;
      63: invokeinterface #135,  2          // InterfaceMethod org/apache/dubbo/common/logger/ErrorTypeAwareLogger.info:(Ljava/lang/String;)V
      68: aload_0
      69: getfield      #23                 // Field subscribed:Ljava/util/concurrent/ConcurrentMap;
      72: aload_1
      73: invokedynamic #197,  0            // InvokeDynamic #3:apply:()Ljava/util/function/Function;
      78: invokeinterface #198,  3          // InterfaceMethod java/util/concurrent/ConcurrentMap.computeIfAbsent:(Ljava/lang/Object;Ljava/util/function/Function;)Ljava/lang/Object;
      83: checkcast     #199                // class java/util/Set
      86: astore_3
      87: aload_3
      88: aload_2
      89: invokeinterface #190,  2          // InterfaceMethod java/util/Set.add:(Ljava/lang/Object;)Z
      94: pop
      95: return

  public void unsubscribe(org.apache.dubbo.common.URL, org.apache.dubbo.registry.NotifyListener);
    Code:
       0: aload_1
       1: ifnonnull     14
       4: new           #62                 // class java/lang/IllegalArgumentException
       7: dup
       8: ldc           #200                // String unsubscribe url == null
      10: invokespecial #67                 // Method java/lang/IllegalArgumentException."<init>":(Ljava/lang/String;)V
      13: athrow
      14: aload_2
      15: ifnonnull     28
      18: new           #62                 // class java/lang/IllegalArgumentException
      21: dup
      22: ldc           #201                // String unsubscribe listener == null
      24: invokespecial #67                 // Method java/lang/IllegalArgumentException."<init>":(Ljava/lang/String;)V
      27: athrow
      28: aload_0
      29: getfield      #8                  // Field logger:Lorg/apache/dubbo/common/logger/ErrorTypeAwareLogger;
      32: invokeinterface #150,  1          // InterfaceMethod org/apache/dubbo/common/logger/ErrorTypeAwareLogger.isInfoEnabled:()Z
      37: ifeq          68
      40: aload_0
      41: getfield      #8                  // Field logger:Lorg/apache/dubbo/common/logger/ErrorTypeAwareLogger;
      44: new           #41                 // class java/lang/StringBuilder
      47: dup
      48: invokespecial #42                 // Method java/lang/StringBuilder."<init>":()V
      51: ldc           #202                // String Unsubscribe:
      53: invokevirtual #45                 // Method java/lang/StringBuilder.append:(Ljava/lang/String;)Ljava/lang/StringBuilder;
      56: aload_1
      57: invokevirtual #64                 // Method java/lang/StringBuilder.append:(Ljava/lang/Object;)Ljava/lang/StringBuilder;
      60: invokevirtual #53                 // Method java/lang/StringBuilder.toString:()Ljava/lang/String;
      63: invokeinterface #135,  2          // InterfaceMethod org/apache/dubbo/common/logger/ErrorTypeAwareLogger.info:(Ljava/lang/String;)V
      68: aload_0
      69: getfield      #23                 // Field subscribed:Ljava/util/concurrent/ConcurrentMap;
      72: aload_1
      73: invokeinterface #155,  2          // InterfaceMethod java/util/concurrent/ConcurrentMap.get:(Ljava/lang/Object;)Ljava/lang/Object;
      78: checkcast     #199                // class java/util/Set
      81: astore_3
      82: aload_3
      83: ifnull        94
      86: aload_3
      87: aload_2
      88: invokeinterface #193,  2          // InterfaceMethod java/util/Set.remove:(Ljava/lang/Object;)Z
      93: pop
      94: aload_0
      95: getfield      #24                 // Field notified:Ljava/util/concurrent/ConcurrentMap;
      98: aload_1
      99: invokeinterface #203,  2          // InterfaceMethod java/util/concurrent/ConcurrentMap.remove:(Ljava/lang/Object;)Ljava/lang/Object;
     104: pop
     105: return

  protected void recover() throws java.lang.Exception;
    Code:
       0: new           #204                // class java/util/HashSet
       3: dup
       4: aload_0
       5: invokevirtual #205                // Method getRegistered:()Ljava/util/Set;
       8: invokespecial #206                // Method java/util/HashSet."<init>":(Ljava/util/Collection;)V
      11: astore_1
      12: aload_1
      13: invokeinterface #207,  1          // InterfaceMethod java/util/Set.isEmpty:()Z
      18: ifne          95
      21: aload_0
      22: getfield      #8                  // Field logger:Lorg/apache/dubbo/common/logger/ErrorTypeAwareLogger;
      25: invokeinterface #150,  1          // InterfaceMethod org/apache/dubbo/common/logger/ErrorTypeAwareLogger.isInfoEnabled:()Z
      30: ifeq          61
      33: aload_0
      34: getfield      #8                  // Field logger:Lorg/apache/dubbo/common/logger/ErrorTypeAwareLogger;
      37: new           #41                 // class java/lang/StringBuilder
      40: dup
      41: invokespecial #42                 // Method java/lang/StringBuilder."<init>":()V
      44: ldc           #208                // String Recover register url
      46: invokevirtual #45                 // Method java/lang/StringBuilder.append:(Ljava/lang/String;)Ljava/lang/StringBuilder;
      49: aload_1
      50: invokevirtual #64                 // Method java/lang/StringBuilder.append:(Ljava/lang/Object;)Ljava/lang/StringBuilder;
      53: invokevirtual #53                 // Method java/lang/StringBuilder.toString:()Ljava/lang/String;
      56: invokeinterface #135,  2          // InterfaceMethod org/apache/dubbo/common/logger/ErrorTypeAwareLogger.info:(Ljava/lang/String;)V
      61: aload_1
      62: invokeinterface #106,  1          // InterfaceMethod java/util/Set.iterator:()Ljava/util/Iterator;
      67: astore_2
      68: aload_2
      69: invokeinterface #107,  1          // InterfaceMethod java/util/Iterator.hasNext:()Z
      74: ifeq          95
      77: aload_2
      78: invokeinterface #108,  1          // InterfaceMethod java/util/Iterator.next:()Ljava/lang/Object;
      83: checkcast     #179                // class org/apache/dubbo/common/URL
      86: astore_3
      87: aload_0
      88: aload_3
      89: invokevirtual #209                // Method register:(Lorg/apache/dubbo/common/URL;)V
      92: goto          68
      95: new           #210                // class java/util/HashMap
      98: dup
      99: aload_0
     100: invokevirtual #211                // Method getSubscribed:()Ljava/util/Map;
     103: invokespecial #212                // Method java/util/HashMap."<init>":(Ljava/util/Map;)V
     106: astore_2
     107: aload_2
     108: invokeinterface #213,  1          // InterfaceMethod java/util/Map.isEmpty:()Z
     113: ifne          258
     116: aload_0
     117: getfield      #8                  // Field logger:Lorg/apache/dubbo/common/logger/ErrorTypeAwareLogger;
     120: invokeinterface #150,  1          // InterfaceMethod org/apache/dubbo/common/logger/ErrorTypeAwareLogger.isInfoEnabled:()Z
     125: ifeq          161
     128: aload_0
     129: getfield      #8                  // Field logger:Lorg/apache/dubbo/common/logger/ErrorTypeAwareLogger;
     132: new           #41                 // class java/lang/StringBuilder
     135: dup
     136: invokespecial #42                 // Method java/lang/StringBuilder."<init>":()V
     139: ldc           #214                // String Recover subscribe url
     141: invokevirtual #45                 // Method java/lang/StringBuilder.append:(Ljava/lang/String;)Ljava/lang/StringBuilder;
     144: aload_2
     145: invokeinterface #215,  1          // InterfaceMethod java/util/Map.keySet:()Ljava/util/Set;
     150: invokevirtual #64                 // Method java/lang/StringBuilder.append:(Ljava/lang/Object;)Ljava/lang/StringBuilder;
     153: invokevirtual #53                 // Method java/lang/StringBuilder.toString:()Ljava/lang/String;
     156: invokeinterface #135,  2          // InterfaceMethod org/apache/dubbo/common/logger/ErrorTypeAwareLogger.info:(Ljava/lang/String;)V
     161: aload_2
     162: invokeinterface #216,  1          // InterfaceMethod java/util/Map.entrySet:()Ljava/util/Set;
     167: invokeinterface #106,  1          // InterfaceMethod java/util/Set.iterator:()Ljava/util/Iterator;
     172: astore_3
     173: aload_3
     174: invokeinterface #107,  1          // InterfaceMethod java/util/Iterator.hasNext:()Z
     179: ifeq          258
     182: aload_3
     183: invokeinterface #108,  1          // InterfaceMethod java/util/Iterator.next:()Ljava/lang/Object;
     188: checkcast     #109                // class java/util/Map$Entry
     191: astore        4
     193: aload         4
     195: invokeinterface #110,  1          // InterfaceMethod java/util/Map$Entry.getKey:()Ljava/lang/Object;
     200: checkcast     #179                // class org/apache/dubbo/common/URL
     203: astore        5
     205: aload         4
     207: invokeinterface #112,  1          // InterfaceMethod java/util/Map$Entry.getValue:()Ljava/lang/Object;
     212: checkcast     #199                // class java/util/Set
     215: invokeinterface #106,  1          // InterfaceMethod java/util/Set.iterator:()Ljava/util/Iterator;
     220: astore        6
     222: aload         6
     224: invokeinterface #107,  1          // InterfaceMethod java/util/Iterator.hasNext:()Z
     229: ifeq          255
     232: aload         6
     234: invokeinterface #108,  1          // InterfaceMethod java/util/Iterator.next:()Ljava/lang/Object;
     239: checkcast     #217                // class org/apache/dubbo/registry/NotifyListener
     242: astore        7
     244: aload_0
     245: aload         5
     247: aload         7
     249: invokevirtual #184                // Method subscribe:(Lorg/apache/dubbo/common/URL;Lorg/apache/dubbo/registry/NotifyListener;)V
     252: goto          222
     255: goto          173
     258: return

  protected void notify(java.util.List<org.apache.dubbo.common.URL>);
    Code:
       0: aload_1
       1: invokestatic  #77                 // Method org/apache/dubbo/common/utils/CollectionUtils.isEmpty:(Ljava/util/Collection;)Z
       4: ifeq          8
       7: return
       8: aload_0
       9: invokevirtual #211                // Method getSubscribed:()Ljava/util/Map;
      12: invokeinterface #216,  1          // InterfaceMethod java/util/Map.entrySet:()Ljava/util/Set;
      17: invokeinterface #106,  1          // InterfaceMethod java/util/Set.iterator:()Ljava/util/Iterator;
      22: astore_2
      23: aload_2
      24: invokeinterface #107,  1          // InterfaceMethod java/util/Iterator.hasNext:()Z
      29: ifeq          195
      32: aload_2
      33: invokeinterface #108,  1          // InterfaceMethod java/util/Iterator.next:()Ljava/lang/Object;
      38: checkcast     #109                // class java/util/Map$Entry
      41: astore_3
      42: aload_3
      43: invokeinterface #110,  1          // InterfaceMethod java/util/Map$Entry.getKey:()Ljava/lang/Object;
      48: checkcast     #179                // class org/apache/dubbo/common/URL
      51: astore        4
      53: aload         4
      55: aload_1
      56: iconst_0
      57: invokeinterface #218,  2          // InterfaceMethod java/util/List.get:(I)Ljava/lang/Object;
      62: checkcast     #179                // class org/apache/dubbo/common/URL
      65: invokestatic  #219                // Method org/apache/dubbo/common/utils/UrlUtils.isMatch:(Lorg/apache/dubbo/common/URL;Lorg/apache/dubbo/common/URL;)Z
      68: ifne          74
      71: goto          23
      74: aload_3
      75: invokeinterface #112,  1          // InterfaceMethod java/util/Map$Entry.getValue:()Ljava/lang/Object;
      80: checkcast     #199                // class java/util/Set
      83: astore        5
      85: aload         5
      87: ifnull        192
      90: aload         5
      92: invokeinterface #106,  1          // InterfaceMethod java/util/Set.iterator:()Ljava/util/Iterator;
      97: astore        6
      99: aload         6
     101: invokeinterface #107,  1          // InterfaceMethod java/util/Iterator.hasNext:()Z
     106: ifeq          192
     109: aload         6
     111: invokeinterface #108,  1          // InterfaceMethod java/util/Iterator.next:()Ljava/lang/Object;
     116: checkcast     #217                // class org/apache/dubbo/registry/NotifyListener
     119: astore        7
     121: aload_0
     122: aload         4
     124: aload         7
     126: aload         4
     128: aload_1
     129: invokestatic  #220                // Method filterEmpty:(Lorg/apache/dubbo/common/URL;Ljava/util/List;)Ljava/util/List;
     132: invokevirtual #221                // Method notify:(Lorg/apache/dubbo/common/URL;Lorg/apache/dubbo/registry/NotifyListener;Ljava/util/List;)V
     135: goto          189
     138: astore        8
     140: aload_0
     141: getfield      #8                  // Field logger:Lorg/apache/dubbo/common/logger/ErrorTypeAwareLogger;
     144: ldc           #222                // String 1-7
     146: ldc           #223                // String consumer is offline
     148: ldc           #102                // String
     150: new           #41                 // class java/lang/StringBuilder
     153: dup
     154: invokespecial #42                 // Method java/lang/StringBuilder."<init>":()V
     157: ldc           #224                // String Failed to notify registry event, urls:
     159: invokevirtual #45                 // Method java/lang/StringBuilder.append:(Ljava/lang/String;)Ljava/lang/StringBuilder;
     162: aload_1
     163: invokevirtual #64                 // Method java/lang/StringBuilder.append:(Ljava/lang/Object;)Ljava/lang/StringBuilder;
     166: ldc           #225                // String , cause:
     168: invokevirtual #45                 // Method java/lang/StringBuilder.append:(Ljava/lang/String;)Ljava/lang/StringBuilder;
     171: aload         8
     173: invokevirtual #137                // Method java/lang/Throwable.getMessage:()Ljava/lang/String;
     176: invokevirtual #45                 // Method java/lang/StringBuilder.append:(Ljava/lang/String;)Ljava/lang/StringBuilder;
     179: invokevirtual #53                 // Method java/lang/StringBuilder.toString:()Ljava/lang/String;
     182: aload         8
     184: invokeinterface #72,  6           // InterfaceMethod org/apache/dubbo/common/logger/ErrorTypeAwareLogger.error:(Ljava/lang/String;Ljava/lang/String;Ljava/lang/String;Ljava/lang/String;Ljava/lang/Throwable;)V
     189: goto          99
     192: goto          23
     195: return
    Exception table:
       from    to  target type
         121   135   138   Class java/lang/Throwable

  protected void notify(org.apache.dubbo.common.URL, org.apache.dubbo.registry.NotifyListener, java.util.List<org.apache.dubbo.common.URL>);
    Code:
       0: aload_1
       1: ifnonnull     14
       4: new           #62                 // class java/lang/IllegalArgumentException
       7: dup
       8: ldc           #226                // String notify url == null
      10: invokespecial #67                 // Method java/lang/IllegalArgumentException."<init>":(Ljava/lang/String;)V
      13: athrow
      14: aload_2
      15: ifnonnull     28
      18: new           #62                 // class java/lang/IllegalArgumentException
      21: dup
      22: ldc           #227                // String notify listener == null
      24: invokespecial #67                 // Method java/lang/IllegalArgumentException."<init>":(Ljava/lang/String;)V
      27: athrow
      28: aload_3
      29: invokestatic  #77                 // Method org/apache/dubbo/common/utils/CollectionUtils.isEmpty:(Ljava/util/Collection;)Z
      32: ifeq          82
      35: ldc           #228                // String *
      37: aload_1
      38: invokevirtual #229                // Method org/apache/dubbo/common/URL.getServiceInterface:()Ljava/lang/String;
      41: invokevirtual #167                // Method java/lang/String.equals:(Ljava/lang/Object;)Z
      44: ifne          82
      47: aload_0
      48: getfield      #8                  // Field logger:Lorg/apache/dubbo/common/logger/ErrorTypeAwareLogger;
      51: ldc           #230                // String 1-4
      53: ldc           #102                // String
      55: ldc           #102                // String
      57: new           #41                 // class java/lang/StringBuilder
      60: dup
      61: invokespecial #42                 // Method java/lang/StringBuilder."<init>":()V
      64: ldc           #231                // String Ignore empty notify urls for subscribe url
      66: invokevirtual #45                 // Method java/lang/StringBuilder.append:(Ljava/lang/String;)Ljava/lang/StringBuilder;
      69: aload_1
      70: invokevirtual #64                 // Method java/lang/StringBuilder.append:(Ljava/lang/Object;)Ljava/lang/StringBuilder;
      73: invokevirtual #53                 // Method java/lang/StringBuilder.toString:()Ljava/lang/String;
      76: invokeinterface #130,  5          // InterfaceMethod org/apache/dubbo/common/logger/ErrorTypeAwareLogger.warn:(Ljava/lang/String;Ljava/lang/String;Ljava/lang/String;Ljava/lang/String;)V
      81: return
      82: aload_0
      83: getfield      #8                  // Field logger:Lorg/apache/dubbo/common/logger/ErrorTypeAwareLogger;
      86: invokeinterface #150,  1          // InterfaceMethod org/apache/dubbo/common/logger/ErrorTypeAwareLogger.isInfoEnabled:()Z
      91: ifeq          136
      94: aload_0
      95: getfield      #8                  // Field logger:Lorg/apache/dubbo/common/logger/ErrorTypeAwareLogger;
      98: new           #41                 // class java/lang/StringBuilder
     101: dup
     102: invokespecial #42                 // Method java/lang/StringBuilder."<init>":()V
     105: ldc           #232                // String Notify urls for subscribe url
     107: invokevirtual #45                 // Method java/lang/StringBuilder.append:(Ljava/lang/String;)Ljava/lang/StringBuilder;
     110: aload_1
     111: invokevirtual #64                 // Method java/lang/StringBuilder.append:(Ljava/lang/Object;)Ljava/lang/StringBuilder;
     114: ldc           #233                // String , url size:
     116: invokevirtual #45                 // Method java/lang/StringBuilder.append:(Ljava/lang/String;)Ljava/lang/StringBuilder;
     119: aload_3
     120: invokeinterface #234,  1          // InterfaceMethod java/util/List.size:()I
     125: invokevirtual #235                // Method java/lang/StringBuilder.append:(I)Ljava/lang/StringBuilder;
     128: invokevirtual #53                 // Method java/lang/StringBuilder.toString:()Ljava/lang/String;
     131: invokeinterface #135,  2          // InterfaceMethod org/apache/dubbo/common/logger/ErrorTypeAwareLogger.info:(Ljava/lang/String;)V
     136: new           #210                // class java/util/HashMap
     139: dup
     140: invokespecial #236                // Method java/util/HashMap."<init>":()V
     143: astore        4
     145: aload_3
     146: invokeinterface #178,  1          // InterfaceMethod java/util/List.iterator:()Ljava/util/Iterator;
     151: astore        5
     153: aload         5
     155: invokeinterface #107,  1          // InterfaceMethod java/util/Iterator.hasNext:()Z
     160: ifeq          225
     163: aload         5
     165: invokeinterface #108,  1          // InterfaceMethod java/util/Iterator.next:()Ljava/lang/Object;
     170: checkcast     #179                // class org/apache/dubbo/common/URL
     173: astore        6
     175: aload_1
     176: aload         6
     178: invokestatic  #219                // Method org/apache/dubbo/common/utils/UrlUtils.isMatch:(Lorg/apache/dubbo/common/URL;Lorg/apache/dubbo/common/URL;)Z
     181: ifeq          222
     184: aload         6
     186: ldc           #237                // String providers
     188: invokevirtual #238                // Method org/apache/dubbo/common/URL.getCategory:(Ljava/lang/String;)Ljava/lang/String;
     191: astore        7
     193: aload         4
     195: aload         7
     197: invokedynamic #239,  0            // InvokeDynamic #4:apply:()Ljava/util/function/Function;
     202: invokeinterface #240,  3          // InterfaceMethod java/util/Map.computeIfAbsent:(Ljava/lang/Object;Ljava/util/function/Function;)Ljava/lang/Object;
     207: checkcast     #164                // class java/util/List
     210: astore        8
     212: aload         8
     214: aload         6
     216: invokeinterface #82,  2           // InterfaceMethod java/util/List.add:(Ljava/lang/Object;)Z
     221: pop
     222: goto          153
     225: aload         4
     227: invokeinterface #241,  1          // InterfaceMethod java/util/Map.size:()I
     232: ifne          236
     235: return
     236: aload_0
     237: getfield      #24                 // Field notified:Ljava/util/concurrent/ConcurrentMap;
     240: aload_1
     241: invokedynamic #242,  0            // InvokeDynamic #5:apply:()Ljava/util/function/Function;
     246: invokeinterface #198,  3          // InterfaceMethod java/util/concurrent/ConcurrentMap.computeIfAbsent:(Ljava/lang/Object;Ljava/util/function/Function;)Ljava/lang/Object;
     251: checkcast     #156                // class java/util/Map
     254: astore        5
     256: aload         4
     258: invokeinterface #216,  1          // InterfaceMethod java/util/Map.entrySet:()Ljava/util/Set;
     263: invokeinterface #106,  1          // InterfaceMethod java/util/Set.iterator:()Ljava/util/Iterator;
     268: astore        6
     270: aload         6
     272: invokeinterface #107,  1          // InterfaceMethod java/util/Iterator.hasNext:()Z
     277: ifeq          351
     280: aload         6
     282: invokeinterface #108,  1          // InterfaceMethod java/util/Iterator.next:()Ljava/lang/Object;
     287: checkcast     #109                // class java/util/Map$Entry
     290: astore        7
     292: aload         7
     294: invokeinterface #110,  1          // InterfaceMethod java/util/Map$Entry.getKey:()Ljava/lang/Object;
     299: checkcast     #111                // class java/lang/String
     302: astore        8
     304: aload         7
     306: invokeinterface #112,  1          // InterfaceMethod java/util/Map$Entry.getValue:()Ljava/lang/Object;
     311: checkcast     #164                // class java/util/List
     314: astore        9
     316: aload         5
     318: aload         8
     320: aload         9
     322: invokeinterface #243,  3          // InterfaceMethod java/util/Map.put:(Ljava/lang/Object;Ljava/lang/Object;)Ljava/lang/Object;
     327: pop
     328: aload_2
     329: aload         9
     331: invokeinterface #244,  2          // InterfaceMethod org/apache/dubbo/registry/NotifyListener.notify:(Ljava/util/List;)V
     336: aload_0
     337: getfield      #33                 // Field localCacheEnabled:Z
     340: ifeq          348
     343: aload_0
     344: aload_1
     345: invokespecial #245                // Method saveProperties:(Lorg/apache/dubbo/common/URL;)V
     348: goto          270
     351: return

  private void saveProperties(org.apache.dubbo.common.URL);
    Code:
       0: aload_0
       1: getfield      #73                 // Field file:Ljava/io/File;
       4: ifnonnull     8
       7: return
       8: new           #41                 // class java/lang/StringBuilder
      11: dup
      12: invokespecial #42                 // Method java/lang/StringBuilder."<init>":()V
      15: astore_2
      16: aload_0
      17: getfield      #24                 // Field notified:Ljava/util/concurrent/ConcurrentMap;
      20: aload_1
      21: invokeinterface #155,  2          // InterfaceMethod java/util/concurrent/ConcurrentMap.get:(Ljava/lang/Object;)Ljava/lang/Object;
      26: checkcast     #156                // class java/util/Map
      29: astore_3
      30: aload_3
      31: ifnull        130
      34: aload_3
      35: invokeinterface #158,  1          // InterfaceMethod java/util/Map.values:()Ljava/util/Collection;
      40: invokeinterface #177,  1          // InterfaceMethod java/util/Collection.iterator:()Ljava/util/Iterator;
      45: astore        4
      47: aload         4
      49: invokeinterface #107,  1          // InterfaceMethod java/util/Iterator.hasNext:()Z
      54: ifeq          130
      57: aload         4
      59: invokeinterface #108,  1          // InterfaceMethod java/util/Iterator.next:()Ljava/lang/Object;
      64: checkcast     #164                // class java/util/List
      67: astore        5
      69: aload         5
      71: invokeinterface #178,  1          // InterfaceMethod java/util/List.iterator:()Ljava/util/Iterator;
      76: astore        6
      78: aload         6
      80: invokeinterface #107,  1          // InterfaceMethod java/util/Iterator.hasNext:()Z
      85: ifeq          127
      88: aload         6
      90: invokeinterface #108,  1          // InterfaceMethod java/util/Iterator.next:()Ljava/lang/Object;
      95: checkcast     #179                // class org/apache/dubbo/common/URL
      98: astore        7
     100: aload_2
     101: invokevirtual #246                // Method java/lang/StringBuilder.length:()I
     104: ifle          114
     107: aload_2
     108: bipush        32
     110: invokevirtual #247                // Method java/lang/StringBuilder.append:(C)Ljava/lang/StringBuilder;
     113: pop
     114: aload_2
     115: aload         7
     117: invokevirtual #248                // Method org/apache/dubbo/common/URL.toFullString:()Ljava/lang/String;
     120: invokevirtual #45                 // Method java/lang/StringBuilder.append:(Ljava/lang/String;)Ljava/lang/StringBuilder;
     123: pop
     124: goto          78
     127: goto          47
     130: aload_0
     131: getfield      #11                 // Field properties:Ljava/util/Properties;
     134: aload_1
     135: invokevirtual #166                // Method org/apache/dubbo/common/URL.getServiceKey:()Ljava/lang/String;
     138: aload_2
     139: invokevirtual #53                 // Method java/lang/StringBuilder.toString:()Ljava/lang/String;
     142: invokevirtual #113                // Method java/util/Properties.setProperty:(Ljava/lang/String;Ljava/lang/String;)Ljava/lang/Object;
     145: pop
     146: aload_0
     147: getfield      #14                 // Field lastCacheChanged:Ljava/util/concurrent/atomic/AtomicLong;
     150: invokevirtual #249                // Method java/util/concurrent/atomic/AtomicLong.incrementAndGet:()J
     153: lstore        4
     155: aload_0
     156: getfield      #40                 // Field syncSaveFile:Z
     159: ifeq          171
     162: aload_0
     163: lload         4
     165: invokevirtual #250                // Method doSaveProperties:(J)V
     168: goto          195
     171: aload_0
     172: getfield      #38                 // Field registryCacheExecutor:Ljava/util/concurrent/ScheduledExecutorService;
     175: aload_0
     176: lload         4
     178: invokedynamic #251,  0            // InvokeDynamic #6:run:(Lorg/apache/dubbo/registry/support/AbstractRegistry;J)Ljava/lang/Runnable;
     183: ldc2_w        #140                // long 500l
     186: getstatic     #142                // Field java/util/concurrent/TimeUnit.MILLISECONDS:Ljava/util/concurrent/TimeUnit;
     189: invokeinterface #143,  5          // InterfaceMethod java/util/concurrent/ScheduledExecutorService.schedule:(Ljava/lang/Runnable;JLjava/util/concurrent/TimeUnit;)Ljava/util/concurrent/ScheduledFuture;
     194: pop
     195: goto          219
     198: astore_2
     199: aload_0
     200: getfield      #8                  // Field logger:Lorg/apache/dubbo/common/logger/ErrorTypeAwareLogger;
     203: ldc           #252                // String 99-0
     205: ldc           #253                // String unknown error in registry module
     207: ldc           #102                // String
     209: aload_2
     210: invokevirtual #137                // Method java/lang/Throwable.getMessage:()Ljava/lang/String;
     213: aload_2
     214: invokeinterface #104,  6          // InterfaceMethod org/apache/dubbo/common/logger/ErrorTypeAwareLogger.warn:(Ljava/lang/String;Ljava/lang/String;Ljava/lang/String;Ljava/lang/String;Ljava/lang/Throwable;)V
     219: return
    Exception table:
       from    to  target type
           8   195   198   Class java/lang/Throwable

  public void destroy();
    Code:
       0: aload_0
       1: getfield      #8                  // Field logger:Lorg/apache/dubbo/common/logger/ErrorTypeAwareLogger;
       4: invokeinterface #150,  1          // InterfaceMethod org/apache/dubbo/common/logger/ErrorTypeAwareLogger.isInfoEnabled:()Z
       9: ifeq          43
      12: aload_0
      13: getfield      #8                  // Field logger:Lorg/apache/dubbo/common/logger/ErrorTypeAwareLogger;
      16: new           #41                 // class java/lang/StringBuilder
      19: dup
      20: invokespecial #42                 // Method java/lang/StringBuilder."<init>":()V
      23: ldc           #254                // String Destroy registry:
      25: invokevirtual #45                 // Method java/lang/StringBuilder.append:(Ljava/lang/String;)Ljava/lang/StringBuilder;
      28: aload_0
      29: invokevirtual #255                // Method getUrl:()Lorg/apache/dubbo/common/URL;
      32: invokevirtual #64                 // Method java/lang/StringBuilder.append:(Ljava/lang/Object;)Ljava/lang/StringBuilder;
      35: invokevirtual #53                 // Method java/lang/StringBuilder.toString:()Ljava/lang/String;
      38: invokeinterface #135,  2          // InterfaceMethod org/apache/dubbo/common/logger/ErrorTypeAwareLogger.info:(Ljava/lang/String;)V
      43: new           #204                // class java/util/HashSet
      46: dup
      47: aload_0
      48: invokevirtual #205                // Method getRegistered:()Ljava/util/Set;
      51: invokespecial #206                // Method java/util/HashSet."<init>":(Ljava/util/Collection;)V
      54: astore_1
      55: aload_1
      56: invokeinterface #207,  1          // InterfaceMethod java/util/Set.isEmpty:()Z
      61: ifne          225
      64: new           #204                // class java/util/HashSet
      67: dup
      68: aload_1
      69: invokespecial #206                // Method java/util/HashSet."<init>":(Ljava/util/Collection;)V
      72: invokevirtual #256                // Method java/util/HashSet.iterator:()Ljava/util/Iterator;
      75: astore_2
      76: aload_2
      77: invokeinterface #107,  1          // InterfaceMethod java/util/Iterator.hasNext:()Z
      82: ifeq          225
      85: aload_2
      86: invokeinterface #108,  1          // InterfaceMethod java/util/Iterator.next:()Ljava/lang/Object;
      91: checkcast     #179                // class org/apache/dubbo/common/URL
      94: astore_3
      95: aload_3
      96: ldc_w         #257                // String dynamic
      99: iconst_1
     100: invokevirtual #32                 // Method org/apache/dubbo/common/URL.getParameter:(Ljava/lang/String;Z)Z
     103: ifeq          222
     106: aload_0
     107: aload_3
     108: invokevirtual #258                // Method unregister:(Lorg/apache/dubbo/common/URL;)V
     111: aload_0
     112: getfield      #8                  // Field logger:Lorg/apache/dubbo/common/logger/ErrorTypeAwareLogger;
     115: invokeinterface #150,  1          // InterfaceMethod org/apache/dubbo/common/logger/ErrorTypeAwareLogger.isInfoEnabled:()Z
     120: ifeq          152
     123: aload_0
     124: getfield      #8                  // Field logger:Lorg/apache/dubbo/common/logger/ErrorTypeAwareLogger;
     127: new           #41                 // class java/lang/StringBuilder
     130: dup
     131: invokespecial #42                 // Method java/lang/StringBuilder."<init>":()V
     134: ldc_w         #259                // String Destroy unregister url
     137: invokevirtual #45                 // Method java/lang/StringBuilder.append:(Ljava/lang/String;)Ljava/lang/StringBuilder;
     140: aload_3
     141: invokevirtual #64                 // Method java/lang/StringBuilder.append:(Ljava/lang/Object;)Ljava/lang/StringBuilder;
     144: invokevirtual #53                 // Method java/lang/StringBuilder.toString:()Ljava/lang/String;
     147: invokeinterface #135,  2          // InterfaceMethod org/apache/dubbo/common/logger/ErrorTypeAwareLogger.info:(Ljava/lang/String;)V
     152: goto          222
     155: astore        4
     157: aload_0
     158: getfield      #8                  // Field logger:Lorg/apache/dubbo/common/logger/ErrorTypeAwareLogger;
     161: ldc_w         #260                // String 1-8
     164: ldc           #102                // String
     166: ldc           #102                // String
     168: new           #41                 // class java/lang/StringBuilder
     171: dup
     172: invokespecial #42                 // Method java/lang/StringBuilder."<init>":()V
     175: ldc_w         #261                // String Failed to unregister url
     178: invokevirtual #45                 // Method java/lang/StringBuilder.append:(Ljava/lang/String;)Ljava/lang/StringBuilder;
     181: aload_3
     182: invokevirtual #64                 // Method java/lang/StringBuilder.append:(Ljava/lang/Object;)Ljava/lang/StringBuilder;
     185: ldc_w         #262                // String  to registry
     188: invokevirtual #45                 // Method java/lang/StringBuilder.append:(Ljava/lang/String;)Ljava/lang/StringBuilder;
     191: aload_0
     192: invokevirtual #255                // Method getUrl:()Lorg/apache/dubbo/common/URL;
     195: invokevirtual #64                 // Method java/lang/StringBuilder.append:(Ljava/lang/Object;)Ljava/lang/StringBuilder;
     198: ldc_w         #263                // String  on destroy, cause:
     201: invokevirtual #45                 // Method java/lang/StringBuilder.append:(Ljava/lang/String;)Ljava/lang/StringBuilder;
     204: aload         4
     206: invokevirtual #137                // Method java/lang/Throwable.getMessage:()Ljava/lang/String;
     209: invokevirtual #45                 // Method java/lang/StringBuilder.append:(Ljava/lang/String;)Ljava/lang/StringBuilder;
     212: invokevirtual #53                 // Method java/lang/StringBuilder.toString:()Ljava/lang/String;
     215: aload         4
     217: invokeinterface #104,  6          // InterfaceMethod org/apache/dubbo/common/logger/ErrorTypeAwareLogger.warn:(Ljava/lang/String;Ljava/lang/String;Ljava/lang/String;Ljava/lang/String;Ljava/lang/Throwable;)V
     222: goto          76
     225: new           #210                // class java/util/HashMap
     228: dup
     229: aload_0
     230: invokevirtual #211                // Method getSubscribed:()Ljava/util/Map;
     233: invokespecial #212                // Method java/util/HashMap."<init>":(Ljava/util/Map;)V
     236: astore_2
     237: aload_2
     238: invokeinterface #213,  1          // InterfaceMethod java/util/Map.isEmpty:()Z
     243: ifne          456
     246: aload_2
     247: invokeinterface #216,  1          // InterfaceMethod java/util/Map.entrySet:()Ljava/util/Set;
     252: invokeinterface #106,  1          // InterfaceMethod java/util/Set.iterator:()Ljava/util/Iterator;
     257: astore_3
     258: aload_3
     259: invokeinterface #107,  1          // InterfaceMethod java/util/Iterator.hasNext:()Z
     264: ifeq          456
     267: aload_3
     268: invokeinterface #108,  1          // InterfaceMethod java/util/Iterator.next:()Ljava/lang/Object;
     273: checkcast     #109                // class java/util/Map$Entry
     276: astore        4
     278: aload         4
     280: invokeinterface #110,  1          // InterfaceMethod java/util/Map$Entry.getKey:()Ljava/lang/Object;
     285: checkcast     #179                // class org/apache/dubbo/common/URL
     288: astore        5
     290: aload         4
     292: invokeinterface #112,  1          // InterfaceMethod java/util/Map$Entry.getValue:()Ljava/lang/Object;
     297: checkcast     #199                // class java/util/Set
     300: invokeinterface #106,  1          // InterfaceMethod java/util/Set.iterator:()Ljava/util/Iterator;
     305: astore        6
     307: aload         6
     309: invokeinterface #107,  1          // InterfaceMethod java/util/Iterator.hasNext:()Z
     314: ifeq          453
     317: aload         6
     319: invokeinterface #108,  1          // InterfaceMethod java/util/Iterator.next:()Ljava/lang/Object;
     324: checkcast     #217                // class org/apache/dubbo/registry/NotifyListener
     327: astore        7
     329: aload_0
     330: aload         5
     332: aload         7
     334: invokevirtual #264                // Method unsubscribe:(Lorg/apache/dubbo/common/URL;Lorg/apache/dubbo/registry/NotifyListener;)V
     337: aload_0
     338: getfield      #8                  // Field logger:Lorg/apache/dubbo/common/logger/ErrorTypeAwareLogger;
     341: invokeinterface #150,  1          // InterfaceMethod org/apache/dubbo/common/logger/ErrorTypeAwareLogger.isInfoEnabled:()Z
     346: ifeq          379
     349: aload_0
     350: getfield      #8                  // Field logger:Lorg/apache/dubbo/common/logger/ErrorTypeAwareLogger;
     353: new           #41                 // class java/lang/StringBuilder
     356: dup
     357: invokespecial #42                 // Method java/lang/StringBuilder."<init>":()V
     360: ldc_w         #265                // String Destroy unsubscribe url
     363: invokevirtual #45                 // Method java/lang/StringBuilder.append:(Ljava/lang/String;)Ljava/lang/StringBuilder;
     366: aload         5
     368: invokevirtual #64                 // Method java/lang/StringBuilder.append:(Ljava/lang/Object;)Ljava/lang/StringBuilder;
     371: invokevirtual #53                 // Method java/lang/StringBuilder.toString:()Ljava/lang/String;
     374: invokeinterface #135,  2          // InterfaceMethod org/apache/dubbo/common/logger/ErrorTypeAwareLogger.info:(Ljava/lang/String;)V
     379: goto          450
     382: astore        8
     384: aload_0
     385: getfield      #8                  // Field logger:Lorg/apache/dubbo/common/logger/ErrorTypeAwareLogger;
     388: ldc_w         #260                // String 1-8
     391: ldc           #102                // String
     393: ldc           #102                // String
     395: new           #41                 // class java/lang/StringBuilder
     398: dup
     399: invokespecial #42                 // Method java/lang/StringBuilder."<init>":()V
     402: ldc_w         #266                // String Failed to unsubscribe url
     405: invokevirtual #45                 // Method java/lang/StringBuilder.append:(Ljava/lang/String;)Ljava/lang/StringBuilder;
     408: aload         5
     410: invokevirtual #64                 // Method java/lang/StringBuilder.append:(Ljava/lang/Object;)Ljava/lang/StringBuilder;
     413: ldc_w         #262                // String  to registry
     416: invokevirtual #45                 // Method java/lang/StringBuilder.append:(Ljava/lang/String;)Ljava/lang/StringBuilder;
     419: aload_0
     420: invokevirtual #255                // Method getUrl:()Lorg/apache/dubbo/common/URL;
     423: invokevirtual #64                 // Method java/lang/StringBuilder.append:(Ljava/lang/Object;)Ljava/lang/StringBuilder;
     426: ldc_w         #263                // String  on destroy, cause:
     429: invokevirtual #45                 // Method java/lang/StringBuilder.append:(Ljava/lang/String;)Ljava/lang/StringBuilder;
     432: aload         8
     434: invokevirtual #137                // Method java/lang/Throwable.getMessage:()Ljava/lang/String;
     437: invokevirtual #45                 // Method java/lang/StringBuilder.append:(Ljava/lang/String;)Ljava/lang/StringBuilder;
     440: invokevirtual #53                 // Method java/lang/StringBuilder.toString:()Ljava/lang/String;
     443: aload         8
     445: invokeinterface #104,  6          // InterfaceMethod org/apache/dubbo/common/logger/ErrorTypeAwareLogger.warn:(Ljava/lang/String;Ljava/lang/String;Ljava/lang/String;Ljava/lang/String;Ljava/lang/Throwable;)V
     450: goto          307
     453: goto          258
     456: aload_0
     457: getfield      #30                 // Field registryManager:Lorg/apache/dubbo/registry/support/RegistryManager;
     460: aload_0
     461: invokevirtual #267                // Method org/apache/dubbo/registry/support/RegistryManager.removeDestroyedRegistry:(Lorg/apache/dubbo/registry/Registry;)V
     464: return
    Exception table:
       from    to  target type
         106   152   155   Class java/lang/Throwable
         329   379   382   Class java/lang/Throwable

  protected boolean acceptable(org.apache.dubbo.common.URL);
    Code:
       0: aload_0
       1: getfield      #83                 // Field registryUrl:Lorg/apache/dubbo/common/URL;
       4: ldc_w         #268                // String accepts
       7: invokevirtual #269                // Method org/apache/dubbo/common/URL.getParameter:(Ljava/lang/String;)Ljava/lang/String;
      10: astore_2
      11: aload_2
      12: invokestatic  #270                // Method org/apache/dubbo/common/utils/StringUtils.isEmpty:(Ljava/lang/String;)Z
      15: ifeq          20
      18: iconst_1
      19: ireturn
      20: getstatic     #271                // Field org/apache/dubbo/common/constants/CommonConstants.COMMA_SPLIT_PATTERN:Ljava/util/regex/Pattern;
      23: aload_2
      24: invokevirtual #272                // Method java/util/regex/Pattern.split:(Ljava/lang/CharSequence;)[Ljava/lang/String;
      27: astore_3
      28: aload_3
      29: invokestatic  #273                // Method java/util/Arrays.stream:([Ljava/lang/Object;)Ljava/util/stream/Stream;
      32: invokedynamic #274,  0            // InvokeDynamic #7:test:()Ljava/util/function/Predicate;
      37: invokeinterface #275,  2          // InterfaceMethod java/util/stream/Stream.filter:(Ljava/util/function/Predicate;)Ljava/util/stream/Stream;
      42: invokestatic  #276                // Method java/util/stream/Collectors.toSet:()Ljava/util/stream/Collector;
      45: invokeinterface #163,  2          // InterfaceMethod java/util/stream/Stream.collect:(Ljava/util/stream/Collector;)Ljava/lang/Object;
      50: checkcast     #199                // class java/util/Set
      53: astore        4
      55: aload_3
      56: invokestatic  #273                // Method java/util/Arrays.stream:([Ljava/lang/Object;)Ljava/util/stream/Stream;
      59: invokedynamic #277,  0            // InvokeDynamic #8:test:()Ljava/util/function/Predicate;
      64: invokeinterface #275,  2          // InterfaceMethod java/util/stream/Stream.filter:(Ljava/util/function/Predicate;)Ljava/util/stream/Stream;
      69: invokedynamic #278,  0            // InvokeDynamic #9:apply:()Ljava/util/function/Function;
      74: invokeinterface #279,  2          // InterfaceMethod java/util/stream/Stream.map:(Ljava/util/function/Function;)Ljava/util/stream/Stream;
      79: invokestatic  #276                // Method java/util/stream/Collectors.toSet:()Ljava/util/stream/Collector;
      82: invokeinterface #163,  2          // InterfaceMethod java/util/stream/Stream.collect:(Ljava/util/stream/Collector;)Ljava/lang/Object;
      87: checkcast     #199                // class java/util/Set
      90: astore        5
      92: aload         4
      94: invokestatic  #186                // Method org/apache/dubbo/common/utils/CollectionUtils.isNotEmpty:(Ljava/util/Collection;)Z
      97: ifeq          112
     100: aload         4
     102: aload_1
     103: invokevirtual #180                // Method org/apache/dubbo/common/URL.getProtocol:()Ljava/lang/String;
     106: invokeinterface #280,  2          // InterfaceMethod java/util/Set.contains:(Ljava/lang/Object;)Z
     111: ireturn
     112: aload         5
     114: invokestatic  #186                // Method org/apache/dubbo/common/utils/CollectionUtils.isNotEmpty:(Ljava/util/Collection;)Z
     117: ifeq          140
     120: aload         5
     122: aload_1
     123: invokevirtual #180                // Method org/apache/dubbo/common/URL.getProtocol:()Ljava/lang/String;
     126: invokeinterface #280,  2          // InterfaceMethod java/util/Set.contains:(Ljava/lang/Object;)Z
     131: ifne          138
     134: iconst_1
     135: goto          139
     138: iconst_0
     139: ireturn
     140: iconst_1
     141: ireturn

  public java.lang.String toString();
    Code:
       0: aload_0
       1: invokevirtual #255                // Method getUrl:()Lorg/apache/dubbo/common/URL;
       4: invokevirtual #281                // Method org/apache/dubbo/common/URL.toString:()Ljava/lang/String;
       7: areturn

  private static java.lang.String lambda$acceptable$7(java.lang.String);
    Code:
       0: aload_0
       1: iconst_1
       2: invokevirtual #282                // Method java/lang/String.substring:(I)Ljava/lang/String;
       5: areturn

  private static boolean lambda$acceptable$6(java.lang.String);
    Code:
       0: aload_0
       1: ldc           #48                 // String -
       3: invokevirtual #283                // Method java/lang/String.startsWith:(Ljava/lang/String;)Z
       6: ireturn

  private static boolean lambda$acceptable$5(java.lang.String);
    Code:
       0: aload_0
       1: ldc           #48                 // String -
       3: invokevirtual #283                // Method java/lang/String.startsWith:(Ljava/lang/String;)Z
       6: ifne          13
       9: iconst_1
      10: goto          14
      13: iconst_0
      14: ireturn

  private void lambda$saveProperties$4(long);
    Code:
       0: aload_0
       1: lload_1
       2: invokevirtual #250                // Method doSaveProperties:(J)V
       5: return

  private static java.util.Map lambda$notify$3(org.apache.dubbo.common.URL);
    Code:
       0: new           #21                 // class java/util/concurrent/ConcurrentHashMap
       3: dup
       4: invokespecial #22                 // Method java/util/concurrent/ConcurrentHashMap."<init>":()V
       7: areturn

  private static java.util.List lambda$notify$2(java.lang.String);
    Code:
       0: new           #78                 // class java/util/ArrayList
       3: dup
       4: invokespecial #173                // Method java/util/ArrayList."<init>":()V
       7: areturn

  private static java.util.Set lambda$subscribe$1(org.apache.dubbo.common.URL);
    Code:
       0: new           #18                 // class org/apache/dubbo/common/utils/ConcurrentHashSet
       3: dup
       4: invokespecial #19                 // Method org/apache/dubbo/common/utils/ConcurrentHashSet."<init>":()V
       7: areturn

  private void lambda$doSaveProperties$0();
    Code:
       0: aload_0
       1: aload_0
       2: getfield      #14                 // Field lastCacheChanged:Ljava/util/concurrent/atomic/AtomicLong;
       5: invokevirtual #249                // Method java/util/concurrent/atomic/AtomicLong.incrementAndGet:()J
       8: invokevirtual #250                // Method doSaveProperties:(J)V
      11: return
}
