Compiled from "CacheableFailbackRegistry.java"
public abstract class org.apache.dubbo.registry.support.CacheableFailbackRegistry extends org.apache.dubbo.registry.support.FailbackRegistry {
  private static final org.apache.dubbo.common.logger.ErrorTypeAwareLogger logger;

  private static java.lang.String[] VARIABLE_KEYS;

  protected java.util.concurrent.ConcurrentMap<java.lang.String, org.apache.dubbo.common.url.component.URLAddress> stringAddress;

  protected java.util.concurrent.ConcurrentMap<java.lang.String, org.apache.dubbo.common.url.component.URLParam> stringParam;

  private java.util.concurrent.ScheduledExecutorService cacheRemovalScheduler;

  private int cacheRemovalTaskIntervalInMillis;

  private int cacheClearWaitingThresholdInMillis;

  private java.util.Map<org.apache.dubbo.common.url.component.ServiceAddressURL, java.lang.Long> waitForRemove;

  private java.util.concurrent.Semaphore semaphore;

  private final java.util.Map<java.lang.String, java.lang.String> extraParameters;

  protected final java.util.Map<org.apache.dubbo.common.URL, java.util.Map<java.lang.String, org.apache.dubbo.common.url.component.ServiceAddressURL>> stringUrls;

  protected org.apache.dubbo.registry.support.CacheableFailbackRegistry(org.apache.dubbo.common.URL);
    Code:
       0: aload_0
       1: aload_1
       2: invokespecial #11                 // Method org/apache/dubbo/registry/support/FailbackRegistry."<init>":(Lorg/apache/dubbo/common/URL;)V
       5: aload_0
       6: new           #12                 // class java/util/concurrent/ConcurrentHashMap
       9: dup
      10: invokespecial #13                 // Method java/util/concurrent/ConcurrentHashMap."<init>":()V
      13: putfield      #14                 // Field stringAddress:Ljava/util/concurrent/ConcurrentMap;
      16: aload_0
      17: new           #12                 // class java/util/concurrent/ConcurrentHashMap
      20: dup
      21: invokespecial #13                 // Method java/util/concurrent/ConcurrentHashMap."<init>":()V
      24: putfield      #15                 // Field stringParam:Ljava/util/concurrent/ConcurrentMap;
      27: aload_0
      28: new           #12                 // class java/util/concurrent/ConcurrentHashMap
      31: dup
      32: invokespecial #13                 // Method java/util/concurrent/ConcurrentHashMap."<init>":()V
      35: putfield      #10                 // Field waitForRemove:Ljava/util/Map;
      38: aload_0
      39: new           #16                 // class java/util/concurrent/Semaphore
      42: dup
      43: iconst_1
      44: invokespecial #17                 // Method java/util/concurrent/Semaphore."<init>":(I)V
      47: putfield      #7                  // Field semaphore:Ljava/util/concurrent/Semaphore;
      50: aload_0
      51: new           #12                 // class java/util/concurrent/ConcurrentHashMap
      54: dup
      55: invokespecial #13                 // Method java/util/concurrent/ConcurrentHashMap."<init>":()V
      58: putfield      #18                 // Field stringUrls:Ljava/util/Map;
      61: aload_0
      62: new           #19                 // class java/util/HashMap
      65: dup
      66: bipush        8
      68: invokespecial #20                 // Method java/util/HashMap."<init>":(I)V
      71: putfield      #21                 // Field extraParameters:Ljava/util/Map;
      74: aload_0
      75: getfield      #21                 // Field extraParameters:Ljava/util/Map;
      78: ldc           #22                 // String check
      80: iconst_0
      81: invokestatic  #23                 // Method java/lang/String.valueOf:(Z)Ljava/lang/String;
      84: invokeinterface #24,  3           // InterfaceMethod java/util/Map.put:(Ljava/lang/Object;Ljava/lang/Object;)Ljava/lang/Object;
      89: pop
      90: aload_0
      91: aload_1
      92: invokevirtual #25                 // Method org/apache/dubbo/common/URL.getOrDefaultFrameworkModel:()Lorg/apache/dubbo/rpc/model/FrameworkModel;
      95: invokevirtual #26                 // Method org/apache/dubbo/rpc/model/FrameworkModel.getBeanFactory:()Lorg/apache/dubbo/common/beans/factory/ScopeBeanFactory;
      98: ldc           #27                 // class org/apache/dubbo/common/threadpool/manager/FrameworkExecutorRepository
     100: invokevirtual #28                 // Method org/apache/dubbo/common/beans/factory/ScopeBeanFactory.getBean:(Ljava/lang/Class;)Ljava/lang/Object;
     103: checkcast     #27                 // class org/apache/dubbo/common/threadpool/manager/FrameworkExecutorRepository
     106: invokevirtual #29                 // Method org/apache/dubbo/common/threadpool/manager/FrameworkExecutorRepository.nextScheduledExecutor:()Ljava/util/concurrent/ScheduledExecutorService;
     109: putfield      #5                  // Field cacheRemovalScheduler:Ljava/util/concurrent/ScheduledExecutorService;
     112: aload_0
     113: aload_1
     114: invokevirtual #30                 // Method org/apache/dubbo/common/URL.getScopeModel:()Lorg/apache/dubbo/rpc/model/ScopeModel;
     117: ldc           #31                 // String dubbo.application.url.cache.task.interval
     119: ldc           #32                 // int 120000
     121: invokestatic  #33                 // Method getIntConfig:(Lorg/apache/dubbo/rpc/model/ScopeModel;Ljava/lang/String;I)I
     124: putfield      #6                  // Field cacheRemovalTaskIntervalInMillis:I
     127: aload_0
     128: aload_1
     129: invokevirtual #30                 // Method org/apache/dubbo/common/URL.getScopeModel:()Lorg/apache/dubbo/rpc/model/ScopeModel;
     132: ldc           #34                 // String dubbo.application.url.cache.clear.waiting
     134: ldc           #35                 // int 300000
     136: invokestatic  #33                 // Method getIntConfig:(Lorg/apache/dubbo/rpc/model/ScopeModel;Ljava/lang/String;I)I
     139: putfield      #8                  // Field cacheClearWaitingThresholdInMillis:I
     142: return

  protected static int getIntConfig(org.apache.dubbo.rpc.model.ScopeModel, java.lang.String, int);
    Code:
       0: aload_0
       1: aload_1
       2: invokestatic  #36                 // Method org/apache/dubbo/common/config/ConfigurationUtils.getProperty:(Lorg/apache/dubbo/rpc/model/ScopeModel;Ljava/lang/String;)Ljava/lang/String;
       5: astore_3
       6: iload_2
       7: istore        4
       9: aload_3
      10: invokestatic  #37                 // Method org/apache/dubbo/common/utils/StringUtils.isNotEmpty:(Ljava/lang/String;)Z
      13: ifeq          69
      16: aload_3
      17: invokestatic  #38                 // Method java/lang/Integer.parseInt:(Ljava/lang/String;)I
      20: istore        4
      22: goto          69
      25: astore        5
      27: getstatic     #9                  // Field logger:Lorg/apache/dubbo/common/logger/ErrorTypeAwareLogger;
      30: ldc           #40                 // String 0-2
      32: ldc           #41                 // String typo in property value
      34: ldc           #42                 // String This property requires an integer value.
      36: new           #43                 // class java/lang/StringBuilder
      39: dup
      40: invokespecial #44                 // Method java/lang/StringBuilder."<init>":()V
      43: ldc           #45                 // String Invalid registry properties configuration key
      45: invokevirtual #46                 // Method java/lang/StringBuilder.append:(Ljava/lang/String;)Ljava/lang/StringBuilder;
      48: aload_1
      49: invokevirtual #46                 // Method java/lang/StringBuilder.append:(Ljava/lang/String;)Ljava/lang/StringBuilder;
      52: ldc           #47                 // String , value
      54: invokevirtual #46                 // Method java/lang/StringBuilder.append:(Ljava/lang/String;)Ljava/lang/StringBuilder;
      57: aload_3
      58: invokevirtual #46                 // Method java/lang/StringBuilder.append:(Ljava/lang/String;)Ljava/lang/StringBuilder;
      61: invokevirtual #48                 // Method java/lang/StringBuilder.toString:()Ljava/lang/String;
      64: invokeinterface #49,  5           // InterfaceMethod org/apache/dubbo/common/logger/ErrorTypeAwareLogger.warn:(Ljava/lang/String;Ljava/lang/String;Ljava/lang/String;Ljava/lang/String;)V
      69: iload         4
      71: ireturn
    Exception table:
       from    to  target type
          16    22    25   Class java/lang/NumberFormatException

  public void doUnsubscribe(org.apache.dubbo.common.URL, org.apache.dubbo.registry.NotifyListener);
    Code:
       0: aload_0
       1: aload_1
       2: invokevirtual #50                 // Method evictURLCache:(Lorg/apache/dubbo/common/URL;)V
       5: return

  protected void evictURLCache(org.apache.dubbo.common.URL);
    Code:
       0: aload_0
       1: getfield      #18                 // Field stringUrls:Ljava/util/Map;
       4: aload_1
       5: invokeinterface #51,  2           // InterfaceMethod java/util/Map.remove:(Ljava/lang/Object;)Ljava/lang/Object;
      10: checkcast     #52                 // class java/util/Map
      13: astore_2
      14: aload_2
      15: invokestatic  #53                 // Method org/apache/dubbo/common/utils/CollectionUtils.isNotEmptyMap:(Ljava/util/Map;)Z
      18: ifeq          175
      21: getstatic     #9                  // Field logger:Lorg/apache/dubbo/common/logger/ErrorTypeAwareLogger;
      24: new           #43                 // class java/lang/StringBuilder
      27: dup
      28: invokespecial #44                 // Method java/lang/StringBuilder."<init>":()V
      31: ldc           #54                 // String Evicting urls for service
      33: invokevirtual #46                 // Method java/lang/StringBuilder.append:(Ljava/lang/String;)Ljava/lang/StringBuilder;
      36: aload_1
      37: invokevirtual #55                 // Method org/apache/dubbo/common/URL.getServiceKey:()Ljava/lang/String;
      40: invokevirtual #46                 // Method java/lang/StringBuilder.append:(Ljava/lang/String;)Ljava/lang/StringBuilder;
      43: ldc           #56                 // String , size
      45: invokevirtual #46                 // Method java/lang/StringBuilder.append:(Ljava/lang/String;)Ljava/lang/StringBuilder;
      48: aload_2
      49: invokeinterface #57,  1           // InterfaceMethod java/util/Map.size:()I
      54: invokevirtual #58                 // Method java/lang/StringBuilder.append:(I)Ljava/lang/StringBuilder;
      57: invokevirtual #48                 // Method java/lang/StringBuilder.toString:()Ljava/lang/String;
      60: invokeinterface #59,  2           // InterfaceMethod org/apache/dubbo/common/logger/ErrorTypeAwareLogger.info:(Ljava/lang/String;)V
      65: invokestatic  #60                 // Method java/lang/System.currentTimeMillis:()J
      68: invokestatic  #61                 // Method java/lang/Long.valueOf:(J)Ljava/lang/Long;
      71: astore_3
      72: aload_2
      73: invokeinterface #62,  1           // InterfaceMethod java/util/Map.entrySet:()Ljava/util/Set;
      78: invokeinterface #63,  1           // InterfaceMethod java/util/Set.iterator:()Ljava/util/Iterator;
      83: astore        4
      85: aload         4
      87: invokeinterface #64,  1           // InterfaceMethod java/util/Iterator.hasNext:()Z
      92: ifeq          128
      95: aload         4
      97: invokeinterface #65,  1           // InterfaceMethod java/util/Iterator.next:()Ljava/lang/Object;
     102: checkcast     #66                 // class java/util/Map$Entry
     105: astore        5
     107: aload_0
     108: getfield      #10                 // Field waitForRemove:Ljava/util/Map;
     111: aload         5
     113: invokeinterface #67,  1           // InterfaceMethod java/util/Map$Entry.getValue:()Ljava/lang/Object;
     118: aload_3
     119: invokeinterface #24,  3           // InterfaceMethod java/util/Map.put:(Ljava/lang/Object;Ljava/lang/Object;)Ljava/lang/Object;
     124: pop
     125: goto          85
     128: aload_0
     129: getfield      #10                 // Field waitForRemove:Ljava/util/Map;
     132: invokestatic  #53                 // Method org/apache/dubbo/common/utils/CollectionUtils.isNotEmptyMap:(Ljava/util/Map;)Z
     135: ifeq          175
     138: aload_0
     139: getfield      #7                  // Field semaphore:Ljava/util/concurrent/Semaphore;
     142: invokevirtual #68                 // Method java/util/concurrent/Semaphore.tryAcquire:()Z
     145: ifeq          175
     148: aload_0
     149: getfield      #5                  // Field cacheRemovalScheduler:Ljava/util/concurrent/ScheduledExecutorService;
     152: new           #69                 // class org/apache/dubbo/registry/support/CacheableFailbackRegistry$RemovalTask
     155: dup
     156: aload_0
     157: aconst_null
     158: invokespecial #70                 // Method org/apache/dubbo/registry/support/CacheableFailbackRegistry$RemovalTask."<init>":(Lorg/apache/dubbo/registry/support/CacheableFailbackRegistry;Lorg/apache/dubbo/registry/support/CacheableFailbackRegistry$1;)V
     161: aload_0
     162: getfield      #6                  // Field cacheRemovalTaskIntervalInMillis:I
     165: i2l
     166: getstatic     #71                 // Field java/util/concurrent/TimeUnit.MILLISECONDS:Ljava/util/concurrent/TimeUnit;
     169: invokeinterface #72,  5           // InterfaceMethod java/util/concurrent/ScheduledExecutorService.schedule:(Ljava/lang/Runnable;JLjava/util/concurrent/TimeUnit;)Ljava/util/concurrent/ScheduledFuture;
     174: pop
     175: goto          216
     178: astore_3
     179: getstatic     #9                  // Field logger:Lorg/apache/dubbo/common/logger/ErrorTypeAwareLogger;
     182: ldc           #74                 // String 1-3
     184: ldc           #75                 // String thread pool getting destroyed
     186: ldc           #76                 // String
     188: new           #43                 // class java/lang/StringBuilder
     191: dup
     192: invokespecial #44                 // Method java/lang/StringBuilder."<init>":()V
     195: ldc           #77                 // String Failed to evict url for
     197: invokevirtual #46                 // Method java/lang/StringBuilder.append:(Ljava/lang/String;)Ljava/lang/StringBuilder;
     200: aload_1
     201: invokevirtual #55                 // Method org/apache/dubbo/common/URL.getServiceKey:()Ljava/lang/String;
     204: invokevirtual #46                 // Method java/lang/StringBuilder.append:(Ljava/lang/String;)Ljava/lang/StringBuilder;
     207: invokevirtual #48                 // Method java/lang/StringBuilder.toString:()Ljava/lang/String;
     210: aload_3
     211: invokeinterface #78,  6           // InterfaceMethod org/apache/dubbo/common/logger/ErrorTypeAwareLogger.warn:(Ljava/lang/String;Ljava/lang/String;Ljava/lang/String;Ljava/lang/String;Ljava/lang/Throwable;)V
     216: return
    Exception table:
       from    to  target type
          14   175   178   Class java/lang/Exception

  protected java.util.List<org.apache.dubbo.common.URL> toUrlsWithoutEmpty(org.apache.dubbo.common.URL, java.util.Collection<java.lang.String>);
    Code:
       0: aload_0
       1: getfield      #18                 // Field stringUrls:Ljava/util/Map;
       4: aload_1
       5: invokeinterface #79,  2           // InterfaceMethod java/util/Map.get:(Ljava/lang/Object;)Ljava/lang/Object;
      10: checkcast     #52                 // class java/util/Map
      13: astore_3
      14: new           #19                 // class java/util/HashMap
      17: dup
      18: aload_2
      19: invokeinterface #80,  1           // InterfaceMethod java/util/Collection.size:()I
      24: i2f
      25: ldc           #81                 // float 0.75f
      27: fdiv
      28: fconst_1
      29: fadd
      30: f2i
      31: invokespecial #20                 // Method java/util/HashMap."<init>":(I)V
      34: astore        4
      36: aload_0
      37: aload_1
      38: invokevirtual #82                 // Method removeParamsFromConsumer:(Lorg/apache/dubbo/common/URL;)Lorg/apache/dubbo/common/URL;
      41: astore        5
      43: aload_3
      44: ifnonnull     125
      47: aload_2
      48: invokeinterface #83,  1           // InterfaceMethod java/util/Collection.iterator:()Ljava/util/Iterator;
      53: astore        6
      55: aload         6
      57: invokeinterface #64,  1           // InterfaceMethod java/util/Iterator.hasNext:()Z
      62: ifeq          122
      65: aload         6
      67: invokeinterface #65,  1           // InterfaceMethod java/util/Iterator.next:()Ljava/lang/Object;
      72: checkcast     #84                 // class java/lang/String
      75: astore        7
      77: aload_0
      78: aload         7
      80: invokespecial #85                 // Method stripOffVariableKeys:(Ljava/lang/String;)Ljava/lang/String;
      83: astore        7
      85: aload_0
      86: aload         7
      88: aload         5
      90: aload_0
      91: invokevirtual #86                 // Method getExtraParameters:()Ljava/util/Map;
      94: invokevirtual #87                 // Method createURL:(Ljava/lang/String;Lorg/apache/dubbo/common/URL;Ljava/util/Map;)Lorg/apache/dubbo/common/url/component/ServiceAddressURL;
      97: astore        8
      99: aload         8
     101: ifnonnull     107
     104: goto          55
     107: aload         4
     109: aload         7
     111: aload         8
     113: invokeinterface #24,  3           // InterfaceMethod java/util/Map.put:(Ljava/lang/Object;Ljava/lang/Object;)Ljava/lang/Object;
     118: pop
     119: goto          55
     122: goto          218
     125: aload_2
     126: invokeinterface #83,  1           // InterfaceMethod java/util/Collection.iterator:()Ljava/util/Iterator;
     131: astore        6
     133: aload         6
     135: invokeinterface #64,  1           // InterfaceMethod java/util/Iterator.hasNext:()Z
     140: ifeq          218
     143: aload         6
     145: invokeinterface #65,  1           // InterfaceMethod java/util/Iterator.next:()Ljava/lang/Object;
     150: checkcast     #84                 // class java/lang/String
     153: astore        7
     155: aload_0
     156: aload         7
     158: invokespecial #85                 // Method stripOffVariableKeys:(Ljava/lang/String;)Ljava/lang/String;
     161: astore        7
     163: aload_3
     164: aload         7
     166: invokeinterface #51,  2           // InterfaceMethod java/util/Map.remove:(Ljava/lang/Object;)Ljava/lang/Object;
     171: checkcast     #88                 // class org/apache/dubbo/common/url/component/ServiceAddressURL
     174: astore        8
     176: aload         8
     178: ifnonnull     203
     181: aload_0
     182: aload         7
     184: aload         5
     186: aload_0
     187: invokevirtual #86                 // Method getExtraParameters:()Ljava/util/Map;
     190: invokevirtual #87                 // Method createURL:(Ljava/lang/String;Lorg/apache/dubbo/common/URL;Ljava/util/Map;)Lorg/apache/dubbo/common/url/component/ServiceAddressURL;
     193: astore        8
     195: aload         8
     197: ifnonnull     203
     200: goto          133
     203: aload         4
     205: aload         7
     207: aload         8
     209: invokeinterface #24,  3           // InterfaceMethod java/util/Map.put:(Ljava/lang/Object;Ljava/lang/Object;)Ljava/lang/Object;
     214: pop
     215: goto          133
     218: aload_0
     219: aload_1
     220: invokevirtual #50                 // Method evictURLCache:(Lorg/apache/dubbo/common/URL;)V
     223: aload_0
     224: getfield      #18                 // Field stringUrls:Ljava/util/Map;
     227: aload_1
     228: aload         4
     230: invokeinterface #24,  3           // InterfaceMethod java/util/Map.put:(Ljava/lang/Object;Ljava/lang/Object;)Ljava/lang/Object;
     235: pop
     236: new           #89                 // class java/util/ArrayList
     239: dup
     240: aload         4
     242: invokeinterface #90,  1           // InterfaceMethod java/util/Map.values:()Ljava/util/Collection;
     247: invokespecial #91                 // Method java/util/ArrayList."<init>":(Ljava/util/Collection;)V
     250: areturn

  protected java.util.List<org.apache.dubbo.common.URL> toUrlsWithEmpty(org.apache.dubbo.common.URL, java.lang.String, java.util.Collection<java.lang.String>);
    Code:
       0: new           #89                 // class java/util/ArrayList
       3: dup
       4: iconst_1
       5: invokespecial #92                 // Method java/util/ArrayList."<init>":(I)V
       8: astore        4
      10: aload_2
      11: ldc           #93                 // String providers
      13: invokevirtual #94                 // Method java/lang/String.endsWith:(Ljava/lang/String;)Z
      16: istore        5
      18: iload         5
      20: ifeq          49
      23: aload_3
      24: invokestatic  #95                 // Method org/apache/dubbo/common/utils/CollectionUtils.isNotEmpty:(Ljava/util/Collection;)Z
      27: ifeq          41
      30: aload_0
      31: aload_1
      32: aload_3
      33: invokevirtual #96                 // Method toUrlsWithoutEmpty:(Lorg/apache/dubbo/common/URL;Ljava/util/Collection;)Ljava/util/List;
      36: astore        4
      38: goto          64
      41: aload_0
      42: aload_1
      43: invokevirtual #50                 // Method evictURLCache:(Lorg/apache/dubbo/common/URL;)V
      46: goto          64
      49: aload_3
      50: invokestatic  #95                 // Method org/apache/dubbo/common/utils/CollectionUtils.isNotEmpty:(Ljava/util/Collection;)Z
      53: ifeq          64
      56: aload_0
      57: aload_1
      58: aload_3
      59: invokespecial #97                 // Method toConfiguratorsWithoutEmpty:(Lorg/apache/dubbo/common/URL;Ljava/util/Collection;)Ljava/util/List;
      62: astore        4
      64: aload         4
      66: invokeinterface #98,  1           // InterfaceMethod java/util/List.isEmpty:()Z
      71: ifeq          206
      74: aload_2
      75: ldc           #99                 // String /
      77: invokevirtual #100                // Method java/lang/String.lastIndexOf:(Ljava/lang/String;)I
      80: istore        6
      82: iload         6
      84: ifge          91
      87: aload_2
      88: goto          99
      91: aload_2
      92: iload         6
      94: iconst_1
      95: iadd
      96: invokevirtual #101                // Method java/lang/String.substring:(I)Ljava/lang/String;
      99: astore        7
     101: ldc           #93                 // String providers
     103: aload         7
     105: invokevirtual #102                // Method java/lang/String.equals:(Ljava/lang/Object;)Z
     108: ifeq          124
     111: aload_0
     112: invokevirtual #103                // Method getUrl:()Lorg/apache/dubbo/common/URL;
     115: ldc           #104                // String enable-empty-protection
     117: iconst_0
     118: invokevirtual #105                // Method org/apache/dubbo/common/URL.getParameter:(Ljava/lang/String;Z)Z
     121: ifne          206
     124: ldc           #93                 // String providers
     126: aload         7
     128: invokevirtual #102                // Method java/lang/String.equals:(Ljava/lang/Object;)Z
     131: ifeq          175
     134: getstatic     #9                  // Field logger:Lorg/apache/dubbo/common/logger/ErrorTypeAwareLogger;
     137: ldc           #106                // String 1-4
     139: ldc           #76                 // String
     141: ldc           #76                 // String
     143: new           #43                 // class java/lang/StringBuilder
     146: dup
     147: invokespecial #44                 // Method java/lang/StringBuilder."<init>":()V
     150: ldc           #107                // String Service
     152: invokevirtual #46                 // Method java/lang/StringBuilder.append:(Ljava/lang/String;)Ljava/lang/StringBuilder;
     155: aload_1
     156: invokevirtual #55                 // Method org/apache/dubbo/common/URL.getServiceKey:()Ljava/lang/String;
     159: invokevirtual #46                 // Method java/lang/StringBuilder.append:(Ljava/lang/String;)Ljava/lang/StringBuilder;
     162: ldc           #108                // String  received empty address list and empty protection is disabled, will clear current available addresses
     164: invokevirtual #46                 // Method java/lang/StringBuilder.append:(Ljava/lang/String;)Ljava/lang/StringBuilder;
     167: invokevirtual #48                 // Method java/lang/StringBuilder.toString:()Ljava/lang/String;
     170: invokeinterface #49,  5           // InterfaceMethod org/apache/dubbo/common/logger/ErrorTypeAwareLogger.warn:(Ljava/lang/String;Ljava/lang/String;Ljava/lang/String;Ljava/lang/String;)V
     175: aload_1
     176: invokestatic  #109                // Method org/apache/dubbo/common/URLBuilder.from:(Lorg/apache/dubbo/common/URL;)Lorg/apache/dubbo/common/URLBuilder;
     179: ldc           #110                // String empty
     181: invokevirtual #111                // Method org/apache/dubbo/common/URLBuilder.setProtocol:(Ljava/lang/String;)Lorg/apache/dubbo/common/URLBuilder;
     184: ldc           #112                // String category
     186: aload         7
     188: invokevirtual #113                // Method org/apache/dubbo/common/URLBuilder.addParameter:(Ljava/lang/String;Ljava/lang/String;)Lorg/apache/dubbo/common/URLBuilder;
     191: invokevirtual #114                // Method org/apache/dubbo/common/URLBuilder.build:()Lorg/apache/dubbo/common/url/component/ServiceConfigURL;
     194: astore        8
     196: aload         4
     198: aload         8
     200: invokeinterface #115,  2          // InterfaceMethod java/util/List.add:(Ljava/lang/Object;)Z
     205: pop
     206: aload         4
     208: areturn

  protected org.apache.dubbo.common.url.component.ServiceAddressURL createURL(java.lang.String, org.apache.dubbo.common.URL, java.util.Map<java.lang.String, java.lang.String>);
    Code:
       0: iconst_1
       1: istore        4
       3: aload_1
       4: ldc           #116                // String %3F
       6: invokevirtual #117                // Method java/lang/String.indexOf:(Ljava/lang/String;)I
       9: istore        5
      11: iload         5
      13: iconst_m1
      14: if_icmpne     20
      17: iconst_0
      18: istore        4
      20: aload_1
      21: iload         5
      23: invokestatic  #118                // Method org/apache/dubbo/common/URLStrParser.parseRawURLToArrays:(Ljava/lang/String;I)[Ljava/lang/String;
      26: astore        6
      28: aload         6
      30: arraylength
      31: iconst_1
      32: if_icmpgt     74
      35: getstatic     #9                  // Field logger:Lorg/apache/dubbo/common/logger/ErrorTypeAwareLogger;
      38: ldc           #119                // String 1-5
      40: ldc           #76                 // String
      42: ldc           #76                 // String
      44: new           #43                 // class java/lang/StringBuilder
      47: dup
      48: invokespecial #44                 // Method java/lang/StringBuilder."<init>":()V
      51: ldc           #120                // String Received url without any parameters
      53: invokevirtual #46                 // Method java/lang/StringBuilder.append:(Ljava/lang/String;)Ljava/lang/StringBuilder;
      56: aload_1
      57: invokevirtual #46                 // Method java/lang/StringBuilder.append:(Ljava/lang/String;)Ljava/lang/StringBuilder;
      60: invokevirtual #48                 // Method java/lang/StringBuilder.toString:()Ljava/lang/String;
      63: invokeinterface #49,  5           // InterfaceMethod org/apache/dubbo/common/logger/ErrorTypeAwareLogger.warn:(Ljava/lang/String;Ljava/lang/String;Ljava/lang/String;Ljava/lang/String;)V
      68: aload_1
      69: aload_2
      70: invokestatic  #121                // Method org/apache/dubbo/common/url/component/DubboServiceAddressURL.valueOf:(Ljava/lang/String;Lorg/apache/dubbo/common/URL;)Lorg/apache/dubbo/common/url/component/DubboServiceAddressURL;
      73: areturn
      74: aload         6
      76: iconst_0
      77: aaload
      78: astore        7
      80: aload         6
      82: iconst_1
      83: aaload
      84: astore        8
      86: iload         4
      88: istore        9
      90: aload_0
      91: getfield      #14                 // Field stringAddress:Ljava/util/concurrent/ConcurrentMap;
      94: aload         7
      96: aload_0
      97: iload         9
      99: invokedynamic #122,  0            // InvokeDynamic #0:apply:(Lorg/apache/dubbo/registry/support/CacheableFailbackRegistry;Z)Ljava/util/function/Function;
     104: invokestatic  #123                // Method org/apache/dubbo/common/utils/ConcurrentHashMapUtils.computeIfAbsent:(Ljava/util/concurrent/ConcurrentMap;Ljava/lang/Object;Ljava/util/function/Function;)Ljava/lang/Object;
     107: checkcast     #124                // class org/apache/dubbo/common/url/component/URLAddress
     110: astore        10
     112: aload         10
     114: invokestatic  #60                 // Method java/lang/System.currentTimeMillis:()J
     117: invokevirtual #125                // Method org/apache/dubbo/common/url/component/URLAddress.setTimestamp:(J)V
     120: aload_0
     121: getfield      #15                 // Field stringParam:Ljava/util/concurrent/ConcurrentMap;
     124: aload         8
     126: iload         9
     128: aload_3
     129: invokedynamic #126,  0            // InvokeDynamic #1:apply:(ZLjava/util/Map;)Ljava/util/function/Function;
     134: invokestatic  #123                // Method org/apache/dubbo/common/utils/ConcurrentHashMapUtils.computeIfAbsent:(Ljava/util/concurrent/ConcurrentMap;Ljava/lang/Object;Ljava/util/function/Function;)Ljava/lang/Object;
     137: checkcast     #127                // class org/apache/dubbo/common/url/component/URLParam
     140: astore        11
     142: aload         11
     144: invokestatic  #60                 // Method java/lang/System.currentTimeMillis:()J
     147: invokevirtual #128                // Method org/apache/dubbo/common/url/component/URLParam.setTimestamp:(J)V
     150: aload_0
     151: aload         10
     153: aload         11
     155: aload_2
     156: invokevirtual #129                // Method createServiceURL:(Lorg/apache/dubbo/common/url/component/URLAddress;Lorg/apache/dubbo/common/url/component/URLParam;Lorg/apache/dubbo/common/URL;)Lorg/apache/dubbo/common/url/component/ServiceAddressURL;
     159: astore        12
     161: aload_0
     162: aload_2
     163: aload         12
     165: invokevirtual #130                // Method isMatch:(Lorg/apache/dubbo/common/URL;Lorg/apache/dubbo/common/URL;)Z
     168: ifeq          174
     171: aload         12
     173: areturn
     174: aconst_null
     175: areturn

  protected org.apache.dubbo.common.url.component.ServiceAddressURL createServiceURL(org.apache.dubbo.common.url.component.URLAddress, org.apache.dubbo.common.url.component.URLParam, org.apache.dubbo.common.URL);
    Code:
       0: new           #131                // class org/apache/dubbo/common/url/component/DubboServiceAddressURL
       3: dup
       4: aload_1
       5: aload_2
       6: aload_3
       7: aconst_null
       8: invokespecial #132                // Method org/apache/dubbo/common/url/component/DubboServiceAddressURL."<init>":(Lorg/apache/dubbo/common/url/component/URLAddress;Lorg/apache/dubbo/common/url/component/URLParam;Lorg/apache/dubbo/common/URL;Lorg/apache/dubbo/common/url/component/ServiceConfigURL;)V
      11: areturn

  protected org.apache.dubbo.common.URL removeParamsFromConsumer(org.apache.dubbo.common.URL);
    Code:
       0: aload_1
       1: invokevirtual #133                // Method org/apache/dubbo/common/URL.getOrDefaultApplicationModel:()Lorg/apache/dubbo/rpc/model/ApplicationModel;
       4: ldc           #134                // class org/apache/dubbo/registry/ProviderFirstParams
       6: invokevirtual #135                // Method org/apache/dubbo/rpc/model/ApplicationModel.getExtensionLoader:(Ljava/lang/Class;)Lorg/apache/dubbo/common/extension/ExtensionLoader;
       9: invokevirtual #136                // Method org/apache/dubbo/common/extension/ExtensionLoader.getSupportedExtensionInstances:()Ljava/util/Set;
      12: astore_2
      13: aload_2
      14: invokestatic  #137                // Method org/apache/dubbo/common/utils/CollectionUtils.isEmpty:(Ljava/util/Collection;)Z
      17: ifeq          22
      20: aload_1
      21: areturn
      22: aload_2
      23: invokeinterface #63,  1           // InterfaceMethod java/util/Set.iterator:()Ljava/util/Iterator;
      28: astore_3
      29: aload_3
      30: invokeinterface #64,  1           // InterfaceMethod java/util/Iterator.hasNext:()Z
      35: ifeq          64
      38: aload_3
      39: invokeinterface #65,  1           // InterfaceMethod java/util/Iterator.next:()Ljava/lang/Object;
      44: checkcast     #134                // class org/apache/dubbo/registry/ProviderFirstParams
      47: astore        4
      49: aload_1
      50: aload         4
      52: invokeinterface #138,  1          // InterfaceMethod org/apache/dubbo/registry/ProviderFirstParams.params:()Ljava/util/Set;
      57: invokevirtual #139                // Method org/apache/dubbo/common/URL.removeParameters:(Ljava/util/Collection;)Lorg/apache/dubbo/common/URL;
      60: astore_1
      61: goto          29
      64: aload_1
      65: areturn

  private java.lang.String stripOffVariableKeys(java.lang.String);
    Code:
       0: aload_0
       1: invokevirtual #140                // Method getVariableKeys:()[Ljava/lang/String;
       4: astore_2
       5: aload_2
       6: ifnull        14
       9: aload_2
      10: arraylength
      11: ifne          16
      14: aload_1
      15: areturn
      16: aload_2
      17: astore_3
      18: aload_3
      19: arraylength
      20: istore        4
      22: iconst_0
      23: istore        5
      25: iload         5
      27: iload         4
      29: if_icmpge     127
      32: aload_3
      33: iload         5
      35: aaload
      36: astore        6
      38: aload_1
      39: aload         6
      41: invokevirtual #117                // Method java/lang/String.indexOf:(Ljava/lang/String;)I
      44: istore        7
      46: iload         7
      48: iconst_m1
      49: if_icmpne     55
      52: goto          121
      55: aload_1
      56: ldc           #141                // String %26
      58: iload         7
      60: invokevirtual #142                // Method java/lang/String.indexOf:(Ljava/lang/String;I)I
      63: istore        8
      65: aload_1
      66: iconst_0
      67: iload         7
      69: invokevirtual #143                // Method java/lang/String.substring:(II)Ljava/lang/String;
      72: astore        9
      74: iload         8
      76: iconst_m1
      77: if_icmpne     86
      80: aload         9
      82: astore_1
      83: goto          121
      86: aload_1
      87: iload         8
      89: ldc           #141                // String %26
      91: invokevirtual #144                // Method java/lang/String.length:()I
      94: iadd
      95: invokevirtual #101                // Method java/lang/String.substring:(I)Ljava/lang/String;
      98: astore        10
     100: new           #43                 // class java/lang/StringBuilder
     103: dup
     104: invokespecial #44                 // Method java/lang/StringBuilder."<init>":()V
     107: aload         9
     109: invokevirtual #46                 // Method java/lang/StringBuilder.append:(Ljava/lang/String;)Ljava/lang/StringBuilder;
     112: aload         10
     114: invokevirtual #46                 // Method java/lang/StringBuilder.append:(Ljava/lang/String;)Ljava/lang/StringBuilder;
     117: invokevirtual #48                 // Method java/lang/StringBuilder.toString:()Ljava/lang/String;
     120: astore_1
     121: iinc          5, 1
     124: goto          25
     127: aload_1
     128: ldc           #141                // String %26
     130: invokevirtual #94                 // Method java/lang/String.endsWith:(Ljava/lang/String;)Z
     133: ifeq          152
     136: aload_1
     137: iconst_0
     138: aload_1
     139: invokevirtual #144                // Method java/lang/String.length:()I
     142: ldc           #141                // String %26
     144: invokevirtual #144                // Method java/lang/String.length:()I
     147: isub
     148: invokevirtual #143                // Method java/lang/String.substring:(II)Ljava/lang/String;
     151: astore_1
     152: aload_1
     153: ldc           #116                // String %3F
     155: invokevirtual #94                 // Method java/lang/String.endsWith:(Ljava/lang/String;)Z
     158: ifeq          177
     161: aload_1
     162: iconst_0
     163: aload_1
     164: invokevirtual #144                // Method java/lang/String.length:()I
     167: ldc           #116                // String %3F
     169: invokevirtual #144                // Method java/lang/String.length:()I
     172: isub
     173: invokevirtual #143                // Method java/lang/String.substring:(II)Ljava/lang/String;
     176: astore_1
     177: aload_1
     178: areturn

  private java.util.List<org.apache.dubbo.common.URL> toConfiguratorsWithoutEmpty(org.apache.dubbo.common.URL, java.util.Collection<java.lang.String>);
    Code:
       0: new           #89                 // class java/util/ArrayList
       3: dup
       4: invokespecial #145                // Method java/util/ArrayList."<init>":()V
       7: astore_3
       8: aload_2
       9: invokestatic  #95                 // Method org/apache/dubbo/common/utils/CollectionUtils.isNotEmpty:(Ljava/util/Collection;)Z
      12: ifeq          84
      15: aload_2
      16: invokeinterface #83,  1           // InterfaceMethod java/util/Collection.iterator:()Ljava/util/Iterator;
      21: astore        4
      23: aload         4
      25: invokeinterface #64,  1           // InterfaceMethod java/util/Iterator.hasNext:()Z
      30: ifeq          84
      33: aload         4
      35: invokeinterface #65,  1           // InterfaceMethod java/util/Iterator.next:()Ljava/lang/Object;
      40: checkcast     #84                 // class java/lang/String
      43: astore        5
      45: aload         5
      47: getstatic     #146                // Field org/apache/dubbo/common/constants/CommonConstants.PROTOCOL_SEPARATOR_ENCODED:Ljava/lang/String;
      50: invokevirtual #147                // Method java/lang/String.contains:(Ljava/lang/CharSequence;)Z
      53: ifeq          81
      56: aload         5
      58: invokestatic  #148                // Method org/apache/dubbo/common/URLStrParser.parseEncodedStr:(Ljava/lang/String;)Lorg/apache/dubbo/common/URL;
      61: astore        6
      63: aload_1
      64: aload         6
      66: invokestatic  #149                // Method org/apache/dubbo/common/utils/UrlUtils.isMatch:(Lorg/apache/dubbo/common/URL;Lorg/apache/dubbo/common/URL;)Z
      69: ifeq          81
      72: aload_3
      73: aload         6
      75: invokeinterface #115,  2          // InterfaceMethod java/util/List.add:(Ljava/lang/Object;)Z
      80: pop
      81: goto          23
      84: aload_3
      85: areturn

  protected java.util.Map<java.lang.String, java.lang.String> getExtraParameters();
    Code:
       0: aload_0
       1: getfield      #21                 // Field extraParameters:Ljava/util/Map;
       4: areturn

  protected java.lang.String[] getVariableKeys();
    Code:
       0: getstatic     #150                // Field VARIABLE_KEYS:[Ljava/lang/String;
       3: areturn

  protected java.lang.String getDefaultURLProtocol();
    Code:
       0: ldc           #151                // String dubbo
       2: areturn

  protected java.util.concurrent.Semaphore getSemaphore();
    Code:
       0: aload_0
       1: getfield      #7                  // Field semaphore:Ljava/util/concurrent/Semaphore;
       4: areturn

  protected abstract boolean isMatch(org.apache.dubbo.common.URL, org.apache.dubbo.common.URL);

  private static org.apache.dubbo.common.url.component.URLParam lambda$createURL$1(boolean, java.util.Map, java.lang.String);
    Code:
       0: aload_2
       1: iload_0
       2: aload_1
       3: invokestatic  #152                // Method org/apache/dubbo/common/url/component/URLParam.parse:(Ljava/lang/String;ZLjava/util/Map;)Lorg/apache/dubbo/common/url/component/URLParam;
       6: areturn

  private org.apache.dubbo.common.url.component.URLAddress lambda$createURL$0(boolean, java.lang.String);
    Code:
       0: aload_2
       1: aload_0
       2: invokevirtual #153                // Method getDefaultURLProtocol:()Ljava/lang/String;
       5: iload_1
       6: invokestatic  #154                // Method org/apache/dubbo/common/url/component/URLAddress.parse:(Ljava/lang/String;Ljava/lang/String;Z)Lorg/apache/dubbo/common/url/component/URLAddress;
       9: areturn

  static java.util.Map access$100(org.apache.dubbo.registry.support.CacheableFailbackRegistry);
    Code:
       0: aload_0
       1: getfield      #10                 // Field waitForRemove:Ljava/util/Map;
       4: areturn

  static org.apache.dubbo.common.logger.ErrorTypeAwareLogger access$200();
    Code:
       0: getstatic     #9                  // Field logger:Lorg/apache/dubbo/common/logger/ErrorTypeAwareLogger;
       3: areturn

  static int access$300(org.apache.dubbo.registry.support.CacheableFailbackRegistry);
    Code:
       0: aload_0
       1: getfield      #8                  // Field cacheClearWaitingThresholdInMillis:I
       4: ireturn

  static java.util.concurrent.Semaphore access$400(org.apache.dubbo.registry.support.CacheableFailbackRegistry);
    Code:
       0: aload_0
       1: getfield      #7                  // Field semaphore:Ljava/util/concurrent/Semaphore;
       4: areturn

  static int access$500(org.apache.dubbo.registry.support.CacheableFailbackRegistry);
    Code:
       0: aload_0
       1: getfield      #6                  // Field cacheRemovalTaskIntervalInMillis:I
       4: ireturn

  static java.util.concurrent.ScheduledExecutorService access$600(org.apache.dubbo.registry.support.CacheableFailbackRegistry);
    Code:
       0: aload_0
       1: getfield      #5                  // Field cacheRemovalScheduler:Ljava/util/concurrent/ScheduledExecutorService;
       4: areturn

  static {};
    Code:
       0: ldc           #155                // class org/apache/dubbo/registry/support/CacheableFailbackRegistry
       2: invokestatic  #156                // Method org/apache/dubbo/common/logger/LoggerFactory.getErrorTypeAwareLogger:(Ljava/lang/Class;)Lorg/apache/dubbo/common/logger/ErrorTypeAwareLogger;
       5: putstatic     #9                  // Field logger:Lorg/apache/dubbo/common/logger/ErrorTypeAwareLogger;
       8: iconst_2
       9: anewarray     #84                 // class java/lang/String
      12: dup
      13: iconst_0
      14: ldc           #157                // String timestamp%3D
      16: aastore
      17: dup
      18: iconst_1
      19: ldc           #158                // String pid%3D
      21: aastore
      22: putstatic     #150                // Field VARIABLE_KEYS:[Ljava/lang/String;
      25: return
}
