Compiled from "CacheableFailbackRegistry.java"
class org.apache.dubbo.registry.support.CacheableFailbackRegistry$RemovalTask implements java.lang.Runnable {
  final org.apache.dubbo.registry.support.CacheableFailbackRegistry this$0;

  private org.apache.dubbo.registry.support.CacheableFailbackRegistry$RemovalTask(org.apache.dubbo.registry.support.CacheableFailbackRegistry);
    Code:
       0: aload_0
       1: aload_1
       2: putfield      #3                  // Field this$0:Lorg/apache/dubbo/registry/support/CacheableFailbackRegistry;
       5: aload_0
       6: invokespecial #4                  // Method java/lang/Object."<init>":()V
       9: return

  public void run();
    Code:
       0: invokestatic  #5                  // Method org/apache/dubbo/registry/support/CacheableFailbackRegistry.access$200:()Lorg/apache/dubbo/common/logger/ErrorTypeAwareLogger;
       3: new           #6                  // class java/lang/StringBuilder
       6: dup
       7: invokespecial #7                  // Method java/lang/StringBuilder."<init>":()V
      10: ldc           #8                  // String Clearing cached URLs, waiting to clear size
      12: invokevirtual #9                  // Method java/lang/StringBuilder.append:(Ljava/lang/String;)Ljava/lang/StringBuilder;
      15: aload_0
      16: getfield      #3                  // Field this$0:Lorg/apache/dubbo/registry/support/CacheableFailbackRegistry;
      19: invokestatic  #10                 // Method org/apache/dubbo/registry/support/CacheableFailbackRegistry.access$100:(Lorg/apache/dubbo/registry/support/CacheableFailbackRegistry;)Ljava/util/Map;
      22: invokeinterface #11,  1           // InterfaceMethod java/util/Map.size:()I
      27: invokevirtual #12                 // Method java/lang/StringBuilder.append:(I)Ljava/lang/StringBuilder;
      30: invokevirtual #13                 // Method java/lang/StringBuilder.toString:()Ljava/lang/String;
      33: invokeinterface #14,  2           // InterfaceMethod org/apache/dubbo/common/logger/ErrorTypeAwareLogger.info:(Ljava/lang/String;)V
      38: iconst_0
      39: istore_1
      40: aload_0
      41: getfield      #3                  // Field this$0:Lorg/apache/dubbo/registry/support/CacheableFailbackRegistry;
      44: invokestatic  #10                 // Method org/apache/dubbo/registry/support/CacheableFailbackRegistry.access$100:(Lorg/apache/dubbo/registry/support/CacheableFailbackRegistry;)Ljava/util/Map;
      47: invokeinterface #15,  1           // InterfaceMethod java/util/Map.entrySet:()Ljava/util/Set;
      52: invokeinterface #16,  1           // InterfaceMethod java/util/Set.iterator:()Ljava/util/Iterator;
      57: astore_2
      58: aload_2
      59: invokeinterface #17,  1           // InterfaceMethod java/util/Iterator.hasNext:()Z
      64: ifeq          226
      67: aload_2
      68: invokeinterface #18,  1           // InterfaceMethod java/util/Iterator.next:()Ljava/lang/Object;
      73: checkcast     #19                 // class java/util/Map$Entry
      76: astore_3
      77: aload_3
      78: invokeinterface #20,  1           // InterfaceMethod java/util/Map$Entry.getKey:()Ljava/lang/Object;
      83: checkcast     #21                 // class org/apache/dubbo/common/url/component/ServiceAddressURL
      86: astore        4
      88: aload_3
      89: invokeinterface #22,  1           // InterfaceMethod java/util/Map$Entry.getValue:()Ljava/lang/Object;
      94: checkcast     #23                 // class java/lang/Long
      97: invokevirtual #24                 // Method java/lang/Long.longValue:()J
     100: lstore        5
     102: invokestatic  #25                 // Method java/lang/System.currentTimeMillis:()J
     105: lstore        7
     107: lload         7
     109: lload         5
     111: lsub
     112: aload_0
     113: getfield      #3                  // Field this$0:Lorg/apache/dubbo/registry/support/CacheableFailbackRegistry;
     116: invokestatic  #26                 // Method org/apache/dubbo/registry/support/CacheableFailbackRegistry.access$300:(Lorg/apache/dubbo/registry/support/CacheableFailbackRegistry;)I
     119: i2l
     120: lcmp
     121: iflt          223
     124: aload         4
     126: invokevirtual #27                 // Method org/apache/dubbo/common/url/component/ServiceAddressURL.getUrlAddress:()Lorg/apache/dubbo/common/url/component/URLAddress;
     129: astore        9
     131: aload         4
     133: invokevirtual #28                 // Method org/apache/dubbo/common/url/component/ServiceAddressURL.getUrlParam:()Lorg/apache/dubbo/common/url/component/URLParam;
     136: astore        10
     138: lload         7
     140: aload         9
     142: invokevirtual #29                 // Method org/apache/dubbo/common/url/component/URLAddress.getTimestamp:()J
     145: lsub
     146: aload_0
     147: getfield      #3                  // Field this$0:Lorg/apache/dubbo/registry/support/CacheableFailbackRegistry;
     150: invokestatic  #26                 // Method org/apache/dubbo/registry/support/CacheableFailbackRegistry.access$300:(Lorg/apache/dubbo/registry/support/CacheableFailbackRegistry;)I
     153: i2l
     154: lcmp
     155: iflt          176
     158: aload_0
     159: getfield      #3                  // Field this$0:Lorg/apache/dubbo/registry/support/CacheableFailbackRegistry;
     162: getfield      #30                 // Field org/apache/dubbo/registry/support/CacheableFailbackRegistry.stringAddress:Ljava/util/concurrent/ConcurrentMap;
     165: aload         9
     167: invokevirtual #31                 // Method org/apache/dubbo/common/url/component/URLAddress.getRawAddress:()Ljava/lang/String;
     170: invokeinterface #32,  2           // InterfaceMethod java/util/concurrent/ConcurrentMap.remove:(Ljava/lang/Object;)Ljava/lang/Object;
     175: pop
     176: lload         7
     178: aload         10
     180: invokevirtual #33                 // Method org/apache/dubbo/common/url/component/URLParam.getTimestamp:()J
     183: lsub
     184: aload_0
     185: getfield      #3                  // Field this$0:Lorg/apache/dubbo/registry/support/CacheableFailbackRegistry;
     188: invokestatic  #26                 // Method org/apache/dubbo/registry/support/CacheableFailbackRegistry.access$300:(Lorg/apache/dubbo/registry/support/CacheableFailbackRegistry;)I
     191: i2l
     192: lcmp
     193: iflt          214
     196: aload_0
     197: getfield      #3                  // Field this$0:Lorg/apache/dubbo/registry/support/CacheableFailbackRegistry;
     200: getfield      #34                 // Field org/apache/dubbo/registry/support/CacheableFailbackRegistry.stringParam:Ljava/util/concurrent/ConcurrentMap;
     203: aload         10
     205: invokevirtual #35                 // Method org/apache/dubbo/common/url/component/URLParam.getRawParam:()Ljava/lang/String;
     208: invokeinterface #32,  2           // InterfaceMethod java/util/concurrent/ConcurrentMap.remove:(Ljava/lang/Object;)Ljava/lang/Object;
     213: pop
     214: aload_2
     215: invokeinterface #36,  1           // InterfaceMethod java/util/Iterator.remove:()V
     220: iinc          1, 1
     223: goto          58
     226: aload_0
     227: getfield      #3                  // Field this$0:Lorg/apache/dubbo/registry/support/CacheableFailbackRegistry;
     230: invokestatic  #37                 // Method org/apache/dubbo/registry/support/CacheableFailbackRegistry.access$400:(Lorg/apache/dubbo/registry/support/CacheableFailbackRegistry;)Ljava/util/concurrent/Semaphore;
     233: invokevirtual #38                 // Method java/util/concurrent/Semaphore.release:()V
     236: goto          285
     239: astore_2
     240: invokestatic  #5                  // Method org/apache/dubbo/registry/support/CacheableFailbackRegistry.access$200:()Lorg/apache/dubbo/common/logger/ErrorTypeAwareLogger;
     243: ldc           #40                 // String 1-6
     245: ldc           #41                 // String
     247: ldc           #41                 // String
     249: ldc           #42                 // String Error occurred when clearing cached URLs
     251: aload_2
     252: invokeinterface #43,  6           // InterfaceMethod org/apache/dubbo/common/logger/ErrorTypeAwareLogger.error:(Ljava/lang/String;Ljava/lang/String;Ljava/lang/String;Ljava/lang/String;Ljava/lang/Throwable;)V
     257: aload_0
     258: getfield      #3                  // Field this$0:Lorg/apache/dubbo/registry/support/CacheableFailbackRegistry;
     261: invokestatic  #37                 // Method org/apache/dubbo/registry/support/CacheableFailbackRegistry.access$400:(Lorg/apache/dubbo/registry/support/CacheableFailbackRegistry;)Ljava/util/concurrent/Semaphore;
     264: invokevirtual #38                 // Method java/util/concurrent/Semaphore.release:()V
     267: goto          285
     270: astore        11
     272: aload_0
     273: getfield      #3                  // Field this$0:Lorg/apache/dubbo/registry/support/CacheableFailbackRegistry;
     276: invokestatic  #37                 // Method org/apache/dubbo/registry/support/CacheableFailbackRegistry.access$400:(Lorg/apache/dubbo/registry/support/CacheableFailbackRegistry;)Ljava/util/concurrent/Semaphore;
     279: invokevirtual #38                 // Method java/util/concurrent/Semaphore.release:()V
     282: aload         11
     284: athrow
     285: invokestatic  #5                  // Method org/apache/dubbo/registry/support/CacheableFailbackRegistry.access$200:()Lorg/apache/dubbo/common/logger/ErrorTypeAwareLogger;
     288: new           #6                  // class java/lang/StringBuilder
     291: dup
     292: invokespecial #7                  // Method java/lang/StringBuilder."<init>":()V
     295: ldc           #44                 // String Clear cached URLs, size
     297: invokevirtual #9                  // Method java/lang/StringBuilder.append:(Ljava/lang/String;)Ljava/lang/StringBuilder;
     300: iload_1
     301: invokevirtual #12                 // Method java/lang/StringBuilder.append:(I)Ljava/lang/StringBuilder;
     304: invokevirtual #13                 // Method java/lang/StringBuilder.toString:()Ljava/lang/String;
     307: invokeinterface #14,  2           // InterfaceMethod org/apache/dubbo/common/logger/ErrorTypeAwareLogger.info:(Ljava/lang/String;)V
     312: aload_0
     313: getfield      #3                  // Field this$0:Lorg/apache/dubbo/registry/support/CacheableFailbackRegistry;
     316: invokestatic  #10                 // Method org/apache/dubbo/registry/support/CacheableFailbackRegistry.access$100:(Lorg/apache/dubbo/registry/support/CacheableFailbackRegistry;)Ljava/util/Map;
     319: invokestatic  #45                 // Method org/apache/dubbo/common/utils/CollectionUtils.isNotEmptyMap:(Ljava/util/Map;)Z
     322: ifeq          373
     325: aload_0
     326: getfield      #3                  // Field this$0:Lorg/apache/dubbo/registry/support/CacheableFailbackRegistry;
     329: invokestatic  #37                 // Method org/apache/dubbo/registry/support/CacheableFailbackRegistry.access$400:(Lorg/apache/dubbo/registry/support/CacheableFailbackRegistry;)Ljava/util/concurrent/Semaphore;
     332: invokevirtual #46                 // Method java/util/concurrent/Semaphore.tryAcquire:()Z
     335: ifeq          373
     338: aload_0
     339: getfield      #3                  // Field this$0:Lorg/apache/dubbo/registry/support/CacheableFailbackRegistry;
     342: invokestatic  #47                 // Method org/apache/dubbo/registry/support/CacheableFailbackRegistry.access$600:(Lorg/apache/dubbo/registry/support/CacheableFailbackRegistry;)Ljava/util/concurrent/ScheduledExecutorService;
     345: new           #48                 // class org/apache/dubbo/registry/support/CacheableFailbackRegistry$RemovalTask
     348: dup
     349: aload_0
     350: getfield      #3                  // Field this$0:Lorg/apache/dubbo/registry/support/CacheableFailbackRegistry;
     353: invokespecial #2                  // Method "<init>":(Lorg/apache/dubbo/registry/support/CacheableFailbackRegistry;)V
     356: aload_0
     357: getfield      #3                  // Field this$0:Lorg/apache/dubbo/registry/support/CacheableFailbackRegistry;
     360: invokestatic  #49                 // Method org/apache/dubbo/registry/support/CacheableFailbackRegistry.access$500:(Lorg/apache/dubbo/registry/support/CacheableFailbackRegistry;)I
     363: i2l
     364: getstatic     #50                 // Field java/util/concurrent/TimeUnit.MILLISECONDS:Ljava/util/concurrent/TimeUnit;
     367: invokeinterface #51,  5           // InterfaceMethod java/util/concurrent/ScheduledExecutorService.schedule:(Ljava/lang/Runnable;JLjava/util/concurrent/TimeUnit;)Ljava/util/concurrent/ScheduledFuture;
     372: pop
     373: return
    Exception table:
       from    to  target type
          40   226   239   Class java/lang/Throwable
          40   226   270   any
         239   257   270   any
         270   272   270   any

  org.apache.dubbo.registry.support.CacheableFailbackRegistry$RemovalTask(org.apache.dubbo.registry.support.CacheableFailbackRegistry, org.apache.dubbo.registry.support.CacheableFailbackRegistry$1);
    Code:
       0: aload_0
       1: aload_1
       2: invokespecial #2                  // Method "<init>":(Lorg/apache/dubbo/registry/support/CacheableFailbackRegistry;)V
       5: return
}
