Compiled from "DefaultProviderFirstParams.java"
public class org.apache.dubbo.registry.support.DefaultProviderFirstParams implements org.apache.dubbo.registry.ProviderFirstParams {
  private static final java.util.Set<java.lang.String> PARAMS;

  public org.apache.dubbo.registry.support.DefaultProviderFirstParams();
    Code:
       0: aload_0
       1: invokespecial #1                  // Method java/lang/Object."<init>":()V
       4: return

  public java.util.Set<java.lang.String> params();
    Code:
       0: getstatic     #2                  // Field PARAMS:Ljava/util/Set;
       3: areturn

  static {};
    Code:
       0: new           #3                  // class org/apache/dubbo/registry/support/DefaultProviderFirstParams$1
       3: dup
       4: invokespecial #4                  // Method org/apache/dubbo/registry/support/DefaultProviderFirstParams$1."<init>":()V
       7: invokestatic  #5                  // Method java/util/Collections.unmodifiableSet:(Ljava/util/Set;)Ljava/util/Set;
      10: putstatic     #2                  // Field PARAMS:Ljava/util/Set;
      13: return
}
