Compiled from "FailbackRegistry.java"
class org.apache.dubbo.registry.support.FailbackRegistry$Holder {
  private final org.apache.dubbo.common.URL url;

  private final org.apache.dubbo.registry.NotifyListener notifyListener;

  org.apache.dubbo.registry.support.FailbackRegistry$Holder(org.apache.dubbo.common.URL, org.apache.dubbo.registry.NotifyListener);
    Code:
       0: aload_0
       1: invokespecial #1                  // Method java/lang/Object."<init>":()V
       4: aload_1
       5: ifnull        12
       8: aload_2
       9: ifnonnull     20
      12: new           #2                  // class java/lang/IllegalArgumentException
      15: dup
      16: invokespecial #3                  // Method java/lang/IllegalArgumentException."<init>":()V
      19: athrow
      20: aload_0
      21: aload_1
      22: putfield      #4                  // Field url:Lorg/apache/dubbo/common/URL;
      25: aload_0
      26: aload_2
      27: putfield      #5                  // Field notifyListener:Lorg/apache/dubbo/registry/NotifyListener;
      30: return

  public int hashCode();
    Code:
       0: aload_0
       1: getfield      #4                  // Field url:Lorg/apache/dubbo/common/URL;
       4: invokevirtual #6                  // Method org/apache/dubbo/common/URL.hashCode:()I
       7: aload_0
       8: getfield      #5                  // Field notifyListener:Lorg/apache/dubbo/registry/NotifyListener;
      11: invokevirtual #7                  // Method java/lang/Object.hashCode:()I
      14: iadd
      15: ireturn

  public boolean equals(java.lang.Object);
    Code:
       0: aload_1
       1: instanceof    #8                  // class org/apache/dubbo/registry/support/FailbackRegistry$Holder
       4: ifeq          46
       7: aload_1
       8: checkcast     #8                  // class org/apache/dubbo/registry/support/FailbackRegistry$Holder
      11: astore_2
      12: aload_0
      13: getfield      #4                  // Field url:Lorg/apache/dubbo/common/URL;
      16: aload_2
      17: getfield      #4                  // Field url:Lorg/apache/dubbo/common/URL;
      20: invokevirtual #9                  // Method org/apache/dubbo/common/URL.equals:(Ljava/lang/Object;)Z
      23: ifeq          44
      26: aload_0
      27: getfield      #5                  // Field notifyListener:Lorg/apache/dubbo/registry/NotifyListener;
      30: aload_2
      31: getfield      #5                  // Field notifyListener:Lorg/apache/dubbo/registry/NotifyListener;
      34: invokevirtual #10                 // Method java/lang/Object.equals:(Ljava/lang/Object;)Z
      37: ifeq          44
      40: iconst_1
      41: goto          45
      44: iconst_0
      45: ireturn
      46: iconst_0
      47: ireturn
}
