Compiled from "FailbackRegistry.java"
public abstract class org.apache.dubbo.registry.support.FailbackRegistry extends org.apache.dubbo.registry.support.AbstractRegistry {
  private final java.util.concurrent.ConcurrentMap<org.apache.dubbo.common.URL, org.apache.dubbo.registry.retry.FailedRegisteredTask> failedRegistered;

  private final java.util.concurrent.ConcurrentMap<org.apache.dubbo.common.URL, org.apache.dubbo.registry.retry.FailedUnregisteredTask> failedUnregistered;

  private final java.util.concurrent.ConcurrentMap<org.apache.dubbo.registry.support.FailbackRegistry$Holder, org.apache.dubbo.registry.retry.FailedSubscribedTask> failedSubscribed;

  private final java.util.concurrent.ConcurrentMap<org.apache.dubbo.registry.support.FailbackRegistry$Holder, org.apache.dubbo.registry.retry.FailedUnsubscribedTask> failedUnsubscribed;

  private final int retryPeriod;

  private final org.apache.dubbo.common.timer.HashedWheelTimer retryTimer;

  public org.apache.dubbo.registry.support.FailbackRegistry(org.apache.dubbo.common.URL);
    Code:
       0: aload_0
       1: aload_1
       2: invokespecial #3                  // Method org/apache/dubbo/registry/support/AbstractRegistry."<init>":(Lorg/apache/dubbo/common/URL;)V
       5: aload_0
       6: new           #4                  // class java/util/concurrent/ConcurrentHashMap
       9: dup
      10: invokespecial #5                  // Method java/util/concurrent/ConcurrentHashMap."<init>":()V
      13: putfield      #6                  // Field failedRegistered:Ljava/util/concurrent/ConcurrentMap;
      16: aload_0
      17: new           #4                  // class java/util/concurrent/ConcurrentHashMap
      20: dup
      21: invokespecial #5                  // Method java/util/concurrent/ConcurrentHashMap."<init>":()V
      24: putfield      #7                  // Field failedUnregistered:Ljava/util/concurrent/ConcurrentMap;
      27: aload_0
      28: new           #4                  // class java/util/concurrent/ConcurrentHashMap
      31: dup
      32: invokespecial #5                  // Method java/util/concurrent/ConcurrentHashMap."<init>":()V
      35: putfield      #8                  // Field failedSubscribed:Ljava/util/concurrent/ConcurrentMap;
      38: aload_0
      39: new           #4                  // class java/util/concurrent/ConcurrentHashMap
      42: dup
      43: invokespecial #5                  // Method java/util/concurrent/ConcurrentHashMap."<init>":()V
      46: putfield      #9                  // Field failedUnsubscribed:Ljava/util/concurrent/ConcurrentMap;
      49: aload_0
      50: aload_1
      51: ldc           #10                 // String retry.period
      53: sipush        5000
      56: invokevirtual #11                 // Method org/apache/dubbo/common/URL.getParameter:(Ljava/lang/String;I)I
      59: putfield      #12                 // Field retryPeriod:I
      62: aload_0
      63: new           #13                 // class org/apache/dubbo/common/timer/HashedWheelTimer
      66: dup
      67: new           #14                 // class org/apache/dubbo/common/utils/NamedThreadFactory
      70: dup
      71: ldc           #15                 // String DubboRegistryRetryTimer
      73: iconst_1
      74: invokespecial #16                 // Method org/apache/dubbo/common/utils/NamedThreadFactory."<init>":(Ljava/lang/String;Z)V
      77: aload_0
      78: getfield      #12                 // Field retryPeriod:I
      81: i2l
      82: getstatic     #17                 // Field java/util/concurrent/TimeUnit.MILLISECONDS:Ljava/util/concurrent/TimeUnit;
      85: sipush        128
      88: invokespecial #18                 // Method org/apache/dubbo/common/timer/HashedWheelTimer."<init>":(Ljava/util/concurrent/ThreadFactory;JLjava/util/concurrent/TimeUnit;I)V
      91: putfield      #19                 // Field retryTimer:Lorg/apache/dubbo/common/timer/HashedWheelTimer;
      94: return

  public void removeFailedRegisteredTask(org.apache.dubbo.common.URL);
    Code:
       0: aload_0
       1: getfield      #6                  // Field failedRegistered:Ljava/util/concurrent/ConcurrentMap;
       4: aload_1
       5: invokeinterface #20,  2           // InterfaceMethod java/util/concurrent/ConcurrentMap.remove:(Ljava/lang/Object;)Ljava/lang/Object;
      10: pop
      11: return

  public void removeFailedUnregisteredTask(org.apache.dubbo.common.URL);
    Code:
       0: aload_0
       1: getfield      #7                  // Field failedUnregistered:Ljava/util/concurrent/ConcurrentMap;
       4: aload_1
       5: invokeinterface #20,  2           // InterfaceMethod java/util/concurrent/ConcurrentMap.remove:(Ljava/lang/Object;)Ljava/lang/Object;
      10: pop
      11: return

  public void removeFailedSubscribedTask(org.apache.dubbo.common.URL, org.apache.dubbo.registry.NotifyListener);
    Code:
       0: new           #21                 // class org/apache/dubbo/registry/support/FailbackRegistry$Holder
       3: dup
       4: aload_1
       5: aload_2
       6: invokespecial #22                 // Method org/apache/dubbo/registry/support/FailbackRegistry$Holder."<init>":(Lorg/apache/dubbo/common/URL;Lorg/apache/dubbo/registry/NotifyListener;)V
       9: astore_3
      10: aload_0
      11: getfield      #8                  // Field failedSubscribed:Ljava/util/concurrent/ConcurrentMap;
      14: aload_3
      15: invokeinterface #20,  2           // InterfaceMethod java/util/concurrent/ConcurrentMap.remove:(Ljava/lang/Object;)Ljava/lang/Object;
      20: pop
      21: return

  public void removeFailedUnsubscribedTask(org.apache.dubbo.common.URL, org.apache.dubbo.registry.NotifyListener);
    Code:
       0: new           #21                 // class org/apache/dubbo/registry/support/FailbackRegistry$Holder
       3: dup
       4: aload_1
       5: aload_2
       6: invokespecial #22                 // Method org/apache/dubbo/registry/support/FailbackRegistry$Holder."<init>":(Lorg/apache/dubbo/common/URL;Lorg/apache/dubbo/registry/NotifyListener;)V
       9: astore_3
      10: aload_0
      11: getfield      #9                  // Field failedUnsubscribed:Ljava/util/concurrent/ConcurrentMap;
      14: aload_3
      15: invokeinterface #20,  2           // InterfaceMethod java/util/concurrent/ConcurrentMap.remove:(Ljava/lang/Object;)Ljava/lang/Object;
      20: pop
      21: return

  private void addFailedRegistered(org.apache.dubbo.common.URL);
    Code:
       0: aload_0
       1: getfield      #6                  // Field failedRegistered:Ljava/util/concurrent/ConcurrentMap;
       4: aload_1
       5: invokeinterface #23,  2           // InterfaceMethod java/util/concurrent/ConcurrentMap.get:(Ljava/lang/Object;)Ljava/lang/Object;
      10: checkcast     #24                 // class org/apache/dubbo/registry/retry/FailedRegisteredTask
      13: astore_2
      14: aload_2
      15: ifnull        19
      18: return
      19: new           #24                 // class org/apache/dubbo/registry/retry/FailedRegisteredTask
      22: dup
      23: aload_1
      24: aload_0
      25: invokespecial #25                 // Method org/apache/dubbo/registry/retry/FailedRegisteredTask."<init>":(Lorg/apache/dubbo/common/URL;Lorg/apache/dubbo/registry/support/FailbackRegistry;)V
      28: astore_3
      29: aload_0
      30: getfield      #6                  // Field failedRegistered:Ljava/util/concurrent/ConcurrentMap;
      33: aload_1
      34: aload_3
      35: invokeinterface #26,  3           // InterfaceMethod java/util/concurrent/ConcurrentMap.putIfAbsent:(Ljava/lang/Object;Ljava/lang/Object;)Ljava/lang/Object;
      40: checkcast     #24                 // class org/apache/dubbo/registry/retry/FailedRegisteredTask
      43: astore_2
      44: aload_2
      45: ifnonnull     65
      48: aload_0
      49: getfield      #19                 // Field retryTimer:Lorg/apache/dubbo/common/timer/HashedWheelTimer;
      52: aload_3
      53: aload_0
      54: getfield      #12                 // Field retryPeriod:I
      57: i2l
      58: getstatic     #17                 // Field java/util/concurrent/TimeUnit.MILLISECONDS:Ljava/util/concurrent/TimeUnit;
      61: invokevirtual #27                 // Method org/apache/dubbo/common/timer/HashedWheelTimer.newTimeout:(Lorg/apache/dubbo/common/timer/TimerTask;JLjava/util/concurrent/TimeUnit;)Lorg/apache/dubbo/common/timer/Timeout;
      64: pop
      65: return

  private void removeFailedRegistered(org.apache.dubbo.common.URL);
    Code:
       0: aload_0
       1: getfield      #6                  // Field failedRegistered:Ljava/util/concurrent/ConcurrentMap;
       4: aload_1
       5: invokeinterface #20,  2           // InterfaceMethod java/util/concurrent/ConcurrentMap.remove:(Ljava/lang/Object;)Ljava/lang/Object;
      10: checkcast     #24                 // class org/apache/dubbo/registry/retry/FailedRegisteredTask
      13: astore_2
      14: aload_2
      15: ifnull        22
      18: aload_2
      19: invokevirtual #28                 // Method org/apache/dubbo/registry/retry/FailedRegisteredTask.cancel:()V
      22: return

  private void addFailedUnregistered(org.apache.dubbo.common.URL);
    Code:
       0: aload_0
       1: getfield      #7                  // Field failedUnregistered:Ljava/util/concurrent/ConcurrentMap;
       4: aload_1
       5: invokeinterface #23,  2           // InterfaceMethod java/util/concurrent/ConcurrentMap.get:(Ljava/lang/Object;)Ljava/lang/Object;
      10: checkcast     #29                 // class org/apache/dubbo/registry/retry/FailedUnregisteredTask
      13: astore_2
      14: aload_2
      15: ifnull        19
      18: return
      19: new           #29                 // class org/apache/dubbo/registry/retry/FailedUnregisteredTask
      22: dup
      23: aload_1
      24: aload_0
      25: invokespecial #30                 // Method org/apache/dubbo/registry/retry/FailedUnregisteredTask."<init>":(Lorg/apache/dubbo/common/URL;Lorg/apache/dubbo/registry/support/FailbackRegistry;)V
      28: astore_3
      29: aload_0
      30: getfield      #7                  // Field failedUnregistered:Ljava/util/concurrent/ConcurrentMap;
      33: aload_1
      34: aload_3
      35: invokeinterface #26,  3           // InterfaceMethod java/util/concurrent/ConcurrentMap.putIfAbsent:(Ljava/lang/Object;Ljava/lang/Object;)Ljava/lang/Object;
      40: checkcast     #29                 // class org/apache/dubbo/registry/retry/FailedUnregisteredTask
      43: astore_2
      44: aload_2
      45: ifnonnull     65
      48: aload_0
      49: getfield      #19                 // Field retryTimer:Lorg/apache/dubbo/common/timer/HashedWheelTimer;
      52: aload_3
      53: aload_0
      54: getfield      #12                 // Field retryPeriod:I
      57: i2l
      58: getstatic     #17                 // Field java/util/concurrent/TimeUnit.MILLISECONDS:Ljava/util/concurrent/TimeUnit;
      61: invokevirtual #27                 // Method org/apache/dubbo/common/timer/HashedWheelTimer.newTimeout:(Lorg/apache/dubbo/common/timer/TimerTask;JLjava/util/concurrent/TimeUnit;)Lorg/apache/dubbo/common/timer/Timeout;
      64: pop
      65: return

  private void removeFailedUnregistered(org.apache.dubbo.common.URL);
    Code:
       0: aload_0
       1: getfield      #7                  // Field failedUnregistered:Ljava/util/concurrent/ConcurrentMap;
       4: aload_1
       5: invokeinterface #20,  2           // InterfaceMethod java/util/concurrent/ConcurrentMap.remove:(Ljava/lang/Object;)Ljava/lang/Object;
      10: checkcast     #29                 // class org/apache/dubbo/registry/retry/FailedUnregisteredTask
      13: astore_2
      14: aload_2
      15: ifnull        22
      18: aload_2
      19: invokevirtual #31                 // Method org/apache/dubbo/registry/retry/FailedUnregisteredTask.cancel:()V
      22: return

  protected void addFailedSubscribed(org.apache.dubbo.common.URL, org.apache.dubbo.registry.NotifyListener);
    Code:
       0: new           #21                 // class org/apache/dubbo/registry/support/FailbackRegistry$Holder
       3: dup
       4: aload_1
       5: aload_2
       6: invokespecial #22                 // Method org/apache/dubbo/registry/support/FailbackRegistry$Holder."<init>":(Lorg/apache/dubbo/common/URL;Lorg/apache/dubbo/registry/NotifyListener;)V
       9: astore_3
      10: aload_0
      11: getfield      #8                  // Field failedSubscribed:Ljava/util/concurrent/ConcurrentMap;
      14: aload_3
      15: invokeinterface #23,  2           // InterfaceMethod java/util/concurrent/ConcurrentMap.get:(Ljava/lang/Object;)Ljava/lang/Object;
      20: checkcast     #32                 // class org/apache/dubbo/registry/retry/FailedSubscribedTask
      23: astore        4
      25: aload         4
      27: ifnull        31
      30: return
      31: new           #32                 // class org/apache/dubbo/registry/retry/FailedSubscribedTask
      34: dup
      35: aload_1
      36: aload_0
      37: aload_2
      38: invokespecial #33                 // Method org/apache/dubbo/registry/retry/FailedSubscribedTask."<init>":(Lorg/apache/dubbo/common/URL;Lorg/apache/dubbo/registry/support/FailbackRegistry;Lorg/apache/dubbo/registry/NotifyListener;)V
      41: astore        5
      43: aload_0
      44: getfield      #8                  // Field failedSubscribed:Ljava/util/concurrent/ConcurrentMap;
      47: aload_3
      48: aload         5
      50: invokeinterface #26,  3           // InterfaceMethod java/util/concurrent/ConcurrentMap.putIfAbsent:(Ljava/lang/Object;Ljava/lang/Object;)Ljava/lang/Object;
      55: checkcast     #32                 // class org/apache/dubbo/registry/retry/FailedSubscribedTask
      58: astore        4
      60: aload         4
      62: ifnonnull     83
      65: aload_0
      66: getfield      #19                 // Field retryTimer:Lorg/apache/dubbo/common/timer/HashedWheelTimer;
      69: aload         5
      71: aload_0
      72: getfield      #12                 // Field retryPeriod:I
      75: i2l
      76: getstatic     #17                 // Field java/util/concurrent/TimeUnit.MILLISECONDS:Ljava/util/concurrent/TimeUnit;
      79: invokevirtual #27                 // Method org/apache/dubbo/common/timer/HashedWheelTimer.newTimeout:(Lorg/apache/dubbo/common/timer/TimerTask;JLjava/util/concurrent/TimeUnit;)Lorg/apache/dubbo/common/timer/Timeout;
      82: pop
      83: return

  public void removeFailedSubscribed(org.apache.dubbo.common.URL, org.apache.dubbo.registry.NotifyListener);
    Code:
       0: new           #21                 // class org/apache/dubbo/registry/support/FailbackRegistry$Holder
       3: dup
       4: aload_1
       5: aload_2
       6: invokespecial #22                 // Method org/apache/dubbo/registry/support/FailbackRegistry$Holder."<init>":(Lorg/apache/dubbo/common/URL;Lorg/apache/dubbo/registry/NotifyListener;)V
       9: astore_3
      10: aload_0
      11: getfield      #8                  // Field failedSubscribed:Ljava/util/concurrent/ConcurrentMap;
      14: aload_3
      15: invokeinterface #20,  2           // InterfaceMethod java/util/concurrent/ConcurrentMap.remove:(Ljava/lang/Object;)Ljava/lang/Object;
      20: checkcast     #32                 // class org/apache/dubbo/registry/retry/FailedSubscribedTask
      23: astore        4
      25: aload         4
      27: ifnull        35
      30: aload         4
      32: invokevirtual #34                 // Method org/apache/dubbo/registry/retry/FailedSubscribedTask.cancel:()V
      35: aload_0
      36: aload_1
      37: aload_2
      38: invokespecial #35                 // Method removeFailedUnsubscribed:(Lorg/apache/dubbo/common/URL;Lorg/apache/dubbo/registry/NotifyListener;)V
      41: return

  private void addFailedUnsubscribed(org.apache.dubbo.common.URL, org.apache.dubbo.registry.NotifyListener);
    Code:
       0: new           #21                 // class org/apache/dubbo/registry/support/FailbackRegistry$Holder
       3: dup
       4: aload_1
       5: aload_2
       6: invokespecial #22                 // Method org/apache/dubbo/registry/support/FailbackRegistry$Holder."<init>":(Lorg/apache/dubbo/common/URL;Lorg/apache/dubbo/registry/NotifyListener;)V
       9: astore_3
      10: aload_0
      11: getfield      #9                  // Field failedUnsubscribed:Ljava/util/concurrent/ConcurrentMap;
      14: aload_3
      15: invokeinterface #23,  2           // InterfaceMethod java/util/concurrent/ConcurrentMap.get:(Ljava/lang/Object;)Ljava/lang/Object;
      20: checkcast     #36                 // class org/apache/dubbo/registry/retry/FailedUnsubscribedTask
      23: astore        4
      25: aload         4
      27: ifnull        31
      30: return
      31: new           #36                 // class org/apache/dubbo/registry/retry/FailedUnsubscribedTask
      34: dup
      35: aload_1
      36: aload_0
      37: aload_2
      38: invokespecial #37                 // Method org/apache/dubbo/registry/retry/FailedUnsubscribedTask."<init>":(Lorg/apache/dubbo/common/URL;Lorg/apache/dubbo/registry/support/FailbackRegistry;Lorg/apache/dubbo/registry/NotifyListener;)V
      41: astore        5
      43: aload_0
      44: getfield      #9                  // Field failedUnsubscribed:Ljava/util/concurrent/ConcurrentMap;
      47: aload_3
      48: aload         5
      50: invokeinterface #26,  3           // InterfaceMethod java/util/concurrent/ConcurrentMap.putIfAbsent:(Ljava/lang/Object;Ljava/lang/Object;)Ljava/lang/Object;
      55: checkcast     #36                 // class org/apache/dubbo/registry/retry/FailedUnsubscribedTask
      58: astore        4
      60: aload         4
      62: ifnonnull     83
      65: aload_0
      66: getfield      #19                 // Field retryTimer:Lorg/apache/dubbo/common/timer/HashedWheelTimer;
      69: aload         5
      71: aload_0
      72: getfield      #12                 // Field retryPeriod:I
      75: i2l
      76: getstatic     #17                 // Field java/util/concurrent/TimeUnit.MILLISECONDS:Ljava/util/concurrent/TimeUnit;
      79: invokevirtual #27                 // Method org/apache/dubbo/common/timer/HashedWheelTimer.newTimeout:(Lorg/apache/dubbo/common/timer/TimerTask;JLjava/util/concurrent/TimeUnit;)Lorg/apache/dubbo/common/timer/Timeout;
      82: pop
      83: return

  private void removeFailedUnsubscribed(org.apache.dubbo.common.URL, org.apache.dubbo.registry.NotifyListener);
    Code:
       0: new           #21                 // class org/apache/dubbo/registry/support/FailbackRegistry$Holder
       3: dup
       4: aload_1
       5: aload_2
       6: invokespecial #22                 // Method org/apache/dubbo/registry/support/FailbackRegistry$Holder."<init>":(Lorg/apache/dubbo/common/URL;Lorg/apache/dubbo/registry/NotifyListener;)V
       9: astore_3
      10: aload_0
      11: getfield      #9                  // Field failedUnsubscribed:Ljava/util/concurrent/ConcurrentMap;
      14: aload_3
      15: invokeinterface #20,  2           // InterfaceMethod java/util/concurrent/ConcurrentMap.remove:(Ljava/lang/Object;)Ljava/lang/Object;
      20: checkcast     #36                 // class org/apache/dubbo/registry/retry/FailedUnsubscribedTask
      23: astore        4
      25: aload         4
      27: ifnull        35
      30: aload         4
      32: invokevirtual #38                 // Method org/apache/dubbo/registry/retry/FailedUnsubscribedTask.cancel:()V
      35: return

  java.util.concurrent.ConcurrentMap<org.apache.dubbo.common.URL, org.apache.dubbo.registry.retry.FailedRegisteredTask> getFailedRegistered();
    Code:
       0: aload_0
       1: getfield      #6                  // Field failedRegistered:Ljava/util/concurrent/ConcurrentMap;
       4: areturn

  java.util.concurrent.ConcurrentMap<org.apache.dubbo.common.URL, org.apache.dubbo.registry.retry.FailedUnregisteredTask> getFailedUnregistered();
    Code:
       0: aload_0
       1: getfield      #7                  // Field failedUnregistered:Ljava/util/concurrent/ConcurrentMap;
       4: areturn

  java.util.concurrent.ConcurrentMap<org.apache.dubbo.registry.support.FailbackRegistry$Holder, org.apache.dubbo.registry.retry.FailedSubscribedTask> getFailedSubscribed();
    Code:
       0: aload_0
       1: getfield      #8                  // Field failedSubscribed:Ljava/util/concurrent/ConcurrentMap;
       4: areturn

  java.util.concurrent.ConcurrentMap<org.apache.dubbo.registry.support.FailbackRegistry$Holder, org.apache.dubbo.registry.retry.FailedUnsubscribedTask> getFailedUnsubscribed();
    Code:
       0: aload_0
       1: getfield      #9                  // Field failedUnsubscribed:Ljava/util/concurrent/ConcurrentMap;
       4: areturn

  public void register(org.apache.dubbo.common.URL);
    Code:
       0: aload_0
       1: aload_1
       2: invokevirtual #39                 // Method acceptable:(Lorg/apache/dubbo/common/URL;)Z
       5: ifne          54
       8: aload_0
       9: getfield      #40                 // Field logger:Lorg/apache/dubbo/common/logger/ErrorTypeAwareLogger;
      12: new           #41                 // class java/lang/StringBuilder
      15: dup
      16: invokespecial #42                 // Method java/lang/StringBuilder."<init>":()V
      19: ldc           #43                 // String URL
      21: invokevirtual #44                 // Method java/lang/StringBuilder.append:(Ljava/lang/String;)Ljava/lang/StringBuilder;
      24: aload_1
      25: invokevirtual #45                 // Method java/lang/StringBuilder.append:(Ljava/lang/Object;)Ljava/lang/StringBuilder;
      28: ldc           #46                 // String  will not be registered to Registry. Registry
      30: invokevirtual #44                 // Method java/lang/StringBuilder.append:(Ljava/lang/String;)Ljava/lang/StringBuilder;
      33: aload_0
      34: invokevirtual #47                 // Method getUrl:()Lorg/apache/dubbo/common/URL;
      37: invokevirtual #45                 // Method java/lang/StringBuilder.append:(Ljava/lang/Object;)Ljava/lang/StringBuilder;
      40: ldc           #48                 // String  does not accept service of this protocol type.
      42: invokevirtual #44                 // Method java/lang/StringBuilder.append:(Ljava/lang/String;)Ljava/lang/StringBuilder;
      45: invokevirtual #49                 // Method java/lang/StringBuilder.toString:()Ljava/lang/String;
      48: invokeinterface #50,  2           // InterfaceMethod org/apache/dubbo/common/logger/ErrorTypeAwareLogger.info:(Ljava/lang/String;)V
      53: return
      54: aload_0
      55: aload_1
      56: invokespecial #51                 // Method org/apache/dubbo/registry/support/AbstractRegistry.register:(Lorg/apache/dubbo/common/URL;)V
      59: aload_0
      60: aload_1
      61: invokespecial #52                 // Method removeFailedRegistered:(Lorg/apache/dubbo/common/URL;)V
      64: aload_0
      65: aload_1
      66: invokespecial #53                 // Method removeFailedUnregistered:(Lorg/apache/dubbo/common/URL;)V
      69: aload_0
      70: aload_1
      71: invokevirtual #54                 // Method doRegister:(Lorg/apache/dubbo/common/URL;)V
      74: goto          250
      77: astore_2
      78: aload_2
      79: astore_3
      80: aload_0
      81: invokevirtual #47                 // Method getUrl:()Lorg/apache/dubbo/common/URL;
      84: ldc           #57                 // String check
      86: iconst_1
      87: invokevirtual #58                 // Method org/apache/dubbo/common/URL.getParameter:(Ljava/lang/String;Z)Z
      90: ifeq          114
      93: aload_1
      94: ldc           #57                 // String check
      96: iconst_1
      97: invokevirtual #58                 // Method org/apache/dubbo/common/URL.getParameter:(Ljava/lang/String;Z)Z
     100: ifeq          114
     103: aload_1
     104: invokevirtual #59                 // Method org/apache/dubbo/common/URL.getPort:()I
     107: ifeq          114
     110: iconst_1
     111: goto          115
     114: iconst_0
     115: istore        4
     117: aload_3
     118: instanceof    #60                 // class org/apache/dubbo/registry/support/SkipFailbackWrapperException
     121: istore        5
     123: iload         4
     125: ifne          133
     128: iload         5
     130: ifeq          198
     133: iload         5
     135: ifeq          143
     138: aload_3
     139: invokevirtual #61                 // Method java/lang/Throwable.getCause:()Ljava/lang/Throwable;
     142: astore_3
     143: new           #62                 // class java/lang/IllegalStateException
     146: dup
     147: new           #41                 // class java/lang/StringBuilder
     150: dup
     151: invokespecial #42                 // Method java/lang/StringBuilder."<init>":()V
     154: ldc           #63                 // String Failed to register
     156: invokevirtual #44                 // Method java/lang/StringBuilder.append:(Ljava/lang/String;)Ljava/lang/StringBuilder;
     159: aload_1
     160: invokevirtual #45                 // Method java/lang/StringBuilder.append:(Ljava/lang/Object;)Ljava/lang/StringBuilder;
     163: ldc           #64                 // String  to registry
     165: invokevirtual #44                 // Method java/lang/StringBuilder.append:(Ljava/lang/String;)Ljava/lang/StringBuilder;
     168: aload_0
     169: invokevirtual #47                 // Method getUrl:()Lorg/apache/dubbo/common/URL;
     172: invokevirtual #65                 // Method org/apache/dubbo/common/URL.getAddress:()Ljava/lang/String;
     175: invokevirtual #44                 // Method java/lang/StringBuilder.append:(Ljava/lang/String;)Ljava/lang/StringBuilder;
     178: ldc           #66                 // String , cause:
     180: invokevirtual #44                 // Method java/lang/StringBuilder.append:(Ljava/lang/String;)Ljava/lang/StringBuilder;
     183: aload_3
     184: invokevirtual #67                 // Method java/lang/Throwable.getMessage:()Ljava/lang/String;
     187: invokevirtual #44                 // Method java/lang/StringBuilder.append:(Ljava/lang/String;)Ljava/lang/StringBuilder;
     190: invokevirtual #49                 // Method java/lang/StringBuilder.toString:()Ljava/lang/String;
     193: aload_3
     194: invokespecial #68                 // Method java/lang/IllegalStateException."<init>":(Ljava/lang/String;Ljava/lang/Throwable;)V
     197: athrow
     198: aload_0
     199: getfield      #40                 // Field logger:Lorg/apache/dubbo/common/logger/ErrorTypeAwareLogger;
     202: ldc           #69                 // String 99-0
     204: ldc           #70                 // String unknown error in registry module
     206: ldc           #71                 // String
     208: new           #41                 // class java/lang/StringBuilder
     211: dup
     212: invokespecial #42                 // Method java/lang/StringBuilder."<init>":()V
     215: ldc           #63                 // String Failed to register
     217: invokevirtual #44                 // Method java/lang/StringBuilder.append:(Ljava/lang/String;)Ljava/lang/StringBuilder;
     220: aload_1
     221: invokevirtual #45                 // Method java/lang/StringBuilder.append:(Ljava/lang/Object;)Ljava/lang/StringBuilder;
     224: ldc           #72                 // String , waiting for retry, cause:
     226: invokevirtual #44                 // Method java/lang/StringBuilder.append:(Ljava/lang/String;)Ljava/lang/StringBuilder;
     229: aload_3
     230: invokevirtual #67                 // Method java/lang/Throwable.getMessage:()Ljava/lang/String;
     233: invokevirtual #44                 // Method java/lang/StringBuilder.append:(Ljava/lang/String;)Ljava/lang/StringBuilder;
     236: invokevirtual #49                 // Method java/lang/StringBuilder.toString:()Ljava/lang/String;
     239: aload_3
     240: invokeinterface #73,  6           // InterfaceMethod org/apache/dubbo/common/logger/ErrorTypeAwareLogger.error:(Ljava/lang/String;Ljava/lang/String;Ljava/lang/String;Ljava/lang/String;Ljava/lang/Throwable;)V
     245: aload_0
     246: aload_1
     247: invokespecial #74                 // Method addFailedRegistered:(Lorg/apache/dubbo/common/URL;)V
     250: return
    Exception table:
       from    to  target type
          69    74    77   Class java/lang/Exception

  public void reExportRegister(org.apache.dubbo.common.URL);
    Code:
       0: aload_0
       1: aload_1
       2: invokevirtual #39                 // Method acceptable:(Lorg/apache/dubbo/common/URL;)Z
       5: ifne          51
       8: aload_0
       9: getfield      #40                 // Field logger:Lorg/apache/dubbo/common/logger/ErrorTypeAwareLogger;
      12: new           #41                 // class java/lang/StringBuilder
      15: dup
      16: invokespecial #42                 // Method java/lang/StringBuilder."<init>":()V
      19: ldc           #43                 // String URL
      21: invokevirtual #44                 // Method java/lang/StringBuilder.append:(Ljava/lang/String;)Ljava/lang/StringBuilder;
      24: aload_1
      25: invokevirtual #45                 // Method java/lang/StringBuilder.append:(Ljava/lang/Object;)Ljava/lang/StringBuilder;
      28: ldc           #46                 // String  will not be registered to Registry. Registry
      30: invokevirtual #44                 // Method java/lang/StringBuilder.append:(Ljava/lang/String;)Ljava/lang/StringBuilder;
      33: aload_1
      34: invokevirtual #45                 // Method java/lang/StringBuilder.append:(Ljava/lang/Object;)Ljava/lang/StringBuilder;
      37: ldc           #48                 // String  does not accept service of this protocol type.
      39: invokevirtual #44                 // Method java/lang/StringBuilder.append:(Ljava/lang/String;)Ljava/lang/StringBuilder;
      42: invokevirtual #49                 // Method java/lang/StringBuilder.toString:()Ljava/lang/String;
      45: invokeinterface #50,  2           // InterfaceMethod org/apache/dubbo/common/logger/ErrorTypeAwareLogger.info:(Ljava/lang/String;)V
      50: return
      51: aload_0
      52: aload_1
      53: invokespecial #51                 // Method org/apache/dubbo/registry/support/AbstractRegistry.register:(Lorg/apache/dubbo/common/URL;)V
      56: aload_0
      57: aload_1
      58: invokespecial #52                 // Method removeFailedRegistered:(Lorg/apache/dubbo/common/URL;)V
      61: aload_0
      62: aload_1
      63: invokespecial #53                 // Method removeFailedUnregistered:(Lorg/apache/dubbo/common/URL;)V
      66: aload_0
      67: aload_1
      68: invokevirtual #54                 // Method doRegister:(Lorg/apache/dubbo/common/URL;)V
      71: goto          137
      74: astore_2
      75: aload_2
      76: instanceof    #60                 // class org/apache/dubbo/registry/support/SkipFailbackWrapperException
      79: ifne          137
      82: new           #62                 // class java/lang/IllegalStateException
      85: dup
      86: new           #41                 // class java/lang/StringBuilder
      89: dup
      90: invokespecial #42                 // Method java/lang/StringBuilder."<init>":()V
      93: ldc           #75                 // String Failed to register (re-export)
      95: invokevirtual #44                 // Method java/lang/StringBuilder.append:(Ljava/lang/String;)Ljava/lang/StringBuilder;
      98: aload_1
      99: invokevirtual #45                 // Method java/lang/StringBuilder.append:(Ljava/lang/Object;)Ljava/lang/StringBuilder;
     102: ldc           #64                 // String  to registry
     104: invokevirtual #44                 // Method java/lang/StringBuilder.append:(Ljava/lang/String;)Ljava/lang/StringBuilder;
     107: aload_0
     108: invokevirtual #47                 // Method getUrl:()Lorg/apache/dubbo/common/URL;
     111: invokevirtual #65                 // Method org/apache/dubbo/common/URL.getAddress:()Ljava/lang/String;
     114: invokevirtual #44                 // Method java/lang/StringBuilder.append:(Ljava/lang/String;)Ljava/lang/StringBuilder;
     117: ldc           #66                 // String , cause:
     119: invokevirtual #44                 // Method java/lang/StringBuilder.append:(Ljava/lang/String;)Ljava/lang/StringBuilder;
     122: aload_2
     123: invokevirtual #76                 // Method java/lang/Exception.getMessage:()Ljava/lang/String;
     126: invokevirtual #44                 // Method java/lang/StringBuilder.append:(Ljava/lang/String;)Ljava/lang/StringBuilder;
     129: invokevirtual #49                 // Method java/lang/StringBuilder.toString:()Ljava/lang/String;
     132: aload_2
     133: invokespecial #68                 // Method java/lang/IllegalStateException."<init>":(Ljava/lang/String;Ljava/lang/Throwable;)V
     136: athrow
     137: return
    Exception table:
       from    to  target type
          66    71    74   Class java/lang/Exception

  public void unregister(org.apache.dubbo.common.URL);
    Code:
       0: aload_0
       1: aload_1
       2: invokespecial #77                 // Method org/apache/dubbo/registry/support/AbstractRegistry.unregister:(Lorg/apache/dubbo/common/URL;)V
       5: aload_0
       6: aload_1
       7: invokespecial #52                 // Method removeFailedRegistered:(Lorg/apache/dubbo/common/URL;)V
      10: aload_0
      11: aload_1
      12: invokespecial #53                 // Method removeFailedUnregistered:(Lorg/apache/dubbo/common/URL;)V
      15: aload_0
      16: aload_1
      17: invokevirtual #78                 // Method doUnregister:(Lorg/apache/dubbo/common/URL;)V
      20: goto          196
      23: astore_2
      24: aload_2
      25: astore_3
      26: aload_0
      27: invokevirtual #47                 // Method getUrl:()Lorg/apache/dubbo/common/URL;
      30: ldc           #57                 // String check
      32: iconst_1
      33: invokevirtual #58                 // Method org/apache/dubbo/common/URL.getParameter:(Ljava/lang/String;Z)Z
      36: ifeq          60
      39: aload_1
      40: ldc           #57                 // String check
      42: iconst_1
      43: invokevirtual #58                 // Method org/apache/dubbo/common/URL.getParameter:(Ljava/lang/String;Z)Z
      46: ifeq          60
      49: aload_1
      50: invokevirtual #59                 // Method org/apache/dubbo/common/URL.getPort:()I
      53: ifeq          60
      56: iconst_1
      57: goto          61
      60: iconst_0
      61: istore        4
      63: aload_3
      64: instanceof    #60                 // class org/apache/dubbo/registry/support/SkipFailbackWrapperException
      67: istore        5
      69: iload         4
      71: ifne          79
      74: iload         5
      76: ifeq          144
      79: iload         5
      81: ifeq          89
      84: aload_3
      85: invokevirtual #61                 // Method java/lang/Throwable.getCause:()Ljava/lang/Throwable;
      88: astore_3
      89: new           #62                 // class java/lang/IllegalStateException
      92: dup
      93: new           #41                 // class java/lang/StringBuilder
      96: dup
      97: invokespecial #42                 // Method java/lang/StringBuilder."<init>":()V
     100: ldc           #79                 // String Failed to unregister
     102: invokevirtual #44                 // Method java/lang/StringBuilder.append:(Ljava/lang/String;)Ljava/lang/StringBuilder;
     105: aload_1
     106: invokevirtual #45                 // Method java/lang/StringBuilder.append:(Ljava/lang/Object;)Ljava/lang/StringBuilder;
     109: ldc           #64                 // String  to registry
     111: invokevirtual #44                 // Method java/lang/StringBuilder.append:(Ljava/lang/String;)Ljava/lang/StringBuilder;
     114: aload_0
     115: invokevirtual #47                 // Method getUrl:()Lorg/apache/dubbo/common/URL;
     118: invokevirtual #65                 // Method org/apache/dubbo/common/URL.getAddress:()Ljava/lang/String;
     121: invokevirtual #44                 // Method java/lang/StringBuilder.append:(Ljava/lang/String;)Ljava/lang/StringBuilder;
     124: ldc           #66                 // String , cause:
     126: invokevirtual #44                 // Method java/lang/StringBuilder.append:(Ljava/lang/String;)Ljava/lang/StringBuilder;
     129: aload_3
     130: invokevirtual #67                 // Method java/lang/Throwable.getMessage:()Ljava/lang/String;
     133: invokevirtual #44                 // Method java/lang/StringBuilder.append:(Ljava/lang/String;)Ljava/lang/StringBuilder;
     136: invokevirtual #49                 // Method java/lang/StringBuilder.toString:()Ljava/lang/String;
     139: aload_3
     140: invokespecial #68                 // Method java/lang/IllegalStateException."<init>":(Ljava/lang/String;Ljava/lang/Throwable;)V
     143: athrow
     144: aload_0
     145: getfield      #40                 // Field logger:Lorg/apache/dubbo/common/logger/ErrorTypeAwareLogger;
     148: ldc           #69                 // String 99-0
     150: ldc           #70                 // String unknown error in registry module
     152: ldc           #71                 // String
     154: new           #41                 // class java/lang/StringBuilder
     157: dup
     158: invokespecial #42                 // Method java/lang/StringBuilder."<init>":()V
     161: ldc           #79                 // String Failed to unregister
     163: invokevirtual #44                 // Method java/lang/StringBuilder.append:(Ljava/lang/String;)Ljava/lang/StringBuilder;
     166: aload_1
     167: invokevirtual #45                 // Method java/lang/StringBuilder.append:(Ljava/lang/Object;)Ljava/lang/StringBuilder;
     170: ldc           #72                 // String , waiting for retry, cause:
     172: invokevirtual #44                 // Method java/lang/StringBuilder.append:(Ljava/lang/String;)Ljava/lang/StringBuilder;
     175: aload_3
     176: invokevirtual #67                 // Method java/lang/Throwable.getMessage:()Ljava/lang/String;
     179: invokevirtual #44                 // Method java/lang/StringBuilder.append:(Ljava/lang/String;)Ljava/lang/StringBuilder;
     182: invokevirtual #49                 // Method java/lang/StringBuilder.toString:()Ljava/lang/String;
     185: aload_3
     186: invokeinterface #73,  6           // InterfaceMethod org/apache/dubbo/common/logger/ErrorTypeAwareLogger.error:(Ljava/lang/String;Ljava/lang/String;Ljava/lang/String;Ljava/lang/String;Ljava/lang/Throwable;)V
     191: aload_0
     192: aload_1
     193: invokespecial #80                 // Method addFailedUnregistered:(Lorg/apache/dubbo/common/URL;)V
     196: return
    Exception table:
       from    to  target type
          15    20    23   Class java/lang/Exception

  public void reExportUnregister(org.apache.dubbo.common.URL);
    Code:
       0: aload_0
       1: aload_1
       2: invokespecial #77                 // Method org/apache/dubbo/registry/support/AbstractRegistry.unregister:(Lorg/apache/dubbo/common/URL;)V
       5: aload_0
       6: aload_1
       7: invokespecial #52                 // Method removeFailedRegistered:(Lorg/apache/dubbo/common/URL;)V
      10: aload_0
      11: aload_1
      12: invokespecial #53                 // Method removeFailedUnregistered:(Lorg/apache/dubbo/common/URL;)V
      15: aload_0
      16: aload_1
      17: invokevirtual #78                 // Method doUnregister:(Lorg/apache/dubbo/common/URL;)V
      20: goto          86
      23: astore_2
      24: aload_2
      25: instanceof    #60                 // class org/apache/dubbo/registry/support/SkipFailbackWrapperException
      28: ifne          86
      31: new           #62                 // class java/lang/IllegalStateException
      34: dup
      35: new           #41                 // class java/lang/StringBuilder
      38: dup
      39: invokespecial #42                 // Method java/lang/StringBuilder."<init>":()V
      42: ldc           #81                 // String Failed to unregister(re-export)
      44: invokevirtual #44                 // Method java/lang/StringBuilder.append:(Ljava/lang/String;)Ljava/lang/StringBuilder;
      47: aload_1
      48: invokevirtual #45                 // Method java/lang/StringBuilder.append:(Ljava/lang/Object;)Ljava/lang/StringBuilder;
      51: ldc           #64                 // String  to registry
      53: invokevirtual #44                 // Method java/lang/StringBuilder.append:(Ljava/lang/String;)Ljava/lang/StringBuilder;
      56: aload_0
      57: invokevirtual #47                 // Method getUrl:()Lorg/apache/dubbo/common/URL;
      60: invokevirtual #65                 // Method org/apache/dubbo/common/URL.getAddress:()Ljava/lang/String;
      63: invokevirtual #44                 // Method java/lang/StringBuilder.append:(Ljava/lang/String;)Ljava/lang/StringBuilder;
      66: ldc           #66                 // String , cause:
      68: invokevirtual #44                 // Method java/lang/StringBuilder.append:(Ljava/lang/String;)Ljava/lang/StringBuilder;
      71: aload_2
      72: invokevirtual #76                 // Method java/lang/Exception.getMessage:()Ljava/lang/String;
      75: invokevirtual #44                 // Method java/lang/StringBuilder.append:(Ljava/lang/String;)Ljava/lang/StringBuilder;
      78: invokevirtual #49                 // Method java/lang/StringBuilder.toString:()Ljava/lang/String;
      81: aload_2
      82: invokespecial #68                 // Method java/lang/IllegalStateException."<init>":(Ljava/lang/String;Ljava/lang/Throwable;)V
      85: athrow
      86: return
    Exception table:
       from    to  target type
          15    20    23   Class java/lang/Exception

  public void subscribe(org.apache.dubbo.common.URL, org.apache.dubbo.registry.NotifyListener);
    Code:
       0: aload_0
       1: aload_1
       2: aload_2
       3: invokespecial #82                 // Method org/apache/dubbo/registry/support/AbstractRegistry.subscribe:(Lorg/apache/dubbo/common/URL;Lorg/apache/dubbo/registry/NotifyListener;)V
       6: aload_0
       7: aload_1
       8: aload_2
       9: invokevirtual #83                 // Method removeFailedSubscribed:(Lorg/apache/dubbo/common/URL;Lorg/apache/dubbo/registry/NotifyListener;)V
      12: aload_0
      13: aload_1
      14: aload_2
      15: invokevirtual #84                 // Method doSubscribe:(Lorg/apache/dubbo/common/URL;Lorg/apache/dubbo/registry/NotifyListener;)V
      18: goto          281
      21: astore_3
      22: aload_3
      23: astore        4
      25: aload_0
      26: aload_1
      27: invokevirtual #85                 // Method getCacheUrls:(Lorg/apache/dubbo/common/URL;)Ljava/util/List;
      30: astore        5
      32: aload         5
      34: invokestatic  #86                 // Method org/apache/dubbo/common/utils/CollectionUtils.isNotEmpty:(Ljava/util/Collection;)Z
      37: ifeq          125
      40: aload_0
      41: aload_1
      42: aload_2
      43: aload         5
      45: invokevirtual #87                 // Method notify:(Lorg/apache/dubbo/common/URL;Lorg/apache/dubbo/registry/NotifyListener;Ljava/util/List;)V
      48: aload_0
      49: getfield      #40                 // Field logger:Lorg/apache/dubbo/common/logger/ErrorTypeAwareLogger;
      52: ldc           #88                 // String 1-7
      54: ldc           #71                 // String
      56: ldc           #71                 // String
      58: new           #41                 // class java/lang/StringBuilder
      61: dup
      62: invokespecial #42                 // Method java/lang/StringBuilder."<init>":()V
      65: ldc           #89                 // String Failed to subscribe
      67: invokevirtual #44                 // Method java/lang/StringBuilder.append:(Ljava/lang/String;)Ljava/lang/StringBuilder;
      70: aload_1
      71: invokevirtual #45                 // Method java/lang/StringBuilder.append:(Ljava/lang/Object;)Ljava/lang/StringBuilder;
      74: ldc           #90                 // String , Using cached list:
      76: invokevirtual #44                 // Method java/lang/StringBuilder.append:(Ljava/lang/String;)Ljava/lang/StringBuilder;
      79: aload         5
      81: invokevirtual #45                 // Method java/lang/StringBuilder.append:(Ljava/lang/Object;)Ljava/lang/StringBuilder;
      84: ldc           #91                 // String  from cache file:
      86: invokevirtual #44                 // Method java/lang/StringBuilder.append:(Ljava/lang/String;)Ljava/lang/StringBuilder;
      89: aload_0
      90: invokevirtual #92                 // Method getCacheFile:()Ljava/io/File;
      93: invokevirtual #93                 // Method java/io/File.getName:()Ljava/lang/String;
      96: invokevirtual #44                 // Method java/lang/StringBuilder.append:(Ljava/lang/String;)Ljava/lang/StringBuilder;
      99: ldc           #66                 // String , cause:
     101: invokevirtual #44                 // Method java/lang/StringBuilder.append:(Ljava/lang/String;)Ljava/lang/StringBuilder;
     104: aload         4
     106: invokevirtual #67                 // Method java/lang/Throwable.getMessage:()Ljava/lang/String;
     109: invokevirtual #44                 // Method java/lang/StringBuilder.append:(Ljava/lang/String;)Ljava/lang/StringBuilder;
     112: invokevirtual #49                 // Method java/lang/StringBuilder.toString:()Ljava/lang/String;
     115: aload         4
     117: invokeinterface #73,  6           // InterfaceMethod org/apache/dubbo/common/logger/ErrorTypeAwareLogger.error:(Ljava/lang/String;Ljava/lang/String;Ljava/lang/String;Ljava/lang/String;Ljava/lang/Throwable;)V
     122: goto          275
     125: aload_0
     126: invokevirtual #47                 // Method getUrl:()Lorg/apache/dubbo/common/URL;
     129: ldc           #57                 // String check
     131: iconst_1
     132: invokevirtual #58                 // Method org/apache/dubbo/common/URL.getParameter:(Ljava/lang/String;Z)Z
     135: ifeq          152
     138: aload_1
     139: ldc           #57                 // String check
     141: iconst_1
     142: invokevirtual #58                 // Method org/apache/dubbo/common/URL.getParameter:(Ljava/lang/String;Z)Z
     145: ifeq          152
     148: iconst_1
     149: goto          153
     152: iconst_0
     153: istore        6
     155: aload         4
     157: instanceof    #60                 // class org/apache/dubbo/registry/support/SkipFailbackWrapperException
     160: istore        7
     162: iload         6
     164: ifne          172
     167: iload         7
     169: ifeq          226
     172: iload         7
     174: ifeq          184
     177: aload         4
     179: invokevirtual #61                 // Method java/lang/Throwable.getCause:()Ljava/lang/Throwable;
     182: astore        4
     184: new           #62                 // class java/lang/IllegalStateException
     187: dup
     188: new           #41                 // class java/lang/StringBuilder
     191: dup
     192: invokespecial #42                 // Method java/lang/StringBuilder."<init>":()V
     195: ldc           #89                 // String Failed to subscribe
     197: invokevirtual #44                 // Method java/lang/StringBuilder.append:(Ljava/lang/String;)Ljava/lang/StringBuilder;
     200: aload_1
     201: invokevirtual #45                 // Method java/lang/StringBuilder.append:(Ljava/lang/Object;)Ljava/lang/StringBuilder;
     204: ldc           #66                 // String , cause:
     206: invokevirtual #44                 // Method java/lang/StringBuilder.append:(Ljava/lang/String;)Ljava/lang/StringBuilder;
     209: aload         4
     211: invokevirtual #67                 // Method java/lang/Throwable.getMessage:()Ljava/lang/String;
     214: invokevirtual #44                 // Method java/lang/StringBuilder.append:(Ljava/lang/String;)Ljava/lang/StringBuilder;
     217: invokevirtual #49                 // Method java/lang/StringBuilder.toString:()Ljava/lang/String;
     220: aload         4
     222: invokespecial #68                 // Method java/lang/IllegalStateException."<init>":(Ljava/lang/String;Ljava/lang/Throwable;)V
     225: athrow
     226: aload_0
     227: getfield      #40                 // Field logger:Lorg/apache/dubbo/common/logger/ErrorTypeAwareLogger;
     230: ldc           #88                 // String 1-7
     232: ldc           #71                 // String
     234: ldc           #71                 // String
     236: new           #41                 // class java/lang/StringBuilder
     239: dup
     240: invokespecial #42                 // Method java/lang/StringBuilder."<init>":()V
     243: ldc           #89                 // String Failed to subscribe
     245: invokevirtual #44                 // Method java/lang/StringBuilder.append:(Ljava/lang/String;)Ljava/lang/StringBuilder;
     248: aload_1
     249: invokevirtual #45                 // Method java/lang/StringBuilder.append:(Ljava/lang/Object;)Ljava/lang/StringBuilder;
     252: ldc           #72                 // String , waiting for retry, cause:
     254: invokevirtual #44                 // Method java/lang/StringBuilder.append:(Ljava/lang/String;)Ljava/lang/StringBuilder;
     257: aload         4
     259: invokevirtual #67                 // Method java/lang/Throwable.getMessage:()Ljava/lang/String;
     262: invokevirtual #44                 // Method java/lang/StringBuilder.append:(Ljava/lang/String;)Ljava/lang/StringBuilder;
     265: invokevirtual #49                 // Method java/lang/StringBuilder.toString:()Ljava/lang/String;
     268: aload         4
     270: invokeinterface #73,  6           // InterfaceMethod org/apache/dubbo/common/logger/ErrorTypeAwareLogger.error:(Ljava/lang/String;Ljava/lang/String;Ljava/lang/String;Ljava/lang/String;Ljava/lang/Throwable;)V
     275: aload_0
     276: aload_1
     277: aload_2
     278: invokevirtual #94                 // Method addFailedSubscribed:(Lorg/apache/dubbo/common/URL;Lorg/apache/dubbo/registry/NotifyListener;)V
     281: return
    Exception table:
       from    to  target type
          12    18    21   Class java/lang/Exception

  public void unsubscribe(org.apache.dubbo.common.URL, org.apache.dubbo.registry.NotifyListener);
    Code:
       0: aload_0
       1: aload_1
       2: aload_2
       3: invokespecial #95                 // Method org/apache/dubbo/registry/support/AbstractRegistry.unsubscribe:(Lorg/apache/dubbo/common/URL;Lorg/apache/dubbo/registry/NotifyListener;)V
       6: aload_0
       7: aload_1
       8: aload_2
       9: invokevirtual #83                 // Method removeFailedSubscribed:(Lorg/apache/dubbo/common/URL;Lorg/apache/dubbo/registry/NotifyListener;)V
      12: aload_0
      13: aload_1
      14: aload_2
      15: invokevirtual #96                 // Method doUnsubscribe:(Lorg/apache/dubbo/common/URL;Lorg/apache/dubbo/registry/NotifyListener;)V
      18: goto          196
      21: astore_3
      22: aload_3
      23: astore        4
      25: aload_0
      26: invokevirtual #47                 // Method getUrl:()Lorg/apache/dubbo/common/URL;
      29: ldc           #57                 // String check
      31: iconst_1
      32: invokevirtual #58                 // Method org/apache/dubbo/common/URL.getParameter:(Ljava/lang/String;Z)Z
      35: ifeq          52
      38: aload_1
      39: ldc           #57                 // String check
      41: iconst_1
      42: invokevirtual #58                 // Method org/apache/dubbo/common/URL.getParameter:(Ljava/lang/String;Z)Z
      45: ifeq          52
      48: iconst_1
      49: goto          53
      52: iconst_0
      53: istore        5
      55: aload         4
      57: instanceof    #60                 // class org/apache/dubbo/registry/support/SkipFailbackWrapperException
      60: istore        6
      62: iload         5
      64: ifne          72
      67: iload         6
      69: ifeq          141
      72: iload         6
      74: ifeq          84
      77: aload         4
      79: invokevirtual #61                 // Method java/lang/Throwable.getCause:()Ljava/lang/Throwable;
      82: astore        4
      84: new           #62                 // class java/lang/IllegalStateException
      87: dup
      88: new           #41                 // class java/lang/StringBuilder
      91: dup
      92: invokespecial #42                 // Method java/lang/StringBuilder."<init>":()V
      95: ldc           #97                 // String Failed to unsubscribe
      97: invokevirtual #44                 // Method java/lang/StringBuilder.append:(Ljava/lang/String;)Ljava/lang/StringBuilder;
     100: aload_1
     101: invokevirtual #45                 // Method java/lang/StringBuilder.append:(Ljava/lang/Object;)Ljava/lang/StringBuilder;
     104: ldc           #64                 // String  to registry
     106: invokevirtual #44                 // Method java/lang/StringBuilder.append:(Ljava/lang/String;)Ljava/lang/StringBuilder;
     109: aload_0
     110: invokevirtual #47                 // Method getUrl:()Lorg/apache/dubbo/common/URL;
     113: invokevirtual #65                 // Method org/apache/dubbo/common/URL.getAddress:()Ljava/lang/String;
     116: invokevirtual #44                 // Method java/lang/StringBuilder.append:(Ljava/lang/String;)Ljava/lang/StringBuilder;
     119: ldc           #66                 // String , cause:
     121: invokevirtual #44                 // Method java/lang/StringBuilder.append:(Ljava/lang/String;)Ljava/lang/StringBuilder;
     124: aload         4
     126: invokevirtual #67                 // Method java/lang/Throwable.getMessage:()Ljava/lang/String;
     129: invokevirtual #44                 // Method java/lang/StringBuilder.append:(Ljava/lang/String;)Ljava/lang/StringBuilder;
     132: invokevirtual #49                 // Method java/lang/StringBuilder.toString:()Ljava/lang/String;
     135: aload         4
     137: invokespecial #68                 // Method java/lang/IllegalStateException."<init>":(Ljava/lang/String;Ljava/lang/Throwable;)V
     140: athrow
     141: aload_0
     142: getfield      #40                 // Field logger:Lorg/apache/dubbo/common/logger/ErrorTypeAwareLogger;
     145: ldc           #88                 // String 1-7
     147: ldc           #71                 // String
     149: ldc           #71                 // String
     151: new           #41                 // class java/lang/StringBuilder
     154: dup
     155: invokespecial #42                 // Method java/lang/StringBuilder."<init>":()V
     158: ldc           #97                 // String Failed to unsubscribe
     160: invokevirtual #44                 // Method java/lang/StringBuilder.append:(Ljava/lang/String;)Ljava/lang/StringBuilder;
     163: aload_1
     164: invokevirtual #45                 // Method java/lang/StringBuilder.append:(Ljava/lang/Object;)Ljava/lang/StringBuilder;
     167: ldc           #72                 // String , waiting for retry, cause:
     169: invokevirtual #44                 // Method java/lang/StringBuilder.append:(Ljava/lang/String;)Ljava/lang/StringBuilder;
     172: aload         4
     174: invokevirtual #67                 // Method java/lang/Throwable.getMessage:()Ljava/lang/String;
     177: invokevirtual #44                 // Method java/lang/StringBuilder.append:(Ljava/lang/String;)Ljava/lang/StringBuilder;
     180: invokevirtual #49                 // Method java/lang/StringBuilder.toString:()Ljava/lang/String;
     183: aload         4
     185: invokeinterface #73,  6           // InterfaceMethod org/apache/dubbo/common/logger/ErrorTypeAwareLogger.error:(Ljava/lang/String;Ljava/lang/String;Ljava/lang/String;Ljava/lang/String;Ljava/lang/Throwable;)V
     190: aload_0
     191: aload_1
     192: aload_2
     193: invokespecial #98                 // Method addFailedUnsubscribed:(Lorg/apache/dubbo/common/URL;Lorg/apache/dubbo/registry/NotifyListener;)V
     196: return
    Exception table:
       from    to  target type
          12    18    21   Class java/lang/Exception

  protected void notify(org.apache.dubbo.common.URL, org.apache.dubbo.registry.NotifyListener, java.util.List<org.apache.dubbo.common.URL>);
    Code:
       0: aload_1
       1: ifnonnull     14
       4: new           #99                 // class java/lang/IllegalArgumentException
       7: dup
       8: ldc           #100                // String notify url == null
      10: invokespecial #101                // Method java/lang/IllegalArgumentException."<init>":(Ljava/lang/String;)V
      13: athrow
      14: aload_2
      15: ifnonnull     28
      18: new           #99                 // class java/lang/IllegalArgumentException
      21: dup
      22: ldc           #102                // String notify listener == null
      24: invokespecial #101                // Method java/lang/IllegalArgumentException."<init>":(Ljava/lang/String;)V
      27: athrow
      28: aload_0
      29: aload_1
      30: aload_2
      31: aload_3
      32: invokevirtual #103                // Method doNotify:(Lorg/apache/dubbo/common/URL;Lorg/apache/dubbo/registry/NotifyListener;Ljava/util/List;)V
      35: goto          89
      38: astore        4
      40: aload_0
      41: getfield      #40                 // Field logger:Lorg/apache/dubbo/common/logger/ErrorTypeAwareLogger;
      44: ldc           #88                 // String 1-7
      46: ldc           #71                 // String
      48: ldc           #71                 // String
      50: new           #41                 // class java/lang/StringBuilder
      53: dup
      54: invokespecial #42                 // Method java/lang/StringBuilder."<init>":()V
      57: ldc           #104                // String Failed to notify addresses for subscribe
      59: invokevirtual #44                 // Method java/lang/StringBuilder.append:(Ljava/lang/String;)Ljava/lang/StringBuilder;
      62: aload_1
      63: invokevirtual #45                 // Method java/lang/StringBuilder.append:(Ljava/lang/Object;)Ljava/lang/StringBuilder;
      66: ldc           #66                 // String , cause:
      68: invokevirtual #44                 // Method java/lang/StringBuilder.append:(Ljava/lang/String;)Ljava/lang/StringBuilder;
      71: aload         4
      73: invokevirtual #76                 // Method java/lang/Exception.getMessage:()Ljava/lang/String;
      76: invokevirtual #44                 // Method java/lang/StringBuilder.append:(Ljava/lang/String;)Ljava/lang/StringBuilder;
      79: invokevirtual #49                 // Method java/lang/StringBuilder.toString:()Ljava/lang/String;
      82: aload         4
      84: invokeinterface #73,  6           // InterfaceMethod org/apache/dubbo/common/logger/ErrorTypeAwareLogger.error:(Ljava/lang/String;Ljava/lang/String;Ljava/lang/String;Ljava/lang/String;Ljava/lang/Throwable;)V
      89: return
    Exception table:
       from    to  target type
          28    35    38   Class java/lang/Exception

  protected void doNotify(org.apache.dubbo.common.URL, org.apache.dubbo.registry.NotifyListener, java.util.List<org.apache.dubbo.common.URL>);
    Code:
       0: aload_0
       1: aload_1
       2: aload_2
       3: aload_3
       4: invokespecial #105                // Method org/apache/dubbo/registry/support/AbstractRegistry.notify:(Lorg/apache/dubbo/common/URL;Lorg/apache/dubbo/registry/NotifyListener;Ljava/util/List;)V
       7: return

  protected void recover() throws java.lang.Exception;
    Code:
       0: new           #106                // class java/util/HashSet
       3: dup
       4: aload_0
       5: invokevirtual #107                // Method getRegistered:()Ljava/util/Set;
       8: invokespecial #108                // Method java/util/HashSet."<init>":(Ljava/util/Collection;)V
      11: astore_1
      12: aload_1
      13: invokeinterface #109,  1          // InterfaceMethod java/util/Set.isEmpty:()Z
      18: ifne          105
      21: aload_0
      22: getfield      #40                 // Field logger:Lorg/apache/dubbo/common/logger/ErrorTypeAwareLogger;
      25: invokeinterface #110,  1          // InterfaceMethod org/apache/dubbo/common/logger/ErrorTypeAwareLogger.isInfoEnabled:()Z
      30: ifeq          61
      33: aload_0
      34: getfield      #40                 // Field logger:Lorg/apache/dubbo/common/logger/ErrorTypeAwareLogger;
      37: new           #41                 // class java/lang/StringBuilder
      40: dup
      41: invokespecial #42                 // Method java/lang/StringBuilder."<init>":()V
      44: ldc           #111                // String Recover register url
      46: invokevirtual #44                 // Method java/lang/StringBuilder.append:(Ljava/lang/String;)Ljava/lang/StringBuilder;
      49: aload_1
      50: invokevirtual #45                 // Method java/lang/StringBuilder.append:(Ljava/lang/Object;)Ljava/lang/StringBuilder;
      53: invokevirtual #49                 // Method java/lang/StringBuilder.toString:()Ljava/lang/String;
      56: invokeinterface #50,  2           // InterfaceMethod org/apache/dubbo/common/logger/ErrorTypeAwareLogger.info:(Ljava/lang/String;)V
      61: aload_1
      62: invokeinterface #112,  1          // InterfaceMethod java/util/Set.iterator:()Ljava/util/Iterator;
      67: astore_2
      68: aload_2
      69: invokeinterface #113,  1          // InterfaceMethod java/util/Iterator.hasNext:()Z
      74: ifeq          105
      77: aload_2
      78: invokeinterface #114,  1          // InterfaceMethod java/util/Iterator.next:()Ljava/lang/Object;
      83: checkcast     #115                // class org/apache/dubbo/common/URL
      86: astore_3
      87: aload_0
      88: aload_3
      89: invokespecial #52                 // Method removeFailedRegistered:(Lorg/apache/dubbo/common/URL;)V
      92: aload_0
      93: aload_3
      94: invokespecial #53                 // Method removeFailedUnregistered:(Lorg/apache/dubbo/common/URL;)V
      97: aload_0
      98: aload_3
      99: invokespecial #74                 // Method addFailedRegistered:(Lorg/apache/dubbo/common/URL;)V
     102: goto          68
     105: new           #116                // class java/util/HashMap
     108: dup
     109: aload_0
     110: invokevirtual #117                // Method getSubscribed:()Ljava/util/Map;
     113: invokespecial #118                // Method java/util/HashMap."<init>":(Ljava/util/Map;)V
     116: astore_2
     117: aload_2
     118: invokeinterface #119,  1          // InterfaceMethod java/util/Map.isEmpty:()Z
     123: ifne          276
     126: aload_0
     127: getfield      #40                 // Field logger:Lorg/apache/dubbo/common/logger/ErrorTypeAwareLogger;
     130: invokeinterface #110,  1          // InterfaceMethod org/apache/dubbo/common/logger/ErrorTypeAwareLogger.isInfoEnabled:()Z
     135: ifeq          171
     138: aload_0
     139: getfield      #40                 // Field logger:Lorg/apache/dubbo/common/logger/ErrorTypeAwareLogger;
     142: new           #41                 // class java/lang/StringBuilder
     145: dup
     146: invokespecial #42                 // Method java/lang/StringBuilder."<init>":()V
     149: ldc           #120                // String Recover subscribe url
     151: invokevirtual #44                 // Method java/lang/StringBuilder.append:(Ljava/lang/String;)Ljava/lang/StringBuilder;
     154: aload_2
     155: invokeinterface #121,  1          // InterfaceMethod java/util/Map.keySet:()Ljava/util/Set;
     160: invokevirtual #45                 // Method java/lang/StringBuilder.append:(Ljava/lang/Object;)Ljava/lang/StringBuilder;
     163: invokevirtual #49                 // Method java/lang/StringBuilder.toString:()Ljava/lang/String;
     166: invokeinterface #50,  2           // InterfaceMethod org/apache/dubbo/common/logger/ErrorTypeAwareLogger.info:(Ljava/lang/String;)V
     171: aload_2
     172: invokeinterface #122,  1          // InterfaceMethod java/util/Map.entrySet:()Ljava/util/Set;
     177: invokeinterface #112,  1          // InterfaceMethod java/util/Set.iterator:()Ljava/util/Iterator;
     182: astore_3
     183: aload_3
     184: invokeinterface #113,  1          // InterfaceMethod java/util/Iterator.hasNext:()Z
     189: ifeq          276
     192: aload_3
     193: invokeinterface #114,  1          // InterfaceMethod java/util/Iterator.next:()Ljava/lang/Object;
     198: checkcast     #123                // class java/util/Map$Entry
     201: astore        4
     203: aload         4
     205: invokeinterface #124,  1          // InterfaceMethod java/util/Map$Entry.getKey:()Ljava/lang/Object;
     210: checkcast     #115                // class org/apache/dubbo/common/URL
     213: astore        5
     215: aload         4
     217: invokeinterface #125,  1          // InterfaceMethod java/util/Map$Entry.getValue:()Ljava/lang/Object;
     222: checkcast     #126                // class java/util/Set
     225: invokeinterface #112,  1          // InterfaceMethod java/util/Set.iterator:()Ljava/util/Iterator;
     230: astore        6
     232: aload         6
     234: invokeinterface #113,  1          // InterfaceMethod java/util/Iterator.hasNext:()Z
     239: ifeq          273
     242: aload         6
     244: invokeinterface #114,  1          // InterfaceMethod java/util/Iterator.next:()Ljava/lang/Object;
     249: checkcast     #127                // class org/apache/dubbo/registry/NotifyListener
     252: astore        7
     254: aload_0
     255: aload         5
     257: aload         7
     259: invokevirtual #83                 // Method removeFailedSubscribed:(Lorg/apache/dubbo/common/URL;Lorg/apache/dubbo/registry/NotifyListener;)V
     262: aload_0
     263: aload         5
     265: aload         7
     267: invokevirtual #94                 // Method addFailedSubscribed:(Lorg/apache/dubbo/common/URL;Lorg/apache/dubbo/registry/NotifyListener;)V
     270: goto          232
     273: goto          183
     276: return

  public void destroy();
    Code:
       0: aload_0
       1: invokespecial #128                // Method org/apache/dubbo/registry/support/AbstractRegistry.destroy:()V
       4: aload_0
       5: getfield      #19                 // Field retryTimer:Lorg/apache/dubbo/common/timer/HashedWheelTimer;
       8: invokevirtual #129                // Method org/apache/dubbo/common/timer/HashedWheelTimer.stop:()Ljava/util/Set;
      11: pop
      12: return

  public abstract void doRegister(org.apache.dubbo.common.URL);

  public abstract void doUnregister(org.apache.dubbo.common.URL);

  public abstract void doSubscribe(org.apache.dubbo.common.URL, org.apache.dubbo.registry.NotifyListener);

  public abstract void doUnsubscribe(org.apache.dubbo.common.URL, org.apache.dubbo.registry.NotifyListener);
}
