Compiled from "RegistryManager.java"
final class org.apache.dubbo.registry.support.RegistryManager$1 implements org.apache.dubbo.registry.Registry {
  org.apache.dubbo.registry.support.RegistryManager$1();
    Code:
       0: aload_0
       1: invokespecial #1                  // Method java/lang/Object."<init>":()V
       4: return

  public org.apache.dubbo.common.URL getUrl();
    Code:
       0: aconst_null
       1: areturn

  public boolean isAvailable();
    Code:
       0: iconst_0
       1: ireturn

  public void destroy();
    Code:
       0: return

  public void register(org.apache.dubbo.common.URL);
    Code:
       0: return

  public void unregister(org.apache.dubbo.common.URL);
    Code:
       0: return

  public void subscribe(org.apache.dubbo.common.URL, org.apache.dubbo.registry.NotifyListener);
    Code:
       0: return

  public void unsubscribe(org.apache.dubbo.common.URL, org.apache.dubbo.registry.NotifyListener);
    Code:
       0: return

  public java.util.List<org.apache.dubbo.common.URL> lookup(org.apache.dubbo.common.URL);
    Code:
       0: aconst_null
       1: areturn
}
