Compiled from "WildcardValuePattern.java"
public class org.apache.dubbo.rpc.cluster.router.condition.matcher.pattern.wildcard.WildcardValuePattern implements org.apache.dubbo.rpc.cluster.router.condition.matcher.pattern.ValuePattern {
  public org.apache.dubbo.rpc.cluster.router.condition.matcher.pattern.wildcard.WildcardValuePattern();
    Code:
       0: aload_0
       1: invokespecial #1                  // Method java/lang/Object."<init>":()V
       4: return

  public boolean shouldMatch(java.lang.String);
    Code:
       0: iconst_1
       1: ireturn

  public boolean match(java.lang.String, java.lang.String, org.apache.dubbo.common.URL, org.apache.dubbo.rpc.Invocation, boolean);
    Code:
       0: aload_1
       1: aload_2
       2: aload_3
       3: invokestatic  #2                  // Method org/apache/dubbo/common/utils/UrlUtils.isMatchGlobPattern:(Ljava/lang/String;Ljava/lang/String;Lorg/apache/dubbo/common/URL;)Z
       6: ireturn
}
