Compiled from "DefaultMultipleSerialization.java"
public class org.apache.dubbo.common.serialize.DefaultMultipleSerialization implements org.apache.dubbo.common.serialize.MultipleSerialization {
  public org.apache.dubbo.common.serialize.DefaultMultipleSerialization();
    Code:
       0: aload_0
       1: invokespecial #1                  // Method java/lang/Object."<init>":()V
       4: return

  public void serialize(org.apache.dubbo.common.URL, java.lang.String, java.lang.Class<?>, java.lang.Object, java.io.OutputStream) throws java.io.IOException;
    Code:
       0: aload_0
       1: aload_2
       2: invokespecial #2                  // Method convertHessian:(Ljava/lang/String;)Ljava/lang/String;
       5: astore_2
       6: aload_1
       7: invokevirtual #3                  // Method org/apache/dubbo/common/URL.getOrDefaultFrameworkModel:()Lorg/apache/dubbo/rpc/model/FrameworkModel;
      10: ldc           #4                  // class org/apache/dubbo/common/serialize/Serialization
      12: invokevirtual #5                  // Method org/apache/dubbo/rpc/model/FrameworkModel.getExtensionLoader:(Ljava/lang/Class;)Lorg/apache/dubbo/common/extension/ExtensionLoader;
      15: aload_2
      16: invokevirtual #6                  // Method org/apache/dubbo/common/extension/ExtensionLoader.getExtension:(Ljava/lang/String;)Ljava/lang/Object;
      19: checkcast     #4                  // class org/apache/dubbo/common/serialize/Serialization
      22: astore        6
      24: aload         6
      26: aconst_null
      27: aload         5
      29: invokeinterface #7,  3            // InterfaceMethod org/apache/dubbo/common/serialize/Serialization.serialize:(Lorg/apache/dubbo/common/URL;Ljava/io/OutputStream;)Lorg/apache/dubbo/common/serialize/ObjectOutput;
      34: astore        7
      36: aload         7
      38: aload         4
      40: invokeinterface #8,  2            // InterfaceMethod org/apache/dubbo/common/serialize/ObjectOutput.writeObject:(Ljava/lang/Object;)V
      45: aload         7
      47: invokeinterface #9,  1            // InterfaceMethod org/apache/dubbo/common/serialize/ObjectOutput.flushBuffer:()V
      52: return

  public java.lang.Object deserialize(org.apache.dubbo.common.URL, java.lang.String, java.lang.Class<?>, java.io.InputStream) throws java.io.IOException, java.lang.ClassNotFoundException;
    Code:
       0: aload_0
       1: aload_2
       2: invokespecial #2                  // Method convertHessian:(Ljava/lang/String;)Ljava/lang/String;
       5: astore_2
       6: aload_1
       7: invokevirtual #3                  // Method org/apache/dubbo/common/URL.getOrDefaultFrameworkModel:()Lorg/apache/dubbo/rpc/model/FrameworkModel;
      10: ldc           #4                  // class org/apache/dubbo/common/serialize/Serialization
      12: invokevirtual #5                  // Method org/apache/dubbo/rpc/model/FrameworkModel.getExtensionLoader:(Ljava/lang/Class;)Lorg/apache/dubbo/common/extension/ExtensionLoader;
      15: aload_2
      16: invokevirtual #6                  // Method org/apache/dubbo/common/extension/ExtensionLoader.getExtension:(Ljava/lang/String;)Ljava/lang/Object;
      19: checkcast     #4                  // class org/apache/dubbo/common/serialize/Serialization
      22: astore        5
      24: aload         5
      26: aconst_null
      27: aload         4
      29: invokeinterface #10,  3           // InterfaceMethod org/apache/dubbo/common/serialize/Serialization.deserialize:(Lorg/apache/dubbo/common/URL;Ljava/io/InputStream;)Lorg/apache/dubbo/common/serialize/ObjectInput;
      34: astore        6
      36: aload         6
      38: aload_3
      39: invokeinterface #11,  2           // InterfaceMethod org/apache/dubbo/common/serialize/ObjectInput.readObject:(Ljava/lang/Class;)Ljava/lang/Object;
      44: areturn

  private java.lang.String convertHessian(java.lang.String);
    Code:
       0: aload_1
       1: ldc           #12                 // String hessian4
       3: invokevirtual #13                 // Method java/lang/String.equals:(Ljava/lang/Object;)Z
       6: ifeq          12
       9: ldc           #14                 // String hessian2
      11: areturn
      12: aload_1
      13: areturn
}
