Compiled from "ObjectInput.java"
public interface org.apache.dubbo.common.serialize.ObjectInput extends org.apache.dubbo.common.serialize.DataInput {
  public abstract java.lang.Object readObject() throws java.io.IOException, java.lang.ClassNotFoundException;

  public abstract <T> T readObject(java.lang.Class<T>) throws java.io.IOException, java.lang.ClassNotFoundException;

  public abstract <T> T readObject(java.lang.Class<T>, java.lang.reflect.Type) throws java.io.IOException, java.lang.ClassNotFoundException;

  public default java.lang.Throwable readThrowable() throws java.io.IOException, java.lang.ClassNotFoundException;
    Code:
       0: aload_0
       1: invokeinterface #1,  1            // InterfaceMethod readObject:()Ljava/lang/Object;
       6: astore_1
       7: aload_1
       8: instanceof    #2                  // class java/lang/Throwable
      11: ifne          41
      14: new           #3                  // class java/io/IOException
      17: dup
      18: new           #4                  // class java/lang/StringBuilder
      21: dup
      22: invokespecial #5                  // Method java/lang/StringBuilder."<init>":()V
      25: ldc           #6                  // String Response data error, expect Throwable, but get
      27: invokevirtual #7                  // Method java/lang/StringBuilder.append:(Ljava/lang/String;)Ljava/lang/StringBuilder;
      30: aload_1
      31: invokevirtual #8                  // Method java/lang/StringBuilder.append:(Ljava/lang/Object;)Ljava/lang/StringBuilder;
      34: invokevirtual #9                  // Method java/lang/StringBuilder.toString:()Ljava/lang/String;
      37: invokespecial #10                 // Method java/io/IOException."<init>":(Ljava/lang/String;)V
      40: athrow
      41: aload_1
      42: checkcast     #2                  // class java/lang/Throwable
      45: areturn

  public default java.lang.String readEvent() throws java.io.IOException, java.lang.ClassNotFoundException;
    Code:
       0: aload_0
       1: invokeinterface #11,  1           // InterfaceMethod readUTF:()Ljava/lang/String;
       6: areturn

  public default java.util.Map<java.lang.String, java.lang.Object> readAttachments() throws java.io.IOException, java.lang.ClassNotFoundException;
    Code:
       0: aload_0
       1: ldc           #12                 // class java/util/Map
       3: invokeinterface #13,  2           // InterfaceMethod readObject:(Ljava/lang/Class;)Ljava/lang/Object;
       8: checkcast     #12                 // class java/util/Map
      11: areturn
}
