Compiled from "ObjectOutput.java"
public interface org.apache.dubbo.common.serialize.ObjectOutput extends org.apache.dubbo.common.serialize.DataOutput {
  public abstract void writeObject(java.lang.Object) throws java.io.IOException;

  public default void writeThrowable(java.lang.Throwable) throws java.io.IOException;
    Code:
       0: aload_0
       1: aload_1
       2: invokeinterface #1,  2            // InterfaceMethod writeObject:(Ljava/lang/Object;)V
       7: return

  public default void writeEvent(java.lang.String) throws java.io.IOException;
    Code:
       0: aload_0
       1: aload_1
       2: invokeinterface #1,  2            // InterfaceMethod writeObject:(Ljava/lang/Object;)V
       7: return

  public default void writeAttachments(java.util.Map<java.lang.String, java.lang.Object>) throws java.io.IOException;
    Code:
       0: aload_0
       1: aload_1
       2: invokeinterface #1,  2            // InterfaceMethod writeObject:(Ljava/lang/Object;)V
       7: return
}
