Compiled from "ErrorAttributeOptions.java"
public final class org.springframework.boot.web.error.ErrorAttributeOptions {
  private final java.util.Set<org.springframework.boot.web.error.ErrorAttributeOptions$Include> includes;

  private org.springframework.boot.web.error.ErrorAttributeOptions(java.util.Set<org.springframework.boot.web.error.ErrorAttributeOptions$Include>);
    Code:
       0: aload_0
       1: invokespecial #1                  // Method java/lang/Object."<init>":()V
       4: aload_0
       5: aload_1
       6: putfield      #7                  // Field includes:Ljava/util/Set;
       9: return

  public boolean isIncluded(org.springframework.boot.web.error.ErrorAttributeOptions$Include);
    Code:
       0: aload_0
       1: getfield      #7                  // Field includes:Ljava/util/Set;
       4: aload_1
       5: invokeinterface #13,  2           // InterfaceMethod java/util/Set.contains:(Ljava/lang/Object;)Z
      10: ireturn

  public java.util.Set<org.springframework.boot.web.error.ErrorAttributeOptions$Include> getIncludes();
    Code:
       0: aload_0
       1: getfield      #7                  // Field includes:Ljava/util/Set;
       4: areturn

  public org.springframework.boot.web.error.ErrorAttributeOptions including(org.springframework.boot.web.error.ErrorAttributeOptions$Include...);
    Code:
       0: aload_0
       1: invokevirtual #19                 // Method copyIncludes:()Ljava/util/EnumSet;
       4: astore_2
       5: aload_2
       6: aload_1
       7: invokestatic  #23                 // Method java/util/Arrays.asList:([Ljava/lang/Object;)Ljava/util/List;
      10: invokevirtual #29                 // Method java/util/EnumSet.addAll:(Ljava/util/Collection;)Z
      13: pop
      14: new           #8                  // class org/springframework/boot/web/error/ErrorAttributeOptions
      17: dup
      18: aload_2
      19: invokestatic  #35                 // Method java/util/Collections.unmodifiableSet:(Ljava/util/Set;)Ljava/util/Set;
      22: invokespecial #41                 // Method "<init>":(Ljava/util/Set;)V
      25: areturn

  public org.springframework.boot.web.error.ErrorAttributeOptions excluding(org.springframework.boot.web.error.ErrorAttributeOptions$Include...);
    Code:
       0: aload_0
       1: invokevirtual #19                 // Method copyIncludes:()Ljava/util/EnumSet;
       4: astore_2
       5: aload_1
       6: invokestatic  #44                 // Method java/util/Arrays.stream:([Ljava/lang/Object;)Ljava/util/stream/Stream;
       9: aload_2
      10: dup
      11: invokestatic  #48                 // Method java/util/Objects.requireNonNull:(Ljava/lang/Object;)Ljava/lang/Object;
      14: pop
      15: invokedynamic #54,  0             // InvokeDynamic #0:accept:(Ljava/util/EnumSet;)Ljava/util/function/Consumer;
      20: invokeinterface #58,  2           // InterfaceMethod java/util/stream/Stream.forEach:(Ljava/util/function/Consumer;)V
      25: new           #8                  // class org/springframework/boot/web/error/ErrorAttributeOptions
      28: dup
      29: aload_2
      30: invokestatic  #35                 // Method java/util/Collections.unmodifiableSet:(Ljava/util/Set;)Ljava/util/Set;
      33: invokespecial #41                 // Method "<init>":(Ljava/util/Set;)V
      36: areturn

  private java.util.EnumSet<org.springframework.boot.web.error.ErrorAttributeOptions$Include> copyIncludes();
    Code:
       0: aload_0
       1: getfield      #7                  // Field includes:Ljava/util/Set;
       4: invokeinterface #64,  1           // InterfaceMethod java/util/Set.isEmpty:()Z
       9: ifeq          20
      12: ldc           #68                 // class org/springframework/boot/web/error/ErrorAttributeOptions$Include
      14: invokestatic  #70                 // Method java/util/EnumSet.noneOf:(Ljava/lang/Class;)Ljava/util/EnumSet;
      17: goto          27
      20: aload_0
      21: getfield      #7                  // Field includes:Ljava/util/Set;
      24: invokestatic  #74                 // Method java/util/EnumSet.copyOf:(Ljava/util/Collection;)Ljava/util/EnumSet;
      27: areturn

  public static org.springframework.boot.web.error.ErrorAttributeOptions defaults();
    Code:
       0: iconst_0
       1: anewarray     #68                 // class org/springframework/boot/web/error/ErrorAttributeOptions$Include
       4: invokestatic  #78                 // Method of:([Lorg/springframework/boot/web/error/ErrorAttributeOptions$Include;)Lorg/springframework/boot/web/error/ErrorAttributeOptions;
       7: areturn

  public static org.springframework.boot.web.error.ErrorAttributeOptions of(org.springframework.boot.web.error.ErrorAttributeOptions$Include...);
    Code:
       0: aload_0
       1: invokestatic  #23                 // Method java/util/Arrays.asList:([Ljava/lang/Object;)Ljava/util/List;
       4: invokestatic  #82                 // Method of:(Ljava/util/Collection;)Lorg/springframework/boot/web/error/ErrorAttributeOptions;
       7: areturn

  public static org.springframework.boot.web.error.ErrorAttributeOptions of(java.util.Collection<org.springframework.boot.web.error.ErrorAttributeOptions$Include>);
    Code:
       0: new           #8                  // class org/springframework/boot/web/error/ErrorAttributeOptions
       3: dup
       4: aload_0
       5: invokeinterface #85,  1           // InterfaceMethod java/util/Collection.isEmpty:()Z
      10: ifeq          19
      13: invokestatic  #88                 // Method java/util/Collections.emptySet:()Ljava/util/Set;
      16: goto          26
      19: aload_0
      20: invokestatic  #74                 // Method java/util/EnumSet.copyOf:(Ljava/util/Collection;)Ljava/util/EnumSet;
      23: invokestatic  #35                 // Method java/util/Collections.unmodifiableSet:(Ljava/util/Set;)Ljava/util/Set;
      26: invokespecial #41                 // Method "<init>":(Ljava/util/Set;)V
      29: areturn
}
