Compiled from "ErrorAttributeOptions.java"
public final class org.springframework.boot.web.error.ErrorAttributeOptions$Include extends java.lang.Enum<org.springframework.boot.web.error.ErrorAttributeOptions$Include> {
  public static final org.springframework.boot.web.error.ErrorAttributeOptions$Include EXCEPTION;

  public static final org.springframework.boot.web.error.ErrorAttributeOptions$Include STACK_TRACE;

  public static final org.springframework.boot.web.error.ErrorAttributeOptions$Include MESSAGE;

  public static final org.springframework.boot.web.error.ErrorAttributeOptions$Include BINDING_ERRORS;

  private static final org.springframework.boot.web.error.ErrorAttributeOptions$Include[] $VALUES;

  public static org.springframework.boot.web.error.ErrorAttributeOptions$Include[] values();
    Code:
       0: getstatic     #16                 // Field $VALUES:[Lorg/springframework/boot/web/error/ErrorAttributeOptions$Include;
       3: invokevirtual #20                 // Method "[Lorg/springframework/boot/web/error/ErrorAttributeOptions$Include;".clone:()Ljava/lang/Object;
       6: checkcast     #21                 // class "[Lorg/springframework/boot/web/error/ErrorAttributeOptions$Include;"
       9: areturn

  public static org.springframework.boot.web.error.ErrorAttributeOptions$Include valueOf(java.lang.String);
    Code:
       0: ldc           #1                  // class org/springframework/boot/web/error/ErrorAttributeOptions$Include
       2: aload_0
       3: invokestatic  #25                 // Method java/lang/Enum.valueOf:(Ljava/lang/Class;Ljava/lang/String;)Ljava/lang/Enum;
       6: checkcast     #1                  // class org/springframework/boot/web/error/ErrorAttributeOptions$Include
       9: areturn

  private org.springframework.boot.web.error.ErrorAttributeOptions$Include();
    Code:
       0: aload_0
       1: aload_1
       2: iload_2
       3: invokespecial #31                 // Method java/lang/Enum."<init>":(Ljava/lang/String;I)V
       6: return

  private static org.springframework.boot.web.error.ErrorAttributeOptions$Include[] $values();
    Code:
       0: iconst_4
       1: anewarray     #1                  // class org/springframework/boot/web/error/ErrorAttributeOptions$Include
       4: dup
       5: iconst_0
       6: getstatic     #3                  // Field EXCEPTION:Lorg/springframework/boot/web/error/ErrorAttributeOptions$Include;
       9: aastore
      10: dup
      11: iconst_1
      12: getstatic     #7                  // Field STACK_TRACE:Lorg/springframework/boot/web/error/ErrorAttributeOptions$Include;
      15: aastore
      16: dup
      17: iconst_2
      18: getstatic     #10                 // Field MESSAGE:Lorg/springframework/boot/web/error/ErrorAttributeOptions$Include;
      21: aastore
      22: dup
      23: iconst_3
      24: getstatic     #13                 // Field BINDING_ERRORS:Lorg/springframework/boot/web/error/ErrorAttributeOptions$Include;
      27: aastore
      28: areturn

  static {};
    Code:
       0: new           #1                  // class org/springframework/boot/web/error/ErrorAttributeOptions$Include
       3: dup
       4: ldc           #35                 // String EXCEPTION
       6: iconst_0
       7: invokespecial #36                 // Method "<init>":(Ljava/lang/String;I)V
      10: putstatic     #3                  // Field EXCEPTION:Lorg/springframework/boot/web/error/ErrorAttributeOptions$Include;
      13: new           #1                  // class org/springframework/boot/web/error/ErrorAttributeOptions$Include
      16: dup
      17: ldc           #37                 // String STACK_TRACE
      19: iconst_1
      20: invokespecial #36                 // Method "<init>":(Ljava/lang/String;I)V
      23: putstatic     #7                  // Field STACK_TRACE:Lorg/springframework/boot/web/error/ErrorAttributeOptions$Include;
      26: new           #1                  // class org/springframework/boot/web/error/ErrorAttributeOptions$Include
      29: dup
      30: ldc           #38                 // String MESSAGE
      32: iconst_2
      33: invokespecial #36                 // Method "<init>":(Ljava/lang/String;I)V
      36: putstatic     #10                 // Field MESSAGE:Lorg/springframework/boot/web/error/ErrorAttributeOptions$Include;
      39: new           #1                  // class org/springframework/boot/web/error/ErrorAttributeOptions$Include
      42: dup
      43: ldc           #39                 // String BINDING_ERRORS
      45: iconst_3
      46: invokespecial #36                 // Method "<init>":(Ljava/lang/String;I)V
      49: putstatic     #13                 // Field BINDING_ERRORS:Lorg/springframework/boot/web/error/ErrorAttributeOptions$Include;
      52: invokestatic  #40                 // Method $values:()[Lorg/springframework/boot/web/error/ErrorAttributeOptions$Include;
      55: putstatic     #16                 // Field $VALUES:[Lorg/springframework/boot/web/error/ErrorAttributeOptions$Include;
      58: return
}
