Compiled from "DefaultParamDeepCopyUtil.java"
public class org.apache.dubbo.rpc.protocol.injvm.DefaultParamDeepCopyUtil implements org.apache.dubbo.rpc.protocol.injvm.ParamDeepCopyUtil {
  private static final org.apache.dubbo.common.logger.ErrorTypeAwareLogger logger;

  public static final java.lang.String NAME;

  public org.apache.dubbo.rpc.protocol.injvm.DefaultParamDeepCopyUtil();
    Code:
       0: aload_0
       1: invokespecial #2                  // Method java/lang/Object."<init>":()V
       4: return

  public <T> T copy(org.apache.dubbo.common.URL, java.lang.Object, java.lang.Class<T>);
    Code:
       0: aload_1
       1: invokevirtual #3                  // Method org/apache/dubbo/common/URL.getOrDefaultFrameworkModel:()Lorg/apache/dubbo/rpc/model/FrameworkModel;
       4: ldc           #4                  // class org/apache/dubbo/common/serialize/Serialization
       6: invokevirtual #5                  // Method org/apache/dubbo/rpc/model/FrameworkModel.getExtensionLoader:(Ljava/lang/Class;)Lorg/apache/dubbo/common/extension/ExtensionLoader;
       9: aload_1
      10: invokestatic  #6                  // Method org/apache/dubbo/remoting/utils/UrlUtils.serializationOrDefault:(Lorg/apache/dubbo/common/URL;)Ljava/lang/String;
      13: invokevirtual #7                  // Method org/apache/dubbo/common/extension/ExtensionLoader.getExtension:(Ljava/lang/String;)Ljava/lang/Object;
      16: checkcast     #4                  // class org/apache/dubbo/common/serialize/Serialization
      19: astore        4
      21: new           #8                  // class java/io/ByteArrayOutputStream
      24: dup
      25: invokespecial #9                  // Method java/io/ByteArrayOutputStream."<init>":()V
      28: astore        5
      30: aconst_null
      31: astore        6
      33: aload         4
      35: aload_1
      36: aload         5
      38: invokeinterface #10,  3           // InterfaceMethod org/apache/dubbo/common/serialize/Serialization.serialize:(Lorg/apache/dubbo/common/URL;Ljava/io/OutputStream;)Lorg/apache/dubbo/common/serialize/ObjectOutput;
      43: astore        7
      45: aload         7
      47: aload_2
      48: invokeinterface #11,  2           // InterfaceMethod org/apache/dubbo/common/serialize/ObjectOutput.writeObject:(Ljava/lang/Object;)V
      53: aload         7
      55: invokeinterface #12,  1           // InterfaceMethod org/apache/dubbo/common/serialize/ObjectOutput.flushBuffer:()V
      60: new           #13                 // class java/io/ByteArrayInputStream
      63: dup
      64: aload         5
      66: invokevirtual #14                 // Method java/io/ByteArrayOutputStream.toByteArray:()[B
      69: invokespecial #15                 // Method java/io/ByteArrayInputStream."<init>":([B)V
      72: astore        8
      74: aconst_null
      75: astore        9
      77: aload         4
      79: aload_1
      80: aload         8
      82: invokeinterface #16,  3           // InterfaceMethod org/apache/dubbo/common/serialize/Serialization.deserialize:(Lorg/apache/dubbo/common/URL;Ljava/io/InputStream;)Lorg/apache/dubbo/common/serialize/ObjectInput;
      87: astore        10
      89: aload         10
      91: aload_3
      92: invokeinterface #17,  2           // InterfaceMethod org/apache/dubbo/common/serialize/ObjectInput.readObject:(Ljava/lang/Class;)Ljava/lang/Object;
      97: astore        11
      99: aload         8
     101: ifnull        134
     104: aload         9
     106: ifnull        129
     109: aload         8
     111: invokevirtual #18                 // Method java/io/ByteArrayInputStream.close:()V
     114: goto          134
     117: astore        12
     119: aload         9
     121: aload         12
     123: invokevirtual #20                 // Method java/lang/Throwable.addSuppressed:(Ljava/lang/Throwable;)V
     126: goto          134
     129: aload         8
     131: invokevirtual #18                 // Method java/io/ByteArrayInputStream.close:()V
     134: aload         5
     136: ifnull        169
     139: aload         6
     141: ifnull        164
     144: aload         5
     146: invokevirtual #21                 // Method java/io/ByteArrayOutputStream.close:()V
     149: goto          169
     152: astore        12
     154: aload         6
     156: aload         12
     158: invokevirtual #20                 // Method java/lang/Throwable.addSuppressed:(Ljava/lang/Throwable;)V
     161: goto          169
     164: aload         5
     166: invokevirtual #21                 // Method java/io/ByteArrayOutputStream.close:()V
     169: aload         11
     171: areturn
     172: astore        10
     174: aload         10
     176: astore        9
     178: aload         10
     180: athrow
     181: astore        13
     183: aload         8
     185: ifnull        218
     188: aload         9
     190: ifnull        213
     193: aload         8
     195: invokevirtual #18                 // Method java/io/ByteArrayInputStream.close:()V
     198: goto          218
     201: astore        14
     203: aload         9
     205: aload         14
     207: invokevirtual #20                 // Method java/lang/Throwable.addSuppressed:(Ljava/lang/Throwable;)V
     210: goto          218
     213: aload         8
     215: invokevirtual #18                 // Method java/io/ByteArrayInputStream.close:()V
     218: aload         13
     220: athrow
     221: astore        8
     223: getstatic     #24                 // Field logger:Lorg/apache/dubbo/common/logger/ErrorTypeAwareLogger;
     226: ldc           #25                 // String 4-6
     228: ldc           #26                 // String
     230: ldc           #26                 // String
     232: ldc           #27                 // String Unable to deep copy parameter to target class.
     234: aload         8
     236: invokeinterface #28,  6           // InterfaceMethod org/apache/dubbo/common/logger/ErrorTypeAwareLogger.error:(Ljava/lang/String;Ljava/lang/String;Ljava/lang/String;Ljava/lang/String;Ljava/lang/Throwable;)V
     241: aload         5
     243: ifnull        328
     246: aload         6
     248: ifnull        271
     251: aload         5
     253: invokevirtual #21                 // Method java/io/ByteArrayOutputStream.close:()V
     256: goto          328
     259: astore        7
     261: aload         6
     263: aload         7
     265: invokevirtual #20                 // Method java/lang/Throwable.addSuppressed:(Ljava/lang/Throwable;)V
     268: goto          328
     271: aload         5
     273: invokevirtual #21                 // Method java/io/ByteArrayOutputStream.close:()V
     276: goto          328
     279: astore        7
     281: aload         7
     283: astore        6
     285: aload         7
     287: athrow
     288: astore        15
     290: aload         5
     292: ifnull        325
     295: aload         6
     297: ifnull        320
     300: aload         5
     302: invokevirtual #21                 // Method java/io/ByteArrayOutputStream.close:()V
     305: goto          325
     308: astore        16
     310: aload         6
     312: aload         16
     314: invokevirtual #20                 // Method java/lang/Throwable.addSuppressed:(Ljava/lang/Throwable;)V
     317: goto          325
     320: aload         5
     322: invokevirtual #21                 // Method java/io/ByteArrayOutputStream.close:()V
     325: aload         15
     327: athrow
     328: goto          351
     331: astore        5
     333: getstatic     #24                 // Field logger:Lorg/apache/dubbo/common/logger/ErrorTypeAwareLogger;
     336: ldc           #25                 // String 4-6
     338: ldc           #26                 // String
     340: ldc           #26                 // String
     342: ldc           #27                 // String Unable to deep copy parameter to target class.
     344: aload         5
     346: invokeinterface #28,  6           // InterfaceMethod org/apache/dubbo/common/logger/ErrorTypeAwareLogger.error:(Ljava/lang/String;Ljava/lang/String;Ljava/lang/String;Ljava/lang/String;Ljava/lang/Throwable;)V
     351: aload_2
     352: invokevirtual #29                 // Method java/lang/Object.getClass:()Ljava/lang/Class;
     355: aload_3
     356: invokevirtual #30                 // Method java/lang/Object.equals:(Ljava/lang/Object;)Z
     359: ifeq          364
     362: aload_2
     363: areturn
     364: aconst_null
     365: areturn
    Exception table:
       from    to  target type
         109   114   117   Class java/lang/Throwable
         144   149   152   Class java/lang/Throwable
          77    99   172   Class java/lang/Throwable
          77    99   181   any
         193   198   201   Class java/lang/Throwable
         172   183   181   any
          60   134   221   Class java/lang/ClassNotFoundException
          60   134   221   Class java/io/IOException
         172   221   221   Class java/lang/ClassNotFoundException
         172   221   221   Class java/io/IOException
         251   256   259   Class java/lang/Throwable
          33   134   279   Class java/lang/Throwable
         172   241   279   Class java/lang/Throwable
          33   134   288   any
         172   241   288   any
         300   305   308   Class java/lang/Throwable
         279   290   288   any
          21   169   331   Class java/lang/Throwable
         172   328   331   Class java/lang/Throwable

  static {};
    Code:
       0: ldc           #31                 // class org/apache/dubbo/rpc/protocol/injvm/DefaultParamDeepCopyUtil
       2: invokestatic  #32                 // Method org/apache/dubbo/common/logger/LoggerFactory.getErrorTypeAwareLogger:(Ljava/lang/Class;)Lorg/apache/dubbo/common/logger/ErrorTypeAwareLogger;
       5: putstatic     #24                 // Field logger:Lorg/apache/dubbo/common/logger/ErrorTypeAwareLogger;
       8: return
}
