Compiled from "InjvmProtocol.java"
public class org.apache.dubbo.rpc.protocol.injvm.InjvmProtocol extends org.apache.dubbo.rpc.protocol.AbstractProtocol {
  public static final java.lang.String NAME;

  public static final int DEFAULT_PORT;

  public org.apache.dubbo.rpc.protocol.injvm.InjvmProtocol();
    Code:
       0: aload_0
       1: invokespecial #3                  // Method org/apache/dubbo/rpc/protocol/AbstractProtocol."<init>":()V
       4: return

  public static org.apache.dubbo.rpc.protocol.injvm.InjvmProtocol getInjvmProtocol(org.apache.dubbo.rpc.model.ScopeModel);
    Code:
       0: aload_0
       1: ldc           #4                  // class org/apache/dubbo/rpc/Protocol
       3: invokevirtual #5                  // Method org/apache/dubbo/rpc/model/ScopeModel.getExtensionLoader:(Ljava/lang/Class;)Lorg/apache/dubbo/common/extension/ExtensionLoader;
       6: ldc           #7                  // String injvm
       8: iconst_0
       9: invokevirtual #8                  // Method org/apache/dubbo/common/extension/ExtensionLoader.getExtension:(Ljava/lang/String;Z)Ljava/lang/Object;
      12: checkcast     #6                  // class org/apache/dubbo/rpc/protocol/injvm/InjvmProtocol
      15: areturn

  static org.apache.dubbo.rpc.Exporter<?> getExporter(java.util.Map<java.lang.String, org.apache.dubbo.rpc.Exporter<?>>, org.apache.dubbo.common.URL);
    Code:
       0: aconst_null
       1: astore_2
       2: aload_1
       3: invokevirtual #9                  // Method org/apache/dubbo/common/URL.getServiceKey:()Ljava/lang/String;
       6: ldc           #10                 // String *
       8: invokevirtual #11                 // Method java/lang/String.contains:(Ljava/lang/CharSequence;)Z
      11: ifne          31
      14: aload_0
      15: aload_1
      16: invokevirtual #9                  // Method org/apache/dubbo/common/URL.getServiceKey:()Ljava/lang/String;
      19: invokeinterface #12,  2           // InterfaceMethod java/util/Map.get:(Ljava/lang/Object;)Ljava/lang/Object;
      24: checkcast     #13                 // class org/apache/dubbo/rpc/Exporter
      27: astore_2
      28: goto          98
      31: aload_0
      32: invokestatic  #14                 // Method org/apache/dubbo/common/utils/CollectionUtils.isNotEmptyMap:(Ljava/util/Map;)Z
      35: ifeq          98
      38: aload_0
      39: invokeinterface #15,  1           // InterfaceMethod java/util/Map.values:()Ljava/util/Collection;
      44: invokeinterface #16,  1           // InterfaceMethod java/util/Collection.iterator:()Ljava/util/Iterator;
      49: astore_3
      50: aload_3
      51: invokeinterface #17,  1           // InterfaceMethod java/util/Iterator.hasNext:()Z
      56: ifeq          98
      59: aload_3
      60: invokeinterface #18,  1           // InterfaceMethod java/util/Iterator.next:()Ljava/lang/Object;
      65: checkcast     #13                 // class org/apache/dubbo/rpc/Exporter
      68: astore        4
      70: aload_1
      71: aload         4
      73: invokeinterface #19,  1           // InterfaceMethod org/apache/dubbo/rpc/Exporter.getInvoker:()Lorg/apache/dubbo/rpc/Invoker;
      78: invokeinterface #20,  1           // InterfaceMethod org/apache/dubbo/rpc/Invoker.getUrl:()Lorg/apache/dubbo/common/URL;
      83: invokestatic  #21                 // Method org/apache/dubbo/common/utils/UrlUtils.isServiceKeyMatch:(Lorg/apache/dubbo/common/URL;Lorg/apache/dubbo/common/URL;)Z
      86: ifeq          95
      89: aload         4
      91: astore_2
      92: goto          98
      95: goto          50
      98: aload_2
      99: ifnonnull     104
     102: aconst_null
     103: areturn
     104: aload_2
     105: invokeinterface #19,  1           // InterfaceMethod org/apache/dubbo/rpc/Exporter.getInvoker:()Lorg/apache/dubbo/rpc/Invoker;
     110: invokeinterface #20,  1           // InterfaceMethod org/apache/dubbo/rpc/Invoker.getUrl:()Lorg/apache/dubbo/common/URL;
     115: ldc           #22                 // String generic
     117: invokevirtual #23                 // Method org/apache/dubbo/common/URL.getParameter:(Ljava/lang/String;)Ljava/lang/String;
     120: invokestatic  #24                 // Method org/apache/dubbo/rpc/support/ProtocolUtils.isGeneric:(Ljava/lang/String;)Z
     123: ifeq          128
     126: aconst_null
     127: areturn
     128: aload_2
     129: areturn

  public int getDefaultPort();
    Code:
       0: iconst_0
       1: ireturn

  public <T> org.apache.dubbo.rpc.Exporter<T> export(org.apache.dubbo.rpc.Invoker<T>) throws org.apache.dubbo.rpc.RpcException;
    Code:
       0: new           #25                 // class org/apache/dubbo/rpc/protocol/injvm/InjvmExporter
       3: dup
       4: aload_1
       5: aload_1
       6: invokeinterface #20,  1           // InterfaceMethod org/apache/dubbo/rpc/Invoker.getUrl:()Lorg/apache/dubbo/common/URL;
      11: invokevirtual #9                  // Method org/apache/dubbo/common/URL.getServiceKey:()Ljava/lang/String;
      14: aload_0
      15: getfield      #26                 // Field exporterMap:Ljava/util/Map;
      18: invokespecial #27                 // Method org/apache/dubbo/rpc/protocol/injvm/InjvmExporter."<init>":(Lorg/apache/dubbo/rpc/Invoker;Ljava/lang/String;Ljava/util/Map;)V
      21: areturn

  public <T> org.apache.dubbo.rpc.Invoker<T> protocolBindingRefer(java.lang.Class<T>, org.apache.dubbo.common.URL) throws org.apache.dubbo.rpc.RpcException;
    Code:
       0: new           #28                 // class org/apache/dubbo/rpc/protocol/injvm/InjvmInvoker
       3: dup
       4: aload_1
       5: aload_2
       6: aload_2
       7: invokevirtual #9                  // Method org/apache/dubbo/common/URL.getServiceKey:()Ljava/lang/String;
      10: aload_0
      11: getfield      #26                 // Field exporterMap:Ljava/util/Map;
      14: invokespecial #29                 // Method org/apache/dubbo/rpc/protocol/injvm/InjvmInvoker."<init>":(Ljava/lang/Class;Lorg/apache/dubbo/common/URL;Ljava/lang/String;Ljava/util/Map;)V
      17: areturn

  public boolean isInjvmRefer(org.apache.dubbo.common.URL);
    Code:
       0: aload_1
       1: ldc           #30                 // String scope
       3: invokevirtual #23                 // Method org/apache/dubbo/common/URL.getParameter:(Ljava/lang/String;)Ljava/lang/String;
       6: astore_2
       7: ldc           #31                 // String local
       9: aload_2
      10: invokevirtual #32                 // Method java/lang/String.equals:(Ljava/lang/Object;)Z
      13: ifne          26
      16: aload_1
      17: ldc           #7                  // String injvm
      19: iconst_0
      20: invokevirtual #33                 // Method org/apache/dubbo/common/URL.getParameter:(Ljava/lang/String;Z)Z
      23: ifeq          28
      26: iconst_1
      27: ireturn
      28: ldc           #34                 // String remote
      30: aload_2
      31: invokevirtual #32                 // Method java/lang/String.equals:(Ljava/lang/Object;)Z
      34: ifeq          39
      37: iconst_0
      38: ireturn
      39: aload_1
      40: ldc           #22                 // String generic
      42: iconst_0
      43: invokevirtual #33                 // Method org/apache/dubbo/common/URL.getParameter:(Ljava/lang/String;Z)Z
      46: ifeq          51
      49: iconst_0
      50: ireturn
      51: aload_0
      52: getfield      #26                 // Field exporterMap:Ljava/util/Map;
      55: aload_1
      56: invokestatic  #35                 // Method getExporter:(Ljava/util/Map;Lorg/apache/dubbo/common/URL;)Lorg/apache/dubbo/rpc/Exporter;
      59: ifnull        80
      62: ldc           #36                 // String broadcast
      64: aload_1
      65: ldc           #37                 // String cluster
      67: invokevirtual #23                 // Method org/apache/dubbo/common/URL.getParameter:(Ljava/lang/String;)Ljava/lang/String;
      70: invokevirtual #38                 // Method java/lang/String.equalsIgnoreCase:(Ljava/lang/String;)Z
      73: ifeq          78
      76: iconst_0
      77: ireturn
      78: iconst_1
      79: ireturn
      80: iconst_0
      81: ireturn
}
