Compiled from "AccessLogData.java"
public final class org.apache.dubbo.rpc.support.AccessLogData {
  private static final java.lang.String MESSAGE_DATE_FORMAT;

  private static final java.time.format.DateTimeFormatter MESSAGE_DATE_FORMATTER;

  private static final java.lang.String VERSION;

  private static final java.lang.String GROUP;

  private static final java.lang.String SERVICE;

  private static final java.lang.String METHOD_NAME;

  private static final java.lang.String INVOCATION_TIME;

  private static final java.lang.String OUT_TIME;

  private static final java.lang.String TYPES;

  private static final java.lang.String ARGUMENTS;

  private static final java.lang.String REMOTE_HOST;

  private static final java.lang.String REMOTE_PORT;

  private static final java.lang.String LOCAL_HOST;

  private static final java.lang.String LOCAL_PORT;

  private final java.util.Map<java.lang.String, java.lang.Object> data;

  private org.apache.dubbo.rpc.support.AccessLogData();
    Code:
       0: aload_0
       1: invokespecial #1                  // Method java/lang/Object."<init>":()V
       4: invokestatic  #2                  // Method org/apache/dubbo/rpc/RpcContext.getServiceContext:()Lorg/apache/dubbo/rpc/RpcServiceContext;
       7: astore_1
       8: aload_0
       9: new           #3                  // class java/util/HashMap
      12: dup
      13: invokespecial #4                  // Method java/util/HashMap."<init>":()V
      16: putfield      #5                  // Field data:Ljava/util/Map;
      19: aload_0
      20: aload_1
      21: invokevirtual #6                  // Method org/apache/dubbo/rpc/RpcContext.getLocalHost:()Ljava/lang/String;
      24: invokespecial #7                  // Method setLocalHost:(Ljava/lang/String;)V
      27: aload_0
      28: aload_1
      29: invokevirtual #8                  // Method org/apache/dubbo/rpc/RpcContext.getLocalPort:()I
      32: invokestatic  #9                  // Method java/lang/Integer.valueOf:(I)Ljava/lang/Integer;
      35: invokespecial #10                 // Method setLocalPort:(Ljava/lang/Integer;)V
      38: aload_0
      39: aload_1
      40: invokevirtual #11                 // Method org/apache/dubbo/rpc/RpcContext.getRemoteHost:()Ljava/lang/String;
      43: invokespecial #12                 // Method setRemoteHost:(Ljava/lang/String;)V
      46: aload_0
      47: aload_1
      48: invokevirtual #13                 // Method org/apache/dubbo/rpc/RpcContext.getRemotePort:()I
      51: invokestatic  #9                  // Method java/lang/Integer.valueOf:(I)Ljava/lang/Integer;
      54: invokespecial #14                 // Method setRemotePort:(Ljava/lang/Integer;)V
      57: return

  public static org.apache.dubbo.rpc.support.AccessLogData newLogData();
    Code:
       0: new           #15                 // class org/apache/dubbo/rpc/support/AccessLogData
       3: dup
       4: invokespecial #16                 // Method "<init>":()V
       7: areturn

  public void setVersion(java.lang.String);
    Code:
       0: aload_0
       1: ldc           #17                 // String version
       3: aload_1
       4: invokespecial #18                 // Method set:(Ljava/lang/String;Ljava/lang/Object;)V
       7: return

  public void setServiceName(java.lang.String);
    Code:
       0: aload_0
       1: ldc           #19                 // String service
       3: aload_1
       4: invokespecial #18                 // Method set:(Ljava/lang/String;Ljava/lang/Object;)V
       7: return

  public void setGroup(java.lang.String);
    Code:
       0: aload_0
       1: ldc           #20                 // String group
       3: aload_1
       4: invokespecial #18                 // Method set:(Ljava/lang/String;Ljava/lang/Object;)V
       7: return

  public void setInvocationTime(java.util.Date);
    Code:
       0: aload_0
       1: ldc           #21                 // String invocation-time
       3: aload_1
       4: invokespecial #18                 // Method set:(Ljava/lang/String;Ljava/lang/Object;)V
       7: return

  public void setOutTime(java.util.Date);
    Code:
       0: aload_0
       1: ldc           #22                 // String out-time
       3: aload_1
       4: invokespecial #18                 // Method set:(Ljava/lang/String;Ljava/lang/Object;)V
       7: return

  private void setRemoteHost(java.lang.String);
    Code:
       0: aload_0
       1: ldc           #23                 // String remote-host
       3: aload_1
       4: invokespecial #18                 // Method set:(Ljava/lang/String;Ljava/lang/Object;)V
       7: return

  private void setRemotePort(java.lang.Integer);
    Code:
       0: aload_0
       1: ldc           #24                 // String remote-port
       3: aload_1
       4: invokespecial #18                 // Method set:(Ljava/lang/String;Ljava/lang/Object;)V
       7: return

  private void setLocalHost(java.lang.String);
    Code:
       0: aload_0
       1: ldc           #25                 // String localhost
       3: aload_1
       4: invokespecial #18                 // Method set:(Ljava/lang/String;Ljava/lang/Object;)V
       7: return

  private void setLocalPort(java.lang.Integer);
    Code:
       0: aload_0
       1: ldc           #26                 // String local-port
       3: aload_1
       4: invokespecial #18                 // Method set:(Ljava/lang/String;Ljava/lang/Object;)V
       7: return

  public void setMethodName(java.lang.String);
    Code:
       0: aload_0
       1: ldc           #27                 // String method-name
       3: aload_1
       4: invokespecial #18                 // Method set:(Ljava/lang/String;Ljava/lang/Object;)V
       7: return

  public void setTypes(java.lang.Class[]);
    Code:
       0: aload_0
       1: ldc           #28                 // String types
       3: aload_1
       4: ifnull        16
       7: aload_1
       8: aload_1
       9: arraylength
      10: invokestatic  #29                 // Method java/util/Arrays.copyOf:([Ljava/lang/Object;I)[Ljava/lang/Object;
      13: goto          17
      16: aconst_null
      17: invokespecial #18                 // Method set:(Ljava/lang/String;Ljava/lang/Object;)V
      20: return

  public void setArguments(java.lang.Object[]);
    Code:
       0: aload_0
       1: ldc           #30                 // String arguments
       3: aload_1
       4: ifnull        16
       7: aload_1
       8: aload_1
       9: arraylength
      10: invokestatic  #29                 // Method java/util/Arrays.copyOf:([Ljava/lang/Object;I)[Ljava/lang/Object;
      13: goto          17
      16: aconst_null
      17: invokespecial #18                 // Method set:(Ljava/lang/String;Ljava/lang/Object;)V
      20: return

  public java.lang.String getServiceName();
    Code:
       0: aload_0
       1: ldc           #19                 // String service
       3: invokespecial #31                 // Method get:(Ljava/lang/String;)Ljava/lang/Object;
       6: invokevirtual #32                 // Method java/lang/Object.toString:()Ljava/lang/String;
       9: areturn

  public java.lang.String getLogMessage();
    Code:
       0: new           #33                 // class java/lang/StringBuilder
       3: dup
       4: invokespecial #34                 // Method java/lang/StringBuilder."<init>":()V
       7: astore_1
       8: aload_1
       9: ldc           #35                 // String [
      11: invokevirtual #36                 // Method java/lang/StringBuilder.append:(Ljava/lang/String;)Ljava/lang/StringBuilder;
      14: aload_0
      15: invokespecial #37                 // Method getInvocationTime:()Ljava/util/Date;
      18: invokevirtual #38                 // Method java/util/Date.toInstant:()Ljava/time/Instant;
      21: invokestatic  #39                 // Method java/time/ZoneId.systemDefault:()Ljava/time/ZoneId;
      24: invokestatic  #40                 // Method java/time/LocalDateTime.ofInstant:(Ljava/time/Instant;Ljava/time/ZoneId;)Ljava/time/LocalDateTime;
      27: getstatic     #41                 // Field MESSAGE_DATE_FORMATTER:Ljava/time/format/DateTimeFormatter;
      30: invokevirtual #42                 // Method java/time/LocalDateTime.format:(Ljava/time/format/DateTimeFormatter;)Ljava/lang/String;
      33: invokevirtual #36                 // Method java/lang/StringBuilder.append:(Ljava/lang/String;)Ljava/lang/StringBuilder;
      36: ldc           #43                 // String ]
      38: invokevirtual #36                 // Method java/lang/StringBuilder.append:(Ljava/lang/String;)Ljava/lang/StringBuilder;
      41: ldc           #44                 // String ->
      43: invokevirtual #36                 // Method java/lang/StringBuilder.append:(Ljava/lang/String;)Ljava/lang/StringBuilder;
      46: ldc           #35                 // String [
      48: invokevirtual #36                 // Method java/lang/StringBuilder.append:(Ljava/lang/String;)Ljava/lang/StringBuilder;
      51: aload_0
      52: invokespecial #45                 // Method getOutTime:()Ljava/util/Date;
      55: invokevirtual #38                 // Method java/util/Date.toInstant:()Ljava/time/Instant;
      58: invokestatic  #39                 // Method java/time/ZoneId.systemDefault:()Ljava/time/ZoneId;
      61: invokestatic  #40                 // Method java/time/LocalDateTime.ofInstant:(Ljava/time/Instant;Ljava/time/ZoneId;)Ljava/time/LocalDateTime;
      64: getstatic     #41                 // Field MESSAGE_DATE_FORMATTER:Ljava/time/format/DateTimeFormatter;
      67: invokevirtual #42                 // Method java/time/LocalDateTime.format:(Ljava/time/format/DateTimeFormatter;)Ljava/lang/String;
      70: invokevirtual #36                 // Method java/lang/StringBuilder.append:(Ljava/lang/String;)Ljava/lang/StringBuilder;
      73: ldc           #43                 // String ]
      75: invokevirtual #36                 // Method java/lang/StringBuilder.append:(Ljava/lang/String;)Ljava/lang/StringBuilder;
      78: aload_0
      79: ldc           #23                 // String remote-host
      81: invokespecial #31                 // Method get:(Ljava/lang/String;)Ljava/lang/Object;
      84: invokevirtual #46                 // Method java/lang/StringBuilder.append:(Ljava/lang/Object;)Ljava/lang/StringBuilder;
      87: bipush        58
      89: invokevirtual #47                 // Method java/lang/StringBuilder.append:(C)Ljava/lang/StringBuilder;
      92: aload_0
      93: ldc           #24                 // String remote-port
      95: invokespecial #31                 // Method get:(Ljava/lang/String;)Ljava/lang/Object;
      98: invokevirtual #46                 // Method java/lang/StringBuilder.append:(Ljava/lang/Object;)Ljava/lang/StringBuilder;
     101: ldc           #48                 // String  ->
     103: invokevirtual #36                 // Method java/lang/StringBuilder.append:(Ljava/lang/String;)Ljava/lang/StringBuilder;
     106: aload_0
     107: ldc           #25                 // String localhost
     109: invokespecial #31                 // Method get:(Ljava/lang/String;)Ljava/lang/Object;
     112: invokevirtual #46                 // Method java/lang/StringBuilder.append:(Ljava/lang/Object;)Ljava/lang/StringBuilder;
     115: bipush        58
     117: invokevirtual #47                 // Method java/lang/StringBuilder.append:(C)Ljava/lang/StringBuilder;
     120: aload_0
     121: ldc           #26                 // String local-port
     123: invokespecial #31                 // Method get:(Ljava/lang/String;)Ljava/lang/Object;
     126: invokevirtual #46                 // Method java/lang/StringBuilder.append:(Ljava/lang/Object;)Ljava/lang/StringBuilder;
     129: ldc           #49                 // String  -
     131: invokevirtual #36                 // Method java/lang/StringBuilder.append:(Ljava/lang/String;)Ljava/lang/StringBuilder;
     134: pop
     135: aload_0
     136: ldc           #20                 // String group
     138: invokespecial #31                 // Method get:(Ljava/lang/String;)Ljava/lang/Object;
     141: ifnull        156
     144: aload_0
     145: ldc           #20                 // String group
     147: invokespecial #31                 // Method get:(Ljava/lang/String;)Ljava/lang/Object;
     150: invokevirtual #32                 // Method java/lang/Object.toString:()Ljava/lang/String;
     153: goto          158
     156: ldc           #50                 // String
     158: astore_2
     159: aload_2
     160: invokestatic  #51                 // Method org/apache/dubbo/common/utils/StringUtils.isNotEmpty:(Ljava/lang/String;)Z
     163: ifeq          177
     166: aload_1
     167: aload_2
     168: invokevirtual #36                 // Method java/lang/StringBuilder.append:(Ljava/lang/String;)Ljava/lang/StringBuilder;
     171: bipush        47
     173: invokevirtual #47                 // Method java/lang/StringBuilder.append:(C)Ljava/lang/StringBuilder;
     176: pop
     177: aload_1
     178: aload_0
     179: ldc           #19                 // String service
     181: invokespecial #31                 // Method get:(Ljava/lang/String;)Ljava/lang/Object;
     184: invokevirtual #46                 // Method java/lang/StringBuilder.append:(Ljava/lang/Object;)Ljava/lang/StringBuilder;
     187: pop
     188: aload_0
     189: ldc           #17                 // String version
     191: invokespecial #31                 // Method get:(Ljava/lang/String;)Ljava/lang/Object;
     194: ifnull        209
     197: aload_0
     198: ldc           #17                 // String version
     200: invokespecial #31                 // Method get:(Ljava/lang/String;)Ljava/lang/Object;
     203: invokevirtual #32                 // Method java/lang/Object.toString:()Ljava/lang/String;
     206: goto          211
     209: ldc           #50                 // String
     211: astore_3
     212: aload_3
     213: invokestatic  #51                 // Method org/apache/dubbo/common/utils/StringUtils.isNotEmpty:(Ljava/lang/String;)Z
     216: ifeq          230
     219: aload_1
     220: bipush        58
     222: invokevirtual #47                 // Method java/lang/StringBuilder.append:(C)Ljava/lang/StringBuilder;
     225: aload_3
     226: invokevirtual #36                 // Method java/lang/StringBuilder.append:(Ljava/lang/String;)Ljava/lang/StringBuilder;
     229: pop
     230: aload_1
     231: bipush        32
     233: invokevirtual #47                 // Method java/lang/StringBuilder.append:(C)Ljava/lang/StringBuilder;
     236: pop
     237: aload_1
     238: aload_0
     239: ldc           #27                 // String method-name
     241: invokespecial #31                 // Method get:(Ljava/lang/String;)Ljava/lang/Object;
     244: invokevirtual #46                 // Method java/lang/StringBuilder.append:(Ljava/lang/Object;)Ljava/lang/StringBuilder;
     247: pop
     248: aload_1
     249: bipush        40
     251: invokevirtual #47                 // Method java/lang/StringBuilder.append:(C)Ljava/lang/StringBuilder;
     254: pop
     255: aload_0
     256: ldc           #28                 // String types
     258: invokespecial #31                 // Method get:(Ljava/lang/String;)Ljava/lang/Object;
     261: ifnull        279
     264: aload_0
     265: ldc           #28                 // String types
     267: invokespecial #31                 // Method get:(Ljava/lang/String;)Ljava/lang/Object;
     270: checkcast     #52                 // class "[Ljava/lang/Class;"
     273: checkcast     #52                 // class "[Ljava/lang/Class;"
     276: goto          283
     279: iconst_0
     280: anewarray     #53                 // class java/lang/Class
     283: astore        4
     285: iconst_1
     286: istore        5
     288: aload         4
     290: astore        6
     292: aload         6
     294: arraylength
     295: istore        7
     297: iconst_0
     298: istore        8
     300: iload         8
     302: iload         7
     304: if_icmpge     348
     307: aload         6
     309: iload         8
     311: aaload
     312: astore        9
     314: iload         5
     316: ifeq          325
     319: iconst_0
     320: istore        5
     322: goto          332
     325: aload_1
     326: bipush        44
     328: invokevirtual #47                 // Method java/lang/StringBuilder.append:(C)Ljava/lang/StringBuilder;
     331: pop
     332: aload_1
     333: aload         9
     335: invokevirtual #54                 // Method java/lang/Class.getName:()Ljava/lang/String;
     338: invokevirtual #36                 // Method java/lang/StringBuilder.append:(Ljava/lang/String;)Ljava/lang/StringBuilder;
     341: pop
     342: iinc          8, 1
     345: goto          300
     348: aload_1
     349: ldc           #55                 // String )
     351: invokevirtual #36                 // Method java/lang/StringBuilder.append:(Ljava/lang/String;)Ljava/lang/StringBuilder;
     354: pop
     355: aload_0
     356: ldc           #30                 // String arguments
     358: invokespecial #31                 // Method get:(Ljava/lang/String;)Ljava/lang/Object;
     361: ifnull        379
     364: aload_0
     365: ldc           #30                 // String arguments
     367: invokespecial #31                 // Method get:(Ljava/lang/String;)Ljava/lang/Object;
     370: checkcast     #56                 // class "[Ljava/lang/Object;"
     373: checkcast     #56                 // class "[Ljava/lang/Object;"
     376: goto          380
     379: aconst_null
     380: astore        6
     382: aload         6
     384: ifnull        403
     387: aload         6
     389: arraylength
     390: ifle          403
     393: aload_1
     394: aload         6
     396: invokestatic  #57                 // Method org/apache/dubbo/common/utils/JsonUtils.toJson:(Ljava/lang/Object;)Ljava/lang/String;
     399: invokevirtual #36                 // Method java/lang/StringBuilder.append:(Ljava/lang/String;)Ljava/lang/StringBuilder;
     402: pop
     403: aload_1
     404: invokevirtual #58                 // Method java/lang/StringBuilder.toString:()Ljava/lang/String;
     407: areturn

  private java.util.Date getInvocationTime();
    Code:
       0: aload_0
       1: ldc           #21                 // String invocation-time
       3: invokespecial #31                 // Method get:(Ljava/lang/String;)Ljava/lang/Object;
       6: checkcast     #59                 // class java/util/Date
       9: areturn

  private java.util.Date getOutTime();
    Code:
       0: aload_0
       1: ldc           #22                 // String out-time
       3: invokespecial #31                 // Method get:(Ljava/lang/String;)Ljava/lang/Object;
       6: checkcast     #59                 // class java/util/Date
       9: areturn

  private java.lang.Object get(java.lang.String);
    Code:
       0: aload_0
       1: getfield      #5                  // Field data:Ljava/util/Map;
       4: aload_1
       5: invokeinterface #60,  2           // InterfaceMethod java/util/Map.get:(Ljava/lang/Object;)Ljava/lang/Object;
      10: areturn

  private void set(java.lang.String, java.lang.Object);
    Code:
       0: aload_0
       1: getfield      #5                  // Field data:Ljava/util/Map;
       4: aload_1
       5: aload_2
       6: invokeinterface #61,  3           // InterfaceMethod java/util/Map.put:(Ljava/lang/Object;Ljava/lang/Object;)Ljava/lang/Object;
      11: pop
      12: return

  public void buildAccessLogData(org.apache.dubbo.rpc.Invoker<?>, org.apache.dubbo.rpc.Invocation);
    Code:
       0: aload_0
       1: aload_1
       2: invokeinterface #62,  1           // InterfaceMethod org/apache/dubbo/rpc/Invoker.getInterface:()Ljava/lang/Class;
       7: invokevirtual #54                 // Method java/lang/Class.getName:()Ljava/lang/String;
      10: invokevirtual #63                 // Method setServiceName:(Ljava/lang/String;)V
      13: aload_0
      14: aload_2
      15: invokeinterface #64,  1           // InterfaceMethod org/apache/dubbo/rpc/Invocation.getMethodName:()Ljava/lang/String;
      20: invokevirtual #65                 // Method setMethodName:(Ljava/lang/String;)V
      23: aload_0
      24: aload_1
      25: invokeinterface #66,  1           // InterfaceMethod org/apache/dubbo/rpc/Invoker.getUrl:()Lorg/apache/dubbo/common/URL;
      30: invokevirtual #67                 // Method org/apache/dubbo/common/URL.getVersion:()Ljava/lang/String;
      33: invokevirtual #68                 // Method setVersion:(Ljava/lang/String;)V
      36: aload_0
      37: aload_1
      38: invokeinterface #66,  1           // InterfaceMethod org/apache/dubbo/rpc/Invoker.getUrl:()Lorg/apache/dubbo/common/URL;
      43: invokevirtual #69                 // Method org/apache/dubbo/common/URL.getGroup:()Ljava/lang/String;
      46: invokevirtual #70                 // Method setGroup:(Ljava/lang/String;)V
      49: aload_0
      50: new           #59                 // class java/util/Date
      53: dup
      54: invokespecial #71                 // Method java/util/Date."<init>":()V
      57: invokevirtual #72                 // Method setInvocationTime:(Ljava/util/Date;)V
      60: aload_0
      61: aload_2
      62: invokeinterface #73,  1           // InterfaceMethod org/apache/dubbo/rpc/Invocation.getParameterTypes:()[Ljava/lang/Class;
      67: invokevirtual #74                 // Method setTypes:([Ljava/lang/Class;)V
      70: aload_0
      71: aload_2
      72: invokeinterface #75,  1           // InterfaceMethod org/apache/dubbo/rpc/Invocation.getArguments:()[Ljava/lang/Object;
      77: invokevirtual #76                 // Method setArguments:([Ljava/lang/Object;)V
      80: return

  static {};
    Code:
       0: ldc           #77                 // String yyyy-MM-dd HH:mm:ss.SSSSS
       2: invokestatic  #78                 // Method java/time/format/DateTimeFormatter.ofPattern:(Ljava/lang/String;)Ljava/time/format/DateTimeFormatter;
       5: putstatic     #41                 // Field MESSAGE_DATE_FORMATTER:Ljava/time/format/DateTimeFormatter;
       8: return
}
