Compiled from "MockProtocol.java"
public final class org.apache.dubbo.rpc.support.MockProtocol extends org.apache.dubbo.rpc.protocol.AbstractProtocol {
  public org.apache.dubbo.rpc.support.MockProtocol();
    Code:
       0: aload_0
       1: invokespecial #1                  // Method org/apache/dubbo/rpc/protocol/AbstractProtocol."<init>":()V
       4: return

  public int getDefaultPort();
    Code:
       0: iconst_0
       1: ireturn

  public <T> org.apache.dubbo.rpc.Exporter<T> export(org.apache.dubbo.rpc.Invoker<T>) throws org.apache.dubbo.rpc.RpcException;
    Code:
       0: new           #2                  // class java/lang/UnsupportedOperationException
       3: dup
       4: invokespecial #3                  // Method java/lang/UnsupportedOperationException."<init>":()V
       7: athrow

  public <T> org.apache.dubbo.rpc.Invoker<T> protocolBindingRefer(java.lang.Class<T>, org.apache.dubbo.common.URL) throws org.apache.dubbo.rpc.RpcException;
    Code:
       0: new           #4                  // class org/apache/dubbo/rpc/support/MockInvoker
       3: dup
       4: aload_2
       5: aload_1
       6: invokespecial #5                  // Method org/apache/dubbo/rpc/support/MockInvoker."<init>":(Lorg/apache/dubbo/common/URL;Ljava/lang/Class;)V
       9: areturn
}
