Compiled from "RpcUtils.java"
public class org.apache.dubbo.rpc.support.RpcUtils {
  private static final org.apache.dubbo.common.logger.ErrorTypeAwareLogger logger;

  private static final java.util.concurrent.atomic.AtomicLong INVOKE_ID;

  public org.apache.dubbo.rpc.support.RpcUtils();
    Code:
       0: aload_0
       1: invokespecial #4                  // Method java/lang/Object."<init>":()V
       4: return

  public static java.lang.Class<?> getReturnType(org.apache.dubbo.rpc.Invocation);
    Code:
       0: aload_0
       1: ifnull        98
       4: aload_0
       5: invokeinterface #5,  1            // InterfaceMethod org/apache/dubbo/rpc/Invocation.getInvoker:()Lorg/apache/dubbo/rpc/Invoker;
      10: ifnull        98
      13: aload_0
      14: invokeinterface #5,  1            // InterfaceMethod org/apache/dubbo/rpc/Invocation.getInvoker:()Lorg/apache/dubbo/rpc/Invoker;
      19: invokeinterface #6,  1            // InterfaceMethod org/apache/dubbo/rpc/Invoker.getUrl:()Lorg/apache/dubbo/common/URL;
      24: ifnull        98
      27: aload_0
      28: invokeinterface #5,  1            // InterfaceMethod org/apache/dubbo/rpc/Invocation.getInvoker:()Lorg/apache/dubbo/rpc/Invoker;
      33: invokeinterface #7,  1            // InterfaceMethod org/apache/dubbo/rpc/Invoker.getInterface:()Ljava/lang/Class;
      38: ldc           #8                  // class org/apache/dubbo/rpc/service/GenericService
      40: if_acmpeq     98
      43: aload_0
      44: invokeinterface #9,  1            // InterfaceMethod org/apache/dubbo/rpc/Invocation.getMethodName:()Ljava/lang/String;
      49: ldc           #10                 // String $
      51: invokevirtual #11                 // Method java/lang/String.startsWith:(Ljava/lang/String;)Z
      54: ifne          98
      57: aload_0
      58: invokeinterface #5,  1            // InterfaceMethod org/apache/dubbo/rpc/Invocation.getInvoker:()Lorg/apache/dubbo/rpc/Invoker;
      63: invokeinterface #6,  1            // InterfaceMethod org/apache/dubbo/rpc/Invoker.getUrl:()Lorg/apache/dubbo/common/URL;
      68: invokevirtual #12                 // Method org/apache/dubbo/common/URL.getServiceInterface:()Ljava/lang/String;
      71: astore_1
      72: aload_1
      73: invokestatic  #13                 // Method org/apache/dubbo/common/utils/StringUtils.isNotEmpty:(Ljava/lang/String;)Z
      76: ifeq          98
      79: aload_0
      80: aload_1
      81: invokestatic  #14                 // Method getMethodByService:(Lorg/apache/dubbo/rpc/Invocation;Ljava/lang/String;)Ljava/lang/reflect/Method;
      84: astore_2
      85: aload_2
      86: ifnonnull     93
      89: aconst_null
      90: goto          97
      93: aload_2
      94: invokevirtual #15                 // Method java/lang/reflect/Method.getReturnType:()Ljava/lang/Class;
      97: areturn
      98: goto          121
     101: astore_1
     102: getstatic     #17                 // Field logger:Lorg/apache/dubbo/common/logger/ErrorTypeAwareLogger;
     105: ldc           #18                 // String 0-8
     107: ldc           #19                 // String
     109: ldc           #19                 // String
     111: aload_1
     112: invokevirtual #20                 // Method java/lang/Throwable.getMessage:()Ljava/lang/String;
     115: aload_1
     116: invokeinterface #21,  6           // InterfaceMethod org/apache/dubbo/common/logger/ErrorTypeAwareLogger.warn:(Ljava/lang/String;Ljava/lang/String;Ljava/lang/String;Ljava/lang/String;Ljava/lang/Throwable;)V
     121: aconst_null
     122: areturn
    Exception table:
       from    to  target type
           0    97   101   Class java/lang/Throwable

  public static java.lang.reflect.Type[] getReturnTypes(org.apache.dubbo.rpc.Invocation);
    Code:
       0: aload_0
       1: ifnull        123
       4: aload_0
       5: invokeinterface #5,  1            // InterfaceMethod org/apache/dubbo/rpc/Invocation.getInvoker:()Lorg/apache/dubbo/rpc/Invoker;
      10: ifnull        123
      13: aload_0
      14: invokeinterface #5,  1            // InterfaceMethod org/apache/dubbo/rpc/Invocation.getInvoker:()Lorg/apache/dubbo/rpc/Invoker;
      19: invokeinterface #6,  1            // InterfaceMethod org/apache/dubbo/rpc/Invoker.getUrl:()Lorg/apache/dubbo/common/URL;
      24: ifnull        123
      27: aload_0
      28: invokeinterface #5,  1            // InterfaceMethod org/apache/dubbo/rpc/Invocation.getInvoker:()Lorg/apache/dubbo/rpc/Invoker;
      33: invokeinterface #7,  1            // InterfaceMethod org/apache/dubbo/rpc/Invoker.getInterface:()Ljava/lang/Class;
      38: ldc           #8                  // class org/apache/dubbo/rpc/service/GenericService
      40: if_acmpeq     123
      43: aload_0
      44: invokeinterface #9,  1            // InterfaceMethod org/apache/dubbo/rpc/Invocation.getMethodName:()Ljava/lang/String;
      49: ldc           #10                 // String $
      51: invokevirtual #11                 // Method java/lang/String.startsWith:(Ljava/lang/String;)Z
      54: ifne          123
      57: aconst_null
      58: astore_1
      59: aload_0
      60: instanceof    #22                 // class org/apache/dubbo/rpc/RpcInvocation
      63: ifeq          80
      66: aload_0
      67: checkcast     #22                 // class org/apache/dubbo/rpc/RpcInvocation
      70: invokevirtual #23                 // Method org/apache/dubbo/rpc/RpcInvocation.getReturnTypes:()[Ljava/lang/reflect/Type;
      73: astore_1
      74: aload_1
      75: ifnull        80
      78: aload_1
      79: areturn
      80: aload_0
      81: invokeinterface #5,  1            // InterfaceMethod org/apache/dubbo/rpc/Invocation.getInvoker:()Lorg/apache/dubbo/rpc/Invoker;
      86: invokeinterface #6,  1            // InterfaceMethod org/apache/dubbo/rpc/Invoker.getUrl:()Lorg/apache/dubbo/common/URL;
      91: invokevirtual #12                 // Method org/apache/dubbo/common/URL.getServiceInterface:()Ljava/lang/String;
      94: astore_2
      95: aload_2
      96: invokestatic  #13                 // Method org/apache/dubbo/common/utils/StringUtils.isNotEmpty:(Ljava/lang/String;)Z
      99: ifeq          117
     102: aload_0
     103: aload_2
     104: invokestatic  #14                 // Method getMethodByService:(Lorg/apache/dubbo/rpc/Invocation;Ljava/lang/String;)Ljava/lang/reflect/Method;
     107: astore_3
     108: aload_3
     109: ifnull        117
     112: aload_3
     113: invokestatic  #24                 // Method org/apache/dubbo/common/utils/ReflectUtils.getReturnTypes:(Ljava/lang/reflect/Method;)[Ljava/lang/reflect/Type;
     116: astore_1
     117: aload_1
     118: ifnull        123
     121: aload_1
     122: areturn
     123: goto          146
     126: astore_1
     127: getstatic     #17                 // Field logger:Lorg/apache/dubbo/common/logger/ErrorTypeAwareLogger;
     130: ldc           #18                 // String 0-8
     132: ldc           #19                 // String
     134: ldc           #19                 // String
     136: aload_1
     137: invokevirtual #20                 // Method java/lang/Throwable.getMessage:()Ljava/lang/String;
     140: aload_1
     141: invokeinterface #21,  6           // InterfaceMethod org/apache/dubbo/common/logger/ErrorTypeAwareLogger.warn:(Ljava/lang/String;Ljava/lang/String;Ljava/lang/String;Ljava/lang/String;Ljava/lang/Throwable;)V
     146: aconst_null
     147: areturn
    Exception table:
       from    to  target type
           0    79   126   Class java/lang/Throwable
          80   122   126   Class java/lang/Throwable

  public static java.lang.Long getInvocationId(org.apache.dubbo.rpc.Invocation);
    Code:
       0: aload_0
       1: ldc           #25                 // String id
       3: invokeinterface #26,  2           // InterfaceMethod org/apache/dubbo/rpc/Invocation.getAttachment:(Ljava/lang/String;)Ljava/lang/String;
       8: astore_1
       9: aload_1
      10: ifnonnull     17
      13: aconst_null
      14: goto          25
      17: new           #27                 // class java/lang/Long
      20: dup
      21: aload_1
      22: invokespecial #28                 // Method java/lang/Long."<init>":(Ljava/lang/String;)V
      25: areturn

  public static void attachInvocationIdIfAsync(org.apache.dubbo.common.URL, org.apache.dubbo.rpc.Invocation);
    Code:
       0: aload_0
       1: aload_1
       2: invokestatic  #29                 // Method isAttachInvocationId:(Lorg/apache/dubbo/common/URL;Lorg/apache/dubbo/rpc/Invocation;)Z
       5: ifeq          39
       8: aload_1
       9: invokestatic  #30                 // Method getInvocationId:(Lorg/apache/dubbo/rpc/Invocation;)Ljava/lang/Long;
      12: ifnonnull     39
      15: aload_1
      16: instanceof    #22                 // class org/apache/dubbo/rpc/RpcInvocation
      19: ifeq          39
      22: aload_1
      23: ldc           #25                 // String id
      25: getstatic     #31                 // Field INVOKE_ID:Ljava/util/concurrent/atomic/AtomicLong;
      28: invokevirtual #32                 // Method java/util/concurrent/atomic/AtomicLong.getAndIncrement:()J
      31: invokestatic  #33                 // Method java/lang/String.valueOf:(J)Ljava/lang/String;
      34: invokeinterface #34,  3           // InterfaceMethod org/apache/dubbo/rpc/Invocation.setAttachment:(Ljava/lang/String;Ljava/lang/String;)V
      39: return

  private static boolean isAttachInvocationId(org.apache.dubbo.common.URL, org.apache.dubbo.rpc.Invocation);
    Code:
       0: aload_0
       1: aload_1
       2: invokeinterface #9,  1            // InterfaceMethod org/apache/dubbo/rpc/Invocation.getMethodName:()Ljava/lang/String;
       7: ldc           #35                 // String invocationid.autoattach
       9: invokevirtual #36                 // Method org/apache/dubbo/common/URL.getMethodParameter:(Ljava/lang/String;Ljava/lang/String;)Ljava/lang/String;
      12: astore_2
      13: aload_2
      14: ifnonnull     23
      17: aload_0
      18: aload_1
      19: invokestatic  #37                 // Method isAsync:(Lorg/apache/dubbo/common/URL;Lorg/apache/dubbo/rpc/Invocation;)Z
      22: ireturn
      23: getstatic     #38                 // Field java/lang/Boolean.TRUE:Ljava/lang/Boolean;
      26: invokevirtual #39                 // Method java/lang/Boolean.toString:()Ljava/lang/String;
      29: aload_2
      30: invokevirtual #40                 // Method java/lang/String.equalsIgnoreCase:(Ljava/lang/String;)Z
      33: ifeq          38
      36: iconst_1
      37: ireturn
      38: iconst_0
      39: ireturn

  public static java.lang.String getMethodName(org.apache.dubbo.rpc.Invocation);
    Code:
       0: ldc           #41                 // String $invoke
       2: aload_0
       3: invokeinterface #9,  1            // InterfaceMethod org/apache/dubbo/rpc/Invocation.getMethodName:()Ljava/lang/String;
       8: invokevirtual #42                 // Method java/lang/String.equals:(Ljava/lang/Object;)Z
      11: ifeq          59
      14: aload_0
      15: invokeinterface #43,  1           // InterfaceMethod org/apache/dubbo/rpc/Invocation.getArguments:()[Ljava/lang/Object;
      20: ifnull        59
      23: aload_0
      24: invokeinterface #43,  1           // InterfaceMethod org/apache/dubbo/rpc/Invocation.getArguments:()[Ljava/lang/Object;
      29: arraylength
      30: ifle          59
      33: aload_0
      34: invokeinterface #43,  1           // InterfaceMethod org/apache/dubbo/rpc/Invocation.getArguments:()[Ljava/lang/Object;
      39: iconst_0
      40: aaload
      41: instanceof    #44                 // class java/lang/String
      44: ifeq          59
      47: aload_0
      48: invokeinterface #43,  1           // InterfaceMethod org/apache/dubbo/rpc/Invocation.getArguments:()[Ljava/lang/Object;
      53: iconst_0
      54: aaload
      55: checkcast     #44                 // class java/lang/String
      58: areturn
      59: aload_0
      60: invokeinterface #9,  1            // InterfaceMethod org/apache/dubbo/rpc/Invocation.getMethodName:()Ljava/lang/String;
      65: areturn

  public static java.lang.Object[] getArguments(org.apache.dubbo.rpc.Invocation);
    Code:
       0: ldc           #41                 // String $invoke
       2: aload_0
       3: invokeinterface #9,  1            // InterfaceMethod org/apache/dubbo/rpc/Invocation.getMethodName:()Ljava/lang/String;
       8: invokevirtual #42                 // Method java/lang/String.equals:(Ljava/lang/Object;)Z
      11: ifeq          63
      14: aload_0
      15: invokeinterface #43,  1           // InterfaceMethod org/apache/dubbo/rpc/Invocation.getArguments:()[Ljava/lang/Object;
      20: ifnull        63
      23: aload_0
      24: invokeinterface #43,  1           // InterfaceMethod org/apache/dubbo/rpc/Invocation.getArguments:()[Ljava/lang/Object;
      29: arraylength
      30: iconst_2
      31: if_icmple     63
      34: aload_0
      35: invokeinterface #43,  1           // InterfaceMethod org/apache/dubbo/rpc/Invocation.getArguments:()[Ljava/lang/Object;
      40: iconst_2
      41: aaload
      42: instanceof    #45                 // class "[Ljava/lang/Object;"
      45: ifeq          63
      48: aload_0
      49: invokeinterface #43,  1           // InterfaceMethod org/apache/dubbo/rpc/Invocation.getArguments:()[Ljava/lang/Object;
      54: iconst_2
      55: aaload
      56: checkcast     #45                 // class "[Ljava/lang/Object;"
      59: checkcast     #45                 // class "[Ljava/lang/Object;"
      62: areturn
      63: aload_0
      64: invokeinterface #43,  1           // InterfaceMethod org/apache/dubbo/rpc/Invocation.getArguments:()[Ljava/lang/Object;
      69: areturn

  public static java.lang.Class<?>[] getParameterTypes(org.apache.dubbo.rpc.Invocation);
    Code:
       0: ldc           #41                 // String $invoke
       2: aload_0
       3: invokeinterface #9,  1            // InterfaceMethod org/apache/dubbo/rpc/Invocation.getMethodName:()Ljava/lang/String;
       8: invokevirtual #42                 // Method java/lang/String.equals:(Ljava/lang/Object;)Z
      11: ifeq          103
      14: aload_0
      15: invokeinterface #43,  1           // InterfaceMethod org/apache/dubbo/rpc/Invocation.getArguments:()[Ljava/lang/Object;
      20: ifnull        103
      23: aload_0
      24: invokeinterface #43,  1           // InterfaceMethod org/apache/dubbo/rpc/Invocation.getArguments:()[Ljava/lang/Object;
      29: arraylength
      30: iconst_1
      31: if_icmple     103
      34: aload_0
      35: invokeinterface #43,  1           // InterfaceMethod org/apache/dubbo/rpc/Invocation.getArguments:()[Ljava/lang/Object;
      40: iconst_1
      41: aaload
      42: instanceof    #46                 // class "[Ljava/lang/String;"
      45: ifeq          103
      48: aload_0
      49: invokeinterface #43,  1           // InterfaceMethod org/apache/dubbo/rpc/Invocation.getArguments:()[Ljava/lang/Object;
      54: iconst_1
      55: aaload
      56: checkcast     #46                 // class "[Ljava/lang/String;"
      59: checkcast     #46                 // class "[Ljava/lang/String;"
      62: astore_1
      63: aload_1
      64: ifnonnull     72
      67: iconst_0
      68: anewarray     #47                 // class java/lang/Class
      71: areturn
      72: aload_1
      73: arraylength
      74: anewarray     #47                 // class java/lang/Class
      77: astore_2
      78: iconst_0
      79: istore_3
      80: iload_3
      81: aload_1
      82: arraylength
      83: if_icmpge     101
      86: aload_2
      87: iload_3
      88: aload_1
      89: iload_3
      90: aaload
      91: invokestatic  #48                 // Method org/apache/dubbo/common/utils/ReflectUtils.forName:(Ljava/lang/String;)Ljava/lang/Class;
      94: aastore
      95: iinc          3, 1
      98: goto          80
     101: aload_2
     102: areturn
     103: aload_0
     104: invokeinterface #49,  1           // InterfaceMethod org/apache/dubbo/rpc/Invocation.getParameterTypes:()[Ljava/lang/Class;
     109: areturn

  public static boolean isAsync(org.apache.dubbo.common.URL, org.apache.dubbo.rpc.Invocation);
    Code:
       0: aload_1
       1: instanceof    #22                 // class org/apache/dubbo/rpc/RpcInvocation
       4: ifeq          35
       7: aload_1
       8: checkcast     #22                 // class org/apache/dubbo/rpc/RpcInvocation
      11: astore_3
      12: aload_3
      13: invokevirtual #50                 // Method org/apache/dubbo/rpc/RpcInvocation.getInvokeMode:()Lorg/apache/dubbo/rpc/InvokeMode;
      16: ifnull        35
      19: aload_3
      20: invokevirtual #50                 // Method org/apache/dubbo/rpc/RpcInvocation.getInvokeMode:()Lorg/apache/dubbo/rpc/InvokeMode;
      23: getstatic     #51                 // Field org/apache/dubbo/rpc/InvokeMode.ASYNC:Lorg/apache/dubbo/rpc/InvokeMode;
      26: if_acmpne     33
      29: iconst_1
      30: goto          34
      33: iconst_0
      34: ireturn
      35: getstatic     #38                 // Field java/lang/Boolean.TRUE:Ljava/lang/Boolean;
      38: invokevirtual #39                 // Method java/lang/Boolean.toString:()Ljava/lang/String;
      41: aload_1
      42: ldc           #52                 // String async
      44: invokeinterface #26,  2           // InterfaceMethod org/apache/dubbo/rpc/Invocation.getAttachment:(Ljava/lang/String;)Ljava/lang/String;
      49: invokevirtual #42                 // Method java/lang/String.equals:(Ljava/lang/Object;)Z
      52: ifeq          60
      55: iconst_1
      56: istore_2
      57: goto          72
      60: aload_0
      61: aload_1
      62: invokestatic  #53                 // Method getMethodName:(Lorg/apache/dubbo/rpc/Invocation;)Ljava/lang/String;
      65: ldc           #52                 // String async
      67: iconst_0
      68: invokevirtual #54                 // Method org/apache/dubbo/common/URL.getMethodParameter:(Ljava/lang/String;Ljava/lang/String;Z)Z
      71: istore_2
      72: iload_2
      73: ireturn

  public static boolean isReturnTypeFuture(org.apache.dubbo.rpc.Invocation);
    Code:
       0: aload_0
       1: instanceof    #22                 // class org/apache/dubbo/rpc/RpcInvocation
       4: ifeq          18
       7: aload_0
       8: checkcast     #22                 // class org/apache/dubbo/rpc/RpcInvocation
      11: invokevirtual #55                 // Method org/apache/dubbo/rpc/RpcInvocation.getReturnType:()Ljava/lang/Class;
      14: astore_1
      15: goto          23
      18: aload_0
      19: invokestatic  #56                 // Method getReturnType:(Lorg/apache/dubbo/rpc/Invocation;)Ljava/lang/Class;
      22: astore_1
      23: aload_1
      24: ifnull        36
      27: ldc           #57                 // class java/util/concurrent/CompletableFuture
      29: aload_1
      30: invokevirtual #58                 // Method java/lang/Class.isAssignableFrom:(Ljava/lang/Class;)Z
      33: ifne          43
      36: aload_0
      37: invokestatic  #59                 // Method isGenericAsync:(Lorg/apache/dubbo/rpc/Invocation;)Z
      40: ifeq          47
      43: iconst_1
      44: goto          48
      47: iconst_0
      48: ireturn

  public static boolean isGenericAsync(org.apache.dubbo.rpc.Invocation);
    Code:
       0: ldc           #60                 // String $invokeAsync
       2: aload_0
       3: invokeinterface #9,  1            // InterfaceMethod org/apache/dubbo/rpc/Invocation.getMethodName:()Ljava/lang/String;
       8: invokevirtual #42                 // Method java/lang/String.equals:(Ljava/lang/Object;)Z
      11: ireturn

  public static boolean isGenericCall(java.lang.String, java.lang.String);
    Code:
       0: ldc           #41                 // String $invoke
       2: aload_1
       3: invokevirtual #42                 // Method java/lang/String.equals:(Ljava/lang/Object;)Z
       6: ifne          18
       9: ldc           #60                 // String $invokeAsync
      11: aload_1
      12: invokevirtual #42                 // Method java/lang/String.equals:(Ljava/lang/Object;)Z
      15: ifeq          31
      18: ldc           #61                 // String Ljava/lang/String;[Ljava/lang/String;[Ljava/lang/Object;
      20: aload_0
      21: invokevirtual #42                 // Method java/lang/String.equals:(Ljava/lang/Object;)Z
      24: ifeq          31
      27: iconst_1
      28: goto          32
      31: iconst_0
      32: ireturn

  public static boolean isEcho(java.lang.String, java.lang.String);
    Code:
       0: ldc           #62                 // String $echo
       2: aload_1
       3: invokevirtual #42                 // Method java/lang/String.equals:(Ljava/lang/Object;)Z
       6: ifeq          22
       9: ldc           #63                 // String Ljava/lang/Object;
      11: aload_0
      12: invokevirtual #42                 // Method java/lang/String.equals:(Ljava/lang/Object;)Z
      15: ifeq          22
      18: iconst_1
      19: goto          23
      22: iconst_0
      23: ireturn

  public static org.apache.dubbo.rpc.InvokeMode getInvokeMode(org.apache.dubbo.common.URL, org.apache.dubbo.rpc.Invocation);
    Code:
       0: aload_1
       1: instanceof    #22                 // class org/apache/dubbo/rpc/RpcInvocation
       4: ifeq          24
       7: aload_1
       8: checkcast     #22                 // class org/apache/dubbo/rpc/RpcInvocation
      11: astore_2
      12: aload_2
      13: invokevirtual #50                 // Method org/apache/dubbo/rpc/RpcInvocation.getInvokeMode:()Lorg/apache/dubbo/rpc/InvokeMode;
      16: ifnull        24
      19: aload_2
      20: invokevirtual #50                 // Method org/apache/dubbo/rpc/RpcInvocation.getInvokeMode:()Lorg/apache/dubbo/rpc/InvokeMode;
      23: areturn
      24: aload_1
      25: invokestatic  #64                 // Method isReturnTypeFuture:(Lorg/apache/dubbo/rpc/Invocation;)Z
      28: ifeq          35
      31: getstatic     #65                 // Field org/apache/dubbo/rpc/InvokeMode.FUTURE:Lorg/apache/dubbo/rpc/InvokeMode;
      34: areturn
      35: aload_0
      36: aload_1
      37: invokestatic  #37                 // Method isAsync:(Lorg/apache/dubbo/common/URL;Lorg/apache/dubbo/rpc/Invocation;)Z
      40: ifeq          47
      43: getstatic     #51                 // Field org/apache/dubbo/rpc/InvokeMode.ASYNC:Lorg/apache/dubbo/rpc/InvokeMode;
      46: areturn
      47: getstatic     #66                 // Field org/apache/dubbo/rpc/InvokeMode.SYNC:Lorg/apache/dubbo/rpc/InvokeMode;
      50: areturn

  public static boolean isOneway(org.apache.dubbo.common.URL, org.apache.dubbo.rpc.Invocation);
    Code:
       0: getstatic     #67                 // Field java/lang/Boolean.FALSE:Ljava/lang/Boolean;
       3: invokevirtual #39                 // Method java/lang/Boolean.toString:()Ljava/lang/String;
       6: aload_1
       7: ldc           #68                 // String return
       9: invokeinterface #26,  2           // InterfaceMethod org/apache/dubbo/rpc/Invocation.getAttachment:(Ljava/lang/String;)Ljava/lang/String;
      14: invokevirtual #42                 // Method java/lang/String.equals:(Ljava/lang/Object;)Z
      17: ifeq          25
      20: iconst_1
      21: istore_2
      22: goto          45
      25: aload_0
      26: aload_1
      27: invokestatic  #53                 // Method getMethodName:(Lorg/apache/dubbo/rpc/Invocation;)Ljava/lang/String;
      30: ldc           #68                 // String return
      32: iconst_1
      33: invokevirtual #54                 // Method org/apache/dubbo/common/URL.getMethodParameter:(Ljava/lang/String;Ljava/lang/String;Z)Z
      36: ifne          43
      39: iconst_1
      40: goto          44
      43: iconst_0
      44: istore_2
      45: iload_2
      46: ireturn

  private static java.lang.reflect.Method getMethodByService(org.apache.dubbo.rpc.Invocation, java.lang.String) throws java.lang.NoSuchMethodException;
    Code:
       0: aload_0
       1: invokeinterface #5,  1            // InterfaceMethod org/apache/dubbo/rpc/Invocation.getInvoker:()Lorg/apache/dubbo/rpc/Invoker;
       6: invokeinterface #7,  1            // InterfaceMethod org/apache/dubbo/rpc/Invoker.getInterface:()Ljava/lang/Class;
      11: astore_2
      12: aload_2
      13: ifnull        27
      16: aload_2
      17: invokevirtual #69                 // Method java/lang/Class.getClassLoader:()Ljava/lang/ClassLoader;
      20: aload_1
      21: invokestatic  #70                 // Method org/apache/dubbo/common/utils/ReflectUtils.forName:(Ljava/lang/ClassLoader;Ljava/lang/String;)Ljava/lang/Class;
      24: goto          31
      27: aload_1
      28: invokestatic  #48                 // Method org/apache/dubbo/common/utils/ReflectUtils.forName:(Ljava/lang/String;)Ljava/lang/Class;
      31: astore_3
      32: aload_3
      33: aload_0
      34: invokeinterface #9,  1            // InterfaceMethod org/apache/dubbo/rpc/Invocation.getMethodName:()Ljava/lang/String;
      39: aload_0
      40: invokeinterface #49,  1           // InterfaceMethod org/apache/dubbo/rpc/Invocation.getParameterTypes:()[Ljava/lang/Class;
      45: invokevirtual #71                 // Method java/lang/Class.getMethod:(Ljava/lang/String;[Ljava/lang/Class;)Ljava/lang/reflect/Method;
      48: astore        4
      50: aload         4
      52: invokevirtual #15                 // Method java/lang/reflect/Method.getReturnType:()Ljava/lang/Class;
      55: getstatic     #72                 // Field java/lang/Void.TYPE:Ljava/lang/Class;
      58: if_acmpne     63
      61: aconst_null
      62: areturn
      63: aload         4
      65: areturn

  public static long getTimeout(org.apache.dubbo.rpc.Invocation, long);
    Code:
       0: lload_1
       1: lstore_3
       2: aload_0
       3: ldc           #73                 // String _TO
       5: invokeinterface #74,  2           // InterfaceMethod org/apache/dubbo/rpc/Invocation.getObjectAttachmentWithoutConvert:(Ljava/lang/String;)Ljava/lang/Object;
      10: astore        5
      12: aload         5
      14: ifnonnull     27
      17: aload_0
      18: ldc           #75                 // String _to
      20: invokeinterface #74,  2           // InterfaceMethod org/apache/dubbo/rpc/Invocation.getObjectAttachmentWithoutConvert:(Ljava/lang/String;)Ljava/lang/Object;
      25: astore        5
      27: aload         5
      29: ifnull        42
      32: aload         5
      34: lload_1
      35: invokestatic  #76                 // Method convertToNumber:(Ljava/lang/Object;J)Ljava/lang/Long;
      38: invokevirtual #77                 // Method java/lang/Long.longValue:()J
      41: lstore_3
      42: lload_3
      43: lreturn

  public static long getTimeout(org.apache.dubbo.common.URL, java.lang.String, org.apache.dubbo.rpc.RpcContext, org.apache.dubbo.rpc.Invocation, long);
    Code:
       0: lload         4
       2: lstore        6
       4: aload_2
       5: ldc           #78                 // String timeout
       7: invokevirtual #79                 // Method org/apache/dubbo/rpc/RpcContext.getObjectAttachment:(Ljava/lang/String;)Ljava/lang/Object;
      10: astore        8
      12: aload_3
      13: ldc           #78                 // String timeout
      15: invokeinterface #80,  2           // InterfaceMethod org/apache/dubbo/rpc/Invocation.getObjectAttachment:(Ljava/lang/String;)Ljava/lang/Object;
      20: astore        9
      22: aload         8
      24: ifnull        42
      27: aload         8
      29: lload         4
      31: invokestatic  #76                 // Method convertToNumber:(Ljava/lang/Object;J)Ljava/lang/Long;
      34: invokevirtual #77                 // Method java/lang/Long.longValue:()J
      37: lstore        6
      39: goto          77
      42: aload         9
      44: ifnull        62
      47: aload         9
      49: lload         4
      51: invokestatic  #76                 // Method convertToNumber:(Ljava/lang/Object;J)Ljava/lang/Long;
      54: invokevirtual #77                 // Method java/lang/Long.longValue:()J
      57: lstore        6
      59: goto          77
      62: aload_0
      63: ifnull        77
      66: aload_0
      67: aload_1
      68: ldc           #78                 // String timeout
      70: lload         4
      72: invokevirtual #81                 // Method org/apache/dubbo/common/URL.getMethodPositiveParameter:(Ljava/lang/String;Ljava/lang/String;J)J
      75: lstore        6
      77: lload         6
      79: lreturn

  public static int calculateTimeout(org.apache.dubbo.common.URL, org.apache.dubbo.rpc.Invocation, java.lang.String, long);
    Code:
       0: invokestatic  #82                 // Method org/apache/dubbo/rpc/RpcContext.getClientAttachment:()Lorg/apache/dubbo/rpc/RpcContextAttachment;
       3: ldc           #83                 // String timeout-countdown
       5: invokevirtual #84                 // Method org/apache/dubbo/rpc/RpcContextAttachment.getObjectAttachment:(Ljava/lang/String;)Ljava/lang/Object;
       8: astore        5
      10: lload_3
      11: l2i
      12: istore        6
      14: aload         5
      16: ifnonnull     63
      19: aload_0
      20: ifnull        94
      23: aload_0
      24: aload_2
      25: invokestatic  #82                 // Method org/apache/dubbo/rpc/RpcContext.getClientAttachment:()Lorg/apache/dubbo/rpc/RpcContextAttachment;
      28: aload_1
      29: lload_3
      30: invokestatic  #85                 // Method getTimeout:(Lorg/apache/dubbo/common/URL;Ljava/lang/String;Lorg/apache/dubbo/rpc/RpcContext;Lorg/apache/dubbo/rpc/Invocation;J)J
      33: l2i
      34: istore        6
      36: aload_0
      37: aload_2
      38: ldc           #86                 // String enable-timeout-countdown
      40: iconst_0
      41: invokevirtual #54                 // Method org/apache/dubbo/common/URL.getMethodParameter:(Ljava/lang/String;Ljava/lang/String;Z)Z
      44: ifeq          94
      47: aload_1
      48: ldc           #73                 // String _TO
      50: iload         6
      52: invokestatic  #87                 // Method java/lang/Integer.valueOf:(I)Ljava/lang/Integer;
      55: invokeinterface #88,  3           // InterfaceMethod org/apache/dubbo/rpc/Invocation.setObjectAttachment:(Ljava/lang/String;Ljava/lang/Object;)V
      60: goto          94
      63: aload         5
      65: checkcast     #89                 // class org/apache/dubbo/rpc/TimeoutCountDown
      68: astore        7
      70: aload         7
      72: getstatic     #90                 // Field java/util/concurrent/TimeUnit.MILLISECONDS:Ljava/util/concurrent/TimeUnit;
      75: invokevirtual #91                 // Method org/apache/dubbo/rpc/TimeoutCountDown.timeRemaining:(Ljava/util/concurrent/TimeUnit;)J
      78: l2i
      79: istore        6
      81: aload_1
      82: ldc           #73                 // String _TO
      84: iload         6
      86: invokestatic  #87                 // Method java/lang/Integer.valueOf:(I)Ljava/lang/Integer;
      89: invokeinterface #88,  3           // InterfaceMethod org/apache/dubbo/rpc/Invocation.setObjectAttachment:(Ljava/lang/String;Ljava/lang/Object;)V
      94: aload_1
      95: invokeinterface #92,  1           // InterfaceMethod org/apache/dubbo/rpc/Invocation.getObjectAttachments:()Ljava/util/Map;
     100: ldc           #83                 // String timeout-countdown
     102: invokeinterface #93,  2           // InterfaceMethod java/util/Map.remove:(Ljava/lang/Object;)Ljava/lang/Object;
     107: pop
     108: iload         6
     110: ireturn

  public static java.lang.Long convertToNumber(java.lang.Object, long);
    Code:
       0: aload_0
       1: invokestatic  #94                 // Method convertToNumber:(Ljava/lang/Object;)Ljava/lang/Long;
       4: astore_3
       5: aload_3
       6: ifnonnull     13
       9: lload_1
      10: goto          17
      13: aload_3
      14: invokevirtual #77                 // Method java/lang/Long.longValue:()J
      17: invokestatic  #95                 // Method java/lang/Long.valueOf:(J)Ljava/lang/Long;
      20: areturn

  public static java.lang.Long convertToNumber(java.lang.Object);
    Code:
       0: aconst_null
       1: astore_1
       2: aload_0
       3: instanceof    #44                 // class java/lang/String
       6: ifeq          23
       9: aload_0
      10: checkcast     #44                 // class java/lang/String
      13: invokestatic  #96                 // Method java/lang/Long.parseLong:(Ljava/lang/String;)J
      16: invokestatic  #95                 // Method java/lang/Long.valueOf:(J)Ljava/lang/Long;
      19: astore_1
      20: goto          55
      23: aload_0
      24: instanceof    #97                 // class java/lang/Number
      27: ifeq          44
      30: aload_0
      31: checkcast     #97                 // class java/lang/Number
      34: invokevirtual #98                 // Method java/lang/Number.longValue:()J
      37: invokestatic  #95                 // Method java/lang/Long.valueOf:(J)Ljava/lang/Long;
      40: astore_1
      41: goto          55
      44: aload_0
      45: invokevirtual #99                 // Method java/lang/Object.toString:()Ljava/lang/String;
      48: invokestatic  #96                 // Method java/lang/Long.parseLong:(Ljava/lang/String;)J
      51: invokestatic  #95                 // Method java/lang/Long.valueOf:(J)Ljava/lang/Long;
      54: astore_1
      55: goto          59
      58: astore_2
      59: aload_1
      60: areturn
    Exception table:
       from    to  target type
           2    55    58   Class java/lang/Exception

  static {};
    Code:
       0: ldc           #101                // class org/apache/dubbo/rpc/support/RpcUtils
       2: invokestatic  #102                // Method org/apache/dubbo/common/logger/LoggerFactory.getErrorTypeAwareLogger:(Ljava/lang/Class;)Lorg/apache/dubbo/common/logger/ErrorTypeAwareLogger;
       5: putstatic     #17                 // Field logger:Lorg/apache/dubbo/common/logger/ErrorTypeAwareLogger;
       8: new           #103                // class java/util/concurrent/atomic/AtomicLong
      11: dup
      12: lconst_0
      13: invokespecial #104                // Method java/util/concurrent/atomic/AtomicLong."<init>":(J)V
      16: putstatic     #31                 // Field INVOKE_ID:Ljava/util/concurrent/atomic/AtomicLong;
      19: return
}
