Compiled from "AbstractClusterInvoker.java"
public abstract class org.apache.dubbo.rpc.cluster.support.AbstractClusterInvoker<T> implements org.apache.dubbo.rpc.cluster.ClusterInvoker<T> {
  private static final org.apache.dubbo.common.logger.ErrorTypeAwareLogger logger;

  protected org.apache.dubbo.rpc.cluster.Directory<T> directory;

  protected boolean availableCheck;

  private volatile int reselectCount;

  private volatile boolean enableConnectivityValidation;

  private final java.util.concurrent.atomic.AtomicBoolean destroyed;

  private volatile org.apache.dubbo.rpc.Invoker<T> stickyInvoker;

  public org.apache.dubbo.rpc.cluster.support.AbstractClusterInvoker();
    Code:
       0: aload_0
       1: invokespecial #4                  // Method java/lang/Object."<init>":()V
       4: aload_0
       5: bipush        10
       7: putfield      #5                  // Field reselectCount:I
      10: aload_0
      11: iconst_1
      12: putfield      #6                  // Field enableConnectivityValidation:Z
      15: aload_0
      16: new           #7                  // class java/util/concurrent/atomic/AtomicBoolean
      19: dup
      20: iconst_0
      21: invokespecial #8                  // Method java/util/concurrent/atomic/AtomicBoolean."<init>":(Z)V
      24: putfield      #9                  // Field destroyed:Ljava/util/concurrent/atomic/AtomicBoolean;
      27: aload_0
      28: aconst_null
      29: putfield      #10                 // Field stickyInvoker:Lorg/apache/dubbo/rpc/Invoker;
      32: return

  public org.apache.dubbo.rpc.cluster.support.AbstractClusterInvoker(org.apache.dubbo.rpc.cluster.Directory<T>);
    Code:
       0: aload_0
       1: aload_1
       2: aload_1
       3: invokeinterface #11,  1           // InterfaceMethod org/apache/dubbo/rpc/cluster/Directory.getUrl:()Lorg/apache/dubbo/common/URL;
       8: invokespecial #12                 // Method "<init>":(Lorg/apache/dubbo/rpc/cluster/Directory;Lorg/apache/dubbo/common/URL;)V
      11: return

  public org.apache.dubbo.rpc.cluster.support.AbstractClusterInvoker(org.apache.dubbo.rpc.cluster.Directory<T>, org.apache.dubbo.common.URL);
    Code:
       0: aload_0
       1: invokespecial #4                  // Method java/lang/Object."<init>":()V
       4: aload_0
       5: bipush        10
       7: putfield      #5                  // Field reselectCount:I
      10: aload_0
      11: iconst_1
      12: putfield      #6                  // Field enableConnectivityValidation:Z
      15: aload_0
      16: new           #7                  // class java/util/concurrent/atomic/AtomicBoolean
      19: dup
      20: iconst_0
      21: invokespecial #8                  // Method java/util/concurrent/atomic/AtomicBoolean."<init>":(Z)V
      24: putfield      #9                  // Field destroyed:Ljava/util/concurrent/atomic/AtomicBoolean;
      27: aload_0
      28: aconst_null
      29: putfield      #10                 // Field stickyInvoker:Lorg/apache/dubbo/rpc/Invoker;
      32: aload_1
      33: ifnonnull     46
      36: new           #13                 // class java/lang/IllegalArgumentException
      39: dup
      40: ldc           #14                 // String service directory == null
      42: invokespecial #15                 // Method java/lang/IllegalArgumentException."<init>":(Ljava/lang/String;)V
      45: athrow
      46: aload_0
      47: aload_1
      48: putfield      #16                 // Field directory:Lorg/apache/dubbo/rpc/cluster/Directory;
      51: aload_0
      52: aload_2
      53: ldc           #17                 // String cluster.availablecheck
      55: iconst_1
      56: invokevirtual #18                 // Method org/apache/dubbo/common/URL.getParameter:(Ljava/lang/String;Z)Z
      59: putfield      #19                 // Field availableCheck:Z
      62: aload_2
      63: invokevirtual #20                 // Method org/apache/dubbo/common/URL.getOrDefaultModuleModel:()Lorg/apache/dubbo/rpc/model/ModuleModel;
      66: invokestatic  #21                 // Method org/apache/dubbo/common/config/ConfigurationUtils.getGlobalConfiguration:(Lorg/apache/dubbo/rpc/model/ScopeModel;)Lorg/apache/dubbo/common/config/Configuration;
      69: astore_3
      70: aload_0
      71: aload_3
      72: ldc           #22                 // String dubbo.reselect.count
      74: bipush        10
      76: invokeinterface #23,  3           // InterfaceMethod org/apache/dubbo/common/config/Configuration.getInt:(Ljava/lang/String;I)I
      81: putfield      #5                  // Field reselectCount:I
      84: aload_0
      85: aload_3
      86: ldc           #24                 // String dubbo.connectivity.validation
      88: iconst_1
      89: invokeinterface #25,  3           // InterfaceMethod org/apache/dubbo/common/config/Configuration.getBoolean:(Ljava/lang/String;Z)Z
      94: putfield      #6                  // Field enableConnectivityValidation:Z
      97: return

  public java.lang.Class<T> getInterface();
    Code:
       0: aload_0
       1: invokevirtual #26                 // Method getDirectory:()Lorg/apache/dubbo/rpc/cluster/Directory;
       4: invokeinterface #27,  1           // InterfaceMethod org/apache/dubbo/rpc/cluster/Directory.getInterface:()Ljava/lang/Class;
       9: areturn

  public org.apache.dubbo.common.URL getUrl();
    Code:
       0: aload_0
       1: invokevirtual #26                 // Method getDirectory:()Lorg/apache/dubbo/rpc/cluster/Directory;
       4: invokeinterface #28,  1           // InterfaceMethod org/apache/dubbo/rpc/cluster/Directory.getConsumerUrl:()Lorg/apache/dubbo/common/URL;
       9: areturn

  public org.apache.dubbo.common.URL getRegistryUrl();
    Code:
       0: aload_0
       1: invokevirtual #26                 // Method getDirectory:()Lorg/apache/dubbo/rpc/cluster/Directory;
       4: invokeinterface #11,  1           // InterfaceMethod org/apache/dubbo/rpc/cluster/Directory.getUrl:()Lorg/apache/dubbo/common/URL;
       9: areturn

  public boolean isAvailable();
    Code:
       0: aload_0
       1: getfield      #10                 // Field stickyInvoker:Lorg/apache/dubbo/rpc/Invoker;
       4: astore_1
       5: aload_1
       6: ifnull        16
       9: aload_1
      10: invokeinterface #29,  1           // InterfaceMethod org/apache/dubbo/rpc/Invoker.isAvailable:()Z
      15: ireturn
      16: aload_0
      17: invokevirtual #26                 // Method getDirectory:()Lorg/apache/dubbo/rpc/cluster/Directory;
      20: invokeinterface #30,  1           // InterfaceMethod org/apache/dubbo/rpc/cluster/Directory.isAvailable:()Z
      25: ireturn

  public org.apache.dubbo.rpc.cluster.Directory<T> getDirectory();
    Code:
       0: aload_0
       1: getfield      #16                 // Field directory:Lorg/apache/dubbo/rpc/cluster/Directory;
       4: areturn

  public void destroy();
    Code:
       0: aload_0
       1: getfield      #9                  // Field destroyed:Ljava/util/concurrent/atomic/AtomicBoolean;
       4: iconst_0
       5: iconst_1
       6: invokevirtual #31                 // Method java/util/concurrent/atomic/AtomicBoolean.compareAndSet:(ZZ)Z
       9: ifeq          21
      12: aload_0
      13: invokevirtual #26                 // Method getDirectory:()Lorg/apache/dubbo/rpc/cluster/Directory;
      16: invokeinterface #32,  1           // InterfaceMethod org/apache/dubbo/rpc/cluster/Directory.destroy:()V
      21: return

  public boolean isDestroyed();
    Code:
       0: aload_0
       1: getfield      #9                  // Field destroyed:Ljava/util/concurrent/atomic/AtomicBoolean;
       4: invokevirtual #33                 // Method java/util/concurrent/atomic/AtomicBoolean.get:()Z
       7: ireturn

  protected org.apache.dubbo.rpc.Invoker<T> select(org.apache.dubbo.rpc.cluster.LoadBalance, org.apache.dubbo.rpc.Invocation, java.util.List<org.apache.dubbo.rpc.Invoker<T>>, java.util.List<org.apache.dubbo.rpc.Invoker<T>>) throws org.apache.dubbo.rpc.RpcException;
    Code:
       0: aload_3
       1: invokestatic  #34                 // Method org/apache/dubbo/common/utils/CollectionUtils.isEmpty:(Ljava/util/Collection;)Z
       4: ifeq          9
       7: aconst_null
       8: areturn
       9: aload_2
      10: ifnonnull     18
      13: ldc           #36                 // String
      15: goto          24
      18: aload_2
      19: invokeinterface #37,  1           // InterfaceMethod org/apache/dubbo/rpc/Invocation.getMethodName:()Ljava/lang/String;
      24: astore        5
      26: aload_3
      27: iconst_0
      28: invokeinterface #38,  2           // InterfaceMethod java/util/List.get:(I)Ljava/lang/Object;
      33: checkcast     #39                 // class org/apache/dubbo/rpc/Invoker
      36: invokeinterface #40,  1           // InterfaceMethod org/apache/dubbo/rpc/Invoker.getUrl:()Lorg/apache/dubbo/common/URL;
      41: aload         5
      43: ldc           #41                 // String sticky
      45: iconst_0
      46: invokevirtual #42                 // Method org/apache/dubbo/common/URL.getMethodParameter:(Ljava/lang/String;Ljava/lang/String;Z)Z
      49: istore        6
      51: aload_0
      52: getfield      #10                 // Field stickyInvoker:Lorg/apache/dubbo/rpc/Invoker;
      55: ifnull        76
      58: aload_3
      59: aload_0
      60: getfield      #10                 // Field stickyInvoker:Lorg/apache/dubbo/rpc/Invoker;
      63: invokeinterface #43,  2           // InterfaceMethod java/util/List.contains:(Ljava/lang/Object;)Z
      68: ifne          76
      71: aload_0
      72: aconst_null
      73: putfield      #10                 // Field stickyInvoker:Lorg/apache/dubbo/rpc/Invoker;
      76: iload         6
      78: ifeq          131
      81: aload_0
      82: getfield      #10                 // Field stickyInvoker:Lorg/apache/dubbo/rpc/Invoker;
      85: ifnull        131
      88: aload         4
      90: ifnull        107
      93: aload         4
      95: aload_0
      96: getfield      #10                 // Field stickyInvoker:Lorg/apache/dubbo/rpc/Invoker;
      99: invokeinterface #43,  2           // InterfaceMethod java/util/List.contains:(Ljava/lang/Object;)Z
     104: ifne          131
     107: aload_0
     108: getfield      #19                 // Field availableCheck:Z
     111: ifeq          131
     114: aload_0
     115: getfield      #10                 // Field stickyInvoker:Lorg/apache/dubbo/rpc/Invoker;
     118: invokeinterface #29,  1           // InterfaceMethod org/apache/dubbo/rpc/Invoker.isAvailable:()Z
     123: ifeq          131
     126: aload_0
     127: getfield      #10                 // Field stickyInvoker:Lorg/apache/dubbo/rpc/Invoker;
     130: areturn
     131: aload_0
     132: aload_1
     133: aload_2
     134: aload_3
     135: aload         4
     137: invokespecial #44                 // Method doSelect:(Lorg/apache/dubbo/rpc/cluster/LoadBalance;Lorg/apache/dubbo/rpc/Invocation;Ljava/util/List;Ljava/util/List;)Lorg/apache/dubbo/rpc/Invoker;
     140: astore        7
     142: iload         6
     144: ifeq          153
     147: aload_0
     148: aload         7
     150: putfield      #10                 // Field stickyInvoker:Lorg/apache/dubbo/rpc/Invoker;
     153: aload         7
     155: areturn

  private org.apache.dubbo.rpc.Invoker<T> doSelect(org.apache.dubbo.rpc.cluster.LoadBalance, org.apache.dubbo.rpc.Invocation, java.util.List<org.apache.dubbo.rpc.Invoker<T>>, java.util.List<org.apache.dubbo.rpc.Invoker<T>>) throws org.apache.dubbo.rpc.RpcException;
    Code:
       0: aload_3
       1: invokestatic  #34                 // Method org/apache/dubbo/common/utils/CollectionUtils.isEmpty:(Ljava/util/Collection;)Z
       4: ifeq          9
       7: aconst_null
       8: areturn
       9: aload_3
      10: invokeinterface #45,  1           // InterfaceMethod java/util/List.size:()I
      15: iconst_1
      16: if_icmpne     40
      19: aload_3
      20: iconst_0
      21: invokeinterface #38,  2           // InterfaceMethod java/util/List.get:(I)Ljava/lang/Object;
      26: checkcast     #39                 // class org/apache/dubbo/rpc/Invoker
      29: astore        5
      31: aload_0
      32: aload         5
      34: invokespecial #46                 // Method checkShouldInvalidateInvoker:(Lorg/apache/dubbo/rpc/Invoker;)V
      37: aload         5
      39: areturn
      40: aload_1
      41: aload_3
      42: aload_0
      43: invokevirtual #47                 // Method getUrl:()Lorg/apache/dubbo/common/URL;
      46: aload_2
      47: invokeinterface #48,  4           // InterfaceMethod org/apache/dubbo/rpc/cluster/LoadBalance.select:(Ljava/util/List;Lorg/apache/dubbo/common/URL;Lorg/apache/dubbo/rpc/Invocation;)Lorg/apache/dubbo/rpc/Invoker;
      52: astore        5
      54: aload         4
      56: ifnull        75
      59: aload         4
      61: aload         5
      63: invokeinterface #43,  2           // InterfaceMethod java/util/List.contains:(Ljava/lang/Object;)Z
      68: ifeq          75
      71: iconst_1
      72: goto          76
      75: iconst_0
      76: istore        6
      78: aload_0
      79: getfield      #19                 // Field availableCheck:Z
      82: ifeq          106
      85: aload         5
      87: invokeinterface #29,  1           // InterfaceMethod org/apache/dubbo/rpc/Invoker.isAvailable:()Z
      92: ifne          106
      95: aload_0
      96: invokevirtual #47                 // Method getUrl:()Lorg/apache/dubbo/common/URL;
      99: ifnull        106
     102: iconst_1
     103: goto          107
     106: iconst_0
     107: istore        7
     109: iload         7
     111: ifeq          120
     114: aload_0
     115: aload         5
     117: invokespecial #49                 // Method invalidateInvoker:(Lorg/apache/dubbo/rpc/Invoker;)V
     120: iload         6
     122: ifne          130
     125: iload         7
     127: ifeq          282
     130: aload_0
     131: aload_1
     132: aload_2
     133: aload_3
     134: aload         4
     136: aload_0
     137: getfield      #19                 // Field availableCheck:Z
     140: invokespecial #50                 // Method reselect:(Lorg/apache/dubbo/rpc/cluster/LoadBalance;Lorg/apache/dubbo/rpc/Invocation;Ljava/util/List;Ljava/util/List;Z)Lorg/apache/dubbo/rpc/Invoker;
     143: astore        8
     145: aload         8
     147: ifnull        157
     150: aload         8
     152: astore        5
     154: goto          233
     157: aload_3
     158: aload         5
     160: invokeinterface #51,  2           // InterfaceMethod java/util/List.indexOf:(Ljava/lang/Object;)I
     165: istore        9
     167: aload_3
     168: iload         9
     170: iconst_1
     171: iadd
     172: aload_3
     173: invokeinterface #45,  1           // InterfaceMethod java/util/List.size:()I
     178: irem
     179: invokeinterface #38,  2           // InterfaceMethod java/util/List.get:(I)Ljava/lang/Object;
     184: checkcast     #39                 // class org/apache/dubbo/rpc/Invoker
     187: astore        5
     189: goto          233
     192: astore        10
     194: getstatic     #53                 // Field logger:Lorg/apache/dubbo/common/logger/ErrorTypeAwareLogger;
     197: ldc           #54                 // String 2-5
     199: ldc           #55                 // String select invokers exception
     201: ldc           #36                 // String
     203: new           #56                 // class java/lang/StringBuilder
     206: dup
     207: invokespecial #57                 // Method java/lang/StringBuilder."<init>":()V
     210: aload         10
     212: invokevirtual #58                 // Method java/lang/Exception.getMessage:()Ljava/lang/String;
     215: invokevirtual #59                 // Method java/lang/StringBuilder.append:(Ljava/lang/String;)Ljava/lang/StringBuilder;
     218: ldc           #60                 // String  may because invokers list dynamic change, ignore.
     220: invokevirtual #59                 // Method java/lang/StringBuilder.append:(Ljava/lang/String;)Ljava/lang/StringBuilder;
     223: invokevirtual #61                 // Method java/lang/StringBuilder.toString:()Ljava/lang/String;
     226: aload         10
     228: invokeinterface #62,  6           // InterfaceMethod org/apache/dubbo/common/logger/ErrorTypeAwareLogger.warn:(Ljava/lang/String;Ljava/lang/String;Ljava/lang/String;Ljava/lang/String;Ljava/lang/Throwable;)V
     233: goto          282
     236: astore        8
     238: getstatic     #53                 // Field logger:Lorg/apache/dubbo/common/logger/ErrorTypeAwareLogger;
     241: ldc           #54                 // String 2-5
     243: ldc           #64                 // String failed to reselect invokers
     245: ldc           #36                 // String
     247: new           #56                 // class java/lang/StringBuilder
     250: dup
     251: invokespecial #57                 // Method java/lang/StringBuilder."<init>":()V
     254: ldc           #65                 // String cluster reselect fail reason is :
     256: invokevirtual #59                 // Method java/lang/StringBuilder.append:(Ljava/lang/String;)Ljava/lang/StringBuilder;
     259: aload         8
     261: invokevirtual #66                 // Method java/lang/Throwable.getMessage:()Ljava/lang/String;
     264: invokevirtual #59                 // Method java/lang/StringBuilder.append:(Ljava/lang/String;)Ljava/lang/StringBuilder;
     267: ldc           #67                 // String  if can not solve, you can set cluster.availablecheck=false in url
     269: invokevirtual #59                 // Method java/lang/StringBuilder.append:(Ljava/lang/String;)Ljava/lang/StringBuilder;
     272: invokevirtual #61                 // Method java/lang/StringBuilder.toString:()Ljava/lang/String;
     275: aload         8
     277: invokeinterface #68,  6           // InterfaceMethod org/apache/dubbo/common/logger/ErrorTypeAwareLogger.error:(Ljava/lang/String;Ljava/lang/String;Ljava/lang/String;Ljava/lang/String;Ljava/lang/Throwable;)V
     282: aload         5
     284: areturn
    Exception table:
       from    to  target type
         167   189   192   Class java/lang/Exception
         130   233   236   Class java/lang/Throwable

  private org.apache.dubbo.rpc.Invoker<T> reselect(org.apache.dubbo.rpc.cluster.LoadBalance, org.apache.dubbo.rpc.Invocation, java.util.List<org.apache.dubbo.rpc.Invoker<T>>, java.util.List<org.apache.dubbo.rpc.Invoker<T>>, boolean) throws org.apache.dubbo.rpc.RpcException;
    Code:
       0: new           #69                 // class java/util/ArrayList
       3: dup
       4: aload_3
       5: invokeinterface #45,  1           // InterfaceMethod java/util/List.size:()I
      10: aload_0
      11: getfield      #5                  // Field reselectCount:I
      14: invokestatic  #70                 // Method java/lang/Math.min:(II)I
      17: invokespecial #71                 // Method java/util/ArrayList."<init>":(I)V
      20: astore        6
      22: aload_0
      23: getfield      #5                  // Field reselectCount:I
      26: aload_3
      27: invokeinterface #45,  1           // InterfaceMethod java/util/List.size:()I
      32: if_icmplt     122
      35: aload_3
      36: invokeinterface #72,  1           // InterfaceMethod java/util/List.iterator:()Ljava/util/Iterator;
      41: astore        7
      43: aload         7
      45: invokeinterface #73,  1           // InterfaceMethod java/util/Iterator.hasNext:()Z
      50: ifeq          119
      53: aload         7
      55: invokeinterface #74,  1           // InterfaceMethod java/util/Iterator.next:()Ljava/lang/Object;
      60: checkcast     #39                 // class org/apache/dubbo/rpc/Invoker
      63: astore        8
      65: iload         5
      67: ifeq          89
      70: aload         8
      72: invokeinterface #29,  1           // InterfaceMethod org/apache/dubbo/rpc/Invoker.isAvailable:()Z
      77: ifne          89
      80: aload_0
      81: aload         8
      83: invokespecial #49                 // Method invalidateInvoker:(Lorg/apache/dubbo/rpc/Invoker;)V
      86: goto          43
      89: aload         4
      91: ifnull        106
      94: aload         4
      96: aload         8
      98: invokeinterface #43,  2           // InterfaceMethod java/util/List.contains:(Ljava/lang/Object;)Z
     103: ifne          116
     106: aload         6
     108: aload         8
     110: invokeinterface #75,  2           // InterfaceMethod java/util/List.add:(Ljava/lang/Object;)Z
     115: pop
     116: goto          43
     119: goto          226
     122: iconst_0
     123: istore        7
     125: iload         7
     127: aload_0
     128: getfield      #5                  // Field reselectCount:I
     131: if_icmpge     226
     134: aload_3
     135: invokestatic  #76                 // Method java/util/concurrent/ThreadLocalRandom.current:()Ljava/util/concurrent/ThreadLocalRandom;
     138: aload_3
     139: invokeinterface #45,  1           // InterfaceMethod java/util/List.size:()I
     144: invokevirtual #77                 // Method java/util/concurrent/ThreadLocalRandom.nextInt:(I)I
     147: invokeinterface #38,  2           // InterfaceMethod java/util/List.get:(I)Ljava/lang/Object;
     152: checkcast     #39                 // class org/apache/dubbo/rpc/Invoker
     155: astore        8
     157: iload         5
     159: ifeq          181
     162: aload         8
     164: invokeinterface #29,  1           // InterfaceMethod org/apache/dubbo/rpc/Invoker.isAvailable:()Z
     169: ifne          181
     172: aload_0
     173: aload         8
     175: invokespecial #49                 // Method invalidateInvoker:(Lorg/apache/dubbo/rpc/Invoker;)V
     178: goto          220
     181: aload         4
     183: ifnull        210
     186: aload         4
     188: aload         8
     190: invokeinterface #43,  2           // InterfaceMethod java/util/List.contains:(Ljava/lang/Object;)Z
     195: ifeq          210
     198: aload         6
     200: aload         8
     202: invokeinterface #43,  2           // InterfaceMethod java/util/List.contains:(Ljava/lang/Object;)Z
     207: ifne          220
     210: aload         6
     212: aload         8
     214: invokeinterface #75,  2           // InterfaceMethod java/util/List.add:(Ljava/lang/Object;)Z
     219: pop
     220: iinc          7, 1
     223: goto          125
     226: aload         6
     228: invokeinterface #78,  1           // InterfaceMethod java/util/List.isEmpty:()Z
     233: ifne          250
     236: aload_1
     237: aload         6
     239: aload_0
     240: invokevirtual #47                 // Method getUrl:()Lorg/apache/dubbo/common/URL;
     243: aload_2
     244: invokeinterface #48,  4           // InterfaceMethod org/apache/dubbo/rpc/cluster/LoadBalance.select:(Ljava/util/List;Lorg/apache/dubbo/common/URL;Lorg/apache/dubbo/rpc/Invocation;)Lorg/apache/dubbo/rpc/Invoker;
     249: areturn
     250: aload         4
     252: ifnull        321
     255: aload         4
     257: invokeinterface #72,  1           // InterfaceMethod java/util/List.iterator:()Ljava/util/Iterator;
     262: astore        7
     264: aload         7
     266: invokeinterface #73,  1           // InterfaceMethod java/util/Iterator.hasNext:()Z
     271: ifeq          321
     274: aload         7
     276: invokeinterface #74,  1           // InterfaceMethod java/util/Iterator.next:()Ljava/lang/Object;
     281: checkcast     #39                 // class org/apache/dubbo/rpc/Invoker
     284: astore        8
     286: aload         8
     288: invokeinterface #29,  1           // InterfaceMethod org/apache/dubbo/rpc/Invoker.isAvailable:()Z
     293: ifeq          318
     296: aload         6
     298: aload         8
     300: invokeinterface #43,  2           // InterfaceMethod java/util/List.contains:(Ljava/lang/Object;)Z
     305: ifne          318
     308: aload         6
     310: aload         8
     312: invokeinterface #75,  2           // InterfaceMethod java/util/List.add:(Ljava/lang/Object;)Z
     317: pop
     318: goto          264
     321: aload         6
     323: invokeinterface #78,  1           // InterfaceMethod java/util/List.isEmpty:()Z
     328: ifne          345
     331: aload_1
     332: aload         6
     334: aload_0
     335: invokevirtual #47                 // Method getUrl:()Lorg/apache/dubbo/common/URL;
     338: aload_2
     339: invokeinterface #48,  4           // InterfaceMethod org/apache/dubbo/rpc/cluster/LoadBalance.select:(Ljava/util/List;Lorg/apache/dubbo/common/URL;Lorg/apache/dubbo/rpc/Invocation;)Lorg/apache/dubbo/rpc/Invoker;
     344: areturn
     345: aconst_null
     346: areturn

  private void checkShouldInvalidateInvoker(org.apache.dubbo.rpc.Invoker<T>);
    Code:
       0: aload_0
       1: getfield      #19                 // Field availableCheck:Z
       4: ifeq          21
       7: aload_1
       8: invokeinterface #29,  1           // InterfaceMethod org/apache/dubbo/rpc/Invoker.isAvailable:()Z
      13: ifne          21
      16: aload_0
      17: aload_1
      18: invokespecial #49                 // Method invalidateInvoker:(Lorg/apache/dubbo/rpc/Invoker;)V
      21: return

  private void invalidateInvoker(org.apache.dubbo.rpc.Invoker<T>);
    Code:
       0: aload_0
       1: getfield      #6                  // Field enableConnectivityValidation:Z
       4: ifeq          24
       7: aload_0
       8: invokevirtual #26                 // Method getDirectory:()Lorg/apache/dubbo/rpc/cluster/Directory;
      11: ifnull        24
      14: aload_0
      15: invokevirtual #26                 // Method getDirectory:()Lorg/apache/dubbo/rpc/cluster/Directory;
      18: aload_1
      19: invokeinterface #79,  2           // InterfaceMethod org/apache/dubbo/rpc/cluster/Directory.addInvalidateInvoker:(Lorg/apache/dubbo/rpc/Invoker;)V
      24: return

  public org.apache.dubbo.rpc.Result invoke(org.apache.dubbo.rpc.Invocation) throws org.apache.dubbo.rpc.RpcException;
    Code:
       0: aload_0
       1: invokevirtual #80                 // Method checkWhetherDestroyed:()V
       4: aload_1
       5: invokedynamic #81,  0             // InvokeDynamic #0:call:()Ljava/util/concurrent/Callable;
      10: invokestatic  #82                 // Method org/apache/dubbo/rpc/InvocationProfilerUtils.enterDetailProfiler:(Lorg/apache/dubbo/rpc/Invocation;Ljava/util/concurrent/Callable;)V
      13: aload_0
      14: aload_1
      15: invokevirtual #83                 // Method list:(Lorg/apache/dubbo/rpc/Invocation;)Ljava/util/List;
      18: astore_2
      19: aload_1
      20: invokestatic  #84                 // Method org/apache/dubbo/rpc/InvocationProfilerUtils.releaseDetailProfiler:(Lorg/apache/dubbo/rpc/Invocation;)V
      23: aload_0
      24: aload_2
      25: aload_1
      26: invokevirtual #85                 // Method checkInvokers:(Ljava/util/List;Lorg/apache/dubbo/rpc/Invocation;)V
      29: aload_0
      30: aload_2
      31: aload_1
      32: invokevirtual #86                 // Method initLoadBalance:(Ljava/util/List;Lorg/apache/dubbo/rpc/Invocation;)Lorg/apache/dubbo/rpc/cluster/LoadBalance;
      35: astore_3
      36: aload_0
      37: invokevirtual #47                 // Method getUrl:()Lorg/apache/dubbo/common/URL;
      40: aload_1
      41: invokestatic  #87                 // Method org/apache/dubbo/rpc/support/RpcUtils.attachInvocationIdIfAsync:(Lorg/apache/dubbo/common/URL;Lorg/apache/dubbo/rpc/Invocation;)V
      44: aload_1
      45: aload_0
      46: invokedynamic #88,  0             // InvokeDynamic #1:call:(Lorg/apache/dubbo/rpc/cluster/support/AbstractClusterInvoker;)Ljava/util/concurrent/Callable;
      51: invokestatic  #82                 // Method org/apache/dubbo/rpc/InvocationProfilerUtils.enterDetailProfiler:(Lorg/apache/dubbo/rpc/Invocation;Ljava/util/concurrent/Callable;)V
      54: aload_0
      55: aload_1
      56: aload_2
      57: aload_3
      58: invokevirtual #89                 // Method doInvoke:(Lorg/apache/dubbo/rpc/Invocation;Ljava/util/List;Lorg/apache/dubbo/rpc/cluster/LoadBalance;)Lorg/apache/dubbo/rpc/Result;
      61: astore        4
      63: aload_1
      64: invokestatic  #84                 // Method org/apache/dubbo/rpc/InvocationProfilerUtils.releaseDetailProfiler:(Lorg/apache/dubbo/rpc/Invocation;)V
      67: aload         4
      69: areturn
      70: astore        5
      72: aload_1
      73: invokestatic  #84                 // Method org/apache/dubbo/rpc/InvocationProfilerUtils.releaseDetailProfiler:(Lorg/apache/dubbo/rpc/Invocation;)V
      76: aload         5
      78: athrow
    Exception table:
       from    to  target type
          54    63    70   any
          70    72    70   any

  protected void checkWhetherDestroyed();
    Code:
       0: aload_0
       1: getfield      #9                  // Field destroyed:Ljava/util/concurrent/atomic/AtomicBoolean;
       4: invokevirtual #33                 // Method java/util/concurrent/atomic/AtomicBoolean.get:()Z
       7: ifeq          67
      10: new           #90                 // class org/apache/dubbo/rpc/RpcException
      13: dup
      14: new           #56                 // class java/lang/StringBuilder
      17: dup
      18: invokespecial #57                 // Method java/lang/StringBuilder."<init>":()V
      21: ldc           #91                 // String Rpc cluster invoker for
      23: invokevirtual #59                 // Method java/lang/StringBuilder.append:(Ljava/lang/String;)Ljava/lang/StringBuilder;
      26: aload_0
      27: invokevirtual #92                 // Method getInterface:()Ljava/lang/Class;
      30: invokevirtual #93                 // Method java/lang/StringBuilder.append:(Ljava/lang/Object;)Ljava/lang/StringBuilder;
      33: ldc           #94                 // String  on consumer
      35: invokevirtual #59                 // Method java/lang/StringBuilder.append:(Ljava/lang/String;)Ljava/lang/StringBuilder;
      38: invokestatic  #95                 // Method org/apache/dubbo/common/utils/NetUtils.getLocalHost:()Ljava/lang/String;
      41: invokevirtual #59                 // Method java/lang/StringBuilder.append:(Ljava/lang/String;)Ljava/lang/StringBuilder;
      44: ldc           #96                 // String  use dubbo version
      46: invokevirtual #59                 // Method java/lang/StringBuilder.append:(Ljava/lang/String;)Ljava/lang/StringBuilder;
      49: invokestatic  #97                 // Method org/apache/dubbo/common/Version.getVersion:()Ljava/lang/String;
      52: invokevirtual #59                 // Method java/lang/StringBuilder.append:(Ljava/lang/String;)Ljava/lang/StringBuilder;
      55: ldc           #98                 // String  is now destroyed! Can not invoke any more.
      57: invokevirtual #59                 // Method java/lang/StringBuilder.append:(Ljava/lang/String;)Ljava/lang/StringBuilder;
      60: invokevirtual #61                 // Method java/lang/StringBuilder.toString:()Ljava/lang/String;
      63: invokespecial #99                 // Method org/apache/dubbo/rpc/RpcException."<init>":(Ljava/lang/String;)V
      66: athrow
      67: return

  public java.lang.String toString();
    Code:
       0: new           #56                 // class java/lang/StringBuilder
       3: dup
       4: invokespecial #57                 // Method java/lang/StringBuilder."<init>":()V
       7: aload_0
       8: invokevirtual #92                 // Method getInterface:()Ljava/lang/Class;
      11: invokevirtual #93                 // Method java/lang/StringBuilder.append:(Ljava/lang/Object;)Ljava/lang/StringBuilder;
      14: ldc           #100                // String  ->
      16: invokevirtual #59                 // Method java/lang/StringBuilder.append:(Ljava/lang/String;)Ljava/lang/StringBuilder;
      19: aload_0
      20: invokevirtual #47                 // Method getUrl:()Lorg/apache/dubbo/common/URL;
      23: invokevirtual #101                // Method org/apache/dubbo/common/URL.toString:()Ljava/lang/String;
      26: invokevirtual #59                 // Method java/lang/StringBuilder.append:(Ljava/lang/String;)Ljava/lang/StringBuilder;
      29: invokevirtual #61                 // Method java/lang/StringBuilder.toString:()Ljava/lang/String;
      32: areturn

  protected void checkInvokers(java.util.List<org.apache.dubbo.rpc.Invoker<T>>, org.apache.dubbo.rpc.Invocation);
    Code:
       0: aload_1
       1: invokestatic  #34                 // Method org/apache/dubbo/common/utils/CollectionUtils.isEmpty:(Ljava/util/Collection;)Z
       4: ifeq          123
       7: new           #90                 // class org/apache/dubbo/rpc/RpcException
      10: dup
      11: bipush        6
      13: new           #56                 // class java/lang/StringBuilder
      16: dup
      17: invokespecial #57                 // Method java/lang/StringBuilder."<init>":()V
      20: ldc           #102                // String Failed to invoke the method
      22: invokevirtual #59                 // Method java/lang/StringBuilder.append:(Ljava/lang/String;)Ljava/lang/StringBuilder;
      25: aload_2
      26: invokeinterface #37,  1           // InterfaceMethod org/apache/dubbo/rpc/Invocation.getMethodName:()Ljava/lang/String;
      31: invokevirtual #59                 // Method java/lang/StringBuilder.append:(Ljava/lang/String;)Ljava/lang/StringBuilder;
      34: ldc           #103                // String  in the service
      36: invokevirtual #59                 // Method java/lang/StringBuilder.append:(Ljava/lang/String;)Ljava/lang/StringBuilder;
      39: aload_0
      40: invokevirtual #92                 // Method getInterface:()Ljava/lang/Class;
      43: invokevirtual #104                // Method java/lang/Class.getName:()Ljava/lang/String;
      46: invokevirtual #59                 // Method java/lang/StringBuilder.append:(Ljava/lang/String;)Ljava/lang/StringBuilder;
      49: ldc           #105                // String . No provider available for the service
      51: invokevirtual #59                 // Method java/lang/StringBuilder.append:(Ljava/lang/String;)Ljava/lang/StringBuilder;
      54: aload_0
      55: invokevirtual #26                 // Method getDirectory:()Lorg/apache/dubbo/rpc/cluster/Directory;
      58: invokeinterface #28,  1           // InterfaceMethod org/apache/dubbo/rpc/cluster/Directory.getConsumerUrl:()Lorg/apache/dubbo/common/URL;
      63: invokevirtual #106                // Method org/apache/dubbo/common/URL.getServiceKey:()Ljava/lang/String;
      66: invokevirtual #59                 // Method java/lang/StringBuilder.append:(Ljava/lang/String;)Ljava/lang/StringBuilder;
      69: ldc           #107                // String  from registry
      71: invokevirtual #59                 // Method java/lang/StringBuilder.append:(Ljava/lang/String;)Ljava/lang/StringBuilder;
      74: aload_0
      75: invokevirtual #26                 // Method getDirectory:()Lorg/apache/dubbo/rpc/cluster/Directory;
      78: invokeinterface #11,  1           // InterfaceMethod org/apache/dubbo/rpc/cluster/Directory.getUrl:()Lorg/apache/dubbo/common/URL;
      83: invokevirtual #108                // Method org/apache/dubbo/common/URL.getAddress:()Ljava/lang/String;
      86: invokevirtual #59                 // Method java/lang/StringBuilder.append:(Ljava/lang/String;)Ljava/lang/StringBuilder;
      89: ldc           #109                // String  on the consumer
      91: invokevirtual #59                 // Method java/lang/StringBuilder.append:(Ljava/lang/String;)Ljava/lang/StringBuilder;
      94: invokestatic  #95                 // Method org/apache/dubbo/common/utils/NetUtils.getLocalHost:()Ljava/lang/String;
      97: invokevirtual #59                 // Method java/lang/StringBuilder.append:(Ljava/lang/String;)Ljava/lang/StringBuilder;
     100: ldc           #110                // String  using the dubbo version
     102: invokevirtual #59                 // Method java/lang/StringBuilder.append:(Ljava/lang/String;)Ljava/lang/StringBuilder;
     105: invokestatic  #97                 // Method org/apache/dubbo/common/Version.getVersion:()Ljava/lang/String;
     108: invokevirtual #59                 // Method java/lang/StringBuilder.append:(Ljava/lang/String;)Ljava/lang/StringBuilder;
     111: ldc           #111                // String . Please check if the providers have been started and registered.
     113: invokevirtual #59                 // Method java/lang/StringBuilder.append:(Ljava/lang/String;)Ljava/lang/StringBuilder;
     116: invokevirtual #61                 // Method java/lang/StringBuilder.toString:()Ljava/lang/String;
     119: invokespecial #112                // Method org/apache/dubbo/rpc/RpcException."<init>":(ILjava/lang/String;)V
     122: athrow
     123: return

  protected org.apache.dubbo.rpc.Result invokeWithContext(org.apache.dubbo.rpc.Invoker<T>, org.apache.dubbo.rpc.Invocation);
    Code:
       0: aload_0
       1: aload_1
       2: invokespecial #113                // Method setContext:(Lorg/apache/dubbo/rpc/Invoker;)V
       5: invokestatic  #114                // Method org/apache/dubbo/common/profiler/ProfilerSwitch.isEnableSimpleProfiler:()Z
       8: ifeq          42
      11: aload_2
      12: new           #56                 // class java/lang/StringBuilder
      15: dup
      16: invokespecial #57                 // Method java/lang/StringBuilder."<init>":()V
      19: ldc           #115                // String Invoker invoke. Target Address:
      21: invokevirtual #59                 // Method java/lang/StringBuilder.append:(Ljava/lang/String;)Ljava/lang/StringBuilder;
      24: aload_1
      25: invokeinterface #40,  1           // InterfaceMethod org/apache/dubbo/rpc/Invoker.getUrl:()Lorg/apache/dubbo/common/URL;
      30: invokevirtual #108                // Method org/apache/dubbo/common/URL.getAddress:()Ljava/lang/String;
      33: invokevirtual #59                 // Method java/lang/StringBuilder.append:(Ljava/lang/String;)Ljava/lang/StringBuilder;
      36: invokevirtual #61                 // Method java/lang/StringBuilder.toString:()Ljava/lang/String;
      39: invokestatic  #116                // Method org/apache/dubbo/rpc/InvocationProfilerUtils.enterProfiler:(Lorg/apache/dubbo/rpc/Invocation;Ljava/lang/String;)V
      42: aload_2
      43: aload_1
      44: invokeinterface #117,  2          // InterfaceMethod org/apache/dubbo/rpc/Invocation.addInvokedInvoker:(Lorg/apache/dubbo/rpc/Invoker;)V
      49: aload_1
      50: aload_2
      51: invokeinterface #118,  2          // InterfaceMethod org/apache/dubbo/rpc/Invoker.invoke:(Lorg/apache/dubbo/rpc/Invocation;)Lorg/apache/dubbo/rpc/Result;
      56: astore_3
      57: aload_0
      58: aload_1
      59: invokespecial #119                // Method clearContext:(Lorg/apache/dubbo/rpc/Invoker;)V
      62: aload_2
      63: invokestatic  #120                // Method org/apache/dubbo/rpc/InvocationProfilerUtils.releaseSimpleProfiler:(Lorg/apache/dubbo/rpc/Invocation;)V
      66: goto          83
      69: astore        4
      71: aload_0
      72: aload_1
      73: invokespecial #119                // Method clearContext:(Lorg/apache/dubbo/rpc/Invoker;)V
      76: aload_2
      77: invokestatic  #120                // Method org/apache/dubbo/rpc/InvocationProfilerUtils.releaseSimpleProfiler:(Lorg/apache/dubbo/rpc/Invocation;)V
      80: aload         4
      82: athrow
      83: aload_3
      84: areturn
    Exception table:
       from    to  target type
           5    57    69   any
          69    71    69   any

  protected org.apache.dubbo.rpc.Result invokeWithContextAsync(org.apache.dubbo.rpc.Invoker<T>, org.apache.dubbo.rpc.Invocation, org.apache.dubbo.common.URL);
    Code:
       0: aload_0
       1: aload_1
       2: aload_3
       3: invokespecial #121                // Method setContext:(Lorg/apache/dubbo/rpc/Invoker;Lorg/apache/dubbo/common/URL;)V
       6: aload_1
       7: aload_2
       8: invokeinterface #118,  2          // InterfaceMethod org/apache/dubbo/rpc/Invoker.invoke:(Lorg/apache/dubbo/rpc/Invocation;)Lorg/apache/dubbo/rpc/Result;
      13: astore        4
      15: aload_0
      16: aload_1
      17: invokespecial #119                // Method clearContext:(Lorg/apache/dubbo/rpc/Invoker;)V
      20: goto          33
      23: astore        5
      25: aload_0
      26: aload_1
      27: invokespecial #119                // Method clearContext:(Lorg/apache/dubbo/rpc/Invoker;)V
      30: aload         5
      32: athrow
      33: aload         4
      35: areturn
    Exception table:
       from    to  target type
           6    15    23   any
          23    25    23   any

  protected abstract org.apache.dubbo.rpc.Result doInvoke(org.apache.dubbo.rpc.Invocation, java.util.List<org.apache.dubbo.rpc.Invoker<T>>, org.apache.dubbo.rpc.cluster.LoadBalance) throws org.apache.dubbo.rpc.RpcException;

  protected java.util.List<org.apache.dubbo.rpc.Invoker<T>> list(org.apache.dubbo.rpc.Invocation) throws org.apache.dubbo.rpc.RpcException;
    Code:
       0: aload_0
       1: invokevirtual #26                 // Method getDirectory:()Lorg/apache/dubbo/rpc/cluster/Directory;
       4: aload_1
       5: invokeinterface #122,  2          // InterfaceMethod org/apache/dubbo/rpc/cluster/Directory.list:(Lorg/apache/dubbo/rpc/Invocation;)Ljava/util/List;
      10: areturn

  protected org.apache.dubbo.rpc.cluster.LoadBalance initLoadBalance(java.util.List<org.apache.dubbo.rpc.Invoker<T>>, org.apache.dubbo.rpc.Invocation);
    Code:
       0: aload_2
       1: invokeinterface #123,  1          // InterfaceMethod org/apache/dubbo/rpc/Invocation.getModuleModel:()Lorg/apache/dubbo/rpc/model/ModuleModel;
       6: invokestatic  #124                // Method org/apache/dubbo/rpc/model/ScopeModelUtil.getApplicationModel:(Lorg/apache/dubbo/rpc/model/ScopeModel;)Lorg/apache/dubbo/rpc/model/ApplicationModel;
       9: astore_3
      10: aload_1
      11: invokestatic  #125                // Method org/apache/dubbo/common/utils/CollectionUtils.isNotEmpty:(Ljava/util/Collection;)Z
      14: ifeq          56
      17: aload_3
      18: ldc           #126                // class org/apache/dubbo/rpc/cluster/LoadBalance
      20: invokevirtual #127                // Method org/apache/dubbo/rpc/model/ApplicationModel.getExtensionLoader:(Ljava/lang/Class;)Lorg/apache/dubbo/common/extension/ExtensionLoader;
      23: aload_1
      24: iconst_0
      25: invokeinterface #38,  2           // InterfaceMethod java/util/List.get:(I)Ljava/lang/Object;
      30: checkcast     #39                 // class org/apache/dubbo/rpc/Invoker
      33: invokeinterface #40,  1           // InterfaceMethod org/apache/dubbo/rpc/Invoker.getUrl:()Lorg/apache/dubbo/common/URL;
      38: aload_2
      39: invokestatic  #128                // Method org/apache/dubbo/rpc/support/RpcUtils.getMethodName:(Lorg/apache/dubbo/rpc/Invocation;)Ljava/lang/String;
      42: ldc           #129                // String loadbalance
      44: ldc           #130                // String random
      46: invokevirtual #131                // Method org/apache/dubbo/common/URL.getMethodParameter:(Ljava/lang/String;Ljava/lang/String;Ljava/lang/String;)Ljava/lang/String;
      49: invokevirtual #132                // Method org/apache/dubbo/common/extension/ExtensionLoader.getExtension:(Ljava/lang/String;)Ljava/lang/Object;
      52: checkcast     #126                // class org/apache/dubbo/rpc/cluster/LoadBalance
      55: areturn
      56: aload_3
      57: ldc           #126                // class org/apache/dubbo/rpc/cluster/LoadBalance
      59: invokevirtual #127                // Method org/apache/dubbo/rpc/model/ApplicationModel.getExtensionLoader:(Ljava/lang/Class;)Lorg/apache/dubbo/common/extension/ExtensionLoader;
      62: ldc           #130                // String random
      64: invokevirtual #132                // Method org/apache/dubbo/common/extension/ExtensionLoader.getExtension:(Ljava/lang/String;)Ljava/lang/Object;
      67: checkcast     #126                // class org/apache/dubbo/rpc/cluster/LoadBalance
      70: areturn

  private void setContext(org.apache.dubbo.rpc.Invoker<T>);
    Code:
       0: aload_0
       1: aload_1
       2: aconst_null
       3: invokespecial #121                // Method setContext:(Lorg/apache/dubbo/rpc/Invoker;Lorg/apache/dubbo/common/URL;)V
       6: return

  private void setContext(org.apache.dubbo.rpc.Invoker<T>, org.apache.dubbo.common.URL);
    Code:
       0: invokestatic  #133                // Method org/apache/dubbo/rpc/RpcContext.getServiceContext:()Lorg/apache/dubbo/rpc/RpcServiceContext;
       3: astore_3
       4: aload_3
       5: aload_1
       6: invokevirtual #134                // Method org/apache/dubbo/rpc/RpcContext.setInvoker:(Lorg/apache/dubbo/rpc/Invoker;)Lorg/apache/dubbo/rpc/RpcContext;
       9: aconst_null
      10: aload_2
      11: if_acmpeq     18
      14: aload_2
      15: goto          24
      18: invokestatic  #133                // Method org/apache/dubbo/rpc/RpcContext.getServiceContext:()Lorg/apache/dubbo/rpc/RpcServiceContext;
      21: invokevirtual #135                // Method org/apache/dubbo/rpc/RpcServiceContext.getConsumerUrl:()Lorg/apache/dubbo/common/URL;
      24: invokevirtual #136                // Method org/apache/dubbo/rpc/RpcContext.setConsumerUrl:(Lorg/apache/dubbo/common/URL;)V
      27: return

  private void clearContext(org.apache.dubbo.rpc.Invoker<T>);
    Code:
       0: invokestatic  #133                // Method org/apache/dubbo/rpc/RpcContext.getServiceContext:()Lorg/apache/dubbo/rpc/RpcServiceContext;
       3: astore_2
       4: aload_2
       5: aconst_null
       6: invokevirtual #134                // Method org/apache/dubbo/rpc/RpcContext.setInvoker:(Lorg/apache/dubbo/rpc/Invoker;)Lorg/apache/dubbo/rpc/RpcContext;
       9: pop
      10: return

  private java.lang.String lambda$invoke$1() throws java.lang.Exception;
    Code:
       0: new           #56                 // class java/lang/StringBuilder
       3: dup
       4: invokespecial #57                 // Method java/lang/StringBuilder."<init>":()V
       7: ldc           #137                // String Cluster
       9: invokevirtual #59                 // Method java/lang/StringBuilder.append:(Ljava/lang/String;)Ljava/lang/StringBuilder;
      12: aload_0
      13: invokevirtual #138                // Method java/lang/Object.getClass:()Ljava/lang/Class;
      16: invokevirtual #104                // Method java/lang/Class.getName:()Ljava/lang/String;
      19: invokevirtual #59                 // Method java/lang/StringBuilder.append:(Ljava/lang/String;)Ljava/lang/StringBuilder;
      22: ldc           #139                // String  invoke.
      24: invokevirtual #59                 // Method java/lang/StringBuilder.append:(Ljava/lang/String;)Ljava/lang/StringBuilder;
      27: invokevirtual #61                 // Method java/lang/StringBuilder.toString:()Ljava/lang/String;
      30: areturn

  private static java.lang.String lambda$invoke$0() throws java.lang.Exception;
    Code:
       0: ldc           #140                // String Router route.
       2: areturn

  static {};
    Code:
       0: ldc           #141                // class org/apache/dubbo/rpc/cluster/support/AbstractClusterInvoker
       2: invokestatic  #142                // Method org/apache/dubbo/common/logger/LoggerFactory.getErrorTypeAwareLogger:(Ljava/lang/Class;)Lorg/apache/dubbo/common/logger/ErrorTypeAwareLogger;
       5: putstatic     #53                 // Field logger:Lorg/apache/dubbo/common/logger/ErrorTypeAwareLogger;
       8: return
}
