Compiled from "AvailableClusterInvoker.java"
public class org.apache.dubbo.rpc.cluster.support.AvailableClusterInvoker<T> extends org.apache.dubbo.rpc.cluster.support.AbstractClusterInvoker<T> {
  public org.apache.dubbo.rpc.cluster.support.AvailableClusterInvoker(org.apache.dubbo.rpc.cluster.Directory<T>);
    Code:
       0: aload_0
       1: aload_1
       2: invokespecial #1                  // Method org/apache/dubbo/rpc/cluster/support/AbstractClusterInvoker."<init>":(Lorg/apache/dubbo/rpc/cluster/Directory;)V
       5: return

  public org.apache.dubbo.rpc.Result doInvoke(org.apache.dubbo.rpc.Invocation, java.util.List<org.apache.dubbo.rpc.Invoker<T>>, org.apache.dubbo.rpc.cluster.LoadBalance) throws org.apache.dubbo.rpc.RpcException;
    Code:
       0: aload_2
       1: invokeinterface #2,  1            // InterfaceMethod java/util/List.iterator:()Ljava/util/Iterator;
       6: astore        4
       8: aload         4
      10: invokeinterface #3,  1            // InterfaceMethod java/util/Iterator.hasNext:()Z
      15: ifeq          51
      18: aload         4
      20: invokeinterface #4,  1            // InterfaceMethod java/util/Iterator.next:()Ljava/lang/Object;
      25: checkcast     #5                  // class org/apache/dubbo/rpc/Invoker
      28: astore        5
      30: aload         5
      32: invokeinterface #6,  1            // InterfaceMethod org/apache/dubbo/rpc/Invoker.isAvailable:()Z
      37: ifeq          48
      40: aload_0
      41: aload         5
      43: aload_1
      44: invokevirtual #7                  // Method invokeWithContext:(Lorg/apache/dubbo/rpc/Invoker;Lorg/apache/dubbo/rpc/Invocation;)Lorg/apache/dubbo/rpc/Result;
      47: areturn
      48: goto          8
      51: new           #8                  // class org/apache/dubbo/rpc/RpcException
      54: dup
      55: new           #9                  // class java/lang/StringBuilder
      58: dup
      59: invokespecial #10                 // Method java/lang/StringBuilder."<init>":()V
      62: ldc           #11                 // String No provider available in
      64: invokevirtual #12                 // Method java/lang/StringBuilder.append:(Ljava/lang/String;)Ljava/lang/StringBuilder;
      67: aload_2
      68: invokevirtual #13                 // Method java/lang/StringBuilder.append:(Ljava/lang/Object;)Ljava/lang/StringBuilder;
      71: invokevirtual #14                 // Method java/lang/StringBuilder.toString:()Ljava/lang/String;
      74: invokespecial #15                 // Method org/apache/dubbo/rpc/RpcException."<init>":(Ljava/lang/String;)V
      77: athrow
}
