Compiled from "ClusterUtils.java"
public class org.apache.dubbo.rpc.cluster.support.ClusterUtils implements org.apache.dubbo.rpc.model.ScopeModelAware {
  private org.apache.dubbo.rpc.model.ApplicationModel applicationModel;

  public org.apache.dubbo.rpc.cluster.support.ClusterUtils();
    Code:
       0: aload_0
       1: invokespecial #2                  // Method java/lang/Object."<init>":()V
       4: return

  public void setApplicationModel(org.apache.dubbo.rpc.model.ApplicationModel);
    Code:
       0: aload_0
       1: aload_1
       2: putfield      #3                  // Field applicationModel:Lorg/apache/dubbo/rpc/model/ApplicationModel;
       5: return

  public org.apache.dubbo.common.URL mergeUrl(org.apache.dubbo.common.URL, java.util.Map<java.lang.String, java.lang.String>);
    Code:
       0: aload_2
       1: ldc           #4                  // String url-merge-processor
       3: invokeinterface #5,  2            // InterfaceMethod java/util/Map.get:(Ljava/lang/Object;)Ljava/lang/Object;
       8: checkcast     #6                  // class java/lang/String
      11: astore_3
      12: aload_3
      13: invokestatic  #7                  // Method org/apache/dubbo/common/utils/StringUtils.isNotEmpty:(Ljava/lang/String;)Z
      16: ifeq          40
      19: aload_0
      20: getfield      #3                  // Field applicationModel:Lorg/apache/dubbo/rpc/model/ApplicationModel;
      23: ldc           #8                  // class org/apache/dubbo/rpc/cluster/ProviderURLMergeProcessor
      25: invokevirtual #9                  // Method org/apache/dubbo/rpc/model/ApplicationModel.getExtensionLoader:(Ljava/lang/Class;)Lorg/apache/dubbo/common/extension/ExtensionLoader;
      28: aload_3
      29: invokevirtual #10                 // Method org/apache/dubbo/common/extension/ExtensionLoader.getExtension:(Ljava/lang/String;)Ljava/lang/Object;
      32: checkcast     #8                  // class org/apache/dubbo/rpc/cluster/ProviderURLMergeProcessor
      35: astore        4
      37: goto          59
      40: aload_0
      41: getfield      #3                  // Field applicationModel:Lorg/apache/dubbo/rpc/model/ApplicationModel;
      44: ldc           #8                  // class org/apache/dubbo/rpc/cluster/ProviderURLMergeProcessor
      46: invokevirtual #9                  // Method org/apache/dubbo/rpc/model/ApplicationModel.getExtensionLoader:(Ljava/lang/Class;)Lorg/apache/dubbo/common/extension/ExtensionLoader;
      49: ldc           #11                 // String default
      51: invokevirtual #10                 // Method org/apache/dubbo/common/extension/ExtensionLoader.getExtension:(Ljava/lang/String;)Ljava/lang/Object;
      54: checkcast     #8                  // class org/apache/dubbo/rpc/cluster/ProviderURLMergeProcessor
      57: astore        4
      59: aload         4
      61: aload_1
      62: aload_2
      63: invokeinterface #12,  3           // InterfaceMethod org/apache/dubbo/rpc/cluster/ProviderURLMergeProcessor.mergeUrl:(Lorg/apache/dubbo/common/URL;Ljava/util/Map;)Lorg/apache/dubbo/common/URL;
      68: areturn

  public java.util.Map<java.lang.String, java.lang.String> mergeLocalParams(java.util.Map<java.lang.String, java.lang.String>);
    Code:
       0: aload_1
       1: ldc           #4                  // String url-merge-processor
       3: invokeinterface #5,  2            // InterfaceMethod java/util/Map.get:(Ljava/lang/Object;)Ljava/lang/Object;
       8: checkcast     #6                  // class java/lang/String
      11: astore_2
      12: aload_2
      13: invokestatic  #7                  // Method org/apache/dubbo/common/utils/StringUtils.isNotEmpty:(Ljava/lang/String;)Z
      16: ifeq          39
      19: aload_0
      20: getfield      #3                  // Field applicationModel:Lorg/apache/dubbo/rpc/model/ApplicationModel;
      23: ldc           #8                  // class org/apache/dubbo/rpc/cluster/ProviderURLMergeProcessor
      25: invokevirtual #9                  // Method org/apache/dubbo/rpc/model/ApplicationModel.getExtensionLoader:(Ljava/lang/Class;)Lorg/apache/dubbo/common/extension/ExtensionLoader;
      28: aload_2
      29: invokevirtual #10                 // Method org/apache/dubbo/common/extension/ExtensionLoader.getExtension:(Ljava/lang/String;)Ljava/lang/Object;
      32: checkcast     #8                  // class org/apache/dubbo/rpc/cluster/ProviderURLMergeProcessor
      35: astore_3
      36: goto          57
      39: aload_0
      40: getfield      #3                  // Field applicationModel:Lorg/apache/dubbo/rpc/model/ApplicationModel;
      43: ldc           #8                  // class org/apache/dubbo/rpc/cluster/ProviderURLMergeProcessor
      45: invokevirtual #9                  // Method org/apache/dubbo/rpc/model/ApplicationModel.getExtensionLoader:(Ljava/lang/Class;)Lorg/apache/dubbo/common/extension/ExtensionLoader;
      48: ldc           #11                 // String default
      50: invokevirtual #10                 // Method org/apache/dubbo/common/extension/ExtensionLoader.getExtension:(Ljava/lang/String;)Ljava/lang/Object;
      53: checkcast     #8                  // class org/apache/dubbo/rpc/cluster/ProviderURLMergeProcessor
      56: astore_3
      57: aload_3
      58: aload_1
      59: invokeinterface #13,  2           // InterfaceMethod org/apache/dubbo/rpc/cluster/ProviderURLMergeProcessor.mergeLocalParams:(Ljava/util/Map;)Ljava/util/Map;
      64: areturn
}
