Compiled from "FailfastClusterInvoker.java"
public class org.apache.dubbo.rpc.cluster.support.FailfastClusterInvoker<T> extends org.apache.dubbo.rpc.cluster.support.AbstractClusterInvoker<T> {
  public org.apache.dubbo.rpc.cluster.support.FailfastClusterInvoker(org.apache.dubbo.rpc.cluster.Directory<T>);
    Code:
       0: aload_0
       1: aload_1
       2: invokespecial #1                  // Method org/apache/dubbo/rpc/cluster/support/AbstractClusterInvoker."<init>":(Lorg/apache/dubbo/rpc/cluster/Directory;)V
       5: return

  public org.apache.dubbo.rpc.Result doInvoke(org.apache.dubbo.rpc.Invocation, java.util.List<org.apache.dubbo.rpc.Invoker<T>>, org.apache.dubbo.rpc.cluster.LoadBalance) throws org.apache.dubbo.rpc.RpcException;
    Code:
       0: aload_0
       1: aload_3
       2: aload_1
       3: aload_2
       4: aconst_null
       5: invokevirtual #2                  // Method select:(Lorg/apache/dubbo/rpc/cluster/LoadBalance;Lorg/apache/dubbo/rpc/Invocation;Ljava/util/List;Ljava/util/List;)Lorg/apache/dubbo/rpc/Invoker;
       8: astore        4
      10: aload_0
      11: aload         4
      13: aload_1
      14: invokevirtual #3                  // Method invokeWithContext:(Lorg/apache/dubbo/rpc/Invoker;Lorg/apache/dubbo/rpc/Invocation;)Lorg/apache/dubbo/rpc/Result;
      17: areturn
      18: astore        5
      20: aload         5
      22: instanceof    #5                  // class org/apache/dubbo/rpc/RpcException
      25: ifeq          45
      28: aload         5
      30: checkcast     #5                  // class org/apache/dubbo/rpc/RpcException
      33: invokevirtual #6                  // Method org/apache/dubbo/rpc/RpcException.isBiz:()Z
      36: ifeq          45
      39: aload         5
      41: checkcast     #5                  // class org/apache/dubbo/rpc/RpcException
      44: athrow
      45: new           #5                  // class org/apache/dubbo/rpc/RpcException
      48: dup
      49: aload         5
      51: instanceof    #5                  // class org/apache/dubbo/rpc/RpcException
      54: ifeq          68
      57: aload         5
      59: checkcast     #5                  // class org/apache/dubbo/rpc/RpcException
      62: invokevirtual #7                  // Method org/apache/dubbo/rpc/RpcException.getCode:()I
      65: goto          69
      68: iconst_0
      69: new           #8                  // class java/lang/StringBuilder
      72: dup
      73: invokespecial #9                  // Method java/lang/StringBuilder."<init>":()V
      76: ldc           #10                 // String Failfast invoke providers
      78: invokevirtual #11                 // Method java/lang/StringBuilder.append:(Ljava/lang/String;)Ljava/lang/StringBuilder;
      81: aload         4
      83: invokeinterface #12,  1           // InterfaceMethod org/apache/dubbo/rpc/Invoker.getUrl:()Lorg/apache/dubbo/common/URL;
      88: invokevirtual #13                 // Method java/lang/StringBuilder.append:(Ljava/lang/Object;)Ljava/lang/StringBuilder;
      91: ldc           #14                 // String
      93: invokevirtual #11                 // Method java/lang/StringBuilder.append:(Ljava/lang/String;)Ljava/lang/StringBuilder;
      96: aload_3
      97: invokevirtual #15                 // Method java/lang/Object.getClass:()Ljava/lang/Class;
     100: invokevirtual #16                 // Method java/lang/Class.getSimpleName:()Ljava/lang/String;
     103: invokevirtual #11                 // Method java/lang/StringBuilder.append:(Ljava/lang/String;)Ljava/lang/StringBuilder;
     106: ldc           #17                 // String  for service
     108: invokevirtual #11                 // Method java/lang/StringBuilder.append:(Ljava/lang/String;)Ljava/lang/StringBuilder;
     111: aload_0
     112: invokevirtual #18                 // Method getInterface:()Ljava/lang/Class;
     115: invokevirtual #19                 // Method java/lang/Class.getName:()Ljava/lang/String;
     118: invokevirtual #11                 // Method java/lang/StringBuilder.append:(Ljava/lang/String;)Ljava/lang/StringBuilder;
     121: ldc           #20                 // String  method
     123: invokevirtual #11                 // Method java/lang/StringBuilder.append:(Ljava/lang/String;)Ljava/lang/StringBuilder;
     126: aload_1
     127: invokeinterface #21,  1           // InterfaceMethod org/apache/dubbo/rpc/Invocation.getMethodName:()Ljava/lang/String;
     132: invokevirtual #11                 // Method java/lang/StringBuilder.append:(Ljava/lang/String;)Ljava/lang/StringBuilder;
     135: ldc           #22                 // String  on consumer
     137: invokevirtual #11                 // Method java/lang/StringBuilder.append:(Ljava/lang/String;)Ljava/lang/StringBuilder;
     140: invokestatic  #23                 // Method org/apache/dubbo/common/utils/NetUtils.getLocalHost:()Ljava/lang/String;
     143: invokevirtual #11                 // Method java/lang/StringBuilder.append:(Ljava/lang/String;)Ljava/lang/StringBuilder;
     146: ldc           #24                 // String  use dubbo version
     148: invokevirtual #11                 // Method java/lang/StringBuilder.append:(Ljava/lang/String;)Ljava/lang/StringBuilder;
     151: invokestatic  #25                 // Method org/apache/dubbo/common/Version.getVersion:()Ljava/lang/String;
     154: invokevirtual #11                 // Method java/lang/StringBuilder.append:(Ljava/lang/String;)Ljava/lang/StringBuilder;
     157: ldc           #26                 // String , but no luck to perform the invocation. Last error is:
     159: invokevirtual #11                 // Method java/lang/StringBuilder.append:(Ljava/lang/String;)Ljava/lang/StringBuilder;
     162: aload         5
     164: invokevirtual #27                 // Method java/lang/Throwable.getMessage:()Ljava/lang/String;
     167: invokevirtual #11                 // Method java/lang/StringBuilder.append:(Ljava/lang/String;)Ljava/lang/StringBuilder;
     170: invokevirtual #28                 // Method java/lang/StringBuilder.toString:()Ljava/lang/String;
     173: aload         5
     175: invokevirtual #29                 // Method java/lang/Throwable.getCause:()Ljava/lang/Throwable;
     178: ifnull        189
     181: aload         5
     183: invokevirtual #29                 // Method java/lang/Throwable.getCause:()Ljava/lang/Throwable;
     186: goto          191
     189: aload         5
     191: invokespecial #30                 // Method org/apache/dubbo/rpc/RpcException."<init>":(ILjava/lang/String;Ljava/lang/Throwable;)V
     194: athrow
    Exception table:
       from    to  target type
          10    17    18   Class java/lang/Throwable
}
