Compiled from "FailbackClusterInvoker.java"
public class org.apache.dubbo.rpc.cluster.support.FailbackClusterInvoker<T> extends org.apache.dubbo.rpc.cluster.support.AbstractClusterInvoker<T> {
  private static final org.apache.dubbo.common.logger.ErrorTypeAwareLogger logger;

  private static final long RETRY_FAILED_PERIOD;

  private final int retries;

  private final int failbackTasks;

  private volatile org.apache.dubbo.common.timer.Timer failTimer;

  public org.apache.dubbo.rpc.cluster.support.FailbackClusterInvoker(org.apache.dubbo.rpc.cluster.Directory<T>);
    Code:
       0: aload_0
       1: aload_1
       2: invokespecial #5                  // Method org/apache/dubbo/rpc/cluster/support/AbstractClusterInvoker."<init>":(Lorg/apache/dubbo/rpc/cluster/Directory;)V
       5: aload_0
       6: invokevirtual #6                  // Method getUrl:()Lorg/apache/dubbo/common/URL;
       9: ldc           #7                  // String retries
      11: iconst_3
      12: invokevirtual #8                  // Method org/apache/dubbo/common/URL.getParameter:(Ljava/lang/String;I)I
      15: istore_2
      16: iload_2
      17: ifge          22
      20: iconst_3
      21: istore_2
      22: aload_0
      23: invokevirtual #6                  // Method getUrl:()Lorg/apache/dubbo/common/URL;
      26: ldc           #9                  // String failbacktasks
      28: bipush        100
      30: invokevirtual #8                  // Method org/apache/dubbo/common/URL.getParameter:(Ljava/lang/String;I)I
      33: istore_3
      34: iload_3
      35: ifgt          41
      38: bipush        100
      40: istore_3
      41: aload_0
      42: iload_2
      43: putfield      #10                 // Field retries:I
      46: aload_0
      47: iload_3
      48: putfield      #11                 // Field failbackTasks:I
      51: return

  private void addFailed(org.apache.dubbo.rpc.cluster.LoadBalance, org.apache.dubbo.rpc.Invocation, java.util.List<org.apache.dubbo.rpc.Invoker<T>>, org.apache.dubbo.rpc.Invoker<T>, org.apache.dubbo.common.URL);
    Code:
       0: aload_0
       1: getfield      #12                 // Field failTimer:Lorg/apache/dubbo/common/timer/Timer;
       4: ifnonnull     65
       7: aload_0
       8: dup
       9: astore        6
      11: monitorenter
      12: aload_0
      13: getfield      #12                 // Field failTimer:Lorg/apache/dubbo/common/timer/Timer;
      16: ifnonnull     51
      19: aload_0
      20: new           #13                 // class org/apache/dubbo/common/timer/HashedWheelTimer
      23: dup
      24: new           #14                 // class org/apache/dubbo/common/utils/NamedThreadFactory
      27: dup
      28: ldc           #15                 // String failback-cluster-timer
      30: iconst_1
      31: invokespecial #16                 // Method org/apache/dubbo/common/utils/NamedThreadFactory."<init>":(Ljava/lang/String;Z)V
      34: lconst_1
      35: getstatic     #17                 // Field java/util/concurrent/TimeUnit.SECONDS:Ljava/util/concurrent/TimeUnit;
      38: bipush        32
      40: aload_0
      41: getfield      #11                 // Field failbackTasks:I
      44: i2l
      45: invokespecial #18                 // Method org/apache/dubbo/common/timer/HashedWheelTimer."<init>":(Ljava/util/concurrent/ThreadFactory;JLjava/util/concurrent/TimeUnit;IJ)V
      48: putfield      #12                 // Field failTimer:Lorg/apache/dubbo/common/timer/Timer;
      51: aload         6
      53: monitorexit
      54: goto          65
      57: astore        7
      59: aload         6
      61: monitorexit
      62: aload         7
      64: athrow
      65: new           #19                 // class org/apache/dubbo/rpc/cluster/support/FailbackClusterInvoker$RetryTimerTask
      68: dup
      69: aload_0
      70: aload_1
      71: aload_2
      72: aload_3
      73: aload         4
      75: aload_0
      76: getfield      #10                 // Field retries:I
      79: ldc2_w        #21                 // long 5l
      82: aload         5
      84: invokespecial #23                 // Method org/apache/dubbo/rpc/cluster/support/FailbackClusterInvoker$RetryTimerTask."<init>":(Lorg/apache/dubbo/rpc/cluster/support/FailbackClusterInvoker;Lorg/apache/dubbo/rpc/cluster/LoadBalance;Lorg/apache/dubbo/rpc/Invocation;Ljava/util/List;Lorg/apache/dubbo/rpc/Invoker;IJLorg/apache/dubbo/common/URL;)V
      87: astore        6
      89: aload_0
      90: getfield      #12                 // Field failTimer:Lorg/apache/dubbo/common/timer/Timer;
      93: aload         6
      95: ldc2_w        #21                 // long 5l
      98: getstatic     #17                 // Field java/util/concurrent/TimeUnit.SECONDS:Ljava/util/concurrent/TimeUnit;
     101: invokeinterface #24,  5           // InterfaceMethod org/apache/dubbo/common/timer/Timer.newTimeout:(Lorg/apache/dubbo/common/timer/TimerTask;JLjava/util/concurrent/TimeUnit;)Lorg/apache/dubbo/common/timer/Timeout;
     106: pop
     107: goto          160
     110: astore        7
     112: getstatic     #4                  // Field logger:Lorg/apache/dubbo/common/logger/ErrorTypeAwareLogger;
     115: ldc           #26                 // String 2-9
     117: ldc           #27                 // String add newTimeout exception
     119: ldc           #28                 // String
     121: new           #29                 // class java/lang/StringBuilder
     124: dup
     125: invokespecial #30                 // Method java/lang/StringBuilder."<init>":()V
     128: ldc           #31                 // String Failback background works error, invocation->
     130: invokevirtual #32                 // Method java/lang/StringBuilder.append:(Ljava/lang/String;)Ljava/lang/StringBuilder;
     133: aload_2
     134: invokevirtual #33                 // Method java/lang/StringBuilder.append:(Ljava/lang/Object;)Ljava/lang/StringBuilder;
     137: ldc           #34                 // String , exception:
     139: invokevirtual #32                 // Method java/lang/StringBuilder.append:(Ljava/lang/String;)Ljava/lang/StringBuilder;
     142: aload         7
     144: invokevirtual #35                 // Method java/lang/Throwable.getMessage:()Ljava/lang/String;
     147: invokevirtual #32                 // Method java/lang/StringBuilder.append:(Ljava/lang/String;)Ljava/lang/StringBuilder;
     150: invokevirtual #36                 // Method java/lang/StringBuilder.toString:()Ljava/lang/String;
     153: aload         7
     155: invokeinterface #37,  6           // InterfaceMethod org/apache/dubbo/common/logger/ErrorTypeAwareLogger.error:(Ljava/lang/String;Ljava/lang/String;Ljava/lang/String;Ljava/lang/String;Ljava/lang/Throwable;)V
     160: return
    Exception table:
       from    to  target type
          12    54    57   any
          57    62    57   any
          89   107   110   Class java/lang/Throwable

  protected org.apache.dubbo.rpc.Result doInvoke(org.apache.dubbo.rpc.Invocation, java.util.List<org.apache.dubbo.rpc.Invoker<T>>, org.apache.dubbo.rpc.cluster.LoadBalance) throws org.apache.dubbo.rpc.RpcException;
    Code:
       0: aconst_null
       1: astore        4
       3: invokestatic  #38                 // Method org/apache/dubbo/rpc/RpcContext.getServiceContext:()Lorg/apache/dubbo/rpc/RpcServiceContext;
       6: invokevirtual #39                 // Method org/apache/dubbo/rpc/RpcServiceContext.getConsumerUrl:()Lorg/apache/dubbo/common/URL;
       9: astore        5
      11: aload_0
      12: aload_3
      13: aload_1
      14: aload_2
      15: aconst_null
      16: invokevirtual #40                 // Method select:(Lorg/apache/dubbo/rpc/cluster/LoadBalance;Lorg/apache/dubbo/rpc/Invocation;Ljava/util/List;Ljava/util/List;)Lorg/apache/dubbo/rpc/Invoker;
      19: astore        4
      21: aload_0
      22: aload         4
      24: aload_1
      25: aload         5
      27: invokevirtual #41                 // Method invokeWithContextAsync:(Lorg/apache/dubbo/rpc/Invoker;Lorg/apache/dubbo/rpc/Invocation;Lorg/apache/dubbo/common/URL;)Lorg/apache/dubbo/rpc/Result;
      30: areturn
      31: astore        6
      33: getstatic     #4                  // Field logger:Lorg/apache/dubbo/common/logger/ErrorTypeAwareLogger;
      36: ldc           #42                 // String 2-10
      38: ldc           #43                 // String Failback to invoke method and start to retries
      40: ldc           #28                 // String
      42: new           #29                 // class java/lang/StringBuilder
      45: dup
      46: invokespecial #30                 // Method java/lang/StringBuilder."<init>":()V
      49: ldc           #44                 // String Failback to invoke method
      51: invokevirtual #32                 // Method java/lang/StringBuilder.append:(Ljava/lang/String;)Ljava/lang/StringBuilder;
      54: aload_1
      55: invokeinterface #45,  1           // InterfaceMethod org/apache/dubbo/rpc/Invocation.getMethodName:()Ljava/lang/String;
      60: invokevirtual #32                 // Method java/lang/StringBuilder.append:(Ljava/lang/String;)Ljava/lang/StringBuilder;
      63: ldc           #46                 // String , wait for retry in background. Ignored exception:
      65: invokevirtual #32                 // Method java/lang/StringBuilder.append:(Ljava/lang/String;)Ljava/lang/StringBuilder;
      68: aload         6
      70: invokevirtual #35                 // Method java/lang/Throwable.getMessage:()Ljava/lang/String;
      73: invokevirtual #32                 // Method java/lang/StringBuilder.append:(Ljava/lang/String;)Ljava/lang/StringBuilder;
      76: ldc           #47                 // String ,
      78: invokevirtual #32                 // Method java/lang/StringBuilder.append:(Ljava/lang/String;)Ljava/lang/StringBuilder;
      81: invokevirtual #36                 // Method java/lang/StringBuilder.toString:()Ljava/lang/String;
      84: aload         6
      86: invokeinterface #37,  6           // InterfaceMethod org/apache/dubbo/common/logger/ErrorTypeAwareLogger.error:(Ljava/lang/String;Ljava/lang/String;Ljava/lang/String;Ljava/lang/String;Ljava/lang/Throwable;)V
      91: aload_0
      92: getfield      #10                 // Field retries:I
      95: ifle          109
      98: aload_0
      99: aload_3
     100: aload_1
     101: aload_2
     102: aload         4
     104: aload         5
     106: invokespecial #48                 // Method addFailed:(Lorg/apache/dubbo/rpc/cluster/LoadBalance;Lorg/apache/dubbo/rpc/Invocation;Ljava/util/List;Lorg/apache/dubbo/rpc/Invoker;Lorg/apache/dubbo/common/URL;)V
     109: aconst_null
     110: aconst_null
     111: aload_1
     112: invokestatic  #49                 // Method org/apache/dubbo/rpc/AsyncRpcResult.newDefaultAsyncResult:(Ljava/lang/Object;Ljava/lang/Throwable;Lorg/apache/dubbo/rpc/Invocation;)Lorg/apache/dubbo/rpc/AsyncRpcResult;
     115: areturn
    Exception table:
       from    to  target type
          11    30    31   Class java/lang/Throwable

  public void destroy();
    Code:
       0: aload_0
       1: invokespecial #50                 // Method org/apache/dubbo/rpc/cluster/support/AbstractClusterInvoker.destroy:()V
       4: aload_0
       5: getfield      #12                 // Field failTimer:Lorg/apache/dubbo/common/timer/Timer;
       8: ifnull        21
      11: aload_0
      12: getfield      #12                 // Field failTimer:Lorg/apache/dubbo/common/timer/Timer;
      15: invokeinterface #51,  1           // InterfaceMethod org/apache/dubbo/common/timer/Timer.stop:()Ljava/util/Set;
      20: pop
      21: return

  static org.apache.dubbo.common.logger.ErrorTypeAwareLogger access$000();
    Code:
       0: getstatic     #4                  // Field logger:Lorg/apache/dubbo/common/logger/ErrorTypeAwareLogger;
       3: areturn

  static {};
    Code:
       0: ldc           #20                 // class org/apache/dubbo/rpc/cluster/support/FailbackClusterInvoker
       2: invokestatic  #52                 // Method org/apache/dubbo/common/logger/LoggerFactory.getErrorTypeAwareLogger:(Ljava/lang/Class;)Lorg/apache/dubbo/common/logger/ErrorTypeAwareLogger;
       5: putstatic     #4                  // Field logger:Lorg/apache/dubbo/common/logger/ErrorTypeAwareLogger;
       8: return
}
