Compiled from "FailoverClusterInvoker.java"
public class org.apache.dubbo.rpc.cluster.support.FailoverClusterInvoker<T> extends org.apache.dubbo.rpc.cluster.support.AbstractClusterInvoker<T> {
  private static final org.apache.dubbo.common.logger.ErrorTypeAwareLogger logger;

  public org.apache.dubbo.rpc.cluster.support.FailoverClusterInvoker(org.apache.dubbo.rpc.cluster.Directory<T>);
    Code:
       0: aload_0
       1: aload_1
       2: invokespecial #3                  // Method org/apache/dubbo/rpc/cluster/support/AbstractClusterInvoker."<init>":(Lorg/apache/dubbo/rpc/cluster/Directory;)V
       5: return

  public org.apache.dubbo.rpc.Result doInvoke(org.apache.dubbo.rpc.Invocation, java.util.List<org.apache.dubbo.rpc.Invoker<T>>, org.apache.dubbo.rpc.cluster.LoadBalance) throws org.apache.dubbo.rpc.RpcException;
    Code:
       0: aload_2
       1: astore        4
       3: aload_1
       4: invokestatic  #4                  // Method org/apache/dubbo/rpc/support/RpcUtils.getMethodName:(Lorg/apache/dubbo/rpc/Invocation;)Ljava/lang/String;
       7: astore        5
       9: aload_0
      10: aload         5
      12: invokespecial #5                  // Method calculateInvokeTimes:(Ljava/lang/String;)I
      15: istore        6
      17: aconst_null
      18: astore        7
      20: new           #6                  // class java/util/ArrayList
      23: dup
      24: aload         4
      26: invokeinterface #7,  1            // InterfaceMethod java/util/List.size:()I
      31: invokespecial #8                  // Method java/util/ArrayList."<init>":(I)V
      34: astore        8
      36: new           #9                  // class java/util/HashSet
      39: dup
      40: iload         6
      42: invokespecial #10                 // Method java/util/HashSet."<init>":(I)V
      45: astore        9
      47: iconst_0
      48: istore        10
      50: iload         10
      52: iload         6
      54: if_icmpge     457
      57: iload         10
      59: ifle          80
      62: aload_0
      63: invokevirtual #11                 // Method checkWhetherDestroyed:()V
      66: aload_0
      67: aload_1
      68: invokevirtual #12                 // Method list:(Lorg/apache/dubbo/rpc/Invocation;)Ljava/util/List;
      71: astore        4
      73: aload_0
      74: aload         4
      76: aload_1
      77: invokevirtual #13                 // Method checkInvokers:(Ljava/util/List;Lorg/apache/dubbo/rpc/Invocation;)V
      80: aload_0
      81: aload_3
      82: aload_1
      83: aload         4
      85: aload         8
      87: invokevirtual #14                 // Method select:(Lorg/apache/dubbo/rpc/cluster/LoadBalance;Lorg/apache/dubbo/rpc/Invocation;Ljava/util/List;Ljava/util/List;)Lorg/apache/dubbo/rpc/Invoker;
      90: astore        11
      92: aload         8
      94: aload         11
      96: invokeinterface #15,  2           // InterfaceMethod java/util/List.add:(Ljava/lang/Object;)Z
     101: pop
     102: invokestatic  #16                 // Method org/apache/dubbo/rpc/RpcContext.getServiceContext:()Lorg/apache/dubbo/rpc/RpcServiceContext;
     105: aload         8
     107: invokevirtual #17                 // Method org/apache/dubbo/rpc/RpcServiceContext.setInvokers:(Ljava/util/List;)Lorg/apache/dubbo/rpc/RpcServiceContext;
     110: pop
     111: iconst_0
     112: istore        12
     114: aload_0
     115: aload         11
     117: aload_1
     118: invokevirtual #18                 // Method invokeWithContext:(Lorg/apache/dubbo/rpc/Invoker;Lorg/apache/dubbo/rpc/Invocation;)Lorg/apache/dubbo/rpc/Result;
     121: astore        13
     123: aload         7
     125: ifnull        303
     128: getstatic     #19                 // Field logger:Lorg/apache/dubbo/common/logger/ErrorTypeAwareLogger;
     131: invokeinterface #20,  1           // InterfaceMethod org/apache/dubbo/common/logger/ErrorTypeAwareLogger.isWarnEnabled:()Z
     136: ifeq          303
     139: getstatic     #19                 // Field logger:Lorg/apache/dubbo/common/logger/ErrorTypeAwareLogger;
     142: ldc           #21                 // String 2-16
     144: ldc           #22                 // String failed to retry do invoke
     146: ldc           #23                 // String
     148: new           #24                 // class java/lang/StringBuilder
     151: dup
     152: invokespecial #25                 // Method java/lang/StringBuilder."<init>":()V
     155: ldc           #26                 // String Although retry the method
     157: invokevirtual #27                 // Method java/lang/StringBuilder.append:(Ljava/lang/String;)Ljava/lang/StringBuilder;
     160: aload         5
     162: invokevirtual #27                 // Method java/lang/StringBuilder.append:(Ljava/lang/String;)Ljava/lang/StringBuilder;
     165: ldc           #28                 // String  in the service
     167: invokevirtual #27                 // Method java/lang/StringBuilder.append:(Ljava/lang/String;)Ljava/lang/StringBuilder;
     170: aload_0
     171: invokevirtual #29                 // Method getInterface:()Ljava/lang/Class;
     174: invokevirtual #30                 // Method java/lang/Class.getName:()Ljava/lang/String;
     177: invokevirtual #27                 // Method java/lang/StringBuilder.append:(Ljava/lang/String;)Ljava/lang/StringBuilder;
     180: ldc           #31                 // String  was successful by the provider
     182: invokevirtual #27                 // Method java/lang/StringBuilder.append:(Ljava/lang/String;)Ljava/lang/StringBuilder;
     185: aload         11
     187: invokeinterface #32,  1           // InterfaceMethod org/apache/dubbo/rpc/Invoker.getUrl:()Lorg/apache/dubbo/common/URL;
     192: invokevirtual #33                 // Method org/apache/dubbo/common/URL.getAddress:()Ljava/lang/String;
     195: invokevirtual #27                 // Method java/lang/StringBuilder.append:(Ljava/lang/String;)Ljava/lang/StringBuilder;
     198: ldc           #34                 // String , but there have been failed providers
     200: invokevirtual #27                 // Method java/lang/StringBuilder.append:(Ljava/lang/String;)Ljava/lang/StringBuilder;
     203: aload         9
     205: invokevirtual #35                 // Method java/lang/StringBuilder.append:(Ljava/lang/Object;)Ljava/lang/StringBuilder;
     208: ldc           #36                 // String  (
     210: invokevirtual #27                 // Method java/lang/StringBuilder.append:(Ljava/lang/String;)Ljava/lang/StringBuilder;
     213: aload         9
     215: invokeinterface #37,  1           // InterfaceMethod java/util/Set.size:()I
     220: invokevirtual #38                 // Method java/lang/StringBuilder.append:(I)Ljava/lang/StringBuilder;
     223: ldc           #39                 // String /
     225: invokevirtual #27                 // Method java/lang/StringBuilder.append:(Ljava/lang/String;)Ljava/lang/StringBuilder;
     228: aload         4
     230: invokeinterface #7,  1            // InterfaceMethod java/util/List.size:()I
     235: invokevirtual #38                 // Method java/lang/StringBuilder.append:(I)Ljava/lang/StringBuilder;
     238: ldc           #40                 // String ) from the registry
     240: invokevirtual #27                 // Method java/lang/StringBuilder.append:(Ljava/lang/String;)Ljava/lang/StringBuilder;
     243: aload_0
     244: getfield      #41                 // Field directory:Lorg/apache/dubbo/rpc/cluster/Directory;
     247: invokeinterface #42,  1           // InterfaceMethod org/apache/dubbo/rpc/cluster/Directory.getUrl:()Lorg/apache/dubbo/common/URL;
     252: invokevirtual #33                 // Method org/apache/dubbo/common/URL.getAddress:()Ljava/lang/String;
     255: invokevirtual #27                 // Method java/lang/StringBuilder.append:(Ljava/lang/String;)Ljava/lang/StringBuilder;
     258: ldc           #43                 // String  on the consumer
     260: invokevirtual #27                 // Method java/lang/StringBuilder.append:(Ljava/lang/String;)Ljava/lang/StringBuilder;
     263: invokestatic  #44                 // Method org/apache/dubbo/common/utils/NetUtils.getLocalHost:()Ljava/lang/String;
     266: invokevirtual #27                 // Method java/lang/StringBuilder.append:(Ljava/lang/String;)Ljava/lang/StringBuilder;
     269: ldc           #45                 // String  using the dubbo version
     271: invokevirtual #27                 // Method java/lang/StringBuilder.append:(Ljava/lang/String;)Ljava/lang/StringBuilder;
     274: invokestatic  #46                 // Method org/apache/dubbo/common/Version.getVersion:()Ljava/lang/String;
     277: invokevirtual #27                 // Method java/lang/StringBuilder.append:(Ljava/lang/String;)Ljava/lang/StringBuilder;
     280: ldc           #47                 // String . Last error is:
     282: invokevirtual #27                 // Method java/lang/StringBuilder.append:(Ljava/lang/String;)Ljava/lang/StringBuilder;
     285: aload         7
     287: invokevirtual #48                 // Method org/apache/dubbo/rpc/RpcException.getMessage:()Ljava/lang/String;
     290: invokevirtual #27                 // Method java/lang/StringBuilder.append:(Ljava/lang/String;)Ljava/lang/StringBuilder;
     293: invokevirtual #49                 // Method java/lang/StringBuilder.toString:()Ljava/lang/String;
     296: aload         7
     298: invokeinterface #50,  6           // InterfaceMethod org/apache/dubbo/common/logger/ErrorTypeAwareLogger.warn:(Ljava/lang/String;Ljava/lang/String;Ljava/lang/String;Ljava/lang/String;Ljava/lang/Throwable;)V
     303: iconst_1
     304: istore        12
     306: aload         13
     308: astore        14
     310: iload         12
     312: ifne          333
     315: aload         9
     317: aload         11
     319: invokeinterface #32,  1           // InterfaceMethod org/apache/dubbo/rpc/Invoker.getUrl:()Lorg/apache/dubbo/common/URL;
     324: invokevirtual #33                 // Method org/apache/dubbo/common/URL.getAddress:()Ljava/lang/String;
     327: invokeinterface #51,  2           // InterfaceMethod java/util/Set.add:(Ljava/lang/Object;)Z
     332: pop
     333: aload         14
     335: areturn
     336: astore        13
     338: aload         13
     340: invokevirtual #53                 // Method org/apache/dubbo/rpc/RpcException.isBiz:()Z
     343: ifeq          349
     346: aload         13
     348: athrow
     349: aload         13
     351: astore        7
     353: iload         12
     355: ifne          451
     358: aload         9
     360: aload         11
     362: invokeinterface #32,  1           // InterfaceMethod org/apache/dubbo/rpc/Invoker.getUrl:()Lorg/apache/dubbo/common/URL;
     367: invokevirtual #33                 // Method org/apache/dubbo/common/URL.getAddress:()Ljava/lang/String;
     370: invokeinterface #51,  2           // InterfaceMethod java/util/Set.add:(Ljava/lang/Object;)Z
     375: pop
     376: goto          451
     379: astore        13
     381: new           #52                 // class org/apache/dubbo/rpc/RpcException
     384: dup
     385: aload         13
     387: invokevirtual #55                 // Method java/lang/Throwable.getMessage:()Ljava/lang/String;
     390: aload         13
     392: invokespecial #56                 // Method org/apache/dubbo/rpc/RpcException."<init>":(Ljava/lang/String;Ljava/lang/Throwable;)V
     395: astore        7
     397: iload         12
     399: ifne          451
     402: aload         9
     404: aload         11
     406: invokeinterface #32,  1           // InterfaceMethod org/apache/dubbo/rpc/Invoker.getUrl:()Lorg/apache/dubbo/common/URL;
     411: invokevirtual #33                 // Method org/apache/dubbo/common/URL.getAddress:()Ljava/lang/String;
     414: invokeinterface #51,  2           // InterfaceMethod java/util/Set.add:(Ljava/lang/Object;)Z
     419: pop
     420: goto          451
     423: astore        15
     425: iload         12
     427: ifne          448
     430: aload         9
     432: aload         11
     434: invokeinterface #32,  1           // InterfaceMethod org/apache/dubbo/rpc/Invoker.getUrl:()Lorg/apache/dubbo/common/URL;
     439: invokevirtual #33                 // Method org/apache/dubbo/common/URL.getAddress:()Ljava/lang/String;
     442: invokeinterface #51,  2           // InterfaceMethod java/util/Set.add:(Ljava/lang/Object;)Z
     447: pop
     448: aload         15
     450: athrow
     451: iinc          10, 1
     454: goto          50
     457: new           #52                 // class org/apache/dubbo/rpc/RpcException
     460: dup
     461: aload         7
     463: invokevirtual #57                 // Method org/apache/dubbo/rpc/RpcException.getCode:()I
     466: new           #24                 // class java/lang/StringBuilder
     469: dup
     470: invokespecial #25                 // Method java/lang/StringBuilder."<init>":()V
     473: ldc           #58                 // String Failed to invoke the method
     475: invokevirtual #27                 // Method java/lang/StringBuilder.append:(Ljava/lang/String;)Ljava/lang/StringBuilder;
     478: aload         5
     480: invokevirtual #27                 // Method java/lang/StringBuilder.append:(Ljava/lang/String;)Ljava/lang/StringBuilder;
     483: ldc           #28                 // String  in the service
     485: invokevirtual #27                 // Method java/lang/StringBuilder.append:(Ljava/lang/String;)Ljava/lang/StringBuilder;
     488: aload_0
     489: invokevirtual #29                 // Method getInterface:()Ljava/lang/Class;
     492: invokevirtual #30                 // Method java/lang/Class.getName:()Ljava/lang/String;
     495: invokevirtual #27                 // Method java/lang/StringBuilder.append:(Ljava/lang/String;)Ljava/lang/StringBuilder;
     498: ldc           #59                 // String . Tried
     500: invokevirtual #27                 // Method java/lang/StringBuilder.append:(Ljava/lang/String;)Ljava/lang/StringBuilder;
     503: iload         6
     505: invokevirtual #38                 // Method java/lang/StringBuilder.append:(I)Ljava/lang/StringBuilder;
     508: ldc           #60                 // String  times of the providers
     510: invokevirtual #27                 // Method java/lang/StringBuilder.append:(Ljava/lang/String;)Ljava/lang/StringBuilder;
     513: aload         9
     515: invokevirtual #35                 // Method java/lang/StringBuilder.append:(Ljava/lang/Object;)Ljava/lang/StringBuilder;
     518: ldc           #36                 // String  (
     520: invokevirtual #27                 // Method java/lang/StringBuilder.append:(Ljava/lang/String;)Ljava/lang/StringBuilder;
     523: aload         9
     525: invokeinterface #37,  1           // InterfaceMethod java/util/Set.size:()I
     530: invokevirtual #38                 // Method java/lang/StringBuilder.append:(I)Ljava/lang/StringBuilder;
     533: ldc           #39                 // String /
     535: invokevirtual #27                 // Method java/lang/StringBuilder.append:(Ljava/lang/String;)Ljava/lang/StringBuilder;
     538: aload         4
     540: invokeinterface #7,  1            // InterfaceMethod java/util/List.size:()I
     545: invokevirtual #38                 // Method java/lang/StringBuilder.append:(I)Ljava/lang/StringBuilder;
     548: ldc           #40                 // String ) from the registry
     550: invokevirtual #27                 // Method java/lang/StringBuilder.append:(Ljava/lang/String;)Ljava/lang/StringBuilder;
     553: aload_0
     554: getfield      #41                 // Field directory:Lorg/apache/dubbo/rpc/cluster/Directory;
     557: invokeinterface #42,  1           // InterfaceMethod org/apache/dubbo/rpc/cluster/Directory.getUrl:()Lorg/apache/dubbo/common/URL;
     562: invokevirtual #33                 // Method org/apache/dubbo/common/URL.getAddress:()Ljava/lang/String;
     565: invokevirtual #27                 // Method java/lang/StringBuilder.append:(Ljava/lang/String;)Ljava/lang/StringBuilder;
     568: ldc           #43                 // String  on the consumer
     570: invokevirtual #27                 // Method java/lang/StringBuilder.append:(Ljava/lang/String;)Ljava/lang/StringBuilder;
     573: invokestatic  #44                 // Method org/apache/dubbo/common/utils/NetUtils.getLocalHost:()Ljava/lang/String;
     576: invokevirtual #27                 // Method java/lang/StringBuilder.append:(Ljava/lang/String;)Ljava/lang/StringBuilder;
     579: ldc           #45                 // String  using the dubbo version
     581: invokevirtual #27                 // Method java/lang/StringBuilder.append:(Ljava/lang/String;)Ljava/lang/StringBuilder;
     584: invokestatic  #46                 // Method org/apache/dubbo/common/Version.getVersion:()Ljava/lang/String;
     587: invokevirtual #27                 // Method java/lang/StringBuilder.append:(Ljava/lang/String;)Ljava/lang/StringBuilder;
     590: ldc           #47                 // String . Last error is:
     592: invokevirtual #27                 // Method java/lang/StringBuilder.append:(Ljava/lang/String;)Ljava/lang/StringBuilder;
     595: aload         7
     597: invokevirtual #48                 // Method org/apache/dubbo/rpc/RpcException.getMessage:()Ljava/lang/String;
     600: invokevirtual #27                 // Method java/lang/StringBuilder.append:(Ljava/lang/String;)Ljava/lang/StringBuilder;
     603: invokevirtual #49                 // Method java/lang/StringBuilder.toString:()Ljava/lang/String;
     606: aload         7
     608: invokevirtual #61                 // Method org/apache/dubbo/rpc/RpcException.getCause:()Ljava/lang/Throwable;
     611: ifnull        622
     614: aload         7
     616: invokevirtual #61                 // Method org/apache/dubbo/rpc/RpcException.getCause:()Ljava/lang/Throwable;
     619: goto          624
     622: aload         7
     624: invokespecial #62                 // Method org/apache/dubbo/rpc/RpcException."<init>":(ILjava/lang/String;Ljava/lang/Throwable;)V
     627: athrow
    Exception table:
       from    to  target type
         114   310   336   Class org/apache/dubbo/rpc/RpcException
         114   310   379   Class java/lang/Throwable
         114   310   423   any
         336   353   423   any
         379   397   423   any
         423   425   423   any

  private int calculateInvokeTimes(java.lang.String);
    Code:
       0: aload_0
       1: invokevirtual #63                 // Method getUrl:()Lorg/apache/dubbo/common/URL;
       4: aload_1
       5: ldc           #64                 // String retries
       7: iconst_2
       8: invokevirtual #65                 // Method org/apache/dubbo/common/URL.getMethodParameter:(Ljava/lang/String;Ljava/lang/String;I)I
      11: iconst_1
      12: iadd
      13: istore_2
      14: invokestatic  #66                 // Method org/apache/dubbo/rpc/RpcContext.getClientAttachment:()Lorg/apache/dubbo/rpc/RpcContextAttachment;
      17: astore_3
      18: aload_3
      19: ldc           #64                 // String retries
      21: invokevirtual #67                 // Method org/apache/dubbo/rpc/RpcContext.getObjectAttachment:(Ljava/lang/String;)Ljava/lang/Object;
      24: astore        4
      26: aload         4
      28: instanceof    #68                 // class java/lang/Number
      31: ifeq          52
      34: aload         4
      36: checkcast     #68                 // class java/lang/Number
      39: invokevirtual #69                 // Method java/lang/Number.intValue:()I
      42: iconst_1
      43: iadd
      44: istore_2
      45: aload_3
      46: ldc           #64                 // String retries
      48: invokevirtual #70                 // Method org/apache/dubbo/rpc/RpcContext.removeAttachment:(Ljava/lang/String;)Lorg/apache/dubbo/rpc/RpcContext;
      51: pop
      52: iload_2
      53: ifgt          58
      56: iconst_1
      57: istore_2
      58: iload_2
      59: ireturn

  static {};
    Code:
       0: ldc           #71                 // class org/apache/dubbo/rpc/cluster/support/FailoverClusterInvoker
       2: invokestatic  #72                 // Method org/apache/dubbo/common/logger/LoggerFactory.getErrorTypeAwareLogger:(Ljava/lang/Class;)Lorg/apache/dubbo/common/logger/ErrorTypeAwareLogger;
       5: putstatic     #19                 // Field logger:Lorg/apache/dubbo/common/logger/ErrorTypeAwareLogger;
       8: return
}
