Compiled from "FailsafeClusterInvoker.java"
public class org.apache.dubbo.rpc.cluster.support.FailsafeClusterInvoker<T> extends org.apache.dubbo.rpc.cluster.support.AbstractClusterInvoker<T> {
  private static final org.apache.dubbo.common.logger.ErrorTypeAwareLogger logger;

  public org.apache.dubbo.rpc.cluster.support.FailsafeClusterInvoker(org.apache.dubbo.rpc.cluster.Directory<T>);
    Code:
       0: aload_0
       1: aload_1
       2: invokespecial #2                  // Method org/apache/dubbo/rpc/cluster/support/AbstractClusterInvoker."<init>":(Lorg/apache/dubbo/rpc/cluster/Directory;)V
       5: return

  public org.apache.dubbo.rpc.Result doInvoke(org.apache.dubbo.rpc.Invocation, java.util.List<org.apache.dubbo.rpc.Invoker<T>>, org.apache.dubbo.rpc.cluster.LoadBalance) throws org.apache.dubbo.rpc.RpcException;
    Code:
       0: aload_0
       1: aload_3
       2: aload_1
       3: aload_2
       4: aconst_null
       5: invokevirtual #3                  // Method select:(Lorg/apache/dubbo/rpc/cluster/LoadBalance;Lorg/apache/dubbo/rpc/Invocation;Ljava/util/List;Ljava/util/List;)Lorg/apache/dubbo/rpc/Invoker;
       8: astore        4
      10: aload_0
      11: aload         4
      13: aload_1
      14: invokevirtual #4                  // Method invokeWithContext:(Lorg/apache/dubbo/rpc/Invoker;Lorg/apache/dubbo/rpc/Invocation;)Lorg/apache/dubbo/rpc/Result;
      17: areturn
      18: astore        4
      20: getstatic     #6                  // Field logger:Lorg/apache/dubbo/common/logger/ErrorTypeAwareLogger;
      23: ldc           #7                  // String 2-8
      25: ldc           #8                  // String Failsafe for provider exception
      27: ldc           #9                  // String
      29: new           #10                 // class java/lang/StringBuilder
      32: dup
      33: invokespecial #11                 // Method java/lang/StringBuilder."<init>":()V
      36: ldc           #12                 // String Failsafe ignore exception:
      38: invokevirtual #13                 // Method java/lang/StringBuilder.append:(Ljava/lang/String;)Ljava/lang/StringBuilder;
      41: aload         4
      43: invokevirtual #14                 // Method java/lang/Throwable.getMessage:()Ljava/lang/String;
      46: invokevirtual #13                 // Method java/lang/StringBuilder.append:(Ljava/lang/String;)Ljava/lang/StringBuilder;
      49: invokevirtual #15                 // Method java/lang/StringBuilder.toString:()Ljava/lang/String;
      52: aload         4
      54: invokeinterface #16,  6           // InterfaceMethod org/apache/dubbo/common/logger/ErrorTypeAwareLogger.error:(Ljava/lang/String;Ljava/lang/String;Ljava/lang/String;Ljava/lang/String;Ljava/lang/Throwable;)V
      59: aconst_null
      60: aconst_null
      61: aload_1
      62: invokestatic  #17                 // Method org/apache/dubbo/rpc/AsyncRpcResult.newDefaultAsyncResult:(Ljava/lang/Object;Ljava/lang/Throwable;Lorg/apache/dubbo/rpc/Invocation;)Lorg/apache/dubbo/rpc/AsyncRpcResult;
      65: areturn
    Exception table:
       from    to  target type
           0    17    18   Class java/lang/Throwable

  static {};
    Code:
       0: ldc           #18                 // class org/apache/dubbo/rpc/cluster/support/FailsafeClusterInvoker
       2: invokestatic  #19                 // Method org/apache/dubbo/common/logger/LoggerFactory.getErrorTypeAwareLogger:(Ljava/lang/Class;)Lorg/apache/dubbo/common/logger/ErrorTypeAwareLogger;
       5: putstatic     #6                  // Field logger:Lorg/apache/dubbo/common/logger/ErrorTypeAwareLogger;
       8: return
}
