Compiled from "FailbackClusterInvoker.java"
class org.apache.dubbo.rpc.cluster.support.FailbackClusterInvoker$RetryTimerTask implements org.apache.dubbo.common.timer.TimerTask {
  private final org.apache.dubbo.rpc.Invocation invocation;

  private final org.apache.dubbo.rpc.cluster.LoadBalance loadbalance;

  private final java.util.List<org.apache.dubbo.rpc.Invoker<T>> invokers;

  private final long tick;

  private org.apache.dubbo.rpc.Invoker<T> lastInvoker;

  private org.apache.dubbo.common.URL consumerUrl;

  private final int retries;

  private int retriedTimes;

  final org.apache.dubbo.rpc.cluster.support.FailbackClusterInvoker this$0;

  org.apache.dubbo.rpc.cluster.support.FailbackClusterInvoker$RetryTimerTask(org.apache.dubbo.rpc.cluster.LoadBalance, org.apache.dubbo.rpc.Invocation, java.util.List<org.apache.dubbo.rpc.Invoker<T>>, org.apache.dubbo.rpc.Invoker<T>, int, long, org.apache.dubbo.common.URL);
    Code:
       0: aload_0
       1: aload_1
       2: putfield      #2                  // Field this$0:Lorg/apache/dubbo/rpc/cluster/support/FailbackClusterInvoker;
       5: aload_0
       6: invokespecial #3                  // Method java/lang/Object."<init>":()V
       9: aload_0
      10: iconst_0
      11: putfield      #4                  // Field retriedTimes:I
      14: aload_0
      15: aload_2
      16: putfield      #5                  // Field loadbalance:Lorg/apache/dubbo/rpc/cluster/LoadBalance;
      19: aload_0
      20: aload_3
      21: putfield      #6                  // Field invocation:Lorg/apache/dubbo/rpc/Invocation;
      24: aload_0
      25: aload         4
      27: putfield      #7                  // Field invokers:Ljava/util/List;
      30: aload_0
      31: iload         6
      33: putfield      #8                  // Field retries:I
      36: aload_0
      37: lload         7
      39: putfield      #9                  // Field tick:J
      42: aload_0
      43: aload         5
      45: putfield      #10                 // Field lastInvoker:Lorg/apache/dubbo/rpc/Invoker;
      48: aload_0
      49: aload         9
      51: putfield      #11                 // Field consumerUrl:Lorg/apache/dubbo/common/URL;
      54: return

  public void run(org.apache.dubbo.common.timer.Timeout);
    Code:
       0: invokestatic  #12                 // Method org/apache/dubbo/rpc/cluster/support/FailbackClusterInvoker.access$000:()Lorg/apache/dubbo/common/logger/ErrorTypeAwareLogger;
       3: new           #13                 // class java/lang/StringBuilder
       6: dup
       7: invokespecial #14                 // Method java/lang/StringBuilder."<init>":()V
      10: ldc           #15                 // String Attempt to retry to invoke method
      12: invokevirtual #16                 // Method java/lang/StringBuilder.append:(Ljava/lang/String;)Ljava/lang/StringBuilder;
      15: aload_0
      16: getfield      #6                  // Field invocation:Lorg/apache/dubbo/rpc/Invocation;
      19: invokeinterface #17,  1           // InterfaceMethod org/apache/dubbo/rpc/Invocation.getMethodName:()Ljava/lang/String;
      24: invokevirtual #16                 // Method java/lang/StringBuilder.append:(Ljava/lang/String;)Ljava/lang/StringBuilder;
      27: ldc           #18                 // String . The total will retry
      29: invokevirtual #16                 // Method java/lang/StringBuilder.append:(Ljava/lang/String;)Ljava/lang/StringBuilder;
      32: aload_0
      33: getfield      #8                  // Field retries:I
      36: invokevirtual #19                 // Method java/lang/StringBuilder.append:(I)Ljava/lang/StringBuilder;
      39: ldc           #20                 // String  times, the current is the
      41: invokevirtual #16                 // Method java/lang/StringBuilder.append:(Ljava/lang/String;)Ljava/lang/StringBuilder;
      44: aload_0
      45: getfield      #4                  // Field retriedTimes:I
      48: invokevirtual #19                 // Method java/lang/StringBuilder.append:(I)Ljava/lang/StringBuilder;
      51: ldc           #21                 // String  retry
      53: invokevirtual #16                 // Method java/lang/StringBuilder.append:(Ljava/lang/String;)Ljava/lang/StringBuilder;
      56: invokevirtual #22                 // Method java/lang/StringBuilder.toString:()Ljava/lang/String;
      59: invokeinterface #23,  2           // InterfaceMethod org/apache/dubbo/common/logger/ErrorTypeAwareLogger.info:(Ljava/lang/String;)V
      64: aload_0
      65: getfield      #2                  // Field this$0:Lorg/apache/dubbo/rpc/cluster/support/FailbackClusterInvoker;
      68: aload_0
      69: getfield      #5                  // Field loadbalance:Lorg/apache/dubbo/rpc/cluster/LoadBalance;
      72: aload_0
      73: getfield      #6                  // Field invocation:Lorg/apache/dubbo/rpc/Invocation;
      76: aload_0
      77: getfield      #7                  // Field invokers:Ljava/util/List;
      80: aload_0
      81: getfield      #10                 // Field lastInvoker:Lorg/apache/dubbo/rpc/Invoker;
      84: invokestatic  #24                 // Method java/util/Collections.singletonList:(Ljava/lang/Object;)Ljava/util/List;
      87: invokevirtual #25                 // Method org/apache/dubbo/rpc/cluster/support/FailbackClusterInvoker.select:(Lorg/apache/dubbo/rpc/cluster/LoadBalance;Lorg/apache/dubbo/rpc/Invocation;Ljava/util/List;Ljava/util/List;)Lorg/apache/dubbo/rpc/Invoker;
      90: astore_2
      91: aload_0
      92: aload_2
      93: putfield      #10                 // Field lastInvoker:Lorg/apache/dubbo/rpc/Invoker;
      96: aload_0
      97: getfield      #2                  // Field this$0:Lorg/apache/dubbo/rpc/cluster/support/FailbackClusterInvoker;
     100: aload_2
     101: aload_0
     102: getfield      #6                  // Field invocation:Lorg/apache/dubbo/rpc/Invocation;
     105: aload_0
     106: getfield      #11                 // Field consumerUrl:Lorg/apache/dubbo/common/URL;
     109: invokevirtual #26                 // Method org/apache/dubbo/rpc/cluster/support/FailbackClusterInvoker.invokeWithContextAsync:(Lorg/apache/dubbo/rpc/Invoker;Lorg/apache/dubbo/rpc/Invocation;Lorg/apache/dubbo/common/URL;)Lorg/apache/dubbo/rpc/Result;
     112: pop
     113: goto          239
     116: astore_2
     117: invokestatic  #12                 // Method org/apache/dubbo/rpc/cluster/support/FailbackClusterInvoker.access$000:()Lorg/apache/dubbo/common/logger/ErrorTypeAwareLogger;
     120: ldc           #28                 // String 2-10
     122: ldc           #29                 // String Failed retry to invoke method
     124: ldc           #30                 // String
     126: new           #13                 // class java/lang/StringBuilder
     129: dup
     130: invokespecial #14                 // Method java/lang/StringBuilder."<init>":()V
     133: ldc           #31                 // String Failed retry to invoke method
     135: invokevirtual #16                 // Method java/lang/StringBuilder.append:(Ljava/lang/String;)Ljava/lang/StringBuilder;
     138: aload_0
     139: getfield      #6                  // Field invocation:Lorg/apache/dubbo/rpc/Invocation;
     142: invokeinterface #17,  1           // InterfaceMethod org/apache/dubbo/rpc/Invocation.getMethodName:()Ljava/lang/String;
     147: invokevirtual #16                 // Method java/lang/StringBuilder.append:(Ljava/lang/String;)Ljava/lang/StringBuilder;
     150: ldc           #32                 // String , waiting again.
     152: invokevirtual #16                 // Method java/lang/StringBuilder.append:(Ljava/lang/String;)Ljava/lang/StringBuilder;
     155: invokevirtual #22                 // Method java/lang/StringBuilder.toString:()Ljava/lang/String;
     158: aload_2
     159: invokeinterface #33,  6           // InterfaceMethod org/apache/dubbo/common/logger/ErrorTypeAwareLogger.error:(Ljava/lang/String;Ljava/lang/String;Ljava/lang/String;Ljava/lang/String;Ljava/lang/Throwable;)V
     164: aload_0
     165: dup
     166: getfield      #4                  // Field retriedTimes:I
     169: iconst_1
     170: iadd
     171: dup_x1
     172: putfield      #4                  // Field retriedTimes:I
     175: aload_0
     176: getfield      #8                  // Field retries:I
     179: if_icmplt     234
     182: invokestatic  #12                 // Method org/apache/dubbo/rpc/cluster/support/FailbackClusterInvoker.access$000:()Lorg/apache/dubbo/common/logger/ErrorTypeAwareLogger;
     185: ldc           #28                 // String 2-10
     187: ldc           #34                 // String Failed retry to invoke method and retry times exceed threshold
     189: ldc           #30                 // String
     191: new           #13                 // class java/lang/StringBuilder
     194: dup
     195: invokespecial #14                 // Method java/lang/StringBuilder."<init>":()V
     198: ldc           #35                 // String Failed retry times exceed threshold (
     200: invokevirtual #16                 // Method java/lang/StringBuilder.append:(Ljava/lang/String;)Ljava/lang/StringBuilder;
     203: aload_0
     204: getfield      #8                  // Field retries:I
     207: invokevirtual #19                 // Method java/lang/StringBuilder.append:(I)Ljava/lang/StringBuilder;
     210: ldc           #36                 // String ), We have to abandon, invocation->
     212: invokevirtual #16                 // Method java/lang/StringBuilder.append:(Ljava/lang/String;)Ljava/lang/StringBuilder;
     215: aload_0
     216: getfield      #6                  // Field invocation:Lorg/apache/dubbo/rpc/Invocation;
     219: invokevirtual #37                 // Method java/lang/StringBuilder.append:(Ljava/lang/Object;)Ljava/lang/StringBuilder;
     222: invokevirtual #22                 // Method java/lang/StringBuilder.toString:()Ljava/lang/String;
     225: aload_2
     226: invokeinterface #33,  6           // InterfaceMethod org/apache/dubbo/common/logger/ErrorTypeAwareLogger.error:(Ljava/lang/String;Ljava/lang/String;Ljava/lang/String;Ljava/lang/String;Ljava/lang/Throwable;)V
     231: goto          239
     234: aload_0
     235: aload_1
     236: invokespecial #38                 // Method rePut:(Lorg/apache/dubbo/common/timer/Timeout;)V
     239: return
    Exception table:
       from    to  target type
           0   113   116   Class java/lang/Throwable

  private void rePut(org.apache.dubbo.common.timer.Timeout);
    Code:
       0: aload_1
       1: ifnonnull     5
       4: return
       5: aload_1
       6: invokeinterface #39,  1           // InterfaceMethod org/apache/dubbo/common/timer/Timeout.timer:()Lorg/apache/dubbo/common/timer/Timer;
      11: astore_2
      12: aload_2
      13: invokeinterface #40,  1           // InterfaceMethod org/apache/dubbo/common/timer/Timer.isStop:()Z
      18: ifne          30
      21: aload_1
      22: invokeinterface #41,  1           // InterfaceMethod org/apache/dubbo/common/timer/Timeout.isCancelled:()Z
      27: ifeq          31
      30: return
      31: aload_2
      32: aload_1
      33: invokeinterface #42,  1           // InterfaceMethod org/apache/dubbo/common/timer/Timeout.task:()Lorg/apache/dubbo/common/timer/TimerTask;
      38: aload_0
      39: getfield      #9                  // Field tick:J
      42: getstatic     #43                 // Field java/util/concurrent/TimeUnit.SECONDS:Ljava/util/concurrent/TimeUnit;
      45: invokeinterface #44,  5           // InterfaceMethod org/apache/dubbo/common/timer/Timer.newTimeout:(Lorg/apache/dubbo/common/timer/TimerTask;JLjava/util/concurrent/TimeUnit;)Lorg/apache/dubbo/common/timer/Timeout;
      50: pop
      51: return
}
