Compiled from "ForkingClusterInvoker.java"
public class org.apache.dubbo.rpc.cluster.support.ForkingClusterInvoker<T> extends org.apache.dubbo.rpc.cluster.support.AbstractClusterInvoker<T> {
  private final java.util.concurrent.ExecutorService executor;

  public org.apache.dubbo.rpc.cluster.support.ForkingClusterInvoker(org.apache.dubbo.rpc.cluster.Directory<T>);
    Code:
       0: aload_0
       1: aload_1
       2: invokespecial #3                  // Method org/apache/dubbo/rpc/cluster/support/AbstractClusterInvoker."<init>":(Lorg/apache/dubbo/rpc/cluster/Directory;)V
       5: aload_0
       6: aload_1
       7: invokeinterface #4,  1            // InterfaceMethod org/apache/dubbo/rpc/cluster/Directory.getUrl:()Lorg/apache/dubbo/common/URL;
      12: invokevirtual #5                  // Method org/apache/dubbo/common/URL.getOrDefaultFrameworkModel:()Lorg/apache/dubbo/rpc/model/FrameworkModel;
      15: invokevirtual #6                  // Method org/apache/dubbo/rpc/model/FrameworkModel.getBeanFactory:()Lorg/apache/dubbo/common/beans/factory/ScopeBeanFactory;
      18: ldc           #7                  // class org/apache/dubbo/common/threadpool/manager/FrameworkExecutorRepository
      20: invokevirtual #8                  // Method org/apache/dubbo/common/beans/factory/ScopeBeanFactory.getBean:(Ljava/lang/Class;)Ljava/lang/Object;
      23: checkcast     #7                  // class org/apache/dubbo/common/threadpool/manager/FrameworkExecutorRepository
      26: invokevirtual #9                  // Method org/apache/dubbo/common/threadpool/manager/FrameworkExecutorRepository.getSharedExecutor:()Ljava/util/concurrent/ExecutorService;
      29: putfield      #10                 // Field executor:Ljava/util/concurrent/ExecutorService;
      32: return

  public org.apache.dubbo.rpc.Result doInvoke(org.apache.dubbo.rpc.Invocation, java.util.List<org.apache.dubbo.rpc.Invoker<T>>, org.apache.dubbo.rpc.cluster.LoadBalance) throws org.apache.dubbo.rpc.RpcException;
    Code:
       0: aload_0
       1: invokevirtual #11                 // Method getUrl:()Lorg/apache/dubbo/common/URL;
       4: ldc           #12                 // String forks
       6: iconst_2
       7: invokevirtual #13                 // Method org/apache/dubbo/common/URL.getParameter:(Ljava/lang/String;I)I
      10: istore        5
      12: aload_0
      13: invokevirtual #11                 // Method getUrl:()Lorg/apache/dubbo/common/URL;
      16: ldc           #14                 // String timeout
      18: sipush        1000
      21: invokevirtual #13                 // Method org/apache/dubbo/common/URL.getParameter:(Ljava/lang/String;I)I
      24: istore        6
      26: iload         5
      28: ifle          42
      31: iload         5
      33: aload_2
      34: invokeinterface #15,  1           // InterfaceMethod java/util/List.size:()I
      39: if_icmplt     48
      42: aload_2
      43: astore        4
      45: goto          107
      48: new           #16                 // class java/util/ArrayList
      51: dup
      52: iload         5
      54: invokespecial #17                 // Method java/util/ArrayList."<init>":(I)V
      57: astore        4
      59: aload         4
      61: invokeinterface #15,  1           // InterfaceMethod java/util/List.size:()I
      66: iload         5
      68: if_icmpge     107
      71: aload_0
      72: aload_3
      73: aload_1
      74: aload_2
      75: aload         4
      77: invokevirtual #18                 // Method select:(Lorg/apache/dubbo/rpc/cluster/LoadBalance;Lorg/apache/dubbo/rpc/Invocation;Ljava/util/List;Ljava/util/List;)Lorg/apache/dubbo/rpc/Invoker;
      80: astore        7
      82: aload         4
      84: aload         7
      86: invokeinterface #19,  2           // InterfaceMethod java/util/List.contains:(Ljava/lang/Object;)Z
      91: ifne          104
      94: aload         4
      96: aload         7
      98: invokeinterface #20,  2           // InterfaceMethod java/util/List.add:(Ljava/lang/Object;)Z
     103: pop
     104: goto          59
     107: invokestatic  #21                 // Method org/apache/dubbo/rpc/RpcContext.getServiceContext:()Lorg/apache/dubbo/rpc/RpcServiceContext;
     110: aload         4
     112: invokevirtual #22                 // Method org/apache/dubbo/rpc/RpcServiceContext.setInvokers:(Ljava/util/List;)Lorg/apache/dubbo/rpc/RpcServiceContext;
     115: pop
     116: new           #23                 // class java/util/concurrent/atomic/AtomicInteger
     119: dup
     120: invokespecial #24                 // Method java/util/concurrent/atomic/AtomicInteger."<init>":()V
     123: astore        7
     125: new           #25                 // class java/util/concurrent/LinkedBlockingQueue
     128: dup
     129: iconst_1
     130: invokespecial #26                 // Method java/util/concurrent/LinkedBlockingQueue."<init>":(I)V
     133: astore        8
     135: aload         4
     137: aload_0
     138: aload         8
     140: aload_1
     141: aload         7
     143: aload         4
     145: invokedynamic #27,  0             // InvokeDynamic #0:accept:(Lorg/apache/dubbo/rpc/cluster/support/ForkingClusterInvoker;Ljava/util/concurrent/BlockingQueue;Lorg/apache/dubbo/rpc/Invocation;Ljava/util/concurrent/atomic/AtomicInteger;Ljava/util/List;)Ljava/util/function/Consumer;
     150: invokeinterface #28,  2           // InterfaceMethod java/util/List.forEach:(Ljava/util/function/Consumer;)V
     155: aload         8
     157: iload         6
     159: i2l
     160: getstatic     #29                 // Field java/util/concurrent/TimeUnit.MILLISECONDS:Ljava/util/concurrent/TimeUnit;
     163: invokeinterface #30,  4           // InterfaceMethod java/util/concurrent/BlockingQueue.poll:(JLjava/util/concurrent/TimeUnit;)Ljava/lang/Object;
     168: astore        9
     170: aload         9
     172: instanceof    #31                 // class java/lang/Throwable
     175: ifeq          283
     178: aload         9
     180: instanceof    #32                 // class java/util/concurrent/CompletionException
     183: ifeq          197
     186: aload         9
     188: checkcast     #32                 // class java/util/concurrent/CompletionException
     191: invokevirtual #33                 // Method java/util/concurrent/CompletionException.getCause:()Ljava/lang/Throwable;
     194: goto          202
     197: aload         9
     199: checkcast     #31                 // class java/lang/Throwable
     202: astore        10
     204: new           #34                 // class org/apache/dubbo/rpc/RpcException
     207: dup
     208: aload         10
     210: instanceof    #34                 // class org/apache/dubbo/rpc/RpcException
     213: ifeq          227
     216: aload         10
     218: checkcast     #34                 // class org/apache/dubbo/rpc/RpcException
     221: invokevirtual #35                 // Method org/apache/dubbo/rpc/RpcException.getCode:()I
     224: goto          228
     227: iconst_0
     228: new           #36                 // class java/lang/StringBuilder
     231: dup
     232: invokespecial #37                 // Method java/lang/StringBuilder."<init>":()V
     235: ldc           #38                 // String Failed to forking invoke provider
     237: invokevirtual #39                 // Method java/lang/StringBuilder.append:(Ljava/lang/String;)Ljava/lang/StringBuilder;
     240: aload         4
     242: invokevirtual #40                 // Method java/lang/StringBuilder.append:(Ljava/lang/Object;)Ljava/lang/StringBuilder;
     245: ldc           #41                 // String , but no luck to perform the invocation. Last error is:
     247: invokevirtual #39                 // Method java/lang/StringBuilder.append:(Ljava/lang/String;)Ljava/lang/StringBuilder;
     250: aload         10
     252: invokevirtual #42                 // Method java/lang/Throwable.getMessage:()Ljava/lang/String;
     255: invokevirtual #39                 // Method java/lang/StringBuilder.append:(Ljava/lang/String;)Ljava/lang/StringBuilder;
     258: invokevirtual #43                 // Method java/lang/StringBuilder.toString:()Ljava/lang/String;
     261: aload         10
     263: invokevirtual #44                 // Method java/lang/Throwable.getCause:()Ljava/lang/Throwable;
     266: ifnull        277
     269: aload         10
     271: invokevirtual #44                 // Method java/lang/Throwable.getCause:()Ljava/lang/Throwable;
     274: goto          279
     277: aload         10
     279: invokespecial #45                 // Method org/apache/dubbo/rpc/RpcException."<init>":(ILjava/lang/String;Ljava/lang/Throwable;)V
     282: athrow
     283: aload         9
     285: checkcast     #46                 // class org/apache/dubbo/rpc/Result
     288: astore        10
     290: invokestatic  #47                 // Method org/apache/dubbo/rpc/RpcContext.getClientAttachment:()Lorg/apache/dubbo/rpc/RpcContextAttachment;
     293: invokevirtual #48                 // Method org/apache/dubbo/rpc/RpcContextAttachment.clearAttachments:()V
     296: aload         10
     298: areturn
     299: astore        9
     301: new           #34                 // class org/apache/dubbo/rpc/RpcException
     304: dup
     305: new           #36                 // class java/lang/StringBuilder
     308: dup
     309: invokespecial #37                 // Method java/lang/StringBuilder."<init>":()V
     312: ldc           #38                 // String Failed to forking invoke provider
     314: invokevirtual #39                 // Method java/lang/StringBuilder.append:(Ljava/lang/String;)Ljava/lang/StringBuilder;
     317: aload         4
     319: invokevirtual #40                 // Method java/lang/StringBuilder.append:(Ljava/lang/Object;)Ljava/lang/StringBuilder;
     322: ldc           #41                 // String , but no luck to perform the invocation. Last error is:
     324: invokevirtual #39                 // Method java/lang/StringBuilder.append:(Ljava/lang/String;)Ljava/lang/StringBuilder;
     327: aload         9
     329: invokevirtual #50                 // Method java/lang/InterruptedException.getMessage:()Ljava/lang/String;
     332: invokevirtual #39                 // Method java/lang/StringBuilder.append:(Ljava/lang/String;)Ljava/lang/StringBuilder;
     335: invokevirtual #43                 // Method java/lang/StringBuilder.toString:()Ljava/lang/String;
     338: aload         9
     340: invokespecial #51                 // Method org/apache/dubbo/rpc/RpcException."<init>":(Ljava/lang/String;Ljava/lang/Throwable;)V
     343: athrow
     344: astore        11
     346: invokestatic  #47                 // Method org/apache/dubbo/rpc/RpcContext.getClientAttachment:()Lorg/apache/dubbo/rpc/RpcContextAttachment;
     349: invokevirtual #48                 // Method org/apache/dubbo/rpc/RpcContextAttachment.clearAttachments:()V
     352: aload         11
     354: athrow
    Exception table:
       from    to  target type
         155   290   299   Class java/lang/InterruptedException
           0   290   344   any
         299   346   344   any

  private void lambda$doInvoke$2(java.util.concurrent.BlockingQueue, org.apache.dubbo.rpc.Invocation, java.util.concurrent.atomic.AtomicInteger, java.util.List, org.apache.dubbo.rpc.Invoker);
    Code:
       0: invokestatic  #21                 // Method org/apache/dubbo/rpc/RpcContext.getServiceContext:()Lorg/apache/dubbo/rpc/RpcServiceContext;
       3: invokevirtual #52                 // Method org/apache/dubbo/rpc/RpcServiceContext.getConsumerUrl:()Lorg/apache/dubbo/common/URL;
       6: astore        6
       8: aload_0
       9: aload_1
      10: aload         5
      12: aload_2
      13: aload         6
      15: invokedynamic #53,  0             // InvokeDynamic #1:get:(Lorg/apache/dubbo/rpc/cluster/support/ForkingClusterInvoker;Ljava/util/concurrent/BlockingQueue;Lorg/apache/dubbo/rpc/Invoker;Lorg/apache/dubbo/rpc/Invocation;Lorg/apache/dubbo/common/URL;)Ljava/util/function/Supplier;
      20: aload_0
      21: getfield      #10                 // Field executor:Ljava/util/concurrent/ExecutorService;
      24: invokestatic  #54                 // Method java/util/concurrent/CompletableFuture.supplyAsync:(Ljava/util/function/Supplier;Ljava/util/concurrent/Executor;)Ljava/util/concurrent/CompletableFuture;
      27: aload_1
      28: aload_3
      29: aload         4
      31: invokedynamic #55,  0             // InvokeDynamic #2:accept:(Ljava/util/concurrent/BlockingQueue;Ljava/util/concurrent/atomic/AtomicInteger;Ljava/util/List;)Ljava/util/function/BiConsumer;
      36: invokevirtual #56                 // Method java/util/concurrent/CompletableFuture.whenComplete:(Ljava/util/function/BiConsumer;)Ljava/util/concurrent/CompletableFuture;
      39: pop
      40: return

  private static void lambda$null$1(java.util.concurrent.BlockingQueue, java.util.concurrent.atomic.AtomicInteger, java.util.List, java.lang.Object, java.lang.Throwable);
    Code:
       0: aload         4
       2: ifnonnull     16
       5: aload_0
       6: aload_3
       7: invokeinterface #57,  2           // InterfaceMethod java/util/concurrent/BlockingQueue.offer:(Ljava/lang/Object;)Z
      12: pop
      13: goto          42
      16: aload_1
      17: invokevirtual #58                 // Method java/util/concurrent/atomic/AtomicInteger.incrementAndGet:()I
      20: istore        5
      22: iload         5
      24: aload_2
      25: invokeinterface #15,  1           // InterfaceMethod java/util/List.size:()I
      30: if_icmplt     42
      33: aload_0
      34: aload         4
      36: invokeinterface #57,  2           // InterfaceMethod java/util/concurrent/BlockingQueue.offer:(Ljava/lang/Object;)Z
      41: pop
      42: return

  private java.lang.Object lambda$null$0(java.util.concurrent.BlockingQueue, org.apache.dubbo.rpc.Invoker, org.apache.dubbo.rpc.Invocation, org.apache.dubbo.common.URL);
    Code:
       0: aload_1
       1: invokeinterface #59,  1           // InterfaceMethod java/util/concurrent/BlockingQueue.size:()I
       6: ifle          11
       9: aconst_null
      10: areturn
      11: aload_0
      12: aload_2
      13: aload_3
      14: aload         4
      16: invokevirtual #60                 // Method invokeWithContextAsync:(Lorg/apache/dubbo/rpc/Invoker;Lorg/apache/dubbo/rpc/Invocation;Lorg/apache/dubbo/common/URL;)Lorg/apache/dubbo/rpc/Result;
      19: areturn
}
