Compiled from "AbstractStateRouter.java"
public abstract class org.apache.dubbo.rpc.cluster.router.state.AbstractStateRouter<T> implements org.apache.dubbo.rpc.cluster.router.state.StateRouter<T> {
  private volatile boolean force;

  private volatile org.apache.dubbo.common.URL url;

  private volatile org.apache.dubbo.rpc.cluster.router.state.StateRouter<T> nextRouter;

  private final org.apache.dubbo.rpc.cluster.governance.GovernanceRuleRepository ruleRepository;

  private final boolean shouldFailFast;

  protected org.apache.dubbo.rpc.model.ModuleModel moduleModel;

  public org.apache.dubbo.rpc.cluster.router.state.AbstractStateRouter(org.apache.dubbo.common.URL);
    Code:
       0: aload_0
       1: invokespecial #1                  // Method java/lang/Object."<init>":()V
       4: aload_0
       5: iconst_0
       6: putfield      #2                  // Field force:Z
       9: aload_0
      10: aconst_null
      11: putfield      #3                  // Field nextRouter:Lorg/apache/dubbo/rpc/cluster/router/state/StateRouter;
      14: aload_0
      15: aload_1
      16: invokevirtual #4                  // Method org/apache/dubbo/common/URL.getOrDefaultModuleModel:()Lorg/apache/dubbo/rpc/model/ModuleModel;
      19: putfield      #5                  // Field moduleModel:Lorg/apache/dubbo/rpc/model/ModuleModel;
      22: aload_0
      23: aload_0
      24: getfield      #5                  // Field moduleModel:Lorg/apache/dubbo/rpc/model/ModuleModel;
      27: ldc           #6                  // class org/apache/dubbo/rpc/cluster/governance/GovernanceRuleRepository
      29: invokevirtual #7                  // Method org/apache/dubbo/rpc/model/ModuleModel.getExtensionLoader:(Ljava/lang/Class;)Lorg/apache/dubbo/common/extension/ExtensionLoader;
      32: invokevirtual #8                  // Method org/apache/dubbo/common/extension/ExtensionLoader.getDefaultExtension:()Ljava/lang/Object;
      35: checkcast     #6                  // class org/apache/dubbo/rpc/cluster/governance/GovernanceRuleRepository
      38: putfield      #9                  // Field ruleRepository:Lorg/apache/dubbo/rpc/cluster/governance/GovernanceRuleRepository;
      41: aload_0
      42: aload_1
      43: putfield      #10                 // Field url:Lorg/apache/dubbo/common/URL;
      46: aload_0
      47: aload_0
      48: getfield      #5                  // Field moduleModel:Lorg/apache/dubbo/rpc/model/ModuleModel;
      51: ldc           #12                 // String dubbo.router.should-fail-fast
      53: ldc           #13                 // String true
      55: invokestatic  #14                 // Method org/apache/dubbo/common/config/ConfigurationUtils.getProperty:(Lorg/apache/dubbo/rpc/model/ScopeModel;Ljava/lang/String;Ljava/lang/String;)Ljava/lang/String;
      58: invokestatic  #15                 // Method java/lang/Boolean.parseBoolean:(Ljava/lang/String;)Z
      61: putfield      #16                 // Field shouldFailFast:Z
      64: return

  public org.apache.dubbo.common.URL getUrl();
    Code:
       0: aload_0
       1: getfield      #10                 // Field url:Lorg/apache/dubbo/common/URL;
       4: areturn

  public void setUrl(org.apache.dubbo.common.URL);
    Code:
       0: aload_0
       1: aload_1
       2: putfield      #10                 // Field url:Lorg/apache/dubbo/common/URL;
       5: return

  public boolean isRuntime();
    Code:
       0: iconst_1
       1: ireturn

  public boolean isForce();
    Code:
       0: aload_0
       1: getfield      #2                  // Field force:Z
       4: ireturn

  public void setForce(boolean);
    Code:
       0: aload_0
       1: iload_1
       2: putfield      #2                  // Field force:Z
       5: return

  public org.apache.dubbo.rpc.cluster.governance.GovernanceRuleRepository getRuleRepository();
    Code:
       0: aload_0
       1: getfield      #9                  // Field ruleRepository:Lorg/apache/dubbo/rpc/cluster/governance/GovernanceRuleRepository;
       4: areturn

  public org.apache.dubbo.rpc.cluster.router.state.StateRouter<T> getNextRouter();
    Code:
       0: aload_0
       1: getfield      #3                  // Field nextRouter:Lorg/apache/dubbo/rpc/cluster/router/state/StateRouter;
       4: areturn

  public void notify(org.apache.dubbo.rpc.cluster.router.state.BitList<org.apache.dubbo.rpc.Invoker<T>>);
    Code:
       0: return

  public final org.apache.dubbo.rpc.cluster.router.state.BitList<org.apache.dubbo.rpc.Invoker<T>> route(org.apache.dubbo.rpc.cluster.router.state.BitList<org.apache.dubbo.rpc.Invoker<T>>, org.apache.dubbo.common.URL, org.apache.dubbo.rpc.Invocation, boolean, org.apache.dubbo.common.utils.Holder<org.apache.dubbo.rpc.cluster.router.RouterSnapshotNode<T>>) throws org.apache.dubbo.rpc.RpcException;
    Code:
       0: iload         4
       2: ifeq          21
       5: aload         5
       7: ifnull        18
      10: aload         5
      12: invokevirtual #17                 // Method org/apache/dubbo/common/utils/Holder.get:()Ljava/lang/Object;
      15: ifnonnull     21
      18: iconst_0
      19: istore        4
      21: aconst_null
      22: astore        6
      24: aconst_null
      25: astore        7
      27: aconst_null
      28: astore        8
      30: iload         4
      32: ifeq          109
      35: aload         5
      37: invokevirtual #17                 // Method org/apache/dubbo/common/utils/Holder.get:()Ljava/lang/Object;
      40: checkcast     #18                 // class org/apache/dubbo/rpc/cluster/router/RouterSnapshotNode
      43: astore        7
      45: new           #18                 // class org/apache/dubbo/rpc/cluster/router/RouterSnapshotNode
      48: dup
      49: aload_0
      50: invokevirtual #19                 // Method java/lang/Object.getClass:()Ljava/lang/Class;
      53: invokevirtual #20                 // Method java/lang/Class.getSimpleName:()Ljava/lang/String;
      56: aload_1
      57: invokevirtual #21                 // Method org/apache/dubbo/rpc/cluster/router/state/BitList.clone:()Lorg/apache/dubbo/rpc/cluster/router/state/BitList;
      60: invokespecial #22                 // Method org/apache/dubbo/rpc/cluster/router/RouterSnapshotNode."<init>":(Ljava/lang/String;Ljava/util/List;)V
      63: astore        6
      65: aload         7
      67: aload         6
      69: invokevirtual #23                 // Method org/apache/dubbo/rpc/cluster/router/RouterSnapshotNode.appendNode:(Lorg/apache/dubbo/rpc/cluster/router/RouterSnapshotNode;)V
      72: aload         7
      74: invokevirtual #24                 // Method org/apache/dubbo/rpc/cluster/router/RouterSnapshotNode.getNodeOutputSize:()I
      77: aload_1
      78: invokevirtual #25                 // Method org/apache/dubbo/rpc/cluster/router/state/BitList.size:()I
      81: if_icmpge     93
      84: aload         7
      86: aload_1
      87: invokevirtual #21                 // Method org/apache/dubbo/rpc/cluster/router/state/BitList.clone:()Lorg/apache/dubbo/rpc/cluster/router/state/BitList;
      90: invokevirtual #26                 // Method org/apache/dubbo/rpc/cluster/router/RouterSnapshotNode.setNodeOutputInvokers:(Ljava/util/List;)V
      93: new           #27                 // class org/apache/dubbo/common/utils/Holder
      96: dup
      97: invokespecial #28                 // Method org/apache/dubbo/common/utils/Holder."<init>":()V
     100: astore        8
     102: aload         5
     104: aload         6
     106: invokevirtual #29                 // Method org/apache/dubbo/common/utils/Holder.set:(Ljava/lang/Object;)V
     109: aload_0
     110: aload_1
     111: aload_2
     112: aload_3
     113: iload         4
     115: aload         5
     117: aload         8
     119: invokevirtual #30                 // Method doRoute:(Lorg/apache/dubbo/rpc/cluster/router/state/BitList;Lorg/apache/dubbo/common/URL;Lorg/apache/dubbo/rpc/Invocation;ZLorg/apache/dubbo/common/utils/Holder;Lorg/apache/dubbo/common/utils/Holder;)Lorg/apache/dubbo/rpc/cluster/router/state/BitList;
     122: astore        9
     124: aload         9
     126: aload_1
     127: if_acmpeq     138
     130: aload_1
     131: aload         9
     133: invokevirtual #31                 // Method org/apache/dubbo/rpc/cluster/router/state/BitList.and:(Lorg/apache/dubbo/rpc/cluster/router/state/BitList;)Lorg/apache/dubbo/rpc/cluster/router/state/BitList;
     136: astore        9
     138: aload_0
     139: invokevirtual #32                 // Method supportContinueRoute:()Z
     142: ifne          174
     145: aload_0
     146: getfield      #16                 // Field shouldFailFast:Z
     149: ifeq          160
     152: aload         9
     154: invokevirtual #33                 // Method org/apache/dubbo/rpc/cluster/router/state/BitList.isEmpty:()Z
     157: ifne          174
     160: aload_0
     161: aload         9
     163: aload_2
     164: aload_3
     165: iload         4
     167: aload         5
     169: invokevirtual #34                 // Method continueRoute:(Lorg/apache/dubbo/rpc/cluster/router/state/BitList;Lorg/apache/dubbo/common/URL;Lorg/apache/dubbo/rpc/Invocation;ZLorg/apache/dubbo/common/utils/Holder;)Lorg/apache/dubbo/rpc/cluster/router/state/BitList;
     172: astore        9
     174: iload         4
     176: ifeq          227
     179: aload         6
     181: aload         8
     183: invokevirtual #17                 // Method org/apache/dubbo/common/utils/Holder.get:()Ljava/lang/Object;
     186: checkcast     #35                 // class java/lang/String
     189: invokevirtual #36                 // Method org/apache/dubbo/rpc/cluster/router/RouterSnapshotNode.setRouterMessage:(Ljava/lang/String;)V
     192: aload         6
     194: invokevirtual #24                 // Method org/apache/dubbo/rpc/cluster/router/RouterSnapshotNode.getNodeOutputSize:()I
     197: ifne          210
     200: aload         6
     202: aload         9
     204: invokevirtual #21                 // Method org/apache/dubbo/rpc/cluster/router/state/BitList.clone:()Lorg/apache/dubbo/rpc/cluster/router/state/BitList;
     207: invokevirtual #26                 // Method org/apache/dubbo/rpc/cluster/router/RouterSnapshotNode.setNodeOutputInvokers:(Ljava/util/List;)V
     210: aload         6
     212: aload         9
     214: invokevirtual #21                 // Method org/apache/dubbo/rpc/cluster/router/state/BitList.clone:()Lorg/apache/dubbo/rpc/cluster/router/state/BitList;
     217: invokevirtual #37                 // Method org/apache/dubbo/rpc/cluster/router/RouterSnapshotNode.setChainOutputInvokers:(Ljava/util/List;)V
     220: aload         5
     222: aload         7
     224: invokevirtual #29                 // Method org/apache/dubbo/common/utils/Holder.set:(Ljava/lang/Object;)V
     227: aload         9
     229: areturn

  protected abstract org.apache.dubbo.rpc.cluster.router.state.BitList<org.apache.dubbo.rpc.Invoker<T>> doRoute(org.apache.dubbo.rpc.cluster.router.state.BitList<org.apache.dubbo.rpc.Invoker<T>>, org.apache.dubbo.common.URL, org.apache.dubbo.rpc.Invocation, boolean, org.apache.dubbo.common.utils.Holder<org.apache.dubbo.rpc.cluster.router.RouterSnapshotNode<T>>, org.apache.dubbo.common.utils.Holder<java.lang.String>) throws org.apache.dubbo.rpc.RpcException;

  protected final org.apache.dubbo.rpc.cluster.router.state.BitList<org.apache.dubbo.rpc.Invoker<T>> continueRoute(org.apache.dubbo.rpc.cluster.router.state.BitList<org.apache.dubbo.rpc.Invoker<T>>, org.apache.dubbo.common.URL, org.apache.dubbo.rpc.Invocation, boolean, org.apache.dubbo.common.utils.Holder<org.apache.dubbo.rpc.cluster.router.RouterSnapshotNode<T>>);
    Code:
       0: aload_0
       1: getfield      #3                  // Field nextRouter:Lorg/apache/dubbo/rpc/cluster/router/state/StateRouter;
       4: ifnull        24
       7: aload_0
       8: getfield      #3                  // Field nextRouter:Lorg/apache/dubbo/rpc/cluster/router/state/StateRouter;
      11: aload_1
      12: aload_2
      13: aload_3
      14: iload         4
      16: aload         5
      18: invokeinterface #38,  6           // InterfaceMethod org/apache/dubbo/rpc/cluster/router/state/StateRouter.route:(Lorg/apache/dubbo/rpc/cluster/router/state/BitList;Lorg/apache/dubbo/common/URL;Lorg/apache/dubbo/rpc/Invocation;ZLorg/apache/dubbo/common/utils/Holder;)Lorg/apache/dubbo/rpc/cluster/router/state/BitList;
      23: areturn
      24: aload_1
      25: areturn

  protected boolean supportContinueRoute();
    Code:
       0: iconst_0
       1: ireturn

  public final void setNextRouter(org.apache.dubbo.rpc.cluster.router.state.StateRouter<T>);
    Code:
       0: aload_0
       1: aload_1
       2: putfield      #3                  // Field nextRouter:Lorg/apache/dubbo/rpc/cluster/router/state/StateRouter;
       5: return

  public final java.lang.String buildSnapshot();
    Code:
       0: new           #39                 // class java/lang/StringBuilder
       3: dup
       4: invokespecial #40                 // Method java/lang/StringBuilder."<init>":()V
       7: aload_0
       8: invokevirtual #41                 // Method doBuildSnapshot:()Ljava/lang/String;
      11: invokevirtual #42                 // Method java/lang/StringBuilder.append:(Ljava/lang/String;)Ljava/lang/StringBuilder;
      14: ldc           #43                 // String             v \n
      16: invokevirtual #42                 // Method java/lang/StringBuilder.append:(Ljava/lang/String;)Ljava/lang/StringBuilder;
      19: aload_0
      20: getfield      #3                  // Field nextRouter:Lorg/apache/dubbo/rpc/cluster/router/state/StateRouter;
      23: invokeinterface #44,  1           // InterfaceMethod org/apache/dubbo/rpc/cluster/router/state/StateRouter.buildSnapshot:()Ljava/lang/String;
      28: invokevirtual #42                 // Method java/lang/StringBuilder.append:(Ljava/lang/String;)Ljava/lang/StringBuilder;
      31: invokevirtual #45                 // Method java/lang/StringBuilder.toString:()Ljava/lang/String;
      34: areturn

  protected java.lang.String doBuildSnapshot();
    Code:
       0: new           #39                 // class java/lang/StringBuilder
       3: dup
       4: invokespecial #40                 // Method java/lang/StringBuilder."<init>":()V
       7: aload_0
       8: invokevirtual #19                 // Method java/lang/Object.getClass:()Ljava/lang/Class;
      11: invokevirtual #20                 // Method java/lang/Class.getSimpleName:()Ljava/lang/String;
      14: invokevirtual #42                 // Method java/lang/StringBuilder.append:(Ljava/lang/String;)Ljava/lang/StringBuilder;
      17: ldc           #46                 // String  not support\n
      19: invokevirtual #42                 // Method java/lang/StringBuilder.append:(Ljava/lang/String;)Ljava/lang/StringBuilder;
      22: invokevirtual #45                 // Method java/lang/StringBuilder.toString:()Ljava/lang/String;
      25: areturn
}
