Compiled from "BitList.java"
public class org.apache.dubbo.rpc.cluster.router.state.BitList$BitListIterator<E> implements java.util.ListIterator<E> {
  private org.apache.dubbo.rpc.cluster.router.state.BitList<E> bitList;

  private int index;

  private java.util.ListIterator<E> tailListIterator;

  private int curBitIndex;

  private boolean isInTailList;

  private int lastReturnedIndex;

  public org.apache.dubbo.rpc.cluster.router.state.BitList$BitListIterator(org.apache.dubbo.rpc.cluster.router.state.BitList<E>, int);
    Code:
       0: aload_0
       1: invokespecial #1                  // Method java/lang/Object."<init>":()V
       4: aload_0
       5: iconst_m1
       6: putfield      #2                  // Field curBitIndex:I
       9: aload_0
      10: iconst_0
      11: putfield      #3                  // Field isInTailList:Z
      14: aload_0
      15: iconst_m1
      16: putfield      #4                  // Field lastReturnedIndex:I
      19: aload_0
      20: aload_1
      21: putfield      #5                  // Field bitList:Lorg/apache/dubbo/rpc/cluster/router/state/BitList;
      24: aload_0
      25: iload_2
      26: iconst_1
      27: isub
      28: putfield      #6                  // Field index:I
      31: iconst_0
      32: istore_3
      33: iload_3
      34: iload_2
      35: if_icmpge     127
      38: aload_0
      39: getfield      #3                  // Field isInTailList:Z
      42: ifne          111
      45: aload_0
      46: aload_1
      47: invokestatic  #7                  // Method org/apache/dubbo/rpc/cluster/router/state/BitList.access$000:(Lorg/apache/dubbo/rpc/cluster/router/state/BitList;)Ljava/util/BitSet;
      50: aload_0
      51: getfield      #2                  // Field curBitIndex:I
      54: iconst_1
      55: iadd
      56: invokevirtual #8                  // Method java/util/BitSet.nextSetBit:(I)I
      59: putfield      #2                  // Field curBitIndex:I
      62: aload_0
      63: getfield      #2                  // Field curBitIndex:I
      66: iconst_m1
      67: if_icmpne     121
      70: aload_1
      71: invokestatic  #9                  // Method org/apache/dubbo/rpc/cluster/router/state/BitList.access$100:(Lorg/apache/dubbo/rpc/cluster/router/state/BitList;)Ljava/util/List;
      74: invokestatic  #10                 // Method org/apache/dubbo/common/utils/CollectionUtils.isNotEmpty:(Ljava/util/Collection;)Z
      77: ifeq          127
      80: aload_0
      81: iconst_1
      82: putfield      #3                  // Field isInTailList:Z
      85: aload_0
      86: aload_1
      87: invokestatic  #9                  // Method org/apache/dubbo/rpc/cluster/router/state/BitList.access$100:(Lorg/apache/dubbo/rpc/cluster/router/state/BitList;)Ljava/util/List;
      90: invokeinterface #11,  1           // InterfaceMethod java/util/List.listIterator:()Ljava/util/ListIterator;
      95: putfield      #12                 // Field tailListIterator:Ljava/util/ListIterator;
      98: aload_0
      99: getfield      #12                 // Field tailListIterator:Ljava/util/ListIterator;
     102: invokeinterface #13,  1           // InterfaceMethod java/util/ListIterator.next:()Ljava/lang/Object;
     107: pop
     108: goto          121
     111: aload_0
     112: getfield      #12                 // Field tailListIterator:Ljava/util/ListIterator;
     115: invokeinterface #13,  1           // InterfaceMethod java/util/ListIterator.next:()Ljava/lang/Object;
     120: pop
     121: iinc          3, 1
     124: goto          33
     127: return

  public boolean hasNext();
    Code:
       0: aload_0
       1: getfield      #3                  // Field isInTailList:Z
       4: ifeq          17
       7: aload_0
       8: getfield      #12                 // Field tailListIterator:Ljava/util/ListIterator;
      11: invokeinterface #14,  1           // InterfaceMethod java/util/ListIterator.hasNext:()Z
      16: ireturn
      17: aload_0
      18: getfield      #5                  // Field bitList:Lorg/apache/dubbo/rpc/cluster/router/state/BitList;
      21: invokestatic  #7                  // Method org/apache/dubbo/rpc/cluster/router/state/BitList.access$000:(Lorg/apache/dubbo/rpc/cluster/router/state/BitList;)Ljava/util/BitSet;
      24: aload_0
      25: getfield      #2                  // Field curBitIndex:I
      28: iconst_1
      29: iadd
      30: invokevirtual #8                  // Method java/util/BitSet.nextSetBit:(I)I
      33: istore_1
      34: iload_1
      35: iconst_m1
      36: if_icmpne     47
      39: aload_0
      40: getfield      #5                  // Field bitList:Lorg/apache/dubbo/rpc/cluster/router/state/BitList;
      43: invokevirtual #15                 // Method org/apache/dubbo/rpc/cluster/router/state/BitList.hasMoreElementInTailList:()Z
      46: ireturn
      47: iconst_1
      48: ireturn

  public E next();
    Code:
       0: aload_0
       1: getfield      #3                  // Field isInTailList:Z
       4: ifeq          47
       7: aload_0
       8: getfield      #12                 // Field tailListIterator:Ljava/util/ListIterator;
      11: invokeinterface #14,  1           // InterfaceMethod java/util/ListIterator.hasNext:()Z
      16: ifeq          37
      19: aload_0
      20: dup
      21: getfield      #6                  // Field index:I
      24: iconst_1
      25: iadd
      26: putfield      #6                  // Field index:I
      29: aload_0
      30: aload_0
      31: getfield      #6                  // Field index:I
      34: putfield      #4                  // Field lastReturnedIndex:I
      37: aload_0
      38: getfield      #12                 // Field tailListIterator:Ljava/util/ListIterator;
      41: invokeinterface #13,  1           // InterfaceMethod java/util/ListIterator.next:()Ljava/lang/Object;
      46: areturn
      47: aload_0
      48: getfield      #5                  // Field bitList:Lorg/apache/dubbo/rpc/cluster/router/state/BitList;
      51: invokestatic  #7                  // Method org/apache/dubbo/rpc/cluster/router/state/BitList.access$000:(Lorg/apache/dubbo/rpc/cluster/router/state/BitList;)Ljava/util/BitSet;
      54: aload_0
      55: getfield      #2                  // Field curBitIndex:I
      58: iconst_1
      59: iadd
      60: invokevirtual #8                  // Method java/util/BitSet.nextSetBit:(I)I
      63: istore_1
      64: iload_1
      65: iconst_m1
      66: if_icmpne     136
      69: aload_0
      70: getfield      #5                  // Field bitList:Lorg/apache/dubbo/rpc/cluster/router/state/BitList;
      73: invokevirtual #15                 // Method org/apache/dubbo/rpc/cluster/router/state/BitList.hasMoreElementInTailList:()Z
      76: ifeq          128
      79: aload_0
      80: aload_0
      81: getfield      #5                  // Field bitList:Lorg/apache/dubbo/rpc/cluster/router/state/BitList;
      84: invokestatic  #9                  // Method org/apache/dubbo/rpc/cluster/router/state/BitList.access$100:(Lorg/apache/dubbo/rpc/cluster/router/state/BitList;)Ljava/util/List;
      87: invokeinterface #11,  1           // InterfaceMethod java/util/List.listIterator:()Ljava/util/ListIterator;
      92: putfield      #12                 // Field tailListIterator:Ljava/util/ListIterator;
      95: aload_0
      96: iconst_1
      97: putfield      #3                  // Field isInTailList:Z
     100: aload_0
     101: dup
     102: getfield      #6                  // Field index:I
     105: iconst_1
     106: iadd
     107: putfield      #6                  // Field index:I
     110: aload_0
     111: aload_0
     112: getfield      #6                  // Field index:I
     115: putfield      #4                  // Field lastReturnedIndex:I
     118: aload_0
     119: getfield      #12                 // Field tailListIterator:Ljava/util/ListIterator;
     122: invokeinterface #13,  1           // InterfaceMethod java/util/ListIterator.next:()Ljava/lang/Object;
     127: areturn
     128: new           #16                 // class java/util/NoSuchElementException
     131: dup
     132: invokespecial #17                 // Method java/util/NoSuchElementException."<init>":()V
     135: athrow
     136: aload_0
     137: dup
     138: getfield      #6                  // Field index:I
     141: iconst_1
     142: iadd
     143: putfield      #6                  // Field index:I
     146: aload_0
     147: aload_0
     148: getfield      #6                  // Field index:I
     151: putfield      #4                  // Field lastReturnedIndex:I
     154: aload_0
     155: iload_1
     156: putfield      #2                  // Field curBitIndex:I
     159: aload_0
     160: getfield      #5                  // Field bitList:Lorg/apache/dubbo/rpc/cluster/router/state/BitList;
     163: invokestatic  #18                 // Method org/apache/dubbo/rpc/cluster/router/state/BitList.access$200:(Lorg/apache/dubbo/rpc/cluster/router/state/BitList;)Ljava/util/List;
     166: iload_1
     167: invokeinterface #19,  2           // InterfaceMethod java/util/List.get:(I)Ljava/lang/Object;
     172: areturn

  public boolean hasPrevious();
    Code:
       0: aload_0
       1: getfield      #3                  // Field isInTailList:Z
       4: ifeq          53
       7: aload_0
       8: getfield      #12                 // Field tailListIterator:Ljava/util/ListIterator;
      11: invokeinterface #20,  1           // InterfaceMethod java/util/ListIterator.hasPrevious:()Z
      16: istore_1
      17: iload_1
      18: ifeq          23
      21: iconst_1
      22: ireturn
      23: aload_0
      24: getfield      #5                  // Field bitList:Lorg/apache/dubbo/rpc/cluster/router/state/BitList;
      27: invokestatic  #7                  // Method org/apache/dubbo/rpc/cluster/router/state/BitList.access$000:(Lorg/apache/dubbo/rpc/cluster/router/state/BitList;)Ljava/util/BitSet;
      30: aload_0
      31: getfield      #5                  // Field bitList:Lorg/apache/dubbo/rpc/cluster/router/state/BitList;
      34: invokestatic  #7                  // Method org/apache/dubbo/rpc/cluster/router/state/BitList.access$000:(Lorg/apache/dubbo/rpc/cluster/router/state/BitList;)Ljava/util/BitSet;
      37: invokevirtual #21                 // Method java/util/BitSet.size:()I
      40: invokevirtual #22                 // Method java/util/BitSet.previousSetBit:(I)I
      43: iconst_m1
      44: if_icmpeq     51
      47: iconst_1
      48: goto          52
      51: iconst_0
      52: ireturn
      53: aload_0
      54: getfield      #2                  // Field curBitIndex:I
      57: iconst_m1
      58: if_icmpeq     65
      61: iconst_1
      62: goto          66
      65: iconst_0
      66: ireturn

  public E previous();
    Code:
       0: aload_0
       1: getfield      #3                  // Field isInTailList:Z
       4: ifeq          137
       7: aload_0
       8: getfield      #12                 // Field tailListIterator:Ljava/util/ListIterator;
      11: invokeinterface #20,  1           // InterfaceMethod java/util/ListIterator.hasPrevious:()Z
      16: istore_1
      17: iload_1
      18: ifeq          49
      21: aload_0
      22: aload_0
      23: getfield      #6                  // Field index:I
      26: putfield      #4                  // Field lastReturnedIndex:I
      29: aload_0
      30: dup
      31: getfield      #6                  // Field index:I
      34: iconst_1
      35: isub
      36: putfield      #6                  // Field index:I
      39: aload_0
      40: getfield      #12                 // Field tailListIterator:Ljava/util/ListIterator;
      43: invokeinterface #23,  1           // InterfaceMethod java/util/ListIterator.previous:()Ljava/lang/Object;
      48: areturn
      49: aload_0
      50: getfield      #5                  // Field bitList:Lorg/apache/dubbo/rpc/cluster/router/state/BitList;
      53: invokestatic  #7                  // Method org/apache/dubbo/rpc/cluster/router/state/BitList.access$000:(Lorg/apache/dubbo/rpc/cluster/router/state/BitList;)Ljava/util/BitSet;
      56: aload_0
      57: getfield      #5                  // Field bitList:Lorg/apache/dubbo/rpc/cluster/router/state/BitList;
      60: invokestatic  #7                  // Method org/apache/dubbo/rpc/cluster/router/state/BitList.access$000:(Lorg/apache/dubbo/rpc/cluster/router/state/BitList;)Ljava/util/BitSet;
      63: invokevirtual #21                 // Method java/util/BitSet.size:()I
      66: invokevirtual #22                 // Method java/util/BitSet.previousSetBit:(I)I
      69: istore_2
      70: iload_2
      71: iconst_m1
      72: if_icmpne     83
      75: new           #16                 // class java/util/NoSuchElementException
      78: dup
      79: invokespecial #17                 // Method java/util/NoSuchElementException."<init>":()V
      82: athrow
      83: aload_0
      84: iconst_0
      85: putfield      #3                  // Field isInTailList:Z
      88: aload_0
      89: aload_0
      90: getfield      #5                  // Field bitList:Lorg/apache/dubbo/rpc/cluster/router/state/BitList;
      93: invokestatic  #7                  // Method org/apache/dubbo/rpc/cluster/router/state/BitList.access$000:(Lorg/apache/dubbo/rpc/cluster/router/state/BitList;)Ljava/util/BitSet;
      96: iload_2
      97: iconst_1
      98: isub
      99: invokevirtual #22                 // Method java/util/BitSet.previousSetBit:(I)I
     102: putfield      #2                  // Field curBitIndex:I
     105: aload_0
     106: aload_0
     107: getfield      #6                  // Field index:I
     110: putfield      #4                  // Field lastReturnedIndex:I
     113: aload_0
     114: dup
     115: getfield      #6                  // Field index:I
     118: iconst_1
     119: isub
     120: putfield      #6                  // Field index:I
     123: aload_0
     124: getfield      #5                  // Field bitList:Lorg/apache/dubbo/rpc/cluster/router/state/BitList;
     127: invokestatic  #18                 // Method org/apache/dubbo/rpc/cluster/router/state/BitList.access$200:(Lorg/apache/dubbo/rpc/cluster/router/state/BitList;)Ljava/util/List;
     130: iload_2
     131: invokeinterface #19,  2           // InterfaceMethod java/util/List.get:(I)Ljava/lang/Object;
     136: areturn
     137: aload_0
     138: getfield      #2                  // Field curBitIndex:I
     141: iconst_m1
     142: if_icmpne     153
     145: new           #16                 // class java/util/NoSuchElementException
     148: dup
     149: invokespecial #17                 // Method java/util/NoSuchElementException."<init>":()V
     152: athrow
     153: aload_0
     154: getfield      #2                  // Field curBitIndex:I
     157: istore_1
     158: aload_0
     159: aload_0
     160: getfield      #5                  // Field bitList:Lorg/apache/dubbo/rpc/cluster/router/state/BitList;
     163: invokestatic  #7                  // Method org/apache/dubbo/rpc/cluster/router/state/BitList.access$000:(Lorg/apache/dubbo/rpc/cluster/router/state/BitList;)Ljava/util/BitSet;
     166: aload_0
     167: getfield      #2                  // Field curBitIndex:I
     170: iconst_1
     171: isub
     172: invokevirtual #22                 // Method java/util/BitSet.previousSetBit:(I)I
     175: putfield      #2                  // Field curBitIndex:I
     178: aload_0
     179: aload_0
     180: getfield      #6                  // Field index:I
     183: putfield      #4                  // Field lastReturnedIndex:I
     186: aload_0
     187: dup
     188: getfield      #6                  // Field index:I
     191: iconst_1
     192: isub
     193: putfield      #6                  // Field index:I
     196: aload_0
     197: getfield      #5                  // Field bitList:Lorg/apache/dubbo/rpc/cluster/router/state/BitList;
     200: invokestatic  #18                 // Method org/apache/dubbo/rpc/cluster/router/state/BitList.access$200:(Lorg/apache/dubbo/rpc/cluster/router/state/BitList;)Ljava/util/List;
     203: iload_1
     204: invokeinterface #19,  2           // InterfaceMethod java/util/List.get:(I)Ljava/lang/Object;
     209: areturn

  public int nextIndex();
    Code:
       0: aload_0
       1: invokevirtual #24                 // Method hasNext:()Z
       4: ifeq          16
       7: aload_0
       8: getfield      #6                  // Field index:I
      11: iconst_1
      12: iadd
      13: goto          20
      16: aload_0
      17: getfield      #6                  // Field index:I
      20: ireturn

  public int previousIndex();
    Code:
       0: aload_0
       1: getfield      #6                  // Field index:I
       4: ireturn

  public void remove();
    Code:
       0: aload_0
       1: getfield      #4                  // Field lastReturnedIndex:I
       4: iconst_m1
       5: if_icmpne     16
       8: new           #25                 // class java/lang/IllegalStateException
      11: dup
      12: invokespecial #26                 // Method java/lang/IllegalStateException."<init>":()V
      15: athrow
      16: aload_0
      17: getfield      #4                  // Field lastReturnedIndex:I
      20: aload_0
      21: getfield      #5                  // Field bitList:Lorg/apache/dubbo/rpc/cluster/router/state/BitList;
      24: invokestatic  #7                  // Method org/apache/dubbo/rpc/cluster/router/state/BitList.access$000:(Lorg/apache/dubbo/rpc/cluster/router/state/BitList;)Ljava/util/BitSet;
      27: invokevirtual #27                 // Method java/util/BitSet.cardinality:()I
      30: if_icmplt     45
      33: aload_0
      34: getfield      #12                 // Field tailListIterator:Ljava/util/ListIterator;
      37: invokeinterface #28,  1           // InterfaceMethod java/util/ListIterator.remove:()V
      42: goto          89
      45: iconst_m1
      46: istore_1
      47: iconst_0
      48: istore_2
      49: iload_2
      50: aload_0
      51: getfield      #4                  // Field lastReturnedIndex:I
      54: if_icmpgt     77
      57: aload_0
      58: getfield      #5                  // Field bitList:Lorg/apache/dubbo/rpc/cluster/router/state/BitList;
      61: invokestatic  #7                  // Method org/apache/dubbo/rpc/cluster/router/state/BitList.access$000:(Lorg/apache/dubbo/rpc/cluster/router/state/BitList;)Ljava/util/BitSet;
      64: iload_1
      65: iconst_1
      66: iadd
      67: invokevirtual #8                  // Method java/util/BitSet.nextSetBit:(I)I
      70: istore_1
      71: iinc          2, 1
      74: goto          49
      77: aload_0
      78: getfield      #5                  // Field bitList:Lorg/apache/dubbo/rpc/cluster/router/state/BitList;
      81: invokestatic  #7                  // Method org/apache/dubbo/rpc/cluster/router/state/BitList.access$000:(Lorg/apache/dubbo/rpc/cluster/router/state/BitList;)Ljava/util/BitSet;
      84: iload_1
      85: iconst_0
      86: invokevirtual #29                 // Method java/util/BitSet.set:(IZ)V
      89: aload_0
      90: getfield      #4                  // Field lastReturnedIndex:I
      93: aload_0
      94: getfield      #6                  // Field index:I
      97: if_icmpgt     110
     100: aload_0
     101: dup
     102: getfield      #6                  // Field index:I
     105: iconst_1
     106: isub
     107: putfield      #6                  // Field index:I
     110: return

  public void set(E);
    Code:
       0: new           #30                 // class java/lang/UnsupportedOperationException
       3: dup
       4: ldc           #31                 // String Set method is not supported in BitListIterator!
       6: invokespecial #32                 // Method java/lang/UnsupportedOperationException."<init>":(Ljava/lang/String;)V
       9: athrow

  public void add(E);
    Code:
       0: new           #30                 // class java/lang/UnsupportedOperationException
       3: dup
       4: ldc           #33                 // String Add method is not supported in BitListIterator!
       6: invokespecial #32                 // Method java/lang/UnsupportedOperationException."<init>":(Ljava/lang/String;)V
       9: athrow
}
