Compiled from "RouterGroupingState.java"
public class org.apache.dubbo.rpc.cluster.router.state.RouterGroupingState<T> {
  private final java.lang.String routerName;

  private final int total;

  private final java.util.Map<java.lang.String, org.apache.dubbo.rpc.cluster.router.state.BitList<org.apache.dubbo.rpc.Invoker<T>>> grouping;

  public org.apache.dubbo.rpc.cluster.router.state.RouterGroupingState(java.lang.String, int, java.util.Map<java.lang.String, org.apache.dubbo.rpc.cluster.router.state.BitList<org.apache.dubbo.rpc.Invoker<T>>>);
    Code:
       0: aload_0
       1: invokespecial #1                  // Method java/lang/Object."<init>":()V
       4: aload_0
       5: aload_1
       6: putfield      #2                  // Field routerName:Ljava/lang/String;
       9: aload_0
      10: iload_2
      11: putfield      #3                  // Field total:I
      14: aload_0
      15: aload_3
      16: putfield      #4                  // Field grouping:Ljava/util/Map;
      19: return

  public java.lang.String getRouterName();
    Code:
       0: aload_0
       1: getfield      #2                  // Field routerName:Ljava/lang/String;
       4: areturn

  public int getTotal();
    Code:
       0: aload_0
       1: getfield      #3                  // Field total:I
       4: ireturn

  public java.util.Map<java.lang.String, org.apache.dubbo.rpc.cluster.router.state.BitList<org.apache.dubbo.rpc.Invoker<T>>> getGrouping();
    Code:
       0: aload_0
       1: getfield      #4                  // Field grouping:Ljava/util/Map;
       4: areturn

  public java.lang.String toString();
    Code:
       0: new           #5                  // class java/lang/StringBuilder
       3: dup
       4: invokespecial #6                  // Method java/lang/StringBuilder."<init>":()V
       7: astore_1
       8: aload_1
       9: aload_0
      10: getfield      #2                  // Field routerName:Ljava/lang/String;
      13: invokevirtual #7                  // Method java/lang/StringBuilder.append:(Ljava/lang/String;)Ljava/lang/StringBuilder;
      16: bipush        32
      18: invokevirtual #8                  // Method java/lang/StringBuilder.append:(C)Ljava/lang/StringBuilder;
      21: ldc           #9                  // String  Total:
      23: invokevirtual #7                  // Method java/lang/StringBuilder.append:(Ljava/lang/String;)Ljava/lang/StringBuilder;
      26: aload_0
      27: getfield      #3                  // Field total:I
      30: invokevirtual #10                 // Method java/lang/StringBuilder.append:(I)Ljava/lang/StringBuilder;
      33: ldc           #11                 // String \n
      35: invokevirtual #7                  // Method java/lang/StringBuilder.append:(Ljava/lang/String;)Ljava/lang/StringBuilder;
      38: pop
      39: aload_0
      40: getfield      #4                  // Field grouping:Ljava/util/Map;
      43: invokeinterface #12,  1           // InterfaceMethod java/util/Map.entrySet:()Ljava/util/Set;
      48: invokeinterface #13,  1           // InterfaceMethod java/util/Set.iterator:()Ljava/util/Iterator;
      53: astore_2
      54: aload_2
      55: invokeinterface #14,  1           // InterfaceMethod java/util/Iterator.hasNext:()Z
      60: ifeq          215
      63: aload_2
      64: invokeinterface #15,  1           // InterfaceMethod java/util/Iterator.next:()Ljava/lang/Object;
      69: checkcast     #16                 // class java/util/Map$Entry
      72: astore_3
      73: aload_3
      74: invokeinterface #17,  1           // InterfaceMethod java/util/Map$Entry.getValue:()Ljava/lang/Object;
      79: checkcast     #18                 // class org/apache/dubbo/rpc/cluster/router/state/BitList
      82: astore        4
      84: aload_1
      85: ldc           #19                 // String [
      87: invokevirtual #7                  // Method java/lang/StringBuilder.append:(Ljava/lang/String;)Ljava/lang/StringBuilder;
      90: aload_3
      91: invokeinterface #20,  1           // InterfaceMethod java/util/Map$Entry.getKey:()Ljava/lang/Object;
      96: checkcast     #21                 // class java/lang/String
      99: invokevirtual #7                  // Method java/lang/StringBuilder.append:(Ljava/lang/String;)Ljava/lang/StringBuilder;
     102: ldc           #22                 // String  ->
     104: invokevirtual #7                  // Method java/lang/StringBuilder.append:(Ljava/lang/String;)Ljava/lang/StringBuilder;
     107: aload         4
     109: invokevirtual #23                 // Method org/apache/dubbo/rpc/cluster/router/state/BitList.isEmpty:()Z
     112: ifeq          120
     115: ldc           #24                 // String Empty
     117: goto          166
     120: aload         4
     122: invokevirtual #25                 // Method org/apache/dubbo/rpc/cluster/router/state/BitList.stream:()Ljava/util/stream/Stream;
     125: ldc2_w        #26                 // long 5l
     128: invokeinterface #28,  3           // InterfaceMethod java/util/stream/Stream.limit:(J)Ljava/util/stream/Stream;
     133: invokedynamic #29,  0             // InvokeDynamic #0:apply:()Ljava/util/function/Function;
     138: invokeinterface #30,  2           // InterfaceMethod java/util/stream/Stream.map:(Ljava/util/function/Function;)Ljava/util/stream/Stream;
     143: invokedynamic #31,  0             // InvokeDynamic #1:apply:()Ljava/util/function/Function;
     148: invokeinterface #30,  2           // InterfaceMethod java/util/stream/Stream.map:(Ljava/util/function/Function;)Ljava/util/stream/Stream;
     153: ldc           #32                 // String ,
     155: invokestatic  #33                 // Method java/util/stream/Collectors.joining:(Ljava/lang/CharSequence;)Ljava/util/stream/Collector;
     158: invokeinterface #34,  2           // InterfaceMethod java/util/stream/Stream.collect:(Ljava/util/stream/Collector;)Ljava/lang/Object;
     163: checkcast     #21                 // class java/lang/String
     166: invokevirtual #7                  // Method java/lang/StringBuilder.append:(Ljava/lang/String;)Ljava/lang/StringBuilder;
     169: aload         4
     171: invokevirtual #35                 // Method org/apache/dubbo/rpc/cluster/router/state/BitList.size:()I
     174: iconst_5
     175: if_icmple     183
     178: ldc           #36                 // String ...
     180: goto          185
     183: ldc           #37                 // String
     185: invokevirtual #7                  // Method java/lang/StringBuilder.append:(Ljava/lang/String;)Ljava/lang/StringBuilder;
     188: ldc           #38                 // String  (Total:
     190: invokevirtual #7                  // Method java/lang/StringBuilder.append:(Ljava/lang/String;)Ljava/lang/StringBuilder;
     193: aload         4
     195: invokevirtual #35                 // Method org/apache/dubbo/rpc/cluster/router/state/BitList.size:()I
     198: invokevirtual #10                 // Method java/lang/StringBuilder.append:(I)Ljava/lang/StringBuilder;
     201: ldc           #39                 // String ) ]
     203: invokevirtual #7                  // Method java/lang/StringBuilder.append:(Ljava/lang/String;)Ljava/lang/StringBuilder;
     206: ldc           #11                 // String \n
     208: invokevirtual #7                  // Method java/lang/StringBuilder.append:(Ljava/lang/String;)Ljava/lang/StringBuilder;
     211: pop
     212: goto          54
     215: aload_1
     216: invokevirtual #40                 // Method java/lang/StringBuilder.toString:()Ljava/lang/String;
     219: areturn
}
