Compiled from "TailStateRouter.java"
public class org.apache.dubbo.rpc.cluster.router.state.TailStateRouter<T> implements org.apache.dubbo.rpc.cluster.router.state.StateRouter<T> {
  private static final org.apache.dubbo.rpc.cluster.router.state.TailStateRouter INSTANCE;

  public static <T> org.apache.dubbo.rpc.cluster.router.state.TailStateRouter<T> getInstance();
    Code:
       0: getstatic     #1                  // Field INSTANCE:Lorg/apache/dubbo/rpc/cluster/router/state/TailStateRouter;
       3: areturn

  private org.apache.dubbo.rpc.cluster.router.state.TailStateRouter();
    Code:
       0: aload_0
       1: invokespecial #2                  // Method java/lang/Object."<init>":()V
       4: return

  public void setNextRouter(org.apache.dubbo.rpc.cluster.router.state.StateRouter<T>);
    Code:
       0: return

  public org.apache.dubbo.common.URL getUrl();
    Code:
       0: aconst_null
       1: areturn

  public org.apache.dubbo.rpc.cluster.router.state.BitList<org.apache.dubbo.rpc.Invoker<T>> route(org.apache.dubbo.rpc.cluster.router.state.BitList<org.apache.dubbo.rpc.Invoker<T>>, org.apache.dubbo.common.URL, org.apache.dubbo.rpc.Invocation, boolean, org.apache.dubbo.common.utils.Holder<org.apache.dubbo.rpc.cluster.router.RouterSnapshotNode<T>>) throws org.apache.dubbo.rpc.RpcException;
    Code:
       0: aload_1
       1: areturn

  public boolean isRuntime();
    Code:
       0: iconst_0
       1: ireturn

  public boolean isForce();
    Code:
       0: iconst_0
       1: ireturn

  public void notify(org.apache.dubbo.rpc.cluster.router.state.BitList<org.apache.dubbo.rpc.Invoker<T>>);
    Code:
       0: return

  public java.lang.String buildSnapshot();
    Code:
       0: ldc           #3                  // String TailStateRouter End
       2: areturn

  static {};
    Code:
       0: new           #4                  // class org/apache/dubbo/rpc/cluster/router/state/TailStateRouter
       3: dup
       4: invokespecial #5                  // Method "<init>":()V
       7: putstatic     #1                  // Field INSTANCE:Lorg/apache/dubbo/rpc/cluster/router/state/TailStateRouter;
      10: return
}
