Compiled from "IstioCitadelCertificateSigner.java"
class org.apache.dubbo.registry.xds.istio.IstioCitadelCertificateSigner$GenerateCertTask implements java.lang.Runnable {
  final org.apache.dubbo.registry.xds.istio.IstioCitadelCertificateSigner this$0;

  private org.apache.dubbo.registry.xds.istio.IstioCitadelCertificateSigner$GenerateCertTask(org.apache.dubbo.registry.xds.istio.IstioCitadelCertificateSigner);
    Code:
       0: aload_0
       1: aload_1
       2: putfield      #2                  // Field this$0:Lorg/apache/dubbo/registry/xds/istio/IstioCitadelCertificateSigner;
       5: aload_0
       6: invokespecial #3                  // Method java/lang/Object."<init>":()V
       9: return

  public void run();
    Code:
       0: aload_0
       1: getfield      #2                  // Field this$0:Lorg/apache/dubbo/registry/xds/istio/IstioCitadelCertificateSigner;
       4: invokestatic  #4                  // Method org/apache/dubbo/registry/xds/istio/IstioCitadelCertificateSigner.access$100:(Lorg/apache/dubbo/registry/xds/istio/IstioCitadelCertificateSigner;)Lorg/apache/dubbo/registry/xds/XdsCertificateSigner$CertPair;
       7: pop
       8: return

  org.apache.dubbo.registry.xds.istio.IstioCitadelCertificateSigner$GenerateCertTask(org.apache.dubbo.registry.xds.istio.IstioCitadelCertificateSigner, org.apache.dubbo.registry.xds.istio.IstioCitadelCertificateSigner$1);
    Code:
       0: aload_0
       1: aload_1
       2: invokespecial #1                  // Method "<init>":(Lorg/apache/dubbo/registry/xds/istio/IstioCitadelCertificateSigner;)V
       5: return
}
