Compiled from "IstioCitadelCertificateSigner.java"
class org.apache.dubbo.registry.xds.istio.IstioCitadelCertificateSigner$1 implements io.grpc.stub.StreamObserver<istio.v1.auth.IstioCertificateResponse> {
  final java.lang.StringBuffer val$publicKeyBuilder;

  final java.util.concurrent.CountDownLatch val$countDownLatch;

  final java.util.concurrent.atomic.AtomicBoolean val$failed;

  final org.apache.dubbo.registry.xds.istio.IstioCitadelCertificateSigner this$0;

  org.apache.dubbo.registry.xds.istio.IstioCitadelCertificateSigner$1(org.apache.dubbo.registry.xds.istio.IstioCitadelCertificateSigner, java.lang.StringBuffer, java.util.concurrent.CountDownLatch, java.util.concurrent.atomic.AtomicBoolean);
    Code:
       0: aload_0
       1: aload_1
       2: putfield      #2                  // Field this$0:Lorg/apache/dubbo/registry/xds/istio/IstioCitadelCertificateSigner;
       5: aload_0
       6: aload_2
       7: putfield      #3                  // Field val$publicKeyBuilder:Ljava/lang/StringBuffer;
      10: aload_0
      11: aload_3
      12: putfield      #4                  // Field val$countDownLatch:Ljava/util/concurrent/CountDownLatch;
      15: aload_0
      16: aload         4
      18: putfield      #5                  // Field val$failed:Ljava/util/concurrent/atomic/AtomicBoolean;
      21: aload_0
      22: invokespecial #6                  // Method java/lang/Object."<init>":()V
      25: return

  public void onNext(istio.v1.auth.IstioCertificateResponse);
    Code:
       0: iconst_0
       1: istore_2
       2: iload_2
       3: aload_1
       4: invokevirtual #7                  // Method istio/v1/auth/IstioCertificateResponse.getCertChainCount:()I
       7: if_icmpge     32
      10: aload_0
      11: getfield      #3                  // Field val$publicKeyBuilder:Ljava/lang/StringBuffer;
      14: aload_1
      15: iload_2
      16: invokevirtual #8                  // Method istio/v1/auth/IstioCertificateResponse.getCertChainBytes:(I)Lcom/google/protobuf/ByteString;
      19: invokevirtual #9                  // Method com/google/protobuf/ByteString.toStringUtf8:()Ljava/lang/String;
      22: invokevirtual #10                 // Method java/lang/StringBuffer.append:(Ljava/lang/String;)Ljava/lang/StringBuffer;
      25: pop
      26: iinc          2, 1
      29: goto          2
      32: invokestatic  #11                 // Method org/apache/dubbo/registry/xds/istio/IstioCitadelCertificateSigner.access$200:()Lorg/apache/dubbo/common/logger/ErrorTypeAwareLogger;
      35: invokeinterface #12,  1           // InterfaceMethod org/apache/dubbo/common/logger/ErrorTypeAwareLogger.isDebugEnabled:()Z
      40: ifeq          73
      43: invokestatic  #11                 // Method org/apache/dubbo/registry/xds/istio/IstioCitadelCertificateSigner.access$200:()Lorg/apache/dubbo/common/logger/ErrorTypeAwareLogger;
      46: new           #13                 // class java/lang/StringBuilder
      49: dup
      50: invokespecial #14                 // Method java/lang/StringBuilder."<init>":()V
      53: ldc           #15                 // String Receive Cert chain from Istio Citadel. \n
      55: invokevirtual #16                 // Method java/lang/StringBuilder.append:(Ljava/lang/String;)Ljava/lang/StringBuilder;
      58: aload_0
      59: getfield      #3                  // Field val$publicKeyBuilder:Ljava/lang/StringBuffer;
      62: invokevirtual #17                 // Method java/lang/StringBuilder.append:(Ljava/lang/Object;)Ljava/lang/StringBuilder;
      65: invokevirtual #18                 // Method java/lang/StringBuilder.toString:()Ljava/lang/String;
      68: invokeinterface #19,  2           // InterfaceMethod org/apache/dubbo/common/logger/ErrorTypeAwareLogger.debug:(Ljava/lang/String;)V
      73: aload_0
      74: getfield      #4                  // Field val$countDownLatch:Ljava/util/concurrent/CountDownLatch;
      77: invokevirtual #20                 // Method java/util/concurrent/CountDownLatch.countDown:()V
      80: return

  public void onError(java.lang.Throwable);
    Code:
       0: aload_0
       1: getfield      #5                  // Field val$failed:Ljava/util/concurrent/atomic/AtomicBoolean;
       4: iconst_1
       5: invokevirtual #21                 // Method java/util/concurrent/atomic/AtomicBoolean.set:(Z)V
       8: invokestatic  #11                 // Method org/apache/dubbo/registry/xds/istio/IstioCitadelCertificateSigner.access$200:()Lorg/apache/dubbo/common/logger/ErrorTypeAwareLogger;
      11: ldc           #22                 // String 1-28
      13: ldc           #23                 // String
      15: ldc           #23                 // String
      17: ldc           #24                 // String Receive error message from Istio Citadel grpc stub.
      19: aload_1
      20: invokeinterface #25,  6           // InterfaceMethod org/apache/dubbo/common/logger/ErrorTypeAwareLogger.error:(Ljava/lang/String;Ljava/lang/String;Ljava/lang/String;Ljava/lang/String;Ljava/lang/Throwable;)V
      25: aload_0
      26: getfield      #4                  // Field val$countDownLatch:Ljava/util/concurrent/CountDownLatch;
      29: invokevirtual #20                 // Method java/util/concurrent/CountDownLatch.countDown:()V
      32: return

  public void onCompleted();
    Code:
       0: aload_0
       1: getfield      #4                  // Field val$countDownLatch:Ljava/util/concurrent/CountDownLatch;
       4: invokevirtual #20                 // Method java/util/concurrent/CountDownLatch.countDown:()V
       7: return

  public void onNext(java.lang.Object);
    Code:
       0: aload_0
       1: aload_1
       2: checkcast     #26                 // class istio/v1/auth/IstioCertificateResponse
       5: invokevirtual #27                 // Method onNext:(Listio/v1/auth/IstioCertificateResponse;)V
       8: return
}
