Compiled from "IstioCitadelCertificateSigner.java"
public class org.apache.dubbo.registry.xds.istio.IstioCitadelCertificateSigner implements org.apache.dubbo.registry.xds.XdsCertificateSigner {
  private static final org.apache.dubbo.common.logger.ErrorTypeAwareLogger logger;

  private final org.apache.dubbo.registry.xds.istio.IstioEnv istioEnv;

  private org.apache.dubbo.registry.xds.XdsCertificateSigner$CertPair certPair;

  public org.apache.dubbo.registry.xds.istio.IstioCitadelCertificateSigner();
    Code:
       0: aload_0
       1: invokespecial #4                  // Method java/lang/Object."<init>":()V
       4: iconst_1
       5: invokestatic  #5                  // Method java/util/concurrent/Executors.newScheduledThreadPool:(I)Ljava/util/concurrent/ScheduledExecutorService;
       8: astore_1
       9: aload_1
      10: new           #6                  // class org/apache/dubbo/registry/xds/istio/IstioCitadelCertificateSigner$GenerateCertTask
      13: dup
      14: aload_0
      15: aconst_null
      16: invokespecial #7                  // Method org/apache/dubbo/registry/xds/istio/IstioCitadelCertificateSigner$GenerateCertTask."<init>":(Lorg/apache/dubbo/registry/xds/istio/IstioCitadelCertificateSigner;Lorg/apache/dubbo/registry/xds/istio/IstioCitadelCertificateSigner$1;)V
      19: lconst_0
      20: ldc2_w        #8                  // long 30l
      23: getstatic     #10                 // Field java/util/concurrent/TimeUnit.SECONDS:Ljava/util/concurrent/TimeUnit;
      26: invokeinterface #11,  7           // InterfaceMethod java/util/concurrent/ScheduledExecutorService.scheduleAtFixedRate:(Ljava/lang/Runnable;JJLjava/util/concurrent/TimeUnit;)Ljava/util/concurrent/ScheduledFuture;
      31: pop
      32: aload_0
      33: invokestatic  #12                 // Method org/apache/dubbo/registry/xds/istio/IstioEnv.getInstance:()Lorg/apache/dubbo/registry/xds/istio/IstioEnv;
      36: putfield      #13                 // Field istioEnv:Lorg/apache/dubbo/registry/xds/istio/IstioEnv;
      39: return

  public org.apache.dubbo.registry.xds.XdsCertificateSigner$CertPair GenerateCert(org.apache.dubbo.common.URL);
    Code:
       0: aload_0
       1: getfield      #14                 // Field certPair:Lorg/apache/dubbo/registry/xds/XdsCertificateSigner$CertPair;
       4: ifnull        22
       7: aload_0
       8: getfield      #14                 // Field certPair:Lorg/apache/dubbo/registry/xds/XdsCertificateSigner$CertPair;
      11: invokevirtual #15                 // Method org/apache/dubbo/registry/xds/XdsCertificateSigner$CertPair.isExpire:()Z
      14: ifne          22
      17: aload_0
      18: getfield      #14                 // Field certPair:Lorg/apache/dubbo/registry/xds/XdsCertificateSigner$CertPair;
      21: areturn
      22: aload_0
      23: invokespecial #3                  // Method doGenerateCert:()Lorg/apache/dubbo/registry/xds/XdsCertificateSigner$CertPair;
      26: areturn

  private org.apache.dubbo.registry.xds.XdsCertificateSigner$CertPair doGenerateCert();
    Code:
       0: aload_0
       1: dup
       2: astore_1
       3: monitorenter
       4: aload_0
       5: getfield      #14                 // Field certPair:Lorg/apache/dubbo/registry/xds/XdsCertificateSigner$CertPair;
       8: ifnull        21
      11: aload_0
      12: getfield      #14                 // Field certPair:Lorg/apache/dubbo/registry/xds/XdsCertificateSigner$CertPair;
      15: invokevirtual #15                 // Method org/apache/dubbo/registry/xds/XdsCertificateSigner$CertPair.isExpire:()Z
      18: ifeq          61
      21: aload_0
      22: aload_0
      23: invokevirtual #16                 // Method createCert:()Lorg/apache/dubbo/registry/xds/XdsCertificateSigner$CertPair;
      26: putfield      #14                 // Field certPair:Lorg/apache/dubbo/registry/xds/XdsCertificateSigner$CertPair;
      29: goto          61
      32: astore_2
      33: getstatic     #2                  // Field logger:Lorg/apache/dubbo/common/logger/ErrorTypeAwareLogger;
      36: ldc           #18                 // String 1-26
      38: ldc           #19                 // String
      40: ldc           #19                 // String
      42: ldc           #20                 // String Generate Cert from Istio failed.
      44: aload_2
      45: invokeinterface #21,  6           // InterfaceMethod org/apache/dubbo/common/logger/ErrorTypeAwareLogger.error:(Ljava/lang/String;Ljava/lang/String;Ljava/lang/String;Ljava/lang/String;Ljava/lang/Throwable;)V
      50: new           #22                 // class org/apache/dubbo/rpc/RpcException
      53: dup
      54: ldc           #20                 // String Generate Cert from Istio failed.
      56: aload_2
      57: invokespecial #23                 // Method org/apache/dubbo/rpc/RpcException."<init>":(Ljava/lang/String;Ljava/lang/Throwable;)V
      60: athrow
      61: aload_1
      62: monitorexit
      63: goto          71
      66: astore_3
      67: aload_1
      68: monitorexit
      69: aload_3
      70: athrow
      71: aload_0
      72: getfield      #14                 // Field certPair:Lorg/apache/dubbo/registry/xds/XdsCertificateSigner$CertPair;
      75: areturn
    Exception table:
       from    to  target type
          21    29    32   Class java/io/IOException
           4    63    66   any
          66    69    66   any

  public org.apache.dubbo.registry.xds.XdsCertificateSigner$CertPair createCert() throws java.io.IOException;
    Code:
       0: aconst_null
       1: astore_1
       2: aconst_null
       3: astore_2
       4: aconst_null
       5: astore_3
       6: aload_0
       7: getfield      #13                 // Field istioEnv:Lorg/apache/dubbo/registry/xds/istio/IstioEnv;
      10: invokevirtual #24                 // Method org/apache/dubbo/registry/xds/istio/IstioEnv.isECCFirst:()Z
      13: ifeq          108
      16: new           #25                 // class java/security/spec/ECGenParameterSpec
      19: dup
      20: ldc           #26                 // String secp256r1
      22: invokespecial #27                 // Method java/security/spec/ECGenParameterSpec."<init>":(Ljava/lang/String;)V
      25: astore        4
      27: ldc           #28                 // String EC
      29: invokestatic  #29                 // Method java/security/KeyPairGenerator.getInstance:(Ljava/lang/String;)Ljava/security/KeyPairGenerator;
      32: astore        5
      34: aload         5
      36: aload         4
      38: new           #30                 // class java/security/SecureRandom
      41: dup
      42: invokespecial #31                 // Method java/security/SecureRandom."<init>":()V
      45: invokevirtual #32                 // Method java/security/KeyPairGenerator.initialize:(Ljava/security/spec/AlgorithmParameterSpec;Ljava/security/SecureRandom;)V
      48: aload         5
      50: invokevirtual #33                 // Method java/security/KeyPairGenerator.generateKeyPair:()Ljava/security/KeyPair;
      53: astore        6
      55: aload         6
      57: invokevirtual #34                 // Method java/security/KeyPair.getPublic:()Ljava/security/PublicKey;
      60: astore_1
      61: aload         6
      63: invokevirtual #35                 // Method java/security/KeyPair.getPrivate:()Ljava/security/PrivateKey;
      66: astore_2
      67: new           #36                 // class org/bouncycastle/operator/jcajce/JcaContentSignerBuilder
      70: dup
      71: ldc           #37                 // String SHA256withECDSA
      73: invokespecial #38                 // Method org/bouncycastle/operator/jcajce/JcaContentSignerBuilder."<init>":(Ljava/lang/String;)V
      76: aload         6
      78: invokevirtual #35                 // Method java/security/KeyPair.getPrivate:()Ljava/security/PrivateKey;
      81: invokevirtual #39                 // Method org/bouncycastle/operator/jcajce/JcaContentSignerBuilder.build:(Ljava/security/PrivateKey;)Lorg/bouncycastle/operator/ContentSigner;
      84: astore_3
      85: goto          108
      88: astore        4
      90: getstatic     #2                  // Field logger:Lorg/apache/dubbo/common/logger/ErrorTypeAwareLogger;
      93: ldc           #43                 // String 1-27
      95: ldc           #19                 // String
      97: ldc           #19                 // String
      99: ldc           #44                 // String Generate Key with secp256r1 algorithm failed. Please check if your system support. Will attempt to generate with RSA2048.
     101: aload         4
     103: invokeinterface #21,  6           // InterfaceMethod org/apache/dubbo/common/logger/ErrorTypeAwareLogger.error:(Ljava/lang/String;Ljava/lang/String;Ljava/lang/String;Ljava/lang/String;Ljava/lang/Throwable;)V
     108: aload_1
     109: ifnonnull     201
     112: ldc           #45                 // String RSA
     114: invokestatic  #29                 // Method java/security/KeyPairGenerator.getInstance:(Ljava/lang/String;)Ljava/security/KeyPairGenerator;
     117: astore        4
     119: aload         4
     121: aload_0
     122: getfield      #13                 // Field istioEnv:Lorg/apache/dubbo/registry/xds/istio/IstioEnv;
     125: invokevirtual #46                 // Method org/apache/dubbo/registry/xds/istio/IstioEnv.getRasKeySize:()I
     128: invokevirtual #47                 // Method java/security/KeyPairGenerator.initialize:(I)V
     131: aload         4
     133: invokevirtual #33                 // Method java/security/KeyPairGenerator.generateKeyPair:()Ljava/security/KeyPair;
     136: astore        5
     138: aload         5
     140: invokevirtual #34                 // Method java/security/KeyPair.getPublic:()Ljava/security/PublicKey;
     143: astore_1
     144: aload         5
     146: invokevirtual #35                 // Method java/security/KeyPair.getPrivate:()Ljava/security/PrivateKey;
     149: astore_2
     150: new           #36                 // class org/bouncycastle/operator/jcajce/JcaContentSignerBuilder
     153: dup
     154: ldc           #48                 // String SHA256WithRSA
     156: invokespecial #38                 // Method org/bouncycastle/operator/jcajce/JcaContentSignerBuilder."<init>":(Ljava/lang/String;)V
     159: aload         5
     161: invokevirtual #35                 // Method java/security/KeyPair.getPrivate:()Ljava/security/PrivateKey;
     164: invokevirtual #39                 // Method org/bouncycastle/operator/jcajce/JcaContentSignerBuilder.build:(Ljava/security/PrivateKey;)Lorg/bouncycastle/operator/ContentSigner;
     167: astore_3
     168: goto          201
     171: astore        4
     173: getstatic     #2                  // Field logger:Lorg/apache/dubbo/common/logger/ErrorTypeAwareLogger;
     176: ldc           #43                 // String 1-27
     178: ldc           #19                 // String
     180: ldc           #19                 // String
     182: ldc           #49                 // String Generate Key with SHA256WithRSA algorithm failed. Please check if your system support.
     184: aload         4
     186: invokeinterface #21,  6           // InterfaceMethod org/apache/dubbo/common/logger/ErrorTypeAwareLogger.error:(Ljava/lang/String;Ljava/lang/String;Ljava/lang/String;Ljava/lang/String;Ljava/lang/Throwable;)V
     191: new           #22                 // class org/apache/dubbo/rpc/RpcException
     194: dup
     195: aload         4
     197: invokespecial #50                 // Method org/apache/dubbo/rpc/RpcException."<init>":(Ljava/lang/Throwable;)V
     200: athrow
     201: aload_0
     202: aload_1
     203: aload_3
     204: invokespecial #51                 // Method generateCsr:(Ljava/security/PublicKey;Lorg/bouncycastle/operator/ContentSigner;)Ljava/lang/String;
     207: astore        4
     209: aload_0
     210: getfield      #13                 // Field istioEnv:Lorg/apache/dubbo/registry/xds/istio/IstioEnv;
     213: invokevirtual #52                 // Method org/apache/dubbo/registry/xds/istio/IstioEnv.getCaCert:()Ljava/lang/String;
     216: astore        5
     218: aload         5
     220: invokestatic  #53                 // Method org/apache/dubbo/common/utils/StringUtils.isNotEmpty:(Ljava/lang/String;)Z
     223: ifeq          271
     226: aload_0
     227: getfield      #13                 // Field istioEnv:Lorg/apache/dubbo/registry/xds/istio/IstioEnv;
     230: invokevirtual #54                 // Method org/apache/dubbo/registry/xds/istio/IstioEnv.getCaAddr:()Ljava/lang/String;
     233: invokestatic  #55                 // Method io/grpc/netty/shaded/io/grpc/netty/NettyChannelBuilder.forTarget:(Ljava/lang/String;)Lio/grpc/netty/shaded/io/grpc/netty/NettyChannelBuilder;
     236: invokestatic  #56                 // Method io/grpc/netty/shaded/io/grpc/netty/GrpcSslContexts.forClient:()Lio/grpc/netty/shaded/io/netty/handler/ssl/SslContextBuilder;
     239: new           #57                 // class java/io/ByteArrayInputStream
     242: dup
     243: aload         5
     245: getstatic     #58                 // Field java/nio/charset/StandardCharsets.UTF_8:Ljava/nio/charset/Charset;
     248: invokevirtual #59                 // Method java/lang/String.getBytes:(Ljava/nio/charset/Charset;)[B
     251: invokespecial #60                 // Method java/io/ByteArrayInputStream."<init>":([B)V
     254: invokevirtual #61                 // Method io/grpc/netty/shaded/io/netty/handler/ssl/SslContextBuilder.trustManager:(Ljava/io/InputStream;)Lio/grpc/netty/shaded/io/netty/handler/ssl/SslContextBuilder;
     257: invokevirtual #62                 // Method io/grpc/netty/shaded/io/netty/handler/ssl/SslContextBuilder.build:()Lio/grpc/netty/shaded/io/netty/handler/ssl/SslContext;
     260: invokevirtual #63                 // Method io/grpc/netty/shaded/io/grpc/netty/NettyChannelBuilder.sslContext:(Lio/grpc/netty/shaded/io/netty/handler/ssl/SslContext;)Lio/grpc/netty/shaded/io/grpc/netty/NettyChannelBuilder;
     263: invokevirtual #64                 // Method io/grpc/netty/shaded/io/grpc/netty/NettyChannelBuilder.build:()Lio/grpc/ManagedChannel;
     266: astore        6
     268: goto          301
     271: aload_0
     272: getfield      #13                 // Field istioEnv:Lorg/apache/dubbo/registry/xds/istio/IstioEnv;
     275: invokevirtual #54                 // Method org/apache/dubbo/registry/xds/istio/IstioEnv.getCaAddr:()Ljava/lang/String;
     278: invokestatic  #55                 // Method io/grpc/netty/shaded/io/grpc/netty/NettyChannelBuilder.forTarget:(Ljava/lang/String;)Lio/grpc/netty/shaded/io/grpc/netty/NettyChannelBuilder;
     281: invokestatic  #56                 // Method io/grpc/netty/shaded/io/grpc/netty/GrpcSslContexts.forClient:()Lio/grpc/netty/shaded/io/netty/handler/ssl/SslContextBuilder;
     284: getstatic     #65                 // Field io/grpc/netty/shaded/io/netty/handler/ssl/util/InsecureTrustManagerFactory.INSTANCE:Ljavax/net/ssl/TrustManagerFactory;
     287: invokevirtual #66                 // Method io/grpc/netty/shaded/io/netty/handler/ssl/SslContextBuilder.trustManager:(Ljavax/net/ssl/TrustManagerFactory;)Lio/grpc/netty/shaded/io/netty/handler/ssl/SslContextBuilder;
     290: invokevirtual #62                 // Method io/grpc/netty/shaded/io/netty/handler/ssl/SslContextBuilder.build:()Lio/grpc/netty/shaded/io/netty/handler/ssl/SslContext;
     293: invokevirtual #63                 // Method io/grpc/netty/shaded/io/grpc/netty/NettyChannelBuilder.sslContext:(Lio/grpc/netty/shaded/io/netty/handler/ssl/SslContext;)Lio/grpc/netty/shaded/io/grpc/netty/NettyChannelBuilder;
     296: invokevirtual #64                 // Method io/grpc/netty/shaded/io/grpc/netty/NettyChannelBuilder.build:()Lio/grpc/ManagedChannel;
     299: astore        6
     301: new           #67                 // class io/grpc/Metadata
     304: dup
     305: invokespecial #68                 // Method io/grpc/Metadata."<init>":()V
     308: astore        7
     310: ldc           #69                 // String authorization
     312: getstatic     #70                 // Field io/grpc/Metadata.ASCII_STRING_MARSHALLER:Lio/grpc/Metadata$AsciiMarshaller;
     315: invokestatic  #71                 // Method io/grpc/Metadata$Key.of:(Ljava/lang/String;Lio/grpc/Metadata$AsciiMarshaller;)Lio/grpc/Metadata$Key;
     318: astore        8
     320: aload         7
     322: aload         8
     324: new           #72                 // class java/lang/StringBuilder
     327: dup
     328: invokespecial #73                 // Method java/lang/StringBuilder."<init>":()V
     331: ldc           #74                 // String Bearer
     333: invokevirtual #75                 // Method java/lang/StringBuilder.append:(Ljava/lang/String;)Ljava/lang/StringBuilder;
     336: aload_0
     337: getfield      #13                 // Field istioEnv:Lorg/apache/dubbo/registry/xds/istio/IstioEnv;
     340: invokevirtual #76                 // Method org/apache/dubbo/registry/xds/istio/IstioEnv.getServiceAccount:()Ljava/lang/String;
     343: invokevirtual #75                 // Method java/lang/StringBuilder.append:(Ljava/lang/String;)Ljava/lang/StringBuilder;
     346: invokevirtual #77                 // Method java/lang/StringBuilder.toString:()Ljava/lang/String;
     349: invokevirtual #78                 // Method io/grpc/Metadata.put:(Lio/grpc/Metadata$Key;Ljava/lang/Object;)V
     352: ldc           #79                 // String ClusterID
     354: getstatic     #70                 // Field io/grpc/Metadata.ASCII_STRING_MARSHALLER:Lio/grpc/Metadata$AsciiMarshaller;
     357: invokestatic  #71                 // Method io/grpc/Metadata$Key.of:(Ljava/lang/String;Lio/grpc/Metadata$AsciiMarshaller;)Lio/grpc/Metadata$Key;
     360: astore        8
     362: aload         7
     364: aload         8
     366: aload_0
     367: getfield      #13                 // Field istioEnv:Lorg/apache/dubbo/registry/xds/istio/IstioEnv;
     370: invokevirtual #80                 // Method org/apache/dubbo/registry/xds/istio/IstioEnv.getIstioMetaClusterId:()Ljava/lang/String;
     373: invokevirtual #78                 // Method io/grpc/Metadata.put:(Lio/grpc/Metadata$Key;Ljava/lang/Object;)V
     376: aload         6
     378: invokestatic  #81                 // Method istio/v1/auth/IstioCertificateServiceGrpc.newStub:(Lio/grpc/Channel;)Listio/v1/auth/IstioCertificateServiceGrpc$IstioCertificateServiceStub;
     381: astore        9
     383: aload         9
     385: aload         7
     387: invokestatic  #82                 // Method io/grpc/stub/MetadataUtils.attachHeaders:(Lio/grpc/stub/AbstractStub;Lio/grpc/Metadata;)Lio/grpc/stub/AbstractStub;
     390: checkcast     #83                 // class istio/v1/auth/IstioCertificateServiceGrpc$IstioCertificateServiceStub
     393: astore        9
     395: new           #84                 // class java/util/concurrent/CountDownLatch
     398: dup
     399: iconst_1
     400: invokespecial #85                 // Method java/util/concurrent/CountDownLatch."<init>":(I)V
     403: astore        10
     405: new           #86                 // class java/lang/StringBuffer
     408: dup
     409: invokespecial #87                 // Method java/lang/StringBuffer."<init>":()V
     412: astore        11
     414: new           #88                 // class java/util/concurrent/atomic/AtomicBoolean
     417: dup
     418: iconst_0
     419: invokespecial #89                 // Method java/util/concurrent/atomic/AtomicBoolean."<init>":(Z)V
     422: astore        12
     424: aload         9
     426: aload_0
     427: aload         4
     429: invokespecial #90                 // Method generateRequest:(Ljava/lang/String;)Listio/v1/auth/IstioCertificateRequest;
     432: aload_0
     433: aload         10
     435: aload         11
     437: aload         12
     439: invokespecial #91                 // Method generateResponseObserver:(Ljava/util/concurrent/CountDownLatch;Ljava/lang/StringBuffer;Ljava/util/concurrent/atomic/AtomicBoolean;)Lio/grpc/stub/StreamObserver;
     442: invokevirtual #92                 // Method istio/v1/auth/IstioCertificateServiceGrpc$IstioCertificateServiceStub.createCertificate:(Listio/v1/auth/IstioCertificateRequest;Lio/grpc/stub/StreamObserver;)V
     445: invokestatic  #93                 // Method java/lang/System.currentTimeMillis:()J
     448: aload_0
     449: getfield      #13                 // Field istioEnv:Lorg/apache/dubbo/registry/xds/istio/IstioEnv;
     452: invokevirtual #94                 // Method org/apache/dubbo/registry/xds/istio/IstioEnv.getSecretTTL:()I
     455: i2f
     456: aload_0
     457: getfield      #13                 // Field istioEnv:Lorg/apache/dubbo/registry/xds/istio/IstioEnv;
     460: invokevirtual #95                 // Method org/apache/dubbo/registry/xds/istio/IstioEnv.getSecretGracePeriodRatio:()F
     463: fmul
     464: f2l
     465: ladd
     466: lstore        13
     468: aload         10
     470: invokevirtual #96                 // Method java/util/concurrent/CountDownLatch.await:()V
     473: goto          490
     476: astore        15
     478: new           #22                 // class org/apache/dubbo/rpc/RpcException
     481: dup
     482: ldc           #98                 // String Generate Cert Failed. Wait for cert failed.
     484: aload         15
     486: invokespecial #23                 // Method org/apache/dubbo/rpc/RpcException."<init>":(Ljava/lang/String;Ljava/lang/Throwable;)V
     489: athrow
     490: aload         12
     492: invokevirtual #99                 // Method java/util/concurrent/atomic/AtomicBoolean.get:()Z
     495: ifeq          508
     498: new           #22                 // class org/apache/dubbo/rpc/RpcException
     501: dup
     502: ldc           #100                // String Generate Cert Failed. Send csr request failed. Please check log above.
     504: invokespecial #101                // Method org/apache/dubbo/rpc/RpcException."<init>":(Ljava/lang/String;)V
     507: athrow
     508: aload_0
     509: aload_2
     510: invokespecial #102                // Method generatePrivatePemKey:(Ljava/security/PrivateKey;)Ljava/lang/String;
     513: astore        15
     515: new           #103                // class org/apache/dubbo/registry/xds/XdsCertificateSigner$CertPair
     518: dup
     519: aload         15
     521: aload         11
     523: invokevirtual #104                // Method java/lang/StringBuffer.toString:()Ljava/lang/String;
     526: invokestatic  #93                 // Method java/lang/System.currentTimeMillis:()J
     529: lload         13
     531: invokespecial #105                // Method org/apache/dubbo/registry/xds/XdsCertificateSigner$CertPair."<init>":(Ljava/lang/String;Ljava/lang/String;JJ)V
     534: astore        16
     536: aload         6
     538: invokevirtual #106                // Method io/grpc/ManagedChannel.shutdown:()Lio/grpc/ManagedChannel;
     541: pop
     542: aload         16
     544: areturn
    Exception table:
       from    to  target type
          16    85    88   Class java/security/NoSuchAlgorithmException
          16    85    88   Class java/security/InvalidAlgorithmParameterException
          16    85    88   Class org/bouncycastle/operator/OperatorCreationException
         112   168   171   Class java/security/NoSuchAlgorithmException
         112   168   171   Class org/bouncycastle/operator/OperatorCreationException
         468   473   476   Class java/lang/InterruptedException

  private istio.v1.auth.IstioCertificateRequest generateRequest(java.lang.String);
    Code:
       0: invokestatic  #107                // Method istio/v1/auth/IstioCertificateRequest.newBuilder:()Listio/v1/auth/IstioCertificateRequest$Builder;
       3: aload_1
       4: invokevirtual #108                // Method istio/v1/auth/IstioCertificateRequest$Builder.setCsr:(Ljava/lang/String;)Listio/v1/auth/IstioCertificateRequest$Builder;
       7: aload_0
       8: getfield      #13                 // Field istioEnv:Lorg/apache/dubbo/registry/xds/istio/IstioEnv;
      11: invokevirtual #94                 // Method org/apache/dubbo/registry/xds/istio/IstioEnv.getSecretTTL:()I
      14: i2l
      15: invokevirtual #109                // Method istio/v1/auth/IstioCertificateRequest$Builder.setValidityDuration:(J)Listio/v1/auth/IstioCertificateRequest$Builder;
      18: invokevirtual #110                // Method istio/v1/auth/IstioCertificateRequest$Builder.build:()Listio/v1/auth/IstioCertificateRequest;
      21: areturn

  private io.grpc.stub.StreamObserver<istio.v1.auth.IstioCertificateResponse> generateResponseObserver(java.util.concurrent.CountDownLatch, java.lang.StringBuffer, java.util.concurrent.atomic.AtomicBoolean);
    Code:
       0: new           #111                // class org/apache/dubbo/registry/xds/istio/IstioCitadelCertificateSigner$1
       3: dup
       4: aload_0
       5: aload_2
       6: aload_1
       7: aload_3
       8: invokespecial #112                // Method org/apache/dubbo/registry/xds/istio/IstioCitadelCertificateSigner$1."<init>":(Lorg/apache/dubbo/registry/xds/istio/IstioCitadelCertificateSigner;Ljava/lang/StringBuffer;Ljava/util/concurrent/CountDownLatch;Ljava/util/concurrent/atomic/AtomicBoolean;)V
      11: areturn

  private java.lang.String generatePrivatePemKey(java.security.PrivateKey) throws java.io.IOException;
    Code:
       0: aload_0
       1: ldc           #113                // String RSA PRIVATE KEY
       3: aload_1
       4: invokeinterface #114,  1          // InterfaceMethod java/security/PrivateKey.getEncoded:()[B
       9: invokespecial #115                // Method generatePemKey:(Ljava/lang/String;[B)Ljava/lang/String;
      12: astore_2
      13: getstatic     #2                  // Field logger:Lorg/apache/dubbo/common/logger/ErrorTypeAwareLogger;
      16: invokeinterface #116,  1          // InterfaceMethod org/apache/dubbo/common/logger/ErrorTypeAwareLogger.isDebugEnabled:()Z
      21: ifeq          51
      24: getstatic     #2                  // Field logger:Lorg/apache/dubbo/common/logger/ErrorTypeAwareLogger;
      27: new           #72                 // class java/lang/StringBuilder
      30: dup
      31: invokespecial #73                 // Method java/lang/StringBuilder."<init>":()V
      34: ldc           #117                // String Generated Private Key. \n
      36: invokevirtual #75                 // Method java/lang/StringBuilder.append:(Ljava/lang/String;)Ljava/lang/StringBuilder;
      39: aload_2
      40: invokevirtual #75                 // Method java/lang/StringBuilder.append:(Ljava/lang/String;)Ljava/lang/StringBuilder;
      43: invokevirtual #77                 // Method java/lang/StringBuilder.toString:()Ljava/lang/String;
      46: invokeinterface #118,  2          // InterfaceMethod org/apache/dubbo/common/logger/ErrorTypeAwareLogger.debug:(Ljava/lang/String;)V
      51: aload_2
      52: areturn

  private java.lang.String generatePemKey(java.lang.String, byte[]) throws java.io.IOException;
    Code:
       0: new           #119                // class org/bouncycastle/util/io/pem/PemObject
       3: dup
       4: aload_1
       5: aload_2
       6: invokespecial #120                // Method org/bouncycastle/util/io/pem/PemObject."<init>":(Ljava/lang/String;[B)V
       9: astore_3
      10: new           #121                // class java/io/StringWriter
      13: dup
      14: invokespecial #122                // Method java/io/StringWriter."<init>":()V
      17: astore        4
      19: new           #123                // class org/bouncycastle/openssl/jcajce/JcaPEMWriter
      22: dup
      23: aload         4
      25: invokespecial #124                // Method org/bouncycastle/openssl/jcajce/JcaPEMWriter."<init>":(Ljava/io/Writer;)V
      28: astore        5
      30: aload         5
      32: aload_3
      33: invokevirtual #125                // Method org/bouncycastle/openssl/jcajce/JcaPEMWriter.writeObject:(Lorg/bouncycastle/util/io/pem/PemObjectGenerator;)V
      36: aload         5
      38: invokevirtual #126                // Method org/bouncycastle/openssl/jcajce/JcaPEMWriter.close:()V
      41: aload         4
      43: invokevirtual #127                // Method java/io/StringWriter.close:()V
      46: aload         4
      48: invokevirtual #128                // Method java/io/StringWriter.toString:()Ljava/lang/String;
      51: areturn

  private java.lang.String generateCsr(java.security.PublicKey, org.bouncycastle.operator.ContentSigner) throws java.io.IOException;
    Code:
       0: new           #129                // class org/bouncycastle/asn1/x509/GeneralNames
       3: dup
       4: iconst_1
       5: anewarray     #130                // class org/bouncycastle/asn1/x509/GeneralName
       8: dup
       9: iconst_0
      10: new           #130                // class org/bouncycastle/asn1/x509/GeneralName
      13: dup
      14: bipush        6
      16: aload_0
      17: getfield      #13                 // Field istioEnv:Lorg/apache/dubbo/registry/xds/istio/IstioEnv;
      20: invokevirtual #131                // Method org/apache/dubbo/registry/xds/istio/IstioEnv.getCsrHost:()Ljava/lang/String;
      23: invokespecial #132                // Method org/bouncycastle/asn1/x509/GeneralName."<init>":(ILjava/lang/String;)V
      26: aastore
      27: invokespecial #133                // Method org/bouncycastle/asn1/x509/GeneralNames."<init>":([Lorg/bouncycastle/asn1/x509/GeneralName;)V
      30: astore_3
      31: new           #134                // class org/bouncycastle/asn1/x509/ExtensionsGenerator
      34: dup
      35: invokespecial #135                // Method org/bouncycastle/asn1/x509/ExtensionsGenerator."<init>":()V
      38: astore        4
      40: aload         4
      42: getstatic     #136                // Field org/bouncycastle/asn1/x509/Extension.subjectAlternativeName:Lorg/bouncycastle/asn1/ASN1ObjectIdentifier;
      45: iconst_1
      46: aload_3
      47: invokevirtual #137                // Method org/bouncycastle/asn1/x509/ExtensionsGenerator.addExtension:(Lorg/bouncycastle/asn1/ASN1ObjectIdentifier;ZLorg/bouncycastle/asn1/ASN1Encodable;)V
      50: new           #138                // class org/bouncycastle/pkcs/jcajce/JcaPKCS10CertificationRequestBuilder
      53: dup
      54: new           #139                // class org/bouncycastle/asn1/x500/X500Name
      57: dup
      58: new           #72                 // class java/lang/StringBuilder
      61: dup
      62: invokespecial #73                 // Method java/lang/StringBuilder."<init>":()V
      65: ldc           #140                // String O=
      67: invokevirtual #75                 // Method java/lang/StringBuilder.append:(Ljava/lang/String;)Ljava/lang/StringBuilder;
      70: aload_0
      71: getfield      #13                 // Field istioEnv:Lorg/apache/dubbo/registry/xds/istio/IstioEnv;
      74: invokevirtual #141                // Method org/apache/dubbo/registry/xds/istio/IstioEnv.getTrustDomain:()Ljava/lang/String;
      77: invokevirtual #75                 // Method java/lang/StringBuilder.append:(Ljava/lang/String;)Ljava/lang/StringBuilder;
      80: invokevirtual #77                 // Method java/lang/StringBuilder.toString:()Ljava/lang/String;
      83: invokespecial #142                // Method org/bouncycastle/asn1/x500/X500Name."<init>":(Ljava/lang/String;)V
      86: aload_1
      87: invokespecial #143                // Method org/bouncycastle/pkcs/jcajce/JcaPKCS10CertificationRequestBuilder."<init>":(Lorg/bouncycastle/asn1/x500/X500Name;Ljava/security/PublicKey;)V
      90: getstatic     #144                // Field org/bouncycastle/asn1/pkcs/PKCSObjectIdentifiers.pkcs_9_at_extensionRequest:Lorg/bouncycastle/asn1/ASN1ObjectIdentifier;
      93: aload         4
      95: invokevirtual #145                // Method org/bouncycastle/asn1/x509/ExtensionsGenerator.generate:()Lorg/bouncycastle/asn1/x509/Extensions;
      98: invokevirtual #146                // Method org/bouncycastle/pkcs/jcajce/JcaPKCS10CertificationRequestBuilder.addAttribute:(Lorg/bouncycastle/asn1/ASN1ObjectIdentifier;Lorg/bouncycastle/asn1/ASN1Encodable;)Lorg/bouncycastle/pkcs/PKCS10CertificationRequestBuilder;
     101: aload_2
     102: invokevirtual #147                // Method org/bouncycastle/pkcs/PKCS10CertificationRequestBuilder.build:(Lorg/bouncycastle/operator/ContentSigner;)Lorg/bouncycastle/pkcs/PKCS10CertificationRequest;
     105: astore        5
     107: aload_0
     108: ldc           #148                // String CERTIFICATE REQUEST
     110: aload         5
     112: invokevirtual #149                // Method org/bouncycastle/pkcs/PKCS10CertificationRequest.getEncoded:()[B
     115: invokespecial #115                // Method generatePemKey:(Ljava/lang/String;[B)Ljava/lang/String;
     118: astore        6
     120: getstatic     #2                  // Field logger:Lorg/apache/dubbo/common/logger/ErrorTypeAwareLogger;
     123: invokeinterface #116,  1          // InterfaceMethod org/apache/dubbo/common/logger/ErrorTypeAwareLogger.isDebugEnabled:()Z
     128: ifeq          159
     131: getstatic     #2                  // Field logger:Lorg/apache/dubbo/common/logger/ErrorTypeAwareLogger;
     134: new           #72                 // class java/lang/StringBuilder
     137: dup
     138: invokespecial #73                 // Method java/lang/StringBuilder."<init>":()V
     141: ldc           #150                // String CSR Request to Istio Citadel. \n
     143: invokevirtual #75                 // Method java/lang/StringBuilder.append:(Ljava/lang/String;)Ljava/lang/StringBuilder;
     146: aload         6
     148: invokevirtual #75                 // Method java/lang/StringBuilder.append:(Ljava/lang/String;)Ljava/lang/StringBuilder;
     151: invokevirtual #77                 // Method java/lang/StringBuilder.toString:()Ljava/lang/String;
     154: invokeinterface #118,  2          // InterfaceMethod org/apache/dubbo/common/logger/ErrorTypeAwareLogger.debug:(Ljava/lang/String;)V
     159: aload         6
     161: areturn

  static org.apache.dubbo.registry.xds.XdsCertificateSigner$CertPair access$100(org.apache.dubbo.registry.xds.istio.IstioCitadelCertificateSigner);
    Code:
       0: aload_0
       1: invokespecial #3                  // Method doGenerateCert:()Lorg/apache/dubbo/registry/xds/XdsCertificateSigner$CertPair;
       4: areturn

  static org.apache.dubbo.common.logger.ErrorTypeAwareLogger access$200();
    Code:
       0: getstatic     #2                  // Field logger:Lorg/apache/dubbo/common/logger/ErrorTypeAwareLogger;
       3: areturn

  static {};
    Code:
       0: ldc           #151                // class org/apache/dubbo/registry/xds/istio/IstioCitadelCertificateSigner
       2: invokestatic  #152                // Method org/apache/dubbo/common/logger/LoggerFactory.getErrorTypeAwareLogger:(Ljava/lang/Class;)Lorg/apache/dubbo/common/logger/ErrorTypeAwareLogger;
       5: putstatic     #2                  // Field logger:Lorg/apache/dubbo/common/logger/ErrorTypeAwareLogger;
       8: return
}
