Compiled from "IstioEnv.java"
public class org.apache.dubbo.registry.xds.istio.IstioEnv implements org.apache.dubbo.registry.xds.XdsEnv {
  private static final org.apache.dubbo.common.logger.ErrorTypeAwareLogger logger;

  private static final org.apache.dubbo.registry.xds.istio.IstioEnv INSTANCE;

  private java.lang.String podName;

  private java.lang.String caAddr;

  private java.lang.String jwtPolicy;

  private java.lang.String trustDomain;

  private java.lang.String workloadNameSpace;

  private int rasKeySize;

  private java.lang.String eccSigAlg;

  private int secretTTL;

  private float secretGracePeriodRatio;

  private java.lang.String istioMetaClusterId;

  private java.lang.String pilotCertProvider;

  private org.apache.dubbo.registry.xds.istio.IstioEnv();
    Code:
       0: aload_0
       1: invokespecial #3                  // Method java/lang/Object."<init>":()V
       4: aload_0
       5: ldc           #4                  // String JWT_POLICY
       7: invokestatic  #5                  // Method java/lang/System.getenv:(Ljava/lang/String;)Ljava/lang/String;
      10: invokestatic  #6                  // Method java/util/Optional.ofNullable:(Ljava/lang/Object;)Ljava/util/Optional;
      13: ldc           #7                  // String first-party-jwt
      15: invokevirtual #8                  // Method java/util/Optional.orElse:(Ljava/lang/Object;)Ljava/lang/Object;
      18: checkcast     #9                  // class java/lang/String
      21: putfield      #10                 // Field jwtPolicy:Ljava/lang/String;
      24: aload_0
      25: ldc           #11                 // String POD_NAME
      27: invokestatic  #5                  // Method java/lang/System.getenv:(Ljava/lang/String;)Ljava/lang/String;
      30: invokestatic  #6                  // Method java/util/Optional.ofNullable:(Ljava/lang/Object;)Ljava/util/Optional;
      33: ldc           #12                 // String HOSTNAME
      35: invokestatic  #5                  // Method java/lang/System.getenv:(Ljava/lang/String;)Ljava/lang/String;
      38: invokevirtual #8                  // Method java/util/Optional.orElse:(Ljava/lang/Object;)Ljava/lang/Object;
      41: checkcast     #9                  // class java/lang/String
      44: putfield      #13                 // Field podName:Ljava/lang/String;
      47: aload_0
      48: ldc           #14                 // String TRUST_DOMAIN
      50: invokestatic  #5                  // Method java/lang/System.getenv:(Ljava/lang/String;)Ljava/lang/String;
      53: invokestatic  #6                  // Method java/util/Optional.ofNullable:(Ljava/lang/Object;)Ljava/util/Optional;
      56: ldc           #15                 // String cluster.local
      58: invokevirtual #8                  // Method java/util/Optional.orElse:(Ljava/lang/Object;)Ljava/lang/Object;
      61: checkcast     #9                  // class java/lang/String
      64: putfield      #16                 // Field trustDomain:Ljava/lang/String;
      67: aload_0
      68: ldc           #17                 // String WORKLOAD_NAMESPACE
      70: invokestatic  #5                  // Method java/lang/System.getenv:(Ljava/lang/String;)Ljava/lang/String;
      73: invokestatic  #6                  // Method java/util/Optional.ofNullable:(Ljava/lang/Object;)Ljava/util/Optional;
      76: invokedynamic #18,  0             // InvokeDynamic #0:get:()Ljava/util/function/Supplier;
      81: invokevirtual #19                 // Method java/util/Optional.orElseGet:(Ljava/util/function/Supplier;)Ljava/lang/Object;
      84: checkcast     #9                  // class java/lang/String
      87: putfield      #20                 // Field workloadNameSpace:Ljava/lang/String;
      90: aload_0
      91: ldc           #21                 // String CA_ADDR
      93: invokestatic  #5                  // Method java/lang/System.getenv:(Ljava/lang/String;)Ljava/lang/String;
      96: invokestatic  #6                  // Method java/util/Optional.ofNullable:(Ljava/lang/Object;)Ljava/util/Optional;
      99: ldc           #22                 // String istiod.istio-system.svc:15012
     101: invokevirtual #8                  // Method java/util/Optional.orElse:(Ljava/lang/Object;)Ljava/lang/Object;
     104: checkcast     #9                  // class java/lang/String
     107: putfield      #23                 // Field caAddr:Ljava/lang/String;
     110: aload_0
     111: ldc           #24                 // String RSA_KEY_SIZE
     113: invokestatic  #5                  // Method java/lang/System.getenv:(Ljava/lang/String;)Ljava/lang/String;
     116: invokestatic  #6                  // Method java/util/Optional.ofNullable:(Ljava/lang/Object;)Ljava/util/Optional;
     119: ldc           #25                 // String 2048
     121: invokevirtual #8                  // Method java/util/Optional.orElse:(Ljava/lang/Object;)Ljava/lang/Object;
     124: checkcast     #9                  // class java/lang/String
     127: invokestatic  #26                 // Method java/lang/Integer.parseInt:(Ljava/lang/String;)I
     130: putfield      #27                 // Field rasKeySize:I
     133: aload_0
     134: ldc           #28                 // String ECC_SIGNATURE_ALGORITHM
     136: invokestatic  #5                  // Method java/lang/System.getenv:(Ljava/lang/String;)Ljava/lang/String;
     139: invokestatic  #6                  // Method java/util/Optional.ofNullable:(Ljava/lang/Object;)Ljava/util/Optional;
     142: ldc           #29                 // String ECDSA
     144: invokevirtual #8                  // Method java/util/Optional.orElse:(Ljava/lang/Object;)Ljava/lang/Object;
     147: checkcast     #9                  // class java/lang/String
     150: putfield      #30                 // Field eccSigAlg:Ljava/lang/String;
     153: aload_0
     154: ldc           #31                 // String SECRET_TTL
     156: invokestatic  #5                  // Method java/lang/System.getenv:(Ljava/lang/String;)Ljava/lang/String;
     159: invokestatic  #6                  // Method java/util/Optional.ofNullable:(Ljava/lang/Object;)Ljava/util/Optional;
     162: ldc           #32                 // String 86400
     164: invokevirtual #8                  // Method java/util/Optional.orElse:(Ljava/lang/Object;)Ljava/lang/Object;
     167: checkcast     #9                  // class java/lang/String
     170: invokestatic  #26                 // Method java/lang/Integer.parseInt:(Ljava/lang/String;)I
     173: putfield      #33                 // Field secretTTL:I
     176: aload_0
     177: ldc           #34                 // String SECRET_GRACE_PERIOD_RATIO
     179: invokestatic  #5                  // Method java/lang/System.getenv:(Ljava/lang/String;)Ljava/lang/String;
     182: invokestatic  #6                  // Method java/util/Optional.ofNullable:(Ljava/lang/Object;)Ljava/util/Optional;
     185: ldc           #35                 // String 0.5
     187: invokevirtual #8                  // Method java/util/Optional.orElse:(Ljava/lang/Object;)Ljava/lang/Object;
     190: checkcast     #9                  // class java/lang/String
     193: invokestatic  #36                 // Method java/lang/Float.parseFloat:(Ljava/lang/String;)F
     196: putfield      #37                 // Field secretGracePeriodRatio:F
     199: aload_0
     200: ldc           #38                 // String ISTIO_META_CLUSTER_ID
     202: invokestatic  #5                  // Method java/lang/System.getenv:(Ljava/lang/String;)Ljava/lang/String;
     205: invokestatic  #6                  // Method java/util/Optional.ofNullable:(Ljava/lang/Object;)Ljava/util/Optional;
     208: ldc           #39                 // String Kubernetes
     210: invokevirtual #8                  // Method java/util/Optional.orElse:(Ljava/lang/Object;)Ljava/lang/Object;
     213: checkcast     #9                  // class java/lang/String
     216: putfield      #40                 // Field istioMetaClusterId:Ljava/lang/String;
     219: aload_0
     220: ldc           #41                 // String PILOT_CERT_PROVIDER
     222: invokestatic  #5                  // Method java/lang/System.getenv:(Ljava/lang/String;)Ljava/lang/String;
     225: invokestatic  #6                  // Method java/util/Optional.ofNullable:(Ljava/lang/Object;)Ljava/util/Optional;
     228: ldc           #42                 // String
     230: invokevirtual #8                  // Method java/util/Optional.orElse:(Ljava/lang/Object;)Ljava/lang/Object;
     233: checkcast     #9                  // class java/lang/String
     236: putfield      #43                 // Field pilotCertProvider:Ljava/lang/String;
     239: aload_0
     240: invokevirtual #44                 // Method getServiceAccount:()Ljava/lang/String;
     243: ifnonnull     256
     246: new           #45                 // class java/lang/UnsupportedOperationException
     249: dup
     250: ldc           #46                 // String Unable to found kubernetes service account token file. Please check if work in Kubernetes and mount service account token file correctly.
     252: invokespecial #47                 // Method java/lang/UnsupportedOperationException."<init>":(Ljava/lang/String;)V
     255: athrow
     256: return

  public static org.apache.dubbo.registry.xds.istio.IstioEnv getInstance();
    Code:
       0: getstatic     #48                 // Field INSTANCE:Lorg/apache/dubbo/registry/xds/istio/IstioEnv;
       3: areturn

  public java.lang.String getPodName();
    Code:
       0: aload_0
       1: getfield      #13                 // Field podName:Ljava/lang/String;
       4: areturn

  public java.lang.String getCaAddr();
    Code:
       0: aload_0
       1: getfield      #23                 // Field caAddr:Ljava/lang/String;
       4: areturn

  public java.lang.String getServiceAccount();
    Code:
       0: aload_0
       1: getfield      #10                 // Field jwtPolicy:Ljava/lang/String;
       4: astore_2
       5: iconst_m1
       6: istore_3
       7: aload_2
       8: invokevirtual #49                 // Method java/lang/String.hashCode:()I
      11: lookupswitch  { // 2
             445538947: 36
            1779981434: 50
               default: 61
          }
      36: aload_2
      37: ldc           #7                  // String first-party-jwt
      39: invokevirtual #50                 // Method java/lang/String.equals:(Ljava/lang/Object;)Z
      42: ifeq          61
      45: iconst_0
      46: istore_3
      47: goto          61
      50: aload_2
      51: ldc           #51                 // String third-party-jwt
      53: invokevirtual #50                 // Method java/lang/String.equals:(Ljava/lang/Object;)Z
      56: ifeq          61
      59: iconst_1
      60: istore_3
      61: iload_3
      62: lookupswitch  { // 2
                     0: 88
                     1: 101
               default: 101
          }
      88: new           #52                 // class java/io/File
      91: dup
      92: ldc           #53                 // String /var/run/secrets/kubernetes.io/serviceaccount/token
      94: invokespecial #54                 // Method java/io/File."<init>":(Ljava/lang/String;)V
      97: astore_1
      98: goto          111
     101: new           #52                 // class java/io/File
     104: dup
     105: ldc           #55                 // String /var/run/secrets/tokens/istio-token
     107: invokespecial #54                 // Method java/io/File."<init>":(Ljava/lang/String;)V
     110: astore_1
     111: aload_1
     112: invokevirtual #56                 // Method java/io/File.canRead:()Z
     115: ifeq          144
     118: aload_1
     119: getstatic     #57                 // Field java/nio/charset/StandardCharsets.UTF_8:Ljava/nio/charset/Charset;
     122: invokestatic  #58                 // Method org/apache/commons/io/FileUtils.readFileToString:(Ljava/io/File;Ljava/nio/charset/Charset;)Ljava/lang/String;
     125: areturn
     126: astore_2
     127: getstatic     #60                 // Field logger:Lorg/apache/dubbo/common/logger/ErrorTypeAwareLogger;
     130: ldc           #61                 // String 1-41
     132: ldc           #62                 // String File Read Failed
     134: ldc           #42                 // String
     136: ldc           #63                 // String Unable to read token file.
     138: aload_2
     139: invokeinterface #64,  6           // InterfaceMethod org/apache/dubbo/common/logger/ErrorTypeAwareLogger.error:(Ljava/lang/String;Ljava/lang/String;Ljava/lang/String;Ljava/lang/String;Ljava/lang/Throwable;)V
     144: aconst_null
     145: areturn
    Exception table:
       from    to  target type
         118   125   126   Class java/io/IOException

  public java.lang.String getCsrHost();
    Code:
       0: new           #65                 // class java/lang/StringBuilder
       3: dup
       4: invokespecial #66                 // Method java/lang/StringBuilder."<init>":()V
       7: ldc           #67                 // String spiffe://
       9: invokevirtual #68                 // Method java/lang/StringBuilder.append:(Ljava/lang/String;)Ljava/lang/StringBuilder;
      12: aload_0
      13: getfield      #16                 // Field trustDomain:Ljava/lang/String;
      16: invokevirtual #68                 // Method java/lang/StringBuilder.append:(Ljava/lang/String;)Ljava/lang/StringBuilder;
      19: ldc           #69                 // String /ns/
      21: invokevirtual #68                 // Method java/lang/StringBuilder.append:(Ljava/lang/String;)Ljava/lang/StringBuilder;
      24: aload_0
      25: getfield      #20                 // Field workloadNameSpace:Ljava/lang/String;
      28: invokevirtual #68                 // Method java/lang/StringBuilder.append:(Ljava/lang/String;)Ljava/lang/StringBuilder;
      31: ldc           #70                 // String /sa/
      33: invokevirtual #68                 // Method java/lang/StringBuilder.append:(Ljava/lang/String;)Ljava/lang/StringBuilder;
      36: aload_0
      37: invokevirtual #44                 // Method getServiceAccount:()Ljava/lang/String;
      40: invokevirtual #68                 // Method java/lang/StringBuilder.append:(Ljava/lang/String;)Ljava/lang/StringBuilder;
      43: invokevirtual #71                 // Method java/lang/StringBuilder.toString:()Ljava/lang/String;
      46: areturn

  public java.lang.String getTrustDomain();
    Code:
       0: aload_0
       1: getfield      #16                 // Field trustDomain:Ljava/lang/String;
       4: areturn

  public java.lang.String getWorkloadNameSpace();
    Code:
       0: aload_0
       1: getfield      #20                 // Field workloadNameSpace:Ljava/lang/String;
       4: areturn

  public java.lang.String getCluster();
    Code:
       0: aconst_null
       1: areturn

  public int getRasKeySize();
    Code:
       0: aload_0
       1: getfield      #27                 // Field rasKeySize:I
       4: ireturn

  public boolean isECCFirst();
    Code:
       0: ldc           #29                 // String ECDSA
       2: aload_0
       3: getfield      #30                 // Field eccSigAlg:Ljava/lang/String;
       6: invokevirtual #50                 // Method java/lang/String.equals:(Ljava/lang/Object;)Z
       9: ireturn

  public int getSecretTTL();
    Code:
       0: aload_0
       1: getfield      #33                 // Field secretTTL:I
       4: ireturn

  public float getSecretGracePeriodRatio();
    Code:
       0: aload_0
       1: getfield      #37                 // Field secretGracePeriodRatio:F
       4: freturn

  public java.lang.String getIstioMetaClusterId();
    Code:
       0: aload_0
       1: getfield      #40                 // Field istioMetaClusterId:Ljava/lang/String;
       4: areturn

  public java.lang.String getCaCert();
    Code:
       0: ldc           #72                 // String istiod
       2: aload_0
       3: getfield      #43                 // Field pilotCertProvider:Ljava/lang/String;
       6: invokevirtual #50                 // Method java/lang/String.equals:(Ljava/lang/Object;)Z
       9: ifeq          25
      12: new           #52                 // class java/io/File
      15: dup
      16: ldc           #73                 // String /var/run/secrets/istio/root-cert.pem
      18: invokespecial #54                 // Method java/io/File."<init>":(Ljava/lang/String;)V
      21: astore_1
      22: goto          27
      25: aconst_null
      26: areturn
      27: aload_1
      28: invokevirtual #56                 // Method java/io/File.canRead:()Z
      31: ifeq          60
      34: aload_1
      35: getstatic     #57                 // Field java/nio/charset/StandardCharsets.UTF_8:Ljava/nio/charset/Charset;
      38: invokestatic  #58                 // Method org/apache/commons/io/FileUtils.readFileToString:(Ljava/io/File;Ljava/nio/charset/Charset;)Ljava/lang/String;
      41: areturn
      42: astore_2
      43: getstatic     #60                 // Field logger:Lorg/apache/dubbo/common/logger/ErrorTypeAwareLogger;
      46: ldc           #61                 // String 1-41
      48: ldc           #62                 // String File Read Failed
      50: ldc           #42                 // String
      52: ldc           #74                 // String read ca file error
      54: aload_2
      55: invokeinterface #64,  6           // InterfaceMethod org/apache/dubbo/common/logger/ErrorTypeAwareLogger.error:(Ljava/lang/String;Ljava/lang/String;Ljava/lang/String;Ljava/lang/String;Ljava/lang/Throwable;)V
      60: aconst_null
      61: areturn
    Exception table:
       from    to  target type
          34    41    42   Class java/io/IOException

  private static java.lang.String lambda$new$0();
    Code:
       0: new           #52                 // class java/io/File
       3: dup
       4: ldc           #75                 // String /var/run/secrets/kubernetes.io/serviceaccount/namespace
       6: invokespecial #54                 // Method java/io/File."<init>":(Ljava/lang/String;)V
       9: astore_0
      10: aload_0
      11: invokevirtual #56                 // Method java/io/File.canRead:()Z
      14: ifeq          43
      17: aload_0
      18: getstatic     #57                 // Field java/nio/charset/StandardCharsets.UTF_8:Ljava/nio/charset/Charset;
      21: invokestatic  #58                 // Method org/apache/commons/io/FileUtils.readFileToString:(Ljava/io/File;Ljava/nio/charset/Charset;)Ljava/lang/String;
      24: areturn
      25: astore_1
      26: getstatic     #60                 // Field logger:Lorg/apache/dubbo/common/logger/ErrorTypeAwareLogger;
      29: ldc           #76                 // String 1-29
      31: ldc           #42                 // String
      33: ldc           #42                 // String
      35: ldc           #77                 // String read namespace file error
      37: aload_1
      38: invokeinterface #64,  6           // InterfaceMethod org/apache/dubbo/common/logger/ErrorTypeAwareLogger.error:(Ljava/lang/String;Ljava/lang/String;Ljava/lang/String;Ljava/lang/String;Ljava/lang/Throwable;)V
      43: ldc           #78                 // String default
      45: areturn
    Exception table:
       from    to  target type
          17    24    25   Class java/io/IOException

  static {};
    Code:
       0: ldc           #79                 // class org/apache/dubbo/registry/xds/istio/IstioEnv
       2: invokestatic  #80                 // Method org/apache/dubbo/common/logger/LoggerFactory.getErrorTypeAwareLogger:(Ljava/lang/Class;)Lorg/apache/dubbo/common/logger/ErrorTypeAwareLogger;
       5: putstatic     #60                 // Field logger:Lorg/apache/dubbo/common/logger/ErrorTypeAwareLogger;
       8: new           #79                 // class org/apache/dubbo/registry/xds/istio/IstioEnv
      11: dup
      12: invokespecial #81                 // Method "<init>":()V
      15: putstatic     #48                 // Field INSTANCE:Lorg/apache/dubbo/registry/xds/istio/IstioEnv;
      18: return
}
