Compiled from "TempFileCreator.java"
abstract class com.google.common.io.TempFileCreator {
  static final com.google.common.io.TempFileCreator INSTANCE;

  abstract java.io.File createTempDir();

  abstract java.io.File createTempFile(java.lang.String) throws java.io.IOException;

  private static com.google.common.io.TempFileCreator pickSecureCreator();
    Code:
       0: ldc           #2                  // String java.nio.file.Path
       2: invokestatic  #3                  // Method java/lang/Class.forName:(Ljava/lang/String;)Ljava/lang/Class;
       5: pop
       6: new           #4                  // class com/google/common/io/TempFileCreator$JavaNioCreator
       9: dup
      10: aconst_null
      11: invokespecial #5                  // Method com/google/common/io/TempFileCreator$JavaNioCreator."<init>":(Lcom/google/common/io/TempFileCreator$1;)V
      14: areturn
      15: astore_0
      16: ldc           #7                  // String android.os.Build$VERSION
      18: invokestatic  #3                  // Method java/lang/Class.forName:(Ljava/lang/String;)Ljava/lang/Class;
      21: ldc           #8                  // String SDK_INT
      23: invokevirtual #9                  // Method java/lang/Class.getField:(Ljava/lang/String;)Ljava/lang/reflect/Field;
      26: aconst_null
      27: invokevirtual #10                 // Method java/lang/reflect/Field.get:(Ljava/lang/Object;)Ljava/lang/Object;
      30: checkcast     #11                 // class java/lang/Integer
      33: invokevirtual #12                 // Method java/lang/Integer.intValue:()I
      36: istore_0
      37: ldc           #13                 // String android.os.Build$VERSION_CODES
      39: invokestatic  #3                  // Method java/lang/Class.forName:(Ljava/lang/String;)Ljava/lang/Class;
      42: ldc           #14                 // String JELLY_BEAN
      44: invokevirtual #9                  // Method java/lang/Class.getField:(Ljava/lang/String;)Ljava/lang/reflect/Field;
      47: aconst_null
      48: invokevirtual #10                 // Method java/lang/reflect/Field.get:(Ljava/lang/Object;)Ljava/lang/Object;
      51: checkcast     #11                 // class java/lang/Integer
      54: invokevirtual #12                 // Method java/lang/Integer.intValue:()I
      57: istore_1
      58: iload_0
      59: iload_1
      60: if_icmpge     72
      63: new           #15                 // class com/google/common/io/TempFileCreator$ThrowingCreator
      66: dup
      67: aconst_null
      68: invokespecial #16                 // Method com/google/common/io/TempFileCreator$ThrowingCreator."<init>":(Lcom/google/common/io/TempFileCreator$1;)V
      71: areturn
      72: goto          105
      75: astore_0
      76: new           #15                 // class com/google/common/io/TempFileCreator$ThrowingCreator
      79: dup
      80: aconst_null
      81: invokespecial #16                 // Method com/google/common/io/TempFileCreator$ThrowingCreator."<init>":(Lcom/google/common/io/TempFileCreator$1;)V
      84: areturn
      85: astore_0
      86: new           #15                 // class com/google/common/io/TempFileCreator$ThrowingCreator
      89: dup
      90: aconst_null
      91: invokespecial #16                 // Method com/google/common/io/TempFileCreator$ThrowingCreator."<init>":(Lcom/google/common/io/TempFileCreator$1;)V
      94: areturn
      95: astore_0
      96: new           #15                 // class com/google/common/io/TempFileCreator$ThrowingCreator
      99: dup
     100: aconst_null
     101: invokespecial #16                 // Method com/google/common/io/TempFileCreator$ThrowingCreator."<init>":(Lcom/google/common/io/TempFileCreator$1;)V
     104: areturn
     105: new           #19                 // class com/google/common/io/TempFileCreator$JavaIoCreator
     108: dup
     109: aconst_null
     110: invokespecial #20                 // Method com/google/common/io/TempFileCreator$JavaIoCreator."<init>":(Lcom/google/common/io/TempFileCreator$1;)V
     113: areturn
    Exception table:
       from    to  target type
           0    14    15   Class java/lang/ClassNotFoundException
          16    71    75   Class java/lang/NoSuchFieldException
          16    71    85   Class java/lang/ClassNotFoundException
          16    71    95   Class java/lang/IllegalAccessException

  private com.google.common.io.TempFileCreator();
    Code:
       0: aload_0
       1: invokespecial #21                 // Method java/lang/Object."<init>":()V
       4: return

  com.google.common.io.TempFileCreator(com.google.common.io.TempFileCreator$1);
    Code:
       0: aload_0
       1: invokespecial #1                  // Method "<init>":()V
       4: return

  static {};
    Code:
       0: invokestatic  #22                 // Method pickSecureCreator:()Lcom/google/common/io/TempFileCreator;
       3: putstatic     #23                 // Field INSTANCE:Lcom/google/common/io/TempFileCreator;
       6: return
}
