Compiled from "TempFileCreator.java"
class com.google.common.io.TempFileCreator$JavaNioCreator$1 implements java.nio.file.attribute.FileAttribute<com.google.common.collect.ImmutableList<java.nio.file.attribute.AclEntry>> {
  final com.google.common.collect.ImmutableList val$acl;

  com.google.common.io.TempFileCreator$JavaNioCreator$1(com.google.common.collect.ImmutableList);
    Code:
       0: aload_0
       1: aload_1
       2: putfield      #1                  // Field val$acl:Lcom/google/common/collect/ImmutableList;
       5: aload_0
       6: invokespecial #2                  // Method java/lang/Object."<init>":()V
       9: return

  public java.lang.String name();
    Code:
       0: ldc           #3                  // String acl:acl
       2: areturn

  public com.google.common.collect.ImmutableList<java.nio.file.attribute.AclEntry> value();
    Code:
       0: aload_0
       1: getfield      #1                  // Field val$acl:Lcom/google/common/collect/ImmutableList;
       4: areturn

  public java.lang.Object value();
    Code:
       0: aload_0
       1: invokevirtual #4                  // Method value:()Lcom/google/common/collect/ImmutableList;
       4: areturn
}
