Compiled from "TempFileCreator.java"
final class com.google.common.io.TempFileCreator$JavaIoCreator extends com.google.common.io.TempFileCreator {
  private static final int TEMP_DIR_ATTEMPTS;

  private com.google.common.io.TempFileCreator$JavaIoCreator();
    Code:
       0: aload_0
       1: aconst_null
       2: invokespecial #2                  // Method com/google/common/io/TempFileCreator."<init>":(Lcom/google/common/io/TempFileCreator$1;)V
       5: return

  java.io.File createTempDir();
    Code:
       0: new           #3                  // class java/io/File
       3: dup
       4: getstatic     #4                  // Field com/google/common/base/StandardSystemProperty.JAVA_IO_TMPDIR:Lcom/google/common/base/StandardSystemProperty;
       7: invokevirtual #5                  // Method com/google/common/base/StandardSystemProperty.value:()Ljava/lang/String;
      10: invokespecial #6                  // Method java/io/File."<init>":(Ljava/lang/String;)V
      13: astore_1
      14: new           #7                  // class java/lang/StringBuilder
      17: dup
      18: invokespecial #8                  // Method java/lang/StringBuilder."<init>":()V
      21: invokestatic  #9                  // Method java/lang/System.currentTimeMillis:()J
      24: invokevirtual #10                 // Method java/lang/StringBuilder.append:(J)Ljava/lang/StringBuilder;
      27: ldc           #11                 // String -
      29: invokevirtual #12                 // Method java/lang/StringBuilder.append:(Ljava/lang/String;)Ljava/lang/StringBuilder;
      32: invokevirtual #13                 // Method java/lang/StringBuilder.toString:()Ljava/lang/String;
      35: astore_2
      36: iconst_0
      37: istore_3
      38: iload_3
      39: sipush        10000
      42: if_icmpge     90
      45: new           #3                  // class java/io/File
      48: dup
      49: aload_1
      50: new           #7                  // class java/lang/StringBuilder
      53: dup
      54: invokespecial #8                  // Method java/lang/StringBuilder."<init>":()V
      57: aload_2
      58: invokevirtual #12                 // Method java/lang/StringBuilder.append:(Ljava/lang/String;)Ljava/lang/StringBuilder;
      61: iload_3
      62: invokevirtual #15                 // Method java/lang/StringBuilder.append:(I)Ljava/lang/StringBuilder;
      65: invokevirtual #13                 // Method java/lang/StringBuilder.toString:()Ljava/lang/String;
      68: invokespecial #16                 // Method java/io/File."<init>":(Ljava/io/File;Ljava/lang/String;)V
      71: astore        4
      73: aload         4
      75: invokevirtual #17                 // Method java/io/File.mkdir:()Z
      78: ifeq          84
      81: aload         4
      83: areturn
      84: iinc          3, 1
      87: goto          38
      90: new           #18                 // class java/lang/IllegalStateException
      93: dup
      94: new           #7                  // class java/lang/StringBuilder
      97: dup
      98: invokespecial #8                  // Method java/lang/StringBuilder."<init>":()V
     101: ldc           #19                 // String Failed to create directory within 10000 attempts (tried
     103: invokevirtual #12                 // Method java/lang/StringBuilder.append:(Ljava/lang/String;)Ljava/lang/StringBuilder;
     106: aload_2
     107: invokevirtual #12                 // Method java/lang/StringBuilder.append:(Ljava/lang/String;)Ljava/lang/StringBuilder;
     110: ldc           #20                 // String 0 to
     112: invokevirtual #12                 // Method java/lang/StringBuilder.append:(Ljava/lang/String;)Ljava/lang/StringBuilder;
     115: aload_2
     116: invokevirtual #12                 // Method java/lang/StringBuilder.append:(Ljava/lang/String;)Ljava/lang/StringBuilder;
     119: sipush        9999
     122: invokevirtual #15                 // Method java/lang/StringBuilder.append:(I)Ljava/lang/StringBuilder;
     125: bipush        41
     127: invokevirtual #21                 // Method java/lang/StringBuilder.append:(C)Ljava/lang/StringBuilder;
     130: invokevirtual #13                 // Method java/lang/StringBuilder.toString:()Ljava/lang/String;
     133: invokespecial #22                 // Method java/lang/IllegalStateException."<init>":(Ljava/lang/String;)V
     136: athrow

  java.io.File createTempFile(java.lang.String) throws java.io.IOException;
    Code:
       0: aload_1
       1: aconst_null
       2: aconst_null
       3: invokestatic  #23                 // Method java/io/File.createTempFile:(Ljava/lang/String;Ljava/lang/String;Ljava/io/File;)Ljava/io/File;
       6: areturn

  com.google.common.io.TempFileCreator$JavaIoCreator(com.google.common.io.TempFileCreator$1);
    Code:
       0: aload_0
       1: invokespecial #1                  // Method "<init>":()V
       4: return
}
