Compiled from "TempFileCreator.java"
final class com.google.common.io.TempFileCreator$ThrowingCreator extends com.google.common.io.TempFileCreator {
  private static final java.lang.String MESSAGE;

  private com.google.common.io.TempFileCreator$ThrowingCreator();
    Code:
       0: aload_0
       1: aconst_null
       2: invokespecial #2                  // Method com/google/common/io/TempFileCreator."<init>":(Lcom/google/common/io/TempFileCreator$1;)V
       5: return

  java.io.File createTempDir();
    Code:
       0: new           #3                  // class java/lang/IllegalStateException
       3: dup
       4: ldc           #5                  // String Guava cannot securely create temporary files or directories under SDK versions before Jelly Bean. You can create one yourself, either in the insecure default directory or in a more secure directory, such as context.getCacheDir(). For more information, see the Javadoc for Files.createTempDir().
       6: invokespecial #6                  // Method java/lang/IllegalStateException."<init>":(Ljava/lang/String;)V
       9: athrow

  java.io.File createTempFile(java.lang.String) throws java.io.IOException;
    Code:
       0: new           #7                  // class java/io/IOException
       3: dup
       4: ldc           #5                  // String Guava cannot securely create temporary files or directories under SDK versions before Jelly Bean. You can create one yourself, either in the insecure default directory or in a more secure directory, such as context.getCacheDir(). For more information, see the Javadoc for Files.createTempDir().
       6: invokespecial #8                  // Method java/io/IOException."<init>":(Ljava/lang/String;)V
       9: athrow

  com.google.common.io.TempFileCreator$ThrowingCreator(com.google.common.io.TempFileCreator$1);
    Code:
       0: aload_0
       1: invokespecial #1                  // Method "<init>":()V
       4: return
}
