Compiled from "BodyConsumerParamParser.java"
public class org.apache.dubbo.rpc.protocol.rest.annotation.param.parse.consumer.BodyConsumerParamParser implements org.apache.dubbo.rpc.protocol.rest.annotation.param.parse.consumer.BaseConsumerParamParser {
  public org.apache.dubbo.rpc.protocol.rest.annotation.param.parse.consumer.BodyConsumerParamParser();
    Code:
       0: aload_0
       1: invokespecial #1                  // Method java/lang/Object."<init>":()V
       4: return

  public void parse(org.apache.dubbo.rpc.protocol.rest.annotation.param.parse.consumer.ConsumerParseContext, org.apache.dubbo.metadata.rest.ArgInfo);
    Code:
       0: aload_1
       1: invokevirtual #2                  // Method org/apache/dubbo/rpc/protocol/rest/annotation/param/parse/consumer/ConsumerParseContext.getArgs:()Ljava/util/List;
       4: astore_3
       5: aload_1
       6: invokevirtual #3                  // Method org/apache/dubbo/rpc/protocol/rest/annotation/param/parse/consumer/ConsumerParseContext.getRequestTemplate:()Lorg/apache/dubbo/remoting/http/RequestTemplate;
       9: astore        4
      11: aload         4
      13: aload_3
      14: aload_2
      15: invokevirtual #4                  // Method org/apache/dubbo/metadata/rest/ArgInfo.getIndex:()I
      18: invokeinterface #5,  2            // InterfaceMethod java/util/List.get:(I)Ljava/lang/Object;
      23: aload_2
      24: invokevirtual #6                  // Method org/apache/dubbo/metadata/rest/ArgInfo.getParamType:()Ljava/lang/Class;
      27: invokevirtual #7                  // Method org/apache/dubbo/remoting/http/RequestTemplate.body:(Ljava/lang/Object;Ljava/lang/Class;)Lorg/apache/dubbo/remoting/http/RequestTemplate;
      30: pop
      31: return

  public boolean paramTypeMatch(org.apache.dubbo.metadata.rest.ArgInfo);
    Code:
       0: getstatic     #8                  // Field org/apache/dubbo/metadata/rest/ParamType.BODY:Lorg/apache/dubbo/metadata/rest/ParamType;
       3: aload_1
       4: invokevirtual #9                  // Method org/apache/dubbo/metadata/rest/ArgInfo.getParamAnnotationType:()Ljava/lang/Class;
       7: invokevirtual #10                 // Method org/apache/dubbo/metadata/rest/ParamType.supportAnno:(Ljava/lang/Class;)Z
      10: ireturn

  public void parse(java.lang.Object, org.apache.dubbo.metadata.rest.ArgInfo);
    Code:
       0: aload_0
       1: aload_1
       2: checkcast     #11                 // class org/apache/dubbo/rpc/protocol/rest/annotation/param/parse/consumer/ConsumerParseContext
       5: aload_2
       6: invokevirtual #12                 // Method parse:(Lorg/apache/dubbo/rpc/protocol/rest/annotation/param/parse/consumer/ConsumerParseContext;Lorg/apache/dubbo/metadata/rest/ArgInfo;)V
       9: return
}
