Compiled from "ConsumerParseContext.java"
public class org.apache.dubbo.rpc.protocol.rest.annotation.param.parse.consumer.ConsumerParseContext extends org.apache.dubbo.rpc.protocol.rest.annotation.BaseParseContext {
  private org.apache.dubbo.remoting.http.RequestTemplate requestTemplate;

  public org.apache.dubbo.rpc.protocol.rest.annotation.param.parse.consumer.ConsumerParseContext(org.apache.dubbo.remoting.http.RequestTemplate);
    Code:
       0: aload_0
       1: invokespecial #1                  // Method org/apache/dubbo/rpc/protocol/rest/annotation/BaseParseContext."<init>":()V
       4: aload_0
       5: aload_1
       6: putfield      #2                  // Field requestTemplate:Lorg/apache/dubbo/remoting/http/RequestTemplate;
       9: return

  public org.apache.dubbo.remoting.http.RequestTemplate getRequestTemplate();
    Code:
       0: aload_0
       1: getfield      #2                  // Field requestTemplate:Lorg/apache/dubbo/remoting/http/RequestTemplate;
       4: areturn
}
