Compiled from "FormConsumerParamParser.java"
public class org.apache.dubbo.rpc.protocol.rest.annotation.param.parse.consumer.FormConsumerParamParser implements org.apache.dubbo.rpc.protocol.rest.annotation.param.parse.consumer.BaseConsumerParamParser {
  public org.apache.dubbo.rpc.protocol.rest.annotation.param.parse.consumer.FormConsumerParamParser();
    Code:
       0: aload_0
       1: invokespecial #1                  // Method java/lang/Object."<init>":()V
       4: return

  public void parse(org.apache.dubbo.rpc.protocol.rest.annotation.param.parse.consumer.ConsumerParseContext, org.apache.dubbo.metadata.rest.ArgInfo);
    Code:
       0: aload_1
       1: invokevirtual #2                  // Method org/apache/dubbo/rpc/protocol/rest/annotation/param/parse/consumer/ConsumerParseContext.getArgs:()Ljava/util/List;
       4: astore_3
       5: aload_1
       6: invokevirtual #3                  // Method org/apache/dubbo/rpc/protocol/rest/annotation/param/parse/consumer/ConsumerParseContext.getRequestTemplate:()Lorg/apache/dubbo/remoting/http/RequestTemplate;
       9: astore        4
      11: aload_3
      12: aload_2
      13: invokevirtual #4                  // Method org/apache/dubbo/metadata/rest/ArgInfo.getIndex:()I
      16: invokeinterface #5,  2            // InterfaceMethod java/util/List.get:(I)Ljava/lang/Object;
      21: astore        5
      23: aload         5
      25: ifnonnull     29
      28: return
      29: new           #6                  // class java/util/HashMap
      32: dup
      33: invokespecial #7                  // Method java/util/HashMap."<init>":()V
      36: astore        6
      38: aload         5
      40: invokevirtual #8                  // Method java/lang/Object.getClass:()Ljava/lang/Class;
      43: invokestatic  #9                  // Method org/apache/dubbo/rpc/protocol/rest/util/DataParseUtils.isTextType:(Ljava/lang/Class;)Z
      46: ifeq          89
      49: aload         6
      51: aload_2
      52: invokevirtual #10                 // Method org/apache/dubbo/metadata/rest/ArgInfo.getAnnotationNameAttribute:()Ljava/lang/String;
      55: iconst_1
      56: anewarray     #11                 // class java/lang/String
      59: dup
      60: iconst_0
      61: aload         5
      63: invokestatic  #12                 // Method java/lang/String.valueOf:(Ljava/lang/Object;)Ljava/lang/String;
      66: aastore
      67: invokestatic  #13                 // Method java/util/Arrays.asList:([Ljava/lang/Object;)Ljava/util/List;
      70: invokeinterface #14,  3           // InterfaceMethod java/util/Map.put:(Ljava/lang/Object;Ljava/lang/Object;)Ljava/lang/Object;
      75: pop
      76: aload         4
      78: aload         6
      80: ldc           #15                 // class java/util/Map
      82: invokevirtual #16                 // Method org/apache/dubbo/remoting/http/RequestTemplate.body:(Ljava/lang/Object;Ljava/lang/Class;)Lorg/apache/dubbo/remoting/http/RequestTemplate;
      85: pop
      86: goto          151
      89: aload         5
      91: instanceof    #15                 // class java/util/Map
      94: ifeq          110
      97: aload         4
      99: aload         5
     101: ldc           #15                 // class java/util/Map
     103: invokevirtual #16                 // Method org/apache/dubbo/remoting/http/RequestTemplate.body:(Ljava/lang/Object;Ljava/lang/Class;)Lorg/apache/dubbo/remoting/http/RequestTemplate;
     106: pop
     107: goto          151
     110: aload         5
     112: invokevirtual #8                  // Method java/lang/Object.getClass:()Ljava/lang/Class;
     115: invokestatic  #17                 // Method org/apache/dubbo/common/utils/ReflectUtils.getAllFieldNames:(Ljava/lang/Class;)Ljava/util/Set;
     118: astore        7
     120: aload         7
     122: invokeinterface #18,  1           // InterfaceMethod java/util/Set.stream:()Ljava/util/stream/Stream;
     127: aload         5
     129: aload         6
     131: invokedynamic #19,  0             // InvokeDynamic #0:accept:(Ljava/lang/Object;Ljava/util/Map;)Ljava/util/function/Consumer;
     136: invokeinterface #20,  2           // InterfaceMethod java/util/stream/Stream.forEach:(Ljava/util/function/Consumer;)V
     141: aload         4
     143: aload         6
     145: ldc           #15                 // class java/util/Map
     147: invokevirtual #16                 // Method org/apache/dubbo/remoting/http/RequestTemplate.body:(Ljava/lang/Object;Ljava/lang/Class;)Lorg/apache/dubbo/remoting/http/RequestTemplate;
     150: pop
     151: aload         4
     153: ldc           #22                 // String Content-Type
     155: invokevirtual #23                 // Method org/apache/dubbo/remoting/http/RequestTemplate.getHeaders:(Ljava/lang/String;)Ljava/util/Collection;
     158: astore        7
     160: aload         7
     162: invokestatic  #24                 // Method org/apache/dubbo/common/utils/CollectionUtils.isEmpty:(Ljava/util/Collection;)Z
     165: ifeq          181
     168: aload         4
     170: ldc           #22                 // String Content-Type
     172: getstatic     #25                 // Field org/apache/dubbo/metadata/rest/media/MediaType.APPLICATION_FORM_URLENCODED_VALUE:Lorg/apache/dubbo/metadata/rest/media/MediaType;
     175: getfield      #26                 // Field org/apache/dubbo/metadata/rest/media/MediaType.value:Ljava/lang/String;
     178: invokevirtual #27                 // Method org/apache/dubbo/remoting/http/RequestTemplate.addHeader:(Ljava/lang/String;Ljava/lang/String;)V
     181: return

  public boolean paramTypeMatch(org.apache.dubbo.metadata.rest.ArgInfo);
    Code:
       0: getstatic     #28                 // Field org/apache/dubbo/metadata/rest/ParamType.FORM:Lorg/apache/dubbo/metadata/rest/ParamType;
       3: aload_1
       4: invokevirtual #29                 // Method org/apache/dubbo/metadata/rest/ArgInfo.getParamAnnotationType:()Ljava/lang/Class;
       7: invokevirtual #30                 // Method org/apache/dubbo/metadata/rest/ParamType.supportAnno:(Ljava/lang/Class;)Z
      10: ireturn

  public void parse(java.lang.Object, org.apache.dubbo.metadata.rest.ArgInfo);
    Code:
       0: aload_0
       1: aload_1
       2: checkcast     #31                 // class org/apache/dubbo/rpc/protocol/rest/annotation/param/parse/consumer/ConsumerParseContext
       5: aload_2
       6: invokevirtual #32                 // Method parse:(Lorg/apache/dubbo/rpc/protocol/rest/annotation/param/parse/consumer/ConsumerParseContext;Lorg/apache/dubbo/metadata/rest/ArgInfo;)V
       9: return

  private static void lambda$parse$0(java.lang.Object, java.util.Map, java.lang.String);
    Code:
       0: aload_0
       1: aload_2
       2: invokestatic  #33                 // Method org/apache/dubbo/common/utils/ReflectUtils.getFieldValue:(Ljava/lang/Object;Ljava/lang/String;)Ljava/lang/Object;
       5: astore_3
       6: aload_1
       7: aload_2
       8: invokestatic  #12                 // Method java/lang/String.valueOf:(Ljava/lang/Object;)Ljava/lang/String;
      11: iconst_1
      12: anewarray     #11                 // class java/lang/String
      15: dup
      16: iconst_0
      17: aload_3
      18: invokestatic  #12                 // Method java/lang/String.valueOf:(Ljava/lang/Object;)Ljava/lang/String;
      21: aastore
      22: invokestatic  #13                 // Method java/util/Arrays.asList:([Ljava/lang/Object;)Ljava/util/List;
      25: invokeinterface #14,  3           // InterfaceMethod java/util/Map.put:(Ljava/lang/Object;Ljava/lang/Object;)Ljava/lang/Object;
      30: pop
      31: return
}
