Compiled from "ParameterConsumerParamParser.java"
public class org.apache.dubbo.rpc.protocol.rest.annotation.param.parse.consumer.ParameterConsumerParamParser implements org.apache.dubbo.rpc.protocol.rest.annotation.param.parse.consumer.BaseConsumerParamParser {
  public org.apache.dubbo.rpc.protocol.rest.annotation.param.parse.consumer.ParameterConsumerParamParser();
    Code:
       0: aload_0
       1: invokespecial #1                  // Method java/lang/Object."<init>":()V
       4: return

  public void parse(org.apache.dubbo.rpc.protocol.rest.annotation.param.parse.consumer.ConsumerParseContext, org.apache.dubbo.metadata.rest.ArgInfo);
    Code:
       0: aload_1
       1: invokevirtual #2                  // Method org/apache/dubbo/rpc/protocol/rest/annotation/param/parse/consumer/ConsumerParseContext.getArgs:()Ljava/util/List;
       4: astore_3
       5: aload_1
       6: invokevirtual #3                  // Method org/apache/dubbo/rpc/protocol/rest/annotation/param/parse/consumer/ConsumerParseContext.getRequestTemplate:()Lorg/apache/dubbo/remoting/http/RequestTemplate;
       9: astore        4
      11: aload_3
      12: aload_2
      13: invokevirtual #4                  // Method org/apache/dubbo/metadata/rest/ArgInfo.getIndex:()I
      16: invokeinterface #5,  2            // InterfaceMethod java/util/List.get:(I)Ljava/lang/Object;
      21: astore        5
      23: aload         5
      25: ifnonnull     29
      28: return
      29: ldc           #6                  // class java/util/Map
      31: aload_2
      32: invokevirtual #7                  // Method org/apache/dubbo/metadata/rest/ArgInfo.getParamType:()Ljava/lang/Class;
      35: invokevirtual #8                  // Method java/lang/Class.isAssignableFrom:(Ljava/lang/Class;)Z
      38: ifeq          106
      41: aload         5
      43: checkcast     #6                  // class java/util/Map
      46: astore        6
      48: aload         6
      50: invokeinterface #9,  1            // InterfaceMethod java/util/Map.keySet:()Ljava/util/Set;
      55: invokeinterface #10,  1           // InterfaceMethod java/util/Set.iterator:()Ljava/util/Iterator;
      60: astore        7
      62: aload         7
      64: invokeinterface #11,  1           // InterfaceMethod java/util/Iterator.hasNext:()Z
      69: ifeq          103
      72: aload         7
      74: invokeinterface #12,  1           // InterfaceMethod java/util/Iterator.next:()Ljava/lang/Object;
      79: astore        8
      81: aload         4
      83: aload         8
      85: invokestatic  #13                 // Method java/lang/String.valueOf:(Ljava/lang/Object;)Ljava/lang/String;
      88: aload         6
      90: aload         8
      92: invokeinterface #14,  2           // InterfaceMethod java/util/Map.get:(Ljava/lang/Object;)Ljava/lang/Object;
      97: invokevirtual #15                 // Method org/apache/dubbo/remoting/http/RequestTemplate.addParam:(Ljava/lang/String;Ljava/lang/Object;)V
     100: goto          62
     103: goto          117
     106: aload         4
     108: aload_2
     109: invokevirtual #16                 // Method org/apache/dubbo/metadata/rest/ArgInfo.getAnnotationNameAttribute:()Ljava/lang/String;
     112: aload         5
     114: invokevirtual #15                 // Method org/apache/dubbo/remoting/http/RequestTemplate.addParam:(Ljava/lang/String;Ljava/lang/Object;)V
     117: return

  public boolean paramTypeMatch(org.apache.dubbo.metadata.rest.ArgInfo);
    Code:
       0: getstatic     #17                 // Field org/apache/dubbo/metadata/rest/ParamType.PARAM:Lorg/apache/dubbo/metadata/rest/ParamType;
       3: aload_1
       4: invokevirtual #18                 // Method org/apache/dubbo/metadata/rest/ArgInfo.getParamAnnotationType:()Ljava/lang/Class;
       7: invokevirtual #19                 // Method org/apache/dubbo/metadata/rest/ParamType.supportAnno:(Ljava/lang/Class;)Z
      10: ireturn

  public void parse(java.lang.Object, org.apache.dubbo.metadata.rest.ArgInfo);
    Code:
       0: aload_0
       1: aload_1
       2: checkcast     #20                 // class org/apache/dubbo/rpc/protocol/rest/annotation/param/parse/consumer/ConsumerParseContext
       5: aload_2
       6: invokevirtual #21                 // Method parse:(Lorg/apache/dubbo/rpc/protocol/rest/annotation/param/parse/consumer/ConsumerParseContext;Lorg/apache/dubbo/metadata/rest/ArgInfo;)V
       9: return
}
