Compiled from "OriginTrackedResource.java"
public class org.springframework.boot.origin.OriginTrackedResource implements org.springframework.core.io.Resource,org.springframework.boot.origin.OriginProvider {
  private final org.springframework.core.io.Resource resource;

  private final org.springframework.boot.origin.Origin origin;

  org.springframework.boot.origin.OriginTrackedResource(org.springframework.core.io.Resource, org.springframework.boot.origin.Origin);
    Code:
       0: aload_0
       1: invokespecial #1                  // Method java/lang/Object."<init>":()V
       4: aload_1
       5: ldc           #7                  // String Resource must not be null
       7: invokestatic  #9                  // Method org/springframework/util/Assert.notNull:(Ljava/lang/Object;Ljava/lang/String;)V
      10: aload_0
      11: aload_1
      12: putfield      #15                 // Field resource:Lorg/springframework/core/io/Resource;
      15: aload_0
      16: aload_2
      17: putfield      #21                 // Field origin:Lorg/springframework/boot/origin/Origin;
      20: return

  public java.io.InputStream getInputStream() throws java.io.IOException;
    Code:
       0: aload_0
       1: invokevirtual #25                 // Method getResource:()Lorg/springframework/core/io/Resource;
       4: invokeinterface #29,  1           // InterfaceMethod org/springframework/core/io/Resource.getInputStream:()Ljava/io/InputStream;
       9: areturn

  public boolean exists();
    Code:
       0: aload_0
       1: invokevirtual #25                 // Method getResource:()Lorg/springframework/core/io/Resource;
       4: invokeinterface #35,  1           // InterfaceMethod org/springframework/core/io/Resource.exists:()Z
       9: ireturn

  public boolean isReadable();
    Code:
       0: aload_0
       1: invokevirtual #25                 // Method getResource:()Lorg/springframework/core/io/Resource;
       4: invokeinterface #39,  1           // InterfaceMethod org/springframework/core/io/Resource.isReadable:()Z
       9: ireturn

  public boolean isOpen();
    Code:
       0: aload_0
       1: invokevirtual #25                 // Method getResource:()Lorg/springframework/core/io/Resource;
       4: invokeinterface #42,  1           // InterfaceMethod org/springframework/core/io/Resource.isOpen:()Z
       9: ireturn

  public boolean isFile();
    Code:
       0: aload_0
       1: invokevirtual #25                 // Method getResource:()Lorg/springframework/core/io/Resource;
       4: invokeinterface #45,  1           // InterfaceMethod org/springframework/core/io/Resource.isFile:()Z
       9: ireturn

  public java.net.URL getURL() throws java.io.IOException;
    Code:
       0: aload_0
       1: invokevirtual #25                 // Method getResource:()Lorg/springframework/core/io/Resource;
       4: invokeinterface #48,  1           // InterfaceMethod org/springframework/core/io/Resource.getURL:()Ljava/net/URL;
       9: areturn

  public java.net.URI getURI() throws java.io.IOException;
    Code:
       0: aload_0
       1: invokevirtual #25                 // Method getResource:()Lorg/springframework/core/io/Resource;
       4: invokeinterface #52,  1           // InterfaceMethod org/springframework/core/io/Resource.getURI:()Ljava/net/URI;
       9: areturn

  public java.io.File getFile() throws java.io.IOException;
    Code:
       0: aload_0
       1: invokevirtual #25                 // Method getResource:()Lorg/springframework/core/io/Resource;
       4: invokeinterface #56,  1           // InterfaceMethod org/springframework/core/io/Resource.getFile:()Ljava/io/File;
       9: areturn

  public java.nio.channels.ReadableByteChannel readableChannel() throws java.io.IOException;
    Code:
       0: aload_0
       1: invokevirtual #25                 // Method getResource:()Lorg/springframework/core/io/Resource;
       4: invokeinterface #60,  1           // InterfaceMethod org/springframework/core/io/Resource.readableChannel:()Ljava/nio/channels/ReadableByteChannel;
       9: areturn

  public long contentLength() throws java.io.IOException;
    Code:
       0: aload_0
       1: invokevirtual #25                 // Method getResource:()Lorg/springframework/core/io/Resource;
       4: invokeinterface #64,  1           // InterfaceMethod org/springframework/core/io/Resource.contentLength:()J
       9: lreturn

  public long lastModified() throws java.io.IOException;
    Code:
       0: aload_0
       1: invokevirtual #25                 // Method getResource:()Lorg/springframework/core/io/Resource;
       4: invokeinterface #68,  1           // InterfaceMethod org/springframework/core/io/Resource.lastModified:()J
       9: lreturn

  public org.springframework.core.io.Resource createRelative(java.lang.String) throws java.io.IOException;
    Code:
       0: aload_0
       1: invokevirtual #25                 // Method getResource:()Lorg/springframework/core/io/Resource;
       4: aload_1
       5: invokeinterface #71,  2           // InterfaceMethod org/springframework/core/io/Resource.createRelative:(Ljava/lang/String;)Lorg/springframework/core/io/Resource;
      10: areturn

  public java.lang.String getFilename();
    Code:
       0: aload_0
       1: invokevirtual #25                 // Method getResource:()Lorg/springframework/core/io/Resource;
       4: invokeinterface #75,  1           // InterfaceMethod org/springframework/core/io/Resource.getFilename:()Ljava/lang/String;
       9: areturn

  public java.lang.String getDescription();
    Code:
       0: aload_0
       1: invokevirtual #25                 // Method getResource:()Lorg/springframework/core/io/Resource;
       4: invokeinterface #79,  1           // InterfaceMethod org/springframework/core/io/Resource.getDescription:()Ljava/lang/String;
       9: areturn

  public org.springframework.core.io.Resource getResource();
    Code:
       0: aload_0
       1: getfield      #15                 // Field resource:Lorg/springframework/core/io/Resource;
       4: areturn

  public org.springframework.boot.origin.Origin getOrigin();
    Code:
       0: aload_0
       1: getfield      #21                 // Field origin:Lorg/springframework/boot/origin/Origin;
       4: areturn

  public boolean equals(java.lang.Object);
    Code:
       0: aload_0
       1: aload_1
       2: if_acmpne     7
       5: iconst_1
       6: ireturn
       7: aload_1
       8: ifnull        22
      11: aload_0
      12: invokevirtual #82                 // Method java/lang/Object.getClass:()Ljava/lang/Class;
      15: aload_1
      16: invokevirtual #82                 // Method java/lang/Object.getClass:()Ljava/lang/Class;
      19: if_acmpeq     24
      22: iconst_0
      23: ireturn
      24: aload_1
      25: checkcast     #16                 // class org/springframework/boot/origin/OriginTrackedResource
      28: astore_2
      29: aload_0
      30: getfield      #15                 // Field resource:Lorg/springframework/core/io/Resource;
      33: aload_2
      34: invokevirtual #86                 // Method java/lang/Object.equals:(Ljava/lang/Object;)Z
      37: ifeq          58
      40: aload_0
      41: getfield      #21                 // Field origin:Lorg/springframework/boot/origin/Origin;
      44: aload_2
      45: getfield      #21                 // Field origin:Lorg/springframework/boot/origin/Origin;
      48: invokestatic  #90                 // Method org/springframework/util/ObjectUtils.nullSafeEquals:(Ljava/lang/Object;Ljava/lang/Object;)Z
      51: ifeq          58
      54: iconst_1
      55: goto          59
      58: iconst_0
      59: ireturn

  public int hashCode();
    Code:
       0: bipush        31
       2: istore_1
       3: aload_0
       4: getfield      #15                 // Field resource:Lorg/springframework/core/io/Resource;
       7: invokevirtual #96                 // Method java/lang/Object.hashCode:()I
      10: istore_2
      11: bipush        31
      13: iload_2
      14: imul
      15: aload_0
      16: getfield      #21                 // Field origin:Lorg/springframework/boot/origin/Origin;
      19: invokestatic  #100                // Method org/springframework/util/ObjectUtils.nullSafeHashCode:(Ljava/lang/Object;)I
      22: iadd
      23: istore_2
      24: iload_2
      25: ireturn

  public java.lang.String toString();
    Code:
       0: aload_0
       1: getfield      #15                 // Field resource:Lorg/springframework/core/io/Resource;
       4: invokevirtual #104                // Method java/lang/Object.toString:()Ljava/lang/String;
       7: areturn

  public static org.springframework.boot.origin.OriginTrackedResource$OriginTrackedWritableResource of(org.springframework.core.io.WritableResource, org.springframework.boot.origin.Origin);
    Code:
       0: aload_0
       1: aload_1
       2: invokestatic  #107                // Method of:(Lorg/springframework/core/io/Resource;Lorg/springframework/boot/origin/Origin;)Lorg/springframework/boot/origin/OriginTrackedResource;
       5: checkcast     #111                // class org/springframework/boot/origin/OriginTrackedResource$OriginTrackedWritableResource
       8: areturn

  public static org.springframework.boot.origin.OriginTrackedResource of(org.springframework.core.io.Resource, org.springframework.boot.origin.Origin);
    Code:
       0: aload_0
       1: instanceof    #113                // class org/springframework/core/io/WritableResource
       4: ifeq          22
       7: aload_0
       8: checkcast     #113                // class org/springframework/core/io/WritableResource
      11: astore_2
      12: new           #111                // class org/springframework/boot/origin/OriginTrackedResource$OriginTrackedWritableResource
      15: dup
      16: aload_2
      17: aload_1
      18: invokespecial #115                // Method org/springframework/boot/origin/OriginTrackedResource$OriginTrackedWritableResource."<init>":(Lorg/springframework/core/io/WritableResource;Lorg/springframework/boot/origin/Origin;)V
      21: areturn
      22: new           #16                 // class org/springframework/boot/origin/OriginTrackedResource
      25: dup
      26: aload_0
      27: aload_1
      28: invokespecial #118                // Method "<init>":(Lorg/springframework/core/io/Resource;Lorg/springframework/boot/origin/Origin;)V
      31: areturn
}
