Compiled from "OriginTrackedResource.java"
public class org.springframework.boot.origin.OriginTrackedResource$OriginTrackedWritableResource extends org.springframework.boot.origin.OriginTrackedResource implements org.springframework.core.io.WritableResource {
  org.springframework.boot.origin.OriginTrackedResource$OriginTrackedWritableResource(org.springframework.core.io.WritableResource, org.springframework.boot.origin.Origin);
    Code:
       0: aload_0
       1: aload_1
       2: aload_2
       3: invokespecial #1                  // Method org/springframework/boot/origin/OriginTrackedResource."<init>":(Lorg/springframework/core/io/Resource;Lorg/springframework/boot/origin/Origin;)V
       6: return

  public org.springframework.core.io.WritableResource getResource();
    Code:
       0: aload_0
       1: invokespecial #7                  // Method org/springframework/boot/origin/OriginTrackedResource.getResource:()Lorg/springframework/core/io/Resource;
       4: checkcast     #11                 // class org/springframework/core/io/WritableResource
       7: areturn

  public java.io.OutputStream getOutputStream() throws java.io.IOException;
    Code:
       0: aload_0
       1: invokevirtual #13                 // Method getResource:()Lorg/springframework/core/io/WritableResource;
       4: invokeinterface #18,  1           // InterfaceMethod org/springframework/core/io/WritableResource.getOutputStream:()Ljava/io/OutputStream;
       9: areturn

  public org.springframework.core.io.Resource getResource();
    Code:
       0: aload_0
       1: invokevirtual #13                 // Method getResource:()Lorg/springframework/core/io/WritableResource;
       4: areturn
}
