Compiled from "Origin.java"
public interface org.springframework.boot.origin.Origin {
  public default org.springframework.boot.origin.Origin getParent();
    Code:
       0: aconst_null
       1: areturn

  public static org.springframework.boot.origin.Origin from(java.lang.Object);
    Code:
       0: aload_0
       1: instanceof    #1                  // class org/springframework/boot/origin/Origin
       4: ifeq          14
       7: aload_0
       8: checkcast     #1                  // class org/springframework/boot/origin/Origin
      11: astore_1
      12: aload_1
      13: areturn
      14: aconst_null
      15: astore_1
      16: aload_0
      17: instanceof    #3                  // class org/springframework/boot/origin/OriginProvider
      20: ifeq          35
      23: aload_0
      24: checkcast     #3                  // class org/springframework/boot/origin/OriginProvider
      27: astore_2
      28: aload_2
      29: invokeinterface #5,  1            // InterfaceMethod org/springframework/boot/origin/OriginProvider.getOrigin:()Lorg/springframework/boot/origin/Origin;
      34: astore_1
      35: aload_1
      36: ifnonnull     59
      39: aload_0
      40: instanceof    #9                  // class java/lang/Throwable
      43: ifeq          59
      46: aload_0
      47: checkcast     #9                  // class java/lang/Throwable
      50: astore_2
      51: aload_2
      52: invokevirtual #11                 // Method java/lang/Throwable.getCause:()Ljava/lang/Throwable;
      55: invokestatic  #15                 // InterfaceMethod from:(Ljava/lang/Object;)Lorg/springframework/boot/origin/Origin;
      58: areturn
      59: aload_1
      60: areturn

  public static java.util.List<org.springframework.boot.origin.Origin> parentsFrom(java.lang.Object);
    Code:
       0: aload_0
       1: invokestatic  #15                 // InterfaceMethod from:(Ljava/lang/Object;)Lorg/springframework/boot/origin/Origin;
       4: astore_1
       5: aload_1
       6: ifnonnull     13
       9: invokestatic  #19                 // Method java/util/Collections.emptyList:()Ljava/util/List;
      12: areturn
      13: new           #25                 // class java/util/LinkedHashSet
      16: dup
      17: invokespecial #27                 // Method java/util/LinkedHashSet."<init>":()V
      20: astore_2
      21: aload_1
      22: invokeinterface #31,  1           // InterfaceMethod getParent:()Lorg/springframework/boot/origin/Origin;
      27: astore_1
      28: aload_1
      29: ifnull        60
      32: aload_2
      33: aload_1
      34: invokeinterface #34,  2           // InterfaceMethod java/util/Set.contains:(Ljava/lang/Object;)Z
      39: ifne          60
      42: aload_2
      43: aload_1
      44: invokeinterface #40,  2           // InterfaceMethod java/util/Set.add:(Ljava/lang/Object;)Z
      49: pop
      50: aload_1
      51: invokeinterface #31,  1           // InterfaceMethod getParent:()Lorg/springframework/boot/origin/Origin;
      56: astore_1
      57: goto          28
      60: new           #43                 // class java/util/ArrayList
      63: dup
      64: aload_2
      65: invokespecial #45                 // Method java/util/ArrayList."<init>":(Ljava/util/Collection;)V
      68: invokestatic  #48                 // Method java/util/Collections.unmodifiableList:(Ljava/util/List;)Ljava/util/List;
      71: areturn
}
