Compiled from "PropertySourceOrigin.java"
public class org.springframework.boot.origin.PropertySourceOrigin implements org.springframework.boot.origin.Origin {
  private final org.springframework.core.env.PropertySource<?> propertySource;

  private final java.lang.String propertyName;

  public org.springframework.boot.origin.PropertySourceOrigin(org.springframework.core.env.PropertySource<?>, java.lang.String);
    Code:
       0: aload_0
       1: invokespecial #1                  // Method java/lang/Object."<init>":()V
       4: aload_1
       5: ldc           #7                  // String PropertySource must not be null
       7: invokestatic  #9                  // Method org/springframework/util/Assert.notNull:(Ljava/lang/Object;Ljava/lang/String;)V
      10: aload_2
      11: ldc           #15                 // String PropertyName must not be empty
      13: invokestatic  #17                 // Method org/springframework/util/Assert.hasLength:(Ljava/lang/String;Ljava/lang/String;)V
      16: aload_0
      17: aload_1
      18: putfield      #21                 // Field propertySource:Lorg/springframework/core/env/PropertySource;
      21: aload_0
      22: aload_2
      23: putfield      #27                 // Field propertyName:Ljava/lang/String;
      26: return

  public org.springframework.core.env.PropertySource<?> getPropertySource();
    Code:
       0: aload_0
       1: getfield      #21                 // Field propertySource:Lorg/springframework/core/env/PropertySource;
       4: areturn

  public java.lang.String getPropertyName();
    Code:
       0: aload_0
       1: getfield      #27                 // Field propertyName:Ljava/lang/String;
       4: areturn

  public java.lang.String toString();
    Code:
       0: aload_0
       1: getfield      #27                 // Field propertyName:Ljava/lang/String;
       4: aload_0
       5: getfield      #21                 // Field propertySource:Lorg/springframework/core/env/PropertySource;
       8: invokevirtual #31                 // Method org/springframework/core/env/PropertySource.getName:()Ljava/lang/String;
      11: invokedynamic #37,  0             // InvokeDynamic #0:makeConcatWithConstants:(Ljava/lang/String;Ljava/lang/String;)Ljava/lang/String;
      16: areturn

  public static org.springframework.boot.origin.Origin get(org.springframework.core.env.PropertySource<?>, java.lang.String);
    Code:
       0: aload_0
       1: aload_1
       2: invokestatic  #41                 // InterfaceMethod org/springframework/boot/origin/OriginLookup.getOrigin:(Ljava/lang/Object;Ljava/lang/Object;)Lorg/springframework/boot/origin/Origin;
       5: astore_2
       6: aload_2
       7: ifnull        14
      10: aload_2
      11: goto          23
      14: new           #22                 // class org/springframework/boot/origin/PropertySourceOrigin
      17: dup
      18: aload_0
      19: aload_1
      20: invokespecial #47                 // Method "<init>":(Lorg/springframework/core/env/PropertySource;Ljava/lang/String;)V
      23: areturn
}
