Compiled from "TextResourceOrigin.java"
public class org.springframework.boot.origin.TextResourceOrigin implements org.springframework.boot.origin.Origin {
  private final org.springframework.core.io.Resource resource;

  private final org.springframework.boot.origin.TextResourceOrigin$Location location;

  public org.springframework.boot.origin.TextResourceOrigin(org.springframework.core.io.Resource, org.springframework.boot.origin.TextResourceOrigin$Location);
    Code:
       0: aload_0
       1: invokespecial #1                  // Method java/lang/Object."<init>":()V
       4: aload_0
       5: aload_1
       6: putfield      #7                  // Field resource:Lorg/springframework/core/io/Resource;
       9: aload_0
      10: aload_2
      11: putfield      #13                 // Field location:Lorg/springframework/boot/origin/TextResourceOrigin$Location;
      14: return

  public org.springframework.core.io.Resource getResource();
    Code:
       0: aload_0
       1: getfield      #7                  // Field resource:Lorg/springframework/core/io/Resource;
       4: areturn

  public org.springframework.boot.origin.TextResourceOrigin$Location getLocation();
    Code:
       0: aload_0
       1: getfield      #13                 // Field location:Lorg/springframework/boot/origin/TextResourceOrigin$Location;
       4: areturn

  public org.springframework.boot.origin.Origin getParent();
    Code:
       0: aload_0
       1: getfield      #7                  // Field resource:Lorg/springframework/core/io/Resource;
       4: invokestatic  #17                 // InterfaceMethod org/springframework/boot/origin/Origin.from:(Ljava/lang/Object;)Lorg/springframework/boot/origin/Origin;
       7: areturn

  public boolean equals(java.lang.Object);
    Code:
       0: aload_0
       1: aload_1
       2: if_acmpne     7
       5: iconst_1
       6: ireturn
       7: aload_1
       8: ifnonnull     13
      11: iconst_0
      12: ireturn
      13: aload_1
      14: instanceof    #8                  // class org/springframework/boot/origin/TextResourceOrigin
      17: ifeq          77
      20: aload_1
      21: checkcast     #8                  // class org/springframework/boot/origin/TextResourceOrigin
      24: astore_2
      25: iconst_1
      26: istore_3
      27: iload_3
      28: ifeq          49
      31: aload_0
      32: getfield      #7                  // Field resource:Lorg/springframework/core/io/Resource;
      35: aload_2
      36: getfield      #7                  // Field resource:Lorg/springframework/core/io/Resource;
      39: invokestatic  #23                 // Method org/springframework/util/ObjectUtils.nullSafeEquals:(Ljava/lang/Object;Ljava/lang/Object;)Z
      42: ifeq          49
      45: iconst_1
      46: goto          50
      49: iconst_0
      50: istore_3
      51: iload_3
      52: ifeq          73
      55: aload_0
      56: getfield      #13                 // Field location:Lorg/springframework/boot/origin/TextResourceOrigin$Location;
      59: aload_2
      60: getfield      #13                 // Field location:Lorg/springframework/boot/origin/TextResourceOrigin$Location;
      63: invokestatic  #23                 // Method org/springframework/util/ObjectUtils.nullSafeEquals:(Ljava/lang/Object;Ljava/lang/Object;)Z
      66: ifeq          73
      69: iconst_1
      70: goto          74
      73: iconst_0
      74: istore_3
      75: iload_3
      76: ireturn
      77: aload_0
      78: aload_1
      79: invokespecial #29                 // Method java/lang/Object.equals:(Ljava/lang/Object;)Z
      82: ireturn

  public int hashCode();
    Code:
       0: iconst_1
       1: istore_1
       2: bipush        31
       4: iload_1
       5: imul
       6: aload_0
       7: getfield      #7                  // Field resource:Lorg/springframework/core/io/Resource;
      10: invokestatic  #33                 // Method org/springframework/util/ObjectUtils.nullSafeHashCode:(Ljava/lang/Object;)I
      13: iadd
      14: istore_1
      15: bipush        31
      17: iload_1
      18: imul
      19: aload_0
      20: getfield      #13                 // Field location:Lorg/springframework/boot/origin/TextResourceOrigin$Location;
      23: invokestatic  #33                 // Method org/springframework/util/ObjectUtils.nullSafeHashCode:(Ljava/lang/Object;)I
      26: iadd
      27: istore_1
      28: iload_1
      29: ireturn

  public java.lang.String toString();
    Code:
       0: new           #37                 // class java/lang/StringBuilder
       3: dup
       4: invokespecial #39                 // Method java/lang/StringBuilder."<init>":()V
       7: astore_1
       8: aload_1
       9: aload_0
      10: aload_0
      11: getfield      #7                  // Field resource:Lorg/springframework/core/io/Resource;
      14: invokevirtual #40                 // Method getResourceDescription:(Lorg/springframework/core/io/Resource;)Ljava/lang/String;
      17: invokevirtual #44                 // Method java/lang/StringBuilder.append:(Ljava/lang/String;)Ljava/lang/StringBuilder;
      20: pop
      21: aload_0
      22: getfield      #13                 // Field location:Lorg/springframework/boot/origin/TextResourceOrigin$Location;
      25: ifnull        42
      28: aload_1
      29: ldc           #48                 // String  -
      31: invokevirtual #44                 // Method java/lang/StringBuilder.append:(Ljava/lang/String;)Ljava/lang/StringBuilder;
      34: aload_0
      35: getfield      #13                 // Field location:Lorg/springframework/boot/origin/TextResourceOrigin$Location;
      38: invokevirtual #50                 // Method java/lang/StringBuilder.append:(Ljava/lang/Object;)Ljava/lang/StringBuilder;
      41: pop
      42: aload_1
      43: invokevirtual #53                 // Method java/lang/StringBuilder.toString:()Ljava/lang/String;
      46: areturn

  private java.lang.String getResourceDescription(org.springframework.core.io.Resource);
    Code:
       0: aload_1
       1: instanceof    #57                 // class org/springframework/boot/origin/OriginTrackedResource
       4: ifeq          21
       7: aload_1
       8: checkcast     #57                 // class org/springframework/boot/origin/OriginTrackedResource
      11: astore_2
      12: aload_0
      13: aload_2
      14: invokevirtual #59                 // Method org/springframework/boot/origin/OriginTrackedResource.getResource:()Lorg/springframework/core/io/Resource;
      17: invokevirtual #40                 // Method getResourceDescription:(Lorg/springframework/core/io/Resource;)Ljava/lang/String;
      20: areturn
      21: aload_1
      22: ifnonnull     28
      25: ldc           #63                 // String unknown resource [?]
      27: areturn
      28: aload_1
      29: instanceof    #65                 // class org/springframework/core/io/ClassPathResource
      32: ifeq          46
      35: aload_1
      36: checkcast     #65                 // class org/springframework/core/io/ClassPathResource
      39: astore_2
      40: aload_0
      41: aload_2
      42: invokevirtual #67                 // Method getResourceDescription:(Lorg/springframework/core/io/ClassPathResource;)Ljava/lang/String;
      45: areturn
      46: aload_1
      47: invokeinterface #70,  1           // InterfaceMethod org/springframework/core/io/Resource.getDescription:()Ljava/lang/String;
      52: areturn

  private java.lang.String getResourceDescription(org.springframework.core.io.ClassPathResource);
    Code:
       0: aload_1
       1: invokevirtual #75                 // Method org/springframework/core/io/ClassPathResource.getURI:()Ljava/net/URI;
       4: invokestatic  #79                 // Method org/springframework/boot/origin/JarUri.from:(Ljava/net/URI;)Lorg/springframework/boot/origin/JarUri;
       7: astore_2
       8: aload_2
       9: ifnull        21
      12: aload_2
      13: aload_1
      14: invokevirtual #84                 // Method org/springframework/core/io/ClassPathResource.getDescription:()Ljava/lang/String;
      17: invokevirtual #85                 // Method org/springframework/boot/origin/JarUri.getDescription:(Ljava/lang/String;)Ljava/lang/String;
      20: areturn
      21: goto          25
      24: astore_2
      25: aload_1
      26: invokevirtual #84                 // Method org/springframework/core/io/ClassPathResource.getDescription:()Ljava/lang/String;
      29: areturn
    Exception table:
       from    to  target type
           0    20    24   Class java/io/IOException
}
