Compiled from "AbstractServletWebServerFactory.java"
class org.springframework.boot.web.servlet.server.AbstractServletWebServerFactory$SessionConfiguringInitializer implements org.springframework.boot.web.servlet.ServletContextInitializer {
  private final org.springframework.boot.web.servlet.server.Session session;

  org.springframework.boot.web.servlet.server.AbstractServletWebServerFactory$SessionConfiguringInitializer(org.springframework.boot.web.servlet.server.Session);
    Code:
       0: aload_0
       1: invokespecial #1                  // Method java/lang/Object."<init>":()V
       4: aload_0
       5: aload_1
       6: putfield      #7                  // Field session:Lorg/springframework/boot/web/servlet/server/Session;
       9: return

  public void onStartup(jakarta.servlet.ServletContext) throws jakarta.servlet.ServletException;
    Code:
       0: aload_0
       1: getfield      #7                  // Field session:Lorg/springframework/boot/web/servlet/server/Session;
       4: invokevirtual #13                 // Method org/springframework/boot/web/servlet/server/Session.getTrackingModes:()Ljava/util/Set;
       7: ifnull        27
      10: aload_1
      11: aload_0
      12: aload_0
      13: getfield      #7                  // Field session:Lorg/springframework/boot/web/servlet/server/Session;
      16: invokevirtual #13                 // Method org/springframework/boot/web/servlet/server/Session.getTrackingModes:()Ljava/util/Set;
      19: invokevirtual #19                 // Method unwrap:(Ljava/util/Set;)Ljava/util/Set;
      22: invokeinterface #23,  2           // InterfaceMethod jakarta/servlet/ServletContext.setSessionTrackingModes:(Ljava/util/Set;)V
      27: aload_0
      28: aload_1
      29: invokeinterface #29,  1           // InterfaceMethod jakarta/servlet/ServletContext.getSessionCookieConfig:()Ljakarta/servlet/SessionCookieConfig;
      34: invokevirtual #33                 // Method configureSessionCookie:(Ljakarta/servlet/SessionCookieConfig;)V
      37: return

  private void configureSessionCookie(jakarta.servlet.SessionCookieConfig);
    Code:
       0: aload_0
       1: getfield      #7                  // Field session:Lorg/springframework/boot/web/servlet/server/Session;
       4: invokevirtual #37                 // Method org/springframework/boot/web/servlet/server/Session.getCookie:()Lorg/springframework/boot/web/servlet/server/Session$Cookie;
       7: astore_2
       8: invokestatic  #41                 // Method org/springframework/boot/context/properties/PropertyMapper.get:()Lorg/springframework/boot/context/properties/PropertyMapper;
      11: invokevirtual #47                 // Method org/springframework/boot/context/properties/PropertyMapper.alwaysApplyingWhenNonNull:()Lorg/springframework/boot/context/properties/PropertyMapper;
      14: astore_3
      15: aload_3
      16: aload_2
      17: dup
      18: invokestatic  #50                 // Method java/util/Objects.requireNonNull:(Ljava/lang/Object;)Ljava/lang/Object;
      21: pop
      22: invokedynamic #56,  0             // InvokeDynamic #0:get:(Lorg/springframework/boot/web/servlet/server/Session$Cookie;)Ljava/util/function/Supplier;
      27: invokevirtual #59                 // Method org/springframework/boot/context/properties/PropertyMapper.from:(Ljava/util/function/Supplier;)Lorg/springframework/boot/context/properties/PropertyMapper$Source;
      30: aload_1
      31: dup
      32: invokestatic  #50                 // Method java/util/Objects.requireNonNull:(Ljava/lang/Object;)Ljava/lang/Object;
      35: pop
      36: invokedynamic #63,  0             // InvokeDynamic #1:accept:(Ljakarta/servlet/SessionCookieConfig;)Ljava/util/function/Consumer;
      41: invokevirtual #67                 // Method org/springframework/boot/context/properties/PropertyMapper$Source.to:(Ljava/util/function/Consumer;)V
      44: aload_3
      45: aload_2
      46: dup
      47: invokestatic  #50                 // Method java/util/Objects.requireNonNull:(Ljava/lang/Object;)Ljava/lang/Object;
      50: pop
      51: invokedynamic #73,  0             // InvokeDynamic #2:get:(Lorg/springframework/boot/web/servlet/server/Session$Cookie;)Ljava/util/function/Supplier;
      56: invokevirtual #59                 // Method org/springframework/boot/context/properties/PropertyMapper.from:(Ljava/util/function/Supplier;)Lorg/springframework/boot/context/properties/PropertyMapper$Source;
      59: aload_1
      60: dup
      61: invokestatic  #50                 // Method java/util/Objects.requireNonNull:(Ljava/lang/Object;)Ljava/lang/Object;
      64: pop
      65: invokedynamic #74,  0             // InvokeDynamic #3:accept:(Ljakarta/servlet/SessionCookieConfig;)Ljava/util/function/Consumer;
      70: invokevirtual #67                 // Method org/springframework/boot/context/properties/PropertyMapper$Source.to:(Ljava/util/function/Consumer;)V
      73: aload_3
      74: aload_2
      75: dup
      76: invokestatic  #50                 // Method java/util/Objects.requireNonNull:(Ljava/lang/Object;)Ljava/lang/Object;
      79: pop
      80: invokedynamic #75,  0             // InvokeDynamic #4:get:(Lorg/springframework/boot/web/servlet/server/Session$Cookie;)Ljava/util/function/Supplier;
      85: invokevirtual #59                 // Method org/springframework/boot/context/properties/PropertyMapper.from:(Ljava/util/function/Supplier;)Lorg/springframework/boot/context/properties/PropertyMapper$Source;
      88: aload_1
      89: dup
      90: invokestatic  #50                 // Method java/util/Objects.requireNonNull:(Ljava/lang/Object;)Ljava/lang/Object;
      93: pop
      94: invokedynamic #76,  0             // InvokeDynamic #5:accept:(Ljakarta/servlet/SessionCookieConfig;)Ljava/util/function/Consumer;
      99: invokevirtual #67                 // Method org/springframework/boot/context/properties/PropertyMapper$Source.to:(Ljava/util/function/Consumer;)V
     102: aload_3
     103: aload_2
     104: dup
     105: invokestatic  #50                 // Method java/util/Objects.requireNonNull:(Ljava/lang/Object;)Ljava/lang/Object;
     108: pop
     109: invokedynamic #77,  0             // InvokeDynamic #6:get:(Lorg/springframework/boot/web/servlet/server/Session$Cookie;)Ljava/util/function/Supplier;
     114: invokevirtual #59                 // Method org/springframework/boot/context/properties/PropertyMapper.from:(Ljava/util/function/Supplier;)Lorg/springframework/boot/context/properties/PropertyMapper$Source;
     117: aload_1
     118: dup
     119: invokestatic  #50                 // Method java/util/Objects.requireNonNull:(Ljava/lang/Object;)Ljava/lang/Object;
     122: pop
     123: invokedynamic #78,  0             // InvokeDynamic #7:accept:(Ljakarta/servlet/SessionCookieConfig;)Ljava/util/function/Consumer;
     128: invokevirtual #67                 // Method org/springframework/boot/context/properties/PropertyMapper$Source.to:(Ljava/util/function/Consumer;)V
     131: aload_3
     132: aload_2
     133: dup
     134: invokestatic  #50                 // Method java/util/Objects.requireNonNull:(Ljava/lang/Object;)Ljava/lang/Object;
     137: pop
     138: invokedynamic #79,  0             // InvokeDynamic #8:get:(Lorg/springframework/boot/web/servlet/server/Session$Cookie;)Ljava/util/function/Supplier;
     143: invokevirtual #59                 // Method org/springframework/boot/context/properties/PropertyMapper.from:(Ljava/util/function/Supplier;)Lorg/springframework/boot/context/properties/PropertyMapper$Source;
     146: aload_1
     147: dup
     148: invokestatic  #50                 // Method java/util/Objects.requireNonNull:(Ljava/lang/Object;)Ljava/lang/Object;
     151: pop
     152: invokedynamic #80,  0             // InvokeDynamic #9:accept:(Ljakarta/servlet/SessionCookieConfig;)Ljava/util/function/Consumer;
     157: invokevirtual #67                 // Method org/springframework/boot/context/properties/PropertyMapper$Source.to:(Ljava/util/function/Consumer;)V
     160: aload_3
     161: aload_2
     162: dup
     163: invokestatic  #50                 // Method java/util/Objects.requireNonNull:(Ljava/lang/Object;)Ljava/lang/Object;
     166: pop
     167: invokedynamic #81,  0             // InvokeDynamic #10:get:(Lorg/springframework/boot/web/servlet/server/Session$Cookie;)Ljava/util/function/Supplier;
     172: invokevirtual #59                 // Method org/springframework/boot/context/properties/PropertyMapper.from:(Ljava/util/function/Supplier;)Lorg/springframework/boot/context/properties/PropertyMapper$Source;
     175: aload_1
     176: dup
     177: invokestatic  #50                 // Method java/util/Objects.requireNonNull:(Ljava/lang/Object;)Ljava/lang/Object;
     180: pop
     181: invokedynamic #82,  0             // InvokeDynamic #11:accept:(Ljakarta/servlet/SessionCookieConfig;)Ljava/util/function/Consumer;
     186: invokevirtual #67                 // Method org/springframework/boot/context/properties/PropertyMapper$Source.to:(Ljava/util/function/Consumer;)V
     189: aload_3
     190: aload_2
     191: dup
     192: invokestatic  #50                 // Method java/util/Objects.requireNonNull:(Ljava/lang/Object;)Ljava/lang/Object;
     195: pop
     196: invokedynamic #83,  0             // InvokeDynamic #12:get:(Lorg/springframework/boot/web/servlet/server/Session$Cookie;)Ljava/util/function/Supplier;
     201: invokevirtual #59                 // Method org/springframework/boot/context/properties/PropertyMapper.from:(Ljava/util/function/Supplier;)Lorg/springframework/boot/context/properties/PropertyMapper$Source;
     204: invokedynamic #84,  0             // InvokeDynamic #13:apply:()Ljava/util/function/Function;
     209: invokevirtual #88                 // Method org/springframework/boot/context/properties/PropertyMapper$Source.asInt:(Ljava/util/function/Function;)Lorg/springframework/boot/context/properties/PropertyMapper$Source;
     212: aload_1
     213: dup
     214: invokestatic  #50                 // Method java/util/Objects.requireNonNull:(Ljava/lang/Object;)Ljava/lang/Object;
     217: pop
     218: invokedynamic #92,  0             // InvokeDynamic #14:accept:(Ljakarta/servlet/SessionCookieConfig;)Ljava/util/function/Consumer;
     223: invokevirtual #67                 // Method org/springframework/boot/context/properties/PropertyMapper$Source.to:(Ljava/util/function/Consumer;)V
     226: return

  private java.util.Set<jakarta.servlet.SessionTrackingMode> unwrap(java.util.Set<org.springframework.boot.web.servlet.server.Session$SessionTrackingMode>);
    Code:
       0: aload_1
       1: ifnonnull     6
       4: aconst_null
       5: areturn
       6: new           #93                 // class java/util/LinkedHashSet
       9: dup
      10: invokespecial #95                 // Method java/util/LinkedHashSet."<init>":()V
      13: astore_2
      14: aload_1
      15: invokeinterface #96,  1           // InterfaceMethod java/util/Set.iterator:()Ljava/util/Iterator;
      20: astore_3
      21: aload_3
      22: invokeinterface #102,  1          // InterfaceMethod java/util/Iterator.hasNext:()Z
      27: ifeq          59
      30: aload_3
      31: invokeinterface #108,  1          // InterfaceMethod java/util/Iterator.next:()Ljava/lang/Object;
      36: checkcast     #112                // class org/springframework/boot/web/servlet/server/Session$SessionTrackingMode
      39: astore        4
      41: aload_2
      42: aload         4
      44: invokevirtual #114                // Method org/springframework/boot/web/servlet/server/Session$SessionTrackingMode.name:()Ljava/lang/String;
      47: invokestatic  #118                // Method jakarta/servlet/SessionTrackingMode.valueOf:(Ljava/lang/String;)Ljakarta/servlet/SessionTrackingMode;
      50: invokeinterface #124,  2          // InterfaceMethod java/util/Set.add:(Ljava/lang/Object;)Z
      55: pop
      56: goto          21
      59: aload_2
      60: areturn
}
