Compiled from "AbstractServletWebServerFactory.java"
public abstract class org.springframework.boot.web.servlet.server.AbstractServletWebServerFactory extends org.springframework.boot.web.server.AbstractConfigurableWebServerFactory implements org.springframework.boot.web.servlet.server.ConfigurableServletWebServerFactory {
  protected final org.apache.commons.logging.Log logger;

  private java.lang.String contextPath;

  private java.lang.String displayName;

  private org.springframework.boot.web.servlet.server.Session session;

  private boolean registerDefaultServlet;

  private org.springframework.boot.web.server.MimeMappings mimeMappings;

  private java.util.List<org.springframework.boot.web.servlet.ServletContextInitializer> initializers;

  private org.springframework.boot.web.servlet.server.Jsp jsp;

  private java.util.Map<java.util.Locale, java.nio.charset.Charset> localeCharsetMappings;

  private java.util.Map<java.lang.String, java.lang.String> initParameters;

  private java.util.List<org.springframework.boot.web.servlet.server.CookieSameSiteSupplier> cookieSameSiteSuppliers;

  private final org.springframework.boot.web.servlet.server.DocumentRoot documentRoot;

  private final org.springframework.boot.web.servlet.server.StaticResourceJars staticResourceJars;

  private final java.util.Set<java.lang.String> webListenerClassNames;

  public org.springframework.boot.web.servlet.server.AbstractServletWebServerFactory();
    Code:
       0: aload_0
       1: invokespecial #1                  // Method org/springframework/boot/web/server/AbstractConfigurableWebServerFactory."<init>":()V
       4: aload_0
       5: aload_0
       6: invokevirtual #7                  // Method java/lang/Object.getClass:()Ljava/lang/Class;
       9: invokestatic  #13                 // Method org/apache/commons/logging/LogFactory.getLog:(Ljava/lang/Class;)Lorg/apache/commons/logging/Log;
      12: putfield      #19                 // Field logger:Lorg/apache/commons/logging/Log;
      15: aload_0
      16: ldc           #25                 // String
      18: putfield      #27                 // Field contextPath:Ljava/lang/String;
      21: aload_0
      22: new           #31                 // class org/springframework/boot/web/servlet/server/Session
      25: dup
      26: invokespecial #33                 // Method org/springframework/boot/web/servlet/server/Session."<init>":()V
      29: putfield      #34                 // Field session:Lorg/springframework/boot/web/servlet/server/Session;
      32: aload_0
      33: iconst_0
      34: putfield      #38                 // Field registerDefaultServlet:Z
      37: aload_0
      38: getstatic     #42                 // Field org/springframework/boot/web/server/MimeMappings.DEFAULT:Lorg/springframework/boot/web/server/MimeMappings;
      41: invokestatic  #48                 // Method org/springframework/boot/web/server/MimeMappings.lazyCopy:(Lorg/springframework/boot/web/server/MimeMappings;)Lorg/springframework/boot/web/server/MimeMappings;
      44: putfield      #52                 // Field mimeMappings:Lorg/springframework/boot/web/server/MimeMappings;
      47: aload_0
      48: new           #55                 // class java/util/ArrayList
      51: dup
      52: invokespecial #57                 // Method java/util/ArrayList."<init>":()V
      55: putfield      #58                 // Field initializers:Ljava/util/List;
      58: aload_0
      59: new           #62                 // class org/springframework/boot/web/servlet/server/Jsp
      62: dup
      63: invokespecial #64                 // Method org/springframework/boot/web/servlet/server/Jsp."<init>":()V
      66: putfield      #65                 // Field jsp:Lorg/springframework/boot/web/servlet/server/Jsp;
      69: aload_0
      70: new           #69                 // class java/util/HashMap
      73: dup
      74: invokespecial #71                 // Method java/util/HashMap."<init>":()V
      77: putfield      #72                 // Field localeCharsetMappings:Ljava/util/Map;
      80: aload_0
      81: invokestatic  #76                 // Method java/util/Collections.emptyMap:()Ljava/util/Map;
      84: putfield      #82                 // Field initParameters:Ljava/util/Map;
      87: aload_0
      88: new           #55                 // class java/util/ArrayList
      91: dup
      92: invokespecial #57                 // Method java/util/ArrayList."<init>":()V
      95: putfield      #85                 // Field cookieSameSiteSuppliers:Ljava/util/List;
      98: aload_0
      99: new           #88                 // class org/springframework/boot/web/servlet/server/DocumentRoot
     102: dup
     103: aload_0
     104: getfield      #19                 // Field logger:Lorg/apache/commons/logging/Log;
     107: invokespecial #90                 // Method org/springframework/boot/web/servlet/server/DocumentRoot."<init>":(Lorg/apache/commons/logging/Log;)V
     110: putfield      #93                 // Field documentRoot:Lorg/springframework/boot/web/servlet/server/DocumentRoot;
     113: aload_0
     114: new           #97                 // class org/springframework/boot/web/servlet/server/StaticResourceJars
     117: dup
     118: invokespecial #99                 // Method org/springframework/boot/web/servlet/server/StaticResourceJars."<init>":()V
     121: putfield      #100                // Field staticResourceJars:Lorg/springframework/boot/web/servlet/server/StaticResourceJars;
     124: aload_0
     125: new           #104                // class java/util/HashSet
     128: dup
     129: invokespecial #106                // Method java/util/HashSet."<init>":()V
     132: putfield      #107                // Field webListenerClassNames:Ljava/util/Set;
     135: return

  public org.springframework.boot.web.servlet.server.AbstractServletWebServerFactory(int);
    Code:
       0: aload_0
       1: iload_1
       2: invokespecial #111                // Method org/springframework/boot/web/server/AbstractConfigurableWebServerFactory."<init>":(I)V
       5: aload_0
       6: aload_0
       7: invokevirtual #7                  // Method java/lang/Object.getClass:()Ljava/lang/Class;
      10: invokestatic  #13                 // Method org/apache/commons/logging/LogFactory.getLog:(Ljava/lang/Class;)Lorg/apache/commons/logging/Log;
      13: putfield      #19                 // Field logger:Lorg/apache/commons/logging/Log;
      16: aload_0
      17: ldc           #25                 // String
      19: putfield      #27                 // Field contextPath:Ljava/lang/String;
      22: aload_0
      23: new           #31                 // class org/springframework/boot/web/servlet/server/Session
      26: dup
      27: invokespecial #33                 // Method org/springframework/boot/web/servlet/server/Session."<init>":()V
      30: putfield      #34                 // Field session:Lorg/springframework/boot/web/servlet/server/Session;
      33: aload_0
      34: iconst_0
      35: putfield      #38                 // Field registerDefaultServlet:Z
      38: aload_0
      39: getstatic     #42                 // Field org/springframework/boot/web/server/MimeMappings.DEFAULT:Lorg/springframework/boot/web/server/MimeMappings;
      42: invokestatic  #48                 // Method org/springframework/boot/web/server/MimeMappings.lazyCopy:(Lorg/springframework/boot/web/server/MimeMappings;)Lorg/springframework/boot/web/server/MimeMappings;
      45: putfield      #52                 // Field mimeMappings:Lorg/springframework/boot/web/server/MimeMappings;
      48: aload_0
      49: new           #55                 // class java/util/ArrayList
      52: dup
      53: invokespecial #57                 // Method java/util/ArrayList."<init>":()V
      56: putfield      #58                 // Field initializers:Ljava/util/List;
      59: aload_0
      60: new           #62                 // class org/springframework/boot/web/servlet/server/Jsp
      63: dup
      64: invokespecial #64                 // Method org/springframework/boot/web/servlet/server/Jsp."<init>":()V
      67: putfield      #65                 // Field jsp:Lorg/springframework/boot/web/servlet/server/Jsp;
      70: aload_0
      71: new           #69                 // class java/util/HashMap
      74: dup
      75: invokespecial #71                 // Method java/util/HashMap."<init>":()V
      78: putfield      #72                 // Field localeCharsetMappings:Ljava/util/Map;
      81: aload_0
      82: invokestatic  #76                 // Method java/util/Collections.emptyMap:()Ljava/util/Map;
      85: putfield      #82                 // Field initParameters:Ljava/util/Map;
      88: aload_0
      89: new           #55                 // class java/util/ArrayList
      92: dup
      93: invokespecial #57                 // Method java/util/ArrayList."<init>":()V
      96: putfield      #85                 // Field cookieSameSiteSuppliers:Ljava/util/List;
      99: aload_0
     100: new           #88                 // class org/springframework/boot/web/servlet/server/DocumentRoot
     103: dup
     104: aload_0
     105: getfield      #19                 // Field logger:Lorg/apache/commons/logging/Log;
     108: invokespecial #90                 // Method org/springframework/boot/web/servlet/server/DocumentRoot."<init>":(Lorg/apache/commons/logging/Log;)V
     111: putfield      #93                 // Field documentRoot:Lorg/springframework/boot/web/servlet/server/DocumentRoot;
     114: aload_0
     115: new           #97                 // class org/springframework/boot/web/servlet/server/StaticResourceJars
     118: dup
     119: invokespecial #99                 // Method org/springframework/boot/web/servlet/server/StaticResourceJars."<init>":()V
     122: putfield      #100                // Field staticResourceJars:Lorg/springframework/boot/web/servlet/server/StaticResourceJars;
     125: aload_0
     126: new           #104                // class java/util/HashSet
     129: dup
     130: invokespecial #106                // Method java/util/HashSet."<init>":()V
     133: putfield      #107                // Field webListenerClassNames:Ljava/util/Set;
     136: return

  public org.springframework.boot.web.servlet.server.AbstractServletWebServerFactory(java.lang.String, int);
    Code:
       0: aload_0
       1: iload_2
       2: invokespecial #111                // Method org/springframework/boot/web/server/AbstractConfigurableWebServerFactory."<init>":(I)V
       5: aload_0
       6: aload_0
       7: invokevirtual #7                  // Method java/lang/Object.getClass:()Ljava/lang/Class;
      10: invokestatic  #13                 // Method org/apache/commons/logging/LogFactory.getLog:(Ljava/lang/Class;)Lorg/apache/commons/logging/Log;
      13: putfield      #19                 // Field logger:Lorg/apache/commons/logging/Log;
      16: aload_0
      17: ldc           #25                 // String
      19: putfield      #27                 // Field contextPath:Ljava/lang/String;
      22: aload_0
      23: new           #31                 // class org/springframework/boot/web/servlet/server/Session
      26: dup
      27: invokespecial #33                 // Method org/springframework/boot/web/servlet/server/Session."<init>":()V
      30: putfield      #34                 // Field session:Lorg/springframework/boot/web/servlet/server/Session;
      33: aload_0
      34: iconst_0
      35: putfield      #38                 // Field registerDefaultServlet:Z
      38: aload_0
      39: getstatic     #42                 // Field org/springframework/boot/web/server/MimeMappings.DEFAULT:Lorg/springframework/boot/web/server/MimeMappings;
      42: invokestatic  #48                 // Method org/springframework/boot/web/server/MimeMappings.lazyCopy:(Lorg/springframework/boot/web/server/MimeMappings;)Lorg/springframework/boot/web/server/MimeMappings;
      45: putfield      #52                 // Field mimeMappings:Lorg/springframework/boot/web/server/MimeMappings;
      48: aload_0
      49: new           #55                 // class java/util/ArrayList
      52: dup
      53: invokespecial #57                 // Method java/util/ArrayList."<init>":()V
      56: putfield      #58                 // Field initializers:Ljava/util/List;
      59: aload_0
      60: new           #62                 // class org/springframework/boot/web/servlet/server/Jsp
      63: dup
      64: invokespecial #64                 // Method org/springframework/boot/web/servlet/server/Jsp."<init>":()V
      67: putfield      #65                 // Field jsp:Lorg/springframework/boot/web/servlet/server/Jsp;
      70: aload_0
      71: new           #69                 // class java/util/HashMap
      74: dup
      75: invokespecial #71                 // Method java/util/HashMap."<init>":()V
      78: putfield      #72                 // Field localeCharsetMappings:Ljava/util/Map;
      81: aload_0
      82: invokestatic  #76                 // Method java/util/Collections.emptyMap:()Ljava/util/Map;
      85: putfield      #82                 // Field initParameters:Ljava/util/Map;
      88: aload_0
      89: new           #55                 // class java/util/ArrayList
      92: dup
      93: invokespecial #57                 // Method java/util/ArrayList."<init>":()V
      96: putfield      #85                 // Field cookieSameSiteSuppliers:Ljava/util/List;
      99: aload_0
     100: new           #88                 // class org/springframework/boot/web/servlet/server/DocumentRoot
     103: dup
     104: aload_0
     105: getfield      #19                 // Field logger:Lorg/apache/commons/logging/Log;
     108: invokespecial #90                 // Method org/springframework/boot/web/servlet/server/DocumentRoot."<init>":(Lorg/apache/commons/logging/Log;)V
     111: putfield      #93                 // Field documentRoot:Lorg/springframework/boot/web/servlet/server/DocumentRoot;
     114: aload_0
     115: new           #97                 // class org/springframework/boot/web/servlet/server/StaticResourceJars
     118: dup
     119: invokespecial #99                 // Method org/springframework/boot/web/servlet/server/StaticResourceJars."<init>":()V
     122: putfield      #100                // Field staticResourceJars:Lorg/springframework/boot/web/servlet/server/StaticResourceJars;
     125: aload_0
     126: new           #104                // class java/util/HashSet
     129: dup
     130: invokespecial #106                // Method java/util/HashSet."<init>":()V
     133: putfield      #107                // Field webListenerClassNames:Ljava/util/Set;
     136: aload_0
     137: aload_1
     138: invokevirtual #114                // Method checkContextPath:(Ljava/lang/String;)V
     141: aload_0
     142: aload_1
     143: putfield      #27                 // Field contextPath:Ljava/lang/String;
     146: return

  public java.lang.String getContextPath();
    Code:
       0: aload_0
       1: getfield      #27                 // Field contextPath:Ljava/lang/String;
       4: areturn

  public void setContextPath(java.lang.String);
    Code:
       0: aload_0
       1: aload_1
       2: invokevirtual #114                // Method checkContextPath:(Ljava/lang/String;)V
       5: aload_0
       6: aload_1
       7: putfield      #27                 // Field contextPath:Ljava/lang/String;
      10: return

  private void checkContextPath(java.lang.String);
    Code:
       0: aload_1
       1: ldc           #118                // String ContextPath must not be null
       3: invokestatic  #120                // Method org/springframework/util/Assert.notNull:(Ljava/lang/Object;Ljava/lang/String;)V
       6: aload_1
       7: invokevirtual #126                // Method java/lang/String.isEmpty:()Z
      10: ifne          60
      13: ldc           #132                // String /
      15: aload_1
      16: invokevirtual #134                // Method java/lang/String.equals:(Ljava/lang/Object;)Z
      19: ifeq          32
      22: new           #138                // class java/lang/IllegalArgumentException
      25: dup
      26: ldc           #140                // String Root ContextPath must be specified using an empty string
      28: invokespecial #142                // Method java/lang/IllegalArgumentException."<init>":(Ljava/lang/String;)V
      31: athrow
      32: aload_1
      33: ldc           #132                // String /
      35: invokevirtual #144                // Method java/lang/String.startsWith:(Ljava/lang/String;)Z
      38: ifeq          50
      41: aload_1
      42: ldc           #132                // String /
      44: invokevirtual #148                // Method java/lang/String.endsWith:(Ljava/lang/String;)Z
      47: ifeq          60
      50: new           #138                // class java/lang/IllegalArgumentException
      53: dup
      54: ldc           #151                // String ContextPath must start with \'/\' and not end with \'/\'
      56: invokespecial #142                // Method java/lang/IllegalArgumentException."<init>":(Ljava/lang/String;)V
      59: athrow
      60: return

  public java.lang.String getDisplayName();
    Code:
       0: aload_0
       1: getfield      #153                // Field displayName:Ljava/lang/String;
       4: areturn

  public void setDisplayName(java.lang.String);
    Code:
       0: aload_0
       1: aload_1
       2: putfield      #153                // Field displayName:Ljava/lang/String;
       5: return

  public boolean isRegisterDefaultServlet();
    Code:
       0: aload_0
       1: getfield      #38                 // Field registerDefaultServlet:Z
       4: ireturn

  public void setRegisterDefaultServlet(boolean);
    Code:
       0: aload_0
       1: iload_1
       2: putfield      #38                 // Field registerDefaultServlet:Z
       5: return

  public org.springframework.boot.web.server.MimeMappings getMimeMappings();
    Code:
       0: aload_0
       1: getfield      #52                 // Field mimeMappings:Lorg/springframework/boot/web/server/MimeMappings;
       4: areturn

  public void setMimeMappings(org.springframework.boot.web.server.MimeMappings);
    Code:
       0: aload_1
       1: ldc           #156                // String MimeMappings must not be null
       3: invokestatic  #120                // Method org/springframework/util/Assert.notNull:(Ljava/lang/Object;Ljava/lang/String;)V
       6: aload_0
       7: new           #43                 // class org/springframework/boot/web/server/MimeMappings
      10: dup
      11: aload_1
      12: invokespecial #158                // Method org/springframework/boot/web/server/MimeMappings."<init>":(Lorg/springframework/boot/web/server/MimeMappings;)V
      15: putfield      #52                 // Field mimeMappings:Lorg/springframework/boot/web/server/MimeMappings;
      18: return

  public java.io.File getDocumentRoot();
    Code:
       0: aload_0
       1: getfield      #93                 // Field documentRoot:Lorg/springframework/boot/web/servlet/server/DocumentRoot;
       4: invokevirtual #161                // Method org/springframework/boot/web/servlet/server/DocumentRoot.getDirectory:()Ljava/io/File;
       7: areturn

  public void setDocumentRoot(java.io.File);
    Code:
       0: aload_0
       1: getfield      #93                 // Field documentRoot:Lorg/springframework/boot/web/servlet/server/DocumentRoot;
       4: aload_1
       5: invokevirtual #165                // Method org/springframework/boot/web/servlet/server/DocumentRoot.setDirectory:(Ljava/io/File;)V
       8: return

  public void setInitializers(java.util.List<? extends org.springframework.boot.web.servlet.ServletContextInitializer>);
    Code:
       0: aload_1
       1: ldc           #169                // String Initializers must not be null
       3: invokestatic  #120                // Method org/springframework/util/Assert.notNull:(Ljava/lang/Object;Ljava/lang/String;)V
       6: aload_0
       7: new           #55                 // class java/util/ArrayList
      10: dup
      11: aload_1
      12: invokespecial #171                // Method java/util/ArrayList."<init>":(Ljava/util/Collection;)V
      15: putfield      #58                 // Field initializers:Ljava/util/List;
      18: return

  public void addInitializers(org.springframework.boot.web.servlet.ServletContextInitializer...);
    Code:
       0: aload_1
       1: ldc           #169                // String Initializers must not be null
       3: invokestatic  #120                // Method org/springframework/util/Assert.notNull:(Ljava/lang/Object;Ljava/lang/String;)V
       6: aload_0
       7: getfield      #58                 // Field initializers:Ljava/util/List;
      10: aload_1
      11: invokestatic  #174                // Method java/util/Arrays.asList:([Ljava/lang/Object;)Ljava/util/List;
      14: invokeinterface #180,  2          // InterfaceMethod java/util/List.addAll:(Ljava/util/Collection;)Z
      19: pop
      20: return

  public org.springframework.boot.web.servlet.server.Jsp getJsp();
    Code:
       0: aload_0
       1: getfield      #65                 // Field jsp:Lorg/springframework/boot/web/servlet/server/Jsp;
       4: areturn

  public void setJsp(org.springframework.boot.web.servlet.server.Jsp);
    Code:
       0: aload_0
       1: aload_1
       2: putfield      #65                 // Field jsp:Lorg/springframework/boot/web/servlet/server/Jsp;
       5: return

  public org.springframework.boot.web.servlet.server.Session getSession();
    Code:
       0: aload_0
       1: getfield      #34                 // Field session:Lorg/springframework/boot/web/servlet/server/Session;
       4: areturn

  public void setSession(org.springframework.boot.web.servlet.server.Session);
    Code:
       0: aload_0
       1: aload_1
       2: putfield      #34                 // Field session:Lorg/springframework/boot/web/servlet/server/Session;
       5: return

  public java.util.Map<java.util.Locale, java.nio.charset.Charset> getLocaleCharsetMappings();
    Code:
       0: aload_0
       1: getfield      #72                 // Field localeCharsetMappings:Ljava/util/Map;
       4: areturn

  public void setLocaleCharsetMappings(java.util.Map<java.util.Locale, java.nio.charset.Charset>);
    Code:
       0: aload_1
       1: ldc           #186                // String localeCharsetMappings must not be null
       3: invokestatic  #120                // Method org/springframework/util/Assert.notNull:(Ljava/lang/Object;Ljava/lang/String;)V
       6: aload_0
       7: aload_1
       8: putfield      #72                 // Field localeCharsetMappings:Ljava/util/Map;
      11: return

  public void setInitParameters(java.util.Map<java.lang.String, java.lang.String>);
    Code:
       0: aload_0
       1: aload_1
       2: putfield      #82                 // Field initParameters:Ljava/util/Map;
       5: return

  public java.util.Map<java.lang.String, java.lang.String> getInitParameters();
    Code:
       0: aload_0
       1: getfield      #82                 // Field initParameters:Ljava/util/Map;
       4: areturn

  public void setCookieSameSiteSuppliers(java.util.List<? extends org.springframework.boot.web.servlet.server.CookieSameSiteSupplier>);
    Code:
       0: aload_1
       1: ldc           #188                // String CookieSameSiteSuppliers must not be null
       3: invokestatic  #120                // Method org/springframework/util/Assert.notNull:(Ljava/lang/Object;Ljava/lang/String;)V
       6: aload_0
       7: new           #55                 // class java/util/ArrayList
      10: dup
      11: aload_1
      12: invokespecial #171                // Method java/util/ArrayList."<init>":(Ljava/util/Collection;)V
      15: putfield      #85                 // Field cookieSameSiteSuppliers:Ljava/util/List;
      18: return

  public void addCookieSameSiteSuppliers(org.springframework.boot.web.servlet.server.CookieSameSiteSupplier...);
    Code:
       0: aload_1
       1: ldc           #188                // String CookieSameSiteSuppliers must not be null
       3: invokestatic  #120                // Method org/springframework/util/Assert.notNull:(Ljava/lang/Object;Ljava/lang/String;)V
       6: aload_0
       7: getfield      #85                 // Field cookieSameSiteSuppliers:Ljava/util/List;
      10: aload_1
      11: invokestatic  #174                // Method java/util/Arrays.asList:([Ljava/lang/Object;)Ljava/util/List;
      14: invokeinterface #180,  2          // InterfaceMethod java/util/List.addAll:(Ljava/util/Collection;)Z
      19: pop
      20: return

  public java.util.List<org.springframework.boot.web.servlet.server.CookieSameSiteSupplier> getCookieSameSiteSuppliers();
    Code:
       0: aload_0
       1: getfield      #85                 // Field cookieSameSiteSuppliers:Ljava/util/List;
       4: areturn

  protected final org.springframework.boot.web.servlet.ServletContextInitializer[] mergeInitializers(org.springframework.boot.web.servlet.ServletContextInitializer...);
    Code:
       0: new           #55                 // class java/util/ArrayList
       3: dup
       4: invokespecial #57                 // Method java/util/ArrayList."<init>":()V
       7: astore_2
       8: aload_2
       9: aload_0
      10: invokedynamic #190,  0            // InvokeDynamic #0:onStartup:(Lorg/springframework/boot/web/servlet/server/AbstractServletWebServerFactory;)Lorg/springframework/boot/web/servlet/ServletContextInitializer;
      15: invokeinterface #194,  2          // InterfaceMethod java/util/List.add:(Ljava/lang/Object;)Z
      20: pop
      21: aload_2
      22: new           #197                // class org/springframework/boot/web/servlet/server/AbstractServletWebServerFactory$SessionConfiguringInitializer
      25: dup
      26: aload_0
      27: getfield      #34                 // Field session:Lorg/springframework/boot/web/servlet/server/Session;
      30: invokespecial #199                // Method org/springframework/boot/web/servlet/server/AbstractServletWebServerFactory$SessionConfiguringInitializer."<init>":(Lorg/springframework/boot/web/servlet/server/Session;)V
      33: invokeinterface #194,  2          // InterfaceMethod java/util/List.add:(Ljava/lang/Object;)Z
      38: pop
      39: aload_2
      40: aload_1
      41: invokestatic  #174                // Method java/util/Arrays.asList:([Ljava/lang/Object;)Ljava/util/List;
      44: invokeinterface #180,  2          // InterfaceMethod java/util/List.addAll:(Ljava/util/Collection;)Z
      49: pop
      50: aload_2
      51: aload_0
      52: getfield      #58                 // Field initializers:Ljava/util/List;
      55: invokeinterface #180,  2          // InterfaceMethod java/util/List.addAll:(Ljava/util/Collection;)Z
      60: pop
      61: aload_2
      62: iconst_0
      63: anewarray     #202                // class org/springframework/boot/web/servlet/ServletContextInitializer
      66: invokeinterface #204,  2          // InterfaceMethod java/util/List.toArray:([Ljava/lang/Object;)[Ljava/lang/Object;
      71: checkcast     #208                // class "[Lorg/springframework/boot/web/servlet/ServletContextInitializer;"
      74: areturn

  protected boolean shouldRegisterJspServlet();
    Code:
       0: aload_0
       1: getfield      #65                 // Field jsp:Lorg/springframework/boot/web/servlet/server/Jsp;
       4: ifnull        41
       7: aload_0
       8: getfield      #65                 // Field jsp:Lorg/springframework/boot/web/servlet/server/Jsp;
      11: invokevirtual #210                // Method org/springframework/boot/web/servlet/server/Jsp.getRegistered:()Z
      14: ifeq          41
      17: aload_0
      18: getfield      #65                 // Field jsp:Lorg/springframework/boot/web/servlet/server/Jsp;
      21: invokevirtual #213                // Method org/springframework/boot/web/servlet/server/Jsp.getClassName:()Ljava/lang/String;
      24: aload_0
      25: invokevirtual #7                  // Method java/lang/Object.getClass:()Ljava/lang/Class;
      28: invokevirtual #217                // Method java/lang/Class.getClassLoader:()Ljava/lang/ClassLoader;
      31: invokestatic  #223                // Method org/springframework/util/ClassUtils.isPresent:(Ljava/lang/String;Ljava/lang/ClassLoader;)Z
      34: ifeq          41
      37: iconst_1
      38: goto          42
      41: iconst_0
      42: ireturn

  protected final java.io.File getValidDocumentRoot();
    Code:
       0: aload_0
       1: getfield      #93                 // Field documentRoot:Lorg/springframework/boot/web/servlet/server/DocumentRoot;
       4: invokevirtual #229                // Method org/springframework/boot/web/servlet/server/DocumentRoot.getValidDirectory:()Ljava/io/File;
       7: areturn

  protected final java.util.List<java.net.URL> getUrlsOfJarsWithMetaInfResources();
    Code:
       0: aload_0
       1: getfield      #100                // Field staticResourceJars:Lorg/springframework/boot/web/servlet/server/StaticResourceJars;
       4: invokevirtual #232                // Method org/springframework/boot/web/servlet/server/StaticResourceJars.getUrls:()Ljava/util/List;
       7: areturn

  protected final java.io.File getValidSessionStoreDir();
    Code:
       0: aload_0
       1: iconst_1
       2: invokevirtual #236                // Method getValidSessionStoreDir:(Z)Ljava/io/File;
       5: areturn

  protected final java.io.File getValidSessionStoreDir(boolean);
    Code:
       0: aload_0
       1: getfield      #34                 // Field session:Lorg/springframework/boot/web/servlet/server/Session;
       4: invokevirtual #240                // Method org/springframework/boot/web/servlet/server/Session.getSessionStoreDirectory:()Lorg/springframework/boot/web/servlet/server/SessionStoreDirectory;
       7: iload_1
       8: invokevirtual #244                // Method org/springframework/boot/web/servlet/server/SessionStoreDirectory.getValidDirectory:(Z)Ljava/io/File;
      11: areturn

  public void addWebListeners(java.lang.String...);
    Code:
       0: aload_0
       1: getfield      #107                // Field webListenerClassNames:Ljava/util/Set;
       4: aload_1
       5: invokestatic  #174                // Method java/util/Arrays.asList:([Ljava/lang/Object;)Ljava/util/List;
       8: invokeinterface #248,  2          // InterfaceMethod java/util/Set.addAll:(Ljava/util/Collection;)Z
      13: pop
      14: return

  protected final java.util.Set<java.lang.String> getWebListenerClassNames();
    Code:
       0: aload_0
       1: getfield      #107                // Field webListenerClassNames:Ljava/util/Set;
       4: areturn

  private void lambda$mergeInitializers$0(jakarta.servlet.ServletContext) throws jakarta.servlet.ServletException;
    Code:
       0: aload_0
       1: getfield      #82                 // Field initParameters:Ljava/util/Map;
       4: aload_1
       5: dup
       6: invokestatic  #251                // Method java/util/Objects.requireNonNull:(Ljava/lang/Object;)Ljava/lang/Object;
       9: pop
      10: invokedynamic #257,  0            // InvokeDynamic #1:accept:(Ljakarta/servlet/ServletContext;)Ljava/util/function/BiConsumer;
      15: invokeinterface #261,  2          // InterfaceMethod java/util/Map.forEach:(Ljava/util/function/BiConsumer;)V
      20: return
}
