Compiled from "CookieSameSiteSupplier.java"
public interface org.springframework.boot.web.servlet.server.CookieSameSiteSupplier {
  public abstract org.springframework.boot.web.server.Cookie$SameSite getSameSite(jakarta.servlet.http.Cookie);

  public default org.springframework.boot.web.servlet.server.CookieSameSiteSupplier whenHasName(java.lang.String);
    Code:
       0: aload_1
       1: ldc           #1                  // String Name must not be empty
       3: invokestatic  #3                  // Method org/springframework/util/Assert.hasText:(Ljava/lang/String;Ljava/lang/String;)V
       6: aload_0
       7: aload_1
       8: invokedynamic #9,  0              // InvokeDynamic #0:test:(Ljava/lang/String;)Ljava/util/function/Predicate;
      13: invokeinterface #13,  2           // InterfaceMethod when:(Ljava/util/function/Predicate;)Lorg/springframework/boot/web/servlet/server/CookieSameSiteSupplier;
      18: areturn

  public default org.springframework.boot.web.servlet.server.CookieSameSiteSupplier whenHasName(java.util.function.Supplier<java.lang.String>);
    Code:
       0: aload_1
       1: ldc           #19                 // String NameSupplier must not be empty
       3: invokestatic  #21                 // Method org/springframework/util/Assert.notNull:(Ljava/lang/Object;Ljava/lang/String;)V
       6: aload_0
       7: aload_1
       8: invokedynamic #25,  0             // InvokeDynamic #1:test:(Ljava/util/function/Supplier;)Ljava/util/function/Predicate;
      13: invokeinterface #13,  2           // InterfaceMethod when:(Ljava/util/function/Predicate;)Lorg/springframework/boot/web/servlet/server/CookieSameSiteSupplier;
      18: areturn

  public default org.springframework.boot.web.servlet.server.CookieSameSiteSupplier whenHasNameMatching(java.lang.String);
    Code:
       0: aload_1
       1: ldc           #28                 // String Regex must not be empty
       3: invokestatic  #3                  // Method org/springframework/util/Assert.hasText:(Ljava/lang/String;Ljava/lang/String;)V
       6: aload_0
       7: aload_1
       8: invokestatic  #30                 // Method java/util/regex/Pattern.compile:(Ljava/lang/String;)Ljava/util/regex/Pattern;
      11: invokeinterface #36,  2           // InterfaceMethod whenHasNameMatching:(Ljava/util/regex/Pattern;)Lorg/springframework/boot/web/servlet/server/CookieSameSiteSupplier;
      16: areturn

  public default org.springframework.boot.web.servlet.server.CookieSameSiteSupplier whenHasNameMatching(java.util.regex.Pattern);
    Code:
       0: aload_1
       1: ldc           #40                 // String Pattern must not be null
       3: invokestatic  #21                 // Method org/springframework/util/Assert.notNull:(Ljava/lang/Object;Ljava/lang/String;)V
       6: aload_0
       7: aload_1
       8: invokedynamic #42,  0             // InvokeDynamic #2:test:(Ljava/util/regex/Pattern;)Ljava/util/function/Predicate;
      13: invokeinterface #13,  2           // InterfaceMethod when:(Ljava/util/function/Predicate;)Lorg/springframework/boot/web/servlet/server/CookieSameSiteSupplier;
      18: areturn

  public default org.springframework.boot.web.servlet.server.CookieSameSiteSupplier when(java.util.function.Predicate<jakarta.servlet.http.Cookie>);
    Code:
       0: aload_1
       1: ldc           #45                 // String Predicate must not be null
       3: invokestatic  #21                 // Method org/springframework/util/Assert.notNull:(Ljava/lang/Object;Ljava/lang/String;)V
       6: aload_0
       7: aload_1
       8: invokedynamic #47,  0             // InvokeDynamic #3:getSameSite:(Lorg/springframework/boot/web/servlet/server/CookieSameSiteSupplier;Ljava/util/function/Predicate;)Lorg/springframework/boot/web/servlet/server/CookieSameSiteSupplier;
      13: areturn

  public static org.springframework.boot.web.servlet.server.CookieSameSiteSupplier ofNone();
    Code:
       0: getstatic     #51                 // Field org/springframework/boot/web/server/Cookie$SameSite.NONE:Lorg/springframework/boot/web/server/Cookie$SameSite;
       3: invokestatic  #57                 // InterfaceMethod of:(Lorg/springframework/boot/web/server/Cookie$SameSite;)Lorg/springframework/boot/web/servlet/server/CookieSameSiteSupplier;
       6: areturn

  public static org.springframework.boot.web.servlet.server.CookieSameSiteSupplier ofLax();
    Code:
       0: getstatic     #61                 // Field org/springframework/boot/web/server/Cookie$SameSite.LAX:Lorg/springframework/boot/web/server/Cookie$SameSite;
       3: invokestatic  #57                 // InterfaceMethod of:(Lorg/springframework/boot/web/server/Cookie$SameSite;)Lorg/springframework/boot/web/servlet/server/CookieSameSiteSupplier;
       6: areturn

  public static org.springframework.boot.web.servlet.server.CookieSameSiteSupplier ofStrict();
    Code:
       0: getstatic     #64                 // Field org/springframework/boot/web/server/Cookie$SameSite.STRICT:Lorg/springframework/boot/web/server/Cookie$SameSite;
       3: invokestatic  #57                 // InterfaceMethod of:(Lorg/springframework/boot/web/server/Cookie$SameSite;)Lorg/springframework/boot/web/servlet/server/CookieSameSiteSupplier;
       6: areturn

  public static org.springframework.boot.web.servlet.server.CookieSameSiteSupplier of(org.springframework.boot.web.server.Cookie$SameSite);
    Code:
       0: aload_0
       1: ldc           #67                 // String SameSite must not be null
       3: invokestatic  #21                 // Method org/springframework/util/Assert.notNull:(Ljava/lang/Object;Ljava/lang/String;)V
       6: aload_0
       7: invokedynamic #69,  0             // InvokeDynamic #4:getSameSite:(Lorg/springframework/boot/web/server/Cookie$SameSite;)Lorg/springframework/boot/web/servlet/server/CookieSameSiteSupplier;
      12: areturn

  private static org.springframework.boot.web.server.Cookie$SameSite lambda$of$4(org.springframework.boot.web.server.Cookie$SameSite, jakarta.servlet.http.Cookie);
    Code:
       0: aload_0
       1: areturn

  private org.springframework.boot.web.server.Cookie$SameSite lambda$when$3(java.util.function.Predicate, jakarta.servlet.http.Cookie);
    Code:
       0: aload_1
       1: aload_2
       2: invokeinterface #71,  2           // InterfaceMethod java/util/function/Predicate.test:(Ljava/lang/Object;)Z
       7: ifeq          20
      10: aload_0
      11: aload_2
      12: invokeinterface #76,  2           // InterfaceMethod getSameSite:(Ljakarta/servlet/http/Cookie;)Lorg/springframework/boot/web/server/Cookie$SameSite;
      17: goto          21
      20: aconst_null
      21: areturn

  private static boolean lambda$whenHasNameMatching$2(java.util.regex.Pattern, jakarta.servlet.http.Cookie);
    Code:
       0: aload_0
       1: aload_1
       2: invokevirtual #79                 // Method jakarta/servlet/http/Cookie.getName:()Ljava/lang/String;
       5: invokevirtual #85                 // Method java/util/regex/Pattern.matcher:(Ljava/lang/CharSequence;)Ljava/util/regex/Matcher;
       8: invokevirtual #89                 // Method java/util/regex/Matcher.matches:()Z
      11: ireturn

  private static boolean lambda$whenHasName$1(java.util.function.Supplier, jakarta.servlet.http.Cookie);
    Code:
       0: aload_1
       1: invokevirtual #79                 // Method jakarta/servlet/http/Cookie.getName:()Ljava/lang/String;
       4: aload_0
       5: invokeinterface #95,  1           // InterfaceMethod java/util/function/Supplier.get:()Ljava/lang/Object;
      10: invokestatic  #101                // Method org/springframework/util/ObjectUtils.nullSafeEquals:(Ljava/lang/Object;Ljava/lang/Object;)Z
      13: ireturn

  private static boolean lambda$whenHasName$0(java.lang.String, jakarta.servlet.http.Cookie);
    Code:
       0: aload_1
       1: invokevirtual #79                 // Method jakarta/servlet/http/Cookie.getName:()Ljava/lang/String;
       4: aload_0
       5: invokestatic  #101                // Method org/springframework/util/ObjectUtils.nullSafeEquals:(Ljava/lang/Object;Ljava/lang/Object;)Z
       8: ireturn
}
