Compiled from "DocumentRoot.java"
class org.springframework.boot.web.servlet.server.DocumentRoot {
  private static final java.lang.String[] COMMON_DOC_ROOTS;

  private final org.apache.commons.logging.Log logger;

  private java.io.File directory;

  org.springframework.boot.web.servlet.server.DocumentRoot(org.apache.commons.logging.Log);
    Code:
       0: aload_0
       1: invokespecial #1                  // Method java/lang/Object."<init>":()V
       4: aload_0
       5: aload_1
       6: putfield      #7                  // Field logger:Lorg/apache/commons/logging/Log;
       9: return

  java.io.File getDirectory();
    Code:
       0: aload_0
       1: getfield      #13                 // Field directory:Ljava/io/File;
       4: areturn

  void setDirectory(java.io.File);
    Code:
       0: aload_0
       1: aload_1
       2: putfield      #13                 // Field directory:Ljava/io/File;
       5: return

  final java.io.File getValidDirectory();
    Code:
       0: aload_0
       1: getfield      #13                 // Field directory:Ljava/io/File;
       4: astore_1
       5: aload_1
       6: ifnull        13
       9: aload_1
      10: goto          17
      13: aload_0
      14: invokevirtual #17                 // Method getWarFileDocumentRoot:()Ljava/io/File;
      17: astore_1
      18: aload_1
      19: ifnull        26
      22: aload_1
      23: goto          30
      26: aload_0
      27: invokevirtual #21                 // Method getExplodedWarFileDocumentRoot:()Ljava/io/File;
      30: astore_1
      31: aload_1
      32: ifnull        39
      35: aload_1
      36: goto          43
      39: aload_0
      40: invokevirtual #24                 // Method getCommonDocumentRoot:()Ljava/io/File;
      43: astore_1
      44: aload_1
      45: ifnonnull     67
      48: aload_0
      49: getfield      #7                  // Field logger:Lorg/apache/commons/logging/Log;
      52: invokeinterface #27,  1           // InterfaceMethod org/apache/commons/logging/Log.isDebugEnabled:()Z
      57: ifeq          67
      60: aload_0
      61: invokevirtual #33                 // Method logNoDocumentRoots:()V
      64: goto          94
      67: aload_0
      68: getfield      #7                  // Field logger:Lorg/apache/commons/logging/Log;
      71: invokeinterface #27,  1           // InterfaceMethod org/apache/commons/logging/Log.isDebugEnabled:()Z
      76: ifeq          94
      79: aload_0
      80: getfield      #7                  // Field logger:Lorg/apache/commons/logging/Log;
      83: aload_1
      84: invokedynamic #36,  0             // InvokeDynamic #0:makeConcatWithConstants:(Ljava/io/File;)Ljava/lang/String;
      89: invokeinterface #40,  2           // InterfaceMethod org/apache/commons/logging/Log.debug:(Ljava/lang/Object;)V
      94: aload_1
      95: areturn

  private java.io.File getWarFileDocumentRoot();
    Code:
       0: aload_0
       1: ldc           #44                 // String .war
       3: invokevirtual #46                 // Method getArchiveFileDocumentRoot:(Ljava/lang/String;)Ljava/io/File;
       6: areturn

  private java.io.File getArchiveFileDocumentRoot(java.lang.String);
    Code:
       0: aload_0
       1: invokevirtual #50                 // Method getCodeSourceArchive:()Ljava/io/File;
       4: astore_2
       5: aload_0
       6: getfield      #7                  // Field logger:Lorg/apache/commons/logging/Log;
       9: invokeinterface #27,  1           // InterfaceMethod org/apache/commons/logging/Log.isDebugEnabled:()Z
      14: ifeq          32
      17: aload_0
      18: getfield      #7                  // Field logger:Lorg/apache/commons/logging/Log;
      21: aload_2
      22: invokedynamic #53,  0             // InvokeDynamic #1:makeConcatWithConstants:(Ljava/io/File;)Ljava/lang/String;
      27: invokeinterface #40,  2           // InterfaceMethod org/apache/commons/logging/Log.debug:(Ljava/lang/Object;)V
      32: aload_2
      33: ifnull        72
      36: aload_2
      37: invokevirtual #54                 // Method java/io/File.exists:()Z
      40: ifeq          72
      43: aload_2
      44: invokevirtual #59                 // Method java/io/File.isDirectory:()Z
      47: ifne          72
      50: aload_2
      51: invokevirtual #62                 // Method java/io/File.getName:()Ljava/lang/String;
      54: getstatic     #66                 // Field java/util/Locale.ENGLISH:Ljava/util/Locale;
      57: invokevirtual #72                 // Method java/lang/String.toLowerCase:(Ljava/util/Locale;)Ljava/lang/String;
      60: aload_1
      61: invokevirtual #78                 // Method java/lang/String.endsWith:(Ljava/lang/String;)Z
      64: ifeq          72
      67: aload_2
      68: invokevirtual #82                 // Method java/io/File.getAbsoluteFile:()Ljava/io/File;
      71: areturn
      72: aconst_null
      73: areturn

  private java.io.File getExplodedWarFileDocumentRoot();
    Code:
       0: aload_0
       1: aload_0
       2: invokevirtual #50                 // Method getCodeSourceArchive:()Ljava/io/File;
       5: invokevirtual #85                 // Method getExplodedWarFileDocumentRoot:(Ljava/io/File;)Ljava/io/File;
       8: areturn

  private java.io.File getCodeSourceArchive();
    Code:
       0: aload_0
       1: aload_0
       2: invokevirtual #88                 // Method java/lang/Object.getClass:()Ljava/lang/Class;
       5: invokevirtual #92                 // Method java/lang/Class.getProtectionDomain:()Ljava/security/ProtectionDomain;
       8: invokevirtual #98                 // Method java/security/ProtectionDomain.getCodeSource:()Ljava/security/CodeSource;
      11: invokevirtual #104                // Method getCodeSourceArchive:(Ljava/security/CodeSource;)Ljava/io/File;
      14: areturn

  java.io.File getCodeSourceArchive(java.security.CodeSource);
    Code:
       0: aload_1
       1: ifnull        11
       4: aload_1
       5: invokevirtual #107                // Method java/security/CodeSource.getLocation:()Ljava/net/URL;
       8: goto          12
      11: aconst_null
      12: astore_2
      13: aload_2
      14: ifnonnull     19
      17: aconst_null
      18: areturn
      19: aload_2
      20: invokevirtual #113                // Method java/net/URL.openConnection:()Ljava/net/URLConnection;
      23: astore        4
      25: aload         4
      27: instanceof    #119                // class java/net/JarURLConnection
      30: ifeq          52
      33: aload         4
      35: checkcast     #119                // class java/net/JarURLConnection
      38: astore        5
      40: aload         5
      42: invokevirtual #121                // Method java/net/JarURLConnection.getJarFile:()Ljava/util/jar/JarFile;
      45: invokevirtual #125                // Method java/util/jar/JarFile.getName:()Ljava/lang/String;
      48: astore_3
      49: goto          60
      52: aload_2
      53: invokevirtual #128                // Method java/net/URL.toURI:()Ljava/net/URI;
      56: invokevirtual #132                // Method java/net/URI.getPath:()Ljava/lang/String;
      59: astore_3
      60: aload_3
      61: ldc           #137                // String !/
      63: invokevirtual #139                // Method java/lang/String.indexOf:(Ljava/lang/String;)I
      66: istore        5
      68: iload         5
      70: iconst_m1
      71: if_icmpeq     82
      74: aload_3
      75: iconst_0
      76: iload         5
      78: invokevirtual #143                // Method java/lang/String.substring:(II)Ljava/lang/String;
      81: astore_3
      82: new           #55                 // class java/io/File
      85: dup
      86: aload_3
      87: invokespecial #147                // Method java/io/File."<init>":(Ljava/lang/String;)V
      90: areturn
      91: astore_2
      92: aconst_null
      93: areturn
    Exception table:
       from    to  target type
           0    18    91   Class java/lang/Exception
          19    90    91   Class java/lang/Exception

  final java.io.File getExplodedWarFileDocumentRoot(java.io.File);
    Code:
       0: aload_0
       1: getfield      #7                  // Field logger:Lorg/apache/commons/logging/Log;
       4: invokeinterface #27,  1           // InterfaceMethod org/apache/commons/logging/Log.isDebugEnabled:()Z
       9: ifeq          27
      12: aload_0
      13: getfield      #7                  // Field logger:Lorg/apache/commons/logging/Log;
      16: aload_1
      17: invokedynamic #53,  0             // InvokeDynamic #1:makeConcatWithConstants:(Ljava/io/File;)Ljava/lang/String;
      22: invokeinterface #40,  2           // InterfaceMethod org/apache/commons/logging/Log.debug:(Ljava/lang/Object;)V
      27: aload_1
      28: ifnull        79
      31: aload_1
      32: invokevirtual #54                 // Method java/io/File.exists:()Z
      35: ifeq          79
      38: aload_1
      39: invokevirtual #152                // Method java/io/File.getAbsolutePath:()Ljava/lang/String;
      42: astore_2
      43: aload_2
      44: getstatic     #155                // Field java/io/File.separatorChar:C
      47: getstatic     #155                // Field java/io/File.separatorChar:C
      50: invokedynamic #159,  0            // InvokeDynamic #2:makeConcatWithConstants:(CC)Ljava/lang/String;
      55: invokevirtual #139                // Method java/lang/String.indexOf:(Ljava/lang/String;)I
      58: istore_3
      59: iload_3
      60: iflt          79
      63: aload_2
      64: iconst_0
      65: iload_3
      66: invokevirtual #143                // Method java/lang/String.substring:(II)Ljava/lang/String;
      69: astore_2
      70: new           #55                 // class java/io/File
      73: dup
      74: aload_2
      75: invokespecial #147                // Method java/io/File."<init>":(Ljava/lang/String;)V
      78: areturn
      79: aconst_null
      80: areturn

  private java.io.File getCommonDocumentRoot();
    Code:
       0: getstatic     #162                // Field COMMON_DOC_ROOTS:[Ljava/lang/String;
       3: astore_1
       4: aload_1
       5: arraylength
       6: istore_2
       7: iconst_0
       8: istore_3
       9: iload_3
      10: iload_2
      11: if_icmpge     58
      14: aload_1
      15: iload_3
      16: aaload
      17: astore        4
      19: new           #55                 // class java/io/File
      22: dup
      23: aload         4
      25: invokespecial #147                // Method java/io/File."<init>":(Ljava/lang/String;)V
      28: astore        5
      30: aload         5
      32: invokevirtual #54                 // Method java/io/File.exists:()Z
      35: ifeq          52
      38: aload         5
      40: invokevirtual #59                 // Method java/io/File.isDirectory:()Z
      43: ifeq          52
      46: aload         5
      48: invokevirtual #82                 // Method java/io/File.getAbsoluteFile:()Ljava/io/File;
      51: areturn
      52: iinc          3, 1
      55: goto          9
      58: aconst_null
      59: areturn

  private void logNoDocumentRoots();
    Code:
       0: aload_0
       1: getfield      #7                  // Field logger:Lorg/apache/commons/logging/Log;
       4: getstatic     #162                // Field COMMON_DOC_ROOTS:[Ljava/lang/String;
       7: invokestatic  #166                // Method java/util/Arrays.asList:([Ljava/lang/Object;)Ljava/util/List;
      10: invokedynamic #172,  0            // InvokeDynamic #3:makeConcatWithConstants:(Ljava/util/List;)Ljava/lang/String;
      15: invokeinterface #40,  2           // InterfaceMethod org/apache/commons/logging/Log.debug:(Ljava/lang/Object;)V
      20: return

  static {};
    Code:
       0: iconst_3
       1: anewarray     #73                 // class java/lang/String
       4: dup
       5: iconst_0
       6: ldc           #175                // String src/main/webapp
       8: aastore
       9: dup
      10: iconst_1
      11: ldc           #177                // String public
      13: aastore
      14: dup
      15: iconst_2
      16: ldc           #179                // String static
      18: aastore
      19: putstatic     #162                // Field COMMON_DOC_ROOTS:[Ljava/lang/String;
      22: return
}
