Compiled from "Encoding.java"
public final class org.springframework.boot.web.servlet.server.Encoding$Type extends java.lang.Enum<org.springframework.boot.web.servlet.server.Encoding$Type> {
  public static final org.springframework.boot.web.servlet.server.Encoding$Type REQUEST;

  public static final org.springframework.boot.web.servlet.server.Encoding$Type RESPONSE;

  private static final org.springframework.boot.web.servlet.server.Encoding$Type[] $VALUES;

  public static org.springframework.boot.web.servlet.server.Encoding$Type[] values();
    Code:
       0: getstatic     #10                 // Field $VALUES:[Lorg/springframework/boot/web/servlet/server/Encoding$Type;
       3: invokevirtual #14                 // Method "[Lorg/springframework/boot/web/servlet/server/Encoding$Type;".clone:()Ljava/lang/Object;
       6: checkcast     #15                 // class "[Lorg/springframework/boot/web/servlet/server/Encoding$Type;"
       9: areturn

  public static org.springframework.boot.web.servlet.server.Encoding$Type valueOf(java.lang.String);
    Code:
       0: ldc           #1                  // class org/springframework/boot/web/servlet/server/Encoding$Type
       2: aload_0
       3: invokestatic  #19                 // Method java/lang/Enum.valueOf:(Ljava/lang/Class;Ljava/lang/String;)Ljava/lang/Enum;
       6: checkcast     #1                  // class org/springframework/boot/web/servlet/server/Encoding$Type
       9: areturn

  private org.springframework.boot.web.servlet.server.Encoding$Type();
    Code:
       0: aload_0
       1: aload_1
       2: iload_2
       3: invokespecial #25                 // Method java/lang/Enum."<init>":(Ljava/lang/String;I)V
       6: return

  private static org.springframework.boot.web.servlet.server.Encoding$Type[] $values();
    Code:
       0: iconst_2
       1: anewarray     #1                  // class org/springframework/boot/web/servlet/server/Encoding$Type
       4: dup
       5: iconst_0
       6: getstatic     #3                  // Field REQUEST:Lorg/springframework/boot/web/servlet/server/Encoding$Type;
       9: aastore
      10: dup
      11: iconst_1
      12: getstatic     #7                  // Field RESPONSE:Lorg/springframework/boot/web/servlet/server/Encoding$Type;
      15: aastore
      16: areturn

  static {};
    Code:
       0: new           #1                  // class org/springframework/boot/web/servlet/server/Encoding$Type
       3: dup
       4: ldc           #29                 // String REQUEST
       6: iconst_0
       7: invokespecial #30                 // Method "<init>":(Ljava/lang/String;I)V
      10: putstatic     #3                  // Field REQUEST:Lorg/springframework/boot/web/servlet/server/Encoding$Type;
      13: new           #1                  // class org/springframework/boot/web/servlet/server/Encoding$Type
      16: dup
      17: ldc           #31                 // String RESPONSE
      19: iconst_1
      20: invokespecial #30                 // Method "<init>":(Ljava/lang/String;I)V
      23: putstatic     #7                  // Field RESPONSE:Lorg/springframework/boot/web/servlet/server/Encoding$Type;
      26: invokestatic  #32                 // Method $values:()[Lorg/springframework/boot/web/servlet/server/Encoding$Type;
      29: putstatic     #10                 // Field $VALUES:[Lorg/springframework/boot/web/servlet/server/Encoding$Type;
      32: return
}
