Compiled from "Jsp.java"
public class org.springframework.boot.web.servlet.server.Jsp {
  private java.lang.String className;

  private java.util.Map<java.lang.String, java.lang.String> initParameters;

  private boolean registered;

  public org.springframework.boot.web.servlet.server.Jsp();
    Code:
       0: aload_0
       1: invokespecial #1                  // Method java/lang/Object."<init>":()V
       4: aload_0
       5: ldc           #7                  // String org.apache.jasper.servlet.JspServlet
       7: putfield      #9                  // Field className:Ljava/lang/String;
      10: aload_0
      11: new           #15                 // class java/util/HashMap
      14: dup
      15: invokespecial #17                 // Method java/util/HashMap."<init>":()V
      18: putfield      #18                 // Field initParameters:Ljava/util/Map;
      21: aload_0
      22: iconst_1
      23: putfield      #22                 // Field registered:Z
      26: aload_0
      27: getfield      #18                 // Field initParameters:Ljava/util/Map;
      30: ldc           #26                 // String development
      32: ldc           #28                 // String false
      34: invokeinterface #30,  3           // InterfaceMethod java/util/Map.put:(Ljava/lang/Object;Ljava/lang/Object;)Ljava/lang/Object;
      39: pop
      40: return

  public java.lang.String getClassName();
    Code:
       0: aload_0
       1: getfield      #9                  // Field className:Ljava/lang/String;
       4: areturn

  public void setClassName(java.lang.String);
    Code:
       0: aload_0
       1: aload_1
       2: putfield      #9                  // Field className:Ljava/lang/String;
       5: return

  public java.util.Map<java.lang.String, java.lang.String> getInitParameters();
    Code:
       0: aload_0
       1: getfield      #18                 // Field initParameters:Ljava/util/Map;
       4: areturn

  public void setInitParameters(java.util.Map<java.lang.String, java.lang.String>);
    Code:
       0: aload_0
       1: aload_1
       2: putfield      #18                 // Field initParameters:Ljava/util/Map;
       5: return

  public boolean getRegistered();
    Code:
       0: aload_0
       1: getfield      #22                 // Field registered:Z
       4: ireturn

  public void setRegistered(boolean);
    Code:
       0: aload_0
       1: iload_1
       2: putfield      #22                 // Field registered:Z
       5: return
}
