Compiled from "Session.java"
public final class org.springframework.boot.web.servlet.server.Session$SessionTrackingMode extends java.lang.Enum<org.springframework.boot.web.servlet.server.Session$SessionTrackingMode> {
  public static final org.springframework.boot.web.servlet.server.Session$SessionTrackingMode COOKIE;

  public static final org.springframework.boot.web.servlet.server.Session$SessionTrackingMode URL;

  public static final org.springframework.boot.web.servlet.server.Session$SessionTrackingMode SSL;

  private static final org.springframework.boot.web.servlet.server.Session$SessionTrackingMode[] $VALUES;

  public static org.springframework.boot.web.servlet.server.Session$SessionTrackingMode[] values();
    Code:
       0: getstatic     #13                 // Field $VALUES:[Lorg/springframework/boot/web/servlet/server/Session$SessionTrackingMode;
       3: invokevirtual #17                 // Method "[Lorg/springframework/boot/web/servlet/server/Session$SessionTrackingMode;".clone:()Ljava/lang/Object;
       6: checkcast     #18                 // class "[Lorg/springframework/boot/web/servlet/server/Session$SessionTrackingMode;"
       9: areturn

  public static org.springframework.boot.web.servlet.server.Session$SessionTrackingMode valueOf(java.lang.String);
    Code:
       0: ldc           #1                  // class org/springframework/boot/web/servlet/server/Session$SessionTrackingMode
       2: aload_0
       3: invokestatic  #22                 // Method java/lang/Enum.valueOf:(Ljava/lang/Class;Ljava/lang/String;)Ljava/lang/Enum;
       6: checkcast     #1                  // class org/springframework/boot/web/servlet/server/Session$SessionTrackingMode
       9: areturn

  private org.springframework.boot.web.servlet.server.Session$SessionTrackingMode();
    Code:
       0: aload_0
       1: aload_1
       2: iload_2
       3: invokespecial #28                 // Method java/lang/Enum."<init>":(Ljava/lang/String;I)V
       6: return

  private static org.springframework.boot.web.servlet.server.Session$SessionTrackingMode[] $values();
    Code:
       0: iconst_3
       1: anewarray     #1                  // class org/springframework/boot/web/servlet/server/Session$SessionTrackingMode
       4: dup
       5: iconst_0
       6: getstatic     #3                  // Field COOKIE:Lorg/springframework/boot/web/servlet/server/Session$SessionTrackingMode;
       9: aastore
      10: dup
      11: iconst_1
      12: getstatic     #7                  // Field URL:Lorg/springframework/boot/web/servlet/server/Session$SessionTrackingMode;
      15: aastore
      16: dup
      17: iconst_2
      18: getstatic     #10                 // Field SSL:Lorg/springframework/boot/web/servlet/server/Session$SessionTrackingMode;
      21: aastore
      22: areturn

  static {};
    Code:
       0: new           #1                  // class org/springframework/boot/web/servlet/server/Session$SessionTrackingMode
       3: dup
       4: ldc           #32                 // String COOKIE
       6: iconst_0
       7: invokespecial #33                 // Method "<init>":(Ljava/lang/String;I)V
      10: putstatic     #3                  // Field COOKIE:Lorg/springframework/boot/web/servlet/server/Session$SessionTrackingMode;
      13: new           #1                  // class org/springframework/boot/web/servlet/server/Session$SessionTrackingMode
      16: dup
      17: ldc           #34                 // String URL
      19: iconst_1
      20: invokespecial #33                 // Method "<init>":(Ljava/lang/String;I)V
      23: putstatic     #7                  // Field URL:Lorg/springframework/boot/web/servlet/server/Session$SessionTrackingMode;
      26: new           #1                  // class org/springframework/boot/web/servlet/server/Session$SessionTrackingMode
      29: dup
      30: ldc           #35                 // String SSL
      32: iconst_2
      33: invokespecial #33                 // Method "<init>":(Ljava/lang/String;I)V
      36: putstatic     #10                 // Field SSL:Lorg/springframework/boot/web/servlet/server/Session$SessionTrackingMode;
      39: invokestatic  #36                 // Method $values:()[Lorg/springframework/boot/web/servlet/server/Session$SessionTrackingMode;
      42: putstatic     #13                 // Field $VALUES:[Lorg/springframework/boot/web/servlet/server/Session$SessionTrackingMode;
      45: return
}
