Compiled from "JValidatorNew.java"
public class org.apache.dubbo.validation.support.jvalidation.JValidatorNew implements org.apache.dubbo.validation.Validator {
  private static final org.apache.dubbo.common.logger.ErrorTypeAwareLogger logger;

  private final java.lang.Class<?> clazz;

  private final java.util.Map<java.lang.String, java.lang.Class<?>> methodClassMap;

  private final jakarta.validation.Validator validator;

  public org.apache.dubbo.validation.support.jvalidation.JValidatorNew(org.apache.dubbo.common.URL);
    Code:
       0: aload_0
       1: invokespecial #2                  // Method java/lang/Object."<init>":()V
       4: aload_0
       5: aload_1
       6: invokevirtual #3                  // Method org/apache/dubbo/common/URL.getServiceInterface:()Ljava/lang/String;
       9: invokestatic  #4                  // Method org/apache/dubbo/common/utils/ReflectUtils.forName:(Ljava/lang/String;)Ljava/lang/Class;
      12: putfield      #5                  // Field clazz:Ljava/lang/Class;
      15: aload_1
      16: ldc           #6                  // String jvalidationNew
      18: invokevirtual #7                  // Method org/apache/dubbo/common/URL.getParameter:(Ljava/lang/String;)Ljava/lang/String;
      21: astore_2
      22: aload_2
      23: ifnull        54
      26: aload_2
      27: invokevirtual #8                  // Method java/lang/String.length:()I
      30: ifle          54
      33: aload_2
      34: invokestatic  #4                  // Method org/apache/dubbo/common/utils/ReflectUtils.forName:(Ljava/lang/String;)Ljava/lang/Class;
      37: invokestatic  #9                  // Method jakarta/validation/Validation.byProvider:(Ljava/lang/Class;)Ljakarta/validation/bootstrap/ProviderSpecificBootstrap;
      40: invokeinterface #10,  1           // InterfaceMethod jakarta/validation/bootstrap/ProviderSpecificBootstrap.configure:()Ljakarta/validation/Configuration;
      45: invokeinterface #11,  1           // InterfaceMethod jakarta/validation/Configuration.buildValidatorFactory:()Ljakarta/validation/ValidatorFactory;
      50: astore_3
      51: goto          58
      54: invokestatic  #12                 // Method jakarta/validation/Validation.buildDefaultValidatorFactory:()Ljakarta/validation/ValidatorFactory;
      57: astore_3
      58: aload_0
      59: aload_3
      60: invokeinterface #13,  1           // InterfaceMethod jakarta/validation/ValidatorFactory.getValidator:()Ljakarta/validation/Validator;
      65: putfield      #14                 // Field validator:Ljakarta/validation/Validator;
      68: aload_0
      69: new           #15                 // class java/util/concurrent/ConcurrentHashMap
      72: dup
      73: invokespecial #16                 // Method java/util/concurrent/ConcurrentHashMap."<init>":()V
      76: putfield      #17                 // Field methodClassMap:Ljava/util/Map;
      79: return

  private static java.lang.Object getMethodParameterBean(java.lang.Class<?>, java.lang.reflect.Method, java.lang.Object[]);
    Code:
       0: aload_1
       1: invokestatic  #18                 // Method hasConstraintParameter:(Ljava/lang/reflect/Method;)Z
       4: ifne          9
       7: aconst_null
       8: areturn
       9: aload_0
      10: aload_1
      11: invokestatic  #19                 // Method generateMethodParameterClassName:(Ljava/lang/Class;Ljava/lang/reflect/Method;)Ljava/lang/String;
      14: astore_3
      15: aload_3
      16: iconst_1
      17: aload_0
      18: invokevirtual #20                 // Method java/lang/Class.getClassLoader:()Ljava/lang/ClassLoader;
      21: invokestatic  #21                 // Method java/lang/Class.forName:(Ljava/lang/String;ZLjava/lang/ClassLoader;)Ljava/lang/Class;
      24: astore        4
      26: goto          39
      29: astore        5
      31: aload_0
      32: aload_1
      33: aload_3
      34: invokestatic  #23                 // Method generateMethodParameterClass:(Ljava/lang/Class;Ljava/lang/reflect/Method;Ljava/lang/String;)Ljava/lang/Class;
      37: astore        4
      39: aload         4
      41: iconst_0
      42: anewarray     #24                 // class java/lang/Class
      45: invokevirtual #25                 // Method java/lang/Class.getDeclaredConstructor:([Ljava/lang/Class;)Ljava/lang/reflect/Constructor;
      48: iconst_0
      49: anewarray     #26                 // class java/lang/Object
      52: invokevirtual #27                 // Method java/lang/reflect/Constructor.newInstance:([Ljava/lang/Object;)Ljava/lang/Object;
      55: astore        5
      57: iconst_0
      58: istore        6
      60: iload         6
      62: aload_2
      63: arraylength
      64: if_icmpge     118
      67: aload         4
      69: new           #28                 // class java/lang/StringBuilder
      72: dup
      73: invokespecial #29                 // Method java/lang/StringBuilder."<init>":()V
      76: aload_1
      77: invokevirtual #30                 // Method java/lang/reflect/Method.getName:()Ljava/lang/String;
      80: invokevirtual #31                 // Method java/lang/StringBuilder.append:(Ljava/lang/String;)Ljava/lang/StringBuilder;
      83: ldc           #32                 // String Argument
      85: invokevirtual #31                 // Method java/lang/StringBuilder.append:(Ljava/lang/String;)Ljava/lang/StringBuilder;
      88: iload         6
      90: invokevirtual #33                 // Method java/lang/StringBuilder.append:(I)Ljava/lang/StringBuilder;
      93: invokevirtual #34                 // Method java/lang/StringBuilder.toString:()Ljava/lang/String;
      96: invokevirtual #35                 // Method java/lang/Class.getField:(Ljava/lang/String;)Ljava/lang/reflect/Field;
      99: astore        7
     101: aload         7
     103: aload         5
     105: aload_2
     106: iload         6
     108: aaload
     109: invokevirtual #36                 // Method java/lang/reflect/Field.set:(Ljava/lang/Object;Ljava/lang/Object;)V
     112: iinc          6, 1
     115: goto          60
     118: aload         5
     120: areturn
     121: astore_3
     122: getstatic     #38                 // Field logger:Lorg/apache/dubbo/common/logger/ErrorTypeAwareLogger;
     125: ldc           #39                 // String 5-36
     127: ldc           #40                 // String
     129: ldc           #40                 // String
     131: aload_3
     132: invokevirtual #41                 // Method java/lang/Throwable.getMessage:()Ljava/lang/String;
     135: aload_3
     136: invokeinterface #42,  6           // InterfaceMethod org/apache/dubbo/common/logger/ErrorTypeAwareLogger.warn:(Ljava/lang/String;Ljava/lang/String;Ljava/lang/String;Ljava/lang/String;Ljava/lang/Throwable;)V
     141: aconst_null
     142: areturn
    Exception table:
       from    to  target type
          15    26    29   Class java/lang/ClassNotFoundException
           9   120   121   Class java/lang/Throwable

  private static java.lang.Class<?> generateMethodParameterClass(java.lang.Class<?>, java.lang.reflect.Method, java.lang.String) throws java.lang.Exception;
    Code:
       0: aload_0
       1: invokevirtual #20                 // Method java/lang/Class.getClassLoader:()Ljava/lang/ClassLoader;
       4: invokestatic  #43                 // Method org/apache/dubbo/common/bytecode/ClassGenerator.getClassPool:(Ljava/lang/ClassLoader;)Ljavassist/ClassPool;
       7: astore_3
       8: aload_2
       9: invokevirtual #44                 // Method java/lang/String.intern:()Ljava/lang/String;
      12: dup
      13: astore        4
      15: monitorenter
      16: aconst_null
      17: astore        5
      19: aload_3
      20: aload_2
      21: invokevirtual #45                 // Method javassist/ClassPool.getCtClass:(Ljava/lang/String;)Ljavassist/CtClass;
      24: astore        5
      26: goto          31
      29: astore        6
      31: aconst_null
      32: aload         5
      34: if_acmpne     452
      37: aload_3
      38: aload_2
      39: invokevirtual #47                 // Method javassist/ClassPool.makeClass:(Ljava/lang/String;)Ljavassist/CtClass;
      42: astore        5
      44: aload         5
      46: invokevirtual #48                 // Method javassist/CtClass.getClassFile:()Ljavassist/bytecode/ClassFile;
      49: astore        6
      51: aload         6
      53: invokevirtual #49                 // Method javassist/bytecode/ClassFile.setVersionToJava5:()V
      56: aload         5
      58: aload_3
      59: aload_2
      60: invokevirtual #45                 // Method javassist/ClassPool.getCtClass:(Ljava/lang/String;)Ljavassist/CtClass;
      63: invokestatic  #50                 // Method javassist/CtNewConstructor.defaultConstructor:(Ljavassist/CtClass;)Ljavassist/CtConstructor;
      66: invokevirtual #51                 // Method javassist/CtClass.addConstructor:(Ljavassist/CtConstructor;)V
      69: aload_1
      70: invokevirtual #52                 // Method java/lang/reflect/Method.getParameterTypes:()[Ljava/lang/Class;
      73: astore        7
      75: aload_1
      76: invokevirtual #53                 // Method java/lang/reflect/Method.getParameterAnnotations:()[[Ljava/lang/annotation/Annotation;
      79: astore        8
      81: iconst_0
      82: istore        9
      84: iload         9
      86: aload         7
      88: arraylength
      89: if_icmpge     438
      92: aload         7
      94: iload         9
      96: aaload
      97: astore        10
      99: aload         8
     101: iload         9
     103: aaload
     104: astore        11
     106: new           #54                 // class javassist/bytecode/AnnotationsAttribute
     109: dup
     110: aload         6
     112: invokevirtual #55                 // Method javassist/bytecode/ClassFile.getConstPool:()Ljavassist/bytecode/ConstPool;
     115: ldc           #56                 // String RuntimeVisibleAnnotations
     117: invokespecial #57                 // Method javassist/bytecode/AnnotationsAttribute."<init>":(Ljavassist/bytecode/ConstPool;Ljava/lang/String;)V
     120: astore        12
     122: aload         11
     124: astore        13
     126: aload         13
     128: arraylength
     129: istore        14
     131: iconst_0
     132: istore        15
     134: iload         15
     136: iload         14
     138: if_icmpge     338
     141: aload         13
     143: iload         15
     145: aaload
     146: astore        16
     148: aload         16
     150: invokeinterface #58,  1           // InterfaceMethod java/lang/annotation/Annotation.annotationType:()Ljava/lang/Class;
     155: ldc           #59                 // class jakarta/validation/Constraint
     157: invokevirtual #60                 // Method java/lang/Class.isAnnotationPresent:(Ljava/lang/Class;)Z
     160: ifeq          332
     163: new           #61                 // class javassist/bytecode/annotation/Annotation
     166: dup
     167: aload         6
     169: invokevirtual #55                 // Method javassist/bytecode/ClassFile.getConstPool:()Ljavassist/bytecode/ConstPool;
     172: aload_3
     173: aload         16
     175: invokeinterface #58,  1           // InterfaceMethod java/lang/annotation/Annotation.annotationType:()Ljava/lang/Class;
     180: invokevirtual #62                 // Method java/lang/Class.getName:()Ljava/lang/String;
     183: invokevirtual #45                 // Method javassist/ClassPool.getCtClass:(Ljava/lang/String;)Ljavassist/CtClass;
     186: invokespecial #63                 // Method javassist/bytecode/annotation/Annotation."<init>":(Ljavassist/bytecode/ConstPool;Ljavassist/CtClass;)V
     189: astore        17
     191: aload         16
     193: invokeinterface #58,  1           // InterfaceMethod java/lang/annotation/Annotation.annotationType:()Ljava/lang/Class;
     198: invokevirtual #64                 // Method java/lang/Class.getMethods:()[Ljava/lang/reflect/Method;
     201: astore        18
     203: aload         18
     205: astore        19
     207: aload         19
     209: arraylength
     210: istore        20
     212: iconst_0
     213: istore        21
     215: iload         21
     217: iload         20
     219: if_icmpge     325
     222: aload         19
     224: iload         21
     226: aaload
     227: astore        22
     229: aload         22
     231: invokevirtual #65                 // Method java/lang/reflect/Method.getModifiers:()I
     234: invokestatic  #66                 // Method javassist/Modifier.isPublic:(I)Z
     237: ifeq          319
     240: aload         22
     242: invokevirtual #52                 // Method java/lang/reflect/Method.getParameterTypes:()[Ljava/lang/Class;
     245: arraylength
     246: ifne          319
     249: aload         22
     251: invokevirtual #67                 // Method java/lang/reflect/Method.getDeclaringClass:()Ljava/lang/Class;
     254: aload         16
     256: invokeinterface #58,  1           // InterfaceMethod java/lang/annotation/Annotation.annotationType:()Ljava/lang/Class;
     261: if_acmpne     319
     264: aload         22
     266: aload         16
     268: iconst_0
     269: anewarray     #26                 // class java/lang/Object
     272: invokevirtual #68                 // Method java/lang/reflect/Method.invoke:(Ljava/lang/Object;[Ljava/lang/Object;)Ljava/lang/Object;
     275: astore        23
     277: aconst_null
     278: aload         23
     280: if_acmpeq     319
     283: aload         6
     285: invokevirtual #55                 // Method javassist/bytecode/ClassFile.getConstPool:()Ljavassist/bytecode/ConstPool;
     288: aload_3
     289: aload         22
     291: invokevirtual #69                 // Method java/lang/reflect/Method.getReturnType:()Ljava/lang/Class;
     294: invokevirtual #62                 // Method java/lang/Class.getName:()Ljava/lang/String;
     297: invokevirtual #70                 // Method javassist/ClassPool.get:(Ljava/lang/String;)Ljavassist/CtClass;
     300: aload         23
     302: invokestatic  #71                 // Method createMemberValue:(Ljavassist/bytecode/ConstPool;Ljavassist/CtClass;Ljava/lang/Object;)Ljavassist/bytecode/annotation/MemberValue;
     305: astore        24
     307: aload         17
     309: aload         22
     311: invokevirtual #30                 // Method java/lang/reflect/Method.getName:()Ljava/lang/String;
     314: aload         24
     316: invokevirtual #72                 // Method javassist/bytecode/annotation/Annotation.addMemberValue:(Ljava/lang/String;Ljavassist/bytecode/annotation/MemberValue;)V
     319: iinc          21, 1
     322: goto          215
     325: aload         12
     327: aload         17
     329: invokevirtual #73                 // Method javassist/bytecode/AnnotationsAttribute.addAnnotation:(Ljavassist/bytecode/annotation/Annotation;)V
     332: iinc          15, 1
     335: goto          134
     338: new           #28                 // class java/lang/StringBuilder
     341: dup
     342: invokespecial #29                 // Method java/lang/StringBuilder."<init>":()V
     345: aload_1
     346: invokevirtual #30                 // Method java/lang/reflect/Method.getName:()Ljava/lang/String;
     349: invokevirtual #31                 // Method java/lang/StringBuilder.append:(Ljava/lang/String;)Ljava/lang/StringBuilder;
     352: ldc           #32                 // String Argument
     354: invokevirtual #31                 // Method java/lang/StringBuilder.append:(Ljava/lang/String;)Ljava/lang/StringBuilder;
     357: iload         9
     359: invokevirtual #33                 // Method java/lang/StringBuilder.append:(I)Ljava/lang/StringBuilder;
     362: invokevirtual #34                 // Method java/lang/StringBuilder.toString:()Ljava/lang/String;
     365: astore        13
     367: new           #28                 // class java/lang/StringBuilder
     370: dup
     371: invokespecial #29                 // Method java/lang/StringBuilder."<init>":()V
     374: ldc           #74                 // String public
     376: invokevirtual #31                 // Method java/lang/StringBuilder.append:(Ljava/lang/String;)Ljava/lang/StringBuilder;
     379: aload         10
     381: invokevirtual #75                 // Method java/lang/Class.getCanonicalName:()Ljava/lang/String;
     384: invokevirtual #31                 // Method java/lang/StringBuilder.append:(Ljava/lang/String;)Ljava/lang/StringBuilder;
     387: ldc           #76                 // String
     389: invokevirtual #31                 // Method java/lang/StringBuilder.append:(Ljava/lang/String;)Ljava/lang/StringBuilder;
     392: aload         13
     394: invokevirtual #31                 // Method java/lang/StringBuilder.append:(Ljava/lang/String;)Ljava/lang/StringBuilder;
     397: ldc           #77                 // String ;
     399: invokevirtual #31                 // Method java/lang/StringBuilder.append:(Ljava/lang/String;)Ljava/lang/StringBuilder;
     402: invokevirtual #34                 // Method java/lang/StringBuilder.toString:()Ljava/lang/String;
     405: aload_3
     406: aload_2
     407: invokevirtual #45                 // Method javassist/ClassPool.getCtClass:(Ljava/lang/String;)Ljavassist/CtClass;
     410: invokestatic  #78                 // Method javassist/CtField.make:(Ljava/lang/String;Ljavassist/CtClass;)Ljavassist/CtField;
     413: astore        14
     415: aload         14
     417: invokevirtual #79                 // Method javassist/CtField.getFieldInfo:()Ljavassist/bytecode/FieldInfo;
     420: aload         12
     422: invokevirtual #80                 // Method javassist/bytecode/FieldInfo.addAttribute:(Ljavassist/bytecode/AttributeInfo;)V
     425: aload         5
     427: aload         14
     429: invokevirtual #81                 // Method javassist/CtClass.addField:(Ljavassist/CtField;)V
     432: iinc          9, 1
     435: goto          84
     438: aload         5
     440: aload_0
     441: invokevirtual #20                 // Method java/lang/Class.getClassLoader:()Ljava/lang/ClassLoader;
     444: aconst_null
     445: invokevirtual #82                 // Method javassist/CtClass.toClass:(Ljava/lang/ClassLoader;Ljava/security/ProtectionDomain;)Ljava/lang/Class;
     448: aload         4
     450: monitorexit
     451: areturn
     452: aload_2
     453: iconst_1
     454: aload_0
     455: invokevirtual #20                 // Method java/lang/Class.getClassLoader:()Ljava/lang/ClassLoader;
     458: invokestatic  #21                 // Method java/lang/Class.forName:(Ljava/lang/String;ZLjava/lang/ClassLoader;)Ljava/lang/Class;
     461: aload         4
     463: monitorexit
     464: areturn
     465: astore        25
     467: aload         4
     469: monitorexit
     470: aload         25
     472: athrow
    Exception table:
       from    to  target type
          19    26    29   Class javassist/NotFoundException
          16   451   465   any
         452   464   465   any
         465   470   465   any

  private static java.lang.String generateMethodParameterClassName(java.lang.Class<?>, java.lang.reflect.Method);
    Code:
       0: new           #28                 // class java/lang/StringBuilder
       3: dup
       4: invokespecial #29                 // Method java/lang/StringBuilder."<init>":()V
       7: aload_0
       8: invokevirtual #62                 // Method java/lang/Class.getName:()Ljava/lang/String;
      11: invokevirtual #31                 // Method java/lang/StringBuilder.append:(Ljava/lang/String;)Ljava/lang/StringBuilder;
      14: bipush        95
      16: invokevirtual #83                 // Method java/lang/StringBuilder.append:(C)Ljava/lang/StringBuilder;
      19: aload_1
      20: invokevirtual #30                 // Method java/lang/reflect/Method.getName:()Ljava/lang/String;
      23: invokestatic  #84                 // Method toUpperMethoName:(Ljava/lang/String;)Ljava/lang/String;
      26: invokevirtual #31                 // Method java/lang/StringBuilder.append:(Ljava/lang/String;)Ljava/lang/StringBuilder;
      29: ldc           #85                 // String Parameter
      31: invokevirtual #31                 // Method java/lang/StringBuilder.append:(Ljava/lang/String;)Ljava/lang/StringBuilder;
      34: astore_2
      35: aload_1
      36: invokevirtual #52                 // Method java/lang/reflect/Method.getParameterTypes:()[Ljava/lang/Class;
      39: astore_3
      40: aload_3
      41: astore        4
      43: aload         4
      45: arraylength
      46: istore        5
      48: iconst_0
      49: istore        6
      51: iload         6
      53: iload         5
      55: if_icmpge     86
      58: aload         4
      60: iload         6
      62: aaload
      63: astore        7
      65: aload_2
      66: bipush        95
      68: invokevirtual #83                 // Method java/lang/StringBuilder.append:(C)Ljava/lang/StringBuilder;
      71: aload         7
      73: invokevirtual #62                 // Method java/lang/Class.getName:()Ljava/lang/String;
      76: invokevirtual #31                 // Method java/lang/StringBuilder.append:(Ljava/lang/String;)Ljava/lang/StringBuilder;
      79: pop
      80: iinc          6, 1
      83: goto          51
      86: aload_2
      87: invokevirtual #34                 // Method java/lang/StringBuilder.toString:()Ljava/lang/String;
      90: areturn

  private static boolean hasConstraintParameter(java.lang.reflect.Method);
    Code:
       0: aload_0
       1: invokevirtual #53                 // Method java/lang/reflect/Method.getParameterAnnotations:()[[Ljava/lang/annotation/Annotation;
       4: astore_1
       5: aload_1
       6: arraylength
       7: ifle          85
      10: aload_1
      11: astore_2
      12: aload_2
      13: arraylength
      14: istore_3
      15: iconst_0
      16: istore        4
      18: iload         4
      20: iload_3
      21: if_icmpge     85
      24: aload_2
      25: iload         4
      27: aaload
      28: astore        5
      30: aload         5
      32: astore        6
      34: aload         6
      36: arraylength
      37: istore        7
      39: iconst_0
      40: istore        8
      42: iload         8
      44: iload         7
      46: if_icmpge     79
      49: aload         6
      51: iload         8
      53: aaload
      54: astore        9
      56: aload         9
      58: invokeinterface #58,  1           // InterfaceMethod java/lang/annotation/Annotation.annotationType:()Ljava/lang/Class;
      63: ldc           #59                 // class jakarta/validation/Constraint
      65: invokevirtual #60                 // Method java/lang/Class.isAnnotationPresent:(Ljava/lang/Class;)Z
      68: ifeq          73
      71: iconst_1
      72: ireturn
      73: iinc          8, 1
      76: goto          42
      79: iinc          4, 1
      82: goto          18
      85: iconst_0
      86: ireturn

  private static java.lang.String toUpperMethoName(java.lang.String);
    Code:
       0: new           #28                 // class java/lang/StringBuilder
       3: dup
       4: invokespecial #29                 // Method java/lang/StringBuilder."<init>":()V
       7: aload_0
       8: iconst_0
       9: iconst_1
      10: invokevirtual #86                 // Method java/lang/String.substring:(II)Ljava/lang/String;
      13: invokevirtual #87                 // Method java/lang/String.toUpperCase:()Ljava/lang/String;
      16: invokevirtual #31                 // Method java/lang/StringBuilder.append:(Ljava/lang/String;)Ljava/lang/StringBuilder;
      19: aload_0
      20: iconst_1
      21: invokevirtual #88                 // Method java/lang/String.substring:(I)Ljava/lang/String;
      24: invokevirtual #31                 // Method java/lang/StringBuilder.append:(Ljava/lang/String;)Ljava/lang/StringBuilder;
      27: invokevirtual #34                 // Method java/lang/StringBuilder.toString:()Ljava/lang/String;
      30: areturn

  private static javassist.bytecode.annotation.MemberValue createMemberValue(javassist.bytecode.ConstPool, javassist.CtClass, java.lang.Object) throws javassist.NotFoundException;
    Code:
       0: aload_0
       1: aload_1
       2: invokestatic  #89                 // Method javassist/bytecode/annotation/Annotation.createMemberValue:(Ljavassist/bytecode/ConstPool;Ljavassist/CtClass;)Ljavassist/bytecode/annotation/MemberValue;
       5: astore_3
       6: aload_3
       7: instanceof    #90                 // class javassist/bytecode/annotation/BooleanMemberValue
      10: ifeq          30
      13: aload_3
      14: checkcast     #90                 // class javassist/bytecode/annotation/BooleanMemberValue
      17: aload_2
      18: checkcast     #91                 // class java/lang/Boolean
      21: invokevirtual #92                 // Method java/lang/Boolean.booleanValue:()Z
      24: invokevirtual #93                 // Method javassist/bytecode/annotation/BooleanMemberValue.setValue:(Z)V
      27: goto          335
      30: aload_3
      31: instanceof    #94                 // class javassist/bytecode/annotation/ByteMemberValue
      34: ifeq          54
      37: aload_3
      38: checkcast     #94                 // class javassist/bytecode/annotation/ByteMemberValue
      41: aload_2
      42: checkcast     #95                 // class java/lang/Byte
      45: invokevirtual #96                 // Method java/lang/Byte.byteValue:()B
      48: invokevirtual #97                 // Method javassist/bytecode/annotation/ByteMemberValue.setValue:(B)V
      51: goto          335
      54: aload_3
      55: instanceof    #98                 // class javassist/bytecode/annotation/CharMemberValue
      58: ifeq          78
      61: aload_3
      62: checkcast     #98                 // class javassist/bytecode/annotation/CharMemberValue
      65: aload_2
      66: checkcast     #99                 // class java/lang/Character
      69: invokevirtual #100                // Method java/lang/Character.charValue:()C
      72: invokevirtual #101                // Method javassist/bytecode/annotation/CharMemberValue.setValue:(C)V
      75: goto          335
      78: aload_3
      79: instanceof    #102                // class javassist/bytecode/annotation/ShortMemberValue
      82: ifeq          102
      85: aload_3
      86: checkcast     #102                // class javassist/bytecode/annotation/ShortMemberValue
      89: aload_2
      90: checkcast     #103                // class java/lang/Short
      93: invokevirtual #104                // Method java/lang/Short.shortValue:()S
      96: invokevirtual #105                // Method javassist/bytecode/annotation/ShortMemberValue.setValue:(S)V
      99: goto          335
     102: aload_3
     103: instanceof    #106                // class javassist/bytecode/annotation/IntegerMemberValue
     106: ifeq          126
     109: aload_3
     110: checkcast     #106                // class javassist/bytecode/annotation/IntegerMemberValue
     113: aload_2
     114: checkcast     #107                // class java/lang/Integer
     117: invokevirtual #108                // Method java/lang/Integer.intValue:()I
     120: invokevirtual #109                // Method javassist/bytecode/annotation/IntegerMemberValue.setValue:(I)V
     123: goto          335
     126: aload_3
     127: instanceof    #110                // class javassist/bytecode/annotation/LongMemberValue
     130: ifeq          150
     133: aload_3
     134: checkcast     #110                // class javassist/bytecode/annotation/LongMemberValue
     137: aload_2
     138: checkcast     #111                // class java/lang/Long
     141: invokevirtual #112                // Method java/lang/Long.longValue:()J
     144: invokevirtual #113                // Method javassist/bytecode/annotation/LongMemberValue.setValue:(J)V
     147: goto          335
     150: aload_3
     151: instanceof    #114                // class javassist/bytecode/annotation/FloatMemberValue
     154: ifeq          174
     157: aload_3
     158: checkcast     #114                // class javassist/bytecode/annotation/FloatMemberValue
     161: aload_2
     162: checkcast     #115                // class java/lang/Float
     165: invokevirtual #116                // Method java/lang/Float.floatValue:()F
     168: invokevirtual #117                // Method javassist/bytecode/annotation/FloatMemberValue.setValue:(F)V
     171: goto          335
     174: aload_3
     175: instanceof    #118                // class javassist/bytecode/annotation/DoubleMemberValue
     178: ifeq          198
     181: aload_3
     182: checkcast     #118                // class javassist/bytecode/annotation/DoubleMemberValue
     185: aload_2
     186: checkcast     #119                // class java/lang/Double
     189: invokevirtual #120                // Method java/lang/Double.doubleValue:()D
     192: invokevirtual #121                // Method javassist/bytecode/annotation/DoubleMemberValue.setValue:(D)V
     195: goto          335
     198: aload_3
     199: instanceof    #122                // class javassist/bytecode/annotation/ClassMemberValue
     202: ifeq          222
     205: aload_3
     206: checkcast     #122                // class javassist/bytecode/annotation/ClassMemberValue
     209: aload_2
     210: checkcast     #24                 // class java/lang/Class
     213: invokevirtual #62                 // Method java/lang/Class.getName:()Ljava/lang/String;
     216: invokevirtual #123                // Method javassist/bytecode/annotation/ClassMemberValue.setValue:(Ljava/lang/String;)V
     219: goto          335
     222: aload_3
     223: instanceof    #124                // class javassist/bytecode/annotation/StringMemberValue
     226: ifeq          243
     229: aload_3
     230: checkcast     #124                // class javassist/bytecode/annotation/StringMemberValue
     233: aload_2
     234: checkcast     #125                // class java/lang/String
     237: invokevirtual #126                // Method javassist/bytecode/annotation/StringMemberValue.setValue:(Ljava/lang/String;)V
     240: goto          335
     243: aload_3
     244: instanceof    #127                // class javassist/bytecode/annotation/EnumMemberValue
     247: ifeq          267
     250: aload_3
     251: checkcast     #127                // class javassist/bytecode/annotation/EnumMemberValue
     254: aload_2
     255: checkcast     #128                // class java/lang/Enum
     258: invokevirtual #129                // Method java/lang/Enum.name:()Ljava/lang/String;
     261: invokevirtual #130                // Method javassist/bytecode/annotation/EnumMemberValue.setValue:(Ljava/lang/String;)V
     264: goto          335
     267: aload_3
     268: instanceof    #131                // class javassist/bytecode/annotation/ArrayMemberValue
     271: ifeq          335
     274: aload_1
     275: invokevirtual #132                // Method javassist/CtClass.getComponentType:()Ljavassist/CtClass;
     278: astore        4
     280: aload_2
     281: invokestatic  #133                // Method java/lang/reflect/Array.getLength:(Ljava/lang/Object;)I
     284: istore        5
     286: iload         5
     288: anewarray     #134                // class javassist/bytecode/annotation/MemberValue
     291: astore        6
     293: iconst_0
     294: istore        7
     296: iload         7
     298: iload         5
     300: if_icmpge     326
     303: aload         6
     305: iload         7
     307: aload_0
     308: aload         4
     310: aload_2
     311: iload         7
     313: invokestatic  #135                // Method java/lang/reflect/Array.get:(Ljava/lang/Object;I)Ljava/lang/Object;
     316: invokestatic  #71                 // Method createMemberValue:(Ljavassist/bytecode/ConstPool;Ljavassist/CtClass;Ljava/lang/Object;)Ljavassist/bytecode/annotation/MemberValue;
     319: aastore
     320: iinc          7, 1
     323: goto          296
     326: aload_3
     327: checkcast     #131                // class javassist/bytecode/annotation/ArrayMemberValue
     330: aload         6
     332: invokevirtual #136                // Method javassist/bytecode/annotation/ArrayMemberValue.setValue:([Ljavassist/bytecode/annotation/MemberValue;)V
     335: aload_3
     336: areturn

  public void validate(java.lang.String, java.lang.Class<?>[], java.lang.Object[]) throws java.lang.Exception;
    Code:
       0: new           #137                // class java/util/ArrayList
       3: dup
       4: invokespecial #138                // Method java/util/ArrayList."<init>":()V
       7: astore        4
       9: aload_0
      10: aload_1
      11: invokespecial #139                // Method methodClass:(Ljava/lang/String;)Ljava/lang/Class;
      14: astore        5
      16: aload         5
      18: ifnull        31
      21: aload         4
      23: aload         5
      25: invokeinterface #140,  2          // InterfaceMethod java/util/List.add:(Ljava/lang/Object;)Z
      30: pop
      31: new           #141                // class java/util/HashSet
      34: dup
      35: invokespecial #142                // Method java/util/HashSet."<init>":()V
      38: astore        6
      40: aload_0
      41: getfield      #5                  // Field clazz:Ljava/lang/Class;
      44: aload_1
      45: aload_2
      46: invokevirtual #143                // Method java/lang/Class.getMethod:(Ljava/lang/String;[Ljava/lang/Class;)Ljava/lang/reflect/Method;
      49: astore        7
      51: aload         7
      53: ldc           #144                // class org/apache/dubbo/validation/MethodValidated
      55: invokevirtual #145                // Method java/lang/reflect/Method.isAnnotationPresent:(Ljava/lang/Class;)Z
      58: ifeq          91
      61: aload         7
      63: ldc           #144                // class org/apache/dubbo/validation/MethodValidated
      65: invokevirtual #146                // Method java/lang/reflect/Method.getAnnotation:(Ljava/lang/Class;)Ljava/lang/annotation/Annotation;
      68: checkcast     #144                // class org/apache/dubbo/validation/MethodValidated
      71: invokeinterface #147,  1          // InterfaceMethod org/apache/dubbo/validation/MethodValidated.value:()[Ljava/lang/Class;
      76: astore        8
      78: aload         4
      80: aload         8
      82: invokestatic  #148                // Method java/util/Arrays.asList:([Ljava/lang/Object;)Ljava/util/List;
      85: invokeinterface #149,  2          // InterfaceMethod java/util/List.addAll:(Ljava/util/Collection;)Z
      90: pop
      91: aload         4
      93: iconst_0
      94: ldc           #150                // class jakarta/validation/groups/Default
      96: invokeinterface #151,  3          // InterfaceMethod java/util/List.add:(ILjava/lang/Object;)V
     101: aload         4
     103: iconst_1
     104: aload_0
     105: getfield      #5                  // Field clazz:Ljava/lang/Class;
     108: invokeinterface #151,  3          // InterfaceMethod java/util/List.add:(ILjava/lang/Object;)V
     113: aload         4
     115: aload         4
     117: invokeinterface #152,  1          // InterfaceMethod java/util/List.size:()I
     122: anewarray     #24                 // class java/lang/Class
     125: invokeinterface #153,  2          // InterfaceMethod java/util/List.toArray:([Ljava/lang/Object;)[Ljava/lang/Object;
     130: checkcast     #154                // class "[Ljava/lang/Class;"
     133: astore        9
     135: aload_0
     136: getfield      #5                  // Field clazz:Ljava/lang/Class;
     139: aload         7
     141: aload_3
     142: invokestatic  #155                // Method getMethodParameterBean:(Ljava/lang/Class;Ljava/lang/reflect/Method;[Ljava/lang/Object;)Ljava/lang/Object;
     145: astore        10
     147: aload         10
     149: ifnull        173
     152: aload         6
     154: aload_0
     155: getfield      #14                 // Field validator:Ljakarta/validation/Validator;
     158: aload         10
     160: aload         9
     162: invokeinterface #156,  3          // InterfaceMethod jakarta/validation/Validator.validate:(Ljava/lang/Object;[Ljava/lang/Class;)Ljava/util/Set;
     167: invokeinterface #157,  2          // InterfaceMethod java/util/Set.addAll:(Ljava/util/Collection;)Z
     172: pop
     173: aload_3
     174: astore        11
     176: aload         11
     178: arraylength
     179: istore        12
     181: iconst_0
     182: istore        13
     184: iload         13
     186: iload         12
     188: if_icmpge     214
     191: aload         11
     193: iload         13
     195: aaload
     196: astore        14
     198: aload_0
     199: aload         6
     201: aload         14
     203: aload         9
     205: invokespecial #158                // Method validate:(Ljava/util/Set;Ljava/lang/Object;[Ljava/lang/Class;)V
     208: iinc          13, 1
     211: goto          184
     214: aload         6
     216: invokeinterface #159,  1          // InterfaceMethod java/util/Set.isEmpty:()Z
     221: ifne          330
     224: getstatic     #38                 // Field logger:Lorg/apache/dubbo/common/logger/ErrorTypeAwareLogger;
     227: new           #28                 // class java/lang/StringBuilder
     230: dup
     231: invokespecial #29                 // Method java/lang/StringBuilder."<init>":()V
     234: ldc           #160                // String Failed to validate service:
     236: invokevirtual #31                 // Method java/lang/StringBuilder.append:(Ljava/lang/String;)Ljava/lang/StringBuilder;
     239: aload_0
     240: getfield      #5                  // Field clazz:Ljava/lang/Class;
     243: invokevirtual #62                 // Method java/lang/Class.getName:()Ljava/lang/String;
     246: invokevirtual #31                 // Method java/lang/StringBuilder.append:(Ljava/lang/String;)Ljava/lang/StringBuilder;
     249: ldc           #161                // String , method:
     251: invokevirtual #31                 // Method java/lang/StringBuilder.append:(Ljava/lang/String;)Ljava/lang/StringBuilder;
     254: aload_1
     255: invokevirtual #31                 // Method java/lang/StringBuilder.append:(Ljava/lang/String;)Ljava/lang/StringBuilder;
     258: ldc           #162                // String , cause:
     260: invokevirtual #31                 // Method java/lang/StringBuilder.append:(Ljava/lang/String;)Ljava/lang/StringBuilder;
     263: aload         6
     265: invokevirtual #163                // Method java/lang/StringBuilder.append:(Ljava/lang/Object;)Ljava/lang/StringBuilder;
     268: invokevirtual #34                 // Method java/lang/StringBuilder.toString:()Ljava/lang/String;
     271: invokeinterface #164,  2          // InterfaceMethod org/apache/dubbo/common/logger/ErrorTypeAwareLogger.info:(Ljava/lang/String;)V
     276: new           #165                // class jakarta/validation/ConstraintViolationException
     279: dup
     280: new           #28                 // class java/lang/StringBuilder
     283: dup
     284: invokespecial #29                 // Method java/lang/StringBuilder."<init>":()V
     287: ldc           #160                // String Failed to validate service:
     289: invokevirtual #31                 // Method java/lang/StringBuilder.append:(Ljava/lang/String;)Ljava/lang/StringBuilder;
     292: aload_0
     293: getfield      #5                  // Field clazz:Ljava/lang/Class;
     296: invokevirtual #62                 // Method java/lang/Class.getName:()Ljava/lang/String;
     299: invokevirtual #31                 // Method java/lang/StringBuilder.append:(Ljava/lang/String;)Ljava/lang/StringBuilder;
     302: ldc           #161                // String , method:
     304: invokevirtual #31                 // Method java/lang/StringBuilder.append:(Ljava/lang/String;)Ljava/lang/StringBuilder;
     307: aload_1
     308: invokevirtual #31                 // Method java/lang/StringBuilder.append:(Ljava/lang/String;)Ljava/lang/StringBuilder;
     311: ldc           #162                // String , cause:
     313: invokevirtual #31                 // Method java/lang/StringBuilder.append:(Ljava/lang/String;)Ljava/lang/StringBuilder;
     316: aload         6
     318: invokevirtual #163                // Method java/lang/StringBuilder.append:(Ljava/lang/Object;)Ljava/lang/StringBuilder;
     321: invokevirtual #34                 // Method java/lang/StringBuilder.toString:()Ljava/lang/String;
     324: aload         6
     326: invokespecial #166                // Method jakarta/validation/ConstraintViolationException."<init>":(Ljava/lang/String;Ljava/util/Set;)V
     329: athrow
     330: return

  private java.lang.Class<?> methodClass(java.lang.String);
    Code:
       0: aconst_null
       1: astore_2
       2: new           #28                 // class java/lang/StringBuilder
       5: dup
       6: invokespecial #29                 // Method java/lang/StringBuilder."<init>":()V
       9: aload_0
      10: getfield      #5                  // Field clazz:Ljava/lang/Class;
      13: invokevirtual #62                 // Method java/lang/Class.getName:()Ljava/lang/String;
      16: invokevirtual #31                 // Method java/lang/StringBuilder.append:(Ljava/lang/String;)Ljava/lang/StringBuilder;
      19: ldc           #167                // String $
      21: invokevirtual #31                 // Method java/lang/StringBuilder.append:(Ljava/lang/String;)Ljava/lang/StringBuilder;
      24: aload_1
      25: invokestatic  #84                 // Method toUpperMethoName:(Ljava/lang/String;)Ljava/lang/String;
      28: invokevirtual #31                 // Method java/lang/StringBuilder.append:(Ljava/lang/String;)Ljava/lang/StringBuilder;
      31: invokevirtual #34                 // Method java/lang/StringBuilder.toString:()Ljava/lang/String;
      34: astore_3
      35: aload_0
      36: getfield      #17                 // Field methodClassMap:Ljava/util/Map;
      39: aload_3
      40: invokeinterface #168,  2          // InterfaceMethod java/util/Map.get:(Ljava/lang/Object;)Ljava/lang/Object;
      45: checkcast     #24                 // class java/lang/Class
      48: astore        4
      50: aload         4
      52: ifnull        71
      55: aload         4
      57: aload_0
      58: getfield      #5                  // Field clazz:Ljava/lang/Class;
      61: if_acmpne     68
      64: aconst_null
      65: goto          70
      68: aload         4
      70: areturn
      71: aload_3
      72: iconst_0
      73: invokestatic  #169                // Method java/lang/Thread.currentThread:()Ljava/lang/Thread;
      76: invokevirtual #170                // Method java/lang/Thread.getContextClassLoader:()Ljava/lang/ClassLoader;
      79: invokestatic  #21                 // Method java/lang/Class.forName:(Ljava/lang/String;ZLjava/lang/ClassLoader;)Ljava/lang/Class;
      82: astore_2
      83: aload_0
      84: getfield      #17                 // Field methodClassMap:Ljava/util/Map;
      87: aload_3
      88: aload_2
      89: invokeinterface #171,  3          // InterfaceMethod java/util/Map.put:(Ljava/lang/Object;Ljava/lang/Object;)Ljava/lang/Object;
      94: pop
      95: goto          115
      98: astore        5
     100: aload_0
     101: getfield      #17                 // Field methodClassMap:Ljava/util/Map;
     104: aload_3
     105: aload_0
     106: getfield      #5                  // Field clazz:Ljava/lang/Class;
     109: invokeinterface #171,  3          // InterfaceMethod java/util/Map.put:(Ljava/lang/Object;Ljava/lang/Object;)Ljava/lang/Object;
     114: pop
     115: aload_2
     116: areturn
    Exception table:
       from    to  target type
          71    95    98   Class java/lang/ClassNotFoundException

  private void validate(java.util.Set<jakarta.validation.ConstraintViolation<?>>, java.lang.Object, java.lang.Class<?>...);
    Code:
       0: aload_2
       1: ifnull        215
       4: aload_2
       5: invokevirtual #172                // Method java/lang/Object.getClass:()Ljava/lang/Class;
       8: invokestatic  #173                // Method org/apache/dubbo/common/utils/ReflectUtils.isPrimitives:(Ljava/lang/Class;)Z
      11: ifne          215
      14: aload_2
      15: instanceof    #174                // class "[Ljava/lang/Object;"
      18: ifeq          69
      21: aload_2
      22: checkcast     #174                // class "[Ljava/lang/Object;"
      25: checkcast     #174                // class "[Ljava/lang/Object;"
      28: astore        4
      30: aload         4
      32: arraylength
      33: istore        5
      35: iconst_0
      36: istore        6
      38: iload         6
      40: iload         5
      42: if_icmpge     66
      45: aload         4
      47: iload         6
      49: aaload
      50: astore        7
      52: aload_0
      53: aload_1
      54: aload         7
      56: aload_3
      57: invokespecial #158                // Method validate:(Ljava/util/Set;Ljava/lang/Object;[Ljava/lang/Class;)V
      60: iinc          6, 1
      63: goto          38
      66: goto          215
      69: aload_2
      70: instanceof    #175                // class java/util/Collection
      73: ifeq          120
      76: aload_2
      77: checkcast     #175                // class java/util/Collection
      80: invokeinterface #176,  1          // InterfaceMethod java/util/Collection.iterator:()Ljava/util/Iterator;
      85: astore        4
      87: aload         4
      89: invokeinterface #177,  1          // InterfaceMethod java/util/Iterator.hasNext:()Z
      94: ifeq          117
      97: aload         4
      99: invokeinterface #178,  1          // InterfaceMethod java/util/Iterator.next:()Ljava/lang/Object;
     104: astore        5
     106: aload_0
     107: aload_1
     108: aload         5
     110: aload_3
     111: invokespecial #158                // Method validate:(Ljava/util/Set;Ljava/lang/Object;[Ljava/lang/Class;)V
     114: goto          87
     117: goto          215
     120: aload_2
     121: instanceof    #179                // class java/util/Map
     124: ifeq          197
     127: aload_2
     128: checkcast     #179                // class java/util/Map
     131: invokeinterface #180,  1          // InterfaceMethod java/util/Map.entrySet:()Ljava/util/Set;
     136: invokeinterface #181,  1          // InterfaceMethod java/util/Set.iterator:()Ljava/util/Iterator;
     141: astore        4
     143: aload         4
     145: invokeinterface #177,  1          // InterfaceMethod java/util/Iterator.hasNext:()Z
     150: ifeq          194
     153: aload         4
     155: invokeinterface #178,  1          // InterfaceMethod java/util/Iterator.next:()Ljava/lang/Object;
     160: checkcast     #182                // class java/util/Map$Entry
     163: astore        5
     165: aload_0
     166: aload_1
     167: aload         5
     169: invokeinterface #183,  1          // InterfaceMethod java/util/Map$Entry.getKey:()Ljava/lang/Object;
     174: aload_3
     175: invokespecial #158                // Method validate:(Ljava/util/Set;Ljava/lang/Object;[Ljava/lang/Class;)V
     178: aload_0
     179: aload_1
     180: aload         5
     182: invokeinterface #184,  1          // InterfaceMethod java/util/Map$Entry.getValue:()Ljava/lang/Object;
     187: aload_3
     188: invokespecial #158                // Method validate:(Ljava/util/Set;Ljava/lang/Object;[Ljava/lang/Class;)V
     191: goto          143
     194: goto          215
     197: aload_1
     198: aload_0
     199: getfield      #14                 // Field validator:Ljakarta/validation/Validator;
     202: aload_2
     203: aload_3
     204: invokeinterface #156,  3          // InterfaceMethod jakarta/validation/Validator.validate:(Ljava/lang/Object;[Ljava/lang/Class;)Ljava/util/Set;
     209: invokeinterface #157,  2          // InterfaceMethod java/util/Set.addAll:(Ljava/util/Collection;)Z
     214: pop
     215: return

  static {};
    Code:
       0: ldc           #185                // class org/apache/dubbo/validation/support/jvalidation/JValidatorNew
       2: invokestatic  #186                // Method org/apache/dubbo/common/logger/LoggerFactory.getErrorTypeAwareLogger:(Ljava/lang/Class;)Lorg/apache/dubbo/common/logger/ErrorTypeAwareLogger;
       5: putstatic     #38                 // Field logger:Lorg/apache/dubbo/common/logger/ErrorTypeAwareLogger;
       8: return
}
