Compiled from "JValidationNew.java"
public class org.apache.dubbo.validation.support.jvalidation.JValidationNew extends org.apache.dubbo.validation.support.AbstractValidation {
  public org.apache.dubbo.validation.support.jvalidation.JValidationNew();
    Code:
       0: aload_0
       1: invokespecial #1                  // Method org/apache/dubbo/validation/support/AbstractValidation."<init>":()V
       4: return

  protected org.apache.dubbo.validation.Validator createValidator(org.apache.dubbo.common.URL);
    Code:
       0: new           #2                  // class org/apache/dubbo/validation/support/jvalidation/JValidatorNew
       3: dup
       4: aload_1
       5: invokespecial #3                  // Method org/apache/dubbo/validation/support/jvalidation/JValidatorNew."<init>":(Lorg/apache/dubbo/common/URL;)V
       8: areturn
}
