Compiled from "AbstractHttpClientFactory.java"
public abstract class org.apache.dubbo.remoting.http.factory.AbstractHttpClientFactory implements org.apache.dubbo.remoting.http.factory.RestClientFactory {
  protected final org.apache.dubbo.common.logger.ErrorTypeAwareLogger logger;

  protected org.apache.dubbo.remoting.http.config.HttpClientConfig httpClientConfig;

  public org.apache.dubbo.remoting.http.factory.AbstractHttpClientFactory();
    Code:
       0: aload_0
       1: invokespecial #1                  // Method java/lang/Object."<init>":()V
       4: aload_0
       5: aload_0
       6: invokevirtual #2                  // Method java/lang/Object.getClass:()Ljava/lang/Class;
       9: invokestatic  #3                  // Method org/apache/dubbo/common/logger/LoggerFactory.getErrorTypeAwareLogger:(Ljava/lang/Class;)Lorg/apache/dubbo/common/logger/ErrorTypeAwareLogger;
      12: putfield      #4                  // Field logger:Lorg/apache/dubbo/common/logger/ErrorTypeAwareLogger;
      15: aload_0
      16: new           #5                  // class org/apache/dubbo/remoting/http/config/HttpClientConfig
      19: dup
      20: invokespecial #6                  // Method org/apache/dubbo/remoting/http/config/HttpClientConfig."<init>":()V
      23: putfield      #7                  // Field httpClientConfig:Lorg/apache/dubbo/remoting/http/config/HttpClientConfig;
      26: return

  public org.apache.dubbo.remoting.http.RestClient createRestClient(org.apache.dubbo.common.URL) throws org.apache.dubbo.rpc.RpcException;
    Code:
       0: aload_0
       1: aload_1
       2: invokevirtual #8                  // Method beforeCreated:(Lorg/apache/dubbo/common/URL;)V
       5: aload_0
       6: aload_1
       7: invokevirtual #9                  // Method doCreateRestClient:(Lorg/apache/dubbo/common/URL;)Lorg/apache/dubbo/remoting/http/RestClient;
      10: astore_2
      11: aload_0
      12: aload_2
      13: invokevirtual #10                 // Method afterCreated:(Lorg/apache/dubbo/remoting/http/RestClient;)V
      16: aload_2
      17: areturn

  protected void beforeCreated(org.apache.dubbo.common.URL);
    Code:
       0: return

  protected abstract org.apache.dubbo.remoting.http.RestClient doCreateRestClient(org.apache.dubbo.common.URL) throws org.apache.dubbo.rpc.RpcException;

  protected void afterCreated(org.apache.dubbo.remoting.http.RestClient);
    Code:
       0: return
}
