Compiled from "NopDynamicConfiguration.java"
public class org.apache.dubbo.common.config.configcenter.nop.NopDynamicConfiguration implements org.apache.dubbo.common.config.configcenter.DynamicConfiguration {
  public org.apache.dubbo.common.config.configcenter.nop.NopDynamicConfiguration(org.apache.dubbo.common.URL);
    Code:
       0: aload_0
       1: invokespecial #1                  // Method java/lang/Object."<init>":()V
       4: return

  public java.lang.Object getInternalProperty(java.lang.String);
    Code:
       0: aconst_null
       1: areturn

  public void addListener(java.lang.String, java.lang.String, org.apache.dubbo.common.config.configcenter.ConfigurationListener);
    Code:
       0: return

  public void removeListener(java.lang.String, java.lang.String, org.apache.dubbo.common.config.configcenter.ConfigurationListener);
    Code:
       0: return

  public java.lang.String getConfig(java.lang.String, java.lang.String, long) throws java.lang.IllegalStateException;
    Code:
       0: aconst_null
       1: areturn

  public boolean publishConfig(java.lang.String, java.lang.String, java.lang.String);
    Code:
       0: iconst_1
       1: ireturn

  public void close() throws java.lang.Exception;
    Code:
       0: return
}
