Compiled from "UrlParamConditionMatcher.java"
public class org.apache.dubbo.rpc.cluster.router.condition.matcher.param.UrlParamConditionMatcher extends org.apache.dubbo.rpc.cluster.router.condition.matcher.AbstractConditionMatcher {
  public org.apache.dubbo.rpc.cluster.router.condition.matcher.param.UrlParamConditionMatcher(java.lang.String, org.apache.dubbo.rpc.model.ModuleModel);
    Code:
       0: aload_0
       1: aload_1
       2: aload_2
       3: invokespecial #1                  // Method org/apache/dubbo/rpc/cluster/router/condition/matcher/AbstractConditionMatcher."<init>":(Ljava/lang/String;Lorg/apache/dubbo/rpc/model/ModuleModel;)V
       6: return

  protected java.lang.String getValue(java.util.Map<java.lang.String, java.lang.String>, org.apache.dubbo.common.URL, org.apache.dubbo.rpc.Invocation);
    Code:
       0: aload_0
       1: getfield      #2                  // Field key:Ljava/lang/String;
       4: aload_1
       5: aload_2
       6: aload_3
       7: invokestatic  #3                  // Method getSampleValueFromUrl:(Ljava/lang/String;Ljava/util/Map;Lorg/apache/dubbo/common/URL;Lorg/apache/dubbo/rpc/Invocation;)Ljava/lang/String;
      10: areturn
}
