Compiled from "UrlParamConditionMatcherFactory.java"
public class org.apache.dubbo.rpc.cluster.router.condition.matcher.param.UrlParamConditionMatcherFactory implements org.apache.dubbo.rpc.cluster.router.condition.matcher.ConditionMatcherFactory {
  public org.apache.dubbo.rpc.cluster.router.condition.matcher.param.UrlParamConditionMatcherFactory();
    Code:
       0: aload_0
       1: invokespecial #1                  // Method java/lang/Object."<init>":()V
       4: return

  public boolean shouldMatch(java.lang.String);
    Code:
       0: iconst_1
       1: ireturn

  public org.apache.dubbo.rpc.cluster.router.condition.matcher.ConditionMatcher createMatcher(java.lang.String, org.apache.dubbo.rpc.model.ModuleModel);
    Code:
       0: new           #2                  // class org/apache/dubbo/rpc/cluster/router/condition/matcher/param/UrlParamConditionMatcher
       3: dup
       4: aload_1
       5: aload_2
       6: invokespecial #3                  // Method org/apache/dubbo/rpc/cluster/router/condition/matcher/param/UrlParamConditionMatcher."<init>":(Ljava/lang/String;Lorg/apache/dubbo/rpc/model/ModuleModel;)V
       9: areturn
}
