Compiled from "JksSslStoreBundle.java"
public class org.springframework.boot.ssl.jks.JksSslStoreBundle implements org.springframework.boot.ssl.SslStoreBundle {
  private final org.springframework.boot.ssl.jks.JksSslStoreDetails keyStoreDetails;

  private final org.springframework.boot.ssl.jks.JksSslStoreDetails trustStoreDetails;

  public org.springframework.boot.ssl.jks.JksSslStoreBundle(org.springframework.boot.ssl.jks.JksSslStoreDetails, org.springframework.boot.ssl.jks.JksSslStoreDetails);
    Code:
       0: aload_0
       1: invokespecial #1                  // Method java/lang/Object."<init>":()V
       4: aload_0
       5: aload_1
       6: putfield      #7                  // Field keyStoreDetails:Lorg/springframework/boot/ssl/jks/JksSslStoreDetails;
       9: aload_0
      10: aload_2
      11: putfield      #13                 // Field trustStoreDetails:Lorg/springframework/boot/ssl/jks/JksSslStoreDetails;
      14: return

  public java.security.KeyStore getKeyStore();
    Code:
       0: aload_0
       1: ldc           #16                 // String key
       3: aload_0
       4: getfield      #7                  // Field keyStoreDetails:Lorg/springframework/boot/ssl/jks/JksSslStoreDetails;
       7: invokevirtual #18                 // Method createKeyStore:(Ljava/lang/String;Lorg/springframework/boot/ssl/jks/JksSslStoreDetails;)Ljava/security/KeyStore;
      10: areturn

  public java.lang.String getKeyStorePassword();
    Code:
       0: aload_0
       1: getfield      #7                  // Field keyStoreDetails:Lorg/springframework/boot/ssl/jks/JksSslStoreDetails;
       4: ifnull        17
       7: aload_0
       8: getfield      #7                  // Field keyStoreDetails:Lorg/springframework/boot/ssl/jks/JksSslStoreDetails;
      11: invokevirtual #22                 // Method org/springframework/boot/ssl/jks/JksSslStoreDetails.password:()Ljava/lang/String;
      14: goto          18
      17: aconst_null
      18: areturn

  public java.security.KeyStore getTrustStore();
    Code:
       0: aload_0
       1: ldc           #28                 // String trust
       3: aload_0
       4: getfield      #13                 // Field trustStoreDetails:Lorg/springframework/boot/ssl/jks/JksSslStoreDetails;
       7: invokevirtual #18                 // Method createKeyStore:(Ljava/lang/String;Lorg/springframework/boot/ssl/jks/JksSslStoreDetails;)Ljava/security/KeyStore;
      10: areturn

  private java.security.KeyStore createKeyStore(java.lang.String, org.springframework.boot.ssl.jks.JksSslStoreDetails);
    Code:
       0: aload_2
       1: ifnull        11
       4: aload_2
       5: invokevirtual #30                 // Method org/springframework/boot/ssl/jks/JksSslStoreDetails.isEmpty:()Z
       8: ifeq          13
      11: aconst_null
      12: areturn
      13: aload_2
      14: invokevirtual #34                 // Method org/springframework/boot/ssl/jks/JksSslStoreDetails.type:()Ljava/lang/String;
      17: invokestatic  #37                 // Method org/springframework/util/StringUtils.hasText:(Ljava/lang/String;)Z
      20: ifne          29
      23: invokestatic  #43                 // Method java/security/KeyStore.getDefaultType:()Ljava/lang/String;
      26: goto          33
      29: aload_2
      30: invokevirtual #34                 // Method org/springframework/boot/ssl/jks/JksSslStoreDetails.type:()Ljava/lang/String;
      33: astore_3
      34: aload_2
      35: invokevirtual #22                 // Method org/springframework/boot/ssl/jks/JksSslStoreDetails.password:()Ljava/lang/String;
      38: ifnull        51
      41: aload_2
      42: invokevirtual #22                 // Method org/springframework/boot/ssl/jks/JksSslStoreDetails.password:()Ljava/lang/String;
      45: invokevirtual #48                 // Method java/lang/String.toCharArray:()[C
      48: goto          52
      51: aconst_null
      52: astore        4
      54: aload_2
      55: invokevirtual #54                 // Method org/springframework/boot/ssl/jks/JksSslStoreDetails.location:()Ljava/lang/String;
      58: astore        5
      60: aload_0
      61: aload_3
      62: aload_2
      63: invokevirtual #57                 // Method org/springframework/boot/ssl/jks/JksSslStoreDetails.provider:()Ljava/lang/String;
      66: invokevirtual #60                 // Method getKeyStoreInstance:(Ljava/lang/String;Ljava/lang/String;)Ljava/security/KeyStore;
      69: astore        6
      71: aload_0
      72: aload_3
      73: invokevirtual #64                 // Method isHardwareKeystoreType:(Ljava/lang/String;)Z
      76: ifeq          92
      79: aload_0
      80: aload         6
      82: aload         5
      84: aload         4
      86: invokevirtual #67                 // Method loadHardwareKeyStore:(Ljava/security/KeyStore;Ljava/lang/String;[C)V
      89: goto          102
      92: aload_0
      93: aload         6
      95: aload         5
      97: aload         4
      99: invokevirtual #71                 // Method loadKeyStore:(Ljava/security/KeyStore;Ljava/lang/String;[C)V
     102: aload         6
     104: areturn
     105: astore_3
     106: new           #76                 // class java/lang/IllegalStateException
     109: dup
     110: ldc           #78                 // String Unable to create %s store: %s
     112: iconst_2
     113: anewarray     #2                  // class java/lang/Object
     116: dup
     117: iconst_0
     118: aload_1
     119: aastore
     120: dup
     121: iconst_1
     122: aload_3
     123: invokevirtual #80                 // Method java/lang/Exception.getMessage:()Ljava/lang/String;
     126: aastore
     127: invokevirtual #83                 // Method java/lang/String.formatted:([Ljava/lang/Object;)Ljava/lang/String;
     130: aload_3
     131: invokespecial #87                 // Method java/lang/IllegalStateException."<init>":(Ljava/lang/String;Ljava/lang/Throwable;)V
     134: athrow
    Exception table:
       from    to  target type
          13   104   105   Class java/lang/Exception

  private java.security.KeyStore getKeyStoreInstance(java.lang.String, java.lang.String) throws java.security.KeyStoreException, java.security.NoSuchProviderException;
    Code:
       0: aload_2
       1: invokestatic  #37                 // Method org/springframework/util/StringUtils.hasText:(Ljava/lang/String;)Z
       4: ifne          14
       7: aload_1
       8: invokestatic  #90                 // Method java/security/KeyStore.getInstance:(Ljava/lang/String;)Ljava/security/KeyStore;
      11: goto          19
      14: aload_1
      15: aload_2
      16: invokestatic  #94                 // Method java/security/KeyStore.getInstance:(Ljava/lang/String;Ljava/lang/String;)Ljava/security/KeyStore;
      19: areturn

  private boolean isHardwareKeystoreType(java.lang.String);
    Code:
       0: aload_1
       1: ldc           #96                 // String PKCS11
       3: invokevirtual #98                 // Method java/lang/String.equalsIgnoreCase:(Ljava/lang/String;)Z
       6: ireturn

  private void loadHardwareKeyStore(java.security.KeyStore, java.lang.String, char[]) throws java.io.IOException, java.security.NoSuchAlgorithmException, java.security.cert.CertificateException;
    Code:
       0: aload_2
       1: invokestatic  #37                 // Method org/springframework/util/StringUtils.hasText:(Ljava/lang/String;)Z
       4: ifne          11
       7: iconst_1
       8: goto          12
      11: iconst_0
      12: aload_2
      13: invokedynamic #101,  0            // InvokeDynamic #0:get:(Ljava/lang/String;)Ljava/util/function/Supplier;
      18: invokestatic  #105                // Method org/springframework/util/Assert.state:(ZLjava/util/function/Supplier;)V
      21: aload_1
      22: aconst_null
      23: aload_3
      24: invokevirtual #111                // Method java/security/KeyStore.load:(Ljava/io/InputStream;[C)V
      27: return

  private void loadKeyStore(java.security.KeyStore, java.lang.String, char[]);
    Code:
       0: aload_2
       1: invokestatic  #37                 // Method org/springframework/util/StringUtils.hasText:(Ljava/lang/String;)Z
       4: invokedynamic #115,  0            // InvokeDynamic #1:get:()Ljava/util/function/Supplier;
       9: invokestatic  #105                // Method org/springframework/util/Assert.state:(ZLjava/util/function/Supplier;)V
      12: aload_2
      13: invokestatic  #118                // Method org/springframework/util/ResourceUtils.getURL:(Ljava/lang/String;)Ljava/net/URL;
      16: astore        4
      18: aload         4
      20: invokevirtual #124                // Method java/net/URL.openStream:()Ljava/io/InputStream;
      23: astore        5
      25: aload_1
      26: aload         5
      28: aload_3
      29: invokevirtual #111                // Method java/security/KeyStore.load:(Ljava/io/InputStream;[C)V
      32: aload         5
      34: ifnull        72
      37: aload         5
      39: invokevirtual #130                // Method java/io/InputStream.close:()V
      42: goto          72
      45: astore        6
      47: aload         5
      49: ifnull        69
      52: aload         5
      54: invokevirtual #130                // Method java/io/InputStream.close:()V
      57: goto          69
      60: astore        7
      62: aload         6
      64: aload         7
      66: invokevirtual #137                // Method java/lang/Throwable.addSuppressed:(Ljava/lang/Throwable;)V
      69: aload         6
      71: athrow
      72: goto          93
      75: astore        4
      77: new           #76                 // class java/lang/IllegalStateException
      80: dup
      81: aload_2
      82: invokedynamic #141,  0            // InvokeDynamic #2:makeConcatWithConstants:(Ljava/lang/String;)Ljava/lang/String;
      87: aload         4
      89: invokespecial #87                 // Method java/lang/IllegalStateException."<init>":(Ljava/lang/String;Ljava/lang/Throwable;)V
      92: athrow
      93: return
    Exception table:
       from    to  target type
          25    32    45   Class java/lang/Throwable
          52    57    60   Class java/lang/Throwable
          12    72    75   Class java/lang/Exception

  private static java.lang.String lambda$loadKeyStore$1();
    Code:
       0: ldc           #145                // String Location must not be empty or null
       2: areturn

  private static java.lang.String lambda$loadHardwareKeyStore$0(java.lang.String);
    Code:
       0: ldc           #147                // String Location is \'%s\', but must be empty or null for PKCS11 hardware key stores
       2: iconst_1
       3: anewarray     #2                  // class java/lang/Object
       6: dup
       7: iconst_0
       8: aload_0
       9: aastore
      10: invokevirtual #83                 // Method java/lang/String.formatted:([Ljava/lang/Object;)Ljava/lang/String;
      13: areturn
}
