Compiled from "JksSslStoreDetails.java"
public final class org.springframework.boot.ssl.jks.JksSslStoreDetails extends java.lang.Record {
  private final java.lang.String type;

  private final java.lang.String provider;

  private final java.lang.String location;

  private final java.lang.String password;

  public org.springframework.boot.ssl.jks.JksSslStoreDetails(java.lang.String, java.lang.String, java.lang.String, java.lang.String);
    Code:
       0: aload_0
       1: invokespecial #1                  // Method java/lang/Record."<init>":()V
       4: aload_0
       5: aload_1
       6: putfield      #7                  // Field type:Ljava/lang/String;
       9: aload_0
      10: aload_2
      11: putfield      #13                 // Field provider:Ljava/lang/String;
      14: aload_0
      15: aload_3
      16: putfield      #16                 // Field location:Ljava/lang/String;
      19: aload_0
      20: aload         4
      22: putfield      #19                 // Field password:Ljava/lang/String;
      25: return

  public org.springframework.boot.ssl.jks.JksSslStoreDetails withPassword(java.lang.String);
    Code:
       0: new           #8                  // class org/springframework/boot/ssl/jks/JksSslStoreDetails
       3: dup
       4: aload_0
       5: getfield      #7                  // Field type:Ljava/lang/String;
       8: aload_0
       9: getfield      #13                 // Field provider:Ljava/lang/String;
      12: aload_0
      13: getfield      #16                 // Field location:Ljava/lang/String;
      16: aload_1
      17: invokespecial #22                 // Method "<init>":(Ljava/lang/String;Ljava/lang/String;Ljava/lang/String;Ljava/lang/String;)V
      20: areturn

  boolean isEmpty();
    Code:
       0: aload_0
       1: aload_0
       2: getfield      #7                  // Field type:Ljava/lang/String;
       5: invokevirtual #25                 // Method isEmpty:(Ljava/lang/String;)Z
       8: ifeq          37
      11: aload_0
      12: aload_0
      13: getfield      #13                 // Field provider:Ljava/lang/String;
      16: invokevirtual #25                 // Method isEmpty:(Ljava/lang/String;)Z
      19: ifeq          37
      22: aload_0
      23: aload_0
      24: getfield      #16                 // Field location:Ljava/lang/String;
      27: invokevirtual #25                 // Method isEmpty:(Ljava/lang/String;)Z
      30: ifeq          37
      33: iconst_1
      34: goto          38
      37: iconst_0
      38: ireturn

  private boolean isEmpty(java.lang.String);
    Code:
       0: aload_1
       1: invokestatic  #29                 // Method org/springframework/util/StringUtils.hasText:(Ljava/lang/String;)Z
       4: ifne          11
       7: iconst_1
       8: goto          12
      11: iconst_0
      12: ireturn

  public static org.springframework.boot.ssl.jks.JksSslStoreDetails forLocation(java.lang.String);
    Code:
       0: new           #8                  // class org/springframework/boot/ssl/jks/JksSslStoreDetails
       3: dup
       4: aconst_null
       5: aconst_null
       6: aload_0
       7: aconst_null
       8: invokespecial #22                 // Method "<init>":(Ljava/lang/String;Ljava/lang/String;Ljava/lang/String;Ljava/lang/String;)V
      11: areturn

  public final java.lang.String toString();
    Code:
       0: aload_0
       1: invokedynamic #34,  0             // InvokeDynamic #0:toString:(Lorg/springframework/boot/ssl/jks/JksSslStoreDetails;)Ljava/lang/String;
       6: areturn

  public final int hashCode();
    Code:
       0: aload_0
       1: invokedynamic #38,  0             // InvokeDynamic #0:hashCode:(Lorg/springframework/boot/ssl/jks/JksSslStoreDetails;)I
       6: ireturn

  public final boolean equals(java.lang.Object);
    Code:
       0: aload_0
       1: aload_1
       2: invokedynamic #42,  0             // InvokeDynamic #0:equals:(Lorg/springframework/boot/ssl/jks/JksSslStoreDetails;Ljava/lang/Object;)Z
       7: ireturn

  public java.lang.String type();
    Code:
       0: aload_0
       1: getfield      #7                  // Field type:Ljava/lang/String;
       4: areturn

  public java.lang.String provider();
    Code:
       0: aload_0
       1: getfield      #13                 // Field provider:Ljava/lang/String;
       4: areturn

  public java.lang.String location();
    Code:
       0: aload_0
       1: getfield      #16                 // Field location:Ljava/lang/String;
       4: areturn

  public java.lang.String password();
    Code:
       0: aload_0
       1: getfield      #19                 // Field password:Ljava/lang/String;
       4: areturn
}
