Compiled from "DataCharacter.java"
public class com.google.zxing.oned.rss.DataCharacter {
  private final int value;

  private final int checksumPortion;

  public com.google.zxing.oned.rss.DataCharacter(int, int);
    Code:
       0: aload_0
       1: invokespecial #1                  // Method java/lang/Object."<init>":()V
       4: aload_0
       5: iload_1
       6: putfield      #2                  // Field value:I
       9: aload_0
      10: iload_2
      11: putfield      #3                  // Field checksumPortion:I
      14: return

  public final int getValue();
    Code:
       0: aload_0
       1: getfield      #2                  // Field value:I
       4: ireturn

  public final int getChecksumPortion();
    Code:
       0: aload_0
       1: getfield      #3                  // Field checksumPortion:I
       4: ireturn

  public final java.lang.String toString();
    Code:
       0: new           #4                  // class java/lang/StringBuilder
       3: dup
       4: invokespecial #5                  // Method java/lang/StringBuilder."<init>":()V
       7: aload_0
       8: getfield      #2                  // Field value:I
      11: invokevirtual #6                  // Method java/lang/StringBuilder.append:(I)Ljava/lang/StringBuilder;
      14: ldc           #7                  // String (
      16: invokevirtual #8                  // Method java/lang/StringBuilder.append:(Ljava/lang/String;)Ljava/lang/StringBuilder;
      19: aload_0
      20: getfield      #3                  // Field checksumPortion:I
      23: invokevirtual #6                  // Method java/lang/StringBuilder.append:(I)Ljava/lang/StringBuilder;
      26: bipush        41
      28: invokevirtual #9                  // Method java/lang/StringBuilder.append:(C)Ljava/lang/StringBuilder;
      31: invokevirtual #10                 // Method java/lang/StringBuilder.toString:()Ljava/lang/String;
      34: areturn

  public final boolean equals(java.lang.Object);
    Code:
       0: aload_1
       1: instanceof    #11                 // class com/google/zxing/oned/rss/DataCharacter
       4: ifne          9
       7: iconst_0
       8: ireturn
       9: aload_1
      10: checkcast     #11                 // class com/google/zxing/oned/rss/DataCharacter
      13: astore_2
      14: aload_0
      15: getfield      #2                  // Field value:I
      18: aload_2
      19: getfield      #2                  // Field value:I
      22: if_icmpne     40
      25: aload_0
      26: getfield      #3                  // Field checksumPortion:I
      29: aload_2
      30: getfield      #3                  // Field checksumPortion:I
      33: if_icmpne     40
      36: iconst_1
      37: goto          41
      40: iconst_0
      41: ireturn

  public final int hashCode();
    Code:
       0: aload_0
       1: getfield      #2                  // Field value:I
       4: aload_0
       5: getfield      #3                  // Field checksumPortion:I
       8: ixor
       9: ireturn
}
