Compiled from "Pair.java"
final class com.google.zxing.oned.rss.Pair extends com.google.zxing.oned.rss.DataCharacter {
  private final com.google.zxing.oned.rss.FinderPattern finderPattern;

  private int count;

  com.google.zxing.oned.rss.Pair(int, int, com.google.zxing.oned.rss.FinderPattern);
    Code:
       0: aload_0
       1: iload_1
       2: iload_2
       3: invokespecial #1                  // Method com/google/zxing/oned/rss/DataCharacter."<init>":(II)V
       6: aload_0
       7: aload_3
       8: putfield      #2                  // Field finderPattern:Lcom/google/zxing/oned/rss/FinderPattern;
      11: return

  com.google.zxing.oned.rss.FinderPattern getFinderPattern();
    Code:
       0: aload_0
       1: getfield      #2                  // Field finderPattern:Lcom/google/zxing/oned/rss/FinderPattern;
       4: areturn

  int getCount();
    Code:
       0: aload_0
       1: getfield      #3                  // Field count:I
       4: ireturn

  void incrementCount();
    Code:
       0: aload_0
       1: dup
       2: getfield      #3                  // Field count:I
       5: iconst_1
       6: iadd
       7: putfield      #3                  // Field count:I
      10: return
}
