Compiled from "AbstractConfigurableWebServerFactory.java"
public abstract class org.springframework.boot.web.server.AbstractConfigurableWebServerFactory implements org.springframework.boot.web.server.ConfigurableWebServerFactory {
  private int port;

  private java.net.InetAddress address;

  private java.util.Set<org.springframework.boot.web.server.ErrorPage> errorPages;

  private org.springframework.boot.web.server.Ssl ssl;

  private org.springframework.boot.web.server.SslStoreProvider sslStoreProvider;

  private org.springframework.boot.ssl.SslBundles sslBundles;

  private org.springframework.boot.web.server.Http2 http2;

  private org.springframework.boot.web.server.Compression compression;

  private java.lang.String serverHeader;

  private org.springframework.boot.web.server.Shutdown shutdown;

  public org.springframework.boot.web.server.AbstractConfigurableWebServerFactory();
    Code:
       0: aload_0
       1: invokespecial #1                  // Method java/lang/Object."<init>":()V
       4: aload_0
       5: sipush        8080
       8: putfield      #7                  // Field port:I
      11: aload_0
      12: new           #13                 // class java/util/LinkedHashSet
      15: dup
      16: invokespecial #15                 // Method java/util/LinkedHashSet."<init>":()V
      19: putfield      #16                 // Field errorPages:Ljava/util/Set;
      22: aload_0
      23: getstatic     #20                 // Field org/springframework/boot/web/server/Shutdown.IMMEDIATE:Lorg/springframework/boot/web/server/Shutdown;
      26: putfield      #26                 // Field shutdown:Lorg/springframework/boot/web/server/Shutdown;
      29: return

  public org.springframework.boot.web.server.AbstractConfigurableWebServerFactory(int);
    Code:
       0: aload_0
       1: invokespecial #1                  // Method java/lang/Object."<init>":()V
       4: aload_0
       5: sipush        8080
       8: putfield      #7                  // Field port:I
      11: aload_0
      12: new           #13                 // class java/util/LinkedHashSet
      15: dup
      16: invokespecial #15                 // Method java/util/LinkedHashSet."<init>":()V
      19: putfield      #16                 // Field errorPages:Ljava/util/Set;
      22: aload_0
      23: getstatic     #20                 // Field org/springframework/boot/web/server/Shutdown.IMMEDIATE:Lorg/springframework/boot/web/server/Shutdown;
      26: putfield      #26                 // Field shutdown:Lorg/springframework/boot/web/server/Shutdown;
      29: aload_0
      30: iload_1
      31: putfield      #7                  // Field port:I
      34: return

  public int getPort();
    Code:
       0: aload_0
       1: getfield      #7                  // Field port:I
       4: ireturn

  public void setPort(int);
    Code:
       0: aload_0
       1: iload_1
       2: putfield      #7                  // Field port:I
       5: return

  public java.net.InetAddress getAddress();
    Code:
       0: aload_0
       1: getfield      #29                 // Field address:Ljava/net/InetAddress;
       4: areturn

  public void setAddress(java.net.InetAddress);
    Code:
       0: aload_0
       1: aload_1
       2: putfield      #29                 // Field address:Ljava/net/InetAddress;
       5: return

  public java.util.Set<org.springframework.boot.web.server.ErrorPage> getErrorPages();
    Code:
       0: aload_0
       1: getfield      #16                 // Field errorPages:Ljava/util/Set;
       4: areturn

  public void setErrorPages(java.util.Set<? extends org.springframework.boot.web.server.ErrorPage>);
    Code:
       0: aload_1
       1: ldc           #33                 // String ErrorPages must not be null
       3: invokestatic  #35                 // Method org/springframework/util/Assert.notNull:(Ljava/lang/Object;Ljava/lang/String;)V
       6: aload_0
       7: new           #13                 // class java/util/LinkedHashSet
      10: dup
      11: aload_1
      12: invokespecial #41                 // Method java/util/LinkedHashSet."<init>":(Ljava/util/Collection;)V
      15: putfield      #16                 // Field errorPages:Ljava/util/Set;
      18: return

  public void addErrorPages(org.springframework.boot.web.server.ErrorPage...);
    Code:
       0: aload_1
       1: ldc           #33                 // String ErrorPages must not be null
       3: invokestatic  #35                 // Method org/springframework/util/Assert.notNull:(Ljava/lang/Object;Ljava/lang/String;)V
       6: aload_0
       7: getfield      #16                 // Field errorPages:Ljava/util/Set;
      10: aload_1
      11: invokestatic  #44                 // Method java/util/Arrays.asList:([Ljava/lang/Object;)Ljava/util/List;
      14: invokeinterface #50,  2           // InterfaceMethod java/util/Set.addAll:(Ljava/util/Collection;)Z
      19: pop
      20: return

  public org.springframework.boot.web.server.Ssl getSsl();
    Code:
       0: aload_0
       1: getfield      #56                 // Field ssl:Lorg/springframework/boot/web/server/Ssl;
       4: areturn

  public void setSsl(org.springframework.boot.web.server.Ssl);
    Code:
       0: aload_0
       1: aload_1
       2: putfield      #56                 // Field ssl:Lorg/springframework/boot/web/server/Ssl;
       5: return

  public org.springframework.boot.web.server.SslStoreProvider getSslStoreProvider();
    Code:
       0: aload_0
       1: getfield      #60                 // Field sslStoreProvider:Lorg/springframework/boot/web/server/SslStoreProvider;
       4: areturn

  public void setSslStoreProvider(org.springframework.boot.web.server.SslStoreProvider);
    Code:
       0: aload_0
       1: aload_1
       2: putfield      #60                 // Field sslStoreProvider:Lorg/springframework/boot/web/server/SslStoreProvider;
       5: return

  public void setSslBundles(org.springframework.boot.ssl.SslBundles);
    Code:
       0: aload_0
       1: aload_1
       2: putfield      #64                 // Field sslBundles:Lorg/springframework/boot/ssl/SslBundles;
       5: return

  public org.springframework.boot.web.server.Http2 getHttp2();
    Code:
       0: aload_0
       1: getfield      #68                 // Field http2:Lorg/springframework/boot/web/server/Http2;
       4: areturn

  public void setHttp2(org.springframework.boot.web.server.Http2);
    Code:
       0: aload_0
       1: aload_1
       2: putfield      #68                 // Field http2:Lorg/springframework/boot/web/server/Http2;
       5: return

  public org.springframework.boot.web.server.Compression getCompression();
    Code:
       0: aload_0
       1: getfield      #72                 // Field compression:Lorg/springframework/boot/web/server/Compression;
       4: areturn

  public void setCompression(org.springframework.boot.web.server.Compression);
    Code:
       0: aload_0
       1: aload_1
       2: putfield      #72                 // Field compression:Lorg/springframework/boot/web/server/Compression;
       5: return

  public java.lang.String getServerHeader();
    Code:
       0: aload_0
       1: getfield      #76                 // Field serverHeader:Ljava/lang/String;
       4: areturn

  public void setServerHeader(java.lang.String);
    Code:
       0: aload_0
       1: aload_1
       2: putfield      #76                 // Field serverHeader:Ljava/lang/String;
       5: return

  public void setShutdown(org.springframework.boot.web.server.Shutdown);
    Code:
       0: aload_0
       1: aload_1
       2: putfield      #26                 // Field shutdown:Lorg/springframework/boot/web/server/Shutdown;
       5: return

  public org.springframework.boot.web.server.Shutdown getShutdown();
    Code:
       0: aload_0
       1: getfield      #26                 // Field shutdown:Lorg/springframework/boot/web/server/Shutdown;
       4: areturn

  public final org.springframework.boot.web.server.SslStoreProvider getOrCreateSslStoreProvider();
    Code:
       0: aload_0
       1: getfield      #60                 // Field sslStoreProvider:Lorg/springframework/boot/web/server/SslStoreProvider;
       4: ifnull        12
       7: aload_0
       8: getfield      #60                 // Field sslStoreProvider:Lorg/springframework/boot/web/server/SslStoreProvider;
      11: areturn
      12: aload_0
      13: getfield      #56                 // Field ssl:Lorg/springframework/boot/web/server/Ssl;
      16: invokestatic  #80                 // Method org/springframework/boot/web/server/CertificateFileSslStoreProvider.from:(Lorg/springframework/boot/web/server/Ssl;)Lorg/springframework/boot/web/server/SslStoreProvider;
      19: areturn

  protected final org.springframework.boot.ssl.SslBundle getSslBundle();
    Code:
       0: aload_0
       1: getfield      #56                 // Field ssl:Lorg/springframework/boot/web/server/Ssl;
       4: aload_0
       5: getfield      #64                 // Field sslBundles:Lorg/springframework/boot/ssl/SslBundles;
       8: aload_0
       9: getfield      #60                 // Field sslStoreProvider:Lorg/springframework/boot/web/server/SslStoreProvider;
      12: invokestatic  #86                 // Method org/springframework/boot/web/server/WebServerSslBundle.get:(Lorg/springframework/boot/web/server/Ssl;Lorg/springframework/boot/ssl/SslBundles;Lorg/springframework/boot/web/server/SslStoreProvider;)Lorg/springframework/boot/ssl/SslBundle;
      15: areturn

  protected final java.io.File createTempDir(java.lang.String);
    Code:
       0: aload_1
       1: aload_0
       2: invokevirtual #92                 // Method getPort:()I
       5: invokedynamic #96,  0             // InvokeDynamic #0:makeConcatWithConstants:(Ljava/lang/String;I)Ljava/lang/String;
      10: iconst_0
      11: anewarray     #100                // class java/nio/file/attribute/FileAttribute
      14: invokestatic  #102                // Method java/nio/file/Files.createTempDirectory:(Ljava/lang/String;[Ljava/nio/file/attribute/FileAttribute;)Ljava/nio/file/Path;
      17: invokeinterface #108,  1          // InterfaceMethod java/nio/file/Path.toFile:()Ljava/io/File;
      22: astore_2
      23: aload_2
      24: invokevirtual #114                // Method java/io/File.deleteOnExit:()V
      27: aload_2
      28: areturn
      29: astore_2
      30: new           #121                // class org/springframework/boot/web/server/WebServerException
      33: dup
      34: ldc           #123                // String java.io.tmpdir
      36: invokestatic  #125                // Method java/lang/System.getProperty:(Ljava/lang/String;)Ljava/lang/String;
      39: invokedynamic #131,  0            // InvokeDynamic #1:makeConcatWithConstants:(Ljava/lang/String;)Ljava/lang/String;
      44: aload_2
      45: invokespecial #133                // Method org/springframework/boot/web/server/WebServerException."<init>":(Ljava/lang/String;Ljava/lang/Throwable;)V
      48: athrow
    Exception table:
       from    to  target type
           0    28    29   Class java/io/IOException
}
