Compiled from "CertificateFileSslStoreProvider.java"
public final class org.springframework.boot.web.server.CertificateFileSslStoreProvider implements org.springframework.boot.web.server.SslStoreProvider {
  private final org.springframework.boot.ssl.SslBundle delegate;

  private org.springframework.boot.web.server.CertificateFileSslStoreProvider(org.springframework.boot.ssl.SslBundle);
    Code:
       0: aload_0
       1: invokespecial #1                  // Method java/lang/Object."<init>":()V
       4: aload_0
       5: aload_1
       6: putfield      #7                  // Field delegate:Lorg/springframework/boot/ssl/SslBundle;
       9: return

  public java.security.KeyStore getKeyStore() throws java.lang.Exception;
    Code:
       0: aload_0
       1: getfield      #7                  // Field delegate:Lorg/springframework/boot/ssl/SslBundle;
       4: invokeinterface #13,  1           // InterfaceMethod org/springframework/boot/ssl/SslBundle.getStores:()Lorg/springframework/boot/ssl/SslStoreBundle;
       9: invokeinterface #19,  1           // InterfaceMethod org/springframework/boot/ssl/SslStoreBundle.getKeyStore:()Ljava/security/KeyStore;
      14: areturn

  public java.security.KeyStore getTrustStore() throws java.lang.Exception;
    Code:
       0: aload_0
       1: getfield      #7                  // Field delegate:Lorg/springframework/boot/ssl/SslBundle;
       4: invokeinterface #13,  1           // InterfaceMethod org/springframework/boot/ssl/SslBundle.getStores:()Lorg/springframework/boot/ssl/SslStoreBundle;
       9: invokeinterface #25,  1           // InterfaceMethod org/springframework/boot/ssl/SslStoreBundle.getTrustStore:()Ljava/security/KeyStore;
      14: areturn

  public java.lang.String getKeyPassword();
    Code:
       0: aload_0
       1: getfield      #7                  // Field delegate:Lorg/springframework/boot/ssl/SslBundle;
       4: invokeinterface #28,  1           // InterfaceMethod org/springframework/boot/ssl/SslBundle.getKey:()Lorg/springframework/boot/ssl/SslBundleKey;
       9: invokeinterface #32,  1           // InterfaceMethod org/springframework/boot/ssl/SslBundleKey.getPassword:()Ljava/lang/String;
      14: areturn

  public static org.springframework.boot.web.server.SslStoreProvider from(org.springframework.boot.web.server.Ssl);
    Code:
       0: aload_0
       1: invokestatic  #38                 // Method org/springframework/boot/web/server/WebServerSslBundle.createCertificateFileSslStoreProviderDelegate:(Lorg/springframework/boot/web/server/Ssl;)Lorg/springframework/boot/ssl/SslBundle;
       4: astore_1
       5: aload_1
       6: ifnull        20
       9: new           #8                  // class org/springframework/boot/web/server/CertificateFileSslStoreProvider
      12: dup
      13: aload_1
      14: invokespecial #44                 // Method "<init>":(Lorg/springframework/boot/ssl/SslBundle;)V
      17: goto          21
      20: aconst_null
      21: areturn
}
