Compiled from "Compression.java"
public class org.springframework.boot.web.server.Compression {
  private boolean enabled;

  private java.lang.String[] mimeTypes;

  private java.lang.String[] excludedUserAgents;

  private org.springframework.util.unit.DataSize minResponseSize;

  public org.springframework.boot.web.server.Compression();
    Code:
       0: aload_0
       1: invokespecial #1                  // Method java/lang/Object."<init>":()V
       4: aload_0
       5: iconst_0
       6: putfield      #7                  // Field enabled:Z
       9: aload_0
      10: bipush        8
      12: anewarray     #13                 // class java/lang/String
      15: dup
      16: iconst_0
      17: ldc           #15                 // String text/html
      19: aastore
      20: dup
      21: iconst_1
      22: ldc           #17                 // String text/xml
      24: aastore
      25: dup
      26: iconst_2
      27: ldc           #19                 // String text/plain
      29: aastore
      30: dup
      31: iconst_3
      32: ldc           #21                 // String text/css
      34: aastore
      35: dup
      36: iconst_4
      37: ldc           #23                 // String text/javascript
      39: aastore
      40: dup
      41: iconst_5
      42: ldc           #25                 // String application/javascript
      44: aastore
      45: dup
      46: bipush        6
      48: ldc           #27                 // String application/json
      50: aastore
      51: dup
      52: bipush        7
      54: ldc           #29                 // String application/xml
      56: aastore
      57: putfield      #31                 // Field mimeTypes:[Ljava/lang/String;
      60: aload_0
      61: aconst_null
      62: putfield      #35                 // Field excludedUserAgents:[Ljava/lang/String;
      65: aload_0
      66: ldc2_w        #38                 // long 2l
      69: invokestatic  #40                 // Method org/springframework/util/unit/DataSize.ofKilobytes:(J)Lorg/springframework/util/unit/DataSize;
      72: putfield      #46                 // Field minResponseSize:Lorg/springframework/util/unit/DataSize;
      75: return

  public boolean getEnabled();
    Code:
       0: aload_0
       1: getfield      #7                  // Field enabled:Z
       4: ireturn

  public void setEnabled(boolean);
    Code:
       0: aload_0
       1: iload_1
       2: putfield      #7                  // Field enabled:Z
       5: return

  public java.lang.String[] getMimeTypes();
    Code:
       0: aload_0
       1: getfield      #31                 // Field mimeTypes:[Ljava/lang/String;
       4: areturn

  public void setMimeTypes(java.lang.String[]);
    Code:
       0: aload_0
       1: aload_1
       2: putfield      #31                 // Field mimeTypes:[Ljava/lang/String;
       5: return

  public java.lang.String[] getExcludedUserAgents();
    Code:
       0: aload_0
       1: getfield      #35                 // Field excludedUserAgents:[Ljava/lang/String;
       4: areturn

  public void setExcludedUserAgents(java.lang.String[]);
    Code:
       0: aload_0
       1: aload_1
       2: putfield      #35                 // Field excludedUserAgents:[Ljava/lang/String;
       5: return

  public org.springframework.util.unit.DataSize getMinResponseSize();
    Code:
       0: aload_0
       1: getfield      #46                 // Field minResponseSize:Lorg/springframework/util/unit/DataSize;
       4: areturn

  public void setMinResponseSize(org.springframework.util.unit.DataSize);
    Code:
       0: aload_0
       1: aload_1
       2: putfield      #46                 // Field minResponseSize:Lorg/springframework/util/unit/DataSize;
       5: return
}
