Compiled from "Cookie.java"
public final class org.springframework.boot.web.server.Cookie$SameSite extends java.lang.Enum<org.springframework.boot.web.server.Cookie$SameSite> {
  public static final org.springframework.boot.web.server.Cookie$SameSite NONE;

  public static final org.springframework.boot.web.server.Cookie$SameSite LAX;

  public static final org.springframework.boot.web.server.Cookie$SameSite STRICT;

  private final java.lang.String attributeValue;

  private static final org.springframework.boot.web.server.Cookie$SameSite[] $VALUES;

  public static org.springframework.boot.web.server.Cookie$SameSite[] values();
    Code:
       0: getstatic     #13                 // Field $VALUES:[Lorg/springframework/boot/web/server/Cookie$SameSite;
       3: invokevirtual #17                 // Method "[Lorg/springframework/boot/web/server/Cookie$SameSite;".clone:()Ljava/lang/Object;
       6: checkcast     #18                 // class "[Lorg/springframework/boot/web/server/Cookie$SameSite;"
       9: areturn

  public static org.springframework.boot.web.server.Cookie$SameSite valueOf(java.lang.String);
    Code:
       0: ldc           #1                  // class org/springframework/boot/web/server/Cookie$SameSite
       2: aload_0
       3: invokestatic  #22                 // Method java/lang/Enum.valueOf:(Ljava/lang/Class;Ljava/lang/String;)Ljava/lang/Enum;
       6: checkcast     #1                  // class org/springframework/boot/web/server/Cookie$SameSite
       9: areturn

  private org.springframework.boot.web.server.Cookie$SameSite(java.lang.String);
    Code:
       0: aload_0
       1: aload_1
       2: iload_2
       3: invokespecial #28                 // Method java/lang/Enum."<init>":(Ljava/lang/String;I)V
       6: aload_0
       7: aload_3
       8: putfield      #32                 // Field attributeValue:Ljava/lang/String;
      11: return

  public java.lang.String attributeValue();
    Code:
       0: aload_0
       1: getfield      #32                 // Field attributeValue:Ljava/lang/String;
       4: areturn

  private static org.springframework.boot.web.server.Cookie$SameSite[] $values();
    Code:
       0: iconst_3
       1: anewarray     #1                  // class org/springframework/boot/web/server/Cookie$SameSite
       4: dup
       5: iconst_0
       6: getstatic     #3                  // Field NONE:Lorg/springframework/boot/web/server/Cookie$SameSite;
       9: aastore
      10: dup
      11: iconst_1
      12: getstatic     #7                  // Field LAX:Lorg/springframework/boot/web/server/Cookie$SameSite;
      15: aastore
      16: dup
      17: iconst_2
      18: getstatic     #10                 // Field STRICT:Lorg/springframework/boot/web/server/Cookie$SameSite;
      21: aastore
      22: areturn

  static {};
    Code:
       0: new           #1                  // class org/springframework/boot/web/server/Cookie$SameSite
       3: dup
       4: ldc           #36                 // String NONE
       6: iconst_0
       7: ldc           #37                 // String None
       9: invokespecial #39                 // Method "<init>":(Ljava/lang/String;ILjava/lang/String;)V
      12: putstatic     #3                  // Field NONE:Lorg/springframework/boot/web/server/Cookie$SameSite;
      15: new           #1                  // class org/springframework/boot/web/server/Cookie$SameSite
      18: dup
      19: ldc           #42                 // String LAX
      21: iconst_1
      22: ldc           #43                 // String Lax
      24: invokespecial #39                 // Method "<init>":(Ljava/lang/String;ILjava/lang/String;)V
      27: putstatic     #7                  // Field LAX:Lorg/springframework/boot/web/server/Cookie$SameSite;
      30: new           #1                  // class org/springframework/boot/web/server/Cookie$SameSite
      33: dup
      34: ldc           #45                 // String STRICT
      36: iconst_2
      37: ldc           #46                 // String Strict
      39: invokespecial #39                 // Method "<init>":(Ljava/lang/String;ILjava/lang/String;)V
      42: putstatic     #10                 // Field STRICT:Lorg/springframework/boot/web/server/Cookie$SameSite;
      45: invokestatic  #48                 // Method $values:()[Lorg/springframework/boot/web/server/Cookie$SameSite;
      48: putstatic     #13                 // Field $VALUES:[Lorg/springframework/boot/web/server/Cookie$SameSite;
      51: return
}
