Compiled from "Cookie.java"
public class org.springframework.boot.web.server.Cookie {
  private java.lang.String name;

  private java.lang.String domain;

  private java.lang.String path;

  private java.lang.Boolean httpOnly;

  private java.lang.Boolean secure;

  private java.time.Duration maxAge;

  private org.springframework.boot.web.server.Cookie$SameSite sameSite;

  public org.springframework.boot.web.server.Cookie();
    Code:
       0: aload_0
       1: invokespecial #1                  // Method java/lang/Object."<init>":()V
       4: return

  public java.lang.String getName();
    Code:
       0: aload_0
       1: getfield      #7                  // Field name:Ljava/lang/String;
       4: areturn

  public void setName(java.lang.String);
    Code:
       0: aload_0
       1: aload_1
       2: putfield      #7                  // Field name:Ljava/lang/String;
       5: return

  public java.lang.String getDomain();
    Code:
       0: aload_0
       1: getfield      #13                 // Field domain:Ljava/lang/String;
       4: areturn

  public void setDomain(java.lang.String);
    Code:
       0: aload_0
       1: aload_1
       2: putfield      #13                 // Field domain:Ljava/lang/String;
       5: return

  public java.lang.String getPath();
    Code:
       0: aload_0
       1: getfield      #16                 // Field path:Ljava/lang/String;
       4: areturn

  public void setPath(java.lang.String);
    Code:
       0: aload_0
       1: aload_1
       2: putfield      #16                 // Field path:Ljava/lang/String;
       5: return

  public java.lang.Boolean getHttpOnly();
    Code:
       0: aload_0
       1: getfield      #19                 // Field httpOnly:Ljava/lang/Boolean;
       4: areturn

  public void setHttpOnly(java.lang.Boolean);
    Code:
       0: aload_0
       1: aload_1
       2: putfield      #19                 // Field httpOnly:Ljava/lang/Boolean;
       5: return

  public java.lang.Boolean getSecure();
    Code:
       0: aload_0
       1: getfield      #23                 // Field secure:Ljava/lang/Boolean;
       4: areturn

  public void setSecure(java.lang.Boolean);
    Code:
       0: aload_0
       1: aload_1
       2: putfield      #23                 // Field secure:Ljava/lang/Boolean;
       5: return

  public java.time.Duration getMaxAge();
    Code:
       0: aload_0
       1: getfield      #26                 // Field maxAge:Ljava/time/Duration;
       4: areturn

  public void setMaxAge(java.time.Duration);
    Code:
       0: aload_0
       1: aload_1
       2: putfield      #26                 // Field maxAge:Ljava/time/Duration;
       5: return

  public org.springframework.boot.web.server.Cookie$SameSite getSameSite();
    Code:
       0: aload_0
       1: getfield      #30                 // Field sameSite:Lorg/springframework/boot/web/server/Cookie$SameSite;
       4: areturn

  public void setSameSite(org.springframework.boot.web.server.Cookie$SameSite);
    Code:
       0: aload_0
       1: aload_1
       2: putfield      #30                 // Field sameSite:Lorg/springframework/boot/web/server/Cookie$SameSite;
       5: return
}
