Compiled from "ErrorPageRegistrarBeanPostProcessor.java"
public class org.springframework.boot.web.server.ErrorPageRegistrarBeanPostProcessor implements org.springframework.beans.factory.config.BeanPostProcessor,org.springframework.beans.factory.BeanFactoryAware {
  private org.springframework.beans.factory.ListableBeanFactory beanFactory;

  private java.util.List<org.springframework.boot.web.server.ErrorPageRegistrar> registrars;

  public org.springframework.boot.web.server.ErrorPageRegistrarBeanPostProcessor();
    Code:
       0: aload_0
       1: invokespecial #1                  // Method java/lang/Object."<init>":()V
       4: return

  public void setBeanFactory(org.springframework.beans.factory.BeanFactory);
    Code:
       0: ldc           #7                  // class org/springframework/beans/factory/ListableBeanFactory
       2: aload_1
       3: ldc           #9                  // String ErrorPageRegistrarBeanPostProcessor can only be used with a ListableBeanFactory
       5: invokestatic  #11                 // Method org/springframework/util/Assert.isInstanceOf:(Ljava/lang/Class;Ljava/lang/Object;Ljava/lang/String;)V
       8: aload_0
       9: aload_1
      10: checkcast     #7                  // class org/springframework/beans/factory/ListableBeanFactory
      13: putfield      #17                 // Field beanFactory:Lorg/springframework/beans/factory/ListableBeanFactory;
      16: return

  public java.lang.Object postProcessBeforeInitialization(java.lang.Object, java.lang.String) throws org.springframework.beans.BeansException;
    Code:
       0: aload_1
       1: instanceof    #23                 // class org/springframework/boot/web/server/ErrorPageRegistry
       4: ifeq          17
       7: aload_1
       8: checkcast     #23                 // class org/springframework/boot/web/server/ErrorPageRegistry
      11: astore_3
      12: aload_0
      13: aload_3
      14: invokevirtual #25                 // Method postProcessBeforeInitialization:(Lorg/springframework/boot/web/server/ErrorPageRegistry;)V
      17: aload_1
      18: areturn

  public java.lang.Object postProcessAfterInitialization(java.lang.Object, java.lang.String) throws org.springframework.beans.BeansException;
    Code:
       0: aload_1
       1: areturn

  private void postProcessBeforeInitialization(org.springframework.boot.web.server.ErrorPageRegistry);
    Code:
       0: aload_0
       1: invokevirtual #29                 // Method getRegistrars:()Ljava/util/Collection;
       4: invokeinterface #33,  1           // InterfaceMethod java/util/Collection.iterator:()Ljava/util/Iterator;
       9: astore_2
      10: aload_2
      11: invokeinterface #39,  1           // InterfaceMethod java/util/Iterator.hasNext:()Z
      16: ifeq          39
      19: aload_2
      20: invokeinterface #45,  1           // InterfaceMethod java/util/Iterator.next:()Ljava/lang/Object;
      25: checkcast     #49                 // class org/springframework/boot/web/server/ErrorPageRegistrar
      28: astore_3
      29: aload_3
      30: aload_1
      31: invokeinterface #51,  2           // InterfaceMethod org/springframework/boot/web/server/ErrorPageRegistrar.registerErrorPages:(Lorg/springframework/boot/web/server/ErrorPageRegistry;)V
      36: goto          10
      39: return

  private java.util.Collection<org.springframework.boot.web.server.ErrorPageRegistrar> getRegistrars();
    Code:
       0: aload_0
       1: getfield      #54                 // Field registrars:Ljava/util/List;
       4: ifnonnull     59
       7: aload_0
       8: new           #58                 // class java/util/ArrayList
      11: dup
      12: aload_0
      13: getfield      #17                 // Field beanFactory:Lorg/springframework/beans/factory/ListableBeanFactory;
      16: ldc           #49                 // class org/springframework/boot/web/server/ErrorPageRegistrar
      18: iconst_0
      19: iconst_0
      20: invokeinterface #60,  4           // InterfaceMethod org/springframework/beans/factory/ListableBeanFactory.getBeansOfType:(Ljava/lang/Class;ZZ)Ljava/util/Map;
      25: invokeinterface #64,  1           // InterfaceMethod java/util/Map.values:()Ljava/util/Collection;
      30: invokespecial #69                 // Method java/util/ArrayList."<init>":(Ljava/util/Collection;)V
      33: putfield      #54                 // Field registrars:Ljava/util/List;
      36: aload_0
      37: getfield      #54                 // Field registrars:Ljava/util/List;
      40: getstatic     #72                 // Field org/springframework/core/annotation/AnnotationAwareOrderComparator.INSTANCE:Lorg/springframework/core/annotation/AnnotationAwareOrderComparator;
      43: invokeinterface #78,  2           // InterfaceMethod java/util/List.sort:(Ljava/util/Comparator;)V
      48: aload_0
      49: aload_0
      50: getfield      #54                 // Field registrars:Ljava/util/List;
      53: invokestatic  #84                 // Method java/util/Collections.unmodifiableList:(Ljava/util/List;)Ljava/util/List;
      56: putfield      #54                 // Field registrars:Ljava/util/List;
      59: aload_0
      60: getfield      #54                 // Field registrars:Ljava/util/List;
      63: areturn
}
