Compiled from "GracefulShutdownResult.java"
public final class org.springframework.boot.web.server.GracefulShutdownResult extends java.lang.Enum<org.springframework.boot.web.server.GracefulShutdownResult> {
  public static final org.springframework.boot.web.server.GracefulShutdownResult REQUESTS_ACTIVE;

  public static final org.springframework.boot.web.server.GracefulShutdownResult IDLE;

  public static final org.springframework.boot.web.server.GracefulShutdownResult IMMEDIATE;

  private static final org.springframework.boot.web.server.GracefulShutdownResult[] $VALUES;

  public static org.springframework.boot.web.server.GracefulShutdownResult[] values();
    Code:
       0: getstatic     #13                 // Field $VALUES:[Lorg/springframework/boot/web/server/GracefulShutdownResult;
       3: invokevirtual #17                 // Method "[Lorg/springframework/boot/web/server/GracefulShutdownResult;".clone:()Ljava/lang/Object;
       6: checkcast     #18                 // class "[Lorg/springframework/boot/web/server/GracefulShutdownResult;"
       9: areturn

  public static org.springframework.boot.web.server.GracefulShutdownResult valueOf(java.lang.String);
    Code:
       0: ldc           #1                  // class org/springframework/boot/web/server/GracefulShutdownResult
       2: aload_0
       3: invokestatic  #22                 // Method java/lang/Enum.valueOf:(Ljava/lang/Class;Ljava/lang/String;)Ljava/lang/Enum;
       6: checkcast     #1                  // class org/springframework/boot/web/server/GracefulShutdownResult
       9: areturn

  private org.springframework.boot.web.server.GracefulShutdownResult();
    Code:
       0: aload_0
       1: aload_1
       2: iload_2
       3: invokespecial #28                 // Method java/lang/Enum."<init>":(Ljava/lang/String;I)V
       6: return

  private static org.springframework.boot.web.server.GracefulShutdownResult[] $values();
    Code:
       0: iconst_3
       1: anewarray     #1                  // class org/springframework/boot/web/server/GracefulShutdownResult
       4: dup
       5: iconst_0
       6: getstatic     #3                  // Field REQUESTS_ACTIVE:Lorg/springframework/boot/web/server/GracefulShutdownResult;
       9: aastore
      10: dup
      11: iconst_1
      12: getstatic     #7                  // Field IDLE:Lorg/springframework/boot/web/server/GracefulShutdownResult;
      15: aastore
      16: dup
      17: iconst_2
      18: getstatic     #10                 // Field IMMEDIATE:Lorg/springframework/boot/web/server/GracefulShutdownResult;
      21: aastore
      22: areturn

  static {};
    Code:
       0: new           #1                  // class org/springframework/boot/web/server/GracefulShutdownResult
       3: dup
       4: ldc           #32                 // String REQUESTS_ACTIVE
       6: iconst_0
       7: invokespecial #33                 // Method "<init>":(Ljava/lang/String;I)V
      10: putstatic     #3                  // Field REQUESTS_ACTIVE:Lorg/springframework/boot/web/server/GracefulShutdownResult;
      13: new           #1                  // class org/springframework/boot/web/server/GracefulShutdownResult
      16: dup
      17: ldc           #34                 // String IDLE
      19: iconst_1
      20: invokespecial #33                 // Method "<init>":(Ljava/lang/String;I)V
      23: putstatic     #7                  // Field IDLE:Lorg/springframework/boot/web/server/GracefulShutdownResult;
      26: new           #1                  // class org/springframework/boot/web/server/GracefulShutdownResult
      29: dup
      30: ldc           #35                 // String IMMEDIATE
      32: iconst_2
      33: invokespecial #33                 // Method "<init>":(Ljava/lang/String;I)V
      36: putstatic     #10                 // Field IMMEDIATE:Lorg/springframework/boot/web/server/GracefulShutdownResult;
      39: invokestatic  #36                 // Method $values:()[Lorg/springframework/boot/web/server/GracefulShutdownResult;
      42: putstatic     #13                 // Field $VALUES:[Lorg/springframework/boot/web/server/GracefulShutdownResult;
      45: return
}
