Compiled from "MimeMappings.java"
public class org.springframework.boot.web.server.MimeMappings implements java.lang.Iterable<org.springframework.boot.web.server.MimeMappings$Mapping> {
  public static final org.springframework.boot.web.server.MimeMappings DEFAULT;

  private final java.util.Map<java.lang.String, org.springframework.boot.web.server.MimeMappings$Mapping> map;

  public org.springframework.boot.web.server.MimeMappings();
    Code:
       0: aload_0
       1: invokespecial #1                  // Method java/lang/Object."<init>":()V
       4: aload_0
       5: new           #7                  // class java/util/LinkedHashMap
       8: dup
       9: invokespecial #9                  // Method java/util/LinkedHashMap."<init>":()V
      12: putfield      #10                 // Field map:Ljava/util/Map;
      15: return

  public org.springframework.boot.web.server.MimeMappings(org.springframework.boot.web.server.MimeMappings);
    Code:
       0: aload_0
       1: aload_1
       2: iconst_1
       3: invokespecial #16                 // Method "<init>":(Lorg/springframework/boot/web/server/MimeMappings;Z)V
       6: return

  public org.springframework.boot.web.server.MimeMappings(java.util.Map<java.lang.String, java.lang.String>);
    Code:
       0: aload_0
       1: invokespecial #1                  // Method java/lang/Object."<init>":()V
       4: aload_1
       5: ldc           #19                 // String Mappings must not be null
       7: invokestatic  #21                 // Method org/springframework/util/Assert.notNull:(Ljava/lang/Object;Ljava/lang/String;)V
      10: aload_0
      11: new           #7                  // class java/util/LinkedHashMap
      14: dup
      15: invokespecial #9                  // Method java/util/LinkedHashMap."<init>":()V
      18: putfield      #10                 // Field map:Ljava/util/Map;
      21: aload_1
      22: aload_0
      23: invokedynamic #27,  0             // InvokeDynamic #0:accept:(Lorg/springframework/boot/web/server/MimeMappings;)Ljava/util/function/BiConsumer;
      28: invokeinterface #31,  2           // InterfaceMethod java/util/Map.forEach:(Ljava/util/function/BiConsumer;)V
      33: return

  org.springframework.boot.web.server.MimeMappings(org.springframework.boot.web.server.MimeMappings, boolean);
    Code:
       0: aload_0
       1: invokespecial #1                  // Method java/lang/Object."<init>":()V
       4: aload_1
       5: ldc           #19                 // String Mappings must not be null
       7: invokestatic  #21                 // Method org/springframework/util/Assert.notNull:(Ljava/lang/Object;Ljava/lang/String;)V
      10: aload_0
      11: iload_2
      12: ifeq          29
      15: new           #7                  // class java/util/LinkedHashMap
      18: dup
      19: aload_1
      20: getfield      #10                 // Field map:Ljava/util/Map;
      23: invokespecial #37                 // Method java/util/LinkedHashMap."<init>":(Ljava/util/Map;)V
      26: goto          36
      29: aload_1
      30: getfield      #10                 // Field map:Ljava/util/Map;
      33: invokestatic  #40                 // Method java/util/Collections.unmodifiableMap:(Ljava/util/Map;)Ljava/util/Map;
      36: putfield      #10                 // Field map:Ljava/util/Map;
      39: return

  public java.lang.String add(java.lang.String, java.lang.String);
    Code:
       0: aload_1
       1: ldc           #46                 // String Extension must not be null
       3: invokestatic  #21                 // Method org/springframework/util/Assert.notNull:(Ljava/lang/Object;Ljava/lang/String;)V
       6: aload_2
       7: ldc           #48                 // String MimeType must not be null
       9: invokestatic  #21                 // Method org/springframework/util/Assert.notNull:(Ljava/lang/Object;Ljava/lang/String;)V
      12: aload_0
      13: getfield      #10                 // Field map:Ljava/util/Map;
      16: aload_1
      17: getstatic     #50                 // Field java/util/Locale.ENGLISH:Ljava/util/Locale;
      20: invokevirtual #56                 // Method java/lang/String.toLowerCase:(Ljava/util/Locale;)Ljava/lang/String;
      23: new           #62                 // class org/springframework/boot/web/server/MimeMappings$Mapping
      26: dup
      27: aload_1
      28: aload_2
      29: invokespecial #64                 // Method org/springframework/boot/web/server/MimeMappings$Mapping."<init>":(Ljava/lang/String;Ljava/lang/String;)V
      32: invokeinterface #67,  3           // InterfaceMethod java/util/Map.put:(Ljava/lang/Object;Ljava/lang/Object;)Ljava/lang/Object;
      37: checkcast     #62                 // class org/springframework/boot/web/server/MimeMappings$Mapping
      40: astore_3
      41: aload_3
      42: ifnull        52
      45: aload_3
      46: invokevirtual #71                 // Method org/springframework/boot/web/server/MimeMappings$Mapping.getMimeType:()Ljava/lang/String;
      49: goto          53
      52: aconst_null
      53: areturn

  public java.lang.String remove(java.lang.String);
    Code:
       0: aload_1
       1: ldc           #46                 // String Extension must not be null
       3: invokestatic  #21                 // Method org/springframework/util/Assert.notNull:(Ljava/lang/Object;Ljava/lang/String;)V
       6: aload_0
       7: getfield      #10                 // Field map:Ljava/util/Map;
      10: aload_1
      11: getstatic     #50                 // Field java/util/Locale.ENGLISH:Ljava/util/Locale;
      14: invokevirtual #56                 // Method java/lang/String.toLowerCase:(Ljava/util/Locale;)Ljava/lang/String;
      17: invokeinterface #75,  2           // InterfaceMethod java/util/Map.remove:(Ljava/lang/Object;)Ljava/lang/Object;
      22: checkcast     #62                 // class org/springframework/boot/web/server/MimeMappings$Mapping
      25: astore_2
      26: aload_2
      27: ifnull        37
      30: aload_2
      31: invokevirtual #71                 // Method org/springframework/boot/web/server/MimeMappings$Mapping.getMimeType:()Ljava/lang/String;
      34: goto          38
      37: aconst_null
      38: areturn

  public java.lang.String get(java.lang.String);
    Code:
       0: aload_1
       1: ldc           #46                 // String Extension must not be null
       3: invokestatic  #21                 // Method org/springframework/util/Assert.notNull:(Ljava/lang/Object;Ljava/lang/String;)V
       6: aload_0
       7: getfield      #10                 // Field map:Ljava/util/Map;
      10: aload_1
      11: getstatic     #50                 // Field java/util/Locale.ENGLISH:Ljava/util/Locale;
      14: invokevirtual #56                 // Method java/lang/String.toLowerCase:(Ljava/util/Locale;)Ljava/lang/String;
      17: invokeinterface #79,  2           // InterfaceMethod java/util/Map.get:(Ljava/lang/Object;)Ljava/lang/Object;
      22: checkcast     #62                 // class org/springframework/boot/web/server/MimeMappings$Mapping
      25: astore_2
      26: aload_2
      27: ifnull        37
      30: aload_2
      31: invokevirtual #71                 // Method org/springframework/boot/web/server/MimeMappings$Mapping.getMimeType:()Ljava/lang/String;
      34: goto          38
      37: aconst_null
      38: areturn

  public java.util.Collection<org.springframework.boot.web.server.MimeMappings$Mapping> getAll();
    Code:
       0: aload_0
       1: getfield      #10                 // Field map:Ljava/util/Map;
       4: invokeinterface #82,  1           // InterfaceMethod java/util/Map.values:()Ljava/util/Collection;
       9: areturn

  public final java.util.Iterator<org.springframework.boot.web.server.MimeMappings$Mapping> iterator();
    Code:
       0: aload_0
       1: invokevirtual #86                 // Method getAll:()Ljava/util/Collection;
       4: invokeinterface #89,  1           // InterfaceMethod java/util/Collection.iterator:()Ljava/util/Iterator;
       9: areturn

  public boolean equals(java.lang.Object);
    Code:
       0: aload_1
       1: ifnonnull     6
       4: iconst_0
       5: ireturn
       6: aload_1
       7: aload_0
       8: if_acmpne     13
      11: iconst_1
      12: ireturn
      13: aload_1
      14: instanceof    #11                 // class org/springframework/boot/web/server/MimeMappings
      17: ifeq          39
      20: aload_1
      21: checkcast     #11                 // class org/springframework/boot/web/server/MimeMappings
      24: astore_2
      25: aload_0
      26: invokevirtual #95                 // Method getMap:()Ljava/util/Map;
      29: aload_2
      30: getfield      #10                 // Field map:Ljava/util/Map;
      33: invokeinterface #99,  2           // InterfaceMethod java/util/Map.equals:(Ljava/lang/Object;)Z
      38: ireturn
      39: iconst_0
      40: ireturn

  public int hashCode();
    Code:
       0: aload_0
       1: invokevirtual #95                 // Method getMap:()Ljava/util/Map;
       4: invokeinterface #103,  1          // InterfaceMethod java/util/Map.hashCode:()I
       9: ireturn

  java.util.Map<java.lang.String, org.springframework.boot.web.server.MimeMappings$Mapping> getMap();
    Code:
       0: aload_0
       1: getfield      #10                 // Field map:Ljava/util/Map;
       4: areturn

  public static org.springframework.boot.web.server.MimeMappings unmodifiableMappings(org.springframework.boot.web.server.MimeMappings);
    Code:
       0: aload_0
       1: ldc           #19                 // String Mappings must not be null
       3: invokestatic  #21                 // Method org/springframework/util/Assert.notNull:(Ljava/lang/Object;Ljava/lang/String;)V
       6: new           #11                 // class org/springframework/boot/web/server/MimeMappings
       9: dup
      10: aload_0
      11: iconst_0
      12: invokespecial #16                 // Method "<init>":(Lorg/springframework/boot/web/server/MimeMappings;Z)V
      15: areturn

  public static org.springframework.boot.web.server.MimeMappings lazyCopy(org.springframework.boot.web.server.MimeMappings);
    Code:
       0: aload_0
       1: ldc           #19                 // String Mappings must not be null
       3: invokestatic  #21                 // Method org/springframework/util/Assert.notNull:(Ljava/lang/Object;Ljava/lang/String;)V
       6: new           #107                // class org/springframework/boot/web/server/MimeMappings$LazyMimeMappingsCopy
       9: dup
      10: aload_0
      11: invokespecial #109                // Method org/springframework/boot/web/server/MimeMappings$LazyMimeMappingsCopy."<init>":(Lorg/springframework/boot/web/server/MimeMappings;)V
      14: areturn

  static {};
    Code:
       0: new           #112                // class org/springframework/boot/web/server/MimeMappings$DefaultMimeMappings
       3: dup
       4: invokespecial #114                // Method org/springframework/boot/web/server/MimeMappings$DefaultMimeMappings."<init>":()V
       7: putstatic     #115                // Field DEFAULT:Lorg/springframework/boot/web/server/MimeMappings;
      10: return
}
