Compiled from "MimeMappings.java"
final class org.springframework.boot.web.server.MimeMappings$LazyMimeMappingsCopy extends org.springframework.boot.web.server.MimeMappings {
  private final org.springframework.boot.web.server.MimeMappings source;

  private final java.util.concurrent.atomic.AtomicBoolean copied;

  org.springframework.boot.web.server.MimeMappings$LazyMimeMappingsCopy(org.springframework.boot.web.server.MimeMappings);
    Code:
       0: aload_0
       1: invokespecial #1                  // Method org/springframework/boot/web/server/MimeMappings."<init>":()V
       4: aload_0
       5: new           #7                  // class java/util/concurrent/atomic/AtomicBoolean
       8: dup
       9: invokespecial #9                  // Method java/util/concurrent/atomic/AtomicBoolean."<init>":()V
      12: putfield      #10                 // Field copied:Ljava/util/concurrent/atomic/AtomicBoolean;
      15: aload_0
      16: aload_1
      17: putfield      #16                 // Field source:Lorg/springframework/boot/web/server/MimeMappings;
      20: return

  public java.lang.String add(java.lang.String, java.lang.String);
    Code:
       0: aload_0
       1: invokevirtual #20                 // Method copyIfNecessary:()V
       4: aload_0
       5: aload_1
       6: aload_2
       7: invokespecial #23                 // Method org/springframework/boot/web/server/MimeMappings.add:(Ljava/lang/String;Ljava/lang/String;)Ljava/lang/String;
      10: areturn

  public java.lang.String remove(java.lang.String);
    Code:
       0: aload_0
       1: invokevirtual #20                 // Method copyIfNecessary:()V
       4: aload_0
       5: aload_1
       6: invokespecial #27                 // Method org/springframework/boot/web/server/MimeMappings.remove:(Ljava/lang/String;)Ljava/lang/String;
       9: areturn

  private void copyIfNecessary();
    Code:
       0: aload_0
       1: getfield      #10                 // Field copied:Ljava/util/concurrent/atomic/AtomicBoolean;
       4: iconst_0
       5: iconst_1
       6: invokevirtual #31                 // Method java/util/concurrent/atomic/AtomicBoolean.compareAndSet:(ZZ)Z
       9: ifeq          25
      12: aload_0
      13: getfield      #16                 // Field source:Lorg/springframework/boot/web/server/MimeMappings;
      16: aload_0
      17: invokedynamic #35,  0             // InvokeDynamic #0:accept:(Lorg/springframework/boot/web/server/MimeMappings$LazyMimeMappingsCopy;)Ljava/util/function/Consumer;
      22: invokevirtual #39                 // Method org/springframework/boot/web/server/MimeMappings.forEach:(Ljava/util/function/Consumer;)V
      25: return

  public java.lang.String get(java.lang.String);
    Code:
       0: aload_0
       1: getfield      #10                 // Field copied:Ljava/util/concurrent/atomic/AtomicBoolean;
       4: invokevirtual #43                 // Method java/util/concurrent/atomic/AtomicBoolean.get:()Z
       7: ifne          21
      10: aload_0
      11: getfield      #16                 // Field source:Lorg/springframework/boot/web/server/MimeMappings;
      14: aload_1
      15: invokevirtual #47                 // Method org/springframework/boot/web/server/MimeMappings.get:(Ljava/lang/String;)Ljava/lang/String;
      18: goto          26
      21: aload_0
      22: aload_1
      23: invokespecial #47                 // Method org/springframework/boot/web/server/MimeMappings.get:(Ljava/lang/String;)Ljava/lang/String;
      26: areturn

  public java.util.Collection<org.springframework.boot.web.server.MimeMappings$Mapping> getAll();
    Code:
       0: aload_0
       1: getfield      #10                 // Field copied:Ljava/util/concurrent/atomic/AtomicBoolean;
       4: invokevirtual #43                 // Method java/util/concurrent/atomic/AtomicBoolean.get:()Z
       7: ifne          20
      10: aload_0
      11: getfield      #16                 // Field source:Lorg/springframework/boot/web/server/MimeMappings;
      14: invokevirtual #49                 // Method org/springframework/boot/web/server/MimeMappings.getAll:()Ljava/util/Collection;
      17: goto          24
      20: aload_0
      21: invokespecial #49                 // Method org/springframework/boot/web/server/MimeMappings.getAll:()Ljava/util/Collection;
      24: areturn

  java.util.Map<java.lang.String, org.springframework.boot.web.server.MimeMappings$Mapping> getMap();
    Code:
       0: aload_0
       1: getfield      #10                 // Field copied:Ljava/util/concurrent/atomic/AtomicBoolean;
       4: invokevirtual #43                 // Method java/util/concurrent/atomic/AtomicBoolean.get:()Z
       7: ifne          20
      10: aload_0
      11: getfield      #16                 // Field source:Lorg/springframework/boot/web/server/MimeMappings;
      14: invokevirtual #53                 // Method org/springframework/boot/web/server/MimeMappings.getMap:()Ljava/util/Map;
      17: goto          24
      20: aload_0
      21: invokespecial #53                 // Method org/springframework/boot/web/server/MimeMappings.getMap:()Ljava/util/Map;
      24: areturn

  private void lambda$copyIfNecessary$0(org.springframework.boot.web.server.MimeMappings$Mapping);
    Code:
       0: aload_0
       1: aload_1
       2: invokevirtual #57                 // Method org/springframework/boot/web/server/MimeMappings$Mapping.getExtension:()Ljava/lang/String;
       5: aload_1
       6: invokevirtual #63                 // Method org/springframework/boot/web/server/MimeMappings$Mapping.getMimeType:()Ljava/lang/String;
       9: invokevirtual #66                 // Method add:(Ljava/lang/String;Ljava/lang/String;)Ljava/lang/String;
      12: pop
      13: return
}
