Compiled from "MimeMappings.java"
final class org.springframework.boot.web.server.MimeMappings$DefaultMimeMappings extends org.springframework.boot.web.server.MimeMappings {
  static final java.lang.String MIME_MAPPINGS_PROPERTIES;

  private static final org.springframework.boot.web.server.MimeMappings COMMON;

  private volatile java.util.Map<java.lang.String, org.springframework.boot.web.server.MimeMappings$Mapping> loaded;

  org.springframework.boot.web.server.MimeMappings$DefaultMimeMappings();
    Code:
       0: aload_0
       1: new           #1                  // class org/springframework/boot/web/server/MimeMappings
       4: dup
       5: invokespecial #3                  // Method org/springframework/boot/web/server/MimeMappings."<init>":()V
       8: iconst_0
       9: invokespecial #7                  // Method org/springframework/boot/web/server/MimeMappings."<init>":(Lorg/springframework/boot/web/server/MimeMappings;Z)V
      12: return

  public java.util.Collection<org.springframework.boot.web.server.MimeMappings$Mapping> getAll();
    Code:
       0: aload_0
       1: invokevirtual #10                 // Method load:()Ljava/util/Map;
       4: invokeinterface #16,  1           // InterfaceMethod java/util/Map.values:()Ljava/util/Collection;
       9: areturn

  public java.lang.String get(java.lang.String);
    Code:
       0: aload_1
       1: ldc           #22                 // String Extension must not be null
       3: invokestatic  #24                 // Method org/springframework/util/Assert.notNull:(Ljava/lang/Object;Ljava/lang/String;)V
       6: aload_1
       7: getstatic     #30                 // Field java/util/Locale.ENGLISH:Ljava/util/Locale;
      10: invokevirtual #36                 // Method java/lang/String.toLowerCase:(Ljava/util/Locale;)Ljava/lang/String;
      13: astore_1
      14: aload_0
      15: getfield      #42                 // Field loaded:Ljava/util/Map;
      18: astore_2
      19: aload_2
      20: ifnull        30
      23: aload_0
      24: aload_2
      25: aload_1
      26: invokevirtual #46                 // Method get:(Ljava/util/Map;Ljava/lang/String;)Ljava/lang/String;
      29: areturn
      30: getstatic     #50                 // Field COMMON:Lorg/springframework/boot/web/server/MimeMappings;
      33: aload_1
      34: invokevirtual #54                 // Method org/springframework/boot/web/server/MimeMappings.get:(Ljava/lang/String;)Ljava/lang/String;
      37: astore_3
      38: aload_3
      39: ifnull        44
      42: aload_3
      43: areturn
      44: aload_0
      45: invokevirtual #10                 // Method load:()Ljava/util/Map;
      48: astore_2
      49: aload_0
      50: aload_2
      51: aload_1
      52: invokevirtual #46                 // Method get:(Ljava/util/Map;Ljava/lang/String;)Ljava/lang/String;
      55: areturn

  private java.lang.String get(java.util.Map<java.lang.String, org.springframework.boot.web.server.MimeMappings$Mapping>, java.lang.String);
    Code:
       0: aload_1
       1: aload_2
       2: invokeinterface #57,  2           // InterfaceMethod java/util/Map.get:(Ljava/lang/Object;)Ljava/lang/Object;
       7: checkcast     #60                 // class org/springframework/boot/web/server/MimeMappings$Mapping
      10: astore_3
      11: aload_3
      12: ifnull        22
      15: aload_3
      16: invokevirtual #62                 // Method org/springframework/boot/web/server/MimeMappings$Mapping.getMimeType:()Ljava/lang/String;
      19: goto          23
      22: aconst_null
      23: areturn

  java.util.Map<java.lang.String, org.springframework.boot.web.server.MimeMappings$Mapping> getMap();
    Code:
       0: aload_0
       1: invokevirtual #10                 // Method load:()Ljava/util/Map;
       4: areturn

  private java.util.Map<java.lang.String, org.springframework.boot.web.server.MimeMappings$Mapping> load();
    Code:
       0: aload_0
       1: getfield      #42                 // Field loaded:Ljava/util/Map;
       4: astore_1
       5: aload_1
       6: ifnull        11
       9: aload_1
      10: areturn
      11: new           #66                 // class java/util/LinkedHashMap
      14: dup
      15: invokespecial #68                 // Method java/util/LinkedHashMap."<init>":()V
      18: astore_1
      19: new           #69                 // class org/springframework/core/io/ClassPathResource
      22: dup
      23: ldc           #71                 // String mime-mappings.properties
      25: aload_0
      26: invokevirtual #73                 // Method java/lang/Object.getClass:()Ljava/lang/Class;
      29: invokespecial #79                 // Method org/springframework/core/io/ClassPathResource."<init>":(Ljava/lang/String;Ljava/lang/Class;)V
      32: invokestatic  #82                 // Method org/springframework/core/io/support/PropertiesLoaderUtils.loadProperties:(Lorg/springframework/core/io/Resource;)Ljava/util/Properties;
      35: invokevirtual #88                 // Method java/util/Properties.entrySet:()Ljava/util/Set;
      38: invokeinterface #94,  1           // InterfaceMethod java/util/Set.iterator:()Ljava/util/Iterator;
      43: astore_2
      44: aload_2
      45: invokeinterface #100,  1          // InterfaceMethod java/util/Iterator.hasNext:()Z
      50: ifeq          107
      53: aload_2
      54: invokeinterface #106,  1          // InterfaceMethod java/util/Iterator.next:()Ljava/lang/Object;
      59: checkcast     #110                // class java/util/Map$Entry
      62: astore_3
      63: aload_1
      64: aload_3
      65: invokeinterface #112,  1          // InterfaceMethod java/util/Map$Entry.getKey:()Ljava/lang/Object;
      70: checkcast     #37                 // class java/lang/String
      73: new           #60                 // class org/springframework/boot/web/server/MimeMappings$Mapping
      76: dup
      77: aload_3
      78: invokeinterface #112,  1          // InterfaceMethod java/util/Map$Entry.getKey:()Ljava/lang/Object;
      83: checkcast     #37                 // class java/lang/String
      86: aload_3
      87: invokeinterface #115,  1          // InterfaceMethod java/util/Map$Entry.getValue:()Ljava/lang/Object;
      92: checkcast     #37                 // class java/lang/String
      95: invokespecial #118                // Method org/springframework/boot/web/server/MimeMappings$Mapping."<init>":(Ljava/lang/String;Ljava/lang/String;)V
      98: invokeinterface #121,  3          // InterfaceMethod java/util/Map.put:(Ljava/lang/Object;Ljava/lang/Object;)Ljava/lang/Object;
     103: pop
     104: goto          44
     107: aload_1
     108: invokestatic  #125                // Method java/util/Collections.unmodifiableMap:(Ljava/util/Map;)Ljava/util/Map;
     111: astore_1
     112: aload_0
     113: aload_1
     114: putfield      #42                 // Field loaded:Ljava/util/Map;
     117: aload_1
     118: areturn
     119: astore_2
     120: new           #133                // class java/lang/IllegalArgumentException
     123: dup
     124: ldc           #135                // String Unable to load the default MIME types
     126: aload_2
     127: invokespecial #137                // Method java/lang/IllegalArgumentException."<init>":(Ljava/lang/String;Ljava/lang/Throwable;)V
     130: athrow
    Exception table:
       from    to  target type
          11   118   119   Class java/io/IOException

  static {};
    Code:
       0: new           #1                  // class org/springframework/boot/web/server/MimeMappings
       3: dup
       4: invokespecial #3                  // Method org/springframework/boot/web/server/MimeMappings."<init>":()V
       7: astore_0
       8: aload_0
       9: ldc           #140                // String avi
      11: ldc           #142                // String video/x-msvideo
      13: invokevirtual #144                // Method org/springframework/boot/web/server/MimeMappings.add:(Ljava/lang/String;Ljava/lang/String;)Ljava/lang/String;
      16: pop
      17: aload_0
      18: ldc           #148                // String bin
      20: ldc           #150                // String application/octet-stream
      22: invokevirtual #144                // Method org/springframework/boot/web/server/MimeMappings.add:(Ljava/lang/String;Ljava/lang/String;)Ljava/lang/String;
      25: pop
      26: aload_0
      27: ldc           #152                // String body
      29: ldc           #154                // String text/html
      31: invokevirtual #144                // Method org/springframework/boot/web/server/MimeMappings.add:(Ljava/lang/String;Ljava/lang/String;)Ljava/lang/String;
      34: pop
      35: aload_0
      36: ldc           #156                // String class
      38: ldc           #158                // String application/java
      40: invokevirtual #144                // Method org/springframework/boot/web/server/MimeMappings.add:(Ljava/lang/String;Ljava/lang/String;)Ljava/lang/String;
      43: pop
      44: aload_0
      45: ldc           #160                // String css
      47: ldc           #162                // String text/css
      49: invokevirtual #144                // Method org/springframework/boot/web/server/MimeMappings.add:(Ljava/lang/String;Ljava/lang/String;)Ljava/lang/String;
      52: pop
      53: aload_0
      54: ldc           #164                // String dtd
      56: ldc           #166                // String application/xml-dtd
      58: invokevirtual #144                // Method org/springframework/boot/web/server/MimeMappings.add:(Ljava/lang/String;Ljava/lang/String;)Ljava/lang/String;
      61: pop
      62: aload_0
      63: ldc           #168                // String gif
      65: ldc           #170                // String image/gif
      67: invokevirtual #144                // Method org/springframework/boot/web/server/MimeMappings.add:(Ljava/lang/String;Ljava/lang/String;)Ljava/lang/String;
      70: pop
      71: aload_0
      72: ldc           #172                // String gtar
      74: ldc           #174                // String application/x-gtar
      76: invokevirtual #144                // Method org/springframework/boot/web/server/MimeMappings.add:(Ljava/lang/String;Ljava/lang/String;)Ljava/lang/String;
      79: pop
      80: aload_0
      81: ldc           #176                // String gz
      83: ldc           #178                // String application/x-gzip
      85: invokevirtual #144                // Method org/springframework/boot/web/server/MimeMappings.add:(Ljava/lang/String;Ljava/lang/String;)Ljava/lang/String;
      88: pop
      89: aload_0
      90: ldc           #180                // String htm
      92: ldc           #154                // String text/html
      94: invokevirtual #144                // Method org/springframework/boot/web/server/MimeMappings.add:(Ljava/lang/String;Ljava/lang/String;)Ljava/lang/String;
      97: pop
      98: aload_0
      99: ldc           #182                // String html
     101: ldc           #154                // String text/html
     103: invokevirtual #144                // Method org/springframework/boot/web/server/MimeMappings.add:(Ljava/lang/String;Ljava/lang/String;)Ljava/lang/String;
     106: pop
     107: aload_0
     108: ldc           #184                // String jar
     110: ldc           #186                // String application/java-archive
     112: invokevirtual #144                // Method org/springframework/boot/web/server/MimeMappings.add:(Ljava/lang/String;Ljava/lang/String;)Ljava/lang/String;
     115: pop
     116: aload_0
     117: ldc           #188                // String java
     119: ldc           #190                // String text/x-java-source
     121: invokevirtual #144                // Method org/springframework/boot/web/server/MimeMappings.add:(Ljava/lang/String;Ljava/lang/String;)Ljava/lang/String;
     124: pop
     125: aload_0
     126: ldc           #192                // String jnlp
     128: ldc           #194                // String application/x-java-jnlp-file
     130: invokevirtual #144                // Method org/springframework/boot/web/server/MimeMappings.add:(Ljava/lang/String;Ljava/lang/String;)Ljava/lang/String;
     133: pop
     134: aload_0
     135: ldc           #196                // String jpe
     137: ldc           #198                // String image/jpeg
     139: invokevirtual #144                // Method org/springframework/boot/web/server/MimeMappings.add:(Ljava/lang/String;Ljava/lang/String;)Ljava/lang/String;
     142: pop
     143: aload_0
     144: ldc           #200                // String jpeg
     146: ldc           #198                // String image/jpeg
     148: invokevirtual #144                // Method org/springframework/boot/web/server/MimeMappings.add:(Ljava/lang/String;Ljava/lang/String;)Ljava/lang/String;
     151: pop
     152: aload_0
     153: ldc           #202                // String jpg
     155: ldc           #198                // String image/jpeg
     157: invokevirtual #144                // Method org/springframework/boot/web/server/MimeMappings.add:(Ljava/lang/String;Ljava/lang/String;)Ljava/lang/String;
     160: pop
     161: aload_0
     162: ldc           #204                // String js
     164: ldc           #206                // String text/javascript
     166: invokevirtual #144                // Method org/springframework/boot/web/server/MimeMappings.add:(Ljava/lang/String;Ljava/lang/String;)Ljava/lang/String;
     169: pop
     170: aload_0
     171: ldc           #208                // String json
     173: ldc           #210                // String application/json
     175: invokevirtual #144                // Method org/springframework/boot/web/server/MimeMappings.add:(Ljava/lang/String;Ljava/lang/String;)Ljava/lang/String;
     178: pop
     179: aload_0
     180: ldc           #212                // String otf
     182: ldc           #214                // String font/otf
     184: invokevirtual #144                // Method org/springframework/boot/web/server/MimeMappings.add:(Ljava/lang/String;Ljava/lang/String;)Ljava/lang/String;
     187: pop
     188: aload_0
     189: ldc           #216                // String pdf
     191: ldc           #218                // String application/pdf
     193: invokevirtual #144                // Method org/springframework/boot/web/server/MimeMappings.add:(Ljava/lang/String;Ljava/lang/String;)Ljava/lang/String;
     196: pop
     197: aload_0
     198: ldc           #220                // String png
     200: ldc           #222                // String image/png
     202: invokevirtual #144                // Method org/springframework/boot/web/server/MimeMappings.add:(Ljava/lang/String;Ljava/lang/String;)Ljava/lang/String;
     205: pop
     206: aload_0
     207: ldc           #224                // String ps
     209: ldc           #226                // String application/postscript
     211: invokevirtual #144                // Method org/springframework/boot/web/server/MimeMappings.add:(Ljava/lang/String;Ljava/lang/String;)Ljava/lang/String;
     214: pop
     215: aload_0
     216: ldc           #228                // String tar
     218: ldc           #230                // String application/x-tar
     220: invokevirtual #144                // Method org/springframework/boot/web/server/MimeMappings.add:(Ljava/lang/String;Ljava/lang/String;)Ljava/lang/String;
     223: pop
     224: aload_0
     225: ldc           #232                // String tif
     227: ldc           #234                // String image/tiff
     229: invokevirtual #144                // Method org/springframework/boot/web/server/MimeMappings.add:(Ljava/lang/String;Ljava/lang/String;)Ljava/lang/String;
     232: pop
     233: aload_0
     234: ldc           #236                // String tiff
     236: ldc           #234                // String image/tiff
     238: invokevirtual #144                // Method org/springframework/boot/web/server/MimeMappings.add:(Ljava/lang/String;Ljava/lang/String;)Ljava/lang/String;
     241: pop
     242: aload_0
     243: ldc           #238                // String ttf
     245: ldc           #240                // String font/ttf
     247: invokevirtual #144                // Method org/springframework/boot/web/server/MimeMappings.add:(Ljava/lang/String;Ljava/lang/String;)Ljava/lang/String;
     250: pop
     251: aload_0
     252: ldc           #242                // String txt
     254: ldc           #244                // String text/plain
     256: invokevirtual #144                // Method org/springframework/boot/web/server/MimeMappings.add:(Ljava/lang/String;Ljava/lang/String;)Ljava/lang/String;
     259: pop
     260: aload_0
     261: ldc           #246                // String xht
     263: ldc           #248                // String application/xhtml+xml
     265: invokevirtual #144                // Method org/springframework/boot/web/server/MimeMappings.add:(Ljava/lang/String;Ljava/lang/String;)Ljava/lang/String;
     268: pop
     269: aload_0
     270: ldc           #250                // String xhtml
     272: ldc           #248                // String application/xhtml+xml
     274: invokevirtual #144                // Method org/springframework/boot/web/server/MimeMappings.add:(Ljava/lang/String;Ljava/lang/String;)Ljava/lang/String;
     277: pop
     278: aload_0
     279: ldc           #252                // String xls
     281: ldc           #254                // String application/vnd.ms-excel
     283: invokevirtual #144                // Method org/springframework/boot/web/server/MimeMappings.add:(Ljava/lang/String;Ljava/lang/String;)Ljava/lang/String;
     286: pop
     287: aload_0
     288: ldc_w         #256                // String xml
     291: ldc_w         #258                // String application/xml
     294: invokevirtual #144                // Method org/springframework/boot/web/server/MimeMappings.add:(Ljava/lang/String;Ljava/lang/String;)Ljava/lang/String;
     297: pop
     298: aload_0
     299: ldc_w         #260                // String xsl
     302: ldc_w         #258                // String application/xml
     305: invokevirtual #144                // Method org/springframework/boot/web/server/MimeMappings.add:(Ljava/lang/String;Ljava/lang/String;)Ljava/lang/String;
     308: pop
     309: aload_0
     310: ldc_w         #262                // String xslt
     313: ldc_w         #264                // String application/xslt+xml
     316: invokevirtual #144                // Method org/springframework/boot/web/server/MimeMappings.add:(Ljava/lang/String;Ljava/lang/String;)Ljava/lang/String;
     319: pop
     320: aload_0
     321: ldc_w         #266                // String wasm
     324: ldc_w         #268                // String application/wasm
     327: invokevirtual #144                // Method org/springframework/boot/web/server/MimeMappings.add:(Ljava/lang/String;Ljava/lang/String;)Ljava/lang/String;
     330: pop
     331: aload_0
     332: ldc_w         #270                // String zip
     335: ldc_w         #272                // String application/zip
     338: invokevirtual #144                // Method org/springframework/boot/web/server/MimeMappings.add:(Ljava/lang/String;Ljava/lang/String;)Ljava/lang/String;
     341: pop
     342: aload_0
     343: invokestatic  #274                // Method unmodifiableMappings:(Lorg/springframework/boot/web/server/MimeMappings;)Lorg/springframework/boot/web/server/MimeMappings;
     346: putstatic     #50                 // Field COMMON:Lorg/springframework/boot/web/server/MimeMappings;
     349: return
}
