Compiled from "Ssl.java"
class org.springframework.boot.web.server.Ssl$1 {
  static final int[] $SwitchMap$org$springframework$boot$web$server$Ssl$ClientAuth;

  static {};
    Code:
       0: invokestatic  #1                  // Method org/springframework/boot/web/server/Ssl$ClientAuth.values:()[Lorg/springframework/boot/web/server/Ssl$ClientAuth;
       3: arraylength
       4: newarray       int
       6: putstatic     #7                  // Field $SwitchMap$org$springframework$boot$web$server$Ssl$ClientAuth:[I
       9: getstatic     #7                  // Field $SwitchMap$org$springframework$boot$web$server$Ssl$ClientAuth:[I
      12: getstatic     #13                 // Field org/springframework/boot/web/server/Ssl$ClientAuth.NONE:Lorg/springframework/boot/web/server/Ssl$ClientAuth;
      15: invokevirtual #17                 // Method org/springframework/boot/web/server/Ssl$ClientAuth.ordinal:()I
      18: iconst_1
      19: iastore
      20: goto          24
      23: astore_0
      24: getstatic     #7                  // Field $SwitchMap$org$springframework$boot$web$server$Ssl$ClientAuth:[I
      27: getstatic     #23                 // Field org/springframework/boot/web/server/Ssl$ClientAuth.WANT:Lorg/springframework/boot/web/server/Ssl$ClientAuth;
      30: invokevirtual #17                 // Method org/springframework/boot/web/server/Ssl$ClientAuth.ordinal:()I
      33: iconst_2
      34: iastore
      35: goto          39
      38: astore_0
      39: getstatic     #7                  // Field $SwitchMap$org$springframework$boot$web$server$Ssl$ClientAuth:[I
      42: getstatic     #26                 // Field org/springframework/boot/web/server/Ssl$ClientAuth.NEED:Lorg/springframework/boot/web/server/Ssl$ClientAuth;
      45: invokevirtual #17                 // Method org/springframework/boot/web/server/Ssl$ClientAuth.ordinal:()I
      48: iconst_3
      49: iastore
      50: goto          54
      53: astore_0
      54: return
    Exception table:
       from    to  target type
           9    20    23   Class java/lang/NoSuchFieldError
          24    35    38   Class java/lang/NoSuchFieldError
          39    50    53   Class java/lang/NoSuchFieldError
}
