Compiled from "Ssl.java"
public final class org.springframework.boot.web.server.Ssl$ClientAuth extends java.lang.Enum<org.springframework.boot.web.server.Ssl$ClientAuth> {
  public static final org.springframework.boot.web.server.Ssl$ClientAuth NONE;

  public static final org.springframework.boot.web.server.Ssl$ClientAuth WANT;

  public static final org.springframework.boot.web.server.Ssl$ClientAuth NEED;

  private static final org.springframework.boot.web.server.Ssl$ClientAuth[] $VALUES;

  public static org.springframework.boot.web.server.Ssl$ClientAuth[] values();
    Code:
       0: getstatic     #13                 // Field $VALUES:[Lorg/springframework/boot/web/server/Ssl$ClientAuth;
       3: invokevirtual #17                 // Method "[Lorg/springframework/boot/web/server/Ssl$ClientAuth;".clone:()Ljava/lang/Object;
       6: checkcast     #18                 // class "[Lorg/springframework/boot/web/server/Ssl$ClientAuth;"
       9: areturn

  public static org.springframework.boot.web.server.Ssl$ClientAuth valueOf(java.lang.String);
    Code:
       0: ldc           #1                  // class org/springframework/boot/web/server/Ssl$ClientAuth
       2: aload_0
       3: invokestatic  #22                 // Method java/lang/Enum.valueOf:(Ljava/lang/Class;Ljava/lang/String;)Ljava/lang/Enum;
       6: checkcast     #1                  // class org/springframework/boot/web/server/Ssl$ClientAuth
       9: areturn

  private org.springframework.boot.web.server.Ssl$ClientAuth();
    Code:
       0: aload_0
       1: aload_1
       2: iload_2
       3: invokespecial #28                 // Method java/lang/Enum."<init>":(Ljava/lang/String;I)V
       6: return

  public static <R> R map(org.springframework.boot.web.server.Ssl$ClientAuth, R, R, R);
    Code:
       0: getstatic     #32                 // Field org/springframework/boot/web/server/Ssl$1.$SwitchMap$org$springframework$boot$web$server$Ssl$ClientAuth:[I
       3: aload_0
       4: ifnull        11
       7: aload_0
       8: goto          14
      11: getstatic     #3                  // Field NONE:Lorg/springframework/boot/web/server/Ssl$ClientAuth;
      14: invokevirtual #38                 // Method ordinal:()I
      17: iaload
      18: tableswitch   { // 1 to 3
                     1: 52
                     2: 56
                     3: 60
               default: 44
          }
      44: new           #42                 // class java/lang/IncompatibleClassChangeError
      47: dup
      48: invokespecial #44                 // Method java/lang/IncompatibleClassChangeError."<init>":()V
      51: athrow
      52: aload_1
      53: goto          61
      56: aload_2
      57: goto          61
      60: aload_3
      61: areturn

  private static org.springframework.boot.web.server.Ssl$ClientAuth[] $values();
    Code:
       0: iconst_3
       1: anewarray     #1                  // class org/springframework/boot/web/server/Ssl$ClientAuth
       4: dup
       5: iconst_0
       6: getstatic     #3                  // Field NONE:Lorg/springframework/boot/web/server/Ssl$ClientAuth;
       9: aastore
      10: dup
      11: iconst_1
      12: getstatic     #7                  // Field WANT:Lorg/springframework/boot/web/server/Ssl$ClientAuth;
      15: aastore
      16: dup
      17: iconst_2
      18: getstatic     #10                 // Field NEED:Lorg/springframework/boot/web/server/Ssl$ClientAuth;
      21: aastore
      22: areturn

  static {};
    Code:
       0: new           #1                  // class org/springframework/boot/web/server/Ssl$ClientAuth
       3: dup
       4: ldc           #47                 // String NONE
       6: iconst_0
       7: invokespecial #48                 // Method "<init>":(Ljava/lang/String;I)V
      10: putstatic     #3                  // Field NONE:Lorg/springframework/boot/web/server/Ssl$ClientAuth;
      13: new           #1                  // class org/springframework/boot/web/server/Ssl$ClientAuth
      16: dup
      17: ldc           #49                 // String WANT
      19: iconst_1
      20: invokespecial #48                 // Method "<init>":(Ljava/lang/String;I)V
      23: putstatic     #7                  // Field WANT:Lorg/springframework/boot/web/server/Ssl$ClientAuth;
      26: new           #1                  // class org/springframework/boot/web/server/Ssl$ClientAuth
      29: dup
      30: ldc           #50                 // String NEED
      32: iconst_2
      33: invokespecial #48                 // Method "<init>":(Ljava/lang/String;I)V
      36: putstatic     #10                 // Field NEED:Lorg/springframework/boot/web/server/Ssl$ClientAuth;
      39: invokestatic  #51                 // Method $values:()[Lorg/springframework/boot/web/server/Ssl$ClientAuth;
      42: putstatic     #13                 // Field $VALUES:[Lorg/springframework/boot/web/server/Ssl$ClientAuth;
      45: return
}
