Compiled from "Ssl.java"
public class org.springframework.boot.web.server.Ssl {
  private boolean enabled;

  private java.lang.String bundle;

  private org.springframework.boot.web.server.Ssl$ClientAuth clientAuth;

  private java.lang.String[] ciphers;

  private java.lang.String[] enabledProtocols;

  private java.lang.String keyAlias;

  private java.lang.String keyPassword;

  private java.lang.String keyStore;

  private java.lang.String keyStorePassword;

  private java.lang.String keyStoreType;

  private java.lang.String keyStoreProvider;

  private java.lang.String trustStore;

  private java.lang.String trustStorePassword;

  private java.lang.String trustStoreType;

  private java.lang.String trustStoreProvider;

  private java.lang.String certificate;

  private java.lang.String certificatePrivateKey;

  private java.lang.String trustCertificate;

  private java.lang.String trustCertificatePrivateKey;

  private java.lang.String protocol;

  public org.springframework.boot.web.server.Ssl();
    Code:
       0: aload_0
       1: invokespecial #1                  // Method java/lang/Object."<init>":()V
       4: aload_0
       5: iconst_1
       6: putfield      #7                  // Field enabled:Z
       9: aload_0
      10: ldc           #13                 // String TLS
      12: putfield      #15                 // Field protocol:Ljava/lang/String;
      15: return

  public boolean isEnabled();
    Code:
       0: aload_0
       1: getfield      #7                  // Field enabled:Z
       4: ireturn

  public void setEnabled(boolean);
    Code:
       0: aload_0
       1: iload_1
       2: putfield      #7                  // Field enabled:Z
       5: return

  public java.lang.String getBundle();
    Code:
       0: aload_0
       1: getfield      #19                 // Field bundle:Ljava/lang/String;
       4: areturn

  public void setBundle(java.lang.String);
    Code:
       0: aload_0
       1: aload_1
       2: putfield      #19                 // Field bundle:Ljava/lang/String;
       5: return

  public org.springframework.boot.web.server.Ssl$ClientAuth getClientAuth();
    Code:
       0: aload_0
       1: getfield      #22                 // Field clientAuth:Lorg/springframework/boot/web/server/Ssl$ClientAuth;
       4: areturn

  public void setClientAuth(org.springframework.boot.web.server.Ssl$ClientAuth);
    Code:
       0: aload_0
       1: aload_1
       2: putfield      #22                 // Field clientAuth:Lorg/springframework/boot/web/server/Ssl$ClientAuth;
       5: return

  public java.lang.String[] getCiphers();
    Code:
       0: aload_0
       1: getfield      #26                 // Field ciphers:[Ljava/lang/String;
       4: areturn

  public void setCiphers(java.lang.String[]);
    Code:
       0: aload_0
       1: aload_1
       2: putfield      #26                 // Field ciphers:[Ljava/lang/String;
       5: return

  public java.lang.String[] getEnabledProtocols();
    Code:
       0: aload_0
       1: getfield      #30                 // Field enabledProtocols:[Ljava/lang/String;
       4: areturn

  public void setEnabledProtocols(java.lang.String[]);
    Code:
       0: aload_0
       1: aload_1
       2: putfield      #30                 // Field enabledProtocols:[Ljava/lang/String;
       5: return

  public java.lang.String getKeyAlias();
    Code:
       0: aload_0
       1: getfield      #33                 // Field keyAlias:Ljava/lang/String;
       4: areturn

  public void setKeyAlias(java.lang.String);
    Code:
       0: aload_0
       1: aload_1
       2: putfield      #33                 // Field keyAlias:Ljava/lang/String;
       5: return

  public java.lang.String getKeyPassword();
    Code:
       0: aload_0
       1: getfield      #36                 // Field keyPassword:Ljava/lang/String;
       4: areturn

  public void setKeyPassword(java.lang.String);
    Code:
       0: aload_0
       1: aload_1
       2: putfield      #36                 // Field keyPassword:Ljava/lang/String;
       5: return

  public java.lang.String getKeyStore();
    Code:
       0: aload_0
       1: getfield      #39                 // Field keyStore:Ljava/lang/String;
       4: areturn

  public void setKeyStore(java.lang.String);
    Code:
       0: aload_0
       1: aload_1
       2: putfield      #39                 // Field keyStore:Ljava/lang/String;
       5: return

  public java.lang.String getKeyStorePassword();
    Code:
       0: aload_0
       1: getfield      #42                 // Field keyStorePassword:Ljava/lang/String;
       4: areturn

  public void setKeyStorePassword(java.lang.String);
    Code:
       0: aload_0
       1: aload_1
       2: putfield      #42                 // Field keyStorePassword:Ljava/lang/String;
       5: return

  public java.lang.String getKeyStoreType();
    Code:
       0: aload_0
       1: getfield      #45                 // Field keyStoreType:Ljava/lang/String;
       4: areturn

  public void setKeyStoreType(java.lang.String);
    Code:
       0: aload_0
       1: aload_1
       2: putfield      #45                 // Field keyStoreType:Ljava/lang/String;
       5: return

  public java.lang.String getKeyStoreProvider();
    Code:
       0: aload_0
       1: getfield      #48                 // Field keyStoreProvider:Ljava/lang/String;
       4: areturn

  public void setKeyStoreProvider(java.lang.String);
    Code:
       0: aload_0
       1: aload_1
       2: putfield      #48                 // Field keyStoreProvider:Ljava/lang/String;
       5: return

  public java.lang.String getTrustStore();
    Code:
       0: aload_0
       1: getfield      #51                 // Field trustStore:Ljava/lang/String;
       4: areturn

  public void setTrustStore(java.lang.String);
    Code:
       0: aload_0
       1: aload_1
       2: putfield      #51                 // Field trustStore:Ljava/lang/String;
       5: return

  public java.lang.String getTrustStorePassword();
    Code:
       0: aload_0
       1: getfield      #54                 // Field trustStorePassword:Ljava/lang/String;
       4: areturn

  public void setTrustStorePassword(java.lang.String);
    Code:
       0: aload_0
       1: aload_1
       2: putfield      #54                 // Field trustStorePassword:Ljava/lang/String;
       5: return

  public java.lang.String getTrustStoreType();
    Code:
       0: aload_0
       1: getfield      #57                 // Field trustStoreType:Ljava/lang/String;
       4: areturn

  public void setTrustStoreType(java.lang.String);
    Code:
       0: aload_0
       1: aload_1
       2: putfield      #57                 // Field trustStoreType:Ljava/lang/String;
       5: return

  public java.lang.String getTrustStoreProvider();
    Code:
       0: aload_0
       1: getfield      #60                 // Field trustStoreProvider:Ljava/lang/String;
       4: areturn

  public void setTrustStoreProvider(java.lang.String);
    Code:
       0: aload_0
       1: aload_1
       2: putfield      #60                 // Field trustStoreProvider:Ljava/lang/String;
       5: return

  public java.lang.String getCertificate();
    Code:
       0: aload_0
       1: getfield      #63                 // Field certificate:Ljava/lang/String;
       4: areturn

  public void setCertificate(java.lang.String);
    Code:
       0: aload_0
       1: aload_1
       2: putfield      #63                 // Field certificate:Ljava/lang/String;
       5: return

  public java.lang.String getCertificatePrivateKey();
    Code:
       0: aload_0
       1: getfield      #66                 // Field certificatePrivateKey:Ljava/lang/String;
       4: areturn

  public void setCertificatePrivateKey(java.lang.String);
    Code:
       0: aload_0
       1: aload_1
       2: putfield      #66                 // Field certificatePrivateKey:Ljava/lang/String;
       5: return

  public java.lang.String getTrustCertificate();
    Code:
       0: aload_0
       1: getfield      #69                 // Field trustCertificate:Ljava/lang/String;
       4: areturn

  public void setTrustCertificate(java.lang.String);
    Code:
       0: aload_0
       1: aload_1
       2: putfield      #69                 // Field trustCertificate:Ljava/lang/String;
       5: return

  public java.lang.String getTrustCertificatePrivateKey();
    Code:
       0: aload_0
       1: getfield      #72                 // Field trustCertificatePrivateKey:Ljava/lang/String;
       4: areturn

  public void setTrustCertificatePrivateKey(java.lang.String);
    Code:
       0: aload_0
       1: aload_1
       2: putfield      #72                 // Field trustCertificatePrivateKey:Ljava/lang/String;
       5: return

  public java.lang.String getProtocol();
    Code:
       0: aload_0
       1: getfield      #15                 // Field protocol:Ljava/lang/String;
       4: areturn

  public void setProtocol(java.lang.String);
    Code:
       0: aload_0
       1: aload_1
       2: putfield      #15                 // Field protocol:Ljava/lang/String;
       5: return

  public static boolean isEnabled(org.springframework.boot.web.server.Ssl);
    Code:
       0: aload_0
       1: ifnull        15
       4: aload_0
       5: invokevirtual #75                 // Method isEnabled:()Z
       8: ifeq          15
      11: iconst_1
      12: goto          16
      15: iconst_0
      16: ireturn

  public static org.springframework.boot.web.server.Ssl forBundle(java.lang.String);
    Code:
       0: new           #8                  // class org/springframework/boot/web/server/Ssl
       3: dup
       4: invokespecial #79                 // Method "<init>":()V
       7: astore_1
       8: aload_1
       9: aload_0
      10: invokevirtual #80                 // Method setBundle:(Ljava/lang/String;)V
      13: aload_1
      14: areturn
}
