Compiled from "WebServerSslBundle.java"
class org.springframework.boot.web.server.WebServerSslBundle$SslStoreProviderBundleAdapter implements org.springframework.boot.ssl.SslStoreBundle {
  private final org.springframework.boot.web.server.SslStoreProvider sslStoreProvider;

  org.springframework.boot.web.server.WebServerSslBundle$SslStoreProviderBundleAdapter(org.springframework.boot.web.server.SslStoreProvider);
    Code:
       0: aload_0
       1: invokespecial #1                  // Method java/lang/Object."<init>":()V
       4: aload_0
       5: aload_1
       6: putfield      #7                  // Field sslStoreProvider:Lorg/springframework/boot/web/server/SslStoreProvider;
       9: return

  public java.security.KeyStore getKeyStore();
    Code:
       0: aload_0
       1: getfield      #7                  // Field sslStoreProvider:Lorg/springframework/boot/web/server/SslStoreProvider;
       4: dup
       5: invokestatic  #13                 // Method java/util/Objects.requireNonNull:(Ljava/lang/Object;)Ljava/lang/Object;
       8: pop
       9: invokedynamic #19,  0             // InvokeDynamic #0:getWithException:(Lorg/springframework/boot/web/server/SslStoreProvider;)Lorg/springframework/util/function/ThrowingSupplier;
      14: invokestatic  #23                 // InterfaceMethod org/springframework/util/function/ThrowingSupplier.of:(Lorg/springframework/util/function/ThrowingSupplier;)Lorg/springframework/util/function/ThrowingSupplier;
      17: invokeinterface #29,  1           // InterfaceMethod org/springframework/util/function/ThrowingSupplier.get:()Ljava/lang/Object;
      22: checkcast     #33                 // class java/security/KeyStore
      25: areturn

  public java.lang.String getKeyStorePassword();
    Code:
       0: aconst_null
       1: areturn

  public java.security.KeyStore getTrustStore();
    Code:
       0: aload_0
       1: getfield      #7                  // Field sslStoreProvider:Lorg/springframework/boot/web/server/SslStoreProvider;
       4: dup
       5: invokestatic  #13                 // Method java/util/Objects.requireNonNull:(Ljava/lang/Object;)Ljava/lang/Object;
       8: pop
       9: invokedynamic #35,  0             // InvokeDynamic #1:getWithException:(Lorg/springframework/boot/web/server/SslStoreProvider;)Lorg/springframework/util/function/ThrowingSupplier;
      14: invokestatic  #23                 // InterfaceMethod org/springframework/util/function/ThrowingSupplier.of:(Lorg/springframework/util/function/ThrowingSupplier;)Lorg/springframework/util/function/ThrowingSupplier;
      17: invokeinterface #29,  1           // InterfaceMethod org/springframework/util/function/ThrowingSupplier.get:()Ljava/lang/Object;
      22: checkcast     #33                 // class java/security/KeyStore
      25: areturn
}
