Compiled from "WebServerFactoryCustomizerBeanPostProcessor.java"
public class org.springframework.boot.web.server.WebServerFactoryCustomizerBeanPostProcessor implements org.springframework.beans.factory.config.BeanPostProcessor,org.springframework.beans.factory.BeanFactoryAware {
  private org.springframework.beans.factory.ListableBeanFactory beanFactory;

  private java.util.List<org.springframework.boot.web.server.WebServerFactoryCustomizer<?>> customizers;

  public org.springframework.boot.web.server.WebServerFactoryCustomizerBeanPostProcessor();
    Code:
       0: aload_0
       1: invokespecial #1                  // Method java/lang/Object."<init>":()V
       4: return

  public void setBeanFactory(org.springframework.beans.factory.BeanFactory);
    Code:
       0: ldc           #7                  // class org/springframework/beans/factory/ListableBeanFactory
       2: aload_1
       3: ldc           #9                  // String WebServerCustomizerBeanPostProcessor can only be used with a ListableBeanFactory
       5: invokestatic  #11                 // Method org/springframework/util/Assert.isInstanceOf:(Ljava/lang/Class;Ljava/lang/Object;Ljava/lang/String;)V
       8: aload_0
       9: aload_1
      10: checkcast     #7                  // class org/springframework/beans/factory/ListableBeanFactory
      13: putfield      #17                 // Field beanFactory:Lorg/springframework/beans/factory/ListableBeanFactory;
      16: return

  public java.lang.Object postProcessBeforeInitialization(java.lang.Object, java.lang.String) throws org.springframework.beans.BeansException;
    Code:
       0: aload_1
       1: instanceof    #23                 // class org/springframework/boot/web/server/WebServerFactory
       4: ifeq          17
       7: aload_1
       8: checkcast     #23                 // class org/springframework/boot/web/server/WebServerFactory
      11: astore_3
      12: aload_0
      13: aload_3
      14: invokevirtual #25                 // Method postProcessBeforeInitialization:(Lorg/springframework/boot/web/server/WebServerFactory;)V
      17: aload_1
      18: areturn

  public java.lang.Object postProcessAfterInitialization(java.lang.Object, java.lang.String) throws org.springframework.beans.BeansException;
    Code:
       0: aload_1
       1: areturn

  private void postProcessBeforeInitialization(org.springframework.boot.web.server.WebServerFactory);
    Code:
       0: ldc           #29                 // class org/springframework/boot/web/server/WebServerFactoryCustomizer
       2: aload_0
       3: invokevirtual #31                 // Method getCustomizers:()Ljava/util/Collection;
       6: aload_1
       7: iconst_0
       8: anewarray     #2                  // class java/lang/Object
      11: invokestatic  #35                 // Method org/springframework/boot/util/LambdaSafe.callbacks:(Ljava/lang/Class;Ljava/util/Collection;Ljava/lang/Object;[Ljava/lang/Object;)Lorg/springframework/boot/util/LambdaSafe$Callbacks;
      14: ldc           #18                 // class org/springframework/boot/web/server/WebServerFactoryCustomizerBeanPostProcessor
      16: invokevirtual #41                 // Method org/springframework/boot/util/LambdaSafe$Callbacks.withLogger:(Ljava/lang/Class;)Lorg/springframework/boot/util/LambdaSafe$LambdaSafeCallback;
      19: checkcast     #42                 // class org/springframework/boot/util/LambdaSafe$Callbacks
      22: aload_1
      23: invokedynamic #47,  0             // InvokeDynamic #0:accept:(Lorg/springframework/boot/web/server/WebServerFactory;)Ljava/util/function/Consumer;
      28: invokevirtual #51                 // Method org/springframework/boot/util/LambdaSafe$Callbacks.invoke:(Ljava/util/function/Consumer;)V
      31: return

  private java.util.Collection<org.springframework.boot.web.server.WebServerFactoryCustomizer<?>> getCustomizers();
    Code:
       0: aload_0
       1: getfield      #55                 // Field customizers:Ljava/util/List;
       4: ifnonnull     45
       7: aload_0
       8: new           #59                 // class java/util/ArrayList
      11: dup
      12: aload_0
      13: invokevirtual #61                 // Method getWebServerFactoryCustomizerBeans:()Ljava/util/Collection;
      16: invokespecial #64                 // Method java/util/ArrayList."<init>":(Ljava/util/Collection;)V
      19: putfield      #55                 // Field customizers:Ljava/util/List;
      22: aload_0
      23: getfield      #55                 // Field customizers:Ljava/util/List;
      26: getstatic     #67                 // Field org/springframework/core/annotation/AnnotationAwareOrderComparator.INSTANCE:Lorg/springframework/core/annotation/AnnotationAwareOrderComparator;
      29: invokeinterface #73,  2           // InterfaceMethod java/util/List.sort:(Ljava/util/Comparator;)V
      34: aload_0
      35: aload_0
      36: getfield      #55                 // Field customizers:Ljava/util/List;
      39: invokestatic  #79                 // Method java/util/Collections.unmodifiableList:(Ljava/util/List;)Ljava/util/List;
      42: putfield      #55                 // Field customizers:Ljava/util/List;
      45: aload_0
      46: getfield      #55                 // Field customizers:Ljava/util/List;
      49: areturn

  private java.util.Collection<org.springframework.boot.web.server.WebServerFactoryCustomizer<?>> getWebServerFactoryCustomizerBeans();
    Code:
       0: aload_0
       1: getfield      #17                 // Field beanFactory:Lorg/springframework/beans/factory/ListableBeanFactory;
       4: ldc           #29                 // class org/springframework/boot/web/server/WebServerFactoryCustomizer
       6: iconst_0
       7: iconst_0
       8: invokeinterface #85,  4           // InterfaceMethod org/springframework/beans/factory/ListableBeanFactory.getBeansOfType:(Ljava/lang/Class;ZZ)Ljava/util/Map;
      13: invokeinterface #89,  1           // InterfaceMethod java/util/Map.values:()Ljava/util/Collection;
      18: areturn

  private static void lambda$postProcessBeforeInitialization$0(org.springframework.boot.web.server.WebServerFactory, org.springframework.boot.web.server.WebServerFactoryCustomizer);
    Code:
       0: aload_1
       1: aload_0
       2: invokeinterface #94,  2           // InterfaceMethod org/springframework/boot/web/server/WebServerFactoryCustomizer.customize:(Lorg/springframework/boot/web/server/WebServerFactory;)V
       7: return
}
