Compiled from "WebServerSslBundle.java"
public final class org.springframework.boot.web.server.WebServerSslBundle implements org.springframework.boot.ssl.SslBundle {
  private final org.springframework.boot.ssl.SslStoreBundle stores;

  private final org.springframework.boot.ssl.SslBundleKey key;

  private final org.springframework.boot.ssl.SslOptions options;

  private final java.lang.String protocol;

  private final org.springframework.boot.ssl.SslManagerBundle managers;

  private org.springframework.boot.web.server.WebServerSslBundle(org.springframework.boot.ssl.SslStoreBundle, java.lang.String, org.springframework.boot.web.server.Ssl);
    Code:
       0: aload_0
       1: invokespecial #1                  // Method java/lang/Object."<init>":()V
       4: aload_0
       5: aload_1
       6: putfield      #7                  // Field stores:Lorg/springframework/boot/ssl/SslStoreBundle;
       9: aload_0
      10: aload_2
      11: aload_3
      12: invokevirtual #13                 // Method org/springframework/boot/web/server/Ssl.getKeyAlias:()Ljava/lang/String;
      15: invokestatic  #19                 // InterfaceMethod org/springframework/boot/ssl/SslBundleKey.of:(Ljava/lang/String;Ljava/lang/String;)Lorg/springframework/boot/ssl/SslBundleKey;
      18: putfield      #25                 // Field key:Lorg/springframework/boot/ssl/SslBundleKey;
      21: aload_0
      22: aload_3
      23: invokevirtual #29                 // Method org/springframework/boot/web/server/Ssl.getProtocol:()Ljava/lang/String;
      26: putfield      #32                 // Field protocol:Ljava/lang/String;
      29: aload_0
      30: aload_3
      31: invokevirtual #36                 // Method org/springframework/boot/web/server/Ssl.getCiphers:()[Ljava/lang/String;
      34: aload_3
      35: invokevirtual #40                 // Method org/springframework/boot/web/server/Ssl.getEnabledProtocols:()[Ljava/lang/String;
      38: invokestatic  #43                 // InterfaceMethod org/springframework/boot/ssl/SslOptions.of:([Ljava/lang/String;[Ljava/lang/String;)Lorg/springframework/boot/ssl/SslOptions;
      41: putfield      #48                 // Field options:Lorg/springframework/boot/ssl/SslOptions;
      44: aload_0
      45: aload_0
      46: getfield      #7                  // Field stores:Lorg/springframework/boot/ssl/SslStoreBundle;
      49: aload_0
      50: getfield      #25                 // Field key:Lorg/springframework/boot/ssl/SslBundleKey;
      53: invokestatic  #52                 // InterfaceMethod org/springframework/boot/ssl/SslManagerBundle.from:(Lorg/springframework/boot/ssl/SslStoreBundle;Lorg/springframework/boot/ssl/SslBundleKey;)Lorg/springframework/boot/ssl/SslManagerBundle;
      56: putfield      #58                 // Field managers:Lorg/springframework/boot/ssl/SslManagerBundle;
      59: return

  private static org.springframework.boot.ssl.SslStoreBundle createPemStoreBundle(org.springframework.boot.web.server.Ssl);
    Code:
       0: new           #62                 // class org/springframework/boot/ssl/pem/PemSslStoreDetails
       3: dup
       4: aload_0
       5: invokevirtual #64                 // Method org/springframework/boot/web/server/Ssl.getKeyStoreType:()Ljava/lang/String;
       8: aload_0
       9: invokevirtual #67                 // Method org/springframework/boot/web/server/Ssl.getCertificate:()Ljava/lang/String;
      12: aload_0
      13: invokevirtual #70                 // Method org/springframework/boot/web/server/Ssl.getCertificatePrivateKey:()Ljava/lang/String;
      16: invokespecial #73                 // Method org/springframework/boot/ssl/pem/PemSslStoreDetails."<init>":(Ljava/lang/String;Ljava/lang/String;Ljava/lang/String;)V
      19: astore_1
      20: new           #62                 // class org/springframework/boot/ssl/pem/PemSslStoreDetails
      23: dup
      24: aload_0
      25: invokevirtual #76                 // Method org/springframework/boot/web/server/Ssl.getTrustStoreType:()Ljava/lang/String;
      28: aload_0
      29: invokevirtual #79                 // Method org/springframework/boot/web/server/Ssl.getTrustCertificate:()Ljava/lang/String;
      32: aload_0
      33: invokevirtual #82                 // Method org/springframework/boot/web/server/Ssl.getTrustCertificatePrivateKey:()Ljava/lang/String;
      36: invokespecial #73                 // Method org/springframework/boot/ssl/pem/PemSslStoreDetails."<init>":(Ljava/lang/String;Ljava/lang/String;Ljava/lang/String;)V
      39: astore_2
      40: new           #85                 // class org/springframework/boot/ssl/pem/PemSslStoreBundle
      43: dup
      44: aload_1
      45: aload_2
      46: aload_0
      47: invokevirtual #13                 // Method org/springframework/boot/web/server/Ssl.getKeyAlias:()Ljava/lang/String;
      50: invokespecial #87                 // Method org/springframework/boot/ssl/pem/PemSslStoreBundle."<init>":(Lorg/springframework/boot/ssl/pem/PemSslStoreDetails;Lorg/springframework/boot/ssl/pem/PemSslStoreDetails;Ljava/lang/String;)V
      53: areturn

  private static org.springframework.boot.ssl.SslStoreBundle createJksStoreBundle(org.springframework.boot.web.server.Ssl);
    Code:
       0: new           #90                 // class org/springframework/boot/ssl/jks/JksSslStoreDetails
       3: dup
       4: aload_0
       5: invokevirtual #64                 // Method org/springframework/boot/web/server/Ssl.getKeyStoreType:()Ljava/lang/String;
       8: aload_0
       9: invokevirtual #92                 // Method org/springframework/boot/web/server/Ssl.getKeyStoreProvider:()Ljava/lang/String;
      12: aload_0
      13: invokevirtual #95                 // Method org/springframework/boot/web/server/Ssl.getKeyStore:()Ljava/lang/String;
      16: aload_0
      17: invokevirtual #98                 // Method org/springframework/boot/web/server/Ssl.getKeyStorePassword:()Ljava/lang/String;
      20: invokespecial #101                // Method org/springframework/boot/ssl/jks/JksSslStoreDetails."<init>":(Ljava/lang/String;Ljava/lang/String;Ljava/lang/String;Ljava/lang/String;)V
      23: astore_1
      24: new           #90                 // class org/springframework/boot/ssl/jks/JksSslStoreDetails
      27: dup
      28: aload_0
      29: invokevirtual #76                 // Method org/springframework/boot/web/server/Ssl.getTrustStoreType:()Ljava/lang/String;
      32: aload_0
      33: invokevirtual #104                // Method org/springframework/boot/web/server/Ssl.getTrustStoreProvider:()Ljava/lang/String;
      36: aload_0
      37: invokevirtual #107                // Method org/springframework/boot/web/server/Ssl.getTrustStore:()Ljava/lang/String;
      40: aload_0
      41: invokevirtual #110                // Method org/springframework/boot/web/server/Ssl.getTrustStorePassword:()Ljava/lang/String;
      44: invokespecial #101                // Method org/springframework/boot/ssl/jks/JksSslStoreDetails."<init>":(Ljava/lang/String;Ljava/lang/String;Ljava/lang/String;Ljava/lang/String;)V
      47: astore_2
      48: new           #113                // class org/springframework/boot/ssl/jks/JksSslStoreBundle
      51: dup
      52: aload_1
      53: aload_2
      54: invokespecial #115                // Method org/springframework/boot/ssl/jks/JksSslStoreBundle."<init>":(Lorg/springframework/boot/ssl/jks/JksSslStoreDetails;Lorg/springframework/boot/ssl/jks/JksSslStoreDetails;)V
      57: areturn

  public org.springframework.boot.ssl.SslStoreBundle getStores();
    Code:
       0: aload_0
       1: getfield      #7                  // Field stores:Lorg/springframework/boot/ssl/SslStoreBundle;
       4: areturn

  public org.springframework.boot.ssl.SslBundleKey getKey();
    Code:
       0: aload_0
       1: getfield      #25                 // Field key:Lorg/springframework/boot/ssl/SslBundleKey;
       4: areturn

  public org.springframework.boot.ssl.SslOptions getOptions();
    Code:
       0: aload_0
       1: getfield      #48                 // Field options:Lorg/springframework/boot/ssl/SslOptions;
       4: areturn

  public java.lang.String getProtocol();
    Code:
       0: aload_0
       1: getfield      #32                 // Field protocol:Ljava/lang/String;
       4: areturn

  public org.springframework.boot.ssl.SslManagerBundle getManagers();
    Code:
       0: aload_0
       1: getfield      #58                 // Field managers:Lorg/springframework/boot/ssl/SslManagerBundle;
       4: areturn

  public static org.springframework.boot.ssl.SslBundle get(org.springframework.boot.web.server.Ssl) throws org.springframework.boot.ssl.NoSuchSslBundleException;
    Code:
       0: aload_0
       1: aconst_null
       2: aconst_null
       3: invokestatic  #118                // Method get:(Lorg/springframework/boot/web/server/Ssl;Lorg/springframework/boot/ssl/SslBundles;Lorg/springframework/boot/web/server/SslStoreProvider;)Lorg/springframework/boot/ssl/SslBundle;
       6: areturn

  public static org.springframework.boot.ssl.SslBundle get(org.springframework.boot.web.server.Ssl, org.springframework.boot.ssl.SslBundles) throws org.springframework.boot.ssl.NoSuchSslBundleException;
    Code:
       0: aload_0
       1: aload_1
       2: aconst_null
       3: invokestatic  #118                // Method get:(Lorg/springframework/boot/web/server/Ssl;Lorg/springframework/boot/ssl/SslBundles;Lorg/springframework/boot/web/server/SslStoreProvider;)Lorg/springframework/boot/ssl/SslBundle;
       6: areturn

  public static org.springframework.boot.ssl.SslBundle get(org.springframework.boot.web.server.Ssl, org.springframework.boot.ssl.SslBundles, org.springframework.boot.web.server.SslStoreProvider);
    Code:
       0: aload_0
       1: invokestatic  #122                // Method org/springframework/boot/web/server/Ssl.isEnabled:(Lorg/springframework/boot/web/server/Ssl;)Z
       4: ldc           #126                // String SSL is not enabled
       6: invokestatic  #128                // Method org/springframework/util/Assert.state:(ZLjava/lang/String;)V
       9: aload_2
      10: ifnull        22
      13: aload_2
      14: invokeinterface #134,  1          // InterfaceMethod org/springframework/boot/web/server/SslStoreProvider.getKeyPassword:()Ljava/lang/String;
      19: goto          23
      22: aconst_null
      23: astore_3
      24: aload_3
      25: ifnull        32
      28: aload_3
      29: goto          36
      32: aload_0
      33: invokevirtual #139                // Method org/springframework/boot/web/server/Ssl.getKeyPassword:()Ljava/lang/String;
      36: astore_3
      37: aload_2
      38: ifnull        63
      41: new           #140                // class org/springframework/boot/web/server/WebServerSslBundle$SslStoreProviderBundleAdapter
      44: dup
      45: aload_2
      46: invokespecial #142                // Method org/springframework/boot/web/server/WebServerSslBundle$SslStoreProviderBundleAdapter."<init>":(Lorg/springframework/boot/web/server/SslStoreProvider;)V
      49: astore        4
      51: new           #8                  // class org/springframework/boot/web/server/WebServerSslBundle
      54: dup
      55: aload         4
      57: aload_3
      58: aload_0
      59: invokespecial #145                // Method "<init>":(Lorg/springframework/boot/ssl/SslStoreBundle;Ljava/lang/String;Lorg/springframework/boot/web/server/Ssl;)V
      62: areturn
      63: aload_0
      64: invokevirtual #148                // Method org/springframework/boot/web/server/Ssl.getBundle:()Ljava/lang/String;
      67: astore        4
      69: aload         4
      71: invokestatic  #151                // Method org/springframework/util/StringUtils.hasText:(Ljava/lang/String;)Z
      74: ifeq          105
      77: aload_1
      78: ifnull        85
      81: iconst_1
      82: goto          86
      85: iconst_0
      86: aload         4
      88: invokedynamic #157,  0            // InvokeDynamic #0:get:(Ljava/lang/String;)Ljava/util/function/Supplier;
      93: invokestatic  #160                // Method org/springframework/util/Assert.state:(ZLjava/util/function/Supplier;)V
      96: aload_1
      97: aload         4
      99: invokeinterface #163,  2          // InterfaceMethod org/springframework/boot/ssl/SslBundles.getBundle:(Ljava/lang/String;)Lorg/springframework/boot/ssl/SslBundle;
     104: areturn
     105: aload_0
     106: invokestatic  #168                // Method createStoreBundle:(Lorg/springframework/boot/web/server/Ssl;)Lorg/springframework/boot/ssl/SslStoreBundle;
     109: astore        5
     111: new           #8                  // class org/springframework/boot/web/server/WebServerSslBundle
     114: dup
     115: aload         5
     117: aload_3
     118: aload_0
     119: invokespecial #145                // Method "<init>":(Lorg/springframework/boot/ssl/SslStoreBundle;Ljava/lang/String;Lorg/springframework/boot/web/server/Ssl;)V
     122: areturn

  private static org.springframework.boot.ssl.SslStoreBundle createStoreBundle(org.springframework.boot.web.server.Ssl);
    Code:
       0: aload_0
       1: invokestatic  #172                // Method hasCertificateProperties:(Lorg/springframework/boot/web/server/Ssl;)Z
       4: ifeq          12
       7: aload_0
       8: invokestatic  #175                // Method createPemStoreBundle:(Lorg/springframework/boot/web/server/Ssl;)Lorg/springframework/boot/ssl/SslStoreBundle;
      11: areturn
      12: aload_0
      13: invokestatic  #178                // Method hasJavaKeyStoreProperties:(Lorg/springframework/boot/web/server/Ssl;)Z
      16: ifeq          24
      19: aload_0
      20: invokestatic  #181                // Method createJksStoreBundle:(Lorg/springframework/boot/web/server/Ssl;)Lorg/springframework/boot/ssl/SslStoreBundle;
      23: areturn
      24: new           #184                // class java/lang/IllegalStateException
      27: dup
      28: ldc           #186                // String SSL is enabled but no trust material is configured
      30: invokespecial #188                // Method java/lang/IllegalStateException."<init>":(Ljava/lang/String;)V
      33: athrow

  static org.springframework.boot.ssl.SslBundle createCertificateFileSslStoreProviderDelegate(org.springframework.boot.web.server.Ssl);
    Code:
       0: aload_0
       1: invokestatic  #172                // Method hasCertificateProperties:(Lorg/springframework/boot/web/server/Ssl;)Z
       4: ifne          9
       7: aconst_null
       8: areturn
       9: aload_0
      10: invokestatic  #175                // Method createPemStoreBundle:(Lorg/springframework/boot/web/server/Ssl;)Lorg/springframework/boot/ssl/SslStoreBundle;
      13: astore_1
      14: new           #8                  // class org/springframework/boot/web/server/WebServerSslBundle
      17: dup
      18: aload_1
      19: aload_0
      20: invokevirtual #139                // Method org/springframework/boot/web/server/Ssl.getKeyPassword:()Ljava/lang/String;
      23: aload_0
      24: invokespecial #145                // Method "<init>":(Lorg/springframework/boot/ssl/SslStoreBundle;Ljava/lang/String;Lorg/springframework/boot/web/server/Ssl;)V
      27: areturn

  private static boolean hasCertificateProperties(org.springframework.boot.web.server.Ssl);
    Code:
       0: aload_0
       1: invokestatic  #122                // Method org/springframework/boot/web/server/Ssl.isEnabled:(Lorg/springframework/boot/web/server/Ssl;)Z
       4: ifeq          25
       7: aload_0
       8: invokevirtual #67                 // Method org/springframework/boot/web/server/Ssl.getCertificate:()Ljava/lang/String;
      11: ifnull        25
      14: aload_0
      15: invokevirtual #70                 // Method org/springframework/boot/web/server/Ssl.getCertificatePrivateKey:()Ljava/lang/String;
      18: ifnull        25
      21: iconst_1
      22: goto          26
      25: iconst_0
      26: ireturn

  private static boolean hasJavaKeyStoreProperties(org.springframework.boot.web.server.Ssl);
    Code:
       0: aload_0
       1: invokestatic  #122                // Method org/springframework/boot/web/server/Ssl.isEnabled:(Lorg/springframework/boot/web/server/Ssl;)Z
       4: ifeq          14
       7: aload_0
       8: invokevirtual #95                 // Method org/springframework/boot/web/server/Ssl.getKeyStore:()Ljava/lang/String;
      11: ifnonnull     33
      14: aload_0
      15: invokevirtual #64                 // Method org/springframework/boot/web/server/Ssl.getKeyStoreType:()Ljava/lang/String;
      18: ifnull        37
      21: aload_0
      22: invokevirtual #64                 // Method org/springframework/boot/web/server/Ssl.getKeyStoreType:()Ljava/lang/String;
      25: ldc           #191                // String PKCS11
      27: invokevirtual #193                // Method java/lang/String.equals:(Ljava/lang/Object;)Z
      30: ifeq          37
      33: iconst_1
      34: goto          38
      37: iconst_0
      38: ireturn

  private static java.lang.String lambda$get$0(java.lang.String);
    Code:
       0: ldc           #199                // String SSL bundle \'%s\' was requested but no SslBundles instance was provided
       2: iconst_1
       3: anewarray     #2                  // class java/lang/Object
       6: dup
       7: iconst_0
       8: aload_0
       9: aastore
      10: invokevirtual #201                // Method java/lang/String.formatted:([Ljava/lang/Object;)Ljava/lang/String;
      13: areturn
}
