Compiled from "BasicQueueDisposable.java"
public abstract class io.reactivex.rxjava3.internal.observers.BasicQueueDisposable<T> implements io.reactivex.rxjava3.operators.QueueDisposable<T> {
  public io.reactivex.rxjava3.internal.observers.BasicQueueDisposable();
    Code:
       0: aload_0
       1: invokespecial #1                  // Method java/lang/Object."<init>":()V
       4: return

  public final boolean offer(T);
    Code:
       0: new           #2                  // class java/lang/UnsupportedOperationException
       3: dup
       4: ldc           #3                  // String Should not be called
       6: invokespecial #4                  // Method java/lang/UnsupportedOperationException."<init>":(Ljava/lang/String;)V
       9: athrow

  public final boolean offer(T, T);
    Code:
       0: new           #2                  // class java/lang/UnsupportedOperationException
       3: dup
       4: ldc           #3                  // String Should not be called
       6: invokespecial #4                  // Method java/lang/UnsupportedOperationException."<init>":(Ljava/lang/String;)V
       9: athrow
}
