Compiled from "BlockingFirstObserver.java"
public final class io.reactivex.rxjava3.internal.observers.BlockingFirstObserver<T> extends io.reactivex.rxjava3.internal.observers.BlockingBaseObserver<T> {
  public io.reactivex.rxjava3.internal.observers.BlockingFirstObserver();
    Code:
       0: aload_0
       1: invokespecial #1                  // Method io/reactivex/rxjava3/internal/observers/BlockingBaseObserver."<init>":()V
       4: return

  public void onNext(T);
    Code:
       0: aload_0
       1: getfield      #2                  // Field value:Ljava/lang/Object;
       4: ifnonnull     25
       7: aload_0
       8: aload_1
       9: putfield      #2                  // Field value:Ljava/lang/Object;
      12: aload_0
      13: getfield      #3                  // Field upstream:Lio/reactivex/rxjava3/disposables/Disposable;
      16: invokeinterface #4,  1            // InterfaceMethod io/reactivex/rxjava3/disposables/Disposable.dispose:()V
      21: aload_0
      22: invokevirtual #5                  // Method countDown:()V
      25: return

  public void onError(java.lang.Throwable);
    Code:
       0: aload_0
       1: getfield      #2                  // Field value:Ljava/lang/Object;
       4: ifnonnull     12
       7: aload_0
       8: aload_1
       9: putfield      #6                  // Field error:Ljava/lang/Throwable;
      12: aload_0
      13: invokevirtual #5                  // Method countDown:()V
      16: return
}
