Compiled from "BlockingObserver.java"
public final class io.reactivex.rxjava3.internal.observers.BlockingObserver<T> extends java.util.concurrent.atomic.AtomicReference<io.reactivex.rxjava3.disposables.Disposable> implements io.reactivex.rxjava3.core.Observer<T>, io.reactivex.rxjava3.disposables.Disposable {
  private static final long serialVersionUID;

  public static final java.lang.Object TERMINATED;

  final java.util.Queue<java.lang.Object> queue;

  public io.reactivex.rxjava3.internal.observers.BlockingObserver(java.util.Queue<java.lang.Object>);
    Code:
       0: aload_0
       1: invokespecial #1                  // Method java/util/concurrent/atomic/AtomicReference."<init>":()V
       4: aload_0
       5: aload_1
       6: putfield      #2                  // Field queue:Ljava/util/Queue;
       9: return

  public void onSubscribe(io.reactivex.rxjava3.disposables.Disposable);
    Code:
       0: aload_0
       1: aload_1
       2: invokestatic  #3                  // Method io/reactivex/rxjava3/internal/disposables/DisposableHelper.setOnce:(Ljava/util/concurrent/atomic/AtomicReference;Lio/reactivex/rxjava3/disposables/Disposable;)Z
       5: pop
       6: return

  public void onNext(T);
    Code:
       0: aload_0
       1: getfield      #2                  // Field queue:Ljava/util/Queue;
       4: aload_1
       5: invokestatic  #4                  // Method io/reactivex/rxjava3/internal/util/NotificationLite.next:(Ljava/lang/Object;)Ljava/lang/Object;
       8: invokeinterface #5,  2            // InterfaceMethod java/util/Queue.offer:(Ljava/lang/Object;)Z
      13: pop
      14: return

  public void onError(java.lang.Throwable);
    Code:
       0: aload_0
       1: getfield      #2                  // Field queue:Ljava/util/Queue;
       4: aload_1
       5: invokestatic  #6                  // Method io/reactivex/rxjava3/internal/util/NotificationLite.error:(Ljava/lang/Throwable;)Ljava/lang/Object;
       8: invokeinterface #5,  2            // InterfaceMethod java/util/Queue.offer:(Ljava/lang/Object;)Z
      13: pop
      14: return

  public void onComplete();
    Code:
       0: aload_0
       1: getfield      #2                  // Field queue:Ljava/util/Queue;
       4: invokestatic  #7                  // Method io/reactivex/rxjava3/internal/util/NotificationLite.complete:()Ljava/lang/Object;
       7: invokeinterface #5,  2            // InterfaceMethod java/util/Queue.offer:(Ljava/lang/Object;)Z
      12: pop
      13: return

  public void dispose();
    Code:
       0: aload_0
       1: invokestatic  #8                  // Method io/reactivex/rxjava3/internal/disposables/DisposableHelper.dispose:(Ljava/util/concurrent/atomic/AtomicReference;)Z
       4: ifeq          20
       7: aload_0
       8: getfield      #2                  // Field queue:Ljava/util/Queue;
      11: getstatic     #9                  // Field TERMINATED:Ljava/lang/Object;
      14: invokeinterface #5,  2            // InterfaceMethod java/util/Queue.offer:(Ljava/lang/Object;)Z
      19: pop
      20: return

  public boolean isDisposed();
    Code:
       0: aload_0
       1: invokevirtual #10                 // Method get:()Ljava/lang/Object;
       4: getstatic     #11                 // Field io/reactivex/rxjava3/internal/disposables/DisposableHelper.DISPOSED:Lio/reactivex/rxjava3/internal/disposables/DisposableHelper;
       7: if_acmpne     14
      10: iconst_1
      11: goto          15
      14: iconst_0
      15: ireturn

  static {};
    Code:
       0: new           #12                 // class java/lang/Object
       3: dup
       4: invokespecial #13                 // Method java/lang/Object."<init>":()V
       7: putstatic     #9                  // Field TERMINATED:Ljava/lang/Object;
      10: return
}
