Compiled from "DeferredScalarObserver.java"
public abstract class io.reactivex.rxjava3.internal.observers.DeferredScalarObserver<T, R> extends io.reactivex.rxjava3.internal.observers.DeferredScalarDisposable<R> implements io.reactivex.rxjava3.core.Observer<T> {
  private static final long serialVersionUID;

  protected io.reactivex.rxjava3.disposables.Disposable upstream;

  public io.reactivex.rxjava3.internal.observers.DeferredScalarObserver(io.reactivex.rxjava3.core.Observer<? super R>);
    Code:
       0: aload_0
       1: aload_1
       2: invokespecial #1                  // Method io/reactivex/rxjava3/internal/observers/DeferredScalarDisposable."<init>":(Lio/reactivex/rxjava3/core/Observer;)V
       5: return

  public void onSubscribe(io.reactivex.rxjava3.disposables.Disposable);
    Code:
       0: aload_0
       1: getfield      #2                  // Field upstream:Lio/reactivex/rxjava3/disposables/Disposable;
       4: aload_1
       5: invokestatic  #3                  // Method io/reactivex/rxjava3/internal/disposables/DisposableHelper.validate:(Lio/reactivex/rxjava3/disposables/Disposable;Lio/reactivex/rxjava3/disposables/Disposable;)Z
       8: ifeq          26
      11: aload_0
      12: aload_1
      13: putfield      #2                  // Field upstream:Lio/reactivex/rxjava3/disposables/Disposable;
      16: aload_0
      17: getfield      #4                  // Field downstream:Lio/reactivex/rxjava3/core/Observer;
      20: aload_0
      21: invokeinterface #5,  2            // InterfaceMethod io/reactivex/rxjava3/core/Observer.onSubscribe:(Lio/reactivex/rxjava3/disposables/Disposable;)V
      26: return

  public void onError(java.lang.Throwable);
    Code:
       0: aload_0
       1: aconst_null
       2: putfield      #6                  // Field value:Ljava/lang/Object;
       5: aload_0
       6: aload_1
       7: invokevirtual #7                  // Method error:(Ljava/lang/Throwable;)V
      10: return

  public void onComplete();
    Code:
       0: aload_0
       1: getfield      #6                  // Field value:Ljava/lang/Object;
       4: astore_1
       5: aload_1
       6: ifnull        22
       9: aload_0
      10: aconst_null
      11: putfield      #6                  // Field value:Ljava/lang/Object;
      14: aload_0
      15: aload_1
      16: invokevirtual #8                  // Method complete:(Ljava/lang/Object;)V
      19: goto          26
      22: aload_0
      23: invokevirtual #9                  // Method complete:()V
      26: return

  public void dispose();
    Code:
       0: aload_0
       1: invokespecial #10                 // Method io/reactivex/rxjava3/internal/observers/DeferredScalarDisposable.dispose:()V
       4: aload_0
       5: getfield      #2                  // Field upstream:Lio/reactivex/rxjava3/disposables/Disposable;
       8: invokeinterface #11,  1           // InterfaceMethod io/reactivex/rxjava3/disposables/Disposable.dispose:()V
      13: return
}
