Compiled from "DisposableAutoReleaseMultiObserver.java"
public final class io.reactivex.rxjava3.internal.observers.DisposableAutoReleaseMultiObserver<T> extends io.reactivex.rxjava3.internal.observers.AbstractDisposableAutoRelease implements io.reactivex.rxjava3.core.SingleObserver<T>, io.reactivex.rxjava3.core.MaybeObserver<T>, io.reactivex.rxjava3.core.CompletableObserver {
  private static final long serialVersionUID;

  final io.reactivex.rxjava3.functions.Consumer<? super T> onSuccess;

  public io.reactivex.rxjava3.internal.observers.DisposableAutoReleaseMultiObserver(io.reactivex.rxjava3.disposables.DisposableContainer, io.reactivex.rxjava3.functions.Consumer<? super T>, io.reactivex.rxjava3.functions.Consumer<? super java.lang.Throwable>, io.reactivex.rxjava3.functions.Action);
    Code:
       0: aload_0
       1: aload_1
       2: aload_3
       3: aload         4
       5: invokespecial #1                  // Method io/reactivex/rxjava3/internal/observers/AbstractDisposableAutoRelease."<init>":(Lio/reactivex/rxjava3/disposables/DisposableContainer;Lio/reactivex/rxjava3/functions/Consumer;Lio/reactivex/rxjava3/functions/Action;)V
       8: aload_0
       9: aload_2
      10: putfield      #2                  // Field onSuccess:Lio/reactivex/rxjava3/functions/Consumer;
      13: return

  public void onSuccess(T);
    Code:
       0: aload_0
       1: invokevirtual #3                  // Method get:()Ljava/lang/Object;
       4: getstatic     #4                  // Field io/reactivex/rxjava3/internal/disposables/DisposableHelper.DISPOSED:Lio/reactivex/rxjava3/internal/disposables/DisposableHelper;
       7: if_acmpeq     39
      10: aload_0
      11: getstatic     #4                  // Field io/reactivex/rxjava3/internal/disposables/DisposableHelper.DISPOSED:Lio/reactivex/rxjava3/internal/disposables/DisposableHelper;
      14: invokevirtual #5                  // Method lazySet:(Ljava/lang/Object;)V
      17: aload_0
      18: getfield      #2                  // Field onSuccess:Lio/reactivex/rxjava3/functions/Consumer;
      21: aload_1
      22: invokeinterface #6,  2            // InterfaceMethod io/reactivex/rxjava3/functions/Consumer.accept:(Ljava/lang/Object;)V
      27: goto          39
      30: astore_2
      31: aload_2
      32: invokestatic  #8                  // Method io/reactivex/rxjava3/exceptions/Exceptions.throwIfFatal:(Ljava/lang/Throwable;)V
      35: aload_2
      36: invokestatic  #9                  // Method io/reactivex/rxjava3/plugins/RxJavaPlugins.onError:(Ljava/lang/Throwable;)V
      39: aload_0
      40: invokevirtual #10                 // Method removeSelf:()V
      43: return
    Exception table:
       from    to  target type
          17    27    30   Class java/lang/Throwable
}
