Compiled from "DisposableLambdaObserver.java"
public final class io.reactivex.rxjava3.internal.observers.DisposableLambdaObserver<T> implements io.reactivex.rxjava3.core.Observer<T>, io.reactivex.rxjava3.disposables.Disposable {
  final io.reactivex.rxjava3.core.Observer<? super T> downstream;

  final io.reactivex.rxjava3.functions.Consumer<? super io.reactivex.rxjava3.disposables.Disposable> onSubscribe;

  final io.reactivex.rxjava3.functions.Action onDispose;

  io.reactivex.rxjava3.disposables.Disposable upstream;

  public io.reactivex.rxjava3.internal.observers.DisposableLambdaObserver(io.reactivex.rxjava3.core.Observer<? super T>, io.reactivex.rxjava3.functions.Consumer<? super io.reactivex.rxjava3.disposables.Disposable>, io.reactivex.rxjava3.functions.Action);
    Code:
       0: aload_0
       1: invokespecial #1                  // Method java/lang/Object."<init>":()V
       4: aload_0
       5: aload_1
       6: putfield      #2                  // Field downstream:Lio/reactivex/rxjava3/core/Observer;
       9: aload_0
      10: aload_2
      11: putfield      #3                  // Field onSubscribe:Lio/reactivex/rxjava3/functions/Consumer;
      14: aload_0
      15: aload_3
      16: putfield      #4                  // Field onDispose:Lio/reactivex/rxjava3/functions/Action;
      19: return

  public void onSubscribe(io.reactivex.rxjava3.disposables.Disposable);
    Code:
       0: aload_0
       1: getfield      #3                  // Field onSubscribe:Lio/reactivex/rxjava3/functions/Consumer;
       4: aload_1
       5: invokeinterface #5,  2            // InterfaceMethod io/reactivex/rxjava3/functions/Consumer.accept:(Ljava/lang/Object;)V
      10: goto          40
      13: astore_2
      14: aload_2
      15: invokestatic  #7                  // Method io/reactivex/rxjava3/exceptions/Exceptions.throwIfFatal:(Ljava/lang/Throwable;)V
      18: aload_1
      19: invokeinterface #8,  1            // InterfaceMethod io/reactivex/rxjava3/disposables/Disposable.dispose:()V
      24: aload_0
      25: getstatic     #9                  // Field io/reactivex/rxjava3/internal/disposables/DisposableHelper.DISPOSED:Lio/reactivex/rxjava3/internal/disposables/DisposableHelper;
      28: putfield      #10                 // Field upstream:Lio/reactivex/rxjava3/disposables/Disposable;
      31: aload_2
      32: aload_0
      33: getfield      #2                  // Field downstream:Lio/reactivex/rxjava3/core/Observer;
      36: invokestatic  #11                 // Method io/reactivex/rxjava3/internal/disposables/EmptyDisposable.error:(Ljava/lang/Throwable;Lio/reactivex/rxjava3/core/Observer;)V
      39: return
      40: aload_0
      41: getfield      #10                 // Field upstream:Lio/reactivex/rxjava3/disposables/Disposable;
      44: aload_1
      45: invokestatic  #12                 // Method io/reactivex/rxjava3/internal/disposables/DisposableHelper.validate:(Lio/reactivex/rxjava3/disposables/Disposable;Lio/reactivex/rxjava3/disposables/Disposable;)Z
      48: ifeq          66
      51: aload_0
      52: aload_1
      53: putfield      #10                 // Field upstream:Lio/reactivex/rxjava3/disposables/Disposable;
      56: aload_0
      57: getfield      #2                  // Field downstream:Lio/reactivex/rxjava3/core/Observer;
      60: aload_0
      61: invokeinterface #13,  2           // InterfaceMethod io/reactivex/rxjava3/core/Observer.onSubscribe:(Lio/reactivex/rxjava3/disposables/Disposable;)V
      66: return
    Exception table:
       from    to  target type
           0    10    13   Class java/lang/Throwable

  public void onNext(T);
    Code:
       0: aload_0
       1: getfield      #2                  // Field downstream:Lio/reactivex/rxjava3/core/Observer;
       4: aload_1
       5: invokeinterface #14,  2           // InterfaceMethod io/reactivex/rxjava3/core/Observer.onNext:(Ljava/lang/Object;)V
      10: return

  public void onError(java.lang.Throwable);
    Code:
       0: aload_0
       1: getfield      #10                 // Field upstream:Lio/reactivex/rxjava3/disposables/Disposable;
       4: getstatic     #9                  // Field io/reactivex/rxjava3/internal/disposables/DisposableHelper.DISPOSED:Lio/reactivex/rxjava3/internal/disposables/DisposableHelper;
       7: if_acmpeq     30
      10: aload_0
      11: getstatic     #9                  // Field io/reactivex/rxjava3/internal/disposables/DisposableHelper.DISPOSED:Lio/reactivex/rxjava3/internal/disposables/DisposableHelper;
      14: putfield      #10                 // Field upstream:Lio/reactivex/rxjava3/disposables/Disposable;
      17: aload_0
      18: getfield      #2                  // Field downstream:Lio/reactivex/rxjava3/core/Observer;
      21: aload_1
      22: invokeinterface #15,  2           // InterfaceMethod io/reactivex/rxjava3/core/Observer.onError:(Ljava/lang/Throwable;)V
      27: goto          34
      30: aload_1
      31: invokestatic  #16                 // Method io/reactivex/rxjava3/plugins/RxJavaPlugins.onError:(Ljava/lang/Throwable;)V
      34: return

  public void onComplete();
    Code:
       0: aload_0
       1: getfield      #10                 // Field upstream:Lio/reactivex/rxjava3/disposables/Disposable;
       4: getstatic     #9                  // Field io/reactivex/rxjava3/internal/disposables/DisposableHelper.DISPOSED:Lio/reactivex/rxjava3/internal/disposables/DisposableHelper;
       7: if_acmpeq     26
      10: aload_0
      11: getstatic     #9                  // Field io/reactivex/rxjava3/internal/disposables/DisposableHelper.DISPOSED:Lio/reactivex/rxjava3/internal/disposables/DisposableHelper;
      14: putfield      #10                 // Field upstream:Lio/reactivex/rxjava3/disposables/Disposable;
      17: aload_0
      18: getfield      #2                  // Field downstream:Lio/reactivex/rxjava3/core/Observer;
      21: invokeinterface #17,  1           // InterfaceMethod io/reactivex/rxjava3/core/Observer.onComplete:()V
      26: return

  public void dispose();
    Code:
       0: aload_0
       1: getfield      #10                 // Field upstream:Lio/reactivex/rxjava3/disposables/Disposable;
       4: astore_1
       5: aload_1
       6: getstatic     #9                  // Field io/reactivex/rxjava3/internal/disposables/DisposableHelper.DISPOSED:Lio/reactivex/rxjava3/internal/disposables/DisposableHelper;
       9: if_acmpeq     46
      12: aload_0
      13: getstatic     #9                  // Field io/reactivex/rxjava3/internal/disposables/DisposableHelper.DISPOSED:Lio/reactivex/rxjava3/internal/disposables/DisposableHelper;
      16: putfield      #10                 // Field upstream:Lio/reactivex/rxjava3/disposables/Disposable;
      19: aload_0
      20: getfield      #4                  // Field onDispose:Lio/reactivex/rxjava3/functions/Action;
      23: invokeinterface #18,  1           // InterfaceMethod io/reactivex/rxjava3/functions/Action.run:()V
      28: goto          40
      31: astore_2
      32: aload_2
      33: invokestatic  #7                  // Method io/reactivex/rxjava3/exceptions/Exceptions.throwIfFatal:(Ljava/lang/Throwable;)V
      36: aload_2
      37: invokestatic  #16                 // Method io/reactivex/rxjava3/plugins/RxJavaPlugins.onError:(Ljava/lang/Throwable;)V
      40: aload_1
      41: invokeinterface #8,  1            // InterfaceMethod io/reactivex/rxjava3/disposables/Disposable.dispose:()V
      46: return
    Exception table:
       from    to  target type
          19    28    31   Class java/lang/Throwable

  public boolean isDisposed();
    Code:
       0: aload_0
       1: getfield      #10                 // Field upstream:Lio/reactivex/rxjava3/disposables/Disposable;
       4: invokeinterface #19,  1           // InterfaceMethod io/reactivex/rxjava3/disposables/Disposable.isDisposed:()Z
       9: ireturn
}
