Compiled from "InnerQueuedObserver.java"
public final class io.reactivex.rxjava3.internal.observers.InnerQueuedObserver<T> extends java.util.concurrent.atomic.AtomicReference<io.reactivex.rxjava3.disposables.Disposable> implements io.reactivex.rxjava3.core.Observer<T>, io.reactivex.rxjava3.disposables.Disposable {
  private static final long serialVersionUID;

  final io.reactivex.rxjava3.internal.observers.InnerQueuedObserverSupport<T> parent;

  final int prefetch;

  io.reactivex.rxjava3.operators.SimpleQueue<T> queue;

  volatile boolean done;

  int fusionMode;

  public io.reactivex.rxjava3.internal.observers.InnerQueuedObserver(io.reactivex.rxjava3.internal.observers.InnerQueuedObserverSupport<T>, int);
    Code:
       0: aload_0
       1: invokespecial #1                  // Method java/util/concurrent/atomic/AtomicReference."<init>":()V
       4: aload_0
       5: aload_1
       6: putfield      #2                  // Field parent:Lio/reactivex/rxjava3/internal/observers/InnerQueuedObserverSupport;
       9: aload_0
      10: iload_2
      11: putfield      #3                  // Field prefetch:I
      14: return

  public void onSubscribe(io.reactivex.rxjava3.disposables.Disposable);
    Code:
       0: aload_0
       1: aload_1
       2: invokestatic  #4                  // Method io/reactivex/rxjava3/internal/disposables/DisposableHelper.setOnce:(Ljava/util/concurrent/atomic/AtomicReference;Lio/reactivex/rxjava3/disposables/Disposable;)Z
       5: ifeq          87
       8: aload_1
       9: instanceof    #5                  // class io/reactivex/rxjava3/operators/QueueDisposable
      12: ifeq          75
      15: aload_1
      16: checkcast     #5                  // class io/reactivex/rxjava3/operators/QueueDisposable
      19: astore_2
      20: aload_2
      21: iconst_3
      22: invokeinterface #6,  2            // InterfaceMethod io/reactivex/rxjava3/operators/QueueDisposable.requestFusion:(I)I
      27: istore_3
      28: iload_3
      29: iconst_1
      30: if_icmpne     59
      33: aload_0
      34: iload_3
      35: putfield      #8                  // Field fusionMode:I
      38: aload_0
      39: aload_2
      40: putfield      #9                  // Field queue:Lio/reactivex/rxjava3/operators/SimpleQueue;
      43: aload_0
      44: iconst_1
      45: putfield      #10                 // Field done:Z
      48: aload_0
      49: getfield      #2                  // Field parent:Lio/reactivex/rxjava3/internal/observers/InnerQueuedObserverSupport;
      52: aload_0
      53: invokeinterface #11,  2           // InterfaceMethod io/reactivex/rxjava3/internal/observers/InnerQueuedObserverSupport.innerComplete:(Lio/reactivex/rxjava3/internal/observers/InnerQueuedObserver;)V
      58: return
      59: iload_3
      60: iconst_2
      61: if_icmpne     75
      64: aload_0
      65: iload_3
      66: putfield      #8                  // Field fusionMode:I
      69: aload_0
      70: aload_2
      71: putfield      #9                  // Field queue:Lio/reactivex/rxjava3/operators/SimpleQueue;
      74: return
      75: aload_0
      76: aload_0
      77: getfield      #3                  // Field prefetch:I
      80: ineg
      81: invokestatic  #12                 // Method io/reactivex/rxjava3/internal/util/QueueDrainHelper.createQueue:(I)Lio/reactivex/rxjava3/operators/SimpleQueue;
      84: putfield      #9                  // Field queue:Lio/reactivex/rxjava3/operators/SimpleQueue;
      87: return

  public void onNext(T);
    Code:
       0: aload_0
       1: getfield      #8                  // Field fusionMode:I
       4: ifne          21
       7: aload_0
       8: getfield      #2                  // Field parent:Lio/reactivex/rxjava3/internal/observers/InnerQueuedObserverSupport;
      11: aload_0
      12: aload_1
      13: invokeinterface #13,  3           // InterfaceMethod io/reactivex/rxjava3/internal/observers/InnerQueuedObserverSupport.innerNext:(Lio/reactivex/rxjava3/internal/observers/InnerQueuedObserver;Ljava/lang/Object;)V
      18: goto          30
      21: aload_0
      22: getfield      #2                  // Field parent:Lio/reactivex/rxjava3/internal/observers/InnerQueuedObserverSupport;
      25: invokeinterface #14,  1           // InterfaceMethod io/reactivex/rxjava3/internal/observers/InnerQueuedObserverSupport.drain:()V
      30: return

  public void onError(java.lang.Throwable);
    Code:
       0: aload_0
       1: getfield      #2                  // Field parent:Lio/reactivex/rxjava3/internal/observers/InnerQueuedObserverSupport;
       4: aload_0
       5: aload_1
       6: invokeinterface #15,  3           // InterfaceMethod io/reactivex/rxjava3/internal/observers/InnerQueuedObserverSupport.innerError:(Lio/reactivex/rxjava3/internal/observers/InnerQueuedObserver;Ljava/lang/Throwable;)V
      11: return

  public void onComplete();
    Code:
       0: aload_0
       1: getfield      #2                  // Field parent:Lio/reactivex/rxjava3/internal/observers/InnerQueuedObserverSupport;
       4: aload_0
       5: invokeinterface #11,  2           // InterfaceMethod io/reactivex/rxjava3/internal/observers/InnerQueuedObserverSupport.innerComplete:(Lio/reactivex/rxjava3/internal/observers/InnerQueuedObserver;)V
      10: return

  public void dispose();
    Code:
       0: aload_0
       1: invokestatic  #16                 // Method io/reactivex/rxjava3/internal/disposables/DisposableHelper.dispose:(Ljava/util/concurrent/atomic/AtomicReference;)Z
       4: pop
       5: return

  public boolean isDisposed();
    Code:
       0: aload_0
       1: invokevirtual #17                 // Method get:()Ljava/lang/Object;
       4: checkcast     #18                 // class io/reactivex/rxjava3/disposables/Disposable
       7: invokestatic  #19                 // Method io/reactivex/rxjava3/internal/disposables/DisposableHelper.isDisposed:(Lio/reactivex/rxjava3/disposables/Disposable;)Z
      10: ireturn

  public boolean isDone();
    Code:
       0: aload_0
       1: getfield      #10                 // Field done:Z
       4: ireturn

  public void setDone();
    Code:
       0: aload_0
       1: iconst_1
       2: putfield      #10                 // Field done:Z
       5: return

  public io.reactivex.rxjava3.operators.SimpleQueue<T> queue();
    Code:
       0: aload_0
       1: getfield      #9                  // Field queue:Lio/reactivex/rxjava3/operators/SimpleQueue;
       4: areturn
}
