Compiled from "DubboSpringInitCustomizerHolder.java"
public class org.apache.dubbo.config.spring.context.DubboSpringInitCustomizerHolder {
  private static final java.lang.ThreadLocal<org.apache.dubbo.config.spring.context.DubboSpringInitCustomizerHolder> holders;

  private java.util.Set<org.apache.dubbo.config.spring.context.DubboSpringInitCustomizer> customizers;

  public org.apache.dubbo.config.spring.context.DubboSpringInitCustomizerHolder();
    Code:
       0: aload_0
       1: invokespecial #1                  // Method java/lang/Object."<init>":()V
       4: aload_0
       5: new           #2                  // class java/util/HashSet
       8: dup
       9: invokespecial #3                  // Method java/util/HashSet."<init>":()V
      12: putfield      #4                  // Field customizers:Ljava/util/Set;
      15: return

  public static org.apache.dubbo.config.spring.context.DubboSpringInitCustomizerHolder get();
    Code:
       0: getstatic     #5                  // Field holders:Ljava/lang/ThreadLocal;
       3: invokevirtual #6                  // Method java/lang/ThreadLocal.get:()Ljava/lang/Object;
       6: checkcast     #7                  // class org/apache/dubbo/config/spring/context/DubboSpringInitCustomizerHolder
       9: areturn

  public void addCustomizer(org.apache.dubbo.config.spring.context.DubboSpringInitCustomizer);
    Code:
       0: aload_0
       1: getfield      #4                  // Field customizers:Ljava/util/Set;
       4: aload_1
       5: invokeinterface #8,  2            // InterfaceMethod java/util/Set.add:(Ljava/lang/Object;)Z
      10: pop
      11: return

  public void clearCustomizers();
    Code:
       0: aload_0
       1: new           #2                  // class java/util/HashSet
       4: dup
       5: invokespecial #3                  // Method java/util/HashSet."<init>":()V
       8: putfield      #4                  // Field customizers:Ljava/util/Set;
      11: return

  public java.util.Set<org.apache.dubbo.config.spring.context.DubboSpringInitCustomizer> getCustomizers();
    Code:
       0: aload_0
       1: getfield      #4                  // Field customizers:Ljava/util/Set;
       4: areturn

  static {};
    Code:
       0: invokedynamic #9,  0              // InvokeDynamic #0:get:()Ljava/util/function/Supplier;
       5: invokestatic  #10                 // Method java/lang/ThreadLocal.withInitial:(Ljava/util/function/Supplier;)Ljava/lang/ThreadLocal;
       8: putstatic     #5                  // Field holders:Ljava/lang/ThreadLocal;
      11: return
}
