Compiled from "DubboBootstrapApplicationListener.java"
public class org.apache.dubbo.config.spring.context.DubboBootstrapApplicationListener implements org.springframework.context.ApplicationListener,org.springframework.context.ApplicationContextAware,org.springframework.core.Ordered {
  public static final java.lang.String BEAN_NAME;

  private final org.apache.dubbo.common.logger.ErrorTypeAwareLogger logger;

  private org.springframework.context.ApplicationContext applicationContext;

  private org.apache.dubbo.config.bootstrap.DubboBootstrap bootstrap;

  private boolean shouldInitConfigBeans;

  private org.apache.dubbo.rpc.model.ModuleModel moduleModel;

  public org.apache.dubbo.config.spring.context.DubboBootstrapApplicationListener();
    Code:
       0: aload_0
       1: invokespecial #2                  // Method java/lang/Object."<init>":()V
       4: aload_0
       5: aload_0
       6: invokevirtual #3                  // Method java/lang/Object.getClass:()Ljava/lang/Class;
       9: invokestatic  #4                  // Method org/apache/dubbo/common/logger/LoggerFactory.getErrorTypeAwareLogger:(Ljava/lang/Class;)Lorg/apache/dubbo/common/logger/ErrorTypeAwareLogger;
      12: putfield      #5                  // Field logger:Lorg/apache/dubbo/common/logger/ErrorTypeAwareLogger;
      15: return

  public org.apache.dubbo.config.spring.context.DubboBootstrapApplicationListener(boolean);
    Code:
       0: aload_0
       1: invokespecial #2                  // Method java/lang/Object."<init>":()V
       4: aload_0
       5: aload_0
       6: invokevirtual #3                  // Method java/lang/Object.getClass:()Ljava/lang/Class;
       9: invokestatic  #4                  // Method org/apache/dubbo/common/logger/LoggerFactory.getErrorTypeAwareLogger:(Ljava/lang/Class;)Lorg/apache/dubbo/common/logger/ErrorTypeAwareLogger;
      12: putfield      #5                  // Field logger:Lorg/apache/dubbo/common/logger/ErrorTypeAwareLogger;
      15: aload_0
      16: iload_1
      17: putfield      #6                  // Field shouldInitConfigBeans:Z
      20: return

  private void setBootstrap(org.apache.dubbo.config.bootstrap.DubboBootstrap);
    Code:
       0: aload_0
       1: aload_1
       2: putfield      #7                  // Field bootstrap:Lorg/apache/dubbo/config/bootstrap/DubboBootstrap;
       5: aload_1
       6: invokevirtual #8                  // Method org/apache/dubbo/config/bootstrap/DubboBootstrap.getTakeoverMode:()Lorg/apache/dubbo/config/bootstrap/BootstrapTakeoverMode;
       9: getstatic     #9                  // Field org/apache/dubbo/config/bootstrap/BootstrapTakeoverMode.MANUAL:Lorg/apache/dubbo/config/bootstrap/BootstrapTakeoverMode;
      12: if_acmpeq     22
      15: aload_1
      16: getstatic     #10                 // Field org/apache/dubbo/config/bootstrap/BootstrapTakeoverMode.SPRING:Lorg/apache/dubbo/config/bootstrap/BootstrapTakeoverMode;
      19: invokevirtual #11                 // Method org/apache/dubbo/config/bootstrap/DubboBootstrap.setTakeoverMode:(Lorg/apache/dubbo/config/bootstrap/BootstrapTakeoverMode;)V
      22: return

  public void onApplicationEvent(org.springframework.context.ApplicationEvent);
    Code:
       0: aload_0
       1: aload_1
       2: invokespecial #12                 // Method isOriginalEventSource:(Lorg/springframework/context/ApplicationEvent;)Z
       5: ifeq          37
       8: aload_1
       9: instanceof    #13                 // class org/apache/dubbo/config/spring/context/event/DubboConfigInitEvent
      12: ifeq          22
      15: aload_0
      16: invokespecial #14                 // Method initDubboConfigBeans:()V
      19: goto          37
      22: aload_1
      23: instanceof    #15                 // class org/springframework/context/event/ApplicationContextEvent
      26: ifeq          37
      29: aload_0
      30: aload_1
      31: checkcast     #15                 // class org/springframework/context/event/ApplicationContextEvent
      34: invokespecial #16                 // Method onApplicationContextEvent:(Lorg/springframework/context/event/ApplicationContextEvent;)V
      37: return

  private void initDubboConfigBeans();
    Code:
       0: aload_0
       1: getfield      #17                 // Field applicationContext:Lorg/springframework/context/ApplicationContext;
       4: getstatic     #18                 // Field org/apache/dubbo/config/spring/context/DubboConfigBeanInitializer.BEAN_NAME:Ljava/lang/String;
       7: invokeinterface #19,  2           // InterfaceMethod org/springframework/context/ApplicationContext.containsBean:(Ljava/lang/String;)Z
      12: ifeq          33
      15: aload_0
      16: getfield      #17                 // Field applicationContext:Lorg/springframework/context/ApplicationContext;
      19: getstatic     #18                 // Field org/apache/dubbo/config/spring/context/DubboConfigBeanInitializer.BEAN_NAME:Ljava/lang/String;
      22: ldc           #20                 // class org/apache/dubbo/config/spring/context/DubboConfigBeanInitializer
      24: invokeinterface #21,  3           // InterfaceMethod org/springframework/context/ApplicationContext.getBean:(Ljava/lang/String;Ljava/lang/Class;)Ljava/lang/Object;
      29: pop
      30: goto          74
      33: aload_0
      34: getfield      #5                  // Field logger:Lorg/apache/dubbo/common/logger/ErrorTypeAwareLogger;
      37: ldc           #22                 // String 5-40
      39: ldc           #23                 // String
      41: ldc           #23                 // String
      43: new           #24                 // class java/lang/StringBuilder
      46: dup
      47: invokespecial #25                 // Method java/lang/StringBuilder."<init>":()V
      50: ldc           #26                 // String Bean \'
      52: invokevirtual #27                 // Method java/lang/StringBuilder.append:(Ljava/lang/String;)Ljava/lang/StringBuilder;
      55: getstatic     #18                 // Field org/apache/dubbo/config/spring/context/DubboConfigBeanInitializer.BEAN_NAME:Ljava/lang/String;
      58: invokevirtual #27                 // Method java/lang/StringBuilder.append:(Ljava/lang/String;)Ljava/lang/StringBuilder;
      61: ldc           #28                 // String \' was not found
      63: invokevirtual #27                 // Method java/lang/StringBuilder.append:(Ljava/lang/String;)Ljava/lang/StringBuilder;
      66: invokevirtual #29                 // Method java/lang/StringBuilder.toString:()Ljava/lang/String;
      69: invokeinterface #30,  5           // InterfaceMethod org/apache/dubbo/common/logger/ErrorTypeAwareLogger.warn:(Ljava/lang/String;Ljava/lang/String;Ljava/lang/String;Ljava/lang/String;)V
      74: aload_0
      75: getfield      #31                 // Field moduleModel:Lorg/apache/dubbo/rpc/model/ModuleModel;
      78: invokevirtual #32                 // Method org/apache/dubbo/rpc/model/ModuleModel.getDeployer:()Lorg/apache/dubbo/common/deploy/ModuleDeployer;
      81: invokeinterface #33,  1           // InterfaceMethod org/apache/dubbo/common/deploy/ModuleDeployer.initialize:()V
      86: return

  private void onApplicationContextEvent(org.springframework.context.event.ApplicationContextEvent);
    Code:
       0: getstatic     #34                 // Field org/apache/dubbo/config/spring/context/DubboBootstrapStartStopListenerSpringAdapter.applicationContext:Lorg/springframework/context/ApplicationContext;
       3: ifnonnull     13
       6: aload_1
       7: invokevirtual #35                 // Method org/springframework/context/event/ApplicationContextEvent.getApplicationContext:()Lorg/springframework/context/ApplicationContext;
      10: putstatic     #34                 // Field org/apache/dubbo/config/spring/context/DubboBootstrapStartStopListenerSpringAdapter.applicationContext:Lorg/springframework/context/ApplicationContext;
      13: aload_1
      14: instanceof    #36                 // class org/springframework/context/event/ContextRefreshedEvent
      17: ifeq          31
      20: aload_0
      21: aload_1
      22: checkcast     #36                 // class org/springframework/context/event/ContextRefreshedEvent
      25: invokespecial #37                 // Method onContextRefreshedEvent:(Lorg/springframework/context/event/ContextRefreshedEvent;)V
      28: goto          46
      31: aload_1
      32: instanceof    #38                 // class org/springframework/context/event/ContextClosedEvent
      35: ifeq          46
      38: aload_0
      39: aload_1
      40: checkcast     #38                 // class org/springframework/context/event/ContextClosedEvent
      43: invokespecial #39                 // Method onContextClosedEvent:(Lorg/springframework/context/event/ContextClosedEvent;)V
      46: return

  private void onContextRefreshedEvent(org.springframework.context.event.ContextRefreshedEvent);
    Code:
       0: aload_0
       1: getfield      #7                  // Field bootstrap:Lorg/apache/dubbo/config/bootstrap/DubboBootstrap;
       4: invokevirtual #8                  // Method org/apache/dubbo/config/bootstrap/DubboBootstrap.getTakeoverMode:()Lorg/apache/dubbo/config/bootstrap/BootstrapTakeoverMode;
       7: getstatic     #10                 // Field org/apache/dubbo/config/bootstrap/BootstrapTakeoverMode.SPRING:Lorg/apache/dubbo/config/bootstrap/BootstrapTakeoverMode;
      10: if_acmpne     26
      13: aload_0
      14: getfield      #31                 // Field moduleModel:Lorg/apache/dubbo/rpc/model/ModuleModel;
      17: invokevirtual #32                 // Method org/apache/dubbo/rpc/model/ModuleModel.getDeployer:()Lorg/apache/dubbo/common/deploy/ModuleDeployer;
      20: invokeinterface #40,  1           // InterfaceMethod org/apache/dubbo/common/deploy/ModuleDeployer.start:()Ljava/util/concurrent/Future;
      25: pop
      26: return

  private void onContextClosedEvent(org.springframework.context.event.ContextClosedEvent);
    Code:
       0: aload_0
       1: getfield      #7                  // Field bootstrap:Lorg/apache/dubbo/config/bootstrap/DubboBootstrap;
       4: invokevirtual #8                  // Method org/apache/dubbo/config/bootstrap/DubboBootstrap.getTakeoverMode:()Lorg/apache/dubbo/config/bootstrap/BootstrapTakeoverMode;
       7: getstatic     #10                 // Field org/apache/dubbo/config/bootstrap/BootstrapTakeoverMode.SPRING:Lorg/apache/dubbo/config/bootstrap/BootstrapTakeoverMode;
      10: if_acmpne     25
      13: aload_0
      14: getfield      #31                 // Field moduleModel:Lorg/apache/dubbo/rpc/model/ModuleModel;
      17: invokevirtual #32                 // Method org/apache/dubbo/rpc/model/ModuleModel.getDeployer:()Lorg/apache/dubbo/common/deploy/ModuleDeployer;
      20: invokeinterface #41,  1           // InterfaceMethod org/apache/dubbo/common/deploy/ModuleDeployer.stop:()V
      25: return

  private boolean isOriginalEventSource(org.springframework.context.ApplicationEvent);
    Code:
       0: aload_0
       1: invokevirtual #42                 // Method getApplicationContext:()Lorg/springframework/context/ApplicationContext;
       4: aload_1
       5: invokevirtual #43                 // Method org/springframework/context/ApplicationEvent.getSource:()Ljava/lang/Object;
       8: invokestatic  #44                 // Method org/springframework/util/ObjectUtils.nullSafeEquals:(Ljava/lang/Object;Ljava/lang/Object;)Z
      11: istore_2
      12: iload_2
      13: ireturn

  public int getOrder();
    Code:
       0: ldc           #46                 // int 2147483647
       2: ireturn

  public void setApplicationContext(org.springframework.context.ApplicationContext) throws org.springframework.beans.BeansException;
    Code:
       0: aload_0
       1: aload_1
       2: putfield      #17                 // Field applicationContext:Lorg/springframework/context/ApplicationContext;
       5: aload_0
       6: aload_1
       7: invokestatic  #47                 // InterfaceMethod org/apache/dubbo/config/spring/util/DubboBeanUtils.getModuleModel:(Lorg/springframework/beans/factory/BeanFactory;)Lorg/apache/dubbo/rpc/model/ModuleModel;
      10: putfield      #31                 // Field moduleModel:Lorg/apache/dubbo/rpc/model/ModuleModel;
      13: aload_0
      14: aload_0
      15: getfield      #31                 // Field moduleModel:Lorg/apache/dubbo/rpc/model/ModuleModel;
      18: invokevirtual #48                 // Method org/apache/dubbo/rpc/model/ModuleModel.getApplicationModel:()Lorg/apache/dubbo/rpc/model/ApplicationModel;
      21: invokestatic  #49                 // Method org/apache/dubbo/config/bootstrap/DubboBootstrap.getInstance:(Lorg/apache/dubbo/rpc/model/ApplicationModel;)Lorg/apache/dubbo/config/bootstrap/DubboBootstrap;
      24: invokespecial #50                 // Method setBootstrap:(Lorg/apache/dubbo/config/bootstrap/DubboBootstrap;)V
      27: aload_0
      28: getfield      #6                  // Field shouldInitConfigBeans:Z
      31: ifeq          38
      34: aload_0
      35: invokespecial #51                 // Method checkCallStackAndInit:()V
      38: return

  private void checkCallStackAndInit();
    Code:
       0: new           #52                 // class java/lang/Exception
       3: dup
       4: invokespecial #53                 // Method java/lang/Exception."<init>":()V
       7: astore_1
       8: aload_1
       9: invokevirtual #54                 // Method java/lang/Exception.getStackTrace:()[Ljava/lang/StackTraceElement;
      12: astore_2
      13: iconst_0
      14: istore_3
      15: aload_2
      16: astore        4
      18: aload         4
      20: arraylength
      21: istore        5
      23: iconst_0
      24: istore        6
      26: iload         6
      28: iload         5
      30: if_icmpge     77
      33: aload         4
      35: iload         6
      37: aaload
      38: astore        7
      40: aload         7
      42: invokevirtual #55                 // Method java/lang/StackTraceElement.getMethodName:()Ljava/lang/String;
      45: ldc           #56                 // String registerListeners
      47: invokevirtual #57                 // Method java/lang/String.equals:(Ljava/lang/Object;)Z
      50: ifeq          71
      53: aload         7
      55: invokevirtual #58                 // Method java/lang/StackTraceElement.getClassName:()Ljava/lang/String;
      58: ldc           #59                 // String AbstractApplicationContext
      60: invokevirtual #60                 // Method java/lang/String.endsWith:(Ljava/lang/String;)Z
      63: ifeq          71
      66: iconst_1
      67: istore_3
      68: goto          77
      71: iinc          6, 1
      74: goto          26
      77: iload_3
      78: ifeq          88
      81: aload_0
      82: invokespecial #14                 // Method initDubboConfigBeans:()V
      85: goto          106
      88: aload_0
      89: getfield      #5                  // Field logger:Lorg/apache/dubbo/common/logger/ErrorTypeAwareLogger;
      92: ldc           #61                 // String 5-39
      94: ldc           #23                 // String
      96: ldc           #23                 // String
      98: ldc           #62                 // String DubboBootstrapApplicationListener initialization is unexpected, it should be created in AbstractApplicationContext.registerListeners() method
     100: aload_1
     101: invokeinterface #63,  6           // InterfaceMethod org/apache/dubbo/common/logger/ErrorTypeAwareLogger.warn:(Ljava/lang/String;Ljava/lang/String;Ljava/lang/String;Ljava/lang/String;Ljava/lang/Throwable;)V
     106: return

  public org.springframework.context.ApplicationContext getApplicationContext();
    Code:
       0: aload_0
       1: getfield      #17                 // Field applicationContext:Lorg/springframework/context/ApplicationContext;
       4: areturn
}
