Compiled from "DubboInfraBeanRegisterPostProcessor.java"
public class org.apache.dubbo.config.spring.context.DubboInfraBeanRegisterPostProcessor implements org.springframework.beans.factory.support.BeanDefinitionRegistryPostProcessor,org.springframework.context.ApplicationContextAware {
  public static final java.lang.String BEAN_NAME;

  private org.springframework.beans.factory.support.BeanDefinitionRegistry registry;

  private org.springframework.context.ApplicationContext applicationContext;

  public org.apache.dubbo.config.spring.context.DubboInfraBeanRegisterPostProcessor();
    Code:
       0: aload_0
       1: invokespecial #1                  // Method java/lang/Object."<init>":()V
       4: return

  public void postProcessBeanDefinitionRegistry(org.springframework.beans.factory.support.BeanDefinitionRegistry) throws org.springframework.beans.BeansException;
    Code:
       0: aload_0
       1: aload_1
       2: putfield      #2                  // Field registry:Lorg/springframework/beans/factory/support/BeanDefinitionRegistry;
       5: return

  public void postProcessBeanFactory(org.springframework.beans.factory.config.ConfigurableListableBeanFactory) throws org.springframework.beans.BeansException;
    Code:
       0: aload_0
       1: getfield      #2                  // Field registry:Lorg/springframework/beans/factory/support/BeanDefinitionRegistry;
       4: ifnull        36
       7: aload_1
       8: ldc           #4                  // String referenceAnnotationBeanPostProcessor
      10: ldc           #3                  // class org/apache/dubbo/config/spring/beans/factory/annotation/ReferenceAnnotationBeanPostProcessor
      12: invokeinterface #5,  3            // InterfaceMethod org/springframework/beans/factory/config/ConfigurableListableBeanFactory.getBean:(Ljava/lang/String;Ljava/lang/Class;)Ljava/lang/Object;
      17: checkcast     #3                  // class org/apache/dubbo/config/spring/beans/factory/annotation/ReferenceAnnotationBeanPostProcessor
      20: astore_2
      21: aload_1
      22: aload_2
      23: invokeinterface #6,  2            // InterfaceMethod org/springframework/beans/factory/config/ConfigurableListableBeanFactory.addBeanPostProcessor:(Lorg/springframework/beans/factory/config/BeanPostProcessor;)V
      28: aload_1
      29: aload_0
      30: getfield      #2                  // Field registry:Lorg/springframework/beans/factory/support/BeanDefinitionRegistry;
      33: invokestatic  #7                  // InterfaceMethod org/apache/dubbo/config/spring/util/DubboBeanUtils.registerPlaceholderConfigurerBeanIfNotExists:(Lorg/springframework/beans/factory/config/ConfigurableListableBeanFactory;Lorg/springframework/beans/factory/support/BeanDefinitionRegistry;)V
      36: aload_1
      37: invokestatic  #8                  // InterfaceMethod org/apache/dubbo/config/spring/util/DubboBeanUtils.getApplicationModel:(Lorg/springframework/beans/factory/BeanFactory;)Lorg/apache/dubbo/rpc/model/ApplicationModel;
      40: astore_2
      41: aload_1
      42: invokestatic  #9                  // InterfaceMethod org/apache/dubbo/config/spring/util/DubboBeanUtils.getModuleModel:(Lorg/springframework/beans/factory/BeanFactory;)Lorg/apache/dubbo/rpc/model/ModuleModel;
      45: astore_3
      46: aload_2
      47: invokestatic  #10                 // Method org/apache/dubbo/config/spring/extension/SpringExtensionInjector.get:(Lorg/apache/dubbo/common/extension/ExtensionAccessor;)Lorg/apache/dubbo/config/spring/extension/SpringExtensionInjector;
      50: aload_0
      51: getfield      #11                 // Field applicationContext:Lorg/springframework/context/ApplicationContext;
      54: invokevirtual #12                 // Method org/apache/dubbo/config/spring/extension/SpringExtensionInjector.init:(Lorg/springframework/context/ApplicationContext;)V
      57: aload_3
      58: invokestatic  #10                 // Method org/apache/dubbo/config/spring/extension/SpringExtensionInjector.get:(Lorg/apache/dubbo/common/extension/ExtensionAccessor;)Lorg/apache/dubbo/config/spring/extension/SpringExtensionInjector;
      61: aload_0
      62: getfield      #11                 // Field applicationContext:Lorg/springframework/context/ApplicationContext;
      65: invokevirtual #12                 // Method org/apache/dubbo/config/spring/extension/SpringExtensionInjector.init:(Lorg/springframework/context/ApplicationContext;)V
      68: aload_1
      69: invokestatic  #13                 // InterfaceMethod org/apache/dubbo/config/spring/util/DubboBeanUtils.getInitializationContext:(Lorg/springframework/beans/factory/BeanFactory;)Lorg/apache/dubbo/config/spring/context/DubboSpringInitContext;
      72: aload_0
      73: getfield      #11                 // Field applicationContext:Lorg/springframework/context/ApplicationContext;
      76: invokevirtual #14                 // Method org/apache/dubbo/config/spring/context/DubboSpringInitContext.setApplicationContext:(Lorg/springframework/context/ApplicationContext;)V
      79: aload_0
      80: getfield      #11                 // Field applicationContext:Lorg/springframework/context/ApplicationContext;
      83: invokeinterface #15,  1           // InterfaceMethod org/springframework/context/ApplicationContext.getEnvironment:()Lorg/springframework/core/env/Environment;
      88: checkcast     #16                 // class org/springframework/core/env/ConfigurableEnvironment
      91: astore        4
      93: aload         4
      95: invokestatic  #17                 // Method org/apache/dubbo/config/spring/util/EnvironmentUtils.filterDubboProperties:(Lorg/springframework/core/env/ConfigurableEnvironment;)Ljava/util/SortedMap;
      98: astore        5
     100: aload_2
     101: invokevirtual #18                 // Method org/apache/dubbo/rpc/model/ApplicationModel.getModelEnvironment:()Lorg/apache/dubbo/common/config/Environment;
     104: aload         5
     106: invokevirtual #19                 // Method org/apache/dubbo/common/config/Environment.setAppConfigMap:(Ljava/util/Map;)V
     109: aload_1
     110: ldc           #21                 // String dubboConfigManager
     112: aload_2
     113: invokevirtual #22                 // Method org/apache/dubbo/rpc/model/ApplicationModel.getApplicationConfigManager:()Lorg/apache/dubbo/config/context/ConfigManager;
     116: invokeinterface #23,  3           // InterfaceMethod org/springframework/beans/factory/config/ConfigurableListableBeanFactory.registerSingleton:(Ljava/lang/String;Ljava/lang/Object;)V
     121: aload_0
     122: getfield      #2                  // Field registry:Lorg/springframework/beans/factory/support/BeanDefinitionRegistry;
     125: ifnull        139
     128: aload_0
     129: getfield      #2                  // Field registry:Lorg/springframework/beans/factory/support/BeanDefinitionRegistry;
     132: ldc           #25                 // String dubboInfraBeanRegisterPostProcessor
     134: invokeinterface #26,  2           // InterfaceMethod org/springframework/beans/factory/support/BeanDefinitionRegistry.removeBeanDefinition:(Ljava/lang/String;)V
     139: return

  public void setApplicationContext(org.springframework.context.ApplicationContext) throws org.springframework.beans.BeansException;
    Code:
       0: aload_0
       1: aload_1
       2: putfield      #11                 // Field applicationContext:Lorg/springframework/context/ApplicationContext;
       5: return
}
