Compiled from "DubboBootstrapStartStopListenerSpringAdapter.java"
public class org.apache.dubbo.config.spring.context.DubboBootstrapStartStopListenerSpringAdapter implements org.apache.dubbo.config.bootstrap.DubboBootstrapStartStopListener {
  static org.springframework.context.ApplicationContext applicationContext;

  public org.apache.dubbo.config.spring.context.DubboBootstrapStartStopListenerSpringAdapter();
    Code:
       0: aload_0
       1: invokespecial #1                  // Method java/lang/Object."<init>":()V
       4: return

  public void onStart(org.apache.dubbo.config.bootstrap.DubboBootstrap);
    Code:
       0: getstatic     #2                  // Field applicationContext:Lorg/springframework/context/ApplicationContext;
       3: ifnull        22
       6: getstatic     #2                  // Field applicationContext:Lorg/springframework/context/ApplicationContext;
       9: new           #3                  // class org/apache/dubbo/config/spring/context/event/DubboBootstrapStatedEvent
      12: dup
      13: aload_1
      14: invokespecial #4                  // Method org/apache/dubbo/config/spring/context/event/DubboBootstrapStatedEvent."<init>":(Lorg/apache/dubbo/config/bootstrap/DubboBootstrap;)V
      17: invokeinterface #5,  2            // InterfaceMethod org/springframework/context/ApplicationContext.publishEvent:(Lorg/springframework/context/ApplicationEvent;)V
      22: return

  public void onStop(org.apache.dubbo.config.bootstrap.DubboBootstrap);
    Code:
       0: getstatic     #2                  // Field applicationContext:Lorg/springframework/context/ApplicationContext;
       3: ifnull        22
       6: getstatic     #2                  // Field applicationContext:Lorg/springframework/context/ApplicationContext;
       9: new           #6                  // class org/apache/dubbo/config/spring/context/event/DubboBootstrapStopedEvent
      12: dup
      13: aload_1
      14: invokespecial #7                  // Method org/apache/dubbo/config/spring/context/event/DubboBootstrapStopedEvent."<init>":(Lorg/apache/dubbo/config/bootstrap/DubboBootstrap;)V
      17: invokeinterface #5,  2            // InterfaceMethod org/springframework/context/ApplicationContext.publishEvent:(Lorg/springframework/context/ApplicationEvent;)V
      22: return
}
