Compiled from "DubboDeployApplicationListener.java"
public class org.apache.dubbo.config.spring.context.DubboDeployApplicationListener implements org.springframework.context.ApplicationListener<org.springframework.context.event.ApplicationContextEvent>, org.springframework.context.ApplicationContextAware, org.springframework.core.Ordered {
  private static final org.apache.dubbo.common.logger.ErrorTypeAwareLogger logger;

  private org.springframework.context.ApplicationContext applicationContext;

  private org.apache.dubbo.rpc.model.ApplicationModel applicationModel;

  private org.apache.dubbo.rpc.model.ModuleModel moduleModel;

  public org.apache.dubbo.config.spring.context.DubboDeployApplicationListener();
    Code:
       0: aload_0
       1: invokespecial #4                  // Method java/lang/Object."<init>":()V
       4: return

  public void setApplicationContext(org.springframework.context.ApplicationContext) throws org.springframework.beans.BeansException;
    Code:
       0: aload_0
       1: aload_1
       2: putfield      #5                  // Field applicationContext:Lorg/springframework/context/ApplicationContext;
       5: aload_0
       6: aload_1
       7: invokestatic  #6                  // InterfaceMethod org/apache/dubbo/config/spring/util/DubboBeanUtils.getApplicationModel:(Lorg/springframework/beans/factory/BeanFactory;)Lorg/apache/dubbo/rpc/model/ApplicationModel;
      10: putfield      #7                  // Field applicationModel:Lorg/apache/dubbo/rpc/model/ApplicationModel;
      13: aload_0
      14: aload_1
      15: invokestatic  #8                  // InterfaceMethod org/apache/dubbo/config/spring/util/DubboBeanUtils.getModuleModel:(Lorg/springframework/beans/factory/BeanFactory;)Lorg/apache/dubbo/rpc/model/ModuleModel;
      18: putfield      #9                  // Field moduleModel:Lorg/apache/dubbo/rpc/model/ModuleModel;
      21: aload_0
      22: getfield      #7                  // Field applicationModel:Lorg/apache/dubbo/rpc/model/ApplicationModel;
      25: invokevirtual #10                 // Method org/apache/dubbo/rpc/model/ApplicationModel.getDeployer:()Lorg/apache/dubbo/common/deploy/ApplicationDeployer;
      28: new           #11                 // class org/apache/dubbo/config/spring/context/DubboDeployApplicationListener$1
      31: dup
      32: aload_0
      33: invokespecial #12                 // Method org/apache/dubbo/config/spring/context/DubboDeployApplicationListener$1."<init>":(Lorg/apache/dubbo/config/spring/context/DubboDeployApplicationListener;)V
      36: invokeinterface #13,  2           // InterfaceMethod org/apache/dubbo/common/deploy/ApplicationDeployer.addDeployListener:(Lorg/apache/dubbo/common/deploy/DeployListener;)V
      41: return

  private void publishEvent(org.apache.dubbo.common.deploy.DeployState);
    Code:
       0: aload_0
       1: getfield      #5                  // Field applicationContext:Lorg/springframework/context/ApplicationContext;
       4: new           #14                 // class org/apache/dubbo/config/spring/context/event/DubboApplicationStateEvent
       7: dup
       8: aload_0
       9: getfield      #7                  // Field applicationModel:Lorg/apache/dubbo/rpc/model/ApplicationModel;
      12: aload_1
      13: invokespecial #15                 // Method org/apache/dubbo/config/spring/context/event/DubboApplicationStateEvent."<init>":(Lorg/apache/dubbo/rpc/model/ApplicationModel;Lorg/apache/dubbo/common/deploy/DeployState;)V
      16: invokeinterface #16,  2           // InterfaceMethod org/springframework/context/ApplicationContext.publishEvent:(Lorg/springframework/context/ApplicationEvent;)V
      21: return

  private void publishEvent(org.apache.dubbo.common.deploy.DeployState, java.lang.Throwable);
    Code:
       0: aload_0
       1: getfield      #5                  // Field applicationContext:Lorg/springframework/context/ApplicationContext;
       4: new           #14                 // class org/apache/dubbo/config/spring/context/event/DubboApplicationStateEvent
       7: dup
       8: aload_0
       9: getfield      #7                  // Field applicationModel:Lorg/apache/dubbo/rpc/model/ApplicationModel;
      12: aload_1
      13: aload_2
      14: invokespecial #17                 // Method org/apache/dubbo/config/spring/context/event/DubboApplicationStateEvent."<init>":(Lorg/apache/dubbo/rpc/model/ApplicationModel;Lorg/apache/dubbo/common/deploy/DeployState;Ljava/lang/Throwable;)V
      17: invokeinterface #16,  2           // InterfaceMethod org/springframework/context/ApplicationContext.publishEvent:(Lorg/springframework/context/ApplicationEvent;)V
      22: return

  public void onApplicationEvent(org.springframework.context.event.ApplicationContextEvent);
    Code:
       0: aload_0
       1: getfield      #5                  // Field applicationContext:Lorg/springframework/context/ApplicationContext;
       4: aload_1
       5: invokevirtual #18                 // Method org/springframework/context/event/ApplicationContextEvent.getSource:()Ljava/lang/Object;
       8: invokestatic  #19                 // Method org/springframework/util/ObjectUtils.nullSafeEquals:(Ljava/lang/Object;Ljava/lang/Object;)Z
      11: ifeq          47
      14: aload_1
      15: instanceof    #20                 // class org/springframework/context/event/ContextRefreshedEvent
      18: ifeq          32
      21: aload_0
      22: aload_1
      23: checkcast     #20                 // class org/springframework/context/event/ContextRefreshedEvent
      26: invokespecial #21                 // Method onContextRefreshedEvent:(Lorg/springframework/context/event/ContextRefreshedEvent;)V
      29: goto          47
      32: aload_1
      33: instanceof    #22                 // class org/springframework/context/event/ContextClosedEvent
      36: ifeq          47
      39: aload_0
      40: aload_1
      41: checkcast     #22                 // class org/springframework/context/event/ContextClosedEvent
      44: invokespecial #23                 // Method onContextClosedEvent:(Lorg/springframework/context/event/ContextClosedEvent;)V
      47: return

  private void onContextRefreshedEvent(org.springframework.context.event.ContextRefreshedEvent);
    Code:
       0: aload_0
       1: getfield      #9                  // Field moduleModel:Lorg/apache/dubbo/rpc/model/ModuleModel;
       4: invokevirtual #24                 // Method org/apache/dubbo/rpc/model/ModuleModel.getDeployer:()Lorg/apache/dubbo/common/deploy/ModuleDeployer;
       7: astore_2
       8: aload_2
       9: ldc           #25                 // String Module deployer is null
      11: invokestatic  #26                 // Method org/apache/dubbo/common/utils/Assert.notNull:(Ljava/lang/Object;Ljava/lang/String;)V
      14: aload_2
      15: invokeinterface #27,  1           // InterfaceMethod org/apache/dubbo/common/deploy/ModuleDeployer.start:()Ljava/util/concurrent/Future;
      20: astore_3
      21: aload_2
      22: invokeinterface #28,  1           // InterfaceMethod org/apache/dubbo/common/deploy/ModuleDeployer.isBackground:()Z
      27: ifne          123
      30: aload_3
      31: invokeinterface #29,  1           // InterfaceMethod java/util/concurrent/Future.get:()Ljava/lang/Object;
      36: pop
      37: goto          123
      40: astore        4
      42: getstatic     #31                 // Field logger:Lorg/apache/dubbo/common/logger/ErrorTypeAwareLogger;
      45: ldc           #32                 // String 5-14
      47: ldc           #33                 // String
      49: ldc           #33                 // String
      51: new           #34                 // class java/lang/StringBuilder
      54: dup
      55: invokespecial #35                 // Method java/lang/StringBuilder."<init>":()V
      58: ldc           #36                 // String Interrupted while waiting for dubbo module start:
      60: invokevirtual #37                 // Method java/lang/StringBuilder.append:(Ljava/lang/String;)Ljava/lang/StringBuilder;
      63: aload         4
      65: invokevirtual #38                 // Method java/lang/InterruptedException.getMessage:()Ljava/lang/String;
      68: invokevirtual #37                 // Method java/lang/StringBuilder.append:(Ljava/lang/String;)Ljava/lang/StringBuilder;
      71: invokevirtual #39                 // Method java/lang/StringBuilder.toString:()Ljava/lang/String;
      74: invokeinterface #40,  5           // InterfaceMethod org/apache/dubbo/common/logger/ErrorTypeAwareLogger.warn:(Ljava/lang/String;Ljava/lang/String;Ljava/lang/String;Ljava/lang/String;)V
      79: goto          123
      82: astore        4
      84: getstatic     #31                 // Field logger:Lorg/apache/dubbo/common/logger/ErrorTypeAwareLogger;
      87: ldc           #32                 // String 5-14
      89: ldc           #33                 // String
      91: ldc           #33                 // String
      93: new           #34                 // class java/lang/StringBuilder
      96: dup
      97: invokespecial #35                 // Method java/lang/StringBuilder."<init>":()V
     100: ldc           #42                 // String An error occurred while waiting for dubbo module start:
     102: invokevirtual #37                 // Method java/lang/StringBuilder.append:(Ljava/lang/String;)Ljava/lang/StringBuilder;
     105: aload         4
     107: invokevirtual #43                 // Method java/lang/Exception.getMessage:()Ljava/lang/String;
     110: invokevirtual #37                 // Method java/lang/StringBuilder.append:(Ljava/lang/String;)Ljava/lang/StringBuilder;
     113: invokevirtual #39                 // Method java/lang/StringBuilder.toString:()Ljava/lang/String;
     116: aload         4
     118: invokeinterface #44,  6           // InterfaceMethod org/apache/dubbo/common/logger/ErrorTypeAwareLogger.warn:(Ljava/lang/String;Ljava/lang/String;Ljava/lang/String;Ljava/lang/String;Ljava/lang/Throwable;)V
     123: return
    Exception table:
       from    to  target type
          30    37    40   Class java/lang/InterruptedException
          30    37    82   Class java/lang/Exception

  private void onContextClosedEvent(org.springframework.context.event.ContextClosedEvent);
    Code:
       0: aload_0
       1: getfield      #9                  // Field moduleModel:Lorg/apache/dubbo/rpc/model/ModuleModel;
       4: ldc           #46                 // String keepRunningOnSpringClosed
       6: invokevirtual #47                 // Method org/apache/dubbo/rpc/model/ModuleModel.getAttribute:(Ljava/lang/String;)Ljava/lang/Object;
       9: astore_2
      10: aload_2
      11: invokestatic  #48                 // Method java/lang/String.valueOf:(Ljava/lang/Object;)Ljava/lang/String;
      14: invokestatic  #49                 // Method java/lang/Boolean.parseBoolean:(Ljava/lang/String;)Z
      17: istore_3
      18: iload_3
      19: ifne          39
      22: aload_0
      23: getfield      #9                  // Field moduleModel:Lorg/apache/dubbo/rpc/model/ModuleModel;
      26: invokevirtual #50                 // Method org/apache/dubbo/rpc/model/ModuleModel.isDestroyed:()Z
      29: ifne          39
      32: aload_0
      33: getfield      #9                  // Field moduleModel:Lorg/apache/dubbo/rpc/model/ModuleModel;
      36: invokevirtual #51                 // Method org/apache/dubbo/rpc/model/ModuleModel.destroy:()V
      39: goto          80
      42: astore_2
      43: getstatic     #31                 // Field logger:Lorg/apache/dubbo/common/logger/ErrorTypeAwareLogger;
      46: ldc           #52                 // String 5-20
      48: ldc           #33                 // String
      50: ldc           #33                 // String
      52: new           #34                 // class java/lang/StringBuilder
      55: dup
      56: invokespecial #35                 // Method java/lang/StringBuilder."<init>":()V
      59: ldc           #53                 // String Unexpected error occurred when stop dubbo module:
      61: invokevirtual #37                 // Method java/lang/StringBuilder.append:(Ljava/lang/String;)Ljava/lang/StringBuilder;
      64: aload_2
      65: invokevirtual #43                 // Method java/lang/Exception.getMessage:()Ljava/lang/String;
      68: invokevirtual #37                 // Method java/lang/StringBuilder.append:(Ljava/lang/String;)Ljava/lang/StringBuilder;
      71: invokevirtual #39                 // Method java/lang/StringBuilder.toString:()Ljava/lang/String;
      74: aload_2
      75: invokeinterface #54,  6           // InterfaceMethod org/apache/dubbo/common/logger/ErrorTypeAwareLogger.error:(Ljava/lang/String;Ljava/lang/String;Ljava/lang/String;Ljava/lang/String;Ljava/lang/Throwable;)V
      80: aload_1
      81: invokevirtual #55                 // Method org/springframework/context/event/ContextClosedEvent.getApplicationContext:()Lorg/springframework/context/ApplicationContext;
      84: invokestatic  #56                 // Method org/apache/dubbo/config/spring/context/DubboSpringInitializer.remove:(Lorg/springframework/context/ApplicationContext;)Z
      87: pop
      88: return
    Exception table:
       from    to  target type
           0    39    42   Class java/lang/Exception

  public int getOrder();
    Code:
       0: ldc           #58                 // int 2147483647
       2: ireturn

  public void onApplicationEvent(org.springframework.context.ApplicationEvent);
    Code:
       0: aload_0
       1: aload_1
       2: checkcast     #59                 // class org/springframework/context/event/ApplicationContextEvent
       5: invokevirtual #60                 // Method onApplicationEvent:(Lorg/springframework/context/event/ApplicationContextEvent;)V
       8: return

  static void access$000(org.apache.dubbo.config.spring.context.DubboDeployApplicationListener, org.apache.dubbo.common.deploy.DeployState);
    Code:
       0: aload_0
       1: aload_1
       2: invokespecial #3                  // Method publishEvent:(Lorg/apache/dubbo/common/deploy/DeployState;)V
       5: return

  static void access$100(org.apache.dubbo.config.spring.context.DubboDeployApplicationListener, org.apache.dubbo.common.deploy.DeployState, java.lang.Throwable);
    Code:
       0: aload_0
       1: aload_1
       2: aload_2
       3: invokespecial #2                  // Method publishEvent:(Lorg/apache/dubbo/common/deploy/DeployState;Ljava/lang/Throwable;)V
       6: return

  static {};
    Code:
       0: ldc           #61                 // class org/apache/dubbo/config/spring/context/DubboDeployApplicationListener
       2: invokestatic  #62                 // Method org/apache/dubbo/common/logger/LoggerFactory.getErrorTypeAwareLogger:(Ljava/lang/Class;)Lorg/apache/dubbo/common/logger/ErrorTypeAwareLogger;
       5: putstatic     #31                 // Field logger:Lorg/apache/dubbo/common/logger/ErrorTypeAwareLogger;
       8: return
}
