Compiled from "DubboSpringInitializer.java"
public class org.apache.dubbo.config.spring.context.DubboSpringInitializer {
  private static final org.apache.dubbo.common.logger.Logger logger;

  private static final java.util.Map<org.springframework.beans.factory.support.BeanDefinitionRegistry, org.apache.dubbo.config.spring.context.DubboSpringInitContext> contextMap;

  private org.apache.dubbo.config.spring.context.DubboSpringInitializer();
    Code:
       0: aload_0
       1: invokespecial #1                  // Method java/lang/Object."<init>":()V
       4: return

  public static void initialize(org.springframework.beans.factory.support.BeanDefinitionRegistry);
    Code:
       0: getstatic     #2                  // Field contextMap:Ljava/util/Map;
       3: aload_0
       4: new           #3                  // class org/apache/dubbo/config/spring/context/DubboSpringInitContext
       7: dup
       8: invokespecial #4                  // Method org/apache/dubbo/config/spring/context/DubboSpringInitContext."<init>":()V
      11: invokeinterface #5,  3            // InterfaceMethod java/util/Map.putIfAbsent:(Ljava/lang/Object;Ljava/lang/Object;)Ljava/lang/Object;
      16: ifnull        20
      19: return
      20: getstatic     #2                  // Field contextMap:Ljava/util/Map;
      23: aload_0
      24: invokeinterface #6,  2            // InterfaceMethod java/util/Map.get:(Ljava/lang/Object;)Ljava/lang/Object;
      29: checkcast     #3                  // class org/apache/dubbo/config/spring/context/DubboSpringInitContext
      32: astore_1
      33: aload_0
      34: invokestatic  #7                  // Method findBeanFactory:(Lorg/springframework/beans/factory/support/BeanDefinitionRegistry;)Lorg/springframework/beans/factory/config/ConfigurableListableBeanFactory;
      37: astore_2
      38: aload_1
      39: aload_0
      40: aload_2
      41: invokestatic  #8                  // Method initContext:(Lorg/apache/dubbo/config/spring/context/DubboSpringInitContext;Lorg/springframework/beans/factory/support/BeanDefinitionRegistry;Lorg/springframework/beans/factory/config/ConfigurableListableBeanFactory;)V
      44: return

  public static boolean remove(org.springframework.beans.factory.support.BeanDefinitionRegistry);
    Code:
       0: getstatic     #2                  // Field contextMap:Ljava/util/Map;
       3: aload_0
       4: invokeinterface #9,  2            // InterfaceMethod java/util/Map.remove:(Ljava/lang/Object;)Ljava/lang/Object;
       9: ifnull        16
      12: iconst_1
      13: goto          17
      16: iconst_0
      17: ireturn

  public static boolean remove(org.springframework.context.ApplicationContext);
    Code:
       0: getstatic     #2                  // Field contextMap:Ljava/util/Map;
       3: invokeinterface #10,  1           // InterfaceMethod java/util/Map.entrySet:()Ljava/util/Set;
       8: invokeinterface #11,  1           // InterfaceMethod java/util/Set.iterator:()Ljava/util/Iterator;
      13: astore_1
      14: aload_1
      15: invokeinterface #12,  1           // InterfaceMethod java/util/Iterator.hasNext:()Z
      20: ifeq          152
      23: aload_1
      24: invokeinterface #13,  1           // InterfaceMethod java/util/Iterator.next:()Ljava/lang/Object;
      29: checkcast     #14                 // class java/util/Map$Entry
      32: astore_2
      33: aload_2
      34: invokeinterface #15,  1           // InterfaceMethod java/util/Map$Entry.getValue:()Ljava/lang/Object;
      39: checkcast     #3                  // class org/apache/dubbo/config/spring/context/DubboSpringInitContext
      42: astore_3
      43: aload_3
      44: invokevirtual #16                 // Method org/apache/dubbo/config/spring/context/DubboSpringInitContext.getApplicationContext:()Lorg/springframework/context/ApplicationContext;
      47: aload_0
      48: if_acmpeq     77
      51: aload_3
      52: invokevirtual #17                 // Method org/apache/dubbo/config/spring/context/DubboSpringInitContext.getBeanFactory:()Lorg/springframework/beans/factory/config/ConfigurableListableBeanFactory;
      55: aload_0
      56: invokeinterface #18,  1           // InterfaceMethod org/springframework/context/ApplicationContext.getAutowireCapableBeanFactory:()Lorg/springframework/beans/factory/config/AutowireCapableBeanFactory;
      61: if_acmpeq     77
      64: aload_3
      65: invokevirtual #19                 // Method org/apache/dubbo/config/spring/context/DubboSpringInitContext.getRegistry:()Lorg/springframework/beans/factory/support/BeanDefinitionRegistry;
      68: aload_0
      69: invokeinterface #18,  1           // InterfaceMethod org/springframework/context/ApplicationContext.getAutowireCapableBeanFactory:()Lorg/springframework/beans/factory/config/AutowireCapableBeanFactory;
      74: if_acmpne     149
      77: getstatic     #2                  // Field contextMap:Ljava/util/Map;
      80: aload_2
      81: invokeinterface #20,  1           // InterfaceMethod java/util/Map$Entry.getKey:()Ljava/lang/Object;
      86: invokeinterface #9,  2            // InterfaceMethod java/util/Map.remove:(Ljava/lang/Object;)Ljava/lang/Object;
      91: checkcast     #3                  // class org/apache/dubbo/config/spring/context/DubboSpringInitContext
      94: astore        4
      96: getstatic     #21                 // Field logger:Lorg/apache/dubbo/common/logger/Logger;
      99: new           #22                 // class java/lang/StringBuilder
     102: dup
     103: invokespecial #23                 // Method java/lang/StringBuilder."<init>":()V
     106: ldc           #24                 // String Unbind
     108: invokevirtual #25                 // Method java/lang/StringBuilder.append:(Ljava/lang/String;)Ljava/lang/StringBuilder;
     111: aload         4
     113: invokevirtual #26                 // Method org/apache/dubbo/config/spring/context/DubboSpringInitContext.getModuleModel:()Lorg/apache/dubbo/rpc/model/ModuleModel;
     116: invokestatic  #27                 // Method safeGetModelDesc:(Lorg/apache/dubbo/rpc/model/ScopeModel;)Ljava/lang/String;
     119: invokevirtual #25                 // Method java/lang/StringBuilder.append:(Ljava/lang/String;)Ljava/lang/StringBuilder;
     122: ldc           #28                 // String  from spring container:
     124: invokevirtual #25                 // Method java/lang/StringBuilder.append:(Ljava/lang/String;)Ljava/lang/StringBuilder;
     127: aload_2
     128: invokeinterface #20,  1           // InterfaceMethod java/util/Map$Entry.getKey:()Ljava/lang/Object;
     133: invokestatic  #29                 // Method org/springframework/util/ObjectUtils.identityToString:(Ljava/lang/Object;)Ljava/lang/String;
     136: invokevirtual #25                 // Method java/lang/StringBuilder.append:(Ljava/lang/String;)Ljava/lang/StringBuilder;
     139: invokevirtual #30                 // Method java/lang/StringBuilder.toString:()Ljava/lang/String;
     142: invokeinterface #31,  2           // InterfaceMethod org/apache/dubbo/common/logger/Logger.info:(Ljava/lang/String;)V
     147: iconst_1
     148: ireturn
     149: goto          14
     152: iconst_0
     153: ireturn

  static java.util.Map<org.springframework.beans.factory.support.BeanDefinitionRegistry, org.apache.dubbo.config.spring.context.DubboSpringInitContext> getContextMap();
    Code:
       0: getstatic     #2                  // Field contextMap:Ljava/util/Map;
       3: areturn

  static org.apache.dubbo.config.spring.context.DubboSpringInitContext findBySpringContext(org.springframework.context.ApplicationContext);
    Code:
       0: getstatic     #2                  // Field contextMap:Ljava/util/Map;
       3: invokeinterface #10,  1           // InterfaceMethod java/util/Map.entrySet:()Ljava/util/Set;
       8: invokeinterface #11,  1           // InterfaceMethod java/util/Set.iterator:()Ljava/util/Iterator;
      13: astore_1
      14: aload_1
      15: invokeinterface #12,  1           // InterfaceMethod java/util/Iterator.hasNext:()Z
      20: ifeq          56
      23: aload_1
      24: invokeinterface #13,  1           // InterfaceMethod java/util/Iterator.next:()Ljava/lang/Object;
      29: checkcast     #14                 // class java/util/Map$Entry
      32: astore_2
      33: aload_2
      34: invokeinterface #15,  1           // InterfaceMethod java/util/Map$Entry.getValue:()Ljava/lang/Object;
      39: checkcast     #3                  // class org/apache/dubbo/config/spring/context/DubboSpringInitContext
      42: astore_3
      43: aload_3
      44: invokevirtual #16                 // Method org/apache/dubbo/config/spring/context/DubboSpringInitContext.getApplicationContext:()Lorg/springframework/context/ApplicationContext;
      47: aload_0
      48: if_acmpne     53
      51: aload_3
      52: areturn
      53: goto          14
      56: aconst_null
      57: areturn

  private static void initContext(org.apache.dubbo.config.spring.context.DubboSpringInitContext, org.springframework.beans.factory.support.BeanDefinitionRegistry, org.springframework.beans.factory.config.ConfigurableListableBeanFactory);
    Code:
       0: aload_0
       1: aload_1
       2: invokevirtual #32                 // Method org/apache/dubbo/config/spring/context/DubboSpringInitContext.setRegistry:(Lorg/springframework/beans/factory/support/BeanDefinitionRegistry;)V
       5: aload_0
       6: aload_2
       7: invokevirtual #33                 // Method org/apache/dubbo/config/spring/context/DubboSpringInitContext.setBeanFactory:(Lorg/springframework/beans/factory/config/ConfigurableListableBeanFactory;)V
      10: aload_0
      11: invokestatic  #34                 // Method customize:(Lorg/apache/dubbo/config/spring/context/DubboSpringInitContext;)V
      14: aload_0
      15: invokevirtual #26                 // Method org/apache/dubbo/config/spring/context/DubboSpringInitContext.getModuleModel:()Lorg/apache/dubbo/rpc/model/ModuleModel;
      18: astore_3
      19: aload_3
      20: ifnonnull     154
      23: invokestatic  #35                 // Method org/apache/dubbo/rpc/model/ApplicationModel.defaultModel:()Lorg/apache/dubbo/rpc/model/ApplicationModel;
      26: invokestatic  #36                 // Method findContextForApplication:(Lorg/apache/dubbo/rpc/model/ApplicationModel;)Lorg/apache/dubbo/config/spring/context/DubboSpringInitContext;
      29: ifnonnull     71
      32: invokestatic  #35                 // Method org/apache/dubbo/rpc/model/ApplicationModel.defaultModel:()Lorg/apache/dubbo/rpc/model/ApplicationModel;
      35: astore        4
      37: getstatic     #21                 // Field logger:Lorg/apache/dubbo/common/logger/Logger;
      40: new           #22                 // class java/lang/StringBuilder
      43: dup
      44: invokespecial #23                 // Method java/lang/StringBuilder."<init>":()V
      47: ldc           #37                 // String Use default application:
      49: invokevirtual #25                 // Method java/lang/StringBuilder.append:(Ljava/lang/String;)Ljava/lang/StringBuilder;
      52: aload         4
      54: invokestatic  #27                 // Method safeGetModelDesc:(Lorg/apache/dubbo/rpc/model/ScopeModel;)Ljava/lang/String;
      57: invokevirtual #25                 // Method java/lang/StringBuilder.append:(Ljava/lang/String;)Ljava/lang/StringBuilder;
      60: invokevirtual #30                 // Method java/lang/StringBuilder.toString:()Ljava/lang/String;
      63: invokeinterface #31,  2           // InterfaceMethod org/apache/dubbo/common/logger/Logger.info:(Ljava/lang/String;)V
      68: goto          110
      71: invokestatic  #38                 // Method org/apache/dubbo/rpc/model/FrameworkModel.defaultModel:()Lorg/apache/dubbo/rpc/model/FrameworkModel;
      74: invokevirtual #39                 // Method org/apache/dubbo/rpc/model/FrameworkModel.newApplication:()Lorg/apache/dubbo/rpc/model/ApplicationModel;
      77: astore        4
      79: getstatic     #21                 // Field logger:Lorg/apache/dubbo/common/logger/Logger;
      82: new           #22                 // class java/lang/StringBuilder
      85: dup
      86: invokespecial #23                 // Method java/lang/StringBuilder."<init>":()V
      89: ldc           #40                 // String Create new application:
      91: invokevirtual #25                 // Method java/lang/StringBuilder.append:(Ljava/lang/String;)Ljava/lang/StringBuilder;
      94: aload         4
      96: invokestatic  #27                 // Method safeGetModelDesc:(Lorg/apache/dubbo/rpc/model/ScopeModel;)Ljava/lang/String;
      99: invokevirtual #25                 // Method java/lang/StringBuilder.append:(Ljava/lang/String;)Ljava/lang/StringBuilder;
     102: invokevirtual #30                 // Method java/lang/StringBuilder.toString:()Ljava/lang/String;
     105: invokeinterface #31,  2           // InterfaceMethod org/apache/dubbo/common/logger/Logger.info:(Ljava/lang/String;)V
     110: aload         4
     112: invokevirtual #41                 // Method org/apache/dubbo/rpc/model/ApplicationModel.getDefaultModule:()Lorg/apache/dubbo/rpc/model/ModuleModel;
     115: astore_3
     116: aload_0
     117: aload_3
     118: invokevirtual #42                 // Method org/apache/dubbo/config/spring/context/DubboSpringInitContext.setModuleModel:(Lorg/apache/dubbo/rpc/model/ModuleModel;)V
     121: getstatic     #21                 // Field logger:Lorg/apache/dubbo/common/logger/Logger;
     124: new           #22                 // class java/lang/StringBuilder
     127: dup
     128: invokespecial #23                 // Method java/lang/StringBuilder."<init>":()V
     131: ldc           #43                 // String Use default module model of target application:
     133: invokevirtual #25                 // Method java/lang/StringBuilder.append:(Ljava/lang/String;)Ljava/lang/StringBuilder;
     136: aload_3
     137: invokestatic  #27                 // Method safeGetModelDesc:(Lorg/apache/dubbo/rpc/model/ScopeModel;)Ljava/lang/String;
     140: invokevirtual #25                 // Method java/lang/StringBuilder.append:(Ljava/lang/String;)Ljava/lang/StringBuilder;
     143: invokevirtual #30                 // Method java/lang/StringBuilder.toString:()Ljava/lang/String;
     146: invokeinterface #31,  2           // InterfaceMethod org/apache/dubbo/common/logger/Logger.info:(Ljava/lang/String;)V
     151: goto          184
     154: getstatic     #21                 // Field logger:Lorg/apache/dubbo/common/logger/Logger;
     157: new           #22                 // class java/lang/StringBuilder
     160: dup
     161: invokespecial #23                 // Method java/lang/StringBuilder."<init>":()V
     164: ldc           #44                 // String Use module model from customizer:
     166: invokevirtual #25                 // Method java/lang/StringBuilder.append:(Ljava/lang/String;)Ljava/lang/StringBuilder;
     169: aload_3
     170: invokestatic  #27                 // Method safeGetModelDesc:(Lorg/apache/dubbo/rpc/model/ScopeModel;)Ljava/lang/String;
     173: invokevirtual #25                 // Method java/lang/StringBuilder.append:(Ljava/lang/String;)Ljava/lang/StringBuilder;
     176: invokevirtual #30                 // Method java/lang/StringBuilder.toString:()Ljava/lang/String;
     179: invokeinterface #31,  2           // InterfaceMethod org/apache/dubbo/common/logger/Logger.info:(Ljava/lang/String;)V
     184: getstatic     #21                 // Field logger:Lorg/apache/dubbo/common/logger/Logger;
     187: new           #22                 // class java/lang/StringBuilder
     190: dup
     191: invokespecial #23                 // Method java/lang/StringBuilder."<init>":()V
     194: ldc           #45                 // String Bind
     196: invokevirtual #25                 // Method java/lang/StringBuilder.append:(Ljava/lang/String;)Ljava/lang/StringBuilder;
     199: aload_3
     200: invokestatic  #27                 // Method safeGetModelDesc:(Lorg/apache/dubbo/rpc/model/ScopeModel;)Ljava/lang/String;
     203: invokevirtual #25                 // Method java/lang/StringBuilder.append:(Ljava/lang/String;)Ljava/lang/StringBuilder;
     206: ldc           #46                 // String  to spring container:
     208: invokevirtual #25                 // Method java/lang/StringBuilder.append:(Ljava/lang/String;)Ljava/lang/StringBuilder;
     211: aload_1
     212: invokestatic  #29                 // Method org/springframework/util/ObjectUtils.identityToString:(Ljava/lang/Object;)Ljava/lang/String;
     215: invokevirtual #25                 // Method java/lang/StringBuilder.append:(Ljava/lang/String;)Ljava/lang/StringBuilder;
     218: invokevirtual #30                 // Method java/lang/StringBuilder.toString:()Ljava/lang/String;
     221: invokeinterface #31,  2           // InterfaceMethod org/apache/dubbo/common/logger/Logger.info:(Ljava/lang/String;)V
     226: aload_0
     227: invokevirtual #47                 // Method org/apache/dubbo/config/spring/context/DubboSpringInitContext.getModuleAttributes:()Ljava/util/Map;
     230: invokeinterface #48,  1           // InterfaceMethod java/util/Map.size:()I
     235: ifle          254
     238: aload_0
     239: invokevirtual #26                 // Method org/apache/dubbo/config/spring/context/DubboSpringInitContext.getModuleModel:()Lorg/apache/dubbo/rpc/model/ModuleModel;
     242: invokevirtual #49                 // Method org/apache/dubbo/rpc/model/ModuleModel.getAttributes:()Ljava/util/Map;
     245: aload_0
     246: invokevirtual #47                 // Method org/apache/dubbo/config/spring/context/DubboSpringInitContext.getModuleAttributes:()Ljava/util/Map;
     249: invokeinterface #50,  2           // InterfaceMethod java/util/Map.putAll:(Ljava/util/Map;)V
     254: aload_2
     255: aload_0
     256: invokestatic  #51                 // Method registerContextBeans:(Lorg/springframework/beans/factory/config/ConfigurableListableBeanFactory;Lorg/apache/dubbo/config/spring/context/DubboSpringInitContext;)V
     259: aload_0
     260: invokevirtual #52                 // Method org/apache/dubbo/config/spring/context/DubboSpringInitContext.markAsBound:()V
     263: aload_3
     264: iconst_1
     265: invokevirtual #53                 // Method org/apache/dubbo/rpc/model/ModuleModel.setLifeCycleManagedExternally:(Z)V
     268: aload_1
     269: invokestatic  #54                 // InterfaceMethod org/apache/dubbo/config/spring/util/DubboBeanUtils.registerCommonBeans:(Lorg/springframework/beans/factory/support/BeanDefinitionRegistry;)V
     272: return

  private static java.lang.String safeGetModelDesc(org.apache.dubbo.rpc.model.ScopeModel);
    Code:
       0: aload_0
       1: ifnull        11
       4: aload_0
       5: invokevirtual #55                 // Method org/apache/dubbo/rpc/model/ScopeModel.getDesc:()Ljava/lang/String;
       8: goto          12
      11: aconst_null
      12: areturn

  private static org.springframework.beans.factory.config.ConfigurableListableBeanFactory findBeanFactory(org.springframework.beans.factory.support.BeanDefinitionRegistry);
    Code:
       0: aload_0
       1: instanceof    #56                 // class org/springframework/beans/factory/config/ConfigurableListableBeanFactory
       4: ifeq          15
       7: aload_0
       8: checkcast     #56                 // class org/springframework/beans/factory/config/ConfigurableListableBeanFactory
      11: astore_1
      12: goto          68
      15: aload_0
      16: instanceof    #57                 // class org/springframework/context/support/GenericApplicationContext
      19: ifeq          35
      22: aload_0
      23: checkcast     #57                 // class org/springframework/context/support/GenericApplicationContext
      26: astore_2
      27: aload_2
      28: invokevirtual #58                 // Method org/springframework/context/support/GenericApplicationContext.getBeanFactory:()Lorg/springframework/beans/factory/config/ConfigurableListableBeanFactory;
      31: astore_1
      32: goto          68
      35: new           #59                 // class java/lang/IllegalStateException
      38: dup
      39: new           #22                 // class java/lang/StringBuilder
      42: dup
      43: invokespecial #23                 // Method java/lang/StringBuilder."<init>":()V
      46: ldc           #60                 // String Can not find Spring BeanFactory from registry:
      48: invokevirtual #25                 // Method java/lang/StringBuilder.append:(Ljava/lang/String;)Ljava/lang/StringBuilder;
      51: aload_0
      52: invokevirtual #61                 // Method java/lang/Object.getClass:()Ljava/lang/Class;
      55: invokevirtual #62                 // Method java/lang/Class.getName:()Ljava/lang/String;
      58: invokevirtual #25                 // Method java/lang/StringBuilder.append:(Ljava/lang/String;)Ljava/lang/StringBuilder;
      61: invokevirtual #30                 // Method java/lang/StringBuilder.toString:()Ljava/lang/String;
      64: invokespecial #63                 // Method java/lang/IllegalStateException."<init>":(Ljava/lang/String;)V
      67: athrow
      68: aload_1
      69: areturn

  private static void registerContextBeans(org.springframework.beans.factory.config.ConfigurableListableBeanFactory, org.apache.dubbo.config.spring.context.DubboSpringInitContext);
    Code:
       0: aload_0
       1: aload_1
       2: invokestatic  #64                 // Method registerSingleton:(Lorg/springframework/beans/factory/config/ConfigurableListableBeanFactory;Ljava/lang/Object;)V
       5: aload_0
       6: aload_1
       7: invokevirtual #65                 // Method org/apache/dubbo/config/spring/context/DubboSpringInitContext.getApplicationModel:()Lorg/apache/dubbo/rpc/model/ApplicationModel;
      10: invokestatic  #64                 // Method registerSingleton:(Lorg/springframework/beans/factory/config/ConfigurableListableBeanFactory;Ljava/lang/Object;)V
      13: aload_0
      14: aload_1
      15: invokevirtual #26                 // Method org/apache/dubbo/config/spring/context/DubboSpringInitContext.getModuleModel:()Lorg/apache/dubbo/rpc/model/ModuleModel;
      18: invokestatic  #64                 // Method registerSingleton:(Lorg/springframework/beans/factory/config/ConfigurableListableBeanFactory;Ljava/lang/Object;)V
      21: return

  private static void registerSingleton(org.springframework.beans.factory.config.ConfigurableListableBeanFactory, java.lang.Object);
    Code:
       0: aload_0
       1: aload_1
       2: invokevirtual #61                 // Method java/lang/Object.getClass:()Ljava/lang/Class;
       5: invokevirtual #62                 // Method java/lang/Class.getName:()Ljava/lang/String;
       8: aload_1
       9: invokeinterface #66,  3           // InterfaceMethod org/springframework/beans/factory/config/ConfigurableListableBeanFactory.registerSingleton:(Ljava/lang/String;Ljava/lang/Object;)V
      14: return

  private static org.apache.dubbo.config.spring.context.DubboSpringInitContext findContextForApplication(org.apache.dubbo.rpc.model.ApplicationModel);
    Code:
       0: getstatic     #2                  // Field contextMap:Ljava/util/Map;
       3: invokeinterface #67,  1           // InterfaceMethod java/util/Map.values:()Ljava/util/Collection;
       8: invokeinterface #68,  1           // InterfaceMethod java/util/Collection.iterator:()Ljava/util/Iterator;
      13: astore_1
      14: aload_1
      15: invokeinterface #12,  1           // InterfaceMethod java/util/Iterator.hasNext:()Z
      20: ifeq          46
      23: aload_1
      24: invokeinterface #13,  1           // InterfaceMethod java/util/Iterator.next:()Ljava/lang/Object;
      29: checkcast     #3                  // class org/apache/dubbo/config/spring/context/DubboSpringInitContext
      32: astore_2
      33: aload_2
      34: invokevirtual #65                 // Method org/apache/dubbo/config/spring/context/DubboSpringInitContext.getApplicationModel:()Lorg/apache/dubbo/rpc/model/ApplicationModel;
      37: aload_0
      38: if_acmpne     43
      41: aload_2
      42: areturn
      43: goto          14
      46: aconst_null
      47: areturn

  private static void customize(org.apache.dubbo.config.spring.context.DubboSpringInitContext);
    Code:
       0: invokestatic  #38                 // Method org/apache/dubbo/rpc/model/FrameworkModel.defaultModel:()Lorg/apache/dubbo/rpc/model/FrameworkModel;
       3: ldc           #69                 // class org/apache/dubbo/config/spring/context/DubboSpringInitCustomizer
       5: invokevirtual #70                 // Method org/apache/dubbo/rpc/model/FrameworkModel.getExtensionLoader:(Ljava/lang/Class;)Lorg/apache/dubbo/common/extension/ExtensionLoader;
       8: invokevirtual #71                 // Method org/apache/dubbo/common/extension/ExtensionLoader.getSupportedExtensionInstances:()Ljava/util/Set;
      11: astore_1
      12: aload_1
      13: invokeinterface #11,  1           // InterfaceMethod java/util/Set.iterator:()Ljava/util/Iterator;
      18: astore_2
      19: aload_2
      20: invokeinterface #12,  1           // InterfaceMethod java/util/Iterator.hasNext:()Z
      25: ifeq          48
      28: aload_2
      29: invokeinterface #13,  1           // InterfaceMethod java/util/Iterator.next:()Ljava/lang/Object;
      34: checkcast     #69                 // class org/apache/dubbo/config/spring/context/DubboSpringInitCustomizer
      37: astore_3
      38: aload_3
      39: aload_0
      40: invokeinterface #72,  2           // InterfaceMethod org/apache/dubbo/config/spring/context/DubboSpringInitCustomizer.customize:(Lorg/apache/dubbo/config/spring/context/DubboSpringInitContext;)V
      45: goto          19
      48: invokestatic  #73                 // Method org/apache/dubbo/config/spring/context/DubboSpringInitCustomizerHolder.get:()Lorg/apache/dubbo/config/spring/context/DubboSpringInitCustomizerHolder;
      51: astore_2
      52: aload_2
      53: invokevirtual #74                 // Method org/apache/dubbo/config/spring/context/DubboSpringInitCustomizerHolder.getCustomizers:()Ljava/util/Set;
      56: astore_1
      57: aload_1
      58: invokeinterface #11,  1           // InterfaceMethod java/util/Set.iterator:()Ljava/util/Iterator;
      63: astore_3
      64: aload_3
      65: invokeinterface #12,  1           // InterfaceMethod java/util/Iterator.hasNext:()Z
      70: ifeq          95
      73: aload_3
      74: invokeinterface #13,  1           // InterfaceMethod java/util/Iterator.next:()Ljava/lang/Object;
      79: checkcast     #69                 // class org/apache/dubbo/config/spring/context/DubboSpringInitCustomizer
      82: astore        4
      84: aload         4
      86: aload_0
      87: invokeinterface #72,  2           // InterfaceMethod org/apache/dubbo/config/spring/context/DubboSpringInitCustomizer.customize:(Lorg/apache/dubbo/config/spring/context/DubboSpringInitContext;)V
      92: goto          64
      95: aload_2
      96: invokevirtual #75                 // Method org/apache/dubbo/config/spring/context/DubboSpringInitCustomizerHolder.clearCustomizers:()V
      99: return

  static {};
    Code:
       0: ldc           #76                 // class org/apache/dubbo/config/spring/context/DubboSpringInitializer
       2: invokestatic  #77                 // Method org/apache/dubbo/common/logger/LoggerFactory.getLogger:(Ljava/lang/Class;)Lorg/apache/dubbo/common/logger/Logger;
       5: putstatic     #21                 // Field logger:Lorg/apache/dubbo/common/logger/Logger;
       8: new           #78                 // class java/util/concurrent/ConcurrentHashMap
      11: dup
      12: invokespecial #79                 // Method java/util/concurrent/ConcurrentHashMap."<init>":()V
      15: putstatic     #2                  // Field contextMap:Ljava/util/Map;
      18: return
}
