Compiled from "DubboDeployApplicationListener.java"
class org.apache.dubbo.config.spring.context.DubboDeployApplicationListener$1 extends org.apache.dubbo.common.deploy.DeployListenerAdapter<org.apache.dubbo.rpc.model.ApplicationModel> {
  final org.apache.dubbo.config.spring.context.DubboDeployApplicationListener this$0;

  org.apache.dubbo.config.spring.context.DubboDeployApplicationListener$1(org.apache.dubbo.config.spring.context.DubboDeployApplicationListener);
    Code:
       0: aload_0
       1: aload_1
       2: putfield      #1                  // Field this$0:Lorg/apache/dubbo/config/spring/context/DubboDeployApplicationListener;
       5: aload_0
       6: invokespecial #2                  // Method org/apache/dubbo/common/deploy/DeployListenerAdapter."<init>":()V
       9: return

  public void onStarting(org.apache.dubbo.rpc.model.ApplicationModel);
    Code:
       0: aload_0
       1: getfield      #1                  // Field this$0:Lorg/apache/dubbo/config/spring/context/DubboDeployApplicationListener;
       4: getstatic     #3                  // Field org/apache/dubbo/common/deploy/DeployState.STARTING:Lorg/apache/dubbo/common/deploy/DeployState;
       7: invokestatic  #4                  // Method org/apache/dubbo/config/spring/context/DubboDeployApplicationListener.access$000:(Lorg/apache/dubbo/config/spring/context/DubboDeployApplicationListener;Lorg/apache/dubbo/common/deploy/DeployState;)V
      10: return

  public void onStarted(org.apache.dubbo.rpc.model.ApplicationModel);
    Code:
       0: aload_0
       1: getfield      #1                  // Field this$0:Lorg/apache/dubbo/config/spring/context/DubboDeployApplicationListener;
       4: getstatic     #5                  // Field org/apache/dubbo/common/deploy/DeployState.STARTED:Lorg/apache/dubbo/common/deploy/DeployState;
       7: invokestatic  #4                  // Method org/apache/dubbo/config/spring/context/DubboDeployApplicationListener.access$000:(Lorg/apache/dubbo/config/spring/context/DubboDeployApplicationListener;Lorg/apache/dubbo/common/deploy/DeployState;)V
      10: return

  public void onStopping(org.apache.dubbo.rpc.model.ApplicationModel);
    Code:
       0: aload_0
       1: getfield      #1                  // Field this$0:Lorg/apache/dubbo/config/spring/context/DubboDeployApplicationListener;
       4: getstatic     #6                  // Field org/apache/dubbo/common/deploy/DeployState.STOPPING:Lorg/apache/dubbo/common/deploy/DeployState;
       7: invokestatic  #4                  // Method org/apache/dubbo/config/spring/context/DubboDeployApplicationListener.access$000:(Lorg/apache/dubbo/config/spring/context/DubboDeployApplicationListener;Lorg/apache/dubbo/common/deploy/DeployState;)V
      10: return

  public void onStopped(org.apache.dubbo.rpc.model.ApplicationModel);
    Code:
       0: aload_0
       1: getfield      #1                  // Field this$0:Lorg/apache/dubbo/config/spring/context/DubboDeployApplicationListener;
       4: getstatic     #7                  // Field org/apache/dubbo/common/deploy/DeployState.STOPPED:Lorg/apache/dubbo/common/deploy/DeployState;
       7: invokestatic  #4                  // Method org/apache/dubbo/config/spring/context/DubboDeployApplicationListener.access$000:(Lorg/apache/dubbo/config/spring/context/DubboDeployApplicationListener;Lorg/apache/dubbo/common/deploy/DeployState;)V
      10: return

  public void onFailure(org.apache.dubbo.rpc.model.ApplicationModel, java.lang.Throwable);
    Code:
       0: aload_0
       1: getfield      #1                  // Field this$0:Lorg/apache/dubbo/config/spring/context/DubboDeployApplicationListener;
       4: getstatic     #8                  // Field org/apache/dubbo/common/deploy/DeployState.FAILED:Lorg/apache/dubbo/common/deploy/DeployState;
       7: aload_2
       8: invokestatic  #9                  // Method org/apache/dubbo/config/spring/context/DubboDeployApplicationListener.access$100:(Lorg/apache/dubbo/config/spring/context/DubboDeployApplicationListener;Lorg/apache/dubbo/common/deploy/DeployState;Ljava/lang/Throwable;)V
      11: return

  public void onFailure(org.apache.dubbo.rpc.model.ScopeModel, java.lang.Throwable);
    Code:
       0: aload_0
       1: aload_1
       2: checkcast     #10                 // class org/apache/dubbo/rpc/model/ApplicationModel
       5: aload_2
       6: invokevirtual #11                 // Method onFailure:(Lorg/apache/dubbo/rpc/model/ApplicationModel;Ljava/lang/Throwable;)V
       9: return

  public void onStopped(org.apache.dubbo.rpc.model.ScopeModel);
    Code:
       0: aload_0
       1: aload_1
       2: checkcast     #10                 // class org/apache/dubbo/rpc/model/ApplicationModel
       5: invokevirtual #12                 // Method onStopped:(Lorg/apache/dubbo/rpc/model/ApplicationModel;)V
       8: return

  public void onStopping(org.apache.dubbo.rpc.model.ScopeModel);
    Code:
       0: aload_0
       1: aload_1
       2: checkcast     #10                 // class org/apache/dubbo/rpc/model/ApplicationModel
       5: invokevirtual #13                 // Method onStopping:(Lorg/apache/dubbo/rpc/model/ApplicationModel;)V
       8: return

  public void onStarted(org.apache.dubbo.rpc.model.ScopeModel);
    Code:
       0: aload_0
       1: aload_1
       2: checkcast     #10                 // class org/apache/dubbo/rpc/model/ApplicationModel
       5: invokevirtual #14                 // Method onStarted:(Lorg/apache/dubbo/rpc/model/ApplicationModel;)V
       8: return

  public void onStarting(org.apache.dubbo.rpc.model.ScopeModel);
    Code:
       0: aload_0
       1: aload_1
       2: checkcast     #10                 // class org/apache/dubbo/rpc/model/ApplicationModel
       5: invokevirtual #15                 // Method onStarting:(Lorg/apache/dubbo/rpc/model/ApplicationModel;)V
       8: return
}
