Compiled from "NettyRSocketServerFactory.java"
final class org.springframework.boot.rsocket.netty.NettyRSocketServerFactory$TcpSslServerCustomizer extends org.springframework.boot.web.embedded.netty.SslServerCustomizer {
  private org.springframework.boot.rsocket.netty.NettyRSocketServerFactory$TcpSslServerCustomizer(org.springframework.boot.web.server.Ssl$ClientAuth, org.springframework.boot.ssl.SslBundle);
    Code:
       0: aload_0
       1: aconst_null
       2: aload_1
       3: aload_2
       4: invokespecial #1                  // Method org/springframework/boot/web/embedded/netty/SslServerCustomizer."<init>":(Lorg/springframework/boot/web/server/Http2;Lorg/springframework/boot/web/server/Ssl$ClientAuth;Lorg/springframework/boot/ssl/SslBundle;)V
       7: return

  private reactor.netty.tcp.TcpServer apply(reactor.netty.tcp.TcpServer);
    Code:
       0: aload_0
       1: invokevirtual #7                  // Method createSslContextSpec:()Lreactor/netty/tcp/AbstractProtocolSslContextSpec;
       4: astore_2
       5: aload_1
       6: aload_2
       7: invokedynamic #13,  0             // InvokeDynamic #0:accept:(Lreactor/netty/tcp/AbstractProtocolSslContextSpec;)Ljava/util/function/Consumer;
      12: invokevirtual #17                 // Method reactor/netty/tcp/TcpServer.secure:(Ljava/util/function/Consumer;)Lreactor/netty/tcp/TcpServer;
      15: areturn

  private static void lambda$apply$0(reactor.netty.tcp.AbstractProtocolSslContextSpec, reactor.netty.tcp.SslProvider$SslContextSpec);
    Code:
       0: aload_1
       1: aload_0
       2: invokeinterface #23,  2           // InterfaceMethod reactor/netty/tcp/SslProvider$SslContextSpec.sslContext:(Lreactor/netty/tcp/SslProvider$ProtocolSslContextSpec;)Lreactor/netty/tcp/SslProvider$Builder;
       7: pop
       8: return
}
