Compiled from "CompressionHttpHandlerFactory.java"
class org.springframework.boot.web.embedded.undertow.CompressionHttpHandlerFactory implements org.springframework.boot.web.embedded.undertow.HttpHandlerFactory {
  private final org.springframework.boot.web.server.Compression compression;

  org.springframework.boot.web.embedded.undertow.CompressionHttpHandlerFactory(org.springframework.boot.web.server.Compression);
    Code:
       0: aload_0
       1: invokespecial #1                  // Method java/lang/Object."<init>":()V
       4: aload_0
       5: aload_1
       6: putfield      #7                  // Field compression:Lorg/springframework/boot/web/server/Compression;
       9: return

  public io.undertow.server.HttpHandler getHandler(io.undertow.server.HttpHandler);
    Code:
       0: aload_0
       1: getfield      #7                  // Field compression:Lorg/springframework/boot/web/server/Compression;
       4: invokevirtual #13                 // Method org/springframework/boot/web/server/Compression.getEnabled:()Z
       7: ifne          12
      10: aload_1
      11: areturn
      12: new           #19                 // class io/undertow/server/handlers/encoding/ContentEncodingRepository
      15: dup
      16: invokespecial #21                 // Method io/undertow/server/handlers/encoding/ContentEncodingRepository."<init>":()V
      19: astore_2
      20: aload_2
      21: ldc           #22                 // String gzip
      23: new           #24                 // class io/undertow/server/handlers/encoding/GzipEncodingProvider
      26: dup
      27: invokespecial #26                 // Method io/undertow/server/handlers/encoding/GzipEncodingProvider."<init>":()V
      30: bipush        50
      32: aload_0
      33: getfield      #7                  // Field compression:Lorg/springframework/boot/web/server/Compression;
      36: invokestatic  #27                 // Method getCompressionPredicates:(Lorg/springframework/boot/web/server/Compression;)[Lio/undertow/predicate/Predicate;
      39: invokestatic  #31                 // Method io/undertow/predicate/Predicates.and:([Lio/undertow/predicate/Predicate;)Lio/undertow/predicate/Predicate;
      42: invokevirtual #37                 // Method io/undertow/server/handlers/encoding/ContentEncodingRepository.addEncodingHandler:(Ljava/lang/String;Lio/undertow/server/handlers/encoding/ContentEncodingProvider;ILio/undertow/predicate/Predicate;)Lio/undertow/server/handlers/encoding/ContentEncodingRepository;
      45: pop
      46: new           #41                 // class io/undertow/server/handlers/encoding/EncodingHandler
      49: dup
      50: aload_2
      51: invokespecial #43                 // Method io/undertow/server/handlers/encoding/EncodingHandler."<init>":(Lio/undertow/server/handlers/encoding/ContentEncodingRepository;)V
      54: aload_1
      55: invokevirtual #46                 // Method io/undertow/server/handlers/encoding/EncodingHandler.setNext:(Lio/undertow/server/HttpHandler;)Lio/undertow/server/handlers/encoding/EncodingHandler;
      58: areturn

  private static io.undertow.predicate.Predicate[] getCompressionPredicates(org.springframework.boot.web.server.Compression);
    Code:
       0: new           #50                 // class java/util/ArrayList
       3: dup
       4: invokespecial #52                 // Method java/util/ArrayList."<init>":()V
       7: astore_1
       8: aload_1
       9: new           #53                 // class org/springframework/boot/web/embedded/undertow/CompressionHttpHandlerFactory$MaxSizePredicate
      12: dup
      13: aload_0
      14: invokevirtual #55                 // Method org/springframework/boot/web/server/Compression.getMinResponseSize:()Lorg/springframework/util/unit/DataSize;
      17: invokevirtual #59                 // Method org/springframework/util/unit/DataSize.toBytes:()J
      20: l2i
      21: invokespecial #65                 // Method org/springframework/boot/web/embedded/undertow/CompressionHttpHandlerFactory$MaxSizePredicate."<init>":(I)V
      24: invokeinterface #68,  2           // InterfaceMethod java/util/List.add:(Ljava/lang/Object;)Z
      29: pop
      30: aload_1
      31: new           #74                 // class org/springframework/boot/web/embedded/undertow/CompressionHttpHandlerFactory$CompressibleMimeTypePredicate
      34: dup
      35: aload_0
      36: invokevirtual #76                 // Method org/springframework/boot/web/server/Compression.getMimeTypes:()[Ljava/lang/String;
      39: invokespecial #80                 // Method org/springframework/boot/web/embedded/undertow/CompressionHttpHandlerFactory$CompressibleMimeTypePredicate."<init>":([Ljava/lang/String;)V
      42: invokeinterface #68,  2           // InterfaceMethod java/util/List.add:(Ljava/lang/Object;)Z
      47: pop
      48: aload_0
      49: invokevirtual #83                 // Method org/springframework/boot/web/server/Compression.getExcludedUserAgents:()[Ljava/lang/String;
      52: ifnull        119
      55: aload_0
      56: invokevirtual #83                 // Method org/springframework/boot/web/server/Compression.getExcludedUserAgents:()[Ljava/lang/String;
      59: astore_2
      60: aload_2
      61: arraylength
      62: istore_3
      63: iconst_0
      64: istore        4
      66: iload         4
      68: iload_3
      69: if_icmpge     119
      72: aload_2
      73: iload         4
      75: aaload
      76: astore        5
      78: new           #86                 // class io/undertow/attribute/RequestHeaderAttribute
      81: dup
      82: new           #88                 // class io/undertow/util/HttpString
      85: dup
      86: ldc           #92                 // String User-Agent
      88: invokespecial #94                 // Method io/undertow/util/HttpString."<init>":(Ljava/lang/String;)V
      91: invokespecial #97                 // Method io/undertow/attribute/RequestHeaderAttribute."<init>":(Lio/undertow/util/HttpString;)V
      94: astore        6
      96: aload_1
      97: aload         6
      99: aload         5
     101: invokestatic  #100                // Method io/undertow/predicate/Predicates.regex:(Lio/undertow/attribute/ExchangeAttribute;Ljava/lang/String;)Lio/undertow/predicate/Predicate;
     104: invokestatic  #104                // Method io/undertow/predicate/Predicates.not:(Lio/undertow/predicate/Predicate;)Lio/undertow/predicate/Predicate;
     107: invokeinterface #68,  2           // InterfaceMethod java/util/List.add:(Ljava/lang/Object;)Z
     112: pop
     113: iinc          4, 1
     116: goto          66
     119: aload_1
     120: iconst_0
     121: anewarray     #108                // class io/undertow/predicate/Predicate
     124: invokeinterface #110,  2          // InterfaceMethod java/util/List.toArray:([Ljava/lang/Object;)[Ljava/lang/Object;
     129: checkcast     #114                // class "[Lio/undertow/predicate/Predicate;"
     132: areturn
}
