Compiled from "CompressionHttpHandlerFactory.java"
class org.springframework.boot.web.embedded.undertow.CompressionHttpHandlerFactory$MaxSizePredicate implements io.undertow.predicate.Predicate {
  private final io.undertow.predicate.Predicate maxContentSize;

  org.springframework.boot.web.embedded.undertow.CompressionHttpHandlerFactory$MaxSizePredicate(int);
    Code:
       0: aload_0
       1: invokespecial #1                  // Method java/lang/Object."<init>":()V
       4: aload_0
       5: iload_1
       6: i2l
       7: invokestatic  #7                  // Method io/undertow/predicate/Predicates.requestLargerThan:(J)Lio/undertow/predicate/Predicate;
      10: putfield      #13                 // Field maxContentSize:Lio/undertow/predicate/Predicate;
      13: return

  public boolean resolve(io.undertow.server.HttpServerExchange);
    Code:
       0: aload_1
       1: invokevirtual #19                 // Method io/undertow/server/HttpServerExchange.getResponseHeaders:()Lio/undertow/util/HeaderMap;
       4: getstatic     #25                 // Field io/undertow/util/Headers.CONTENT_LENGTH:Lio/undertow/util/HttpString;
       7: invokevirtual #31                 // Method io/undertow/util/HeaderMap.contains:(Lio/undertow/util/HttpString;)Z
      10: ifeq          24
      13: aload_0
      14: getfield      #13                 // Field maxContentSize:Lio/undertow/predicate/Predicate;
      17: aload_1
      18: invokeinterface #37,  2           // InterfaceMethod io/undertow/predicate/Predicate.resolve:(Lio/undertow/server/HttpServerExchange;)Z
      23: ireturn
      24: iconst_1
      25: ireturn
}
