Compiled from "DeploymentManagerHttpHandlerFactory.java"
class org.springframework.boot.web.embedded.undertow.DeploymentManagerHttpHandlerFactory$DeploymentManagerHandler implements io.undertow.server.HttpHandler,java.io.Closeable {
  private final io.undertow.servlet.api.DeploymentManager deploymentManager;

  private final io.undertow.server.HttpHandler handler;

  org.springframework.boot.web.embedded.undertow.DeploymentManagerHttpHandlerFactory$DeploymentManagerHandler(io.undertow.servlet.api.DeploymentManager);
    Code:
       0: aload_0
       1: invokespecial #1                  // Method java/lang/Object."<init>":()V
       4: aload_0
       5: aload_1
       6: putfield      #7                  // Field deploymentManager:Lio/undertow/servlet/api/DeploymentManager;
       9: aload_0
      10: aload_1
      11: invokeinterface #13,  1           // InterfaceMethod io/undertow/servlet/api/DeploymentManager.start:()Lio/undertow/server/HttpHandler;
      16: putfield      #19                 // Field handler:Lio/undertow/server/HttpHandler;
      19: goto          32
      22: astore_2
      23: new           #25                 // class java/lang/RuntimeException
      26: dup
      27: aload_2
      28: invokespecial #27                 // Method java/lang/RuntimeException."<init>":(Ljava/lang/Throwable;)V
      31: athrow
      32: return
    Exception table:
       from    to  target type
           9    19    22   Class jakarta/servlet/ServletException

  public void handleRequest(io.undertow.server.HttpServerExchange) throws java.lang.Exception;
    Code:
       0: aload_0
       1: getfield      #19                 // Field handler:Lio/undertow/server/HttpHandler;
       4: aload_1
       5: invokeinterface #30,  2           // InterfaceMethod io/undertow/server/HttpHandler.handleRequest:(Lio/undertow/server/HttpServerExchange;)V
      10: return

  public void close() throws java.io.IOException;
    Code:
       0: aload_0
       1: getfield      #7                  // Field deploymentManager:Lio/undertow/servlet/api/DeploymentManager;
       4: invokeinterface #36,  1           // InterfaceMethod io/undertow/servlet/api/DeploymentManager.stop:()V
       9: aload_0
      10: getfield      #7                  // Field deploymentManager:Lio/undertow/servlet/api/DeploymentManager;
      13: invokeinterface #39,  1           // InterfaceMethod io/undertow/servlet/api/DeploymentManager.undeploy:()V
      18: goto          31
      21: astore_1
      22: new           #25                 // class java/lang/RuntimeException
      25: dup
      26: aload_1
      27: invokespecial #27                 // Method java/lang/RuntimeException."<init>":(Ljava/lang/Throwable;)V
      30: athrow
      31: return
    Exception table:
       from    to  target type
           0    18    21   Class jakarta/servlet/ServletException

  io.undertow.servlet.api.DeploymentManager getDeploymentManager();
    Code:
       0: aload_0
       1: getfield      #7                  // Field deploymentManager:Lio/undertow/servlet/api/DeploymentManager;
       4: areturn
}
