Compiled from "UndertowWebServer.java"
final class org.springframework.boot.web.embedded.undertow.UndertowWebServer$CloseableHttpHandlerFactory implements org.springframework.boot.web.embedded.undertow.HttpHandlerFactory {
  private final java.io.Closeable closeable;

  private org.springframework.boot.web.embedded.undertow.UndertowWebServer$CloseableHttpHandlerFactory(java.io.Closeable);
    Code:
       0: aload_0
       1: invokespecial #1                  // Method java/lang/Object."<init>":()V
       4: aload_0
       5: aload_1
       6: putfield      #7                  // Field closeable:Ljava/io/Closeable;
       9: return

  public io.undertow.server.HttpHandler getHandler(io.undertow.server.HttpHandler);
    Code:
       0: aload_0
       1: getfield      #7                  // Field closeable:Ljava/io/Closeable;
       4: ifnonnull     9
       7: aload_1
       8: areturn
       9: new           #13                 // class org/springframework/boot/web/embedded/undertow/UndertowWebServer$CloseableHttpHandlerFactory$1
      12: dup
      13: aload_0
      14: aload_1
      15: invokespecial #15                 // Method org/springframework/boot/web/embedded/undertow/UndertowWebServer$CloseableHttpHandlerFactory$1."<init>":(Lorg/springframework/boot/web/embedded/undertow/UndertowWebServer$CloseableHttpHandlerFactory;Lio/undertow/server/HttpHandler;)V
      18: areturn
}
