Compiled from "UndertowWebServer.java"
final class org.springframework.boot.web.embedded.undertow.UndertowWebServer$Port {
  private final int number;

  private final java.lang.String protocol;

  private org.springframework.boot.web.embedded.undertow.UndertowWebServer$Port(int, java.lang.String);
    Code:
       0: aload_0
       1: invokespecial #1                  // Method java/lang/Object."<init>":()V
       4: aload_0
       5: iload_1
       6: putfield      #7                  // Field number:I
       9: aload_0
      10: aload_2
      11: putfield      #13                 // Field protocol:Ljava/lang/String;
      14: return

  int getNumber();
    Code:
       0: aload_0
       1: getfield      #7                  // Field number:I
       4: ireturn

  public boolean equals(java.lang.Object);
    Code:
       0: aload_0
       1: aload_1
       2: if_acmpne     7
       5: iconst_1
       6: ireturn
       7: aload_1
       8: ifnonnull     13
      11: iconst_0
      12: ireturn
      13: aload_0
      14: invokevirtual #17                 // Method java/lang/Object.getClass:()Ljava/lang/Class;
      17: aload_1
      18: invokevirtual #17                 // Method java/lang/Object.getClass:()Ljava/lang/Class;
      21: if_acmpeq     26
      24: iconst_0
      25: ireturn
      26: aload_1
      27: checkcast     #8                  // class org/springframework/boot/web/embedded/undertow/UndertowWebServer$Port
      30: astore_2
      31: aload_0
      32: getfield      #7                  // Field number:I
      35: aload_2
      36: getfield      #7                  // Field number:I
      39: if_icmpne     46
      42: iconst_1
      43: goto          47
      46: iconst_0
      47: ireturn

  public int hashCode();
    Code:
       0: aload_0
       1: getfield      #7                  // Field number:I
       4: ireturn

  public java.lang.String toString();
    Code:
       0: aload_0
       1: getfield      #7                  // Field number:I
       4: aload_0
       5: getfield      #13                 // Field protocol:Ljava/lang/String;
       8: invokedynamic #21,  0             // InvokeDynamic #0:makeConcatWithConstants:(ILjava/lang/String;)Ljava/lang/String;
      13: areturn
}
