Compiled from "UndertowWebServer.java"
class org.springframework.boot.web.embedded.undertow.UndertowWebServer$CloseableHttpHandlerFactory$1 implements org.springframework.boot.web.embedded.undertow.UndertowWebServer$CloseableHttpHandler {
  final io.undertow.server.HttpHandler val$next;

  final org.springframework.boot.web.embedded.undertow.UndertowWebServer$CloseableHttpHandlerFactory this$0;

  org.springframework.boot.web.embedded.undertow.UndertowWebServer$CloseableHttpHandlerFactory$1();
    Code:
       0: aload_0
       1: aload_1
       2: putfield      #1                  // Field this$0:Lorg/springframework/boot/web/embedded/undertow/UndertowWebServer$CloseableHttpHandlerFactory;
       5: aload_0
       6: aload_2
       7: putfield      #7                  // Field val$next:Lio/undertow/server/HttpHandler;
      10: aload_0
      11: invokespecial #11                 // Method java/lang/Object."<init>":()V
      14: return

  public void handleRequest(io.undertow.server.HttpServerExchange) throws java.lang.Exception;
    Code:
       0: aload_0
       1: getfield      #7                  // Field val$next:Lio/undertow/server/HttpHandler;
       4: aload_1
       5: invokeinterface #17,  2           // InterfaceMethod io/undertow/server/HttpHandler.handleRequest:(Lio/undertow/server/HttpServerExchange;)V
      10: return

  public void close() throws java.io.IOException;
    Code:
       0: aload_0
       1: getfield      #1                  // Field this$0:Lorg/springframework/boot/web/embedded/undertow/UndertowWebServer$CloseableHttpHandlerFactory;
       4: getfield      #23                 // Field org/springframework/boot/web/embedded/undertow/UndertowWebServer$CloseableHttpHandlerFactory.closeable:Ljava/io/Closeable;
       7: invokeinterface #29,  1           // InterfaceMethod java/io/Closeable.close:()V
      12: return
}
