Compiled from "MissingWebServerFactoryBeanException.java"
public class org.springframework.boot.web.context.MissingWebServerFactoryBeanException extends org.springframework.beans.factory.NoSuchBeanDefinitionException {
  private final org.springframework.boot.WebApplicationType webApplicationType;

  public org.springframework.boot.web.context.MissingWebServerFactoryBeanException(java.lang.Class<? extends org.springframework.boot.web.context.WebServerApplicationContext>, java.lang.Class<? extends org.springframework.boot.web.server.WebServerFactory>, org.springframework.boot.WebApplicationType);
    Code:
       0: aload_0
       1: aload_2
       2: ldc           #1                  // String Unable to start %s due to missing %s bean
       4: iconst_2
       5: anewarray     #3                  // class java/lang/Object
       8: dup
       9: iconst_0
      10: aload_1
      11: invokevirtual #5                  // Method java/lang/Class.getSimpleName:()Ljava/lang/String;
      14: aastore
      15: dup
      16: iconst_1
      17: aload_2
      18: invokevirtual #5                  // Method java/lang/Class.getSimpleName:()Ljava/lang/String;
      21: aastore
      22: invokestatic  #11                 // Method java/lang/String.format:(Ljava/lang/String;[Ljava/lang/Object;)Ljava/lang/String;
      25: invokespecial #17                 // Method org/springframework/beans/factory/NoSuchBeanDefinitionException."<init>":(Ljava/lang/Class;Ljava/lang/String;)V
      28: aload_0
      29: aload_3
      30: putfield      #23                 // Field webApplicationType:Lorg/springframework/boot/WebApplicationType;
      33: return

  public org.springframework.boot.WebApplicationType getWebApplicationType();
    Code:
       0: aload_0
       1: getfield      #23                 // Field webApplicationType:Lorg/springframework/boot/WebApplicationType;
       4: areturn
}
