Compiled from "MissingWebServerFactoryBeanFailureAnalyzer.java"
class org.springframework.boot.web.context.MissingWebServerFactoryBeanFailureAnalyzer extends org.springframework.boot.diagnostics.AbstractFailureAnalyzer<org.springframework.boot.web.context.MissingWebServerFactoryBeanException> {
  org.springframework.boot.web.context.MissingWebServerFactoryBeanFailureAnalyzer();
    Code:
       0: aload_0
       1: invokespecial #1                  // Method org/springframework/boot/diagnostics/AbstractFailureAnalyzer."<init>":()V
       4: return

  protected org.springframework.boot.diagnostics.FailureAnalysis analyze(java.lang.Throwable, org.springframework.boot.web.context.MissingWebServerFactoryBeanException);
    Code:
       0: new           #7                  // class org/springframework/boot/diagnostics/FailureAnalysis
       3: dup
       4: aload_2
       5: invokevirtual #9                  // Method org/springframework/boot/web/context/MissingWebServerFactoryBeanException.getBeanType:()Ljava/lang/Class;
       8: invokevirtual #15                 // Method java/lang/Class.getName:()Ljava/lang/String;
      11: invokedynamic #21,  0             // InvokeDynamic #0:makeConcatWithConstants:(Ljava/lang/String;)Ljava/lang/String;
      16: aload_2
      17: invokevirtual #25                 // Method org/springframework/boot/web/context/MissingWebServerFactoryBeanException.getWebApplicationType:()Lorg/springframework/boot/WebApplicationType;
      20: invokevirtual #29                 // Method org/springframework/boot/WebApplicationType.name:()Ljava/lang/String;
      23: getstatic     #34                 // Field java/util/Locale.ENGLISH:Ljava/util/Locale;
      26: invokevirtual #40                 // Method java/lang/String.toLowerCase:(Ljava/util/Locale;)Ljava/lang/String;
      29: invokedynamic #46,  0             // InvokeDynamic #1:makeConcatWithConstants:(Ljava/lang/String;)Ljava/lang/String;
      34: aload_2
      35: invokespecial #47                 // Method org/springframework/boot/diagnostics/FailureAnalysis."<init>":(Ljava/lang/String;Ljava/lang/String;Ljava/lang/Throwable;)V
      38: areturn

  protected org.springframework.boot.diagnostics.FailureAnalysis analyze(java.lang.Throwable, java.lang.Throwable);
    Code:
       0: aload_0
       1: aload_1
       2: aload_2
       3: checkcast     #10                 // class org/springframework/boot/web/context/MissingWebServerFactoryBeanException
       6: invokevirtual #50                 // Method analyze:(Ljava/lang/Throwable;Lorg/springframework/boot/web/context/MissingWebServerFactoryBeanException;)Lorg/springframework/boot/diagnostics/FailureAnalysis;
       9: areturn
}
