Compiled from "WebServerGracefulShutdownLifecycle.java"
public final class org.springframework.boot.web.context.WebServerGracefulShutdownLifecycle implements org.springframework.context.SmartLifecycle {
  public static final int SMART_LIFECYCLE_PHASE;

  private final org.springframework.boot.web.server.WebServer webServer;

  private volatile boolean running;

  public org.springframework.boot.web.context.WebServerGracefulShutdownLifecycle(org.springframework.boot.web.server.WebServer);
    Code:
       0: aload_0
       1: invokespecial #3                  // Method java/lang/Object."<init>":()V
       4: aload_0
       5: aload_1
       6: putfield      #9                  // Field webServer:Lorg/springframework/boot/web/server/WebServer;
       9: return

  public void start();
    Code:
       0: aload_0
       1: iconst_1
       2: putfield      #15                 // Field running:Z
       5: return

  public void stop();
    Code:
       0: new           #19                 // class java/lang/UnsupportedOperationException
       3: dup
       4: ldc           #21                 // String Stop must not be invoked directly
       6: invokespecial #23                 // Method java/lang/UnsupportedOperationException."<init>":(Ljava/lang/String;)V
       9: athrow

  public void stop(java.lang.Runnable);
    Code:
       0: aload_0
       1: iconst_0
       2: putfield      #15                 // Field running:Z
       5: aload_0
       6: getfield      #9                  // Field webServer:Lorg/springframework/boot/web/server/WebServer;
       9: aload_1
      10: invokedynamic #26,  0             // InvokeDynamic #0:shutdownComplete:(Ljava/lang/Runnable;)Lorg/springframework/boot/web/server/GracefulShutdownCallback;
      15: invokeinterface #30,  2           // InterfaceMethod org/springframework/boot/web/server/WebServer.shutDownGracefully:(Lorg/springframework/boot/web/server/GracefulShutdownCallback;)V
      20: return

  public boolean isRunning();
    Code:
       0: aload_0
       1: getfield      #15                 // Field running:Z
       4: ireturn

  public int getPhase();
    Code:
       0: ldc           #36                 // int 2147482623
       2: ireturn

  private static void lambda$stop$0(java.lang.Runnable, org.springframework.boot.web.server.GracefulShutdownResult);
    Code:
       0: aload_0
       1: invokeinterface #37,  1           // InterfaceMethod java/lang/Runnable.run:()V
       6: return
}
