Compiled from "WebServerApplicationContext.java"
public interface org.springframework.boot.web.context.WebServerApplicationContext extends org.springframework.context.ApplicationContext {
  public abstract org.springframework.boot.web.server.WebServer getWebServer();

  public abstract java.lang.String getServerNamespace();

  public static boolean hasServerNamespace(org.springframework.context.ApplicationContext, java.lang.String);
    Code:
       0: aload_0
       1: instanceof    #1                  // class org/springframework/boot/web/context/WebServerApplicationContext
       4: ifeq          29
       7: aload_0
       8: checkcast     #1                  // class org/springframework/boot/web/context/WebServerApplicationContext
      11: astore_2
      12: aload_2
      13: invokeinterface #3,  1            // InterfaceMethod getServerNamespace:()Ljava/lang/String;
      18: aload_1
      19: invokestatic  #7                  // Method org/springframework/util/ObjectUtils.nullSafeEquals:(Ljava/lang/Object;Ljava/lang/Object;)Z
      22: ifeq          29
      25: iconst_1
      26: goto          30
      29: iconst_0
      30: ireturn

  public static java.lang.String getServerNamespace(org.springframework.context.ApplicationContext);
    Code:
       0: aload_0
       1: instanceof    #1                  // class org/springframework/boot/web/context/WebServerApplicationContext
       4: ifeq          21
       7: aload_0
       8: checkcast     #1                  // class org/springframework/boot/web/context/WebServerApplicationContext
      11: astore_1
      12: aload_1
      13: invokeinterface #3,  1            // InterfaceMethod getServerNamespace:()Ljava/lang/String;
      18: goto          22
      21: aconst_null
      22: areturn
}
