Compiled from "AuthPolicy.java"
public final class org.apache.dubbo.common.ssl.AuthPolicy extends java.lang.Enum<org.apache.dubbo.common.ssl.AuthPolicy> {
  public static final org.apache.dubbo.common.ssl.AuthPolicy NONE;

  public static final org.apache.dubbo.common.ssl.AuthPolicy SERVER_AUTH;

  public static final org.apache.dubbo.common.ssl.AuthPolicy CLIENT_AUTH;

  private static final org.apache.dubbo.common.ssl.AuthPolicy[] $VALUES;

  public static org.apache.dubbo.common.ssl.AuthPolicy[] values();
    Code:
       0: getstatic     #1                  // Field $VALUES:[Lorg/apache/dubbo/common/ssl/AuthPolicy;
       3: invokevirtual #2                  // Method "[Lorg/apache/dubbo/common/ssl/AuthPolicy;".clone:()Ljava/lang/Object;
       6: checkcast     #3                  // class "[Lorg/apache/dubbo/common/ssl/AuthPolicy;"
       9: areturn

  public static org.apache.dubbo.common.ssl.AuthPolicy valueOf(java.lang.String);
    Code:
       0: ldc           #4                  // class org/apache/dubbo/common/ssl/AuthPolicy
       2: aload_0
       3: invokestatic  #5                  // Method java/lang/Enum.valueOf:(Ljava/lang/Class;Ljava/lang/String;)Ljava/lang/Enum;
       6: checkcast     #4                  // class org/apache/dubbo/common/ssl/AuthPolicy
       9: areturn

  private org.apache.dubbo.common.ssl.AuthPolicy();
    Code:
       0: aload_0
       1: aload_1
       2: iload_2
       3: invokespecial #6                  // Method java/lang/Enum."<init>":(Ljava/lang/String;I)V
       6: return

  static {};
    Code:
       0: new           #4                  // class org/apache/dubbo/common/ssl/AuthPolicy
       3: dup
       4: ldc           #7                  // String NONE
       6: iconst_0
       7: invokespecial #8                  // Method "<init>":(Ljava/lang/String;I)V
      10: putstatic     #9                  // Field NONE:Lorg/apache/dubbo/common/ssl/AuthPolicy;
      13: new           #4                  // class org/apache/dubbo/common/ssl/AuthPolicy
      16: dup
      17: ldc           #10                 // String SERVER_AUTH
      19: iconst_1
      20: invokespecial #8                  // Method "<init>":(Ljava/lang/String;I)V
      23: putstatic     #11                 // Field SERVER_AUTH:Lorg/apache/dubbo/common/ssl/AuthPolicy;
      26: new           #4                  // class org/apache/dubbo/common/ssl/AuthPolicy
      29: dup
      30: ldc           #12                 // String CLIENT_AUTH
      32: iconst_2
      33: invokespecial #8                  // Method "<init>":(Ljava/lang/String;I)V
      36: putstatic     #13                 // Field CLIENT_AUTH:Lorg/apache/dubbo/common/ssl/AuthPolicy;
      39: iconst_3
      40: anewarray     #4                  // class org/apache/dubbo/common/ssl/AuthPolicy
      43: dup
      44: iconst_0
      45: getstatic     #9                  // Field NONE:Lorg/apache/dubbo/common/ssl/AuthPolicy;
      48: aastore
      49: dup
      50: iconst_1
      51: getstatic     #11                 // Field SERVER_AUTH:Lorg/apache/dubbo/common/ssl/AuthPolicy;
      54: aastore
      55: dup
      56: iconst_2
      57: getstatic     #13                 // Field CLIENT_AUTH:Lorg/apache/dubbo/common/ssl/AuthPolicy;
      60: aastore
      61: putstatic     #1                  // Field $VALUES:[Lorg/apache/dubbo/common/ssl/AuthPolicy;
      64: return
}
