Compiled from "CertManager.java"
public class org.apache.dubbo.common.ssl.CertManager {
  private final java.util.List<org.apache.dubbo.common.ssl.CertProvider> certProviders;

  public org.apache.dubbo.common.ssl.CertManager(org.apache.dubbo.rpc.model.FrameworkModel);
    Code:
       0: aload_0
       1: invokespecial #1                  // Method java/lang/Object."<init>":()V
       4: aload_0
       5: aload_1
       6: ldc           #2                  // class org/apache/dubbo/common/ssl/CertProvider
       8: invokevirtual #3                  // Method org/apache/dubbo/rpc/model/FrameworkModel.getExtensionLoader:(Ljava/lang/Class;)Lorg/apache/dubbo/common/extension/ExtensionLoader;
      11: invokevirtual #4                  // Method org/apache/dubbo/common/extension/ExtensionLoader.getActivateExtensions:()Ljava/util/List;
      14: putfield      #5                  // Field certProviders:Ljava/util/List;
      17: return

  public org.apache.dubbo.common.ssl.ProviderCert getProviderConnectionConfig(org.apache.dubbo.common.URL, java.net.SocketAddress);
    Code:
       0: aload_0
       1: getfield      #5                  // Field certProviders:Ljava/util/List;
       4: invokeinterface #6,  1            // InterfaceMethod java/util/List.iterator:()Ljava/util/Iterator;
       9: astore_3
      10: aload_3
      11: invokeinterface #7,  1            // InterfaceMethod java/util/Iterator.hasNext:()Z
      16: ifeq          62
      19: aload_3
      20: invokeinterface #8,  1            // InterfaceMethod java/util/Iterator.next:()Ljava/lang/Object;
      25: checkcast     #2                  // class org/apache/dubbo/common/ssl/CertProvider
      28: astore        4
      30: aload         4
      32: aload_1
      33: invokeinterface #9,  2            // InterfaceMethod org/apache/dubbo/common/ssl/CertProvider.isSupport:(Lorg/apache/dubbo/common/URL;)Z
      38: ifeq          59
      41: aload         4
      43: aload_1
      44: invokeinterface #10,  2           // InterfaceMethod org/apache/dubbo/common/ssl/CertProvider.getProviderConnectionConfig:(Lorg/apache/dubbo/common/URL;)Lorg/apache/dubbo/common/ssl/ProviderCert;
      49: astore        5
      51: aload         5
      53: ifnull        59
      56: aload         5
      58: areturn
      59: goto          10
      62: aconst_null
      63: areturn

  public org.apache.dubbo.common.ssl.Cert getConsumerConnectionConfig(org.apache.dubbo.common.URL);
    Code:
       0: aload_0
       1: getfield      #5                  // Field certProviders:Ljava/util/List;
       4: invokeinterface #6,  1            // InterfaceMethod java/util/List.iterator:()Ljava/util/Iterator;
       9: astore_2
      10: aload_2
      11: invokeinterface #7,  1            // InterfaceMethod java/util/Iterator.hasNext:()Z
      16: ifeq          59
      19: aload_2
      20: invokeinterface #8,  1            // InterfaceMethod java/util/Iterator.next:()Ljava/lang/Object;
      25: checkcast     #2                  // class org/apache/dubbo/common/ssl/CertProvider
      28: astore_3
      29: aload_3
      30: aload_1
      31: invokeinterface #9,  2            // InterfaceMethod org/apache/dubbo/common/ssl/CertProvider.isSupport:(Lorg/apache/dubbo/common/URL;)Z
      36: ifeq          56
      39: aload_3
      40: aload_1
      41: invokeinterface #11,  2           // InterfaceMethod org/apache/dubbo/common/ssl/CertProvider.getConsumerConnectionConfig:(Lorg/apache/dubbo/common/URL;)Lorg/apache/dubbo/common/ssl/Cert;
      46: astore        4
      48: aload         4
      50: ifnull        56
      53: aload         4
      55: areturn
      56: goto          10
      59: aconst_null
      60: areturn
}
