Compiled from "ProviderCert.java"
public class org.apache.dubbo.common.ssl.ProviderCert extends org.apache.dubbo.common.ssl.Cert {
  private final org.apache.dubbo.common.ssl.AuthPolicy authPolicy;

  public org.apache.dubbo.common.ssl.ProviderCert(byte[], byte[], byte[], org.apache.dubbo.common.ssl.AuthPolicy);
    Code:
       0: aload_0
       1: aload_1
       2: aload_2
       3: aload_3
       4: invokespecial #1                  // Method org/apache/dubbo/common/ssl/Cert."<init>":([B[B[B)V
       7: aload_0
       8: aload         4
      10: putfield      #2                  // Field authPolicy:Lorg/apache/dubbo/common/ssl/AuthPolicy;
      13: return

  public org.apache.dubbo.common.ssl.ProviderCert(byte[], byte[], byte[], java.lang.String, org.apache.dubbo.common.ssl.AuthPolicy);
    Code:
       0: aload_0
       1: aload_1
       2: aload_2
       3: aload_3
       4: aload         4
       6: invokespecial #3                  // Method org/apache/dubbo/common/ssl/Cert."<init>":([B[B[BLjava/lang/String;)V
       9: aload_0
      10: aload         5
      12: putfield      #2                  // Field authPolicy:Lorg/apache/dubbo/common/ssl/AuthPolicy;
      15: return

  public org.apache.dubbo.common.ssl.AuthPolicy getAuthPolicy();
    Code:
       0: aload_0
       1: getfield      #2                  // Field authPolicy:Lorg/apache/dubbo/common/ssl/AuthPolicy;
       4: areturn
}
