Compiled from "FilteredMethodValidationPostProcessor.java"
public class org.springframework.boot.validation.beanvalidation.FilteredMethodValidationPostProcessor extends org.springframework.validation.beanvalidation.MethodValidationPostProcessor {
  private final java.util.Collection<org.springframework.boot.validation.beanvalidation.MethodValidationExcludeFilter> excludeFilters;

  public org.springframework.boot.validation.beanvalidation.FilteredMethodValidationPostProcessor(java.util.stream.Stream<? extends org.springframework.boot.validation.beanvalidation.MethodValidationExcludeFilter>);
    Code:
       0: aload_0
       1: invokespecial #1                  // Method org/springframework/validation/beanvalidation/MethodValidationPostProcessor."<init>":()V
       4: aload_0
       5: aload_1
       6: ldc           #7                  // class org/springframework/boot/validation/beanvalidation/MethodValidationExcludeFilter
       8: dup
       9: invokestatic  #9                  // Method java/util/Objects.requireNonNull:(Ljava/lang/Object;)Ljava/lang/Object;
      12: pop
      13: invokedynamic #15,  0             // InvokeDynamic #0:apply:(Ljava/lang/Class;)Ljava/util/function/Function;
      18: invokeinterface #19,  2           // InterfaceMethod java/util/stream/Stream.map:(Ljava/util/function/Function;)Ljava/util/stream/Stream;
      23: invokeinterface #25,  1           // InterfaceMethod java/util/stream/Stream.toList:()Ljava/util/List;
      28: putfield      #29                 // Field excludeFilters:Ljava/util/Collection;
      31: return

  public org.springframework.boot.validation.beanvalidation.FilteredMethodValidationPostProcessor(java.util.Collection<? extends org.springframework.boot.validation.beanvalidation.MethodValidationExcludeFilter>);
    Code:
       0: aload_0
       1: invokespecial #1                  // Method org/springframework/validation/beanvalidation/MethodValidationPostProcessor."<init>":()V
       4: aload_0
       5: new           #35                 // class java/util/ArrayList
       8: dup
       9: aload_1
      10: invokespecial #37                 // Method java/util/ArrayList."<init>":(Ljava/util/Collection;)V
      13: putfield      #29                 // Field excludeFilters:Ljava/util/Collection;
      16: return

  public void afterPropertiesSet();
    Code:
       0: aload_0
       1: invokespecial #40                 // Method org/springframework/validation/beanvalidation/MethodValidationPostProcessor.afterPropertiesSet:()V
       4: aload_0
       5: getfield      #43                 // Field advisor:Lorg/springframework/aop/Advisor;
       8: checkcast     #47                 // class org/springframework/aop/support/DefaultPointcutAdvisor
      11: astore_1
      12: aload_1
      13: invokevirtual #49                 // Method org/springframework/aop/support/DefaultPointcutAdvisor.getPointcut:()Lorg/springframework/aop/Pointcut;
      16: invokeinterface #53,  1           // InterfaceMethod org/springframework/aop/Pointcut.getClassFilter:()Lorg/springframework/aop/ClassFilter;
      21: astore_2
      22: aload_1
      23: invokevirtual #49                 // Method org/springframework/aop/support/DefaultPointcutAdvisor.getPointcut:()Lorg/springframework/aop/Pointcut;
      26: invokeinterface #59,  1           // InterfaceMethod org/springframework/aop/Pointcut.getMethodMatcher:()Lorg/springframework/aop/MethodMatcher;
      31: astore_3
      32: aload_1
      33: new           #63                 // class org/springframework/aop/support/ComposablePointcut
      36: dup
      37: aload_2
      38: aload_3
      39: invokespecial #65                 // Method org/springframework/aop/support/ComposablePointcut."<init>":(Lorg/springframework/aop/ClassFilter;Lorg/springframework/aop/MethodMatcher;)V
      42: aload_0
      43: invokedynamic #68,  0             // InvokeDynamic #1:matches:(Lorg/springframework/boot/validation/beanvalidation/FilteredMethodValidationPostProcessor;)Lorg/springframework/aop/ClassFilter;
      48: invokevirtual #72                 // Method org/springframework/aop/support/ComposablePointcut.intersection:(Lorg/springframework/aop/ClassFilter;)Lorg/springframework/aop/support/ComposablePointcut;
      51: invokevirtual #76                 // Method org/springframework/aop/support/DefaultPointcutAdvisor.setPointcut:(Lorg/springframework/aop/Pointcut;)V
      54: return

  private boolean isIncluded(java.lang.Class<?>);
    Code:
       0: aload_0
       1: getfield      #29                 // Field excludeFilters:Ljava/util/Collection;
       4: invokeinterface #80,  1           // InterfaceMethod java/util/Collection.iterator:()Ljava/util/Iterator;
       9: astore_2
      10: aload_2
      11: invokeinterface #86,  1           // InterfaceMethod java/util/Iterator.hasNext:()Z
      16: ifeq          44
      19: aload_2
      20: invokeinterface #92,  1           // InterfaceMethod java/util/Iterator.next:()Ljava/lang/Object;
      25: checkcast     #7                  // class org/springframework/boot/validation/beanvalidation/MethodValidationExcludeFilter
      28: astore_3
      29: aload_3
      30: aload_1
      31: invokeinterface #96,  2           // InterfaceMethod org/springframework/boot/validation/beanvalidation/MethodValidationExcludeFilter.isExcluded:(Ljava/lang/Class;)Z
      36: ifeq          41
      39: iconst_0
      40: ireturn
      41: goto          10
      44: iconst_1
      45: ireturn
}
