Compiled from "MethodValidationExcludeFilter.java"
public interface org.springframework.boot.validation.beanvalidation.MethodValidationExcludeFilter {
  public abstract boolean isExcluded(java.lang.Class<?>);

  public static org.springframework.boot.validation.beanvalidation.MethodValidationExcludeFilter byAnnotation(java.lang.Class<? extends java.lang.annotation.Annotation>);
    Code:
       0: aload_0
       1: getstatic     #1                  // Field org/springframework/core/annotation/MergedAnnotations$SearchStrategy.INHERITED_ANNOTATIONS:Lorg/springframework/core/annotation/MergedAnnotations$SearchStrategy;
       4: invokestatic  #7                  // InterfaceMethod byAnnotation:(Ljava/lang/Class;Lorg/springframework/core/annotation/MergedAnnotations$SearchStrategy;)Lorg/springframework/boot/validation/beanvalidation/MethodValidationExcludeFilter;
       7: areturn

  public static org.springframework.boot.validation.beanvalidation.MethodValidationExcludeFilter byAnnotation(java.lang.Class<? extends java.lang.annotation.Annotation>, org.springframework.core.annotation.MergedAnnotations$SearchStrategy);
    Code:
       0: aload_1
       1: aload_0
       2: invokedynamic #13,  0             // InvokeDynamic #0:isExcluded:(Lorg/springframework/core/annotation/MergedAnnotations$SearchStrategy;Ljava/lang/Class;)Lorg/springframework/boot/validation/beanvalidation/MethodValidationExcludeFilter;
       7: areturn

  private static boolean lambda$byAnnotation$0(org.springframework.core.annotation.MergedAnnotations$SearchStrategy, java.lang.Class, java.lang.Class);
    Code:
       0: aload_2
       1: aload_0
       2: invokestatic  #17                 // InterfaceMethod org/springframework/core/annotation/MergedAnnotations.from:(Ljava/lang/reflect/AnnotatedElement;Lorg/springframework/core/annotation/MergedAnnotations$SearchStrategy;)Lorg/springframework/core/annotation/MergedAnnotations;
       5: aload_1
       6: invokeinterface #23,  2           // InterfaceMethod org/springframework/core/annotation/MergedAnnotations.isPresent:(Ljava/lang/Class;)Z
      11: ireturn
}
