Compiled from "KubernetesMeshEnvListenerFactory.java"
public class org.apache.dubbo.registry.kubernetes.KubernetesMeshEnvListenerFactory implements org.apache.dubbo.rpc.cluster.router.mesh.route.MeshEnvListenerFactory {
  public static final org.apache.dubbo.common.logger.Logger logger;

  private final java.util.concurrent.atomic.AtomicBoolean initialized;

  private org.apache.dubbo.rpc.cluster.router.mesh.route.MeshEnvListener listener;

  public org.apache.dubbo.registry.kubernetes.KubernetesMeshEnvListenerFactory();
    Code:
       0: aload_0
       1: invokespecial #1                  // Method java/lang/Object."<init>":()V
       4: aload_0
       5: new           #2                  // class java/util/concurrent/atomic/AtomicBoolean
       8: dup
       9: iconst_0
      10: invokespecial #3                  // Method java/util/concurrent/atomic/AtomicBoolean."<init>":(Z)V
      13: putfield      #4                  // Field initialized:Ljava/util/concurrent/atomic/AtomicBoolean;
      16: aload_0
      17: aconst_null
      18: putfield      #5                  // Field listener:Lorg/apache/dubbo/rpc/cluster/router/mesh/route/MeshEnvListener;
      21: return

  public org.apache.dubbo.rpc.cluster.router.mesh.route.MeshEnvListener getListener();
    Code:
       0: aload_0
       1: getfield      #4                  // Field initialized:Ljava/util/concurrent/atomic/AtomicBoolean;
       4: iconst_0
       5: iconst_1
       6: invokevirtual #6                  // Method java/util/concurrent/atomic/AtomicBoolean.compareAndSet:(ZZ)Z
       9: ifeq          23
      12: aload_0
      13: new           #7                  // class org/apache/dubbo/registry/kubernetes/NopKubernetesMeshEnvListener
      16: dup
      17: invokespecial #8                  // Method org/apache/dubbo/registry/kubernetes/NopKubernetesMeshEnvListener."<init>":()V
      20: putfield      #5                  // Field listener:Lorg/apache/dubbo/rpc/cluster/router/mesh/route/MeshEnvListener;
      23: goto          37
      26: astore_1
      27: getstatic     #10                 // Field logger:Lorg/apache/dubbo/common/logger/Logger;
      30: ldc           #11                 // String Current Env not support Kubernetes.
      32: invokeinterface #12,  2           // InterfaceMethod org/apache/dubbo/common/logger/Logger.info:(Ljava/lang/String;)V
      37: aload_0
      38: getfield      #5                  // Field listener:Lorg/apache/dubbo/rpc/cluster/router/mesh/route/MeshEnvListener;
      41: areturn
    Exception table:
       from    to  target type
           0    23    26   Class java/lang/Throwable

  static {};
    Code:
       0: ldc           #13                 // class org/apache/dubbo/registry/kubernetes/KubernetesMeshEnvListenerFactory
       2: invokestatic  #14                 // Method org/apache/dubbo/common/logger/LoggerFactory.getLogger:(Ljava/lang/Class;)Lorg/apache/dubbo/common/logger/Logger;
       5: putstatic     #10                 // Field logger:Lorg/apache/dubbo/common/logger/Logger;
       8: return
}
