Compiled from "KubernetesMeshEnvListener.java"
class org.apache.dubbo.registry.kubernetes.KubernetesMeshEnvListener$2 implements io.fabric8.kubernetes.client.Watcher<io.fabric8.kubernetes.api.model.GenericKubernetesResource> {
  final java.lang.String val$appName;

  final org.apache.dubbo.registry.kubernetes.KubernetesMeshEnvListener this$0;

  org.apache.dubbo.registry.kubernetes.KubernetesMeshEnvListener$2(org.apache.dubbo.registry.kubernetes.KubernetesMeshEnvListener, java.lang.String);
    Code:
       0: aload_0
       1: aload_1
       2: putfield      #1                  // Field this$0:Lorg/apache/dubbo/registry/kubernetes/KubernetesMeshEnvListener;
       5: aload_0
       6: aload_2
       7: putfield      #2                  // Field val$appName:Ljava/lang/String;
      10: aload_0
      11: invokespecial #3                  // Method java/lang/Object."<init>":()V
      14: return

  public void eventReceived(io.fabric8.kubernetes.client.Watcher$Action, io.fabric8.kubernetes.api.model.GenericKubernetesResource);
    Code:
       0: getstatic     #4                  // Field org/apache/dubbo/registry/kubernetes/KubernetesMeshEnvListener.logger:Lorg/apache/dubbo/common/logger/ErrorTypeAwareLogger;
       3: invokeinterface #5,  1            // InterfaceMethod org/apache/dubbo/common/logger/ErrorTypeAwareLogger.isInfoEnabled:()Z
       8: ifeq          59
      11: getstatic     #4                  // Field org/apache/dubbo/registry/kubernetes/KubernetesMeshEnvListener.logger:Lorg/apache/dubbo/common/logger/ErrorTypeAwareLogger;
      14: new           #6                  // class java/lang/StringBuilder
      17: dup
      18: invokespecial #7                  // Method java/lang/StringBuilder."<init>":()V
      21: ldc           #8                  // String Received VS Rule notification. AppName:
      23: invokevirtual #9                  // Method java/lang/StringBuilder.append:(Ljava/lang/String;)Ljava/lang/StringBuilder;
      26: aload_0
      27: getfield      #2                  // Field val$appName:Ljava/lang/String;
      30: invokevirtual #9                  // Method java/lang/StringBuilder.append:(Ljava/lang/String;)Ljava/lang/StringBuilder;
      33: ldc           #10                 // String  Action:
      35: invokevirtual #9                  // Method java/lang/StringBuilder.append:(Ljava/lang/String;)Ljava/lang/StringBuilder;
      38: aload_1
      39: invokevirtual #11                 // Method java/lang/StringBuilder.append:(Ljava/lang/Object;)Ljava/lang/StringBuilder;
      42: ldc           #12                 // String  Resource:
      44: invokevirtual #9                  // Method java/lang/StringBuilder.append:(Ljava/lang/String;)Ljava/lang/StringBuilder;
      47: aload_2
      48: invokevirtual #11                 // Method java/lang/StringBuilder.append:(Ljava/lang/Object;)Ljava/lang/StringBuilder;
      51: invokevirtual #13                 // Method java/lang/StringBuilder.toString:()Ljava/lang/String;
      54: invokeinterface #14,  2           // InterfaceMethod org/apache/dubbo/common/logger/ErrorTypeAwareLogger.info:(Ljava/lang/String;)V
      59: aload_1
      60: getstatic     #15                 // Field io/fabric8/kubernetes/client/Watcher$Action.ADDED:Lio/fabric8/kubernetes/client/Watcher$Action;
      63: if_acmpeq     73
      66: aload_1
      67: getstatic     #16                 // Field io/fabric8/kubernetes/client/Watcher$Action.MODIFIED:Lio/fabric8/kubernetes/client/Watcher$Action;
      70: if_acmpne     170
      73: new           #17                 // class org/yaml/snakeyaml/Yaml
      76: dup
      77: new           #18                 // class org/yaml/snakeyaml/constructor/SafeConstructor
      80: dup
      81: new           #19                 // class org/yaml/snakeyaml/LoaderOptions
      84: dup
      85: invokespecial #20                 // Method org/yaml/snakeyaml/LoaderOptions."<init>":()V
      88: invokespecial #21                 // Method org/yaml/snakeyaml/constructor/SafeConstructor."<init>":(Lorg/yaml/snakeyaml/LoaderOptions;)V
      91: invokespecial #22                 // Method org/yaml/snakeyaml/Yaml."<init>":(Lorg/yaml/snakeyaml/constructor/BaseConstructor;)V
      94: aload_2
      95: invokevirtual #23                 // Method org/yaml/snakeyaml/Yaml.dump:(Ljava/lang/Object;)Ljava/lang/String;
      98: astore_3
      99: aload_0
     100: getfield      #1                  // Field this$0:Lorg/apache/dubbo/registry/kubernetes/KubernetesMeshEnvListener;
     103: invokestatic  #24                 // Method org/apache/dubbo/registry/kubernetes/KubernetesMeshEnvListener.access$100:(Lorg/apache/dubbo/registry/kubernetes/KubernetesMeshEnvListener;)Ljava/util/Map;
     106: aload_0
     107: getfield      #2                  // Field val$appName:Ljava/lang/String;
     110: aload_3
     111: invokeinterface #25,  3           // InterfaceMethod java/util/Map.put:(Ljava/lang/Object;Ljava/lang/Object;)Ljava/lang/Object;
     116: pop
     117: aload_0
     118: getfield      #1                  // Field this$0:Lorg/apache/dubbo/registry/kubernetes/KubernetesMeshEnvListener;
     121: invokestatic  #26                 // Method org/apache/dubbo/registry/kubernetes/KubernetesMeshEnvListener.access$000:(Lorg/apache/dubbo/registry/kubernetes/KubernetesMeshEnvListener;)Ljava/util/Map;
     124: aload_0
     125: getfield      #2                  // Field val$appName:Ljava/lang/String;
     128: invokeinterface #27,  2           // InterfaceMethod java/util/Map.containsKey:(Ljava/lang/Object;)Z
     133: ifeq          167
     136: aload_0
     137: getfield      #1                  // Field this$0:Lorg/apache/dubbo/registry/kubernetes/KubernetesMeshEnvListener;
     140: aload_0
     141: getfield      #1                  // Field this$0:Lorg/apache/dubbo/registry/kubernetes/KubernetesMeshEnvListener;
     144: invokestatic  #26                 // Method org/apache/dubbo/registry/kubernetes/KubernetesMeshEnvListener.access$000:(Lorg/apache/dubbo/registry/kubernetes/KubernetesMeshEnvListener;)Ljava/util/Map;
     147: aload_0
     148: getfield      #2                  // Field val$appName:Ljava/lang/String;
     151: invokeinterface #28,  2           // InterfaceMethod java/util/Map.get:(Ljava/lang/Object;)Ljava/lang/Object;
     156: checkcast     #29                 // class java/lang/String
     159: aload_0
     160: getfield      #2                  // Field val$appName:Ljava/lang/String;
     163: aload_3
     164: invokestatic  #30                 // Method org/apache/dubbo/registry/kubernetes/KubernetesMeshEnvListener.access$200:(Lorg/apache/dubbo/registry/kubernetes/KubernetesMeshEnvListener;Ljava/lang/String;Ljava/lang/String;Ljava/lang/String;)V
     167: goto          194
     170: aload_0
     171: getfield      #1                  // Field this$0:Lorg/apache/dubbo/registry/kubernetes/KubernetesMeshEnvListener;
     174: invokestatic  #31                 // Method org/apache/dubbo/registry/kubernetes/KubernetesMeshEnvListener.access$300:(Lorg/apache/dubbo/registry/kubernetes/KubernetesMeshEnvListener;)Ljava/util/Map;
     177: aload_0
     178: getfield      #2                  // Field val$appName:Ljava/lang/String;
     181: invokeinterface #28,  2           // InterfaceMethod java/util/Map.get:(Ljava/lang/Object;)Ljava/lang/Object;
     186: checkcast     #32                 // class org/apache/dubbo/rpc/cluster/router/mesh/route/MeshAppRuleListener
     189: ldc           #33                 // String
     191: invokevirtual #34                 // Method org/apache/dubbo/rpc/cluster/router/mesh/route/MeshAppRuleListener.receiveConfigInfo:(Ljava/lang/String;)V
     194: return

  public void onClose(io.fabric8.kubernetes.client.WatcherException);
    Code:
       0: return

  public void eventReceived(io.fabric8.kubernetes.client.Watcher$Action, java.lang.Object);
    Code:
       0: aload_0
       1: aload_1
       2: aload_2
       3: checkcast     #35                 // class io/fabric8/kubernetes/api/model/GenericKubernetesResource
       6: invokevirtual #36                 // Method eventReceived:(Lio/fabric8/kubernetes/client/Watcher$Action;Lio/fabric8/kubernetes/api/model/GenericKubernetesResource;)V
       9: return
}
