Compiled from "KubernetesRegistry.java"
public class org.apache.dubbo.registry.kubernetes.KubernetesRegistry extends org.apache.dubbo.registry.support.FailbackRegistry {
  public org.apache.dubbo.registry.kubernetes.KubernetesRegistry(org.apache.dubbo.common.URL);
    Code:
       0: aload_0
       1: aload_1
       2: invokespecial #1                  // Method org/apache/dubbo/registry/support/FailbackRegistry."<init>":(Lorg/apache/dubbo/common/URL;)V
       5: return

  public boolean isAvailable();
    Code:
       0: iconst_1
       1: ireturn

  public void doRegister(org.apache.dubbo.common.URL);
    Code:
       0: return

  public void doUnregister(org.apache.dubbo.common.URL);
    Code:
       0: return

  public void doSubscribe(org.apache.dubbo.common.URL, org.apache.dubbo.registry.NotifyListener);
    Code:
       0: return

  public void doUnsubscribe(org.apache.dubbo.common.URL, org.apache.dubbo.registry.NotifyListener);
    Code:
       0: return
}
