Compiled from "KubernetesServiceDiscovery.java"
class org.apache.dubbo.registry.kubernetes.KubernetesServiceDiscovery$1 implements io.fabric8.kubernetes.client.informers.ResourceEventHandler<io.fabric8.kubernetes.api.model.Endpoints> {
  final java.lang.String val$serviceName;

  final org.apache.dubbo.registry.client.event.listener.ServiceInstancesChangedListener val$listener;

  final org.apache.dubbo.registry.kubernetes.KubernetesServiceDiscovery this$0;

  org.apache.dubbo.registry.kubernetes.KubernetesServiceDiscovery$1(org.apache.dubbo.registry.kubernetes.KubernetesServiceDiscovery, java.lang.String, org.apache.dubbo.registry.client.event.listener.ServiceInstancesChangedListener);
    Code:
       0: aload_0
       1: aload_1
       2: putfield      #1                  // Field this$0:Lorg/apache/dubbo/registry/kubernetes/KubernetesServiceDiscovery;
       5: aload_0
       6: aload_2
       7: putfield      #2                  // Field val$serviceName:Ljava/lang/String;
      10: aload_0
      11: aload_3
      12: putfield      #3                  // Field val$listener:Lorg/apache/dubbo/registry/client/event/listener/ServiceInstancesChangedListener;
      15: aload_0
      16: invokespecial #4                  // Method java/lang/Object."<init>":()V
      19: return

  public void onAdd(io.fabric8.kubernetes.api.model.Endpoints);
    Code:
       0: aload_0
       1: getfield      #1                  // Field this$0:Lorg/apache/dubbo/registry/kubernetes/KubernetesServiceDiscovery;
       4: invokestatic  #5                  // Method org/apache/dubbo/registry/kubernetes/KubernetesServiceDiscovery.access$000:(Lorg/apache/dubbo/registry/kubernetes/KubernetesServiceDiscovery;)Lorg/apache/dubbo/common/logger/ErrorTypeAwareLogger;
       7: invokeinterface #6,  1            // InterfaceMethod org/apache/dubbo/common/logger/ErrorTypeAwareLogger.isDebugEnabled:()Z
      12: ifeq          61
      15: aload_0
      16: getfield      #1                  // Field this$0:Lorg/apache/dubbo/registry/kubernetes/KubernetesServiceDiscovery;
      19: invokestatic  #5                  // Method org/apache/dubbo/registry/kubernetes/KubernetesServiceDiscovery.access$000:(Lorg/apache/dubbo/registry/kubernetes/KubernetesServiceDiscovery;)Lorg/apache/dubbo/common/logger/ErrorTypeAwareLogger;
      22: new           #7                  // class java/lang/StringBuilder
      25: dup
      26: invokespecial #8                  // Method java/lang/StringBuilder."<init>":()V
      29: ldc           #9                  // String Received Endpoint Event. Event type: added. Current pod name:
      31: invokevirtual #10                 // Method java/lang/StringBuilder.append:(Ljava/lang/String;)Ljava/lang/StringBuilder;
      34: aload_0
      35: getfield      #1                  // Field this$0:Lorg/apache/dubbo/registry/kubernetes/KubernetesServiceDiscovery;
      38: invokestatic  #11                 // Method org/apache/dubbo/registry/kubernetes/KubernetesServiceDiscovery.access$100:(Lorg/apache/dubbo/registry/kubernetes/KubernetesServiceDiscovery;)Ljava/lang/String;
      41: invokevirtual #10                 // Method java/lang/StringBuilder.append:(Ljava/lang/String;)Ljava/lang/StringBuilder;
      44: ldc           #12                 // String . Endpoints is:
      46: invokevirtual #10                 // Method java/lang/StringBuilder.append:(Ljava/lang/String;)Ljava/lang/StringBuilder;
      49: aload_1
      50: invokevirtual #13                 // Method java/lang/StringBuilder.append:(Ljava/lang/Object;)Ljava/lang/StringBuilder;
      53: invokevirtual #14                 // Method java/lang/StringBuilder.toString:()Ljava/lang/String;
      56: invokeinterface #15,  2           // InterfaceMethod org/apache/dubbo/common/logger/ErrorTypeAwareLogger.debug:(Ljava/lang/String;)V
      61: aload_0
      62: getfield      #1                  // Field this$0:Lorg/apache/dubbo/registry/kubernetes/KubernetesServiceDiscovery;
      65: aload_0
      66: getfield      #2                  // Field val$serviceName:Ljava/lang/String;
      69: aload_0
      70: getfield      #3                  // Field val$listener:Lorg/apache/dubbo/registry/client/event/listener/ServiceInstancesChangedListener;
      73: aload_0
      74: getfield      #1                  // Field this$0:Lorg/apache/dubbo/registry/kubernetes/KubernetesServiceDiscovery;
      77: aload_1
      78: aload_0
      79: getfield      #2                  // Field val$serviceName:Ljava/lang/String;
      82: invokestatic  #16                 // Method org/apache/dubbo/registry/kubernetes/KubernetesServiceDiscovery.access$200:(Lorg/apache/dubbo/registry/kubernetes/KubernetesServiceDiscovery;Lio/fabric8/kubernetes/api/model/Endpoints;Ljava/lang/String;)Ljava/util/List;
      85: invokestatic  #17                 // Method org/apache/dubbo/registry/kubernetes/KubernetesServiceDiscovery.access$300:(Lorg/apache/dubbo/registry/kubernetes/KubernetesServiceDiscovery;Ljava/lang/String;Lorg/apache/dubbo/registry/client/event/listener/ServiceInstancesChangedListener;Ljava/util/List;)V
      88: return

  public void onUpdate(io.fabric8.kubernetes.api.model.Endpoints, io.fabric8.kubernetes.api.model.Endpoints);
    Code:
       0: aload_0
       1: getfield      #1                  // Field this$0:Lorg/apache/dubbo/registry/kubernetes/KubernetesServiceDiscovery;
       4: invokestatic  #5                  // Method org/apache/dubbo/registry/kubernetes/KubernetesServiceDiscovery.access$000:(Lorg/apache/dubbo/registry/kubernetes/KubernetesServiceDiscovery;)Lorg/apache/dubbo/common/logger/ErrorTypeAwareLogger;
       7: invokeinterface #6,  1            // InterfaceMethod org/apache/dubbo/common/logger/ErrorTypeAwareLogger.isDebugEnabled:()Z
      12: ifeq          61
      15: aload_0
      16: getfield      #1                  // Field this$0:Lorg/apache/dubbo/registry/kubernetes/KubernetesServiceDiscovery;
      19: invokestatic  #5                  // Method org/apache/dubbo/registry/kubernetes/KubernetesServiceDiscovery.access$000:(Lorg/apache/dubbo/registry/kubernetes/KubernetesServiceDiscovery;)Lorg/apache/dubbo/common/logger/ErrorTypeAwareLogger;
      22: new           #7                  // class java/lang/StringBuilder
      25: dup
      26: invokespecial #8                  // Method java/lang/StringBuilder."<init>":()V
      29: ldc           #18                 // String Received Endpoint Event. Event type: updated. Current pod name:
      31: invokevirtual #10                 // Method java/lang/StringBuilder.append:(Ljava/lang/String;)Ljava/lang/StringBuilder;
      34: aload_0
      35: getfield      #1                  // Field this$0:Lorg/apache/dubbo/registry/kubernetes/KubernetesServiceDiscovery;
      38: invokestatic  #11                 // Method org/apache/dubbo/registry/kubernetes/KubernetesServiceDiscovery.access$100:(Lorg/apache/dubbo/registry/kubernetes/KubernetesServiceDiscovery;)Ljava/lang/String;
      41: invokevirtual #10                 // Method java/lang/StringBuilder.append:(Ljava/lang/String;)Ljava/lang/StringBuilder;
      44: ldc           #19                 // String . The new Endpoints is:
      46: invokevirtual #10                 // Method java/lang/StringBuilder.append:(Ljava/lang/String;)Ljava/lang/StringBuilder;
      49: aload_2
      50: invokevirtual #13                 // Method java/lang/StringBuilder.append:(Ljava/lang/Object;)Ljava/lang/StringBuilder;
      53: invokevirtual #14                 // Method java/lang/StringBuilder.toString:()Ljava/lang/String;
      56: invokeinterface #15,  2           // InterfaceMethod org/apache/dubbo/common/logger/ErrorTypeAwareLogger.debug:(Ljava/lang/String;)V
      61: aload_0
      62: getfield      #1                  // Field this$0:Lorg/apache/dubbo/registry/kubernetes/KubernetesServiceDiscovery;
      65: aload_0
      66: getfield      #2                  // Field val$serviceName:Ljava/lang/String;
      69: aload_0
      70: getfield      #3                  // Field val$listener:Lorg/apache/dubbo/registry/client/event/listener/ServiceInstancesChangedListener;
      73: aload_0
      74: getfield      #1                  // Field this$0:Lorg/apache/dubbo/registry/kubernetes/KubernetesServiceDiscovery;
      77: aload_2
      78: aload_0
      79: getfield      #2                  // Field val$serviceName:Ljava/lang/String;
      82: invokestatic  #16                 // Method org/apache/dubbo/registry/kubernetes/KubernetesServiceDiscovery.access$200:(Lorg/apache/dubbo/registry/kubernetes/KubernetesServiceDiscovery;Lio/fabric8/kubernetes/api/model/Endpoints;Ljava/lang/String;)Ljava/util/List;
      85: invokestatic  #17                 // Method org/apache/dubbo/registry/kubernetes/KubernetesServiceDiscovery.access$300:(Lorg/apache/dubbo/registry/kubernetes/KubernetesServiceDiscovery;Ljava/lang/String;Lorg/apache/dubbo/registry/client/event/listener/ServiceInstancesChangedListener;Ljava/util/List;)V
      88: return

  public void onDelete(io.fabric8.kubernetes.api.model.Endpoints, boolean);
    Code:
       0: aload_0
       1: getfield      #1                  // Field this$0:Lorg/apache/dubbo/registry/kubernetes/KubernetesServiceDiscovery;
       4: invokestatic  #5                  // Method org/apache/dubbo/registry/kubernetes/KubernetesServiceDiscovery.access$000:(Lorg/apache/dubbo/registry/kubernetes/KubernetesServiceDiscovery;)Lorg/apache/dubbo/common/logger/ErrorTypeAwareLogger;
       7: invokeinterface #6,  1            // InterfaceMethod org/apache/dubbo/common/logger/ErrorTypeAwareLogger.isDebugEnabled:()Z
      12: ifeq          61
      15: aload_0
      16: getfield      #1                  // Field this$0:Lorg/apache/dubbo/registry/kubernetes/KubernetesServiceDiscovery;
      19: invokestatic  #5                  // Method org/apache/dubbo/registry/kubernetes/KubernetesServiceDiscovery.access$000:(Lorg/apache/dubbo/registry/kubernetes/KubernetesServiceDiscovery;)Lorg/apache/dubbo/common/logger/ErrorTypeAwareLogger;
      22: new           #7                  // class java/lang/StringBuilder
      25: dup
      26: invokespecial #8                  // Method java/lang/StringBuilder."<init>":()V
      29: ldc           #20                 // String Received Endpoint Event. Event type: deleted. Current pod name:
      31: invokevirtual #10                 // Method java/lang/StringBuilder.append:(Ljava/lang/String;)Ljava/lang/StringBuilder;
      34: aload_0
      35: getfield      #1                  // Field this$0:Lorg/apache/dubbo/registry/kubernetes/KubernetesServiceDiscovery;
      38: invokestatic  #11                 // Method org/apache/dubbo/registry/kubernetes/KubernetesServiceDiscovery.access$100:(Lorg/apache/dubbo/registry/kubernetes/KubernetesServiceDiscovery;)Ljava/lang/String;
      41: invokevirtual #10                 // Method java/lang/StringBuilder.append:(Ljava/lang/String;)Ljava/lang/StringBuilder;
      44: ldc           #12                 // String . Endpoints is:
      46: invokevirtual #10                 // Method java/lang/StringBuilder.append:(Ljava/lang/String;)Ljava/lang/StringBuilder;
      49: aload_1
      50: invokevirtual #13                 // Method java/lang/StringBuilder.append:(Ljava/lang/Object;)Ljava/lang/StringBuilder;
      53: invokevirtual #14                 // Method java/lang/StringBuilder.toString:()Ljava/lang/String;
      56: invokeinterface #15,  2           // InterfaceMethod org/apache/dubbo/common/logger/ErrorTypeAwareLogger.debug:(Ljava/lang/String;)V
      61: aload_0
      62: getfield      #1                  // Field this$0:Lorg/apache/dubbo/registry/kubernetes/KubernetesServiceDiscovery;
      65: aload_0
      66: getfield      #2                  // Field val$serviceName:Ljava/lang/String;
      69: aload_0
      70: getfield      #3                  // Field val$listener:Lorg/apache/dubbo/registry/client/event/listener/ServiceInstancesChangedListener;
      73: aload_0
      74: getfield      #1                  // Field this$0:Lorg/apache/dubbo/registry/kubernetes/KubernetesServiceDiscovery;
      77: aload_1
      78: aload_0
      79: getfield      #2                  // Field val$serviceName:Ljava/lang/String;
      82: invokestatic  #16                 // Method org/apache/dubbo/registry/kubernetes/KubernetesServiceDiscovery.access$200:(Lorg/apache/dubbo/registry/kubernetes/KubernetesServiceDiscovery;Lio/fabric8/kubernetes/api/model/Endpoints;Ljava/lang/String;)Ljava/util/List;
      85: invokestatic  #17                 // Method org/apache/dubbo/registry/kubernetes/KubernetesServiceDiscovery.access$300:(Lorg/apache/dubbo/registry/kubernetes/KubernetesServiceDiscovery;Ljava/lang/String;Lorg/apache/dubbo/registry/client/event/listener/ServiceInstancesChangedListener;Ljava/util/List;)V
      88: return

  public void onDelete(java.lang.Object, boolean);
    Code:
       0: aload_0
       1: aload_1
       2: checkcast     #21                 // class io/fabric8/kubernetes/api/model/Endpoints
       5: iload_2
       6: invokevirtual #22                 // Method onDelete:(Lio/fabric8/kubernetes/api/model/Endpoints;Z)V
       9: return

  public void onUpdate(java.lang.Object, java.lang.Object);
    Code:
       0: aload_0
       1: aload_1
       2: checkcast     #21                 // class io/fabric8/kubernetes/api/model/Endpoints
       5: aload_2
       6: checkcast     #21                 // class io/fabric8/kubernetes/api/model/Endpoints
       9: invokevirtual #23                 // Method onUpdate:(Lio/fabric8/kubernetes/api/model/Endpoints;Lio/fabric8/kubernetes/api/model/Endpoints;)V
      12: return

  public void onAdd(java.lang.Object);
    Code:
       0: aload_0
       1: aload_1
       2: checkcast     #21                 // class io/fabric8/kubernetes/api/model/Endpoints
       5: invokevirtual #24                 // Method onAdd:(Lio/fabric8/kubernetes/api/model/Endpoints;)V
       8: return
}
