Compiled from "KubernetesMeshEnvListener.java"
public class org.apache.dubbo.registry.kubernetes.KubernetesMeshEnvListener implements org.apache.dubbo.rpc.cluster.router.mesh.route.MeshEnvListener {
  public static final org.apache.dubbo.common.logger.ErrorTypeAwareLogger logger;

  private static volatile boolean usingApiServer;

  private static volatile io.fabric8.kubernetes.client.KubernetesClient kubernetesClient;

  private static volatile java.lang.String namespace;

  private final java.util.Map<java.lang.String, org.apache.dubbo.rpc.cluster.router.mesh.route.MeshAppRuleListener> appRuleListenerMap;

  private final java.util.Map<java.lang.String, io.fabric8.kubernetes.client.Watch> vsAppWatch;

  private final java.util.Map<java.lang.String, io.fabric8.kubernetes.client.Watch> drAppWatch;

  private final java.util.Map<java.lang.String, java.lang.String> vsAppCache;

  private final java.util.Map<java.lang.String, java.lang.String> drAppCache;

  public org.apache.dubbo.registry.kubernetes.KubernetesMeshEnvListener();
    Code:
       0: aload_0
       1: invokespecial #6                  // Method java/lang/Object."<init>":()V
       4: aload_0
       5: new           #7                  // class java/util/concurrent/ConcurrentHashMap
       8: dup
       9: invokespecial #8                  // Method java/util/concurrent/ConcurrentHashMap."<init>":()V
      12: putfield      #2                  // Field appRuleListenerMap:Ljava/util/Map;
      15: aload_0
      16: new           #7                  // class java/util/concurrent/ConcurrentHashMap
      19: dup
      20: invokespecial #8                  // Method java/util/concurrent/ConcurrentHashMap."<init>":()V
      23: putfield      #9                  // Field vsAppWatch:Ljava/util/Map;
      26: aload_0
      27: new           #7                  // class java/util/concurrent/ConcurrentHashMap
      30: dup
      31: invokespecial #8                  // Method java/util/concurrent/ConcurrentHashMap."<init>":()V
      34: putfield      #10                 // Field drAppWatch:Ljava/util/Map;
      37: aload_0
      38: new           #7                  // class java/util/concurrent/ConcurrentHashMap
      41: dup
      42: invokespecial #8                  // Method java/util/concurrent/ConcurrentHashMap."<init>":()V
      45: putfield      #5                  // Field vsAppCache:Ljava/util/Map;
      48: aload_0
      49: new           #7                  // class java/util/concurrent/ConcurrentHashMap
      52: dup
      53: invokespecial #8                  // Method java/util/concurrent/ConcurrentHashMap."<init>":()V
      56: putfield      #4                  // Field drAppCache:Ljava/util/Map;
      59: return

  public static void injectKubernetesEnv(io.fabric8.kubernetes.client.KubernetesClient, java.lang.String);
    Code:
       0: iconst_1
       1: putstatic     #11                 // Field usingApiServer:Z
       4: aload_0
       5: putstatic     #12                 // Field kubernetesClient:Lio/fabric8/kubernetes/client/KubernetesClient;
       8: aload_1
       9: putstatic     #13                 // Field namespace:Ljava/lang/String;
      12: return

  public boolean isEnable();
    Code:
       0: getstatic     #11                 // Field usingApiServer:Z
       3: ireturn

  public void onSubscribe(java.lang.String, org.apache.dubbo.rpc.cluster.router.mesh.route.MeshAppRuleListener);
    Code:
       0: aload_0
       1: getfield      #2                  // Field appRuleListenerMap:Ljava/util/Map;
       4: aload_1
       5: aload_2
       6: invokeinterface #14,  3           // InterfaceMethod java/util/Map.put:(Ljava/lang/Object;Ljava/lang/Object;)Ljava/lang/Object;
      11: pop
      12: getstatic     #15                 // Field logger:Lorg/apache/dubbo/common/logger/ErrorTypeAwareLogger;
      15: new           #16                 // class java/lang/StringBuilder
      18: dup
      19: invokespecial #17                 // Method java/lang/StringBuilder."<init>":()V
      22: ldc           #18                 // String Subscribe Mesh Rule in Kubernetes. AppName:
      24: invokevirtual #19                 // Method java/lang/StringBuilder.append:(Ljava/lang/String;)Ljava/lang/StringBuilder;
      27: aload_1
      28: invokevirtual #19                 // Method java/lang/StringBuilder.append:(Ljava/lang/String;)Ljava/lang/StringBuilder;
      31: invokevirtual #20                 // Method java/lang/StringBuilder.toString:()Ljava/lang/String;
      34: invokeinterface #21,  2           // InterfaceMethod org/apache/dubbo/common/logger/ErrorTypeAwareLogger.info:(Ljava/lang/String;)V
      39: aload_0
      40: aload_1
      41: invokespecial #22                 // Method subscribeVs:(Ljava/lang/String;)V
      44: aload_0
      45: aload_1
      46: invokespecial #23                 // Method subscribeDr:(Ljava/lang/String;)V
      49: aload_0
      50: aload_1
      51: invokespecial #24                 // Method notifyOnce:(Ljava/lang/String;)V
      54: return

  private void subscribeVs(java.lang.String);
    Code:
       0: aload_0
       1: getfield      #9                  // Field vsAppWatch:Ljava/util/Map;
       4: aload_1
       5: invokeinterface #25,  2           // InterfaceMethod java/util/Map.containsKey:(Ljava/lang/Object;)Z
      10: ifeq          14
      13: return
      14: getstatic     #12                 // Field kubernetesClient:Lio/fabric8/kubernetes/client/KubernetesClient;
      17: invokestatic  #26                 // Method org/apache/dubbo/registry/kubernetes/MeshConstant.getVsDefinition:()Lio/fabric8/kubernetes/client/dsl/base/CustomResourceDefinitionContext;
      20: invokeinterface #27,  2           // InterfaceMethod io/fabric8/kubernetes/client/KubernetesClient.genericKubernetesResources:(Lio/fabric8/kubernetes/client/dsl/base/ResourceDefinitionContext;)Lio/fabric8/kubernetes/client/dsl/MixedOperation;
      25: getstatic     #13                 // Field namespace:Ljava/lang/String;
      28: invokeinterface #28,  2           // InterfaceMethod io/fabric8/kubernetes/client/dsl/MixedOperation.inNamespace:(Ljava/lang/String;)Ljava/lang/Object;
      33: checkcast     #29                 // class io/fabric8/kubernetes/client/dsl/NonNamespaceOperation
      36: aload_1
      37: invokeinterface #30,  2           // InterfaceMethod io/fabric8/kubernetes/client/dsl/NonNamespaceOperation.withName:(Ljava/lang/String;)Ljava/lang/Object;
      42: checkcast     #31                 // class io/fabric8/kubernetes/client/dsl/Resource
      45: new           #32                 // class org/apache/dubbo/registry/kubernetes/KubernetesMeshEnvListener$1
      48: dup
      49: aload_0
      50: aload_1
      51: invokespecial #33                 // Method org/apache/dubbo/registry/kubernetes/KubernetesMeshEnvListener$1."<init>":(Lorg/apache/dubbo/registry/kubernetes/KubernetesMeshEnvListener;Ljava/lang/String;)V
      54: invokeinterface #34,  2           // InterfaceMethod io/fabric8/kubernetes/client/dsl/Resource.watch:(Lio/fabric8/kubernetes/client/Watcher;)Lio/fabric8/kubernetes/client/Watch;
      59: astore_2
      60: aload_0
      61: getfield      #9                  // Field vsAppWatch:Ljava/util/Map;
      64: aload_1
      65: aload_2
      66: invokeinterface #14,  3           // InterfaceMethod java/util/Map.put:(Ljava/lang/Object;Ljava/lang/Object;)Ljava/lang/Object;
      71: pop
      72: getstatic     #12                 // Field kubernetesClient:Lio/fabric8/kubernetes/client/KubernetesClient;
      75: invokestatic  #26                 // Method org/apache/dubbo/registry/kubernetes/MeshConstant.getVsDefinition:()Lio/fabric8/kubernetes/client/dsl/base/CustomResourceDefinitionContext;
      78: invokeinterface #27,  2           // InterfaceMethod io/fabric8/kubernetes/client/KubernetesClient.genericKubernetesResources:(Lio/fabric8/kubernetes/client/dsl/base/ResourceDefinitionContext;)Lio/fabric8/kubernetes/client/dsl/MixedOperation;
      83: getstatic     #13                 // Field namespace:Ljava/lang/String;
      86: invokeinterface #28,  2           // InterfaceMethod io/fabric8/kubernetes/client/dsl/MixedOperation.inNamespace:(Ljava/lang/String;)Ljava/lang/Object;
      91: checkcast     #29                 // class io/fabric8/kubernetes/client/dsl/NonNamespaceOperation
      94: aload_1
      95: invokeinterface #30,  2           // InterfaceMethod io/fabric8/kubernetes/client/dsl/NonNamespaceOperation.withName:(Ljava/lang/String;)Ljava/lang/Object;
     100: checkcast     #31                 // class io/fabric8/kubernetes/client/dsl/Resource
     103: invokeinterface #35,  1           // InterfaceMethod io/fabric8/kubernetes/client/dsl/Resource.get:()Ljava/lang/Object;
     108: checkcast     #36                 // class io/fabric8/kubernetes/api/model/GenericKubernetesResource
     111: astore_3
     112: aload_0
     113: getfield      #5                  // Field vsAppCache:Ljava/util/Map;
     116: aload_1
     117: new           #37                 // class org/yaml/snakeyaml/Yaml
     120: dup
     121: new           #38                 // class org/yaml/snakeyaml/constructor/SafeConstructor
     124: dup
     125: new           #39                 // class org/yaml/snakeyaml/LoaderOptions
     128: dup
     129: invokespecial #40                 // Method org/yaml/snakeyaml/LoaderOptions."<init>":()V
     132: invokespecial #41                 // Method org/yaml/snakeyaml/constructor/SafeConstructor."<init>":(Lorg/yaml/snakeyaml/LoaderOptions;)V
     135: invokespecial #42                 // Method org/yaml/snakeyaml/Yaml."<init>":(Lorg/yaml/snakeyaml/constructor/BaseConstructor;)V
     138: aload_3
     139: invokevirtual #43                 // Method org/yaml/snakeyaml/Yaml.dump:(Ljava/lang/Object;)Ljava/lang/String;
     142: invokeinterface #14,  3           // InterfaceMethod java/util/Map.put:(Ljava/lang/Object;Ljava/lang/Object;)Ljava/lang/Object;
     147: pop
     148: goto          152
     151: astore_3
     152: goto          173
     155: astore_2
     156: getstatic     #15                 // Field logger:Lorg/apache/dubbo/common/logger/ErrorTypeAwareLogger;
     159: ldc           #46                 // String 1-19
     161: ldc           #47                 // String
     163: ldc           #47                 // String
     165: ldc           #48                 // String Error occurred when listen kubernetes crd.
     167: aload_2
     168: invokeinterface #49,  6           // InterfaceMethod org/apache/dubbo/common/logger/ErrorTypeAwareLogger.error:(Ljava/lang/String;Ljava/lang/String;Ljava/lang/String;Ljava/lang/String;Ljava/lang/Throwable;)V
     173: return
    Exception table:
       from    to  target type
          72   148   151   Class java/lang/Throwable
          14   152   155   Class java/lang/Exception

  private void notifyListener(java.lang.String, java.lang.String, java.lang.String);
    Code:
       0: new           #16                 // class java/lang/StringBuilder
       3: dup
       4: invokespecial #17                 // Method java/lang/StringBuilder."<init>":()V
       7: aload_1
       8: invokevirtual #19                 // Method java/lang/StringBuilder.append:(Ljava/lang/String;)Ljava/lang/StringBuilder;
      11: ldc           #50                 // String \n---\n
      13: invokevirtual #19                 // Method java/lang/StringBuilder.append:(Ljava/lang/String;)Ljava/lang/StringBuilder;
      16: aload_3
      17: invokevirtual #19                 // Method java/lang/StringBuilder.append:(Ljava/lang/String;)Ljava/lang/StringBuilder;
      20: invokevirtual #20                 // Method java/lang/StringBuilder.toString:()Ljava/lang/String;
      23: astore        4
      25: getstatic     #15                 // Field logger:Lorg/apache/dubbo/common/logger/ErrorTypeAwareLogger;
      28: new           #16                 // class java/lang/StringBuilder
      31: dup
      32: invokespecial #17                 // Method java/lang/StringBuilder."<init>":()V
      35: ldc           #51                 // String Notify App Rule Listener. AppName:
      37: invokevirtual #19                 // Method java/lang/StringBuilder.append:(Ljava/lang/String;)Ljava/lang/StringBuilder;
      40: aload_2
      41: invokevirtual #19                 // Method java/lang/StringBuilder.append:(Ljava/lang/String;)Ljava/lang/StringBuilder;
      44: ldc           #52                 // String  Rule:
      46: invokevirtual #19                 // Method java/lang/StringBuilder.append:(Ljava/lang/String;)Ljava/lang/StringBuilder;
      49: aload         4
      51: invokevirtual #19                 // Method java/lang/StringBuilder.append:(Ljava/lang/String;)Ljava/lang/StringBuilder;
      54: invokevirtual #20                 // Method java/lang/StringBuilder.toString:()Ljava/lang/String;
      57: invokeinterface #21,  2           // InterfaceMethod org/apache/dubbo/common/logger/ErrorTypeAwareLogger.info:(Ljava/lang/String;)V
      62: aload_0
      63: getfield      #2                  // Field appRuleListenerMap:Ljava/util/Map;
      66: aload_2
      67: invokeinterface #53,  2           // InterfaceMethod java/util/Map.get:(Ljava/lang/Object;)Ljava/lang/Object;
      72: checkcast     #54                 // class org/apache/dubbo/rpc/cluster/router/mesh/route/MeshAppRuleListener
      75: aload         4
      77: invokevirtual #55                 // Method org/apache/dubbo/rpc/cluster/router/mesh/route/MeshAppRuleListener.receiveConfigInfo:(Ljava/lang/String;)V
      80: return

  private void subscribeDr(java.lang.String);
    Code:
       0: aload_0
       1: getfield      #10                 // Field drAppWatch:Ljava/util/Map;
       4: aload_1
       5: invokeinterface #25,  2           // InterfaceMethod java/util/Map.containsKey:(Ljava/lang/Object;)Z
      10: ifeq          14
      13: return
      14: getstatic     #12                 // Field kubernetesClient:Lio/fabric8/kubernetes/client/KubernetesClient;
      17: invokestatic  #56                 // Method org/apache/dubbo/registry/kubernetes/MeshConstant.getDrDefinition:()Lio/fabric8/kubernetes/client/dsl/base/CustomResourceDefinitionContext;
      20: invokeinterface #27,  2           // InterfaceMethod io/fabric8/kubernetes/client/KubernetesClient.genericKubernetesResources:(Lio/fabric8/kubernetes/client/dsl/base/ResourceDefinitionContext;)Lio/fabric8/kubernetes/client/dsl/MixedOperation;
      25: getstatic     #13                 // Field namespace:Ljava/lang/String;
      28: invokeinterface #28,  2           // InterfaceMethod io/fabric8/kubernetes/client/dsl/MixedOperation.inNamespace:(Ljava/lang/String;)Ljava/lang/Object;
      33: checkcast     #29                 // class io/fabric8/kubernetes/client/dsl/NonNamespaceOperation
      36: aload_1
      37: invokeinterface #30,  2           // InterfaceMethod io/fabric8/kubernetes/client/dsl/NonNamespaceOperation.withName:(Ljava/lang/String;)Ljava/lang/Object;
      42: checkcast     #31                 // class io/fabric8/kubernetes/client/dsl/Resource
      45: new           #57                 // class org/apache/dubbo/registry/kubernetes/KubernetesMeshEnvListener$2
      48: dup
      49: aload_0
      50: aload_1
      51: invokespecial #58                 // Method org/apache/dubbo/registry/kubernetes/KubernetesMeshEnvListener$2."<init>":(Lorg/apache/dubbo/registry/kubernetes/KubernetesMeshEnvListener;Ljava/lang/String;)V
      54: invokeinterface #34,  2           // InterfaceMethod io/fabric8/kubernetes/client/dsl/Resource.watch:(Lio/fabric8/kubernetes/client/Watcher;)Lio/fabric8/kubernetes/client/Watch;
      59: astore_2
      60: aload_0
      61: getfield      #10                 // Field drAppWatch:Ljava/util/Map;
      64: aload_1
      65: aload_2
      66: invokeinterface #14,  3           // InterfaceMethod java/util/Map.put:(Ljava/lang/Object;Ljava/lang/Object;)Ljava/lang/Object;
      71: pop
      72: getstatic     #12                 // Field kubernetesClient:Lio/fabric8/kubernetes/client/KubernetesClient;
      75: invokestatic  #56                 // Method org/apache/dubbo/registry/kubernetes/MeshConstant.getDrDefinition:()Lio/fabric8/kubernetes/client/dsl/base/CustomResourceDefinitionContext;
      78: invokeinterface #27,  2           // InterfaceMethod io/fabric8/kubernetes/client/KubernetesClient.genericKubernetesResources:(Lio/fabric8/kubernetes/client/dsl/base/ResourceDefinitionContext;)Lio/fabric8/kubernetes/client/dsl/MixedOperation;
      83: getstatic     #13                 // Field namespace:Ljava/lang/String;
      86: invokeinterface #28,  2           // InterfaceMethod io/fabric8/kubernetes/client/dsl/MixedOperation.inNamespace:(Ljava/lang/String;)Ljava/lang/Object;
      91: checkcast     #29                 // class io/fabric8/kubernetes/client/dsl/NonNamespaceOperation
      94: aload_1
      95: invokeinterface #30,  2           // InterfaceMethod io/fabric8/kubernetes/client/dsl/NonNamespaceOperation.withName:(Ljava/lang/String;)Ljava/lang/Object;
     100: checkcast     #31                 // class io/fabric8/kubernetes/client/dsl/Resource
     103: invokeinterface #35,  1           // InterfaceMethod io/fabric8/kubernetes/client/dsl/Resource.get:()Ljava/lang/Object;
     108: checkcast     #36                 // class io/fabric8/kubernetes/api/model/GenericKubernetesResource
     111: astore_3
     112: aload_0
     113: getfield      #4                  // Field drAppCache:Ljava/util/Map;
     116: aload_1
     117: new           #37                 // class org/yaml/snakeyaml/Yaml
     120: dup
     121: new           #38                 // class org/yaml/snakeyaml/constructor/SafeConstructor
     124: dup
     125: new           #39                 // class org/yaml/snakeyaml/LoaderOptions
     128: dup
     129: invokespecial #40                 // Method org/yaml/snakeyaml/LoaderOptions."<init>":()V
     132: invokespecial #41                 // Method org/yaml/snakeyaml/constructor/SafeConstructor."<init>":(Lorg/yaml/snakeyaml/LoaderOptions;)V
     135: invokespecial #42                 // Method org/yaml/snakeyaml/Yaml."<init>":(Lorg/yaml/snakeyaml/constructor/BaseConstructor;)V
     138: aload_3
     139: invokevirtual #43                 // Method org/yaml/snakeyaml/Yaml.dump:(Ljava/lang/Object;)Ljava/lang/String;
     142: invokeinterface #14,  3           // InterfaceMethod java/util/Map.put:(Ljava/lang/Object;Ljava/lang/Object;)Ljava/lang/Object;
     147: pop
     148: goto          152
     151: astore_3
     152: goto          173
     155: astore_2
     156: getstatic     #15                 // Field logger:Lorg/apache/dubbo/common/logger/ErrorTypeAwareLogger;
     159: ldc           #46                 // String 1-19
     161: ldc           #47                 // String
     163: ldc           #47                 // String
     165: ldc           #48                 // String Error occurred when listen kubernetes crd.
     167: aload_2
     168: invokeinterface #49,  6           // InterfaceMethod org/apache/dubbo/common/logger/ErrorTypeAwareLogger.error:(Ljava/lang/String;Ljava/lang/String;Ljava/lang/String;Ljava/lang/String;Ljava/lang/Throwable;)V
     173: return
    Exception table:
       from    to  target type
          72   148   151   Class java/lang/Throwable
          14   152   155   Class java/lang/Exception

  private void notifyOnce(java.lang.String);
    Code:
       0: aload_0
       1: getfield      #5                  // Field vsAppCache:Ljava/util/Map;
       4: aload_1
       5: invokeinterface #25,  2           // InterfaceMethod java/util/Map.containsKey:(Ljava/lang/Object;)Z
      10: ifeq          57
      13: aload_0
      14: getfield      #4                  // Field drAppCache:Ljava/util/Map;
      17: aload_1
      18: invokeinterface #25,  2           // InterfaceMethod java/util/Map.containsKey:(Ljava/lang/Object;)Z
      23: ifeq          57
      26: aload_0
      27: aload_0
      28: getfield      #5                  // Field vsAppCache:Ljava/util/Map;
      31: aload_1
      32: invokeinterface #53,  2           // InterfaceMethod java/util/Map.get:(Ljava/lang/Object;)Ljava/lang/Object;
      37: checkcast     #59                 // class java/lang/String
      40: aload_1
      41: aload_0
      42: getfield      #4                  // Field drAppCache:Ljava/util/Map;
      45: aload_1
      46: invokeinterface #53,  2           // InterfaceMethod java/util/Map.get:(Ljava/lang/Object;)Ljava/lang/Object;
      51: checkcast     #59                 // class java/lang/String
      54: invokespecial #3                  // Method notifyListener:(Ljava/lang/String;Ljava/lang/String;Ljava/lang/String;)V
      57: return

  public void onUnSubscribe(java.lang.String);
    Code:
       0: aload_0
       1: getfield      #2                  // Field appRuleListenerMap:Ljava/util/Map;
       4: aload_1
       5: invokeinterface #60,  2           // InterfaceMethod java/util/Map.remove:(Ljava/lang/Object;)Ljava/lang/Object;
      10: pop
      11: aload_0
      12: getfield      #9                  // Field vsAppWatch:Ljava/util/Map;
      15: aload_1
      16: invokeinterface #25,  2           // InterfaceMethod java/util/Map.containsKey:(Ljava/lang/Object;)Z
      21: ifeq          42
      24: aload_0
      25: getfield      #9                  // Field vsAppWatch:Ljava/util/Map;
      28: aload_1
      29: invokeinterface #60,  2           // InterfaceMethod java/util/Map.remove:(Ljava/lang/Object;)Ljava/lang/Object;
      34: checkcast     #61                 // class io/fabric8/kubernetes/client/Watch
      37: invokeinterface #62,  1           // InterfaceMethod io/fabric8/kubernetes/client/Watch.close:()V
      42: aload_0
      43: getfield      #5                  // Field vsAppCache:Ljava/util/Map;
      46: aload_1
      47: invokeinterface #60,  2           // InterfaceMethod java/util/Map.remove:(Ljava/lang/Object;)Ljava/lang/Object;
      52: pop
      53: aload_0
      54: getfield      #10                 // Field drAppWatch:Ljava/util/Map;
      57: aload_1
      58: invokeinterface #25,  2           // InterfaceMethod java/util/Map.containsKey:(Ljava/lang/Object;)Z
      63: ifeq          84
      66: aload_0
      67: getfield      #10                 // Field drAppWatch:Ljava/util/Map;
      70: aload_1
      71: invokeinterface #60,  2           // InterfaceMethod java/util/Map.remove:(Ljava/lang/Object;)Ljava/lang/Object;
      76: checkcast     #61                 // class io/fabric8/kubernetes/client/Watch
      79: invokeinterface #62,  1           // InterfaceMethod io/fabric8/kubernetes/client/Watch.close:()V
      84: aload_0
      85: getfield      #4                  // Field drAppCache:Ljava/util/Map;
      88: aload_1
      89: invokeinterface #60,  2           // InterfaceMethod java/util/Map.remove:(Ljava/lang/Object;)Ljava/lang/Object;
      94: pop
      95: return

  static java.util.Map access$000(org.apache.dubbo.registry.kubernetes.KubernetesMeshEnvListener);
    Code:
       0: aload_0
       1: getfield      #5                  // Field vsAppCache:Ljava/util/Map;
       4: areturn

  static java.util.Map access$100(org.apache.dubbo.registry.kubernetes.KubernetesMeshEnvListener);
    Code:
       0: aload_0
       1: getfield      #4                  // Field drAppCache:Ljava/util/Map;
       4: areturn

  static void access$200(org.apache.dubbo.registry.kubernetes.KubernetesMeshEnvListener, java.lang.String, java.lang.String, java.lang.String);
    Code:
       0: aload_0
       1: aload_1
       2: aload_2
       3: aload_3
       4: invokespecial #3                  // Method notifyListener:(Ljava/lang/String;Ljava/lang/String;Ljava/lang/String;)V
       7: return

  static java.util.Map access$300(org.apache.dubbo.registry.kubernetes.KubernetesMeshEnvListener);
    Code:
       0: aload_0
       1: getfield      #2                  // Field appRuleListenerMap:Ljava/util/Map;
       4: areturn

  static {};
    Code:
       0: ldc           #63                 // class org/apache/dubbo/registry/kubernetes/KubernetesMeshEnvListener
       2: invokestatic  #64                 // Method org/apache/dubbo/common/logger/LoggerFactory.getErrorTypeAwareLogger:(Ljava/lang/Class;)Lorg/apache/dubbo/common/logger/ErrorTypeAwareLogger;
       5: putstatic     #15                 // Field logger:Lorg/apache/dubbo/common/logger/ErrorTypeAwareLogger;
       8: iconst_0
       9: putstatic     #11                 // Field usingApiServer:Z
      12: return
}
