Compiled from "KubernetesServiceDiscovery.java"
public class org.apache.dubbo.registry.kubernetes.KubernetesServiceDiscovery extends org.apache.dubbo.registry.client.AbstractServiceDiscovery {
  private final org.apache.dubbo.common.logger.ErrorTypeAwareLogger logger;

  private io.fabric8.kubernetes.client.KubernetesClient kubernetesClient;

  private java.lang.String currentHostname;

  private final org.apache.dubbo.common.URL registryURL;

  private final java.lang.String namespace;

  private final boolean enableRegister;

  public static final java.lang.String KUBERNETES_PROPERTIES_KEY;

  private static final java.util.concurrent.ConcurrentHashMap<java.lang.String, java.util.concurrent.atomic.AtomicLong> SERVICE_UPDATE_TIME;

  private static final java.util.concurrent.ConcurrentHashMap<java.lang.String, io.fabric8.kubernetes.client.informers.SharedIndexInformer<io.fabric8.kubernetes.api.model.Service>> SERVICE_INFORMER;

  private static final java.util.concurrent.ConcurrentHashMap<java.lang.String, io.fabric8.kubernetes.client.informers.SharedIndexInformer<io.fabric8.kubernetes.api.model.Pod>> PODS_INFORMER;

  private static final java.util.concurrent.ConcurrentHashMap<java.lang.String, io.fabric8.kubernetes.client.informers.SharedIndexInformer<io.fabric8.kubernetes.api.model.Endpoints>> ENDPOINTS_INFORMER;

  public org.apache.dubbo.registry.kubernetes.KubernetesServiceDiscovery(org.apache.dubbo.rpc.model.ApplicationModel, org.apache.dubbo.common.URL);
    Code:
       0: aload_0
       1: aload_1
       2: aload_2
       3: invokespecial #8                  // Method org/apache/dubbo/registry/client/AbstractServiceDiscovery."<init>":(Lorg/apache/dubbo/rpc/model/ApplicationModel;Lorg/apache/dubbo/common/URL;)V
       6: aload_0
       7: aload_0
       8: invokevirtual #9                  // Method java/lang/Object.getClass:()Ljava/lang/Class;
      11: invokestatic  #10                 // Method org/apache/dubbo/common/logger/LoggerFactory.getErrorTypeAwareLogger:(Ljava/lang/Class;)Lorg/apache/dubbo/common/logger/ErrorTypeAwareLogger;
      14: putfield      #7                  // Field logger:Lorg/apache/dubbo/common/logger/ErrorTypeAwareLogger;
      17: aload_2
      18: invokestatic  #11                 // Method org/apache/dubbo/registry/kubernetes/util/KubernetesConfigUtils.createKubernetesConfig:(Lorg/apache/dubbo/common/URL;)Lio/fabric8/kubernetes/client/Config;
      21: astore_3
      22: aload_0
      23: new           #12                 // class io/fabric8/kubernetes/client/KubernetesClientBuilder
      26: dup
      27: invokespecial #13                 // Method io/fabric8/kubernetes/client/KubernetesClientBuilder."<init>":()V
      30: aload_3
      31: invokevirtual #14                 // Method io/fabric8/kubernetes/client/KubernetesClientBuilder.withConfig:(Lio/fabric8/kubernetes/client/Config;)Lio/fabric8/kubernetes/client/KubernetesClientBuilder;
      34: invokevirtual #15                 // Method io/fabric8/kubernetes/client/KubernetesClientBuilder.build:()Lio/fabric8/kubernetes/client/KubernetesClient;
      37: putfield      #16                 // Field kubernetesClient:Lio/fabric8/kubernetes/client/KubernetesClient;
      40: aload_0
      41: ldc           #17                 // String HOSTNAME
      43: invokestatic  #18                 // Method java/lang/System.getenv:(Ljava/lang/String;)Ljava/lang/String;
      46: putfield      #6                  // Field currentHostname:Ljava/lang/String;
      49: aload_0
      50: aload_2
      51: putfield      #19                 // Field registryURL:Lorg/apache/dubbo/common/URL;
      54: aload_0
      55: aload_3
      56: invokevirtual #20                 // Method io/fabric8/kubernetes/client/Config.getNamespace:()Ljava/lang/String;
      59: putfield      #21                 // Field namespace:Ljava/lang/String;
      62: aload_0
      63: aload_2
      64: ldc           #23                 // String enableRegister
      66: iconst_1
      67: invokevirtual #24                 // Method org/apache/dubbo/common/URL.getParameter:(Ljava/lang/String;Z)Z
      70: putfield      #25                 // Field enableRegister:Z
      73: aload_0
      74: getfield      #16                 // Field kubernetesClient:Lio/fabric8/kubernetes/client/KubernetesClient;
      77: invokeinterface #26,  1           // InterfaceMethod io/fabric8/kubernetes/client/KubernetesClient.pods:()Lio/fabric8/kubernetes/client/dsl/MixedOperation;
      82: aload_0
      83: getfield      #6                  // Field currentHostname:Ljava/lang/String;
      86: invokeinterface #27,  2           // InterfaceMethod io/fabric8/kubernetes/client/dsl/MixedOperation.withName:(Ljava/lang/String;)Ljava/lang/Object;
      91: checkcast     #28                 // class io/fabric8/kubernetes/client/dsl/PodResource
      94: invokeinterface #29,  1           // InterfaceMethod io/fabric8/kubernetes/client/dsl/PodResource.get:()Ljava/lang/Object;
      99: ifnull        106
     102: iconst_1
     103: goto          107
     106: iconst_0
     107: istore        4
     109: goto          117
     112: astore        5
     114: iconst_0
     115: istore        4
     117: iload         4
     119: ifne          178
     122: new           #31                 // class java/lang/StringBuilder
     125: dup
     126: invokespecial #32                 // Method java/lang/StringBuilder."<init>":()V
     129: ldc           #33                 // String Unable to access api server. Please check your url config. Master URL:
     131: invokevirtual #34                 // Method java/lang/StringBuilder.append:(Ljava/lang/String;)Ljava/lang/StringBuilder;
     134: aload_3
     135: invokevirtual #35                 // Method io/fabric8/kubernetes/client/Config.getMasterUrl:()Ljava/lang/String;
     138: invokevirtual #34                 // Method java/lang/StringBuilder.append:(Ljava/lang/String;)Ljava/lang/StringBuilder;
     141: ldc           #36                 // String  Hostname:
     143: invokevirtual #34                 // Method java/lang/StringBuilder.append:(Ljava/lang/String;)Ljava/lang/StringBuilder;
     146: aload_0
     147: getfield      #6                  // Field currentHostname:Ljava/lang/String;
     150: invokevirtual #34                 // Method java/lang/StringBuilder.append:(Ljava/lang/String;)Ljava/lang/StringBuilder;
     153: invokevirtual #37                 // Method java/lang/StringBuilder.toString:()Ljava/lang/String;
     156: astore        5
     158: aload_0
     159: getfield      #7                  // Field logger:Lorg/apache/dubbo/common/logger/ErrorTypeAwareLogger;
     162: ldc           #38                 // String 1-22
     164: ldc           #39                 // String
     166: ldc           #39                 // String
     168: aload         5
     170: invokeinterface #40,  5           // InterfaceMethod org/apache/dubbo/common/logger/ErrorTypeAwareLogger.error:(Ljava/lang/String;Ljava/lang/String;Ljava/lang/String;Ljava/lang/String;)V
     175: goto          189
     178: aload_0
     179: getfield      #16                 // Field kubernetesClient:Lio/fabric8/kubernetes/client/KubernetesClient;
     182: aload_0
     183: getfield      #21                 // Field namespace:Ljava/lang/String;
     186: invokestatic  #41                 // Method org/apache/dubbo/registry/kubernetes/KubernetesMeshEnvListener.injectKubernetesEnv:(Lio/fabric8/kubernetes/client/KubernetesClient;Ljava/lang/String;)V
     189: return
    Exception table:
       from    to  target type
          73   109   112   Class java/lang/Throwable

  public void doDestroy();
    Code:
       0: getstatic     #42                 // Field SERVICE_INFORMER:Ljava/util/concurrent/ConcurrentHashMap;
       3: invokedynamic #43,  0             // InvokeDynamic #0:accept:()Ljava/util/function/BiConsumer;
       8: invokevirtual #44                 // Method java/util/concurrent/ConcurrentHashMap.forEach:(Ljava/util/function/BiConsumer;)V
      11: getstatic     #42                 // Field SERVICE_INFORMER:Ljava/util/concurrent/ConcurrentHashMap;
      14: invokevirtual #45                 // Method java/util/concurrent/ConcurrentHashMap.clear:()V
      17: getstatic     #3                  // Field PODS_INFORMER:Ljava/util/concurrent/ConcurrentHashMap;
      20: invokedynamic #46,  0             // InvokeDynamic #1:accept:()Ljava/util/function/BiConsumer;
      25: invokevirtual #44                 // Method java/util/concurrent/ConcurrentHashMap.forEach:(Ljava/util/function/BiConsumer;)V
      28: getstatic     #3                  // Field PODS_INFORMER:Ljava/util/concurrent/ConcurrentHashMap;
      31: invokevirtual #45                 // Method java/util/concurrent/ConcurrentHashMap.clear:()V
      34: getstatic     #47                 // Field ENDPOINTS_INFORMER:Ljava/util/concurrent/ConcurrentHashMap;
      37: invokedynamic #48,  0             // InvokeDynamic #2:accept:()Ljava/util/function/BiConsumer;
      42: invokevirtual #44                 // Method java/util/concurrent/ConcurrentHashMap.forEach:(Ljava/util/function/BiConsumer;)V
      45: getstatic     #47                 // Field ENDPOINTS_INFORMER:Ljava/util/concurrent/ConcurrentHashMap;
      48: invokevirtual #45                 // Method java/util/concurrent/ConcurrentHashMap.clear:()V
      51: aload_0
      52: getfield      #16                 // Field kubernetesClient:Lio/fabric8/kubernetes/client/KubernetesClient;
      55: invokeinterface #49,  1           // InterfaceMethod io/fabric8/kubernetes/client/KubernetesClient.close:()V
      60: return

  public void doRegister(org.apache.dubbo.registry.client.ServiceInstance) throws java.lang.RuntimeException;
    Code:
       0: aload_0
       1: getfield      #25                 // Field enableRegister:Z
       4: ifeq          95
       7: aload_0
       8: getfield      #16                 // Field kubernetesClient:Lio/fabric8/kubernetes/client/KubernetesClient;
      11: invokeinterface #26,  1           // InterfaceMethod io/fabric8/kubernetes/client/KubernetesClient.pods:()Lio/fabric8/kubernetes/client/dsl/MixedOperation;
      16: aload_0
      17: getfield      #21                 // Field namespace:Ljava/lang/String;
      20: invokeinterface #50,  2           // InterfaceMethod io/fabric8/kubernetes/client/dsl/MixedOperation.inNamespace:(Ljava/lang/String;)Ljava/lang/Object;
      25: checkcast     #51                 // class io/fabric8/kubernetes/client/dsl/NonNamespaceOperation
      28: aload_0
      29: getfield      #6                  // Field currentHostname:Ljava/lang/String;
      32: invokeinterface #52,  2           // InterfaceMethod io/fabric8/kubernetes/client/dsl/NonNamespaceOperation.withName:(Ljava/lang/String;)Ljava/lang/Object;
      37: checkcast     #28                 // class io/fabric8/kubernetes/client/dsl/PodResource
      40: aload_1
      41: invokedynamic #53,  0             // InvokeDynamic #3:apply:(Lorg/apache/dubbo/registry/client/ServiceInstance;)Ljava/util/function/UnaryOperator;
      46: invokeinterface #54,  2           // InterfaceMethod io/fabric8/kubernetes/client/dsl/PodResource.edit:(Ljava/util/function/UnaryOperator;)Ljava/lang/Object;
      51: pop
      52: aload_0
      53: getfield      #7                  // Field logger:Lorg/apache/dubbo/common/logger/ErrorTypeAwareLogger;
      56: invokeinterface #55,  1           // InterfaceMethod org/apache/dubbo/common/logger/ErrorTypeAwareLogger.isInfoEnabled:()Z
      61: ifeq          95
      64: aload_0
      65: getfield      #7                  // Field logger:Lorg/apache/dubbo/common/logger/ErrorTypeAwareLogger;
      68: new           #31                 // class java/lang/StringBuilder
      71: dup
      72: invokespecial #32                 // Method java/lang/StringBuilder."<init>":()V
      75: ldc           #56                 // String Write Current Service Instance Metadata to Kubernetes pod. Current pod name:
      77: invokevirtual #34                 // Method java/lang/StringBuilder.append:(Ljava/lang/String;)Ljava/lang/StringBuilder;
      80: aload_0
      81: getfield      #6                  // Field currentHostname:Ljava/lang/String;
      84: invokevirtual #34                 // Method java/lang/StringBuilder.append:(Ljava/lang/String;)Ljava/lang/StringBuilder;
      87: invokevirtual #37                 // Method java/lang/StringBuilder.toString:()Ljava/lang/String;
      90: invokeinterface #57,  2           // InterfaceMethod org/apache/dubbo/common/logger/ErrorTypeAwareLogger.info:(Ljava/lang/String;)V
      95: return

  public void doUpdate(org.apache.dubbo.registry.client.ServiceInstance, org.apache.dubbo.registry.client.ServiceInstance) throws java.lang.RuntimeException;
    Code:
       0: aload_0
       1: aload_2
       2: invokeinterface #58,  1           // InterfaceMethod org/apache/dubbo/registry/client/ServiceInstance.getServiceMetadata:()Lorg/apache/dubbo/metadata/MetadataInfo;
       7: invokevirtual #59                 // Method reportMetadata:(Lorg/apache/dubbo/metadata/MetadataInfo;)V
      10: aload_0
      11: aload_2
      12: invokevirtual #60                 // Method doRegister:(Lorg/apache/dubbo/registry/client/ServiceInstance;)V
      15: return

  public void doUnregister(org.apache.dubbo.registry.client.ServiceInstance) throws java.lang.RuntimeException;
    Code:
       0: aload_0
       1: getfield      #25                 // Field enableRegister:Z
       4: ifeq          94
       7: aload_0
       8: getfield      #16                 // Field kubernetesClient:Lio/fabric8/kubernetes/client/KubernetesClient;
      11: invokeinterface #26,  1           // InterfaceMethod io/fabric8/kubernetes/client/KubernetesClient.pods:()Lio/fabric8/kubernetes/client/dsl/MixedOperation;
      16: aload_0
      17: getfield      #21                 // Field namespace:Ljava/lang/String;
      20: invokeinterface #50,  2           // InterfaceMethod io/fabric8/kubernetes/client/dsl/MixedOperation.inNamespace:(Ljava/lang/String;)Ljava/lang/Object;
      25: checkcast     #51                 // class io/fabric8/kubernetes/client/dsl/NonNamespaceOperation
      28: aload_0
      29: getfield      #6                  // Field currentHostname:Ljava/lang/String;
      32: invokeinterface #52,  2           // InterfaceMethod io/fabric8/kubernetes/client/dsl/NonNamespaceOperation.withName:(Ljava/lang/String;)Ljava/lang/Object;
      37: checkcast     #28                 // class io/fabric8/kubernetes/client/dsl/PodResource
      40: invokedynamic #61,  0             // InvokeDynamic #4:apply:()Ljava/util/function/UnaryOperator;
      45: invokeinterface #54,  2           // InterfaceMethod io/fabric8/kubernetes/client/dsl/PodResource.edit:(Ljava/util/function/UnaryOperator;)Ljava/lang/Object;
      50: pop
      51: aload_0
      52: getfield      #7                  // Field logger:Lorg/apache/dubbo/common/logger/ErrorTypeAwareLogger;
      55: invokeinterface #55,  1           // InterfaceMethod org/apache/dubbo/common/logger/ErrorTypeAwareLogger.isInfoEnabled:()Z
      60: ifeq          94
      63: aload_0
      64: getfield      #7                  // Field logger:Lorg/apache/dubbo/common/logger/ErrorTypeAwareLogger;
      67: new           #31                 // class java/lang/StringBuilder
      70: dup
      71: invokespecial #32                 // Method java/lang/StringBuilder."<init>":()V
      74: ldc           #62                 // String Remove Current Service Instance from Kubernetes pod. Current pod name:
      76: invokevirtual #34                 // Method java/lang/StringBuilder.append:(Ljava/lang/String;)Ljava/lang/StringBuilder;
      79: aload_0
      80: getfield      #6                  // Field currentHostname:Ljava/lang/String;
      83: invokevirtual #34                 // Method java/lang/StringBuilder.append:(Ljava/lang/String;)Ljava/lang/StringBuilder;
      86: invokevirtual #37                 // Method java/lang/StringBuilder.toString:()Ljava/lang/String;
      89: invokeinterface #57,  2           // InterfaceMethod org/apache/dubbo/common/logger/ErrorTypeAwareLogger.info:(Ljava/lang/String;)V
      94: return

  public java.util.Set<java.lang.String> getServices();
    Code:
       0: aload_0
       1: getfield      #16                 // Field kubernetesClient:Lio/fabric8/kubernetes/client/KubernetesClient;
       4: invokeinterface #63,  1           // InterfaceMethod io/fabric8/kubernetes/client/KubernetesClient.services:()Lio/fabric8/kubernetes/client/dsl/MixedOperation;
       9: aload_0
      10: getfield      #21                 // Field namespace:Ljava/lang/String;
      13: invokeinterface #50,  2           // InterfaceMethod io/fabric8/kubernetes/client/dsl/MixedOperation.inNamespace:(Ljava/lang/String;)Ljava/lang/Object;
      18: checkcast     #51                 // class io/fabric8/kubernetes/client/dsl/NonNamespaceOperation
      21: invokeinterface #64,  1           // InterfaceMethod io/fabric8/kubernetes/client/dsl/NonNamespaceOperation.list:()Ljava/lang/Object;
      26: checkcast     #65                 // class io/fabric8/kubernetes/api/model/ServiceList
      29: invokevirtual #66                 // Method io/fabric8/kubernetes/api/model/ServiceList.getItems:()Ljava/util/List;
      32: invokeinterface #67,  1           // InterfaceMethod java/util/List.stream:()Ljava/util/stream/Stream;
      37: invokedynamic #68,  0             // InvokeDynamic #5:apply:()Ljava/util/function/Function;
      42: invokeinterface #69,  2           // InterfaceMethod java/util/stream/Stream.map:(Ljava/util/function/Function;)Ljava/util/stream/Stream;
      47: invokestatic  #70                 // Method java/util/stream/Collectors.toSet:()Ljava/util/stream/Collector;
      50: invokeinterface #71,  2           // InterfaceMethod java/util/stream/Stream.collect:(Ljava/util/stream/Collector;)Ljava/lang/Object;
      55: checkcast     #72                 // class java/util/Set
      58: areturn

  public java.util.List<org.apache.dubbo.registry.client.ServiceInstance> getInstances(java.lang.String) throws java.lang.NullPointerException;
    Code:
       0: aconst_null
       1: astore_2
       2: getstatic     #47                 // Field ENDPOINTS_INFORMER:Ljava/util/concurrent/ConcurrentHashMap;
       5: aload_1
       6: invokevirtual #73                 // Method java/util/concurrent/ConcurrentHashMap.get:(Ljava/lang/Object;)Ljava/lang/Object;
       9: checkcast     #74                 // class io/fabric8/kubernetes/client/informers/SharedIndexInformer
      12: astore_3
      13: aload_3
      14: ifnull        52
      17: aload_3
      18: invokeinterface #75,  1           // InterfaceMethod io/fabric8/kubernetes/client/informers/SharedIndexInformer.getStore:()Lio/fabric8/kubernetes/client/informers/cache/Store;
      23: invokeinterface #76,  1           // InterfaceMethod io/fabric8/kubernetes/client/informers/cache/Store.list:()Ljava/util/List;
      28: astore        4
      30: aload         4
      32: invokeinterface #77,  1           // InterfaceMethod java/util/List.size:()I
      37: ifle          52
      40: aload         4
      42: iconst_0
      43: invokeinterface #78,  2           // InterfaceMethod java/util/List.get:(I)Ljava/lang/Object;
      48: checkcast     #79                 // class io/fabric8/kubernetes/api/model/Endpoints
      51: astore_2
      52: aload_2
      53: ifnonnull     95
      56: aload_0
      57: getfield      #16                 // Field kubernetesClient:Lio/fabric8/kubernetes/client/KubernetesClient;
      60: invokeinterface #80,  1           // InterfaceMethod io/fabric8/kubernetes/client/KubernetesClient.endpoints:()Lio/fabric8/kubernetes/client/dsl/MixedOperation;
      65: aload_0
      66: getfield      #21                 // Field namespace:Ljava/lang/String;
      69: invokeinterface #50,  2           // InterfaceMethod io/fabric8/kubernetes/client/dsl/MixedOperation.inNamespace:(Ljava/lang/String;)Ljava/lang/Object;
      74: checkcast     #51                 // class io/fabric8/kubernetes/client/dsl/NonNamespaceOperation
      77: aload_1
      78: invokeinterface #52,  2           // InterfaceMethod io/fabric8/kubernetes/client/dsl/NonNamespaceOperation.withName:(Ljava/lang/String;)Ljava/lang/Object;
      83: checkcast     #81                 // class io/fabric8/kubernetes/client/dsl/Resource
      86: invokeinterface #82,  1           // InterfaceMethod io/fabric8/kubernetes/client/dsl/Resource.get:()Ljava/lang/Object;
      91: checkcast     #79                 // class io/fabric8/kubernetes/api/model/Endpoints
      94: astore_2
      95: aload_0
      96: aload_2
      97: aload_1
      98: invokespecial #5                  // Method toServiceInstance:(Lio/fabric8/kubernetes/api/model/Endpoints;Ljava/lang/String;)Ljava/util/List;
     101: areturn

  public void addServiceInstancesChangedListener(org.apache.dubbo.registry.client.event.listener.ServiceInstancesChangedListener) throws java.lang.NullPointerException, java.lang.IllegalArgumentException;
    Code:
       0: aload_1
       1: invokevirtual #83                 // Method org/apache/dubbo/registry/client/event/listener/ServiceInstancesChangedListener.getServiceNames:()Ljava/util/Set;
       4: aload_0
       5: aload_1
       6: invokedynamic #84,  0             // InvokeDynamic #6:accept:(Lorg/apache/dubbo/registry/kubernetes/KubernetesServiceDiscovery;Lorg/apache/dubbo/registry/client/event/listener/ServiceInstancesChangedListener;)Ljava/util/function/Consumer;
      11: invokeinterface #85,  2           // InterfaceMethod java/util/Set.forEach:(Ljava/util/function/Consumer;)V
      16: return

  private void watchEndpoints(org.apache.dubbo.registry.client.event.listener.ServiceInstancesChangedListener, java.lang.String);
    Code:
       0: aload_0
       1: getfield      #16                 // Field kubernetesClient:Lio/fabric8/kubernetes/client/KubernetesClient;
       4: invokeinterface #80,  1           // InterfaceMethod io/fabric8/kubernetes/client/KubernetesClient.endpoints:()Lio/fabric8/kubernetes/client/dsl/MixedOperation;
       9: aload_0
      10: getfield      #21                 // Field namespace:Ljava/lang/String;
      13: invokeinterface #50,  2           // InterfaceMethod io/fabric8/kubernetes/client/dsl/MixedOperation.inNamespace:(Ljava/lang/String;)Ljava/lang/Object;
      18: checkcast     #51                 // class io/fabric8/kubernetes/client/dsl/NonNamespaceOperation
      21: aload_2
      22: invokeinterface #52,  2           // InterfaceMethod io/fabric8/kubernetes/client/dsl/NonNamespaceOperation.withName:(Ljava/lang/String;)Ljava/lang/Object;
      27: checkcast     #81                 // class io/fabric8/kubernetes/client/dsl/Resource
      30: new           #86                 // class org/apache/dubbo/registry/kubernetes/KubernetesServiceDiscovery$1
      33: dup
      34: aload_0
      35: aload_2
      36: aload_1
      37: invokespecial #87                 // Method org/apache/dubbo/registry/kubernetes/KubernetesServiceDiscovery$1."<init>":(Lorg/apache/dubbo/registry/kubernetes/KubernetesServiceDiscovery;Ljava/lang/String;Lorg/apache/dubbo/registry/client/event/listener/ServiceInstancesChangedListener;)V
      40: invokeinterface #88,  2           // InterfaceMethod io/fabric8/kubernetes/client/dsl/Resource.inform:(Lio/fabric8/kubernetes/client/informers/ResourceEventHandler;)Lio/fabric8/kubernetes/client/informers/SharedIndexInformer;
      45: astore_3
      46: getstatic     #47                 // Field ENDPOINTS_INFORMER:Ljava/util/concurrent/ConcurrentHashMap;
      49: aload_2
      50: aload_3
      51: invokevirtual #89                 // Method java/util/concurrent/ConcurrentHashMap.put:(Ljava/lang/Object;Ljava/lang/Object;)Ljava/lang/Object;
      54: pop
      55: return

  private void watchPods(org.apache.dubbo.registry.client.event.listener.ServiceInstancesChangedListener, java.lang.String);
    Code:
       0: aload_0
       1: aload_2
       2: invokespecial #90                 // Method getServiceSelector:(Ljava/lang/String;)Ljava/util/Map;
       5: astore_3
       6: aload_3
       7: ifnonnull     11
      10: return
      11: aload_0
      12: getfield      #16                 // Field kubernetesClient:Lio/fabric8/kubernetes/client/KubernetesClient;
      15: invokeinterface #26,  1           // InterfaceMethod io/fabric8/kubernetes/client/KubernetesClient.pods:()Lio/fabric8/kubernetes/client/dsl/MixedOperation;
      20: aload_0
      21: getfield      #21                 // Field namespace:Ljava/lang/String;
      24: invokeinterface #50,  2           // InterfaceMethod io/fabric8/kubernetes/client/dsl/MixedOperation.inNamespace:(Ljava/lang/String;)Ljava/lang/Object;
      29: checkcast     #51                 // class io/fabric8/kubernetes/client/dsl/NonNamespaceOperation
      32: aload_3
      33: invokeinterface #91,  2           // InterfaceMethod io/fabric8/kubernetes/client/dsl/NonNamespaceOperation.withLabels:(Ljava/util/Map;)Ljava/lang/Object;
      38: checkcast     #92                 // class io/fabric8/kubernetes/client/dsl/FilterWatchListDeletable
      41: new           #93                 // class org/apache/dubbo/registry/kubernetes/KubernetesServiceDiscovery$2
      44: dup
      45: aload_0
      46: aload_2
      47: aload_1
      48: invokespecial #94                 // Method org/apache/dubbo/registry/kubernetes/KubernetesServiceDiscovery$2."<init>":(Lorg/apache/dubbo/registry/kubernetes/KubernetesServiceDiscovery;Ljava/lang/String;Lorg/apache/dubbo/registry/client/event/listener/ServiceInstancesChangedListener;)V
      51: invokeinterface #95,  2           // InterfaceMethod io/fabric8/kubernetes/client/dsl/FilterWatchListDeletable.inform:(Lio/fabric8/kubernetes/client/informers/ResourceEventHandler;)Lio/fabric8/kubernetes/client/informers/SharedIndexInformer;
      56: astore        4
      58: getstatic     #3                  // Field PODS_INFORMER:Ljava/util/concurrent/ConcurrentHashMap;
      61: aload_2
      62: aload         4
      64: invokevirtual #89                 // Method java/util/concurrent/ConcurrentHashMap.put:(Ljava/lang/Object;Ljava/lang/Object;)Ljava/lang/Object;
      67: pop
      68: return

  private void watchService(org.apache.dubbo.registry.client.event.listener.ServiceInstancesChangedListener, java.lang.String);
    Code:
       0: aload_0
       1: getfield      #16                 // Field kubernetesClient:Lio/fabric8/kubernetes/client/KubernetesClient;
       4: invokeinterface #63,  1           // InterfaceMethod io/fabric8/kubernetes/client/KubernetesClient.services:()Lio/fabric8/kubernetes/client/dsl/MixedOperation;
       9: aload_0
      10: getfield      #21                 // Field namespace:Ljava/lang/String;
      13: invokeinterface #50,  2           // InterfaceMethod io/fabric8/kubernetes/client/dsl/MixedOperation.inNamespace:(Ljava/lang/String;)Ljava/lang/Object;
      18: checkcast     #51                 // class io/fabric8/kubernetes/client/dsl/NonNamespaceOperation
      21: aload_2
      22: invokeinterface #52,  2           // InterfaceMethod io/fabric8/kubernetes/client/dsl/NonNamespaceOperation.withName:(Ljava/lang/String;)Ljava/lang/Object;
      27: checkcast     #96                 // class io/fabric8/kubernetes/client/dsl/ServiceResource
      30: new           #97                 // class org/apache/dubbo/registry/kubernetes/KubernetesServiceDiscovery$3
      33: dup
      34: aload_0
      35: aload_2
      36: aload_1
      37: invokespecial #98                 // Method org/apache/dubbo/registry/kubernetes/KubernetesServiceDiscovery$3."<init>":(Lorg/apache/dubbo/registry/kubernetes/KubernetesServiceDiscovery;Ljava/lang/String;Lorg/apache/dubbo/registry/client/event/listener/ServiceInstancesChangedListener;)V
      40: invokeinterface #99,  2           // InterfaceMethod io/fabric8/kubernetes/client/dsl/ServiceResource.inform:(Lio/fabric8/kubernetes/client/informers/ResourceEventHandler;)Lio/fabric8/kubernetes/client/informers/SharedIndexInformer;
      45: astore_3
      46: getstatic     #42                 // Field SERVICE_INFORMER:Ljava/util/concurrent/ConcurrentHashMap;
      49: aload_2
      50: aload_3
      51: invokevirtual #89                 // Method java/util/concurrent/ConcurrentHashMap.put:(Ljava/lang/Object;Ljava/lang/Object;)Ljava/lang/Object;
      54: pop
      55: return

  private void notifyServiceChanged(java.lang.String, org.apache.dubbo.registry.client.event.listener.ServiceInstancesChangedListener, java.util.List<org.apache.dubbo.registry.client.ServiceInstance>);
    Code:
       0: invokestatic  #100                // Method java/lang/System.nanoTime:()J
       3: lstore        4
       5: new           #101                // class org/apache/dubbo/registry/client/event/ServiceInstancesChangedEvent
       8: dup
       9: aload_1
      10: aload_3
      11: invokespecial #102                // Method org/apache/dubbo/registry/client/event/ServiceInstancesChangedEvent."<init>":(Ljava/lang/String;Ljava/util/List;)V
      14: astore        6
      16: getstatic     #103                // Field SERVICE_UPDATE_TIME:Ljava/util/concurrent/ConcurrentHashMap;
      19: aload_1
      20: invokevirtual #73                 // Method java/util/concurrent/ConcurrentHashMap.get:(Ljava/lang/Object;)Ljava/lang/Object;
      23: checkcast     #104                // class java/util/concurrent/atomic/AtomicLong
      26: astore        7
      28: aload         7
      30: invokevirtual #105                // Method java/util/concurrent/atomic/AtomicLong.get:()J
      33: lstore        8
      35: lload         8
      37: lload         4
      39: lcmp
      40: ifgt          62
      43: aload         7
      45: lload         8
      47: lload         4
      49: invokevirtual #106                // Method java/util/concurrent/atomic/AtomicLong.compareAndSet:(JJ)Z
      52: ifeq          62
      55: aload_2
      56: aload         6
      58: invokevirtual #107                // Method org/apache/dubbo/registry/client/event/listener/ServiceInstancesChangedListener.onEvent:(Lorg/apache/dubbo/registry/client/event/ServiceInstancesChangedEvent;)V
      61: return
      62: aload_0
      63: getfield      #7                  // Field logger:Lorg/apache/dubbo/common/logger/ErrorTypeAwareLogger;
      66: invokeinterface #55,  1           // InterfaceMethod org/apache/dubbo/common/logger/ErrorTypeAwareLogger.isInfoEnabled:()Z
      71: ifeq          118
      74: aload_0
      75: getfield      #7                  // Field logger:Lorg/apache/dubbo/common/logger/ErrorTypeAwareLogger;
      78: new           #31                 // class java/lang/StringBuilder
      81: dup
      82: invokespecial #32                 // Method java/lang/StringBuilder."<init>":()V
      85: ldc           #108                // String Discard Service Instance Data. Possible Cause: Newer message has been processed or Failed to update time record by CAS. Current Data received time:
      87: invokevirtual #34                 // Method java/lang/StringBuilder.append:(Ljava/lang/String;)Ljava/lang/StringBuilder;
      90: lload         4
      92: invokevirtual #109                // Method java/lang/StringBuilder.append:(J)Ljava/lang/StringBuilder;
      95: ldc           #110                // String . Newer Data received time:
      97: invokevirtual #34                 // Method java/lang/StringBuilder.append:(Ljava/lang/String;)Ljava/lang/StringBuilder;
     100: lload         8
     102: invokevirtual #109                // Method java/lang/StringBuilder.append:(J)Ljava/lang/StringBuilder;
     105: ldc           #111                // String .
     107: invokevirtual #34                 // Method java/lang/StringBuilder.append:(Ljava/lang/String;)Ljava/lang/StringBuilder;
     110: invokevirtual #37                 // Method java/lang/StringBuilder.toString:()Ljava/lang/String;
     113: invokeinterface #57,  2           // InterfaceMethod org/apache/dubbo/common/logger/ErrorTypeAwareLogger.info:(Ljava/lang/String;)V
     118: return

  public org.apache.dubbo.common.URL getUrl();
    Code:
       0: aload_0
       1: getfield      #19                 // Field registryURL:Lorg/apache/dubbo/common/URL;
       4: areturn

  private java.util.Map<java.lang.String, java.lang.String> getServiceSelector(java.lang.String);
    Code:
       0: aload_0
       1: getfield      #16                 // Field kubernetesClient:Lio/fabric8/kubernetes/client/KubernetesClient;
       4: invokeinterface #63,  1           // InterfaceMethod io/fabric8/kubernetes/client/KubernetesClient.services:()Lio/fabric8/kubernetes/client/dsl/MixedOperation;
       9: aload_0
      10: getfield      #21                 // Field namespace:Ljava/lang/String;
      13: invokeinterface #50,  2           // InterfaceMethod io/fabric8/kubernetes/client/dsl/MixedOperation.inNamespace:(Ljava/lang/String;)Ljava/lang/Object;
      18: checkcast     #51                 // class io/fabric8/kubernetes/client/dsl/NonNamespaceOperation
      21: aload_1
      22: invokeinterface #52,  2           // InterfaceMethod io/fabric8/kubernetes/client/dsl/NonNamespaceOperation.withName:(Ljava/lang/String;)Ljava/lang/Object;
      27: checkcast     #96                 // class io/fabric8/kubernetes/client/dsl/ServiceResource
      30: invokeinterface #112,  1          // InterfaceMethod io/fabric8/kubernetes/client/dsl/ServiceResource.get:()Ljava/lang/Object;
      35: checkcast     #113                // class io/fabric8/kubernetes/api/model/Service
      38: astore_2
      39: aload_2
      40: ifnonnull     45
      43: aconst_null
      44: areturn
      45: aload_2
      46: invokevirtual #114                // Method io/fabric8/kubernetes/api/model/Service.getSpec:()Lio/fabric8/kubernetes/api/model/ServiceSpec;
      49: invokevirtual #115                // Method io/fabric8/kubernetes/api/model/ServiceSpec.getSelector:()Ljava/util/Map;
      52: areturn

  private java.util.List<org.apache.dubbo.registry.client.ServiceInstance> toServiceInstance(io.fabric8.kubernetes.api.model.Endpoints, java.lang.String);
    Code:
       0: aload_0
       1: aload_2
       2: invokespecial #90                 // Method getServiceSelector:(Ljava/lang/String;)Ljava/util/Map;
       5: astore_3
       6: aload_3
       7: ifnonnull     18
      10: new           #116                // class java/util/LinkedList
      13: dup
      14: invokespecial #117                // Method java/util/LinkedList."<init>":()V
      17: areturn
      18: aload_0
      19: getfield      #16                 // Field kubernetesClient:Lio/fabric8/kubernetes/client/KubernetesClient;
      22: invokeinterface #26,  1           // InterfaceMethod io/fabric8/kubernetes/client/KubernetesClient.pods:()Lio/fabric8/kubernetes/client/dsl/MixedOperation;
      27: aload_0
      28: getfield      #21                 // Field namespace:Ljava/lang/String;
      31: invokeinterface #50,  2           // InterfaceMethod io/fabric8/kubernetes/client/dsl/MixedOperation.inNamespace:(Ljava/lang/String;)Ljava/lang/Object;
      36: checkcast     #51                 // class io/fabric8/kubernetes/client/dsl/NonNamespaceOperation
      39: aload_3
      40: invokeinterface #91,  2           // InterfaceMethod io/fabric8/kubernetes/client/dsl/NonNamespaceOperation.withLabels:(Ljava/util/Map;)Ljava/lang/Object;
      45: checkcast     #92                 // class io/fabric8/kubernetes/client/dsl/FilterWatchListDeletable
      48: invokeinterface #118,  1          // InterfaceMethod io/fabric8/kubernetes/client/dsl/FilterWatchListDeletable.list:()Ljava/lang/Object;
      53: checkcast     #119                // class io/fabric8/kubernetes/api/model/PodList
      56: invokevirtual #120                // Method io/fabric8/kubernetes/api/model/PodList.getItems:()Ljava/util/List;
      59: invokeinterface #67,  1           // InterfaceMethod java/util/List.stream:()Ljava/util/stream/Stream;
      64: invokedynamic #121,  0            // InvokeDynamic #7:apply:()Ljava/util/function/Function;
      69: invokedynamic #122,  0            // InvokeDynamic #8:apply:()Ljava/util/function/Function;
      74: invokestatic  #123                // Method java/util/stream/Collectors.toMap:(Ljava/util/function/Function;Ljava/util/function/Function;)Ljava/util/stream/Collector;
      77: invokeinterface #71,  2           // InterfaceMethod java/util/stream/Stream.collect:(Ljava/util/stream/Collector;)Ljava/lang/Object;
      82: checkcast     #124                // class java/util/Map
      85: astore        4
      87: new           #116                // class java/util/LinkedList
      90: dup
      91: invokespecial #117                // Method java/util/LinkedList."<init>":()V
      94: astore        5
      96: new           #125                // class java/util/HashSet
      99: dup
     100: invokespecial #126                // Method java/util/HashSet."<init>":()V
     103: astore        6
     105: aload_1
     106: invokevirtual #127                // Method io/fabric8/kubernetes/api/model/Endpoints.getSubsets:()Ljava/util/List;
     109: invokeinterface #128,  1          // InterfaceMethod java/util/List.iterator:()Ljava/util/Iterator;
     114: astore        7
     116: aload         7
     118: invokeinterface #129,  1          // InterfaceMethod java/util/Iterator.hasNext:()Z
     123: ifeq          180
     126: aload         7
     128: invokeinterface #130,  1          // InterfaceMethod java/util/Iterator.next:()Ljava/lang/Object;
     133: checkcast     #131                // class io/fabric8/kubernetes/api/model/EndpointSubset
     136: astore        8
     138: aload         6
     140: aload         8
     142: invokevirtual #132                // Method io/fabric8/kubernetes/api/model/EndpointSubset.getPorts:()Ljava/util/List;
     145: invokeinterface #67,  1           // InterfaceMethod java/util/List.stream:()Ljava/util/stream/Stream;
     150: invokedynamic #133,  0            // InvokeDynamic #9:apply:()Ljava/util/function/Function;
     155: invokeinterface #69,  2           // InterfaceMethod java/util/stream/Stream.map:(Ljava/util/function/Function;)Ljava/util/stream/Stream;
     160: invokestatic  #70                 // Method java/util/stream/Collectors.toSet:()Ljava/util/stream/Collector;
     163: invokeinterface #71,  2           // InterfaceMethod java/util/stream/Stream.collect:(Ljava/util/stream/Collector;)Ljava/lang/Object;
     168: checkcast     #134                // class java/util/Collection
     171: invokeinterface #135,  2          // InterfaceMethod java/util/Set.addAll:(Ljava/util/Collection;)Z
     176: pop
     177: goto          116
     180: aload_1
     181: invokevirtual #127                // Method io/fabric8/kubernetes/api/model/Endpoints.getSubsets:()Ljava/util/List;
     184: invokeinterface #128,  1          // InterfaceMethod java/util/List.iterator:()Ljava/util/Iterator;
     189: astore        7
     191: aload         7
     193: invokeinterface #129,  1          // InterfaceMethod java/util/Iterator.hasNext:()Z
     198: ifeq          351
     201: aload         7
     203: invokeinterface #130,  1          // InterfaceMethod java/util/Iterator.next:()Ljava/lang/Object;
     208: checkcast     #131                // class io/fabric8/kubernetes/api/model/EndpointSubset
     211: astore        8
     213: aload         8
     215: invokevirtual #136                // Method io/fabric8/kubernetes/api/model/EndpointSubset.getAddresses:()Ljava/util/List;
     218: invokeinterface #128,  1          // InterfaceMethod java/util/List.iterator:()Ljava/util/Iterator;
     223: astore        9
     225: aload         9
     227: invokeinterface #129,  1          // InterfaceMethod java/util/Iterator.hasNext:()Z
     232: ifeq          348
     235: aload         9
     237: invokeinterface #130,  1          // InterfaceMethod java/util/Iterator.next:()Ljava/lang/Object;
     242: checkcast     #137                // class io/fabric8/kubernetes/api/model/EndpointAddress
     245: astore        10
     247: aload         4
     249: aload         10
     251: invokevirtual #138                // Method io/fabric8/kubernetes/api/model/EndpointAddress.getTargetRef:()Lio/fabric8/kubernetes/api/model/ObjectReference;
     254: invokevirtual #139                // Method io/fabric8/kubernetes/api/model/ObjectReference.getName:()Ljava/lang/String;
     257: invokeinterface #140,  2          // InterfaceMethod java/util/Map.get:(Ljava/lang/Object;)Ljava/lang/Object;
     262: checkcast     #141                // class io/fabric8/kubernetes/api/model/Pod
     265: astore        11
     267: aload         10
     269: invokevirtual #142                // Method io/fabric8/kubernetes/api/model/EndpointAddress.getIp:()Ljava/lang/String;
     272: astore        12
     274: aload         11
     276: ifnonnull     323
     279: aload_0
     280: getfield      #7                  // Field logger:Lorg/apache/dubbo/common/logger/ErrorTypeAwareLogger;
     283: ldc           #143                // String 1-20
     285: ldc           #39                 // String
     287: ldc           #39                 // String
     289: new           #31                 // class java/lang/StringBuilder
     292: dup
     293: invokespecial #32                 // Method java/lang/StringBuilder."<init>":()V
     296: ldc           #144                // String Unable to match Kubernetes Endpoint address with Pod. EndpointAddress Hostname:
     298: invokevirtual #34                 // Method java/lang/StringBuilder.append:(Ljava/lang/String;)Ljava/lang/StringBuilder;
     301: aload         10
     303: invokevirtual #138                // Method io/fabric8/kubernetes/api/model/EndpointAddress.getTargetRef:()Lio/fabric8/kubernetes/api/model/ObjectReference;
     306: invokevirtual #139                // Method io/fabric8/kubernetes/api/model/ObjectReference.getName:()Ljava/lang/String;
     309: invokevirtual #34                 // Method java/lang/StringBuilder.append:(Ljava/lang/String;)Ljava/lang/StringBuilder;
     312: invokevirtual #37                 // Method java/lang/StringBuilder.toString:()Ljava/lang/String;
     315: invokeinterface #145,  5          // InterfaceMethod org/apache/dubbo/common/logger/ErrorTypeAwareLogger.warn:(Ljava/lang/String;Ljava/lang/String;Ljava/lang/String;Ljava/lang/String;)V
     320: goto          225
     323: aload         6
     325: aload_0
     326: aload_2
     327: aload         12
     329: aload         11
     331: aload         5
     333: aload         10
     335: invokedynamic #146,  0            // InvokeDynamic #10:accept:(Lorg/apache/dubbo/registry/kubernetes/KubernetesServiceDiscovery;Ljava/lang/String;Ljava/lang/String;Lio/fabric8/kubernetes/api/model/Pod;Ljava/util/List;Lio/fabric8/kubernetes/api/model/EndpointAddress;)Ljava/util/function/Consumer;
     340: invokeinterface #85,  2           // InterfaceMethod java/util/Set.forEach:(Ljava/util/function/Consumer;)V
     345: goto          225
     348: goto          191
     351: aload         5
     353: areturn

  public void setCurrentHostname(java.lang.String);
    Code:
       0: aload_0
       1: aload_1
       2: putfield      #6                  // Field currentHostname:Ljava/lang/String;
       5: return

  public void setKubernetesClient(io.fabric8.kubernetes.client.KubernetesClient);
    Code:
       0: aload_0
       1: aload_1
       2: putfield      #16                 // Field kubernetesClient:Lio/fabric8/kubernetes/client/KubernetesClient;
       5: return

  private void lambda$toServiceInstance$9(java.lang.String, java.lang.String, io.fabric8.kubernetes.api.model.Pod, java.util.List, io.fabric8.kubernetes.api.model.EndpointAddress, java.lang.Integer);
    Code:
       0: new           #147                // class org/apache/dubbo/registry/client/DefaultServiceInstance
       3: dup
       4: aload_1
       5: aload_2
       6: aload         6
       8: aload_0
       9: invokevirtual #148                // Method getUrl:()Lorg/apache/dubbo/common/URL;
      12: invokevirtual #149                // Method org/apache/dubbo/common/URL.getScopeModel:()Lorg/apache/dubbo/rpc/model/ScopeModel;
      15: invokestatic  #150                // Method org/apache/dubbo/rpc/model/ScopeModelUtil.getApplicationModel:(Lorg/apache/dubbo/rpc/model/ScopeModel;)Lorg/apache/dubbo/rpc/model/ApplicationModel;
      18: invokespecial #151                // Method org/apache/dubbo/registry/client/DefaultServiceInstance."<init>":(Ljava/lang/String;Ljava/lang/String;Ljava/lang/Integer;Lorg/apache/dubbo/rpc/model/ApplicationModel;)V
      21: astore        7
      23: aload_3
      24: invokevirtual #152                // Method io/fabric8/kubernetes/api/model/Pod.getMetadata:()Lio/fabric8/kubernetes/api/model/ObjectMeta;
      27: invokevirtual #153                // Method io/fabric8/kubernetes/api/model/ObjectMeta.getAnnotations:()Ljava/util/Map;
      30: ldc           #155                // String io.dubbo/metadata
      32: invokeinterface #140,  2          // InterfaceMethod java/util/Map.get:(Ljava/lang/Object;)Ljava/lang/Object;
      37: checkcast     #156                // class java/lang/String
      40: astore        8
      42: aload         8
      44: invokestatic  #157                // Method org/apache/dubbo/common/utils/StringUtils.isNotEmpty:(Ljava/lang/String;)Z
      47: ifeq          85
      50: aload         7
      52: invokeinterface #158,  1          // InterfaceMethod org/apache/dubbo/registry/client/ServiceInstance.getMetadata:()Ljava/util/Map;
      57: aload         8
      59: ldc           #124                // class java/util/Map
      61: invokestatic  #159                // Method org/apache/dubbo/common/utils/JsonUtils.toJavaObject:(Ljava/lang/String;Ljava/lang/reflect/Type;)Ljava/lang/Object;
      64: checkcast     #124                // class java/util/Map
      67: invokeinterface #160,  2          // InterfaceMethod java/util/Map.putAll:(Ljava/util/Map;)V
      72: aload         4
      74: aload         7
      76: invokeinterface #161,  2          // InterfaceMethod java/util/List.add:(Ljava/lang/Object;)Z
      81: pop
      82: goto          126
      85: aload_0
      86: getfield      #7                  // Field logger:Lorg/apache/dubbo/common/logger/ErrorTypeAwareLogger;
      89: ldc           #162                // String 1-21
      91: ldc           #39                 // String
      93: ldc           #39                 // String
      95: new           #31                 // class java/lang/StringBuilder
      98: dup
      99: invokespecial #32                 // Method java/lang/StringBuilder."<init>":()V
     102: ldc           #163                // String Unable to find Service Instance metadata in Pod Annotations. Possibly cause: provider has not been initialized successfully. EndpointAddress Hostname:
     104: invokevirtual #34                 // Method java/lang/StringBuilder.append:(Ljava/lang/String;)Ljava/lang/StringBuilder;
     107: aload         5
     109: invokevirtual #138                // Method io/fabric8/kubernetes/api/model/EndpointAddress.getTargetRef:()Lio/fabric8/kubernetes/api/model/ObjectReference;
     112: invokevirtual #139                // Method io/fabric8/kubernetes/api/model/ObjectReference.getName:()Ljava/lang/String;
     115: invokevirtual #34                 // Method java/lang/StringBuilder.append:(Ljava/lang/String;)Ljava/lang/StringBuilder;
     118: invokevirtual #37                 // Method java/lang/StringBuilder.toString:()Ljava/lang/String;
     121: invokeinterface #145,  5          // InterfaceMethod org/apache/dubbo/common/logger/ErrorTypeAwareLogger.warn:(Ljava/lang/String;Ljava/lang/String;Ljava/lang/String;Ljava/lang/String;)V
     126: return

  private static io.fabric8.kubernetes.api.model.Pod lambda$toServiceInstance$8(io.fabric8.kubernetes.api.model.Pod);
    Code:
       0: aload_0
       1: areturn

  private static java.lang.String lambda$toServiceInstance$7(io.fabric8.kubernetes.api.model.Pod);
    Code:
       0: aload_0
       1: invokevirtual #152                // Method io/fabric8/kubernetes/api/model/Pod.getMetadata:()Lio/fabric8/kubernetes/api/model/ObjectMeta;
       4: invokevirtual #164                // Method io/fabric8/kubernetes/api/model/ObjectMeta.getName:()Ljava/lang/String;
       7: areturn

  private void lambda$addServiceInstancesChangedListener$6(org.apache.dubbo.registry.client.event.listener.ServiceInstancesChangedListener, java.lang.String);
    Code:
       0: getstatic     #103                // Field SERVICE_UPDATE_TIME:Ljava/util/concurrent/ConcurrentHashMap;
       3: aload_2
       4: new           #104                // class java/util/concurrent/atomic/AtomicLong
       7: dup
       8: lconst_0
       9: invokespecial #165                // Method java/util/concurrent/atomic/AtomicLong."<init>":(J)V
      12: invokevirtual #89                 // Method java/util/concurrent/ConcurrentHashMap.put:(Ljava/lang/Object;Ljava/lang/Object;)Ljava/lang/Object;
      15: pop
      16: aload_0
      17: aload_1
      18: aload_2
      19: invokespecial #166                // Method watchEndpoints:(Lorg/apache/dubbo/registry/client/event/listener/ServiceInstancesChangedListener;Ljava/lang/String;)V
      22: aload_0
      23: aload_1
      24: aload_2
      25: invokespecial #2                  // Method watchPods:(Lorg/apache/dubbo/registry/client/event/listener/ServiceInstancesChangedListener;Ljava/lang/String;)V
      28: aload_0
      29: aload_1
      30: aload_2
      31: invokespecial #167                // Method watchService:(Lorg/apache/dubbo/registry/client/event/listener/ServiceInstancesChangedListener;Ljava/lang/String;)V
      34: return

  private static java.lang.String lambda$getServices$5(io.fabric8.kubernetes.api.model.Service);
    Code:
       0: aload_0
       1: invokevirtual #168                // Method io/fabric8/kubernetes/api/model/Service.getMetadata:()Lio/fabric8/kubernetes/api/model/ObjectMeta;
       4: invokevirtual #164                // Method io/fabric8/kubernetes/api/model/ObjectMeta.getName:()Ljava/lang/String;
       7: areturn

  private static io.fabric8.kubernetes.api.model.Pod lambda$doUnregister$4(io.fabric8.kubernetes.api.model.Pod);
    Code:
       0: new           #169                // class io/fabric8/kubernetes/api/model/PodBuilder
       3: dup
       4: aload_0
       5: invokespecial #170                // Method io/fabric8/kubernetes/api/model/PodBuilder."<init>":(Lio/fabric8/kubernetes/api/model/Pod;)V
       8: invokevirtual #171                // Method io/fabric8/kubernetes/api/model/PodBuilder.editOrNewMetadata:()Lio/fabric8/kubernetes/api/model/PodFluent$MetadataNested;
      11: ldc           #155                // String io.dubbo/metadata
      13: invokeinterface #172,  2          // InterfaceMethod io/fabric8/kubernetes/api/model/PodFluent$MetadataNested.removeFromAnnotations:(Ljava/lang/String;)Lio/fabric8/kubernetes/api/model/ObjectMetaFluent;
      18: checkcast     #173                // class io/fabric8/kubernetes/api/model/PodFluent$MetadataNested
      21: invokeinterface #174,  1          // InterfaceMethod io/fabric8/kubernetes/api/model/PodFluent$MetadataNested.endMetadata:()Ljava/lang/Object;
      26: checkcast     #169                // class io/fabric8/kubernetes/api/model/PodBuilder
      29: invokevirtual #175                // Method io/fabric8/kubernetes/api/model/PodBuilder.build:()Lio/fabric8/kubernetes/api/model/Pod;
      32: areturn

  private static io.fabric8.kubernetes.api.model.Pod lambda$doRegister$3(org.apache.dubbo.registry.client.ServiceInstance, io.fabric8.kubernetes.api.model.Pod);
    Code:
       0: new           #169                // class io/fabric8/kubernetes/api/model/PodBuilder
       3: dup
       4: aload_1
       5: invokespecial #170                // Method io/fabric8/kubernetes/api/model/PodBuilder."<init>":(Lio/fabric8/kubernetes/api/model/Pod;)V
       8: invokevirtual #171                // Method io/fabric8/kubernetes/api/model/PodBuilder.editOrNewMetadata:()Lio/fabric8/kubernetes/api/model/PodFluent$MetadataNested;
      11: ldc           #155                // String io.dubbo/metadata
      13: aload_0
      14: invokeinterface #158,  1          // InterfaceMethod org/apache/dubbo/registry/client/ServiceInstance.getMetadata:()Ljava/util/Map;
      19: invokestatic  #176                // Method org/apache/dubbo/common/utils/JsonUtils.toJson:(Ljava/lang/Object;)Ljava/lang/String;
      22: invokeinterface #177,  3          // InterfaceMethod io/fabric8/kubernetes/api/model/PodFluent$MetadataNested.addToAnnotations:(Ljava/lang/String;Ljava/lang/String;)Lio/fabric8/kubernetes/api/model/ObjectMetaFluent;
      27: checkcast     #173                // class io/fabric8/kubernetes/api/model/PodFluent$MetadataNested
      30: invokeinterface #174,  1          // InterfaceMethod io/fabric8/kubernetes/api/model/PodFluent$MetadataNested.endMetadata:()Ljava/lang/Object;
      35: checkcast     #169                // class io/fabric8/kubernetes/api/model/PodBuilder
      38: invokevirtual #175                // Method io/fabric8/kubernetes/api/model/PodBuilder.build:()Lio/fabric8/kubernetes/api/model/Pod;
      41: areturn

  private static void lambda$doDestroy$2(java.lang.String, io.fabric8.kubernetes.client.informers.SharedIndexInformer);
    Code:
       0: aload_1
       1: invokeinterface #178,  1          // InterfaceMethod io/fabric8/kubernetes/client/informers/SharedIndexInformer.close:()V
       6: return

  private static void lambda$doDestroy$1(java.lang.String, io.fabric8.kubernetes.client.informers.SharedIndexInformer);
    Code:
       0: aload_1
       1: invokeinterface #178,  1          // InterfaceMethod io/fabric8/kubernetes/client/informers/SharedIndexInformer.close:()V
       6: return

  private static void lambda$doDestroy$0(java.lang.String, io.fabric8.kubernetes.client.informers.SharedIndexInformer);
    Code:
       0: aload_1
       1: invokeinterface #178,  1          // InterfaceMethod io/fabric8/kubernetes/client/informers/SharedIndexInformer.close:()V
       6: return

  static org.apache.dubbo.common.logger.ErrorTypeAwareLogger access$000(org.apache.dubbo.registry.kubernetes.KubernetesServiceDiscovery);
    Code:
       0: aload_0
       1: getfield      #7                  // Field logger:Lorg/apache/dubbo/common/logger/ErrorTypeAwareLogger;
       4: areturn

  static java.lang.String access$100(org.apache.dubbo.registry.kubernetes.KubernetesServiceDiscovery);
    Code:
       0: aload_0
       1: getfield      #6                  // Field currentHostname:Ljava/lang/String;
       4: areturn

  static java.util.List access$200(org.apache.dubbo.registry.kubernetes.KubernetesServiceDiscovery, io.fabric8.kubernetes.api.model.Endpoints, java.lang.String);
    Code:
       0: aload_0
       1: aload_1
       2: aload_2
       3: invokespecial #5                  // Method toServiceInstance:(Lio/fabric8/kubernetes/api/model/Endpoints;Ljava/lang/String;)Ljava/util/List;
       6: areturn

  static void access$300(org.apache.dubbo.registry.kubernetes.KubernetesServiceDiscovery, java.lang.String, org.apache.dubbo.registry.client.event.listener.ServiceInstancesChangedListener, java.util.List);
    Code:
       0: aload_0
       1: aload_1
       2: aload_2
       3: aload_3
       4: invokespecial #4                  // Method notifyServiceChanged:(Ljava/lang/String;Lorg/apache/dubbo/registry/client/event/listener/ServiceInstancesChangedListener;Ljava/util/List;)V
       7: return

  static java.util.concurrent.ConcurrentHashMap access$400();
    Code:
       0: getstatic     #3                  // Field PODS_INFORMER:Ljava/util/concurrent/ConcurrentHashMap;
       3: areturn

  static void access$500(org.apache.dubbo.registry.kubernetes.KubernetesServiceDiscovery, org.apache.dubbo.registry.client.event.listener.ServiceInstancesChangedListener, java.lang.String);
    Code:
       0: aload_0
       1: aload_1
       2: aload_2
       3: invokespecial #2                  // Method watchPods:(Lorg/apache/dubbo/registry/client/event/listener/ServiceInstancesChangedListener;Ljava/lang/String;)V
       6: return

  static {};
    Code:
       0: new           #179                // class java/util/concurrent/ConcurrentHashMap
       3: dup
       4: bipush        64
       6: invokespecial #180                // Method java/util/concurrent/ConcurrentHashMap."<init>":(I)V
       9: putstatic     #103                // Field SERVICE_UPDATE_TIME:Ljava/util/concurrent/ConcurrentHashMap;
      12: new           #179                // class java/util/concurrent/ConcurrentHashMap
      15: dup
      16: bipush        64
      18: invokespecial #180                // Method java/util/concurrent/ConcurrentHashMap."<init>":(I)V
      21: putstatic     #42                 // Field SERVICE_INFORMER:Ljava/util/concurrent/ConcurrentHashMap;
      24: new           #179                // class java/util/concurrent/ConcurrentHashMap
      27: dup
      28: bipush        64
      30: invokespecial #180                // Method java/util/concurrent/ConcurrentHashMap."<init>":(I)V
      33: putstatic     #3                  // Field PODS_INFORMER:Ljava/util/concurrent/ConcurrentHashMap;
      36: new           #179                // class java/util/concurrent/ConcurrentHashMap
      39: dup
      40: bipush        64
      42: invokespecial #180                // Method java/util/concurrent/ConcurrentHashMap."<init>":(I)V
      45: putstatic     #47                 // Field ENDPOINTS_INFORMER:Ljava/util/concurrent/ConcurrentHashMap;
      48: return
}
