Compiled from "MeshConstant.java"
public class org.apache.dubbo.registry.kubernetes.MeshConstant {
  public org.apache.dubbo.registry.kubernetes.MeshConstant();
    Code:
       0: aload_0
       1: invokespecial #1                  // Method java/lang/Object."<init>":()V
       4: return

  public static io.fabric8.kubernetes.client.dsl.base.CustomResourceDefinitionContext getVsDefinition();
    Code:
       0: new           #2                  // class io/fabric8/kubernetes/client/dsl/base/CustomResourceDefinitionContext$Builder
       3: dup
       4: invokespecial #3                  // Method io/fabric8/kubernetes/client/dsl/base/CustomResourceDefinitionContext$Builder."<init>":()V
       7: ldc           #4                  // String service.dubbo.apache.org
       9: invokevirtual #5                  // Method io/fabric8/kubernetes/client/dsl/base/CustomResourceDefinitionContext$Builder.withGroup:(Ljava/lang/String;)Lio/fabric8/kubernetes/client/dsl/base/CustomResourceDefinitionContext$Builder;
      12: ldc           #6                  // String v1alpha1
      14: invokevirtual #7                  // Method io/fabric8/kubernetes/client/dsl/base/CustomResourceDefinitionContext$Builder.withVersion:(Ljava/lang/String;)Lio/fabric8/kubernetes/client/dsl/base/CustomResourceDefinitionContext$Builder;
      17: ldc           #8                  // String Namespaced
      19: invokevirtual #9                  // Method io/fabric8/kubernetes/client/dsl/base/CustomResourceDefinitionContext$Builder.withScope:(Ljava/lang/String;)Lio/fabric8/kubernetes/client/dsl/base/CustomResourceDefinitionContext$Builder;
      22: ldc           #10                 // String virtualservices.service.dubbo.apache.org
      24: invokevirtual #11                 // Method io/fabric8/kubernetes/client/dsl/base/CustomResourceDefinitionContext$Builder.withName:(Ljava/lang/String;)Lio/fabric8/kubernetes/client/dsl/base/CustomResourceDefinitionContext$Builder;
      27: ldc           #12                 // String virtualservices
      29: invokevirtual #13                 // Method io/fabric8/kubernetes/client/dsl/base/CustomResourceDefinitionContext$Builder.withPlural:(Ljava/lang/String;)Lio/fabric8/kubernetes/client/dsl/base/CustomResourceDefinitionContext$Builder;
      32: ldc           #14                 // String VirtualService
      34: invokevirtual #15                 // Method io/fabric8/kubernetes/client/dsl/base/CustomResourceDefinitionContext$Builder.withKind:(Ljava/lang/String;)Lio/fabric8/kubernetes/client/dsl/base/CustomResourceDefinitionContext$Builder;
      37: invokevirtual #16                 // Method io/fabric8/kubernetes/client/dsl/base/CustomResourceDefinitionContext$Builder.build:()Lio/fabric8/kubernetes/client/dsl/base/CustomResourceDefinitionContext;
      40: areturn

  public static io.fabric8.kubernetes.client.dsl.base.CustomResourceDefinitionContext getDrDefinition();
    Code:
       0: new           #2                  // class io/fabric8/kubernetes/client/dsl/base/CustomResourceDefinitionContext$Builder
       3: dup
       4: invokespecial #3                  // Method io/fabric8/kubernetes/client/dsl/base/CustomResourceDefinitionContext$Builder."<init>":()V
       7: ldc           #4                  // String service.dubbo.apache.org
       9: invokevirtual #5                  // Method io/fabric8/kubernetes/client/dsl/base/CustomResourceDefinitionContext$Builder.withGroup:(Ljava/lang/String;)Lio/fabric8/kubernetes/client/dsl/base/CustomResourceDefinitionContext$Builder;
      12: ldc           #6                  // String v1alpha1
      14: invokevirtual #7                  // Method io/fabric8/kubernetes/client/dsl/base/CustomResourceDefinitionContext$Builder.withVersion:(Ljava/lang/String;)Lio/fabric8/kubernetes/client/dsl/base/CustomResourceDefinitionContext$Builder;
      17: ldc           #8                  // String Namespaced
      19: invokevirtual #9                  // Method io/fabric8/kubernetes/client/dsl/base/CustomResourceDefinitionContext$Builder.withScope:(Ljava/lang/String;)Lio/fabric8/kubernetes/client/dsl/base/CustomResourceDefinitionContext$Builder;
      22: ldc           #17                 // String destinationrules.service.dubbo.apache.org
      24: invokevirtual #11                 // Method io/fabric8/kubernetes/client/dsl/base/CustomResourceDefinitionContext$Builder.withName:(Ljava/lang/String;)Lio/fabric8/kubernetes/client/dsl/base/CustomResourceDefinitionContext$Builder;
      27: ldc           #18                 // String destinationrules
      29: invokevirtual #13                 // Method io/fabric8/kubernetes/client/dsl/base/CustomResourceDefinitionContext$Builder.withPlural:(Ljava/lang/String;)Lio/fabric8/kubernetes/client/dsl/base/CustomResourceDefinitionContext$Builder;
      32: ldc           #19                 // String DestinationRule
      34: invokevirtual #15                 // Method io/fabric8/kubernetes/client/dsl/base/CustomResourceDefinitionContext$Builder.withKind:(Ljava/lang/String;)Lio/fabric8/kubernetes/client/dsl/base/CustomResourceDefinitionContext$Builder;
      37: invokevirtual #16                 // Method io/fabric8/kubernetes/client/dsl/base/CustomResourceDefinitionContext$Builder.build:()Lio/fabric8/kubernetes/client/dsl/base/CustomResourceDefinitionContext;
      40: areturn
}
