Compiled from "AbortPolicyWithReport.java"
public class org.apache.dubbo.common.threadpool.support.AbortPolicyWithReport extends java.util.concurrent.ThreadPoolExecutor$AbortPolicy {
  protected static final org.apache.dubbo.common.logger.ErrorTypeAwareLogger logger;

  private final java.lang.String threadName;

  private final org.apache.dubbo.common.URL url;

  protected static volatile long lastPrintTime;

  private static final long TEN_MINUTES_MILLS;

  private static final java.lang.String WIN_DATETIME_FORMAT;

  private static final java.lang.String DEFAULT_DATETIME_FORMAT;

  protected static java.util.concurrent.Semaphore guard;

  private static final java.lang.String USER_HOME;

  private final java.util.Set<org.apache.dubbo.common.threadpool.event.ThreadPoolExhaustedListener> listeners;

  public org.apache.dubbo.common.threadpool.support.AbortPolicyWithReport(java.lang.String, org.apache.dubbo.common.URL);
    Code:
       0: aload_0
       1: invokespecial #3                  // Method java/util/concurrent/ThreadPoolExecutor$AbortPolicy."<init>":()V
       4: aload_0
       5: new           #4                  // class org/apache/dubbo/common/utils/ConcurrentHashSet
       8: dup
       9: invokespecial #5                  // Method org/apache/dubbo/common/utils/ConcurrentHashSet."<init>":()V
      12: putfield      #6                  // Field listeners:Ljava/util/Set;
      15: aload_0
      16: aload_1
      17: putfield      #7                  // Field threadName:Ljava/lang/String;
      20: aload_0
      21: aload_2
      22: putfield      #8                  // Field url:Lorg/apache/dubbo/common/URL;
      25: aload_2
      26: ldc           #9                  // String thread-pool-exhausted-listeners
      28: aload_2
      29: ldc           #9                  // String thread-pool-exhausted-listeners
      31: invokevirtual #10                 // Method org/apache/dubbo/common/URL.getAttribute:(Ljava/lang/String;)Ljava/lang/Object;
      34: checkcast     #11                 // class java/lang/String
      37: invokevirtual #12                 // Method org/apache/dubbo/common/URL.getParameter:(Ljava/lang/String;Ljava/lang/String;)Ljava/lang/String;
      40: astore_3
      41: aload_3
      42: bipush        44
      44: iconst_1
      45: invokestatic  #13                 // Method org/apache/dubbo/common/utils/StringUtils.splitToSet:(Ljava/lang/String;CZ)Ljava/util/Set;
      48: astore        4
      50: aload_2
      51: invokevirtual #14                 // Method org/apache/dubbo/common/URL.getOrDefaultFrameworkModel:()Lorg/apache/dubbo/rpc/model/FrameworkModel;
      54: astore        5
      56: aload         5
      58: ldc           #15                 // class org/apache/dubbo/common/threadpool/event/ThreadPoolExhaustedListener
      60: invokevirtual #16                 // Method org/apache/dubbo/rpc/model/FrameworkModel.getExtensionLoader:(Ljava/lang/Class;)Lorg/apache/dubbo/common/extension/ExtensionLoader;
      63: astore        6
      65: aload         4
      67: aload_0
      68: aload         6
      70: invokedynamic #17,  0             // InvokeDynamic #0:accept:(Lorg/apache/dubbo/common/threadpool/support/AbortPolicyWithReport;Lorg/apache/dubbo/common/extension/ExtensionLoader;)Ljava/util/function/Consumer;
      75: invokeinterface #18,  2           // InterfaceMethod java/util/Set.forEach:(Ljava/util/function/Consumer;)V
      80: return

  public void rejectedExecution(java.lang.Runnable, java.util.concurrent.ThreadPoolExecutor);
    Code:
       0: ldc           #19                 // String Thread pool is EXHAUSTED! Thread Name: %s, Pool Size: %d (active: %d, core: %d, max: %d, largest: %d), Task: %d (completed: %d), Executor status:(isShutdown:%s, isTerminated:%s, isTerminating:%s), in %s://%s:%d!
       2: bipush        14
       4: anewarray     #20                 // class java/lang/Object
       7: dup
       8: iconst_0
       9: aload_0
      10: getfield      #7                  // Field threadName:Ljava/lang/String;
      13: aastore
      14: dup
      15: iconst_1
      16: aload_2
      17: invokevirtual #21                 // Method java/util/concurrent/ThreadPoolExecutor.getPoolSize:()I
      20: invokestatic  #22                 // Method java/lang/Integer.valueOf:(I)Ljava/lang/Integer;
      23: aastore
      24: dup
      25: iconst_2
      26: aload_2
      27: invokevirtual #23                 // Method java/util/concurrent/ThreadPoolExecutor.getActiveCount:()I
      30: invokestatic  #22                 // Method java/lang/Integer.valueOf:(I)Ljava/lang/Integer;
      33: aastore
      34: dup
      35: iconst_3
      36: aload_2
      37: invokevirtual #24                 // Method java/util/concurrent/ThreadPoolExecutor.getCorePoolSize:()I
      40: invokestatic  #22                 // Method java/lang/Integer.valueOf:(I)Ljava/lang/Integer;
      43: aastore
      44: dup
      45: iconst_4
      46: aload_2
      47: invokevirtual #25                 // Method java/util/concurrent/ThreadPoolExecutor.getMaximumPoolSize:()I
      50: invokestatic  #22                 // Method java/lang/Integer.valueOf:(I)Ljava/lang/Integer;
      53: aastore
      54: dup
      55: iconst_5
      56: aload_2
      57: invokevirtual #26                 // Method java/util/concurrent/ThreadPoolExecutor.getLargestPoolSize:()I
      60: invokestatic  #22                 // Method java/lang/Integer.valueOf:(I)Ljava/lang/Integer;
      63: aastore
      64: dup
      65: bipush        6
      67: aload_2
      68: invokevirtual #27                 // Method java/util/concurrent/ThreadPoolExecutor.getTaskCount:()J
      71: invokestatic  #28                 // Method java/lang/Long.valueOf:(J)Ljava/lang/Long;
      74: aastore
      75: dup
      76: bipush        7
      78: aload_2
      79: invokevirtual #29                 // Method java/util/concurrent/ThreadPoolExecutor.getCompletedTaskCount:()J
      82: invokestatic  #28                 // Method java/lang/Long.valueOf:(J)Ljava/lang/Long;
      85: aastore
      86: dup
      87: bipush        8
      89: aload_2
      90: invokevirtual #30                 // Method java/util/concurrent/ThreadPoolExecutor.isShutdown:()Z
      93: invokestatic  #31                 // Method java/lang/Boolean.valueOf:(Z)Ljava/lang/Boolean;
      96: aastore
      97: dup
      98: bipush        9
     100: aload_2
     101: invokevirtual #32                 // Method java/util/concurrent/ThreadPoolExecutor.isTerminated:()Z
     104: invokestatic  #31                 // Method java/lang/Boolean.valueOf:(Z)Ljava/lang/Boolean;
     107: aastore
     108: dup
     109: bipush        10
     111: aload_2
     112: invokevirtual #33                 // Method java/util/concurrent/ThreadPoolExecutor.isTerminating:()Z
     115: invokestatic  #31                 // Method java/lang/Boolean.valueOf:(Z)Ljava/lang/Boolean;
     118: aastore
     119: dup
     120: bipush        11
     122: aload_0
     123: getfield      #8                  // Field url:Lorg/apache/dubbo/common/URL;
     126: invokevirtual #34                 // Method org/apache/dubbo/common/URL.getProtocol:()Ljava/lang/String;
     129: aastore
     130: dup
     131: bipush        12
     133: aload_0
     134: getfield      #8                  // Field url:Lorg/apache/dubbo/common/URL;
     137: invokevirtual #35                 // Method org/apache/dubbo/common/URL.getIp:()Ljava/lang/String;
     140: aastore
     141: dup
     142: bipush        13
     144: aload_0
     145: getfield      #8                  // Field url:Lorg/apache/dubbo/common/URL;
     148: invokevirtual #36                 // Method org/apache/dubbo/common/URL.getPort:()I
     151: invokestatic  #22                 // Method java/lang/Integer.valueOf:(I)Ljava/lang/Integer;
     154: aastore
     155: invokestatic  #37                 // Method java/lang/String.format:(Ljava/lang/String;[Ljava/lang/Object;)Ljava/lang/String;
     158: astore_3
     159: getstatic     #38                 // Field logger:Lorg/apache/dubbo/common/logger/ErrorTypeAwareLogger;
     162: ldc           #39                 // String 0-1
     164: ldc           #40                 // String too much client requesting provider
     166: ldc           #41                 // String
     168: aload_3
     169: invokeinterface #42,  5           // InterfaceMethod org/apache/dubbo/common/logger/ErrorTypeAwareLogger.warn:(Ljava/lang/String;Ljava/lang/String;Ljava/lang/String;Ljava/lang/String;)V
     174: aload_0
     175: getfield      #8                  // Field url:Lorg/apache/dubbo/common/URL;
     178: ldc           #43                 // String dump.enable
     180: ldc           #44                 // String true
     182: invokevirtual #12                 // Method org/apache/dubbo/common/URL.getParameter:(Ljava/lang/String;Ljava/lang/String;)Ljava/lang/String;
     185: invokestatic  #45                 // Method java/lang/Boolean.parseBoolean:(Ljava/lang/String;)Z
     188: ifeq          195
     191: aload_0
     192: invokespecial #46                 // Method dumpJStack:()V
     195: aload_0
     196: aload_3
     197: invokevirtual #47                 // Method dispatchThreadPoolExhaustedEvent:(Ljava/lang/String;)V
     200: new           #48                 // class java/util/concurrent/RejectedExecutionException
     203: dup
     204: aload_3
     205: invokespecial #49                 // Method java/util/concurrent/RejectedExecutionException."<init>":(Ljava/lang/String;)V
     208: athrow

  public void addThreadPoolExhaustedEventListener(org.apache.dubbo.common.threadpool.event.ThreadPoolExhaustedListener);
    Code:
       0: aload_0
       1: getfield      #6                  // Field listeners:Ljava/util/Set;
       4: aload_1
       5: invokeinterface #50,  2           // InterfaceMethod java/util/Set.add:(Ljava/lang/Object;)Z
      10: pop
      11: return

  public void removeThreadPoolExhaustedEventListener(org.apache.dubbo.common.threadpool.event.ThreadPoolExhaustedListener);
    Code:
       0: aload_0
       1: getfield      #6                  // Field listeners:Ljava/util/Set;
       4: aload_1
       5: invokeinterface #51,  2           // InterfaceMethod java/util/Set.remove:(Ljava/lang/Object;)Z
      10: pop
      11: return

  public void dispatchThreadPoolExhaustedEvent(java.lang.String);
    Code:
       0: aload_0
       1: getfield      #6                  // Field listeners:Ljava/util/Set;
       4: aload_1
       5: invokedynamic #52,  0             // InvokeDynamic #1:accept:(Ljava/lang/String;)Ljava/util/function/Consumer;
      10: invokeinterface #18,  2           // InterfaceMethod java/util/Set.forEach:(Ljava/util/function/Consumer;)V
      15: return

  private void dumpJStack();
    Code:
       0: invokestatic  #53                 // Method java/lang/System.currentTimeMillis:()J
       3: lstore_1
       4: lload_1
       5: getstatic     #54                 // Field lastPrintTime:J
       8: lsub
       9: ldc2_w        #56                 // long 600000l
      12: lcmp
      13: ifge          17
      16: return
      17: getstatic     #58                 // Field guard:Ljava/util/concurrent/Semaphore;
      20: invokevirtual #59                 // Method java/util/concurrent/Semaphore.tryAcquire:()Z
      23: ifne          27
      26: return
      27: invokestatic  #60                 // Method java/util/concurrent/Executors.newSingleThreadExecutor:()Ljava/util/concurrent/ExecutorService;
      30: astore_3
      31: aload_3
      32: aload_0
      33: invokedynamic #61,  0             // InvokeDynamic #2:run:(Lorg/apache/dubbo/common/threadpool/support/AbortPolicyWithReport;)Ljava/lang/Runnable;
      38: invokeinterface #62,  2           // InterfaceMethod java/util/concurrent/ExecutorService.execute:(Ljava/lang/Runnable;)V
      43: aload_3
      44: invokeinterface #63,  1           // InterfaceMethod java/util/concurrent/ExecutorService.shutdown:()V
      49: return

  protected void jstack(java.io.FileOutputStream) throws java.lang.Exception;
    Code:
       0: aload_1
       1: invokestatic  #64                 // Method org/apache/dubbo/common/utils/JVMUtil.jstack:(Ljava/io/OutputStream;)V
       4: return

  protected java.lang.String getDumpPath();
    Code:
       0: aload_0
       1: getfield      #8                  // Field url:Lorg/apache/dubbo/common/URL;
       4: ldc           #65                 // String dump.directory
       6: invokevirtual #66                 // Method org/apache/dubbo/common/URL.getParameter:(Ljava/lang/String;)Ljava/lang/String;
       9: astore_1
      10: aload_1
      11: invokestatic  #67                 // Method org/apache/dubbo/common/utils/StringUtils.isEmpty:(Ljava/lang/String;)Z
      14: ifeq          21
      17: getstatic     #68                 // Field USER_HOME:Ljava/lang/String;
      20: areturn
      21: new           #69                 // class java/io/File
      24: dup
      25: aload_1
      26: invokespecial #70                 // Method java/io/File."<init>":(Ljava/lang/String;)V
      29: astore_2
      30: aload_2
      31: invokevirtual #71                 // Method java/io/File.exists:()Z
      34: ifne          111
      37: aload_2
      38: invokevirtual #72                 // Method java/io/File.mkdirs:()Z
      41: ifeq          71
      44: getstatic     #38                 // Field logger:Lorg/apache/dubbo/common/logger/ErrorTypeAwareLogger;
      47: ldc           #73                 // String Dubbo dump directory[%s] created
      49: iconst_1
      50: anewarray     #20                 // class java/lang/Object
      53: dup
      54: iconst_0
      55: aload_2
      56: invokevirtual #74                 // Method java/io/File.getAbsolutePath:()Ljava/lang/String;
      59: aastore
      60: invokestatic  #37                 // Method java/lang/String.format:(Ljava/lang/String;[Ljava/lang/Object;)Ljava/lang/String;
      63: invokeinterface #75,  2           // InterfaceMethod org/apache/dubbo/common/logger/ErrorTypeAwareLogger.info:(Ljava/lang/String;)V
      68: goto          111
      71: getstatic     #38                 // Field logger:Lorg/apache/dubbo/common/logger/ErrorTypeAwareLogger;
      74: ldc           #76                 // String 0-20
      76: ldc           #41                 // String
      78: ldc           #41                 // String
      80: ldc           #77                 // String Dubbo dump directory[%s] can\'t be created, use the \'user.home\'[%s]
      82: iconst_2
      83: anewarray     #20                 // class java/lang/Object
      86: dup
      87: iconst_0
      88: aload_2
      89: invokevirtual #74                 // Method java/io/File.getAbsolutePath:()Ljava/lang/String;
      92: aastore
      93: dup
      94: iconst_1
      95: getstatic     #68                 // Field USER_HOME:Ljava/lang/String;
      98: aastore
      99: invokestatic  #37                 // Method java/lang/String.format:(Ljava/lang/String;[Ljava/lang/Object;)Ljava/lang/String;
     102: invokeinterface #42,  5           // InterfaceMethod org/apache/dubbo/common/logger/ErrorTypeAwareLogger.warn:(Ljava/lang/String;Ljava/lang/String;Ljava/lang/String;Ljava/lang/String;)V
     107: getstatic     #68                 // Field USER_HOME:Ljava/lang/String;
     110: areturn
     111: aload_1
     112: areturn

  private void lambda$dumpJStack$2();
    Code:
       0: aload_0
       1: invokevirtual #78                 // Method getDumpPath:()Ljava/lang/String;
       4: astore_1
       5: ldc           #79                 // String os.name
       7: invokestatic  #80                 // Method java/lang/System.getProperty:(Ljava/lang/String;)Ljava/lang/String;
      10: invokevirtual #81                 // Method java/lang/String.toLowerCase:()Ljava/lang/String;
      13: astore_3
      14: aload_3
      15: ldc           #82                 // String win
      17: invokevirtual #83                 // Method java/lang/String.contains:(Ljava/lang/CharSequence;)Z
      20: ifeq          36
      23: new           #84                 // class java/text/SimpleDateFormat
      26: dup
      27: ldc           #85                 // String yyyy-MM-dd_HH-mm-ss
      29: invokespecial #86                 // Method java/text/SimpleDateFormat."<init>":(Ljava/lang/String;)V
      32: astore_2
      33: goto          46
      36: new           #84                 // class java/text/SimpleDateFormat
      39: dup
      40: ldc           #87                 // String yyyy-MM-dd_HH:mm:ss
      42: invokespecial #86                 // Method java/text/SimpleDateFormat."<init>":(Ljava/lang/String;)V
      45: astore_2
      46: aload_2
      47: new           #88                 // class java/util/Date
      50: dup
      51: invokespecial #89                 // Method java/util/Date."<init>":()V
      54: invokevirtual #90                 // Method java/text/SimpleDateFormat.format:(Ljava/util/Date;)Ljava/lang/String;
      57: astore        4
      59: new           #91                 // class java/io/FileOutputStream
      62: dup
      63: new           #69                 // class java/io/File
      66: dup
      67: aload_1
      68: new           #92                 // class java/lang/StringBuilder
      71: dup
      72: invokespecial #93                 // Method java/lang/StringBuilder."<init>":()V
      75: ldc           #94                 // String Dubbo_JStack.log.
      77: invokevirtual #95                 // Method java/lang/StringBuilder.append:(Ljava/lang/String;)Ljava/lang/StringBuilder;
      80: aload         4
      82: invokevirtual #95                 // Method java/lang/StringBuilder.append:(Ljava/lang/String;)Ljava/lang/StringBuilder;
      85: invokevirtual #96                 // Method java/lang/StringBuilder.toString:()Ljava/lang/String;
      88: invokespecial #97                 // Method java/io/File."<init>":(Ljava/lang/String;Ljava/lang/String;)V
      91: invokespecial #98                 // Method java/io/FileOutputStream."<init>":(Ljava/io/File;)V
      94: astore        5
      96: aconst_null
      97: astore        6
      99: aload_0
     100: aload         5
     102: invokevirtual #99                 // Method jstack:(Ljava/io/FileOutputStream;)V
     105: aload         5
     107: ifnull        192
     110: aload         6
     112: ifnull        135
     115: aload         5
     117: invokevirtual #100                // Method java/io/FileOutputStream.close:()V
     120: goto          192
     123: astore        7
     125: aload         6
     127: aload         7
     129: invokevirtual #102                // Method java/lang/Throwable.addSuppressed:(Ljava/lang/Throwable;)V
     132: goto          192
     135: aload         5
     137: invokevirtual #100                // Method java/io/FileOutputStream.close:()V
     140: goto          192
     143: astore        7
     145: aload         7
     147: astore        6
     149: aload         7
     151: athrow
     152: astore        8
     154: aload         5
     156: ifnull        189
     159: aload         6
     161: ifnull        184
     164: aload         5
     166: invokevirtual #100                // Method java/io/FileOutputStream.close:()V
     169: goto          189
     172: astore        9
     174: aload         6
     176: aload         9
     178: invokevirtual #102                // Method java/lang/Throwable.addSuppressed:(Ljava/lang/Throwable;)V
     181: goto          189
     184: aload         5
     186: invokevirtual #100                // Method java/io/FileOutputStream.close:()V
     189: aload         8
     191: athrow
     192: getstatic     #58                 // Field guard:Ljava/util/concurrent/Semaphore;
     195: invokevirtual #103                // Method java/util/concurrent/Semaphore.release:()V
     198: goto          241
     201: astore        5
     203: getstatic     #38                 // Field logger:Lorg/apache/dubbo/common/logger/ErrorTypeAwareLogger;
     206: ldc           #76                 // String 0-20
     208: ldc           #41                 // String
     210: ldc           #41                 // String
     212: ldc           #105                // String dump jStack error
     214: aload         5
     216: invokeinterface #106,  6          // InterfaceMethod org/apache/dubbo/common/logger/ErrorTypeAwareLogger.error:(Ljava/lang/String;Ljava/lang/String;Ljava/lang/String;Ljava/lang/String;Ljava/lang/Throwable;)V
     221: getstatic     #58                 // Field guard:Ljava/util/concurrent/Semaphore;
     224: invokevirtual #103                // Method java/util/concurrent/Semaphore.release:()V
     227: goto          241
     230: astore        10
     232: getstatic     #58                 // Field guard:Ljava/util/concurrent/Semaphore;
     235: invokevirtual #103                // Method java/util/concurrent/Semaphore.release:()V
     238: aload         10
     240: athrow
     241: invokestatic  #53                 // Method java/lang/System.currentTimeMillis:()J
     244: putstatic     #54                 // Field lastPrintTime:J
     247: return
    Exception table:
       from    to  target type
         115   120   123   Class java/lang/Throwable
          99   105   143   Class java/lang/Throwable
          99   105   152   any
         164   169   172   Class java/lang/Throwable
         143   154   152   any
          59   192   201   Class java/lang/Exception
          59   192   230   any
         201   221   230   any
         230   232   230   any

  private static void lambda$dispatchThreadPoolExhaustedEvent$1(java.lang.String, org.apache.dubbo.common.threadpool.event.ThreadPoolExhaustedListener);
    Code:
       0: aload_1
       1: new           #107                // class org/apache/dubbo/common/threadpool/event/ThreadPoolExhaustedEvent
       4: dup
       5: aload_0
       6: invokespecial #108                // Method org/apache/dubbo/common/threadpool/event/ThreadPoolExhaustedEvent."<init>":(Ljava/lang/String;)V
       9: invokeinterface #109,  2          // InterfaceMethod org/apache/dubbo/common/threadpool/event/ThreadPoolExhaustedListener.onEvent:(Lorg/apache/dubbo/common/threadpool/event/ThreadPoolExhaustedEvent;)V
      14: return

  private void lambda$new$0(org.apache.dubbo.common.extension.ExtensionLoader, java.lang.String);
    Code:
       0: aload_1
       1: aload_2
       2: invokevirtual #110                // Method org/apache/dubbo/common/extension/ExtensionLoader.hasExtension:(Ljava/lang/String;)Z
       5: ifeq          20
       8: aload_0
       9: aload_1
      10: aload_2
      11: invokevirtual #111                // Method org/apache/dubbo/common/extension/ExtensionLoader.getExtension:(Ljava/lang/String;)Ljava/lang/Object;
      14: checkcast     #15                 // class org/apache/dubbo/common/threadpool/event/ThreadPoolExhaustedListener
      17: invokevirtual #112                // Method addThreadPoolExhaustedEventListener:(Lorg/apache/dubbo/common/threadpool/event/ThreadPoolExhaustedListener;)V
      20: return

  static {};
    Code:
       0: ldc           #55                 // class org/apache/dubbo/common/threadpool/support/AbortPolicyWithReport
       2: invokestatic  #113                // Method org/apache/dubbo/common/logger/LoggerFactory.getErrorTypeAwareLogger:(Ljava/lang/Class;)Lorg/apache/dubbo/common/logger/ErrorTypeAwareLogger;
       5: putstatic     #38                 // Field logger:Lorg/apache/dubbo/common/logger/ErrorTypeAwareLogger;
       8: lconst_0
       9: putstatic     #54                 // Field lastPrintTime:J
      12: new           #114                // class java/util/concurrent/Semaphore
      15: dup
      16: iconst_1
      17: invokespecial #115                // Method java/util/concurrent/Semaphore."<init>":(I)V
      20: putstatic     #58                 // Field guard:Ljava/util/concurrent/Semaphore;
      23: ldc           #116                // String user.home
      25: invokestatic  #80                 // Method java/lang/System.getProperty:(Ljava/lang/String;)Ljava/lang/String;
      28: putstatic     #68                 // Field USER_HOME:Ljava/lang/String;
      31: return
}
