Compiled from "DeferredLog.java"
class org.springframework.boot.logging.DeferredLog$Lines implements java.lang.Iterable<org.springframework.boot.logging.DeferredLog$Line> {
  private final java.util.List<org.springframework.boot.logging.DeferredLog$Line> lines;

  org.springframework.boot.logging.DeferredLog$Lines();
    Code:
       0: aload_0
       1: invokespecial #1                  // Method java/lang/Object."<init>":()V
       4: aload_0
       5: new           #7                  // class java/util/ArrayList
       8: dup
       9: invokespecial #9                  // Method java/util/ArrayList."<init>":()V
      12: putfield      #10                 // Field lines:Ljava/util/List;
      15: return

  void add(java.util.function.Supplier<org.apache.commons.logging.Log>, org.springframework.boot.logging.LogLevel, java.lang.Object, java.lang.Throwable);
    Code:
       0: aload_0
       1: getfield      #10                 // Field lines:Ljava/util/List;
       4: new           #16                 // class org/springframework/boot/logging/DeferredLog$Line
       7: dup
       8: aload_1
       9: aload_2
      10: aload_3
      11: aload         4
      13: invokespecial #18                 // Method org/springframework/boot/logging/DeferredLog$Line."<init>":(Ljava/util/function/Supplier;Lorg/springframework/boot/logging/LogLevel;Ljava/lang/Object;Ljava/lang/Throwable;)V
      16: invokeinterface #21,  2           // InterfaceMethod java/util/List.add:(Ljava/lang/Object;)Z
      21: pop
      22: return

  void clear();
    Code:
       0: aload_0
       1: getfield      #10                 // Field lines:Ljava/util/List;
       4: invokeinterface #27,  1           // InterfaceMethod java/util/List.clear:()V
       9: return

  public java.util.Iterator<org.springframework.boot.logging.DeferredLog$Line> iterator();
    Code:
       0: aload_0
       1: getfield      #10                 // Field lines:Ljava/util/List;
       4: invokeinterface #30,  1           // InterfaceMethod java/util/List.iterator:()Ljava/util/Iterator;
       9: areturn
}
