Compiled from "DeferredLogFactory.java"
public interface org.springframework.boot.logging.DeferredLogFactory {
  public default org.apache.commons.logging.Log getLog(java.lang.Class<?>);
    Code:
       0: aload_0
       1: aload_1
       2: invokedynamic #1,  0              // InvokeDynamic #0:get:(Ljava/lang/Class;)Ljava/util/function/Supplier;
       7: invokeinterface #5,  2            // InterfaceMethod getLog:(Ljava/util/function/Supplier;)Lorg/apache/commons/logging/Log;
      12: areturn

  public default org.apache.commons.logging.Log getLog(org.apache.commons.logging.Log);
    Code:
       0: aload_0
       1: aload_1
       2: invokedynamic #11,  0             // InvokeDynamic #1:get:(Lorg/apache/commons/logging/Log;)Ljava/util/function/Supplier;
       7: invokeinterface #5,  2            // InterfaceMethod getLog:(Ljava/util/function/Supplier;)Lorg/apache/commons/logging/Log;
      12: areturn

  public abstract org.apache.commons.logging.Log getLog(java.util.function.Supplier<org.apache.commons.logging.Log>);

  private static org.apache.commons.logging.Log lambda$getLog$1(org.apache.commons.logging.Log);
    Code:
       0: aload_0
       1: areturn

  private static org.apache.commons.logging.Log lambda$getLog$0(java.lang.Class);
    Code:
       0: aload_0
       1: invokestatic  #14                 // Method org/apache/commons/logging/LogFactory.getLog:(Ljava/lang/Class;)Lorg/apache/commons/logging/Log;
       4: areturn
}
