Compiled from "DelegatingLoggingSystemFactory.java"
class org.springframework.boot.logging.DelegatingLoggingSystemFactory implements org.springframework.boot.logging.LoggingSystemFactory {
  private final java.util.function.Function<java.lang.ClassLoader, java.util.List<org.springframework.boot.logging.LoggingSystemFactory>> delegates;

  org.springframework.boot.logging.DelegatingLoggingSystemFactory(java.util.function.Function<java.lang.ClassLoader, java.util.List<org.springframework.boot.logging.LoggingSystemFactory>>);
    Code:
       0: aload_0
       1: invokespecial #1                  // Method java/lang/Object."<init>":()V
       4: aload_0
       5: aload_1
       6: putfield      #7                  // Field delegates:Ljava/util/function/Function;
       9: return

  public org.springframework.boot.logging.LoggingSystem getLoggingSystem(java.lang.ClassLoader);
    Code:
       0: aload_0
       1: getfield      #7                  // Field delegates:Ljava/util/function/Function;
       4: ifnull        23
       7: aload_0
       8: getfield      #7                  // Field delegates:Ljava/util/function/Function;
      11: aload_1
      12: invokeinterface #13,  2           // InterfaceMethod java/util/function/Function.apply:(Ljava/lang/Object;)Ljava/lang/Object;
      17: checkcast     #19                 // class java/util/List
      20: goto          24
      23: aconst_null
      24: astore_2
      25: aload_2
      26: ifnull        77
      29: aload_2
      30: invokeinterface #21,  1           // InterfaceMethod java/util/List.iterator:()Ljava/util/Iterator;
      35: astore_3
      36: aload_3
      37: invokeinterface #25,  1           // InterfaceMethod java/util/Iterator.hasNext:()Z
      42: ifeq          77
      45: aload_3
      46: invokeinterface #31,  1           // InterfaceMethod java/util/Iterator.next:()Ljava/lang/Object;
      51: checkcast     #35                 // class org/springframework/boot/logging/LoggingSystemFactory
      54: astore        4
      56: aload         4
      58: aload_1
      59: invokeinterface #37,  2           // InterfaceMethod org/springframework/boot/logging/LoggingSystemFactory.getLoggingSystem:(Ljava/lang/ClassLoader;)Lorg/springframework/boot/logging/LoggingSystem;
      64: astore        5
      66: aload         5
      68: ifnull        74
      71: aload         5
      73: areturn
      74: goto          36
      77: aconst_null
      78: areturn
}
