Compiled from "LoggingSystemProperties.java"
public class org.springframework.boot.logging.LoggingSystemProperties {
  public static final java.lang.String PID_KEY;

  public static final java.lang.String EXCEPTION_CONVERSION_WORD;

  public static final java.lang.String LOG_FILE;

  public static final java.lang.String LOG_PATH;

  public static final java.lang.String CONSOLE_LOG_PATTERN;

  public static final java.lang.String CONSOLE_LOG_CHARSET;

  public static final java.lang.String CONSOLE_LOG_THRESHOLD;

  public static final java.lang.String FILE_LOG_PATTERN;

  public static final java.lang.String FILE_LOG_CHARSET;

  public static final java.lang.String FILE_LOG_THRESHOLD;

  public static final java.lang.String LOG_LEVEL_PATTERN;

  public static final java.lang.String LOG_DATEFORMAT_PATTERN;

  private static final java.util.function.BiConsumer<java.lang.String, java.lang.String> systemPropertySetter;

  private final org.springframework.core.env.Environment environment;

  private final java.util.function.BiConsumer<java.lang.String, java.lang.String> setter;

  public org.springframework.boot.logging.LoggingSystemProperties(org.springframework.core.env.Environment);
    Code:
       0: aload_0
       1: aload_1
       2: getstatic     #1                  // Field systemPropertySetter:Ljava/util/function/BiConsumer;
       5: invokespecial #7                  // Method "<init>":(Lorg/springframework/core/env/Environment;Ljava/util/function/BiConsumer;)V
       8: return

  public org.springframework.boot.logging.LoggingSystemProperties(org.springframework.core.env.Environment, java.util.function.BiConsumer<java.lang.String, java.lang.String>);
    Code:
       0: aload_0
       1: invokespecial #11                 // Method java/lang/Object."<init>":()V
       4: aload_1
       5: ldc           #16                 // String Environment must not be null
       7: invokestatic  #18                 // Method org/springframework/util/Assert.notNull:(Ljava/lang/Object;Ljava/lang/String;)V
      10: aload_2
      11: ldc           #24                 // String Setter must not be null
      13: invokestatic  #18                 // Method org/springframework/util/Assert.notNull:(Ljava/lang/Object;Ljava/lang/String;)V
      16: aload_0
      17: aload_1
      18: putfield      #26                 // Field environment:Lorg/springframework/core/env/Environment;
      21: aload_0
      22: aload_2
      23: putfield      #30                 // Field setter:Ljava/util/function/BiConsumer;
      26: return

  protected java.nio.charset.Charset getDefaultCharset();
    Code:
       0: getstatic     #33                 // Field java/nio/charset/StandardCharsets.UTF_8:Ljava/nio/charset/Charset;
       3: areturn

  public final void apply();
    Code:
       0: aload_0
       1: aconst_null
       2: invokevirtual #39                 // Method apply:(Lorg/springframework/boot/logging/LogFile;)V
       5: return

  public final void apply(org.springframework.boot.logging.LogFile);
    Code:
       0: aload_0
       1: invokevirtual #43                 // Method getPropertyResolver:()Lorg/springframework/core/env/PropertyResolver;
       4: astore_2
       5: aload_0
       6: aload_1
       7: aload_2
       8: invokevirtual #47                 // Method apply:(Lorg/springframework/boot/logging/LogFile;Lorg/springframework/core/env/PropertyResolver;)V
      11: return

  protected void apply(org.springframework.boot.logging.LogFile, org.springframework.core.env.PropertyResolver);
    Code:
       0: aload_0
       1: aload_2
       2: ldc           #50                 // String LOG_EXCEPTION_CONVERSION_WORD
       4: ldc           #52                 // String logging.exception-conversion-word
       6: invokevirtual #54                 // Method setSystemProperty:(Lorg/springframework/core/env/PropertyResolver;Ljava/lang/String;Ljava/lang/String;)V
       9: aload_0
      10: ldc           #58                 // String PID
      12: new           #60                 // class org/springframework/boot/system/ApplicationPid
      15: dup
      16: invokespecial #62                 // Method org/springframework/boot/system/ApplicationPid."<init>":()V
      19: invokevirtual #63                 // Method org/springframework/boot/system/ApplicationPid.toString:()Ljava/lang/String;
      22: invokevirtual #67                 // Method setSystemProperty:(Ljava/lang/String;Ljava/lang/String;)V
      25: aload_0
      26: aload_2
      27: ldc           #70                 // String CONSOLE_LOG_PATTERN
      29: ldc           #72                 // String logging.pattern.console
      31: invokevirtual #54                 // Method setSystemProperty:(Lorg/springframework/core/env/PropertyResolver;Ljava/lang/String;Ljava/lang/String;)V
      34: aload_0
      35: aload_2
      36: ldc           #74                 // String CONSOLE_LOG_CHARSET
      38: ldc           #76                 // String logging.charset.console
      40: aload_0
      41: invokevirtual #78                 // Method getDefaultCharset:()Ljava/nio/charset/Charset;
      44: invokevirtual #82                 // Method java/nio/charset/Charset.name:()Ljava/lang/String;
      47: invokevirtual #87                 // Method setSystemProperty:(Lorg/springframework/core/env/PropertyResolver;Ljava/lang/String;Ljava/lang/String;Ljava/lang/String;)V
      50: aload_0
      51: aload_2
      52: ldc           #90                 // String CONSOLE_LOG_THRESHOLD
      54: ldc           #92                 // String logging.threshold.console
      56: invokevirtual #54                 // Method setSystemProperty:(Lorg/springframework/core/env/PropertyResolver;Ljava/lang/String;Ljava/lang/String;)V
      59: aload_0
      60: aload_2
      61: ldc           #94                 // String LOG_DATEFORMAT_PATTERN
      63: ldc           #96                 // String logging.pattern.dateformat
      65: invokevirtual #54                 // Method setSystemProperty:(Lorg/springframework/core/env/PropertyResolver;Ljava/lang/String;Ljava/lang/String;)V
      68: aload_0
      69: aload_2
      70: ldc           #98                 // String FILE_LOG_PATTERN
      72: ldc           #100                // String logging.pattern.file
      74: invokevirtual #54                 // Method setSystemProperty:(Lorg/springframework/core/env/PropertyResolver;Ljava/lang/String;Ljava/lang/String;)V
      77: aload_0
      78: aload_2
      79: ldc           #102                // String FILE_LOG_CHARSET
      81: ldc           #104                // String logging.charset.file
      83: aload_0
      84: invokevirtual #78                 // Method getDefaultCharset:()Ljava/nio/charset/Charset;
      87: invokevirtual #82                 // Method java/nio/charset/Charset.name:()Ljava/lang/String;
      90: invokevirtual #87                 // Method setSystemProperty:(Lorg/springframework/core/env/PropertyResolver;Ljava/lang/String;Ljava/lang/String;Ljava/lang/String;)V
      93: aload_0
      94: aload_2
      95: ldc           #106                // String FILE_LOG_THRESHOLD
      97: ldc           #108                // String logging.threshold.file
      99: invokevirtual #54                 // Method setSystemProperty:(Lorg/springframework/core/env/PropertyResolver;Ljava/lang/String;Ljava/lang/String;)V
     102: aload_0
     103: aload_2
     104: ldc           #110                // String LOG_LEVEL_PATTERN
     106: ldc           #112                // String logging.pattern.level
     108: invokevirtual #54                 // Method setSystemProperty:(Lorg/springframework/core/env/PropertyResolver;Ljava/lang/String;Ljava/lang/String;)V
     111: aload_1
     112: ifnull        119
     115: aload_1
     116: invokevirtual #114                // Method org/springframework/boot/logging/LogFile.applyToSystemProperties:()V
     119: return

  private org.springframework.core.env.PropertyResolver getPropertyResolver();
    Code:
       0: aload_0
       1: getfield      #26                 // Field environment:Lorg/springframework/core/env/Environment;
       4: astore_2
       5: aload_2
       6: instanceof    #119                // class org/springframework/core/env/ConfigurableEnvironment
       9: ifeq          54
      12: aload_2
      13: checkcast     #119                // class org/springframework/core/env/ConfigurableEnvironment
      16: astore_1
      17: new           #121                // class org/springframework/core/env/PropertySourcesPropertyResolver
      20: dup
      21: aload_1
      22: invokeinterface #123,  1          // InterfaceMethod org/springframework/core/env/ConfigurableEnvironment.getPropertySources:()Lorg/springframework/core/env/MutablePropertySources;
      27: invokespecial #127                // Method org/springframework/core/env/PropertySourcesPropertyResolver."<init>":(Lorg/springframework/core/env/PropertySources;)V
      30: astore_2
      31: aload_2
      32: aload_0
      33: getfield      #26                 // Field environment:Lorg/springframework/core/env/Environment;
      36: checkcast     #119                // class org/springframework/core/env/ConfigurableEnvironment
      39: invokeinterface #130,  1          // InterfaceMethod org/springframework/core/env/ConfigurableEnvironment.getConversionService:()Lorg/springframework/core/convert/support/ConfigurableConversionService;
      44: invokevirtual #134                // Method org/springframework/core/env/PropertySourcesPropertyResolver.setConversionService:(Lorg/springframework/core/convert/support/ConfigurableConversionService;)V
      47: aload_2
      48: iconst_1
      49: invokevirtual #138                // Method org/springframework/core/env/PropertySourcesPropertyResolver.setIgnoreUnresolvableNestedPlaceholders:(Z)V
      52: aload_2
      53: areturn
      54: aload_0
      55: getfield      #26                 // Field environment:Lorg/springframework/core/env/Environment;
      58: areturn

  protected final void setSystemProperty(org.springframework.core.env.PropertyResolver, java.lang.String, java.lang.String);
    Code:
       0: aload_0
       1: aload_1
       2: aload_2
       3: aload_3
       4: aconst_null
       5: invokevirtual #87                 // Method setSystemProperty:(Lorg/springframework/core/env/PropertyResolver;Ljava/lang/String;Ljava/lang/String;Ljava/lang/String;)V
       8: return

  protected final void setSystemProperty(org.springframework.core.env.PropertyResolver, java.lang.String, java.lang.String, java.lang.String);
    Code:
       0: aload_1
       1: aload_3
       2: invokeinterface #142,  2          // InterfaceMethod org/springframework/core/env/PropertyResolver.getProperty:(Ljava/lang/String;)Ljava/lang/String;
       7: astore        5
       9: aload         5
      11: ifnull        19
      14: aload         5
      16: goto          21
      19: aload         4
      21: astore        5
      23: aload_0
      24: aload_2
      25: aload         5
      27: invokevirtual #67                 // Method setSystemProperty:(Ljava/lang/String;Ljava/lang/String;)V
      30: return

  protected final void setSystemProperty(java.lang.String, java.lang.String);
    Code:
       0: aload_0
       1: getfield      #30                 // Field setter:Ljava/util/function/BiConsumer;
       4: aload_1
       5: aload_2
       6: invokeinterface #148,  3          // InterfaceMethod java/util/function/BiConsumer.accept:(Ljava/lang/Object;Ljava/lang/Object;)V
      11: return

  private static void lambda$static$0(java.lang.String, java.lang.String);
    Code:
       0: aload_0
       1: invokestatic  #154                // Method java/lang/System.getProperty:(Ljava/lang/String;)Ljava/lang/String;
       4: ifnonnull     17
       7: aload_1
       8: ifnull        17
      11: aload_0
      12: aload_1
      13: invokestatic  #157                // Method java/lang/System.setProperty:(Ljava/lang/String;Ljava/lang/String;)Ljava/lang/String;
      16: pop
      17: return

  static {};
    Code:
       0: invokedynamic #161,  0            // InvokeDynamic #0:accept:()Ljava/util/function/BiConsumer;
       5: putstatic     #1                  // Field systemPropertySetter:Ljava/util/function/BiConsumer;
       8: return
}
