Compiled from "LoggingSystemFactory.java"
public interface org.springframework.boot.logging.LoggingSystemFactory {
  public abstract org.springframework.boot.logging.LoggingSystem getLoggingSystem(java.lang.ClassLoader);

  public static org.springframework.boot.logging.LoggingSystemFactory fromSpringFactories();
    Code:
       0: new           #1                  // class org/springframework/boot/logging/DelegatingLoggingSystemFactory
       3: dup
       4: invokedynamic #3,  0              // InvokeDynamic #0:apply:()Ljava/util/function/Function;
       9: invokespecial #7                  // Method org/springframework/boot/logging/DelegatingLoggingSystemFactory."<init>":(Ljava/util/function/Function;)V
      12: areturn

  private static java.util.List lambda$fromSpringFactories$0(java.lang.ClassLoader);
    Code:
       0: ldc           #11                 // class org/springframework/boot/logging/LoggingSystemFactory
       2: aload_0
       3: invokestatic  #13                 // Method org/springframework/core/io/support/SpringFactoriesLoader.loadFactories:(Ljava/lang/Class;Ljava/lang/ClassLoader;)Ljava/util/List;
       6: areturn
}
