Compiled from "LogLevel.java"
public final class org.springframework.boot.logging.LogLevel extends java.lang.Enum<org.springframework.boot.logging.LogLevel> {
  public static final org.springframework.boot.logging.LogLevel TRACE;

  public static final org.springframework.boot.logging.LogLevel DEBUG;

  public static final org.springframework.boot.logging.LogLevel INFO;

  public static final org.springframework.boot.logging.LogLevel WARN;

  public static final org.springframework.boot.logging.LogLevel ERROR;

  public static final org.springframework.boot.logging.LogLevel FATAL;

  public static final org.springframework.boot.logging.LogLevel OFF;

  private final org.springframework.boot.logging.LogLevel$LogMethod logMethod;

  private static final org.springframework.boot.logging.LogLevel[] $VALUES;

  public static org.springframework.boot.logging.LogLevel[] values();
    Code:
       0: getstatic     #25                 // Field $VALUES:[Lorg/springframework/boot/logging/LogLevel;
       3: invokevirtual #29                 // Method "[Lorg/springframework/boot/logging/LogLevel;".clone:()Ljava/lang/Object;
       6: checkcast     #30                 // class "[Lorg/springframework/boot/logging/LogLevel;"
       9: areturn

  public static org.springframework.boot.logging.LogLevel valueOf(java.lang.String);
    Code:
       0: ldc           #1                  // class org/springframework/boot/logging/LogLevel
       2: aload_0
       3: invokestatic  #34                 // Method java/lang/Enum.valueOf:(Ljava/lang/Class;Ljava/lang/String;)Ljava/lang/Enum;
       6: checkcast     #1                  // class org/springframework/boot/logging/LogLevel
       9: areturn

  private org.springframework.boot.logging.LogLevel(org.springframework.boot.logging.LogLevel$LogMethod);
    Code:
       0: aload_0
       1: aload_1
       2: iload_2
       3: invokespecial #40                 // Method java/lang/Enum."<init>":(Ljava/lang/String;I)V
       6: aload_0
       7: aload_3
       8: putfield      #44                 // Field logMethod:Lorg/springframework/boot/logging/LogLevel$LogMethod;
      11: return

  public void log(org.apache.commons.logging.Log, java.lang.Object);
    Code:
       0: aload_0
       1: aload_1
       2: aload_2
       3: aconst_null
       4: invokevirtual #48                 // Method log:(Lorg/apache/commons/logging/Log;Ljava/lang/Object;Ljava/lang/Throwable;)V
       7: return

  public void log(org.apache.commons.logging.Log, java.lang.Object, java.lang.Throwable);
    Code:
       0: aload_1
       1: ifnull        23
       4: aload_0
       5: getfield      #44                 // Field logMethod:Lorg/springframework/boot/logging/LogLevel$LogMethod;
       8: ifnull        23
      11: aload_0
      12: getfield      #44                 // Field logMethod:Lorg/springframework/boot/logging/LogLevel$LogMethod;
      15: aload_1
      16: aload_2
      17: aload_3
      18: invokeinterface #52,  4           // InterfaceMethod org/springframework/boot/logging/LogLevel$LogMethod.log:(Lorg/apache/commons/logging/Log;Ljava/lang/Object;Ljava/lang/Throwable;)V
      23: return

  private static org.springframework.boot.logging.LogLevel[] $values();
    Code:
       0: bipush        7
       2: anewarray     #1                  // class org/springframework/boot/logging/LogLevel
       5: dup
       6: iconst_0
       7: getstatic     #3                  // Field TRACE:Lorg/springframework/boot/logging/LogLevel;
      10: aastore
      11: dup
      12: iconst_1
      13: getstatic     #7                  // Field DEBUG:Lorg/springframework/boot/logging/LogLevel;
      16: aastore
      17: dup
      18: iconst_2
      19: getstatic     #10                 // Field INFO:Lorg/springframework/boot/logging/LogLevel;
      22: aastore
      23: dup
      24: iconst_3
      25: getstatic     #13                 // Field WARN:Lorg/springframework/boot/logging/LogLevel;
      28: aastore
      29: dup
      30: iconst_4
      31: getstatic     #16                 // Field ERROR:Lorg/springframework/boot/logging/LogLevel;
      34: aastore
      35: dup
      36: iconst_5
      37: getstatic     #19                 // Field FATAL:Lorg/springframework/boot/logging/LogLevel;
      40: aastore
      41: dup
      42: bipush        6
      44: getstatic     #22                 // Field OFF:Lorg/springframework/boot/logging/LogLevel;
      47: aastore
      48: areturn

  static {};
    Code:
       0: new           #1                  // class org/springframework/boot/logging/LogLevel
       3: dup
       4: ldc           #55                 // String TRACE
       6: iconst_0
       7: invokedynamic #56,  0             // InvokeDynamic #0:log:()Lorg/springframework/boot/logging/LogLevel$LogMethod;
      12: invokespecial #59                 // Method "<init>":(Ljava/lang/String;ILorg/springframework/boot/logging/LogLevel$LogMethod;)V
      15: putstatic     #3                  // Field TRACE:Lorg/springframework/boot/logging/LogLevel;
      18: new           #1                  // class org/springframework/boot/logging/LogLevel
      21: dup
      22: ldc           #62                 // String DEBUG
      24: iconst_1
      25: invokedynamic #63,  0             // InvokeDynamic #1:log:()Lorg/springframework/boot/logging/LogLevel$LogMethod;
      30: invokespecial #59                 // Method "<init>":(Ljava/lang/String;ILorg/springframework/boot/logging/LogLevel$LogMethod;)V
      33: putstatic     #7                  // Field DEBUG:Lorg/springframework/boot/logging/LogLevel;
      36: new           #1                  // class org/springframework/boot/logging/LogLevel
      39: dup
      40: ldc           #64                 // String INFO
      42: iconst_2
      43: invokedynamic #65,  0             // InvokeDynamic #2:log:()Lorg/springframework/boot/logging/LogLevel$LogMethod;
      48: invokespecial #59                 // Method "<init>":(Ljava/lang/String;ILorg/springframework/boot/logging/LogLevel$LogMethod;)V
      51: putstatic     #10                 // Field INFO:Lorg/springframework/boot/logging/LogLevel;
      54: new           #1                  // class org/springframework/boot/logging/LogLevel
      57: dup
      58: ldc           #66                 // String WARN
      60: iconst_3
      61: invokedynamic #67,  0             // InvokeDynamic #3:log:()Lorg/springframework/boot/logging/LogLevel$LogMethod;
      66: invokespecial #59                 // Method "<init>":(Ljava/lang/String;ILorg/springframework/boot/logging/LogLevel$LogMethod;)V
      69: putstatic     #13                 // Field WARN:Lorg/springframework/boot/logging/LogLevel;
      72: new           #1                  // class org/springframework/boot/logging/LogLevel
      75: dup
      76: ldc           #68                 // String ERROR
      78: iconst_4
      79: invokedynamic #69,  0             // InvokeDynamic #4:log:()Lorg/springframework/boot/logging/LogLevel$LogMethod;
      84: invokespecial #59                 // Method "<init>":(Ljava/lang/String;ILorg/springframework/boot/logging/LogLevel$LogMethod;)V
      87: putstatic     #16                 // Field ERROR:Lorg/springframework/boot/logging/LogLevel;
      90: new           #1                  // class org/springframework/boot/logging/LogLevel
      93: dup
      94: ldc           #70                 // String FATAL
      96: iconst_5
      97: invokedynamic #71,  0             // InvokeDynamic #5:log:()Lorg/springframework/boot/logging/LogLevel$LogMethod;
     102: invokespecial #59                 // Method "<init>":(Ljava/lang/String;ILorg/springframework/boot/logging/LogLevel$LogMethod;)V
     105: putstatic     #19                 // Field FATAL:Lorg/springframework/boot/logging/LogLevel;
     108: new           #1                  // class org/springframework/boot/logging/LogLevel
     111: dup
     112: ldc           #72                 // String OFF
     114: bipush        6
     116: aconst_null
     117: invokespecial #59                 // Method "<init>":(Ljava/lang/String;ILorg/springframework/boot/logging/LogLevel$LogMethod;)V
     120: putstatic     #22                 // Field OFF:Lorg/springframework/boot/logging/LogLevel;
     123: invokestatic  #73                 // Method $values:()[Lorg/springframework/boot/logging/LogLevel;
     126: putstatic     #25                 // Field $VALUES:[Lorg/springframework/boot/logging/LogLevel;
     129: return
}
