Compiled from "Compaction.java"
public final class com.google.zxing.pdf417.encoder.Compaction extends java.lang.Enum<com.google.zxing.pdf417.encoder.Compaction> {
  public static final com.google.zxing.pdf417.encoder.Compaction AUTO;

  public static final com.google.zxing.pdf417.encoder.Compaction TEXT;

  public static final com.google.zxing.pdf417.encoder.Compaction BYTE;

  public static final com.google.zxing.pdf417.encoder.Compaction NUMERIC;

  private static final com.google.zxing.pdf417.encoder.Compaction[] $VALUES;

  public static com.google.zxing.pdf417.encoder.Compaction[] values();
    Code:
       0: getstatic     #1                  // Field $VALUES:[Lcom/google/zxing/pdf417/encoder/Compaction;
       3: invokevirtual #2                  // Method "[Lcom/google/zxing/pdf417/encoder/Compaction;".clone:()Ljava/lang/Object;
       6: checkcast     #3                  // class "[Lcom/google/zxing/pdf417/encoder/Compaction;"
       9: areturn

  public static com.google.zxing.pdf417.encoder.Compaction valueOf(java.lang.String);
    Code:
       0: ldc           #4                  // class com/google/zxing/pdf417/encoder/Compaction
       2: aload_0
       3: invokestatic  #5                  // Method java/lang/Enum.valueOf:(Ljava/lang/Class;Ljava/lang/String;)Ljava/lang/Enum;
       6: checkcast     #4                  // class com/google/zxing/pdf417/encoder/Compaction
       9: areturn

  private com.google.zxing.pdf417.encoder.Compaction();
    Code:
       0: aload_0
       1: aload_1
       2: iload_2
       3: invokespecial #6                  // Method java/lang/Enum."<init>":(Ljava/lang/String;I)V
       6: return

  static {};
    Code:
       0: new           #4                  // class com/google/zxing/pdf417/encoder/Compaction
       3: dup
       4: ldc           #7                  // String AUTO
       6: iconst_0
       7: invokespecial #8                  // Method "<init>":(Ljava/lang/String;I)V
      10: putstatic     #9                  // Field AUTO:Lcom/google/zxing/pdf417/encoder/Compaction;
      13: new           #4                  // class com/google/zxing/pdf417/encoder/Compaction
      16: dup
      17: ldc           #10                 // String TEXT
      19: iconst_1
      20: invokespecial #8                  // Method "<init>":(Ljava/lang/String;I)V
      23: putstatic     #11                 // Field TEXT:Lcom/google/zxing/pdf417/encoder/Compaction;
      26: new           #4                  // class com/google/zxing/pdf417/encoder/Compaction
      29: dup
      30: ldc           #12                 // String BYTE
      32: iconst_2
      33: invokespecial #8                  // Method "<init>":(Ljava/lang/String;I)V
      36: putstatic     #13                 // Field BYTE:Lcom/google/zxing/pdf417/encoder/Compaction;
      39: new           #4                  // class com/google/zxing/pdf417/encoder/Compaction
      42: dup
      43: ldc           #14                 // String NUMERIC
      45: iconst_3
      46: invokespecial #8                  // Method "<init>":(Ljava/lang/String;I)V
      49: putstatic     #15                 // Field NUMERIC:Lcom/google/zxing/pdf417/encoder/Compaction;
      52: iconst_4
      53: anewarray     #4                  // class com/google/zxing/pdf417/encoder/Compaction
      56: dup
      57: iconst_0
      58: getstatic     #9                  // Field AUTO:Lcom/google/zxing/pdf417/encoder/Compaction;
      61: aastore
      62: dup
      63: iconst_1
      64: getstatic     #11                 // Field TEXT:Lcom/google/zxing/pdf417/encoder/Compaction;
      67: aastore
      68: dup
      69: iconst_2
      70: getstatic     #13                 // Field BYTE:Lcom/google/zxing/pdf417/encoder/Compaction;
      73: aastore
      74: dup
      75: iconst_3
      76: getstatic     #15                 // Field NUMERIC:Lcom/google/zxing/pdf417/encoder/Compaction;
      79: aastore
      80: putstatic     #1                  // Field $VALUES:[Lcom/google/zxing/pdf417/encoder/Compaction;
      83: return
}
