Compiled from "Dimensions.java"
public final class com.google.zxing.pdf417.encoder.Dimensions {
  private final int minCols;

  private final int maxCols;

  private final int minRows;

  private final int maxRows;

  public com.google.zxing.pdf417.encoder.Dimensions(int, int, int, int);
    Code:
       0: aload_0
       1: invokespecial #1                  // Method java/lang/Object."<init>":()V
       4: aload_0
       5: iload_1
       6: putfield      #2                  // Field minCols:I
       9: aload_0
      10: iload_2
      11: putfield      #3                  // Field maxCols:I
      14: aload_0
      15: iload_3
      16: putfield      #4                  // Field minRows:I
      19: aload_0
      20: iload         4
      22: putfield      #5                  // Field maxRows:I
      25: return

  public int getMinCols();
    Code:
       0: aload_0
       1: getfield      #2                  // Field minCols:I
       4: ireturn

  public int getMaxCols();
    Code:
       0: aload_0
       1: getfield      #3                  // Field maxCols:I
       4: ireturn

  public int getMinRows();
    Code:
       0: aload_0
       1: getfield      #4                  // Field minRows:I
       4: ireturn

  public int getMaxRows();
    Code:
       0: aload_0
       1: getfield      #5                  // Field maxRows:I
       4: ireturn
}
