Compiled from "PDF417HighLevelEncoder.java"
final class com.google.zxing.pdf417.encoder.PDF417HighLevelEncoder$NoECIInput implements com.google.zxing.common.ECIInput {
  java.lang.String input;

  private com.google.zxing.pdf417.encoder.PDF417HighLevelEncoder$NoECIInput(java.lang.String);
    Code:
       0: aload_0
       1: invokespecial #2                  // Method java/lang/Object."<init>":()V
       4: aload_0
       5: aload_1
       6: putfield      #3                  // Field input:Ljava/lang/String;
       9: return

  public int length();
    Code:
       0: aload_0
       1: getfield      #3                  // Field input:Ljava/lang/String;
       4: invokevirtual #4                  // Method java/lang/String.length:()I
       7: ireturn

  public char charAt(int);
    Code:
       0: aload_0
       1: getfield      #3                  // Field input:Ljava/lang/String;
       4: iload_1
       5: invokevirtual #5                  // Method java/lang/String.charAt:(I)C
       8: ireturn

  public boolean isECI(int);
    Code:
       0: iconst_0
       1: ireturn

  public int getECIValue(int);
    Code:
       0: iconst_m1
       1: ireturn

  public boolean haveNCharacters(int, int);
    Code:
       0: iload_1
       1: iload_2
       2: iadd
       3: aload_0
       4: getfield      #3                  // Field input:Ljava/lang/String;
       7: invokevirtual #4                  // Method java/lang/String.length:()I
      10: if_icmpgt     17
      13: iconst_1
      14: goto          18
      17: iconst_0
      18: ireturn

  public java.lang.CharSequence subSequence(int, int);
    Code:
       0: aload_0
       1: getfield      #3                  // Field input:Ljava/lang/String;
       4: iload_1
       5: iload_2
       6: invokevirtual #6                  // Method java/lang/String.subSequence:(II)Ljava/lang/CharSequence;
       9: areturn

  public java.lang.String toString();
    Code:
       0: aload_0
       1: getfield      #3                  // Field input:Ljava/lang/String;
       4: areturn

  com.google.zxing.pdf417.encoder.PDF417HighLevelEncoder$NoECIInput(java.lang.String, com.google.zxing.pdf417.encoder.PDF417HighLevelEncoder$1);
    Code:
       0: aload_0
       1: aload_1
       2: invokespecial #1                  // Method "<init>":(Ljava/lang/String;)V
       5: return
}
