Compiled from "PDF417HighLevelEncoderTestAdapter.java"
public final class com.google.zxing.pdf417.encoder.PDF417HighLevelEncoderTestAdapter {
  private com.google.zxing.pdf417.encoder.PDF417HighLevelEncoderTestAdapter();
    Code:
       0: aload_0
       1: invokespecial #1                  // Method java/lang/Object."<init>":()V
       4: return

  public static java.lang.String encodeHighLevel(java.lang.String, com.google.zxing.pdf417.encoder.Compaction, java.nio.charset.Charset, boolean) throws com.google.zxing.WriterException;
    Code:
       0: aload_0
       1: aload_1
       2: aload_2
       3: iload_3
       4: invokestatic  #2                  // Method com/google/zxing/pdf417/encoder/PDF417HighLevelEncoder.encodeHighLevel:(Ljava/lang/String;Lcom/google/zxing/pdf417/encoder/Compaction;Ljava/nio/charset/Charset;Z)Ljava/lang/String;
       7: areturn
}
