Compiled from "PDF417HighLevelEncoder.java"
class com.google.zxing.pdf417.encoder.PDF417HighLevelEncoder$1 {
  static final int[] $SwitchMap$com$google$zxing$pdf417$encoder$Compaction;

  static {};
    Code:
       0: invokestatic  #1                  // Method com/google/zxing/pdf417/encoder/Compaction.values:()[Lcom/google/zxing/pdf417/encoder/Compaction;
       3: arraylength
       4: newarray       int
       6: putstatic     #2                  // Field $SwitchMap$com$google$zxing$pdf417$encoder$Compaction:[I
       9: getstatic     #2                  // Field $SwitchMap$com$google$zxing$pdf417$encoder$Compaction:[I
      12: getstatic     #3                  // Field com/google/zxing/pdf417/encoder/Compaction.TEXT:Lcom/google/zxing/pdf417/encoder/Compaction;
      15: invokevirtual #4                  // Method com/google/zxing/pdf417/encoder/Compaction.ordinal:()I
      18: iconst_1
      19: iastore
      20: goto          24
      23: astore_0
      24: getstatic     #2                  // Field $SwitchMap$com$google$zxing$pdf417$encoder$Compaction:[I
      27: getstatic     #6                  // Field com/google/zxing/pdf417/encoder/Compaction.BYTE:Lcom/google/zxing/pdf417/encoder/Compaction;
      30: invokevirtual #4                  // Method com/google/zxing/pdf417/encoder/Compaction.ordinal:()I
      33: iconst_2
      34: iastore
      35: goto          39
      38: astore_0
      39: getstatic     #2                  // Field $SwitchMap$com$google$zxing$pdf417$encoder$Compaction:[I
      42: getstatic     #7                  // Field com/google/zxing/pdf417/encoder/Compaction.NUMERIC:Lcom/google/zxing/pdf417/encoder/Compaction;
      45: invokevirtual #4                  // Method com/google/zxing/pdf417/encoder/Compaction.ordinal:()I
      48: iconst_3
      49: iastore
      50: goto          54
      53: astore_0
      54: return
    Exception table:
       from    to  target type
           9    20    23   Class java/lang/NoSuchFieldError
          24    35    38   Class java/lang/NoSuchFieldError
          39    50    53   Class java/lang/NoSuchFieldError
}
