Compiled from "ConfigTreePropertySource.java"
public class org.springframework.boot.env.ConfigTreePropertySource extends org.springframework.core.env.EnumerablePropertySource<java.nio.file.Path> implements org.springframework.boot.origin.OriginLookup<java.lang.String> {
  private static final int MAX_DEPTH;

  private final java.util.Map<java.lang.String, org.springframework.boot.env.ConfigTreePropertySource$PropertyFile> propertyFiles;

  private final java.lang.String[] names;

  private final java.util.Set<org.springframework.boot.env.ConfigTreePropertySource$Option> options;

  public org.springframework.boot.env.ConfigTreePropertySource(java.lang.String, java.nio.file.Path);
    Code:
       0: aload_0
       1: aload_1
       2: aload_2
       3: ldc           #1                  // class org/springframework/boot/env/ConfigTreePropertySource$Option
       5: invokestatic  #3                  // Method java/util/EnumSet.noneOf:(Ljava/lang/Class;)Ljava/util/EnumSet;
       8: invokespecial #9                  // Method "<init>":(Ljava/lang/String;Ljava/nio/file/Path;Ljava/util/Set;)V
      11: return

  public org.springframework.boot.env.ConfigTreePropertySource(java.lang.String, java.nio.file.Path, org.springframework.boot.env.ConfigTreePropertySource$Option...);
    Code:
       0: aload_0
       1: aload_1
       2: aload_2
       3: aload_3
       4: invokestatic  #15                 // Method java/util/Arrays.asList:([Ljava/lang/Object;)Ljava/util/List;
       7: invokestatic  #21                 // Method java/util/EnumSet.copyOf:(Ljava/util/Collection;)Ljava/util/EnumSet;
      10: invokespecial #9                  // Method "<init>":(Ljava/lang/String;Ljava/nio/file/Path;Ljava/util/Set;)V
      13: return

  private org.springframework.boot.env.ConfigTreePropertySource(java.lang.String, java.nio.file.Path, java.util.Set<org.springframework.boot.env.ConfigTreePropertySource$Option>);
    Code:
       0: aload_0
       1: aload_1
       2: aload_2
       3: invokespecial #25                 // Method org/springframework/core/env/EnumerablePropertySource."<init>":(Ljava/lang/String;Ljava/lang/Object;)V
       6: aload_2
       7: iconst_0
       8: anewarray     #30                 // class java/nio/file/LinkOption
      11: invokestatic  #32                 // Method java/nio/file/Files.exists:(Ljava/nio/file/Path;[Ljava/nio/file/LinkOption;)Z
      14: aload_2
      15: invokedynamic #38,  0             // InvokeDynamic #0:get:(Ljava/nio/file/Path;)Ljava/util/function/Supplier;
      20: invokestatic  #42                 // Method org/springframework/util/Assert.isTrue:(ZLjava/util/function/Supplier;)V
      23: aload_2
      24: iconst_0
      25: anewarray     #30                 // class java/nio/file/LinkOption
      28: invokestatic  #48                 // Method java/nio/file/Files.isDirectory:(Ljava/nio/file/Path;[Ljava/nio/file/LinkOption;)Z
      31: aload_2
      32: invokedynamic #51,  0             // InvokeDynamic #1:get:(Ljava/nio/file/Path;)Ljava/util/function/Supplier;
      37: invokestatic  #42                 // Method org/springframework/util/Assert.isTrue:(ZLjava/util/function/Supplier;)V
      40: aload_0
      41: aload_2
      42: aload_3
      43: invokestatic  #52                 // Method org/springframework/boot/env/ConfigTreePropertySource$PropertyFile.findAll:(Ljava/nio/file/Path;Ljava/util/Set;)Ljava/util/Map;
      46: putfield      #58                 // Field propertyFiles:Ljava/util/Map;
      49: aload_0
      50: aload_3
      51: putfield      #62                 // Field options:Ljava/util/Set;
      54: aload_0
      55: aload_0
      56: getfield      #58                 // Field propertyFiles:Ljava/util/Map;
      59: invokeinterface #66,  1           // InterfaceMethod java/util/Map.keySet:()Ljava/util/Set;
      64: invokestatic  #72                 // Method org/springframework/util/StringUtils.toStringArray:(Ljava/util/Collection;)[Ljava/lang/String;
      67: putfield      #78                 // Field names:[Ljava/lang/String;
      70: return

  public java.lang.String[] getPropertyNames();
    Code:
       0: aload_0
       1: getfield      #78                 // Field names:[Ljava/lang/String;
       4: invokevirtual #82                 // Method "[Ljava/lang/String;".clone:()Ljava/lang/Object;
       7: checkcast     #83                 // class "[Ljava/lang/String;"
      10: areturn

  public org.springframework.boot.env.ConfigTreePropertySource$Value getProperty(java.lang.String);
    Code:
       0: aload_0
       1: getfield      #58                 // Field propertyFiles:Ljava/util/Map;
       4: aload_1
       5: invokeinterface #87,  2           // InterfaceMethod java/util/Map.get:(Ljava/lang/Object;)Ljava/lang/Object;
      10: checkcast     #53                 // class org/springframework/boot/env/ConfigTreePropertySource$PropertyFile
      13: astore_2
      14: aload_2
      15: ifnull        25
      18: aload_2
      19: invokevirtual #90                 // Method org/springframework/boot/env/ConfigTreePropertySource$PropertyFile.getContent:()Lorg/springframework/boot/env/ConfigTreePropertySource$PropertyFileContent;
      22: goto          26
      25: aconst_null
      26: areturn

  public org.springframework.boot.origin.Origin getOrigin(java.lang.String);
    Code:
       0: aload_0
       1: getfield      #58                 // Field propertyFiles:Ljava/util/Map;
       4: aload_1
       5: invokeinterface #87,  2           // InterfaceMethod java/util/Map.get:(Ljava/lang/Object;)Ljava/lang/Object;
      10: checkcast     #53                 // class org/springframework/boot/env/ConfigTreePropertySource$PropertyFile
      13: astore_2
      14: aload_2
      15: ifnull        25
      18: aload_2
      19: invokevirtual #94                 // Method org/springframework/boot/env/ConfigTreePropertySource$PropertyFile.getOrigin:()Lorg/springframework/boot/origin/Origin;
      22: goto          26
      25: aconst_null
      26: areturn

  public boolean isImmutable();
    Code:
       0: aload_0
       1: getfield      #62                 // Field options:Ljava/util/Set;
       4: getstatic     #98                 // Field org/springframework/boot/env/ConfigTreePropertySource$Option.ALWAYS_READ:Lorg/springframework/boot/env/ConfigTreePropertySource$Option;
       7: invokeinterface #102,  2          // InterfaceMethod java/util/Set.contains:(Ljava/lang/Object;)Z
      12: ifne          19
      15: iconst_1
      16: goto          20
      19: iconst_0
      20: ireturn

  public java.lang.Object getProperty(java.lang.String);
    Code:
       0: aload_0
       1: aload_1
       2: invokevirtual #108                // Method getProperty:(Ljava/lang/String;)Lorg/springframework/boot/env/ConfigTreePropertySource$Value;
       5: areturn

  public org.springframework.boot.origin.Origin getOrigin(java.lang.Object);
    Code:
       0: aload_0
       1: aload_1
       2: checkcast     #112                // class java/lang/String
       5: invokevirtual #114                // Method getOrigin:(Ljava/lang/String;)Lorg/springframework/boot/origin/Origin;
       8: areturn

  private static java.lang.String lambda$new$1(java.nio.file.Path);
    Code:
       0: aload_0
       1: invokedynamic #117,  0            // InvokeDynamic #2:makeConcatWithConstants:(Ljava/nio/file/Path;)Ljava/lang/String;
       6: areturn

  private static java.lang.String lambda$new$0(java.nio.file.Path);
    Code:
       0: aload_0
       1: invokedynamic #121,  0            // InvokeDynamic #3:makeConcatWithConstants:(Ljava/nio/file/Path;)Ljava/lang/String;
       6: areturn
}
