Compiled from "ConfigTreePropertySource.java"
final class org.springframework.boot.env.ConfigTreePropertySource$PropertyFile {
  private static final org.springframework.boot.origin.TextResourceOrigin$Location START_OF_FILE;

  private final java.nio.file.Path path;

  private final org.springframework.core.io.PathResource resource;

  private final org.springframework.boot.origin.Origin origin;

  private final org.springframework.boot.env.ConfigTreePropertySource$PropertyFileContent cachedContent;

  private final boolean autoTrimTrailingNewLine;

  private org.springframework.boot.env.ConfigTreePropertySource$PropertyFile(java.nio.file.Path, java.util.Set<org.springframework.boot.env.ConfigTreePropertySource$Option>);
    Code:
       0: aload_0
       1: invokespecial #3                  // Method java/lang/Object."<init>":()V
       4: aload_0
       5: aload_1
       6: putfield      #9                  // Field path:Ljava/nio/file/Path;
       9: aload_0
      10: new           #15                 // class org/springframework/core/io/PathResource
      13: dup
      14: aload_1
      15: invokespecial #17                 // Method org/springframework/core/io/PathResource."<init>":(Ljava/nio/file/Path;)V
      18: putfield      #20                 // Field resource:Lorg/springframework/core/io/PathResource;
      21: aload_0
      22: new           #24                 // class org/springframework/boot/origin/TextResourceOrigin
      25: dup
      26: aload_0
      27: getfield      #20                 // Field resource:Lorg/springframework/core/io/PathResource;
      30: getstatic     #26                 // Field START_OF_FILE:Lorg/springframework/boot/origin/TextResourceOrigin$Location;
      33: invokespecial #30                 // Method org/springframework/boot/origin/TextResourceOrigin."<init>":(Lorg/springframework/core/io/Resource;Lorg/springframework/boot/origin/TextResourceOrigin$Location;)V
      36: putfield      #33                 // Field origin:Lorg/springframework/boot/origin/Origin;
      39: aload_0
      40: aload_2
      41: getstatic     #37                 // Field org/springframework/boot/env/ConfigTreePropertySource$Option.AUTO_TRIM_TRAILING_NEW_LINE:Lorg/springframework/boot/env/ConfigTreePropertySource$Option;
      44: invokeinterface #43,  2           // InterfaceMethod java/util/Set.contains:(Ljava/lang/Object;)Z
      49: putfield      #49                 // Field autoTrimTrailingNewLine:Z
      52: aload_0
      53: aload_2
      54: getstatic     #53                 // Field org/springframework/boot/env/ConfigTreePropertySource$Option.ALWAYS_READ:Lorg/springframework/boot/env/ConfigTreePropertySource$Option;
      57: invokeinterface #43,  2           // InterfaceMethod java/util/Set.contains:(Ljava/lang/Object;)Z
      62: ifeq          69
      65: aconst_null
      66: goto          90
      69: new           #56                 // class org/springframework/boot/env/ConfigTreePropertySource$PropertyFileContent
      72: dup
      73: aload_1
      74: aload_0
      75: getfield      #20                 // Field resource:Lorg/springframework/core/io/PathResource;
      78: aload_0
      79: getfield      #33                 // Field origin:Lorg/springframework/boot/origin/Origin;
      82: iconst_1
      83: aload_0
      84: getfield      #49                 // Field autoTrimTrailingNewLine:Z
      87: invokespecial #58                 // Method org/springframework/boot/env/ConfigTreePropertySource$PropertyFileContent."<init>":(Ljava/nio/file/Path;Lorg/springframework/core/io/Resource;Lorg/springframework/boot/origin/Origin;ZZ)V
      90: putfield      #61                 // Field cachedContent:Lorg/springframework/boot/env/ConfigTreePropertySource$PropertyFileContent;
      93: return

  org.springframework.boot.env.ConfigTreePropertySource$PropertyFileContent getContent();
    Code:
       0: aload_0
       1: getfield      #61                 // Field cachedContent:Lorg/springframework/boot/env/ConfigTreePropertySource$PropertyFileContent;
       4: ifnull        12
       7: aload_0
       8: getfield      #61                 // Field cachedContent:Lorg/springframework/boot/env/ConfigTreePropertySource$PropertyFileContent;
      11: areturn
      12: new           #56                 // class org/springframework/boot/env/ConfigTreePropertySource$PropertyFileContent
      15: dup
      16: aload_0
      17: getfield      #9                  // Field path:Ljava/nio/file/Path;
      20: aload_0
      21: getfield      #20                 // Field resource:Lorg/springframework/core/io/PathResource;
      24: aload_0
      25: getfield      #33                 // Field origin:Lorg/springframework/boot/origin/Origin;
      28: iconst_0
      29: aload_0
      30: getfield      #49                 // Field autoTrimTrailingNewLine:Z
      33: invokespecial #58                 // Method org/springframework/boot/env/ConfigTreePropertySource$PropertyFileContent."<init>":(Ljava/nio/file/Path;Lorg/springframework/core/io/Resource;Lorg/springframework/boot/origin/Origin;ZZ)V
      36: areturn

  org.springframework.boot.origin.Origin getOrigin();
    Code:
       0: aload_0
       1: getfield      #33                 // Field origin:Lorg/springframework/boot/origin/Origin;
       4: areturn

  static java.util.Map<java.lang.String, org.springframework.boot.env.ConfigTreePropertySource$PropertyFile> findAll(java.nio.file.Path, java.util.Set<org.springframework.boot.env.ConfigTreePropertySource$Option>);
    Code:
       0: new           #65                 // class java/util/TreeMap
       3: dup
       4: invokespecial #67                 // Method java/util/TreeMap."<init>":()V
       7: astore_2
       8: aload_0
       9: bipush        100
      11: invokedynamic #68,  0             // InvokeDynamic #0:test:()Ljava/util/function/BiPredicate;
      16: iconst_1
      17: anewarray     #72                 // class java/nio/file/FileVisitOption
      20: dup
      21: iconst_0
      22: getstatic     #74                 // Field java/nio/file/FileVisitOption.FOLLOW_LINKS:Ljava/nio/file/FileVisitOption;
      25: aastore
      26: invokestatic  #78                 // Method java/nio/file/Files.find:(Ljava/nio/file/Path;ILjava/util/function/BiPredicate;[Ljava/nio/file/FileVisitOption;)Ljava/util/stream/Stream;
      29: astore_3
      30: aload_3
      31: aload_0
      32: aload_1
      33: aload_2
      34: invokedynamic #84,  0             // InvokeDynamic #1:accept:(Ljava/nio/file/Path;Ljava/util/Set;Ljava/util/Map;)Ljava/util/function/Consumer;
      39: invokeinterface #88,  2           // InterfaceMethod java/util/stream/Stream.forEach:(Ljava/util/function/Consumer;)V
      44: aload_3
      45: ifnull        84
      48: aload_3
      49: invokeinterface #94,  1           // InterfaceMethod java/util/stream/Stream.close:()V
      54: goto          84
      57: astore        4
      59: aload_3
      60: ifnull        81
      63: aload_3
      64: invokeinterface #94,  1           // InterfaceMethod java/util/stream/Stream.close:()V
      69: goto          81
      72: astore        5
      74: aload         4
      76: aload         5
      78: invokevirtual #99                 // Method java/lang/Throwable.addSuppressed:(Ljava/lang/Throwable;)V
      81: aload         4
      83: athrow
      84: aload_2
      85: invokestatic  #103                // Method java/util/Collections.unmodifiableMap:(Ljava/util/Map;)Ljava/util/Map;
      88: areturn
      89: astore_2
      90: new           #111                // class java/lang/IllegalStateException
      93: dup
      94: aload_0
      95: invokedynamic #113,  0            // InvokeDynamic #2:makeConcatWithConstants:(Ljava/nio/file/Path;)Ljava/lang/String;
     100: aload_2
     101: invokespecial #117                // Method java/lang/IllegalStateException."<init>":(Ljava/lang/String;Ljava/lang/Throwable;)V
     104: athrow
    Exception table:
       from    to  target type
          30    44    57   Class java/lang/Throwable
          63    69    72   Class java/lang/Throwable
           0    88    89   Class java/io/IOException

  private static boolean isPropertyFile(java.nio.file.Path, java.nio.file.attribute.BasicFileAttributes);
    Code:
       0: aload_0
       1: invokestatic  #120                // Method hasHiddenPathElement:(Ljava/nio/file/Path;)Z
       4: ifne          29
       7: aload_1
       8: invokeinterface #124,  1          // InterfaceMethod java/nio/file/attribute/BasicFileAttributes.isRegularFile:()Z
      13: ifne          25
      16: aload_1
      17: invokeinterface #130,  1          // InterfaceMethod java/nio/file/attribute/BasicFileAttributes.isSymbolicLink:()Z
      22: ifeq          29
      25: iconst_1
      26: goto          30
      29: iconst_0
      30: ireturn

  private static boolean hasHiddenPathElement(java.nio.file.Path);
    Code:
       0: aload_0
       1: invokeinterface #133,  1          // InterfaceMethod java/nio/file/Path.iterator:()Ljava/util/Iterator;
       6: astore_1
       7: aload_1
       8: invokeinterface #139,  1          // InterfaceMethod java/util/Iterator.hasNext:()Z
      13: ifeq          45
      16: aload_1
      17: invokeinterface #144,  1          // InterfaceMethod java/util/Iterator.next:()Ljava/lang/Object;
      22: checkcast     #134                // class java/nio/file/Path
      25: astore_2
      26: aload_2
      27: invokeinterface #148,  1          // InterfaceMethod java/nio/file/Path.toString:()Ljava/lang/String;
      32: ldc           #152                // String ..
      34: invokevirtual #154                // Method java/lang/String.startsWith:(Ljava/lang/String;)Z
      37: ifeq          42
      40: iconst_1
      41: ireturn
      42: goto          7
      45: iconst_0
      46: ireturn

  private static java.lang.String getName(java.nio.file.Path);
    Code:
       0: aload_0
       1: invokeinterface #160,  1          // InterfaceMethod java/nio/file/Path.getNameCount:()I
       6: istore_1
       7: iload_1
       8: iconst_1
       9: if_icmpne     19
      12: aload_0
      13: invokeinterface #148,  1          // InterfaceMethod java/nio/file/Path.toString:()Ljava/lang/String;
      18: areturn
      19: new           #164                // class java/lang/StringBuilder
      22: dup
      23: invokespecial #166                // Method java/lang/StringBuilder."<init>":()V
      26: astore_2
      27: iconst_0
      28: istore_3
      29: iload_3
      30: iload_1
      31: if_icmpge     68
      34: aload_2
      35: iload_3
      36: ifeq          44
      39: ldc           #167                // String .
      41: goto          46
      44: ldc           #169                // String
      46: invokevirtual #171                // Method java/lang/StringBuilder.append:(Ljava/lang/String;)Ljava/lang/StringBuilder;
      49: pop
      50: aload_2
      51: aload_0
      52: iload_3
      53: invokeinterface #175,  2          // InterfaceMethod java/nio/file/Path.getName:(I)Ljava/nio/file/Path;
      58: invokevirtual #179                // Method java/lang/StringBuilder.append:(Ljava/lang/Object;)Ljava/lang/StringBuilder;
      61: pop
      62: iinc          3, 1
      65: goto          29
      68: aload_2
      69: invokevirtual #182                // Method java/lang/StringBuilder.toString:()Ljava/lang/String;
      72: areturn

  private static void lambda$findAll$0(java.nio.file.Path, java.util.Set, java.util.Map, java.nio.file.Path);
    Code:
       0: aload_0
       1: aload_3
       2: invokeinterface #183,  2          // InterfaceMethod java/nio/file/Path.relativize:(Ljava/nio/file/Path;)Ljava/nio/file/Path;
       7: invokestatic  #187                // Method getName:(Ljava/nio/file/Path;)Ljava/lang/String;
      10: astore        4
      12: aload         4
      14: invokestatic  #189                // Method org/springframework/util/StringUtils.hasText:(Ljava/lang/String;)Z
      17: ifeq          57
      20: aload_1
      21: getstatic     #194                // Field org/springframework/boot/env/ConfigTreePropertySource$Option.USE_LOWERCASE_NAMES:Lorg/springframework/boot/env/ConfigTreePropertySource$Option;
      24: invokeinterface #43,  2           // InterfaceMethod java/util/Set.contains:(Ljava/lang/Object;)Z
      29: ifeq          39
      32: aload         4
      34: invokevirtual #197                // Method java/lang/String.toLowerCase:()Ljava/lang/String;
      37: astore        4
      39: aload_2
      40: aload         4
      42: new           #10                 // class org/springframework/boot/env/ConfigTreePropertySource$PropertyFile
      45: dup
      46: aload_3
      47: aload_1
      48: invokespecial #200                // Method "<init>":(Ljava/nio/file/Path;Ljava/util/Set;)V
      51: invokeinterface #203,  3          // InterfaceMethod java/util/Map.put:(Ljava/lang/Object;Ljava/lang/Object;)Ljava/lang/Object;
      56: pop
      57: return

  static {};
    Code:
       0: new           #209                // class org/springframework/boot/origin/TextResourceOrigin$Location
       3: dup
       4: iconst_0
       5: iconst_0
       6: invokespecial #211                // Method org/springframework/boot/origin/TextResourceOrigin$Location."<init>":(II)V
       9: putstatic     #26                 // Field START_OF_FILE:Lorg/springframework/boot/origin/TextResourceOrigin$Location;
      12: return
}
