Compiled from "ConfigTreePropertySource.java"
final class org.springframework.boot.env.ConfigTreePropertySource$PropertyFileContent implements org.springframework.boot.env.ConfigTreePropertySource$Value,org.springframework.boot.origin.OriginProvider {
  private final java.nio.file.Path path;

  private final org.springframework.core.io.Resource resource;

  private final org.springframework.boot.origin.Origin origin;

  private final boolean cacheContent;

  private final boolean autoTrimTrailingNewLine;

  private volatile byte[] content;

  private org.springframework.boot.env.ConfigTreePropertySource$PropertyFileContent(java.nio.file.Path, org.springframework.core.io.Resource, org.springframework.boot.origin.Origin, boolean, boolean);
    Code:
       0: aload_0
       1: invokespecial #1                  // Method java/lang/Object."<init>":()V
       4: aload_0
       5: aload_1
       6: putfield      #7                  // Field path:Ljava/nio/file/Path;
       9: aload_0
      10: aload_2
      11: putfield      #13                 // Field resource:Lorg/springframework/core/io/Resource;
      14: aload_0
      15: aload_3
      16: putfield      #17                 // Field origin:Lorg/springframework/boot/origin/Origin;
      19: aload_0
      20: iload         4
      22: putfield      #21                 // Field cacheContent:Z
      25: aload_0
      26: iload         5
      28: putfield      #25                 // Field autoTrimTrailingNewLine:Z
      31: return

  public org.springframework.boot.origin.Origin getOrigin();
    Code:
       0: aload_0
       1: getfield      #17                 // Field origin:Lorg/springframework/boot/origin/Origin;
       4: areturn

  public int length();
    Code:
       0: aload_0
       1: invokevirtual #28                 // Method toString:()Ljava/lang/String;
       4: invokevirtual #32                 // Method java/lang/String.length:()I
       7: ireturn

  public char charAt(int);
    Code:
       0: aload_0
       1: invokevirtual #28                 // Method toString:()Ljava/lang/String;
       4: iload_1
       5: invokevirtual #38                 // Method java/lang/String.charAt:(I)C
       8: ireturn

  public java.lang.CharSequence subSequence(int, int);
    Code:
       0: aload_0
       1: invokevirtual #28                 // Method toString:()Ljava/lang/String;
       4: iload_1
       5: iload_2
       6: invokevirtual #42                 // Method java/lang/String.subSequence:(II)Ljava/lang/CharSequence;
       9: areturn

  public java.lang.String toString();
    Code:
       0: new           #33                 // class java/lang/String
       3: dup
       4: aload_0
       5: invokevirtual #46                 // Method getBytes:()[B
       8: invokespecial #50                 // Method java/lang/String."<init>":([B)V
      11: astore_1
      12: aload_0
      13: getfield      #25                 // Field autoTrimTrailingNewLine:Z
      16: ifeq          25
      19: aload_0
      20: aload_1
      21: invokevirtual #53                 // Method autoTrimTrailingNewLine:(Ljava/lang/String;)Ljava/lang/String;
      24: astore_1
      25: aload_1
      26: areturn

  private java.lang.String autoTrimTrailingNewLine(java.lang.String);
    Code:
       0: aload_1
       1: ldc           #56                 // String \n
       3: invokevirtual #58                 // Method java/lang/String.endsWith:(Ljava/lang/String;)Z
       6: ifne          11
       9: aload_1
      10: areturn
      11: iconst_0
      12: istore_2
      13: iconst_0
      14: istore_3
      15: iload_3
      16: aload_1
      17: invokevirtual #32                 // Method java/lang/String.length:()I
      20: if_icmpge     46
      23: aload_1
      24: iload_3
      25: invokevirtual #38                 // Method java/lang/String.charAt:(I)C
      28: istore        4
      30: iload         4
      32: bipush        10
      34: if_icmpne     40
      37: iinc          2, 1
      40: iinc          3, 1
      43: goto          15
      46: iload_2
      47: iconst_1
      48: if_icmple     53
      51: aload_1
      52: areturn
      53: aload_1
      54: ldc           #62                 // String \r\n
      56: invokevirtual #58                 // Method java/lang/String.endsWith:(Ljava/lang/String;)Z
      59: ifeq          76
      62: aload_1
      63: iconst_0
      64: aload_1
      65: invokevirtual #32                 // Method java/lang/String.length:()I
      68: iconst_2
      69: isub
      70: invokevirtual #64                 // Method java/lang/String.substring:(II)Ljava/lang/String;
      73: goto          87
      76: aload_1
      77: iconst_0
      78: aload_1
      79: invokevirtual #32                 // Method java/lang/String.length:()I
      82: iconst_1
      83: isub
      84: invokevirtual #64                 // Method java/lang/String.substring:(II)Ljava/lang/String;
      87: areturn

  public java.io.InputStream getInputStream() throws java.io.IOException;
    Code:
       0: aload_0
       1: getfield      #21                 // Field cacheContent:Z
       4: ifne          21
       7: aload_0
       8: invokevirtual #68                 // Method assertStillExists:()V
      11: aload_0
      12: getfield      #13                 // Field resource:Lorg/springframework/core/io/Resource;
      15: invokeinterface #71,  1           // InterfaceMethod org/springframework/core/io/Resource.getInputStream:()Ljava/io/InputStream;
      20: areturn
      21: new           #77                 // class java/io/ByteArrayInputStream
      24: dup
      25: aload_0
      26: invokevirtual #46                 // Method getBytes:()[B
      29: invokespecial #79                 // Method java/io/ByteArrayInputStream."<init>":([B)V
      32: areturn

  private byte[] getBytes();
    Code:
       0: aload_0
       1: getfield      #21                 // Field cacheContent:Z
       4: ifne          24
       7: aload_0
       8: invokevirtual #68                 // Method assertStillExists:()V
      11: aload_0
      12: getfield      #13                 // Field resource:Lorg/springframework/core/io/Resource;
      15: invokeinterface #71,  1           // InterfaceMethod org/springframework/core/io/Resource.getInputStream:()Ljava/io/InputStream;
      20: invokestatic  #80                 // Method org/springframework/util/FileCopyUtils.copyToByteArray:(Ljava/io/InputStream;)[B
      23: areturn
      24: aload_0
      25: getfield      #86                 // Field content:[B
      28: ifnonnull     75
      31: aload_0
      32: invokevirtual #68                 // Method assertStillExists:()V
      35: aload_0
      36: getfield      #13                 // Field resource:Lorg/springframework/core/io/Resource;
      39: dup
      40: astore_1
      41: monitorenter
      42: aload_0
      43: getfield      #86                 // Field content:[B
      46: ifnonnull     65
      49: aload_0
      50: aload_0
      51: getfield      #13                 // Field resource:Lorg/springframework/core/io/Resource;
      54: invokeinterface #71,  1           // InterfaceMethod org/springframework/core/io/Resource.getInputStream:()Ljava/io/InputStream;
      59: invokestatic  #80                 // Method org/springframework/util/FileCopyUtils.copyToByteArray:(Ljava/io/InputStream;)[B
      62: putfield      #86                 // Field content:[B
      65: aload_1
      66: monitorexit
      67: goto          75
      70: astore_2
      71: aload_1
      72: monitorexit
      73: aload_2
      74: athrow
      75: aload_0
      76: getfield      #86                 // Field content:[B
      79: areturn
      80: astore_1
      81: new           #92                 // class java/lang/IllegalStateException
      84: dup
      85: aload_1
      86: invokespecial #94                 // Method java/lang/IllegalStateException."<init>":(Ljava/lang/Throwable;)V
      89: athrow
    Exception table:
       from    to  target type
          42    67    70   any
          70    73    70   any
           0    23    80   Class java/io/IOException
          24    79    80   Class java/io/IOException

  private void assertStillExists();
    Code:
       0: aload_0
       1: getfield      #7                  // Field path:Ljava/nio/file/Path;
       4: iconst_0
       5: anewarray     #97                 // class java/nio/file/LinkOption
       8: invokestatic  #99                 // Method java/nio/file/Files.exists:(Ljava/nio/file/Path;[Ljava/nio/file/LinkOption;)Z
      11: aload_0
      12: invokedynamic #105,  0            // InvokeDynamic #0:get:(Lorg/springframework/boot/env/ConfigTreePropertySource$PropertyFileContent;)Ljava/util/function/Supplier;
      17: invokestatic  #109                // Method org/springframework/util/Assert.state:(ZLjava/util/function/Supplier;)V
      20: return

  private java.lang.String lambda$assertStillExists$0();
    Code:
       0: aload_0
       1: getfield      #7                  // Field path:Ljava/nio/file/Path;
       4: invokedynamic #115,  0            // InvokeDynamic #1:makeConcatWithConstants:(Ljava/nio/file/Path;)Ljava/lang/String;
       9: areturn
}
