Compiled from "EnvironmentPostProcessorsFactory.java"
public interface org.springframework.boot.env.EnvironmentPostProcessorsFactory {
  public abstract java.util.List<org.springframework.boot.env.EnvironmentPostProcessor> getEnvironmentPostProcessors(org.springframework.boot.logging.DeferredLogFactory, org.springframework.boot.ConfigurableBootstrapContext);

  public static org.springframework.boot.env.EnvironmentPostProcessorsFactory fromSpringFactories(java.lang.ClassLoader);
    Code:
       0: new           #1                  // class org/springframework/boot/env/SpringFactoriesEnvironmentPostProcessorsFactory
       3: dup
       4: aload_0
       5: invokestatic  #3                  // Method org/springframework/core/io/support/SpringFactoriesLoader.forDefaultResourceLocation:(Ljava/lang/ClassLoader;)Lorg/springframework/core/io/support/SpringFactoriesLoader;
       8: invokespecial #9                  // Method org/springframework/boot/env/SpringFactoriesEnvironmentPostProcessorsFactory."<init>":(Lorg/springframework/core/io/support/SpringFactoriesLoader;)V
      11: areturn

  public static org.springframework.boot.env.EnvironmentPostProcessorsFactory of(java.lang.Class<?>...);
    Code:
       0: new           #13                 // class org/springframework/boot/env/ReflectionEnvironmentPostProcessorsFactory
       3: dup
       4: aload_0
       5: invokespecial #15                 // Method org/springframework/boot/env/ReflectionEnvironmentPostProcessorsFactory."<init>":([Ljava/lang/Class;)V
       8: areturn

  public static org.springframework.boot.env.EnvironmentPostProcessorsFactory of(java.lang.String...);
    Code:
       0: aconst_null
       1: aload_0
       2: invokestatic  #18                 // InterfaceMethod of:(Ljava/lang/ClassLoader;[Ljava/lang/String;)Lorg/springframework/boot/env/EnvironmentPostProcessorsFactory;
       5: areturn

  public static org.springframework.boot.env.EnvironmentPostProcessorsFactory of(java.lang.ClassLoader, java.lang.String...);
    Code:
       0: new           #13                 // class org/springframework/boot/env/ReflectionEnvironmentPostProcessorsFactory
       3: dup
       4: aload_0
       5: aload_1
       6: invokespecial #24                 // Method org/springframework/boot/env/ReflectionEnvironmentPostProcessorsFactory."<init>":(Ljava/lang/ClassLoader;[Ljava/lang/String;)V
       9: areturn
}
