Compiled from "EnvironmentPostProcessorApplicationListener.java"
public class org.springframework.boot.env.EnvironmentPostProcessorApplicationListener implements org.springframework.context.event.SmartApplicationListener,org.springframework.core.Ordered {
  public static final int DEFAULT_ORDER;

  private final org.springframework.boot.logging.DeferredLogs deferredLogs;

  private int order;

  private final java.util.function.Function<java.lang.ClassLoader, org.springframework.boot.env.EnvironmentPostProcessorsFactory> postProcessorsFactory;

  public org.springframework.boot.env.EnvironmentPostProcessorApplicationListener();
    Code:
       0: aload_0
       1: invokedynamic #3,  0              // InvokeDynamic #0:apply:()Ljava/util/function/Function;
       6: invokespecial #7                  // Method "<init>":(Ljava/util/function/Function;)V
       9: return

  private org.springframework.boot.env.EnvironmentPostProcessorApplicationListener(java.util.function.Function<java.lang.ClassLoader, org.springframework.boot.env.EnvironmentPostProcessorsFactory>);
    Code:
       0: aload_0
       1: invokespecial #13                 // Method java/lang/Object."<init>":()V
       4: aload_0
       5: ldc           #18                 // int -2147483638
       7: putfield      #19                 // Field order:I
      10: aload_0
      11: aload_1
      12: putfield      #23                 // Field postProcessorsFactory:Ljava/util/function/Function;
      15: aload_0
      16: new           #27                 // class org/springframework/boot/logging/DeferredLogs
      19: dup
      20: invokespecial #29                 // Method org/springframework/boot/logging/DeferredLogs."<init>":()V
      23: putfield      #30                 // Field deferredLogs:Lorg/springframework/boot/logging/DeferredLogs;
      26: return

  public static org.springframework.boot.env.EnvironmentPostProcessorApplicationListener with(org.springframework.boot.env.EnvironmentPostProcessorsFactory);
    Code:
       0: new           #8                  // class org/springframework/boot/env/EnvironmentPostProcessorApplicationListener
       3: dup
       4: aload_0
       5: invokedynamic #34,  0             // InvokeDynamic #1:apply:(Lorg/springframework/boot/env/EnvironmentPostProcessorsFactory;)Ljava/util/function/Function;
      10: invokespecial #7                  // Method "<init>":(Ljava/util/function/Function;)V
      13: areturn

  public boolean supportsEventType(java.lang.Class<? extends org.springframework.context.ApplicationEvent>);
    Code:
       0: ldc           #37                 // class org/springframework/boot/context/event/ApplicationEnvironmentPreparedEvent
       2: aload_1
       3: invokevirtual #39                 // Method java/lang/Class.isAssignableFrom:(Ljava/lang/Class;)Z
       6: ifne          27
       9: ldc           #45                 // class org/springframework/boot/context/event/ApplicationPreparedEvent
      11: aload_1
      12: invokevirtual #39                 // Method java/lang/Class.isAssignableFrom:(Ljava/lang/Class;)Z
      15: ifne          27
      18: ldc           #47                 // class org/springframework/boot/context/event/ApplicationFailedEvent
      20: aload_1
      21: invokevirtual #39                 // Method java/lang/Class.isAssignableFrom:(Ljava/lang/Class;)Z
      24: ifeq          31
      27: iconst_1
      28: goto          32
      31: iconst_0
      32: ireturn

  public void onApplicationEvent(org.springframework.context.ApplicationEvent);
    Code:
       0: aload_1
       1: instanceof    #37                 // class org/springframework/boot/context/event/ApplicationEnvironmentPreparedEvent
       4: ifeq          17
       7: aload_1
       8: checkcast     #37                 // class org/springframework/boot/context/event/ApplicationEnvironmentPreparedEvent
      11: astore_2
      12: aload_0
      13: aload_2
      14: invokevirtual #49                 // Method onApplicationEnvironmentPreparedEvent:(Lorg/springframework/boot/context/event/ApplicationEnvironmentPreparedEvent;)V
      17: aload_1
      18: instanceof    #45                 // class org/springframework/boot/context/event/ApplicationPreparedEvent
      21: ifeq          28
      24: aload_0
      25: invokevirtual #53                 // Method onApplicationPreparedEvent:()V
      28: aload_1
      29: instanceof    #47                 // class org/springframework/boot/context/event/ApplicationFailedEvent
      32: ifeq          39
      35: aload_0
      36: invokevirtual #56                 // Method onApplicationFailedEvent:()V
      39: return

  private void onApplicationEnvironmentPreparedEvent(org.springframework.boot.context.event.ApplicationEnvironmentPreparedEvent);
    Code:
       0: aload_1
       1: invokevirtual #59                 // Method org/springframework/boot/context/event/ApplicationEnvironmentPreparedEvent.getEnvironment:()Lorg/springframework/core/env/ConfigurableEnvironment;
       4: astore_2
       5: aload_1
       6: invokevirtual #63                 // Method org/springframework/boot/context/event/ApplicationEnvironmentPreparedEvent.getSpringApplication:()Lorg/springframework/boot/SpringApplication;
       9: astore_3
      10: aload_0
      11: aload_3
      12: invokevirtual #67                 // Method org/springframework/boot/SpringApplication.getResourceLoader:()Lorg/springframework/core/io/ResourceLoader;
      15: aload_1
      16: invokevirtual #73                 // Method org/springframework/boot/context/event/ApplicationEnvironmentPreparedEvent.getBootstrapContext:()Lorg/springframework/boot/ConfigurableBootstrapContext;
      19: invokevirtual #77                 // Method getEnvironmentPostProcessors:(Lorg/springframework/core/io/ResourceLoader;Lorg/springframework/boot/ConfigurableBootstrapContext;)Ljava/util/List;
      22: invokeinterface #81,  1           // InterfaceMethod java/util/List.iterator:()Ljava/util/Iterator;
      27: astore        4
      29: aload         4
      31: invokeinterface #87,  1           // InterfaceMethod java/util/Iterator.hasNext:()Z
      36: ifeq          63
      39: aload         4
      41: invokeinterface #93,  1           // InterfaceMethod java/util/Iterator.next:()Ljava/lang/Object;
      46: checkcast     #97                 // class org/springframework/boot/env/EnvironmentPostProcessor
      49: astore        5
      51: aload         5
      53: aload_2
      54: aload_3
      55: invokeinterface #99,  3           // InterfaceMethod org/springframework/boot/env/EnvironmentPostProcessor.postProcessEnvironment:(Lorg/springframework/core/env/ConfigurableEnvironment;Lorg/springframework/boot/SpringApplication;)V
      60: goto          29
      63: return

  private void onApplicationPreparedEvent();
    Code:
       0: aload_0
       1: invokevirtual #103                // Method finish:()V
       4: return

  private void onApplicationFailedEvent();
    Code:
       0: aload_0
       1: invokevirtual #103                // Method finish:()V
       4: return

  private void finish();
    Code:
       0: aload_0
       1: getfield      #30                 // Field deferredLogs:Lorg/springframework/boot/logging/DeferredLogs;
       4: invokevirtual #106                // Method org/springframework/boot/logging/DeferredLogs.switchOverAll:()V
       7: return

  java.util.List<org.springframework.boot.env.EnvironmentPostProcessor> getEnvironmentPostProcessors(org.springframework.core.io.ResourceLoader, org.springframework.boot.ConfigurableBootstrapContext);
    Code:
       0: aload_1
       1: ifnull        13
       4: aload_1
       5: invokeinterface #109,  1          // InterfaceMethod org/springframework/core/io/ResourceLoader.getClassLoader:()Ljava/lang/ClassLoader;
      10: goto          14
      13: aconst_null
      14: astore_3
      15: aload_0
      16: getfield      #23                 // Field postProcessorsFactory:Ljava/util/function/Function;
      19: aload_3
      20: invokeinterface #115,  2          // InterfaceMethod java/util/function/Function.apply:(Ljava/lang/Object;)Ljava/lang/Object;
      25: checkcast     #120                // class org/springframework/boot/env/EnvironmentPostProcessorsFactory
      28: astore        4
      30: aload         4
      32: aload_0
      33: getfield      #30                 // Field deferredLogs:Lorg/springframework/boot/logging/DeferredLogs;
      36: aload_2
      37: invokeinterface #122,  3          // InterfaceMethod org/springframework/boot/env/EnvironmentPostProcessorsFactory.getEnvironmentPostProcessors:(Lorg/springframework/boot/logging/DeferredLogFactory;Lorg/springframework/boot/ConfigurableBootstrapContext;)Ljava/util/List;
      42: areturn

  public int getOrder();
    Code:
       0: aload_0
       1: getfield      #19                 // Field order:I
       4: ireturn

  public void setOrder(int);
    Code:
       0: aload_0
       1: iload_1
       2: putfield      #19                 // Field order:I
       5: return

  private static org.springframework.boot.env.EnvironmentPostProcessorsFactory lambda$with$0(org.springframework.boot.env.EnvironmentPostProcessorsFactory, java.lang.ClassLoader);
    Code:
       0: aload_0
       1: areturn
}
