Compiled from "OriginTrackedYamlLoader.java"
class org.springframework.boot.env.OriginTrackedYamlLoader$OriginTrackingConstructor extends org.yaml.snakeyaml.constructor.SafeConstructor {
  final org.springframework.boot.env.OriginTrackedYamlLoader this$0;

  org.springframework.boot.env.OriginTrackedYamlLoader$OriginTrackingConstructor(org.springframework.boot.env.OriginTrackedYamlLoader, org.yaml.snakeyaml.LoaderOptions);
    Code:
       0: aload_0
       1: aload_1
       2: putfield      #1                  // Field this$0:Lorg/springframework/boot/env/OriginTrackedYamlLoader;
       5: aload_0
       6: aload_2
       7: invokespecial #7                  // Method org/yaml/snakeyaml/constructor/SafeConstructor."<init>":(Lorg/yaml/snakeyaml/LoaderOptions;)V
      10: return

  public java.lang.Object getData() throws java.util.NoSuchElementException;
    Code:
       0: aload_0
       1: invokespecial #13                 // Method org/yaml/snakeyaml/constructor/SafeConstructor.getData:()Ljava/lang/Object;
       4: astore_1
       5: aload_1
       6: instanceof    #17                 // class java/lang/CharSequence
       9: ifeq          28
      12: aload_1
      13: checkcast     #17                 // class java/lang/CharSequence
      16: astore_2
      17: aload_2
      18: invokeinterface #19,  1           // InterfaceMethod java/lang/CharSequence.isEmpty:()Z
      23: ifeq          28
      26: aconst_null
      27: areturn
      28: aload_1
      29: areturn

  protected java.lang.Object constructObject(org.yaml.snakeyaml.nodes.Node);
    Code:
       0: aload_1
       1: instanceof    #23                 // class org/yaml/snakeyaml/nodes/CollectionNode
       4: ifeq          33
       7: aload_1
       8: checkcast     #23                 // class org/yaml/snakeyaml/nodes/CollectionNode
      11: invokevirtual #25                 // Method org/yaml/snakeyaml/nodes/CollectionNode.getValue:()Ljava/util/List;
      14: invokeinterface #29,  1           // InterfaceMethod java/util/List.isEmpty:()Z
      19: ifeq          33
      22: aload_0
      23: aload_1
      24: aload_0
      25: aload_1
      26: invokespecial #32                 // Method org/yaml/snakeyaml/constructor/SafeConstructor.constructObject:(Lorg/yaml/snakeyaml/nodes/Node;)Ljava/lang/Object;
      29: invokevirtual #36                 // Method constructTrackedObject:(Lorg/yaml/snakeyaml/nodes/Node;Ljava/lang/Object;)Ljava/lang/Object;
      32: areturn
      33: aload_1
      34: instanceof    #40                 // class org/yaml/snakeyaml/nodes/ScalarNode
      37: ifeq          58
      40: aload_1
      41: instanceof    #42                 // class org/springframework/boot/env/OriginTrackedYamlLoader$KeyScalarNode
      44: ifne          58
      47: aload_0
      48: aload_1
      49: aload_0
      50: aload_1
      51: invokespecial #32                 // Method org/yaml/snakeyaml/constructor/SafeConstructor.constructObject:(Lorg/yaml/snakeyaml/nodes/Node;)Ljava/lang/Object;
      54: invokevirtual #36                 // Method constructTrackedObject:(Lorg/yaml/snakeyaml/nodes/Node;Ljava/lang/Object;)Ljava/lang/Object;
      57: areturn
      58: aload_1
      59: instanceof    #44                 // class org/yaml/snakeyaml/nodes/MappingNode
      62: ifeq          75
      65: aload_1
      66: checkcast     #44                 // class org/yaml/snakeyaml/nodes/MappingNode
      69: astore_2
      70: aload_0
      71: aload_2
      72: invokevirtual #46                 // Method replaceMappingNodeKeys:(Lorg/yaml/snakeyaml/nodes/MappingNode;)V
      75: aload_0
      76: aload_1
      77: invokespecial #32                 // Method org/yaml/snakeyaml/constructor/SafeConstructor.constructObject:(Lorg/yaml/snakeyaml/nodes/Node;)Ljava/lang/Object;
      80: areturn

  private void replaceMappingNodeKeys(org.yaml.snakeyaml.nodes.MappingNode);
    Code:
       0: new           #50                 // class java/util/ArrayList
       3: dup
       4: invokespecial #52                 // Method java/util/ArrayList."<init>":()V
       7: astore_2
       8: aload_1
       9: invokevirtual #55                 // Method org/yaml/snakeyaml/nodes/MappingNode.getValue:()Ljava/util/List;
      12: invokeinterface #56,  1           // InterfaceMethod java/util/List.stream:()Ljava/util/stream/Stream;
      17: invokedynamic #60,  0             // InvokeDynamic #0:apply:()Ljava/util/function/Function;
      22: invokeinterface #64,  2           // InterfaceMethod java/util/stream/Stream.map:(Ljava/util/function/Function;)Ljava/util/stream/Stream;
      27: aload_2
      28: dup
      29: invokestatic  #70                 // Method java/util/Objects.requireNonNull:(Ljava/lang/Object;)Ljava/lang/Object;
      32: pop
      33: invokedynamic #76,  0             // InvokeDynamic #1:accept:(Ljava/util/List;)Ljava/util/function/Consumer;
      38: invokeinterface #80,  2           // InterfaceMethod java/util/stream/Stream.forEach:(Ljava/util/function/Consumer;)V
      43: aload_1
      44: aload_2
      45: invokevirtual #84                 // Method org/yaml/snakeyaml/nodes/MappingNode.setValue:(Ljava/util/List;)V
      48: return

  private java.lang.Object constructTrackedObject(org.yaml.snakeyaml.nodes.Node, java.lang.Object);
    Code:
       0: aload_0
       1: aload_1
       2: invokevirtual #88                 // Method getOrigin:(Lorg/yaml/snakeyaml/nodes/Node;)Lorg/springframework/boot/origin/Origin;
       5: astore_3
       6: aload_0
       7: aload_2
       8: invokevirtual #92                 // Method getValue:(Ljava/lang/Object;)Ljava/lang/Object;
      11: aload_3
      12: invokestatic  #94                 // Method org/springframework/boot/origin/OriginTrackedValue.of:(Ljava/lang/Object;Lorg/springframework/boot/origin/Origin;)Lorg/springframework/boot/origin/OriginTrackedValue;
      15: areturn

  private java.lang.Object getValue(java.lang.Object);
    Code:
       0: aload_1
       1: ifnull        8
       4: aload_1
       5: goto          10
       8: ldc           #100                // String
      10: areturn

  private org.springframework.boot.origin.Origin getOrigin(org.yaml.snakeyaml.nodes.Node);
    Code:
       0: aload_1
       1: invokevirtual #102                // Method org/yaml/snakeyaml/nodes/Node.getStartMark:()Lorg/yaml/snakeyaml/error/Mark;
       4: astore_2
       5: new           #108                // class org/springframework/boot/origin/TextResourceOrigin$Location
       8: dup
       9: aload_2
      10: invokevirtual #110                // Method org/yaml/snakeyaml/error/Mark.getLine:()I
      13: aload_2
      14: invokevirtual #116                // Method org/yaml/snakeyaml/error/Mark.getColumn:()I
      17: invokespecial #119                // Method org/springframework/boot/origin/TextResourceOrigin$Location."<init>":(II)V
      20: astore_3
      21: new           #122                // class org/springframework/boot/origin/TextResourceOrigin
      24: dup
      25: aload_0
      26: getfield      #1                  // Field this$0:Lorg/springframework/boot/env/OriginTrackedYamlLoader;
      29: getfield      #124                // Field org/springframework/boot/env/OriginTrackedYamlLoader.resource:Lorg/springframework/core/io/Resource;
      32: aload_3
      33: invokespecial #130                // Method org/springframework/boot/origin/TextResourceOrigin."<init>":(Lorg/springframework/core/io/Resource;Lorg/springframework/boot/origin/TextResourceOrigin$Location;)V
      36: areturn
}
