Compiled from "OriginTrackedYamlLoader.java"
class org.springframework.boot.env.OriginTrackedYamlLoader$KeyScalarNode extends org.yaml.snakeyaml.nodes.ScalarNode {
  org.springframework.boot.env.OriginTrackedYamlLoader$KeyScalarNode(org.yaml.snakeyaml.nodes.ScalarNode);
    Code:
       0: aload_0
       1: aload_1
       2: invokevirtual #1                  // Method org/yaml/snakeyaml/nodes/ScalarNode.getTag:()Lorg/yaml/snakeyaml/nodes/Tag;
       5: aload_1
       6: invokevirtual #7                  // Method org/yaml/snakeyaml/nodes/ScalarNode.getValue:()Ljava/lang/String;
       9: aload_1
      10: invokevirtual #11                 // Method org/yaml/snakeyaml/nodes/ScalarNode.getStartMark:()Lorg/yaml/snakeyaml/error/Mark;
      13: aload_1
      14: invokevirtual #15                 // Method org/yaml/snakeyaml/nodes/ScalarNode.getEndMark:()Lorg/yaml/snakeyaml/error/Mark;
      17: aload_1
      18: invokevirtual #18                 // Method org/yaml/snakeyaml/nodes/ScalarNode.getScalarStyle:()Lorg/yaml/snakeyaml/DumperOptions$ScalarStyle;
      21: invokespecial #22                 // Method org/yaml/snakeyaml/nodes/ScalarNode."<init>":(Lorg/yaml/snakeyaml/nodes/Tag;Ljava/lang/String;Lorg/yaml/snakeyaml/error/Mark;Lorg/yaml/snakeyaml/error/Mark;Lorg/yaml/snakeyaml/DumperOptions$ScalarStyle;)V
      24: return

  static org.yaml.snakeyaml.nodes.NodeTuple get(org.yaml.snakeyaml.nodes.NodeTuple);
    Code:
       0: aload_0
       1: invokevirtual #26                 // Method org/yaml/snakeyaml/nodes/NodeTuple.getKeyNode:()Lorg/yaml/snakeyaml/nodes/Node;
       4: astore_1
       5: aload_0
       6: invokevirtual #32                 // Method org/yaml/snakeyaml/nodes/NodeTuple.getValueNode:()Lorg/yaml/snakeyaml/nodes/Node;
       9: astore_2
      10: new           #27                 // class org/yaml/snakeyaml/nodes/NodeTuple
      13: dup
      14: aload_1
      15: invokestatic  #35                 // Method get:(Lorg/yaml/snakeyaml/nodes/Node;)Lorg/yaml/snakeyaml/nodes/Node;
      18: aload_2
      19: invokespecial #41                 // Method org/yaml/snakeyaml/nodes/NodeTuple."<init>":(Lorg/yaml/snakeyaml/nodes/Node;Lorg/yaml/snakeyaml/nodes/Node;)V
      22: areturn

  private static org.yaml.snakeyaml.nodes.Node get(org.yaml.snakeyaml.nodes.Node);
    Code:
       0: aload_0
       1: instanceof    #2                  // class org/yaml/snakeyaml/nodes/ScalarNode
       4: ifeq          21
       7: aload_0
       8: checkcast     #2                  // class org/yaml/snakeyaml/nodes/ScalarNode
      11: astore_1
      12: new           #36                 // class org/springframework/boot/env/OriginTrackedYamlLoader$KeyScalarNode
      15: dup
      16: aload_1
      17: invokespecial #44                 // Method "<init>":(Lorg/yaml/snakeyaml/nodes/ScalarNode;)V
      20: areturn
      21: aload_0
      22: areturn
}
