Compiled from "OriginTrackedPropertiesLoader.java"
class org.springframework.boot.env.OriginTrackedPropertiesLoader {
  private final org.springframework.core.io.Resource resource;

  org.springframework.boot.env.OriginTrackedPropertiesLoader(org.springframework.core.io.Resource);
    Code:
       0: aload_0
       1: invokespecial #1                  // Method java/lang/Object."<init>":()V
       4: aload_1
       5: ldc           #7                  // String Resource must not be null
       7: invokestatic  #9                  // Method org/springframework/util/Assert.notNull:(Ljava/lang/Object;Ljava/lang/String;)V
      10: aload_0
      11: aload_1
      12: putfield      #15                 // Field resource:Lorg/springframework/core/io/Resource;
      15: return

  java.util.List<org.springframework.boot.env.OriginTrackedPropertiesLoader$Document> load() throws java.io.IOException;
    Code:
       0: aload_0
       1: iconst_1
       2: invokevirtual #21                 // Method load:(Z)Ljava/util/List;
       5: areturn

  java.util.List<org.springframework.boot.env.OriginTrackedPropertiesLoader$Document> load(boolean) throws java.io.IOException;
    Code:
       0: new           #25                 // class java/util/ArrayList
       3: dup
       4: invokespecial #27                 // Method java/util/ArrayList."<init>":()V
       7: astore_2
       8: new           #28                 // class org/springframework/boot/env/OriginTrackedPropertiesLoader$Document
      11: dup
      12: invokespecial #30                 // Method org/springframework/boot/env/OriginTrackedPropertiesLoader$Document."<init>":()V
      15: astore_3
      16: new           #31                 // class java/lang/StringBuilder
      19: dup
      20: invokespecial #33                 // Method java/lang/StringBuilder."<init>":()V
      23: astore        4
      25: new           #34                 // class org/springframework/boot/env/OriginTrackedPropertiesLoader$CharacterReader
      28: dup
      29: aload_0
      30: getfield      #15                 // Field resource:Lorg/springframework/core/io/Resource;
      33: invokespecial #36                 // Method org/springframework/boot/env/OriginTrackedPropertiesLoader$CharacterReader."<init>":(Lorg/springframework/core/io/Resource;)V
      36: astore        5
      38: aload         5
      40: invokevirtual #39                 // Method org/springframework/boot/env/OriginTrackedPropertiesLoader$CharacterReader.read:()Z
      43: ifeq          164
      46: aload         5
      48: invokevirtual #43                 // Method org/springframework/boot/env/OriginTrackedPropertiesLoader$CharacterReader.isCommentPrefixCharacter:()Z
      51: ifeq          145
      54: aload         5
      56: invokevirtual #46                 // Method org/springframework/boot/env/OriginTrackedPropertiesLoader$CharacterReader.getCharacter:()C
      59: istore        6
      61: aload_0
      62: aload         5
      64: invokevirtual #50                 // Method isNewDocument:(Lorg/springframework/boot/env/OriginTrackedPropertiesLoader$CharacterReader;)Z
      67: ifeq          96
      70: aload_3
      71: invokevirtual #54                 // Method org/springframework/boot/env/OriginTrackedPropertiesLoader$Document.isEmpty:()Z
      74: ifne          85
      77: aload_2
      78: aload_3
      79: invokeinterface #57,  2           // InterfaceMethod java/util/List.add:(Ljava/lang/Object;)Z
      84: pop
      85: new           #28                 // class org/springframework/boot/env/OriginTrackedPropertiesLoader$Document
      88: dup
      89: invokespecial #30                 // Method org/springframework/boot/env/OriginTrackedPropertiesLoader$Document."<init>":()V
      92: astore_3
      93: goto          142
      96: aload_3
      97: invokevirtual #54                 // Method org/springframework/boot/env/OriginTrackedPropertiesLoader$Document.isEmpty:()Z
     100: ifeq          130
     103: aload_2
     104: invokeinterface #63,  1           // InterfaceMethod java/util/List.isEmpty:()Z
     109: ifne          130
     112: aload_2
     113: aload_2
     114: invokeinterface #64,  1           // InterfaceMethod java/util/List.size:()I
     119: iconst_1
     120: isub
     121: invokeinterface #68,  2           // InterfaceMethod java/util/List.remove:(I)Ljava/lang/Object;
     126: checkcast     #28                 // class org/springframework/boot/env/OriginTrackedPropertiesLoader$Document
     129: astore_3
     130: aload         5
     132: iload         6
     134: invokevirtual #72                 // Method org/springframework/boot/env/OriginTrackedPropertiesLoader$CharacterReader.setLastLineCommentPrefixCharacter:(I)V
     137: aload         5
     139: invokevirtual #76                 // Method org/springframework/boot/env/OriginTrackedPropertiesLoader$CharacterReader.skipComment:()V
     142: goto          38
     145: aload         5
     147: iconst_m1
     148: invokevirtual #72                 // Method org/springframework/boot/env/OriginTrackedPropertiesLoader$CharacterReader.setLastLineCommentPrefixCharacter:(I)V
     151: aload_0
     152: iload_1
     153: aload_3
     154: aload         5
     156: aload         4
     158: invokevirtual #79                 // Method loadKeyAndValue:(ZLorg/springframework/boot/env/OriginTrackedPropertiesLoader$Document;Lorg/springframework/boot/env/OriginTrackedPropertiesLoader$CharacterReader;Ljava/lang/StringBuilder;)V
     161: goto          38
     164: aload         5
     166: invokevirtual #83                 // Method org/springframework/boot/env/OriginTrackedPropertiesLoader$CharacterReader.close:()V
     169: goto          194
     172: astore        6
     174: aload         5
     176: invokevirtual #83                 // Method org/springframework/boot/env/OriginTrackedPropertiesLoader$CharacterReader.close:()V
     179: goto          191
     182: astore        7
     184: aload         6
     186: aload         7
     188: invokevirtual #88                 // Method java/lang/Throwable.addSuppressed:(Ljava/lang/Throwable;)V
     191: aload         6
     193: athrow
     194: aload_3
     195: invokevirtual #54                 // Method org/springframework/boot/env/OriginTrackedPropertiesLoader$Document.isEmpty:()Z
     198: ifne          219
     201: aload_2
     202: aload_3
     203: invokeinterface #92,  2           // InterfaceMethod java/util/List.contains:(Ljava/lang/Object;)Z
     208: ifne          219
     211: aload_2
     212: aload_3
     213: invokeinterface #57,  2           // InterfaceMethod java/util/List.add:(Ljava/lang/Object;)Z
     218: pop
     219: aload_2
     220: areturn
    Exception table:
       from    to  target type
          38   164   172   Class java/lang/Throwable
         174   179   182   Class java/lang/Throwable

  private void loadKeyAndValue(boolean, org.springframework.boot.env.OriginTrackedPropertiesLoader$Document, org.springframework.boot.env.OriginTrackedPropertiesLoader$CharacterReader, java.lang.StringBuilder) throws java.io.IOException;
    Code:
       0: aload_0
       1: aload         4
       3: aload_3
       4: invokevirtual #95                 // Method loadKey:(Ljava/lang/StringBuilder;Lorg/springframework/boot/env/OriginTrackedPropertiesLoader$CharacterReader;)Ljava/lang/String;
       7: invokevirtual #99                 // Method java/lang/String.trim:()Ljava/lang/String;
      10: astore        5
      12: iload_1
      13: ifeq          94
      16: aload         5
      18: ldc           #105                // String []
      20: invokevirtual #107                // Method java/lang/String.endsWith:(Ljava/lang/String;)Z
      23: ifeq          94
      26: aload         5
      28: iconst_0
      29: aload         5
      31: invokevirtual #111                // Method java/lang/String.length:()I
      34: iconst_2
      35: isub
      36: invokevirtual #114                // Method java/lang/String.substring:(II)Ljava/lang/String;
      39: astore        5
      41: iconst_0
      42: istore        6
      44: aload_0
      45: aload         4
      47: aload_3
      48: iconst_1
      49: invokevirtual #118                // Method loadValue:(Ljava/lang/StringBuilder;Lorg/springframework/boot/env/OriginTrackedPropertiesLoader$CharacterReader;Z)Lorg/springframework/boot/origin/OriginTrackedValue;
      52: astore        7
      54: aload_2
      55: aload         5
      57: iload         6
      59: iinc          6, 1
      62: invokedynamic #122,  0            // InvokeDynamic #0:makeConcatWithConstants:(Ljava/lang/String;I)Ljava/lang/String;
      67: aload         7
      69: invokevirtual #126                // Method org/springframework/boot/env/OriginTrackedPropertiesLoader$Document.put:(Ljava/lang/String;Lorg/springframework/boot/origin/OriginTrackedValue;)V
      72: aload_3
      73: invokevirtual #130                // Method org/springframework/boot/env/OriginTrackedPropertiesLoader$CharacterReader.isEndOfLine:()Z
      76: ifne          84
      79: aload_3
      80: invokevirtual #39                 // Method org/springframework/boot/env/OriginTrackedPropertiesLoader$CharacterReader.read:()Z
      83: pop
      84: aload_3
      85: invokevirtual #130                // Method org/springframework/boot/env/OriginTrackedPropertiesLoader$CharacterReader.isEndOfLine:()Z
      88: ifeq          44
      91: goto          112
      94: aload_0
      95: aload         4
      97: aload_3
      98: iconst_0
      99: invokevirtual #118                // Method loadValue:(Ljava/lang/StringBuilder;Lorg/springframework/boot/env/OriginTrackedPropertiesLoader$CharacterReader;Z)Lorg/springframework/boot/origin/OriginTrackedValue;
     102: astore        6
     104: aload_2
     105: aload         5
     107: aload         6
     109: invokevirtual #126                // Method org/springframework/boot/env/OriginTrackedPropertiesLoader$Document.put:(Ljava/lang/String;Lorg/springframework/boot/origin/OriginTrackedValue;)V
     112: return

  private java.lang.String loadKey(java.lang.StringBuilder, org.springframework.boot.env.OriginTrackedPropertiesLoader$CharacterReader) throws java.io.IOException;
    Code:
       0: aload_1
       1: iconst_0
       2: invokevirtual #133                // Method java/lang/StringBuilder.setLength:(I)V
       5: iconst_0
       6: istore_3
       7: aload_2
       8: invokevirtual #130                // Method org/springframework/boot/env/OriginTrackedPropertiesLoader$CharacterReader.isEndOfLine:()Z
      11: ifne          69
      14: aload_2
      15: invokevirtual #136                // Method org/springframework/boot/env/OriginTrackedPropertiesLoader$CharacterReader.isPropertyDelimiter:()Z
      18: ifeq          31
      21: aload_2
      22: invokevirtual #39                 // Method org/springframework/boot/env/OriginTrackedPropertiesLoader$CharacterReader.read:()Z
      25: pop
      26: aload_1
      27: invokevirtual #139                // Method java/lang/StringBuilder.toString:()Ljava/lang/String;
      30: areturn
      31: aload_2
      32: invokevirtual #142                // Method org/springframework/boot/env/OriginTrackedPropertiesLoader$CharacterReader.isWhiteSpace:()Z
      35: ifne          47
      38: iload_3
      39: ifeq          47
      42: aload_1
      43: invokevirtual #139                // Method java/lang/StringBuilder.toString:()Ljava/lang/String;
      46: areturn
      47: aload_2
      48: invokevirtual #142                // Method org/springframework/boot/env/OriginTrackedPropertiesLoader$CharacterReader.isWhiteSpace:()Z
      51: istore_3
      52: aload_1
      53: aload_2
      54: invokevirtual #46                 // Method org/springframework/boot/env/OriginTrackedPropertiesLoader$CharacterReader.getCharacter:()C
      57: invokevirtual #145                // Method java/lang/StringBuilder.append:(C)Ljava/lang/StringBuilder;
      60: pop
      61: aload_2
      62: invokevirtual #39                 // Method org/springframework/boot/env/OriginTrackedPropertiesLoader$CharacterReader.read:()Z
      65: pop
      66: goto          7
      69: aload_1
      70: invokevirtual #139                // Method java/lang/StringBuilder.toString:()Ljava/lang/String;
      73: areturn

  private org.springframework.boot.origin.OriginTrackedValue loadValue(java.lang.StringBuilder, org.springframework.boot.env.OriginTrackedPropertiesLoader$CharacterReader, boolean) throws java.io.IOException;
    Code:
       0: aload_1
       1: iconst_0
       2: invokevirtual #133                // Method java/lang/StringBuilder.setLength:(I)V
       5: aload_2
       6: invokevirtual #142                // Method org/springframework/boot/env/OriginTrackedPropertiesLoader$CharacterReader.isWhiteSpace:()Z
       9: ifeq          27
      12: aload_2
      13: invokevirtual #130                // Method org/springframework/boot/env/OriginTrackedPropertiesLoader$CharacterReader.isEndOfLine:()Z
      16: ifne          27
      19: aload_2
      20: invokevirtual #39                 // Method org/springframework/boot/env/OriginTrackedPropertiesLoader$CharacterReader.read:()Z
      23: pop
      24: goto          5
      27: aload_2
      28: invokevirtual #149                // Method org/springframework/boot/env/OriginTrackedPropertiesLoader$CharacterReader.getLocation:()Lorg/springframework/boot/origin/TextResourceOrigin$Location;
      31: astore        4
      33: aload_2
      34: invokevirtual #130                // Method org/springframework/boot/env/OriginTrackedPropertiesLoader$CharacterReader.isEndOfLine:()Z
      37: ifne          68
      40: iload_3
      41: ifeq          51
      44: aload_2
      45: invokevirtual #153                // Method org/springframework/boot/env/OriginTrackedPropertiesLoader$CharacterReader.isListDelimiter:()Z
      48: ifne          68
      51: aload_1
      52: aload_2
      53: invokevirtual #46                 // Method org/springframework/boot/env/OriginTrackedPropertiesLoader$CharacterReader.getCharacter:()C
      56: invokevirtual #145                // Method java/lang/StringBuilder.append:(C)Ljava/lang/StringBuilder;
      59: pop
      60: aload_2
      61: invokevirtual #39                 // Method org/springframework/boot/env/OriginTrackedPropertiesLoader$CharacterReader.read:()Z
      64: pop
      65: goto          33
      68: new           #156                // class org/springframework/boot/origin/TextResourceOrigin
      71: dup
      72: aload_0
      73: getfield      #15                 // Field resource:Lorg/springframework/core/io/Resource;
      76: aload         4
      78: invokespecial #158                // Method org/springframework/boot/origin/TextResourceOrigin."<init>":(Lorg/springframework/core/io/Resource;Lorg/springframework/boot/origin/TextResourceOrigin$Location;)V
      81: astore        5
      83: aload_1
      84: invokevirtual #139                // Method java/lang/StringBuilder.toString:()Ljava/lang/String;
      87: aload         5
      89: invokestatic  #161                // Method org/springframework/boot/origin/OriginTrackedValue.of:(Ljava/lang/Object;Lorg/springframework/boot/origin/Origin;)Lorg/springframework/boot/origin/OriginTrackedValue;
      92: areturn

  private boolean isNewDocument(org.springframework.boot.env.OriginTrackedPropertiesLoader$CharacterReader) throws java.io.IOException;
    Code:
       0: aload_1
       1: invokevirtual #167                // Method org/springframework/boot/env/OriginTrackedPropertiesLoader$CharacterReader.isSameLastLineCommentPrefix:()Z
       4: ifeq          9
       7: iconst_0
       8: ireturn
       9: aload_1
      10: invokevirtual #149                // Method org/springframework/boot/env/OriginTrackedPropertiesLoader$CharacterReader.getLocation:()Lorg/springframework/boot/origin/TextResourceOrigin$Location;
      13: invokevirtual #170                // Method org/springframework/boot/origin/TextResourceOrigin$Location.getColumn:()I
      16: ifne          23
      19: iconst_1
      20: goto          24
      23: iconst_0
      24: istore_2
      25: iload_2
      26: ifeq          52
      29: aload_0
      30: aload_1
      31: aload_1
      32: dup
      33: invokestatic  #175                // Method java/util/Objects.requireNonNull:(Ljava/lang/Object;)Ljava/lang/Object;
      36: pop
      37: invokedynamic #181,  0            // InvokeDynamic #1:getAsBoolean:(Lorg/springframework/boot/env/OriginTrackedPropertiesLoader$CharacterReader;)Ljava/util/function/BooleanSupplier;
      42: invokevirtual #185                // Method readAndExpect:(Lorg/springframework/boot/env/OriginTrackedPropertiesLoader$CharacterReader;Ljava/util/function/BooleanSupplier;)Z
      45: ifeq          52
      48: iconst_1
      49: goto          53
      52: iconst_0
      53: istore_2
      54: iload_2
      55: ifeq          81
      58: aload_0
      59: aload_1
      60: aload_1
      61: dup
      62: invokestatic  #175                // Method java/util/Objects.requireNonNull:(Ljava/lang/Object;)Ljava/lang/Object;
      65: pop
      66: invokedynamic #181,  0            // InvokeDynamic #1:getAsBoolean:(Lorg/springframework/boot/env/OriginTrackedPropertiesLoader$CharacterReader;)Ljava/util/function/BooleanSupplier;
      71: invokevirtual #185                // Method readAndExpect:(Lorg/springframework/boot/env/OriginTrackedPropertiesLoader$CharacterReader;Ljava/util/function/BooleanSupplier;)Z
      74: ifeq          81
      77: iconst_1
      78: goto          82
      81: iconst_0
      82: istore_2
      83: iload_2
      84: ifeq          110
      87: aload_0
      88: aload_1
      89: aload_1
      90: dup
      91: invokestatic  #175                // Method java/util/Objects.requireNonNull:(Ljava/lang/Object;)Ljava/lang/Object;
      94: pop
      95: invokedynamic #181,  0            // InvokeDynamic #1:getAsBoolean:(Lorg/springframework/boot/env/OriginTrackedPropertiesLoader$CharacterReader;)Ljava/util/function/BooleanSupplier;
     100: invokevirtual #185                // Method readAndExpect:(Lorg/springframework/boot/env/OriginTrackedPropertiesLoader$CharacterReader;Ljava/util/function/BooleanSupplier;)Z
     103: ifeq          110
     106: iconst_1
     107: goto          111
     110: iconst_0
     111: istore_2
     112: aload_1
     113: invokevirtual #130                // Method org/springframework/boot/env/OriginTrackedPropertiesLoader$CharacterReader.isEndOfLine:()Z
     116: ifne          128
     119: aload_1
     120: invokevirtual #39                 // Method org/springframework/boot/env/OriginTrackedPropertiesLoader$CharacterReader.read:()Z
     123: pop
     124: aload_1
     125: invokevirtual #189                // Method org/springframework/boot/env/OriginTrackedPropertiesLoader$CharacterReader.skipWhitespace:()V
     128: iload_2
     129: ifeq          143
     132: aload_1
     133: invokevirtual #130                // Method org/springframework/boot/env/OriginTrackedPropertiesLoader$CharacterReader.isEndOfLine:()Z
     136: ifeq          143
     139: iconst_1
     140: goto          144
     143: iconst_0
     144: ireturn

  private boolean readAndExpect(org.springframework.boot.env.OriginTrackedPropertiesLoader$CharacterReader, java.util.function.BooleanSupplier) throws java.io.IOException;
    Code:
       0: aload_1
       1: invokevirtual #39                 // Method org/springframework/boot/env/OriginTrackedPropertiesLoader$CharacterReader.read:()Z
       4: pop
       5: aload_2
       6: invokeinterface #192,  1          // InterfaceMethod java/util/function/BooleanSupplier.getAsBoolean:()Z
      11: ireturn
}
