Compiled from "OriginTrackedMapPropertySource.java"
public final class org.springframework.boot.env.OriginTrackedMapPropertySource extends org.springframework.core.env.MapPropertySource implements org.springframework.boot.origin.OriginLookup<java.lang.String> {
  private final boolean immutable;

  public org.springframework.boot.env.OriginTrackedMapPropertySource(java.lang.String, java.util.Map);
    Code:
       0: aload_0
       1: aload_1
       2: aload_2
       3: iconst_0
       4: invokespecial #1                  // Method "<init>":(Ljava/lang/String;Ljava/util/Map;Z)V
       7: return

  public org.springframework.boot.env.OriginTrackedMapPropertySource(java.lang.String, java.util.Map, boolean);
    Code:
       0: aload_0
       1: aload_1
       2: aload_2
       3: invokespecial #7                  // Method org/springframework/core/env/MapPropertySource."<init>":(Ljava/lang/String;Ljava/util/Map;)V
       6: aload_0
       7: iload_3
       8: putfield      #12                 // Field immutable:Z
      11: return

  public java.lang.Object getProperty(java.lang.String);
    Code:
       0: aload_0
       1: aload_1
       2: invokespecial #16                 // Method org/springframework/core/env/MapPropertySource.getProperty:(Ljava/lang/String;)Ljava/lang/Object;
       5: astore_2
       6: aload_2
       7: instanceof    #20                 // class org/springframework/boot/origin/OriginTrackedValue
      10: ifeq          23
      13: aload_2
      14: checkcast     #20                 // class org/springframework/boot/origin/OriginTrackedValue
      17: astore_3
      18: aload_3
      19: invokevirtual #22                 // Method org/springframework/boot/origin/OriginTrackedValue.getValue:()Ljava/lang/Object;
      22: areturn
      23: aload_2
      24: areturn

  public org.springframework.boot.origin.Origin getOrigin(java.lang.String);
    Code:
       0: aload_0
       1: aload_1
       2: invokespecial #16                 // Method org/springframework/core/env/MapPropertySource.getProperty:(Ljava/lang/String;)Ljava/lang/Object;
       5: astore_2
       6: aload_2
       7: instanceof    #20                 // class org/springframework/boot/origin/OriginTrackedValue
      10: ifeq          23
      13: aload_2
      14: checkcast     #20                 // class org/springframework/boot/origin/OriginTrackedValue
      17: astore_3
      18: aload_3
      19: invokevirtual #26                 // Method org/springframework/boot/origin/OriginTrackedValue.getOrigin:()Lorg/springframework/boot/origin/Origin;
      22: areturn
      23: aconst_null
      24: areturn

  public boolean isImmutable();
    Code:
       0: aload_0
       1: getfield      #12                 // Field immutable:Z
       4: ireturn

  public org.springframework.boot.origin.Origin getOrigin(java.lang.Object);
    Code:
       0: aload_0
       1: aload_1
       2: checkcast     #30                 // class java/lang/String
       5: invokevirtual #32                 // Method getOrigin:(Ljava/lang/String;)Lorg/springframework/boot/origin/Origin;
       8: areturn
}
