Compiled from "OriginTrackedYamlLoader.java"
class org.springframework.boot.env.OriginTrackedYamlLoader extends org.springframework.beans.factory.config.YamlProcessor {
  private final org.springframework.core.io.Resource resource;

  org.springframework.boot.env.OriginTrackedYamlLoader(org.springframework.core.io.Resource);
    Code:
       0: aload_0
       1: invokespecial #1                  // Method org/springframework/beans/factory/config/YamlProcessor."<init>":()V
       4: aload_0
       5: aload_1
       6: putfield      #7                  // Field resource:Lorg/springframework/core/io/Resource;
       9: aload_0
      10: iconst_1
      11: anewarray     #13                 // class org/springframework/core/io/Resource
      14: dup
      15: iconst_0
      16: aload_1
      17: aastore
      18: invokevirtual #15                 // Method setResources:([Lorg/springframework/core/io/Resource;)V
      21: return

  protected org.yaml.snakeyaml.Yaml createYaml();
    Code:
       0: new           #19                 // class org/yaml/snakeyaml/LoaderOptions
       3: dup
       4: invokespecial #21                 // Method org/yaml/snakeyaml/LoaderOptions."<init>":()V
       7: astore_1
       8: aload_1
       9: iconst_0
      10: invokevirtual #22                 // Method org/yaml/snakeyaml/LoaderOptions.setAllowDuplicateKeys:(Z)V
      13: aload_1
      14: ldc           #28                 // int 2147483647
      16: invokevirtual #29                 // Method org/yaml/snakeyaml/LoaderOptions.setMaxAliasesForCollections:(I)V
      19: aload_1
      20: iconst_1
      21: invokevirtual #33                 // Method org/yaml/snakeyaml/LoaderOptions.setAllowRecursiveKeys:(Z)V
      24: aload_1
      25: ldc           #28                 // int 2147483647
      27: invokevirtual #36                 // Method org/yaml/snakeyaml/LoaderOptions.setCodePointLimit:(I)V
      30: aload_0
      31: aload_1
      32: invokevirtual #39                 // Method createYaml:(Lorg/yaml/snakeyaml/LoaderOptions;)Lorg/yaml/snakeyaml/Yaml;
      35: areturn

  private org.yaml.snakeyaml.Yaml createYaml(org.yaml.snakeyaml.LoaderOptions);
    Code:
       0: new           #43                 // class org/springframework/boot/env/OriginTrackedYamlLoader$OriginTrackingConstructor
       3: dup
       4: aload_0
       5: aload_1
       6: invokespecial #45                 // Method org/springframework/boot/env/OriginTrackedYamlLoader$OriginTrackingConstructor."<init>":(Lorg/springframework/boot/env/OriginTrackedYamlLoader;Lorg/yaml/snakeyaml/LoaderOptions;)V
       9: astore_2
      10: new           #48                 // class org/yaml/snakeyaml/DumperOptions
      13: dup
      14: invokespecial #50                 // Method org/yaml/snakeyaml/DumperOptions."<init>":()V
      17: astore_3
      18: new           #51                 // class org/yaml/snakeyaml/representer/Representer
      21: dup
      22: aload_3
      23: invokespecial #53                 // Method org/yaml/snakeyaml/representer/Representer."<init>":(Lorg/yaml/snakeyaml/DumperOptions;)V
      26: astore        4
      28: new           #56                 // class org/springframework/boot/env/OriginTrackedYamlLoader$NoTimestampResolver
      31: dup
      32: invokespecial #58                 // Method org/springframework/boot/env/OriginTrackedYamlLoader$NoTimestampResolver."<init>":()V
      35: astore        5
      37: new           #59                 // class org/yaml/snakeyaml/Yaml
      40: dup
      41: aload_2
      42: aload         4
      44: aload_3
      45: aload_1
      46: aload         5
      48: invokespecial #61                 // Method org/yaml/snakeyaml/Yaml."<init>":(Lorg/yaml/snakeyaml/constructor/BaseConstructor;Lorg/yaml/snakeyaml/representer/Representer;Lorg/yaml/snakeyaml/DumperOptions;Lorg/yaml/snakeyaml/LoaderOptions;Lorg/yaml/snakeyaml/resolver/Resolver;)V
      51: areturn

  java.util.List<java.util.Map<java.lang.String, java.lang.Object>> load();
    Code:
       0: new           #64                 // class java/util/ArrayList
       3: dup
       4: invokespecial #66                 // Method java/util/ArrayList."<init>":()V
       7: astore_1
       8: aload_0
       9: aload_0
      10: aload_1
      11: invokedynamic #67,  0             // InvokeDynamic #0:process:(Lorg/springframework/boot/env/OriginTrackedYamlLoader;Ljava/util/List;)Lorg/springframework/beans/factory/config/YamlProcessor$MatchCallback;
      16: invokevirtual #71                 // Method process:(Lorg/springframework/beans/factory/config/YamlProcessor$MatchCallback;)V
      19: aload_1
      20: areturn

  private void lambda$load$0(java.util.List, java.util.Properties, java.util.Map);
    Code:
       0: aload_1
       1: aload_0
       2: aload_3
       3: invokevirtual #74                 // Method getFlattenedMap:(Ljava/util/Map;)Ljava/util/Map;
       6: invokeinterface #78,  2           // InterfaceMethod java/util/List.add:(Ljava/lang/Object;)Z
      11: pop
      12: return
}
