Compiled from "OriginTrackedPropertiesLoader.java"
class org.springframework.boot.env.OriginTrackedPropertiesLoader$Document {
  private final java.util.Map<java.lang.String, org.springframework.boot.origin.OriginTrackedValue> values;

  org.springframework.boot.env.OriginTrackedPropertiesLoader$Document();
    Code:
       0: aload_0
       1: invokespecial #1                  // Method java/lang/Object."<init>":()V
       4: aload_0
       5: new           #7                  // class java/util/LinkedHashMap
       8: dup
       9: invokespecial #9                  // Method java/util/LinkedHashMap."<init>":()V
      12: putfield      #10                 // Field values:Ljava/util/Map;
      15: return

  void put(java.lang.String, org.springframework.boot.origin.OriginTrackedValue);
    Code:
       0: aload_1
       1: invokevirtual #16                 // Method java/lang/String.isEmpty:()Z
       4: ifne          19
       7: aload_0
       8: getfield      #10                 // Field values:Ljava/util/Map;
      11: aload_1
      12: aload_2
      13: invokeinterface #22,  3           // InterfaceMethod java/util/Map.put:(Ljava/lang/Object;Ljava/lang/Object;)Ljava/lang/Object;
      18: pop
      19: return

  boolean isEmpty();
    Code:
       0: aload_0
       1: getfield      #10                 // Field values:Ljava/util/Map;
       4: invokeinterface #28,  1           // InterfaceMethod java/util/Map.isEmpty:()Z
       9: ireturn

  java.util.Map<java.lang.String, org.springframework.boot.origin.OriginTrackedValue> asMap();
    Code:
       0: aload_0
       1: getfield      #10                 // Field values:Ljava/util/Map;
       4: areturn
}
