Compiled from "PropertiesPropertySourceLoader.java"
public class org.springframework.boot.env.PropertiesPropertySourceLoader implements org.springframework.boot.env.PropertySourceLoader {
  private static final java.lang.String XML_FILE_EXTENSION;

  public org.springframework.boot.env.PropertiesPropertySourceLoader();
    Code:
       0: aload_0
       1: invokespecial #1                  // Method java/lang/Object."<init>":()V
       4: return

  public java.lang.String[] getFileExtensions();
    Code:
       0: iconst_2
       1: anewarray     #7                  // class java/lang/String
       4: dup
       5: iconst_0
       6: ldc           #9                  // String properties
       8: aastore
       9: dup
      10: iconst_1
      11: ldc           #11                 // String xml
      13: aastore
      14: areturn

  public java.util.List<org.springframework.core.env.PropertySource<?>> load(java.lang.String, org.springframework.core.io.Resource) throws java.io.IOException;
    Code:
       0: aload_0
       1: aload_2
       2: invokevirtual #13                 // Method loadProperties:(Lorg/springframework/core/io/Resource;)Ljava/util/List;
       5: astore_3
       6: aload_3
       7: invokeinterface #19,  1           // InterfaceMethod java/util/List.isEmpty:()Z
      12: ifeq          19
      15: invokestatic  #25                 // Method java/util/Collections.emptyList:()Ljava/util/List;
      18: areturn
      19: new           #31                 // class java/util/ArrayList
      22: dup
      23: aload_3
      24: invokeinterface #33,  1           // InterfaceMethod java/util/List.size:()I
      29: invokespecial #37                 // Method java/util/ArrayList."<init>":(I)V
      32: astore        4
      34: iconst_0
      35: istore        5
      37: iload         5
      39: aload_3
      40: invokeinterface #33,  1           // InterfaceMethod java/util/List.size:()I
      45: if_icmpge     116
      48: aload_3
      49: invokeinterface #33,  1           // InterfaceMethod java/util/List.size:()I
      54: iconst_1
      55: if_icmpeq     68
      58: iload         5
      60: invokedynamic #40,  0             // InvokeDynamic #0:makeConcatWithConstants:(I)Ljava/lang/String;
      65: goto          70
      68: ldc           #44                 // String
      70: astore        6
      72: aload         4
      74: new           #46                 // class org/springframework/boot/env/OriginTrackedMapPropertySource
      77: dup
      78: aload_1
      79: aload         6
      81: invokedynamic #48,  0             // InvokeDynamic #1:makeConcatWithConstants:(Ljava/lang/String;Ljava/lang/String;)Ljava/lang/String;
      86: aload_3
      87: iload         5
      89: invokeinterface #51,  2           // InterfaceMethod java/util/List.get:(I)Ljava/lang/Object;
      94: checkcast     #55                 // class java/util/Map
      97: invokestatic  #57                 // Method java/util/Collections.unmodifiableMap:(Ljava/util/Map;)Ljava/util/Map;
     100: iconst_1
     101: invokespecial #61                 // Method org/springframework/boot/env/OriginTrackedMapPropertySource."<init>":(Ljava/lang/String;Ljava/util/Map;Z)V
     104: invokeinterface #64,  2           // InterfaceMethod java/util/List.add:(Ljava/lang/Object;)Z
     109: pop
     110: iinc          5, 1
     113: goto          37
     116: aload         4
     118: areturn

  private java.util.List<java.util.Map<java.lang.String, ?>> loadProperties(org.springframework.core.io.Resource) throws java.io.IOException;
    Code:
       0: aload_1
       1: invokeinterface #68,  1           // InterfaceMethod org/springframework/core/io/Resource.getFilename:()Ljava/lang/String;
       6: astore_2
       7: new           #31                 // class java/util/ArrayList
      10: dup
      11: invokespecial #74                 // Method java/util/ArrayList."<init>":()V
      14: astore_3
      15: aload_2
      16: ifnull        42
      19: aload_2
      20: ldc           #75                 // String .xml
      22: invokevirtual #77                 // Method java/lang/String.endsWith:(Ljava/lang/String;)Z
      25: ifeq          42
      28: aload_3
      29: aload_1
      30: invokestatic  #81                 // Method org/springframework/core/io/support/PropertiesLoaderUtils.loadProperties:(Lorg/springframework/core/io/Resource;)Ljava/util/Properties;
      33: invokeinterface #64,  2           // InterfaceMethod java/util/List.add:(Ljava/lang/Object;)Z
      38: pop
      39: goto          68
      42: new           #86                 // class org/springframework/boot/env/OriginTrackedPropertiesLoader
      45: dup
      46: aload_1
      47: invokespecial #88                 // Method org/springframework/boot/env/OriginTrackedPropertiesLoader."<init>":(Lorg/springframework/core/io/Resource;)V
      50: invokevirtual #91                 // Method org/springframework/boot/env/OriginTrackedPropertiesLoader.load:()Ljava/util/List;
      53: astore        4
      55: aload         4
      57: aload_3
      58: invokedynamic #94,  0             // InvokeDynamic #2:accept:(Ljava/util/List;)Ljava/util/function/Consumer;
      63: invokeinterface #98,  2           // InterfaceMethod java/util/List.forEach:(Ljava/util/function/Consumer;)V
      68: aload_3
      69: areturn

  private static void lambda$loadProperties$0(java.util.List, org.springframework.boot.env.OriginTrackedPropertiesLoader$Document);
    Code:
       0: aload_0
       1: aload_1
       2: invokevirtual #102                // Method org/springframework/boot/env/OriginTrackedPropertiesLoader$Document.asMap:()Ljava/util/Map;
       5: invokeinterface #64,  2           // InterfaceMethod java/util/List.add:(Ljava/lang/Object;)Z
      10: pop
      11: return
}
