Compiled from "RandomValuePropertySource.java"
final class org.springframework.boot.env.RandomValuePropertySource$Range<T extends java.lang.Number> {
  private final java.lang.String value;

  private final T min;

  private final T max;

  private org.springframework.boot.env.RandomValuePropertySource$Range(java.lang.String, T, T);
    Code:
       0: aload_0
       1: invokespecial #1                  // Method java/lang/Object."<init>":()V
       4: aload_0
       5: aload_1
       6: putfield      #7                  // Field value:Ljava/lang/String;
       9: aload_0
      10: aload_2
      11: putfield      #13                 // Field min:Ljava/lang/Number;
      14: aload_0
      15: aload_3
      16: putfield      #17                 // Field max:Ljava/lang/Number;
      19: return

  T getMin();
    Code:
       0: aload_0
       1: getfield      #13                 // Field min:Ljava/lang/Number;
       4: areturn

  T getMax();
    Code:
       0: aload_0
       1: getfield      #17                 // Field max:Ljava/lang/Number;
       4: areturn

  public java.lang.String toString();
    Code:
       0: aload_0
       1: getfield      #7                  // Field value:Ljava/lang/String;
       4: areturn

  static <T extends java.lang.Number & java.lang.Comparable<T>> org.springframework.boot.env.RandomValuePropertySource$Range<T> of(java.lang.String, java.util.function.Function<java.lang.String, T>);
    Code:
       0: aload_1
       1: ldc           #20                 // String 0
       3: invokeinterface #22,  2           // InterfaceMethod java/util/function/Function.apply:(Ljava/lang/Object;)Ljava/lang/Object;
       8: checkcast     #28                 // class java/lang/Number
      11: astore_2
      12: aload_0
      13: invokestatic  #30                 // Method org/springframework/util/StringUtils.commaDelimitedListToStringArray:(Ljava/lang/String;)[Ljava/lang/String;
      16: astore_3
      17: aload_1
      18: aload_3
      19: iconst_0
      20: aaload
      21: invokeinterface #22,  2           // InterfaceMethod java/util/function/Function.apply:(Ljava/lang/Object;)Ljava/lang/Object;
      26: checkcast     #28                 // class java/lang/Number
      29: astore        4
      31: aload_3
      32: arraylength
      33: iconst_1
      34: if_icmpne     73
      37: aload         4
      39: checkcast     #36                 // class java/lang/Comparable
      42: aload_2
      43: invokeinterface #38,  2           // InterfaceMethod java/lang/Comparable.compareTo:(Ljava/lang/Object;)I
      48: ifle          55
      51: iconst_1
      52: goto          56
      55: iconst_0
      56: ldc           #42                 // String Bound must be positive.
      58: invokestatic  #44                 // Method org/springframework/util/Assert.isTrue:(ZLjava/lang/String;)V
      61: new           #8                  // class org/springframework/boot/env/RandomValuePropertySource$Range
      64: dup
      65: aload_0
      66: aload_2
      67: aload         4
      69: invokespecial #50                 // Method "<init>":(Ljava/lang/String;Ljava/lang/Number;Ljava/lang/Number;)V
      72: areturn
      73: aload_1
      74: aload_3
      75: iconst_1
      76: aaload
      77: invokeinterface #22,  2           // InterfaceMethod java/util/function/Function.apply:(Ljava/lang/Object;)Ljava/lang/Object;
      82: checkcast     #28                 // class java/lang/Number
      85: astore        5
      87: aload         4
      89: checkcast     #36                 // class java/lang/Comparable
      92: aload         5
      94: invokeinterface #38,  2           // InterfaceMethod java/lang/Comparable.compareTo:(Ljava/lang/Object;)I
      99: ifge          106
     102: iconst_1
     103: goto          107
     106: iconst_0
     107: ldc           #53                 // String Lower bound must be less than upper bound.
     109: invokestatic  #44                 // Method org/springframework/util/Assert.isTrue:(ZLjava/lang/String;)V
     112: new           #8                  // class org/springframework/boot/env/RandomValuePropertySource$Range
     115: dup
     116: aload_0
     117: aload         4
     119: aload         5
     121: invokespecial #50                 // Method "<init>":(Ljava/lang/String;Ljava/lang/Number;Ljava/lang/Number;)V
     124: areturn
}
