Compiled from "RandomValuePropertySource.java"
public class org.springframework.boot.env.RandomValuePropertySource extends org.springframework.core.env.PropertySource<java.util.Random> {
  public static final java.lang.String RANDOM_PROPERTY_SOURCE_NAME;

  private static final java.lang.String PREFIX;

  private static final org.apache.commons.logging.Log logger;

  public org.springframework.boot.env.RandomValuePropertySource();
    Code:
       0: aload_0
       1: ldc           #3                  // String random
       3: invokespecial #5                  // Method "<init>":(Ljava/lang/String;)V
       6: return

  public org.springframework.boot.env.RandomValuePropertySource(java.lang.String);
    Code:
       0: aload_0
       1: aload_1
       2: new           #9                  // class java/util/Random
       5: dup
       6: invokespecial #11                 // Method java/util/Random."<init>":()V
       9: invokespecial #14                 // Method org/springframework/core/env/PropertySource."<init>":(Ljava/lang/String;Ljava/lang/Object;)V
      12: return

  public java.lang.Object getProperty(java.lang.String);
    Code:
       0: aload_1
       1: ldc           #19                 // String random.
       3: invokevirtual #21                 // Method java/lang/String.startsWith:(Ljava/lang/String;)Z
       6: ifne          11
       9: aconst_null
      10: areturn
      11: getstatic     #27                 // Field logger:Lorg/apache/commons/logging/Log;
      14: ldc           #31                 // String Generating random property for \'%s\'
      16: aload_1
      17: invokestatic  #33                 // Method org/springframework/core/log/LogMessage.format:(Ljava/lang/String;Ljava/lang/Object;)Lorg/springframework/core/log/LogMessage;
      20: invokeinterface #39,  2           // InterfaceMethod org/apache/commons/logging/Log.trace:(Ljava/lang/Object;)V
      25: aload_0
      26: aload_1
      27: ldc           #19                 // String random.
      29: invokevirtual #45                 // Method java/lang/String.length:()I
      32: invokevirtual #49                 // Method java/lang/String.substring:(I)Ljava/lang/String;
      35: invokevirtual #53                 // Method getRandomValue:(Ljava/lang/String;)Ljava/lang/Object;
      38: areturn

  private java.lang.Object getRandomValue(java.lang.String);
    Code:
       0: aload_1
       1: ldc           #57                 // String int
       3: invokevirtual #59                 // Method java/lang/String.equals:(Ljava/lang/Object;)Z
       6: ifeq          23
       9: aload_0
      10: invokevirtual #63                 // Method getSource:()Ljava/lang/Object;
      13: checkcast     #9                  // class java/util/Random
      16: invokevirtual #67                 // Method java/util/Random.nextInt:()I
      19: invokestatic  #70                 // Method java/lang/Integer.valueOf:(I)Ljava/lang/Integer;
      22: areturn
      23: aload_1
      24: ldc           #76                 // String long
      26: invokevirtual #59                 // Method java/lang/String.equals:(Ljava/lang/Object;)Z
      29: ifeq          46
      32: aload_0
      33: invokevirtual #63                 // Method getSource:()Ljava/lang/Object;
      36: checkcast     #9                  // class java/util/Random
      39: invokevirtual #78                 // Method java/util/Random.nextLong:()J
      42: invokestatic  #82                 // Method java/lang/Long.valueOf:(J)Ljava/lang/Long;
      45: areturn
      46: aload_0
      47: aload_1
      48: ldc           #57                 // String int
      50: invokevirtual #87                 // Method getRange:(Ljava/lang/String;Ljava/lang/String;)Ljava/lang/String;
      53: astore_2
      54: aload_2
      55: ifnull        75
      58: aload_0
      59: aload_2
      60: invokedynamic #91,  0             // InvokeDynamic #0:apply:()Ljava/util/function/Function;
      65: invokestatic  #95                 // Method org/springframework/boot/env/RandomValuePropertySource$Range.of:(Ljava/lang/String;Ljava/util/function/Function;)Lorg/springframework/boot/env/RandomValuePropertySource$Range;
      68: invokevirtual #101                // Method getNextIntInRange:(Lorg/springframework/boot/env/RandomValuePropertySource$Range;)I
      71: invokestatic  #70                 // Method java/lang/Integer.valueOf:(I)Ljava/lang/Integer;
      74: areturn
      75: aload_0
      76: aload_1
      77: ldc           #76                 // String long
      79: invokevirtual #87                 // Method getRange:(Ljava/lang/String;Ljava/lang/String;)Ljava/lang/String;
      82: astore_2
      83: aload_2
      84: ifnull        104
      87: aload_0
      88: aload_2
      89: invokedynamic #105,  0            // InvokeDynamic #1:apply:()Ljava/util/function/Function;
      94: invokestatic  #95                 // Method org/springframework/boot/env/RandomValuePropertySource$Range.of:(Ljava/lang/String;Ljava/util/function/Function;)Lorg/springframework/boot/env/RandomValuePropertySource$Range;
      97: invokevirtual #106                // Method getNextLongInRange:(Lorg/springframework/boot/env/RandomValuePropertySource$Range;)J
     100: invokestatic  #82                 // Method java/lang/Long.valueOf:(J)Ljava/lang/Long;
     103: areturn
     104: aload_1
     105: ldc           #110                // String uuid
     107: invokevirtual #59                 // Method java/lang/String.equals:(Ljava/lang/Object;)Z
     110: ifeq          120
     113: invokestatic  #112                // Method java/util/UUID.randomUUID:()Ljava/util/UUID;
     116: invokevirtual #118                // Method java/util/UUID.toString:()Ljava/lang/String;
     119: areturn
     120: aload_0
     121: invokevirtual #122                // Method getRandomBytes:()Ljava/lang/Object;
     124: areturn

  private java.lang.String getRange(java.lang.String, java.lang.String);
    Code:
       0: aload_1
       1: aload_2
       2: invokevirtual #21                 // Method java/lang/String.startsWith:(Ljava/lang/String;)Z
       5: ifeq          35
       8: aload_2
       9: invokevirtual #45                 // Method java/lang/String.length:()I
      12: iconst_1
      13: iadd
      14: istore_3
      15: aload_1
      16: invokevirtual #45                 // Method java/lang/String.length:()I
      19: iload_3
      20: if_icmple     35
      23: aload_1
      24: iload_3
      25: aload_1
      26: invokevirtual #45                 // Method java/lang/String.length:()I
      29: iconst_1
      30: isub
      31: invokevirtual #125                // Method java/lang/String.substring:(II)Ljava/lang/String;
      34: areturn
      35: aconst_null
      36: areturn

  private int getNextIntInRange(org.springframework.boot.env.RandomValuePropertySource$Range<java.lang.Integer>);
    Code:
       0: aload_0
       1: invokevirtual #63                 // Method getSource:()Ljava/lang/Object;
       4: checkcast     #9                  // class java/util/Random
       7: lconst_1
       8: aload_1
       9: invokevirtual #128                // Method org/springframework/boot/env/RandomValuePropertySource$Range.getMin:()Ljava/lang/Number;
      12: checkcast     #71                 // class java/lang/Integer
      15: invokevirtual #132                // Method java/lang/Integer.intValue:()I
      18: aload_1
      19: invokevirtual #135                // Method org/springframework/boot/env/RandomValuePropertySource$Range.getMax:()Ljava/lang/Number;
      22: checkcast     #71                 // class java/lang/Integer
      25: invokevirtual #132                // Method java/lang/Integer.intValue:()I
      28: invokevirtual #138                // Method java/util/Random.ints:(JII)Ljava/util/stream/IntStream;
      31: invokeinterface #142,  1          // InterfaceMethod java/util/stream/IntStream.findFirst:()Ljava/util/OptionalInt;
      36: astore_2
      37: aload_0
      38: aload_2
      39: invokevirtual #148                // Method java/util/OptionalInt.isPresent:()Z
      42: aload_1
      43: invokevirtual #154                // Method assertPresent:(ZLorg/springframework/boot/env/RandomValuePropertySource$Range;)V
      46: aload_2
      47: invokevirtual #158                // Method java/util/OptionalInt.getAsInt:()I
      50: ireturn

  private long getNextLongInRange(org.springframework.boot.env.RandomValuePropertySource$Range<java.lang.Long>);
    Code:
       0: aload_0
       1: invokevirtual #63                 // Method getSource:()Ljava/lang/Object;
       4: checkcast     #9                  // class java/util/Random
       7: lconst_1
       8: aload_1
       9: invokevirtual #128                // Method org/springframework/boot/env/RandomValuePropertySource$Range.getMin:()Ljava/lang/Number;
      12: checkcast     #83                 // class java/lang/Long
      15: invokevirtual #161                // Method java/lang/Long.longValue:()J
      18: aload_1
      19: invokevirtual #135                // Method org/springframework/boot/env/RandomValuePropertySource$Range.getMax:()Ljava/lang/Number;
      22: checkcast     #83                 // class java/lang/Long
      25: invokevirtual #161                // Method java/lang/Long.longValue:()J
      28: invokevirtual #164                // Method java/util/Random.longs:(JJJ)Ljava/util/stream/LongStream;
      31: invokeinterface #168,  1          // InterfaceMethod java/util/stream/LongStream.findFirst:()Ljava/util/OptionalLong;
      36: astore_2
      37: aload_0
      38: aload_2
      39: invokevirtual #173                // Method java/util/OptionalLong.isPresent:()Z
      42: aload_1
      43: invokevirtual #154                // Method assertPresent:(ZLorg/springframework/boot/env/RandomValuePropertySource$Range;)V
      46: aload_2
      47: invokevirtual #176                // Method java/util/OptionalLong.getAsLong:()J
      50: lreturn

  private void assertPresent(boolean, org.springframework.boot.env.RandomValuePropertySource$Range<?>);
    Code:
       0: iload_1
       1: aload_2
       2: invokedynamic #179,  0            // InvokeDynamic #2:get:(Lorg/springframework/boot/env/RandomValuePropertySource$Range;)Ljava/util/function/Supplier;
       7: invokestatic  #183                // Method org/springframework/util/Assert.state:(ZLjava/util/function/Supplier;)V
      10: return

  private java.lang.Object getRandomBytes();
    Code:
       0: bipush        32
       2: newarray       byte
       4: astore_1
       5: aload_0
       6: invokevirtual #63                 // Method getSource:()Ljava/lang/Object;
       9: checkcast     #9                  // class java/util/Random
      12: aload_1
      13: invokevirtual #189                // Method java/util/Random.nextBytes:([B)V
      16: aload_1
      17: invokestatic  #193                // Method org/springframework/util/DigestUtils.md5DigestAsHex:([B)Ljava/lang/String;
      20: areturn

  public static void addToEnvironment(org.springframework.core.env.ConfigurableEnvironment);
    Code:
       0: aload_0
       1: getstatic     #27                 // Field logger:Lorg/apache/commons/logging/Log;
       4: invokestatic  #199                // Method addToEnvironment:(Lorg/springframework/core/env/ConfigurableEnvironment;Lorg/apache/commons/logging/Log;)V
       7: return

  static void addToEnvironment(org.springframework.core.env.ConfigurableEnvironment, org.apache.commons.logging.Log);
    Code:
       0: aload_0
       1: invokeinterface #203,  1          // InterfaceMethod org/springframework/core/env/ConfigurableEnvironment.getPropertySources:()Lorg/springframework/core/env/MutablePropertySources;
       6: astore_2
       7: aload_2
       8: ldc           #3                  // String random
      10: invokevirtual #209                // Method org/springframework/core/env/MutablePropertySources.get:(Ljava/lang/String;)Lorg/springframework/core/env/PropertySource;
      13: astore_3
      14: aload_3
      15: ifnull        27
      18: aload_1
      19: ldc           #214                // String RandomValuePropertySource already present
      21: invokeinterface #39,  2           // InterfaceMethod org/apache/commons/logging/Log.trace:(Ljava/lang/Object;)V
      26: return
      27: new           #1                  // class org/springframework/boot/env/RandomValuePropertySource
      30: dup
      31: ldc           #3                  // String random
      33: invokespecial #5                  // Method "<init>":(Ljava/lang/String;)V
      36: astore        4
      38: aload_2
      39: ldc           #218                // String systemEnvironment
      41: invokevirtual #209                // Method org/springframework/core/env/MutablePropertySources.get:(Ljava/lang/String;)Lorg/springframework/core/env/PropertySource;
      44: ifnull        58
      47: aload_2
      48: ldc           #218                // String systemEnvironment
      50: aload         4
      52: invokevirtual #220                // Method org/springframework/core/env/MutablePropertySources.addAfter:(Ljava/lang/String;Lorg/springframework/core/env/PropertySource;)V
      55: goto          64
      58: aload_2
      59: aload         4
      61: invokevirtual #224                // Method org/springframework/core/env/MutablePropertySources.addLast:(Lorg/springframework/core/env/PropertySource;)V
      64: aload_1
      65: ldc           #228                // String RandomValuePropertySource add to Environment
      67: invokeinterface #39,  2           // InterfaceMethod org/apache/commons/logging/Log.trace:(Ljava/lang/Object;)V
      72: return

  private static java.lang.String lambda$assertPresent$0(org.springframework.boot.env.RandomValuePropertySource$Range);
    Code:
       0: aload_0
       1: invokedynamic #230,  0            // InvokeDynamic #3:makeConcatWithConstants:(Lorg/springframework/boot/env/RandomValuePropertySource$Range;)Ljava/lang/String;
       6: areturn

  static {};
    Code:
       0: ldc           #1                  // class org/springframework/boot/env/RandomValuePropertySource
       2: invokestatic  #234                // Method org/apache/commons/logging/LogFactory.getLog:(Ljava/lang/Class;)Lorg/apache/commons/logging/Log;
       5: putstatic     #27                 // Field logger:Lorg/apache/commons/logging/Log;
       8: return
}
