Compiled from "RandomValuePropertySourceEnvironmentPostProcessor.java"
public class org.springframework.boot.env.RandomValuePropertySourceEnvironmentPostProcessor implements org.springframework.boot.env.EnvironmentPostProcessor,org.springframework.core.Ordered {
  public static final int ORDER;

  private final org.apache.commons.logging.Log logger;

  public org.springframework.boot.env.RandomValuePropertySourceEnvironmentPostProcessor(org.springframework.boot.logging.DeferredLogFactory);
    Code:
       0: aload_0
       1: invokespecial #3                  // Method java/lang/Object."<init>":()V
       4: aload_0
       5: aload_1
       6: ldc           #9                  // class org/springframework/boot/env/RandomValuePropertySourceEnvironmentPostProcessor
       8: invokeinterface #11,  2           // InterfaceMethod org/springframework/boot/logging/DeferredLogFactory.getLog:(Ljava/lang/Class;)Lorg/apache/commons/logging/Log;
      13: putfield      #17                 // Field logger:Lorg/apache/commons/logging/Log;
      16: return

  public int getOrder();
    Code:
       0: ldc           #21                 // int -2147483647
       2: ireturn

  public void postProcessEnvironment(org.springframework.core.env.ConfigurableEnvironment, org.springframework.boot.SpringApplication);
    Code:
       0: aload_1
       1: aload_0
       2: getfield      #17                 // Field logger:Lorg/apache/commons/logging/Log;
       5: invokestatic  #22                 // Method org/springframework/boot/env/RandomValuePropertySource.addToEnvironment:(Lorg/springframework/core/env/ConfigurableEnvironment;Lorg/apache/commons/logging/Log;)V
       8: return
}
