Compiled from "ReflectionEnvironmentPostProcessorsFactory.java"
class org.springframework.boot.env.ReflectionEnvironmentPostProcessorsFactory implements org.springframework.boot.env.EnvironmentPostProcessorsFactory {
  private final java.util.List<java.lang.Class<?>> classes;

  private java.lang.ClassLoader classLoader;

  private final java.util.List<java.lang.String> classNames;

  org.springframework.boot.env.ReflectionEnvironmentPostProcessorsFactory(java.lang.Class<?>...);
    Code:
       0: aload_0
       1: invokespecial #1                  // Method java/lang/Object."<init>":()V
       4: aload_0
       5: new           #7                  // class java/util/ArrayList
       8: dup
       9: aload_1
      10: invokestatic  #9                  // Method java/util/Arrays.asList:([Ljava/lang/Object;)Ljava/util/List;
      13: invokespecial #15                 // Method java/util/ArrayList."<init>":(Ljava/util/Collection;)V
      16: putfield      #18                 // Field classes:Ljava/util/List;
      19: aload_0
      20: aconst_null
      21: putfield      #24                 // Field classNames:Ljava/util/List;
      24: return

  org.springframework.boot.env.ReflectionEnvironmentPostProcessorsFactory(java.lang.ClassLoader, java.lang.String...);
    Code:
       0: aload_0
       1: aload_1
       2: aload_2
       3: invokestatic  #9                  // Method java/util/Arrays.asList:([Ljava/lang/Object;)Ljava/util/List;
       6: invokespecial #27                 // Method "<init>":(Ljava/lang/ClassLoader;Ljava/util/List;)V
       9: return

  org.springframework.boot.env.ReflectionEnvironmentPostProcessorsFactory(java.lang.ClassLoader, java.util.List<java.lang.String>);
    Code:
       0: aload_0
       1: invokespecial #1                  // Method java/lang/Object."<init>":()V
       4: aload_0
       5: aconst_null
       6: putfield      #18                 // Field classes:Ljava/util/List;
       9: aload_0
      10: aload_1
      11: putfield      #30                 // Field classLoader:Ljava/lang/ClassLoader;
      14: aload_0
      15: aload_2
      16: putfield      #24                 // Field classNames:Ljava/util/List;
      19: return

  public java.util.List<org.springframework.boot.env.EnvironmentPostProcessor> getEnvironmentPostProcessors(org.springframework.boot.logging.DeferredLogFactory, org.springframework.boot.ConfigurableBootstrapContext);
    Code:
       0: new           #34                 // class org/springframework/boot/util/Instantiator
       3: dup
       4: ldc           #36                 // class org/springframework/boot/env/EnvironmentPostProcessor
       6: aload_1
       7: aload_2
       8: invokedynamic #38,  0             // InvokeDynamic #0:accept:(Lorg/springframework/boot/logging/DeferredLogFactory;Lorg/springframework/boot/ConfigurableBootstrapContext;)Ljava/util/function/Consumer;
      13: invokespecial #42                 // Method org/springframework/boot/util/Instantiator."<init>":(Ljava/lang/Class;Ljava/util/function/Consumer;)V
      16: astore_3
      17: aload_0
      18: getfield      #18                 // Field classes:Ljava/util/List;
      21: ifnull        35
      24: aload_3
      25: aload_0
      26: getfield      #18                 // Field classes:Ljava/util/List;
      29: invokevirtual #45                 // Method org/springframework/boot/util/Instantiator.instantiateTypes:(Ljava/util/Collection;)Ljava/util/List;
      32: goto          47
      35: aload_3
      36: aload_0
      37: getfield      #30                 // Field classLoader:Ljava/lang/ClassLoader;
      40: aload_0
      41: getfield      #24                 // Field classNames:Ljava/util/List;
      44: invokevirtual #49                 // Method org/springframework/boot/util/Instantiator.instantiate:(Ljava/lang/ClassLoader;Ljava/util/Collection;)Ljava/util/List;
      47: areturn

  private static void lambda$getEnvironmentPostProcessors$0(org.springframework.boot.logging.DeferredLogFactory, org.springframework.boot.ConfigurableBootstrapContext, org.springframework.boot.util.Instantiator$AvailableParameters);
    Code:
       0: aload_2
       1: ldc           #53                 // class org/springframework/boot/logging/DeferredLogFactory
       3: aload_0
       4: invokeinterface #55,  3           // InterfaceMethod org/springframework/boot/util/Instantiator$AvailableParameters.add:(Ljava/lang/Class;Ljava/lang/Object;)V
       9: aload_2
      10: ldc           #61                 // class org/apache/commons/logging/Log
      12: aload_0
      13: dup
      14: invokestatic  #63                 // Method java/util/Objects.requireNonNull:(Ljava/lang/Object;)Ljava/lang/Object;
      17: pop
      18: invokedynamic #69,  0             // InvokeDynamic #1:apply:(Lorg/springframework/boot/logging/DeferredLogFactory;)Ljava/util/function/Function;
      23: invokeinterface #73,  3           // InterfaceMethod org/springframework/boot/util/Instantiator$AvailableParameters.add:(Ljava/lang/Class;Ljava/util/function/Function;)V
      28: aload_2
      29: ldc           #76                 // class org/springframework/boot/ConfigurableBootstrapContext
      31: aload_1
      32: invokeinterface #55,  3           // InterfaceMethod org/springframework/boot/util/Instantiator$AvailableParameters.add:(Ljava/lang/Class;Ljava/lang/Object;)V
      37: aload_2
      38: ldc           #78                 // class org/springframework/boot/BootstrapContext
      40: aload_1
      41: invokeinterface #55,  3           // InterfaceMethod org/springframework/boot/util/Instantiator$AvailableParameters.add:(Ljava/lang/Class;Ljava/lang/Object;)V
      46: aload_2
      47: ldc           #80                 // class org/springframework/boot/BootstrapRegistry
      49: aload_1
      50: invokeinterface #55,  3           // InterfaceMethod org/springframework/boot/util/Instantiator$AvailableParameters.add:(Ljava/lang/Class;Ljava/lang/Object;)V
      55: return
}
