Compiled from "SpringFactoriesEnvironmentPostProcessorsFactory.java"
class org.springframework.boot.env.SpringFactoriesEnvironmentPostProcessorsFactory implements org.springframework.boot.env.EnvironmentPostProcessorsFactory {
  private final org.springframework.core.io.support.SpringFactoriesLoader loader;

  org.springframework.boot.env.SpringFactoriesEnvironmentPostProcessorsFactory(org.springframework.core.io.support.SpringFactoriesLoader);
    Code:
       0: aload_0
       1: invokespecial #1                  // Method java/lang/Object."<init>":()V
       4: aload_0
       5: aload_1
       6: putfield      #7                  // Field loader:Lorg/springframework/core/io/support/SpringFactoriesLoader;
       9: return

  public java.util.List<org.springframework.boot.env.EnvironmentPostProcessor> getEnvironmentPostProcessors(org.springframework.boot.logging.DeferredLogFactory, org.springframework.boot.ConfigurableBootstrapContext);
    Code:
       0: ldc           #13                 // class org/springframework/boot/logging/DeferredLogFactory
       2: aload_1
       3: invokestatic  #15                 // InterfaceMethod org/springframework/core/io/support/SpringFactoriesLoader$ArgumentResolver.of:(Ljava/lang/Class;Ljava/lang/Object;)Lorg/springframework/core/io/support/SpringFactoriesLoader$ArgumentResolver;
       6: astore_3
       7: aload_3
       8: ldc           #21                 // class org/springframework/boot/ConfigurableBootstrapContext
      10: aload_2
      11: invokeinterface #23,  3           // InterfaceMethod org/springframework/core/io/support/SpringFactoriesLoader$ArgumentResolver.and:(Ljava/lang/Class;Ljava/lang/Object;)Lorg/springframework/core/io/support/SpringFactoriesLoader$ArgumentResolver;
      16: astore_3
      17: aload_3
      18: ldc           #26                 // class org/springframework/boot/BootstrapContext
      20: aload_2
      21: invokeinterface #23,  3           // InterfaceMethod org/springframework/core/io/support/SpringFactoriesLoader$ArgumentResolver.and:(Ljava/lang/Class;Ljava/lang/Object;)Lorg/springframework/core/io/support/SpringFactoriesLoader$ArgumentResolver;
      26: astore_3
      27: aload_3
      28: ldc           #28                 // class org/springframework/boot/BootstrapRegistry
      30: aload_2
      31: invokeinterface #23,  3           // InterfaceMethod org/springframework/core/io/support/SpringFactoriesLoader$ArgumentResolver.and:(Ljava/lang/Class;Ljava/lang/Object;)Lorg/springframework/core/io/support/SpringFactoriesLoader$ArgumentResolver;
      36: astore_3
      37: aload_0
      38: getfield      #7                  // Field loader:Lorg/springframework/core/io/support/SpringFactoriesLoader;
      41: ldc           #30                 // class org/springframework/boot/env/EnvironmentPostProcessor
      43: aload_3
      44: invokevirtual #32                 // Method org/springframework/core/io/support/SpringFactoriesLoader.load:(Ljava/lang/Class;Lorg/springframework/core/io/support/SpringFactoriesLoader$ArgumentResolver;)Ljava/util/List;
      47: areturn
}
