Compiled from "SpringApplicationJsonEnvironmentPostProcessor.java"
public class org.springframework.boot.env.SpringApplicationJsonEnvironmentPostProcessor implements org.springframework.boot.env.EnvironmentPostProcessor,org.springframework.core.Ordered {
  public static final java.lang.String SPRING_APPLICATION_JSON_PROPERTY;

  public static final java.lang.String SPRING_APPLICATION_JSON_ENVIRONMENT_VARIABLE;

  private static final java.lang.String SERVLET_ENVIRONMENT_CLASS;

  private static final java.util.Set<java.lang.String> SERVLET_ENVIRONMENT_PROPERTY_SOURCES;

  public static final int DEFAULT_ORDER;

  private int order;

  public org.springframework.boot.env.SpringApplicationJsonEnvironmentPostProcessor();
    Code:
       0: aload_0
       1: invokespecial #3                  // Method java/lang/Object."<init>":()V
       4: aload_0
       5: ldc           #11                 // int -2147483643
       7: putfield      #12                 // Field order:I
      10: return

  public int getOrder();
    Code:
       0: aload_0
       1: getfield      #12                 // Field order:I
       4: ireturn

  public void setOrder(int);
    Code:
       0: aload_0
       1: iload_1
       2: putfield      #12                 // Field order:I
       5: return

  public void postProcessEnvironment(org.springframework.core.env.ConfigurableEnvironment, org.springframework.boot.SpringApplication);
    Code:
       0: aload_1
       1: invokeinterface #16,  1           // InterfaceMethod org/springframework/core/env/ConfigurableEnvironment.getPropertySources:()Lorg/springframework/core/env/MutablePropertySources;
       6: astore_3
       7: aload_3
       8: invokevirtual #22                 // Method org/springframework/core/env/MutablePropertySources.stream:()Ljava/util/stream/Stream;
      11: invokedynamic #28,  0             // InvokeDynamic #0:apply:()Ljava/util/function/Function;
      16: invokeinterface #32,  2           // InterfaceMethod java/util/stream/Stream.map:(Ljava/util/function/Function;)Ljava/util/stream/Stream;
      21: invokedynamic #38,  0             // InvokeDynamic #1:test:()Ljava/util/function/Predicate;
      26: invokeinterface #42,  2           // InterfaceMethod java/util/stream/Stream.filter:(Ljava/util/function/Predicate;)Ljava/util/stream/Stream;
      31: invokeinterface #46,  1           // InterfaceMethod java/util/stream/Stream.findFirst:()Ljava/util/Optional;
      36: aload_0
      37: aload_1
      38: invokedynamic #50,  0             // InvokeDynamic #2:accept:(Lorg/springframework/boot/env/SpringApplicationJsonEnvironmentPostProcessor;Lorg/springframework/core/env/ConfigurableEnvironment;)Ljava/util/function/Consumer;
      43: invokevirtual #54                 // Method java/util/Optional.ifPresent:(Ljava/util/function/Consumer;)V
      46: return

  private void processJson(org.springframework.core.env.ConfigurableEnvironment, org.springframework.boot.env.SpringApplicationJsonEnvironmentPostProcessor$JsonPropertyValue);
    Code:
       0: invokestatic  #60                 // Method org/springframework/boot/json/JsonParserFactory.getJsonParser:()Lorg/springframework/boot/json/JsonParser;
       3: astore_3
       4: aload_3
       5: aload_2
       6: invokevirtual #66                 // Method org/springframework/boot/env/SpringApplicationJsonEnvironmentPostProcessor$JsonPropertyValue.getJson:()Ljava/lang/String;
       9: invokeinterface #72,  2           // InterfaceMethod org/springframework/boot/json/JsonParser.parseMap:(Ljava/lang/String;)Ljava/util/Map;
      14: astore        4
      16: aload         4
      18: invokeinterface #78,  1           // InterfaceMethod java/util/Map.isEmpty:()Z
      23: ifne          45
      26: aload_0
      27: aload_1
      28: new           #84                 // class org/springframework/boot/env/SpringApplicationJsonEnvironmentPostProcessor$JsonPropertySource
      31: dup
      32: aload_2
      33: aload_0
      34: aload         4
      36: invokevirtual #86                 // Method flatten:(Ljava/util/Map;)Ljava/util/Map;
      39: invokespecial #90                 // Method org/springframework/boot/env/SpringApplicationJsonEnvironmentPostProcessor$JsonPropertySource."<init>":(Lorg/springframework/boot/env/SpringApplicationJsonEnvironmentPostProcessor$JsonPropertyValue;Ljava/util/Map;)V
      42: invokevirtual #93                 // Method addJsonPropertySource:(Lorg/springframework/core/env/ConfigurableEnvironment;Lorg/springframework/core/env/PropertySource;)V
      45: return

  private java.util.Map<java.lang.String, java.lang.Object> flatten(java.util.Map<java.lang.String, java.lang.Object>);
    Code:
       0: new           #97                 // class java/util/LinkedHashMap
       3: dup
       4: invokespecial #99                 // Method java/util/LinkedHashMap."<init>":()V
       7: astore_2
       8: aload_0
       9: aconst_null
      10: aload_2
      11: aload_1
      12: invokevirtual #100                // Method flatten:(Ljava/lang/String;Ljava/util/Map;Ljava/util/Map;)V
      15: aload_2
      16: areturn

  private void flatten(java.lang.String, java.util.Map<java.lang.String, java.lang.Object>, java.util.Map<java.lang.String, java.lang.Object>);
    Code:
       0: aload_1
       1: ifnull        13
       4: aload_1
       5: invokedynamic #103,  0            // InvokeDynamic #3:makeConcatWithConstants:(Ljava/lang/String;)Ljava/lang/String;
      10: goto          15
      13: ldc           #107                // String
      15: astore        4
      17: aload_3
      18: aload_0
      19: aload         4
      21: aload_2
      22: invokedynamic #109,  0            // InvokeDynamic #4:accept:(Lorg/springframework/boot/env/SpringApplicationJsonEnvironmentPostProcessor;Ljava/lang/String;Ljava/util/Map;)Ljava/util/function/BiConsumer;
      27: invokeinterface #112,  2          // InterfaceMethod java/util/Map.forEach:(Ljava/util/function/BiConsumer;)V
      32: return

  private void extract(java.lang.String, java.util.Map<java.lang.String, java.lang.Object>, java.lang.Object);
    Code:
       0: aload_3
       1: instanceof    #79                 // class java/util/Map
       4: ifeq          40
       7: aload_3
       8: checkcast     #79                 // class java/util/Map
      11: invokestatic  #116                // Method org/springframework/util/CollectionUtils.isEmpty:(Ljava/util/Map;)Z
      14: ifeq          27
      17: aload_2
      18: aload_1
      19: aload_3
      20: invokeinterface #121,  3          // InterfaceMethod java/util/Map.put:(Ljava/lang/Object;Ljava/lang/Object;)Ljava/lang/Object;
      25: pop
      26: return
      27: aload_0
      28: aload_1
      29: aload_2
      30: aload_3
      31: checkcast     #79                 // class java/util/Map
      34: invokevirtual #100                // Method flatten:(Ljava/lang/String;Ljava/util/Map;Ljava/util/Map;)V
      37: goto          133
      40: aload_3
      41: instanceof    #125                // class java/util/Collection
      44: ifeq          124
      47: aload_3
      48: checkcast     #125                // class java/util/Collection
      51: invokestatic  #127                // Method org/springframework/util/CollectionUtils.isEmpty:(Ljava/util/Collection;)Z
      54: ifeq          67
      57: aload_2
      58: aload_1
      59: aload_3
      60: invokeinterface #121,  3          // InterfaceMethod java/util/Map.put:(Ljava/lang/Object;Ljava/lang/Object;)Ljava/lang/Object;
      65: pop
      66: return
      67: iconst_0
      68: istore        4
      70: aload_3
      71: checkcast     #125                // class java/util/Collection
      74: invokeinterface #130,  1          // InterfaceMethod java/util/Collection.iterator:()Ljava/util/Iterator;
      79: astore        5
      81: aload         5
      83: invokeinterface #134,  1          // InterfaceMethod java/util/Iterator.hasNext:()Z
      88: ifeq          121
      91: aload         5
      93: invokeinterface #139,  1          // InterfaceMethod java/util/Iterator.next:()Ljava/lang/Object;
      98: astore        6
     100: aload_0
     101: aload_1
     102: iload         4
     104: invokedynamic #143,  0            // InvokeDynamic #5:makeConcatWithConstants:(Ljava/lang/String;I)Ljava/lang/String;
     109: aload_2
     110: aload         6
     112: invokevirtual #146                // Method extract:(Ljava/lang/String;Ljava/util/Map;Ljava/lang/Object;)V
     115: iinc          4, 1
     118: goto          81
     121: goto          133
     124: aload_2
     125: aload_1
     126: aload_3
     127: invokeinterface #121,  3          // InterfaceMethod java/util/Map.put:(Ljava/lang/Object;Ljava/lang/Object;)Ljava/lang/Object;
     132: pop
     133: return

  private void addJsonPropertySource(org.springframework.core.env.ConfigurableEnvironment, org.springframework.core.env.PropertySource<?>);
    Code:
       0: aload_1
       1: invokeinterface #16,  1           // InterfaceMethod org/springframework/core/env/ConfigurableEnvironment.getPropertySources:()Lorg/springframework/core/env/MutablePropertySources;
       6: astore_3
       7: aload_0
       8: aload_3
       9: invokevirtual #150                // Method findPropertySource:(Lorg/springframework/core/env/MutablePropertySources;)Ljava/lang/String;
      12: astore        4
      14: aload_3
      15: aload         4
      17: invokevirtual #154                // Method org/springframework/core/env/MutablePropertySources.contains:(Ljava/lang/String;)Z
      20: ifeq          33
      23: aload_3
      24: aload         4
      26: aload_2
      27: invokevirtual #158                // Method org/springframework/core/env/MutablePropertySources.addBefore:(Ljava/lang/String;Lorg/springframework/core/env/PropertySource;)V
      30: goto          38
      33: aload_3
      34: aload_2
      35: invokevirtual #162                // Method org/springframework/core/env/MutablePropertySources.addFirst:(Lorg/springframework/core/env/PropertySource;)V
      38: return

  private java.lang.String findPropertySource(org.springframework.core.env.MutablePropertySources);
    Code:
       0: ldc           #166                // String org.springframework.web.context.support.StandardServletEnvironment
       2: aconst_null
       3: invokestatic  #168                // Method org/springframework/util/ClassUtils.isPresent:(Ljava/lang/String;Ljava/lang/ClassLoader;)Z
       6: ifeq          45
       9: aload_1
      10: invokevirtual #22                 // Method org/springframework/core/env/MutablePropertySources.stream:()Ljava/util/stream/Stream;
      13: invokedynamic #174,  0            // InvokeDynamic #6:test:()Ljava/util/function/Predicate;
      18: invokeinterface #42,  2           // InterfaceMethod java/util/stream/Stream.filter:(Ljava/util/function/Predicate;)Ljava/util/stream/Stream;
      23: invokeinterface #46,  1           // InterfaceMethod java/util/stream/Stream.findFirst:()Ljava/util/Optional;
      28: aconst_null
      29: invokevirtual #175                // Method java/util/Optional.orElse:(Ljava/lang/Object;)Ljava/lang/Object;
      32: checkcast     #179                // class org/springframework/core/env/PropertySource
      35: astore_2
      36: aload_2
      37: ifnull        45
      40: aload_2
      41: invokevirtual #181                // Method org/springframework/core/env/PropertySource.getName:()Ljava/lang/String;
      44: areturn
      45: ldc           #186                // String systemProperties
      47: areturn

  private static boolean lambda$findPropertySource$2(org.springframework.core.env.PropertySource);
    Code:
       0: getstatic     #188                // Field SERVLET_ENVIRONMENT_PROPERTY_SOURCES:Ljava/util/Set;
       3: aload_0
       4: invokevirtual #181                // Method org/springframework/core/env/PropertySource.getName:()Ljava/lang/String;
       7: invokeinterface #192,  2          // InterfaceMethod java/util/Set.contains:(Ljava/lang/Object;)Z
      12: ireturn

  private void lambda$flatten$1(java.lang.String, java.util.Map, java.lang.String, java.lang.Object);
    Code:
       0: aload_0
       1: aload_1
       2: aload_3
       3: invokedynamic #197,  0            // InvokeDynamic #7:makeConcatWithConstants:(Ljava/lang/String;Ljava/lang/String;)Ljava/lang/String;
       8: aload_2
       9: aload         4
      11: invokevirtual #146                // Method extract:(Ljava/lang/String;Ljava/util/Map;Ljava/lang/Object;)V
      14: return

  private void lambda$postProcessEnvironment$0(org.springframework.core.env.ConfigurableEnvironment, org.springframework.boot.env.SpringApplicationJsonEnvironmentPostProcessor$JsonPropertyValue);
    Code:
       0: aload_0
       1: aload_1
       2: aload_2
       3: invokevirtual #200                // Method processJson:(Lorg/springframework/core/env/ConfigurableEnvironment;Lorg/springframework/boot/env/SpringApplicationJsonEnvironmentPostProcessor$JsonPropertyValue;)V
       6: return

  static {};
    Code:
       0: new           #204                // class java/util/LinkedHashSet
       3: dup
       4: iconst_3
       5: anewarray     #206                // class java/lang/String
       8: dup
       9: iconst_0
      10: ldc           #210                // String jndiProperties
      12: aastore
      13: dup
      14: iconst_1
      15: ldc           #212                // String servletContextInitParams
      17: aastore
      18: dup
      19: iconst_2
      20: ldc           #214                // String servletConfigInitParams
      22: aastore
      23: invokestatic  #216                // Method java/util/Arrays.asList:([Ljava/lang/Object;)Ljava/util/List;
      26: invokespecial #222                // Method java/util/LinkedHashSet."<init>":(Ljava/util/Collection;)V
      29: putstatic     #188                // Field SERVLET_ENVIRONMENT_PROPERTY_SOURCES:Ljava/util/Set;
      32: return
}
