Compiled from "SystemEnvironmentPropertySourceEnvironmentPostProcessor.java"
public class org.springframework.boot.env.SystemEnvironmentPropertySourceEnvironmentPostProcessor$OriginAwareSystemEnvironmentPropertySource extends org.springframework.core.env.SystemEnvironmentPropertySource implements org.springframework.boot.origin.OriginLookup<java.lang.String> {
  private final java.lang.String prefix;

  org.springframework.boot.env.SystemEnvironmentPropertySourceEnvironmentPostProcessor$OriginAwareSystemEnvironmentPropertySource(java.lang.String, java.util.Map<java.lang.String, java.lang.Object>, java.lang.String);
    Code:
       0: aload_0
       1: aload_1
       2: aload_2
       3: invokespecial #1                  // Method org/springframework/core/env/SystemEnvironmentPropertySource."<init>":(Ljava/lang/String;Ljava/util/Map;)V
       6: aload_0
       7: aload_0
       8: aload_3
       9: invokevirtual #7                  // Method determinePrefix:(Ljava/lang/String;)Ljava/lang/String;
      12: putfield      #13                 // Field prefix:Ljava/lang/String;
      15: return

  private java.lang.String determinePrefix(java.lang.String);
    Code:
       0: aload_1
       1: invokestatic  #17                 // Method org/springframework/util/StringUtils.hasText:(Ljava/lang/String;)Z
       4: ifne          9
       7: aconst_null
       8: areturn
       9: aload_1
      10: ldc           #23                 // String .
      12: invokevirtual #25                 // Method java/lang/String.endsWith:(Ljava/lang/String;)Z
      15: ifne          36
      18: aload_1
      19: ldc           #30                 // String _
      21: invokevirtual #25                 // Method java/lang/String.endsWith:(Ljava/lang/String;)Z
      24: ifne          36
      27: aload_1
      28: ldc           #32                 // String -
      30: invokevirtual #25                 // Method java/lang/String.endsWith:(Ljava/lang/String;)Z
      33: ifeq          48
      36: aload_1
      37: iconst_0
      38: aload_1
      39: invokevirtual #34                 // Method java/lang/String.length:()I
      42: iconst_1
      43: isub
      44: invokevirtual #38                 // Method java/lang/String.substring:(II)Ljava/lang/String;
      47: areturn
      48: aload_1
      49: areturn

  public boolean containsProperty(java.lang.String);
    Code:
       0: aload_0
       1: aload_1
       2: invokespecial #42                 // Method org/springframework/core/env/SystemEnvironmentPropertySource.containsProperty:(Ljava/lang/String;)Z
       5: ireturn

  public java.lang.Object getProperty(java.lang.String);
    Code:
       0: aload_0
       1: aload_1
       2: invokespecial #45                 // Method org/springframework/core/env/SystemEnvironmentPropertySource.getProperty:(Ljava/lang/String;)Ljava/lang/Object;
       5: areturn

  public org.springframework.boot.origin.Origin getOrigin(java.lang.String);
    Code:
       0: aload_0
       1: aload_1
       2: invokevirtual #49                 // Method resolvePropertyName:(Ljava/lang/String;)Ljava/lang/String;
       5: astore_2
       6: aload_0
       7: aload_2
       8: invokespecial #42                 // Method org/springframework/core/env/SystemEnvironmentPropertySource.containsProperty:(Ljava/lang/String;)Z
      11: ifeq          23
      14: new           #52                 // class org/springframework/boot/origin/SystemEnvironmentOrigin
      17: dup
      18: aload_2
      19: invokespecial #54                 // Method org/springframework/boot/origin/SystemEnvironmentOrigin."<init>":(Ljava/lang/String;)V
      22: areturn
      23: aconst_null
      24: areturn

  public java.lang.String getPrefix();
    Code:
       0: aload_0
       1: getfield      #13                 // Field prefix:Ljava/lang/String;
       4: areturn

  public org.springframework.boot.origin.Origin getOrigin(java.lang.Object);
    Code:
       0: aload_0
       1: aload_1
       2: checkcast     #26                 // class java/lang/String
       5: invokevirtual #57                 // Method getOrigin:(Ljava/lang/String;)Lorg/springframework/boot/origin/Origin;
       8: areturn
}
