Compiled from "SystemEnvironmentPropertySourceEnvironmentPostProcessor.java"
public class org.springframework.boot.env.SystemEnvironmentPropertySourceEnvironmentPostProcessor implements org.springframework.boot.env.EnvironmentPostProcessor,org.springframework.core.Ordered {
  public static final int DEFAULT_ORDER;

  private int order;

  public org.springframework.boot.env.SystemEnvironmentPropertySourceEnvironmentPostProcessor();
    Code:
       0: aload_0
       1: invokespecial #3                  // Method java/lang/Object."<init>":()V
       4: aload_0
       5: ldc           #11                 // int -2147483644
       7: putfield      #12                 // Field order:I
      10: return

  public void postProcessEnvironment(org.springframework.core.env.ConfigurableEnvironment, org.springframework.boot.SpringApplication);
    Code:
       0: ldc           #18                 // String systemEnvironment
       2: astore_3
       3: aload_1
       4: invokeinterface #20,  1           // InterfaceMethod org/springframework/core/env/ConfigurableEnvironment.getPropertySources:()Lorg/springframework/core/env/MutablePropertySources;
       9: aload_3
      10: invokevirtual #26                 // Method org/springframework/core/env/MutablePropertySources.get:(Ljava/lang/String;)Lorg/springframework/core/env/PropertySource;
      13: astore        4
      15: aload         4
      17: ifnull        32
      20: aload_0
      21: aload_1
      22: aload_3
      23: aload         4
      25: aload_2
      26: invokevirtual #32                 // Method org/springframework/boot/SpringApplication.getEnvironmentPrefix:()Ljava/lang/String;
      29: invokevirtual #38                 // Method replacePropertySource:(Lorg/springframework/core/env/ConfigurableEnvironment;Ljava/lang/String;Lorg/springframework/core/env/PropertySource;Ljava/lang/String;)V
      32: return

  private void replacePropertySource(org.springframework.core.env.ConfigurableEnvironment, java.lang.String, org.springframework.core.env.PropertySource<?>, java.lang.String);
    Code:
       0: aload_3
       1: invokevirtual #42                 // Method org/springframework/core/env/PropertySource.getSource:()Ljava/lang/Object;
       4: checkcast     #48                 // class java/util/Map
       7: astore        5
       9: new           #50                 // class org/springframework/boot/env/SystemEnvironmentPropertySourceEnvironmentPostProcessor$OriginAwareSystemEnvironmentPropertySource
      12: dup
      13: aload_2
      14: aload         5
      16: aload         4
      18: invokespecial #52                 // Method org/springframework/boot/env/SystemEnvironmentPropertySourceEnvironmentPostProcessor$OriginAwareSystemEnvironmentPropertySource."<init>":(Ljava/lang/String;Ljava/util/Map;Ljava/lang/String;)V
      21: astore        6
      23: aload_1
      24: invokeinterface #20,  1           // InterfaceMethod org/springframework/core/env/ConfigurableEnvironment.getPropertySources:()Lorg/springframework/core/env/MutablePropertySources;
      29: aload_2
      30: aload         6
      32: invokevirtual #55                 // Method org/springframework/core/env/MutablePropertySources.replace:(Ljava/lang/String;Lorg/springframework/core/env/PropertySource;)V
      35: return

  public int getOrder();
    Code:
       0: aload_0
       1: getfield      #12                 // Field order:I
       4: ireturn

  public void setOrder(int);
    Code:
       0: aload_0
       1: iload_1
       2: putfield      #12                 // Field order:I
       5: return
}
