Compiled from "YamlPropertySourceLoader.java"
public class org.springframework.boot.env.YamlPropertySourceLoader implements org.springframework.boot.env.PropertySourceLoader {
  public org.springframework.boot.env.YamlPropertySourceLoader();
    Code:
       0: aload_0
       1: invokespecial #1                  // Method java/lang/Object."<init>":()V
       4: return

  public java.lang.String[] getFileExtensions();
    Code:
       0: iconst_2
       1: anewarray     #7                  // class java/lang/String
       4: dup
       5: iconst_0
       6: ldc           #9                  // String yml
       8: aastore
       9: dup
      10: iconst_1
      11: ldc           #11                 // String yaml
      13: aastore
      14: areturn

  public java.util.List<org.springframework.core.env.PropertySource<?>> load(java.lang.String, org.springframework.core.io.Resource) throws java.io.IOException;
    Code:
       0: ldc           #13                 // String org.yaml.snakeyaml.Yaml
       2: aload_0
       3: invokevirtual #15                 // Method java/lang/Object.getClass:()Ljava/lang/Class;
       6: invokevirtual #19                 // Method java/lang/Class.getClassLoader:()Ljava/lang/ClassLoader;
       9: invokestatic  #25                 // Method org/springframework/util/ClassUtils.isPresent:(Ljava/lang/String;Ljava/lang/ClassLoader;)Z
      12: ifne          29
      15: new           #31                 // class java/lang/IllegalStateException
      18: dup
      19: aload_1
      20: invokedynamic #33,  0             // InvokeDynamic #0:makeConcatWithConstants:(Ljava/lang/String;)Ljava/lang/String;
      25: invokespecial #37                 // Method java/lang/IllegalStateException."<init>":(Ljava/lang/String;)V
      28: athrow
      29: new           #40                 // class org/springframework/boot/env/OriginTrackedYamlLoader
      32: dup
      33: aload_2
      34: invokespecial #42                 // Method org/springframework/boot/env/OriginTrackedYamlLoader."<init>":(Lorg/springframework/core/io/Resource;)V
      37: invokevirtual #45                 // Method org/springframework/boot/env/OriginTrackedYamlLoader.load:()Ljava/util/List;
      40: astore_3
      41: aload_3
      42: invokeinterface #49,  1           // InterfaceMethod java/util/List.isEmpty:()Z
      47: ifeq          54
      50: invokestatic  #55                 // Method java/util/Collections.emptyList:()Ljava/util/List;
      53: areturn
      54: new           #60                 // class java/util/ArrayList
      57: dup
      58: aload_3
      59: invokeinterface #62,  1           // InterfaceMethod java/util/List.size:()I
      64: invokespecial #66                 // Method java/util/ArrayList."<init>":(I)V
      67: astore        4
      69: iconst_0
      70: istore        5
      72: iload         5
      74: aload_3
      75: invokeinterface #62,  1           // InterfaceMethod java/util/List.size:()I
      80: if_icmpge     151
      83: aload_3
      84: invokeinterface #62,  1           // InterfaceMethod java/util/List.size:()I
      89: iconst_1
      90: if_icmpeq     103
      93: iload         5
      95: invokedynamic #69,  0             // InvokeDynamic #1:makeConcatWithConstants:(I)Ljava/lang/String;
     100: goto          105
     103: ldc           #72                 // String
     105: astore        6
     107: aload         4
     109: new           #74                 // class org/springframework/boot/env/OriginTrackedMapPropertySource
     112: dup
     113: aload_1
     114: aload         6
     116: invokedynamic #76,  0             // InvokeDynamic #2:makeConcatWithConstants:(Ljava/lang/String;Ljava/lang/String;)Ljava/lang/String;
     121: aload_3
     122: iload         5
     124: invokeinterface #79,  2           // InterfaceMethod java/util/List.get:(I)Ljava/lang/Object;
     129: checkcast     #83                 // class java/util/Map
     132: invokestatic  #85                 // Method java/util/Collections.unmodifiableMap:(Ljava/util/Map;)Ljava/util/Map;
     135: iconst_1
     136: invokespecial #89                 // Method org/springframework/boot/env/OriginTrackedMapPropertySource."<init>":(Ljava/lang/String;Ljava/util/Map;Z)V
     139: invokeinterface #92,  2           // InterfaceMethod java/util/List.add:(Ljava/lang/Object;)Z
     144: pop
     145: iinc          5, 1
     148: goto          72
     151: aload         4
     153: areturn
}
