Compiled from "CompositeException.java"
final class io.reactivex.rxjava3.exceptions.CompositeException$WrappedPrintWriter extends io.reactivex.rxjava3.exceptions.CompositeException$PrintStreamOrWriter {
  private final java.io.PrintWriter printWriter;

  io.reactivex.rxjava3.exceptions.CompositeException$WrappedPrintWriter(java.io.PrintWriter);
    Code:
       0: aload_0
       1: invokespecial #1                  // Method io/reactivex/rxjava3/exceptions/CompositeException$PrintStreamOrWriter."<init>":()V
       4: aload_0
       5: aload_1
       6: putfield      #2                  // Field printWriter:Ljava/io/PrintWriter;
       9: return

  io.reactivex.rxjava3.exceptions.CompositeException$WrappedPrintWriter append(java.lang.Object);
    Code:
       0: aload_0
       1: getfield      #2                  // Field printWriter:Ljava/io/PrintWriter;
       4: aload_1
       5: invokevirtual #3                  // Method java/io/PrintWriter.print:(Ljava/lang/Object;)V
       8: aload_0
       9: areturn

  io.reactivex.rxjava3.exceptions.CompositeException$PrintStreamOrWriter append(java.lang.Object);
    Code:
       0: aload_0
       1: aload_1
       2: invokevirtual #4                  // Method append:(Ljava/lang/Object;)Lio/reactivex/rxjava3/exceptions/CompositeException$WrappedPrintWriter;
       5: areturn
}
