Compiled from "Exceptions.java"
public final class io.reactivex.rxjava3.exceptions.Exceptions {
  private io.reactivex.rxjava3.exceptions.Exceptions();
    Code:
       0: aload_0
       1: invokespecial #1                  // Method java/lang/Object."<init>":()V
       4: new           #2                  // class java/lang/IllegalStateException
       7: dup
       8: ldc           #3                  // String No instances!
      10: invokespecial #4                  // Method java/lang/IllegalStateException."<init>":(Ljava/lang/String;)V
      13: athrow

  public static java.lang.RuntimeException propagate(java.lang.Throwable);
    Code:
       0: aload_0
       1: invokestatic  #5                  // Method io/reactivex/rxjava3/internal/util/ExceptionHelper.wrapOrThrow:(Ljava/lang/Throwable;)Ljava/lang/RuntimeException;
       4: athrow

  public static void throwIfFatal(java.lang.Throwable);
    Code:
       0: aload_0
       1: instanceof    #6                  // class java/lang/VirtualMachineError
       4: ifeq          12
       7: aload_0
       8: checkcast     #6                  // class java/lang/VirtualMachineError
      11: athrow
      12: aload_0
      13: instanceof    #7                  // class java/lang/ThreadDeath
      16: ifeq          24
      19: aload_0
      20: checkcast     #7                  // class java/lang/ThreadDeath
      23: athrow
      24: aload_0
      25: instanceof    #8                  // class java/lang/LinkageError
      28: ifeq          36
      31: aload_0
      32: checkcast     #8                  // class java/lang/LinkageError
      35: athrow
      36: return
}
