Compiled from "MissingBackpressureException.java"
public final class io.reactivex.rxjava3.exceptions.MissingBackpressureException extends java.lang.RuntimeException {
  private static final long serialVersionUID;

  public static final java.lang.String DEFAULT_MESSAGE;

  public io.reactivex.rxjava3.exceptions.MissingBackpressureException();
    Code:
       0: aload_0
       1: invokespecial #1                  // Method java/lang/RuntimeException."<init>":()V
       4: return

  public io.reactivex.rxjava3.exceptions.MissingBackpressureException(java.lang.String);
    Code:
       0: aload_0
       1: aload_1
       2: invokespecial #2                  // Method java/lang/RuntimeException."<init>":(Ljava/lang/String;)V
       5: return

  public static io.reactivex.rxjava3.exceptions.MissingBackpressureException createDefault();
    Code:
       0: new           #3                  // class io/reactivex/rxjava3/exceptions/MissingBackpressureException
       3: dup
       4: ldc           #4                  // String Could not emit value due to lack of requests
       6: invokespecial #5                  // Method "<init>":(Ljava/lang/String;)V
       9: areturn
}
