Compiled from "QueueOverflowException.java"
public final class io.reactivex.rxjava3.exceptions.QueueOverflowException extends java.lang.RuntimeException {
  private static final long serialVersionUID;

  private static final java.lang.String DEFAULT_MESSAGE;

  public io.reactivex.rxjava3.exceptions.QueueOverflowException();
    Code:
       0: aload_0
       1: ldc           #2                  // String Queue overflow due to illegal concurrent onNext calls or a bug in an operator
       3: invokespecial #3                  // Method "<init>":(Ljava/lang/String;)V
       6: return

  public io.reactivex.rxjava3.exceptions.QueueOverflowException(java.lang.String);
    Code:
       0: aload_0
       1: aload_1
       2: invokespecial #4                  // Method java/lang/RuntimeException."<init>":(Ljava/lang/String;)V
       5: return
}
