Compiled from "UndeliverableException.java"
public final class io.reactivex.rxjava3.exceptions.UndeliverableException extends java.lang.IllegalStateException {
  private static final long serialVersionUID;

  public io.reactivex.rxjava3.exceptions.UndeliverableException(java.lang.Throwable);
    Code:
       0: aload_0
       1: new           #1                  // class java/lang/StringBuilder
       4: dup
       5: invokespecial #2                  // Method java/lang/StringBuilder."<init>":()V
       8: ldc           #3                  // String The exception could not be delivered to the consumer because it has already canceled/disposed the flow or the exception has nowhere to go to begin with. Further reading: https://github.com/ReactiveX/RxJava/wiki/What\'s-different-in-2.0#error-handling |
      10: invokevirtual #4                  // Method java/lang/StringBuilder.append:(Ljava/lang/String;)Ljava/lang/StringBuilder;
      13: aload_1
      14: invokevirtual #5                  // Method java/lang/StringBuilder.append:(Ljava/lang/Object;)Ljava/lang/StringBuilder;
      17: invokevirtual #6                  // Method java/lang/StringBuilder.toString:()Ljava/lang/String;
      20: aload_1
      21: invokespecial #7                  // Method java/lang/IllegalStateException."<init>":(Ljava/lang/String;Ljava/lang/Throwable;)V
      24: return
}
