Compiled from "FailsafeLogger.java"
public class org.apache.dubbo.common.logger.support.FailsafeLogger implements org.apache.dubbo.common.logger.Logger {
  private org.apache.dubbo.common.logger.Logger logger;

  private static boolean disabled;

  public org.apache.dubbo.common.logger.support.FailsafeLogger(org.apache.dubbo.common.logger.Logger);
    Code:
       0: aload_0
       1: invokespecial #1                  // Method java/lang/Object."<init>":()V
       4: aload_0
       5: aload_1
       6: putfield      #2                  // Field logger:Lorg/apache/dubbo/common/logger/Logger;
       9: return

  public static void setDisabled(boolean);
    Code:
       0: iload_0
       1: putstatic     #3                  // Field disabled:Z
       4: return

  static boolean getDisabled();
    Code:
       0: getstatic     #3                  // Field disabled:Z
       3: ireturn

  public org.apache.dubbo.common.logger.Logger getLogger();
    Code:
       0: aload_0
       1: getfield      #2                  // Field logger:Lorg/apache/dubbo/common/logger/Logger;
       4: areturn

  public void setLogger(org.apache.dubbo.common.logger.Logger);
    Code:
       0: aload_0
       1: aload_1
       2: putfield      #2                  // Field logger:Lorg/apache/dubbo/common/logger/Logger;
       5: return

  private java.lang.String appendContextMessage(java.lang.String);
    Code:
       0: new           #4                  // class java/lang/StringBuilder
       3: dup
       4: invokespecial #5                  // Method java/lang/StringBuilder."<init>":()V
       7: ldc           #6                  // String  [DUBBO]
       9: invokevirtual #7                  // Method java/lang/StringBuilder.append:(Ljava/lang/String;)Ljava/lang/StringBuilder;
      12: aload_1
      13: invokevirtual #7                  // Method java/lang/StringBuilder.append:(Ljava/lang/String;)Ljava/lang/StringBuilder;
      16: ldc           #8                  // String , dubbo version:
      18: invokevirtual #7                  // Method java/lang/StringBuilder.append:(Ljava/lang/String;)Ljava/lang/StringBuilder;
      21: invokestatic  #9                  // Method org/apache/dubbo/common/Version.getVersion:()Ljava/lang/String;
      24: invokevirtual #7                  // Method java/lang/StringBuilder.append:(Ljava/lang/String;)Ljava/lang/StringBuilder;
      27: ldc           #10                 // String , current host:
      29: invokevirtual #7                  // Method java/lang/StringBuilder.append:(Ljava/lang/String;)Ljava/lang/StringBuilder;
      32: invokestatic  #11                 // Method org/apache/dubbo/common/utils/NetUtils.getLocalHost:()Ljava/lang/String;
      35: invokevirtual #7                  // Method java/lang/StringBuilder.append:(Ljava/lang/String;)Ljava/lang/StringBuilder;
      38: invokevirtual #12                 // Method java/lang/StringBuilder.toString:()Ljava/lang/String;
      41: areturn

  public void trace(java.lang.String, java.lang.Throwable);
    Code:
       0: getstatic     #3                  // Field disabled:Z
       3: ifeq          7
       6: return
       7: aload_0
       8: getfield      #2                  // Field logger:Lorg/apache/dubbo/common/logger/Logger;
      11: aload_0
      12: aload_1
      13: invokespecial #13                 // Method appendContextMessage:(Ljava/lang/String;)Ljava/lang/String;
      16: aload_2
      17: invokeinterface #14,  3           // InterfaceMethod org/apache/dubbo/common/logger/Logger.trace:(Ljava/lang/String;Ljava/lang/Throwable;)V
      22: goto          26
      25: astore_3
      26: return
    Exception table:
       from    to  target type
           7    22    25   Class java/lang/Throwable

  public void trace(java.lang.Throwable);
    Code:
       0: getstatic     #3                  // Field disabled:Z
       3: ifeq          7
       6: return
       7: aload_0
       8: getfield      #2                  // Field logger:Lorg/apache/dubbo/common/logger/Logger;
      11: aload_1
      12: invokeinterface #16,  2           // InterfaceMethod org/apache/dubbo/common/logger/Logger.trace:(Ljava/lang/Throwable;)V
      17: goto          21
      20: astore_2
      21: return
    Exception table:
       from    to  target type
           7    17    20   Class java/lang/Throwable

  public void trace(java.lang.String);
    Code:
       0: getstatic     #3                  // Field disabled:Z
       3: ifeq          7
       6: return
       7: aload_0
       8: getfield      #2                  // Field logger:Lorg/apache/dubbo/common/logger/Logger;
      11: aload_0
      12: aload_1
      13: invokespecial #13                 // Method appendContextMessage:(Ljava/lang/String;)Ljava/lang/String;
      16: invokeinterface #17,  2           // InterfaceMethod org/apache/dubbo/common/logger/Logger.trace:(Ljava/lang/String;)V
      21: goto          25
      24: astore_2
      25: return
    Exception table:
       from    to  target type
           7    21    24   Class java/lang/Throwable

  public void debug(java.lang.String, java.lang.Throwable);
    Code:
       0: getstatic     #3                  // Field disabled:Z
       3: ifeq          7
       6: return
       7: aload_0
       8: getfield      #2                  // Field logger:Lorg/apache/dubbo/common/logger/Logger;
      11: aload_0
      12: aload_1
      13: invokespecial #13                 // Method appendContextMessage:(Ljava/lang/String;)Ljava/lang/String;
      16: aload_2
      17: invokeinterface #18,  3           // InterfaceMethod org/apache/dubbo/common/logger/Logger.debug:(Ljava/lang/String;Ljava/lang/Throwable;)V
      22: goto          26
      25: astore_3
      26: return
    Exception table:
       from    to  target type
           7    22    25   Class java/lang/Throwable

  public void debug(java.lang.Throwable);
    Code:
       0: getstatic     #3                  // Field disabled:Z
       3: ifeq          7
       6: return
       7: aload_0
       8: getfield      #2                  // Field logger:Lorg/apache/dubbo/common/logger/Logger;
      11: aload_1
      12: invokeinterface #19,  2           // InterfaceMethod org/apache/dubbo/common/logger/Logger.debug:(Ljava/lang/Throwable;)V
      17: goto          21
      20: astore_2
      21: return
    Exception table:
       from    to  target type
           7    17    20   Class java/lang/Throwable

  public void debug(java.lang.String);
    Code:
       0: getstatic     #3                  // Field disabled:Z
       3: ifeq          7
       6: return
       7: aload_0
       8: getfield      #2                  // Field logger:Lorg/apache/dubbo/common/logger/Logger;
      11: aload_0
      12: aload_1
      13: invokespecial #13                 // Method appendContextMessage:(Ljava/lang/String;)Ljava/lang/String;
      16: invokeinterface #20,  2           // InterfaceMethod org/apache/dubbo/common/logger/Logger.debug:(Ljava/lang/String;)V
      21: goto          25
      24: astore_2
      25: return
    Exception table:
       from    to  target type
           7    21    24   Class java/lang/Throwable

  public void info(java.lang.String, java.lang.Throwable);
    Code:
       0: getstatic     #3                  // Field disabled:Z
       3: ifeq          7
       6: return
       7: aload_0
       8: getfield      #2                  // Field logger:Lorg/apache/dubbo/common/logger/Logger;
      11: aload_0
      12: aload_1
      13: invokespecial #13                 // Method appendContextMessage:(Ljava/lang/String;)Ljava/lang/String;
      16: aload_2
      17: invokeinterface #21,  3           // InterfaceMethod org/apache/dubbo/common/logger/Logger.info:(Ljava/lang/String;Ljava/lang/Throwable;)V
      22: goto          26
      25: astore_3
      26: return
    Exception table:
       from    to  target type
           7    22    25   Class java/lang/Throwable

  public void info(java.lang.String);
    Code:
       0: getstatic     #3                  // Field disabled:Z
       3: ifeq          7
       6: return
       7: aload_0
       8: getfield      #2                  // Field logger:Lorg/apache/dubbo/common/logger/Logger;
      11: aload_0
      12: aload_1
      13: invokespecial #13                 // Method appendContextMessage:(Ljava/lang/String;)Ljava/lang/String;
      16: invokeinterface #22,  2           // InterfaceMethod org/apache/dubbo/common/logger/Logger.info:(Ljava/lang/String;)V
      21: goto          25
      24: astore_2
      25: return
    Exception table:
       from    to  target type
           7    21    24   Class java/lang/Throwable

  public void warn(java.lang.String, java.lang.Throwable);
    Code:
       0: getstatic     #3                  // Field disabled:Z
       3: ifeq          7
       6: return
       7: aload_0
       8: getfield      #2                  // Field logger:Lorg/apache/dubbo/common/logger/Logger;
      11: aload_0
      12: aload_1
      13: invokespecial #13                 // Method appendContextMessage:(Ljava/lang/String;)Ljava/lang/String;
      16: aload_2
      17: invokeinterface #23,  3           // InterfaceMethod org/apache/dubbo/common/logger/Logger.warn:(Ljava/lang/String;Ljava/lang/Throwable;)V
      22: goto          26
      25: astore_3
      26: return
    Exception table:
       from    to  target type
           7    22    25   Class java/lang/Throwable

  public void warn(java.lang.String);
    Code:
       0: getstatic     #3                  // Field disabled:Z
       3: ifeq          7
       6: return
       7: aload_0
       8: getfield      #2                  // Field logger:Lorg/apache/dubbo/common/logger/Logger;
      11: aload_0
      12: aload_1
      13: invokespecial #13                 // Method appendContextMessage:(Ljava/lang/String;)Ljava/lang/String;
      16: invokeinterface #24,  2           // InterfaceMethod org/apache/dubbo/common/logger/Logger.warn:(Ljava/lang/String;)V
      21: goto          25
      24: astore_2
      25: return
    Exception table:
       from    to  target type
           7    21    24   Class java/lang/Throwable

  public void error(java.lang.String, java.lang.Throwable);
    Code:
       0: getstatic     #3                  // Field disabled:Z
       3: ifeq          7
       6: return
       7: aload_0
       8: getfield      #2                  // Field logger:Lorg/apache/dubbo/common/logger/Logger;
      11: aload_0
      12: aload_1
      13: invokespecial #13                 // Method appendContextMessage:(Ljava/lang/String;)Ljava/lang/String;
      16: aload_2
      17: invokeinterface #25,  3           // InterfaceMethod org/apache/dubbo/common/logger/Logger.error:(Ljava/lang/String;Ljava/lang/Throwable;)V
      22: goto          26
      25: astore_3
      26: return
    Exception table:
       from    to  target type
           7    22    25   Class java/lang/Throwable

  public void error(java.lang.String);
    Code:
       0: getstatic     #3                  // Field disabled:Z
       3: ifeq          7
       6: return
       7: aload_0
       8: getfield      #2                  // Field logger:Lorg/apache/dubbo/common/logger/Logger;
      11: aload_0
      12: aload_1
      13: invokespecial #13                 // Method appendContextMessage:(Ljava/lang/String;)Ljava/lang/String;
      16: invokeinterface #26,  2           // InterfaceMethod org/apache/dubbo/common/logger/Logger.error:(Ljava/lang/String;)V
      21: goto          25
      24: astore_2
      25: return
    Exception table:
       from    to  target type
           7    21    24   Class java/lang/Throwable

  public void error(java.lang.Throwable);
    Code:
       0: getstatic     #3                  // Field disabled:Z
       3: ifeq          7
       6: return
       7: aload_0
       8: getfield      #2                  // Field logger:Lorg/apache/dubbo/common/logger/Logger;
      11: aload_1
      12: invokeinterface #27,  2           // InterfaceMethod org/apache/dubbo/common/logger/Logger.error:(Ljava/lang/Throwable;)V
      17: goto          21
      20: astore_2
      21: return
    Exception table:
       from    to  target type
           7    17    20   Class java/lang/Throwable

  public void info(java.lang.Throwable);
    Code:
       0: getstatic     #3                  // Field disabled:Z
       3: ifeq          7
       6: return
       7: aload_0
       8: getfield      #2                  // Field logger:Lorg/apache/dubbo/common/logger/Logger;
      11: aload_1
      12: invokeinterface #28,  2           // InterfaceMethod org/apache/dubbo/common/logger/Logger.info:(Ljava/lang/Throwable;)V
      17: goto          21
      20: astore_2
      21: return
    Exception table:
       from    to  target type
           7    17    20   Class java/lang/Throwable

  public void warn(java.lang.Throwable);
    Code:
       0: getstatic     #3                  // Field disabled:Z
       3: ifeq          7
       6: return
       7: aload_0
       8: getfield      #2                  // Field logger:Lorg/apache/dubbo/common/logger/Logger;
      11: aload_1
      12: invokeinterface #29,  2           // InterfaceMethod org/apache/dubbo/common/logger/Logger.warn:(Ljava/lang/Throwable;)V
      17: goto          21
      20: astore_2
      21: return
    Exception table:
       from    to  target type
           7    17    20   Class java/lang/Throwable

  public boolean isTraceEnabled();
    Code:
       0: getstatic     #3                  // Field disabled:Z
       3: ifeq          8
       6: iconst_0
       7: ireturn
       8: aload_0
       9: getfield      #2                  // Field logger:Lorg/apache/dubbo/common/logger/Logger;
      12: invokeinterface #30,  1           // InterfaceMethod org/apache/dubbo/common/logger/Logger.isTraceEnabled:()Z
      17: ireturn
      18: astore_1
      19: iconst_0
      20: ireturn
    Exception table:
       from    to  target type
           8    17    18   Class java/lang/Throwable

  public boolean isDebugEnabled();
    Code:
       0: getstatic     #3                  // Field disabled:Z
       3: ifeq          8
       6: iconst_0
       7: ireturn
       8: aload_0
       9: getfield      #2                  // Field logger:Lorg/apache/dubbo/common/logger/Logger;
      12: invokeinterface #31,  1           // InterfaceMethod org/apache/dubbo/common/logger/Logger.isDebugEnabled:()Z
      17: ireturn
      18: astore_1
      19: iconst_0
      20: ireturn
    Exception table:
       from    to  target type
           8    17    18   Class java/lang/Throwable

  public boolean isInfoEnabled();
    Code:
       0: getstatic     #3                  // Field disabled:Z
       3: ifeq          8
       6: iconst_0
       7: ireturn
       8: aload_0
       9: getfield      #2                  // Field logger:Lorg/apache/dubbo/common/logger/Logger;
      12: invokeinterface #32,  1           // InterfaceMethod org/apache/dubbo/common/logger/Logger.isInfoEnabled:()Z
      17: ireturn
      18: astore_1
      19: iconst_0
      20: ireturn
    Exception table:
       from    to  target type
           8    17    18   Class java/lang/Throwable

  public boolean isWarnEnabled();
    Code:
       0: getstatic     #3                  // Field disabled:Z
       3: ifeq          8
       6: iconst_0
       7: ireturn
       8: aload_0
       9: getfield      #2                  // Field logger:Lorg/apache/dubbo/common/logger/Logger;
      12: invokeinterface #33,  1           // InterfaceMethod org/apache/dubbo/common/logger/Logger.isWarnEnabled:()Z
      17: ireturn
      18: astore_1
      19: iconst_0
      20: ireturn
    Exception table:
       from    to  target type
           8    17    18   Class java/lang/Throwable

  public boolean isErrorEnabled();
    Code:
       0: getstatic     #3                  // Field disabled:Z
       3: ifeq          8
       6: iconst_0
       7: ireturn
       8: aload_0
       9: getfield      #2                  // Field logger:Lorg/apache/dubbo/common/logger/Logger;
      12: invokeinterface #34,  1           // InterfaceMethod org/apache/dubbo/common/logger/Logger.isErrorEnabled:()Z
      17: ireturn
      18: astore_1
      19: iconst_0
      20: ireturn
    Exception table:
       from    to  target type
           8    17    18   Class java/lang/Throwable

  static {};
    Code:
       0: iconst_0
       1: putstatic     #3                  // Field disabled:Z
       4: return
}
