Compiled from "FailsafeErrorTypeAwareLogger.java"
public class org.apache.dubbo.common.logger.support.FailsafeErrorTypeAwareLogger extends org.apache.dubbo.common.logger.support.FailsafeLogger implements org.apache.dubbo.common.logger.ErrorTypeAwareLogger {
  private static final java.lang.String INSTRUCTIONS_URL;

  private static final java.util.regex.Pattern ERROR_CODE_PATTERN;

  public org.apache.dubbo.common.logger.support.FailsafeErrorTypeAwareLogger(org.apache.dubbo.common.logger.Logger);
    Code:
       0: aload_0
       1: aload_1
       2: invokespecial #1                  // Method org/apache/dubbo/common/logger/support/FailsafeLogger."<init>":(Lorg/apache/dubbo/common/logger/Logger;)V
       5: return

  private java.lang.String appendContextMessageWithInstructions(java.lang.String, java.lang.String, java.lang.String, java.lang.String);
    Code:
       0: new           #2                  // class java/lang/StringBuilder
       3: dup
       4: invokespecial #3                  // Method java/lang/StringBuilder."<init>":()V
       7: ldc           #4                  // String  [DUBBO]
       9: invokevirtual #5                  // Method java/lang/StringBuilder.append:(Ljava/lang/String;)Ljava/lang/StringBuilder;
      12: aload         4
      14: invokevirtual #5                  // Method java/lang/StringBuilder.append:(Ljava/lang/String;)Ljava/lang/StringBuilder;
      17: ldc           #6                  // String , dubbo version:
      19: invokevirtual #5                  // Method java/lang/StringBuilder.append:(Ljava/lang/String;)Ljava/lang/StringBuilder;
      22: invokestatic  #7                  // Method org/apache/dubbo/common/Version.getVersion:()Ljava/lang/String;
      25: invokevirtual #5                  // Method java/lang/StringBuilder.append:(Ljava/lang/String;)Ljava/lang/StringBuilder;
      28: ldc           #8                  // String , current host:
      30: invokevirtual #5                  // Method java/lang/StringBuilder.append:(Ljava/lang/String;)Ljava/lang/StringBuilder;
      33: invokestatic  #9                  // Method org/apache/dubbo/common/utils/NetUtils.getLocalHost:()Ljava/lang/String;
      36: invokevirtual #5                  // Method java/lang/StringBuilder.append:(Ljava/lang/String;)Ljava/lang/StringBuilder;
      39: ldc           #10                 // String , error code:
      41: invokevirtual #5                  // Method java/lang/StringBuilder.append:(Ljava/lang/String;)Ljava/lang/StringBuilder;
      44: aload_1
      45: invokevirtual #5                  // Method java/lang/StringBuilder.append:(Ljava/lang/String;)Ljava/lang/StringBuilder;
      48: ldc           #11                 // String . This may be caused by
      50: invokevirtual #5                  // Method java/lang/StringBuilder.append:(Ljava/lang/String;)Ljava/lang/StringBuilder;
      53: aload_2
      54: invokevirtual #5                  // Method java/lang/StringBuilder.append:(Ljava/lang/String;)Ljava/lang/StringBuilder;
      57: ldc           #12                 // String , go to
      59: invokevirtual #5                  // Method java/lang/StringBuilder.append:(Ljava/lang/String;)Ljava/lang/StringBuilder;
      62: aload_0
      63: aload_1
      64: invokespecial #13                 // Method getErrorUrl:(Ljava/lang/String;)Ljava/lang/String;
      67: invokevirtual #5                  // Method java/lang/StringBuilder.append:(Ljava/lang/String;)Ljava/lang/StringBuilder;
      70: ldc           #14                 // String  to find instructions.
      72: invokevirtual #5                  // Method java/lang/StringBuilder.append:(Ljava/lang/String;)Ljava/lang/StringBuilder;
      75: aload_3
      76: invokevirtual #5                  // Method java/lang/StringBuilder.append:(Ljava/lang/String;)Ljava/lang/StringBuilder;
      79: invokevirtual #15                 // Method java/lang/StringBuilder.toString:()Ljava/lang/String;
      82: areturn

  private java.lang.String getErrorUrl(java.lang.String);
    Code:
       0: aload_1
       1: invokevirtual #16                 // Method java/lang/String.trim:()Ljava/lang/String;
       4: astore_2
       5: getstatic     #17                 // Field ERROR_CODE_PATTERN:Ljava/util/regex/Pattern;
       8: aload_2
       9: invokevirtual #18                 // Method java/util/regex/Pattern.matcher:(Ljava/lang/CharSequence;)Ljava/util/regex/Matcher;
      12: invokevirtual #19                 // Method java/util/regex/Matcher.matches:()Z
      15: ifne          49
      18: aload_0
      19: new           #2                  // class java/lang/StringBuilder
      22: dup
      23: invokespecial #3                  // Method java/lang/StringBuilder."<init>":()V
      26: ldc           #20                 // String Invalid error code:
      28: invokevirtual #5                  // Method java/lang/StringBuilder.append:(Ljava/lang/String;)Ljava/lang/StringBuilder;
      31: aload_1
      32: invokevirtual #5                  // Method java/lang/StringBuilder.append:(Ljava/lang/String;)Ljava/lang/StringBuilder;
      35: ldc           #21                 // String , the format of error code is: X-X (where X is a number).
      37: invokevirtual #5                  // Method java/lang/StringBuilder.append:(Ljava/lang/String;)Ljava/lang/StringBuilder;
      40: invokevirtual #15                 // Method java/lang/StringBuilder.toString:()Ljava/lang/String;
      43: invokevirtual #22                 // Method error:(Ljava/lang/String;)V
      46: ldc           #23                 // String
      48: areturn
      49: aload_2
      50: ldc           #24                 // String [-]
      52: invokevirtual #25                 // Method java/lang/String.split:(Ljava/lang/String;)[Ljava/lang/String;
      55: astore_3
      56: iconst_2
      57: newarray       int
      59: astore        4
      61: aload         4
      63: iconst_0
      64: aload_3
      65: iconst_0
      66: aaload
      67: invokestatic  #26                 // Method java/lang/Integer.parseInt:(Ljava/lang/String;)I
      70: iastore
      71: aload         4
      73: iconst_1
      74: aload_3
      75: iconst_1
      76: aaload
      77: invokestatic  #26                 // Method java/lang/Integer.parseInt:(Ljava/lang/String;)I
      80: iastore
      81: goto          119
      84: astore        5
      86: aload_0
      87: new           #2                  // class java/lang/StringBuilder
      90: dup
      91: invokespecial #3                  // Method java/lang/StringBuilder."<init>":()V
      94: ldc           #20                 // String Invalid error code:
      96: invokevirtual #5                  // Method java/lang/StringBuilder.append:(Ljava/lang/String;)Ljava/lang/StringBuilder;
      99: aload_1
     100: invokevirtual #5                  // Method java/lang/StringBuilder.append:(Ljava/lang/String;)Ljava/lang/StringBuilder;
     103: ldc           #21                 // String , the format of error code is: X-X (where X is a number).
     105: invokevirtual #5                  // Method java/lang/StringBuilder.append:(Ljava/lang/String;)Ljava/lang/StringBuilder;
     108: invokevirtual #15                 // Method java/lang/StringBuilder.toString:()Ljava/lang/String;
     111: aload         5
     113: invokevirtual #28                 // Method error:(Ljava/lang/String;Ljava/lang/Throwable;)V
     116: ldc           #23                 // String
     118: areturn
     119: ldc           #30                 // String https://dubbo.apache.org/faq/%d/%d
     121: iconst_2
     122: anewarray     #31                 // class java/lang/Object
     125: dup
     126: iconst_0
     127: aload         4
     129: iconst_0
     130: iaload
     131: invokestatic  #32                 // Method java/lang/Integer.valueOf:(I)Ljava/lang/Integer;
     134: aastore
     135: dup
     136: iconst_1
     137: aload         4
     139: iconst_1
     140: iaload
     141: invokestatic  #32                 // Method java/lang/Integer.valueOf:(I)Ljava/lang/Integer;
     144: aastore
     145: invokestatic  #33                 // Method java/lang/String.format:(Ljava/lang/String;[Ljava/lang/Object;)Ljava/lang/String;
     148: areturn
    Exception table:
       from    to  target type
          61    81    84   Class java/lang/NumberFormatException

  public void warn(java.lang.String, java.lang.String, java.lang.String, java.lang.String);
    Code:
       0: invokestatic  #34                 // Method getDisabled:()Z
       3: ifeq          7
       6: return
       7: aload_0
       8: invokevirtual #35                 // Method getLogger:()Lorg/apache/dubbo/common/logger/Logger;
      11: aload_0
      12: aload_1
      13: aload_2
      14: aload_3
      15: aload         4
      17: invokespecial #36                 // Method appendContextMessageWithInstructions:(Ljava/lang/String;Ljava/lang/String;Ljava/lang/String;Ljava/lang/String;)Ljava/lang/String;
      20: invokeinterface #37,  2           // InterfaceMethod org/apache/dubbo/common/logger/Logger.warn:(Ljava/lang/String;)V
      25: goto          30
      28: astore        5
      30: return
    Exception table:
       from    to  target type
           7    25    28   Class java/lang/Throwable

  public void warn(java.lang.String, java.lang.String, java.lang.String, java.lang.String, java.lang.Throwable);
    Code:
       0: invokestatic  #34                 // Method getDisabled:()Z
       3: ifeq          7
       6: return
       7: aload_0
       8: invokevirtual #35                 // Method getLogger:()Lorg/apache/dubbo/common/logger/Logger;
      11: aload_0
      12: aload_1
      13: aload_2
      14: aload_3
      15: aload         4
      17: invokespecial #36                 // Method appendContextMessageWithInstructions:(Ljava/lang/String;Ljava/lang/String;Ljava/lang/String;Ljava/lang/String;)Ljava/lang/String;
      20: aload         5
      22: invokeinterface #39,  3           // InterfaceMethod org/apache/dubbo/common/logger/Logger.warn:(Ljava/lang/String;Ljava/lang/Throwable;)V
      27: goto          32
      30: astore        6
      32: return
    Exception table:
       from    to  target type
           7    27    30   Class java/lang/Throwable

  public void error(java.lang.String, java.lang.String, java.lang.String, java.lang.String);
    Code:
       0: invokestatic  #34                 // Method getDisabled:()Z
       3: ifeq          7
       6: return
       7: aload_0
       8: invokevirtual #35                 // Method getLogger:()Lorg/apache/dubbo/common/logger/Logger;
      11: aload_0
      12: aload_1
      13: aload_2
      14: aload_3
      15: aload         4
      17: invokespecial #36                 // Method appendContextMessageWithInstructions:(Ljava/lang/String;Ljava/lang/String;Ljava/lang/String;Ljava/lang/String;)Ljava/lang/String;
      20: invokeinterface #40,  2           // InterfaceMethod org/apache/dubbo/common/logger/Logger.error:(Ljava/lang/String;)V
      25: goto          30
      28: astore        5
      30: return
    Exception table:
       from    to  target type
           7    25    28   Class java/lang/Throwable

  public void error(java.lang.String, java.lang.String, java.lang.String, java.lang.String, java.lang.Throwable);
    Code:
       0: invokestatic  #34                 // Method getDisabled:()Z
       3: ifeq          7
       6: return
       7: aload_0
       8: invokevirtual #35                 // Method getLogger:()Lorg/apache/dubbo/common/logger/Logger;
      11: aload_0
      12: aload_1
      13: aload_2
      14: aload_3
      15: aload         4
      17: invokespecial #36                 // Method appendContextMessageWithInstructions:(Ljava/lang/String;Ljava/lang/String;Ljava/lang/String;Ljava/lang/String;)Ljava/lang/String;
      20: aload         5
      22: invokeinterface #41,  3           // InterfaceMethod org/apache/dubbo/common/logger/Logger.error:(Ljava/lang/String;Ljava/lang/Throwable;)V
      27: goto          32
      30: astore        6
      32: return
    Exception table:
       from    to  target type
           7    27    30   Class java/lang/Throwable

  static {};
    Code:
       0: ldc           #42                 // String \\d+-\\d+
       2: invokestatic  #43                 // Method java/util/regex/Pattern.compile:(Ljava/lang/String;)Ljava/util/regex/Pattern;
       5: putstatic     #17                 // Field ERROR_CODE_PATTERN:Ljava/util/regex/Pattern;
       8: return
}
