Compiled from "DefaultMetricsService.java"
public class org.apache.dubbo.metrics.service.DefaultMetricsService implements org.apache.dubbo.metrics.service.MetricsService {
  protected final java.util.List<org.apache.dubbo.metrics.collector.MetricsCollector> collectors;

  public org.apache.dubbo.metrics.service.DefaultMetricsService(org.apache.dubbo.rpc.model.ApplicationModel);
    Code:
       0: aload_0
       1: invokespecial #1                  // Method java/lang/Object."<init>":()V
       4: aload_0
       5: new           #2                  // class java/util/ArrayList
       8: dup
       9: invokespecial #3                  // Method java/util/ArrayList."<init>":()V
      12: putfield      #4                  // Field collectors:Ljava/util/List;
      15: aload_0
      16: getfield      #4                  // Field collectors:Ljava/util/List;
      19: aload_1
      20: invokevirtual #5                  // Method org/apache/dubbo/rpc/model/ApplicationModel.getBeanFactory:()Lorg/apache/dubbo/common/beans/factory/ScopeBeanFactory;
      23: ldc           #6                  // class org/apache/dubbo/metrics/collector/MetricsCollector
      25: invokevirtual #7                  // Method org/apache/dubbo/common/beans/factory/ScopeBeanFactory.getBeansOfType:(Ljava/lang/Class;)Ljava/util/List;
      28: invokeinterface #8,  2            // InterfaceMethod java/util/List.addAll:(Ljava/util/Collection;)Z
      33: pop
      34: return

  public java.util.Map<org.apache.dubbo.metrics.model.MetricsCategory, java.util.List<org.apache.dubbo.metrics.service.MetricsEntity>> getMetricsByCategories(java.util.List<org.apache.dubbo.metrics.model.MetricsCategory>);
    Code:
       0: aload_0
       1: aconst_null
       2: aload_1
       3: invokevirtual #9                  // Method getMetricsByCategories:(Ljava/lang/String;Ljava/util/List;)Ljava/util/Map;
       6: areturn

  public java.util.Map<org.apache.dubbo.metrics.model.MetricsCategory, java.util.List<org.apache.dubbo.metrics.service.MetricsEntity>> getMetricsByCategories(java.lang.String, java.util.List<org.apache.dubbo.metrics.model.MetricsCategory>);
    Code:
       0: aload_0
       1: aload_1
       2: aconst_null
       3: aconst_null
       4: aload_2
       5: invokevirtual #10                 // Method getMetricsByCategories:(Ljava/lang/String;Ljava/lang/String;[Ljava/lang/Class;Ljava/util/List;)Ljava/util/Map;
       8: areturn

  public java.util.Map<org.apache.dubbo.metrics.model.MetricsCategory, java.util.List<org.apache.dubbo.metrics.service.MetricsEntity>> getMetricsByCategories(java.lang.String, java.lang.String, java.lang.Class<?>[], java.util.List<org.apache.dubbo.metrics.model.MetricsCategory>);
    Code:
       0: new           #11                 // class java/util/HashMap
       3: dup
       4: invokespecial #12                 // Method java/util/HashMap."<init>":()V
       7: astore        5
       9: aload_0
      10: getfield      #4                  // Field collectors:Ljava/util/List;
      13: invokeinterface #13,  1           // InterfaceMethod java/util/List.iterator:()Ljava/util/Iterator;
      18: astore        6
      20: aload         6
      22: invokeinterface #14,  1           // InterfaceMethod java/util/Iterator.hasNext:()Z
      27: ifeq          139
      30: aload         6
      32: invokeinterface #15,  1           // InterfaceMethod java/util/Iterator.next:()Ljava/lang/Object;
      37: checkcast     #6                  // class org/apache/dubbo/metrics/collector/MetricsCollector
      40: astore        7
      42: aload         7
      44: invokeinterface #16,  1           // InterfaceMethod org/apache/dubbo/metrics/collector/MetricsCollector.collect:()Ljava/util/List;
      49: astore        8
      51: aload         8
      53: invokeinterface #13,  1           // InterfaceMethod java/util/List.iterator:()Ljava/util/Iterator;
      58: astore        9
      60: aload         9
      62: invokeinterface #14,  1           // InterfaceMethod java/util/Iterator.hasNext:()Z
      67: ifeq          136
      70: aload         9
      72: invokeinterface #15,  1           // InterfaceMethod java/util/Iterator.next:()Ljava/lang/Object;
      77: checkcast     #17                 // class org/apache/dubbo/metrics/model/sample/MetricSample
      80: astore        10
      82: aload         4
      84: aload         10
      86: invokevirtual #18                 // Method org/apache/dubbo/metrics/model/sample/MetricSample.getCategory:()Lorg/apache/dubbo/metrics/model/MetricsCategory;
      89: invokeinterface #19,  2           // InterfaceMethod java/util/List.contains:(Ljava/lang/Object;)Z
      94: ifeq          133
      97: aload         5
      99: aload         10
     101: invokevirtual #18                 // Method org/apache/dubbo/metrics/model/sample/MetricSample.getCategory:()Lorg/apache/dubbo/metrics/model/MetricsCategory;
     104: invokedynamic #20,  0             // InvokeDynamic #0:apply:()Ljava/util/function/Function;
     109: invokeinterface #21,  3           // InterfaceMethod java/util/Map.computeIfAbsent:(Ljava/lang/Object;Ljava/util/function/Function;)Ljava/lang/Object;
     114: checkcast     #22                 // class java/util/List
     117: astore        11
     119: aload         11
     121: aload_0
     122: aload         10
     124: invokespecial #23                 // Method sampleToEntity:(Lorg/apache/dubbo/metrics/model/sample/MetricSample;)Lorg/apache/dubbo/metrics/service/MetricsEntity;
     127: invokeinterface #24,  2           // InterfaceMethod java/util/List.add:(Ljava/lang/Object;)Z
     132: pop
     133: goto          60
     136: goto          20
     139: aload         5
     141: areturn

  private org.apache.dubbo.metrics.service.MetricsEntity sampleToEntity(org.apache.dubbo.metrics.model.sample.MetricSample);
    Code:
       0: new           #25                 // class org/apache/dubbo/metrics/service/MetricsEntity
       3: dup
       4: invokespecial #26                 // Method org/apache/dubbo/metrics/service/MetricsEntity."<init>":()V
       7: astore_2
       8: aload_2
       9: aload_1
      10: invokevirtual #27                 // Method org/apache/dubbo/metrics/model/sample/MetricSample.getName:()Ljava/lang/String;
      13: invokevirtual #28                 // Method org/apache/dubbo/metrics/service/MetricsEntity.setName:(Ljava/lang/String;)V
      16: aload_2
      17: aload_1
      18: invokevirtual #29                 // Method org/apache/dubbo/metrics/model/sample/MetricSample.getTags:()Ljava/util/Map;
      21: invokevirtual #30                 // Method org/apache/dubbo/metrics/service/MetricsEntity.setTags:(Ljava/util/Map;)V
      24: aload_2
      25: aload_1
      26: invokevirtual #18                 // Method org/apache/dubbo/metrics/model/sample/MetricSample.getCategory:()Lorg/apache/dubbo/metrics/model/MetricsCategory;
      29: invokevirtual #31                 // Method org/apache/dubbo/metrics/service/MetricsEntity.setCategory:(Lorg/apache/dubbo/metrics/model/MetricsCategory;)V
      32: getstatic     #32                 // Field org/apache/dubbo/metrics/service/DefaultMetricsService$1.$SwitchMap$org$apache$dubbo$metrics$model$sample$MetricSample$Type:[I
      35: aload_1
      36: invokevirtual #33                 // Method org/apache/dubbo/metrics/model/sample/MetricSample.getType:()Lorg/apache/dubbo/metrics/model/sample/MetricSample$Type;
      39: invokevirtual #34                 // Method org/apache/dubbo/metrics/model/sample/MetricSample$Type.ordinal:()I
      42: iaload
      43: tableswitch   { // 1 to 5
                     1: 76
                     2: 104
                     3: 104
                     4: 104
                     5: 104
               default: 104
          }
      76: aload_1
      77: checkcast     #35                 // class org/apache/dubbo/metrics/model/sample/GaugeMetricSample
      80: astore_3
      81: aload_2
      82: aload_3
      83: invokevirtual #36                 // Method org/apache/dubbo/metrics/model/sample/GaugeMetricSample.getApply:()Ljava/util/function/ToDoubleFunction;
      86: aload_3
      87: invokevirtual #37                 // Method org/apache/dubbo/metrics/model/sample/GaugeMetricSample.getValue:()Ljava/lang/Object;
      90: invokeinterface #38,  2           // InterfaceMethod java/util/function/ToDoubleFunction.applyAsDouble:(Ljava/lang/Object;)D
      95: invokestatic  #39                 // Method java/lang/Double.valueOf:(D)Ljava/lang/Double;
      98: invokevirtual #40                 // Method org/apache/dubbo/metrics/service/MetricsEntity.setValue:(Ljava/lang/Object;)V
     101: goto          104
     104: aload_2
     105: areturn

  private static java.util.List lambda$getMetricsByCategories$0(org.apache.dubbo.metrics.model.MetricsCategory);
    Code:
       0: new           #2                  // class java/util/ArrayList
       3: dup
       4: invokespecial #3                  // Method java/util/ArrayList."<init>":()V
       7: areturn
}
