Compiled from "MetricsEntity.java"
public class org.apache.dubbo.metrics.service.MetricsEntity {
  private java.lang.String name;

  private java.util.Map<java.lang.String, java.lang.String> tags;

  private org.apache.dubbo.metrics.model.MetricsCategory category;

  private java.lang.Object value;

  public org.apache.dubbo.metrics.service.MetricsEntity();
    Code:
       0: aload_0
       1: invokespecial #1                  // Method java/lang/Object."<init>":()V
       4: return

  public org.apache.dubbo.metrics.service.MetricsEntity(java.lang.String, java.util.Map<java.lang.String, java.lang.String>, org.apache.dubbo.metrics.model.MetricsCategory, java.lang.Object);
    Code:
       0: aload_0
       1: invokespecial #1                  // Method java/lang/Object."<init>":()V
       4: aload_0
       5: aload_1
       6: putfield      #2                  // Field name:Ljava/lang/String;
       9: aload_0
      10: aload_2
      11: putfield      #3                  // Field tags:Ljava/util/Map;
      14: aload_0
      15: aload_3
      16: putfield      #4                  // Field category:Lorg/apache/dubbo/metrics/model/MetricsCategory;
      19: aload_0
      20: aload         4
      22: putfield      #5                  // Field value:Ljava/lang/Object;
      25: return

  public java.lang.String getName();
    Code:
       0: aload_0
       1: getfield      #2                  // Field name:Ljava/lang/String;
       4: areturn

  public void setName(java.lang.String);
    Code:
       0: aload_0
       1: aload_1
       2: putfield      #2                  // Field name:Ljava/lang/String;
       5: return

  public java.util.Map<java.lang.String, java.lang.String> getTags();
    Code:
       0: aload_0
       1: getfield      #3                  // Field tags:Ljava/util/Map;
       4: areturn

  public void setTags(java.util.Map<java.lang.String, java.lang.String>);
    Code:
       0: aload_0
       1: aload_1
       2: putfield      #3                  // Field tags:Ljava/util/Map;
       5: return

  public org.apache.dubbo.metrics.model.MetricsCategory getCategory();
    Code:
       0: aload_0
       1: getfield      #4                  // Field category:Lorg/apache/dubbo/metrics/model/MetricsCategory;
       4: areturn

  public void setCategory(org.apache.dubbo.metrics.model.MetricsCategory);
    Code:
       0: aload_0
       1: aload_1
       2: putfield      #4                  // Field category:Lorg/apache/dubbo/metrics/model/MetricsCategory;
       5: return

  public java.lang.Object getValue();
    Code:
       0: aload_0
       1: getfield      #5                  // Field value:Ljava/lang/Object;
       4: areturn

  public void setValue(java.lang.Object);
    Code:
       0: aload_0
       1: aload_1
       2: putfield      #5                  // Field value:Ljava/lang/Object;
       5: return

  public boolean equals(java.lang.Object);
    Code:
       0: aload_0
       1: aload_1
       2: if_acmpne     7
       5: iconst_1
       6: ireturn
       7: aload_1
       8: ifnull        22
      11: aload_0
      12: invokevirtual #6                  // Method java/lang/Object.getClass:()Ljava/lang/Class;
      15: aload_1
      16: invokevirtual #6                  // Method java/lang/Object.getClass:()Ljava/lang/Class;
      19: if_acmpeq     24
      22: iconst_0
      23: ireturn
      24: aload_1
      25: checkcast     #7                  // class org/apache/dubbo/metrics/service/MetricsEntity
      28: astore_2
      29: aload_0
      30: getfield      #2                  // Field name:Ljava/lang/String;
      33: aload_2
      34: getfield      #2                  // Field name:Ljava/lang/String;
      37: invokestatic  #8                  // Method java/util/Objects.equals:(Ljava/lang/Object;Ljava/lang/Object;)Z
      40: ifeq          89
      43: aload_0
      44: getfield      #3                  // Field tags:Ljava/util/Map;
      47: aload_2
      48: getfield      #3                  // Field tags:Ljava/util/Map;
      51: invokestatic  #8                  // Method java/util/Objects.equals:(Ljava/lang/Object;Ljava/lang/Object;)Z
      54: ifeq          89
      57: aload_0
      58: getfield      #4                  // Field category:Lorg/apache/dubbo/metrics/model/MetricsCategory;
      61: aload_2
      62: getfield      #4                  // Field category:Lorg/apache/dubbo/metrics/model/MetricsCategory;
      65: invokestatic  #8                  // Method java/util/Objects.equals:(Ljava/lang/Object;Ljava/lang/Object;)Z
      68: ifeq          89
      71: aload_0
      72: getfield      #5                  // Field value:Ljava/lang/Object;
      75: aload_2
      76: getfield      #5                  // Field value:Ljava/lang/Object;
      79: invokestatic  #8                  // Method java/util/Objects.equals:(Ljava/lang/Object;Ljava/lang/Object;)Z
      82: ifeq          89
      85: iconst_1
      86: goto          90
      89: iconst_0
      90: ireturn

  public int hashCode();
    Code:
       0: iconst_4
       1: anewarray     #9                  // class java/lang/Object
       4: dup
       5: iconst_0
       6: aload_0
       7: getfield      #2                  // Field name:Ljava/lang/String;
      10: aastore
      11: dup
      12: iconst_1
      13: aload_0
      14: getfield      #3                  // Field tags:Ljava/util/Map;
      17: aastore
      18: dup
      19: iconst_2
      20: aload_0
      21: getfield      #4                  // Field category:Lorg/apache/dubbo/metrics/model/MetricsCategory;
      24: aastore
      25: dup
      26: iconst_3
      27: aload_0
      28: getfield      #5                  // Field value:Ljava/lang/Object;
      31: aastore
      32: invokestatic  #10                 // Method java/util/Objects.hash:([Ljava/lang/Object;)I
      35: ireturn
}
