Compiled from "AbstractMetricsReporter.java"
public abstract class org.apache.dubbo.metrics.report.AbstractMetricsReporter implements org.apache.dubbo.metrics.report.MetricsReporter {
  private final org.apache.dubbo.common.logger.ErrorTypeAwareLogger logger;

  private final java.util.concurrent.atomic.AtomicBoolean initialized;

  protected final org.apache.dubbo.common.URL url;

  protected final java.util.List<org.apache.dubbo.metrics.collector.MetricsCollector> collectors;

  protected final java.util.List<io.micrometer.core.instrument.binder.MeterBinder> instanceHolder;

  protected final io.micrometer.core.instrument.composite.CompositeMeterRegistry compositeRegistry;

  private final org.apache.dubbo.rpc.model.ApplicationModel applicationModel;

  private java.util.concurrent.ScheduledExecutorService collectorSyncJobExecutor;

  private static final int DEFAULT_SCHEDULE_INITIAL_DELAY;

  private static final int DEFAULT_SCHEDULE_PERIOD;

  protected org.apache.dubbo.metrics.report.AbstractMetricsReporter(org.apache.dubbo.common.URL, org.apache.dubbo.rpc.model.ApplicationModel);
    Code:
       0: aload_0
       1: invokespecial #3                  // Method java/lang/Object."<init>":()V
       4: aload_0
       5: ldc           #4                  // class org/apache/dubbo/metrics/report/AbstractMetricsReporter
       7: invokestatic  #5                  // Method org/apache/dubbo/common/logger/LoggerFactory.getErrorTypeAwareLogger:(Ljava/lang/Class;)Lorg/apache/dubbo/common/logger/ErrorTypeAwareLogger;
      10: putfield      #6                  // Field logger:Lorg/apache/dubbo/common/logger/ErrorTypeAwareLogger;
      13: aload_0
      14: new           #7                  // class java/util/concurrent/atomic/AtomicBoolean
      17: dup
      18: iconst_0
      19: invokespecial #8                  // Method java/util/concurrent/atomic/AtomicBoolean."<init>":(Z)V
      22: putfield      #9                  // Field initialized:Ljava/util/concurrent/atomic/AtomicBoolean;
      25: aload_0
      26: new           #10                 // class java/util/ArrayList
      29: dup
      30: invokespecial #11                 // Method java/util/ArrayList."<init>":()V
      33: putfield      #12                 // Field collectors:Ljava/util/List;
      36: aload_0
      37: new           #10                 // class java/util/ArrayList
      40: dup
      41: invokespecial #11                 // Method java/util/ArrayList."<init>":()V
      44: putfield      #13                 // Field instanceHolder:Ljava/util/List;
      47: aload_0
      48: aconst_null
      49: putfield      #14                 // Field collectorSyncJobExecutor:Ljava/util/concurrent/ScheduledExecutorService;
      52: aload_0
      53: aload_1
      54: putfield      #15                 // Field url:Lorg/apache/dubbo/common/URL;
      57: aload_0
      58: aload_2
      59: putfield      #16                 // Field applicationModel:Lorg/apache/dubbo/rpc/model/ApplicationModel;
      62: aload_0
      63: aload_2
      64: invokestatic  #17                 // Method org/apache/dubbo/metrics/MetricsGlobalRegistry.getCompositeRegistry:(Lorg/apache/dubbo/rpc/model/ApplicationModel;)Lio/micrometer/core/instrument/composite/CompositeMeterRegistry;
      67: putfield      #18                 // Field compositeRegistry:Lio/micrometer/core/instrument/composite/CompositeMeterRegistry;
      70: return

  public void init();
    Code:
       0: aload_0
       1: getfield      #9                  // Field initialized:Ljava/util/concurrent/atomic/AtomicBoolean;
       4: iconst_0
       5: iconst_1
       6: invokevirtual #19                 // Method java/util/concurrent/atomic/AtomicBoolean.compareAndSet:(ZZ)Z
       9: ifeq          32
      12: aload_0
      13: invokespecial #20                 // Method addJvmMetrics:()V
      16: aload_0
      17: invokespecial #21                 // Method initCollectors:()V
      20: aload_0
      21: invokespecial #22                 // Method scheduleMetricsCollectorSyncJob:()V
      24: aload_0
      25: invokevirtual #23                 // Method doInit:()V
      28: aload_0
      29: invokespecial #24                 // Method registerDubboShutdownHook:()V
      32: return

  protected void addMeterRegistry(io.micrometer.core.instrument.MeterRegistry);
    Code:
       0: aload_0
       1: getfield      #18                 // Field compositeRegistry:Lio/micrometer/core/instrument/composite/CompositeMeterRegistry;
       4: aload_1
       5: invokevirtual #25                 // Method io/micrometer/core/instrument/composite/CompositeMeterRegistry.add:(Lio/micrometer/core/instrument/MeterRegistry;)Lio/micrometer/core/instrument/composite/CompositeMeterRegistry;
       8: pop
       9: return

  protected org.apache.dubbo.rpc.model.ApplicationModel getApplicationModel();
    Code:
       0: aload_0
       1: getfield      #16                 // Field applicationModel:Lorg/apache/dubbo/rpc/model/ApplicationModel;
       4: areturn

  private void addJvmMetrics();
    Code:
       0: aload_0
       1: getfield      #15                 // Field url:Lorg/apache/dubbo/common/URL;
       4: ldc           #26                 // String enable.jvm
       6: iconst_0
       7: invokevirtual #27                 // Method org/apache/dubbo/common/URL.getParameter:(Ljava/lang/String;Z)Z
      10: istore_1
      11: iload_1
      12: ifeq          149
      15: ldc           #28                 // String application.name
      17: aload_0
      18: getfield      #16                 // Field applicationModel:Lorg/apache/dubbo/rpc/model/ApplicationModel;
      21: invokevirtual #29                 // Method org/apache/dubbo/rpc/model/ApplicationModel.getApplicationName:()Ljava/lang/String;
      24: invokestatic  #30                 // Method java/util/Optional.ofNullable:(Ljava/lang/Object;)Ljava/util/Optional;
      27: ldc           #31                 // String
      29: invokevirtual #32                 // Method java/util/Optional.orElse:(Ljava/lang/Object;)Ljava/lang/Object;
      32: checkcast     #33                 // class java/lang/String
      35: invokestatic  #34                 // Method io/micrometer/core/instrument/Tags.of:(Ljava/lang/String;Ljava/lang/String;)Lio/micrometer/core/instrument/Tags;
      38: astore_2
      39: new           #35                 // class io/micrometer/core/instrument/binder/jvm/ClassLoaderMetrics
      42: dup
      43: aload_2
      44: invokespecial #36                 // Method io/micrometer/core/instrument/binder/jvm/ClassLoaderMetrics."<init>":(Ljava/lang/Iterable;)V
      47: aload_0
      48: getfield      #18                 // Field compositeRegistry:Lio/micrometer/core/instrument/composite/CompositeMeterRegistry;
      51: invokevirtual #37                 // Method io/micrometer/core/instrument/binder/jvm/ClassLoaderMetrics.bindTo:(Lio/micrometer/core/instrument/MeterRegistry;)V
      54: new           #38                 // class io/micrometer/core/instrument/binder/jvm/JvmMemoryMetrics
      57: dup
      58: aload_2
      59: invokespecial #39                 // Method io/micrometer/core/instrument/binder/jvm/JvmMemoryMetrics."<init>":(Ljava/lang/Iterable;)V
      62: aload_0
      63: getfield      #18                 // Field compositeRegistry:Lio/micrometer/core/instrument/composite/CompositeMeterRegistry;
      66: invokevirtual #40                 // Method io/micrometer/core/instrument/binder/jvm/JvmMemoryMetrics.bindTo:(Lio/micrometer/core/instrument/MeterRegistry;)V
      69: new           #41                 // class io/micrometer/core/instrument/binder/jvm/JvmGcMetrics
      72: dup
      73: aload_2
      74: invokespecial #42                 // Method io/micrometer/core/instrument/binder/jvm/JvmGcMetrics."<init>":(Ljava/lang/Iterable;)V
      77: astore_3
      78: aload_3
      79: aload_0
      80: getfield      #18                 // Field compositeRegistry:Lio/micrometer/core/instrument/composite/CompositeMeterRegistry;
      83: invokevirtual #43                 // Method io/micrometer/core/instrument/binder/jvm/JvmGcMetrics.bindTo:(Lio/micrometer/core/instrument/MeterRegistry;)V
      86: invokestatic  #44                 // Method java/lang/Runtime.getRuntime:()Ljava/lang/Runtime;
      89: new           #45                 // class java/lang/Thread
      92: dup
      93: aload_3
      94: dup
      95: invokevirtual #46                 // Method java/lang/Object.getClass:()Ljava/lang/Class;
      98: pop
      99: invokedynamic #47,  0             // InvokeDynamic #0:run:(Lio/micrometer/core/instrument/binder/jvm/JvmGcMetrics;)Ljava/lang/Runnable;
     104: invokespecial #48                 // Method java/lang/Thread."<init>":(Ljava/lang/Runnable;)V
     107: invokevirtual #49                 // Method java/lang/Runtime.addShutdownHook:(Ljava/lang/Thread;)V
     110: aload_0
     111: new           #50                 // class io/micrometer/core/instrument/binder/system/ProcessorMetrics
     114: dup
     115: aload_2
     116: invokespecial #51                 // Method io/micrometer/core/instrument/binder/system/ProcessorMetrics."<init>":(Ljava/lang/Iterable;)V
     119: invokespecial #52                 // Method bindTo:(Lio/micrometer/core/instrument/binder/MeterBinder;)V
     122: new           #53                 // class io/micrometer/core/instrument/binder/jvm/JvmThreadMetrics
     125: dup
     126: aload_2
     127: invokespecial #54                 // Method io/micrometer/core/instrument/binder/jvm/JvmThreadMetrics."<init>":(Ljava/lang/Iterable;)V
     130: aload_0
     131: getfield      #18                 // Field compositeRegistry:Lio/micrometer/core/instrument/composite/CompositeMeterRegistry;
     134: invokevirtual #55                 // Method io/micrometer/core/instrument/binder/jvm/JvmThreadMetrics.bindTo:(Lio/micrometer/core/instrument/MeterRegistry;)V
     137: aload_0
     138: new           #56                 // class io/micrometer/core/instrument/binder/system/UptimeMetrics
     141: dup
     142: aload_2
     143: invokespecial #57                 // Method io/micrometer/core/instrument/binder/system/UptimeMetrics."<init>":(Ljava/lang/Iterable;)V
     146: invokespecial #52                 // Method bindTo:(Lio/micrometer/core/instrument/binder/MeterBinder;)V
     149: return

  private void bindTo(io.micrometer.core.instrument.binder.MeterBinder);
    Code:
       0: aload_1
       1: aload_0
       2: getfield      #18                 // Field compositeRegistry:Lio/micrometer/core/instrument/composite/CompositeMeterRegistry;
       5: invokeinterface #58,  2           // InterfaceMethod io/micrometer/core/instrument/binder/MeterBinder.bindTo:(Lio/micrometer/core/instrument/MeterRegistry;)V
      10: aload_0
      11: getfield      #13                 // Field instanceHolder:Ljava/util/List;
      14: aload_1
      15: invokeinterface #59,  2           // InterfaceMethod java/util/List.add:(Ljava/lang/Object;)Z
      20: pop
      21: return

  private void initCollectors();
    Code:
       0: aload_0
       1: getfield      #16                 // Field applicationModel:Lorg/apache/dubbo/rpc/model/ApplicationModel;
       4: invokevirtual #60                 // Method org/apache/dubbo/rpc/model/ApplicationModel.getBeanFactory:()Lorg/apache/dubbo/common/beans/factory/ScopeBeanFactory;
       7: astore_1
       8: aload_1
       9: ldc           #61                 // class org/apache/dubbo/metrics/collector/AggregateMetricsCollector
      11: invokevirtual #62                 // Method org/apache/dubbo/common/beans/factory/ScopeBeanFactory.getOrRegisterBean:(Ljava/lang/Class;)Ljava/lang/Object;
      14: pop
      15: aload_1
      16: ldc           #63                 // class org/apache/dubbo/metrics/collector/HistogramMetricsCollector
      18: invokevirtual #62                 // Method org/apache/dubbo/common/beans/factory/ScopeBeanFactory.getOrRegisterBean:(Ljava/lang/Class;)Ljava/lang/Object;
      21: pop
      22: aload_1
      23: ldc           #64                 // class org/apache/dubbo/metrics/collector/MetricsCollector
      25: invokevirtual #65                 // Method org/apache/dubbo/common/beans/factory/ScopeBeanFactory.getBeansOfType:(Ljava/lang/Class;)Ljava/util/List;
      28: astore_2
      29: aload_0
      30: getfield      #12                 // Field collectors:Ljava/util/List;
      33: aload_2
      34: invokeinterface #66,  2           // InterfaceMethod java/util/List.addAll:(Ljava/util/Collection;)Z
      39: pop
      40: return

  private void scheduleMetricsCollectorSyncJob();
    Code:
       0: new           #67                 // class org/apache/dubbo/common/utils/NamedThreadFactory
       3: dup
       4: ldc           #68                 // String metrics-collector-sync-job
       6: iconst_1
       7: invokespecial #69                 // Method org/apache/dubbo/common/utils/NamedThreadFactory."<init>":(Ljava/lang/String;Z)V
      10: astore_1
      11: aload_0
      12: iconst_1
      13: aload_1
      14: invokestatic  #70                 // Method java/util/concurrent/Executors.newScheduledThreadPool:(ILjava/util/concurrent/ThreadFactory;)Ljava/util/concurrent/ScheduledExecutorService;
      17: putfield      #14                 // Field collectorSyncJobExecutor:Ljava/util/concurrent/ScheduledExecutorService;
      20: aload_0
      21: getfield      #14                 // Field collectorSyncJobExecutor:Ljava/util/concurrent/ScheduledExecutorService;
      24: aload_0
      25: invokedynamic #71,  0             // InvokeDynamic #1:run:(Lorg/apache/dubbo/metrics/report/AbstractMetricsReporter;)Ljava/lang/Runnable;
      30: ldc2_w        #72                 // long 5l
      33: ldc2_w        #74                 // long 3l
      36: getstatic     #76                 // Field java/util/concurrent/TimeUnit.SECONDS:Ljava/util/concurrent/TimeUnit;
      39: invokeinterface #77,  7           // InterfaceMethod java/util/concurrent/ScheduledExecutorService.scheduleWithFixedDelay:(Ljava/lang/Runnable;JJLjava/util/concurrent/TimeUnit;)Ljava/util/concurrent/ScheduledFuture;
      44: pop
      45: return

  public void refreshData();
    Code:
       0: aload_0
       1: getfield      #12                 // Field collectors:Ljava/util/List;
       4: aload_0
       5: invokedynamic #78,  0             // InvokeDynamic #2:accept:(Lorg/apache/dubbo/metrics/report/AbstractMetricsReporter;)Ljava/util/function/Consumer;
      10: invokeinterface #79,  2           // InterfaceMethod java/util/List.forEach:(Ljava/util/function/Consumer;)V
      15: return

  private static java.util.List<io.micrometer.core.instrument.Tag> getTags(org.apache.dubbo.metrics.model.sample.MetricSample);
    Code:
       0: new           #10                 // class java/util/ArrayList
       3: dup
       4: invokespecial #11                 // Method java/util/ArrayList."<init>":()V
       7: astore_1
       8: aload_0
       9: invokevirtual #80                 // Method org/apache/dubbo/metrics/model/sample/MetricSample.getTags:()Ljava/util/Map;
      12: aload_1
      13: invokedynamic #81,  0             // InvokeDynamic #3:accept:(Ljava/util/List;)Ljava/util/function/BiConsumer;
      18: invokeinterface #82,  2           // InterfaceMethod java/util/Map.forEach:(Ljava/util/function/BiConsumer;)V
      23: aload_1
      24: areturn

  private void registerDubboShutdownHook();
    Code:
       0: aload_0
       1: getfield      #16                 // Field applicationModel:Lorg/apache/dubbo/rpc/model/ApplicationModel;
       4: invokevirtual #60                 // Method org/apache/dubbo/rpc/model/ApplicationModel.getBeanFactory:()Lorg/apache/dubbo/common/beans/factory/ScopeBeanFactory;
       7: ldc           #83                 // class org/apache/dubbo/common/lang/ShutdownHookCallbacks
       9: invokevirtual #84                 // Method org/apache/dubbo/common/beans/factory/ScopeBeanFactory.getBean:(Ljava/lang/Class;)Ljava/lang/Object;
      12: checkcast     #83                 // class org/apache/dubbo/common/lang/ShutdownHookCallbacks
      15: aload_0
      16: invokedynamic #85,  0             // InvokeDynamic #4:callback:(Lorg/apache/dubbo/metrics/report/AbstractMetricsReporter;)Lorg/apache/dubbo/common/lang/ShutdownHookCallback;
      21: invokevirtual #86                 // Method org/apache/dubbo/common/lang/ShutdownHookCallbacks.addCallback:(Lorg/apache/dubbo/common/lang/ShutdownHookCallback;)Lorg/apache/dubbo/common/lang/ShutdownHookCallbacks;
      24: pop
      25: return

  public void destroy();
    Code:
       0: aload_0
       1: getfield      #14                 // Field collectorSyncJobExecutor:Ljava/util/concurrent/ScheduledExecutorService;
       4: ifnull        17
       7: aload_0
       8: getfield      #14                 // Field collectorSyncJobExecutor:Ljava/util/concurrent/ScheduledExecutorService;
      11: invokeinterface #87,  1           // InterfaceMethod java/util/concurrent/ScheduledExecutorService.shutdownNow:()Ljava/util/List;
      16: pop
      17: aload_0
      18: invokevirtual #88                 // Method doDestroy:()V
      21: return

  protected abstract void doInit();

  protected abstract void doDestroy();

  private static void lambda$getTags$1(java.util.List, java.lang.String, java.lang.String);
    Code:
       0: aload_2
       1: ifnonnull     7
       4: ldc           #31                 // String
       6: astore_2
       7: aload_0
       8: aload_1
       9: aload_2
      10: invokestatic  #89                 // InterfaceMethod io/micrometer/core/instrument/Tag.of:(Ljava/lang/String;Ljava/lang/String;)Lio/micrometer/core/instrument/Tag;
      13: invokeinterface #59,  2           // InterfaceMethod java/util/List.add:(Ljava/lang/Object;)Z
      18: pop
      19: return

  private void lambda$refreshData$0(org.apache.dubbo.metrics.collector.MetricsCollector);
    Code:
       0: aload_1
       1: invokeinterface #90,  1           // InterfaceMethod org/apache/dubbo/metrics/collector/MetricsCollector.collect:()Ljava/util/List;
       6: astore_2
       7: aload_2
       8: invokeinterface #91,  1           // InterfaceMethod java/util/List.iterator:()Ljava/util/Iterator;
      13: astore_3
      14: aload_3
      15: invokeinterface #92,  1           // InterfaceMethod java/util/Iterator.hasNext:()Z
      20: ifeq          215
      23: aload_3
      24: invokeinterface #93,  1           // InterfaceMethod java/util/Iterator.next:()Ljava/lang/Object;
      29: checkcast     #94                 // class org/apache/dubbo/metrics/model/sample/MetricSample
      32: astore        4
      34: getstatic     #95                 // Field org/apache/dubbo/metrics/report/AbstractMetricsReporter$1.$SwitchMap$org$apache$dubbo$metrics$model$sample$MetricSample$Type:[I
      37: aload         4
      39: invokevirtual #96                 // Method org/apache/dubbo/metrics/model/sample/MetricSample.getType:()Lorg/apache/dubbo/metrics/model/sample/MetricSample$Type;
      42: invokevirtual #97                 // Method org/apache/dubbo/metrics/model/sample/MetricSample$Type.ordinal:()I
      45: iaload
      46: tableswitch   { // 1 to 5
                     1: 80
                     2: 136
                     3: 185
                     4: 185
                     5: 185
               default: 188
          }
      80: aload         4
      82: checkcast     #98                 // class org/apache/dubbo/metrics/model/sample/GaugeMetricSample
      85: astore        5
      87: aload         5
      89: invokestatic  #99                 // Method getTags:(Lorg/apache/dubbo/metrics/model/sample/MetricSample;)Ljava/util/List;
      92: astore        6
      94: aload         5
      96: invokevirtual #100                // Method org/apache/dubbo/metrics/model/sample/GaugeMetricSample.getName:()Ljava/lang/String;
      99: aload         5
     101: invokevirtual #101                // Method org/apache/dubbo/metrics/model/sample/GaugeMetricSample.getValue:()Ljava/lang/Object;
     104: aload         5
     106: invokevirtual #102                // Method org/apache/dubbo/metrics/model/sample/GaugeMetricSample.getApply:()Ljava/util/function/ToDoubleFunction;
     109: invokestatic  #103                // InterfaceMethod io/micrometer/core/instrument/Gauge.builder:(Ljava/lang/String;Ljava/lang/Object;Ljava/util/function/ToDoubleFunction;)Lio/micrometer/core/instrument/Gauge$Builder;
     112: aload         5
     114: invokevirtual #104                // Method org/apache/dubbo/metrics/model/sample/GaugeMetricSample.getDescription:()Ljava/lang/String;
     117: invokevirtual #105                // Method io/micrometer/core/instrument/Gauge$Builder.description:(Ljava/lang/String;)Lio/micrometer/core/instrument/Gauge$Builder;
     120: aload         6
     122: invokevirtual #106                // Method io/micrometer/core/instrument/Gauge$Builder.tags:(Ljava/lang/Iterable;)Lio/micrometer/core/instrument/Gauge$Builder;
     125: aload_0
     126: getfield      #18                 // Field compositeRegistry:Lio/micrometer/core/instrument/composite/CompositeMeterRegistry;
     129: invokevirtual #107                // Method io/micrometer/core/instrument/Gauge$Builder.register:(Lio/micrometer/core/instrument/MeterRegistry;)Lio/micrometer/core/instrument/Gauge;
     132: pop
     133: goto          188
     136: aload         4
     138: checkcast     #108                // class org/apache/dubbo/metrics/model/sample/CounterMetricSample
     141: astore        7
     143: aload         7
     145: invokevirtual #109                // Method org/apache/dubbo/metrics/model/sample/CounterMetricSample.getName:()Ljava/lang/String;
     148: aload         7
     150: invokevirtual #110                // Method org/apache/dubbo/metrics/model/sample/CounterMetricSample.getValue:()Ljava/lang/Number;
     153: invokedynamic #111,  0            // InvokeDynamic #5:applyAsDouble:()Ljava/util/function/ToDoubleFunction;
     158: invokestatic  #112                // InterfaceMethod io/micrometer/core/instrument/FunctionCounter.builder:(Ljava/lang/String;Ljava/lang/Object;Ljava/util/function/ToDoubleFunction;)Lio/micrometer/core/instrument/FunctionCounter$Builder;
     161: aload         7
     163: invokevirtual #113                // Method org/apache/dubbo/metrics/model/sample/CounterMetricSample.getDescription:()Ljava/lang/String;
     166: invokevirtual #114                // Method io/micrometer/core/instrument/FunctionCounter$Builder.description:(Ljava/lang/String;)Lio/micrometer/core/instrument/FunctionCounter$Builder;
     169: aload         7
     171: invokestatic  #99                 // Method getTags:(Lorg/apache/dubbo/metrics/model/sample/MetricSample;)Ljava/util/List;
     174: invokevirtual #115                // Method io/micrometer/core/instrument/FunctionCounter$Builder.tags:(Ljava/lang/Iterable;)Lio/micrometer/core/instrument/FunctionCounter$Builder;
     177: aload_0
     178: getfield      #18                 // Field compositeRegistry:Lio/micrometer/core/instrument/composite/CompositeMeterRegistry;
     181: invokevirtual #116                // Method io/micrometer/core/instrument/FunctionCounter$Builder.register:(Lio/micrometer/core/instrument/MeterRegistry;)Lio/micrometer/core/instrument/FunctionCounter;
     184: pop
     185: goto          188
     188: goto          212
     191: astore        5
     193: aload_0
     194: getfield      #6                  // Field logger:Lorg/apache/dubbo/common/logger/ErrorTypeAwareLogger;
     197: ldc           #118                // String 0-13
     199: ldc           #31                 // String
     201: ldc           #31                 // String
     203: ldc           #119                // String error occurred when synchronize metrics collector.
     205: aload         5
     207: invokeinterface #120,  6          // InterfaceMethod org/apache/dubbo/common/logger/ErrorTypeAwareLogger.error:(Ljava/lang/String;Ljava/lang/String;Ljava/lang/String;Ljava/lang/String;Ljava/lang/Throwable;)V
     212: goto          14
     215: return
    Exception table:
       from    to  target type
          34   188   191   Class java/lang/Exception
}
