Compiled from "AbstractMetricsExport.java"
public abstract class org.apache.dubbo.metrics.report.AbstractMetricsExport implements org.apache.dubbo.metrics.report.MetricsExport {
  private final org.apache.dubbo.rpc.model.ApplicationModel applicationModel;

  public org.apache.dubbo.metrics.report.AbstractMetricsExport(org.apache.dubbo.rpc.model.ApplicationModel);
    Code:
       0: aload_0
       1: invokespecial #1                  // Method java/lang/Object."<init>":()V
       4: aload_0
       5: aload_1
       6: putfield      #2                  // Field applicationModel:Lorg/apache/dubbo/rpc/model/ApplicationModel;
       9: return

  public org.apache.dubbo.rpc.model.ApplicationModel getApplicationModel();
    Code:
       0: aload_0
       1: getfield      #2                  // Field applicationModel:Lorg/apache/dubbo/rpc/model/ApplicationModel;
       4: areturn

  public java.lang.String getAppName();
    Code:
       0: aload_0
       1: invokevirtual #3                  // Method getApplicationModel:()Lorg/apache/dubbo/rpc/model/ApplicationModel;
       4: invokevirtual #4                  // Method org/apache/dubbo/rpc/model/ApplicationModel.getApplicationName:()Ljava/lang/String;
       7: areturn
}
