Compiled from "AbstractMetricsReporterFactory.java"
public abstract class org.apache.dubbo.metrics.report.AbstractMetricsReporterFactory implements org.apache.dubbo.metrics.report.MetricsReporterFactory {
  private final org.apache.dubbo.rpc.model.ApplicationModel applicationModel;

  public org.apache.dubbo.metrics.report.AbstractMetricsReporterFactory(org.apache.dubbo.rpc.model.ApplicationModel);
    Code:
       0: aload_0
       1: invokespecial #1                  // Method java/lang/Object."<init>":()V
       4: aload_0
       5: aload_1
       6: putfield      #2                  // Field applicationModel:Lorg/apache/dubbo/rpc/model/ApplicationModel;
       9: return

  protected org.apache.dubbo.rpc.model.ApplicationModel getApplicationModel();
    Code:
       0: aload_0
       1: getfield      #2                  // Field applicationModel:Lorg/apache/dubbo/rpc/model/ApplicationModel;
       4: areturn
}
