Compiled from "CompositeDynamicConfiguration.java"
public class org.apache.dubbo.common.config.configcenter.wrapper.CompositeDynamicConfiguration implements org.apache.dubbo.common.config.configcenter.DynamicConfiguration {
  public static final java.lang.String NAME;

  private static final org.apache.dubbo.common.logger.ErrorTypeAwareLogger logger;

  private final java.util.Set<org.apache.dubbo.common.config.configcenter.DynamicConfiguration> configurations;

  public org.apache.dubbo.common.config.configcenter.wrapper.CompositeDynamicConfiguration();
    Code:
       0: aload_0
       1: invokespecial #2                  // Method java/lang/Object."<init>":()V
       4: aload_0
       5: new           #3                  // class java/util/HashSet
       8: dup
       9: invokespecial #4                  // Method java/util/HashSet."<init>":()V
      12: putfield      #5                  // Field configurations:Ljava/util/Set;
      15: return

  public void addConfiguration(org.apache.dubbo.common.config.configcenter.DynamicConfiguration);
    Code:
       0: aload_1
       1: ifnull        15
       4: aload_0
       5: getfield      #5                  // Field configurations:Ljava/util/Set;
       8: aload_1
       9: invokeinterface #6,  2            // InterfaceMethod java/util/Set.add:(Ljava/lang/Object;)Z
      14: pop
      15: return

  public java.util.Set<org.apache.dubbo.common.config.configcenter.DynamicConfiguration> getInnerConfigurations();
    Code:
       0: aload_0
       1: getfield      #5                  // Field configurations:Ljava/util/Set;
       4: areturn

  public void addListener(java.lang.String, java.lang.String, org.apache.dubbo.common.config.configcenter.ConfigurationListener);
    Code:
       0: aload_0
       1: aload_1
       2: aload_2
       3: aload_3
       4: invokedynamic #7,  0              // InvokeDynamic #0:accept:(Ljava/lang/String;Ljava/lang/String;Lorg/apache/dubbo/common/config/configcenter/ConfigurationListener;)Ljava/util/function/Consumer;
       9: invokespecial #8                  // Method iterateListenerOperation:(Ljava/util/function/Consumer;)V
      12: return

  public void removeListener(java.lang.String, java.lang.String, org.apache.dubbo.common.config.configcenter.ConfigurationListener);
    Code:
       0: aload_0
       1: aload_1
       2: aload_2
       3: aload_3
       4: invokedynamic #9,  0              // InvokeDynamic #1:accept:(Ljava/lang/String;Ljava/lang/String;Lorg/apache/dubbo/common/config/configcenter/ConfigurationListener;)Ljava/util/function/Consumer;
       9: invokespecial #8                  // Method iterateListenerOperation:(Ljava/util/function/Consumer;)V
      12: return

  public java.lang.String getConfig(java.lang.String, java.lang.String, long) throws java.lang.IllegalStateException;
    Code:
       0: aload_0
       1: aload_1
       2: aload_2
       3: lload_3
       4: invokedynamic #10,  0             // InvokeDynamic #2:apply:(Ljava/lang/String;Ljava/lang/String;J)Ljava/util/function/Function;
       9: invokespecial #11                 // Method iterateConfigOperation:(Ljava/util/function/Function;)Ljava/lang/Object;
      12: checkcast     #12                 // class java/lang/String
      15: areturn

  public java.lang.String getProperties(java.lang.String, java.lang.String, long) throws java.lang.IllegalStateException;
    Code:
       0: aload_0
       1: aload_1
       2: aload_2
       3: lload_3
       4: invokedynamic #13,  0             // InvokeDynamic #3:apply:(Ljava/lang/String;Ljava/lang/String;J)Ljava/util/function/Function;
       9: invokespecial #11                 // Method iterateConfigOperation:(Ljava/util/function/Function;)Ljava/lang/Object;
      12: checkcast     #12                 // class java/lang/String
      15: areturn

  public java.lang.Object getInternalProperty(java.lang.String);
    Code:
       0: aload_0
       1: aload_1
       2: invokedynamic #14,  0             // InvokeDynamic #4:apply:(Ljava/lang/String;)Ljava/util/function/Function;
       7: invokespecial #11                 // Method iterateConfigOperation:(Ljava/util/function/Function;)Ljava/lang/Object;
      10: areturn

  public boolean publishConfig(java.lang.String, java.lang.String, java.lang.String) throws java.lang.UnsupportedOperationException;
    Code:
       0: iconst_1
       1: istore        4
       3: aload_0
       4: getfield      #5                  // Field configurations:Ljava/util/Set;
       7: invokeinterface #15,  1           // InterfaceMethod java/util/Set.iterator:()Ljava/util/Iterator;
      12: astore        5
      14: aload         5
      16: invokeinterface #16,  1           // InterfaceMethod java/util/Iterator.hasNext:()Z
      21: ifeq          55
      24: aload         5
      26: invokeinterface #17,  1           // InterfaceMethod java/util/Iterator.next:()Ljava/lang/Object;
      31: checkcast     #18                 // class org/apache/dubbo/common/config/configcenter/DynamicConfiguration
      34: astore        6
      36: aload         6
      38: aload_1
      39: aload_2
      40: aload_3
      41: invokeinterface #19,  4           // InterfaceMethod org/apache/dubbo/common/config/configcenter/DynamicConfiguration.publishConfig:(Ljava/lang/String;Ljava/lang/String;Ljava/lang/String;)Z
      46: ifne          52
      49: iconst_0
      50: istore        4
      52: goto          14
      55: iload         4
      57: ireturn

  public void close() throws java.lang.Exception;
    Code:
       0: aload_0
       1: getfield      #5                  // Field configurations:Ljava/util/Set;
       4: invokeinterface #15,  1           // InterfaceMethod java/util/Set.iterator:()Ljava/util/Iterator;
       9: astore_1
      10: aload_1
      11: invokeinterface #16,  1           // InterfaceMethod java/util/Iterator.hasNext:()Z
      16: ifeq          94
      19: aload_1
      20: invokeinterface #17,  1           // InterfaceMethod java/util/Iterator.next:()Ljava/lang/Object;
      25: checkcast     #18                 // class org/apache/dubbo/common/config/configcenter/DynamicConfiguration
      28: astore_2
      29: aload_2
      30: invokeinterface #20,  1           // InterfaceMethod org/apache/dubbo/common/config/configcenter/DynamicConfiguration.close:()V
      35: goto          91
      38: astore_3
      39: getstatic     #22                 // Field logger:Lorg/apache/dubbo/common/logger/ErrorTypeAwareLogger;
      42: ldc           #23                 // String 99-0
      44: ldc           #24                 // String unknown error in configuration-center related code in common module
      46: ldc           #25                 // String
      48: new           #26                 // class java/lang/StringBuilder
      51: dup
      52: invokespecial #27                 // Method java/lang/StringBuilder."<init>":()V
      55: ldc           #28                 // String close dynamic configuration
      57: invokevirtual #29                 // Method java/lang/StringBuilder.append:(Ljava/lang/String;)Ljava/lang/StringBuilder;
      60: aload_2
      61: invokevirtual #30                 // Method java/lang/Object.getClass:()Ljava/lang/Class;
      64: invokevirtual #31                 // Method java/lang/Class.getName:()Ljava/lang/String;
      67: invokevirtual #29                 // Method java/lang/StringBuilder.append:(Ljava/lang/String;)Ljava/lang/StringBuilder;
      70: ldc           #32                 // String failed:
      72: invokevirtual #29                 // Method java/lang/StringBuilder.append:(Ljava/lang/String;)Ljava/lang/StringBuilder;
      75: aload_3
      76: invokevirtual #33                 // Method java/lang/Exception.getMessage:()Ljava/lang/String;
      79: invokevirtual #29                 // Method java/lang/StringBuilder.append:(Ljava/lang/String;)Ljava/lang/StringBuilder;
      82: invokevirtual #34                 // Method java/lang/StringBuilder.toString:()Ljava/lang/String;
      85: aload_3
      86: invokeinterface #35,  6           // InterfaceMethod org/apache/dubbo/common/logger/ErrorTypeAwareLogger.warn:(Ljava/lang/String;Ljava/lang/String;Ljava/lang/String;Ljava/lang/String;Ljava/lang/Throwable;)V
      91: goto          10
      94: aload_0
      95: getfield      #5                  // Field configurations:Ljava/util/Set;
      98: invokeinterface #36,  1           // InterfaceMethod java/util/Set.clear:()V
     103: return
    Exception table:
       from    to  target type
          29    35    38   Class java/lang/Exception

  private void iterateListenerOperation(java.util.function.Consumer<org.apache.dubbo.common.config.configcenter.DynamicConfiguration>);
    Code:
       0: aload_0
       1: getfield      #5                  // Field configurations:Ljava/util/Set;
       4: invokeinterface #15,  1           // InterfaceMethod java/util/Set.iterator:()Ljava/util/Iterator;
       9: astore_2
      10: aload_2
      11: invokeinterface #16,  1           // InterfaceMethod java/util/Iterator.hasNext:()Z
      16: ifeq          39
      19: aload_2
      20: invokeinterface #17,  1           // InterfaceMethod java/util/Iterator.next:()Ljava/lang/Object;
      25: checkcast     #18                 // class org/apache/dubbo/common/config/configcenter/DynamicConfiguration
      28: astore_3
      29: aload_1
      30: aload_3
      31: invokeinterface #37,  2           // InterfaceMethod java/util/function/Consumer.accept:(Ljava/lang/Object;)V
      36: goto          10
      39: return

  private java.lang.Object iterateConfigOperation(java.util.function.Function<org.apache.dubbo.common.config.configcenter.DynamicConfiguration, java.lang.Object>);
    Code:
       0: aconst_null
       1: astore_2
       2: aload_0
       3: getfield      #5                  // Field configurations:Ljava/util/Set;
       6: invokeinterface #15,  1           // InterfaceMethod java/util/Set.iterator:()Ljava/util/Iterator;
      11: astore_3
      12: aload_3
      13: invokeinterface #16,  1           // InterfaceMethod java/util/Iterator.hasNext:()Z
      18: ifeq          51
      21: aload_3
      22: invokeinterface #17,  1           // InterfaceMethod java/util/Iterator.next:()Ljava/lang/Object;
      27: checkcast     #18                 // class org/apache/dubbo/common/config/configcenter/DynamicConfiguration
      30: astore        4
      32: aload_1
      33: aload         4
      35: invokeinterface #38,  2           // InterfaceMethod java/util/function/Function.apply:(Ljava/lang/Object;)Ljava/lang/Object;
      40: astore_2
      41: aload_2
      42: ifnull        48
      45: goto          51
      48: goto          12
      51: aload_2
      52: areturn

  private static java.lang.Object lambda$getInternalProperty$4(java.lang.String, org.apache.dubbo.common.config.configcenter.DynamicConfiguration);
    Code:
       0: aload_1
       1: aload_0
       2: invokeinterface #39,  2           // InterfaceMethod org/apache/dubbo/common/config/configcenter/DynamicConfiguration.getInternalProperty:(Ljava/lang/String;)Ljava/lang/Object;
       7: areturn

  private static java.lang.Object lambda$getProperties$3(java.lang.String, java.lang.String, long, org.apache.dubbo.common.config.configcenter.DynamicConfiguration);
    Code:
       0: aload         4
       2: aload_0
       3: aload_1
       4: lload_2
       5: invokeinterface #40,  5           // InterfaceMethod org/apache/dubbo/common/config/configcenter/DynamicConfiguration.getProperties:(Ljava/lang/String;Ljava/lang/String;J)Ljava/lang/String;
      10: areturn

  private static java.lang.Object lambda$getConfig$2(java.lang.String, java.lang.String, long, org.apache.dubbo.common.config.configcenter.DynamicConfiguration);
    Code:
       0: aload         4
       2: aload_0
       3: aload_1
       4: lload_2
       5: invokeinterface #41,  5           // InterfaceMethod org/apache/dubbo/common/config/configcenter/DynamicConfiguration.getConfig:(Ljava/lang/String;Ljava/lang/String;J)Ljava/lang/String;
      10: areturn

  private static void lambda$removeListener$1(java.lang.String, java.lang.String, org.apache.dubbo.common.config.configcenter.ConfigurationListener, org.apache.dubbo.common.config.configcenter.DynamicConfiguration);
    Code:
       0: aload_3
       1: aload_0
       2: aload_1
       3: aload_2
       4: invokeinterface #42,  4           // InterfaceMethod org/apache/dubbo/common/config/configcenter/DynamicConfiguration.removeListener:(Ljava/lang/String;Ljava/lang/String;Lorg/apache/dubbo/common/config/configcenter/ConfigurationListener;)V
       9: return

  private static void lambda$addListener$0(java.lang.String, java.lang.String, org.apache.dubbo.common.config.configcenter.ConfigurationListener, org.apache.dubbo.common.config.configcenter.DynamicConfiguration);
    Code:
       0: aload_3
       1: aload_0
       2: aload_1
       3: aload_2
       4: invokeinterface #43,  4           // InterfaceMethod org/apache/dubbo/common/config/configcenter/DynamicConfiguration.addListener:(Ljava/lang/String;Ljava/lang/String;Lorg/apache/dubbo/common/config/configcenter/ConfigurationListener;)V
       9: return

  static {};
    Code:
       0: ldc           #44                 // class org/apache/dubbo/common/config/configcenter/wrapper/CompositeDynamicConfiguration
       2: invokestatic  #45                 // Method org/apache/dubbo/common/logger/LoggerFactory.getErrorTypeAwareLogger:(Ljava/lang/Class;)Lorg/apache/dubbo/common/logger/ErrorTypeAwareLogger;
       5: putstatic     #22                 // Field logger:Lorg/apache/dubbo/common/logger/ErrorTypeAwareLogger;
       8: return
}
