Compiled from "ZookeeperRegistry.java"
public class org.apache.dubbo.registry.zookeeper.ZookeeperRegistry$ZookeeperRegistryNotifier {
  private long lastExecuteTime;

  private final org.apache.dubbo.common.URL consumerUrl;

  private final org.apache.dubbo.registry.NotifyListener listener;

  private final long delayTime;

  final org.apache.dubbo.registry.zookeeper.ZookeeperRegistry this$0;

  public org.apache.dubbo.registry.zookeeper.ZookeeperRegistry$ZookeeperRegistryNotifier(org.apache.dubbo.registry.zookeeper.ZookeeperRegistry, org.apache.dubbo.common.URL, org.apache.dubbo.registry.NotifyListener, long);
    Code:
       0: aload_0
       1: aload_1
       2: putfield      #2                  // Field this$0:Lorg/apache/dubbo/registry/zookeeper/ZookeeperRegistry;
       5: aload_0
       6: invokespecial #3                  // Method java/lang/Object."<init>":()V
       9: aload_0
      10: aload_2
      11: putfield      #4                  // Field consumerUrl:Lorg/apache/dubbo/common/URL;
      14: aload_0
      15: aload_3
      16: putfield      #5                  // Field listener:Lorg/apache/dubbo/registry/NotifyListener;
      19: aload_0
      20: lload         4
      22: putfield      #6                  // Field delayTime:J
      25: return

  public void notify(java.lang.String, java.lang.Object);
    Code:
       0: aload_1
       1: ldc           #7                  // String configurators
       3: invokevirtual #8                  // Method java/lang/String.endsWith:(Ljava/lang/String;)Z
       6: ifne          18
       9: aload_1
      10: ldc           #9                  // String routers
      12: invokevirtual #8                  // Method java/lang/String.endsWith:(Ljava/lang/String;)Z
      15: ifeq          24
      18: aload_0
      19: aload_1
      20: aload_2
      21: invokevirtual #10                 // Method doNotify:(Ljava/lang/String;Ljava/lang/Object;)V
      24: aload_0
      25: getfield      #6                  // Field delayTime:J
      28: lconst_0
      29: lcmp
      30: ifgt          42
      33: aload_0
      34: aload_1
      35: aload_2
      36: invokevirtual #10                 // Method doNotify:(Ljava/lang/String;Ljava/lang/Object;)V
      39: goto          84
      42: aload_0
      43: getfield      #6                  // Field delayTime:J
      46: invokestatic  #11                 // Method java/lang/System.currentTimeMillis:()J
      49: aload_0
      50: getfield      #12                 // Field lastExecuteTime:J
      53: lsub
      54: lsub
      55: lstore_3
      56: lload_3
      57: lconst_0
      58: lcmp
      59: ifle          71
      62: lload_3
      63: invokestatic  #13                 // Method java/lang/Thread.sleep:(J)V
      66: goto          71
      69: astore        5
      71: aload_0
      72: invokestatic  #11                 // Method java/lang/System.currentTimeMillis:()J
      75: putfield      #12                 // Field lastExecuteTime:J
      78: aload_0
      79: aload_1
      80: aload_2
      81: invokevirtual #10                 // Method doNotify:(Ljava/lang/String;Ljava/lang/Object;)V
      84: return
    Exception table:
       from    to  target type
          62    66    69   Class java/lang/InterruptedException

  protected void doNotify(java.lang.String, java.lang.Object);
    Code:
       0: aload_0
       1: getfield      #2                  // Field this$0:Lorg/apache/dubbo/registry/zookeeper/ZookeeperRegistry;
       4: aload_0
       5: getfield      #4                  // Field consumerUrl:Lorg/apache/dubbo/common/URL;
       8: aload_0
       9: getfield      #5                  // Field listener:Lorg/apache/dubbo/registry/NotifyListener;
      12: aload_0
      13: getfield      #2                  // Field this$0:Lorg/apache/dubbo/registry/zookeeper/ZookeeperRegistry;
      16: aload_0
      17: getfield      #4                  // Field consumerUrl:Lorg/apache/dubbo/common/URL;
      20: aload_1
      21: aload_2
      22: checkcast     #15                 // class java/util/List
      25: invokestatic  #16                 // Method org/apache/dubbo/registry/zookeeper/ZookeeperRegistry.access$100:(Lorg/apache/dubbo/registry/zookeeper/ZookeeperRegistry;Lorg/apache/dubbo/common/URL;Ljava/lang/String;Ljava/util/Collection;)Ljava/util/List;
      28: invokestatic  #17                 // Method org/apache/dubbo/registry/zookeeper/ZookeeperRegistry.access$200:(Lorg/apache/dubbo/registry/zookeeper/ZookeeperRegistry;Lorg/apache/dubbo/common/URL;Lorg/apache/dubbo/registry/NotifyListener;Ljava/util/List;)V
      31: return
}
