Compiled from "ZookeeperRegistryFactory.java"
public class org.apache.dubbo.registry.zookeeper.ZookeeperRegistryFactory extends org.apache.dubbo.registry.support.AbstractRegistryFactory {
  private org.apache.dubbo.remoting.zookeeper.ZookeeperTransporter zookeeperTransporter;

  public org.apache.dubbo.registry.zookeeper.ZookeeperRegistryFactory();
    Code:
       0: aload_0
       1: invokestatic  #1                  // Method org/apache/dubbo/rpc/model/ApplicationModel.defaultModel:()Lorg/apache/dubbo/rpc/model/ApplicationModel;
       4: invokespecial #2                  // Method "<init>":(Lorg/apache/dubbo/rpc/model/ApplicationModel;)V
       7: return

  public org.apache.dubbo.registry.zookeeper.ZookeeperRegistryFactory(org.apache.dubbo.rpc.model.ApplicationModel);
    Code:
       0: aload_0
       1: invokespecial #3                  // Method org/apache/dubbo/registry/support/AbstractRegistryFactory."<init>":()V
       4: aload_0
       5: aload_1
       6: putfield      #4                  // Field applicationModel:Lorg/apache/dubbo/rpc/model/ApplicationModel;
       9: aload_0
      10: aload_1
      11: invokestatic  #5                  // InterfaceMethod org/apache/dubbo/remoting/zookeeper/ZookeeperTransporter.getExtension:(Lorg/apache/dubbo/rpc/model/ApplicationModel;)Lorg/apache/dubbo/remoting/zookeeper/ZookeeperTransporter;
      14: putfield      #6                  // Field zookeeperTransporter:Lorg/apache/dubbo/remoting/zookeeper/ZookeeperTransporter;
      17: return

  public void setZookeeperTransporter(org.apache.dubbo.remoting.zookeeper.ZookeeperTransporter);
    Code:
       0: aload_0
       1: aload_1
       2: putfield      #6                  // Field zookeeperTransporter:Lorg/apache/dubbo/remoting/zookeeper/ZookeeperTransporter;
       5: return

  public org.apache.dubbo.registry.Registry createRegistry(org.apache.dubbo.common.URL);
    Code:
       0: new           #7                  // class org/apache/dubbo/registry/zookeeper/ZookeeperRegistry
       3: dup
       4: aload_1
       5: aload_0
       6: getfield      #6                  // Field zookeeperTransporter:Lorg/apache/dubbo/remoting/zookeeper/ZookeeperTransporter;
       9: invokespecial #8                  // Method org/apache/dubbo/registry/zookeeper/ZookeeperRegistry."<init>":(Lorg/apache/dubbo/common/URL;Lorg/apache/dubbo/remoting/zookeeper/ZookeeperTransporter;)V
      12: areturn
}
