Compiled from "ZookeeperServiceDiscoveryChangeWatcher.java"
class org.apache.dubbo.registry.zookeeper.ZookeeperServiceDiscoveryChangeWatcher$1 extends org.apache.dubbo.registry.RegistryNotifier {
  final org.apache.dubbo.registry.zookeeper.ZookeeperServiceDiscoveryChangeWatcher this$0;

  org.apache.dubbo.registry.zookeeper.ZookeeperServiceDiscoveryChangeWatcher$1(org.apache.dubbo.registry.zookeeper.ZookeeperServiceDiscoveryChangeWatcher, org.apache.dubbo.common.URL, long, java.util.concurrent.ScheduledExecutorService);
    Code:
       0: aload_0
       1: aload_1
       2: putfield      #1                  // Field this$0:Lorg/apache/dubbo/registry/zookeeper/ZookeeperServiceDiscoveryChangeWatcher;
       5: aload_0
       6: aload_2
       7: lload_3
       8: aload         5
      10: invokespecial #2                  // Method org/apache/dubbo/registry/RegistryNotifier."<init>":(Lorg/apache/dubbo/common/URL;JLjava/util/concurrent/ScheduledExecutorService;)V
      13: return

  protected void doNotify(java.lang.Object);
    Code:
       0: aload_0
       1: getfield      #1                  // Field this$0:Lorg/apache/dubbo/registry/zookeeper/ZookeeperServiceDiscoveryChangeWatcher;
       4: invokestatic  #3                  // Method org/apache/dubbo/registry/zookeeper/ZookeeperServiceDiscoveryChangeWatcher.access$000:(Lorg/apache/dubbo/registry/zookeeper/ZookeeperServiceDiscoveryChangeWatcher;)Ljava/util/Set;
       7: aload_1
       8: invokedynamic #4,  0              // InvokeDynamic #0:accept:(Ljava/lang/Object;)Ljava/util/function/Consumer;
      13: invokeinterface #5,  2            // InterfaceMethod java/util/Set.forEach:(Ljava/util/function/Consumer;)V
      18: return

  private static void lambda$doNotify$0(java.lang.Object, org.apache.dubbo.registry.client.event.listener.ServiceInstancesChangedListener);
    Code:
       0: aload_1
       1: aload_0
       2: checkcast     #6                  // class org/apache/dubbo/registry/client/event/ServiceInstancesChangedEvent
       5: invokevirtual #7                  // Method org/apache/dubbo/registry/client/event/listener/ServiceInstancesChangedListener.onEvent:(Lorg/apache/dubbo/registry/client/event/ServiceInstancesChangedEvent;)V
       8: return
}
