Compiled from "ZookeeperInstance.java"
public class org.apache.dubbo.registry.zookeeper.ZookeeperInstance {
  private java.lang.String id;

  private java.lang.String name;

  private java.util.Map<java.lang.String, java.lang.String> metadata;

  private org.apache.dubbo.registry.zookeeper.ZookeeperInstance();
    Code:
       0: aload_0
       1: invokespecial #1                  // Method java/lang/Object."<init>":()V
       4: aload_0
       5: new           #2                  // class java/util/HashMap
       8: dup
       9: invokespecial #3                  // Method java/util/HashMap."<init>":()V
      12: putfield      #4                  // Field metadata:Ljava/util/Map;
      15: return

  public org.apache.dubbo.registry.zookeeper.ZookeeperInstance(java.lang.String, java.lang.String, java.util.Map<java.lang.String, java.lang.String>);
    Code:
       0: aload_0
       1: invokespecial #1                  // Method java/lang/Object."<init>":()V
       4: aload_0
       5: new           #2                  // class java/util/HashMap
       8: dup
       9: invokespecial #3                  // Method java/util/HashMap."<init>":()V
      12: putfield      #4                  // Field metadata:Ljava/util/Map;
      15: aload_0
      16: aload_1
      17: putfield      #5                  // Field id:Ljava/lang/String;
      20: aload_0
      21: aload_2
      22: putfield      #6                  // Field name:Ljava/lang/String;
      25: aload_0
      26: aload_3
      27: putfield      #4                  // Field metadata:Ljava/util/Map;
      30: return

  public java.lang.String getId();
    Code:
       0: aload_0
       1: getfield      #5                  // Field id:Ljava/lang/String;
       4: areturn

  public java.lang.String getName();
    Code:
       0: aload_0
       1: getfield      #6                  // Field name:Ljava/lang/String;
       4: areturn

  public void setId(java.lang.String);
    Code:
       0: aload_0
       1: aload_1
       2: putfield      #5                  // Field id:Ljava/lang/String;
       5: return

  public void setName(java.lang.String);
    Code:
       0: aload_0
       1: aload_1
       2: putfield      #6                  // Field name:Ljava/lang/String;
       5: return

  public java.util.Map<java.lang.String, java.lang.String> getMetadata();
    Code:
       0: aload_0
       1: getfield      #4                  // Field metadata:Ljava/util/Map;
       4: areturn

  public void setMetadata(java.util.Map<java.lang.String, java.lang.String>);
    Code:
       0: aload_0
       1: aload_1
       2: putfield      #4                  // Field metadata:Ljava/util/Map;
       5: return

  public java.lang.String toString();
    Code:
       0: new           #7                  // class java/lang/StringBuilder
       3: dup
       4: invokespecial #8                  // Method java/lang/StringBuilder."<init>":()V
       7: ldc           #9                  // String ZookeeperInstance{id=\'
       9: invokevirtual #10                 // Method java/lang/StringBuilder.append:(Ljava/lang/String;)Ljava/lang/StringBuilder;
      12: aload_0
      13: getfield      #5                  // Field id:Ljava/lang/String;
      16: invokevirtual #10                 // Method java/lang/StringBuilder.append:(Ljava/lang/String;)Ljava/lang/StringBuilder;
      19: bipush        39
      21: invokevirtual #11                 // Method java/lang/StringBuilder.append:(C)Ljava/lang/StringBuilder;
      24: ldc           #12                 // String , name=\'
      26: invokevirtual #10                 // Method java/lang/StringBuilder.append:(Ljava/lang/String;)Ljava/lang/StringBuilder;
      29: aload_0
      30: getfield      #6                  // Field name:Ljava/lang/String;
      33: invokevirtual #10                 // Method java/lang/StringBuilder.append:(Ljava/lang/String;)Ljava/lang/StringBuilder;
      36: bipush        39
      38: invokevirtual #11                 // Method java/lang/StringBuilder.append:(C)Ljava/lang/StringBuilder;
      41: ldc           #13                 // String , metadata=
      43: invokevirtual #10                 // Method java/lang/StringBuilder.append:(Ljava/lang/String;)Ljava/lang/StringBuilder;
      46: aload_0
      47: getfield      #4                  // Field metadata:Ljava/util/Map;
      50: invokevirtual #14                 // Method java/lang/StringBuilder.append:(Ljava/lang/Object;)Ljava/lang/StringBuilder;
      53: bipush        125
      55: invokevirtual #11                 // Method java/lang/StringBuilder.append:(C)Ljava/lang/StringBuilder;
      58: invokevirtual #15                 // Method java/lang/StringBuilder.toString:()Ljava/lang/String;
      61: areturn
}
