Compiled from "AsyncSubject.java"
final class io.reactivex.rxjava3.subjects.AsyncSubject$AsyncDisposable<T> extends io.reactivex.rxjava3.internal.observers.DeferredScalarDisposable<T> {
  private static final long serialVersionUID;

  final io.reactivex.rxjava3.subjects.AsyncSubject<T> parent;

  io.reactivex.rxjava3.subjects.AsyncSubject$AsyncDisposable(io.reactivex.rxjava3.core.Observer<? super T>, io.reactivex.rxjava3.subjects.AsyncSubject<T>);
    Code:
       0: aload_0
       1: aload_1
       2: invokespecial #1                  // Method io/reactivex/rxjava3/internal/observers/DeferredScalarDisposable."<init>":(Lio/reactivex/rxjava3/core/Observer;)V
       5: aload_0
       6: aload_2
       7: putfield      #2                  // Field parent:Lio/reactivex/rxjava3/subjects/AsyncSubject;
      10: return

  public void dispose();
    Code:
       0: aload_0
       1: invokespecial #3                  // Method io/reactivex/rxjava3/internal/observers/DeferredScalarDisposable.tryDispose:()Z
       4: ifeq          15
       7: aload_0
       8: getfield      #2                  // Field parent:Lio/reactivex/rxjava3/subjects/AsyncSubject;
      11: aload_0
      12: invokevirtual #4                  // Method io/reactivex/rxjava3/subjects/AsyncSubject.remove:(Lio/reactivex/rxjava3/subjects/AsyncSubject$AsyncDisposable;)V
      15: return

  void onComplete();
    Code:
       0: aload_0
       1: invokevirtual #5                  // Method isDisposed:()Z
       4: ifne          16
       7: aload_0
       8: getfield      #6                  // Field downstream:Lio/reactivex/rxjava3/core/Observer;
      11: invokeinterface #7,  1            // InterfaceMethod io/reactivex/rxjava3/core/Observer.onComplete:()V
      16: return

  void onError(java.lang.Throwable);
    Code:
       0: aload_0
       1: invokevirtual #5                  // Method isDisposed:()Z
       4: ifeq          14
       7: aload_1
       8: invokestatic  #8                  // Method io/reactivex/rxjava3/plugins/RxJavaPlugins.onError:(Ljava/lang/Throwable;)V
      11: goto          24
      14: aload_0
      15: getfield      #6                  // Field downstream:Lio/reactivex/rxjava3/core/Observer;
      18: aload_1
      19: invokeinterface #9,  2            // InterfaceMethod io/reactivex/rxjava3/core/Observer.onError:(Ljava/lang/Throwable;)V
      24: return
}
