Compiled from "CompletableSubject.java"
final class io.reactivex.rxjava3.subjects.CompletableSubject$CompletableDisposable extends java.util.concurrent.atomic.AtomicReference<io.reactivex.rxjava3.subjects.CompletableSubject> implements io.reactivex.rxjava3.disposables.Disposable {
  private static final long serialVersionUID;

  final io.reactivex.rxjava3.core.CompletableObserver downstream;

  io.reactivex.rxjava3.subjects.CompletableSubject$CompletableDisposable(io.reactivex.rxjava3.core.CompletableObserver, io.reactivex.rxjava3.subjects.CompletableSubject);
    Code:
       0: aload_0
       1: invokespecial #1                  // Method java/util/concurrent/atomic/AtomicReference."<init>":()V
       4: aload_0
       5: aload_1
       6: putfield      #2                  // Field downstream:Lio/reactivex/rxjava3/core/CompletableObserver;
       9: aload_0
      10: aload_2
      11: invokevirtual #3                  // Method lazySet:(Ljava/lang/Object;)V
      14: return

  public void dispose();
    Code:
       0: aload_0
       1: aconst_null
       2: invokevirtual #4                  // Method getAndSet:(Ljava/lang/Object;)Ljava/lang/Object;
       5: checkcast     #5                  // class io/reactivex/rxjava3/subjects/CompletableSubject
       8: astore_1
       9: aload_1
      10: ifnull        18
      13: aload_1
      14: aload_0
      15: invokevirtual #6                  // Method io/reactivex/rxjava3/subjects/CompletableSubject.remove:(Lio/reactivex/rxjava3/subjects/CompletableSubject$CompletableDisposable;)V
      18: return

  public boolean isDisposed();
    Code:
       0: aload_0
       1: invokevirtual #7                  // Method get:()Ljava/lang/Object;
       4: ifnonnull     11
       7: iconst_1
       8: goto          12
      11: iconst_0
      12: ireturn
}
