Compiled from "PublishSubject.java"
final class io.reactivex.rxjava3.subjects.PublishSubject$PublishDisposable<T> extends java.util.concurrent.atomic.AtomicBoolean implements io.reactivex.rxjava3.disposables.Disposable {
  private static final long serialVersionUID;

  final io.reactivex.rxjava3.core.Observer<? super T> downstream;

  final io.reactivex.rxjava3.subjects.PublishSubject<T> parent;

  io.reactivex.rxjava3.subjects.PublishSubject$PublishDisposable(io.reactivex.rxjava3.core.Observer<? super T>, io.reactivex.rxjava3.subjects.PublishSubject<T>);
    Code:
       0: aload_0
       1: invokespecial #1                  // Method java/util/concurrent/atomic/AtomicBoolean."<init>":()V
       4: aload_0
       5: aload_1
       6: putfield      #2                  // Field downstream:Lio/reactivex/rxjava3/core/Observer;
       9: aload_0
      10: aload_2
      11: putfield      #3                  // Field parent:Lio/reactivex/rxjava3/subjects/PublishSubject;
      14: return

  public void onNext(T);
    Code:
       0: aload_0
       1: invokevirtual #4                  // Method get:()Z
       4: ifne          17
       7: aload_0
       8: getfield      #2                  // Field downstream:Lio/reactivex/rxjava3/core/Observer;
      11: aload_1
      12: invokeinterface #5,  2            // InterfaceMethod io/reactivex/rxjava3/core/Observer.onNext:(Ljava/lang/Object;)V
      17: return

  public void onError(java.lang.Throwable);
    Code:
       0: aload_0
       1: invokevirtual #4                  // Method get:()Z
       4: ifeq          14
       7: aload_1
       8: invokestatic  #6                  // Method io/reactivex/rxjava3/plugins/RxJavaPlugins.onError:(Ljava/lang/Throwable;)V
      11: goto          24
      14: aload_0
      15: getfield      #2                  // Field downstream:Lio/reactivex/rxjava3/core/Observer;
      18: aload_1
      19: invokeinterface #7,  2            // InterfaceMethod io/reactivex/rxjava3/core/Observer.onError:(Ljava/lang/Throwable;)V
      24: return

  public void onComplete();
    Code:
       0: aload_0
       1: invokevirtual #4                  // Method get:()Z
       4: ifne          16
       7: aload_0
       8: getfield      #2                  // Field downstream:Lio/reactivex/rxjava3/core/Observer;
      11: invokeinterface #8,  1            // InterfaceMethod io/reactivex/rxjava3/core/Observer.onComplete:()V
      16: return

  public void dispose();
    Code:
       0: aload_0
       1: iconst_0
       2: iconst_1
       3: invokevirtual #9                  // Method compareAndSet:(ZZ)Z
       6: ifeq          17
       9: aload_0
      10: getfield      #3                  // Field parent:Lio/reactivex/rxjava3/subjects/PublishSubject;
      13: aload_0
      14: invokevirtual #10                 // Method io/reactivex/rxjava3/subjects/PublishSubject.remove:(Lio/reactivex/rxjava3/subjects/PublishSubject$PublishDisposable;)V
      17: return

  public boolean isDisposed();
    Code:
       0: aload_0
       1: invokevirtual #4                  // Method get:()Z
       4: ireturn
}
