Compiled from "ReplaySubject.java"
final class io.reactivex.rxjava3.subjects.ReplaySubject$TimedNode<T> extends java.util.concurrent.atomic.AtomicReference<io.reactivex.rxjava3.subjects.ReplaySubject$TimedNode<T>> {
  private static final long serialVersionUID;

  final T value;

  final long time;

  io.reactivex.rxjava3.subjects.ReplaySubject$TimedNode(T, long);
    Code:
       0: aload_0
       1: invokespecial #1                  // Method java/util/concurrent/atomic/AtomicReference."<init>":()V
       4: aload_0
       5: aload_1
       6: putfield      #2                  // Field value:Ljava/lang/Object;
       9: aload_0
      10: lload_2
      11: putfield      #3                  // Field time:J
      14: return
}
