Compiled from "Subject.java"
public abstract class io.reactivex.rxjava3.subjects.Subject<T> extends io.reactivex.rxjava3.core.Observable<T> implements io.reactivex.rxjava3.core.Observer<T> {
  public io.reactivex.rxjava3.subjects.Subject();
    Code:
       0: aload_0
       1: invokespecial #1                  // Method io/reactivex/rxjava3/core/Observable."<init>":()V
       4: return

  public abstract boolean hasObservers();

  public abstract boolean hasThrowable();

  public abstract boolean hasComplete();

  public abstract java.lang.Throwable getThrowable();

  public final io.reactivex.rxjava3.subjects.Subject<T> toSerialized();
    Code:
       0: aload_0
       1: instanceof    #2                  // class io/reactivex/rxjava3/subjects/SerializedSubject
       4: ifeq          9
       7: aload_0
       8: areturn
       9: new           #2                  // class io/reactivex/rxjava3/subjects/SerializedSubject
      12: dup
      13: aload_0
      14: invokespecial #3                  // Method io/reactivex/rxjava3/subjects/SerializedSubject."<init>":(Lio/reactivex/rxjava3/subjects/Subject;)V
      17: areturn
}
