Compiled from "UnicastSubject.java"
final class io.reactivex.rxjava3.subjects.UnicastSubject$UnicastQueueDisposable extends io.reactivex.rxjava3.internal.observers.BasicIntQueueDisposable<T> {
  private static final long serialVersionUID;

  final io.reactivex.rxjava3.subjects.UnicastSubject this$0;

  io.reactivex.rxjava3.subjects.UnicastSubject$UnicastQueueDisposable(io.reactivex.rxjava3.subjects.UnicastSubject);
    Code:
       0: aload_0
       1: aload_1
       2: putfield      #1                  // Field this$0:Lio/reactivex/rxjava3/subjects/UnicastSubject;
       5: aload_0
       6: invokespecial #2                  // Method io/reactivex/rxjava3/internal/observers/BasicIntQueueDisposable."<init>":()V
       9: return

  public int requestFusion(int);
    Code:
       0: iload_1
       1: iconst_2
       2: iand
       3: ifeq          16
       6: aload_0
       7: getfield      #1                  // Field this$0:Lio/reactivex/rxjava3/subjects/UnicastSubject;
      10: iconst_1
      11: putfield      #4                  // Field io/reactivex/rxjava3/subjects/UnicastSubject.enableOperatorFusion:Z
      14: iconst_2
      15: ireturn
      16: iconst_0
      17: ireturn

  public T poll();
    Code:
       0: aload_0
       1: getfield      #1                  // Field this$0:Lio/reactivex/rxjava3/subjects/UnicastSubject;
       4: getfield      #5                  // Field io/reactivex/rxjava3/subjects/UnicastSubject.queue:Lio/reactivex/rxjava3/operators/SpscLinkedArrayQueue;
       7: invokevirtual #6                  // Method io/reactivex/rxjava3/operators/SpscLinkedArrayQueue.poll:()Ljava/lang/Object;
      10: areturn

  public boolean isEmpty();
    Code:
       0: aload_0
       1: getfield      #1                  // Field this$0:Lio/reactivex/rxjava3/subjects/UnicastSubject;
       4: getfield      #5                  // Field io/reactivex/rxjava3/subjects/UnicastSubject.queue:Lio/reactivex/rxjava3/operators/SpscLinkedArrayQueue;
       7: invokevirtual #7                  // Method io/reactivex/rxjava3/operators/SpscLinkedArrayQueue.isEmpty:()Z
      10: ireturn

  public void clear();
    Code:
       0: aload_0
       1: getfield      #1                  // Field this$0:Lio/reactivex/rxjava3/subjects/UnicastSubject;
       4: getfield      #5                  // Field io/reactivex/rxjava3/subjects/UnicastSubject.queue:Lio/reactivex/rxjava3/operators/SpscLinkedArrayQueue;
       7: invokevirtual #8                  // Method io/reactivex/rxjava3/operators/SpscLinkedArrayQueue.clear:()V
      10: return

  public void dispose();
    Code:
       0: aload_0
       1: getfield      #1                  // Field this$0:Lio/reactivex/rxjava3/subjects/UnicastSubject;
       4: getfield      #9                  // Field io/reactivex/rxjava3/subjects/UnicastSubject.disposed:Z
       7: ifne          80
      10: aload_0
      11: getfield      #1                  // Field this$0:Lio/reactivex/rxjava3/subjects/UnicastSubject;
      14: iconst_1
      15: putfield      #9                  // Field io/reactivex/rxjava3/subjects/UnicastSubject.disposed:Z
      18: aload_0
      19: getfield      #1                  // Field this$0:Lio/reactivex/rxjava3/subjects/UnicastSubject;
      22: invokevirtual #10                 // Method io/reactivex/rxjava3/subjects/UnicastSubject.doTerminate:()V
      25: aload_0
      26: getfield      #1                  // Field this$0:Lio/reactivex/rxjava3/subjects/UnicastSubject;
      29: getfield      #11                 // Field io/reactivex/rxjava3/subjects/UnicastSubject.downstream:Ljava/util/concurrent/atomic/AtomicReference;
      32: aconst_null
      33: invokevirtual #12                 // Method java/util/concurrent/atomic/AtomicReference.lazySet:(Ljava/lang/Object;)V
      36: aload_0
      37: getfield      #1                  // Field this$0:Lio/reactivex/rxjava3/subjects/UnicastSubject;
      40: getfield      #13                 // Field io/reactivex/rxjava3/subjects/UnicastSubject.wip:Lio/reactivex/rxjava3/internal/observers/BasicIntQueueDisposable;
      43: invokevirtual #14                 // Method io/reactivex/rxjava3/internal/observers/BasicIntQueueDisposable.getAndIncrement:()I
      46: ifne          80
      49: aload_0
      50: getfield      #1                  // Field this$0:Lio/reactivex/rxjava3/subjects/UnicastSubject;
      53: getfield      #11                 // Field io/reactivex/rxjava3/subjects/UnicastSubject.downstream:Ljava/util/concurrent/atomic/AtomicReference;
      56: aconst_null
      57: invokevirtual #12                 // Method java/util/concurrent/atomic/AtomicReference.lazySet:(Ljava/lang/Object;)V
      60: aload_0
      61: getfield      #1                  // Field this$0:Lio/reactivex/rxjava3/subjects/UnicastSubject;
      64: getfield      #4                  // Field io/reactivex/rxjava3/subjects/UnicastSubject.enableOperatorFusion:Z
      67: ifne          80
      70: aload_0
      71: getfield      #1                  // Field this$0:Lio/reactivex/rxjava3/subjects/UnicastSubject;
      74: getfield      #5                  // Field io/reactivex/rxjava3/subjects/UnicastSubject.queue:Lio/reactivex/rxjava3/operators/SpscLinkedArrayQueue;
      77: invokevirtual #8                  // Method io/reactivex/rxjava3/operators/SpscLinkedArrayQueue.clear:()V
      80: return

  public boolean isDisposed();
    Code:
       0: aload_0
       1: getfield      #1                  // Field this$0:Lio/reactivex/rxjava3/subjects/UnicastSubject;
       4: getfield      #9                  // Field io/reactivex/rxjava3/subjects/UnicastSubject.disposed:Z
       7: ireturn
}
