Compiled from "UnicastSubject.java"
public final class io.reactivex.rxjava3.subjects.UnicastSubject<T> extends io.reactivex.rxjava3.subjects.Subject<T> {
  final io.reactivex.rxjava3.operators.SpscLinkedArrayQueue<T> queue;

  final java.util.concurrent.atomic.AtomicReference<io.reactivex.rxjava3.core.Observer<? super T>> downstream;

  final java.util.concurrent.atomic.AtomicReference<java.lang.Runnable> onTerminate;

  final boolean delayError;

  volatile boolean disposed;

  volatile boolean done;

  java.lang.Throwable error;

  final java.util.concurrent.atomic.AtomicBoolean once;

  final io.reactivex.rxjava3.internal.observers.BasicIntQueueDisposable<T> wip;

  boolean enableOperatorFusion;

  public static <T> io.reactivex.rxjava3.subjects.UnicastSubject<T> create();
    Code:
       0: new           #1                  // class io/reactivex/rxjava3/subjects/UnicastSubject
       3: dup
       4: invokestatic  #2                  // Method bufferSize:()I
       7: aconst_null
       8: iconst_1
       9: invokespecial #3                  // Method "<init>":(ILjava/lang/Runnable;Z)V
      12: areturn

  public static <T> io.reactivex.rxjava3.subjects.UnicastSubject<T> create(int);
    Code:
       0: iload_0
       1: ldc           #4                  // String capacityHint
       3: invokestatic  #5                  // Method io/reactivex/rxjava3/internal/functions/ObjectHelper.verifyPositive:(ILjava/lang/String;)I
       6: pop
       7: new           #1                  // class io/reactivex/rxjava3/subjects/UnicastSubject
      10: dup
      11: iload_0
      12: aconst_null
      13: iconst_1
      14: invokespecial #3                  // Method "<init>":(ILjava/lang/Runnable;Z)V
      17: areturn

  public static <T> io.reactivex.rxjava3.subjects.UnicastSubject<T> create(int, java.lang.Runnable);
    Code:
       0: iload_0
       1: ldc           #4                  // String capacityHint
       3: invokestatic  #5                  // Method io/reactivex/rxjava3/internal/functions/ObjectHelper.verifyPositive:(ILjava/lang/String;)I
       6: pop
       7: aload_1
       8: ldc           #6                  // String onTerminate
      10: invokestatic  #7                  // Method java/util/Objects.requireNonNull:(Ljava/lang/Object;Ljava/lang/String;)Ljava/lang/Object;
      13: pop
      14: new           #1                  // class io/reactivex/rxjava3/subjects/UnicastSubject
      17: dup
      18: iload_0
      19: aload_1
      20: iconst_1
      21: invokespecial #3                  // Method "<init>":(ILjava/lang/Runnable;Z)V
      24: areturn

  public static <T> io.reactivex.rxjava3.subjects.UnicastSubject<T> create(int, java.lang.Runnable, boolean);
    Code:
       0: iload_0
       1: ldc           #4                  // String capacityHint
       3: invokestatic  #5                  // Method io/reactivex/rxjava3/internal/functions/ObjectHelper.verifyPositive:(ILjava/lang/String;)I
       6: pop
       7: aload_1
       8: ldc           #6                  // String onTerminate
      10: invokestatic  #7                  // Method java/util/Objects.requireNonNull:(Ljava/lang/Object;Ljava/lang/String;)Ljava/lang/Object;
      13: pop
      14: new           #1                  // class io/reactivex/rxjava3/subjects/UnicastSubject
      17: dup
      18: iload_0
      19: aload_1
      20: iload_2
      21: invokespecial #3                  // Method "<init>":(ILjava/lang/Runnable;Z)V
      24: areturn

  public static <T> io.reactivex.rxjava3.subjects.UnicastSubject<T> create(boolean);
    Code:
       0: new           #1                  // class io/reactivex/rxjava3/subjects/UnicastSubject
       3: dup
       4: invokestatic  #2                  // Method bufferSize:()I
       7: aconst_null
       8: iload_0
       9: invokespecial #3                  // Method "<init>":(ILjava/lang/Runnable;Z)V
      12: areturn

  io.reactivex.rxjava3.subjects.UnicastSubject(int, java.lang.Runnable, boolean);
    Code:
       0: aload_0
       1: invokespecial #8                  // Method io/reactivex/rxjava3/subjects/Subject."<init>":()V
       4: aload_0
       5: new           #9                  // class io/reactivex/rxjava3/operators/SpscLinkedArrayQueue
       8: dup
       9: iload_1
      10: invokespecial #10                 // Method io/reactivex/rxjava3/operators/SpscLinkedArrayQueue."<init>":(I)V
      13: putfield      #11                 // Field queue:Lio/reactivex/rxjava3/operators/SpscLinkedArrayQueue;
      16: aload_0
      17: new           #12                 // class java/util/concurrent/atomic/AtomicReference
      20: dup
      21: aload_2
      22: invokespecial #13                 // Method java/util/concurrent/atomic/AtomicReference."<init>":(Ljava/lang/Object;)V
      25: putfield      #14                 // Field onTerminate:Ljava/util/concurrent/atomic/AtomicReference;
      28: aload_0
      29: iload_3
      30: putfield      #15                 // Field delayError:Z
      33: aload_0
      34: new           #12                 // class java/util/concurrent/atomic/AtomicReference
      37: dup
      38: invokespecial #16                 // Method java/util/concurrent/atomic/AtomicReference."<init>":()V
      41: putfield      #17                 // Field downstream:Ljava/util/concurrent/atomic/AtomicReference;
      44: aload_0
      45: new           #18                 // class java/util/concurrent/atomic/AtomicBoolean
      48: dup
      49: invokespecial #19                 // Method java/util/concurrent/atomic/AtomicBoolean."<init>":()V
      52: putfield      #20                 // Field once:Ljava/util/concurrent/atomic/AtomicBoolean;
      55: aload_0
      56: new           #21                 // class io/reactivex/rxjava3/subjects/UnicastSubject$UnicastQueueDisposable
      59: dup
      60: aload_0
      61: invokespecial #22                 // Method io/reactivex/rxjava3/subjects/UnicastSubject$UnicastQueueDisposable."<init>":(Lio/reactivex/rxjava3/subjects/UnicastSubject;)V
      64: putfield      #23                 // Field wip:Lio/reactivex/rxjava3/internal/observers/BasicIntQueueDisposable;
      67: return

  protected void subscribeActual(io.reactivex.rxjava3.core.Observer<? super T>);
    Code:
       0: aload_0
       1: getfield      #20                 // Field once:Ljava/util/concurrent/atomic/AtomicBoolean;
       4: invokevirtual #24                 // Method java/util/concurrent/atomic/AtomicBoolean.get:()Z
       7: ifne          63
      10: aload_0
      11: getfield      #20                 // Field once:Ljava/util/concurrent/atomic/AtomicBoolean;
      14: iconst_0
      15: iconst_1
      16: invokevirtual #25                 // Method java/util/concurrent/atomic/AtomicBoolean.compareAndSet:(ZZ)Z
      19: ifeq          63
      22: aload_1
      23: aload_0
      24: getfield      #23                 // Field wip:Lio/reactivex/rxjava3/internal/observers/BasicIntQueueDisposable;
      27: invokeinterface #26,  2           // InterfaceMethod io/reactivex/rxjava3/core/Observer.onSubscribe:(Lio/reactivex/rxjava3/disposables/Disposable;)V
      32: aload_0
      33: getfield      #17                 // Field downstream:Ljava/util/concurrent/atomic/AtomicReference;
      36: aload_1
      37: invokevirtual #27                 // Method java/util/concurrent/atomic/AtomicReference.lazySet:(Ljava/lang/Object;)V
      40: aload_0
      41: getfield      #28                 // Field disposed:Z
      44: ifeq          56
      47: aload_0
      48: getfield      #17                 // Field downstream:Ljava/util/concurrent/atomic/AtomicReference;
      51: aconst_null
      52: invokevirtual #27                 // Method java/util/concurrent/atomic/AtomicReference.lazySet:(Ljava/lang/Object;)V
      55: return
      56: aload_0
      57: invokevirtual #29                 // Method drain:()V
      60: goto          76
      63: new           #30                 // class java/lang/IllegalStateException
      66: dup
      67: ldc           #31                 // String Only a single observer allowed.
      69: invokespecial #32                 // Method java/lang/IllegalStateException."<init>":(Ljava/lang/String;)V
      72: aload_1
      73: invokestatic  #33                 // Method io/reactivex/rxjava3/internal/disposables/EmptyDisposable.error:(Ljava/lang/Throwable;Lio/reactivex/rxjava3/core/Observer;)V
      76: return

  void doTerminate();
    Code:
       0: aload_0
       1: getfield      #14                 // Field onTerminate:Ljava/util/concurrent/atomic/AtomicReference;
       4: invokevirtual #34                 // Method java/util/concurrent/atomic/AtomicReference.get:()Ljava/lang/Object;
       7: checkcast     #35                 // class java/lang/Runnable
      10: astore_1
      11: aload_1
      12: ifnull        33
      15: aload_0
      16: getfield      #14                 // Field onTerminate:Ljava/util/concurrent/atomic/AtomicReference;
      19: aload_1
      20: aconst_null
      21: invokevirtual #36                 // Method java/util/concurrent/atomic/AtomicReference.compareAndSet:(Ljava/lang/Object;Ljava/lang/Object;)Z
      24: ifeq          33
      27: aload_1
      28: invokeinterface #37,  1           // InterfaceMethod java/lang/Runnable.run:()V
      33: return

  public void onSubscribe(io.reactivex.rxjava3.disposables.Disposable);
    Code:
       0: aload_0
       1: getfield      #38                 // Field done:Z
       4: ifne          14
       7: aload_0
       8: getfield      #28                 // Field disposed:Z
      11: ifeq          20
      14: aload_1
      15: invokeinterface #39,  1           // InterfaceMethod io/reactivex/rxjava3/disposables/Disposable.dispose:()V
      20: return

  public void onNext(T);
    Code:
       0: aload_1
       1: ldc           #40                 // String onNext called with a null value.
       3: invokestatic  #41                 // Method io/reactivex/rxjava3/internal/util/ExceptionHelper.nullCheck:(Ljava/lang/Object;Ljava/lang/String;)Ljava/lang/Object;
       6: pop
       7: aload_0
       8: getfield      #38                 // Field done:Z
      11: ifne          21
      14: aload_0
      15: getfield      #28                 // Field disposed:Z
      18: ifeq          22
      21: return
      22: aload_0
      23: getfield      #11                 // Field queue:Lio/reactivex/rxjava3/operators/SpscLinkedArrayQueue;
      26: aload_1
      27: invokevirtual #42                 // Method io/reactivex/rxjava3/operators/SpscLinkedArrayQueue.offer:(Ljava/lang/Object;)Z
      30: pop
      31: aload_0
      32: invokevirtual #29                 // Method drain:()V
      35: return

  public void onError(java.lang.Throwable);
    Code:
       0: aload_1
       1: ldc           #43                 // String onError called with a null Throwable.
       3: invokestatic  #41                 // Method io/reactivex/rxjava3/internal/util/ExceptionHelper.nullCheck:(Ljava/lang/Object;Ljava/lang/String;)Ljava/lang/Object;
       6: pop
       7: aload_0
       8: getfield      #38                 // Field done:Z
      11: ifne          21
      14: aload_0
      15: getfield      #28                 // Field disposed:Z
      18: ifeq          26
      21: aload_1
      22: invokestatic  #44                 // Method io/reactivex/rxjava3/plugins/RxJavaPlugins.onError:(Ljava/lang/Throwable;)V
      25: return
      26: aload_0
      27: aload_1
      28: putfield      #45                 // Field error:Ljava/lang/Throwable;
      31: aload_0
      32: iconst_1
      33: putfield      #38                 // Field done:Z
      36: aload_0
      37: invokevirtual #46                 // Method doTerminate:()V
      40: aload_0
      41: invokevirtual #29                 // Method drain:()V
      44: return

  public void onComplete();
    Code:
       0: aload_0
       1: getfield      #38                 // Field done:Z
       4: ifne          14
       7: aload_0
       8: getfield      #28                 // Field disposed:Z
      11: ifeq          15
      14: return
      15: aload_0
      16: iconst_1
      17: putfield      #38                 // Field done:Z
      20: aload_0
      21: invokevirtual #46                 // Method doTerminate:()V
      24: aload_0
      25: invokevirtual #29                 // Method drain:()V
      28: return

  void drainNormal(io.reactivex.rxjava3.core.Observer<? super T>);
    Code:
       0: iconst_1
       1: istore_2
       2: aload_0
       3: getfield      #11                 // Field queue:Lio/reactivex/rxjava3/operators/SpscLinkedArrayQueue;
       6: astore_3
       7: aload_0
       8: getfield      #15                 // Field delayError:Z
      11: ifne          18
      14: iconst_1
      15: goto          19
      18: iconst_0
      19: istore        4
      21: iconst_1
      22: istore        5
      24: aload_0
      25: getfield      #28                 // Field disposed:Z
      28: ifeq          46
      31: aload_0
      32: getfield      #17                 // Field downstream:Ljava/util/concurrent/atomic/AtomicReference;
      35: aconst_null
      36: invokevirtual #27                 // Method java/util/concurrent/atomic/AtomicReference.lazySet:(Ljava/lang/Object;)V
      39: aload_3
      40: invokeinterface #47,  1           // InterfaceMethod io/reactivex/rxjava3/operators/SimpleQueue.clear:()V
      45: return
      46: aload_0
      47: getfield      #38                 // Field done:Z
      50: istore        6
      52: aload_0
      53: getfield      #11                 // Field queue:Lio/reactivex/rxjava3/operators/SpscLinkedArrayQueue;
      56: invokevirtual #48                 // Method io/reactivex/rxjava3/operators/SpscLinkedArrayQueue.poll:()Ljava/lang/Object;
      59: astore        7
      61: aload         7
      63: ifnonnull     70
      66: iconst_1
      67: goto          71
      70: iconst_0
      71: istore        8
      73: iload         6
      75: ifeq          112
      78: iload         4
      80: ifeq          101
      83: iload         5
      85: ifeq          101
      88: aload_0
      89: aload_3
      90: aload_1
      91: invokevirtual #49                 // Method failedFast:(Lio/reactivex/rxjava3/operators/SimpleQueue;Lio/reactivex/rxjava3/core/Observer;)Z
      94: ifeq          98
      97: return
      98: iconst_0
      99: istore        5
     101: iload         8
     103: ifeq          112
     106: aload_0
     107: aload_1
     108: invokevirtual #50                 // Method errorOrComplete:(Lio/reactivex/rxjava3/core/Observer;)V
     111: return
     112: iload         8
     114: ifeq          120
     117: goto          131
     120: aload_1
     121: aload         7
     123: invokeinterface #51,  2           // InterfaceMethod io/reactivex/rxjava3/core/Observer.onNext:(Ljava/lang/Object;)V
     128: goto          24
     131: aload_0
     132: getfield      #23                 // Field wip:Lio/reactivex/rxjava3/internal/observers/BasicIntQueueDisposable;
     135: iload_2
     136: ineg
     137: invokevirtual #52                 // Method io/reactivex/rxjava3/internal/observers/BasicIntQueueDisposable.addAndGet:(I)I
     140: istore_2
     141: iload_2
     142: ifne          24
     145: goto          148
     148: return

  void drainFused(io.reactivex.rxjava3.core.Observer<? super T>);
    Code:
       0: iconst_1
       1: istore_2
       2: aload_0
       3: getfield      #11                 // Field queue:Lio/reactivex/rxjava3/operators/SpscLinkedArrayQueue;
       6: astore_3
       7: aload_0
       8: getfield      #15                 // Field delayError:Z
      11: ifne          18
      14: iconst_1
      15: goto          19
      18: iconst_0
      19: istore        4
      21: aload_0
      22: getfield      #28                 // Field disposed:Z
      25: ifeq          37
      28: aload_0
      29: getfield      #17                 // Field downstream:Ljava/util/concurrent/atomic/AtomicReference;
      32: aconst_null
      33: invokevirtual #27                 // Method java/util/concurrent/atomic/AtomicReference.lazySet:(Ljava/lang/Object;)V
      36: return
      37: aload_0
      38: getfield      #38                 // Field done:Z
      41: istore        5
      43: iload         4
      45: ifeq          63
      48: iload         5
      50: ifeq          63
      53: aload_0
      54: aload_3
      55: aload_1
      56: invokevirtual #49                 // Method failedFast:(Lio/reactivex/rxjava3/operators/SimpleQueue;Lio/reactivex/rxjava3/core/Observer;)Z
      59: ifeq          63
      62: return
      63: aload_1
      64: aconst_null
      65: invokeinterface #51,  2           // InterfaceMethod io/reactivex/rxjava3/core/Observer.onNext:(Ljava/lang/Object;)V
      70: iload         5
      72: ifeq          81
      75: aload_0
      76: aload_1
      77: invokevirtual #50                 // Method errorOrComplete:(Lio/reactivex/rxjava3/core/Observer;)V
      80: return
      81: aload_0
      82: getfield      #23                 // Field wip:Lio/reactivex/rxjava3/internal/observers/BasicIntQueueDisposable;
      85: iload_2
      86: ineg
      87: invokevirtual #52                 // Method io/reactivex/rxjava3/internal/observers/BasicIntQueueDisposable.addAndGet:(I)I
      90: istore_2
      91: iload_2
      92: ifne          98
      95: goto          101
      98: goto          21
     101: return

  void errorOrComplete(io.reactivex.rxjava3.core.Observer<? super T>);
    Code:
       0: aload_0
       1: getfield      #17                 // Field downstream:Ljava/util/concurrent/atomic/AtomicReference;
       4: aconst_null
       5: invokevirtual #27                 // Method java/util/concurrent/atomic/AtomicReference.lazySet:(Ljava/lang/Object;)V
       8: aload_0
       9: getfield      #45                 // Field error:Ljava/lang/Throwable;
      12: astore_2
      13: aload_2
      14: ifnull        27
      17: aload_1
      18: aload_2
      19: invokeinterface #53,  2           // InterfaceMethod io/reactivex/rxjava3/core/Observer.onError:(Ljava/lang/Throwable;)V
      24: goto          33
      27: aload_1
      28: invokeinterface #54,  1           // InterfaceMethod io/reactivex/rxjava3/core/Observer.onComplete:()V
      33: return

  boolean failedFast(io.reactivex.rxjava3.operators.SimpleQueue<T>, io.reactivex.rxjava3.core.Observer<? super T>);
    Code:
       0: aload_0
       1: getfield      #45                 // Field error:Ljava/lang/Throwable;
       4: astore_3
       5: aload_3
       6: ifnull        32
       9: aload_0
      10: getfield      #17                 // Field downstream:Ljava/util/concurrent/atomic/AtomicReference;
      13: aconst_null
      14: invokevirtual #27                 // Method java/util/concurrent/atomic/AtomicReference.lazySet:(Ljava/lang/Object;)V
      17: aload_1
      18: invokeinterface #47,  1           // InterfaceMethod io/reactivex/rxjava3/operators/SimpleQueue.clear:()V
      23: aload_2
      24: aload_3
      25: invokeinterface #53,  2           // InterfaceMethod io/reactivex/rxjava3/core/Observer.onError:(Ljava/lang/Throwable;)V
      30: iconst_1
      31: ireturn
      32: iconst_0
      33: ireturn

  void drain();
    Code:
       0: aload_0
       1: getfield      #23                 // Field wip:Lio/reactivex/rxjava3/internal/observers/BasicIntQueueDisposable;
       4: invokevirtual #55                 // Method io/reactivex/rxjava3/internal/observers/BasicIntQueueDisposable.getAndIncrement:()I
       7: ifeq          11
      10: return
      11: aload_0
      12: getfield      #17                 // Field downstream:Ljava/util/concurrent/atomic/AtomicReference;
      15: invokevirtual #34                 // Method java/util/concurrent/atomic/AtomicReference.get:()Ljava/lang/Object;
      18: checkcast     #56                 // class io/reactivex/rxjava3/core/Observer
      21: astore_1
      22: iconst_1
      23: istore_2
      24: aload_1
      25: ifnull        49
      28: aload_0
      29: getfield      #57                 // Field enableOperatorFusion:Z
      32: ifeq          43
      35: aload_0
      36: aload_1
      37: invokevirtual #58                 // Method drainFused:(Lio/reactivex/rxjava3/core/Observer;)V
      40: goto          48
      43: aload_0
      44: aload_1
      45: invokevirtual #59                 // Method drainNormal:(Lio/reactivex/rxjava3/core/Observer;)V
      48: return
      49: aload_0
      50: getfield      #23                 // Field wip:Lio/reactivex/rxjava3/internal/observers/BasicIntQueueDisposable;
      53: iload_2
      54: ineg
      55: invokevirtual #52                 // Method io/reactivex/rxjava3/internal/observers/BasicIntQueueDisposable.addAndGet:(I)I
      58: istore_2
      59: iload_2
      60: ifne          66
      63: goto          80
      66: aload_0
      67: getfield      #17                 // Field downstream:Ljava/util/concurrent/atomic/AtomicReference;
      70: invokevirtual #34                 // Method java/util/concurrent/atomic/AtomicReference.get:()Ljava/lang/Object;
      73: checkcast     #56                 // class io/reactivex/rxjava3/core/Observer
      76: astore_1
      77: goto          24
      80: return

  public boolean hasObservers();
    Code:
       0: aload_0
       1: getfield      #17                 // Field downstream:Ljava/util/concurrent/atomic/AtomicReference;
       4: invokevirtual #34                 // Method java/util/concurrent/atomic/AtomicReference.get:()Ljava/lang/Object;
       7: ifnull        14
      10: iconst_1
      11: goto          15
      14: iconst_0
      15: ireturn

  public java.lang.Throwable getThrowable();
    Code:
       0: aload_0
       1: getfield      #38                 // Field done:Z
       4: ifeq          12
       7: aload_0
       8: getfield      #45                 // Field error:Ljava/lang/Throwable;
      11: areturn
      12: aconst_null
      13: areturn

  public boolean hasThrowable();
    Code:
       0: aload_0
       1: getfield      #38                 // Field done:Z
       4: ifeq          18
       7: aload_0
       8: getfield      #45                 // Field error:Ljava/lang/Throwable;
      11: ifnull        18
      14: iconst_1
      15: goto          19
      18: iconst_0
      19: ireturn

  public boolean hasComplete();
    Code:
       0: aload_0
       1: getfield      #38                 // Field done:Z
       4: ifeq          18
       7: aload_0
       8: getfield      #45                 // Field error:Ljava/lang/Throwable;
      11: ifnonnull     18
      14: iconst_1
      15: goto          19
      18: iconst_0
      19: ireturn
}
