Compiled from "JavaLoggingSystemRuntimeHints.java"
class org.springframework.boot.logging.java.JavaLoggingSystemRuntimeHints implements org.springframework.aot.hint.RuntimeHintsRegistrar {
  org.springframework.boot.logging.java.JavaLoggingSystemRuntimeHints();
    Code:
       0: aload_0
       1: invokespecial #1                  // Method java/lang/Object."<init>":()V
       4: return

  public void registerHints(org.springframework.aot.hint.RuntimeHints, java.lang.ClassLoader);
    Code:
       0: aload_1
       1: invokevirtual #7                  // Method org/springframework/aot/hint/RuntimeHints.resources:()Lorg/springframework/aot/hint/ResourceHints;
       4: ldc           #13                 // String org/springframework/boot/logging/java/logging.properties
       6: invokevirtual #15                 // Method org/springframework/aot/hint/ResourceHints.registerPattern:(Ljava/lang/String;)Lorg/springframework/aot/hint/ResourceHints;
       9: pop
      10: aload_1
      11: invokevirtual #7                  // Method org/springframework/aot/hint/RuntimeHints.resources:()Lorg/springframework/aot/hint/ResourceHints;
      14: ldc           #21                 // String org/springframework/boot/logging/java/logging-file.properties
      16: invokevirtual #15                 // Method org/springframework/aot/hint/ResourceHints.registerPattern:(Ljava/lang/String;)Lorg/springframework/aot/hint/ResourceHints;
      19: pop
      20: return
}
