Compiled from "EventType.java"
public final class org.apache.dubbo.remoting.zookeeper.EventType extends java.lang.Enum<org.apache.dubbo.remoting.zookeeper.EventType> {
  public static final org.apache.dubbo.remoting.zookeeper.EventType None;

  public static final org.apache.dubbo.remoting.zookeeper.EventType NodeCreated;

  public static final org.apache.dubbo.remoting.zookeeper.EventType NodeDeleted;

  public static final org.apache.dubbo.remoting.zookeeper.EventType NodeDataChanged;

  public static final org.apache.dubbo.remoting.zookeeper.EventType NodeChildrenChanged;

  public static final org.apache.dubbo.remoting.zookeeper.EventType CONNECTION_SUSPENDED;

  public static final org.apache.dubbo.remoting.zookeeper.EventType CONNECTION_RECONNECTED;

  public static final org.apache.dubbo.remoting.zookeeper.EventType CONNECTION_LOST;

  public static final org.apache.dubbo.remoting.zookeeper.EventType INITIALIZED;

  private final int intValue;

  private static final org.apache.dubbo.remoting.zookeeper.EventType[] $VALUES;

  public static org.apache.dubbo.remoting.zookeeper.EventType[] values();
    Code:
       0: getstatic     #1                  // Field $VALUES:[Lorg/apache/dubbo/remoting/zookeeper/EventType;
       3: invokevirtual #2                  // Method "[Lorg/apache/dubbo/remoting/zookeeper/EventType;".clone:()Ljava/lang/Object;
       6: checkcast     #3                  // class "[Lorg/apache/dubbo/remoting/zookeeper/EventType;"
       9: areturn

  public static org.apache.dubbo.remoting.zookeeper.EventType valueOf(java.lang.String);
    Code:
       0: ldc           #4                  // class org/apache/dubbo/remoting/zookeeper/EventType
       2: aload_0
       3: invokestatic  #5                  // Method java/lang/Enum.valueOf:(Ljava/lang/Class;Ljava/lang/String;)Ljava/lang/Enum;
       6: checkcast     #4                  // class org/apache/dubbo/remoting/zookeeper/EventType
       9: areturn

  private org.apache.dubbo.remoting.zookeeper.EventType(int);
    Code:
       0: aload_0
       1: aload_1
       2: iload_2
       3: invokespecial #6                  // Method java/lang/Enum."<init>":(Ljava/lang/String;I)V
       6: aload_0
       7: iload_3
       8: putfield      #7                  // Field intValue:I
      11: return

  public int getIntValue();
    Code:
       0: aload_0
       1: getfield      #7                  // Field intValue:I
       4: ireturn

  static {};
    Code:
       0: new           #4                  // class org/apache/dubbo/remoting/zookeeper/EventType
       3: dup
       4: ldc           #8                  // String None
       6: iconst_0
       7: iconst_m1
       8: invokespecial #9                  // Method "<init>":(Ljava/lang/String;II)V
      11: putstatic     #10                 // Field None:Lorg/apache/dubbo/remoting/zookeeper/EventType;
      14: new           #4                  // class org/apache/dubbo/remoting/zookeeper/EventType
      17: dup
      18: ldc           #11                 // String NodeCreated
      20: iconst_1
      21: iconst_1
      22: invokespecial #9                  // Method "<init>":(Ljava/lang/String;II)V
      25: putstatic     #12                 // Field NodeCreated:Lorg/apache/dubbo/remoting/zookeeper/EventType;
      28: new           #4                  // class org/apache/dubbo/remoting/zookeeper/EventType
      31: dup
      32: ldc           #13                 // String NodeDeleted
      34: iconst_2
      35: iconst_2
      36: invokespecial #9                  // Method "<init>":(Ljava/lang/String;II)V
      39: putstatic     #14                 // Field NodeDeleted:Lorg/apache/dubbo/remoting/zookeeper/EventType;
      42: new           #4                  // class org/apache/dubbo/remoting/zookeeper/EventType
      45: dup
      46: ldc           #15                 // String NodeDataChanged
      48: iconst_3
      49: iconst_3
      50: invokespecial #9                  // Method "<init>":(Ljava/lang/String;II)V
      53: putstatic     #16                 // Field NodeDataChanged:Lorg/apache/dubbo/remoting/zookeeper/EventType;
      56: new           #4                  // class org/apache/dubbo/remoting/zookeeper/EventType
      59: dup
      60: ldc           #17                 // String NodeChildrenChanged
      62: iconst_4
      63: iconst_4
      64: invokespecial #9                  // Method "<init>":(Ljava/lang/String;II)V
      67: putstatic     #18                 // Field NodeChildrenChanged:Lorg/apache/dubbo/remoting/zookeeper/EventType;
      70: new           #4                  // class org/apache/dubbo/remoting/zookeeper/EventType
      73: dup
      74: ldc           #19                 // String CONNECTION_SUSPENDED
      76: iconst_5
      77: bipush        11
      79: invokespecial #9                  // Method "<init>":(Ljava/lang/String;II)V
      82: putstatic     #20                 // Field CONNECTION_SUSPENDED:Lorg/apache/dubbo/remoting/zookeeper/EventType;
      85: new           #4                  // class org/apache/dubbo/remoting/zookeeper/EventType
      88: dup
      89: ldc           #21                 // String CONNECTION_RECONNECTED
      91: bipush        6
      93: bipush        12
      95: invokespecial #9                  // Method "<init>":(Ljava/lang/String;II)V
      98: putstatic     #22                 // Field CONNECTION_RECONNECTED:Lorg/apache/dubbo/remoting/zookeeper/EventType;
     101: new           #4                  // class org/apache/dubbo/remoting/zookeeper/EventType
     104: dup
     105: ldc           #23                 // String CONNECTION_LOST
     107: bipush        7
     109: bipush        12
     111: invokespecial #9                  // Method "<init>":(Ljava/lang/String;II)V
     114: putstatic     #24                 // Field CONNECTION_LOST:Lorg/apache/dubbo/remoting/zookeeper/EventType;
     117: new           #4                  // class org/apache/dubbo/remoting/zookeeper/EventType
     120: dup
     121: ldc           #25                 // String INITIALIZED
     123: bipush        8
     125: bipush        10
     127: invokespecial #9                  // Method "<init>":(Ljava/lang/String;II)V
     130: putstatic     #26                 // Field INITIALIZED:Lorg/apache/dubbo/remoting/zookeeper/EventType;
     133: bipush        9
     135: anewarray     #4                  // class org/apache/dubbo/remoting/zookeeper/EventType
     138: dup
     139: iconst_0
     140: getstatic     #10                 // Field None:Lorg/apache/dubbo/remoting/zookeeper/EventType;
     143: aastore
     144: dup
     145: iconst_1
     146: getstatic     #12                 // Field NodeCreated:Lorg/apache/dubbo/remoting/zookeeper/EventType;
     149: aastore
     150: dup
     151: iconst_2
     152: getstatic     #14                 // Field NodeDeleted:Lorg/apache/dubbo/remoting/zookeeper/EventType;
     155: aastore
     156: dup
     157: iconst_3
     158: getstatic     #16                 // Field NodeDataChanged:Lorg/apache/dubbo/remoting/zookeeper/EventType;
     161: aastore
     162: dup
     163: iconst_4
     164: getstatic     #18                 // Field NodeChildrenChanged:Lorg/apache/dubbo/remoting/zookeeper/EventType;
     167: aastore
     168: dup
     169: iconst_5
     170: getstatic     #20                 // Field CONNECTION_SUSPENDED:Lorg/apache/dubbo/remoting/zookeeper/EventType;
     173: aastore
     174: dup
     175: bipush        6
     177: getstatic     #22                 // Field CONNECTION_RECONNECTED:Lorg/apache/dubbo/remoting/zookeeper/EventType;
     180: aastore
     181: dup
     182: bipush        7
     184: getstatic     #24                 // Field CONNECTION_LOST:Lorg/apache/dubbo/remoting/zookeeper/EventType;
     187: aastore
     188: dup
     189: bipush        8
     191: getstatic     #26                 // Field INITIALIZED:Lorg/apache/dubbo/remoting/zookeeper/EventType;
     194: aastore
     195: putstatic     #1                  // Field $VALUES:[Lorg/apache/dubbo/remoting/zookeeper/EventType;
     198: return
}
