Compiled from "ZookeeperTransporter.java"
public interface org.apache.dubbo.remoting.zookeeper.ZookeeperTransporter {
  public static final java.lang.String CURATOR_5;

  public static final java.lang.String CURATOR;

  public abstract org.apache.dubbo.remoting.zookeeper.ZookeeperClient connect(org.apache.dubbo.common.URL);

  public abstract void destroy();

  public static org.apache.dubbo.remoting.zookeeper.ZookeeperTransporter getExtension(org.apache.dubbo.rpc.model.ApplicationModel);
    Code:
       0: aload_0
       1: ldc           #1                  // class org/apache/dubbo/remoting/zookeeper/ZookeeperTransporter
       3: invokevirtual #2                  // Method org/apache/dubbo/rpc/model/ApplicationModel.getExtensionLoader:(Ljava/lang/Class;)Lorg/apache/dubbo/common/extension/ExtensionLoader;
       6: astore_1
       7: invokestatic  #3                  // InterfaceMethod isHighVersionCurator:()Z
      10: ifeq          25
      13: aload_1
      14: ldc           #4                  // String curator5
      16: invokevirtual #5                  // Method org/apache/dubbo/common/extension/ExtensionLoader.getExtension:(Ljava/lang/String;)Ljava/lang/Object;
      19: checkcast     #1                  // class org/apache/dubbo/remoting/zookeeper/ZookeeperTransporter
      22: goto          34
      25: aload_1
      26: ldc           #6                  // String curator
      28: invokevirtual #5                  // Method org/apache/dubbo/common/extension/ExtensionLoader.getExtension:(Ljava/lang/String;)Ljava/lang/Object;
      31: checkcast     #1                  // class org/apache/dubbo/remoting/zookeeper/ZookeeperTransporter
      34: areturn

  public static boolean isHighVersionCurator();
    Code:
       0: ldc           #7                  // String org.apache.curator.framework.recipes.cache.CuratorCache
       2: invokestatic  #8                  // Method java/lang/Class.forName:(Ljava/lang/String;)Ljava/lang/Class;
       5: pop
       6: iconst_1
       7: ireturn
       8: astore_0
       9: iconst_0
      10: ireturn
    Exception table:
       from    to  target type
           0     7     8   Class java/lang/ClassNotFoundException
}
