Compiled from "TKv.java"
public class org.apache.dubbo.qos.textui.TKv implements org.apache.dubbo.qos.textui.TComponent {
  private final org.apache.dubbo.qos.textui.TTable tTable;

  public org.apache.dubbo.qos.textui.TKv();
    Code:
       0: aload_0
       1: invokespecial #1                  // Method java/lang/Object."<init>":()V
       4: aload_0
       5: new           #2                  // class org/apache/dubbo/qos/textui/TTable
       8: dup
       9: iconst_3
      10: anewarray     #3                  // class org/apache/dubbo/qos/textui/TTable$ColumnDefine
      13: dup
      14: iconst_0
      15: new           #3                  // class org/apache/dubbo/qos/textui/TTable$ColumnDefine
      18: dup
      19: getstatic     #4                  // Field org/apache/dubbo/qos/textui/TTable$Align.RIGHT:Lorg/apache/dubbo/qos/textui/TTable$Align;
      22: invokespecial #5                  // Method org/apache/dubbo/qos/textui/TTable$ColumnDefine."<init>":(Lorg/apache/dubbo/qos/textui/TTable$Align;)V
      25: aastore
      26: dup
      27: iconst_1
      28: new           #3                  // class org/apache/dubbo/qos/textui/TTable$ColumnDefine
      31: dup
      32: getstatic     #4                  // Field org/apache/dubbo/qos/textui/TTable$Align.RIGHT:Lorg/apache/dubbo/qos/textui/TTable$Align;
      35: invokespecial #5                  // Method org/apache/dubbo/qos/textui/TTable$ColumnDefine."<init>":(Lorg/apache/dubbo/qos/textui/TTable$Align;)V
      38: aastore
      39: dup
      40: iconst_2
      41: new           #3                  // class org/apache/dubbo/qos/textui/TTable$ColumnDefine
      44: dup
      45: getstatic     #6                  // Field org/apache/dubbo/qos/textui/TTable$Align.LEFT:Lorg/apache/dubbo/qos/textui/TTable$Align;
      48: invokespecial #5                  // Method org/apache/dubbo/qos/textui/TTable$ColumnDefine."<init>":(Lorg/apache/dubbo/qos/textui/TTable$Align;)V
      51: aastore
      52: invokespecial #7                  // Method org/apache/dubbo/qos/textui/TTable."<init>":([Lorg/apache/dubbo/qos/textui/TTable$ColumnDefine;)V
      55: iconst_0
      56: invokevirtual #8                  // Method org/apache/dubbo/qos/textui/TTable.padding:(I)Lorg/apache/dubbo/qos/textui/TTable;
      59: putfield      #9                  // Field tTable:Lorg/apache/dubbo/qos/textui/TTable;
      62: aload_0
      63: getfield      #9                  // Field tTable:Lorg/apache/dubbo/qos/textui/TTable;
      66: invokevirtual #10                 // Method org/apache/dubbo/qos/textui/TTable.getBorder:()Lorg/apache/dubbo/qos/textui/TTable$Border;
      69: iconst_0
      70: invokevirtual #12                 // Method org/apache/dubbo/qos/textui/TTable$Border.set:(I)Lorg/apache/dubbo/qos/textui/TTable$Border;
      73: pop
      74: return

  public org.apache.dubbo.qos.textui.TKv(org.apache.dubbo.qos.textui.TTable$ColumnDefine, org.apache.dubbo.qos.textui.TTable$ColumnDefine);
    Code:
       0: aload_0
       1: invokespecial #1                  // Method java/lang/Object."<init>":()V
       4: aload_0
       5: new           #2                  // class org/apache/dubbo/qos/textui/TTable
       8: dup
       9: iconst_3
      10: anewarray     #3                  // class org/apache/dubbo/qos/textui/TTable$ColumnDefine
      13: dup
      14: iconst_0
      15: aload_1
      16: aastore
      17: dup
      18: iconst_1
      19: new           #3                  // class org/apache/dubbo/qos/textui/TTable$ColumnDefine
      22: dup
      23: getstatic     #4                  // Field org/apache/dubbo/qos/textui/TTable$Align.RIGHT:Lorg/apache/dubbo/qos/textui/TTable$Align;
      26: invokespecial #5                  // Method org/apache/dubbo/qos/textui/TTable$ColumnDefine."<init>":(Lorg/apache/dubbo/qos/textui/TTable$Align;)V
      29: aastore
      30: dup
      31: iconst_2
      32: aload_2
      33: aastore
      34: invokespecial #7                  // Method org/apache/dubbo/qos/textui/TTable."<init>":([Lorg/apache/dubbo/qos/textui/TTable$ColumnDefine;)V
      37: iconst_0
      38: invokevirtual #8                  // Method org/apache/dubbo/qos/textui/TTable.padding:(I)Lorg/apache/dubbo/qos/textui/TTable;
      41: putfield      #9                  // Field tTable:Lorg/apache/dubbo/qos/textui/TTable;
      44: aload_0
      45: getfield      #9                  // Field tTable:Lorg/apache/dubbo/qos/textui/TTable;
      48: invokevirtual #10                 // Method org/apache/dubbo/qos/textui/TTable.getBorder:()Lorg/apache/dubbo/qos/textui/TTable$Border;
      51: iconst_0
      52: invokevirtual #12                 // Method org/apache/dubbo/qos/textui/TTable$Border.set:(I)Lorg/apache/dubbo/qos/textui/TTable$Border;
      55: pop
      56: return

  public org.apache.dubbo.qos.textui.TKv add(java.lang.Object, java.lang.Object);
    Code:
       0: aload_0
       1: getfield      #9                  // Field tTable:Lorg/apache/dubbo/qos/textui/TTable;
       4: iconst_3
       5: anewarray     #13                 // class java/lang/Object
       8: dup
       9: iconst_0
      10: aload_1
      11: aastore
      12: dup
      13: iconst_1
      14: ldc           #14                 // String  :
      16: aastore
      17: dup
      18: iconst_2
      19: aload_2
      20: aastore
      21: invokevirtual #15                 // Method org/apache/dubbo/qos/textui/TTable.addRow:([Ljava/lang/Object;)Lorg/apache/dubbo/qos/textui/TTable;
      24: pop
      25: aload_0
      26: areturn

  public java.lang.String rendering();
    Code:
       0: aload_0
       1: aload_0
       2: getfield      #9                  // Field tTable:Lorg/apache/dubbo/qos/textui/TTable;
       5: invokevirtual #16                 // Method org/apache/dubbo/qos/textui/TTable.rendering:()Ljava/lang/String;
       8: invokespecial #17                 // Method filterEmptyLine:(Ljava/lang/String;)Ljava/lang/String;
      11: areturn

  private java.lang.String filterEmptyLine(java.lang.String);
    Code:
       0: new           #18                 // class java/lang/StringBuilder
       3: dup
       4: invokespecial #19                 // Method java/lang/StringBuilder."<init>":()V
       7: astore_2
       8: new           #20                 // class java/util/Scanner
      11: dup
      12: aload_1
      13: invokespecial #21                 // Method java/util/Scanner."<init>":(Ljava/lang/String;)V
      16: astore_3
      17: aconst_null
      18: astore        4
      20: aload_3
      21: invokevirtual #22                 // Method java/util/Scanner.hasNextLine:()Z
      24: ifeq          75
      27: aload_3
      28: invokevirtual #23                 // Method java/util/Scanner.nextLine:()Ljava/lang/String;
      31: astore        5
      33: aload         5
      35: ifnull        59
      38: aload         5
      40: ldc           #24                 // String
      42: invokestatic  #25                 // Method org/apache/dubbo/common/utils/StringUtils.stripEnd:(Ljava/lang/String;Ljava/lang/String;)Ljava/lang/String;
      45: astore        5
      47: aload         5
      49: invokevirtual #26                 // Method java/lang/String.isEmpty:()Z
      52: ifeq          59
      55: ldc           #24                 // String
      57: astore        5
      59: aload_2
      60: aload         5
      62: invokevirtual #27                 // Method java/lang/StringBuilder.append:(Ljava/lang/String;)Ljava/lang/StringBuilder;
      65: invokestatic  #28                 // Method java/lang/System.lineSeparator:()Ljava/lang/String;
      68: invokevirtual #27                 // Method java/lang/StringBuilder.append:(Ljava/lang/String;)Ljava/lang/StringBuilder;
      71: pop
      72: goto          20
      75: aload_3
      76: ifnull        156
      79: aload         4
      81: ifnull        103
      84: aload_3
      85: invokevirtual #29                 // Method java/util/Scanner.close:()V
      88: goto          156
      91: astore        5
      93: aload         4
      95: aload         5
      97: invokevirtual #31                 // Method java/lang/Throwable.addSuppressed:(Ljava/lang/Throwable;)V
     100: goto          156
     103: aload_3
     104: invokevirtual #29                 // Method java/util/Scanner.close:()V
     107: goto          156
     110: astore        5
     112: aload         5
     114: astore        4
     116: aload         5
     118: athrow
     119: astore        6
     121: aload_3
     122: ifnull        153
     125: aload         4
     127: ifnull        149
     130: aload_3
     131: invokevirtual #29                 // Method java/util/Scanner.close:()V
     134: goto          153
     137: astore        7
     139: aload         4
     141: aload         7
     143: invokevirtual #31                 // Method java/lang/Throwable.addSuppressed:(Ljava/lang/Throwable;)V
     146: goto          153
     149: aload_3
     150: invokevirtual #29                 // Method java/util/Scanner.close:()V
     153: aload         6
     155: athrow
     156: aload_2
     157: invokevirtual #32                 // Method java/lang/StringBuilder.toString:()Ljava/lang/String;
     160: areturn
    Exception table:
       from    to  target type
          84    88    91   Class java/lang/Throwable
          20    75   110   Class java/lang/Throwable
          20    75   119   any
         130   134   137   Class java/lang/Throwable
         110   121   119   any
}
