Compiled from "TLadder.java"
public class org.apache.dubbo.qos.textui.TLadder implements org.apache.dubbo.qos.textui.TComponent {
  private static final java.lang.String LADDER_CHAR;

  private static final java.lang.String STEP_CHAR;

  private static final int INDENT_STEP;

  private final java.util.List<java.lang.String> items;

  public org.apache.dubbo.qos.textui.TLadder();
    Code:
       0: aload_0
       1: invokespecial #1                  // Method java/lang/Object."<init>":()V
       4: aload_0
       5: new           #2                  // class java/util/LinkedList
       8: dup
       9: invokespecial #3                  // Method java/util/LinkedList."<init>":()V
      12: putfield      #4                  // Field items:Ljava/util/List;
      15: return

  public java.lang.String rendering();
    Code:
       0: new           #5                  // class java/lang/StringBuilder
       3: dup
       4: invokespecial #6                  // Method java/lang/StringBuilder."<init>":()V
       7: astore_1
       8: iconst_0
       9: istore_2
      10: aload_0
      11: getfield      #4                  // Field items:Ljava/util/List;
      14: invokeinterface #7,  1            // InterfaceMethod java/util/List.iterator:()Ljava/util/Iterator;
      19: astore_3
      20: aload_3
      21: invokeinterface #8,  1            // InterfaceMethod java/util/Iterator.hasNext:()Z
      26: ifeq          95
      29: aload_3
      30: invokeinterface #9,  1            // InterfaceMethod java/util/Iterator.next:()Ljava/lang/Object;
      35: checkcast     #10                 // class java/lang/String
      38: astore        4
      40: iload_2
      41: ifne          60
      44: aload_1
      45: aload         4
      47: invokevirtual #11                 // Method java/lang/StringBuilder.append:(Ljava/lang/String;)Ljava/lang/StringBuilder;
      50: invokestatic  #12                 // Method java/lang/System.lineSeparator:()Ljava/lang/String;
      53: invokevirtual #11                 // Method java/lang/StringBuilder.append:(Ljava/lang/String;)Ljava/lang/StringBuilder;
      56: pop
      57: goto          89
      60: aload_1
      61: ldc           #14                 // String
      63: iload_2
      64: iconst_2
      65: imul
      66: invokestatic  #15                 // Method org/apache/dubbo/common/utils/StringUtils.repeat:(Ljava/lang/String;I)Ljava/lang/String;
      69: invokevirtual #11                 // Method java/lang/StringBuilder.append:(Ljava/lang/String;)Ljava/lang/StringBuilder;
      72: ldc           #16                 // String `-
      74: invokevirtual #11                 // Method java/lang/StringBuilder.append:(Ljava/lang/String;)Ljava/lang/StringBuilder;
      77: aload         4
      79: invokevirtual #11                 // Method java/lang/StringBuilder.append:(Ljava/lang/String;)Ljava/lang/StringBuilder;
      82: invokestatic  #12                 // Method java/lang/System.lineSeparator:()Ljava/lang/String;
      85: invokevirtual #11                 // Method java/lang/StringBuilder.append:(Ljava/lang/String;)Ljava/lang/StringBuilder;
      88: pop
      89: iinc          2, 1
      92: goto          20
      95: aload_1
      96: invokevirtual #17                 // Method java/lang/StringBuilder.toString:()Ljava/lang/String;
      99: areturn

  public org.apache.dubbo.qos.textui.TLadder addItem(java.lang.String);
    Code:
       0: aload_0
       1: getfield      #4                  // Field items:Ljava/util/List;
       4: aload_1
       5: invokeinterface #18,  2           // InterfaceMethod java/util/List.add:(Ljava/lang/Object;)Z
      10: pop
      11: aload_0
      12: areturn
}
