Compiled from "TTable.java"
public class org.apache.dubbo.qos.textui.TTable$Border {
  private int borders;

  public static final int BORDER_OUTER_TOP;

  public static final int BORDER_OUTER_RIGHT;

  public static final int BORDER_OUTER_BOTTOM;

  public static final int BORDER_OUTER_LEFT;

  public static final int BORDER_INNER_H;

  public static final int BORDER_INNER_V;

  public static final int BORDER_OUTER;

  public static final int BORDER_INNER;

  public static final int BORDER_NON;

  final org.apache.dubbo.qos.textui.TTable this$0;

  public org.apache.dubbo.qos.textui.TTable$Border(org.apache.dubbo.qos.textui.TTable);
    Code:
       0: aload_0
       1: aload_1
       2: putfield      #2                  // Field this$0:Lorg/apache/dubbo/qos/textui/TTable;
       5: aload_0
       6: invokespecial #3                  // Method java/lang/Object."<init>":()V
       9: aload_0
      10: bipush        63
      12: putfield      #4                  // Field borders:I
      15: return

  public boolean has(int...);
    Code:
       0: aconst_null
       1: aload_1
       2: if_acmpne     7
       5: iconst_0
       6: ireturn
       7: aload_1
       8: astore_2
       9: aload_2
      10: arraylength
      11: istore_3
      12: iconst_0
      13: istore        4
      15: iload         4
      17: iload_3
      18: if_icmpge     47
      21: aload_2
      22: iload         4
      24: iaload
      25: istore        5
      27: aload_0
      28: getfield      #4                  // Field borders:I
      31: iload         5
      33: iand
      34: iload         5
      36: if_icmpne     41
      39: iconst_1
      40: ireturn
      41: iinc          4, 1
      44: goto          15
      47: iconst_0
      48: ireturn

  public int get();
    Code:
       0: aload_0
       1: getfield      #4                  // Field borders:I
       4: ireturn

  public org.apache.dubbo.qos.textui.TTable$Border set(int);
    Code:
       0: aload_0
       1: iload_1
       2: putfield      #4                  // Field borders:I
       5: aload_0
       6: areturn

  public org.apache.dubbo.qos.textui.TTable$Border add(int);
    Code:
       0: aload_0
       1: aload_0
       2: invokevirtual #5                  // Method get:()I
       5: iload_1
       6: ior
       7: invokevirtual #6                  // Method set:(I)Lorg/apache/dubbo/qos/textui/TTable$Border;
      10: areturn

  public org.apache.dubbo.qos.textui.TTable$Border remove(int);
    Code:
       0: aload_0
       1: aload_0
       2: invokevirtual #5                  // Method get:()I
       5: iload_1
       6: ixor
       7: invokevirtual #6                  // Method set:(I)Lorg/apache/dubbo/qos/textui/TTable$Border;
      10: areturn
}
