Compiled from "TTable.java"
class org.apache.dubbo.qos.textui.TTable$1 {
  static final int[] $SwitchMap$org$apache$dubbo$qos$textui$TTable$Align;

  static {};
    Code:
       0: invokestatic  #1                  // Method org/apache/dubbo/qos/textui/TTable$Align.values:()[Lorg/apache/dubbo/qos/textui/TTable$Align;
       3: arraylength
       4: newarray       int
       6: putstatic     #2                  // Field $SwitchMap$org$apache$dubbo$qos$textui$TTable$Align:[I
       9: getstatic     #2                  // Field $SwitchMap$org$apache$dubbo$qos$textui$TTable$Align:[I
      12: getstatic     #3                  // Field org/apache/dubbo/qos/textui/TTable$Align.MIDDLE:Lorg/apache/dubbo/qos/textui/TTable$Align;
      15: invokevirtual #4                  // Method org/apache/dubbo/qos/textui/TTable$Align.ordinal:()I
      18: iconst_1
      19: iastore
      20: goto          24
      23: astore_0
      24: getstatic     #2                  // Field $SwitchMap$org$apache$dubbo$qos$textui$TTable$Align:[I
      27: getstatic     #6                  // Field org/apache/dubbo/qos/textui/TTable$Align.RIGHT:Lorg/apache/dubbo/qos/textui/TTable$Align;
      30: invokevirtual #4                  // Method org/apache/dubbo/qos/textui/TTable$Align.ordinal:()I
      33: iconst_2
      34: iastore
      35: goto          39
      38: astore_0
      39: getstatic     #2                  // Field $SwitchMap$org$apache$dubbo$qos$textui$TTable$Align:[I
      42: getstatic     #7                  // Field org/apache/dubbo/qos/textui/TTable$Align.LEFT:Lorg/apache/dubbo/qos/textui/TTable$Align;
      45: invokevirtual #4                  // Method org/apache/dubbo/qos/textui/TTable$Align.ordinal:()I
      48: iconst_3
      49: iastore
      50: goto          54
      53: astore_0
      54: return
    Exception table:
       from    to  target type
           9    20    23   Class java/lang/NoSuchFieldError
          24    35    38   Class java/lang/NoSuchFieldError
          39    50    53   Class java/lang/NoSuchFieldError
}
