Compiled from "TTable.java"
public class org.apache.dubbo.qos.textui.TTable$ColumnDefine {
  private final int width;

  private final boolean isAutoResize;

  private final org.apache.dubbo.qos.textui.TTable$Align align;

  private final java.util.List<java.lang.String> rows;

  public org.apache.dubbo.qos.textui.TTable$ColumnDefine(int, boolean, org.apache.dubbo.qos.textui.TTable$Align);
    Code:
       0: aload_0
       1: invokespecial #3                  // Method java/lang/Object."<init>":()V
       4: aload_0
       5: new           #4                  // class java/util/ArrayList
       8: dup
       9: invokespecial #5                  // Method java/util/ArrayList."<init>":()V
      12: putfield      #2                  // Field rows:Ljava/util/List;
      15: aload_0
      16: iload_1
      17: putfield      #6                  // Field width:I
      20: aload_0
      21: iload_2
      22: putfield      #7                  // Field isAutoResize:Z
      25: aload_0
      26: aload_3
      27: putfield      #1                  // Field align:Lorg/apache/dubbo/qos/textui/TTable$Align;
      30: return

  public org.apache.dubbo.qos.textui.TTable$ColumnDefine(org.apache.dubbo.qos.textui.TTable$Align);
    Code:
       0: aload_0
       1: iconst_0
       2: iconst_1
       3: aload_1
       4: invokespecial #8                  // Method "<init>":(IZLorg/apache/dubbo/qos/textui/TTable$Align;)V
       7: return

  public org.apache.dubbo.qos.textui.TTable$ColumnDefine(int);
    Code:
       0: aload_0
       1: iload_1
       2: iconst_0
       3: getstatic     #9                  // Field org/apache/dubbo/qos/textui/TTable$Align.LEFT:Lorg/apache/dubbo/qos/textui/TTable$Align;
       6: invokespecial #8                  // Method "<init>":(IZLorg/apache/dubbo/qos/textui/TTable$Align;)V
       9: return

  public org.apache.dubbo.qos.textui.TTable$ColumnDefine(int, org.apache.dubbo.qos.textui.TTable$Align);
    Code:
       0: aload_0
       1: iload_1
       2: iconst_0
       3: aload_2
       4: invokespecial #8                  // Method "<init>":(IZLorg/apache/dubbo/qos/textui/TTable$Align;)V
       7: return

  public org.apache.dubbo.qos.textui.TTable$ColumnDefine();
    Code:
       0: aload_0
       1: getstatic     #9                  // Field org/apache/dubbo/qos/textui/TTable$Align.LEFT:Lorg/apache/dubbo/qos/textui/TTable$Align;
       4: invokespecial #10                 // Method "<init>":(Lorg/apache/dubbo/qos/textui/TTable$Align;)V
       7: return

  public int getWidth();
    Code:
       0: aload_0
       1: getfield      #7                  // Field isAutoResize:Z
       4: ifne          12
       7: aload_0
       8: getfield      #6                  // Field width:I
      11: ireturn
      12: iconst_0
      13: istore_1
      14: aload_0
      15: getfield      #2                  // Field rows:Ljava/util/List;
      18: invokeinterface #11,  1           // InterfaceMethod java/util/List.iterator:()Ljava/util/Iterator;
      23: astore_2
      24: aload_2
      25: invokeinterface #12,  1           // InterfaceMethod java/util/Iterator.hasNext:()Z
      30: ifeq          55
      33: aload_2
      34: invokeinterface #13,  1           // InterfaceMethod java/util/Iterator.next:()Ljava/lang/Object;
      39: checkcast     #14                 // class java/lang/String
      42: astore_3
      43: aload_3
      44: invokestatic  #15                 // Method org/apache/dubbo/qos/textui/TTable.access$200:(Ljava/lang/String;)I
      47: iload_1
      48: invokestatic  #16                 // Method java/lang/Math.max:(II)I
      51: istore_1
      52: goto          24
      55: iload_1
      56: ireturn

  public int getRowCount();
    Code:
       0: aload_0
       1: getfield      #2                  // Field rows:Ljava/util/List;
       4: invokeinterface #17,  1           // InterfaceMethod java/util/List.size:()I
       9: ireturn

  static java.util.List access$000(org.apache.dubbo.qos.textui.TTable$ColumnDefine);
    Code:
       0: aload_0
       1: getfield      #2                  // Field rows:Ljava/util/List;
       4: areturn

  static org.apache.dubbo.qos.textui.TTable$Align access$100(org.apache.dubbo.qos.textui.TTable$ColumnDefine);
    Code:
       0: aload_0
       1: getfield      #1                  // Field align:Lorg/apache/dubbo/qos/textui/TTable$Align;
       4: areturn
}
