Compiled from "TTable.java"
public final class org.apache.dubbo.qos.textui.TTable$Align extends java.lang.Enum<org.apache.dubbo.qos.textui.TTable$Align> {
  public static final org.apache.dubbo.qos.textui.TTable$Align LEFT;

  public static final org.apache.dubbo.qos.textui.TTable$Align RIGHT;

  public static final org.apache.dubbo.qos.textui.TTable$Align MIDDLE;

  private static final org.apache.dubbo.qos.textui.TTable$Align[] $VALUES;

  public static org.apache.dubbo.qos.textui.TTable$Align[] values();
    Code:
       0: getstatic     #1                  // Field $VALUES:[Lorg/apache/dubbo/qos/textui/TTable$Align;
       3: invokevirtual #2                  // Method "[Lorg/apache/dubbo/qos/textui/TTable$Align;".clone:()Ljava/lang/Object;
       6: checkcast     #3                  // class "[Lorg/apache/dubbo/qos/textui/TTable$Align;"
       9: areturn

  public static org.apache.dubbo.qos.textui.TTable$Align valueOf(java.lang.String);
    Code:
       0: ldc           #4                  // class org/apache/dubbo/qos/textui/TTable$Align
       2: aload_0
       3: invokestatic  #5                  // Method java/lang/Enum.valueOf:(Ljava/lang/Class;Ljava/lang/String;)Ljava/lang/Enum;
       6: checkcast     #4                  // class org/apache/dubbo/qos/textui/TTable$Align
       9: areturn

  private org.apache.dubbo.qos.textui.TTable$Align();
    Code:
       0: aload_0
       1: aload_1
       2: iload_2
       3: invokespecial #6                  // Method java/lang/Enum."<init>":(Ljava/lang/String;I)V
       6: return

  static {};
    Code:
       0: new           #4                  // class org/apache/dubbo/qos/textui/TTable$Align
       3: dup
       4: ldc           #7                  // String LEFT
       6: iconst_0
       7: invokespecial #8                  // Method "<init>":(Ljava/lang/String;I)V
      10: putstatic     #9                  // Field LEFT:Lorg/apache/dubbo/qos/textui/TTable$Align;
      13: new           #4                  // class org/apache/dubbo/qos/textui/TTable$Align
      16: dup
      17: ldc           #10                 // String RIGHT
      19: iconst_1
      20: invokespecial #8                  // Method "<init>":(Ljava/lang/String;I)V
      23: putstatic     #11                 // Field RIGHT:Lorg/apache/dubbo/qos/textui/TTable$Align;
      26: new           #4                  // class org/apache/dubbo/qos/textui/TTable$Align
      29: dup
      30: ldc           #12                 // String MIDDLE
      32: iconst_2
      33: invokespecial #8                  // Method "<init>":(Ljava/lang/String;I)V
      36: putstatic     #13                 // Field MIDDLE:Lorg/apache/dubbo/qos/textui/TTable$Align;
      39: iconst_3
      40: anewarray     #4                  // class org/apache/dubbo/qos/textui/TTable$Align
      43: dup
      44: iconst_0
      45: getstatic     #9                  // Field LEFT:Lorg/apache/dubbo/qos/textui/TTable$Align;
      48: aastore
      49: dup
      50: iconst_1
      51: getstatic     #11                 // Field RIGHT:Lorg/apache/dubbo/qos/textui/TTable$Align;
      54: aastore
      55: dup
      56: iconst_2
      57: getstatic     #13                 // Field MIDDLE:Lorg/apache/dubbo/qos/textui/TTable$Align;
      60: aastore
      61: putstatic     #1                  // Field $VALUES:[Lorg/apache/dubbo/qos/textui/TTable$Align;
      64: return
}
