Compiled from "TTree.java"
public class org.apache.dubbo.qos.textui.TTree implements org.apache.dubbo.qos.textui.TComponent {
  private static final java.lang.String STEP_FIRST_CHAR;

  private static final java.lang.String STEP_NORMAL_CHAR;

  private static final java.lang.String STEP_HAS_BOARD;

  private static final java.lang.String STEP_EMPTY_BOARD;

  private final boolean isPrintCost;

  private final org.apache.dubbo.qos.textui.TTree$Node root;

  private org.apache.dubbo.qos.textui.TTree$Node current;

  public org.apache.dubbo.qos.textui.TTree(boolean, java.lang.String);
    Code:
       0: aload_0
       1: invokespecial #3                  // Method java/lang/Object."<init>":()V
       4: aload_0
       5: new           #4                  // class org/apache/dubbo/qos/textui/TTree$Node
       8: dup
       9: aload_2
      10: aconst_null
      11: invokespecial #5                  // Method org/apache/dubbo/qos/textui/TTree$Node."<init>":(Ljava/lang/Object;Lorg/apache/dubbo/qos/textui/TTree$1;)V
      14: invokevirtual #6                  // Method org/apache/dubbo/qos/textui/TTree$Node.markBegin:()Lorg/apache/dubbo/qos/textui/TTree$Node;
      17: invokevirtual #7                  // Method org/apache/dubbo/qos/textui/TTree$Node.markEnd:()Lorg/apache/dubbo/qos/textui/TTree$Node;
      20: putfield      #1                  // Field root:Lorg/apache/dubbo/qos/textui/TTree$Node;
      23: aload_0
      24: aload_0
      25: getfield      #1                  // Field root:Lorg/apache/dubbo/qos/textui/TTree$Node;
      28: putfield      #8                  // Field current:Lorg/apache/dubbo/qos/textui/TTree$Node;
      31: aload_0
      32: iload_1
      33: putfield      #2                  // Field isPrintCost:Z
      36: return

  public java.lang.String rendering();
    Code:
       0: new           #9                  // class java/lang/StringBuilder
       3: dup
       4: invokespecial #10                 // Method java/lang/StringBuilder."<init>":()V
       7: astore_1
       8: aload_0
       9: iconst_0
      10: iconst_1
      11: ldc           #11                 // String
      13: aload_0
      14: getfield      #1                  // Field root:Lorg/apache/dubbo/qos/textui/TTree$Node;
      17: new           #12                 // class org/apache/dubbo/qos/textui/TTree$1
      20: dup
      21: aload_0
      22: aload_1
      23: invokespecial #13                 // Method org/apache/dubbo/qos/textui/TTree$1."<init>":(Lorg/apache/dubbo/qos/textui/TTree;Ljava/lang/StringBuilder;)V
      26: invokespecial #14                 // Method recursive:(IZLjava/lang/String;Lorg/apache/dubbo/qos/textui/TTree$Node;Lorg/apache/dubbo/qos/textui/TTree$Callback;)V
      29: aload_1
      30: invokevirtual #15                 // Method java/lang/StringBuilder.toString:()Ljava/lang/String;
      33: areturn

  private void recursive(int, boolean, java.lang.String, org.apache.dubbo.qos.textui.TTree$Node, org.apache.dubbo.qos.textui.TTree$Callback);
    Code:
       0: aload         5
       2: iload_1
       3: iload_2
       4: aload_3
       5: aload         4
       7: invokeinterface #16,  5           // InterfaceMethod org/apache/dubbo/qos/textui/TTree$Callback.callback:(IZLjava/lang/String;Lorg/apache/dubbo/qos/textui/TTree$Node;)V
      12: aload         4
      14: invokevirtual #17                 // Method org/apache/dubbo/qos/textui/TTree$Node.isLeaf:()Z
      17: ifne          139
      20: aload         4
      22: getfield      #18                 // Field org/apache/dubbo/qos/textui/TTree$Node.children:Ljava/util/List;
      25: invokeinterface #19,  1           // InterfaceMethod java/util/List.size:()I
      30: istore        6
      32: iconst_0
      33: istore        7
      35: iload         7
      37: iload         6
      39: if_icmpge     139
      42: iload         7
      44: iload         6
      46: iconst_1
      47: isub
      48: if_icmpne     55
      51: iconst_1
      52: goto          56
      55: iconst_0
      56: istore        8
      58: iload_2
      59: ifeq          84
      62: new           #9                  // class java/lang/StringBuilder
      65: dup
      66: invokespecial #10                 // Method java/lang/StringBuilder."<init>":()V
      69: aload_3
      70: invokevirtual #20                 // Method java/lang/StringBuilder.append:(Ljava/lang/String;)Ljava/lang/StringBuilder;
      73: ldc           #22                 // String
      75: invokevirtual #20                 // Method java/lang/StringBuilder.append:(Ljava/lang/String;)Ljava/lang/StringBuilder;
      78: invokevirtual #15                 // Method java/lang/StringBuilder.toString:()Ljava/lang/String;
      81: goto          103
      84: new           #9                  // class java/lang/StringBuilder
      87: dup
      88: invokespecial #10                 // Method java/lang/StringBuilder."<init>":()V
      91: aload_3
      92: invokevirtual #20                 // Method java/lang/StringBuilder.append:(Ljava/lang/String;)Ljava/lang/StringBuilder;
      95: ldc           #23                 // String |
      97: invokevirtual #20                 // Method java/lang/StringBuilder.append:(Ljava/lang/String;)Ljava/lang/StringBuilder;
     100: invokevirtual #15                 // Method java/lang/StringBuilder.toString:()Ljava/lang/String;
     103: astore        9
     105: aload_0
     106: iload_1
     107: iconst_1
     108: iadd
     109: iload         8
     111: aload         9
     113: aload         4
     115: getfield      #18                 // Field org/apache/dubbo/qos/textui/TTree$Node.children:Ljava/util/List;
     118: iload         7
     120: invokeinterface #24,  2           // InterfaceMethod java/util/List.get:(I)Ljava/lang/Object;
     125: checkcast     #4                  // class org/apache/dubbo/qos/textui/TTree$Node
     128: aload         5
     130: invokespecial #14                 // Method recursive:(IZLjava/lang/String;Lorg/apache/dubbo/qos/textui/TTree$Node;Lorg/apache/dubbo/qos/textui/TTree$Callback;)V
     133: iinc          7, 1
     136: goto          35
     139: return

  public boolean isTop();
    Code:
       0: aload_0
       1: getfield      #8                  // Field current:Lorg/apache/dubbo/qos/textui/TTree$Node;
       4: invokevirtual #25                 // Method org/apache/dubbo/qos/textui/TTree$Node.isRoot:()Z
       7: ireturn

  public org.apache.dubbo.qos.textui.TTree begin(java.lang.Object);
    Code:
       0: aload_0
       1: new           #4                  // class org/apache/dubbo/qos/textui/TTree$Node
       4: dup
       5: aload_0
       6: getfield      #8                  // Field current:Lorg/apache/dubbo/qos/textui/TTree$Node;
       9: aload_1
      10: aconst_null
      11: invokespecial #26                 // Method org/apache/dubbo/qos/textui/TTree$Node."<init>":(Lorg/apache/dubbo/qos/textui/TTree$Node;Ljava/lang/Object;Lorg/apache/dubbo/qos/textui/TTree$1;)V
      14: putfield      #8                  // Field current:Lorg/apache/dubbo/qos/textui/TTree$Node;
      17: aload_0
      18: getfield      #8                  // Field current:Lorg/apache/dubbo/qos/textui/TTree$Node;
      21: invokevirtual #6                  // Method org/apache/dubbo/qos/textui/TTree$Node.markBegin:()Lorg/apache/dubbo/qos/textui/TTree$Node;
      24: pop
      25: aload_0
      26: areturn

  public org.apache.dubbo.qos.textui.TTree begin();
    Code:
       0: aload_0
       1: aconst_null
       2: invokevirtual #27                 // Method begin:(Ljava/lang/Object;)Lorg/apache/dubbo/qos/textui/TTree;
       5: areturn

  public java.lang.Object get();
    Code:
       0: aload_0
       1: getfield      #8                  // Field current:Lorg/apache/dubbo/qos/textui/TTree$Node;
       4: invokevirtual #25                 // Method org/apache/dubbo/qos/textui/TTree$Node.isRoot:()Z
       7: ifeq          20
      10: new           #28                 // class java/lang/IllegalStateException
      13: dup
      14: ldc           #29                 // String current node is root.
      16: invokespecial #30                 // Method java/lang/IllegalStateException."<init>":(Ljava/lang/String;)V
      19: athrow
      20: aload_0
      21: getfield      #8                  // Field current:Lorg/apache/dubbo/qos/textui/TTree$Node;
      24: getfield      #31                 // Field org/apache/dubbo/qos/textui/TTree$Node.data:Ljava/lang/Object;
      27: areturn

  public org.apache.dubbo.qos.textui.TTree set(java.lang.Object);
    Code:
       0: aload_0
       1: getfield      #8                  // Field current:Lorg/apache/dubbo/qos/textui/TTree$Node;
       4: invokevirtual #25                 // Method org/apache/dubbo/qos/textui/TTree$Node.isRoot:()Z
       7: ifeq          20
      10: new           #28                 // class java/lang/IllegalStateException
      13: dup
      14: ldc           #29                 // String current node is root.
      16: invokespecial #30                 // Method java/lang/IllegalStateException."<init>":(Ljava/lang/String;)V
      19: athrow
      20: aload_0
      21: getfield      #8                  // Field current:Lorg/apache/dubbo/qos/textui/TTree$Node;
      24: aload_1
      25: putfield      #31                 // Field org/apache/dubbo/qos/textui/TTree$Node.data:Ljava/lang/Object;
      28: aload_0
      29: areturn

  public org.apache.dubbo.qos.textui.TTree end();
    Code:
       0: aload_0
       1: getfield      #8                  // Field current:Lorg/apache/dubbo/qos/textui/TTree$Node;
       4: invokevirtual #25                 // Method org/apache/dubbo/qos/textui/TTree$Node.isRoot:()Z
       7: ifeq          20
      10: new           #28                 // class java/lang/IllegalStateException
      13: dup
      14: ldc           #29                 // String current node is root.
      16: invokespecial #30                 // Method java/lang/IllegalStateException."<init>":(Ljava/lang/String;)V
      19: athrow
      20: aload_0
      21: getfield      #8                  // Field current:Lorg/apache/dubbo/qos/textui/TTree$Node;
      24: invokevirtual #7                  // Method org/apache/dubbo/qos/textui/TTree$Node.markEnd:()Lorg/apache/dubbo/qos/textui/TTree$Node;
      27: pop
      28: aload_0
      29: aload_0
      30: getfield      #8                  // Field current:Lorg/apache/dubbo/qos/textui/TTree$Node;
      33: getfield      #32                 // Field org/apache/dubbo/qos/textui/TTree$Node.parent:Lorg/apache/dubbo/qos/textui/TTree$Node;
      36: putfield      #8                  // Field current:Lorg/apache/dubbo/qos/textui/TTree$Node;
      39: aload_0
      40: areturn

  static boolean access$100(org.apache.dubbo.qos.textui.TTree);
    Code:
       0: aload_0
       1: getfield      #2                  // Field isPrintCost:Z
       4: ireturn

  static org.apache.dubbo.qos.textui.TTree$Node access$300(org.apache.dubbo.qos.textui.TTree);
    Code:
       0: aload_0
       1: getfield      #1                  // Field root:Lorg/apache/dubbo/qos/textui/TTree$Node;
       4: areturn
}
