Compiled from "TTree.java"
class org.apache.dubbo.qos.textui.TTree$Node {
  final org.apache.dubbo.qos.textui.TTree$Node parent;

  java.lang.Object data;

  final java.util.List<org.apache.dubbo.qos.textui.TTree$Node> children;

  private long beginTimestamp;

  private long endTimestamp;

  private org.apache.dubbo.qos.textui.TTree$Node(java.lang.Object);
    Code:
       0: aload_0
       1: invokespecial #5                  // Method java/lang/Object."<init>":()V
       4: aload_0
       5: new           #6                  // class java/util/ArrayList
       8: dup
       9: invokespecial #7                  // Method java/util/ArrayList."<init>":()V
      12: putfield      #8                  // Field children:Ljava/util/List;
      15: aload_0
      16: aconst_null
      17: putfield      #9                  // Field parent:Lorg/apache/dubbo/qos/textui/TTree$Node;
      20: aload_0
      21: aload_1
      22: putfield      #10                 // Field data:Ljava/lang/Object;
      25: return

  private org.apache.dubbo.qos.textui.TTree$Node(org.apache.dubbo.qos.textui.TTree$Node, java.lang.Object);
    Code:
       0: aload_0
       1: invokespecial #5                  // Method java/lang/Object."<init>":()V
       4: aload_0
       5: new           #6                  // class java/util/ArrayList
       8: dup
       9: invokespecial #7                  // Method java/util/ArrayList."<init>":()V
      12: putfield      #8                  // Field children:Ljava/util/List;
      15: aload_0
      16: aload_1
      17: putfield      #9                  // Field parent:Lorg/apache/dubbo/qos/textui/TTree$Node;
      20: aload_0
      21: aload_2
      22: putfield      #10                 // Field data:Ljava/lang/Object;
      25: aload_1
      26: getfield      #8                  // Field children:Ljava/util/List;
      29: aload_0
      30: invokeinterface #11,  2           // InterfaceMethod java/util/List.add:(Ljava/lang/Object;)Z
      35: pop
      36: return

  boolean isRoot();
    Code:
       0: aconst_null
       1: aload_0
       2: getfield      #9                  // Field parent:Lorg/apache/dubbo/qos/textui/TTree$Node;
       5: if_acmpne     12
       8: iconst_1
       9: goto          13
      12: iconst_0
      13: ireturn

  boolean isLeaf();
    Code:
       0: aload_0
       1: getfield      #8                  // Field children:Ljava/util/List;
       4: invokeinterface #12,  1           // InterfaceMethod java/util/List.isEmpty:()Z
       9: ireturn

  org.apache.dubbo.qos.textui.TTree$Node markBegin();
    Code:
       0: aload_0
       1: invokestatic  #13                 // Method java/lang/System.currentTimeMillis:()J
       4: putfield      #2                  // Field beginTimestamp:J
       7: aload_0
       8: areturn

  org.apache.dubbo.qos.textui.TTree$Node markEnd();
    Code:
       0: aload_0
       1: invokestatic  #13                 // Method java/lang/System.currentTimeMillis:()J
       4: putfield      #3                  // Field endTimestamp:J
       7: aload_0
       8: areturn

  org.apache.dubbo.qos.textui.TTree$Node(java.lang.Object, org.apache.dubbo.qos.textui.TTree$1);
    Code:
       0: aload_0
       1: aload_1
       2: invokespecial #4                  // Method "<init>":(Ljava/lang/Object;)V
       5: return

  static long access$200(org.apache.dubbo.qos.textui.TTree$Node);
    Code:
       0: aload_0
       1: getfield      #3                  // Field endTimestamp:J
       4: lreturn

  static long access$400(org.apache.dubbo.qos.textui.TTree$Node);
    Code:
       0: aload_0
       1: getfield      #2                  // Field beginTimestamp:J
       4: lreturn

  org.apache.dubbo.qos.textui.TTree$Node(org.apache.dubbo.qos.textui.TTree$Node, java.lang.Object, org.apache.dubbo.qos.textui.TTree$1);
    Code:
       0: aload_0
       1: aload_1
       2: aload_2
       3: invokespecial #1                  // Method "<init>":(Lorg/apache/dubbo/qos/textui/TTree$Node;Ljava/lang/Object;)V
       6: return
}
