Compiled from "NettyPortUnificationServer.java"
class org.apache.dubbo.remoting.transport.netty.NettyPortUnificationServer$1 implements org.jboss.netty.channel.ChannelPipelineFactory {
  final org.apache.dubbo.remoting.transport.netty.NettyHandler val$nettyHandler;

  final org.apache.dubbo.remoting.transport.netty.NettyPortUnificationServer this$0;

  org.apache.dubbo.remoting.transport.netty.NettyPortUnificationServer$1(org.apache.dubbo.remoting.transport.netty.NettyPortUnificationServer, org.apache.dubbo.remoting.transport.netty.NettyHandler);
    Code:
       0: aload_0
       1: aload_1
       2: putfield      #1                  // Field this$0:Lorg/apache/dubbo/remoting/transport/netty/NettyPortUnificationServer;
       5: aload_0
       6: aload_2
       7: putfield      #2                  // Field val$nettyHandler:Lorg/apache/dubbo/remoting/transport/netty/NettyHandler;
      10: aload_0
      11: invokespecial #3                  // Method java/lang/Object."<init>":()V
      14: return

  public org.jboss.netty.channel.ChannelPipeline getPipeline();
    Code:
       0: new           #4                  // class org/apache/dubbo/remoting/transport/netty/NettyCodecAdapter
       3: dup
       4: aload_0
       5: getfield      #1                  // Field this$0:Lorg/apache/dubbo/remoting/transport/netty/NettyPortUnificationServer;
       8: invokestatic  #5                  // Method org/apache/dubbo/remoting/transport/netty/NettyPortUnificationServer.access$000:(Lorg/apache/dubbo/remoting/transport/netty/NettyPortUnificationServer;)Lorg/apache/dubbo/remoting/Codec2;
      11: aload_0
      12: getfield      #1                  // Field this$0:Lorg/apache/dubbo/remoting/transport/netty/NettyPortUnificationServer;
      15: invokevirtual #6                  // Method org/apache/dubbo/remoting/transport/netty/NettyPortUnificationServer.getUrl:()Lorg/apache/dubbo/common/URL;
      18: aload_0
      19: getfield      #1                  // Field this$0:Lorg/apache/dubbo/remoting/transport/netty/NettyPortUnificationServer;
      22: invokespecial #7                  // Method org/apache/dubbo/remoting/transport/netty/NettyCodecAdapter."<init>":(Lorg/apache/dubbo/remoting/Codec2;Lorg/apache/dubbo/common/URL;Lorg/apache/dubbo/remoting/ChannelHandler;)V
      25: astore_1
      26: invokestatic  #8                  // Method org/jboss/netty/channel/Channels.pipeline:()Lorg/jboss/netty/channel/ChannelPipeline;
      29: astore_2
      30: aload_2
      31: ldc           #9                  // String decoder
      33: aload_1
      34: invokevirtual #10                 // Method org/apache/dubbo/remoting/transport/netty/NettyCodecAdapter.getDecoder:()Lorg/jboss/netty/channel/ChannelHandler;
      37: invokeinterface #11,  3           // InterfaceMethod org/jboss/netty/channel/ChannelPipeline.addLast:(Ljava/lang/String;Lorg/jboss/netty/channel/ChannelHandler;)V
      42: aload_2
      43: ldc           #12                 // String encoder
      45: aload_1
      46: invokevirtual #13                 // Method org/apache/dubbo/remoting/transport/netty/NettyCodecAdapter.getEncoder:()Lorg/jboss/netty/channel/ChannelHandler;
      49: invokeinterface #11,  3           // InterfaceMethod org/jboss/netty/channel/ChannelPipeline.addLast:(Ljava/lang/String;Lorg/jboss/netty/channel/ChannelHandler;)V
      54: aload_2
      55: ldc           #14                 // String handler
      57: aload_0
      58: getfield      #2                  // Field val$nettyHandler:Lorg/apache/dubbo/remoting/transport/netty/NettyHandler;
      61: invokeinterface #11,  3           // InterfaceMethod org/jboss/netty/channel/ChannelPipeline.addLast:(Ljava/lang/String;Lorg/jboss/netty/channel/ChannelHandler;)V
      66: aload_2
      67: areturn
}
