Compiled from "NettyHelper.java"
class org.apache.dubbo.remoting.transport.netty.NettyHelper$DubboLogger extends org.jboss.netty.logging.AbstractInternalLogger {
  public static final java.lang.String LOGGER_CAUSE_STRING;

  private org.apache.dubbo.common.logger.ErrorTypeAwareLogger logger;

  org.apache.dubbo.remoting.transport.netty.NettyHelper$DubboLogger(org.apache.dubbo.common.logger.ErrorTypeAwareLogger);
    Code:
       0: aload_0
       1: invokespecial #2                  // Method org/jboss/netty/logging/AbstractInternalLogger."<init>":()V
       4: aload_0
       5: aload_1
       6: putfield      #3                  // Field logger:Lorg/apache/dubbo/common/logger/ErrorTypeAwareLogger;
       9: return

  public boolean isDebugEnabled();
    Code:
       0: aload_0
       1: getfield      #3                  // Field logger:Lorg/apache/dubbo/common/logger/ErrorTypeAwareLogger;
       4: invokeinterface #4,  1            // InterfaceMethod org/apache/dubbo/common/logger/ErrorTypeAwareLogger.isDebugEnabled:()Z
       9: ireturn

  public boolean isInfoEnabled();
    Code:
       0: aload_0
       1: getfield      #3                  // Field logger:Lorg/apache/dubbo/common/logger/ErrorTypeAwareLogger;
       4: invokeinterface #5,  1            // InterfaceMethod org/apache/dubbo/common/logger/ErrorTypeAwareLogger.isInfoEnabled:()Z
       9: ireturn

  public boolean isWarnEnabled();
    Code:
       0: aload_0
       1: getfield      #3                  // Field logger:Lorg/apache/dubbo/common/logger/ErrorTypeAwareLogger;
       4: invokeinterface #6,  1            // InterfaceMethod org/apache/dubbo/common/logger/ErrorTypeAwareLogger.isWarnEnabled:()Z
       9: ireturn

  public boolean isErrorEnabled();
    Code:
       0: aload_0
       1: getfield      #3                  // Field logger:Lorg/apache/dubbo/common/logger/ErrorTypeAwareLogger;
       4: invokeinterface #7,  1            // InterfaceMethod org/apache/dubbo/common/logger/ErrorTypeAwareLogger.isErrorEnabled:()Z
       9: ireturn

  public void debug(java.lang.String);
    Code:
       0: aload_0
       1: getfield      #3                  // Field logger:Lorg/apache/dubbo/common/logger/ErrorTypeAwareLogger;
       4: aload_1
       5: invokeinterface #8,  2            // InterfaceMethod org/apache/dubbo/common/logger/ErrorTypeAwareLogger.debug:(Ljava/lang/String;)V
      10: return

  public void debug(java.lang.String, java.lang.Throwable);
    Code:
       0: aload_0
       1: getfield      #3                  // Field logger:Lorg/apache/dubbo/common/logger/ErrorTypeAwareLogger;
       4: aload_1
       5: aload_2
       6: invokeinterface #9,  3            // InterfaceMethod org/apache/dubbo/common/logger/ErrorTypeAwareLogger.debug:(Ljava/lang/String;Ljava/lang/Throwable;)V
      11: return

  public void info(java.lang.String);
    Code:
       0: aload_0
       1: getfield      #3                  // Field logger:Lorg/apache/dubbo/common/logger/ErrorTypeAwareLogger;
       4: aload_1
       5: invokeinterface #10,  2           // InterfaceMethod org/apache/dubbo/common/logger/ErrorTypeAwareLogger.info:(Ljava/lang/String;)V
      10: return

  public void info(java.lang.String, java.lang.Throwable);
    Code:
       0: aload_0
       1: getfield      #3                  // Field logger:Lorg/apache/dubbo/common/logger/ErrorTypeAwareLogger;
       4: aload_1
       5: aload_2
       6: invokeinterface #11,  3           // InterfaceMethod org/apache/dubbo/common/logger/ErrorTypeAwareLogger.info:(Ljava/lang/String;Ljava/lang/Throwable;)V
      11: return

  public void warn(java.lang.String);
    Code:
       0: aload_0
       1: getfield      #3                  // Field logger:Lorg/apache/dubbo/common/logger/ErrorTypeAwareLogger;
       4: ldc           #12                 // String 99-0
       6: ldc           #14                 // String unknown error in remoting-netty module
       8: ldc           #15                 // String
      10: aload_1
      11: invokeinterface #16,  5           // InterfaceMethod org/apache/dubbo/common/logger/ErrorTypeAwareLogger.warn:(Ljava/lang/String;Ljava/lang/String;Ljava/lang/String;Ljava/lang/String;)V
      16: return

  public void warn(java.lang.String, java.lang.Throwable);
    Code:
       0: aload_0
       1: getfield      #3                  // Field logger:Lorg/apache/dubbo/common/logger/ErrorTypeAwareLogger;
       4: ldc           #12                 // String 99-0
       6: ldc           #14                 // String unknown error in remoting-netty module
       8: ldc           #15                 // String
      10: aload_1
      11: aload_2
      12: invokeinterface #17,  6           // InterfaceMethod org/apache/dubbo/common/logger/ErrorTypeAwareLogger.warn:(Ljava/lang/String;Ljava/lang/String;Ljava/lang/String;Ljava/lang/String;Ljava/lang/Throwable;)V
      17: return

  public void error(java.lang.String);
    Code:
       0: aload_0
       1: getfield      #3                  // Field logger:Lorg/apache/dubbo/common/logger/ErrorTypeAwareLogger;
       4: ldc           #12                 // String 99-0
       6: ldc           #14                 // String unknown error in remoting-netty module
       8: ldc           #15                 // String
      10: aload_1
      11: invokeinterface #18,  5           // InterfaceMethod org/apache/dubbo/common/logger/ErrorTypeAwareLogger.error:(Ljava/lang/String;Ljava/lang/String;Ljava/lang/String;Ljava/lang/String;)V
      16: return

  public void error(java.lang.String, java.lang.Throwable);
    Code:
       0: aload_0
       1: getfield      #3                  // Field logger:Lorg/apache/dubbo/common/logger/ErrorTypeAwareLogger;
       4: ldc           #12                 // String 99-0
       6: ldc           #14                 // String unknown error in remoting-netty module
       8: ldc           #15                 // String
      10: aload_1
      11: aload_2
      12: invokeinterface #19,  6           // InterfaceMethod org/apache/dubbo/common/logger/ErrorTypeAwareLogger.error:(Ljava/lang/String;Ljava/lang/String;Ljava/lang/String;Ljava/lang/String;Ljava/lang/Throwable;)V
      17: return

  public java.lang.String toString();
    Code:
       0: aload_0
       1: getfield      #3                  // Field logger:Lorg/apache/dubbo/common/logger/ErrorTypeAwareLogger;
       4: invokevirtual #20                 // Method java/lang/Object.toString:()Ljava/lang/String;
       7: areturn
}
