Compiled from "NettyHelper.java"
class org.apache.dubbo.remoting.transport.netty.NettyHelper$DubboLoggerFactory extends org.jboss.netty.logging.InternalLoggerFactory {
  org.apache.dubbo.remoting.transport.netty.NettyHelper$DubboLoggerFactory();
    Code:
       0: aload_0
       1: invokespecial #1                  // Method org/jboss/netty/logging/InternalLoggerFactory."<init>":()V
       4: return

  public org.jboss.netty.logging.InternalLogger newInstance(java.lang.String);
    Code:
       0: new           #2                  // class org/apache/dubbo/remoting/transport/netty/NettyHelper$DubboLogger
       3: dup
       4: aload_1
       5: invokestatic  #3                  // Method org/apache/dubbo/common/logger/LoggerFactory.getErrorTypeAwareLogger:(Ljava/lang/String;)Lorg/apache/dubbo/common/logger/ErrorTypeAwareLogger;
       8: invokespecial #4                  // Method org/apache/dubbo/remoting/transport/netty/NettyHelper$DubboLogger."<init>":(Lorg/apache/dubbo/common/logger/ErrorTypeAwareLogger;)V
      11: areturn
}
