Compiled from "NettyPortUnificationServer.java"
public class org.apache.dubbo.remoting.transport.netty.NettyPortUnificationServer extends org.apache.dubbo.remoting.api.pu.AbstractPortUnificationServer {
  private static final org.apache.dubbo.common.logger.ErrorTypeAwareLogger logger;

  private java.util.Map<java.lang.String, org.apache.dubbo.remoting.Channel> dubboChannels;

  private org.jboss.netty.bootstrap.ServerBootstrap bootstrap;

  private org.jboss.netty.channel.Channel channel;

  public org.apache.dubbo.remoting.transport.netty.NettyPortUnificationServer(org.apache.dubbo.common.URL, org.apache.dubbo.remoting.ChannelHandler) throws org.apache.dubbo.remoting.RemotingException;
    Code:
       0: aload_0
       1: aload_1
       2: aload_2
       3: aload_1
       4: invokestatic  #5                  // Method org/apache/dubbo/remoting/transport/dispatcher/ChannelHandlers.wrap:(Lorg/apache/dubbo/remoting/ChannelHandler;Lorg/apache/dubbo/common/URL;)Lorg/apache/dubbo/remoting/ChannelHandler;
       7: invokespecial #6                  // Method org/apache/dubbo/remoting/api/pu/AbstractPortUnificationServer."<init>":(Lorg/apache/dubbo/common/URL;Lorg/apache/dubbo/remoting/ChannelHandler;)V
      10: aload_0
      11: new           #7                  // class java/util/concurrent/ConcurrentHashMap
      14: dup
      15: invokespecial #8                  // Method java/util/concurrent/ConcurrentHashMap."<init>":()V
      18: putfield      #9                  // Field dubboChannels:Ljava/util/Map;
      21: return

  public void addSupportedProtocol(org.apache.dubbo.common.URL, org.apache.dubbo.remoting.ChannelHandler);
    Code:
       0: aload_0
       1: aload_1
       2: aload_2
       3: aload_1
       4: invokestatic  #5                  // Method org/apache/dubbo/remoting/transport/dispatcher/ChannelHandlers.wrap:(Lorg/apache/dubbo/remoting/ChannelHandler;Lorg/apache/dubbo/common/URL;)Lorg/apache/dubbo/remoting/ChannelHandler;
       7: invokespecial #10                 // Method org/apache/dubbo/remoting/api/pu/AbstractPortUnificationServer.addSupportedProtocol:(Lorg/apache/dubbo/common/URL;Lorg/apache/dubbo/remoting/ChannelHandler;)V
      10: return

  public void close();
    Code:
       0: aload_0
       1: getfield      #11                 // Field channel:Lorg/jboss/netty/channel/Channel;
       4: ifnull        11
       7: aload_0
       8: invokevirtual #12                 // Method doClose:()V
      11: return

  public void bind();
    Code:
       0: aload_0
       1: getfield      #11                 // Field channel:Lorg/jboss/netty/channel/Channel;
       4: ifnonnull     11
       7: aload_0
       8: invokevirtual #13                 // Method doOpen:()V
      11: return

  protected void doOpen();
    Code:
       0: invokestatic  #14                 // Method org/apache/dubbo/remoting/transport/netty/NettyHelper.setNettyLoggerFactory:()V
       3: new           #15                 // class org/apache/dubbo/common/utils/NamedThreadFactory
       6: dup
       7: ldc           #16                 // String NettyServerBoss
       9: iconst_1
      10: invokespecial #17                 // Method org/apache/dubbo/common/utils/NamedThreadFactory."<init>":(Ljava/lang/String;Z)V
      13: invokestatic  #18                 // Method java/util/concurrent/Executors.newCachedThreadPool:(Ljava/util/concurrent/ThreadFactory;)Ljava/util/concurrent/ExecutorService;
      16: astore_1
      17: new           #15                 // class org/apache/dubbo/common/utils/NamedThreadFactory
      20: dup
      21: ldc           #19                 // String NettyServerWorker
      23: iconst_1
      24: invokespecial #17                 // Method org/apache/dubbo/common/utils/NamedThreadFactory."<init>":(Ljava/lang/String;Z)V
      27: invokestatic  #18                 // Method java/util/concurrent/Executors.newCachedThreadPool:(Ljava/util/concurrent/ThreadFactory;)Ljava/util/concurrent/ExecutorService;
      30: astore_2
      31: new           #20                 // class org/jboss/netty/channel/socket/nio/NioServerSocketChannelFactory
      34: dup
      35: aload_1
      36: aload_2
      37: aload_0
      38: invokevirtual #21                 // Method getUrl:()Lorg/apache/dubbo/common/URL;
      41: ldc           #22                 // String iothreads
      43: getstatic     #23                 // Field org/apache/dubbo/remoting/Constants.DEFAULT_IO_THREADS:I
      46: invokevirtual #24                 // Method org/apache/dubbo/common/URL.getPositiveParameter:(Ljava/lang/String;I)I
      49: invokespecial #25                 // Method org/jboss/netty/channel/socket/nio/NioServerSocketChannelFactory."<init>":(Ljava/util/concurrent/Executor;Ljava/util/concurrent/Executor;I)V
      52: astore_3
      53: aload_0
      54: new           #26                 // class org/jboss/netty/bootstrap/ServerBootstrap
      57: dup
      58: aload_3
      59: invokespecial #27                 // Method org/jboss/netty/bootstrap/ServerBootstrap."<init>":(Lorg/jboss/netty/channel/ChannelFactory;)V
      62: putfield      #28                 // Field bootstrap:Lorg/jboss/netty/bootstrap/ServerBootstrap;
      65: new           #29                 // class org/apache/dubbo/remoting/transport/netty/NettyHandler
      68: dup
      69: aload_0
      70: invokevirtual #21                 // Method getUrl:()Lorg/apache/dubbo/common/URL;
      73: aload_0
      74: invokespecial #30                 // Method org/apache/dubbo/remoting/transport/netty/NettyHandler."<init>":(Lorg/apache/dubbo/common/URL;Lorg/apache/dubbo/remoting/ChannelHandler;)V
      77: astore        4
      79: aload_0
      80: aload         4
      82: invokevirtual #31                 // Method org/apache/dubbo/remoting/transport/netty/NettyHandler.getChannels:()Ljava/util/Map;
      85: putfield      #9                  // Field dubboChannels:Ljava/util/Map;
      88: aload_0
      89: getfield      #28                 // Field bootstrap:Lorg/jboss/netty/bootstrap/ServerBootstrap;
      92: ldc           #32                 // String child.tcpNoDelay
      94: iconst_1
      95: invokestatic  #33                 // Method java/lang/Boolean.valueOf:(Z)Ljava/lang/Boolean;
      98: invokevirtual #34                 // Method org/jboss/netty/bootstrap/ServerBootstrap.setOption:(Ljava/lang/String;Ljava/lang/Object;)V
     101: aload_0
     102: getfield      #28                 // Field bootstrap:Lorg/jboss/netty/bootstrap/ServerBootstrap;
     105: ldc           #35                 // String backlog
     107: aload_0
     108: invokevirtual #21                 // Method getUrl:()Lorg/apache/dubbo/common/URL;
     111: ldc           #35                 // String backlog
     113: sipush        1024
     116: invokevirtual #24                 // Method org/apache/dubbo/common/URL.getPositiveParameter:(Ljava/lang/String;I)I
     119: invokestatic  #36                 // Method java/lang/Integer.valueOf:(I)Ljava/lang/Integer;
     122: invokevirtual #34                 // Method org/jboss/netty/bootstrap/ServerBootstrap.setOption:(Ljava/lang/String;Ljava/lang/Object;)V
     125: aload_0
     126: getfield      #28                 // Field bootstrap:Lorg/jboss/netty/bootstrap/ServerBootstrap;
     129: new           #37                 // class org/apache/dubbo/remoting/transport/netty/NettyPortUnificationServer$1
     132: dup
     133: aload_0
     134: aload         4
     136: invokespecial #38                 // Method org/apache/dubbo/remoting/transport/netty/NettyPortUnificationServer$1."<init>":(Lorg/apache/dubbo/remoting/transport/netty/NettyPortUnificationServer;Lorg/apache/dubbo/remoting/transport/netty/NettyHandler;)V
     139: invokevirtual #39                 // Method org/jboss/netty/bootstrap/ServerBootstrap.setPipelineFactory:(Lorg/jboss/netty/channel/ChannelPipelineFactory;)V
     142: aload_0
     143: invokevirtual #21                 // Method getUrl:()Lorg/apache/dubbo/common/URL;
     146: ldc           #40                 // String bind.ip
     148: aload_0
     149: invokevirtual #21                 // Method getUrl:()Lorg/apache/dubbo/common/URL;
     152: invokevirtual #41                 // Method org/apache/dubbo/common/URL.getHost:()Ljava/lang/String;
     155: invokevirtual #42                 // Method org/apache/dubbo/common/URL.getParameter:(Ljava/lang/String;Ljava/lang/String;)Ljava/lang/String;
     158: astore        5
     160: aload_0
     161: invokevirtual #21                 // Method getUrl:()Lorg/apache/dubbo/common/URL;
     164: ldc           #43                 // String bind.port
     166: aload_0
     167: invokevirtual #21                 // Method getUrl:()Lorg/apache/dubbo/common/URL;
     170: invokevirtual #44                 // Method org/apache/dubbo/common/URL.getPort:()I
     173: invokevirtual #45                 // Method org/apache/dubbo/common/URL.getParameter:(Ljava/lang/String;I)I
     176: istore        6
     178: aload_0
     179: invokevirtual #21                 // Method getUrl:()Lorg/apache/dubbo/common/URL;
     182: ldc           #46                 // String anyhost
     184: iconst_0
     185: invokevirtual #47                 // Method org/apache/dubbo/common/URL.getParameter:(Ljava/lang/String;Z)Z
     188: ifne          199
     191: aload         5
     193: invokestatic  #48                 // Method org/apache/dubbo/common/utils/NetUtils.isInvalidLocalHost:(Ljava/lang/String;)Z
     196: ifeq          203
     199: ldc           #49                 // String 0.0.0.0
     201: astore        5
     203: new           #50                 // class java/net/InetSocketAddress
     206: dup
     207: aload         5
     209: iload         6
     211: invokespecial #51                 // Method java/net/InetSocketAddress."<init>":(Ljava/lang/String;I)V
     214: astore        7
     216: aload_0
     217: aload_0
     218: getfield      #28                 // Field bootstrap:Lorg/jboss/netty/bootstrap/ServerBootstrap;
     221: aload         7
     223: invokevirtual #52                 // Method org/jboss/netty/bootstrap/ServerBootstrap.bind:(Ljava/net/SocketAddress;)Lorg/jboss/netty/channel/Channel;
     226: putfield      #11                 // Field channel:Lorg/jboss/netty/channel/Channel;
     229: return

  protected void doClose();
    Code:
       0: aload_0
       1: getfield      #11                 // Field channel:Lorg/jboss/netty/channel/Channel;
       4: ifnull        17
       7: aload_0
       8: getfield      #11                 // Field channel:Lorg/jboss/netty/channel/Channel;
      11: invokeinterface #53,  1           // InterfaceMethod org/jboss/netty/channel/Channel.close:()Lorg/jboss/netty/channel/ChannelFuture;
      16: pop
      17: goto          40
      20: astore_1
      21: getstatic     #55                 // Field logger:Lorg/apache/dubbo/common/logger/ErrorTypeAwareLogger;
      24: ldc           #56                 // String 6-3
      26: ldc           #57                 // String
      28: ldc           #57                 // String
      30: aload_1
      31: invokevirtual #58                 // Method java/lang/Throwable.getMessage:()Ljava/lang/String;
      34: aload_1
      35: invokeinterface #59,  6           // InterfaceMethod org/apache/dubbo/common/logger/ErrorTypeAwareLogger.warn:(Ljava/lang/String;Ljava/lang/String;Ljava/lang/String;Ljava/lang/String;Ljava/lang/Throwable;)V
      40: aload_0
      41: invokevirtual #60                 // Method getChannels:()Ljava/util/Collection;
      44: astore_1
      45: aload_1
      46: invokestatic  #61                 // Method org/apache/dubbo/common/utils/CollectionUtils.isNotEmpty:(Ljava/util/Collection;)Z
      49: ifeq          113
      52: aload_1
      53: invokeinterface #62,  1           // InterfaceMethod java/util/Collection.iterator:()Ljava/util/Iterator;
      58: astore_2
      59: aload_2
      60: invokeinterface #63,  1           // InterfaceMethod java/util/Iterator.hasNext:()Z
      65: ifeq          113
      68: aload_2
      69: invokeinterface #64,  1           // InterfaceMethod java/util/Iterator.next:()Ljava/lang/Object;
      74: checkcast     #65                 // class org/apache/dubbo/remoting/Channel
      77: astore_3
      78: aload_3
      79: invokeinterface #66,  1           // InterfaceMethod org/apache/dubbo/remoting/Channel.close:()V
      84: goto          110
      87: astore        4
      89: getstatic     #55                 // Field logger:Lorg/apache/dubbo/common/logger/ErrorTypeAwareLogger;
      92: ldc           #56                 // String 6-3
      94: ldc           #57                 // String
      96: ldc           #57                 // String
      98: aload         4
     100: invokevirtual #58                 // Method java/lang/Throwable.getMessage:()Ljava/lang/String;
     103: aload         4
     105: invokeinterface #59,  6           // InterfaceMethod org/apache/dubbo/common/logger/ErrorTypeAwareLogger.warn:(Ljava/lang/String;Ljava/lang/String;Ljava/lang/String;Ljava/lang/String;Ljava/lang/Throwable;)V
     110: goto          59
     113: goto          136
     116: astore_1
     117: getstatic     #55                 // Field logger:Lorg/apache/dubbo/common/logger/ErrorTypeAwareLogger;
     120: ldc           #56                 // String 6-3
     122: ldc           #57                 // String
     124: ldc           #57                 // String
     126: aload_1
     127: invokevirtual #58                 // Method java/lang/Throwable.getMessage:()Ljava/lang/String;
     130: aload_1
     131: invokeinterface #59,  6           // InterfaceMethod org/apache/dubbo/common/logger/ErrorTypeAwareLogger.warn:(Ljava/lang/String;Ljava/lang/String;Ljava/lang/String;Ljava/lang/String;Ljava/lang/Throwable;)V
     136: aload_0
     137: invokevirtual #67                 // Method getProtocols:()Ljava/util/List;
     140: invokeinterface #68,  1           // InterfaceMethod java/util/List.iterator:()Ljava/util/Iterator;
     145: astore_1
     146: aload_1
     147: invokeinterface #63,  1           // InterfaceMethod java/util/Iterator.hasNext:()Z
     152: ifeq          174
     155: aload_1
     156: invokeinterface #64,  1           // InterfaceMethod java/util/Iterator.next:()Ljava/lang/Object;
     161: checkcast     #69                 // class org/apache/dubbo/remoting/api/WireProtocol
     164: astore_2
     165: aload_2
     166: invokeinterface #70,  1           // InterfaceMethod org/apache/dubbo/remoting/api/WireProtocol.close:()V
     171: goto          146
     174: aload_0
     175: getfield      #28                 // Field bootstrap:Lorg/jboss/netty/bootstrap/ServerBootstrap;
     178: ifnull        188
     181: aload_0
     182: getfield      #28                 // Field bootstrap:Lorg/jboss/netty/bootstrap/ServerBootstrap;
     185: invokevirtual #71                 // Method org/jboss/netty/bootstrap/ServerBootstrap.releaseExternalResources:()V
     188: goto          211
     191: astore_1
     192: getstatic     #55                 // Field logger:Lorg/apache/dubbo/common/logger/ErrorTypeAwareLogger;
     195: ldc           #56                 // String 6-3
     197: ldc           #57                 // String
     199: ldc           #57                 // String
     201: aload_1
     202: invokevirtual #58                 // Method java/lang/Throwable.getMessage:()Ljava/lang/String;
     205: aload_1
     206: invokeinterface #59,  6           // InterfaceMethod org/apache/dubbo/common/logger/ErrorTypeAwareLogger.warn:(Ljava/lang/String;Ljava/lang/String;Ljava/lang/String;Ljava/lang/String;Ljava/lang/Throwable;)V
     211: aload_0
     212: getfield      #9                  // Field dubboChannels:Ljava/util/Map;
     215: ifnull        227
     218: aload_0
     219: getfield      #9                  // Field dubboChannels:Ljava/util/Map;
     222: invokeinterface #72,  1           // InterfaceMethod java/util/Map.clear:()V
     227: goto          250
     230: astore_1
     231: getstatic     #55                 // Field logger:Lorg/apache/dubbo/common/logger/ErrorTypeAwareLogger;
     234: ldc           #56                 // String 6-3
     236: ldc           #57                 // String
     238: ldc           #57                 // String
     240: aload_1
     241: invokevirtual #58                 // Method java/lang/Throwable.getMessage:()Ljava/lang/String;
     244: aload_1
     245: invokeinterface #59,  6           // InterfaceMethod org/apache/dubbo/common/logger/ErrorTypeAwareLogger.warn:(Ljava/lang/String;Ljava/lang/String;Ljava/lang/String;Ljava/lang/String;Ljava/lang/Throwable;)V
     250: return
    Exception table:
       from    to  target type
           0    17    20   Class java/lang/Throwable
          78    84    87   Class java/lang/Throwable
          40   113   116   Class java/lang/Throwable
         174   188   191   Class java/lang/Throwable
         211   227   230   Class java/lang/Throwable

  protected int getChannelsSize();
    Code:
       0: aload_0
       1: getfield      #9                  // Field dubboChannels:Ljava/util/Map;
       4: invokeinterface #73,  1           // InterfaceMethod java/util/Map.size:()I
       9: ireturn

  public java.util.Collection<org.apache.dubbo.remoting.Channel> getChannels();
    Code:
       0: new           #74                 // class java/util/ArrayList
       3: dup
       4: aload_0
       5: getfield      #9                  // Field dubboChannels:Ljava/util/Map;
       8: invokeinterface #73,  1           // InterfaceMethod java/util/Map.size:()I
      13: invokespecial #75                 // Method java/util/ArrayList."<init>":(I)V
      16: astore_1
      17: aload_1
      18: aload_0
      19: getfield      #9                  // Field dubboChannels:Ljava/util/Map;
      22: invokeinterface #76,  1           // InterfaceMethod java/util/Map.values:()Ljava/util/Collection;
      27: invokeinterface #77,  2           // InterfaceMethod java/util/Collection.addAll:(Ljava/util/Collection;)Z
      32: pop
      33: aload_1
      34: areturn

  public org.apache.dubbo.remoting.Channel getChannel(java.net.InetSocketAddress);
    Code:
       0: aload_0
       1: getfield      #9                  // Field dubboChannels:Ljava/util/Map;
       4: aload_1
       5: invokestatic  #78                 // Method org/apache/dubbo/common/utils/NetUtils.toAddressString:(Ljava/net/InetSocketAddress;)Ljava/lang/String;
       8: invokeinterface #79,  2           // InterfaceMethod java/util/Map.get:(Ljava/lang/Object;)Ljava/lang/Object;
      13: checkcast     #65                 // class org/apache/dubbo/remoting/Channel
      16: areturn

  public java.net.InetSocketAddress getLocalAddress();
    Code:
       0: aload_0
       1: getfield      #11                 // Field channel:Lorg/jboss/netty/channel/Channel;
       4: invokeinterface #80,  1           // InterfaceMethod org/jboss/netty/channel/Channel.getLocalAddress:()Ljava/net/SocketAddress;
       9: checkcast     #50                 // class java/net/InetSocketAddress
      12: areturn

  public boolean isBound();
    Code:
       0: aload_0
       1: getfield      #11                 // Field channel:Lorg/jboss/netty/channel/Channel;
       4: invokeinterface #81,  1           // InterfaceMethod org/jboss/netty/channel/Channel.isBound:()Z
       9: ireturn

  static org.apache.dubbo.remoting.Codec2 access$000(org.apache.dubbo.remoting.transport.netty.NettyPortUnificationServer);
    Code:
       0: aload_0
       1: invokevirtual #4                  // Method getCodec:()Lorg/apache/dubbo/remoting/Codec2;
       4: areturn

  static {};
    Code:
       0: ldc           #82                 // class org/apache/dubbo/remoting/transport/netty/NettyPortUnificationServer
       2: invokestatic  #83                 // Method org/apache/dubbo/common/logger/LoggerFactory.getErrorTypeAwareLogger:(Ljava/lang/Class;)Lorg/apache/dubbo/common/logger/ErrorTypeAwareLogger;
       5: putstatic     #55                 // Field logger:Lorg/apache/dubbo/common/logger/ErrorTypeAwareLogger;
       8: return
}
