Compiled from "NettyBackedChannelBuffer.java"
public class org.apache.dubbo.remoting.transport.netty.NettyBackedChannelBuffer implements org.apache.dubbo.remoting.buffer.ChannelBuffer {
  private final org.jboss.netty.buffer.ChannelBuffer buffer;

  public org.apache.dubbo.remoting.transport.netty.NettyBackedChannelBuffer(org.jboss.netty.buffer.ChannelBuffer);
    Code:
       0: aload_0
       1: invokespecial #1                  // Method java/lang/Object."<init>":()V
       4: aload_1
       5: ldc           #2                  // String buffer == null
       7: invokestatic  #3                  // Method org/apache/dubbo/common/utils/Assert.notNull:(Ljava/lang/Object;Ljava/lang/String;)V
      10: aload_0
      11: aload_1
      12: putfield      #4                  // Field buffer:Lorg/jboss/netty/buffer/ChannelBuffer;
      15: return

  public org.jboss.netty.buffer.ChannelBuffer nettyChannelBuffer();
    Code:
       0: aload_0
       1: getfield      #4                  // Field buffer:Lorg/jboss/netty/buffer/ChannelBuffer;
       4: areturn

  public int capacity();
    Code:
       0: aload_0
       1: getfield      #4                  // Field buffer:Lorg/jboss/netty/buffer/ChannelBuffer;
       4: invokeinterface #5,  1            // InterfaceMethod org/jboss/netty/buffer/ChannelBuffer.capacity:()I
       9: ireturn

  public org.apache.dubbo.remoting.buffer.ChannelBuffer copy(int, int);
    Code:
       0: new           #6                  // class org/apache/dubbo/remoting/transport/netty/NettyBackedChannelBuffer
       3: dup
       4: aload_0
       5: getfield      #4                  // Field buffer:Lorg/jboss/netty/buffer/ChannelBuffer;
       8: iload_1
       9: iload_2
      10: invokeinterface #7,  3            // InterfaceMethod org/jboss/netty/buffer/ChannelBuffer.copy:(II)Lorg/jboss/netty/buffer/ChannelBuffer;
      15: invokespecial #8                  // Method "<init>":(Lorg/jboss/netty/buffer/ChannelBuffer;)V
      18: areturn

  public org.apache.dubbo.remoting.buffer.ChannelBufferFactory factory();
    Code:
       0: invokestatic  #9                  // Method org/apache/dubbo/remoting/transport/netty/NettyBackedChannelBufferFactory.getInstance:()Lorg/apache/dubbo/remoting/buffer/ChannelBufferFactory;
       3: areturn

  public byte getByte(int);
    Code:
       0: aload_0
       1: getfield      #4                  // Field buffer:Lorg/jboss/netty/buffer/ChannelBuffer;
       4: iload_1
       5: invokeinterface #10,  2           // InterfaceMethod org/jboss/netty/buffer/ChannelBuffer.getByte:(I)B
      10: ireturn

  public void getBytes(int, byte[], int, int);
    Code:
       0: aload_0
       1: getfield      #4                  // Field buffer:Lorg/jboss/netty/buffer/ChannelBuffer;
       4: iload_1
       5: aload_2
       6: iload_3
       7: iload         4
       9: invokeinterface #11,  5           // InterfaceMethod org/jboss/netty/buffer/ChannelBuffer.getBytes:(I[BII)V
      14: return

  public void getBytes(int, java.nio.ByteBuffer);
    Code:
       0: aload_0
       1: getfield      #4                  // Field buffer:Lorg/jboss/netty/buffer/ChannelBuffer;
       4: iload_1
       5: aload_2
       6: invokeinterface #12,  3           // InterfaceMethod org/jboss/netty/buffer/ChannelBuffer.getBytes:(ILjava/nio/ByteBuffer;)V
      11: return

  public void getBytes(int, org.apache.dubbo.remoting.buffer.ChannelBuffer, int, int);
    Code:
       0: iload         4
       2: newarray       byte
       4: astore        5
       6: aload_0
       7: getfield      #4                  // Field buffer:Lorg/jboss/netty/buffer/ChannelBuffer;
      10: iload_1
      11: aload         5
      13: iconst_0
      14: iload         4
      16: invokeinterface #11,  5           // InterfaceMethod org/jboss/netty/buffer/ChannelBuffer.getBytes:(I[BII)V
      21: aload_2
      22: iload_3
      23: aload         5
      25: iconst_0
      26: iload         4
      28: invokeinterface #13,  5           // InterfaceMethod org/apache/dubbo/remoting/buffer/ChannelBuffer.setBytes:(I[BII)V
      33: return

  public void getBytes(int, java.io.OutputStream, int) throws java.io.IOException;
    Code:
       0: aload_0
       1: getfield      #4                  // Field buffer:Lorg/jboss/netty/buffer/ChannelBuffer;
       4: iload_1
       5: aload_2
       6: iload_3
       7: invokeinterface #14,  4           // InterfaceMethod org/jboss/netty/buffer/ChannelBuffer.getBytes:(ILjava/io/OutputStream;I)V
      12: return

  public boolean isDirect();
    Code:
       0: aload_0
       1: getfield      #4                  // Field buffer:Lorg/jboss/netty/buffer/ChannelBuffer;
       4: invokeinterface #15,  1           // InterfaceMethod org/jboss/netty/buffer/ChannelBuffer.isDirect:()Z
       9: ireturn

  public void setByte(int, int);
    Code:
       0: aload_0
       1: getfield      #4                  // Field buffer:Lorg/jboss/netty/buffer/ChannelBuffer;
       4: iload_1
       5: iload_2
       6: invokeinterface #16,  3           // InterfaceMethod org/jboss/netty/buffer/ChannelBuffer.setByte:(II)V
      11: return

  public void setBytes(int, byte[], int, int);
    Code:
       0: aload_0
       1: getfield      #4                  // Field buffer:Lorg/jboss/netty/buffer/ChannelBuffer;
       4: iload_1
       5: aload_2
       6: iload_3
       7: iload         4
       9: invokeinterface #17,  5           // InterfaceMethod org/jboss/netty/buffer/ChannelBuffer.setBytes:(I[BII)V
      14: return

  public void setBytes(int, java.nio.ByteBuffer);
    Code:
       0: aload_0
       1: getfield      #4                  // Field buffer:Lorg/jboss/netty/buffer/ChannelBuffer;
       4: iload_1
       5: aload_2
       6: invokeinterface #18,  3           // InterfaceMethod org/jboss/netty/buffer/ChannelBuffer.setBytes:(ILjava/nio/ByteBuffer;)V
      11: return

  public void setBytes(int, org.apache.dubbo.remoting.buffer.ChannelBuffer, int, int);
    Code:
       0: iload         4
       2: aload_2
       3: invokeinterface #19,  1           // InterfaceMethod org/apache/dubbo/remoting/buffer/ChannelBuffer.readableBytes:()I
       8: if_icmple     19
      11: new           #20                 // class java/lang/IndexOutOfBoundsException
      14: dup
      15: invokespecial #21                 // Method java/lang/IndexOutOfBoundsException."<init>":()V
      18: athrow
      19: iload         4
      21: newarray       byte
      23: astore        5
      25: aload_2
      26: iload_3
      27: aload         5
      29: iconst_0
      30: iload         4
      32: invokeinterface #22,  5           // InterfaceMethod org/apache/dubbo/remoting/buffer/ChannelBuffer.getBytes:(I[BII)V
      37: aload_0
      38: iload_1
      39: aload         5
      41: iconst_0
      42: iload         4
      44: invokevirtual #23                 // Method setBytes:(I[BII)V
      47: return

  public int setBytes(int, java.io.InputStream, int) throws java.io.IOException;
    Code:
       0: aload_0
       1: getfield      #4                  // Field buffer:Lorg/jboss/netty/buffer/ChannelBuffer;
       4: iload_1
       5: aload_2
       6: iload_3
       7: invokeinterface #24,  4           // InterfaceMethod org/jboss/netty/buffer/ChannelBuffer.setBytes:(ILjava/io/InputStream;I)I
      12: ireturn

  public java.nio.ByteBuffer toByteBuffer(int, int);
    Code:
       0: aload_0
       1: getfield      #4                  // Field buffer:Lorg/jboss/netty/buffer/ChannelBuffer;
       4: iload_1
       5: iload_2
       6: invokeinterface #25,  3           // InterfaceMethod org/jboss/netty/buffer/ChannelBuffer.toByteBuffer:(II)Ljava/nio/ByteBuffer;
      11: areturn

  public byte[] array();
    Code:
       0: aload_0
       1: getfield      #4                  // Field buffer:Lorg/jboss/netty/buffer/ChannelBuffer;
       4: invokeinterface #26,  1           // InterfaceMethod org/jboss/netty/buffer/ChannelBuffer.array:()[B
       9: areturn

  public boolean hasArray();
    Code:
       0: aload_0
       1: getfield      #4                  // Field buffer:Lorg/jboss/netty/buffer/ChannelBuffer;
       4: invokeinterface #27,  1           // InterfaceMethod org/jboss/netty/buffer/ChannelBuffer.hasArray:()Z
       9: ireturn

  public int arrayOffset();
    Code:
       0: aload_0
       1: getfield      #4                  // Field buffer:Lorg/jboss/netty/buffer/ChannelBuffer;
       4: invokeinterface #28,  1           // InterfaceMethod org/jboss/netty/buffer/ChannelBuffer.arrayOffset:()I
       9: ireturn

  public void clear();
    Code:
       0: aload_0
       1: getfield      #4                  // Field buffer:Lorg/jboss/netty/buffer/ChannelBuffer;
       4: invokeinterface #29,  1           // InterfaceMethod org/jboss/netty/buffer/ChannelBuffer.clear:()V
       9: return

  public org.apache.dubbo.remoting.buffer.ChannelBuffer copy();
    Code:
       0: new           #6                  // class org/apache/dubbo/remoting/transport/netty/NettyBackedChannelBuffer
       3: dup
       4: aload_0
       5: getfield      #4                  // Field buffer:Lorg/jboss/netty/buffer/ChannelBuffer;
       8: invokeinterface #30,  1           // InterfaceMethod org/jboss/netty/buffer/ChannelBuffer.copy:()Lorg/jboss/netty/buffer/ChannelBuffer;
      13: invokespecial #8                  // Method "<init>":(Lorg/jboss/netty/buffer/ChannelBuffer;)V
      16: areturn

  public void discardReadBytes();
    Code:
       0: aload_0
       1: getfield      #4                  // Field buffer:Lorg/jboss/netty/buffer/ChannelBuffer;
       4: invokeinterface #31,  1           // InterfaceMethod org/jboss/netty/buffer/ChannelBuffer.discardReadBytes:()V
       9: return

  public void ensureWritableBytes(int);
    Code:
       0: aload_0
       1: getfield      #4                  // Field buffer:Lorg/jboss/netty/buffer/ChannelBuffer;
       4: iload_1
       5: invokeinterface #32,  2           // InterfaceMethod org/jboss/netty/buffer/ChannelBuffer.ensureWritableBytes:(I)V
      10: return

  public void getBytes(int, byte[]);
    Code:
       0: aload_0
       1: getfield      #4                  // Field buffer:Lorg/jboss/netty/buffer/ChannelBuffer;
       4: iload_1
       5: aload_2
       6: invokeinterface #33,  3           // InterfaceMethod org/jboss/netty/buffer/ChannelBuffer.getBytes:(I[B)V
      11: return

  public void getBytes(int, org.apache.dubbo.remoting.buffer.ChannelBuffer);
    Code:
       0: aload_0
       1: iload_1
       2: aload_2
       3: aload_2
       4: invokeinterface #34,  1           // InterfaceMethod org/apache/dubbo/remoting/buffer/ChannelBuffer.writableBytes:()I
       9: invokevirtual #35                 // Method getBytes:(ILorg/apache/dubbo/remoting/buffer/ChannelBuffer;I)V
      12: return

  public void getBytes(int, org.apache.dubbo.remoting.buffer.ChannelBuffer, int);
    Code:
       0: iload_3
       1: aload_2
       2: invokeinterface #34,  1           // InterfaceMethod org/apache/dubbo/remoting/buffer/ChannelBuffer.writableBytes:()I
       7: if_icmple     18
      10: new           #20                 // class java/lang/IndexOutOfBoundsException
      13: dup
      14: invokespecial #21                 // Method java/lang/IndexOutOfBoundsException."<init>":()V
      17: athrow
      18: aload_0
      19: iload_1
      20: aload_2
      21: aload_2
      22: invokeinterface #36,  1           // InterfaceMethod org/apache/dubbo/remoting/buffer/ChannelBuffer.writerIndex:()I
      27: iload_3
      28: invokevirtual #37                 // Method getBytes:(ILorg/apache/dubbo/remoting/buffer/ChannelBuffer;II)V
      31: aload_2
      32: aload_2
      33: invokeinterface #36,  1           // InterfaceMethod org/apache/dubbo/remoting/buffer/ChannelBuffer.writerIndex:()I
      38: iload_3
      39: iadd
      40: invokeinterface #38,  2           // InterfaceMethod org/apache/dubbo/remoting/buffer/ChannelBuffer.writerIndex:(I)V
      45: return

  public void markReaderIndex();
    Code:
       0: aload_0
       1: getfield      #4                  // Field buffer:Lorg/jboss/netty/buffer/ChannelBuffer;
       4: invokeinterface #39,  1           // InterfaceMethod org/jboss/netty/buffer/ChannelBuffer.markReaderIndex:()V
       9: return

  public void markWriterIndex();
    Code:
       0: aload_0
       1: getfield      #4                  // Field buffer:Lorg/jboss/netty/buffer/ChannelBuffer;
       4: invokeinterface #40,  1           // InterfaceMethod org/jboss/netty/buffer/ChannelBuffer.markWriterIndex:()V
       9: return

  public boolean readable();
    Code:
       0: aload_0
       1: getfield      #4                  // Field buffer:Lorg/jboss/netty/buffer/ChannelBuffer;
       4: invokeinterface #41,  1           // InterfaceMethod org/jboss/netty/buffer/ChannelBuffer.readable:()Z
       9: ireturn

  public int readableBytes();
    Code:
       0: aload_0
       1: getfield      #4                  // Field buffer:Lorg/jboss/netty/buffer/ChannelBuffer;
       4: invokeinterface #42,  1           // InterfaceMethod org/jboss/netty/buffer/ChannelBuffer.readableBytes:()I
       9: ireturn

  public byte readByte();
    Code:
       0: aload_0
       1: getfield      #4                  // Field buffer:Lorg/jboss/netty/buffer/ChannelBuffer;
       4: invokeinterface #43,  1           // InterfaceMethod org/jboss/netty/buffer/ChannelBuffer.readByte:()B
       9: ireturn

  public void readBytes(byte[]);
    Code:
       0: aload_0
       1: getfield      #4                  // Field buffer:Lorg/jboss/netty/buffer/ChannelBuffer;
       4: aload_1
       5: invokeinterface #44,  2           // InterfaceMethod org/jboss/netty/buffer/ChannelBuffer.readBytes:([B)V
      10: return

  public void readBytes(byte[], int, int);
    Code:
       0: aload_0
       1: getfield      #4                  // Field buffer:Lorg/jboss/netty/buffer/ChannelBuffer;
       4: aload_1
       5: iload_2
       6: iload_3
       7: invokeinterface #45,  4           // InterfaceMethod org/jboss/netty/buffer/ChannelBuffer.readBytes:([BII)V
      12: return

  public void readBytes(java.nio.ByteBuffer);
    Code:
       0: aload_0
       1: getfield      #4                  // Field buffer:Lorg/jboss/netty/buffer/ChannelBuffer;
       4: aload_1
       5: invokeinterface #46,  2           // InterfaceMethod org/jboss/netty/buffer/ChannelBuffer.readBytes:(Ljava/nio/ByteBuffer;)V
      10: return

  public void readBytes(org.apache.dubbo.remoting.buffer.ChannelBuffer);
    Code:
       0: aload_0
       1: aload_1
       2: aload_1
       3: invokeinterface #34,  1           // InterfaceMethod org/apache/dubbo/remoting/buffer/ChannelBuffer.writableBytes:()I
       8: invokevirtual #47                 // Method readBytes:(Lorg/apache/dubbo/remoting/buffer/ChannelBuffer;I)V
      11: return

  public void readBytes(org.apache.dubbo.remoting.buffer.ChannelBuffer, int);
    Code:
       0: iload_2
       1: aload_1
       2: invokeinterface #34,  1           // InterfaceMethod org/apache/dubbo/remoting/buffer/ChannelBuffer.writableBytes:()I
       7: if_icmple     18
      10: new           #20                 // class java/lang/IndexOutOfBoundsException
      13: dup
      14: invokespecial #21                 // Method java/lang/IndexOutOfBoundsException."<init>":()V
      17: athrow
      18: aload_0
      19: aload_1
      20: aload_1
      21: invokeinterface #36,  1           // InterfaceMethod org/apache/dubbo/remoting/buffer/ChannelBuffer.writerIndex:()I
      26: iload_2
      27: invokevirtual #48                 // Method readBytes:(Lorg/apache/dubbo/remoting/buffer/ChannelBuffer;II)V
      30: aload_1
      31: aload_1
      32: invokeinterface #36,  1           // InterfaceMethod org/apache/dubbo/remoting/buffer/ChannelBuffer.writerIndex:()I
      37: iload_2
      38: iadd
      39: invokeinterface #38,  2           // InterfaceMethod org/apache/dubbo/remoting/buffer/ChannelBuffer.writerIndex:(I)V
      44: return

  public void readBytes(org.apache.dubbo.remoting.buffer.ChannelBuffer, int, int);
    Code:
       0: aload_0
       1: invokevirtual #49                 // Method readableBytes:()I
       4: iload_3
       5: if_icmpge     16
       8: new           #20                 // class java/lang/IndexOutOfBoundsException
      11: dup
      12: invokespecial #21                 // Method java/lang/IndexOutOfBoundsException."<init>":()V
      15: athrow
      16: iload_3
      17: newarray       byte
      19: astore        4
      21: aload_0
      22: getfield      #4                  // Field buffer:Lorg/jboss/netty/buffer/ChannelBuffer;
      25: aload         4
      27: iconst_0
      28: iload_3
      29: invokeinterface #45,  4           // InterfaceMethod org/jboss/netty/buffer/ChannelBuffer.readBytes:([BII)V
      34: aload_1
      35: iload_2
      36: aload         4
      38: iconst_0
      39: iload_3
      40: invokeinterface #13,  5           // InterfaceMethod org/apache/dubbo/remoting/buffer/ChannelBuffer.setBytes:(I[BII)V
      45: return

  public org.apache.dubbo.remoting.buffer.ChannelBuffer readBytes(int);
    Code:
       0: new           #6                  // class org/apache/dubbo/remoting/transport/netty/NettyBackedChannelBuffer
       3: dup
       4: aload_0
       5: getfield      #4                  // Field buffer:Lorg/jboss/netty/buffer/ChannelBuffer;
       8: iload_1
       9: invokeinterface #50,  2           // InterfaceMethod org/jboss/netty/buffer/ChannelBuffer.readBytes:(I)Lorg/jboss/netty/buffer/ChannelBuffer;
      14: invokespecial #8                  // Method "<init>":(Lorg/jboss/netty/buffer/ChannelBuffer;)V
      17: areturn

  public void resetReaderIndex();
    Code:
       0: aload_0
       1: getfield      #4                  // Field buffer:Lorg/jboss/netty/buffer/ChannelBuffer;
       4: invokeinterface #51,  1           // InterfaceMethod org/jboss/netty/buffer/ChannelBuffer.resetReaderIndex:()V
       9: return

  public void resetWriterIndex();
    Code:
       0: aload_0
       1: getfield      #4                  // Field buffer:Lorg/jboss/netty/buffer/ChannelBuffer;
       4: invokeinterface #52,  1           // InterfaceMethod org/jboss/netty/buffer/ChannelBuffer.resetWriterIndex:()V
       9: return

  public int readerIndex();
    Code:
       0: aload_0
       1: getfield      #4                  // Field buffer:Lorg/jboss/netty/buffer/ChannelBuffer;
       4: invokeinterface #53,  1           // InterfaceMethod org/jboss/netty/buffer/ChannelBuffer.readerIndex:()I
       9: ireturn

  public void readerIndex(int);
    Code:
       0: aload_0
       1: getfield      #4                  // Field buffer:Lorg/jboss/netty/buffer/ChannelBuffer;
       4: iload_1
       5: invokeinterface #54,  2           // InterfaceMethod org/jboss/netty/buffer/ChannelBuffer.readerIndex:(I)V
      10: return

  public void readBytes(java.io.OutputStream, int) throws java.io.IOException;
    Code:
       0: aload_0
       1: getfield      #4                  // Field buffer:Lorg/jboss/netty/buffer/ChannelBuffer;
       4: aload_1
       5: iload_2
       6: invokeinterface #55,  3           // InterfaceMethod org/jboss/netty/buffer/ChannelBuffer.readBytes:(Ljava/io/OutputStream;I)V
      11: return

  public void setBytes(int, byte[]);
    Code:
       0: aload_0
       1: getfield      #4                  // Field buffer:Lorg/jboss/netty/buffer/ChannelBuffer;
       4: iload_1
       5: aload_2
       6: invokeinterface #56,  3           // InterfaceMethod org/jboss/netty/buffer/ChannelBuffer.setBytes:(I[B)V
      11: return

  public void setBytes(int, org.apache.dubbo.remoting.buffer.ChannelBuffer);
    Code:
       0: aload_0
       1: iload_1
       2: aload_2
       3: aload_2
       4: invokeinterface #19,  1           // InterfaceMethod org/apache/dubbo/remoting/buffer/ChannelBuffer.readableBytes:()I
       9: invokevirtual #57                 // Method setBytes:(ILorg/apache/dubbo/remoting/buffer/ChannelBuffer;I)V
      12: return

  public void setBytes(int, org.apache.dubbo.remoting.buffer.ChannelBuffer, int);
    Code:
       0: iload_3
       1: aload_2
       2: invokeinterface #19,  1           // InterfaceMethod org/apache/dubbo/remoting/buffer/ChannelBuffer.readableBytes:()I
       7: if_icmple     18
      10: new           #20                 // class java/lang/IndexOutOfBoundsException
      13: dup
      14: invokespecial #21                 // Method java/lang/IndexOutOfBoundsException."<init>":()V
      17: athrow
      18: aload_0
      19: iload_1
      20: aload_2
      21: aload_2
      22: invokeinterface #58,  1           // InterfaceMethod org/apache/dubbo/remoting/buffer/ChannelBuffer.readerIndex:()I
      27: iload_3
      28: invokevirtual #59                 // Method setBytes:(ILorg/apache/dubbo/remoting/buffer/ChannelBuffer;II)V
      31: aload_2
      32: aload_2
      33: invokeinterface #58,  1           // InterfaceMethod org/apache/dubbo/remoting/buffer/ChannelBuffer.readerIndex:()I
      38: iload_3
      39: iadd
      40: invokeinterface #60,  2           // InterfaceMethod org/apache/dubbo/remoting/buffer/ChannelBuffer.readerIndex:(I)V
      45: return

  public void setIndex(int, int);
    Code:
       0: aload_0
       1: getfield      #4                  // Field buffer:Lorg/jboss/netty/buffer/ChannelBuffer;
       4: iload_1
       5: iload_2
       6: invokeinterface #61,  3           // InterfaceMethod org/jboss/netty/buffer/ChannelBuffer.setIndex:(II)V
      11: return

  public void skipBytes(int);
    Code:
       0: aload_0
       1: getfield      #4                  // Field buffer:Lorg/jboss/netty/buffer/ChannelBuffer;
       4: iload_1
       5: invokeinterface #62,  2           // InterfaceMethod org/jboss/netty/buffer/ChannelBuffer.skipBytes:(I)V
      10: return

  public java.nio.ByteBuffer toByteBuffer();
    Code:
       0: aload_0
       1: getfield      #4                  // Field buffer:Lorg/jboss/netty/buffer/ChannelBuffer;
       4: invokeinterface #63,  1           // InterfaceMethod org/jboss/netty/buffer/ChannelBuffer.toByteBuffer:()Ljava/nio/ByteBuffer;
       9: areturn

  public boolean writable();
    Code:
       0: aload_0
       1: getfield      #4                  // Field buffer:Lorg/jboss/netty/buffer/ChannelBuffer;
       4: invokeinterface #64,  1           // InterfaceMethod org/jboss/netty/buffer/ChannelBuffer.writable:()Z
       9: ireturn

  public int writableBytes();
    Code:
       0: aload_0
       1: getfield      #4                  // Field buffer:Lorg/jboss/netty/buffer/ChannelBuffer;
       4: invokeinterface #65,  1           // InterfaceMethod org/jboss/netty/buffer/ChannelBuffer.writableBytes:()I
       9: ireturn

  public void writeByte(int);
    Code:
       0: aload_0
       1: getfield      #4                  // Field buffer:Lorg/jboss/netty/buffer/ChannelBuffer;
       4: iload_1
       5: invokeinterface #66,  2           // InterfaceMethod org/jboss/netty/buffer/ChannelBuffer.writeByte:(I)V
      10: return

  public void writeBytes(byte[]);
    Code:
       0: aload_0
       1: getfield      #4                  // Field buffer:Lorg/jboss/netty/buffer/ChannelBuffer;
       4: aload_1
       5: invokeinterface #67,  2           // InterfaceMethod org/jboss/netty/buffer/ChannelBuffer.writeBytes:([B)V
      10: return

  public void writeBytes(byte[], int, int);
    Code:
       0: aload_0
       1: getfield      #4                  // Field buffer:Lorg/jboss/netty/buffer/ChannelBuffer;
       4: aload_1
       5: iload_2
       6: iload_3
       7: invokeinterface #68,  4           // InterfaceMethod org/jboss/netty/buffer/ChannelBuffer.writeBytes:([BII)V
      12: return

  public void writeBytes(java.nio.ByteBuffer);
    Code:
       0: aload_0
       1: getfield      #4                  // Field buffer:Lorg/jboss/netty/buffer/ChannelBuffer;
       4: aload_1
       5: invokeinterface #69,  2           // InterfaceMethod org/jboss/netty/buffer/ChannelBuffer.writeBytes:(Ljava/nio/ByteBuffer;)V
      10: return

  public void writeBytes(org.apache.dubbo.remoting.buffer.ChannelBuffer);
    Code:
       0: aload_0
       1: aload_1
       2: aload_1
       3: invokeinterface #19,  1           // InterfaceMethod org/apache/dubbo/remoting/buffer/ChannelBuffer.readableBytes:()I
       8: invokevirtual #70                 // Method writeBytes:(Lorg/apache/dubbo/remoting/buffer/ChannelBuffer;I)V
      11: return

  public void writeBytes(org.apache.dubbo.remoting.buffer.ChannelBuffer, int);
    Code:
       0: iload_2
       1: aload_1
       2: invokeinterface #19,  1           // InterfaceMethod org/apache/dubbo/remoting/buffer/ChannelBuffer.readableBytes:()I
       7: if_icmple     18
      10: new           #20                 // class java/lang/IndexOutOfBoundsException
      13: dup
      14: invokespecial #21                 // Method java/lang/IndexOutOfBoundsException."<init>":()V
      17: athrow
      18: aload_0
      19: aload_1
      20: aload_1
      21: invokeinterface #58,  1           // InterfaceMethod org/apache/dubbo/remoting/buffer/ChannelBuffer.readerIndex:()I
      26: iload_2
      27: invokevirtual #71                 // Method writeBytes:(Lorg/apache/dubbo/remoting/buffer/ChannelBuffer;II)V
      30: aload_1
      31: aload_1
      32: invokeinterface #58,  1           // InterfaceMethod org/apache/dubbo/remoting/buffer/ChannelBuffer.readerIndex:()I
      37: iload_2
      38: iadd
      39: invokeinterface #60,  2           // InterfaceMethod org/apache/dubbo/remoting/buffer/ChannelBuffer.readerIndex:(I)V
      44: return

  public void writeBytes(org.apache.dubbo.remoting.buffer.ChannelBuffer, int, int);
    Code:
       0: iload_3
       1: newarray       byte
       3: astore        4
       5: aload_1
       6: iload_2
       7: aload         4
       9: iconst_0
      10: iload_3
      11: invokeinterface #22,  5           // InterfaceMethod org/apache/dubbo/remoting/buffer/ChannelBuffer.getBytes:(I[BII)V
      16: aload_0
      17: aload         4
      19: iconst_0
      20: iload_3
      21: invokevirtual #72                 // Method writeBytes:([BII)V
      24: return

  public int writeBytes(java.io.InputStream, int) throws java.io.IOException;
    Code:
       0: aload_0
       1: getfield      #4                  // Field buffer:Lorg/jboss/netty/buffer/ChannelBuffer;
       4: aload_1
       5: iload_2
       6: invokeinterface #73,  3           // InterfaceMethod org/jboss/netty/buffer/ChannelBuffer.writeBytes:(Ljava/io/InputStream;I)I
      11: ireturn

  public int writerIndex();
    Code:
       0: aload_0
       1: getfield      #4                  // Field buffer:Lorg/jboss/netty/buffer/ChannelBuffer;
       4: invokeinterface #74,  1           // InterfaceMethod org/jboss/netty/buffer/ChannelBuffer.writerIndex:()I
       9: ireturn

  public void writerIndex(int);
    Code:
       0: aload_0
       1: getfield      #4                  // Field buffer:Lorg/jboss/netty/buffer/ChannelBuffer;
       4: iload_1
       5: invokeinterface #75,  2           // InterfaceMethod org/jboss/netty/buffer/ChannelBuffer.writerIndex:(I)V
      10: return

  public int compareTo(org.apache.dubbo.remoting.buffer.ChannelBuffer);
    Code:
       0: aload_0
       1: aload_1
       2: invokestatic  #76                 // Method org/apache/dubbo/remoting/buffer/ChannelBuffers.compare:(Lorg/apache/dubbo/remoting/buffer/ChannelBuffer;Lorg/apache/dubbo/remoting/buffer/ChannelBuffer;)I
       5: ireturn

  public int compareTo(java.lang.Object);
    Code:
       0: aload_0
       1: aload_1
       2: checkcast     #77                 // class org/apache/dubbo/remoting/buffer/ChannelBuffer
       5: invokevirtual #78                 // Method compareTo:(Lorg/apache/dubbo/remoting/buffer/ChannelBuffer;)I
       8: ireturn
}
