Compiled from "NettyHandler.java"
public class org.apache.dubbo.remoting.transport.netty.NettyHandler extends org.jboss.netty.channel.SimpleChannelHandler {
  private static final org.apache.dubbo.common.logger.Logger logger;

  private final java.util.Map<java.lang.String, org.apache.dubbo.remoting.Channel> channels;

  private final org.apache.dubbo.common.URL url;

  private final org.apache.dubbo.remoting.ChannelHandler handler;

  public org.apache.dubbo.remoting.transport.netty.NettyHandler(org.apache.dubbo.common.URL, org.apache.dubbo.remoting.ChannelHandler);
    Code:
       0: aload_0
       1: invokespecial #1                  // Method org/jboss/netty/channel/SimpleChannelHandler."<init>":()V
       4: aload_0
       5: new           #2                  // class java/util/concurrent/ConcurrentHashMap
       8: dup
       9: invokespecial #3                  // Method java/util/concurrent/ConcurrentHashMap."<init>":()V
      12: putfield      #4                  // Field channels:Ljava/util/Map;
      15: aload_1
      16: ifnonnull     29
      19: new           #5                  // class java/lang/IllegalArgumentException
      22: dup
      23: ldc           #6                  // String url == null
      25: invokespecial #7                  // Method java/lang/IllegalArgumentException."<init>":(Ljava/lang/String;)V
      28: athrow
      29: aload_2
      30: ifnonnull     43
      33: new           #5                  // class java/lang/IllegalArgumentException
      36: dup
      37: ldc           #8                  // String handler == null
      39: invokespecial #7                  // Method java/lang/IllegalArgumentException."<init>":(Ljava/lang/String;)V
      42: athrow
      43: aload_0
      44: aload_1
      45: putfield      #9                  // Field url:Lorg/apache/dubbo/common/URL;
      48: aload_0
      49: aload_2
      50: putfield      #10                 // Field handler:Lorg/apache/dubbo/remoting/ChannelHandler;
      53: return

  public java.util.Map<java.lang.String, org.apache.dubbo.remoting.Channel> getChannels();
    Code:
       0: aload_0
       1: getfield      #4                  // Field channels:Ljava/util/Map;
       4: areturn

  public void channelConnected(org.jboss.netty.channel.ChannelHandlerContext, org.jboss.netty.channel.ChannelStateEvent) throws java.lang.Exception;
    Code:
       0: aload_1
       1: invokeinterface #11,  1           // InterfaceMethod org/jboss/netty/channel/ChannelHandlerContext.getChannel:()Lorg/jboss/netty/channel/Channel;
       6: aload_0
       7: getfield      #9                  // Field url:Lorg/apache/dubbo/common/URL;
      10: aload_0
      11: getfield      #10                 // Field handler:Lorg/apache/dubbo/remoting/ChannelHandler;
      14: invokestatic  #12                 // Method org/apache/dubbo/remoting/transport/netty/NettyChannel.getOrAddChannel:(Lorg/jboss/netty/channel/Channel;Lorg/apache/dubbo/common/URL;Lorg/apache/dubbo/remoting/ChannelHandler;)Lorg/apache/dubbo/remoting/transport/netty/NettyChannel;
      17: astore_3
      18: aload_3
      19: ifnull        50
      22: aload_0
      23: getfield      #4                  // Field channels:Ljava/util/Map;
      26: aload_1
      27: invokeinterface #11,  1           // InterfaceMethod org/jboss/netty/channel/ChannelHandlerContext.getChannel:()Lorg/jboss/netty/channel/Channel;
      32: invokeinterface #13,  1           // InterfaceMethod org/jboss/netty/channel/Channel.getRemoteAddress:()Ljava/net/SocketAddress;
      37: checkcast     #14                 // class java/net/InetSocketAddress
      40: invokestatic  #15                 // Method org/apache/dubbo/common/utils/NetUtils.toAddressString:(Ljava/net/InetSocketAddress;)Ljava/lang/String;
      43: aload_3
      44: invokeinterface #16,  3           // InterfaceMethod java/util/Map.put:(Ljava/lang/Object;Ljava/lang/Object;)Ljava/lang/Object;
      49: pop
      50: aload_0
      51: getfield      #10                 // Field handler:Lorg/apache/dubbo/remoting/ChannelHandler;
      54: aload_3
      55: invokeinterface #17,  2           // InterfaceMethod org/apache/dubbo/remoting/ChannelHandler.connected:(Lorg/apache/dubbo/remoting/Channel;)V
      60: aload_1
      61: invokeinterface #11,  1           // InterfaceMethod org/jboss/netty/channel/ChannelHandlerContext.getChannel:()Lorg/jboss/netty/channel/Channel;
      66: invokestatic  #18                 // Method org/apache/dubbo/remoting/transport/netty/NettyChannel.removeChannelIfDisconnected:(Lorg/jboss/netty/channel/Channel;)V
      69: goto          86
      72: astore        4
      74: aload_1
      75: invokeinterface #11,  1           // InterfaceMethod org/jboss/netty/channel/ChannelHandlerContext.getChannel:()Lorg/jboss/netty/channel/Channel;
      80: invokestatic  #18                 // Method org/apache/dubbo/remoting/transport/netty/NettyChannel.removeChannelIfDisconnected:(Lorg/jboss/netty/channel/Channel;)V
      83: aload         4
      85: athrow
      86: getstatic     #19                 // Field logger:Lorg/apache/dubbo/common/logger/Logger;
      89: invokeinterface #20,  1           // InterfaceMethod org/apache/dubbo/common/logger/Logger.isInfoEnabled:()Z
      94: ifeq          144
      97: getstatic     #19                 // Field logger:Lorg/apache/dubbo/common/logger/Logger;
     100: new           #21                 // class java/lang/StringBuilder
     103: dup
     104: invokespecial #22                 // Method java/lang/StringBuilder."<init>":()V
     107: ldc           #23                 // String The connection between
     109: invokevirtual #24                 // Method java/lang/StringBuilder.append:(Ljava/lang/String;)Ljava/lang/StringBuilder;
     112: aload_3
     113: invokevirtual #25                 // Method org/apache/dubbo/remoting/transport/netty/NettyChannel.getRemoteAddress:()Ljava/net/InetSocketAddress;
     116: invokevirtual #26                 // Method java/lang/StringBuilder.append:(Ljava/lang/Object;)Ljava/lang/StringBuilder;
     119: ldc           #27                 // String  and
     121: invokevirtual #24                 // Method java/lang/StringBuilder.append:(Ljava/lang/String;)Ljava/lang/StringBuilder;
     124: aload_3
     125: invokevirtual #28                 // Method org/apache/dubbo/remoting/transport/netty/NettyChannel.getLocalAddress:()Ljava/net/InetSocketAddress;
     128: invokevirtual #26                 // Method java/lang/StringBuilder.append:(Ljava/lang/Object;)Ljava/lang/StringBuilder;
     131: ldc           #29                 // String  is established
     133: invokevirtual #24                 // Method java/lang/StringBuilder.append:(Ljava/lang/String;)Ljava/lang/StringBuilder;
     136: invokevirtual #30                 // Method java/lang/StringBuilder.toString:()Ljava/lang/String;
     139: invokeinterface #31,  2           // InterfaceMethod org/apache/dubbo/common/logger/Logger.info:(Ljava/lang/String;)V
     144: return
    Exception table:
       from    to  target type
          18    60    72   any
          72    74    72   any

  public void channelDisconnected(org.jboss.netty.channel.ChannelHandlerContext, org.jboss.netty.channel.ChannelStateEvent) throws java.lang.Exception;
    Code:
       0: aload_1
       1: invokeinterface #11,  1           // InterfaceMethod org/jboss/netty/channel/ChannelHandlerContext.getChannel:()Lorg/jboss/netty/channel/Channel;
       6: aload_0
       7: getfield      #9                  // Field url:Lorg/apache/dubbo/common/URL;
      10: aload_0
      11: getfield      #10                 // Field handler:Lorg/apache/dubbo/remoting/ChannelHandler;
      14: invokestatic  #12                 // Method org/apache/dubbo/remoting/transport/netty/NettyChannel.getOrAddChannel:(Lorg/jboss/netty/channel/Channel;Lorg/apache/dubbo/common/URL;Lorg/apache/dubbo/remoting/ChannelHandler;)Lorg/apache/dubbo/remoting/transport/netty/NettyChannel;
      17: astore_3
      18: aload_0
      19: getfield      #4                  // Field channels:Ljava/util/Map;
      22: aload_1
      23: invokeinterface #11,  1           // InterfaceMethod org/jboss/netty/channel/ChannelHandlerContext.getChannel:()Lorg/jboss/netty/channel/Channel;
      28: invokeinterface #13,  1           // InterfaceMethod org/jboss/netty/channel/Channel.getRemoteAddress:()Ljava/net/SocketAddress;
      33: checkcast     #14                 // class java/net/InetSocketAddress
      36: invokestatic  #15                 // Method org/apache/dubbo/common/utils/NetUtils.toAddressString:(Ljava/net/InetSocketAddress;)Ljava/lang/String;
      39: invokeinterface #32,  2           // InterfaceMethod java/util/Map.remove:(Ljava/lang/Object;)Ljava/lang/Object;
      44: pop
      45: aload_0
      46: getfield      #10                 // Field handler:Lorg/apache/dubbo/remoting/ChannelHandler;
      49: aload_3
      50: invokeinterface #33,  2           // InterfaceMethod org/apache/dubbo/remoting/ChannelHandler.disconnected:(Lorg/apache/dubbo/remoting/Channel;)V
      55: aload_1
      56: invokeinterface #11,  1           // InterfaceMethod org/jboss/netty/channel/ChannelHandlerContext.getChannel:()Lorg/jboss/netty/channel/Channel;
      61: invokestatic  #18                 // Method org/apache/dubbo/remoting/transport/netty/NettyChannel.removeChannelIfDisconnected:(Lorg/jboss/netty/channel/Channel;)V
      64: goto          81
      67: astore        4
      69: aload_1
      70: invokeinterface #11,  1           // InterfaceMethod org/jboss/netty/channel/ChannelHandlerContext.getChannel:()Lorg/jboss/netty/channel/Channel;
      75: invokestatic  #18                 // Method org/apache/dubbo/remoting/transport/netty/NettyChannel.removeChannelIfDisconnected:(Lorg/jboss/netty/channel/Channel;)V
      78: aload         4
      80: athrow
      81: getstatic     #19                 // Field logger:Lorg/apache/dubbo/common/logger/Logger;
      84: invokeinterface #20,  1           // InterfaceMethod org/apache/dubbo/common/logger/Logger.isInfoEnabled:()Z
      89: ifeq          139
      92: getstatic     #19                 // Field logger:Lorg/apache/dubbo/common/logger/Logger;
      95: new           #21                 // class java/lang/StringBuilder
      98: dup
      99: invokespecial #22                 // Method java/lang/StringBuilder."<init>":()V
     102: ldc           #23                 // String The connection between
     104: invokevirtual #24                 // Method java/lang/StringBuilder.append:(Ljava/lang/String;)Ljava/lang/StringBuilder;
     107: aload_3
     108: invokevirtual #25                 // Method org/apache/dubbo/remoting/transport/netty/NettyChannel.getRemoteAddress:()Ljava/net/InetSocketAddress;
     111: invokevirtual #26                 // Method java/lang/StringBuilder.append:(Ljava/lang/Object;)Ljava/lang/StringBuilder;
     114: ldc           #27                 // String  and
     116: invokevirtual #24                 // Method java/lang/StringBuilder.append:(Ljava/lang/String;)Ljava/lang/StringBuilder;
     119: aload_3
     120: invokevirtual #28                 // Method org/apache/dubbo/remoting/transport/netty/NettyChannel.getLocalAddress:()Ljava/net/InetSocketAddress;
     123: invokevirtual #26                 // Method java/lang/StringBuilder.append:(Ljava/lang/Object;)Ljava/lang/StringBuilder;
     126: ldc           #34                 // String  is disconnected
     128: invokevirtual #24                 // Method java/lang/StringBuilder.append:(Ljava/lang/String;)Ljava/lang/StringBuilder;
     131: invokevirtual #30                 // Method java/lang/StringBuilder.toString:()Ljava/lang/String;
     134: invokeinterface #31,  2           // InterfaceMethod org/apache/dubbo/common/logger/Logger.info:(Ljava/lang/String;)V
     139: return
    Exception table:
       from    to  target type
          18    55    67   any
          67    69    67   any

  public void messageReceived(org.jboss.netty.channel.ChannelHandlerContext, org.jboss.netty.channel.MessageEvent) throws java.lang.Exception;
    Code:
       0: aload_1
       1: invokeinterface #11,  1           // InterfaceMethod org/jboss/netty/channel/ChannelHandlerContext.getChannel:()Lorg/jboss/netty/channel/Channel;
       6: aload_0
       7: getfield      #9                  // Field url:Lorg/apache/dubbo/common/URL;
      10: aload_0
      11: getfield      #10                 // Field handler:Lorg/apache/dubbo/remoting/ChannelHandler;
      14: invokestatic  #12                 // Method org/apache/dubbo/remoting/transport/netty/NettyChannel.getOrAddChannel:(Lorg/jboss/netty/channel/Channel;Lorg/apache/dubbo/common/URL;Lorg/apache/dubbo/remoting/ChannelHandler;)Lorg/apache/dubbo/remoting/transport/netty/NettyChannel;
      17: astore_3
      18: aload_0
      19: getfield      #10                 // Field handler:Lorg/apache/dubbo/remoting/ChannelHandler;
      22: aload_3
      23: aload_2
      24: invokeinterface #35,  1           // InterfaceMethod org/jboss/netty/channel/MessageEvent.getMessage:()Ljava/lang/Object;
      29: invokeinterface #36,  3           // InterfaceMethod org/apache/dubbo/remoting/ChannelHandler.received:(Lorg/apache/dubbo/remoting/Channel;Ljava/lang/Object;)V
      34: aload_1
      35: invokeinterface #11,  1           // InterfaceMethod org/jboss/netty/channel/ChannelHandlerContext.getChannel:()Lorg/jboss/netty/channel/Channel;
      40: invokestatic  #18                 // Method org/apache/dubbo/remoting/transport/netty/NettyChannel.removeChannelIfDisconnected:(Lorg/jboss/netty/channel/Channel;)V
      43: goto          60
      46: astore        4
      48: aload_1
      49: invokeinterface #11,  1           // InterfaceMethod org/jboss/netty/channel/ChannelHandlerContext.getChannel:()Lorg/jboss/netty/channel/Channel;
      54: invokestatic  #18                 // Method org/apache/dubbo/remoting/transport/netty/NettyChannel.removeChannelIfDisconnected:(Lorg/jboss/netty/channel/Channel;)V
      57: aload         4
      59: athrow
      60: return
    Exception table:
       from    to  target type
          18    34    46   any
          46    48    46   any

  public void writeRequested(org.jboss.netty.channel.ChannelHandlerContext, org.jboss.netty.channel.MessageEvent) throws java.lang.Exception;
    Code:
       0: aload_0
       1: aload_1
       2: aload_2
       3: invokespecial #37                 // Method org/jboss/netty/channel/SimpleChannelHandler.writeRequested:(Lorg/jboss/netty/channel/ChannelHandlerContext;Lorg/jboss/netty/channel/MessageEvent;)V
       6: aload_1
       7: invokeinterface #11,  1           // InterfaceMethod org/jboss/netty/channel/ChannelHandlerContext.getChannel:()Lorg/jboss/netty/channel/Channel;
      12: aload_0
      13: getfield      #9                  // Field url:Lorg/apache/dubbo/common/URL;
      16: aload_0
      17: getfield      #10                 // Field handler:Lorg/apache/dubbo/remoting/ChannelHandler;
      20: invokestatic  #12                 // Method org/apache/dubbo/remoting/transport/netty/NettyChannel.getOrAddChannel:(Lorg/jboss/netty/channel/Channel;Lorg/apache/dubbo/common/URL;Lorg/apache/dubbo/remoting/ChannelHandler;)Lorg/apache/dubbo/remoting/transport/netty/NettyChannel;
      23: astore_3
      24: aload_0
      25: getfield      #10                 // Field handler:Lorg/apache/dubbo/remoting/ChannelHandler;
      28: aload_3
      29: aload_2
      30: invokeinterface #35,  1           // InterfaceMethod org/jboss/netty/channel/MessageEvent.getMessage:()Ljava/lang/Object;
      35: invokeinterface #38,  3           // InterfaceMethod org/apache/dubbo/remoting/ChannelHandler.sent:(Lorg/apache/dubbo/remoting/Channel;Ljava/lang/Object;)V
      40: aload_1
      41: invokeinterface #11,  1           // InterfaceMethod org/jboss/netty/channel/ChannelHandlerContext.getChannel:()Lorg/jboss/netty/channel/Channel;
      46: invokestatic  #18                 // Method org/apache/dubbo/remoting/transport/netty/NettyChannel.removeChannelIfDisconnected:(Lorg/jboss/netty/channel/Channel;)V
      49: goto          66
      52: astore        4
      54: aload_1
      55: invokeinterface #11,  1           // InterfaceMethod org/jboss/netty/channel/ChannelHandlerContext.getChannel:()Lorg/jboss/netty/channel/Channel;
      60: invokestatic  #18                 // Method org/apache/dubbo/remoting/transport/netty/NettyChannel.removeChannelIfDisconnected:(Lorg/jboss/netty/channel/Channel;)V
      63: aload         4
      65: athrow
      66: return
    Exception table:
       from    to  target type
          24    40    52   any
          52    54    52   any

  public void exceptionCaught(org.jboss.netty.channel.ChannelHandlerContext, org.jboss.netty.channel.ExceptionEvent) throws java.lang.Exception;
    Code:
       0: aload_1
       1: invokeinterface #11,  1           // InterfaceMethod org/jboss/netty/channel/ChannelHandlerContext.getChannel:()Lorg/jboss/netty/channel/Channel;
       6: aload_0
       7: getfield      #9                  // Field url:Lorg/apache/dubbo/common/URL;
      10: aload_0
      11: getfield      #10                 // Field handler:Lorg/apache/dubbo/remoting/ChannelHandler;
      14: invokestatic  #12                 // Method org/apache/dubbo/remoting/transport/netty/NettyChannel.getOrAddChannel:(Lorg/jboss/netty/channel/Channel;Lorg/apache/dubbo/common/URL;Lorg/apache/dubbo/remoting/ChannelHandler;)Lorg/apache/dubbo/remoting/transport/netty/NettyChannel;
      17: astore_3
      18: aload_0
      19: getfield      #10                 // Field handler:Lorg/apache/dubbo/remoting/ChannelHandler;
      22: aload_3
      23: aload_2
      24: invokeinterface #39,  1           // InterfaceMethod org/jboss/netty/channel/ExceptionEvent.getCause:()Ljava/lang/Throwable;
      29: invokeinterface #40,  3           // InterfaceMethod org/apache/dubbo/remoting/ChannelHandler.caught:(Lorg/apache/dubbo/remoting/Channel;Ljava/lang/Throwable;)V
      34: aload_1
      35: invokeinterface #11,  1           // InterfaceMethod org/jboss/netty/channel/ChannelHandlerContext.getChannel:()Lorg/jboss/netty/channel/Channel;
      40: invokestatic  #18                 // Method org/apache/dubbo/remoting/transport/netty/NettyChannel.removeChannelIfDisconnected:(Lorg/jboss/netty/channel/Channel;)V
      43: goto          60
      46: astore        4
      48: aload_1
      49: invokeinterface #11,  1           // InterfaceMethod org/jboss/netty/channel/ChannelHandlerContext.getChannel:()Lorg/jboss/netty/channel/Channel;
      54: invokestatic  #18                 // Method org/apache/dubbo/remoting/transport/netty/NettyChannel.removeChannelIfDisconnected:(Lorg/jboss/netty/channel/Channel;)V
      57: aload         4
      59: athrow
      60: return
    Exception table:
       from    to  target type
          18    34    46   any
          46    48    46   any

  static {};
    Code:
       0: ldc           #41                 // class org/apache/dubbo/remoting/transport/netty/NettyHandler
       2: invokestatic  #42                 // Method org/apache/dubbo/common/logger/LoggerFactory.getLogger:(Ljava/lang/Class;)Lorg/apache/dubbo/common/logger/Logger;
       5: putstatic     #19                 // Field logger:Lorg/apache/dubbo/common/logger/Logger;
       8: return
}
