Compiled from "NettyPortUnificationTransporter.java"
public class org.apache.dubbo.remoting.transport.netty.NettyPortUnificationTransporter implements org.apache.dubbo.remoting.api.pu.PortUnificationTransporter {
  public static final java.lang.String NAME;

  public org.apache.dubbo.remoting.transport.netty.NettyPortUnificationTransporter();
    Code:
       0: aload_0
       1: invokespecial #1                  // Method java/lang/Object."<init>":()V
       4: return

  public org.apache.dubbo.remoting.api.pu.AbstractPortUnificationServer bind(org.apache.dubbo.common.URL, org.apache.dubbo.remoting.ChannelHandler) throws org.apache.dubbo.remoting.RemotingException;
    Code:
       0: new           #2                  // class org/apache/dubbo/remoting/transport/netty/NettyPortUnificationServer
       3: dup
       4: aload_1
       5: aload_2
       6: invokespecial #3                  // Method org/apache/dubbo/remoting/transport/netty/NettyPortUnificationServer."<init>":(Lorg/apache/dubbo/common/URL;Lorg/apache/dubbo/remoting/ChannelHandler;)V
       9: areturn

  public org.apache.dubbo.remoting.api.connection.AbstractConnectionClient connect(org.apache.dubbo.common.URL, org.apache.dubbo.remoting.ChannelHandler) throws org.apache.dubbo.remoting.RemotingException;
    Code:
       0: new           #4                  // class org/apache/dubbo/remoting/RemotingException
       3: dup
       4: aload_1
       5: invokevirtual #5                  // Method org/apache/dubbo/common/URL.toInetSocketAddress:()Ljava/net/InetSocketAddress;
       8: aconst_null
       9: ldc           #6                  // String connectionManager for netty3 spi not found.
      11: invokespecial #7                  // Method org/apache/dubbo/remoting/RemotingException."<init>":(Ljava/net/InetSocketAddress;Ljava/net/InetSocketAddress;Ljava/lang/String;)V
      14: athrow
}
