Compiled from "NettyBackedChannelBufferFactory.java"
public class org.apache.dubbo.remoting.transport.netty.NettyBackedChannelBufferFactory implements org.apache.dubbo.remoting.buffer.ChannelBufferFactory {
  private static final org.apache.dubbo.remoting.transport.netty.NettyBackedChannelBufferFactory INSTANCE;

  public org.apache.dubbo.remoting.transport.netty.NettyBackedChannelBufferFactory();
    Code:
       0: aload_0
       1: invokespecial #1                  // Method java/lang/Object."<init>":()V
       4: return

  public static org.apache.dubbo.remoting.buffer.ChannelBufferFactory getInstance();
    Code:
       0: getstatic     #2                  // Field INSTANCE:Lorg/apache/dubbo/remoting/transport/netty/NettyBackedChannelBufferFactory;
       3: areturn

  public org.apache.dubbo.remoting.buffer.ChannelBuffer getBuffer(int);
    Code:
       0: new           #3                  // class org/apache/dubbo/remoting/transport/netty/NettyBackedChannelBuffer
       3: dup
       4: iload_1
       5: invokestatic  #4                  // Method org/jboss/netty/buffer/ChannelBuffers.dynamicBuffer:(I)Lorg/jboss/netty/buffer/ChannelBuffer;
       8: invokespecial #5                  // Method org/apache/dubbo/remoting/transport/netty/NettyBackedChannelBuffer."<init>":(Lorg/jboss/netty/buffer/ChannelBuffer;)V
      11: areturn

  public org.apache.dubbo.remoting.buffer.ChannelBuffer getBuffer(byte[], int, int);
    Code:
       0: iload_3
       1: invokestatic  #4                  // Method org/jboss/netty/buffer/ChannelBuffers.dynamicBuffer:(I)Lorg/jboss/netty/buffer/ChannelBuffer;
       4: astore        4
       6: aload         4
       8: aload_1
       9: iload_2
      10: iload_3
      11: invokeinterface #6,  4            // InterfaceMethod org/jboss/netty/buffer/ChannelBuffer.writeBytes:([BII)V
      16: new           #3                  // class org/apache/dubbo/remoting/transport/netty/NettyBackedChannelBuffer
      19: dup
      20: aload         4
      22: invokespecial #5                  // Method org/apache/dubbo/remoting/transport/netty/NettyBackedChannelBuffer."<init>":(Lorg/jboss/netty/buffer/ChannelBuffer;)V
      25: areturn

  public org.apache.dubbo.remoting.buffer.ChannelBuffer getBuffer(java.nio.ByteBuffer);
    Code:
       0: new           #3                  // class org/apache/dubbo/remoting/transport/netty/NettyBackedChannelBuffer
       3: dup
       4: aload_1
       5: invokestatic  #7                  // Method org/jboss/netty/buffer/ChannelBuffers.wrappedBuffer:(Ljava/nio/ByteBuffer;)Lorg/jboss/netty/buffer/ChannelBuffer;
       8: invokespecial #5                  // Method org/apache/dubbo/remoting/transport/netty/NettyBackedChannelBuffer."<init>":(Lorg/jboss/netty/buffer/ChannelBuffer;)V
      11: areturn

  static {};
    Code:
       0: new           #8                  // class org/apache/dubbo/remoting/transport/netty/NettyBackedChannelBufferFactory
       3: dup
       4: invokespecial #9                  // Method "<init>":()V
       7: putstatic     #2                  // Field INSTANCE:Lorg/apache/dubbo/remoting/transport/netty/NettyBackedChannelBufferFactory;
      10: return
}
