Compiled from "NettyCodecAdapter.java"
class org.apache.dubbo.remoting.transport.netty.NettyCodecAdapter$InternalDecoder extends org.jboss.netty.channel.SimpleChannelUpstreamHandler {
  private org.apache.dubbo.remoting.buffer.ChannelBuffer buffer;

  final org.apache.dubbo.remoting.transport.netty.NettyCodecAdapter this$0;

  private org.apache.dubbo.remoting.transport.netty.NettyCodecAdapter$InternalDecoder(org.apache.dubbo.remoting.transport.netty.NettyCodecAdapter);
    Code:
       0: aload_0
       1: aload_1
       2: putfield      #2                  // Field this$0:Lorg/apache/dubbo/remoting/transport/netty/NettyCodecAdapter;
       5: aload_0
       6: invokespecial #3                  // Method org/jboss/netty/channel/SimpleChannelUpstreamHandler."<init>":()V
       9: aload_0
      10: getstatic     #4                  // Field org/apache/dubbo/remoting/buffer/ChannelBuffers.EMPTY_BUFFER:Lorg/apache/dubbo/remoting/buffer/ChannelBuffer;
      13: putfield      #5                  // Field buffer:Lorg/apache/dubbo/remoting/buffer/ChannelBuffer;
      16: return

  public void messageReceived(org.jboss.netty.channel.ChannelHandlerContext, org.jboss.netty.channel.MessageEvent) throws java.lang.Exception;
    Code:
       0: aload_2
       1: invokeinterface #6,  1            // InterfaceMethod org/jboss/netty/channel/MessageEvent.getMessage:()Ljava/lang/Object;
       6: astore_3
       7: aload_3
       8: instanceof    #7                  // class org/jboss/netty/buffer/ChannelBuffer
      11: ifne          22
      14: aload_1
      15: aload_2
      16: invokeinterface #8,  2            // InterfaceMethod org/jboss/netty/channel/ChannelHandlerContext.sendUpstream:(Lorg/jboss/netty/channel/ChannelEvent;)V
      21: return
      22: aload_3
      23: checkcast     #7                  // class org/jboss/netty/buffer/ChannelBuffer
      26: astore        4
      28: aload         4
      30: invokeinterface #9,  1            // InterfaceMethod org/jboss/netty/buffer/ChannelBuffer.readableBytes:()I
      35: istore        5
      37: iload         5
      39: ifgt          43
      42: return
      43: aload_0
      44: getfield      #5                  // Field buffer:Lorg/apache/dubbo/remoting/buffer/ChannelBuffer;
      47: invokeinterface #10,  1           // InterfaceMethod org/apache/dubbo/remoting/buffer/ChannelBuffer.readable:()Z
      52: ifeq          175
      55: aload_0
      56: getfield      #5                  // Field buffer:Lorg/apache/dubbo/remoting/buffer/ChannelBuffer;
      59: instanceof    #11                 // class org/apache/dubbo/remoting/buffer/DynamicChannelBuffer
      62: ifeq          90
      65: aload_0
      66: getfield      #5                  // Field buffer:Lorg/apache/dubbo/remoting/buffer/ChannelBuffer;
      69: aload         4
      71: invokeinterface #12,  1           // InterfaceMethod org/jboss/netty/buffer/ChannelBuffer.toByteBuffer:()Ljava/nio/ByteBuffer;
      76: invokeinterface #13,  2           // InterfaceMethod org/apache/dubbo/remoting/buffer/ChannelBuffer.writeBytes:(Ljava/nio/ByteBuffer;)V
      81: aload_0
      82: getfield      #5                  // Field buffer:Lorg/apache/dubbo/remoting/buffer/ChannelBuffer;
      85: astore        6
      87: goto          187
      90: aload_0
      91: getfield      #5                  // Field buffer:Lorg/apache/dubbo/remoting/buffer/ChannelBuffer;
      94: invokeinterface #14,  1           // InterfaceMethod org/apache/dubbo/remoting/buffer/ChannelBuffer.readableBytes:()I
      99: aload         4
     101: invokeinterface #9,  1            // InterfaceMethod org/jboss/netty/buffer/ChannelBuffer.readableBytes:()I
     106: iadd
     107: istore        7
     109: iload         7
     111: aload_0
     112: getfield      #2                  // Field this$0:Lorg/apache/dubbo/remoting/transport/netty/NettyCodecAdapter;
     115: invokestatic  #15                 // Method org/apache/dubbo/remoting/transport/netty/NettyCodecAdapter.access$500:(Lorg/apache/dubbo/remoting/transport/netty/NettyCodecAdapter;)I
     118: if_icmple     126
     121: iload         7
     123: goto          133
     126: aload_0
     127: getfield      #2                  // Field this$0:Lorg/apache/dubbo/remoting/transport/netty/NettyCodecAdapter;
     130: invokestatic  #15                 // Method org/apache/dubbo/remoting/transport/netty/NettyCodecAdapter.access$500:(Lorg/apache/dubbo/remoting/transport/netty/NettyCodecAdapter;)I
     133: invokestatic  #16                 // Method org/apache/dubbo/remoting/buffer/ChannelBuffers.dynamicBuffer:(I)Lorg/apache/dubbo/remoting/buffer/ChannelBuffer;
     136: astore        6
     138: aload         6
     140: aload_0
     141: getfield      #5                  // Field buffer:Lorg/apache/dubbo/remoting/buffer/ChannelBuffer;
     144: aload_0
     145: getfield      #5                  // Field buffer:Lorg/apache/dubbo/remoting/buffer/ChannelBuffer;
     148: invokeinterface #14,  1           // InterfaceMethod org/apache/dubbo/remoting/buffer/ChannelBuffer.readableBytes:()I
     153: invokeinterface #17,  3           // InterfaceMethod org/apache/dubbo/remoting/buffer/ChannelBuffer.writeBytes:(Lorg/apache/dubbo/remoting/buffer/ChannelBuffer;I)V
     158: aload         6
     160: aload         4
     162: invokeinterface #12,  1           // InterfaceMethod org/jboss/netty/buffer/ChannelBuffer.toByteBuffer:()Ljava/nio/ByteBuffer;
     167: invokeinterface #13,  2           // InterfaceMethod org/apache/dubbo/remoting/buffer/ChannelBuffer.writeBytes:(Ljava/nio/ByteBuffer;)V
     172: goto          187
     175: aload         4
     177: invokeinterface #12,  1           // InterfaceMethod org/jboss/netty/buffer/ChannelBuffer.toByteBuffer:()Ljava/nio/ByteBuffer;
     182: invokestatic  #18                 // Method org/apache/dubbo/remoting/buffer/ChannelBuffers.wrappedBuffer:(Ljava/nio/ByteBuffer;)Lorg/apache/dubbo/remoting/buffer/ChannelBuffer;
     185: astore        6
     187: aload_1
     188: invokeinterface #19,  1           // InterfaceMethod org/jboss/netty/channel/ChannelHandlerContext.getChannel:()Lorg/jboss/netty/channel/Channel;
     193: aload_0
     194: getfield      #2                  // Field this$0:Lorg/apache/dubbo/remoting/transport/netty/NettyCodecAdapter;
     197: invokestatic  #20                 // Method org/apache/dubbo/remoting/transport/netty/NettyCodecAdapter.access$200:(Lorg/apache/dubbo/remoting/transport/netty/NettyCodecAdapter;)Lorg/apache/dubbo/common/URL;
     200: aload_0
     201: getfield      #2                  // Field this$0:Lorg/apache/dubbo/remoting/transport/netty/NettyCodecAdapter;
     204: invokestatic  #21                 // Method org/apache/dubbo/remoting/transport/netty/NettyCodecAdapter.access$300:(Lorg/apache/dubbo/remoting/transport/netty/NettyCodecAdapter;)Lorg/apache/dubbo/remoting/ChannelHandler;
     207: invokestatic  #22                 // Method org/apache/dubbo/remoting/transport/netty/NettyChannel.getOrAddChannel:(Lorg/jboss/netty/channel/Channel;Lorg/apache/dubbo/common/URL;Lorg/apache/dubbo/remoting/ChannelHandler;)Lorg/apache/dubbo/remoting/transport/netty/NettyChannel;
     210: astore        7
     212: aload         6
     214: invokeinterface #23,  1           // InterfaceMethod org/apache/dubbo/remoting/buffer/ChannelBuffer.readerIndex:()I
     219: istore        9
     221: aload_0
     222: getfield      #2                  // Field this$0:Lorg/apache/dubbo/remoting/transport/netty/NettyCodecAdapter;
     225: invokestatic  #24                 // Method org/apache/dubbo/remoting/transport/netty/NettyCodecAdapter.access$400:(Lorg/apache/dubbo/remoting/transport/netty/NettyCodecAdapter;)Lorg/apache/dubbo/remoting/Codec2;
     228: aload         7
     230: aload         6
     232: invokeinterface #25,  3           // InterfaceMethod org/apache/dubbo/remoting/Codec2.decode:(Lorg/apache/dubbo/remoting/Channel;Lorg/apache/dubbo/remoting/buffer/ChannelBuffer;)Ljava/lang/Object;
     237: astore        8
     239: goto          254
     242: astore        10
     244: aload_0
     245: getstatic     #4                  // Field org/apache/dubbo/remoting/buffer/ChannelBuffers.EMPTY_BUFFER:Lorg/apache/dubbo/remoting/buffer/ChannelBuffer;
     248: putfield      #5                  // Field buffer:Lorg/apache/dubbo/remoting/buffer/ChannelBuffer;
     251: aload         10
     253: athrow
     254: aload         8
     256: getstatic     #27                 // Field org/apache/dubbo/remoting/Codec2$DecodeResult.NEED_MORE_INPUT:Lorg/apache/dubbo/remoting/Codec2$DecodeResult;
     259: if_acmpne     274
     262: aload         6
     264: iload         9
     266: invokeinterface #28,  2           // InterfaceMethod org/apache/dubbo/remoting/buffer/ChannelBuffer.readerIndex:(I)V
     271: goto          330
     274: iload         9
     276: aload         6
     278: invokeinterface #23,  1           // InterfaceMethod org/apache/dubbo/remoting/buffer/ChannelBuffer.readerIndex:()I
     283: if_icmpne     303
     286: aload_0
     287: getstatic     #4                  // Field org/apache/dubbo/remoting/buffer/ChannelBuffers.EMPTY_BUFFER:Lorg/apache/dubbo/remoting/buffer/ChannelBuffer;
     290: putfield      #5                  // Field buffer:Lorg/apache/dubbo/remoting/buffer/ChannelBuffer;
     293: new           #26                 // class java/io/IOException
     296: dup
     297: ldc           #29                 // String Decode without read data.
     299: invokespecial #30                 // Method java/io/IOException."<init>":(Ljava/lang/String;)V
     302: athrow
     303: aload         8
     305: ifnull        320
     308: aload_1
     309: aload         8
     311: aload_2
     312: invokeinterface #31,  1           // InterfaceMethod org/jboss/netty/channel/MessageEvent.getRemoteAddress:()Ljava/net/SocketAddress;
     317: invokestatic  #32                 // Method org/jboss/netty/channel/Channels.fireMessageReceived:(Lorg/jboss/netty/channel/ChannelHandlerContext;Ljava/lang/Object;Ljava/net/SocketAddress;)V
     320: aload         6
     322: invokeinterface #10,  1           // InterfaceMethod org/apache/dubbo/remoting/buffer/ChannelBuffer.readable:()Z
     327: ifne          212
     330: aload         6
     332: invokeinterface #10,  1           // InterfaceMethod org/apache/dubbo/remoting/buffer/ChannelBuffer.readable:()Z
     337: ifeq          356
     340: aload         6
     342: invokeinterface #33,  1           // InterfaceMethod org/apache/dubbo/remoting/buffer/ChannelBuffer.discardReadBytes:()V
     347: aload_0
     348: aload         6
     350: putfield      #5                  // Field buffer:Lorg/apache/dubbo/remoting/buffer/ChannelBuffer;
     353: goto          363
     356: aload_0
     357: getstatic     #4                  // Field org/apache/dubbo/remoting/buffer/ChannelBuffers.EMPTY_BUFFER:Lorg/apache/dubbo/remoting/buffer/ChannelBuffer;
     360: putfield      #5                  // Field buffer:Lorg/apache/dubbo/remoting/buffer/ChannelBuffer;
     363: aload_1
     364: invokeinterface #19,  1           // InterfaceMethod org/jboss/netty/channel/ChannelHandlerContext.getChannel:()Lorg/jboss/netty/channel/Channel;
     369: invokestatic  #34                 // Method org/apache/dubbo/remoting/transport/netty/NettyChannel.removeChannelIfDisconnected:(Lorg/jboss/netty/channel/Channel;)V
     372: goto          422
     375: astore        11
     377: aload         6
     379: invokeinterface #10,  1           // InterfaceMethod org/apache/dubbo/remoting/buffer/ChannelBuffer.readable:()Z
     384: ifeq          403
     387: aload         6
     389: invokeinterface #33,  1           // InterfaceMethod org/apache/dubbo/remoting/buffer/ChannelBuffer.discardReadBytes:()V
     394: aload_0
     395: aload         6
     397: putfield      #5                  // Field buffer:Lorg/apache/dubbo/remoting/buffer/ChannelBuffer;
     400: goto          410
     403: aload_0
     404: getstatic     #4                  // Field org/apache/dubbo/remoting/buffer/ChannelBuffers.EMPTY_BUFFER:Lorg/apache/dubbo/remoting/buffer/ChannelBuffer;
     407: putfield      #5                  // Field buffer:Lorg/apache/dubbo/remoting/buffer/ChannelBuffer;
     410: aload_1
     411: invokeinterface #19,  1           // InterfaceMethod org/jboss/netty/channel/ChannelHandlerContext.getChannel:()Lorg/jboss/netty/channel/Channel;
     416: invokestatic  #34                 // Method org/apache/dubbo/remoting/transport/netty/NettyChannel.removeChannelIfDisconnected:(Lorg/jboss/netty/channel/Channel;)V
     419: aload         11
     421: athrow
     422: return
    Exception table:
       from    to  target type
         221   239   242   Class java/io/IOException
         212   330   375   any
         375   377   375   any

  public void exceptionCaught(org.jboss.netty.channel.ChannelHandlerContext, org.jboss.netty.channel.ExceptionEvent) throws java.lang.Exception;
    Code:
       0: aload_1
       1: aload_2
       2: invokeinterface #8,  2            // InterfaceMethod org/jboss/netty/channel/ChannelHandlerContext.sendUpstream:(Lorg/jboss/netty/channel/ChannelEvent;)V
       7: return

  org.apache.dubbo.remoting.transport.netty.NettyCodecAdapter$InternalDecoder(org.apache.dubbo.remoting.transport.netty.NettyCodecAdapter, org.apache.dubbo.remoting.transport.netty.NettyCodecAdapter$1);
    Code:
       0: aload_0
       1: aload_1
       2: invokespecial #1                  // Method "<init>":(Lorg/apache/dubbo/remoting/transport/netty/NettyCodecAdapter;)V
       5: return
}
