Compiled from "NettyCodecAdapter.java"
class org.apache.dubbo.remoting.transport.netty.NettyCodecAdapter$InternalEncoder extends org.jboss.netty.handler.codec.oneone.OneToOneEncoder {
  final org.apache.dubbo.remoting.transport.netty.NettyCodecAdapter this$0;

  private org.apache.dubbo.remoting.transport.netty.NettyCodecAdapter$InternalEncoder(org.apache.dubbo.remoting.transport.netty.NettyCodecAdapter);
    Code:
       0: aload_0
       1: aload_1
       2: putfield      #2                  // Field this$0:Lorg/apache/dubbo/remoting/transport/netty/NettyCodecAdapter;
       5: aload_0
       6: invokespecial #3                  // Method org/jboss/netty/handler/codec/oneone/OneToOneEncoder."<init>":()V
       9: return

  protected java.lang.Object encode(org.jboss.netty.channel.ChannelHandlerContext, org.jboss.netty.channel.Channel, java.lang.Object) throws java.lang.Exception;
    Code:
       0: sipush        1024
       3: invokestatic  #4                  // Method org/apache/dubbo/remoting/buffer/ChannelBuffers.dynamicBuffer:(I)Lorg/apache/dubbo/remoting/buffer/ChannelBuffer;
       6: astore        4
       8: aload_2
       9: aload_0
      10: getfield      #2                  // Field this$0:Lorg/apache/dubbo/remoting/transport/netty/NettyCodecAdapter;
      13: invokestatic  #5                  // Method org/apache/dubbo/remoting/transport/netty/NettyCodecAdapter.access$200:(Lorg/apache/dubbo/remoting/transport/netty/NettyCodecAdapter;)Lorg/apache/dubbo/common/URL;
      16: aload_0
      17: getfield      #2                  // Field this$0:Lorg/apache/dubbo/remoting/transport/netty/NettyCodecAdapter;
      20: invokestatic  #6                  // Method org/apache/dubbo/remoting/transport/netty/NettyCodecAdapter.access$300:(Lorg/apache/dubbo/remoting/transport/netty/NettyCodecAdapter;)Lorg/apache/dubbo/remoting/ChannelHandler;
      23: invokestatic  #7                  // Method org/apache/dubbo/remoting/transport/netty/NettyChannel.getOrAddChannel:(Lorg/jboss/netty/channel/Channel;Lorg/apache/dubbo/common/URL;Lorg/apache/dubbo/remoting/ChannelHandler;)Lorg/apache/dubbo/remoting/transport/netty/NettyChannel;
      26: astore        5
      28: aload_0
      29: getfield      #2                  // Field this$0:Lorg/apache/dubbo/remoting/transport/netty/NettyCodecAdapter;
      32: invokestatic  #8                  // Method org/apache/dubbo/remoting/transport/netty/NettyCodecAdapter.access$400:(Lorg/apache/dubbo/remoting/transport/netty/NettyCodecAdapter;)Lorg/apache/dubbo/remoting/Codec2;
      35: aload         5
      37: aload         4
      39: aload_3
      40: invokeinterface #9,  4            // InterfaceMethod org/apache/dubbo/remoting/Codec2.encode:(Lorg/apache/dubbo/remoting/Channel;Lorg/apache/dubbo/remoting/buffer/ChannelBuffer;Ljava/lang/Object;)V
      45: aload_2
      46: invokestatic  #10                 // Method org/apache/dubbo/remoting/transport/netty/NettyChannel.removeChannelIfDisconnected:(Lorg/jboss/netty/channel/Channel;)V
      49: goto          61
      52: astore        6
      54: aload_2
      55: invokestatic  #10                 // Method org/apache/dubbo/remoting/transport/netty/NettyChannel.removeChannelIfDisconnected:(Lorg/jboss/netty/channel/Channel;)V
      58: aload         6
      60: athrow
      61: aload         4
      63: invokeinterface #11,  1           // InterfaceMethod org/apache/dubbo/remoting/buffer/ChannelBuffer.toByteBuffer:()Ljava/nio/ByteBuffer;
      68: invokestatic  #12                 // Method org/jboss/netty/buffer/ChannelBuffers.wrappedBuffer:(Ljava/nio/ByteBuffer;)Lorg/jboss/netty/buffer/ChannelBuffer;
      71: areturn
    Exception table:
       from    to  target type
          28    45    52   any
          52    54    52   any

  org.apache.dubbo.remoting.transport.netty.NettyCodecAdapter$InternalEncoder(org.apache.dubbo.remoting.transport.netty.NettyCodecAdapter, org.apache.dubbo.remoting.transport.netty.NettyCodecAdapter$1);
    Code:
       0: aload_0
       1: aload_1
       2: invokespecial #1                  // Method "<init>":(Lorg/apache/dubbo/remoting/transport/netty/NettyCodecAdapter;)V
       5: return
}
