Compiled from "NettyCodecAdapter.java"
final class org.apache.dubbo.remoting.transport.netty.NettyCodecAdapter {
  private final org.jboss.netty.channel.ChannelHandler encoder;

  private final org.jboss.netty.channel.ChannelHandler decoder;

  private final org.apache.dubbo.remoting.Codec2 codec;

  private final org.apache.dubbo.common.URL url;

  private final int bufferSize;

  private final org.apache.dubbo.remoting.ChannelHandler handler;

  public org.apache.dubbo.remoting.transport.netty.NettyCodecAdapter(org.apache.dubbo.remoting.Codec2, org.apache.dubbo.common.URL, org.apache.dubbo.remoting.ChannelHandler);
    Code:
       0: aload_0
       1: invokespecial #6                  // Method java/lang/Object."<init>":()V
       4: aload_0
       5: new           #7                  // class org/apache/dubbo/remoting/transport/netty/NettyCodecAdapter$InternalEncoder
       8: dup
       9: aload_0
      10: aconst_null
      11: invokespecial #8                  // Method org/apache/dubbo/remoting/transport/netty/NettyCodecAdapter$InternalEncoder."<init>":(Lorg/apache/dubbo/remoting/transport/netty/NettyCodecAdapter;Lorg/apache/dubbo/remoting/transport/netty/NettyCodecAdapter$1;)V
      14: putfield      #9                  // Field encoder:Lorg/jboss/netty/channel/ChannelHandler;
      17: aload_0
      18: new           #10                 // class org/apache/dubbo/remoting/transport/netty/NettyCodecAdapter$InternalDecoder
      21: dup
      22: aload_0
      23: aconst_null
      24: invokespecial #11                 // Method org/apache/dubbo/remoting/transport/netty/NettyCodecAdapter$InternalDecoder."<init>":(Lorg/apache/dubbo/remoting/transport/netty/NettyCodecAdapter;Lorg/apache/dubbo/remoting/transport/netty/NettyCodecAdapter$1;)V
      27: putfield      #12                 // Field decoder:Lorg/jboss/netty/channel/ChannelHandler;
      30: aload_0
      31: aload_1
      32: putfield      #3                  // Field codec:Lorg/apache/dubbo/remoting/Codec2;
      35: aload_0
      36: aload_2
      37: putfield      #5                  // Field url:Lorg/apache/dubbo/common/URL;
      40: aload_0
      41: aload_3
      42: putfield      #4                  // Field handler:Lorg/apache/dubbo/remoting/ChannelHandler;
      45: aload_2
      46: ldc           #13                 // String buffer
      48: sipush        8192
      51: invokevirtual #14                 // Method org/apache/dubbo/common/URL.getPositiveParameter:(Ljava/lang/String;I)I
      54: istore        4
      56: aload_0
      57: iload         4
      59: sipush        1024
      62: if_icmplt     78
      65: iload         4
      67: sipush        16384
      70: if_icmpgt     78
      73: iload         4
      75: goto          81
      78: sipush        8192
      81: putfield      #2                  // Field bufferSize:I
      84: return

  public org.jboss.netty.channel.ChannelHandler getEncoder();
    Code:
       0: aload_0
       1: getfield      #9                  // Field encoder:Lorg/jboss/netty/channel/ChannelHandler;
       4: areturn

  public org.jboss.netty.channel.ChannelHandler getDecoder();
    Code:
       0: aload_0
       1: getfield      #12                 // Field decoder:Lorg/jboss/netty/channel/ChannelHandler;
       4: areturn

  static org.apache.dubbo.common.URL access$200(org.apache.dubbo.remoting.transport.netty.NettyCodecAdapter);
    Code:
       0: aload_0
       1: getfield      #5                  // Field url:Lorg/apache/dubbo/common/URL;
       4: areturn

  static org.apache.dubbo.remoting.ChannelHandler access$300(org.apache.dubbo.remoting.transport.netty.NettyCodecAdapter);
    Code:
       0: aload_0
       1: getfield      #4                  // Field handler:Lorg/apache/dubbo/remoting/ChannelHandler;
       4: areturn

  static org.apache.dubbo.remoting.Codec2 access$400(org.apache.dubbo.remoting.transport.netty.NettyCodecAdapter);
    Code:
       0: aload_0
       1: getfield      #3                  // Field codec:Lorg/apache/dubbo/remoting/Codec2;
       4: areturn

  static int access$500(org.apache.dubbo.remoting.transport.netty.NettyCodecAdapter);
    Code:
       0: aload_0
       1: getfield      #2                  // Field bufferSize:I
       4: ireturn
}
