Compiled from "NettyHelper.java"
final class org.apache.dubbo.remoting.transport.netty.NettyHelper {
  org.apache.dubbo.remoting.transport.netty.NettyHelper();
    Code:
       0: aload_0
       1: invokespecial #1                  // Method java/lang/Object."<init>":()V
       4: return

  public static void setNettyLoggerFactory();
    Code:
       0: invokestatic  #2                  // Method org/jboss/netty/logging/InternalLoggerFactory.getDefaultFactory:()Lorg/jboss/netty/logging/InternalLoggerFactory;
       3: astore_0
       4: aload_0
       5: instanceof    #3                  // class org/apache/dubbo/remoting/transport/netty/NettyHelper$DubboLoggerFactory
       8: ifne          21
      11: new           #3                  // class org/apache/dubbo/remoting/transport/netty/NettyHelper$DubboLoggerFactory
      14: dup
      15: invokespecial #4                  // Method org/apache/dubbo/remoting/transport/netty/NettyHelper$DubboLoggerFactory."<init>":()V
      18: invokestatic  #5                  // Method org/jboss/netty/logging/InternalLoggerFactory.setDefaultFactory:(Lorg/jboss/netty/logging/InternalLoggerFactory;)V
      21: return
}
