Compiled from "ReactiveWebServerApplicationContextFactory.java"
class org.springframework.boot.web.reactive.context.ReactiveWebServerApplicationContextFactory implements org.springframework.boot.ApplicationContextFactory {
  org.springframework.boot.web.reactive.context.ReactiveWebServerApplicationContextFactory();
    Code:
       0: aload_0
       1: invokespecial #1                  // Method java/lang/Object."<init>":()V
       4: return

  public java.lang.Class<? extends org.springframework.core.env.ConfigurableEnvironment> getEnvironmentType(org.springframework.boot.WebApplicationType);
    Code:
       0: aload_1
       1: getstatic     #7                  // Field org/springframework/boot/WebApplicationType.REACTIVE:Lorg/springframework/boot/WebApplicationType;
       4: if_acmpeq     11
       7: aconst_null
       8: goto          13
      11: ldc           #13                 // class org/springframework/boot/web/reactive/context/ApplicationReactiveWebEnvironment
      13: areturn

  public org.springframework.core.env.ConfigurableEnvironment createEnvironment(org.springframework.boot.WebApplicationType);
    Code:
       0: aload_1
       1: getstatic     #7                  // Field org/springframework/boot/WebApplicationType.REACTIVE:Lorg/springframework/boot/WebApplicationType;
       4: if_acmpeq     11
       7: aconst_null
       8: goto          18
      11: new           #13                 // class org/springframework/boot/web/reactive/context/ApplicationReactiveWebEnvironment
      14: dup
      15: invokespecial #15                 // Method org/springframework/boot/web/reactive/context/ApplicationReactiveWebEnvironment."<init>":()V
      18: areturn

  public org.springframework.context.ConfigurableApplicationContext create(org.springframework.boot.WebApplicationType);
    Code:
       0: aload_1
       1: getstatic     #7                  // Field org/springframework/boot/WebApplicationType.REACTIVE:Lorg/springframework/boot/WebApplicationType;
       4: if_acmpeq     11
       7: aconst_null
       8: goto          15
      11: aload_0
      12: invokevirtual #16                 // Method createContext:()Lorg/springframework/context/ConfigurableApplicationContext;
      15: areturn

  private org.springframework.context.ConfigurableApplicationContext createContext();
    Code:
       0: invokestatic  #22                 // Method org/springframework/aot/AotDetector.useGeneratedArtifacts:()Z
       3: ifne          14
       6: new           #28                 // class org/springframework/boot/web/reactive/context/AnnotationConfigReactiveWebServerApplicationContext
       9: dup
      10: invokespecial #30                 // Method org/springframework/boot/web/reactive/context/AnnotationConfigReactiveWebServerApplicationContext."<init>":()V
      13: areturn
      14: new           #31                 // class org/springframework/boot/web/reactive/context/ReactiveWebServerApplicationContext
      17: dup
      18: invokespecial #33                 // Method org/springframework/boot/web/reactive/context/ReactiveWebServerApplicationContext."<init>":()V
      21: areturn
}
