Compiled from "ReactiveWebServerApplicationContext.java"
public class org.springframework.boot.web.reactive.context.ReactiveWebServerApplicationContext extends org.springframework.boot.web.reactive.context.GenericReactiveWebApplicationContext implements org.springframework.boot.web.context.ConfigurableWebServerApplicationContext {
  private volatile org.springframework.boot.web.reactive.context.WebServerManager serverManager;

  private java.lang.String serverNamespace;

  public org.springframework.boot.web.reactive.context.ReactiveWebServerApplicationContext();
    Code:
       0: aload_0
       1: invokespecial #1                  // Method org/springframework/boot/web/reactive/context/GenericReactiveWebApplicationContext."<init>":()V
       4: return

  public org.springframework.boot.web.reactive.context.ReactiveWebServerApplicationContext(org.springframework.beans.factory.support.DefaultListableBeanFactory);
    Code:
       0: aload_0
       1: aload_1
       2: invokespecial #7                  // Method org/springframework/boot/web/reactive/context/GenericReactiveWebApplicationContext."<init>":(Lorg/springframework/beans/factory/support/DefaultListableBeanFactory;)V
       5: return

  public final void refresh() throws org.springframework.beans.BeansException, java.lang.IllegalStateException;
    Code:
       0: aload_0
       1: invokespecial #10                 // Method org/springframework/boot/web/reactive/context/GenericReactiveWebApplicationContext.refresh:()V
       4: goto          28
       7: astore_1
       8: aload_0
       9: getfield      #15                 // Field serverManager:Lorg/springframework/boot/web/reactive/context/WebServerManager;
      12: astore_2
      13: aload_2
      14: ifnull        26
      17: aload_2
      18: invokevirtual #21                 // Method org/springframework/boot/web/reactive/context/WebServerManager.getWebServer:()Lorg/springframework/boot/web/server/WebServer;
      21: invokeinterface #27,  1           // InterfaceMethod org/springframework/boot/web/server/WebServer.stop:()V
      26: aload_1
      27: athrow
      28: return
    Exception table:
       from    to  target type
           0     4     7   Class java/lang/RuntimeException

  protected void onRefresh();
    Code:
       0: aload_0
       1: invokespecial #32                 // Method org/springframework/boot/web/reactive/context/GenericReactiveWebApplicationContext.onRefresh:()V
       4: aload_0
       5: invokevirtual #35                 // Method createWebServer:()V
       8: goto          23
      11: astore_1
      12: new           #40                 // class org/springframework/context/ApplicationContextException
      15: dup
      16: ldc           #42                 // String Unable to start reactive web server
      18: aload_1
      19: invokespecial #44                 // Method org/springframework/context/ApplicationContextException."<init>":(Ljava/lang/String;Ljava/lang/Throwable;)V
      22: athrow
      23: return
    Exception table:
       from    to  target type
           4     8    11   Class java/lang/Throwable

  private void createWebServer();
    Code:
       0: aload_0
       1: getfield      #15                 // Field serverManager:Lorg/springframework/boot/web/reactive/context/WebServerManager;
       4: astore_1
       5: aload_1
       6: ifnonnull     142
       9: aload_0
      10: invokevirtual #47                 // Method getApplicationStartup:()Lorg/springframework/core/metrics/ApplicationStartup;
      13: ldc           #51                 // String spring.boot.webserver.create
      15: invokeinterface #53,  2           // InterfaceMethod org/springframework/core/metrics/ApplicationStartup.start:(Ljava/lang/String;)Lorg/springframework/core/metrics/StartupStep;
      20: astore_2
      21: aload_0
      22: invokevirtual #59                 // Method getWebServerFactoryBeanName:()Ljava/lang/String;
      25: astore_3
      26: aload_0
      27: aload_3
      28: invokevirtual #63                 // Method getWebServerFactory:(Ljava/lang/String;)Lorg/springframework/boot/web/reactive/server/ReactiveWebServerFactory;
      31: astore        4
      33: aload_2
      34: ldc           #67                 // String factory
      36: aload         4
      38: invokevirtual #69                 // Method java/lang/Object.getClass:()Ljava/lang/Class;
      41: invokevirtual #75                 // Method java/lang/Class.toString:()Ljava/lang/String;
      44: invokeinterface #80,  3           // InterfaceMethod org/springframework/core/metrics/StartupStep.tag:(Ljava/lang/String;Ljava/lang/String;)Lorg/springframework/core/metrics/StartupStep;
      49: pop
      50: aload_0
      51: invokevirtual #86                 // Method getBeanFactory:()Lorg/springframework/beans/factory/config/ConfigurableListableBeanFactory;
      54: aload_3
      55: invokeinterface #90,  2           // InterfaceMethod org/springframework/beans/factory/config/ConfigurableListableBeanFactory.getBeanDefinition:(Ljava/lang/String;)Lorg/springframework/beans/factory/config/BeanDefinition;
      60: invokeinterface #96,  1           // InterfaceMethod org/springframework/beans/factory/config/BeanDefinition.isLazyInit:()Z
      65: istore        5
      67: aload_0
      68: new           #22                 // class org/springframework/boot/web/reactive/context/WebServerManager
      71: dup
      72: aload_0
      73: aload         4
      75: aload_0
      76: invokedynamic #102,  0            // InvokeDynamic #0:get:(Lorg/springframework/boot/web/reactive/context/ReactiveWebServerApplicationContext;)Ljava/util/function/Supplier;
      81: iload         5
      83: invokespecial #106                // Method org/springframework/boot/web/reactive/context/WebServerManager."<init>":(Lorg/springframework/boot/web/reactive/context/ReactiveWebServerApplicationContext;Lorg/springframework/boot/web/reactive/server/ReactiveWebServerFactory;Ljava/util/function/Supplier;Z)V
      86: putfield      #15                 // Field serverManager:Lorg/springframework/boot/web/reactive/context/WebServerManager;
      89: aload_0
      90: invokevirtual #86                 // Method getBeanFactory:()Lorg/springframework/beans/factory/config/ConfigurableListableBeanFactory;
      93: ldc           #109                // String webServerGracefulShutdown
      95: new           #111                // class org/springframework/boot/web/context/WebServerGracefulShutdownLifecycle
      98: dup
      99: aload_0
     100: getfield      #15                 // Field serverManager:Lorg/springframework/boot/web/reactive/context/WebServerManager;
     103: invokevirtual #21                 // Method org/springframework/boot/web/reactive/context/WebServerManager.getWebServer:()Lorg/springframework/boot/web/server/WebServer;
     106: invokespecial #113                // Method org/springframework/boot/web/context/WebServerGracefulShutdownLifecycle."<init>":(Lorg/springframework/boot/web/server/WebServer;)V
     109: invokeinterface #116,  3          // InterfaceMethod org/springframework/beans/factory/config/ConfigurableListableBeanFactory.registerSingleton:(Ljava/lang/String;Ljava/lang/Object;)V
     114: aload_0
     115: invokevirtual #86                 // Method getBeanFactory:()Lorg/springframework/beans/factory/config/ConfigurableListableBeanFactory;
     118: ldc           #120                // String webServerStartStop
     120: new           #122                // class org/springframework/boot/web/reactive/context/WebServerStartStopLifecycle
     123: dup
     124: aload_0
     125: getfield      #15                 // Field serverManager:Lorg/springframework/boot/web/reactive/context/WebServerManager;
     128: invokespecial #124                // Method org/springframework/boot/web/reactive/context/WebServerStartStopLifecycle."<init>":(Lorg/springframework/boot/web/reactive/context/WebServerManager;)V
     131: invokeinterface #116,  3          // InterfaceMethod org/springframework/beans/factory/config/ConfigurableListableBeanFactory.registerSingleton:(Ljava/lang/String;Ljava/lang/Object;)V
     136: aload_2
     137: invokeinterface #127,  1          // InterfaceMethod org/springframework/core/metrics/StartupStep.end:()V
     142: aload_0
     143: invokevirtual #130                // Method initPropertySources:()V
     146: return

  protected java.lang.String getWebServerFactoryBeanName();
    Code:
       0: aload_0
       1: invokevirtual #86                 // Method getBeanFactory:()Lorg/springframework/beans/factory/config/ConfigurableListableBeanFactory;
       4: ldc           #133                // class org/springframework/boot/web/reactive/server/ReactiveWebServerFactory
       6: invokeinterface #135,  2          // InterfaceMethod org/springframework/beans/factory/config/ConfigurableListableBeanFactory.getBeanNamesForType:(Ljava/lang/Class;)[Ljava/lang/String;
      11: astore_1
      12: aload_1
      13: arraylength
      14: ifne          34
      17: new           #139                // class org/springframework/boot/web/context/MissingWebServerFactoryBeanException
      20: dup
      21: aload_0
      22: invokevirtual #69                 // Method java/lang/Object.getClass:()Ljava/lang/Class;
      25: ldc           #133                // class org/springframework/boot/web/reactive/server/ReactiveWebServerFactory
      27: getstatic     #141                // Field org/springframework/boot/WebApplicationType.REACTIVE:Lorg/springframework/boot/WebApplicationType;
      30: invokespecial #147                // Method org/springframework/boot/web/context/MissingWebServerFactoryBeanException."<init>":(Ljava/lang/Class;Ljava/lang/Class;Lorg/springframework/boot/WebApplicationType;)V
      33: athrow
      34: aload_1
      35: arraylength
      36: iconst_1
      37: if_icmple     57
      40: new           #40                 // class org/springframework/context/ApplicationContextException
      43: dup
      44: aload_1
      45: invokestatic  #150                // Method org/springframework/util/StringUtils.arrayToCommaDelimitedString:([Ljava/lang/Object;)Ljava/lang/String;
      48: invokedynamic #156,  0            // InvokeDynamic #1:makeConcatWithConstants:(Ljava/lang/String;)Ljava/lang/String;
      53: invokespecial #160                // Method org/springframework/context/ApplicationContextException."<init>":(Ljava/lang/String;)V
      56: athrow
      57: aload_1
      58: iconst_0
      59: aaload
      60: areturn

  protected org.springframework.boot.web.reactive.server.ReactiveWebServerFactory getWebServerFactory(java.lang.String);
    Code:
       0: aload_0
       1: invokevirtual #86                 // Method getBeanFactory:()Lorg/springframework/beans/factory/config/ConfigurableListableBeanFactory;
       4: aload_1
       5: ldc           #133                // class org/springframework/boot/web/reactive/server/ReactiveWebServerFactory
       7: invokeinterface #163,  3          // InterfaceMethod org/springframework/beans/factory/config/ConfigurableListableBeanFactory.getBean:(Ljava/lang/String;Ljava/lang/Class;)Ljava/lang/Object;
      12: checkcast     #133                // class org/springframework/boot/web/reactive/server/ReactiveWebServerFactory
      15: areturn

  protected org.springframework.http.server.reactive.HttpHandler getHttpHandler();
    Code:
       0: aload_0
       1: invokevirtual #86                 // Method getBeanFactory:()Lorg/springframework/beans/factory/config/ConfigurableListableBeanFactory;
       4: ldc           #167                // class org/springframework/http/server/reactive/HttpHandler
       6: invokeinterface #135,  2          // InterfaceMethod org/springframework/beans/factory/config/ConfigurableListableBeanFactory.getBeanNamesForType:(Ljava/lang/Class;)[Ljava/lang/String;
      11: astore_1
      12: aload_1
      13: arraylength
      14: ifne          27
      17: new           #40                 // class org/springframework/context/ApplicationContextException
      20: dup
      21: ldc           #169                // String Unable to start ReactiveWebApplicationContext due to missing HttpHandler bean.
      23: invokespecial #160                // Method org/springframework/context/ApplicationContextException."<init>":(Ljava/lang/String;)V
      26: athrow
      27: aload_1
      28: arraylength
      29: iconst_1
      30: if_icmple     50
      33: new           #40                 // class org/springframework/context/ApplicationContextException
      36: dup
      37: aload_1
      38: invokestatic  #150                // Method org/springframework/util/StringUtils.arrayToCommaDelimitedString:([Ljava/lang/Object;)Ljava/lang/String;
      41: invokedynamic #171,  0            // InvokeDynamic #2:makeConcatWithConstants:(Ljava/lang/String;)Ljava/lang/String;
      46: invokespecial #160                // Method org/springframework/context/ApplicationContextException."<init>":(Ljava/lang/String;)V
      49: athrow
      50: aload_0
      51: invokevirtual #86                 // Method getBeanFactory:()Lorg/springframework/beans/factory/config/ConfigurableListableBeanFactory;
      54: aload_1
      55: iconst_0
      56: aaload
      57: ldc           #167                // class org/springframework/http/server/reactive/HttpHandler
      59: invokeinterface #163,  3          // InterfaceMethod org/springframework/beans/factory/config/ConfigurableListableBeanFactory.getBean:(Ljava/lang/String;Ljava/lang/Class;)Ljava/lang/Object;
      64: checkcast     #167                // class org/springframework/http/server/reactive/HttpHandler
      67: areturn

  protected void doClose();
    Code:
       0: aload_0
       1: invokevirtual #172                // Method isActive:()Z
       4: ifeq          14
       7: aload_0
       8: getstatic     #175                // Field org/springframework/boot/availability/ReadinessState.REFUSING_TRAFFIC:Lorg/springframework/boot/availability/ReadinessState;
      11: invokestatic  #181                // Method org/springframework/boot/availability/AvailabilityChangeEvent.publish:(Lorg/springframework/context/ApplicationContext;Lorg/springframework/boot/availability/AvailabilityState;)V
      14: aload_0
      15: invokespecial #187                // Method org/springframework/boot/web/reactive/context/GenericReactiveWebApplicationContext.doClose:()V
      18: return

  public org.springframework.boot.web.server.WebServer getWebServer();
    Code:
       0: aload_0
       1: getfield      #15                 // Field serverManager:Lorg/springframework/boot/web/reactive/context/WebServerManager;
       4: astore_1
       5: aload_1
       6: ifnull        16
       9: aload_1
      10: invokevirtual #21                 // Method org/springframework/boot/web/reactive/context/WebServerManager.getWebServer:()Lorg/springframework/boot/web/server/WebServer;
      13: goto          17
      16: aconst_null
      17: areturn

  public java.lang.String getServerNamespace();
    Code:
       0: aload_0
       1: getfield      #190                // Field serverNamespace:Ljava/lang/String;
       4: areturn

  public void setServerNamespace(java.lang.String);
    Code:
       0: aload_0
       1: aload_1
       2: putfield      #190                // Field serverNamespace:Ljava/lang/String;
       5: return
}
