Compiled from "WebServerManager.java"
final class org.springframework.boot.web.reactive.context.WebServerManager$LazyHttpHandler implements org.springframework.http.server.reactive.HttpHandler {
  private final reactor.core.publisher.Mono<org.springframework.http.server.reactive.HttpHandler> delegate;

  private org.springframework.boot.web.reactive.context.WebServerManager$LazyHttpHandler(java.util.function.Supplier<org.springframework.http.server.reactive.HttpHandler>);
    Code:
       0: aload_0
       1: invokespecial #1                  // Method java/lang/Object."<init>":()V
       4: aload_0
       5: aload_1
       6: invokestatic  #7                  // Method reactor/core/publisher/Mono.fromSupplier:(Ljava/util/function/Supplier;)Lreactor/core/publisher/Mono;
       9: putfield      #13                 // Field delegate:Lreactor/core/publisher/Mono;
      12: return

  public reactor.core.publisher.Mono<java.lang.Void> handle(org.springframework.http.server.reactive.ServerHttpRequest, org.springframework.http.server.reactive.ServerHttpResponse);
    Code:
       0: aload_0
       1: getfield      #13                 // Field delegate:Lreactor/core/publisher/Mono;
       4: aload_1
       5: aload_2
       6: invokedynamic #19,  0             // InvokeDynamic #0:apply:(Lorg/springframework/http/server/reactive/ServerHttpRequest;Lorg/springframework/http/server/reactive/ServerHttpResponse;)Ljava/util/function/Function;
      11: invokevirtual #23                 // Method reactor/core/publisher/Mono.flatMap:(Ljava/util/function/Function;)Lreactor/core/publisher/Mono;
      14: areturn

  private static reactor.core.publisher.Mono lambda$handle$0(org.springframework.http.server.reactive.ServerHttpRequest, org.springframework.http.server.reactive.ServerHttpResponse, org.springframework.http.server.reactive.HttpHandler);
    Code:
       0: aload_2
       1: aload_0
       2: aload_1
       3: invokeinterface #27,  3           // InterfaceMethod org/springframework/http/server/reactive/HttpHandler.handle:(Lorg/springframework/http/server/reactive/ServerHttpRequest;Lorg/springframework/http/server/reactive/ServerHttpResponse;)Lreactor/core/publisher/Mono;
       8: areturn
}
