Compiled from "WebServerManager.java"
class org.springframework.boot.web.reactive.context.WebServerManager {
  private final org.springframework.boot.web.reactive.context.ReactiveWebServerApplicationContext applicationContext;

  private final org.springframework.boot.web.reactive.context.WebServerManager$DelayedInitializationHttpHandler handler;

  private final org.springframework.boot.web.server.WebServer webServer;

  org.springframework.boot.web.reactive.context.WebServerManager(org.springframework.boot.web.reactive.context.ReactiveWebServerApplicationContext, org.springframework.boot.web.reactive.server.ReactiveWebServerFactory, java.util.function.Supplier<org.springframework.http.server.reactive.HttpHandler>, boolean);
    Code:
       0: aload_0
       1: invokespecial #1                  // Method java/lang/Object."<init>":()V
       4: aload_0
       5: aload_1
       6: putfield      #7                  // Field applicationContext:Lorg/springframework/boot/web/reactive/context/ReactiveWebServerApplicationContext;
       9: aload_2
      10: ldc           #13                 // String Factory must not be null
      12: invokestatic  #15                 // Method org/springframework/util/Assert.notNull:(Ljava/lang/Object;Ljava/lang/String;)V
      15: aload_0
      16: new           #21                 // class org/springframework/boot/web/reactive/context/WebServerManager$DelayedInitializationHttpHandler
      19: dup
      20: aload_3
      21: iload         4
      23: invokespecial #23                 // Method org/springframework/boot/web/reactive/context/WebServerManager$DelayedInitializationHttpHandler."<init>":(Ljava/util/function/Supplier;Z)V
      26: putfield      #26                 // Field handler:Lorg/springframework/boot/web/reactive/context/WebServerManager$DelayedInitializationHttpHandler;
      29: aload_0
      30: aload_2
      31: aload_0
      32: getfield      #26                 // Field handler:Lorg/springframework/boot/web/reactive/context/WebServerManager$DelayedInitializationHttpHandler;
      35: invokeinterface #30,  2           // InterfaceMethod org/springframework/boot/web/reactive/server/ReactiveWebServerFactory.getWebServer:(Lorg/springframework/http/server/reactive/HttpHandler;)Lorg/springframework/boot/web/server/WebServer;
      40: putfield      #36                 // Field webServer:Lorg/springframework/boot/web/server/WebServer;
      43: return

  void start();
    Code:
       0: aload_0
       1: getfield      #26                 // Field handler:Lorg/springframework/boot/web/reactive/context/WebServerManager$DelayedInitializationHttpHandler;
       4: invokevirtual #40                 // Method org/springframework/boot/web/reactive/context/WebServerManager$DelayedInitializationHttpHandler.initializeHandler:()V
       7: aload_0
       8: getfield      #36                 // Field webServer:Lorg/springframework/boot/web/server/WebServer;
      11: invokeinterface #43,  1           // InterfaceMethod org/springframework/boot/web/server/WebServer.start:()V
      16: aload_0
      17: getfield      #7                  // Field applicationContext:Lorg/springframework/boot/web/reactive/context/ReactiveWebServerApplicationContext;
      20: new           #48                 // class org/springframework/boot/web/reactive/context/ReactiveWebServerInitializedEvent
      23: dup
      24: aload_0
      25: getfield      #36                 // Field webServer:Lorg/springframework/boot/web/server/WebServer;
      28: aload_0
      29: getfield      #7                  // Field applicationContext:Lorg/springframework/boot/web/reactive/context/ReactiveWebServerApplicationContext;
      32: invokespecial #50                 // Method org/springframework/boot/web/reactive/context/ReactiveWebServerInitializedEvent."<init>":(Lorg/springframework/boot/web/server/WebServer;Lorg/springframework/boot/web/reactive/context/ReactiveWebServerApplicationContext;)V
      35: invokevirtual #53                 // Method org/springframework/boot/web/reactive/context/ReactiveWebServerApplicationContext.publishEvent:(Lorg/springframework/context/ApplicationEvent;)V
      38: return

  void shutDownGracefully(org.springframework.boot.web.server.GracefulShutdownCallback);
    Code:
       0: aload_0
       1: getfield      #36                 // Field webServer:Lorg/springframework/boot/web/server/WebServer;
       4: aload_1
       5: invokeinterface #59,  2           // InterfaceMethod org/springframework/boot/web/server/WebServer.shutDownGracefully:(Lorg/springframework/boot/web/server/GracefulShutdownCallback;)V
      10: return

  void stop();
    Code:
       0: aload_0
       1: getfield      #36                 // Field webServer:Lorg/springframework/boot/web/server/WebServer;
       4: invokeinterface #63,  1           // InterfaceMethod org/springframework/boot/web/server/WebServer.stop:()V
       9: return

  org.springframework.boot.web.server.WebServer getWebServer();
    Code:
       0: aload_0
       1: getfield      #36                 // Field webServer:Lorg/springframework/boot/web/server/WebServer;
       4: areturn

  org.springframework.http.server.reactive.HttpHandler getHandler();
    Code:
       0: aload_0
       1: getfield      #26                 // Field handler:Lorg/springframework/boot/web/reactive/context/WebServerManager$DelayedInitializationHttpHandler;
       4: areturn
}
