Compiled from "AbstractValidation.java"
public abstract class org.apache.dubbo.validation.support.AbstractValidation implements org.apache.dubbo.validation.Validation {
  private final java.util.concurrent.ConcurrentMap<java.lang.String, org.apache.dubbo.validation.Validator> validators;

  public org.apache.dubbo.validation.support.AbstractValidation();
    Code:
       0: aload_0
       1: invokespecial #1                  // Method java/lang/Object."<init>":()V
       4: aload_0
       5: new           #2                  // class java/util/concurrent/ConcurrentHashMap
       8: dup
       9: invokespecial #3                  // Method java/util/concurrent/ConcurrentHashMap."<init>":()V
      12: putfield      #4                  // Field validators:Ljava/util/concurrent/ConcurrentMap;
      15: return

  public org.apache.dubbo.validation.Validator getValidator(org.apache.dubbo.common.URL);
    Code:
       0: aload_1
       1: invokevirtual #5                  // Method org/apache/dubbo/common/URL.toFullString:()Ljava/lang/String;
       4: astore_2
       5: aload_0
       6: getfield      #4                  // Field validators:Ljava/util/concurrent/ConcurrentMap;
       9: aload_2
      10: invokeinterface #6,  2            // InterfaceMethod java/util/concurrent/ConcurrentMap.get:(Ljava/lang/Object;)Ljava/lang/Object;
      15: checkcast     #7                  // class org/apache/dubbo/validation/Validator
      18: astore_3
      19: aload_3
      20: ifnonnull     53
      23: aload_0
      24: getfield      #4                  // Field validators:Ljava/util/concurrent/ConcurrentMap;
      27: aload_2
      28: aload_0
      29: aload_1
      30: invokevirtual #8                  // Method createValidator:(Lorg/apache/dubbo/common/URL;)Lorg/apache/dubbo/validation/Validator;
      33: invokeinterface #9,  3            // InterfaceMethod java/util/concurrent/ConcurrentMap.put:(Ljava/lang/Object;Ljava/lang/Object;)Ljava/lang/Object;
      38: pop
      39: aload_0
      40: getfield      #4                  // Field validators:Ljava/util/concurrent/ConcurrentMap;
      43: aload_2
      44: invokeinterface #6,  2            // InterfaceMethod java/util/concurrent/ConcurrentMap.get:(Ljava/lang/Object;)Ljava/lang/Object;
      49: checkcast     #7                  // class org/apache/dubbo/validation/Validator
      52: astore_3
      53: aload_3
      54: areturn

  protected abstract org.apache.dubbo.validation.Validator createValidator(org.apache.dubbo.common.URL);
}
